Workbook

Sheet 2023レビュー
A1: 【R5 さっぽろテレビ塔ビアガーデン振り返り】
A2: ①売上 | I2: 単位：円 | J2: 平均気温 | L2: ①コメント
A3: 月 | B3: 実績 | C3: 予算 | D3: 予算比 | E3: 差異 | F3: 予測 | G3: 予測比 | H3: 差異 | I3: 1日平均売上 | J3: LOW | K3: HIGH | L3: 売上については左記の通り、対予算123.9％にて終了いたしました。コロナ禍前の2019年と比較しても対比125.4％（+22,223千円）の結果となりました。これまで1億円の大台に達したことはなかったということです。その大きな要因としてはスタッフの頑張りはもちろんですが、やはり史上稀に見る猛暑となったことが挙げられます。特に6月と8月は気象庁の観測史上最高値を記録し、7月においても史上2番目の平均気温となりました。ただ、天候要因については影響値として一定の条件下で記録していかなければならないもので、いかにこの天候要因を限定的にできるか？というのが引き続きの課題となります。※各月に天候要因を数値化したものを載せています。次年度へ向け今年度のデータを活かし、テーブル配置・スタッフアサインメント・予約システム再構築・RPA/DX 促進・メニューラインナップの見直し等により、さらにポテンシャルを引き出し売上を積み上げられると認識しています。
A4: 5 | B4: 1795227.3 | C4: 6890000 | D4: =B4/C4 -> 0.26055548 | E4: =B4-C4 -> -5094772.7 | F4: 1963000 | G4: =B4/F4 -> 0.91453249 | H4: =B4-F4 -> -167772.73 | I4: =B4/T4 -> 359045.45 | T4: 5
A5: 6 | B5: 19049727 | C5: 25440000 | D5: =B5/C5 -> 0.74881003 | E5: =B5-C5 -> -6390272.7 | F5: 17338000 | G5: =B5/F5 -> 1.0987269 | H5: =B5-F5 -> 1711727.3 | I5: =B5/T5 -> 634990.91 | J5: 12.7℃ | K5: 20.0℃ | T5: 30
A6: 7 | B6: 44856909 | C6: 25440000 | D6: =B6/C6 -> 1.7632433 | E6: =B6-C6 -> 19416909 | F6: 35016000 | G6: =B6/F6 -> 1.2810404 | H6: =B6-F6 -> 9840909.1 | I6: =B6/T6 -> 1446997.1 | J6: 15.6℃ | K6: 24.1℃ | T6: 31
A7: 8 | B7: 44863045 | C7: 25440000 | D7: =B7/C7 -> 1.7634845 | E7: =B7-C7 -> 19423045 | F7: 39760000 | G7: =B7/F7 -> 1.1283462 | H7: =B7-F7 -> 5103045.5 | I7: =B7/T7 -> 1447195 | J7: 21.0℃ | K7: 27.8℃ | T7: 31
A8: 9 | B8: 4058727.3 | C8: 9275000 | D8: =B8/C8 -> 0.43759863 | E8: =B8-C8 -> -5216272.7 | F8: 4300000 | G8: =B8/F8 -> 0.94389006 | H8: =B8-F8 -> -241272.73 | I8: =B8/T8 -> 1352909.1 | J8: 24.0℃ | K8: 30.9℃ | T8: 3
A9: TOTAL | B9: =SUM(B4:B8) -> 1.1462364e+08 | C9: =SUM(C4:C8) -> 92485000 | D9: =B9/C9 -> 1.2393754 | E9: =B9-C9 -> 22138636 | F9: =SUM(F4:F8) -> 98377000 | G9: =B9/F9 -> 1.1651467 | H9: =B9-F9 -> 16246636 | I9: =B9/T9 -> 1146236.4 | J9: 21.4℃ | K9: 28.6℃ | T9: 100
A11: ②客数 | I11: 単位：名 | L11: ②コメント
A12: 月 | B12: 実績 | C12: 予算 | D12: 予算比 | E12: 差異 | F12: 予測 | G12: 予測比 | H12: 差異 | I12: 1日平均 | L12: 入客実績は左記の通りです。7/21（金）から8/16（土）の間で開催された大通りビアガーデン期間中も1日平均405名の入客となり、客数減少懸念は杞憂となりました。過去開催の数値によると盆明けは下降線を辿るはずでしたが、①にもある通り観測史上最高の平均気温となったことやチケットの駆け込み利用もあり、勢いを保ったまま最終日まで賑わいが続きました。シーズン設定をして6月末までは20:30クローズ、7月1日〜は21:30クローズとしたことは大きな成果に繋がったと考えています。7/22（土）が717名の来場とピーク、また、この週（7月第4週・通期では第9週）が最大の売上・入客となりました。次年度は予約システムをさらに活用し、入客を引き上げたいと考えています。
A13: 5 | B13: 506 | C13: 1300 | D13: =B13/C13 -> 0.38923077 | E13: =B13-C13 -> -794 | F13: 395 | G13: =B13/F13 -> 1.2810127 | H13: =B13-F13 -> 111 | I13: =B13/T13 -> 101.2 | T13: 5
A14: 6 | B14: 5309 | C14: 4800 | D14: =B14/C14 -> 1.1060417 | E14: =B14-C14 -> 509 | F14: 3450 | G14: =B14/F14 -> 1.5388406 | H14: =B14-F14 -> 1859 | I14: =B14/T14 -> 176.96667 | T14: 30
A15: 7 | B15: 11036 | C15: 4800 | D15: =B15/C15 -> 2.2991667 | E15: =B15-C15 -> 6236 | F15: 7050 | G15: =B15/F15 -> 1.5653901 | H15: =B15-F15 -> 3986 | I15: =B15/T15 -> 356 | T15: 31
A16: 8 | B16: 11093 | C16: 4800 | D16: =B16/C16 -> 2.3110417 | E16: =B16-C16 -> 6293 | F16: 8100 | G16: =B16/F16 -> 1.3695062 | H16: =B16-F16 -> 2993 | I16: =B16/T16 -> 357.83871 | T16: 31
A17: 9 | B17: 974 | C17: 1750 | D17: =B17/C17 -> 0.55657143 | E17: =B17-C17 -> -776 | F17: 880 | G17: =B17/F17 -> 1.1068182 | H17: =B17-F17 -> 94 | I17: =B17/T17 -> 324.66667 | T17: 3
A18: TOTAL | B18: =SUM(B13:B17) -> 28918 | C18: =SUM(C13:C17) -> 17450 | D18: =B18/C18 -> 1.657192 | E18: =B18-C18 -> 11468 | F18: =SUM(F13:F17) -> 19875 | G18: =B18/F18 -> 1.4549937 | H18: =B18-F18 -> 9043 | I18: =B18/T18 -> 289.18 | T18: 100
A20: ③-1 客単価 | I20: 単位：円 | L20: ③コメント
A21: 月 | B21: 実績 | C21: 予算 | D21: 予算比 | E21: 差異 | F21: 予測 | G21: 予測比 | H21: 差異 | L21: 通期での客単価は3,964円にて着地いたしました。予算設定時点では80%がプラン利用を想定しての数値でしたので、予算値からはマイナスとなっています。最終的にプラン利用率は53.6%となり、アラカルト（単品）利用率を上回りました。左記データから読み取れるのは、とてもシンプルですが、パッサージュ（フリー入客）利用率が高いと客単価が下がるという事実と、予約数を高めることにより客単価が伸びるという事実です。このことから、次年度は今回25％程であった予約利用率を35％程度まで引き上げることで、いわゆる「値上げ」の必要がなく、客単価と入客の天秤関係を限定的にしながら、【入客を高めつつ客単価も引き上げることができる】という伸び代を確認することができました。また今回はテーブルチェックを導入し、専用LPと紐付けして予約受注を行ったことにより、約83%の方がWebから予約をしてくださいました。これまでの開催は全て電話予約で対応し紙台帳管理をしていたという課題を、予約システム導入によって解決できた大きな成果と認められます。現地オペレーションとの連携を高めていけば、まだまだこうしたシステムを活かすことができます。今年度実績を基にし、人員発注と人員配置、予約システムの強みをさらに引き出しての予約受注強化（相性が良いと見られるLINE/L-STEPの活用など）や、天候要件の影響値を最小化（※悪天候時でも当日キャンセルは2割に満たない）していくことで、次年度は客席拡大、スタッフ増員に強気で臨むことができます。設備を含めて改善しつつ、さらに客単価を10％程度引き上げることで、売上も今年度の1日平均114万円から130万円（合計1億3,000万円）までは伸ばすことができると確信しています。
A22: 5 | B22: =B4/B13 -> 3547.88 | C22: 5300 | D22: =B22/C22 -> 0.66941132 | E22: =B22-C22 -> -1752.12 | F22: 4970 | G22: =B22/F22 -> 0.71385915 | H22: =B22-F22 -> -1422.12
A23: 6 | B23: =B5/B14 -> 3588.195 | C23: 5300 | D23: =B23/C23 -> 0.67701793 | E23: =B23-C23 -> -1711.805 | F23: 5026 | G23: =B23/F23 -> 0.71392658 | H23: =B23-F23 -> -1437.805
A24: 7 | B24: =B6/B15 -> 4064.5985 | C24: 5300 | D24: =B24/C24 -> 0.76690538 | E24: =B24-C24 -> -1235.4015 | F24: 4967 | G24: =B24/F24 -> 0.81832062 | H24: =B24-F24 -> -902.4015
A25: 8 | B25: =B7/B16 -> 4044.2662 | C25: 5300 | D25: =B25/C25 -> 0.7630691 | E25: =B25-C25 -> -1255.7338 | F25: 4909 | G25: =B25/F25 -> 0.82384727 | H25: =B25-F25 -> -864.73376
A26: 9 | B26: =B8/B17 -> 4167.0711 | C26: 5300 | D26: =B26/C26 -> 0.78623983 | E26: =B26-C26 -> -1132.9289 | F26: 4886 | G26: =B26/F26 -> 0.85285942 | H26: =B26-F26 -> -718.92888
A27: TOTAL | B27: =B9/B18 -> 3963.747 | C27: =C9/C18 -> 5300 | D27: =B27/C27 -> 0.7478768 | E27: =B27-C27 -> -1336.253 | F27: =F9/F18 -> 4949.7862 | G27: =B27/F27 -> 0.80079157 | H27: =B27-F27 -> -986.03914
A29: ③-2 プラン出卓数と月別プラン利用率
A30: 月 | B30: 客数 | C30: 5,500プラン | D30: 利用率 | E30: 6,600プラン | F30: 利用率 | G30: 8,800プラン | H30: 利用率 | I30: 小計
A31: 5 | B31: 506 | C31: 205 | D31: =C31/B31 -> 0.40513834 | E31: 7 | F31: =E31/B31 -> 0.013833992 | G31: 2 | H31: =G31/B31 -> 0.0039525692 | I31: =C31+E31+G31 -> 214
A32: 6 | B32: 5309 | C32: 2074 | D32: =C32/B32 -> 0.39065737 | E32: 80 | F32: =E32/B32 -> 0.015068751 | G32: 9 | H32: =G32/B32 -> 0.0016952345 | I32: =C32+E32+G32 -> 2163
A33: 7 | B33: 11036 | C33: 5792 | D33: =C33/B33 -> 0.52482784 | E33: 190 | F33: =E33/B33 -> 0.017216383 | G33: 161 | H33: =G33/B33 -> 0.014588619 | I33: =C33+E33+G33 -> 6143
A34: 8 | B34: 11093 | C34: 5149 | D34: =C34/B34 -> 0.46416659 | E34: 271 | F34: =E34/B34 -> 0.024429821 | G34: 77 | H34: =G34/B34 -> 0.0069413143 | I34: =C34+E34+G34 -> 5497
A35: 9 | B35: 974 | C35: 314 | D35: =C35/B35 -> 0.32238193 | E35: 34 | F35: =E35/B35 -> 0.034907598 | G35: 9 | H35: =G35/B35 -> 0.0092402464 | I35: =C35+E35+G35 -> 357
A36: TOTAL | B36: =SUM(B31:B35) -> 28918 | C36: =SUM(C31:C35) -> 13534 | D36: =C36/B36 -> 0.468013 | E36: =SUM(E31:E35) -> 582 | F36: =E36/B36 -> 0.020125873 | G36: =SUM(G31:G35) -> 258 | H36: =G36/B36 -> 0.0089217788 | I36: =C36+E36+G36 -> 14374
A37: 月 | B37: 客数 | C37: チケットプラン | D37: 利用率 | E37: プラン合計 | F37: 利用率 | G37: アラカルト利用 | H37: 利用率
A38: 5 | B38: 506 | C38: 0 | D38: =C38/B38 -> 0 | E38: =C38+I31 -> 214 | F38: =E38/B38 -> 0.4229249 | G38: =B38-E38 -> 292 | H38: =G38/B38 -> 0.5770751 | L38: ④memo
A39: 6 | B39: 5309 | C39: 0 | D39: =C39/B39 -> 0 | E39: =C39+I32 -> 2163 | F39: =E39/B39 -> 0.40742136 | G39: =B39-E39 -> 3146 | H39: =G39/B39 -> 0.59257864 | L39: 設備・備品課題※情報共有前 ◆英字メニュー ◆テーブル番号札（視認性・会計） ◆会計カード（プラスチック札）の作成 ◆会計の仕方がわからない ◆キャッシュレス決済が行えることの告知 ◆エクスキューズ（場内案内・トイレ・会計方法など） ◆飲み放題と単品オーダーの判別がつきづらい ◆床清掃の定期スケジュールと不定期実施のオペレーション ◆ワインの利用方法と場所 ◆ワインコーナーにローズマリーのプランター設置 ◆イベント開催 ◆キャッシャー増設検討 ◆ジョッキのサイズ ◆グラス洗浄マシンとの相性 ◆鍋洗い機（高圧洗浄機）の複数洗浄機導入 ◆Wi-Fi環境 ◆問い合わせ専用電話の設置
A40: 7 | B40: 11036 | C40: 107 | D40: =C40/B40 -> 0.0096955419 | E40: =C40+I33 -> 6250 | F40: =E40/B40 -> 0.56632838 | G40: =B40-E40 -> 4786 | H40: =G40/B40 -> 0.43367162
A41: 8 | B41: 11093 | C41: 765 | D41: =C41/B41 -> 0.068962409 | E41: =C41+I34 -> 6262 | F41: =E41/B41 -> 0.56450014 | G41: =B41-E41 -> 4831 | H41: =G41/B41 -> 0.43549986
A42: 9 | B42: 974 | C42: 240 | D42: =C42/B42 -> 0.24640657 | E42: =C42+I35 -> 597 | F42: =E42/B42 -> 0.61293634 | G42: =B42-E42 -> 377 | H42: =G42/B42 -> 0.38706366
A43: TOTAL | B43: =SUM(B38:B42) -> 28918 | C43: =SUM(C38:C42) -> 1112 | D43: =C43/B43 -> 0.038453558 | E43: =SUM(E38:E42) -> 15486 | F43: =E43/B43 -> 0.53551421 | G43: =SUM(G38:G42) -> 13432 | H43: =G43/B43 -> 0.46448579
A45: ③-3 Web予約受注率
A46: 月 | B46: 組数 | C46: TC | D46: 利用率 | E46: 電話 | F46: 利用率 | G46: パッサージュ | H46: 利用率 | I46: Web予約率
A47: 5 | B47: 122 | C47: 13 | D47: =C47/B47 -> 0.10655738 | E47: 16 | F47: =E47/B47 -> 0.13114754 | G47: =B47-C47-E47 -> 93 | H47: =G47/B47 -> 0.76229508 | I47: =C47/(C47+E47) -> 0.44827586
A48: 6 | B48: 2015 | C48: 240 | D48: =C48/B48 -> 0.1191067 | E48: 51 | F48: =E48/B48 -> 0.025310174 | G48: =B48-C48-E48 -> 1724 | H48: =G48/B48 -> 0.85558313 | I48: =C48/(C48+E48) -> 0.82474227
A49: 7 | B49: 3542 | C49: 674 | D49: =C49/B49 -> 0.19028797 | E49: 160 | F49: =E49/B49 -> 0.045172219 | G49: =B49-C49-E49 -> 2708 | H49: =G49/B49 -> 0.76453981 | I49: =C49/(C49+E49) -> 0.80815348
A50: 8 | B50: 3618 | C50: 885 | D50: =C50/B50 -> 0.24461028 | E50: 156 | F50: =E50/B50 -> 0.043117745 | G50: =B50-C50-E50 -> 2577 | H50: =G50/B50 -> 0.71227197 | I50: =C50/(C50+E50) -> 0.85014409
A51: 9 | B51: 340 | C51: 125 | D51: =C51/B51 -> 0.36764706 | E51: 19 | F51: =E51/B51 -> 0.055882353 | G51: =B51-C51-E51 -> 196 | H51: =G51/B51 -> 0.57647059 | I51: =C51/(C51+E51) -> 0.86805556
A52: TOTAL | B52: =SUM(B47:B51) -> 9637 | C52: =SUM(C47:C51) -> 1937 | D52: =C52/B52 -> 0.20099616 | E52: =SUM(E47:E51) -> 402 | F52: =E52/B52 -> 0.041714226 | G52: =SUM(G47:G51) -> 7298 | H52: =G52/B52 -> 0.75728961 | I52: =C52/(C52+E52) -> 0.82813168
E55: =E43*300 -> 4645800 | F55: ＝

Sheet 2024レビュー
A1: 【R6 さっぽろテレビ塔ビアガーデン（ピコレワインガーデン）振り返り】
A2: ①売上 | I2: 単位：円 | J2: 平均気温 | L2: ①コメント
A3: 月 | B3: 実績 | C3: 予算 | D3: 予算比 | E3: 差異 | F3: 予測 | G3: 予測比 | H3: 差異 | I3: 1日平均売上 | J3: LOW | K3: HIGH | V3: BG営業天候指数 | Y3: 2024 | Z3: 平均気温 | AB3: 2023 | AC3: 平均気温 | AE3: 差異 | AF3: 平均気温
A4: 4 | B4: 499227 | C4: 260000 | D4: =B4/C4 -> 1.9201038 | E4: =B4-C4 -> 239227 | F4: 260000 | G4: =B4/F4 -> 1.9201038 | H4: =B4-F4 -> 239227 | I4: =B4/T4 -> 124806.75 | T4: 4 | U4: 月 | V4: 2024 | W4: 2023 | Y4: 月 | Z4: LOW | AA4: HIGH | AB4: 月 | AC4: LOW | AD4: HIGH | AE4: 月 | AF4: LOW | AG4: HIGH | AJ4: 2024 | AK4: 期 間 | AL4: 日 数 | AM4: 売 上 | AN4: 客 数 | AO4: 客単価 | AP4: 2023 | AQ4: 期 間 | AR4: 日 数 | AS4: 売 上 | AT4: 客 数 | AU4: 客単価 | AV4: 売 上 前 年 比 | AX4: 客 数 前 年 比 | AZ4: 客 単 価 前 年 比
A5: 5 | B5: 2919145 | C5: 1851200 | D5: =B5/C5 -> 1.5768934 | E5: =B5-C5 -> 1067945 | F5: 1851200 | G5: =B5/F5 -> 1.5768934 | H5: =B5-F5 -> 1067945 | I5: =B5/T5 -> 121631.04 | J5: 11.6℃ | K5: 17.0℃ | T5: 24 | U5: 4 | V5: 1.33 | W5: 2.1 | X5: =V5/W5 -> 0.63333333 | Y5: 4 | AB5: 4 | AE5: 4 | AF5: =Z5-AC5 -> 0 | AG5: =AA5-AD5 -> 0 | AJ5: 4~5 | AK5: PC 4/27-5/19 | AL5: 23 | AM5: 2939522 | AN5: 2348 | AO5: =AM5/AN5 -> 1251.9259 | AP5: 4~5 | AQ5: PC営業なし | AR5: 0 | AS5: 0 | AT5: 0 | AU5: =AS5/AT5 -> #DIV/0! | AV5: =AM5-AS5 -> 2939522 | AW5: =AM5/AS5 -> #DIV/0! | AX5: =AN5-AT5 -> 2348 | AY5: =AN5/AT5 -> #DIV/0! | AZ5: =AO5-AU5 -> #DIV/0! | BA5: =AO5/AU5 -> #DIV/0!
A6: 6 | B6: 19194436 | C6: 25690000 | D6: =B6/C6 -> 0.74715594 | E6: =B6-C6 -> -6495564 | F6: 22000000 | G6: =B6/F6 -> 0.87247436 | H6: =B6-F6 -> -2805564 | I6: =B6/T6 -> 639814.53 | J6: 15.6℃ | K6: 23.9℃ | T6: 30 | U6: 5 | V6: 2.78 | W6: 3.37 | X6: =V6/W6 -> 0.82492582 | Y6: 5 | Z6: 11.6 | AA6: 17 | AB6: 5 | AC6: 12.7 | AD6: 20 | AE6: 5 | AF6: =Z6-AC6 -> -1.1 | AG6: =AA6-AD6 -> -3 | AJ6: 5 | AK6: BG 5/27-5/31 | AL6: 5 | AM6: 477807 | AN6: 133 | AO6: =AM6/AN6 -> 3592.5338 | AP6: 5 | AQ6: BG 5/27-5/31 | AR6: 5 | AS6: 1795227.3 | AT6: 506 | AU6: =AS6/AT6 -> 3547.88 | AV6: =AM6-AS6 -> -1317420.3 | AW6: =AM6/AS6 -> 0.26615404 | AX6: =AN6-AT6 -> -373 | AY6: =AN6/AT6 -> 0.26284585 | AZ6: =AO6-AU6 -> 44.653849 | BA6: =AO6/AU6 -> 1.0125861
A7: 7 | B7: 47613345 | C7: 51610000 | D7: =B7/C7 -> 0.92256045 | E7: =B7-C7 -> -3996655 | F7: 50000000 | G7: =B7/F7 -> 0.9522669 | H7: =B7-F7 -> -2386655 | I7: =B7/T7 -> 1535914.4 | J7: 20.5℃ | K7: 28.0℃ | T7: 31 | U7: 6 | V7: 3.19 | W7: 3.49 | X7: =V7/W7 -> 0.91404011 | Y7: 6 | Z7: 15.6 | AA7: 23.9 | AB7: 6 | AC7: 15.6 | AD7: 24.1 | AE7: 6 | AF7: =Z7-AC7 -> 0 | AG7: =AA7-AD7 -> -0.2 | AJ7: 6 | AK7: BG フル営業 | AL7: 30 | AM7: 19170665 | AN7: 5174 | AO7: =AM7/AN7 -> 3705.1923 | AP7: 6 | AQ7: BG フル営業 | AR7: 30 | AS7: 19049727 | AT7: 5309 | AU7: =AS7/AT7 -> 3588.195 | AV7: =AM7-AS7 -> 120937.73 | AW7: =AM7/AS7 -> 1.0063485 | AX7: =AN7-AT7 -> -135 | AY7: =AN7/AT7 -> 0.97457148 | AZ7: =AO7-AU7 -> 116.9973 | BA7: =AO7/AU7 -> 1.0326062
A8: 8 | B8: 55874978 | C8: 49500000 | D8: =B8/C8 -> 1.1287874 | E8: =B8-C8 -> 6374978 | F8: 50000000 | G8: =B8/F8 -> 1.1174996 | H8: =B8-F8 -> 5874978 | I8: =B8/T8 -> 1802418.6 | J8: 22.0℃ | K8: 28.4℃ | T8: 31 | U8: 7 | V8: 3.04 | W8: 3.39 | X8: =V8/W8 -> 0.89675516 | Y8: 7 | Z8: 20.5 | AA8: 28 | AB8: 7 | AC8: 21 | AD8: 27.8 | AE8: 7 | AF8: =Z8-AC8 -> -0.5 | AG8: =AA8-AD8 -> 0.2 | AJ8: 7 | AK8: BG フル営業 | AL8: 31 | AM8: 47598067 | AN8: 11438 | AO8: =AM8/AN8 -> 4161.3977 | AP8: 7 | AQ8: BG フル営業 | AR8: 31 | AS8: 44856909 | AT8: 11036 | AU8: =AS8/AT8 -> 4064.5985 | AV8: =AM8-AS8 -> 2741157.9 | AW8: =AM8/AS8 -> 1.0611089 | AX8: =AN8-AT8 -> 402 | AY8: =AN8/AT8 -> 1.0364262 | AZ8: =AO8-AU8 -> 96.799205 | BA8: =AO8/AU8 -> 1.0238152
A9: 9 | B9: 12350827 | C9: 7000000 | D9: =B9/C9 -> 1.7644039 | E9: =B9-C9 -> 5350827 | F9: 8000000 | G9: =B9/F9 -> 1.5438534 | H9: =B9-F9 -> 4350827 | I9: =B9/T9 -> 494033.08 | J9: 15.6℃ | K9: 24.0℃ | T9: 25 | U9: 8 | V9: 3.55 | W9: 3.44 | X9: =V9/W9 -> 1.0319767 | Y9: 8 | Z9: 22 | AA9: 28.4 | AB9: 8 | AC9: 24 | AD9: 30.9 | AE9: 8 | AF9: =Z9-AC9 -> -2 | AG9: =AA9-AD9 -> -2.5 | AJ9: 8 | AK9: BG フル営業 | AL9: 31 | AM9: 55870570 | AN9: 13891 | AO9: =AM9/AN9 -> 4022.0697 | AP9: 8 | AQ9: BG フル営業 | AR9: 31 | AS9: 44860591 | AT9: 11093 | AU9: =AS9/AT9 -> 4044.045 | AV9: =AM9-AS9 -> 11009979 | AW9: =AM9/AS9 -> 1.2454265 | AX9: =AN9-AT9 -> 2798 | AY9: =AN9/AT9 -> 1.2522311 | AZ9: =AO9-AU9 -> -21.97529 | BA9: =AO9/AU9 -> 0.99456601
A10: 10 | B10: 1454318 | C10: 455000 | D10: =B10/C10 -> 3.1963033 | E10: =B10-C10 -> 999318 | F10: 692727 | G10: =B10/F10 -> 2.09941 | H10: =B10-F10 -> 761591 | I10: =B10/T10 -> 242386.33 | J10: 13.7℃ | K10: 20.7℃ | T10: 6 | U10: 9 | V10: 2.72 | W10: - | X10: =V10/W10 -> #VALUE! | Y10: 9 | Z10: 15.6 | AA10: 24 | AB10: 9 | AC10: 21.4 | AD10: 28.6 | AE10: 9 | AF10: =Z10-AC10 -> -5.8 | AG10: =AA10-AD10 -> -4.6 | AJ10: 9 | AK10: BG 9/1-9/8 | AL10: 8 | AM10: 8816632 | AN10: 2410 | AO10: =AM10/AN10 -> 3658.3535 | AP10: 9 | AQ10: BG 9/1-9/3 | AR10: 8 | AS10: 4058727.3 | AT10: =263+385+76 -> 724 | AU10: =AS10/AT10 -> 5605.9769 | AV10: =AM10-AS10 -> 4757904.7 | AW10: =AM10/AS10 -> 2.1722652 | AX10: =AN10-AT10 -> 1686 | AY10: =AN10/AT10 -> 3.3287293 | AZ10: =AO10-AU10 -> -1947.6234 | BA10: =AO10/AU10 -> 0.65258091
A11: TOTAL | B11: =SUM(B4:B10) -> 139906276 | C11: =SUM(C4:C10) -> 136366200 | D11: =B11/C11 -> 1.0259601 | E11: =B11-C11 -> 3540076 | F11: =SUM(F4:F10) -> 132803927 | G11: =B11/F11 -> 1.05348 | H11: =B11-F11 -> 7102349 | I11: =B11/T11 -> 926531.63 | T11: =SUM(T4:T10) -> 151 | U11: 10 | V11: =SUM(V5:V10)/6 -> 2.7683333 | W11: =SUM(W5:W10)/5 -> 3.158 | X11: =V11/W11 -> 0.87660967 | Y11: 10 | Z11: 13.7 | AA11: 20.7 | AB11: 10 | AE11: 10 | AF11: =Z11-AC11 -> 13.7 | AG11: =AA11-AD11 -> 20.7 | AJ11: 9~10 | AK11: PC-BG 秋営業 9/14-10/6 | AL11: 23 | AM11: 4982837 | AN11: 1704 | AO11: =AM11/AN11 -> 2924.2001 | AP11: 9~10 | AQ11: PC 9/9-10/1 | AR11: 23 | AS11: 1489815.5 | AT11: 1365 | AU11: =AS11/AT11 -> 1091.4399 | AV11: =AM11-AS11 -> 3493021.5 | AW11: =AM11/AS11 -> 3.3446002 | AX11: =AN11-AT11 -> 339 | AY11: =AN11/AT11 -> 1.2483516 | AZ11: =AO11-AU11 -> 1832.7602 | BA11: =AO11/AU11 -> 2.6792132
AJ12: ビアガのみ105日 | AL12: =AL7+AL6+AL8+AL9+AL10 -> 105 | AM12: =AM7+AM6+AM8+AM9+AM10 -> 131933741 | AN12: =AN7+AN6+AN8+AN9+AN10 -> 33046 | AO12: =AM12/AN12 -> 3992.427 | AP12: ビアガのみ105日 | AR12: =AR7+AR6+AR8+AR9+AR10 -> 105 | AS12: =AS7+AS6+AS8+AS9+AS10 -> 1.1462118e+08 | AT12: =AT7+AT6+AT8+AT9+AT10 -> 28668 | AU12: =AS12/AT12 -> 3998.2274 | AV12: =AM12-AS12 -> 17312559 | AW12: =AM12/AS12 -> 1.1510415 | AX12: =AN12-AT12 -> 4378 | AY12: =AN12/AT12 -> 1.1527138 | AZ12: =AO12-AU12 -> -5.8004049 | BA12: =AO12/AU12 -> 0.99854926
A13: ②客数 | I13: 単位：名 | L13: ②コメント | V13: =V11-W11 -> -0.38966667 | AJ13: ピコレ&ピコレ共催 | AL13: =AL5+AL11 -> 46 | AM13: =AM5+AM11 -> 7922359 | AN13: =AN5+AN11 -> 4052 | AO13: =AM13/AN13 -> 1955.1725 | AP13: ピコレ&ピコレ共催 | AR13: =AR5+AR11 -> 23 | AS13: =AS5+AS11 -> 1489815.5 | AT13: =AT5+AT11 -> 1365 | AU13: =AS13/AT13 -> 1091.4399 | AV13: =AM13-AS13 -> 6432543.5 | AW13: =AM13/AS13 -> 5.3176781 | AX13: =AN13-AT13 -> 2687 | AY13: =AN13/AT13 -> 2.9684982 | AZ13: =AO13-AU13 -> 863.73261 | BA13: =AO13/AU13 -> 1.7913698
A14: 月 | B14: 実績 | C14: 予算 | D14: 予算比 | E14: 差異 | F14: 予測 | G14: 予測比 | H14: 差異 | I14: 1日平均 | V14: 2369 | AJ14: 総合計 | AL14: =SUM(AL5:AL11) -> 151 | AM14: =SUM(AM5:AM11) -> 139856100 | AN14: =SUM(AN5:AN11) -> 37098 | AO14: =AM14/AN14 -> 3769.9094 | AP14: 総合計 | AR14: =SUM(AR5:AR11) -> 128 | AS14: =SUM(AS5:AS11) -> 1.16111e+08 | AT14: =SUM(AT5:AT11) -> 30033 | AU14: =AS14/AT14 -> 3866.1139 | AV14: =AM14-AS14 -> 23745103 | AW14: =AM14/AS14 -> 1.2045035 | AX14: =AN14-AT14 -> 7065 | AY14: =AN14/AT14 -> 1.2352412 | AZ14: =AO14-AU14 -> -96.204421 | BA14: =AO14/AU14 -> 0.97511599
A15: 4 | B15: 379 | C15: 200 | D15: =B15/C15 -> 1.895 | E15: =B15-C15 -> 179 | F15: 395 | G15: =B15/F15 -> 0.95949367 | H15: =B15-F15 -> -16 | I15: =B15/T15 -> 75.8 | T15: 5
A16: 5 | B16: =133+1236+223+278+120 -> 1990 | C16: 520 | D16: =B16/C16 -> 3.8269231 | E16: =B16-C16 -> 1470 | F16: 372 | G16: =B16/F16 -> 5.3494624 | H16: =B16-F16 -> 1618 | I16: =B16/T16 -> #DIV/0! | V16: 133
A17: 6 | B17: 5174 | C17: 7000 | D17: =B17/C17 -> 0.73914286 | E17: =B17-C17 -> -1826 | F17: 5558 | G17: =B17/F17 -> 0.9309104 | H17: =B17-F17 -> -384 | I17: =B17/T17 -> 172.46667 | T17: 30 | V17: =V14-V16 -> 2236
A18: 7 | B18: 11438 | C18: 13000 | D18: =B18/C18 -> 0.87984615 | E18: =B18-C18 -> -1562 | F18: 12016 | G18: =B18/F18 -> 0.95189747 | H18: =B18-F18 -> -578 | I18: =B18/T18 -> 368.96774 | T18: 31
A19: 8 | B19: 13891 | C19: 12500 | D19: =B19/C19 -> 1.11128 | E19: =B19-C19 -> 1391 | F19: 12386 | G19: =B19/F19 -> 1.1215082 | H19: =B19-F19 -> 1505 | I19: =B19/T19 -> 448.09677 | T19: 31
A20: 9 | B20: 3458 | C20: 2000 | D20: =B20/C20 -> 1.729 | E20: =B20-C20 -> 1458 | F20: 1976 | G20: =B20/F20 -> 1.75 | H20: =B20-F20 -> 1482 | I20: =B20/T20 -> #DIV/0!
A21: 10 | B21: 538 | C21: 350 | D21: =B21/C21 -> 1.5371429 | E21: =B21-C21 -> 188 | F21: 194 | G21: =B21/F21 -> 2.7731959 | H21: =B21-F21 -> 344 | I21: =B21/T21 -> 179.33333 | T21: 3
A22: TOTAL | B22: =SUM(B15:B21) -> 36868 | C22: =SUM(C15:C21) -> 35570 | D22: =B22/C22 -> 1.0364914 | E22: =B22-C22 -> 1298 | F22: =SUM(F15:F21) -> 32897 | G22: =B22/F22 -> 1.1207101 | H22: =B22-F22 -> 3971 | I22: =B22/T22 -> 368.68 | T22: 100
A24: ③-1 客単価 | I24: 単位：円 | L24: ③コメント
A25: 月 | B25: 実績 | C25: 予算 | D25: 予算比 | E25: 差異 | F25: 予測 | G25: 予測比 | H25: 差異
A26: 4 | B26: =B4/B15 -> 1317.2216 | C26: 1300 | D26: =B26/C26 -> 1.0132474 | E26: =B26-C26 -> 17.221636 | F26: =F4/F15 -> 658.22785 | G26: =B26/F26 -> 2.0011636 | H26: =B26-F26 -> 658.99379
A27: 5 | B27: =B5/B16 -> 1466.907 | C27: 3500 | D27: =B27/C27 -> 0.4191163 | E27: =B27-C27 -> -2033.093 | F27: =F5/F16 -> 4976.3441 | G27: =B27/F27 -> 0.29477605 | H27: =B27-F27 -> -3509.4371
A28: 6 | B28: =B6/B17 -> 3709.7866 | C28: 3600 | D28: =B28/C28 -> 1.0304963 | E28: =B28-C28 -> 109.78663 | F28: =F6/F17 -> 3958.2584 | G28: =B28/F28 -> 0.937227 | H28: =B28-F28 -> -248.47174
A29: 7 | B29: =B7/B18 -> 4162.7334 | C29: 3900 | D29: =B29/C29 -> 1.0673675 | E29: =B29-C29 -> 262.73343 | F29: =F7/F18 -> 4161.1185 | G29: =B29/F29 -> 1.0003881 | H29: =B29-F29 -> 1.6149238
A30: 8 | B30: =B8/B19 -> 4022.387 | C30: 3900 | D30: =B30/C30 -> 1.0313813 | E30: =B30-C30 -> 122.38701 | F30: =F8/F19 -> 4036.8158 | G30: =B30/F30 -> 0.99642571 | H30: =B30-F30 -> -14.428747
A31: 9 | B31: =B9/B20 -> 3571.6677 | C31: 3500 | D31: =B31/C31 -> 1.0204765 | E31: =B31-C31 -> 71.667727 | F31: =F9/F20 -> 4048.583 | G31: =B31/F31 -> 0.88220193 | H31: =B31-F31 -> -476.91527
A32: 10 | B32: =B10/B21 -> 2703.1933 | C32: 1300 | D32: =B32/C32 -> 2.0793795 | E32: =B32-C32 -> 1403.1933 | F32: =F10/F21 -> 3570.7577 | G32: =B32/F32 -> 0.75703632 | H32: =B32-F32 -> -867.56442
A33: TOTAL | B33: =B11/B22 -> 3794.7889 | C33: =C11/C22 -> 3833.7419 | D33: =B33/C33 -> 0.98983942 | E33: =B33-C33 -> -38.953049 | F33: =F11/F22 -> 4036.9616 | G33: =B33/F33 -> 0.94001113 | H33: =B33-F33 -> -242.17277
A35: ③-2 プラン出卓数と月別プラン利用率
A36: 月 | B36: 客数 | C36: 5,500プラン | D36: 利用率 | E36: 6,600プラン | F36: 利用率 | G36: 8,800プラン | H36: 利用率 | I36: 小計
A37: 4 | B37: 379 | C37: 0 | D37: =C37/B37 -> 0 | E37: 0 | F37: =E37/B37 -> 0 | G37: 0 | H37: =G37/B37 -> 0 | I37: =C37+E37+G37 -> 0
A38: 5 | B38: =133+1236+223+278+120 -> 1990 | C38: 59 | D38: =C38/B38 -> 0.029648241 | E38: 0 | F38: =E38/B38 -> 0 | G38: 4 | H38: =G38/B38 -> 0.0020100503 | I38: =C38+E38+G38 -> 63
A39: 6 | B39: 5174 | C39: 2281 | D39: =C39/B39 -> 0.44085814 | E39: 58 | F39: =E39/B39 -> 0.011209896 | G39: 17 | H39: =G39/B39 -> 0.0032856591 | I39: =C39+E39+G39 -> 2356
A40: 7 | B40: 11438 | C40: 5791 | D40: =C40/B40 -> 0.50629481 | E40: 226 | F40: =E40/B40 -> 0.019758699 | G40: 167 | H40: =G40/B40 -> 0.014600455 | I40: =C40+E40+G40 -> 6184
A41: 8 | B41: 13891 | C41: 6305 | D41: =C41/B41 -> 0.45389101 | E41: 397 | F41: =E41/B41 -> 0.028579656 | G41: 140 | H41: =G41/B41 -> 0.010078468 | I41: =C41+E41+G41 -> 6842
A42: 9 | B42: 3458 | C42: 863 | D42: =C42/B42 -> 0.24956622 | E42: 37 | F42: =E42/B42 -> 0.010699826 | G42: 2 | H42: =G42/B42 -> 0.000578369 | I42: =C42+E42+G42 -> 902
A43: 10 | B43: 538 | C43: 150 | D43: =C43/B43 -> 0.27881041 | E43: 0 | F43: =E43/B43 -> 0 | G43: 0 | H43: =G43/B43 -> 0 | I43: =C43+E43+G43 -> 150
A44: TOTAL | B44: =SUM(B37:B43) -> 36868 | C44: =SUM(C37:C43) -> 15449 | D44: =C44/B44 -> 0.41903548 | E44: =SUM(E37:E43) -> 718 | F44: =E44/B44 -> 0.019474883 | G44: =SUM(G37:G43) -> 330 | H44: =G44/B44 -> 0.0089508517 | I44: =C44+E44+G44 -> 16497
A45: 月 | B45: 客数 | C45: チケットプラン | D45: 利用率 | E45: プラン合計 | F45: 利用率 | G45: アラカルト利用 | H45: 利用率
A46: 4 | B46: 379 | C46: 0 | D46: =C46/B46 -> 0 | E46: =C46+I37 -> 0 | F46: =E46/B46 -> 0 | G46: =B46-E46 -> 379 | H46: =G46/B46 -> 1 | L46: ④memo
A47: 5 | B47: =133+1236+223+278+120 -> 1990 | C47: 0 | D47: =C47/B47 -> 0 | E47: =C47+I38 -> 63 | F47: =E47/B47 -> 0.031658291 | G47: =B47-E47 -> 1927 | H47: =G47/B47 -> 0.96834171
A48: 6 | B48: 5174 | C48: 182 | D48: =C48/B48 -> 0.035175879 | E48: =C48+I39 -> 2538 | F48: =E48/B48 -> 0.49052957 | G48: =B48-E48 -> 2636 | H48: =G48/B48 -> 0.50947043
A49: 7 | B49: 11438 | C49: 757 | D49: =C49/B49 -> 0.066182899 | E49: =C49+I40 -> 6941 | F49: =E49/B49 -> 0.60683686 | G49: =B49-E49 -> 4497 | H49: =G49/B49 -> 0.39316314
A50: 8 | B50: 13891 | C50: 1287 | D50: =C50/B50 -> 0.092649917 | E50: =C50+I41 -> 8129 | F50: =E50/B50 -> 0.58519905 | G50: =B50-E50 -> 5762 | H50: =G50/B50 -> 0.41480095
A51: 9 | B51: 3458 | C51: 405 | D51: =C51/B51 -> 0.11711972 | E51: =C51+I42 -> 1307 | F51: =E51/B51 -> 0.37796414 | G51: =B51-E51 -> 2151 | H51: =G51/B51 -> 0.62203586
A52: 10 | B52: 538 | C52: 50 | D52: =C52/B52 -> 0.092936803 | E52: =C52+I43 -> 200 | F52: =E52/B52 -> 0.37174721 | G52: =B52-E52 -> 338 | H52: =G52/B52 -> 0.62825279
A53: TOTAL | B53: =SUM(B46:B52) -> 36868 | C53: =SUM(C46:C52) -> 2681 | D53: =C53/B53 -> 0.072718889 | E53: =SUM(E46:E52) -> 19178 | F53: =E53/B53 -> 0.5201801 | G53: =SUM(G46:G52) -> 17690 | H53: =G53/B53 -> 0.4798199
A55: ③-3 Web予約受注率
A56: 月 | B56: 人数 | C56: TC | D56: TC利用率 | E56: 電話 | F56: 電話利用率 | G56: パッサージュ | H56: 利用率 | I56: 予約利用率
A57: 4 | B57: 379 | C57: 0 | D57: =C57/B57 -> 0 | E57: 0 | F57: =E57/B57 -> 0 | G57: =B57-C57-E57 -> 379 | H57: =G57/B57 -> 1 | I57: =C57/(C57+E57) -> #DIV/0!
A58: 5 | B58: =133+1236+223+278+120 -> 1990 | C58: 25 | D58: =C58/B58 -> 0.012562814 | E58: 16 | F58: =E58/B58 -> 0.008040201 | G58: =B58-C58-E58 -> 1949 | H58: =G58/B58 -> 0.97939698 | I58: =C58/(C58+E58) -> 0.6097561
A59: 6 | B59: 5174 | C59: 1281 | D59: =C59/B59 -> 0.24758407 | E59: 507 | F59: =E59/B59 -> 0.09798995 | G59: =B59-C59-E59 -> 3386 | H59: =G59/B59 -> 0.65442598 | I59: =C59/(C59+E59) -> 0.71644295
A60: 7 | B60: 11438 | C60: 3566 | D60: =C60/B60 -> 0.31176779 | E60: 2029 | F60: =E60/B60 -> 0.17739115 | G60: =B60-C60-E60 -> 5843 | H60: =G60/B60 -> 0.51084106 | I60: =C60/(C60+E60) -> 0.63735478
A61: 8 | B61: 13891 | C61: 4639 | D61: =C61/B61 -> 0.33395724 | E61: 2010 | F61: =E61/B61 -> 0.14469801 | G61: =B61-C61-E61 -> 7242 | H61: =G61/B61 -> 0.52134476 | I61: =C61/(C61+E61) -> 0.6976989
A62: 9 | B62: 3458 | C62: 910 | D62: =C62/B62 -> 0.26315789 | E62: 343 | F62: =E62/B62 -> 0.099190283 | G62: =B62-C62-E62 -> 2205 | H62: =G62/B62 -> 0.63765182 | I62: =C62/(C62+E62) -> 0.72625698
A63: 10 | B63: 538 | C63: 72 | D63: =C63/B63 -> 0.133829 | E63: 65 | F63: =E63/B63 -> 0.12081784 | G63: =B63-C63-E63 -> 401 | H63: =G63/B63 -> 0.74535316 | I63: =C63/(C63+E63) -> 0.52554745
A64: TOTAL | B64: =SUM(B57:B63) -> 36868 | C64: =SUM(C57:C63) -> 10493 | D64: =C64/B64 -> 0.28460996 | E64: =SUM(E57:E63) -> 4970 | F64: =E64/B64 -> 0.13480525 | G64: =SUM(G57:G63) -> 21405 | H64: =G64/B64 -> 0.58058479 | I64: =C64/(C64+E64) -> 0.6785876
A67: 2024 | B67: 期間 | C67: 売上 | D67: 値引き | E67: 税抜売上 | F67: 税込売上 | G67: 値引き | H67: 税込売上合計
A68: 4~5 | B68: ピコレ4/27-5/19 | C68: 2939522 | D68: 4040 | E68: =C68-D68 -> 2935482 | F68: 3232260 | G68: 4040 | H68: =F68-G68 -> 3228220 | I68: 23 | J68: =1969+379 -> 2348 | L68: =H68/J68 -> 1374.8807
A69: 5 | B69: ビアガ5/27-5/31 | C69: 477807 | D69: 3480 | E69: =C69-D69 -> 474327 | F69: 525570 | G69: 3480 | H69: =F69-G69 -> 522090 | I69: 5 | J69: 133 | L69: =H69/J69 -> 3925.4887 | S69: 115000000 | T69: =S69*0.13 -> 14950000 | V69: 13
A70: 6 | B70: ビアガフル | C70: 19170665 | D70: 26790 | E70: =C70-D70 -> 19143875 | F70: 21087090 | G70: 26790 | H70: =F70-G70 -> 21060300 | I70: 30 | J70: 5174 | L70: =H70/J70 -> 4070.4097 | S70: 139757096 | T70: =S70*0.13 -> 18168422 | V70: 13
A71: 7 | B71: ビアガフル | C71: 47598067 | D71: 17800 | E71: =C71-D71 -> 47580267 | F71: 52356880 | G71: 17800 | H71: =F71-G71 -> 52339080 | I71: 31 | J71: 11438 | L71: =H71/J71 -> 4575.8944 | S71: 91500000 | T71: =S71*0.13 -> 11895000 | V71: 13
A72: 8 | B72: ビアガフル | C72: 55870570 | D72: 5980 | E72: =C72-D72 -> 55864590 | F72: 61456496 | G72: 5980 | H72: =F72-G72 -> 61450516 | I72: 31 | J72: 13891 | L72: =H72/J72 -> 4423.7647 | S72: 139757096 | T72: =S72*0.105 -> 14674495 | V72: 11
A73: 9 | B73: ビアガ9/1-9/8 | C73: 8816632 | D73: 5700 | E73: =C73-D73 -> 8810932 | F73: 9698100 | G73: 5700 | H73: =F73-G73 -> 9692400 | I73: 8 | J73: 2410 | L73: =H73/J73 -> 4021.7427 | S73: =S72-S71 -> 48257096 | T73: =T72-T71 -> 2779495.1
A74: 9~10 | B74: ピコレ共催アキノジン | C74: 4982837 | D74: 1100 | E74: =C74-D74 -> 4981737 | F74: 5480760 | G74: 1100 | H74: =F74-G74 -> 5479660 | I74: 23 | J74: =1196+508 -> 1704 | L74: =H74/J74 -> 3215.7629 | S74: 150000000 | T74: =S74*0.11 -> 16500000 | V74: 11
B75: ビアガのみ105日 | C75: =C70+C69+C71+C72+C73 -> 131933741 | D75: =D70+D69+D71+D72+D73 -> 59750 | E75: =E70+E69+E71+E72+E73 -> 131873991 | F75: =F70+F69+F71+F72+F73 -> 145124136 | G75: =G70+G69+G71+G72+G73 -> 59750 | H75: =H70+H69+H71+H72+H73 -> 145064386 | I75: =I70+I69+I71+I72+I73 -> 105
A76: チケット未食売り上げ | C76: 953750 | E76: 953750 | F76: =E76*1.1 -> 1049125 | H76: =F76-G76 -> 1049125 | I76: 23 | J76: =1196+508 -> 1704 | L76: =H76/J76 -> 615.68369
B77: ピコレ&ピコレ共催 | C77: =C68+C74 -> 7922359 | D77: =D68+D74 -> 5140 | E77: =E68+E74 -> 7917219 | F77: =F68+F74 -> 8713020 | G77: =G68+G74 -> 5140 | H77: =H68+H74 -> 8707880 | I77: =I68+I74 -> 46
B78: 総合計 | C78: =SUM(C68:C74)+C76 -> 140809850 | D78: =SUM(D68:D74) -> 64890 | E78: =SUM(E68:E74)+E76 -> 140744960 | F78: =SUM(F68:F74) -> 153837156 | G78: =SUM(G68:G74) -> 64890 | H78: =SUM(H68:H74)+H76 -> 154821391 | I78: =SUM(I68:I74) -> 151 | J78: =SUM(J68:J77) -> 38802 | L78: =H78/J78 -> 3990.0364
A80: 2023 | B80: 期間 | C80: 売上 | D80: 値引き | E80: 税抜売上 | F80: 税込売上 | G80: 値引き | H80: 税込売上合計
A81: 4~5 | B81: ピコレ参戦なし | E81: =C81-D81 -> 0 | H81: =F81-G81 -> 0 | I81: 0 | L81: =H81/J81 -> #DIV/0!
A82: 5 | B82: ビアガ5/27-5/31 | C82: =F82/1.1 -> 1795227.3 | E82: =C82-D82 -> 1795227.3 | F82: 1974750 | H82: =F82-G82 -> 1974750 | I82: 5 | J82: 506 | L82: =H82/J82 -> 3902.668
A83: 6 | B83: ビアガフル | C83: =F83/1.1 -> 19049727 | E83: =C83-D83 -> 19049727 | F83: 20954700 | H83: =F83-G83 -> 20954700 | I83: 30 | J83: 5309 | L83: =H83/J83 -> 3947.0145
A84: 7 | B84: ビアガフル | C84: =F84/1.1 -> 44856909 | E84: =C84-D84 -> 44856909 | F84: 49342600 | H84: =F84-G84 -> 49342600 | I84: 31 | J84: 11036 | L84: =H84/J84 -> 4471.0584
A85: 8 | B85: ビアガフル | C85: =F85/1.1 -> 44860591 | E85: =C85-D85 -> 44860591 | F85: 49346650 | H85: =F85-G85 -> 49346650 | I85: 31 | J85: 11093 | L85: =H85/J85 -> 4448.4495
A86: 9 | B86: ビアガ9/1-9/3 | C86: =F86/1.1 -> 4058727.3 | E86: =C86-D86 -> 4058727.3 | F86: 4464600 | H86: =F86-G86 -> 4464600 | I86: 3 | J86: =263+385+76 -> 724 | L86: =H86/J86 -> 6166.5746
A87: 9~10 | B87: ピコレ | C87: =F87/1.1 -> 1489815.5 | E87: =C87-D87 -> 1489815.5 | F87: 1638797 | H87: =F87-G87 -> 1638797 | I87: 23 | J87: 1365 | L87: =H87/J87 -> 1200.5839
B88: ビアガのみ105日 | C88: =C83+C82+C84+C85+C86 -> 1.1462118e+08 | D88: =D83+D82+D84+D85+D86 -> 0 | E88: =E83+E82+E84+E85+E86 -> 1.1462118e+08 | F88: =F83+F82+F84+F85+F86 -> 126083300 | G88: =G83+G82+G84+G85+G86 -> 0 | H88: =H83+H82+H84+H85+H86 -> 126083300 | I88: =I83+I82+I84+I85+I86 -> 100
B89: ピコレ&ピコレ共催 | C89: =C81+C87 -> 1489815.5 | D89: =D81+D87 -> 0 | E89: =E81+E87 -> 1489815.5 | F89: =F81+F87 -> 1638797 | G89: =G81+G87 -> 0 | H89: =H81+H87 -> 1638797 | I89: =I81+I87 -> 23
B90: 総合計 | C90: =SUM(C81:C87) -> 1.16111e+08 | D90: =SUM(D81:D87) -> 0 | E90: =SUM(E81:E87) -> 1.16111e+08 | F90: =SUM(F81:F87) -> 127722097 | G90: =SUM(G81:G87) -> 0 | H90: =SUM(H81:H87) -> 127722097 | I90: =SUM(I81:I87) -> 123 | J90: =SUM(J81:J89) -> 30033 | L90: =H90/J90 -> 4252.7252
E92: =E75/E90 -> 1.135758
E93: =E75-E90 -> 15762994

Sheet 2023通期実績
A1: ■R5年さっぽろテレビ塔ビアガーデン売上計画（予算）・売上予測・実績進捗確認表
B2: 計画値 | E2: 予測値 | K2: 実績進捗（派遣分のみ） | R2: ノヴェロさん請求内容 | Y2: 家賃 | AA2: 概算（仮置き）
A3: 月 | B3: 売上予算 | C3: 客数 | D3: 客単価 | E3: 労働時間（予測値） | F3: 人時生産性 | G3: 想定人件費 | H3: 人件費率 | I3: 売上予測 | J3: 対予算 | K3: 売上実績 | L3: 対予測 | M3: 対予算 | N3: 実労働時間 | O3: 人時生産性 | P3: 概算人件費率 | Q3: 派遣人件費（リザルト） | R3: 人件費 | S3: 営業日数 | T3: 拘束時間 | U3: 残業時間 | V3: 人件費合計 | W3: 交通費合計 | X3: 合計 | Y3: 家賃 | Z3: 1日 | AA3: =K9 -> 1.1462364e+08
A4: 5 | B4: 6890000 | C4: 1300 | D4: =B4/C4 -> 5300 | E4: 310 | F4: =I4/E4 -> 6332.2581 | G4: =E4*R4 -> 526437.81 | H4: =G4/B4 -> 0.076406068 | I4: 1963000 | J4: =I4/B4 -> 0.28490566 | K4: 1795227.3 | L4: =K4/I4 -> 0.91453249 | M4: =K4/B4 -> 0.26055548 | N4: =T4+U4 -> 488 | O4: =K4/N4 -> 3678.7444 | P4: =Q4/K4 -> 0.46162122 | Q4: =X4 -> 828715 | R4: =Q4/N4 -> 1698.1865 | S4: 5 | T4: 479.5 | U4: 8.5 | V4: 759715 | W4: 69000 | X4: =V4+W4 -> 828715 | Y4: 150000 | Z4: 30000 | AA4: =AA3*23.8% -> 27280425 | AB4: 人件費
A5: 6 | B5: 25440000 | C5: 4800 | D5: =B5/C5 -> 5300 | E5: 3555 | F5: =I5/E5 -> 4877.0745 | G5: =E5*R5 -> 6025477.3 | H5: =G5/B5 -> 0.23685052 | I5: 17338000 | J5: =I5/B5 -> 0.68152516 | K5: 19049727 | L5: =K5/I5 -> 1.0987269 | M5: =K5/B5 -> 0.74881003 | N5: =2946+32.5 -> 2978.5 | O5: =K5/N5 -> 6395.7453 | P5: =Q5/K5 -> 0.26500904 | Q5: =X5 -> 5048350 | R5: =Q5/N5 -> 1694.9303 | S5: 30 | T5: 2946 | U5: 32.5 | V5: 4629350 | W5: 419000 | X5: =V5+W5 -> 5048350 | Y5: 2250000 | Z5: 75000 | AA5: =AA3*31.5% -> 36106445 | AB5: 材料費
A6: 7 | B6: 25440000 | C6: 4800 | D6: =B6/C6 -> 5300 | E6: 4940 | F6: =I6/E6 -> 7088.2591 | G6: =E6*R6 -> 8385722.9 | H6: =G6/B6 -> 0.32962747 | I6: 35016000 | J6: =I6/B6 -> 1.3764151 | K6: 44856909 | L6: =K6/I6 -> 1.2810404 | M6: =K6/B6 -> 1.7632433 | N6: =4281.75+241.75 -> 4523.5 | O6: =K6/N6 -> 9916.4163 | P6: =Q6/K6 -> 0.17118228 | Q6: =X6 -> 7678708 | R6: =Q6/N6 -> 1697.5148 | S6: 31 | T6: 4281.75 | U6: 241.75 | V6: 7105708 | W6: 573000 | X6: =V6+W6 -> 7678708 | Y6: 3100000 | Z6: 100000 | AA6: =AA3*7% -> 8023654.5 | AB6: 消耗品費
A7: 8 | B7: 25440000 | C7: 4800 | D7: =B7/C7 -> 5300 | E7: 5080 | F7: =I7/E7 -> 7826.7717 | G7: =E7*R7 -> 9144000 | H7: =G7/B7 -> 0.35943396 | I7: 39760000 | J7: =I7/B7 -> 1.5628931 | K7: 44863045 | L7: =K7/I7 -> 1.1283462 | M7: =K7/B7 -> 1.7634845 | N7: =T7+U7 -> 4935.5 | O7: =K7/N7 -> 9089.8684 | P7: =Q7/K7 -> 0.20105169 | Q7: =X7 -> 9019791 | R7: 1800 | S7: 31 | T7: 4717.25 | U7: 218.25 | V7: 8392791 | W7: 627000 | X7: =V7+W7 -> 9019791 | Y7: 3100000 | Z7: 100000 | AA7: =AA3*15% -> 17193545 | AB7: イニシャル
A8: 9 | B8: 9275000 | C8: 1750 | D8: =B8/C8 -> 5300 | E8: 510 | F8: =I8/E8 -> 8431.3725 | G8: =E8*R8 -> 950482.65 | H8: =G8/B8 -> 0.10247791 | I8: 4300000 | J8: =I8/B8 -> 0.46361186 | K8: 4058727.3 | L8: =K8/I8 -> 0.94389006 | M8: =K8/B8 -> 0.43759863 | N8: =T8+U8 -> 551 | O8: =K8/N8 -> 7366.1112 | P8: =Q8/K8 -> 0.25300887 | Q8: =X8 -> 1026894 | R8: =Q8/N8 -> 1863.6915 | S8: 3 | T8: 506 | U8: 45 | V8: 958894 | W8: 68000 | X8: =V8+W8 -> 1026894 | Y8: 90000 | Z8: 30000 | AA8: =Y9 -> 8690000 | AB8: 家賃
A9: TOTAL | B9: =SUM(B4:B8) -> 92485000 | C9: =SUM(C4:C8) -> 17450 | D9: =B9/C9 -> 5300 | E9: =SUM(E4:E8) -> 14395 | F9: =I9/E9 -> 6834.1091 | G9: =E9*R9 -> 25211100 | H9: =G9/B9 -> 0.27259663 | I9: =SUM(I4:I8) -> 98377000 | J9: =I9/B9 -> 1.0637076 | K9: =SUM(K4:K8) -> 1.1462364e+08 | L9: =K9/I9 -> 1.1651467 | M9: =K9/B9 -> 1.2393754 | N9: =SUM(N4:N8) -> 13476.5 | O9: =K9/N9 -> 8505.4455 | P9: =Q9/K9 -> 0.20591266 | Q9: =SUM(Q4:Q8) -> 23602458 | R9: =Q9/N9 -> 1751.3789 | S9: =SUM(S4:S8) -> 100 | T9: =SUM(T4:T8) -> 12930.5 | U9: =SUM(U4:U8) -> 546 | V9: =SUM(V4:V8) -> 21846458 | W9: =SUM(W4:W8) -> 1756000 | X9: =SUM(X4:X8) -> 23602458 | Y9: =SUM(Y4:Y8) -> 8690000 | Z9: =SUM(Z4:Z8) -> 335000 | AA9: =AA3*5% -> 5731181.8 | AB9: 流動固定費
B10: 92485000 | C10: 提出予算 | G10: ※ノヴェロ派遣分のみ算出 | I10: ※天気要因見込まず算出 | K10: 43710 | L10: 終了時点の進捗状況 | N10: =K9/S10 -> 1146236.4 | O10: =K9-B10 -> 22138636 | P10: =K9/B10 -> 1.2393754 | S10: 100 | X10: =X9/K9 -> 0.20591266 | AA10: =AA3-AA4-AA5-AA6-AA7-AA8-AA9 -> 11598384 | AB10: 利益
B11: =B9-B10 -> 0 | C11: 差異 | D11: ※予算値は115日計算でP/D（1日平均）804千円にて積み上げ。予測は100日営業、各施策と季節波動を効かせて算出。
I14: 100000000 | J14: 予算まで | K14: =B9-K9 -> -22138636 | L14: 12 | M14: =K14/L14 -> -1844886.4 | N14: 2019 | O14: 58190982 | P14: =K9/O14 -> 1.9697835
I15: 111111111 | J15: 予測まで | K15: =I9-K9 -> -16246636 | L15: 12 | M15: =K15/L15 -> -1353886.4 | N15: 2018 | O15: 44179221 | P15: =K9/O15 -> 2.5945147
J16: 一億円まで | K16: =I14-K9 -> -14623636 | L16: 12 | M16: =K16/L16 -> -1218636.4 | N16: 平均 | O16: =(O14+O15)/2 -> 51185102 | P16: =K9/O16 -> 2.2393945
G17: 2019年度 | J17: 一億一千万まで | K17: =I15-K9 -> -3512525.4 | L17: 12 | M17: =K17/L17 -> -292710.45
G18: 91399704 | H18: =K6-K7 -> -6136.3636 | I18: 945247 | J18: =I18-H18 -> 951383.36 | K18: =K9 -> 1.1462364e+08 | L18: =K18/G18 -> 1.254092 | M18: =K18-G18 -> 23223932
F19: 0.13 | G19: =G18*0.13 -> 11881962
L25: 5187 | M25: 6717 | N25: =M25-L25 -> 1530 | O25: =M25/L25 -> 1.2949682
L26: 992 | M26: 1941 | N26: =M26-L26 -> 949 | O26: =M26/L26 -> 1.9566532
L27: 318 | M27: 2503 | N27: =M27-L27 -> 2185 | O27: =M27/L27 -> 7.8710692
L28: =SUM(L25:L27) -> 6497 | M28: =SUM(M25:M27) -> 11161 | N28: =SUM(N25:N27) -> 4664 | O28: =M28/L28 -> 1.7178698

Sheet 24-23天候指数対比
B1: ◆2024-2023 天候指数対比
B2: 4月 天候指数対比 <気象庁資料マクロクリマ> | F2: 平均気温 最高 15.7℃ （13.5℃）最低 6.5℃（5.5℃） カッコ内は前年値 <M-4th> | P2: 8月 天候指数対比 <現地ミクロクリマ> | T2: 平均気温 最高 28.4℃ （30.9℃）最低 22.0℃（24.0℃） カッコ内は前年値 <M-1st>
B3: 天候状況 | E3: ポイント | F3: 2024日数＊3 | G3: 2024合計 | H3: 比率 | I3: 2023日数＊3 | J3: 2023合計 | K3: 比率 | L3: 前年差異 | P3: 天候状況 | S3: ポイント | T3: 2024日数＊3 | U3: 2024合計 | V3: 比率 | W3: 2023日数＊3 | X3: 2023合計 | Y3: 比率 | Z3: 前年差異
B4: ポジティブ | C4: 晴れ（33度まで） | E4: 5 | F4: 0 | G4: =E4*F4 -> 0 | H4: =(F4+F5+F6)/F10 -> #DIV/0! | I4: 0 | J4: =E4*I4 -> 0 | K4: =(I4+I5+I6)/I10 -> #DIV/0! | L4: =F4-I4 -> 0 | M4: =G4-J4 -> 0 | N4: =H4-K4 -> #DIV/0! | P4: ポジティブ | Q4: 晴れ（33度まで） | S4: 5 | T4: 27 | U4: =S4*T4 -> 135 | V4: =(T4+T5+T6)/T10 -> 0.69892473 | W4: 31 | X4: =S4*W4 -> 155 | Y4: =(W4+W5+W6)/W10 -> 0.82795699 | Z4: =T4-W4 -> -4 | AA4: =U4-X4 -> -20 | AB4: =V4-Y4 -> -0.12903226
C5: 晴れ（25度以下） | E5: 4 | F5: 0 | G5: =E5*F5 -> 0 | I5: 0 | J5: =E5*I5 -> 0 | L5: =F5-I5 -> 0 | M5: =G5-J5 -> 0 | Q5: 晴れ（25度以下） | S5: 4 | T5: 0 | U5: =S5*T5 -> 0 | W5: 6 | X5: =S5*W5 -> 24 | Z5: =T5-W5 -> -6 | AA5: =U5-X5 -> -24
C6: 晴れ（33度以上15以下） 曇25度以上 | E6: 3 | F6: 0 | G6: =E6*F6 -> 0 | I6: 0 | J6: =E6*I6 -> 0 | L6: =F6-I6 -> 0 | M6: =G6-J6 -> 0 | Q6: 晴れ（33度以上15以下） 曇25度以上 | S6: 3 | T6: 38 | U6: =S6*T6 -> 114 | W6: 40 | X6: =S6*W6 -> 120 | Z6: =T6-W6 -> -2 | AA6: =U6-X6 -> -6
B7: ネガティブ | C7: 曇 | E7: 2 | F7: 0 | G7: =E7*F7 -> 0 | H7: =(F7+F8+F9)/F10 -> #DIV/0! | I7: 0 | J7: =E7*I7 -> 0 | K7: =(I7+I8+I9)/I10 -> #DIV/0! | L7: =F7-I7 -> 0 | M7: =G7-J7 -> 0 | N7: =H7-K7 -> #DIV/0! | P7: ネガティブ | Q7: 曇 | S7: 2 | T7: 6 | U7: =S7*T7 -> 12 | V7: =(T7+T8+T9)/T10 -> 0.30107527 | W7: 0 | X7: =S7*W7 -> 0 | Y7: =(W7+W8+W9)/W10 -> 0.17204301 | Z7: =T7-W7 -> 6 | AA7: =U7-X7 -> 12 | AB7: =V7-Y7 -> 0.12903226
C8: 雨 | E8: 1 | F8: 0 | G8: =E8*F8 -> 0 | I8: 0 | J8: =E8*I8 -> 0 | L8: =F8-I8 -> 0 | M8: =G8-J8 -> 0 | Q8: 雨 | S8: 1 | T8: 22 | U8: =S8*T8 -> 22 | W8: 16 | X8: =S8*W8 -> 16 | Z8: =T8-W8 -> 6 | AA8: =U8-X8 -> 6
C9: 豪雨・雷雨 | E9: 0 | F9: 0 | G9: =E9*F9 -> 0 | J9: =E9*I9 -> 0 | L9: =F9-I9 -> 0 | M9: =G9-J9 -> 0 | Q9: 豪雨・雷雨 | S9: 0 | T9: 0 | U9: =S9*T9 -> 0 | W9: 0 | X9: =S9*W9 -> 0 | Z9: =T9-W9 -> 0 | AA9: =U9-X9 -> 0
B10: TOTAL | F10: =SUM(F4:F9) -> 0 | G10: =SUM(G4:G9) -> 0 | H10: =H4+H7 -> #DIV/0! | I10: =SUM(I4:I9) -> 0 | J10: =SUM(J4:J9) -> 0 | K10: =K4+K7 -> #DIV/0! | L10: =SUM(L4:L9) -> 0 | M10: =SUM(M4:M9) -> 0 | N10: =G10/J10 -> #DIV/0! | P10: TOTAL | T10: =SUM(T4:T9) -> 93 | U10: =SUM(U4:U9) -> 283 | V10: =V4+V7 -> 1 | W10: =SUM(W4:W9) -> 93 | X10: =SUM(X4:X9) -> 315 | Y10: =Y4+Y7 -> 1 | Z10: =SUM(Z4:Z9) -> 0 | AA10: =SUM(AA4:AA9) -> -32 | AB10: =U10/X10 -> 0.8984127
F11: =G10/F10 -> #DIV/0! | I11: =J10/I10 -> #DIV/0! | L11: =F11-I11 -> #DIV/0! | N11: =F11/I11 -> #DIV/0! | T11: =U10/T10 -> 3.0430108 | W11: =X10/W10 -> 3.3870968 | Z11: =T11-W11 -> -0.34408602 | AB11: =T11/W11 -> 0.8984127
B13: 5月 天候指数対比 <現地ミクロクリマ> | F13: 平均気温 最高 17.0℃ （20.0℃）最低 11.6℃（12.7℃） カッコ内は前年値 <M-4th> | P13: 9月 天候指数対比 <現地ミクロクリマ> | T13: 平均気温 最高 24.0℃ （28.6℃）最低 15.6℃（21.4℃） カッコ内は前年値 <M- 2nd>
B14: 天候状況 | E14: ポイント | F14: 2024日数＊3 | G14: 2024合計 | H14: 比率 | I14: 2023日数＊3 | J14: 2023合計 | K14: 比率 | L14: 前年差異 | P14: 天候状況 | S14: ポイント | T14: 2024日数＊3 | U14: 2024合計 | V14: 比率 | W14: 2023日数＊3 | X14: 2023合計 | Y14: 比率 | Z14: 前年差異
B15: ポジティブ | C15: 晴れ（33度まで） | E15: 5 | F15: 0 | G15: =E15*F15 -> 0 | H15: =(F15+F16+F17)/F21 -> 0.066666667 | I15: 2 | J15: =E15*I15 -> 10 | K15: =(I15+I16+I17)/I21 -> 0.4 | L15: =F15-I15 -> -2 | M15: =G15-J15 -> -10 | N15: =H15-K15 -> -0.33333333 | P15: ポジティブ | Q15: 晴れ（33度まで） | S15: 5 | T15: 16 | U15: =S15*T15 -> 80 | V15: =(T15+T16+T17)/T21 -> 0.74666667 | W15: 5 | X15: =S15*W15 -> 25 | Y15: =(W15+W16+W17)/W21 -> 0.66666667 | Z15: =T15-W15 -> 11 | AA15: =U15-X15 -> 55 | AB15: =V15-Y15 -> 0.08
C16: 晴れ（25度以下） | E16: 4 | F16: 0 | G16: =E16*F16 -> 0 | I16: 4 | J16: =E16*I16 -> 16 | L16: =F16-I16 -> -4 | M16: =G16-J16 -> -16 | Q16: 晴れ（25度以下） | S16: 4 | T16: 32 | U16: =S16*T16 -> 128 | W16: 0 | X16: =S16*W16 -> 0 | Z16: =T16-W16 -> 32 | AA16: =U16-X16 -> 128
C17: 晴れ（33度以上15以下） 曇25度以上 | E17: 3 | F17: 1 | G17: =E17*F17 -> 3 | I17: 0 | J17: =E17*I17 -> 0 | L17: =F17-I17 -> 1 | M17: =G17-J17 -> 3 | Q17: 晴れ（33度以上15以下） 曇25度以上 | S17: 3 | T17: 8 | U17: =S17*T17 -> 24 | W17: 1 | X17: =S17*W17 -> 3 | Z17: =T17-W17 -> 7 | AA17: =U17-X17 -> 21
B18: ネガティブ | C18: 曇 | E18: 2 | F18: 5 | G18: =E18*F18 -> 10 | H18: =(F18+F19+F20)/F21 -> 0.93333333 | I18: 4 | J18: =E18*I18 -> 8 | K18: =(I18+I19+I20)/I21 -> 0.6 | L18: =F18-I18 -> 1 | M18: =G18-J18 -> 2 | N18: =H18-K18 -> 0.33333333 | P18: ネガティブ | Q18: 曇 | S18: 2 | T18: 15 | U18: =S18*T18 -> 30 | V18: =(T18+T19+T20)/T21 -> 0.25333333 | W18: 0 | X18: =S18*W18 -> 0 | Y18: =(W18+W19+W20)/W21 -> 0.33333333 | Z18: =T18-W18 -> 15 | AA18: =U18-X18 -> 30 | AB18: =V18-Y18 -> -0.08
C19: 雨 | E19: 1 | F19: 7 | G19: =E19*F19 -> 7 | I19: 5 | J19: =E19*I19 -> 5 | L19: =F19-I19 -> 2 | M19: =G19-J19 -> 2 | Q19: 雨 | S19: 1 | T19: 4 | U19: =S19*T19 -> 4 | W19: 3 | X19: =S19*W19 -> 3 | Z19: =T19-W19 -> 1 | AA19: =U19-X19 -> 1
C20: 豪雨・雷雨 | E20: 0 | F20: 2 | G20: =E20*F20 -> 0 | J20: =E20*I20 -> 0 | L20: =F20-I20 -> 2 | M20: =G20-J20 -> 0 | Q20: 豪雨・雷雨 | S20: 0 | T20: 0 | U20: =S20*T20 -> 0 | X20: =S20*W20 -> 0 | Z20: =T20-W20 -> 0 | AA20: =U20-X20 -> 0
B21: TOTAL | F21: =SUM(F15:F20) -> 15 | G21: =SUM(G15:G20) -> 20 | H21: =H15+H18 -> 1 | I21: =SUM(I15:I20) -> 15 | J21: =SUM(J15:J20) -> 39 | K21: =K15+K18 -> 1 | L21: =SUM(L15:L20) -> 0 | M21: =SUM(M15:M20) -> -19 | N21: =G21/J21 -> 0.51282051 | P21: TOTAL | T21: =SUM(T15:T20) -> 75 | U21: =SUM(U15:U20) -> 266 | V21: =V15+V18 -> 1 | W21: =SUM(W15:W20) -> 9 | X21: =SUM(X15:X20) -> 31 | Y21: =Y15+Y18 -> 1 | Z21: =SUM(Z15:Z20) -> 66 | AA21: =SUM(AA15:AA20) -> 235 | AB21: =U21/X21 -> 8.5806452
F22: =G21/F21 -> 1.3333333 | I22: =J21/I21 -> 2.6 | L22: =F22-I22 -> -1.2666667 | N22: =F22/I22 -> 0.51282051 | T22: =U21/T21 -> 3.5466667 | W22: =X21/W21 -> 3.4444444 | Z22: =T22-W22 -> 0.10222222 | AB22: =T22/W22 -> 1.0296774
B24: 6月 天候指数対比 <現地ミクロクリマ> | F24: 平均気温 最高 23.9℃ （24.1℃）最低 15.6℃（15.6℃） カッコ内は前年値 <M-3rd> | P24: 10月 天候指数対比 <気象庁資料マクロクリマ> | T24: 平均気温 最高 18.3℃ （17.9℃）最低 9.0℃（9.3℃） カッコ内は前年値 <M-5th>
B25: 天候状況 | E25: ポイント | F25: 2024日数＊3 | G25: 2024合計 | H25: 比率 | I25: 2023日数＊3 | J25: 2023合計 | K25: 比率 | L25: 前年差異 | P25: 天候状況 | S25: ポイント | T25: 2024日数＊3 | U25: 2024合計 | V25: 比率 | W25: 2023日数＊3 | X25: 2023合計 | Y25: 比率 | Z25: 前年差異
B26: ポジティブ | C26: 晴れ（33度まで） | E26: 5 | F26: 13 | G26: =E26*F26 -> 65 | H26: =(F26+F27+F28)/F32 -> 0.48888889 | I26: 20 | J26: =E26*I26 -> 100 | K26: =(I26+I27+I28)/I32 -> 0.71111111 | L26: =F26-I26 -> -7 | M26: =G26-J26 -> -35 | N26: =H26-K26 -> -0.22222222 | P26: ポジティブ | Q26: 晴れ（33度まで） | S26: 5 | T26: 2 | U26: =S26*T26 -> 10 | V26: =(T26+T27+T28)/T32 -> 0.38888889 | W26: 0 | X26: =S26*W26 -> 0 | Y26: =(W26+W27+W28)/W32 -> #DIV/0! | Z26: =T26-W26 -> 2 | AA26: =U26-X26 -> 10 | AB26: =V26-Y26 -> #DIV/0!
C27: 晴れ（25度以下） | E27: 4 | F27: 16 | G27: =E27*F27 -> 64 | I27: 38 | J27: =E27*I27 -> 152 | L27: =F27-I27 -> -22 | M27: =G27-J27 -> -88 | Q27: 晴れ（25度以下） | S27: 4 | T27: 5 | U27: =S27*T27 -> 20 | W27: 0 | X27: =S27*W27 -> 0 | Z27: =T27-W27 -> 5 | AA27: =U27-X27 -> 20
C28: 晴れ（33度以上15以下） 曇25度以上 | E28: 3 | F28: 15 | G28: =E28*F28 -> 45 | I28: 6 | J28: =E28*I28 -> 18 | L28: =F28-I28 -> 9 | M28: =G28-J28 -> 27 | Q28: 晴れ（33度以上15以下） 曇25度以上 | S28: 3 | T28: 0 | U28: =S28*T28 -> 0 | W28: 0 | X28: =S28*W28 -> 0 | Z28: =T28-W28 -> 0 | AA28: =U28-X28 -> 0
B29: ネガティブ | C29: 曇 | E29: 2 | F29: 30 | G29: =E29*F29 -> 60 | H29: =(F29+F30+F31)/F32 -> 0.51111111 | I29: 7 | J29: =E29*I29 -> 14 | K29: =(I29+I30+I31)/I32 -> 0.28888889 | L29: =F29-I29 -> 23 | M29: =G29-J29 -> 46 | N29: =H29-K29 -> 0.22222222 | P29: ネガティブ | Q29: 曇 | S29: 2 | T29: 8 | U29: =S29*T29 -> 16 | V29: =(T29+T30+T31)/T32 -> 0.61111111 | W29: 0 | X29: =S29*W29 -> 0 | Y29: =(W29+W30+W31)/W32 -> #DIV/0! | Z29: =T29-W29 -> 8 | AA29: =U29-X29 -> 16 | AB29: =V29-Y29 -> #DIV/0!
C30: 雨 | E30: 1 | F30: 15 | G30: =E30*F30 -> 15 | I30: 19 | J30: =E30*I30 -> 19 | L30: =F30-I30 -> -4 | M30: =G30-J30 -> -4 | Q30: 雨 | S30: 1 | T30: 3 | U30: =S30*T30 -> 3 | W30: 0 | X30: =S30*W30 -> 0 | Z30: =T30-W30 -> 3 | AA30: =U30-X30 -> 3
C31: 豪雨・雷雨 | E31: 0 | F31: 1 | G31: =E31*F31 -> 0 | I31: 0 | J31: =E31*I31 -> 0 | L31: =F31-I31 -> 1 | M31: =G31-J31 -> 0 | Q31: 豪雨・雷雨 | S31: 0 | T31: 0 | U31: =S31*T31 -> 0 | W31: 0 | X31: =S31*W31 -> 0 | Z31: =T31-W31 -> 0 | AA31: =U31-X31 -> 0
B32: TOTAL | F32: =SUM(F26:F31) -> 90 | G32: =SUM(G26:G31) -> 249 | H32: =H26+H29 -> 1 | I32: =SUM(I26:I31) -> 90 | J32: =SUM(J26:J31) -> 303 | K32: =K26+K29 -> 1 | L32: =SUM(L26:L31) -> 0 | M32: =SUM(M26:M31) -> -54 | N32: =G32/J32 -> 0.82178218 | P32: TOTAL | T32: =SUM(T26:T31) -> 18 | U32: =SUM(U26:U31) -> 49 | V32: =V26+V29 -> 1 | W32: =SUM(W26:W31) -> 0 | X32: =SUM(X26:X31) -> 0 | Y32: =Y26+Y29 -> #DIV/0! | Z32: =SUM(Z26:Z31) -> 18 | AA32: =SUM(AA26:AA31) -> 49 | AB32: =U32/X32 -> #DIV/0!
F33: =G32/F32 -> 2.7666667 | I33: =J32/I32 -> 3.3666667 | L33: =F33-I33 -> -0.6 | N33: =F33/I33 -> 0.82178218 | T33: =U32/T32 -> 2.7222222 | W33: =X32/W32 -> #DIV/0! | Z33: =T33-W33 -> #DIV/0! | AB33: =T33/W33 -> #DIV/0!
B35: 7月 天候指数対比 <現地ミクロクリマ> | F35: 平均気温 最高 28.0℃ （27.8℃）最低 20.5℃（21.0℃） カッコ内は前年値 <M-1st> | P35: TOTAL 天候指数 対比
B36: 天候状況 | E36: ポイント | F36: 2024日数＊3 | G36: 2024合計 | H36: 比率 | I36: 2023日数＊3 | J36: 2023合計 | K36: 比率 | L36: 前年差異 | P36: 天候状況 | S36: ポイント | T36: 2024日数＊3 | U36: 2024合計 | V36: 比率 | W36: 2023日数＊3 | X36: 2023合計 | Y36: 比率 | Z36: 前年差異
B37: ポジティブ | C37: 晴れ（33度まで） | E37: 5 | F37: 26 | G37: =E37*F37 -> 130 | H37: =(F37+F38+F39)/F43 -> 0.74193548 | I37: 35 | J37: =E37*I37 -> 175 | K37: =(I37+I38+I39)/I43 -> 0.79569892 | L37: =F37-I37 -> -9 | M37: =G37-J37 -> -45 | N37: =H37-K37 -> -0.053763441 | P37: ポジティブ | Q37: 晴れ（33度まで） | S37: 5 | T37: =F4+F15+F26+F37+T4+T15+T26 -> 84 | U37: =S37*T37 -> 420 | V37: =(T37+T38+T39)/T43 -> 0.63020833 | W37: =I4+I15+I26+I37+W4+W15+W26 -> 93 | X37: =S37*W37 -> 465 | Y37: =(W37+W38+W39)/W43 -> 0.75666667 | Z37: =T37-W37 -> -9 | AA37: =U37-X37 -> -45 | AB37: =V37-Y37 -> -0.12645833
C38: 晴れ（25度以下） | E38: 4 | F38: 5 | G38: =E38*F38 -> 20 | I38: 10 | J38: =E38*I38 -> 40 | L38: =F38-I38 -> -5 | M38: =G38-J38 -> -20 | Q38: 晴れ（25度以下） | S38: 4 | T38: =F5+F16+F27+F38+T5+T16+T27 -> 58 | U38: =S38*T38 -> 232 | W38: =I5+I16+I27+I38+W5+W16+W27 -> 58 | X38: =S38*W38 -> 232 | Z38: =T38-W38 -> 0 | AA38: =U38-X38 -> 0
C39: 晴れ（33度以上15以下） 曇25度以上 | E39: 3 | F39: 38 | G39: =E39*F39 -> 114 | I39: 29 | J39: =E39*I39 -> 87 | L39: =F39-I39 -> 9 | M39: =G39-J39 -> 27 | Q39: 晴れ（33度以上15以下） 曇25度以上 | S39: 3 | T39: =F6+F17+F28+F39+T6+T17+T28 -> 100 | U39: =S39*T39 -> 300 | W39: =I6+I17+I28+I39+W6+W17+W28 -> 76 | X39: =S39*W39 -> 228 | Z39: =T39-W39 -> 24 | AA39: =U39-X39 -> 72
B40: ネガティブ | C40: 曇 | E40: 2 | F40: 9 | G40: =E40*F40 -> 18 | H40: =(F40+F41+F42)/F43 -> 0.25806452 | I40: 4 | J40: =E40*I40 -> 8 | K40: =(I40+I41+I42)/I43 -> 0.20430108 | L40: =F40-I40 -> 5 | M40: =G40-J40 -> 10 | N40: =H40-K40 -> 0.053763441 | P40: ネガティブ | Q40: 曇 | S40: 2 | T40: =F7+F18+F29+F40+T7+T18+T29 -> 73 | U40: =S40*T40 -> 146 | V40: =(T40+T41+T42)/T43 -> 0.36979167 | W40: =I7+I18+I29+I40+W7+W18+W29 -> 15 | X40: =S40*W40 -> 30 | Y40: =(W40+W41+W42)/W43 -> 0.24333333 | Z40: =T40-W40 -> 58 | AA40: =U40-X40 -> 116 | AB40: =V40-Y40 -> 0.12645833
C41: 雨 | E41: 1 | F41: 15 | G41: =E41*F41 -> 15 | I41: 15 | J41: =E41*I41 -> 15 | L41: =F41-I41 -> 0 | M41: =G41-J41 -> 0 | Q41: 雨 | S41: 1 | T41: =F8+F19+F30+F41+T8+T19+T30 -> 66 | U41: =S41*T41 -> 66 | W41: =I8+I19+I30+I41+W8+W19+W30 -> 58 | X41: =S41*W41 -> 58 | Z41: =T41-W41 -> 8 | AA41: =U41-X41 -> 8
C42: 豪雨・雷雨 | E42: 0 | F42: 0 | G42: =E42*F42 -> 0 | J42: =E42*I42 -> 0 | L42: =F42-I42 -> 0 | M42: =G42-J42 -> 0 | Q42: 豪雨・雷雨 | S42: 0 | T42: =F9+F20+F31+F42+T9+T20+T31 -> 3 | U42: =S42*T42 -> 0 | W42: =I9+I20+I31+I42+W9+W20+W31 -> 0 | X42: =S42*W42 -> 0 | Z42: =T42-W42 -> 3 | AA42: =U42-X42 -> 0
B43: TOTAL | F43: =SUM(F37:F42) -> 93 | G43: =SUM(G37:G42) -> 297 | H43: =H37+H40 -> 1 | I43: =SUM(I37:I42) -> 93 | J43: =SUM(J37:J42) -> 325 | K43: =K37+K40 -> 1 | L43: =SUM(L37:L42) -> 0 | M43: =SUM(M37:M42) -> -28 | N43: =G43/J43 -> 0.91384615 | P43: TOTAL | T43: =SUM(T37:T42) -> 384 | U43: =SUM(U37:U42) -> 1164 | V43: =V37+V40 -> 1 | W43: =SUM(W37:W42) -> 300 | X43: =SUM(X37:X42) -> 1013 | Y43: =Y37+Y40 -> 1 | Z43: =SUM(Z37:Z42) -> 84 | AA43: =SUM(AA37:AA42) -> 151 | AB43: =U43/X43 -> 1.1490622
F44: =G43/F43 -> 3.1935484 | I44: =J43/I43 -> 3.4946237 | L44: =F44-I44 -> -0.30107527 | N44: =F44/I44 -> 0.91384615 | T44: =U43/T43 -> 3.03125 | W44: =X43/W43 -> 3.3766667 | Z44: =T44-W44 -> -0.34541667 | AB44: =T44/W44 -> 0.89770484

Sheet 24-23期間別KPI対比
B1: 【KPI対比（予算比・前年比）】
B2: 実績 | C2: 営 業 形 態 | D2: 日 数 | E2: 売 上 | F2: 客 数 | G2: 客単価 | H2: 予算 | I2: 予 定 | J2: 日 数 | K2: 売 上 | L2: 客 数 | M2: 客単価 | N2: 売 上 予 算 比 | P2: 客 数 予 算 比 | R2: 客 単 価 予 算 比
B3: 4 | C3: PC | D3: 5 | E3: 499227 | F3: 400 | G3: =E3/F3 -> 1248.0675 | H3: 4 | I3: PC | J3: 5 | K3: 260000 | L3: 200 | M3: =K3/L3 -> 1300 | N3: =E3-K3 -> 239227 | O3: =E3/K3 -> 1.9201038 | P3: =F3-L3 -> 200 | Q3: =F3/L3 -> 2 | R3: =G3-M3 -> -51.9325 | S3: =G3/M3 -> 0.96005192
B4: 5 | C4: PC & BG | D4: 23 | E4: 2919145 | F4: 2102 | G4: =E4/F4 -> 1388.7464 | H4: 5 | I4: PC & BG | J4: 23 | K4: 1853120 | L4: 520 | M4: =K4/L4 -> 3563.6923 | N4: =E4-K4 -> 1066025 | O4: =E4/K4 -> 1.5752596 | P4: =F4-L4 -> 1582 | Q4: =F4/L4 -> 4.0423077 | R4: =G4-M4 -> -2174.9459 | S4: =G4/M4 -> 0.38969314
B5: 6 | C5: BG フル営業 | D5: 30 | E5: 19170665 | F5: 5174 | G5: =E5/F5 -> 3705.1923 | H5: 6 | I5: BG フル営業 | J5: 30 | K5: 25690000 | L5: 7000 | M5: =K5/L5 -> 3670 | N5: =E5-K5 -> -6519335 | O5: =E5/K5 -> 0.74623063 | P5: =F5-L5 -> -1826 | Q5: =F5/L5 -> 0.73914286 | R5: =G5-M5 -> 35.192308 | S5: =G5/M5 -> 1.0095892
B6: 7 | C6: BG フル営業 | D6: 31 | E6: 47598067 | F6: 11438 | G6: =E6/F6 -> 4161.3977 | H6: 7 | I6: BG フル営業 | J6: 31 | K6: 51610000 | L6: 13000 | M6: =K6/L6 -> 3970 | N6: =E6-K6 -> -4011933 | O6: =E6/K6 -> 0.92226443 | P6: =F6-L6 -> -1562 | Q6: =F6/L6 -> 0.87984615 | R6: =G6-M6 -> 191.39771 | S6: =G6/M6 -> 1.048211
B7: 8 | C7: BG フル営業 | D7: 31 | E7: 55870570 | F7: 13891 | G7: =E7/F7 -> 4022.0697 | H7: 8 | I7: BG フル営業 | J7: 31 | K7: 49500000 | L7: 12500 | M7: =K7/L7 -> 3960 | N7: =E7-K7 -> 6370570 | O7: =E7/K7 -> 1.1286984 | P7: =F7-L7 -> 1391 | Q7: =F7/L7 -> 1.11128 | R7: =G7-M7 -> 62.069685 | S7: =G7/M7 -> 1.0156742
B8: 9 | C8: BG & PC | D8: 25 | E8: =12344645-537 -> 12344108 | F8: 3585 | G8: =E8/F8 -> 3443.2658 | H8: 9 | I8: BG & PC | J8: 25 | K8: 7000000 | L8: 2000 | M8: =K8/L8 -> 3500 | N8: =E8-K8 -> 5344108 | O8: =E8/K8 -> 1.763444 | P8: =F8-L8 -> 1585 | Q8: =F8/L8 -> 1.7925 | R8: =G8-M8 -> -56.73417 | S8: =G8/M8 -> 0.98379024
B9: 10 | C9: BG & PC | D9: 6 | E9: 1454318 | F9: 508 | G9: =E9/F9 -> 2862.8307 | H9: 10 | I9: PC | J9: 6 | K9: 455000 | L9: 350 | M9: =K9/L9 -> 1300 | N9: =E9-K9 -> 999318 | O9: =E9/K9 -> 3.1963033 | P9: =F9-L9 -> 158 | Q9: =F9/L9 -> 1.4514286 | R9: =G9-M9 -> 1562.8307 | S9: =G9/M9 -> 2.2021775
B10: 総合計 | D10: =SUM(D3:D9) -> 151 | E10: =SUM(E3:E9) -> 139856100 | F10: =SUM(F3:F9) -> 37098 | G10: =E10/F10 -> 3769.9094 | H10: 総合計 | J10: =SUM(J3:J9) -> 151 | K10: =SUM(K3:K9) -> 136368120 | L10: =SUM(L3:L9) -> 35570 | M10: =K10/L10 -> 3833.7959 | N10: =E10-K10 -> 3487980 | O10: =E10/K10 -> 1.0255777 | P10: =F10-L10 -> 1528 | Q10: =F10/L10 -> 1.0429575 | R10: =G10-M10 -> -63.886466 | S10: =G10/M10 -> 0.98333598
B12: 2024 | C12: 営 業 形 態 | D12: 日 数 | E12: 売 上 | F12: 客 数 | G12: 客単価 | H12: 2023 | I12: 営 業 形 態 | J12: 日 数 | K12: 売 上 | L12: 客 数 | M12: 客単価 | N12: 売 上 前 年 比 | P12: 客 数 前 年 比 | R12: 客 単 価 前 年 比
B13: 4~5 | C13: PC 4/27-5/19 | D13: 23 | E13: 2939522 | F13: 2348 | G13: =E13/F13 -> 1251.9259 | H13: 4~5 | I13: PC営業なし | J13: 0 | K13: 0 | L13: 0 | M13: =K13/L13 -> #DIV/0! | N13: =E13-K13 -> 2939522 | O13: =E13/K13 -> #DIV/0! | P13: =F13-L13 -> 2348 | Q13: =F13/L13 -> #DIV/0! | R13: =G13-M13 -> #DIV/0! | S13: =G13/M13 -> #DIV/0!
B14: 5 | C14: BG 5/27-5/31 | D14: 5 | E14: 477807 | F14: 133 | G14: =E14/F14 -> 3592.5338 | H14: 5 | I14: BG 5/27-5/31 | J14: 5 | K14: 1795227.3 | L14: 506 | M14: =K14/L14 -> 3547.88 | N14: =E14-K14 -> -1317420.3 | O14: =E14/K14 -> 0.26615404 | P14: =F14-L14 -> -373 | Q14: =F14/L14 -> 0.26284585 | R14: =G14-M14 -> 44.653849 | S14: =G14/M14 -> 1.0125861
B15: 6 | C15: BG フル営業 | D15: 30 | E15: 19170665 | F15: 5174 | G15: =E15/F15 -> 3705.1923 | H15: 6 | I15: BG フル営業 | J15: 30 | K15: 19049727 | L15: 5309 | M15: =K15/L15 -> 3588.195 | N15: =E15-K15 -> 120937.73 | O15: =E15/K15 -> 1.0063485 | P15: =F15-L15 -> -135 | Q15: =F15/L15 -> 0.97457148 | R15: =G15-M15 -> 116.9973 | S15: =G15/M15 -> 1.0326062
B16: 7 | C16: BG フル営業 | D16: 31 | E16: 47598067 | F16: 11438 | G16: =E16/F16 -> 4161.3977 | H16: 7 | I16: BG フル営業 | J16: 31 | K16: 44856909 | L16: 11036 | M16: =K16/L16 -> 4064.5985 | N16: =E16-K16 -> 2741157.9 | O16: =E16/K16 -> 1.0611089 | P16: =F16-L16 -> 402 | Q16: =F16/L16 -> 1.0364262 | R16: =G16-M16 -> 96.799205 | S16: =G16/M16 -> 1.0238152
B17: 8 | C17: BG フル営業 | D17: 31 | E17: 55870570 | F17: 13891 | G17: =E17/F17 -> 4022.0697 | H17: 8 | I17: BG フル営業 | J17: 31 | K17: 44860591 | L17: 11093 | M17: =K17/L17 -> 4044.045 | N17: =E17-K17 -> 11009979 | O17: =E17/K17 -> 1.2454265 | P17: =F17-L17 -> 2798 | Q17: =F17/L17 -> 1.2522311 | R17: =G17-M17 -> -21.97529 | S17: =G17/M17 -> 0.99456601
B18: 9 | C18: BG 9/1-9/8 | D18: 8 | E18: 8816632 | F18: 2410 | G18: =E18/F18 -> 3658.3535 | H18: 9 | I18: BG 9/1-9/3 | J18: 3 | K18: 4058727.3 | L18: =263+385+76 -> 724 | M18: =K18/L18 -> 5605.9769 | N18: =E18-K18 -> 4757904.7 | O18: =E18/K18 -> 2.1722652 | P18: =F18-L18 -> 1686 | Q18: =F18/L18 -> 3.3287293 | R18: =G18-M18 -> -1947.6234 | S18: =G18/M18 -> 0.65258091
B19: 9~10 | C19: PC-BG 秋営業 9/14-10/6 | D19: 23 | E19: 4982837 | F19: 1704 | G19: =E19/F19 -> 2924.2001 | H19: 9~10 | I19: PC 9/9-10/1 | J19: 23 | K19: 1489815.5 | L19: 1365 | M19: =K19/L19 -> 1091.4399 | N19: =E19-K19 -> 3493021.5 | O19: =E19/K19 -> 3.3446002 | P19: =F19-L19 -> 339 | Q19: =F19/L19 -> 1.2483516 | R19: =G19-M19 -> 1832.7602 | S19: =G19/M19 -> 2.6792132
B20: ビアガのみ105日 | D20: =D15+D14+D16+D17+D18 -> 105 | E20: =E15+E14+E16+E17+E18 -> 131933741 | F20: =F15+F14+F16+F17+F18 -> 33046 | G20: =E20/F20 -> 3992.427 | H20: ビアガのみ100日 | J20: =J15+J14+J16+J17+J18 -> 100 | K20: =K15+K14+K16+K17+K18 -> 1.1462118e+08 | L20: =L15+L14+L16+L17+L18 -> 28668 | M20: =K20/L20 -> 3998.2274 | N20: =E20-K20 -> 17312559 | O20: =E20/K20 -> 1.1510415 | P20: =F20-L20 -> 4378 | Q20: =F20/L20 -> 1.1527138 | R20: =G20-M20 -> -5.8004049 | S20: =G20/M20 -> 0.99854926
B21: ピコレ&ピコレ共催 | D21: =D13+D19 -> 46 | E21: =E13+E19 -> 7922359 | F21: =F13+F19 -> 4052 | G21: =E21/F21 -> 1955.1725 | H21: ピコレ&ピコレ共催 | J21: =J13+J19 -> 23 | K21: =K13+K19 -> 1489815.5 | L21: =L13+L19 -> 1365 | M21: =K21/L21 -> 1091.4399 | N21: =E21-K21 -> 6432543.5 | O21: =E21/K21 -> 5.3176781 | P21: =F21-L21 -> 2687 | Q21: =F21/L21 -> 2.9684982 | R21: =G21-M21 -> 863.73261 | S21: =G21/M21 -> 1.7913698
B22: 総合計 | D22: =SUM(D13:D19) -> 151 | E22: =SUM(E13:E19) -> 139856100 | F22: =SUM(F13:F19) -> 37098 | G22: =E22/F22 -> 3769.9094 | H22: 総合計 | J22: =SUM(J13:J19) -> 123 | K22: =SUM(K13:K19) -> 1.16111e+08 | L22: =SUM(L13:L19) -> 30033 | M22: =K22/L22 -> 3866.1139 | N22: =E22-K22 -> 23745103 | O22: =E22/K22 -> 1.2045035 | P22: =F22-L22 -> 7065 | Q22: =F22/L22 -> 1.2352412 | R22: =G22-M22 -> -96.204421 | S22: =G22/M22 -> 0.97511599

Sheet 2024計画値・予測・実績進捗
A1: ■R6年 ポップアップ ヒツジニワイン / さっぽろテレビ塔ビアガーデン売上計画（予算）・売上予測（9/8まで）・実績進捗確認表
B2: 計画値 | E2: 予測値（目標値） | K2: 実績進捗（派遣分のみ） | R2: ノヴェロさん請求内容 | Z2: 家賃 | AB2: 概算（仮置き）
A3: 月 | B3: 売上予算 | C3: 客数 | D3: 客単価 | E3: 労働時間（予測値） | F3: 人時生産性 | G3: 想定人件費 | H3: 人件費率 | I3: 売上予測 | J3: 対予算 | K3: 売上実績 | L3: 対予測 | M3: 対予算 | N3: 実労働時間 | O3: 人時生産性 | P3: 概算人件費率 | Q3: 派遣人件費（リザルト） | R3: 人件費 | S3: 営業日数 | T3: 拘束時間 | U3: 残業時間 | V3: 人件費合計 | W3: 交通費合計 | X3: 手当 | Y3: 合計 | Z3: 家賃 | AA3: 1日 | AB3: =K11 -> 1.4045928e+08 | AQ3: =AQ4/AQ5 -> 1.1585148
A4: 4 | B4: 260000 | C4: 200 | D4: =B4/C4 -> 1300 | E4: 200 | F4: =I4/E4 -> 1300 | G4: =E4*R4 -> #DIV/0! | H4: =G4/B4 -> #DIV/0! | I4: 260000 | J4: =I4/B4 -> 1 | K4: 499227 | L4: =K4/I4 -> 1.9201038 | M4: =K4/B4 -> 1.9201038 | N4: =T4+U4 -> 0 | O4: =K4/N4 -> #DIV/0! | P4: =Q4/K4 -> 0 | Q4: =Y4 -> 0 | R4: =Q4/N4 -> #DIV/0! | Y4: =V4+W4 -> 0 | AA4: 30000 | AB4: =AB3*23.8% -> 33429308 | AC4: 人件費 | AD4: 時給＋交通費 | AH4: 499227 | AO4: =AO8*AO6 -> 6865350 | AP4: =AP8*AP6 -> 3664000 | AQ4: =AO4+AP4 -> 10529350
A5: 5 | B5: 1851200 | C5: 520 | D5: =B5/C5 -> 3560 | E5: 550 | F5: =I5/E5 -> 3365.8182 | G5: =E5*R5 -> 991969.37 | H5: =G5/B5 -> 0.53585208 | I5: 1851200 | J5: =I5/B5 -> 1 | K5: 2919145 | L5: =K5/I5 -> 1.5768934 | M5: =K5/B5 -> 1.5768934 | N5: =T5+U5 -> 579.5 | O5: =K5/N5 -> 5037.3512 | P5: =Q5/K5 -> 0.35804148 | Q5: =Y5 -> 1045175 | R5: =Q5/N5 -> 1803.5807 | S5: 5 | T5: 579.5 | U5: 0 | V5: 956175 | W5: 89000 | Y5: =V5+W5+X5 -> 1045175 | AA5: 30000 | AD5: Timee | AF5: Forking | AH5: 2919145 | AO5: =AO7*AO6 -> 7555862.5 | AP5: =AP7*AP6 -> 1532800 | AQ5: =AO5+AP5 -> 9088662.5
A6: 6 | B6: 25690000 | C6: 7000 | D6: =B6/C6 -> 3670 | E6: 4500 | F6: =I6/E6 -> 4888.8889 | G6: =E6*R6 -> 8136786.5 | H6: =G6/B6 -> 0.31672972 | I6: 22000000 | J6: =I6/B6 -> 0.85636434 | K6: ='2024.6月 '!CE93 -> 19747436 | L6: =K6/I6 -> 0.89761074 | M6: =K6/B6 -> 0.76868184 | N6: =T6+U6 -> 3587.5 | O6: =K6/N6 -> 5504.5119 | P6: =Q6/K6 -> 0.32848958 | Q6: =Y6 -> 6486827 | R6: =Q6/N6 -> 1808.1748 | S6: 30 | T6: 3580.5 | U6: 7 | V6: 5939877 | W6: 545000 | X6: 1950 | Y6: =V6+W6+X6 -> 6486827 | AA6: 75000 | AD6: 0 | AE6: 0 | AF6: 250 | AG6: 370861 | AM6: 157 | AO6: 1850 | AP6: 1600
A7: 7 | B7: 51610000 | C7: 13000 | D7: =B7/C7 -> 3970 | E7: 5600 | F7: =I7/E7 -> 8928.5714 | G7: =E7*R7 -> 8405473.9 | H7: =G7/B7 -> 0.16286522 | I7: 50000000 | J7: =I7/B7 -> 0.9688045 | K7: ='2024.7月'!CE93 -> 47613345 | L7: =K7/I7 -> 0.95226691 | M7: =K7/B7 -> 0.92256046 | N7: =T7+AD7+AF7+U7 -> 5074.25 | O7: =K7/N7 -> 9383.3267 | P7: =Q7/K7 -> 0.15996219 | Q7: =Y7 -> 7616335 | R7: =Q7/N7 -> 1500.9775 | S7: 31 | T7: 4084.25 | U7: 32 | V7: 7019597 | W7: 583000 | X7: 13738 | Y7: =V7+W7+X7 -> 7616335 | AA7: 100000 | AB7: =AB3*31.5% -> 44244672 | AC7: 材料費 | AD7: 303 | AE7: 391038 | AF7: 655 | AG7: 976046 | AH7: =AE7+AG7 -> 1367084 | AN7: =AF7+AD7+T7 -> 5042.25 | AO7: =AN7-AP7 -> 4084.25 | AP7: =AD7+AF7 -> 958
A8: 8 | B8: 49500000 | C8: 12500 | D8: =B8/C8 -> 3960 | E8: 5600 | F8: =I8/E8 -> 8928.5714 | G8: =E8*R8 -> 8711664.7 | H8: =G8/B8 -> 0.17599323 | I8: 50000000 | J8: =I8/B8 -> 1.010101 | K8: ='2024.8月'!CE93 -> 55874978 | L8: =K8/I8 -> 1.1174996 | M8: =K8/B8 -> 1.1287874 | N8: =T8+U8+AD8+AF8 -> 5382 | O8: =K8/N8 -> 10381.824 | P8: =Q8/K8 -> 0.14984403 | Q8: =Y8 -> 8372532 | R8: =Q8/N8 -> 1555.6544 | S8: 31 | T8: 4444 | U8: 39 | V8: 7728270 | W8: 633000 | X8: 11262 | Y8: =V8+W8+X8 -> 8372532 | AA8: 100000 | AB8: =AB3*7% -> 9832149.4 | AC8: 消耗品費 | AD8: 23 | AE8: 52747 | AF8: 876 | AG8: 1316824 | AH8: =AE8+AG8 -> 1369571 | AN8: 6001 | AO8: =AN8-AP8 -> 3711 | AP8: 2290
A9: 9 | B9: 7000000 | C9: 2000 | D9: =B9/C9 -> 3500 | E9: 1400 | F9: =I9/E9 -> 5714.2857 | G9: =E9*R9 -> 2660000 | H9: =G9/B9 -> 0.38 | I9: 8000000 | J9: =I9/B9 -> 1.1428571 | K9: ='2024.9月'!CE93 -> 12350827 | L9: =K9/I9 -> 1.5438534 | M9: =K9/B9 -> 1.7644039 | N9: =T9+U9 -> 1065 | O9: =K9/N9 -> 11597.021 | P9: =Q9/K9 -> 0.16334582 | Q9: =Y9 -> 2017456 | R9: 1900 | S9: 8 | T9: 1063 | U9: 2 | V9: 1866106 | W9: 150000 | X9: 1350 | Y9: =V9+W9+X9 -> 2017456 | AA9: 30000 | AB9: 25266300 | AC9: イニシャル | AD9: 23 | AE9: =51100+5700 -> 56800 | AF9: 912 | AG9: 1468290 | AH9: =AE9+AG9 -> 1525090 | AJ9: 17040 | AN9: =AN8/AN7 -> 1.1901433 | AO9: =AO8/AO7 -> 0.90861235 | AP9: =AP8/AP7 -> 2.3903967
A10: 10 | B10: 455000 | C10: 350 | D10: =B10/C10 -> 1300 | E10: 100 | F10: =I10/E10 -> 6927.2727 | G10: =E10*R10 -> 190000 | H10: =G10/B10 -> 0.41758242 | I10: ='2024.10'!BL93 -> 692727.27 | J10: =I10/B10 -> 1.5224775 | K10: ='2024.10'!CD93 -> 1454318.2 | L10: =K10/I10 -> 2.0994094 | M10: =K10/B10 -> 3.1963037 | N10: =T10+U10 -> 0 | O10: =K10/N10 -> #DIV/0! | P10: =Q10/K10 -> 0 | R10: 1900 | Y10: =V10+W10 -> 0 | AA10: 30000 | AB10: 14000000 | AC10: 家賃 | AF10: 278 | AG10: 462089 | AH10: =AE10+AG10 -> 462089 | AJ10: 業務委託＆スキマ人件費費用圧縮対策<25年度想定>
A11: TOTAL | B11: =SUM(B4:B10) -> 136366200 | C11: =SUM(C4:C10) -> 35570 | D11: =B11/C11 -> 3833.7419 | E11: =SUM(E4:E10) -> 17950 | F11: =I11/E11 -> 7398.5475 | G11: =E11*R11 -> 29220145 | H11: =G11/B11 -> 0.21427703 | I11: =SUM(I4:I10) -> 1.3280393e+08 | J11: =I11/B11 -> 0.97387716 | K11: =SUM(K4:K10) -> 1.4045928e+08 | L11: =K11/I11 -> 1.057644 | M11: =K11/B11 -> 1.0300153 | N11: =SUM(N4:N10) -> 15688.25 | O11: =K11/N11 -> 8953.1514 | P11: =Q11/K11 -> 0.18182014 | Q11: =SUM(Q4:Q10) -> 25538325 | R11: =Q11/N11 -> 1627.8632 | S11: =SUM(S4:S10) -> 105 | T11: =SUM(T4:T10) -> 13751.25 | U11: =SUM(U4:U10) -> 80 | V11: =SUM(V4:V10) -> 23510025 | W11: =SUM(W4:W10) -> 2000000 | Y11: =SUM(Y4:Y10) -> 25538325 | Z11: =SUM(Z4:Z10) -> 0 | AA11: =SUM(AA4:AA10) -> 395000 | AB11: =AB3*5% -> 7022963.9 | AC11: 流動固定費 | AD11: =SUM(AD7:AD10) -> 349 | AE11: =SUM(AE7:AE10) -> 500585 | AF11: =SUM(AF6:AF10) -> 2971 | AG11: =SUM(AG6:AG10) -> 4594110 | AH11: スキマ | AI11: =AE11+AG11 -> 5094695 | AJ11: =AI11/AI13 -> 0.16631383 | AK11: =AF11+AD11 -> 3320 | AL11: =AI11/AK11 -> 1534.5467 | AM11: =AK11/AK13 -> 0.19357472 | AN11: 6000 | AO11: 1560 | AP11: =AN11*AO11 -> 9360000 | AQ11: =AN11/AN13 -> 0.34983383 | AR11: =AP11/AP13 -> 0.30641407 | AS11: =AO11*AK11 -> 5179200
B12: 136366200 | C12: 提出予算 | I12: ※天気要因見込まず算出 | K12: 44109 | L12: 終了時点の進捗状況 | N12: =K11/S12 -> 1404592.8 | O12: =K11-B12 -> 4093077.5 | P12: =K11/B12 -> 1.0300153 | Q12: =Q11/K11 -> 0.18182014 | S12: 100 | Y12: =Y11/K11 -> 0.18182014 | AB12: =AB3-AB4-AB7-AB8-AB9-AB10-AB11 -> 6663883.7 | AC12: 利益 | AE12: =AE11/AD11 -> 1434.341 | AG12: =AG11/AF11 -> 1546.3177 | AH12: 派遣 | AI12: =Q11 -> 25538325 | AJ12: =AI12/AI13 -> 0.83368617 | AK12: 13831 | AL12: =AI12/AK12 -> 1846.4554 | AM12: =AK12/AK13 -> 0.80642528 | AN12: =AK13-AN11 -> 11151 | AO12: 1900 | AP12: =AN12*AO12 -> 21186900 | AQ12: =AN12/AN13 -> 0.65016617 | AR12: =AP12/AP13 -> 0.69358593 | AS12: =AO12*AK12 -> 26278900
B13: =B11-B12 -> 0 | C13: 差異 | AG13: 139916000 | AH13: 合計 | AI13: =SUM(AI11:AI12) -> 30633020 | AJ13: =AI13/AG13 -> 0.21893865 | AK13: =SUM(AK11:AK12) -> 17151 | AL13: =(AL11+AL12)/2 -> 1690.5011 | AN13: =SUM(AN11:AN12) -> 17151 | AO13: =(AO11+AO12)/2 -> 1730 | AP13: =SUM(AP11:AP12) -> 30546900 | AS13: =SUM(AS11:AS12) -> 31458100
AJ14: 人件費率 | AK14: 労働時間 | AL14: 単価 | AM14: 比率 | AN14: 労働時間 | AO14: 単価 | AP14: 人件費 | AQ14: 労働時間比率 | AR14: 人件費比率 | AS14: =AS13/AG13 -> 0.22483562
AP15: =AS13-AP13 -> 911200 | AS15: =AS13-AI13 -> 825080
I16: 100000000 | J16: 予算まで | K16: =B11-K11 -> -4093077.5 | L16: 12 | M16: =K16/L16 -> -341089.79 | N16: 2019 | O16: 58190982 | P16: =K11/O16 -> 2.4137637 | V16: 税込 | AP16: =AS15-AP15 -> -86120
B17: =B7+B8 -> 101110000 | C17: =K7+K8 -> 1.0348832e+08 | D17: =C17-B17 -> 2378323.6 | I17: 111111111 | J17: 予測まで | K17: =I11-K11 -> -7655350.2 | L17: 12 | M17: =K17/L17 -> -637945.85 | N17: 2018 | O17: 44179221 | P17: =K11/O17 -> 3.1793063 | U17: 5 | V17: 1149692
J18: 一億円まで | K18: =I16-K11 -> -40459277 | L18: 12 | M18: =K18/L18 -> -3371606.5 | N18: 平均 | O18: =(O16+O17)/2 -> 51185102 | P18: =K11/O18 -> 2.7441438 | U18: 6 | V18: 7135509
G19: 2019年度 | J19: 一億一千万まで | K19: =I17-K11 -> -29348166 | L19: 12 | M19: =K19/L19 -> -2445680.5 | U19: 7 | V19: 8381268 | Z19: 4085 | AB19: =K7 -> 47613345
G20: 91399704 | H20: =K8-K9 -> 43524151 | I20: 945247 | J20: =I20-H20 -> -42578904 | K20: =K11 -> 1.4045928e+08 | L20: =K20/G20 -> 1.5367586 | M20: =K20-G20 -> 49059573 | U20: 8 | V20: 9209785 | Y20: 3700 | Z20: 3700 | AB20: 63000000
U21: 9 | V21: 2219201 | Z21: =Z20/Z19 -> 0.90575275 | AB21: =AB20/AB19 -> 1.3231584
V22: =SUM(V17:V21) -> 28095455
I23: 115000000 | K23: =K11 -> 1.4045928e+08 | L23: =K23/I23 -> 1.221385 | N23: =K23*1.1 -> 1.5450521e+08
M24: 150000000 | N24: =M24*10/110 -> 13636364 | O24: =M24-N24 -> 1.3636364e+08 | P24: =K11-O24 -> 4095641.1
A25: ■大通りビアガーデン2024 実績
A26: 推計 | B26: 2019 | C26: ー | D26: 2023 | E26: 2024 | F26: 2006 | H26: 2019 | I26: =G20 -> 91399704 | J26: =K11/I26 -> 1.5367586 | K26: =K11-I26 -> 49059573
A27: 来場者数 | B27: 1170000 | D27: 886000 | E27: 902000 | F27: 1523000 | H27: 2023 | I27: 114623699 | J27: =K11/I27 -> 1.2253947 | K27: =K11-I27 -> 25835578 | L27: 5187 | M27: 6717 | N27: =M27-L27 -> 1530 | O27: =M27/L27 -> 1.2949682
A28: 前年比 | B28: - | D28: 75.8 | E28: 101.8 | F28: =F27/E27 -> 1.6884701 | L28: 992 | M28: 1941 | N28: =M28-L28 -> 949 | O28: =M28/L28 -> 1.9566532
A29: ビール消費量（L） | B29: 441456 | D29: 334182 | E29: 340050 | F29: 574842 | L29: 318 | M29: 2503 | N29: =M29-L29 -> 2185 | O29: =M29/L29 -> 7.8710692
A30: 前年比 | B30: - | D30: 75.7 | E30: =E29/D29 -> 1.0175593 | F30: =F29/E29 -> 1.6904632 | L30: =SUM(L27:L29) -> 6497 | M30: =SUM(M27:M29) -> 11161 | N30: =SUM(N27:N29) -> 4664 | O30: =M30/L30 -> 1.7178698
A31: 20L樽本数 | B31: =B29/20 -> 22072.8 | D31: =D29/20 -> 16709.1 | E31: =E29/20 -> 17002.5 | F31: =F29/20 -> 28742.1 | J31: 2024 | K31: 期間 | L31: 売上 | M31: 値引き | N31: 税抜売上 | O31: 税込売上 | P31: 値引き | Q31: 税込売上合計
A32: 前年比 | D32: =D31/B31 -> 0.75699957 | E32: =E31/D31 -> 1.0175593 | F32: =F31/E31 -> 1.6904632 | J32: 4~5 | K32: ピコレ4/27-5/19 | L32: 2939522 | M32: 4040 | N32: =L32-M32 -> 2935482 | O32: 3232260 | P32: 4040 | Q32: =O32-P32 -> 3228220 | R32: 23
A33: ビール原価金額 | B33: =B31*9000 -> 198655200 | C33: 原価率想定 | D33: =D31*9000 -> 150381900 | E33: =E31*9700 -> 164924250 | F33: =F31*9000 -> 258678900 | J33: 5 | K33: ビアガ5/27-5/31 | L33: 477807 | M33: 3480 | N33: =L33-M33 -> 474327 | O33: 525570 | P33: 3480 | Q33: =O33-P33 -> 522090 | R33: 5
A34: ビール売上推定金額 | B34: =B33*3.5 -> 695293200 | C34: =B33/B34 -> 0.28571429 | D34: =D33*3.5 -> 526336650 | E34: =E33*3.5 -> 577234875 | F34: =F33*3.5 -> 905376150 | J34: 6 | K34: ビアガフル | L34: 19170665 | M34: 26790 | N34: =L34-M34 -> 19143875 | O34: 21087090 | P34: 26790 | Q34: =O34-P34 -> 21060300 | R34: 30
A35: ひとり当たりのビール購入額 | B35: =B34/B27 -> 594.26769 | C35: =C34/C27 -> #DIV/0! | D35: =D34/D27 -> 594.05942 | E35: =E34/E27 -> 639.94997 | F35: =F34/F27 -> 594.46891 | J35: 7 | K35: ビアガフル | L35: 47598067 | M35: 17800 | N35: =L35-M35 -> 47580267 | O35: 52356880 | P35: 17800 | Q35: =O35-P35 -> 52339080 | R35: 31
A36: 客単価想定 | B36: 1300 | D36: 1300 | E36: 1300 | F36: 1300 | J36: 8 | K36: ビアガフル | L36: 55870570 | M36: 5980 | N36: =L36-M36 -> 55864590 | O36: 61456496 | P36: 5980 | Q36: =O36-P36 -> 61450516 | R36: 31
A37: 推定売上額 | B37: =B27*B36 -> 1521000000 | D37: =D27*D36 -> 1151800000 | E37: =E27*E36 -> 1172600000 | F37: =F27*F36 -> 1979900000 | J37: 9 | K37: ビアガ9/1-9/8 | L37: 8816632 | M37: 5700 | N37: =L37-M37 -> 8810932 | O37: 9698100 | P37: 5700 | Q37: =O37-P37 -> 9692400 | R37: 8
J38: 9~10 | K38: ピコレ共催アキノジン | L38: 4982837 | M38: 1100 | N38: =L38-M38 -> 4981737 | O38: 5480760 | P38: 1100 | Q38: =O38-P38 -> 5479660 | R38: 23
K39: ビアガのみ105日 | L39: =L34+L33+L35+L36+L37 -> 131933741 | M39: =M34+M33+M35+M36+M37 -> 59750 | N39: =N34+N33+N35+N36+N37 -> 131873991 | O39: =O34+O33+O35+O36+O37 -> 145124136 | P39: =P34+P33+P35+P36+P37 -> 59750 | Q39: =Q34+Q33+Q35+Q36+Q37 -> 145064386 | R39: =R34+R33+R35+R36+R37 -> 105
K40: ピコレ&ピコレ共催 | L40: =L32+L38 -> 7922359 | M40: =M32+M38 -> 5140 | N40: =N32+N38 -> 7917219 | O40: =O32+O38 -> 8713020 | P40: =P32+P38 -> 5140 | Q40: =Q32+Q38 -> 8707880 | R40: =R32+R38 -> 46
K41: 総合計 | L41: =SUM(L32:L38) -> 139856100 | M41: =SUM(M32:M38) -> 64890 | N41: =SUM(N32:N38) -> 139791210 | O41: =SUM(O32:O38) -> 153837156 | P41: =SUM(P32:P38) -> 64890 | Q41: =SUM(Q32:Q38) -> 153772266 | R41: =SUM(R32:R38) -> 151
J43: 2023 | K43: 期間 | L43: 売上 | M43: 値引き | N43: 税抜売上 | O43: 税込売上 | P43: 値引き | Q43: 税込売上合計
J44: 4~5 | K44: ピコレ参戦なし | N44: =L44-M44 -> 0 | Q44: =O44-P44 -> 0 | R44: 0
J45: 5 | K45: ビアガ5/27-5/31 | L45: =O45/1.1 -> 1795227.3 | N45: =L45-M45 -> 1795227.3 | O45: 1974750 | Q45: =O45-P45 -> 1974750 | R45: 5 | S45: 506
J46: 6 | K46: ビアガフル | L46: =O46/1.1 -> 19049727 | N46: =L46-M46 -> 19049727 | O46: 20954700 | Q46: =O46-P46 -> 20954700 | R46: 30 | S46: 5309
J47: 7 | K47: ビアガフル | L47: =O47/1.1 -> 44856909 | N47: =L47-M47 -> 44856909 | O47: 49342600 | Q47: =O47-P47 -> 49342600 | R47: 31 | S47: 11036
J48: 8 | K48: ビアガフル | L48: =O48/1.1 -> 44860591 | N48: =L48-M48 -> 44860591 | O48: 49346650 | Q48: =O48-P48 -> 49346650 | R48: 31 | S48: 11093
J49: 9 | K49: ビアガ9/1-9/3 | L49: =O49/1.1 -> 8816454.5 | N49: =L49-M49 -> 8816454.5 | O49: 9698100 | Q49: =O49-P49 -> 9698100 | R49: 3 | S49: 263
J50: 9~10 | K50: ピコレ | L50: 1487994 | N50: =L50-M50 -> 1487994 | O50: 1636793 | P50: 4040 | Q50: =O50-P50 -> 1632753 | R50: 0
K51: ビアガのみ105日 | L51: =L46+L45+L47+L48+L49 -> 1.1937891e+08 | M51: =M46+M45+M47+M48+M49 -> 0 | N51: =N46+N45+N47+N48+N49 -> 1.1937891e+08 | O51: =O46+O45+O47+O48+O49 -> 131316800 | P51: =P46+P45+P47+P48+P49 -> 0 | Q51: =Q46+Q45+Q47+Q48+Q49 -> 131316800 | R51: =R46+R45+R47+R48+R49 -> 100
K52: ピコレ&ピコレ共催 | L52: =L44+L50 -> 1487994 | M52: =M44+M50 -> 0 | N52: =N44+N50 -> 1487994 | O52: =O44+O50 -> 1636793 | P52: =P44+P50 -> 4040 | Q52: =Q44+Q50 -> 1632753 | R52: =R44+R50 -> 0
K53: 総合計 | L53: =SUM(L44:L50) -> 1.208669e+08 | M53: =SUM(M44:M50) -> 0 | N53: =SUM(N44:N50) -> 1.208669e+08 | O53: =SUM(O44:O50) -> 132953593 | P53: =SUM(P44:P50) -> 4040 | Q53: =SUM(Q44:Q50) -> 132949553 | R53: =SUM(R44:R50) -> 100

Sheet 25-24天候指数対比
B1: ◆2025-2024 天候指数対比
B2: 4月 天候指数対比 <気象庁資料マクロクリマ> | F2: 平均気温 最高 13.0℃ （13.5℃）最低 5.2℃（5.5℃） カッコ内は前年値 <M-4th> | P2: 8月 天候指数対比 <現地ミクロクリマ> | T2: 平均気温 最高 28.8℃ （28.4℃）最低 21.6℃（22.0℃） カッコ内は前年値 <M-1st>
B3: 天候状況 | E3: ポイント | F3: 2025日数＊3 | G3: 2025合計 | H3: 比率 | I3: 2024日数＊3 | J3: 2024合計 | K3: 比率 | L3: 前年差異 | P3: 天候状況 | S3: ポイント | T3: 2025日数＊3 | U3: 2025合計 | V3: 比率 | W3: 2024日数＊3 | X3: 2024合計 | Y3: 比率 | Z3: 前年差異
B4: ポジティブ | C4: 晴れ（33度まで） | E4: 5 | F4: 0 | G4: =E4*F4 -> 0 | H4: =(F4+F5+F6)/F10 -> #DIV/0! | I4: 0 | J4: =E4*I4 -> 0 | K4: =(I4+I5+I6)/I10 -> #DIV/0! | L4: =F4-I4 -> 0 | M4: =G4-J4 -> 0 | N4: =H4-K4 -> #DIV/0! | P4: ポジティブ | Q4: 晴れ（33度まで） | S4: 5 | T4: 37 | U4: =S4*T4 -> 185 | V4: =(T4+T5+T6)/T10 -> 0.80645161 | W4: 27 | X4: =S4*W4 -> 135 | Y4: =(W4+W5+W6)/W10 -> 0.69892473 | Z4: =T4-W4 -> 10 | AA4: =U4-X4 -> 50 | AB4: =V4-Y4 -> 0.10752688
C5: 晴れ（25度以下） | E5: 4 | F5: 0 | G5: =E5*F5 -> 0 | I5: 0 | J5: =E5*I5 -> 0 | L5: =F5-I5 -> 0 | M5: =G5-J5 -> 0 | Q5: 晴れ（25度以下） | S5: 4 | T5: 0 | U5: =S5*T5 -> 0 | W5: 0 | X5: =S5*W5 -> 0 | Z5: =T5-W5 -> 0 | AA5: =U5-X5 -> 0
C6: 晴れ（33度以上15以下） 曇25度以上 | E6: 3 | F6: 0 | G6: =E6*F6 -> 0 | I6: 0 | J6: =E6*I6 -> 0 | L6: =F6-I6 -> 0 | M6: =G6-J6 -> 0 | Q6: 晴れ（33度以上15以下） 曇25度以上 | S6: 3 | T6: 38 | U6: =S6*T6 -> 114 | W6: 38 | X6: =S6*W6 -> 114 | Z6: =T6-W6 -> 0 | AA6: =U6-X6 -> 0
B7: ネガティブ | C7: 曇 | E7: 2 | F7: 0 | G7: =E7*F7 -> 0 | H7: =(F7+F8+F9)/F10 -> #DIV/0! | I7: 0 | J7: =E7*I7 -> 0 | K7: =(I7+I8+I9)/I10 -> #DIV/0! | L7: =F7-I7 -> 0 | M7: =G7-J7 -> 0 | N7: =H7-K7 -> #DIV/0! | P7: ネガティブ | Q7: 曇 | S7: 2 | T7: 0 | U7: =S7*T7 -> 0 | V7: =(T7+T8+T9)/T10 -> 0.19354839 | W7: 6 | X7: =S7*W7 -> 12 | Y7: =(W7+W8+W9)/W10 -> 0.30107527 | Z7: =T7-W7 -> -6 | AA7: =U7-X7 -> -12 | AB7: =V7-Y7 -> -0.10752688
C8: 雨 | E8: 1 | F8: 0 | G8: =E8*F8 -> 0 | I8: 0 | J8: =E8*I8 -> 0 | L8: =F8-I8 -> 0 | M8: =G8-J8 -> 0 | Q8: 雨 | S8: 1 | T8: 18 | U8: =S8*T8 -> 18 | W8: 22 | X8: =S8*W8 -> 22 | Z8: =T8-W8 -> -4 | AA8: =U8-X8 -> -4
C9: 豪雨・雷雨 | E9: 0 | F9: 0 | G9: =E9*F9 -> 0 | J9: =E9*I9 -> 0 | L9: =F9-I9 -> 0 | M9: =G9-J9 -> 0 | Q9: 豪雨・雷雨 | S9: 0 | T9: 0 | U9: =S9*T9 -> 0 | W9: 0 | X9: =S9*W9 -> 0 | Z9: =T9-W9 -> 0 | AA9: =U9-X9 -> 0
B10: TOTAL | F10: =SUM(F4:F9) -> 0 | G10: =SUM(G4:G9) -> 0 | H10: =H4+H7 -> #DIV/0! | I10: =SUM(I4:I9) -> 0 | J10: =SUM(J4:J9) -> 0 | K10: =K4+K7 -> #DIV/0! | L10: =SUM(L4:L9) -> 0 | M10: =SUM(M4:M9) -> 0 | N10: =G10/J10 -> #DIV/0! | P10: TOTAL | T10: =SUM(T4:T9) -> 93 | U10: =SUM(U4:U9) -> 317 | V10: =V4+V7 -> 1 | W10: =SUM(W4:W9) -> 93 | X10: =SUM(X4:X9) -> 283 | Y10: =Y4+Y7 -> 1 | Z10: =SUM(Z4:Z9) -> 0 | AA10: =SUM(AA4:AA9) -> 34 | AB10: =U10/X10 -> 1.1201413
F11: =G10/F10 -> #DIV/0! | I11: =J10/I10 -> #DIV/0! | L11: =F11-I11 -> #DIV/0! | N11: =F11/I11 -> #DIV/0! | T11: =U10/T10 -> 3.4086022 | W11: =X10/W10 -> 3.0430108 | Z11: =T11-W11 -> 0.3655914 | AB11: =T11/W11 -> 1.1201413
B13: 5月 天候指数対比 <現地ミクロクリマ> | F13: 平均気温 最高 25.9℃ （17.0℃）最低 14.8℃（11.6℃） カッコ内は前年値 <M-2nd> | P13: 9月 天候指数対比 <現地ミクロクリマ> | T13: 平均気温 最高 27.0℃ （24.0℃）最低 19.0℃（15.6℃） カッコ内は前年値 <M- 2nd>
B14: 天候状況 | E14: ポイント | F14: 2025日数＊3 | G14: 2025合計 | H14: 比率 | I14: 2024日数＊3 | J14: 2024合計 | K14: 比率 | L14: 前年差異 | P14: 天候状況 | S14: ポイント | T14: 2025日数＊3 | U14: 2025合計 | V14: 比率 | W14: 2024日数＊3 | X14: 2024合計 | Y14: 比率 | Z14: 前年差異
B15: ポジティブ | C15: 晴れ（33度まで） | E15: 5 | F15: 2 | G15: =E15*F15 -> 10 | H15: =(F15+F16+F17)/F21 -> 0.66666667 | I15: 0 | J15: =E15*I15 -> 0 | K15: =(I15+I16+I17)/I21 -> 0.066666667 | L15: =F15-I15 -> 2 | M15: =G15-J15 -> 10 | N15: =H15-K15 -> 0.6 | P15: ポジティブ | Q15: 晴れ（33度まで） | S15: 5 | T15: 20 | U15: =S15*T15 -> 100 | V15: =(T15+T16+T17)/T21 -> 0.8 | W15: 16 | X15: =S15*W15 -> 80 | Y15: =(W15+W16+W17)/W21 -> 0.74666667 | Z15: =T15-W15 -> 4 | AA15: =U15-X15 -> 20 | AB15: =V15-Y15 -> 0.053333333
C16: 晴れ（25度以下） | E16: 4 | F16: 2 | G16: =E16*F16 -> 8 | I16: 0 | J16: =E16*I16 -> 0 | L16: =F16-I16 -> 2 | M16: =G16-J16 -> 8 | Q16: 晴れ（25度以下） | S16: 4 | T16: 2 | U16: =S16*T16 -> 8 | W16: 32 | X16: =S16*W16 -> 128 | Z16: =T16-W16 -> -30 | AA16: =U16-X16 -> -120
C17: 晴れ（33度以上15以下） 曇25度以上 | E17: 3 | F17: 0 | G17: =E17*F17 -> 0 | I17: 1 | J17: =E17*I17 -> 3 | L17: =F17-I17 -> -1 | M17: =G17-J17 -> -3 | Q17: 晴れ（33度以上15以下） 曇25度以上 | S17: 3 | T17: 14 | U17: =S17*T17 -> 42 | W17: 8 | X17: =S17*W17 -> 24 | Z17: =T17-W17 -> 6 | AA17: =U17-X17 -> 18
B18: ネガティブ | C18: 曇 | E18: 2 | F18: 2 | G18: =E18*F18 -> 4 | H18: =(F18+F19+F20)/F21 -> 0.33333333 | I18: 5 | J18: =E18*I18 -> 10 | K18: =(I18+I19+I20)/I21 -> 0.93333333 | L18: =F18-I18 -> -3 | M18: =G18-J18 -> -6 | N18: =H18-K18 -> -0.6 | P18: ネガティブ | Q18: 曇 | S18: 2 | T18: 1 | U18: =S18*T18 -> 2 | V18: =(T18+T19+T20)/T21 -> 0.2 | W18: 15 | X18: =S18*W18 -> 30 | Y18: =(W18+W19+W20)/W21 -> 0.25333333 | Z18: =T18-W18 -> -14 | AA18: =U18-X18 -> -28 | AB18: =V18-Y18 -> -0.053333333
C19: 雨 | E19: 1 | F19: 0 | G19: =E19*F19 -> 0 | I19: 7 | J19: =E19*I19 -> 7 | L19: =F19-I19 -> -7 | M19: =G19-J19 -> -7 | Q19: 雨 | S19: 1 | T19: 8 | U19: =S19*T19 -> 8 | W19: 4 | X19: =S19*W19 -> 4 | Z19: =T19-W19 -> 4 | AA19: =U19-X19 -> 4
C20: 豪雨・雷雨 | E20: 0 | F20: 0 | G20: =E20*F20 -> 0 | I20: 2 | J20: =E20*I20 -> 0 | L20: =F20-I20 -> -2 | M20: =G20-J20 -> 0 | Q20: 豪雨・雷雨 | S20: 0 | T20: 0 | U20: =S20*T20 -> 0 | W20: 0 | X20: =S20*W20 -> 0 | Z20: =T20-W20 -> 0 | AA20: =U20-X20 -> 0
B21: TOTAL | F21: =SUM(F15:F20) -> 6 | G21: =SUM(G15:G20) -> 22 | H21: =H15+H18 -> 1 | I21: =SUM(I15:I20) -> 15 | J21: =SUM(J15:J20) -> 20 | K21: =K15+K18 -> 1 | L21: =SUM(L15:L20) -> -9 | M21: =SUM(M15:M20) -> 2 | N21: =G21/J21 -> 1.1 | P21: TOTAL | T21: =SUM(T15:T20) -> 45 | U21: =SUM(U15:U20) -> 160 | V21: =V15+V18 -> 1 | W21: =SUM(W15:W20) -> 75 | X21: =SUM(X15:X20) -> 266 | Y21: =Y15+Y18 -> 1 | Z21: =SUM(Z15:Z20) -> -30 | AA21: =SUM(AA15:AA20) -> -106 | AB21: =U21/X21 -> 0.60150376
F22: =G21/F21 -> 3.6666667 | I22: =J21/I21 -> 1.3333333 | L22: =F22-I22 -> 2.3333333 | N22: =F22/I22 -> 2.75 | T22: =U21/T21 -> 3.5555556 | W22: =X21/W21 -> 3.5466667 | Z22: =T22-W22 -> 0.0088888889 | AB22: =T22/W22 -> 1.0025063
B24: 6月 天候指数対比 <現地ミクロクリマ> | F24: 平均気温 最高 25.8℃ （23.9℃）最低 16.8℃（15.6℃） カッコ内は前年値 <M-2nd> | P24: 10月 天候指数対比 <気象庁資料マクロクリマ> | T24: 平均気温 最高 16.8℃ （18.3℃）最低 8.9℃（9.0℃） カッコ内は前年値 <M-5th>
B25: 天候状況 | E25: ポイント | F25: 2025日数＊3 | G25: 2025合計 | H25: 比率 | I25: 2024日数＊3 | J25: 2024合計 | K25: 比率 | L25: 前年差異 | P25: 天候状況 | S25: ポイント | T25: 2025日数＊3 | U25: 2025合計 | V25: 比率 | W25: 2024日数＊3 | X25: 2024合計 | Y25: 比率 | Z25: 前年差異
B26: ポジティブ | C26: 晴れ（33度まで） | E26: 5 | F26: 37 | G26: =E26*F26 -> 185 | H26: =(F26+F27+F28)/F32 -> 0.58888889 | I26: 13 | J26: =E26*I26 -> 65 | K26: =(I26+I27+I28)/I32 -> 0.48888889 | L26: =F26-I26 -> 24 | M26: =G26-J26 -> 120 | N26: =H26-K26 -> 0.1 | P26: ポジティブ | Q26: 晴れ（33度まで） | S26: 5 | T26: 0 | U26: =S26*T26 -> 0 | V26: =(T26+T27+T28)/T32 -> #DIV/0! | W26: 2 | X26: =S26*W26 -> 10 | Y26: =(W26+W27+W28)/W32 -> 0.38888889 | Z26: =T26-W26 -> -2 | AA26: =U26-X26 -> -10 | AB26: =V26-Y26 -> #DIV/0!
C27: 晴れ（25度以下） | E27: 4 | F27: 7 | G27: =E27*F27 -> 28 | I27: 16 | J27: =E27*I27 -> 64 | L27: =F27-I27 -> -9 | M27: =G27-J27 -> -36 | Q27: 晴れ（25度以下） | S27: 4 | T27: 0 | U27: =S27*T27 -> 0 | W27: 5 | X27: =S27*W27 -> 20 | Z27: =T27-W27 -> -5 | AA27: =U27-X27 -> -20
C28: 晴れ（33度以上15以下） 曇25度以上 | E28: 3 | F28: 9 | G28: =E28*F28 -> 27 | I28: 15 | J28: =E28*I28 -> 45 | L28: =F28-I28 -> -6 | M28: =G28-J28 -> -18 | Q28: 晴れ（33度以上15以下） 曇25度以上 | S28: 3 | T28: 0 | U28: =S28*T28 -> 0 | W28: 0 | X28: =S28*W28 -> 0 | Z28: =T28-W28 -> 0 | AA28: =U28-X28 -> 0
B29: ネガティブ | C29: 曇 | E29: 2 | F29: 22 | G29: =E29*F29 -> 44 | H29: =(F29+F30+F31)/F32 -> 0.41111111 | I29: 30 | J29: =E29*I29 -> 60 | K29: =(I29+I30+I31)/I32 -> 0.51111111 | L29: =F29-I29 -> -8 | M29: =G29-J29 -> -16 | N29: =H29-K29 -> -0.1 | P29: ネガティブ | Q29: 曇 | S29: 2 | T29: 0 | U29: =S29*T29 -> 0 | V29: =(T29+T30+T31)/T32 -> #DIV/0! | W29: 8 | X29: =S29*W29 -> 16 | Y29: =(W29+W30+W31)/W32 -> 0.61111111 | Z29: =T29-W29 -> -8 | AA29: =U29-X29 -> -16 | AB29: =V29-Y29 -> #DIV/0!
C30: 雨 | E30: 1 | F30: 15 | G30: =E30*F30 -> 15 | I30: 15 | J30: =E30*I30 -> 15 | L30: =F30-I30 -> 0 | M30: =G30-J30 -> 0 | Q30: 雨 | S30: 1 | T30: 0 | U30: =S30*T30 -> 0 | W30: 3 | X30: =S30*W30 -> 3 | Z30: =T30-W30 -> -3 | AA30: =U30-X30 -> -3
C31: 豪雨・雷雨 | E31: 0 | F31: 0 | G31: =E31*F31 -> 0 | I31: 1 | J31: =E31*I31 -> 0 | L31: =F31-I31 -> -1 | M31: =G31-J31 -> 0 | Q31: 豪雨・雷雨 | S31: 0 | T31: 0 | U31: =S31*T31 -> 0 | W31: 0 | X31: =S31*W31 -> 0 | Z31: =T31-W31 -> 0 | AA31: =U31-X31 -> 0
B32: TOTAL | F32: =SUM(F26:F31) -> 90 | G32: =SUM(G26:G31) -> 299 | H32: =H26+H29 -> 1 | I32: =SUM(I26:I31) -> 90 | J32: =SUM(J26:J31) -> 249 | K32: =K26+K29 -> 1 | L32: =SUM(L26:L31) -> 0 | M32: =SUM(M26:M31) -> 50 | N32: =G32/J32 -> 1.2008032 | P32: TOTAL | T32: =SUM(T26:T31) -> 0 | U32: =SUM(U26:U31) -> 0 | V32: =V26+V29 -> #DIV/0! | W32: =SUM(W26:W31) -> 18 | X32: =SUM(X26:X31) -> 49 | Y32: =Y26+Y29 -> 1 | Z32: =SUM(Z26:Z31) -> -18 | AA32: =SUM(AA26:AA31) -> -49 | AB32: =U32/X32 -> 0
F33: =G32/F32 -> 3.3222222 | I33: =J32/I32 -> 2.7666667 | L33: =F33-I33 -> 0.55555556 | N33: =F33/I33 -> 1.2008032 | T33: =U32/T32 -> #DIV/0! | W33: =X32/W32 -> 2.7222222 | Z33: =T33-W33 -> #DIV/0! | AB33: =T33/W33 -> #DIV/0!
B35: 7月 天候指数対比 <現地ミクロクリマ> | F35: 平均気温 最高 30.4℃ （28.0℃）最低 22.4℃（20.5℃） カッコ内は前年値 <M-1st> | P35: TOTAL 天候指数 対比
B36: 天候状況 | E36: ポイント | F36: 2025日数＊3 | G36: 2025合計 | H36: 比率 | I36: 2024日数＊3 | J36: 2024合計 | K36: 比率 | L36: 前年差異 | P36: 天候状況 | S36: ポイント | T36: 2025日数＊3 | U36: 2025合計 | V36: 比率 | W36: 2024日数＊3 | X36: 2024合計 | Y36: 比率 | Z36: 前年差異
B37: ポジティブ | C37: 晴れ（33度まで） | E37: 5 | F37: 39 | G37: =E37*F37 -> 195 | H37: =(F37+F38+F39)/F43 -> 0.92473118 | I37: 35 | J37: =E37*I37 -> 175 | K37: =(I37+I38+I39)/I43 -> 0.79569892 | L37: =F37-I37 -> 4 | M37: =G37-J37 -> 20 | N37: =H37-K37 -> 0.12903226 | P37: ポジティブ | Q37: 晴れ（33度まで） | S37: 5 | T37: =F4+F15+F26+F37+T4+T15+T26 -> 135 | U37: =S37*T37 -> 675 | V37: =(T37+T38+T39)/T43 -> 0.77675841 | W37: =I4+I15+I26+I37+W4+W15+W26 -> 93 | X37: =S37*W37 -> 465 | Y37: =(W37+W38+W39)/W43 -> 0.64322917 | Z37: =T37-W37 -> 42 | AA37: =U37-X37 -> 210 | AB37: =V37-Y37 -> 0.13352924
C38: 晴れ（25度以下） | E38: 4 | F38: 0 | G38: =E38*F38 -> 0 | I38: 10 | J38: =E38*I38 -> 40 | L38: =F38-I38 -> -10 | M38: =G38-J38 -> -40 | Q38: 晴れ（25度以下） | S38: 4 | T38: =F5+F16+F27+F38+T5+T16+T27 -> 11 | U38: =S38*T38 -> 44 | W38: =I5+I16+I27+I38+W5+W16+W27 -> 63 | X38: =S38*W38 -> 252 | Z38: =T38-W38 -> -52 | AA38: =U38-X38 -> -208
C39: 晴れ（33度以上15以下） 曇25度以上 | E39: 3 | F39: 47 | G39: =E39*F39 -> 141 | I39: 29 | J39: =E39*I39 -> 87 | L39: =F39-I39 -> 18 | M39: =G39-J39 -> 54 | Q39: 晴れ（33度以上15以下） 曇25度以上 | S39: 3 | T39: =F6+F17+F28+F39+T6+T17+T28 -> 108 | U39: =S39*T39 -> 324 | W39: =I6+I17+I28+I39+W6+W17+W28 -> 91 | X39: =S39*W39 -> 273 | Z39: =T39-W39 -> 17 | AA39: =U39-X39 -> 51
B40: ネガティブ | C40: 曇 | E40: 2 | F40: 0 | G40: =E40*F40 -> 0 | H40: =(F40+F41+F42)/F43 -> 0.075268817 | I40: 4 | J40: =E40*I40 -> 8 | K40: =(I40+I41+I42)/I43 -> 0.20430108 | L40: =F40-I40 -> -4 | M40: =G40-J40 -> -8 | N40: =H40-K40 -> -0.12903226 | P40: ネガティブ | Q40: 曇 | S40: 2 | T40: =F7+F18+F29+F40+T7+T18+T29 -> 25 | U40: =S40*T40 -> 50 | V40: =(T40+T41+T42)/T43 -> 0.22324159 | W40: =I7+I18+I29+I40+W7+W18+W29 -> 68 | X40: =S40*W40 -> 136 | Y40: =(W40+W41+W42)/W43 -> 0.35677083 | Z40: =T40-W40 -> -43 | AA40: =U40-X40 -> -86 | AB40: =V40-Y40 -> -0.13352924
C41: 雨 | E41: 1 | F41: 7 | G41: =E41*F41 -> 7 | I41: 15 | J41: =E41*I41 -> 15 | L41: =F41-I41 -> -8 | M41: =G41-J41 -> -8 | Q41: 雨 | S41: 1 | T41: =F8+F19+F30+F41+T8+T19+T30 -> 48 | U41: =S41*T41 -> 48 | W41: =I8+I19+I30+I41+W8+W19+W30 -> 66 | X41: =S41*W41 -> 66 | Z41: =T41-W41 -> -18 | AA41: =U41-X41 -> -18
C42: 豪雨・雷雨 | E42: 0 | F42: 0 | G42: =E42*F42 -> 0 | J42: =E42*I42 -> 0 | L42: =F42-I42 -> 0 | M42: =G42-J42 -> 0 | Q42: 豪雨・雷雨 | S42: 0 | T42: =F9+F20+F31+F42+T9+T20+T31 -> 0 | U42: =S42*T42 -> 0 | W42: =I9+I20+I31+I42+W9+W20+W31 -> 3 | X42: =S42*W42 -> 0 | Z42: =T42-W42 -> -3 | AA42: =U42-X42 -> 0
B43: TOTAL | F43: =SUM(F37:F42) -> 93 | G43: =SUM(G37:G42) -> 343 | H43: =H37+H40 -> 1 | I43: =SUM(I37:I42) -> 93 | J43: =SUM(J37:J42) -> 325 | K43: =K37+K40 -> 1 | L43: =SUM(L37:L42) -> 0 | M43: =SUM(M37:M42) -> 18 | N43: =G43/J43 -> 1.0553846 | P43: TOTAL | T43: =SUM(T37:T42) -> 327 | U43: =SUM(U37:U42) -> 1141 | V43: =V37+V40 -> 1 | W43: =SUM(W37:W42) -> 384 | X43: =SUM(X37:X42) -> 1192 | Y43: =Y37+Y40 -> 1 | Z43: =SUM(Z37:Z42) -> -57 | AA43: =SUM(AA37:AA42) -> -51 | AB43: =U43/X43 -> 0.95721477
F44: =G43/F43 -> 3.688172 | I44: =J43/I43 -> 3.4946237 | L44: =F44-I44 -> 0.19354839 | N44: =F44/I44 -> 1.0553846 | T44: =U43/T43 -> 3.4892966 | W44: =X43/W43 -> 3.1041667 | Z44: =T44-W44 -> 0.38512997 | AB44: =T44/W44 -> 1.1240687

Sheet 25-24期間別KPI対比
B1: 【KPI対比（予算比・前年比）】
B2: 実績 | C2: 営 業 形 態 | D2: 日 数 | E2: 売 上 | F2: 客 数 | G2: 客単価 | H2: 予算 | I2: 計画 | J2: 日 数 | K2: 売 上 | L2: 客 数 | M2: 客単価 | N2: 売 上 予 算 比 | P2: 客 数 予 算 比 | R2: 客 単 価 予 算 比
B3: 4 | C3: PC | D3: 5 | E3: 490136 | F3: 352 | G3: =E3/F3 -> 1392.4318 | H3: 4 | I3: PC | J3: 5 | K3: 543750 | L3: 375 | M3: =K3/L3 -> 1450 | N3: =E3-K3 -> -53614 | O3: =E3/K3 -> 0.90139954 | P3: =F3-L3 -> -23 | Q3: =F3/L3 -> 0.93866667 | R3: =G3-M3 -> -57.568182 | S3: =G3/M3 -> 0.96029781
B4: 5 | C4: PC & BG | D4: 20 | E4: 5112218 | F4: 2610 | G4: =E4/F4 -> 1958.7042 | H4: 5 | I4: PC & BG | J4: 23 | K4: 2847520 | L4: 1600 | M4: =K4/L4 -> 1779.7 | N4: =E4-K4 -> 2264698 | O4: =E4/K4 -> 1.7953229 | P4: =F4-L4 -> 1010 | Q4: =F4/L4 -> 1.63125 | R4: =G4-M4 -> 179.00421 | S4: =G4/M4 -> 1.1005811
B5: 6 | C5: BG フル営業 | D5: 30 | E5: 33132365 | F5: 8280 | G5: =E5/F5 -> 4001.4934 | H5: 6 | I5: BG フル営業 | J5: 30 | K5: 22680000 | L5: 6000 | M5: =K5/L5 -> 3780 | N5: =E5-K5 -> 10452365 | O5: =E5/K5 -> 1.4608627 | P5: =F5-L5 -> 2280 | Q5: =F5/L5 -> 1.38 | R5: =G5-M5 -> 221.49336 | S5: =G5/M5 -> 1.0585961
B6: 7 | C6: BG フル営業 | D6: 31 | E6: 63022682 | F6: 14790 | G6: =E6/F6 -> 4261.1685 | H6: 7 | I6: BG フル営業 | J6: 31 | K6: 49815000 | L6: 12150 | M6: =K6/L6 -> 4100 | N6: =E6-K6 -> 13207682 | O6: =E6/K6 -> 1.2651346 | P6: =F6-L6 -> 2640 | Q6: =F6/L6 -> 1.217284 | R6: =G6-M6 -> 161.16849 | S6: =G6/M6 -> 1.0393094
B7: 8 | C7: BG フル営業 | D7: 31 | E7: 61443318 | F7: 14547 | G7: =E7/F7 -> 4223.7793 | H7: 8 | I7: BG フル営業 | J7: 31 | K7: 56840000 | L7: 14000 | M7: =K7/L7 -> 4060 | N7: =E7-K7 -> 4603318 | O7: =E7/K7 -> 1.0809873 | P7: =F7-L7 -> 547 | Q7: =F7/L7 -> 1.0390714 | R7: =G7-M7 -> 163.77934 | S7: =G7/M7 -> 1.0403397
B8: 9 | C8: BG & PC | D8: 26 | E8: 15779145 | F8: 4669 | G8: =E8/F8 -> 3379.5556 | H8: 9 | I8: BG & PC | J8: 26 | K8: 20842025 | L8: 5750 | M8: =K8/L8 -> 3624.7 | N8: =E8-K8 -> -5062880 | O8: =E8/K8 -> 0.7570831 | P8: =F8-L8 -> -1081 | Q8: =F8/L8 -> 0.812 | R8: =G8-M8 -> -245.14442 | S8: =G8/M8 -> 0.93236836
B9: 10 | C9: BG & PC | D9: 5 | E9: 397683 | F9: 274 | G9: =E9/F9 -> 1451.3978 | H9: 10 | I9: PC | J9: 13 | K9: 840000 | L9: 600 | M9: =K9/L9 -> 1400 | N9: =E9-K9 -> -442317 | O9: =E9/K9 -> 0.47343214 | P9: =F9-L9 -> -326 | Q9: =F9/L9 -> 0.45666667 | R9: =G9-M9 -> 51.39781 | S9: =G9/M9 -> 1.0367127
B10: 総合計 | D10: =SUM(D3:D9) -> 148 | E10: =SUM(E3:E9) -> 179377547 | F10: =SUM(F3:F9) -> 45522 | G10: =E10/F10 -> 3940.4584 | H10: 総合計 | J10: =SUM(J3:J9) -> 159 | K10: =SUM(K3:K9) -> 154408295 | L10: =SUM(L3:L9) -> 40475 | M10: =K10/L10 -> 3814.9054 | N10: =E10-K10 -> 24969252 | O10: =E10/K10 -> 1.1617093 | P10: =F10-L10 -> 5047 | Q10: =F10/L10 -> 1.1246943 | R10: =G10-M10 -> 125.55302 | S10: =G10/M10 -> 1.0329112
B12: 2025 | C12: 営 業 形 態 | D12: 日 数 | E12: 売 上 | F12: 客 数 | G12: 客単価 | H12: 2024 | I12: 営 業 形 態 | J12: 日 数 | K12: 売 上 | L12: 客 数 | M12: 客単価 | N12: 売 上 前 年 比 | P12: 客 数 前 年 比 | R12: 客 単 価 前 年 比
B13: 4~5 | C13: PC 4/27-5/19 | D13: 23 | E13: 3013909 | F13: 2311 | G13: =E13/F13 -> 1304.1579 | H13: 4~5 | I13: PC 4/27-5/19 | J13: 23 | K13: 2939522 | L13: 2348 | M13: =K13/L13 -> 1251.9259 | N13: =E13-K13 -> 74387 | O13: =E13/K13 -> 1.0253058 | P13: =F13-L13 -> -37 | Q13: =F13/L13 -> 0.98424191 | R13: =G13-M13 -> 52.232046 | S13: =G13/M13 -> 1.0417214
B14: 5 | C14: BG 5/30-5/31 | D14: 2 | E14: 2588445 | F14: 651 | G14: =E14/F14 -> 3976.106 | H14: 5 | I14: BG 5/27-5/31 | J14: 5 | K14: 477807 | L14: 133 | M14: =K14/L14 -> 3592.5338 | N14: =E14-K14 -> 2110638 | O14: =E14/K14 -> 5.4173442 | P14: =F14-L14 -> 518 | Q14: =F14/L14 -> 4.8947368 | R14: =G14-M14 -> 383.57216 | S14: =G14/M14 -> 1.1067693
B15: 6 | C15: BG フル営業 | D15: 30 | E15: 33132365 | F15: 8280 | G15: =E15/F15 -> 4001.4934 | H15: 6 | I15: BG フル営業 | J15: 30 | K15: 19170665 | L15: 5174 | M15: =K15/L15 -> 3705.1923 | N15: =E15-K15 -> 13961700 | O15: =E15/K15 -> 1.7282846 | P15: =F15-L15 -> 3106 | Q15: =F15/L15 -> 1.6003092 | R15: =G15-M15 -> 296.30105 | S15: =G15/M15 -> 1.0799691
B16: 7 | C16: BG フル営業 | D16: 31 | E16: 63022682 | F16: 14790 | G16: =E16/F16 -> 4261.1685 | H16: 7 | I16: BG フル営業 | J16: 31 | K16: 47598067 | L16: 11438 | M16: =K16/L16 -> 4161.3977 | N16: =E16-K16 -> 15424615 | O16: =E16/K16 -> 1.3240597 | P16: =F16-L16 -> 3352 | Q16: =F16/L16 -> 1.2930582 | R16: =G16-M16 -> 99.770783 | S16: =G16/M16 -> 1.0239753
B17: 8 | C17: BG フル営業 | D17: 31 | E17: 61443318 | F17: 14547 | G17: =E17/F17 -> 4223.7793 | H17: 8 | I17: BG フル営業 | J17: 31 | K17: 55870570 | L17: 13891 | M17: =K17/L17 -> 4022.0697 | N17: =E17-K17 -> 5572748 | O17: =E17/K17 -> 1.0997439 | P17: =F17-L17 -> 656 | Q17: =F17/L17 -> 1.0472248 | R17: =G17-M17 -> 201.70965 | S17: =G17/M17 -> 1.0501507
B18: 9 | C18: BG 9/1-9/15 | D18: 15 | E18: 14966464 | F18: 4073 | G18: =E18/F18 -> 3674.5554 | H18: 9 | I18: BG 9/1-9/8 | J18: 8 | K18: 8816632 | L18: 2410 | M18: =K18/L18 -> 3658.3535 | N18: =E18-K18 -> 6149832 | O18: =E18/K18 -> 1.6975262 | P18: =F18-L18 -> 1663 | Q18: =F18/L18 -> 1.6900415 | R18: =G18-M18 -> 16.201838 | S18: =G18/M18 -> 1.0044287
B19: 9~10 | C19: PC 9/20-10/5 | D19: 16 | E19: 1210364 | F19: 870 | G19: =E19/F19 -> 1391.223 | H19: 9~10 | I19: PC-BG 秋営業 9/14-10/6 | J19: 23 | K19: 4982837 | L19: 1704 | M19: =K19/L19 -> 2924.2001 | N19: =E19-K19 -> -3772473 | O19: =E19/K19 -> 0.2429066 | P19: =F19-L19 -> -834 | Q19: =F19/L19 -> 0.51056338 | R19: =G19-M19 -> -1532.9771 | S19: =G19/M19 -> 0.47576189
B20: ビアガのみ109日 | D20: =D15+D14+D16+D17+D18 -> 109 | E20: =E15+E14+E16+E17+E18 -> 175153274 | F20: =F15+F14+F16+F17+F18 -> 42341 | G20: =E20/F20 -> 4136.7297 | H20: ビアガのみ105日 | J20: =J15+J14+J16+J17+J18 -> 105 | K20: =K15+K14+K16+K17+K18 -> 131933741 | L20: =L15+L14+L16+L17+L18 -> 33046 | M20: =K20/L20 -> 3992.427 | N20: =E20-K20 -> 43219533 | O20: =E20/K20 -> 1.3275851 | P20: =F20-L20 -> 9295 | Q20: =F20/L20 -> 1.2812746 | R20: =G20-M20 -> 144.30279 | S20: =G20/M20 -> 1.0361441
B21: ピコレ春・秋 | D21: =D13+D19 -> 39 | E21: =E13+E19 -> 4224273 | F21: =F13+F19 -> 3181 | G21: =E21/F21 -> 1327.9701 | H21: ピコレ&ピコレ共催 | J21: =J13+J19 -> 46 | K21: =K13+K19 -> 7922359 | L21: =L13+L19 -> 4052 | M21: =K21/L21 -> 1955.1725 | N21: =E21-K21 -> -3698086 | O21: =E21/K21 -> 0.53320898 | P21: =F21-L21 -> -871 | Q21: =F21/L21 -> 0.78504442 | R21: =G21-M21 -> -627.20237 | S21: =G21/M21 -> 0.67920868
B22: 総合計 | D22: =SUM(D13:D19) -> 148 | E22: =SUM(E13:E19) -> 179377547 | F22: =SUM(F13:F19) -> 45522 | G22: =E22/F22 -> 3940.4584 | H22: 総合計 | J22: =SUM(J13:J19) -> 151 | K22: =SUM(K13:K19) -> 139856100 | L22: =SUM(L13:L19) -> 37098 | M22: =K22/L22 -> 3769.9094 | N22: =E22-K22 -> 39521447 | O22: =E22/K22 -> 1.2825865 | P22: =F22-L22 -> 8424 | Q22: =F22/L22 -> 1.2270742 | R22: =G22-M22 -> 170.54896 | S22: =G22/M22 -> 1.0452395

Sheet 人件費圧縮対策効果
A1: ◆さっぽろテレビ塔ビアガーデン 人件費圧縮施策効果サマリー
A2: チャンネル別労働時間＆費用合計 | E2: 2024 | M2: 2025
A3: 依頼先 | E3: 労働時間 | G3: 労働時間比率 | I3: 報酬費用合計 | K3: 報酬費用合計比率 | M3: 労働時間 | O3: 労働時間比率 | Q3: 報酬費用合計 | S3: 報酬費用合計比率 | U3: 費用対比
A4: サーフィンズ | E4: =C24 -> 13751.25 | G4: =E4/E7 -> 0.81749275 | I4: =H24 -> 25538325 | K4: =I4/I7 -> 0.83368617 | M4: =K24 -> 12450.5 | O4: =M4/M7 -> 0.66508975 | Q4: =P24 -> 24127089 | S4: =Q4/Q7 -> 0.70660756 | U4: =Q4/I4 -> 0.94474046
A5: Forking | E5: =C36 -> 2721 | G5: =E5/E7 -> 0.16175968 | I5: =H36 -> 4594110 | K5: =I5/I7 -> 0.14997248 | M5: =K36 -> 3282.5 | O5: =M5/M7 -> 0.17534694 | Q5: =P36 -> 5395621 | S5: =Q5/Q7 -> 0.15802099 | U5: =Q5/I5 -> 1.1744649
A6: Timee | E6: =C48 -> 349 | G6: =E6/E7 -> 0.020747566 | I6: =H48 -> 500585 | K6: =I6/I7 -> 0.016341353 | M6: =K48 -> 2987.03 | O6: =M6/M7 -> 0.15956331 | Q6: =P48 -> 4622253 | S6: =Q6/Q7 -> 0.13537145 | U6: =Q6/I6 -> 9.2337026
A7: 合計 | E7: =SUM(E4:F6) -> 16821.25 | G7: =SUM(G4:H6) -> 1 | I7: =SUM(I4:J6) -> 30633020 | K7: =SUM(K4:L6) -> 1 | M7: =SUM(M4:N6) -> 18720.03 | O7: =SUM(O4:P6) -> 1 | Q7: =SUM(Q4:R6) -> 34144963 | S7: =SUM(S4:T6) -> 1 | U7: =Q7/I7 -> 1.1146457
A9: ◆売上&人件費率
A10: ビアガーデン | E10: 2024 収入 | K10: 人件費率 | M10: 2025 収入 | S10: 人件費率 | U10: 圧縮効果
E11: =F25 -> 136916578 | K11: =I7/E11 -> 0.22373492 | M11: =N25 -> 175153274 | S11: =Q7/M11 -> 0.19494333 | U11: =S11-K11 -> -0.02879159
M12: =M11*K11 -> 39187904 | S12: 0.224
M13: =M12-Q7 -> 5042941.2
A14: ◆チャンネル別詳細
B15: 2024 サーフィンズ派遣人件費実績 | J15: 2025 サーフィンズ派遣人件費実績 | R15: 比較
A16: 月 | B16: 日数 | C16: 労働時間 | D16: 残業 | E16: 基本給 | F16: 交通費 | G16: 諸手当 | H16: 報酬合計 | I16: 時間単価 | J16: 日数 | K16: 労働時間 | L16: 残業 | M16: 給与 | N16: 交通費 | O16: 諸手当 | P16: 報酬合計 | Q16: 時間単価 | R16: 圧縮時間 | S16: 圧縮費用 | T16: 時間単価 | U16: 前年比
A17: 4 | G17: ※残業1.25加算分 | O17: ※残業加算分は給与に | R17: =K17-C17 -> 0 | S17: =N17-D17 -> 0 | T17: =Q17-I17 -> 0 | U17: =P17/H17 -> #DIV/0!
A18: 5 | B18: 5 | C18: 579.5 | D18: 0 | E18: 956175 | F18: 89000 | H18: =E18+F18+G18 -> 1045175 | I18: =H18/C18 -> 1803.5807 | J18: 2 | K18: 221.5 | L18: 0.5 | M18: 377613 | N18: 36000 | P18: =M18+N18+O18 -> 413613 | Q18: =P18/K18 -> 1867.3273 | R18: =K18-C18 -> -358 | S18: =P18-H18 -> -631562 | T18: =Q18-I18 -> 63.746641 | U18: =P18/H18 -> 0.39573564
A19: 6 | B19: 30 | C19: 3580.5 | D19: 7 | E19: 5939877 | F19: 545000 | G19: 1950 | H19: =E19+F19+G19 -> 6486827 | I19: =H19/C19 -> 1811.7098 | J19: 30 | K19: 3156.25 | L19: 12 | M19: 5410094 | N19: 527000 | P19: =M19+N19+O19 -> 5937094 | Q19: =P19/K19 -> 1881.0595 | R19: =K19-C19 -> -424.25 | S19: =P19-H19 -> -549733 | T19: =Q19-I19 -> 69.349668 | U19: =P19/H19 -> 0.91525394
A20: 7 | B20: 31 | C20: 4084.25 | D20: 32 | E20: 7019597 | F20: 583000 | G20: 13738 | H20: =E20+F20+G20 -> 7616335 | I20: =H20/C20 -> 1864.8063 | J20: 31 | K20: 3671.25 | L20: 50.25 | M20: 6544024 | N20: 573000 | P20: =M20+N20+O20 -> 7117024 | Q20: =P20/K20 -> 1938.5833 | R20: =K20-C20 -> -413 | S20: =P20-H20 -> -499311 | T20: =Q20-I20 -> 73.777048 | U20: =P20/H20 -> 0.93444209
A21: 8 | B21: 31 | C21: 4444 | D21: 39 | E21: 7728270 | F21: 633000 | G21: 11262 | H21: =E21+F21+G21 -> 8372532 | I21: =H21/C21 -> 1884.0081 | J21: 31 | K21: 3768 | L21: 46.5 | M21: 6814246 | N21: 590000 | P21: =M21+N21+O21 -> 7404246 | Q21: =P21/K21 -> 1965.0334 | R21: =K21-C21 -> -676 | S21: =P21-H21 -> -968286 | T21: =Q21-I21 -> 81.025339 | U21: =P21/H21 -> 0.88434968
A22: 9 | B22: 8 | C22: 1063 | D22: 2 | E22: 1866106 | F22: 150000 | G22: 1350 | H22: =E22+F22+G22 -> 2017456 | I22: =H22/C22 -> 1897.889 | J22: 15 | K22: 1633.5 | L22: 23 | M22: 2993112 | N22: 262000 | P22: =M22+N22+O22 -> 3255112 | Q22: =P22/K22 -> 1992.7224 | R22: =K22-C22 -> 570.5 | S22: =P22-H22 -> 1237656 | T22: =Q22-I22 -> 94.833382 | U22: =P22/H22 -> 1.6134736
A23: 10 | H23: =E23+F23 -> 0 | I23: =H23/C23 -> #DIV/0! | P23: =M23+N23 -> 0 | Q23: =P23/K23 -> #DIV/0! | R23: =K23-C23 -> 0 | S23: =P23-H23 -> 0 | T23: =Q23-I23 -> #DIV/0! | U23: =P23/H23 -> #DIV/0!
B24: =SUM(B16:B23) -> 105 | C24: =SUM(C16:C23) -> 13751.25 | D24: =SUM(D16:D23) -> 80 | E24: =SUM(E16:E23) -> 23510025 | F24: =SUM(F16:F23) -> 2000000 | G24: =SUM(G16:G23) -> 28300 | H24: =SUM(H16:H23) -> 25538325 | I24: =H24/C24 -> 1857.1639 | J24: =SUM(J16:J23) -> 109 | K24: =SUM(K16:K23) -> 12450.5 | L24: =SUM(L16:L23) -> 132.25 | M24: =SUM(M16:M23) -> 22139089 | N24: =SUM(N16:N23) -> 1988000 | P24: =SUM(P16:P23) -> 24127089 | Q24: =P24/K24 -> 1937.841 | R24: =(K24+D24)-(C24+L24) -> -1353 | S24: =P24-H24 -> -1411236 | T24: =Q24-I24 -> 80.677076 | U24: =P24/H24 -> 0.94474046
A25: 2024収入合計（ビアガ＋秋ピコレ共催） | F25: 136916578 | I25: =H24/F25 -> 0.18652471 | J25: 2025収入合計（ビアガのみ） | N25: 175153274 | Q25: =P24/N25 -> 0.13774843 | R25: =N25-F25 -> 38236696 | T25: =N25/F25 -> 1.27927
B27: 2024 Forking | J27: 2025 Forking | R27: 比較差異
A28: 月 | C28: 労働時間 | D28: 基本給 | E28: 交通費 | F28: 手数料 | G28: その他 | H28: 費用合計 | I28: 単価 | K28: 労働時間 | L28: 基本給 | M28: 交通費 | N28: 手数料 | O28: その他 | P28: 費用合計 | Q28: 単価 | R28: 時間 | S28: 費用 | T28: 時間単価 | U28: 前年比
A29: 4 | R29: =K29-C29 -> 0 | S29: =N29-D29 -> 0 | T29: =Q29-I29 -> 0 | U29: =P29/H29 -> #DIV/0!
A30: 5 | C30: 250 | H30: 370861 | I30: =H30/C30 -> 1483.444 | K30: 49.5 | L30: 53550 | M30: 5500 | N30: =19491+1815 -> 21306 | P30: =L30+M30+N30 -> 80356 | Q30: =P30/K30 -> 1623.3535 | R30: =K30-C30 -> -200.5 | S30: =P30-H30 -> -290505 | T30: =Q30-I30 -> 139.90954 | U30: =P30/H30 -> 0.21667417
A31: 6 | C31: 655 | H31: 976046 | I31: =H31/C31 -> 1490.1466 | K31: 771.5 | L31: 786865 | M31: 81500 | N31: =286633+24420 -> 311053 | P31: =L31+M31+N31 -> 1179418 | Q31: =P31/K31 -> 1528.7336 | R31: =K31-C31 -> 116.5 | S31: =P31-H31 -> 203372 | T31: =Q31-I31 -> 38.587071 | U31: =P31/H31 -> 1.2083631
A32: 7 | C32: 876 | H32: 1316824 | I32: =H32/C32 -> 1503.2237 | K32: 1150 | L32: 1220009 | M32: 121500 | N32: =441550+34650 -> 476200 | P32: =L32+M32+N32 -> 1817709 | Q32: =P32/K32 -> 1580.6165 | R32: =K32-C32 -> 274 | S32: =P32-H32 -> 500885 | T32: =Q32-I32 -> 77.392777 | U32: =P32/H32 -> 1.3803735
A33: 8 | C33: 912 | H33: 1468290 | I33: =H33/C33 -> 1609.9671 | K33: 1289 | L33: 1373740 | M33: 137500 | N33: =498759+37950 -> 536709 | P33: =L33+M33+N33 -> 2047949 | Q33: =P33/K33 -> 1588.789 | R33: =K33-C33 -> 377 | S33: =P33-H33 -> 579659 | T33: =Q33-I33 -> -21.178122 | U33: =P33/H33 -> 1.3947851
A34: 9 | C34: 278 | H34: 462089 | I34: =H34/C34 -> 1662.1906 | K34: 72 | L34: 239253 | M34: 19600 | N34: 91692 | P34: =L34+M34+N34 -> 350545 | Q34: =P34/K34 -> 4868.6806 | R34: =K34-C34 -> -206 | S34: =P34-H34 -> -111544 | T34: =Q34-I34 -> 3206.4899 | U34: =P34/H34 -> 0.75860927
A35: 10 | H35: =D35+E35+F35 -> 0 | I35: =H35/C35 -> #DIV/0! | P35: =L35+M35+N35 -> 0 | Q35: =P35/K35 -> #DIV/0! | R35: =K35-C35 -> 0 | S35: =P35-H35 -> 0 | T35: =Q35-I35 -> #DIV/0! | U35: =P35/H35 -> #DIV/0!
C36: =SUM(C31:C35) -> 2721 | D36: =SUM(D31:D35) -> 0 | E36: =SUM(E31:E35) -> 0 | F36: =SUM(F31:F35) -> 0 | H36: =SUM(H29:H35) -> 4594110 | I36: =H36/C36 -> 1688.3903 | K36: =SUM(K31:K35) -> 3282.5 | L36: =SUM(L31:L35) -> 3619867 | M36: =SUM(M31:M35) -> 360100 | N36: =SUM(N31:N35) -> 1415654 | P36: =L36+M36+N36 -> 5395621 | Q36: =P36/K36 -> 1643.7535 | R36: =K36-C36 -> 561.5 | S36: =P36-H36 -> 801511 | T36: =Q36-I36 -> -44.636756 | U36: =P36/H36 -> 1.1744649
C37: Forking 人件費率 | I37: =H36/F25 -> 0.033554081 | K37: Forking 人件費率 | Q37: =P36/N25 -> 0.030805139 | R37: 人件費率増減 | T37: =Q37-I37 -> -0.0027489421
B39: 2024 Timee | J39: 2025 Timee | R39: 比較差異
A40: 月 | C40: 労働時間 | D40: 基本給 | E40: 交通費 | F40: 手数料 | G40: その他 | H40: 費用合計 | I40: 単価 | K40: 労働時間 | L40: 基本給 | M40: 交通費 | N40: 手数料 | O40: その他 | P40: 費用合計 | Q40: 単価 | R40: 時間 | S40: 費用 | T40: 時間単価 | U40: 前年比
A41: 4 | R41: =K41-C41 -> 0 | S41: =N41-D41 -> 0 | T41: =Q41-I41 -> 0 | U41: =P41/H41 -> #DIV/0!
A42: 5 | I42: =H42/C42 -> #DIV/0! | P42: =L42+M42+N42 -> 0 | Q42: =P42/K42 -> #DIV/0! | R42: =K42-C42 -> 0 | S42: =P42-H42 -> 0 | T42: =Q42-I42 -> #DIV/0! | U42: =P42/H42 -> #DIV/0!
A43: 6 | C43: 303 | H43: 391038 | I43: =H43/C43 -> 1290.5545 | K43: 462.53 | L43: 492750 | M43: 44000 | N43: 161008 | P43: =L43+M43+N43 -> 697758 | Q43: =P43/K43 -> 1508.5681 | R43: =K43-C43 -> 159.53 | S43: =P43-H43 -> 306720 | T43: =Q43-I43 -> 218.01364 | U43: =P43/H43 -> 1.7843739
A44: 7 | C44: 23 | H44: 52747 | I44: =H44/C44 -> 2293.3478 | K44: 1139.94 | L44: =1244597+3389 -> 1247986 | M44: 121300 | N44: 410736 | P44: =L44+M44+N44 -> 1780022 | Q44: =P44/K44 -> 1561.505 | R44: =K44-C44 -> 1116.94 | S44: =P44-H44 -> 1727275 | T44: =Q44-I44 -> -731.84283 | U44: =P44/H44 -> 33.746412
A45: 8 | C45: 23 | H45: 56800 | I45: =H45/C45 -> 2469.5652 | K45: 1366.56 | L45: =1493853+8303 -> 1502156 | M45: 127760 | N45: 488973 | P45: =L45+M45+N45 -> 2118889 | Q45: =P45/K45 -> 1550.5276 | R45: =K45-C45 -> 1343.56 | S45: =P45-H45 -> 2062089 | T45: =Q45-I45 -> -919.03762 | U45: =P45/H45 -> 37.304384
A46: 9 | C46: 0 | I46: =H46/C46 -> #DIV/0! | K46: 18 | L46: 18180 | M46: 1500 | N46: 5904 | P46: =L46+M46+N46 -> 25584 | Q46: =P46/K46 -> 1421.3333 | R46: =K46-C46 -> 18 | S46: =P46-H46 -> 25584 | T46: =Q46-I46 -> #DIV/0! | U46: =P46/H46 -> #DIV/0!
A47: 10 | H47: =D47+E47+F47 -> 0 | I47: =H47/C47 -> #DIV/0! | P47: =L47+M47+N47 -> 0 | Q47: =P47/K47 -> #DIV/0! | R47: =K47-C47 -> 0 | S47: =P47-H47 -> 0 | T47: =Q47-I47 -> #DIV/0! | U47: =P47/H47 -> #DIV/0!
C48: =SUM(C43:C47) -> 349 | D48: =SUM(D43:D47) -> 0 | E48: =SUM(E43:E47) -> 0 | F48: =SUM(F43:F47) -> 0 | H48: =SUM(H41:H47) -> 500585 | I48: =H48/C48 -> 1434.341 | K48: =SUM(K43:K47) -> 2987.03 | L48: =SUM(L43:L47) -> 3261072 | M48: =SUM(M43:M47) -> 294560 | N48: =SUM(N43:N47) -> 1066621 | P48: =L48+M48+N48 -> 4622253 | Q48: =P48/K48 -> 1547.4411 | R48: =K48-C48 -> 2638.03 | S48: =P48-H48 -> 4121668 | T48: =Q48-I48 -> 113.10013 | U48: =P48/H48 -> 9.2337026
C49: Timee 人件費率 | I49: =H48/F25 -> 0.0036561314 | K49: Timee 人件費率 | Q49: =P48/N25 -> 0.026389761 | R49: 人件費率増減 | T49: =Q49-I49 -> 0.022733629
B51: 2024 スポットワーク合計 | J51: 2025スポットワーク合計 | R51: 比較差異
A52: 月 | C52: 労働時間 | D52: 基本給 | E52: 交通費 | F52: 手数料 | G52: その他 | H52: 費用合計 | I52: 単価 | K52: 労働時間 | L52: 基本給 | M52: 交通費 | N52: 手数料 | O52: その他 | P52: 費用合計 | Q52: 単価 | R52: 圧縮時間 | S52: 圧縮費用 | T52: 時間単価 | U52: 前年比
A53: 4 | C53: =C29+C41 -> 0 | D53: =D29+D41 -> 0 | E53: =E29+E41 -> 0 | F53: =F29+F41 -> 0 | G53: =G29+G41 -> 0 | H53: =H29+H41 -> 0 | K53: =K29+K41 -> 0 | L53: =L29+L41 -> 0 | M53: =M29+M41 -> 0 | N53: =N29+N41 -> 0 | O53: =O29+O41 -> 0 | P53: =P29+P41 -> 0 | R53: =K53-C53 -> 0 | S53: =N53-D53 -> 0 | T53: =Q53-I53 -> 0 | U53: =P53/H53 -> #DIV/0!
A54: 5 | C54: =C30+C42 -> 250 | D54: =D30+D42 -> 0 | E54: =E30+E42 -> 0 | F54: =F30+F42 -> 0 | G54: =G30+G42 -> 0 | H54: =H30+H42 -> 370861 | I54: =H54/C54 -> 1483.444 | K54: =K30+K42 -> 49.5 | L54: =L30+L42 -> 53550 | M54: =M30+M42 -> 5500 | N54: =N30+N42 -> 21306 | O54: =O30+O42 -> 0 | P54: =P30+P42 -> 80356 | Q54: =P54/K54 -> 1623.3535 | R54: =K54-C54 -> -200.5 | S54: =P54-H54 -> -290505 | T54: =Q54-I54 -> 139.90954 | U54: =P54/H54 -> 0.21667417
A55: 6 | C55: =C31+C43 -> 958 | D55: =D31+D43 -> 0 | E55: =E31+E43 -> 0 | F55: =F31+F43 -> 0 | G55: =G31+G43 -> 0 | H55: =H31+H43 -> 1367084 | I55: =H55/C55 -> 1427.0188 | K55: =K31+K43 -> 1234.03 | L55: =L31+L43 -> 1279615 | M55: =M31+M43 -> 125500 | N55: =N31+N43 -> 472061 | O55: =O31+O43 -> 0 | P55: =P31+P43 -> 1877176 | Q55: =P55/K55 -> 1521.1753 | R55: =K55-C55 -> 276.03 | S55: =P55-H55 -> 510092 | T55: =Q55-I55 -> 94.156547 | U55: =P55/H55 -> 1.3731241
A56: 7 | C56: =C32+C44 -> 899 | D56: =D32+D44 -> 0 | E56: =E32+E44 -> 0 | F56: =F32+F44 -> 0 | G56: =G32+G44 -> 0 | H56: =H32+H44 -> 1369571 | I56: =H56/C56 -> 1523.4383 | K56: =K32+K44 -> 2289.94 | L56: =L32+L44 -> 2467995 | M56: =M32+M44 -> 242800 | N56: =N32+N44 -> 886936 | O56: =O32+O44 -> 0 | P56: =P32+P44 -> 3597731 | Q56: =P56/K56 -> 1571.1027 | R56: =K56-C56 -> 1390.94 | S56: =P56-H56 -> 2228160 | T56: =Q56-I56 -> 47.664472 | U56: =P56/H56 -> 2.6269036
A57: 8 | C57: =C33+C45 -> 935 | D57: =D33+D45 -> 0 | E57: =E33+E45 -> 0 | F57: =F33+F45 -> 0 | G57: =G33+G45 -> 0 | H57: =H33+H45 -> 1525090 | I57: =H57/C57 -> 1631.1123 | K57: =K33+K45 -> 2655.56 | L57: =L33+L45 -> 2875896 | M57: =M33+M45 -> 265260 | N57: =N33+N45 -> 1025682 | O57: =O33+O45 -> 0 | P57: =P33+P45 -> 4166838 | Q57: =P57/K57 -> 1569.0995 | R57: =K57-C57 -> 1720.56 | S57: =P57-H57 -> 2641748 | T57: =Q57-I57 -> -62.01275 | U57: =P57/H57 -> 2.7321915
A58: 9 | C58: =C34+C46 -> 278 | D58: =D34+D46 -> 0 | E58: =E34+E46 -> 0 | F58: =F34+F46 -> 0 | G58: =G34+G46 -> 0 | H58: =H34+H46 -> 462089 | I58: =H58/C58 -> 1662.1906 | K58: =K34+K46 -> 90 | L58: =L34+L46 -> 257433 | M58: =M34+M46 -> 21100 | N58: =N34+N46 -> 97596 | O58: =O34+O46 -> 0 | P58: =P34+P46 -> 376129 | Q58: =P58/K58 -> 4179.2111 | R58: =K58-C58 -> -188 | S58: =P58-H58 -> -85960 | T58: =Q58-I58 -> 2517.0205 | U58: =P58/H58 -> 0.81397523
A59: 10 | C59: =C35+C47 -> 0 | D59: =D35+D47 -> 0 | E59: =E35+E47 -> 0 | F59: =F35+F47 -> 0 | G59: =G35+G47 -> 0 | H59: =H35+H47 -> 0 | I59: =H59/C59 -> #DIV/0! | K59: =K35+K47 -> 0 | L59: =L35+L47 -> 0 | M59: =M35+M47 -> 0 | N59: =N35+N47 -> 0 | O59: =O35+O47 -> 0 | P59: =P35+P47 -> 0 | Q59: =P59/K59 -> #DIV/0! | R59: =K59-C59 -> 0 | S59: =P59-H59 -> 0 | T59: =Q59-I59 -> #DIV/0! | U59: =P59/H59 -> #DIV/0!
C60: =C36+C48 -> 3070 | D60: =D36+D48 -> 0 | E60: =E36+E48 -> 0 | F60: =F36+F48 -> 0 | G60: =G36+G48 -> 0 | H60: =H36+H48 -> 5094695 | I60: =H60/C60 -> 1659.5098 | K60: =K36+K48 -> 6269.53 | L60: =L36+L48 -> 6880939 | M60: =M36+M48 -> 654660 | N60: =N36+N48 -> 2482275 | O60: =O36+O48 -> 0 | P60: =P36+P48 -> 10017874 | Q60: =P60/K60 -> 1597.8668 | R60: =K60-C60 -> 3199.53 | S60: =P60-H60 -> 4923179 | T60: =Q60-I60 -> -61.642946 | U60: =P60/H60 -> 1.9663344
C61: スポットワーク 人件費率 | I61: =H60/F25 -> 0.037210213 | K61: スポットワーク 人件費率 | Q61: =P60/N25 -> 0.0571949 | R61: 人件費率増減 | T61: =Q61-I61 -> 0.019984687

Sheet 2025計画値・予測・実績進捗
A1: ■R7年 ポップアップ ヒツジニワイン / さっぽろテレビ塔ビアガーデン売上計画（予算）・売上予測（9/15まで）・実績進捗確認表 | M1: 8・31終了時点
B2: 計画値 | E2: 予測値（目標値） | K2: 実績進捗（派遣分+スポットワーク） | R2: ノヴェロさん請求内容（手数料込み） | Z2: 家賃 | AB2: 概算（仮置き） | AD2: スポットワーク内訳（税抜/手数料込み）
A3: 月 | B3: 売上予算 | C3: 客数 | D3: 客単価 | E3: 労働時間（予測値） | F3: 人時生産性 | G3: 想定人件費 | H3: 人件費率 | I3: 売上予測 | J3: 対予算 | K3: 売上実績 | L3: 対予測 | M3: 対予算 | N3: 実労働時間 | O3: 人時生産性 | P3: 概算人件費率 | Q3: 人件費（リザルト） | R3: 人件費 | S3: 営業日数 | T3: 拘束時間 | U3: 残業時間 | V3: 人件費合計 | W3: 交通費合計 | X3: 手当 | Y3: 合計 | Z3: 家賃 | AA3: 1日 | AD3: Forking | AJ3: Timee | AY3: =AY4/AY5 -> 0.051860592
A4: 4（ピコレ） | B4: 543750 | C4: 375 | D4: =B4/C4 -> 1450 | E4: 120 | F4: =I4/E4 -> 4583.3333 | G4: =E4*R4 -> #DIV/0! | H4: =G4/B4 -> #DIV/0! | I4: 550000 | J4: =I4/B4 -> 1.0114943 | K4: 3013909 | L4: =K4/I4 -> 5.4798345 | M4: =K4/B4 -> 5.5428211 | N4: =T4+U4 -> 0 | O4: =K4/N4 -> #DIV/0! | P4: =Q4/K4 -> 0 | Q4: =Y4 -> 0 | R4: =Q4/N4 -> #DIV/0! | Y4: =V4+W4 -> 0 | AD4: 労働時間 | AE4: 基本給 | AF4: 交通費 | AG4: 手数料 | AH4: 報酬合計 | AI4: 単価 | AJ4: 実働時間 | AK4: 基本給 | AL4: 交通費 | AM4: 手数料 | AN4: 報酬合計 | AO4: 単価 | AP4: 月 | AW4: =AW8*AW6 -> 6865350 | AX4: =AX8*AX6 -> 3664000 | AY4: =AW4+AX4 -> 10529350
A5: 5 | B5: 2847520 | C5: 1600 | D5: =B5/C5 -> 1779.7 | E5: 400 | F5: =I5/E5 -> 7500 | G5: =E5*R5 -> 688269.61 | H5: =G5/B5 -> 0.24170844 | I5: 3000000 | J5: =I5/B5 -> 1.0535484 | K5: 2588445 | L5: =K5/I5 -> 0.862815 | M5: =K5/B5 -> 0.90901732 | N5: =T5+U5+AD5+AJ5 -> 271.5 | O5: =K5/N5 -> 9533.8674 | P5: =Q5/K5 -> 0.18048017 | Q5: =Y5+AE5+AK5 -> 467163 | R5: =Q5/N5 -> 1720.674 | S5: 2 | T5: 221.5 | U5: 0.5 | V5: 377613 | W5: 36000 | Y5: =V5+W5+X5 -> 413613 | AC5: 5 | AD5: 49.5 | AE5: 53550 | AF5: 5500 | AG5: =19491+1815 -> 21306 | AH5: =AE5+AF5+AG5 -> 80356 | AI5: =AH5/AD5 -> 1623.3535 | AP5: 5 | AW5: =AW7*AW6 -> 6791812.5 | AX5: =AX7*AX6 -> 196240000 | AY5: =AW5+AX5 -> 2.0303181e+08
A6: 6 | B6: 22680000 | C6: 8050 | D6: =B6/C6 -> 2817.3913 | E6: 3300 | F6: =I6/E6 -> 6969.697 | G6: =E6*R6 -> 5413289.2 | H6: =G6/B6 -> 0.23868118 | I6: 23000000 | J6: =I6/B6 -> 1.0141093 | K6: 33132365 | L6: =K6/I6 -> 1.4405376 | M6: =K6/B6 -> 1.4608627 | N6: =T6+U6+AD6+AJ6 -> 4402.28 | O6: =K6/N6 -> 7526.183 | P6: =Q6/K6 -> 0.21795785 | Q6: =Y6+AE6+AK6 -> 7221459 | R6: =Q6/N6 -> 1640.3907 | S6: 30 | T6: 3156.25 | U6: 12 | V6: 5410094 | W6: 527000 | Y6: =V6+W6+X6 -> 5937094 | AC6: 6 | AD6: 771.5 | AE6: 791615 | AF6: 81500 | AG6: =286633+24420 -> 311053 | AH6: =AE6+AF6+AG6 -> 1184168 | AI6: =AH6/AD6 -> 1534.8905 | AJ6: 462.53 | AK6: 492750 | AL6: 44000 | AM6: 161008 | AN6: =AK6+AL6+AM6 -> 697758 | AO6: =AN6/AJ6 -> 1508.5681 | AP6: 6 | AU6: 157 | AV6: 単価 | AW6: 1850 | AX6: 1600
A7: 7 | B7: 49815000 | C7: 14280 | D7: =B7/C7 -> 3488.4454 | E7: 5800 | F7: =I7/E7 -> 9137.931 | G7: =E7*R7 -> 9247909.9 | H7: =G7/B7 -> 0.18564508 | I7: 53000000 | J7: =I7/B7 -> 1.0639366 | K7: 63022682 | L7: =K7/I7 -> 1.1891072 | M7: =K7/B7 -> 1.2651346 | N7: =T7+U7+AD7+AJ7 -> 6011.44 | O7: =K7/N7 -> 10483.791 | P7: =Q7/K7 -> 0.1520888 | Q7: =Y7+AE7+AK7 -> 9585044 | R7: =Q7/N7 -> 1594.4672 | S7: 31 | T7: 3671.25 | U7: 50.25 | V7: 6544024 | W7: 573000 | Y7: =V7+W7+X7 -> 7117024 | AC7: 7 | AD7: 1150 | AE7: 1220034 | AF7: 121500 | AG7: =441550+34650 -> 476200 | AH7: =AE7+AF7+AG7 -> 1817734 | AI7: =AH7/AD7 -> 1580.6383 | AJ7: 1139.94 | AK7: =1244597+3389 -> 1247986 | AL7: 121300 | AM7: 410736 | AN7: =AK7+AL7+AM7 -> 1780022 | AO7: =AN7/AJ7 -> 1561.505 | AP7: 7 | AV7: =AF7+AD7+T7 -> 126321.25 | AW7: =AV7-AX7 -> 3671.25 | AX7: =AD7+AF7 -> 122650
A8: 8 | B8: 56840000 | C8: 15789 | D8: =B8/C8 -> 3599.9747 | E8: 5800 | F8: =I8/E8 -> 9482.7586 | G8: =E8*R8 -> 9193535.1 | H8: =G8/B8 -> 0.16174411 | I8: 55000000 | J8: =I8/B8 -> 0.96762843 | K8: 61443318 | L8: =K8/I8 -> 1.1171512 | M8: =K8/B8 -> 1.0809873 | N8: =T8+U8+AD8+AJ8 -> 6470.06 | O8: =K8/N8 -> 9496.5608 | P8: =Q8/K8 -> 0.16691224 | Q8: =Y8+AE8+AK8 -> 10255642 | R8: =Q8/N8 -> 1585.0923 | S8: 31 | T8: 3768 | U8: 46.5 | V8: 6814246 | W8: 590000 | Y8: =V8+W8+X8 -> 7404246 | AC8: 8 | AD8: 1289 | AE8: 1349240 | AF8: 137500 | AG8: =498759+37950 -> 536709 | AH8: =AE8+AF8+AG8 -> 2023449 | AI8: =AH8/AD8 -> 1569.782 | AJ8: 1366.56 | AK8: =1493853+8303 -> 1502156 | AL8: 127760 | AM8: 488973 | AN8: =AK8+AL8+AM8 -> 2118889 | AO8: =AN8/AJ8 -> 1550.5276 | AP8: 8 | AV8: 6001 | AW8: =AV8-AX8 -> 3711 | AX8: 2290
A9: 9 | B9: 20842025 | C9: 7485 | D9: =B9/C9 -> 2784.5057 | E9: 3150 | F9: =I9/E9 -> 6666.6667 | G9: =E9*R9 -> 7136348.3 | H9: =G9/B9 -> 0.34240187 | I9: 21000000 | J9: =I9/B9 -> 1.0075796 | K9: 15779145 | L9: =K9/I9 -> 0.75138786 | M9: =K9/B9 -> 0.7570831 | N9: =T9+U9 -> 1656.5 | O9: =K9/N9 -> 9525.5931 | P9: =Q9/K9 -> 0.23783374 | Q9: =Y9+AE9+AK9 -> 3752813 | R9: =Q9/N9 -> 2265.5074 | S9: 15 | T9: 1633.5 | U9: 23 | V9: 2993112 | W9: 262000 | Y9: =V9+W9+X9 -> 3255112 | AC9: 9 | AD9: 72 | AE9: 479521 | AF9: 19600 | AG9: 91692 | AH9: =AE9+AF9+AG9 -> 590813 | AI9: =AH9/AD9 -> 8205.7361 | AJ9: 18 | AK9: 18180 | AL9: 1500 | AM9: 5904 | AN9: =AK9+AL9+AM9 -> 25584 | AO9: =AN9/AJ9 -> 1421.3333 | AP9: 9 | AR9: 17040 | AV9: =AV8/AV7 -> 0.047505863 | AW9: =AW8/AW7 -> 1.0108274 | AX9: =AX8/AX7 -> 0.018671015
A10: 10 | B10: 840000 | C10: 1400 | D10: =B10/C10 -> 600 | E10: 150 | F10: =I10/E10 -> 4618.1818 | G10: =E10*R10 -> 285000 | H10: =G10/B10 -> 0.33928571 | I10: ='2024.10'!BL93 -> 692727.27 | J10: =I10/B10 -> 0.82467532 | K10: 397683 | L10: =K10/I10 -> 0.57408307 | M10: =K10/B10 -> 0.47343214 | N10: =T10+U10 -> 0 | O10: =K10/N10 -> #DIV/0! | P10: =Q10/K10 -> 0 | Q10: =Y10+AE10+AK10 -> 0 | R10: 1900 | Y10: =V10+W10 -> 0 | AC10: 10 | AH10: =AE10+AF10+AG10 -> 0 | AI10: =AH10/AD10 -> #DIV/0! | AN10: =AK10+AL10+AM10 -> 0 | AO10: =AN10/AJ10 -> #DIV/0! | AP10: 10
A11: TOTAL | B11: =SUM(B4:B10) -> 154408295 | C11: =SUM(C4:C10) -> 48979 | D11: =B11/C11 -> 3152.5408 | E11: =SUM(E4:E10) -> 18720 | F11: =I11/E11 -> 8346.2995 | G11: =E11*R11 -> 31129500 | H11: =G11/B11 -> 0.2016051 | I11: =SUM(I4:I10) -> 1.5624273e+08 | J11: =I11/B11 -> 1.0118804 | K11: =SUM(K4:K10) -> 179377547 | L11: =K11/I11 -> 1.1480697 | M11: =K11/B11 -> 1.1617093 | N11: =SUM(N4:N10) -> 18811.78 | O11: =K11/N11 -> 9535.3841 | P11: =Q11/K11 -> 0.17439262 | Q11: =SUM(Q4:Q10) -> 31282121 | R11: =Q11/N11 -> 1662.9006 | S11: =SUM(S4:S10) -> 109 | T11: =SUM(T4:T10) -> 12450.5 | U11: =SUM(U4:U10) -> 132.25 | V11: =SUM(V4:V10) -> 22139089 | W11: =SUM(W4:W10) -> 1988000 | Y11: =SUM(Y4:Y10) -> 24127089 | Z11: =SUM(Z4:Z10) -> 0 | AA11: =SUM(AA4:AA10) -> 0 | AB11: =AE11+AK11 -> 7101482 | AD11: =SUM(AD6:AD10) -> 3282.5 | AE11: =SUM(AE6:AE10) -> 3840410 | AF11: =SUM(AF6:AF10) -> 360100 | AG11: =SUM(AG6:AG10) -> 1415654 | AH11: =AE11+AF11+AG11 -> 5616164 | AI11: =AH11/AD11 -> 1710.9411 | AJ11: =SUM(AJ6:AJ10) -> 2987.03 | AK11: =SUM(AK6:AK10) -> 3261072 | AL11: =SUM(AL6:AL10) -> 294560 | AM11: =SUM(AM6:AM10) -> 1066621 | AN11: =SUM(AN6:AN10) -> 4622253 | AO11: =AN11/AJ11 -> 1547.4411 | AR11: =AJ11/AJ13 -> #VALUE! | AS11: =AJ11/AT11 -> 1.8325337 | AT11: 1630 | AU11: =AS11/AS13 -> 0.00011642651 | AV11: 5000 | AW11: 1650 | AX11: =AV11*AW11 -> 8250000 | AY11: =AV11/AV13 -> 0.2792984 | AZ11: =AX11/AX13 -> 0.25380117
B12: =B11 -> 154408295 | C12: 提出予算 | I12: ※天気要因見込まず算出 | K12: 44473 | L12: 終了時点の進捗状況 | N12: =K11/S12 -> 1645665.6 | O12: =K11-B12 -> 24969252 | P12: =K11/B12 -> 1.1617093 | Q12: =Q11/K11 -> 0.17439262 | S12: 109 | Y12: =Y11/K11 -> 0.13450451 | AJ12: スポットワーク合計 | AR12: =AJ12/AJ13 -> #VALUE! | AS12: 15738 | AT12: =AJ12/AS12 -> #VALUE! | AU12: =AS12/AS13 -> 0.99988357 | AV12: 12902 | AW12: 1880 | AX12: =AV12*AW12 -> 24255760 | AY12: =AV12/AV13 -> 0.7207016 | AZ12: =AX12/AX13 -> 0.74619883
B13: =B11-B12 -> 0 | C13: 差異 | AE13: =AF13/AF16 -> 0.16342445 | AF13: =AH11 -> 5616164 | AG13: Forking | AH13: =AD11 -> 3282.5 | AI13: =AH13/AH16 -> 0.17534694 | AJ13: 実働時間 | AK13: 基本給 | AL13: 交通費 | AM13: 手数料 | AN13: 報酬合計 | AO13: 単価 | AP13: 月 | AR13: =AJ13/AG13 -> #VALUE! | AS13: =SUM(AS11:AS12) -> 15739.833 | AT13: =(AT11+AT12)/2 -> #VALUE! | AV13: =SUM(AV11:AV12) -> 17902 | AW13: =(AW11+AW12)/2 -> 1765 | AX13: =SUM(AX11:AX12) -> 32505760
AE14: =AF14/AF16 -> 0.13450269 | AF14: =AN11 -> 4622253 | AG14: Timee | AH14: =AJ11 -> 2987.03 | AI14: =AH14/AH16 -> 0.15956331 | AJ14: =AD5+AJ5 -> 49.5 | AK14: =AE5+AK5 -> 53550 | AL14: =AF5+AL5 -> 5500 | AM14: =AG5+AM5 -> 21306 | AN14: =AH5+AN5 -> 80356 | AO14: =AN14/AJ14 -> 1623.3535 | AP14: 5
AE15: =AF15/AF16 -> 0.70207286 | AF15: =AQ31 -> 24127089 | AG15: Surfins | AH15: =AL31 -> 12450.5 | AI15: =AH15/AH16 -> 0.66508975 | AJ15: =AD6+AJ6 -> 1234.03 | AK15: =AE6+AK6 -> 1284365 | AL15: =AF6+AL6 -> 125500 | AM15: =AG6+AM6 -> 472061 | AN15: =AH6+AN6 -> 1881926 | AO15: =AN15/AJ15 -> 1525.0245 | AP15: 6
I16: 100000000 | J16: 予算まで | K16: =B11-K11 -> -24969252 | L16: 12 | M16: =K16/L16 -> -2080771 | N16: 2019 | O16: 58190982 | P16: =K11/O16 -> 3.0825661 | V16: 税込 | AE16: =SUM(AE13:AE15) -> 1 | AF16: =SUM(AF13:AF15) -> 34365506 | AG16: =K11 -> 179377547 | AH16: =AD11+AJ11+AL31 -> 18720.03 | AI16: =SUM(AI13:AI15) -> 1 | AJ16: =AD7+AJ7 -> 2289.94 | AK16: =AE7+AK7 -> 2468020 | AL16: =AF7+AL7 -> 242800 | AM16: =AG7+AM7 -> 886936 | AN16: =AH7+AN7 -> 3597756 | AO16: =AN16/AJ16 -> 1571.1137 | AP16: 7
B17: =B7+B8 -> 106655000 | C17: =K7+K8 -> 124466000 | D17: =C17-B17 -> 17811000 | I17: 111111111 | J17: 予測まで | K17: =I11-K11 -> -23134820 | L17: 12 | M17: =K17/L17 -> -1927901.6 | N17: 2018 | O17: 44179221 | P17: =K11/O17 -> 4.0602243 | U17: 5 | V17: 1149692 | Y17: 8072564367 | AE17: 平均時間単価 | AF17: =AF16/AH16 -> 1835.7613 | AG17: 人事売上高 | AH17: =AG16/AH16 -> 9582.1186 | AJ17: =AD8+AJ8 -> 2655.56 | AK17: =AE8+AK8 -> 2851396 | AL17: =AF8+AL8 -> 265260 | AM17: =AG8+AM8 -> 1025682 | AN17: =AH8+AN8 -> 4142338 | AO17: =AN17/AJ17 -> 1559.8736 | AP17: 8
J18: 一億円まで | K18: =I16-K11 -> -79377547 | L18: 12 | M18: =K18/L18 -> -6614795.6 | N18: 平均 | O18: =(O16+O17)/2 -> 51185102 | P18: =K11/O18 -> 3.5044875 | U18: 6 | V18: 7135509 | AJ18: =AD9+AJ9 -> 90 | AK18: =AE9+AK9 -> 497701 | AL18: =AF9+AL9 -> 21100 | AM18: =AG9+AM9 -> 97596 | AN18: =AH9+AN9 -> 616397 | AO18: =AN18/AJ18 -> 6848.8556 | AP18: 9
G19: 2019年度 | J19: 一億一千万まで | K19: =I17-K11 -> -68266436 | L19: 12 | M19: =K19/L19 -> -5688869.7 | U19: 7 | V19: 8381268 | Z19: 4085 | AB19: =K7 -> 63022682 | AH19: =K11*0.01908 -> 3422523.6 | AJ19: =AD10+AJ10 -> 0 | AK19: =AE10+AK10 -> 0 | AL19: =AF10+AL10 -> 0 | AM19: =AG10+AM10 -> 0 | AN19: =AH10+AN10 -> 0 | AO19: =AN19/AJ19 -> #DIV/0! | AP19: 10
G20: 91399704 | H20: =K8-K9 -> 45664173 | I20: 945247 | J20: =I20-H20 -> -44718926 | K20: =K11 -> 179377547 | L20: =K20/G20 -> 1.9625616 | M20: =K20-G20 -> 87977843 | Q20: 2050 | U20: 8 | V20: 9209785 | Y20: 3700 | Z20: 3700 | AB20: 63000000 | AJ20: =AD11+AJ11 -> 6269.53 | AK20: =AE11+AK11 -> 7101482 | AL20: =AF11+AL11 -> 654660 | AM20: =AG11+AM11 -> 2482275 | AN20: =AH11+AN11 -> 10238417 | AO20: =AN20/AJ20 -> 1633.0438
E21: =L39/B11 -> 1.1343515 | Q21: 1879 | U21: 9 | V21: 2219201 | Z21: =Z20/Z19 -> 0.90575275 | AB21: =AB20/AB19 -> 0.9996401
E22: =L39-B11 -> 20744979 | Q22: =Q20-Q21 -> 171 | V22: =SUM(V17:V21) -> 28095455
I23: 115000000 | K23: =K11 -> 179377547 | L23: =K23/I23 -> 1.5598048 | N23: =K23*1.1 -> 1.973153e+08 | Z23: 2024 | AA23: サーフィンズ派遣人件費 | AJ23: 2025 | AK23: サーフィンズ派遣人件費 | AU23: 成果
M24: 150000000 | N24: =M24*10/110 -> 13636364 | O24: =M24-N24 -> 1.3636364e+08 | P24: =K11-O24 -> 43013911 | AA24: 日数 | AB24: 労働時間 | AC24: 残業 | AD24: 基本給 | AE24: 交通費 | AF24: 諸手当 | AG24: 報酬合計 | AH24: 時間単価 | AK24: 日数 | AL24: 労働時間 | AM24: 残業 | AN24: 基本給 | AO24: 交通費 | AP24: 諸手当 | AQ24: 報酬合計 | AR24: 時間単価 | AU24: 圧縮時間 | AV24: 圧縮費用 | AX24: 前年比
A25: ■大通りビアガーデン2025実績 | F25: 過去最高 | R25: 200000000 | AA25: 5 | AB25: 579.5 | AC25: 0 | AD25: 956175 | AE25: 89000 | AG25: =AD25+AE25+AF25 -> 1045175 | AH25: =AG25/AB25 -> 1803.5807 | AK25: 2 | AL25: 221.5 | AM25: 0.5 | AN25: 377613 | AO25: 36000 | AQ25: =AN25+AO25+AP25 -> 413613 | AR25: =AQ25/AL25 -> 1867.3273 | AS25: 5 | AU25: =AB25-AL25 -> 358 | AV25: =AQ25-AG25 -> -631562 | AX25: =AQ25/AG25 -> 0.39573564
A26: 推計 | B26: 2019 | C26: ー | D26: 2023 | E26: 2024 | F26: 2006 | G26: 2025 | H26: 2019 | I26: =G20 -> 91399704 | J26: =I29/I26 -> 1.9625616 | K26: =K11-I26 -> 87977843 | R26: =R25/1.1 -> 1.8181818e+08 | AA26: 30 | AB26: 3580.5 | AC26: 7 | AD26: 5939877 | AE26: 545000 | AF26: 1950 | AG26: =AD26+AE26+AF26 -> 6486827 | AH26: =AG26/AB26 -> 1811.7098 | AK26: 30 | AL26: 3156.25 | AM26: 12 | AN26: 5410094 | AO26: 527000 | AQ26: =AN26+AO26+AP26 -> 5937094 | AR26: =AQ26/AL26 -> 1881.0595 | AS26: 6 | AU26: =AB26-AL26 -> 424.25 | AV26: =AQ26-AG26 -> -549733 | AX26: =AQ26/AG26 -> 0.91525394
A27: 来場者数 | B27: 1170000 | D27: 886000 | E27: 902000 | F27: 1523000 | G27: 984000 | H27: 2023 | I27: 114623699 | J27: =I29/I27 -> 1.5649255 | K27: =K11-I27 -> 64753848 | L27: 5187 | M27: 6717 | N27: =M27-L27 -> 1530 | O27: =M27/L27 -> 1.2949682 | AA27: 31 | AB27: 4084.25 | AC27: 32 | AD27: 7019597 | AE27: 583000 | AF27: 13738 | AG27: =AD27+AE27+AF27 -> 7616335 | AH27: =AG27/AB27 -> 1864.8063 | AK27: 31 | AL27: 3671.25 | AM27: 50.25 | AN27: 6544024 | AO27: 573000 | AQ27: =AN27+AO27+AP27 -> 7117024 | AR27: =AQ27/AL27 -> 1938.5833 | AS27: 7 | AU27: =AB27-AL27 -> 413 | AV27: =AQ27-AG27 -> -499311 | AX27: =AQ27/AG27 -> 0.93444209
A28: 前年比 | B28: - | D28: 75.8 | E28: 101.8 | F28: =F27/E27 -> 1.6884701 | G28: 109.1 | H28: 2024 | I28: 139791210 | J28: =I29/I28 -> 1.2831819 | L28: 992 | M28: 1941 | N28: =M28-L28 -> 949 | O28: =M28/L28 -> 1.9566532 | AA28: 31 | AB28: 4444 | AC28: 39 | AD28: 7728270 | AE28: 633000 | AF28: 11262 | AG28: =AD28+AE28+AF28 -> 8372532 | AH28: =AG28/AB28 -> 1884.0081 | AK28: 31 | AL28: 3768 | AM28: 46.5 | AN28: 6814246 | AO28: 590000 | AQ28: =AN28+AO28+AP28 -> 7404246 | AR28: =AQ28/AL28 -> 1965.0334 | AS28: 8 | AU28: =AB28-AL28 -> 676 | AV28: =AQ28-AG28 -> -968286 | AX28: =AQ28/AG28 -> 0.88434968
A29: ビール消費量（L） | B29: 441456 | D29: 334182 | E29: 340050 | F29: 574842 | G29: 371111 | H29: 2025 | I29: =K11 -> 179377547 | L29: 318 | M29: 2503 | N29: =M29-L29 -> 2185 | O29: =M29/L29 -> 7.8710692 | AA29: 8 | AB29: 1063 | AC29: 2 | AD29: 1866106 | AE29: 150000 | AF29: 1350 | AG29: =AD29+AE29+AF29 -> 2017456 | AH29: =AG29/AB29 -> 1897.889 | AK29: 15 | AL29: 1633.5 | AM29: 23 | AN29: 2993112 | AO29: 262000 | AQ29: =AN29+AO29+AP29 -> 3255112 | AR29: =AQ29/AL29 -> 1992.7224 | AS29: 9 | AU29: =AB29-AL29 -> -570.5 | AV29: =AQ29-AG29 -> 1237656 | AX29: =AQ29/AG29 -> 1.6134736
A30: 前年比 | B30: - | D30: 75.7 | E30: =E29/D29 -> 1.0175593 | F30: =F29/E29 -> 1.6904632 | G30: =G29/E29 -> 1.0913424 | H30: =G29/B29 -> 0.8406523 | L30: =SUM(L27:L29) -> 6497 | M30: =SUM(M27:M29) -> 11161 | N30: =SUM(N27:N29) -> 4664 | O30: =M30/L30 -> 1.7178698 | AG30: =AD30+AE30 -> 0 | AH30: =AG30/AB30 -> #DIV/0! | AQ30: =AN30+AO30 -> 0 | AR30: =AQ30/AL30 -> #DIV/0! | AS30: 10 | AU30: =AB30-AL30 -> 0 | AV30: =AQ30-AG30 -> 0 | AX30: =AQ30/AG30 -> #DIV/0!
A31: 20L樽本数 | B31: =B29/20 -> 22072.8 | D31: =D29/20 -> 16709.1 | E31: =E29/20 -> 17002.5 | F31: =F29/20 -> 28742.1 | G31: =G29/20 -> 18555.55 | J31: 2025 | K31: 期間 | L31: 売上 | M31: 値引き | N31: 税抜売上 | O31: 税込売上 | P31: 値引き | Q31: 税込売上合計 | R31: 日数 | T31: 前年比 | U31: 前年差異 | AA31: =SUM(AA24:AA30) -> 105 | AB31: =SUM(AB24:AB30) -> 13751.25 | AC31: =SUM(AC24:AC30) -> 80 | AD31: =SUM(AD24:AD30) -> 23510025 | AE31: =SUM(AE24:AE30) -> 2000000 | AG31: =SUM(AG24:AG30) -> 25538325 | AH31: =AG31/AB31 -> 1857.1639 | AK31: =SUM(AK24:AK30) -> 109 | AL31: =SUM(AL24:AL30) -> 12450.5 | AM31: =SUM(AM24:AM30) -> 132.25 | AN31: =SUM(AN24:AN30) -> 22139089 | AO31: =SUM(AO24:AO30) -> 1988000 | AQ31: =SUM(AQ24:AQ30) -> 24127089 | AR31: =AQ31/AL31 -> 1937.841 | AU31: =AB31-AL31 -> 1300.75 | AV31: =AQ31-AG31 -> -1411236 | AX31: =AQ31/AG31 -> 0.94474046
A32: 前年比 | D32: =D31/B31 -> 0.75699957 | E32: =E31/D31 -> 1.0175593 | F32: =F31/E31 -> 1.6904632 | G32: =G31/E31 -> 1.0913424 | H32: =G31/B31 -> 0.8406523 | J32: 4~5 | K32: ピコレ4/26-5/18 | L32: =2523773+490136 -> 3013909 | M32: =P32/1.1 -> 0 | N32: =L32-M32 -> 3013909 | O32: =2683110+539150 -> 3222260 | Q32: =O32-P32 -> 3222260 | R32: 23 | T32: =L32/L44 -> 1.0253058 | U32: =L32-L44 -> 74387
A33: ビール原価金額 | B33: =B31*9000 -> 198655200 | C33: 原価率想定 | D33: =D31*9000 -> 150381900 | E33: =E31*9700 -> 164924250 | F33: =F31*9000 -> 258678900 | G33: =G31*10000 -> 185555500 | J33: 5 | K33: ビアガ5/30-5/31 | L33: 2588445 | N33: =L33-M33 -> 2588445 | O33: 2847290 | Q33: =O33-P33 -> 2847290 | R33: 2 | T33: =L33/L45 -> 5.4173442 | U33: =L33-L45 -> 2110638 | X33: 133 | Y33: 326 | AJ33: 時間単価 | AK33: 人件費 | AL33: 時間数 | AN33: 時間単価 | AO33: 人件費 | AP33: 時間数
A34: ビール売上推定金額 | B34: =B33*3.5 -> 695293200 | C34: =B33/B34 -> 0.28571429 | D34: =D33*3.5 -> 526336650 | E34: =E33*3.5 -> 577234875 | F34: =F33*3.5 -> 905376150 | G34: =G33*3.5 -> 649444250 | J34: 6 | K34: ビアガフル | L34: 33132365 | N34: =L34-M34 -> 33132365 | O34: 36445602 | Q34: =O34-P34 -> 36445602 | R34: 30 | T34: =L34/L46 -> 1.7282846 | U34: =L34-L46 -> 13961700 | X34: 5144 | Y34: 8280 | AJ34: 1900 | AK34: 35000000 | AL34: =AK34/AJ34 -> 18421.053 | AN34: 1900 | AO34: =AN34*AP34 -> 34999900 | AP34: 18421
A35: ひとり当たりのビール購入額 | B35: =B34/B27 -> 594.26769 | C35: =C34/C27 -> #DIV/0! | D35: =D34/D27 -> 594.05942 | E35: =E34/E27 -> 639.94997 | F35: =F34/F27 -> 594.46891 | G35: =G34/G27 -> 660.00432 | J35: 7 | K35: ビアガフル | L35: 63022682 | N35: =L35-M35 -> 63022682 | O35: 69324950 | Q35: =O35-P35 -> 69324950 | R35: 31 | T35: =L35/L47 -> 1.3240597 | U35: =L35-L47 -> 15424615 | X35: 11558 | Y35: 14790 | AJ35: 1560 | AK35: 35000000 | AL35: =AK35/AJ35 -> 22435.897 | AN35: 1560 | AO35: =AN35*AP35 -> 28736760 | AP35: 18421
A36: 客単価想定 | B36: 1300 | D36: 1300 | E36: 1300 | F36: 1300 | G36: 1300 | J36: 8 | K36: ビアガフル | L36: 61443318 | N36: =L36-M36 -> 61443318 | O36: 67721890 | Q36: =O36-P36 -> 67721890 | R36: 31 | T36: =L36/L48 -> 1.0997439 | U36: =L36-L48 -> 5572748 | X36: 13891 | Y36: 14547 | AO36: =AO34-AO35 -> 6263140
A37: 推定売上額 | B37: =B27*B36 -> 1521000000 | D37: =D27*D36 -> 1151800000 | E37: =E27*E36 -> 1172600000 | F37: =F27*F36 -> 1979900000 | G37: =G27*G36 -> 1279200000 | J37: 9 | K37: ビアガ9/1-9/15 | L37: 14966464 | N37: =L37-M37 -> 14966464 | O37: 16463110 | Q37: =O37-P37 -> 16463110 | R37: 15 | T37: =L37/L49 -> 1.6975262 | U37: =L37-L49 -> 6149832 | X37: 3606 | Y37: 3286
G38: =G37/E37 -> 1.0909091 | H38: =G37/B37 -> 0.84102564 | J38: 9~10 | K38: ピコレ | L38: =812682+397682 -> 1210364 | N38: =L38-M38 -> 1210364 | O38: =893950+437450 -> 1331400 | Q38: =O38-P38 -> 1331400 | R38: 16 | T38: =L38/L50 -> 0.2429066 | U38: =L38-L50 -> -3772473
K39: ビアガのみ109日 | L39: =L34+L33+L35+L36+L37 -> 175153274 | M39: =M34+M33+M35+M36+M37 -> 0 | N39: =N34+N33+N35+N36+N37 -> 175153274 | O39: =O34+O33+O35+O36+O37 -> 192802842 | P39: =P34+P33+P35+P36+P37 -> 0 | Q39: =Q34+Q33+Q35+Q36+Q37 -> 192802842 | R39: =R34+R33+R35+R36+R37 -> 109 | T39: =L39/L51 -> 1.3275851 | U39: =L39-L51 -> 43219533
K40: ピコレ春・秋 | L40: =L32+L38 -> 4224273 | M40: =M32+M38 -> 0 | N40: =N32+N38 -> 4224273 | O40: =O32+O38 -> 4553660 | P40: =P32+P38 -> 0 | Q40: =Q32+Q38 -> 4553660 | R40: =R32+R38 -> 39 | T40: =L40/L52 -> 0.53320898 | U40: =L40-L52 -> -3698086 | X40: =SUM(X33:X39) -> 34332 | Y40: =SUM(Y33:Y39) -> 41229 | Z40: =Y40/X40 -> 1.2008913
K41: 総合計 | L41: =SUM(L32:L38) -> 179377547 | M41: =SUM(M32:M38) -> 0 | N41: =SUM(N32:N38) -> 179377547 | O41: =SUM(O32:O38) -> 197356502 | P41: =SUM(P32:P38) -> 0 | Q41: =SUM(Q32:Q38) -> 197356502 | R41: =SUM(R32:R38) -> 148 | T41: =L41/L53 -> 1.2825865 | U41: =L41-L53 -> 39521447
B42: BEV売上 | C42: 仕入れ | D42: 仕入れコスト
A43: 4 | B43: 174682 | D43: =C43/B43 -> 0 | J43: 2024 | K43: 期間 | L43: 売上 | M43: 値引き | N43: 税抜売上 | O43: 税込売上 | P43: 値引き | Q43: 税込売上合計
A44: 5 | B44: 1908727 | C44: 1309283 | D44: =C44/B44 -> 0.68594566 | J44: 4~5 | K44: ピコレ4/27-5/19 | L44: 2939522 | M44: 4040 | N44: =L44-M44 -> 2935482 | O44: 539150 | P44: 4040 | Q44: =O44-P44 -> 535110 | R44: 23 | U44: =L41-V52 -> 38571187
A45: 6 | B45: 11797227 | C45: 5356956 | D45: =C45/B45 -> 0.45408603 | J45: 5 | K45: ビアガ5/27-5/31 | L45: 477807 | M45: 3480 | N45: =L45-M45 -> 474327 | O45: 525570 | P45: 3480 | Q45: =O45-P45 -> 522090 | R45: 5 | S45: 506 | U45: =L41/V52 -> 1.2739307
A46: 7 | B46: 21547545 | C46: 10253393 | D46: =C46/B46 -> 0.47584971 | J46: 6 | K46: ビアガフル | L46: 19170665 | M46: 26790 | N46: =L46-M46 -> 19143875 | O46: 21087090 | P46: 26790 | Q46: =O46-P46 -> 21060300 | R46: 30 | S46: 5309
A47: 8 | B47: 20699455 | C47: 8588143 | D47: =C47/B47 -> 0.41489706 | J47: 7 | K47: ビアガフル | L47: 47598067 | M47: 17800 | N47: =L47-M47 -> 47580267 | O47: 52356880 | P47: 17800 | Q47: =O47-P47 -> 52339080 | R47: 31 | S47: 11036
A48: 9 | B48: 5433727 | C48: 2181339 | D48: =C48/B48 -> 0.40144435 | J48: 8 | K48: ビアガフル | L48: 55870570 | M48: 5980 | N48: =L48-M48 -> 55864590 | O48: 61456496 | P48: 5980 | Q48: =O48-P48 -> 61450516 | R48: 31 | S48: 11093
A49: 10 | B49: 174136 | D49: =C49/B49 -> 0 | J49: 9 | K49: ビアガ9/1-9/8 | L49: 8816632 | M49: 5700 | N49: =L49-M49 -> 8810932 | O49: 9698100 | P49: 5700 | Q49: =O49-P49 -> 9692400 | R49: 8 | S49: 263
B50: =SUM(B43:B49) -> 61735499 | C50: =SUM(C43:C49) -> 27689114 | D50: =C50/B50 -> 0.44851203 | J50: 9~10 | K50: ピコレ共催アキノジン | L50: 4982837 | M50: 1100 | N50: =L50-M50 -> 4981737 | O50: 5480760 | P50: 1100 | Q50: =O50-P50 -> 5479660 | R50: 23
K51: ビアガのみ105日 | L51: =L46+L45+L47+L48+L49 -> 131933741 | M51: =M46+M45+M47+M48+M49 -> 59750 | N51: =N46+N45+N47+N48+N49 -> 131873991 | O51: =O46+O45+O47+O48+O49 -> 145124136 | P51: =P46+P45+P47+P48+P49 -> 59750 | Q51: =Q46+Q45+Q47+Q48+Q49 -> 145064386 | R51: =R46+R45+R47+R48+R49 -> 105
K52: ピコレ&ピコレ共催 | L52: =L44+L50 -> 7922359 | M52: =M44+M50 -> 5140 | N52: =N44+N50 -> 7917219 | O52: =O44+O50 -> 6019910 | P52: =P44+P50 -> 5140 | Q52: =Q44+Q50 -> 6014770 | R52: =R44+R50 -> 46 | U52: 未食処理2024 | V52: 140806360 | W52: 本実績
K53: 総合計 | L53: =SUM(L44:L50) -> 139856100 | M53: =SUM(M44:M50) -> 64890 | N53: =SUM(N44:N50) -> 139791210 | O53: =SUM(O44:O50) -> 151144046 | P53: =SUM(P44:P50) -> 64890 | Q53: =SUM(Q44:Q50) -> 151079156 | R53: =SUM(R44:R50) -> 151 | U53: 953704 | V53: =N53+U53 -> 140744914
K54: ビアガ＋秋ピコレ | L54: =L50+L51 -> 136916578 | N54: =N50+N51 -> 136855728 | O54: =O50+O51 -> 150604896 | Q54: =Q50+Q51 -> 150544046 | R54: =R50+R51 -> 128 | V54: =V52-V53 -> 61446
J55: 2023 | K55: 期間 | L55: 売上 | M55: 値引き | N55: 税抜売上 | O55: 税込売上 | P55: 値引き | Q55: 税込売上合計
J56: 4~5 | K56: ピコレ参戦なし | N56: =L56-M56 -> 0 | Q56: =O56-P56 -> 0 | R56: 0
J57: 5 | K57: ビアガ5/27-5/31 | L57: =O57/1.1 -> 1795227.3 | N57: =L57-M57 -> 1795227.3 | O57: 1974750 | Q57: =O57-P57 -> 1974750 | R57: 5 | S57: 506
J58: 6 | K58: ビアガフル | L58: =O58/1.1 -> 19049727 | N58: =L58-M58 -> 19049727 | O58: 20954700 | Q58: =O58-P58 -> 20954700 | R58: 30 | S58: 5309
J59: 7 | K59: ビアガフル | L59: =O59/1.1 -> 44856909 | N59: =L59-M59 -> 44856909 | O59: 49342600 | Q59: =O59-P59 -> 49342600 | R59: 31 | S59: 11036
J60: 8 | K60: ビアガフル | L60: =O60/1.1 -> 44860591 | N60: =L60-M60 -> 44860591 | O60: 49346650 | Q60: =O60-P60 -> 49346650 | R60: 31 | S60: 11093
J61: 9 | K61: ビアガ9/1-9/3 | L61: =O61/1.1 -> 8816454.5 | N61: =L61-M61 -> 8816454.5 | O61: 9698100 | Q61: =O61-P61 -> 9698100 | R61: 3 | S61: 263
J62: 9~10 | K62: ピコレ | L62: 1487994 | N62: =L62-M62 -> 1487994 | O62: 1636793 | P62: 4040 | Q62: =O62-P62 -> 1632753 | R62: 0
K63: ビアガのみ105日 | L63: =L58+L57+L59+L60+L61 -> 1.1937891e+08 | M63: =M58+M57+M59+M60+M61 -> 0 | N63: =N58+N57+N59+N60+N61 -> 1.1937891e+08 | O63: =O58+O57+O59+O60+O61 -> 131316800 | P63: =P58+P57+P59+P60+P61 -> 0 | Q63: =Q58+Q57+Q59+Q60+Q61 -> 131316800 | R63: =R58+R57+R59+R60+R61 -> 100
K64: ピコレ&ピコレ共催 | L64: =L56+L62 -> 1487994 | M64: =M56+M62 -> 0 | N64: =N56+N62 -> 1487994 | O64: =O56+O62 -> 1636793 | P64: =P56+P62 -> 4040 | Q64: =Q56+Q62 -> 1632753 | R64: =R56+R62 -> 0
K65: 総合計 | L65: =SUM(L56:L62) -> 1.208669e+08 | M65: =SUM(M56:M62) -> 0 | N65: =SUM(N56:N62) -> 1.208669e+08 | O65: =SUM(O56:O62) -> 132953593 | P65: =SUM(P56:P62) -> 4040 | Q65: =SUM(Q56:Q62) -> 132949553 | R65: =SUM(R56:R62) -> 100

Sheet 予約&フリー実績
A1: 年度別予約実績

Sheet 2025.10月実績付与済 
A1: ■R7年度 ピコレ＆ビアガーデン売上予測 | CB1: ç
A2: 8月 | C2: 営業日数 | F2: 31 | G2: 平日 | J2: 3 | K2: 休日・祝日 | O2: 0 | P2: 席数 | Q2: 240 | AA2: 営業日数 | AD2: 3 | AE2: 平日 | AH2: 0 | AI2: 休日・祝日 | AN2: 席数 | AO2: 240 | BJ2: 31 | BL2: 席数 | BO2: 240 | CE2: =CE14+CE24+CE34+CE44+CE54+CE64 -> 437450 | CK2: 31
A3: FOOD予測 | C3: 施策・企画・イベント | Y3: BEV予測 | AA3: 施策・企画・イベント | AW3: ビアガーデン10月 予測TOTAL | BN3: 客数 | BO3: 売上 | BV3: 2025 ピコレ10月 TOTAL実績 9/20-10/5までの15日開催 | CG3: 客数 | CK3: 売上
A4: 予算 | C4: 客数 | D4: 13000 | E4: 料理単価 | N4: 売上 | O4: =D4*L4 -> 0 | Y4: 予算 | AA4: 客数 | AB4: =D4 -> 13000 | AC4: 飲料単価 | AL4: 売上 | AM4: =AB4*AJ4 -> 0 | AW4: 予算 | AY4: 客数 | BI4: 客単価 | BK4: 売上 | BM4: 1日平均 | BN4: =BH4/BJ2 -> 0 | BO4: =BL4/BJ2 -> 0 | BV4: 実績 | BX4: 客数 | BZ4: 客単価 | CB4: 売上予算 | CF4: 1日平均 | CG4: オータムフェスト9/12-10/4 | CK4: =CE4/CK2 -> 0 | CM4: 天候要因（売上との関連性を数値化する） | DA4: 天候要因（売上との関連性を数値化する）
A5: 1st week | Y5: 1st week | AW5: 1st week | BV5: 1st week | CM5: =BV5 -> 1st week | DA5: =CM5 -> 1st week
A6: 曜日 | B6: 日にち | C6: 客数 | D6: MENU A 出卓 | E6: 売上 | F6: MENU B 出卓 | G6: 売上 | H6: MENU C 出卓 | I6: 売上 | J6: アラカルト利用数 | K6: 売上 | L6: 料理売上 | M6: 料理単価 | N6: モデルシフト | O6: モデルシフト時間数 | P6: 実時間数 | Q6: 人時売上高 | T6: A | U6: B | V6: C | W6: カルト | Y6: 曜日 | Z6: 日にち | AA6: 客数 | AB6: MENU A 出卓 | AC6: 売上 | AD6: MENU B 出卓 | AE6: 売上 | AF6: MENU C 出卓 | AG6: 売上 | AH6: アラカルト利用数 | AI6: 売上 | AJ6: 飲料売上 | AK6: 飲料単価 | AL6: モデルシフト | AM6: モデルシフト時間数 | AN6: 実時間数 | AO6: 人時売上高 | AR6: A | AS6: B | AT6: C | AU6: S | AW6: 曜日 | AX6: 日にち | AY6: 客数 | AZ6: MENU A 出卓 | BA6: 売上 | BB6: MENU B 出卓 | BC6: 売上 | BD6: MENU C 出卓 | BE6: 売上 | BF6: MENU S 出卓 | BG6: 売上 | BH6: 料理売上 | BI6: 料理単価 | BJ6: 飲料売上 | BK6: 飲料単価 | BL6: 合計売上予測 | BM6: 合計単価 | BO6: 人時売上高予測 | BR6: A | BS6: B | BT6: C | BU6: S | BV6: 曜日 | BW6: 日にち | BX6: 客数 | BY6: 料理売上 | BZ6: 料理単価 | CA6: 飲料売上 | CB6: 飲料単価 | CC6: その他売上 | CD6: 物販 | CE6: 売上合計 | CF6: 合計単価 | CG6: サーフィンズ | CH6: forking | CI6: Timee | CJ6: 合計 | CK6: 人時売上高 | CM6: 最低 | CN6: 最高 | CO6: 12時 | CP6: 15時 | CQ6: 18時 | CR6: Ave | CT6: ■天候要因 | CV6: 評価点 | DA6: 最低 | DB6: 最高 | DC6: 12時 | DD6: 15時 | DE6: 18時 | DF6: Ave | DH6: ■天候要因 | DJ6: 評価点
A7: 日 | C7: =D7+F7+H7+J7 -> 0 | E7: =D7*T7 -> 0 | G7: =F7*U7 -> 0 | I7: =H7*V7 -> 0 | K7: =J7*W7 -> 0 | L7: =E7+G7+I7+K7 -> 0 | M7: =L7/C7 -> #DIV/0! | Q7: =L7/P7 -> #DIV/0! | T7: 3300 | U7: 3800 | V7: 4800 | W7: 2000 | Y7: 日 | Z7: =B7 -> 0 | AA7: =AB7+AD7+AF7+AH7 -> 0 | AB7: =D7 -> 0 | AC7: =AB7*AR7 -> 0 | AD7: =F7 -> 0 | AE7: =AD7*AS7 -> 0 | AF7: =H7 -> 0 | AG7: =AF7*AT7 -> 0 | AH7: =J7 -> 0 | AI7: =AH7*AU7 -> 0 | AJ7: =AC7+AE7+AG7+AI7 -> 0 | AK7: =AJ7/AA7 -> #DIV/0! | AL7: =N7 -> 0 | AM7: =O7 -> 0 | AN7: =P7 -> 0 | AO7: =(AJ7+BH7)/AN7 -> #DIV/0! | AR7: 1700 | AS7: 2200 | AT7: 2200 | AU7: 1400 | AW7: 日 | AX7: =B7 -> 0 | AY7: =C7 -> 0 | BA7: =AZ7*BR7 -> 0 | BC7: =BB7*BS7 -> 0 | BE7: =BD7*BT7 -> 0 | BG7: =BF7*BU7 -> 0 | BH7: =L7 -> 0 | BI7: =M7 -> #DIV/0! | BJ7: =AJ7 -> 0 | BK7: =AK7 -> #DIV/0! | BL7: =BH7+BJ7 -> 0 | BM7: =BI7+BK7 -> #DIV/0! | BO7: =Q7+AO7 -> #DIV/0! | BV7: 日 | BW7: =AX7 -> 0 | BZ7: =BY7/BX7 -> #DIV/0! | CB7: =CA7/BX7 -> #DIV/0! | CE7: =BY7+CA7+CC7+CD7 -> 0 | CF7: =CE7/BX7 -> #DIV/0! | CJ7: =SUM(CG7:CI7) -> 0 | CK7: =CE7/CJ7 -> #DIV/0! | CR7: =SUM(CO7:CQ7)/3 -> 0 | CT7: 晴れ（33度まで） | CV7: 5 | DA7: 18.3 | DB7: 29 | DC7: 5 | DD7: 5 | DE7: 3 | DF7: =SUM(DC7:DE7)/3 -> 4.3333333 | DH7: 晴れ（33度まで） | DJ7: 5 | DO7: 1
A8: 月 | C8: =D8+F8+H8+J8 -> 0 | E8: =D8*T8 -> 0 | G8: =F8*U8 -> 0 | I8: =H8*V8 -> 0 | K8: =J8*W8 -> 0 | L8: =E8+G8+I8+K8 -> 0 | M8: =L8/C8 -> #DIV/0! | Q8: =L8/P8 -> #DIV/0! | T8: 3300 | U8: 3800 | V8: 4800 | W8: 2000 | Y8: 月 | Z8: =B8 -> 0 | AA8: =AB8+AD8+AF8+AH8 -> 0 | AB8: =D8 -> 0 | AC8: =AB8*AR8 -> 0 | AD8: =F8 -> 0 | AE8: =AD8*AS8 -> 0 | AF8: =H8 -> 0 | AG8: =AF8*AT8 -> 0 | AH8: =J8 -> 0 | AI8: =AH8*AU8 -> 0 | AJ8: =AC8+AE8+AG8+AI8 -> 0 | AK8: =AJ8/AA8 -> #DIV/0! | AL8: =N8 -> 0 | AM8: =O8 -> 0 | AN8: =P8 -> 0 | AO8: =(AJ8+BH8)/AN8 -> #DIV/0! | AR8: 1700 | AS8: 2200 | AT8: 2200 | AU8: 1400 | AW8: 月 | AX8: =B8 -> 0 | AY8: =C8 -> 0 | AZ8: 22 | BA8: =AZ8*BR8 -> 0 | BB8: 10 | BC8: =BB8*BS8 -> 0 | BD8: 6 | BE8: =BD8*BT8 -> 0 | BG8: =BF8*BU8 -> 0 | BH8: =L8 -> 0 | BI8: =M8 -> #DIV/0! | BJ8: =AJ8 -> 0 | BK8: =AK8 -> #DIV/0! | BL8: =BH8+BJ8 -> 0 | BM8: =BI8+BK8 -> #DIV/0! | BO8: =Q8+AO8 -> #DIV/0! | BV8: 月 | BW8: =AX8 -> 0 | BZ8: =BY8/BX8 -> #DIV/0! | CB8: =CA8/BX8 -> #DIV/0! | CE8: =BY8+CA8+CC8+CD8 -> 0 | CF8: =CE8/BX8 -> #DIV/0! | CJ8: =SUM(CG8:CI8) -> 0 | CK8: =CE8/CJ8 -> #DIV/0! | CM8: 22 | CN8: 27.7 | CO8: 3 | CP8: 1 | CQ8: 1 | CR8: =SUM(CO8:CQ8)/3 -> 1.6666667 | CT8: 晴れ（25度以下） | CV8: 4 | DA8: 18.8 | DB8: 27 | DC8: 3 | DD8: 3 | DE8: 1 | DF8: =SUM(DC8:DE8)/3 -> 2.3333333 | DH8: 晴れ（25度以下） | DJ8: 4 | DO8: 2
A9: 火 | C9: =D9+F9+H9+J9 -> 0 | E9: =D9*T9 -> 0 | G9: =F9*U9 -> 0 | I9: =H9*V9 -> 0 | K9: =J9*W9 -> 0 | L9: =E9+G9+I9+K9 -> 0 | M9: =L9/C9 -> #DIV/0! | Q9: =L9/P9 -> #DIV/0! | T9: 3300 | U9: 3800 | V9: 4800 | W9: 2000 | Y9: 火 | Z9: =B9 -> 0 | AA9: =AB9+AD9+AF9+AH9 -> 0 | AB9: =D9 -> 0 | AC9: =AB9*AR9 -> 0 | AD9: =F9 -> 0 | AE9: =AD9*AS9 -> 0 | AF9: =H9 -> 0 | AG9: =AF9*AT9 -> 0 | AH9: =J9 -> 0 | AI9: =AH9*AU9 -> 0 | AJ9: =AC9+AE9+AG9+AI9 -> 0 | AK9: =AJ9/AA9 -> #DIV/0! | AL9: =N9 -> 0 | AM9: =O9 -> 0 | AN9: =P9 -> 0 | AO9: =(AJ9+BH9)/AN9 -> #DIV/0! | AR9: 1700 | AS9: 2200 | AT9: 2200 | AU9: 1400 | AW9: 火 | AX9: =B9 -> 0 | AY9: =C9 -> 0 | AZ9: 22 | BA9: =AZ9*BR9 -> 0 | BB9: 10 | BC9: =BB9*BS9 -> 0 | BD9: 6 | BE9: =BD9*BT9 -> 0 | BG9: =BF9*BU9 -> 0 | BH9: =L9 -> 0 | BI9: =M9 -> #DIV/0! | BJ9: =AJ9 -> 0 | BK9: =AK9 -> #DIV/0! | BL9: =BH9+BJ9 -> 0 | BM9: =BI9+BK9 -> #DIV/0! | BO9: =Q9+AO9 -> #DIV/0! | BV9: 火 | BW9: =AX9 -> 0 | BZ9: =BY9/BX9 -> #DIV/0! | CB9: =CA9/BX9 -> #DIV/0! | CE9: =BY9+CA9+CC9+CD9 -> 0 | CF9: =CE9/BX9 -> #DIV/0! | CJ9: =SUM(CG9:CI9) -> 0 | CK9: =CE9/CJ9 -> #DIV/0! | CM9: 22.2 | CN9: 24.3 | CO9: 1 | CP9: 2 | CQ9: 1 | CR9: =SUM(CO9:CQ9)/3 -> 1.3333333 | CT9: 晴れ（33度以上）曇25度以上 | CV9: 3 | DA9: 18.2 | DB9: 27.8 | DC9: 5 | DD9: 5 | DE9: 5 | DF9: =SUM(DC9:DE9)/3 -> 5 | DH9: 晴れ（33度以上）曇25度以上 | DJ9: 3 | DO9: 3
A10: 水 | B10: 1 | C10: =D10+F10+H10+J10 -> 0 | E10: =D10*T10 -> 0 | G10: =F10*U10 -> 0 | I10: =H10*V10 -> 0 | K10: =J10*W10 -> 0 | L10: =E10+G10+I10+K10 -> 0 | M10: =L10/C10 -> #DIV/0! | Q10: =L10/P10 -> #DIV/0! | T10: 3300 | U10: 3800 | V10: 4800 | W10: 2000 | Y10: 水 | Z10: =B10 -> 1 | AA10: =AB10+AD10+AF10+AH10 -> 0 | AB10: =D10 -> 0 | AC10: =AB10*AR10 -> 0 | AD10: =F10 -> 0 | AE10: =AD10*AS10 -> 0 | AF10: =H10 -> 0 | AG10: =AF10*AT10 -> 0 | AH10: =J10 -> 0 | AI10: =AH10*AU10 -> 0 | AJ10: =AC10+AE10+AG10+AI10 -> 0 | AK10: =AJ10/AA10 -> #DIV/0! | AL10: =N10 -> 0 | AM10: =O10 -> 0 | AN10: =P10 -> 0 | AO10: =(AJ10+BH10)/AN10 -> #DIV/0! | AR10: 1700 | AS10: 2200 | AT10: 2200 | AU10: 1400 | AW10: 水 | AX10: =B10 -> 1 | AY10: =C10 -> 0 | AZ10: 10 | BA10: =AZ10*BR10 -> 0 | BB10: 24 | BC10: =BB10*BS10 -> 0 | BD10: 12 | BE10: =BD10*BT10 -> 0 | BG10: =BF10*BU10 -> 0 | BH10: =L10 -> 0 | BI10: =M10 -> #DIV/0! | BJ10: =AJ10 -> 0 | BK10: =AK10 -> #DIV/0! | BL10: =BH10+BJ10 -> 0 | BM10: =BI10+BK10 -> #DIV/0! | BO10: =Q10+AO10 -> #DIV/0! | BV10: 水 | BW10: =AX10 -> 1 | BX10: 35 | BY10: 25200 | BZ10: =BY10/BX10 -> 720 | CA10: 14950 | CB10: =CA10/BX10 -> 427.14286 | CE10: =BY10+CA10+CC10+CD10 -> 40150 | CF10: =CE10/BX10 -> 1147.1429 | CJ10: =SUM(CG10:CI10) -> 0 | CK10: =CE10/CJ10 -> #DIV/0! | CM10: 21.1 | CN10: 27.3 | CO10: 5 | CP10: 5 | CQ10: 5 | CR10: =SUM(CO10:CQ10)/3 -> 5 | CT10: 曇 | CV10: 2 | DA10: 16.8 | DB10: 28.6 | DC10: 5 | DD10: 5 | DE10: 5 | DF10: =SUM(DC10:DE10)/3 -> 5 | DH10: 曇 | DJ10: 2 | DO10: 4
A11: 木 | B11: 2 | C11: =D11+F11+H11+J11 -> 0 | E11: =D11*T11 -> 0 | G11: =F11*U11 -> 0 | I11: =H11*V11 -> 0 | K11: =J11*W11 -> 0 | L11: =E11+G11+I11+K11 -> 0 | M11: =L11/C11 -> #DIV/0! | Q11: =L11/P11 -> #DIV/0! | T11: 3300 | U11: 3800 | V11: 4800 | W11: 2000 | Y11: 木 | Z11: =B11 -> 2 | AA11: =AB11+AD11+AF11+AH11 -> 0 | AB11: =D11 -> 0 | AC11: =AB11*AR11 -> 0 | AD11: =F11 -> 0 | AE11: =AD11*AS11 -> 0 | AF11: =H11 -> 0 | AG11: =AF11*AT11 -> 0 | AH11: =J11 -> 0 | AI11: =AH11*AU11 -> 0 | AJ11: =AC11+AE11+AG11+AI11 -> 0 | AK11: =AJ11/AA11 -> #DIV/0! | AL11: =N11 -> 0 | AM11: =O11 -> 0 | AN11: =P11 -> 0 | AO11: =(AJ11+BH11)/AN11 -> #DIV/0! | AR11: 1700 | AS11: 2200 | AT11: 2200 | AU11: 1400 | AW11: 木 | AX11: =B11 -> 2 | AY11: =C11 -> 0 | AZ11: 10 | BA11: =AZ11*BR11 -> 0 | BB11: 24 | BC11: =BB11*BS11 -> 0 | BD11: 12 | BE11: =BD11*BT11 -> 0 | BG11: =BF11*BU11 -> 0 | BH11: =L11 -> 0 | BI11: =M11 -> #DIV/0! | BJ11: =AJ11 -> 0 | BK11: =AK11 -> #DIV/0! | BL11: =BH11+BJ11 -> 0 | BM11: =BI11+BK11 -> #DIV/0! | BO11: =Q11+AO11 -> #DIV/0! | BV11: 木 | BW11: =AX11 -> 2 | BX11: 43 | BY11: 36900 | BZ11: =BY11/BX11 -> 858.13953 | CA11: 26900 | CB11: =CA11/BX11 -> 625.5814 | CE11: =BY11+CA11+CC11+CD11 -> 63800 | CF11: =CE11/BX11 -> 1483.7209 | CJ11: =SUM(CG11:CI11) -> 0 | CK11: =CE11/CJ11 -> #DIV/0! | CM11: 17.8 | CN11: 28.2 | CO11: 5 | CP11: 3 | CQ11: 3 | CR11: =SUM(CO11:CQ11)/3 -> 3.6666667 | CT11: 雨 | CV11: 1 | DA11: 20.4 | DB11: 27.6 | DC11: 3 | DD11: 3 | DE11: 3 | DF11: =SUM(DC11:DE11)/3 -> 3 | DH11: 雨 | DJ11: 1 | DO11: 5
A12: 金 | B12: 3 | C12: =D12+F12+H12+J12 -> 0 | E12: =D12*T12 -> 0 | G12: =F12*U12 -> 0 | I12: =H12*V12 -> 0 | K12: =J12*W12 -> 0 | L12: =E12+G12+I12+K12 -> 0 | M12: =L12/C12 -> #DIV/0! | Q12: =L12/P12 -> #DIV/0! | T12: 3300 | U12: 3800 | V12: 4800 | W12: 2000 | Y12: 金 | Z12: =B12 -> 3 | AA12: =AB12+AD12+AF12+AH12 -> 0 | AB12: =D12 -> 0 | AC12: =AB12*AR12 -> 0 | AD12: =F12 -> 0 | AE12: =AD12*AS12 -> 0 | AF12: =H12 -> 0 | AG12: =AF12*AT12 -> 0 | AH12: =J12 -> 0 | AI12: =AH12*AU12 -> 0 | AJ12: =AC12+AE12+AG12+AI12 -> 0 | AK12: =AJ12/AA12 -> #DIV/0! | AL12: =N12 -> 0 | AM12: =O12 -> 0 | AN12: =P12 -> 0 | AO12: =(AJ12+BH12)/AN12 -> #DIV/0! | AR12: 1700 | AS12: 2200 | AT12: 2200 | AU12: 1400 | AW12: 金 | AX12: =B12 -> 3 | AY12: =C12 -> 0 | AZ12: 10 | BA12: =AZ12*BR12 -> 0 | BB12: 24 | BC12: =BB12*BS12 -> 0 | BD12: 12 | BE12: =BD12*BT12 -> 0 | BG12: =BF12*BU12 -> 0 | BH12: =L12 -> 0 | BI12: =M12 -> #DIV/0! | BJ12: =AJ12 -> 0 | BK12: =AK12 -> #DIV/0! | BL12: =BH12+BJ12 -> 0 | BM12: =BI12+BK12 -> #DIV/0! | BO12: =Q12+AO12 -> #DIV/0! | BV12: 金 | BW12: =AX12 -> 3 | BX12: 59 | BY12: 52100 | BZ12: =BY12/BX12 -> 883.05085 | CA12: 36700 | CB12: =CA12/BX12 -> 622.0339 | CE12: =BY12+CA12+CC12+CD12 -> 88800 | CF12: =CE12/BX12 -> 1505.0847 | CJ12: =SUM(CG12:CI12) -> 0 | CK12: =#REF!/CJ12 -> #REF! | CM12: 18.6 | CN12: 28.2 | CO12: 5 | CP12: 1 | CQ12: 5 | CR12: =SUM(CO12:CQ12)/3 -> 3.6666667 | CT12: 豪雨・雷雨 | CV12: 0 | DA12: 19.6 | DB12: 25.9 | DC12: 5 | DD12: 5 | DE12: 3 | DF12: =SUM(DC12:DE12)/3 -> 4.3333333 | DH12: 豪雨・雷雨 | DJ12: 0 | DO12: 6
A13: 土 | B13: 4 | C13: =D13+F13+H13+J13 -> 0 | E13: =D13*T13 -> 0 | G13: =F13*U13 -> 0 | I13: =H13*V13 -> 0 | K13: =J13*W13 -> 0 | L13: =E13+G13+I13+K13 -> 0 | M13: =L13/C13 -> #DIV/0! | N13: TOP1 | O13: 180 | Q13: =L13/P13 -> #DIV/0! | T13: 3300 | U13: 3800 | V13: 4800 | W13: 2000 | Y13: 土 | Z13: =B13 -> 4 | AA13: =AB13+AD13+AF13+AH13 -> 0 | AB13: =D13 -> 0 | AC13: =AB13*AR13 -> 0 | AD13: =F13 -> 0 | AE13: =AD13*AS13 -> 0 | AF13: =H13 -> 0 | AG13: =AF13*AT13 -> 0 | AH13: =J13 -> 0 | AI13: =AH13*AU13 -> 0 | AJ13: =AC13+AE13+AG13+AI13 -> 0 | AK13: =AJ13/AA13 -> #DIV/0! | AL13: =N13 -> TOP1 | AM13: =O13 -> 180 | AN13: =P13 -> 0 | AO13: =(AJ13+BH13)/AN13 -> #DIV/0! | AR13: 1700 | AS13: 2200 | AT13: 2200 | AU13: 1400 | AW13: 土 | AX13: =B13 -> 4 | AY13: =C13 -> 0 | AZ13: 10 | BA13: =AZ13*BR13 -> 0 | BB13: 28 | BC13: =BB13*BS13 -> 0 | BD13: 12 | BE13: =BD13*BT13 -> 0 | BG13: =BF13*BU13 -> 0 | BH13: =L13 -> 0 | BI13: =M13 -> #DIV/0! | BJ13: =AJ13 -> 0 | BK13: =AK13 -> #DIV/0! | BL13: =BH13+BJ13 -> 0 | BM13: =BI13+BK13 -> #DIV/0! | BO13: =Q13+AO13 -> #DIV/0! | BV13: 土 | BW13: =AX13 -> 4 | BX13: 72 | BY13: 61150 | BZ13: =BY13/BX13 -> 849.30556 | CA13: 50000 | CB13: =CA13/BX13 -> 694.44444 | CE13: =BY13+CA13+CC13+CD13 -> 111150 | CF13: =CE13/BX13 -> 1543.75 | CJ13: =SUM(CG13:CI13) -> 0 | CK13: =CE12/CJ13 -> #DIV/0! | CM13: 18.7 | CN13: 28.6 | CO13: 5 | CP13: 3 | CQ13: 3 | CR13: =SUM(CO13:CQ13)/3 -> 3.6666667 | CT13: ※5.6月は18時は最低気温を採用。7月〜は最高気温を採用。 | DA13: 15.8 | DB13: 26.7 | DC13: 5 | DD13: 5 | DE13: 3 | DF13: =SUM(DC13:DE13)/3 -> 4.3333333 | DH13: ※5.6月は18時は最低気温を採用。7月〜は最高気温を採用。 | DO13: 7
A14: SUB TOTAL | C14: =SUM(C7:C13) -> 0 | D14: =SUM(D7:D13) -> 0 | E14: =SUM(E7:E13) -> 0 | F14: =SUM(F7:F13) -> 0 | G14: =SUM(G7:G13) -> 0 | H14: =SUM(H7:H13) -> 0 | I14: =SUM(I7:I13) -> 0 | J14: =SUM(J7:J13) -> 0 | ... L14: =SUM(L7:L13) -> 0 | M14: =L14/C14 -> #DIV/0! | O14: =SUM(O7:O13) -> 180 | P14: =SUM(P7:P13) -> 0 | Q14: =L14/P14 -> #DIV/0! | T14: P/D | U14: =C14/W14 -> #DIV/0! | V14: 日にち | W14: 0 | Y14: SUB TOTAL | AA14: =SUM(AA7:AA13) -> 0 | AB14: =SUM(AB7:AB13) -> 0 | AC14: =SUM(AC7:AC13) -> 0 | AD14: =SUM(AD7:AD13) -> 0 | AE14: =SUM(AE7:AE13) -> 0 | AF14: =SUM(AF7:AF13) -> 0 | AG14: =SUM(AG7:AG13) -> 0 | AH14: =SUM(AH7:AH13) -> 0 | ... AJ14: =SUM(AJ7:AJ13) -> 0 | AK14: =AJ14/AA14 -> #DIV/0! | AM14: =SUM(AM7:AM13) -> 180 | AN14: =SUM(AN7:AN13) -> 0 | AO14: =(AJ14+BH14)/AN14 -> #DIV/0! | AR14: P/D | AS14: =AA14/AU14 -> #DIV/0! | AT14: 日にち | AU14: =W14 -> 0 | AW14: SUB TOTAL | AY14: =C14 -> 0 | AZ14: =SUM(AZ7:AZ13) -> 84 | BA14: =SUM(BA7:BA13) -> 0 | BB14: =SUM(BB7:BB13) -> 120 | BC14: =SUM(BC7:BC13) -> 0 | BD14: =SUM(BD7:BD13) -> 60 | BE14: =SUM(BE7:BE13) -> 0 | BF14: =SUM(BF7:BF13) -> 0 | BG14: =SUM(BG7:BG13) -> 0 | BH14: =L14 -> 0 | BI14: =M14 -> #DIV/0! | BJ14: =AJ14 -> 0 | BK14: =AK14 -> #DIV/0! | BL14: =SUM(BL7:BL13) -> 0 | BM14: =BI14+BK14 -> #DIV/0! | BO14: =Q14+AO14 -> #DIV/0! | BR14: P/D | BS14: =AY14/BU14 -> #DIV/0! | BT14: 日にち | BU14: =W14 -> 0 | BV14: SUB TOTAL | BX14: =SUM(BX7:BX13) -> 209 | BY14: =SUM(BY7:BY13) -> 175350 | BZ14: =BY14/BX14 -> 838.99522 | CA14: =SUM(CA7:CA13) -> 128550 | CB14: =CA14/BX14 -> 615.07177 | CC14: =SUM(CC7:CC13) -> 0 | CD14: =SUM(CD7:CD13) -> 0 | CE14: =BY14+CA14+CC14+CD14 -> 303900 | CF14: =CE14/BX14 -> 1454.067 | CG14: =SUM(CG7:CG13) -> 0 | CH14: =SUM(CH7:CH13) -> 0 | CI14: =SUM(CI7:CI13) -> 0 | CJ14: =SUM(CJ7:CJ13) -> 0 | CK14: =CE14/CJ14 -> #DIV/0! | CL14: 6 | CM14: =SUM(CM7:CM13)/CL14 -> 20.066667 | CN14: =SUM(CN7:CN13)/CL14 -> 27.383333 | CO14: =SUM(CO7:CO13)/CL14 -> 4 | CP14: =SUM(CP7:CP13)/CL14 -> 2.5 | CQ14: =SUM(CQ7:CQ13)/CL14 -> 3 | CR14: =SUM(CO14:CQ14)/3 -> 3.1666667 | CS14: 12 | CT14: =CE14/CL14 -> 50650 | CY14: ※1日平均売上 | CZ14: 7 | DA14: =SUM(DA7:DA13)/CZ14 -> 18.271429 | DB14: =SUM(DB7:DB13)/CZ14 -> 27.514286 | DC14: =SUM(DC7:DC13)/CZ14 -> 4.4285714 | DD14: =SUM(DD7:DD13)/CZ14 -> 4.4285714 | DE14: =SUM(DE7:DE13)/CZ14 -> 3.2857143 | DF14: =SUM(DC14:DE14)/3 -> 4.047619 | DG14: 15 | DH14: =CV14/CZ14 -> 0 | DM14: ※1日平均売上
A15: 2nd week | Y15: 2nd week | AW15: 2nd week | BV15: 2nd week | CM15: =BV15 -> 2nd week | CY15: ※1日平均売上 | DA15: =CM15 -> 2nd week | DM15: ※1日平均売上
A16: 曜日 | B16: 日にち | C16: 客数 | D16: MENU A 出卓 | E16: 売上 | F16: MENU B 出卓 | G16: 売上 | H16: MENU C 出卓 | I16: 売上 | J16: アラカルト利用数 | K16: 売上 | L16: 料理売上 | M16: 料理単価 | N16: モデルシフト | O16: モデルシフト時間数 | P16: 実時間数 | Q16: 人時売上高 | T16: A | U16: B | V16: C | W16: S | Y16: 曜日 | Z16: 日にち | AA16: 客数 | AB16: MENU A 出卓 | AC16: 売上 | AD16: MENU B 出卓 | AE16: 売上 | AF16: MENU C 出卓 | AG16: 売上 | AH16: アラカルト利用数 | AI16: 売上 | AJ16: 飲料売上 | AK16: 飲料単価 | AL16: モデルシフト | AM16: モデルシフト時間数 | AN16: 実時間数 | AO16: 人時売上高 | AR16: A | AS16: B | AT16: C | AU16: S | AW16: 曜日 | AX16: 日にち | AY16: 客数 | AZ16: MENU A 出卓 | BA16: 売上 | BB16: MENU B 出卓 | BC16: 売上 | BD16: MENU C 出卓 | BE16: 売上 | BF16: MENU S 出卓 | BG16: 売上 | BH16: 料理売上 | BI16: 料理単価 | BJ16: 飲料売上 | BK16: 飲料単価 | BL16: 合計売上予測 | BM16: 合計単価 | BO16: 人時売上高予測 | BR16: A | BS16: B | BT16: C | BU16: S | BV16: 曜日 | BW16: 日にち | BX16: 客数 | BY16: 料理売上 | BZ16: 料理単価 | CA16: 飲料売上 | CB16: 飲料単価 | CC16: その他売上 | CD16: 物販 | CE16: 売上合計 | CF16: 合計単価 | CG16: サーフィンズ | CH16: forking | CI16: Timee | CJ16: 合計 | CK16: 人時売上高 | CM16: 最低 | CN16: 最高 | CO16: 12時 | CP16: 15時 | CQ16: 18時 | CR16: Ave | CT16: ■天候要因 | CV16: 評価点 | DA16: 最低 | DB16: 最高 | DC16: 12時 | DD16: 15時 | DE16: 18時 | DF16: Ave | DH16: ■天候要因 | DJ16: 評価点
A17: 日 | B17: 5 | C17: =D17+F17+H17+J17 -> 0 | E17: =D17*T17 -> 0 | G17: =F17*U17 -> 0 | I17: =H17*V17 -> 0 | K17: =J17*W17 -> 0 | L17: =E17+G17+I17+K17 -> 0 | M17: =L17/C17 -> #DIV/0! | N17: TOP2 | O17: 170 | Q17: =L17/P17 -> #DIV/0! | T17: 3300 | U17: 3800 | V17: 4800 | W17: 2000 | Y17: 日 | Z17: =B17 -> 5 | AA17: =AB17+AD17+AF17+AH17 -> 0 | AB17: =D17 -> 0 | AC17: =AB17*AR17 -> 0 | AD17: =F17 -> 0 | AE17: =AD17*AS17 -> 0 | AF17: =H17 -> 0 | AG17: =AF17*AT17 -> 0 | AH17: =J17 -> 0 | AI17: =AH17*AU17 -> 0 | AJ17: =AC17+AE17+AG17+AI17 -> 0 | AK17: =AJ17/AA17 -> #DIV/0! | AL17: =N17 -> TOP2 | AM17: =O17 -> 170 | AN17: =P17 -> 0 | AO17: =(AJ17+BH17)/AN17 -> #DIV/0! | AR17: 1700 | AS17: 2200 | AT17: 2200 | AU17: 1400 | AW17: 日 | AX17: =B17 -> 5 | AY17: =C17 -> 0 | BA17: =AZ17*BR17 -> 0 | BC17: =BB17*BS17 -> 0 | BE17: =BD17*BT17 -> 0 | BG17: =BF17*BU17 -> 0 | BH17: =L17 -> 0 | BI17: =M17 -> #DIV/0! | BJ17: =AJ17 -> 0 | BK17: =AK17 -> #DIV/0! | BL17: =BH17+BJ17 -> 0 | BM17: =BI17+BK17 -> #DIV/0! | BO17: =Q17+AO17 -> #DIV/0! | BV17: 日 | BW17: =AX17 -> 5 | BX17: 65 | BY17: 70550 | BZ17: =BY17/BX17 -> 1085.3846 | CA17: 63000 | CB17: =CA17/BX17 -> 969.23077 | CE17: =BY17+CA17+CC17+CD17 -> 133550 | CF17: =CE17/BX17 -> 2054.6154 | CJ17: =SUM(CG17:CI17) -> 0 | CK17: =CE17/CJ17 -> #DIV/0! | CM17: 20.7 | CN17: 25.2 | CO17: 3 | CP17: 5 | CQ17: 3 | CR17: =SUM(CO17:CQ17)/3 -> 3.6666667 | CT17: 晴れ（33度まで） | CV17: 5 | DA17: 17.2 | DB17: 31.5 | DC17: 5 | DD17: 5 | DE17: 5 | DF17: =SUM(DC17:DE17)/3 -> 5 | DH17: 晴れ（33度まで） | DJ17: 5 | DO17: 8
A18: 月 | B18: 6 | C18: =D18+F18+H18+J18 -> 0 | E18: =D18*T18 -> 0 | G18: =F18*U18 -> 0 | I18: =H18*V18 -> 0 | K18: =J18*W18 -> 0 | L18: =E18+G18+I18+K18 -> 0 | M18: =L18/C18 -> #DIV/0! | N18: ON2 | O18: 150 | Q18: =L18/P18 -> #DIV/0! | T18: 3300 | U18: 3800 | V18: 4800 | W18: 2000 | Y18: 月 | Z18: =B18 -> 6 | AA18: =AB18+AD18+AF18+AH18 -> 0 | AB18: =D18 -> 0 | AC18: =AB18*AR18 -> 0 | AD18: =F18 -> 0 | AE18: =AD18*AS18 -> 0 | AF18: =H18 -> 0 | AG18: =AF18*AT18 -> 0 | AH18: =J18 -> 0 | AI18: =AH18*AU18 -> 0 | AJ18: =AC18+AE18+AG18+AI18 -> 0 | AK18: =AJ18/AA18 -> #DIV/0! | AL18: =N18 -> ON2 | AM18: =O18 -> 150 | AN18: =P18 -> 0 | AO18: =(AJ18+BH18)/AN18 -> #DIV/0! | AR18: 1700 | AS18: 2200 | AT18: 2200 | AU18: 1400 | AW18: 月 | AX18: =B18 -> 6 | AY18: =C18 -> 0 | AZ18: 22 | BA18: =AZ18*BR18 -> 0 | BB18: 10 | BC18: =BB18*BS18 -> 0 | BD18: 6 | BE18: =BD18*BT18 -> 0 | BG18: =BF18*BU18 -> 0 | BH18: =L18 -> 0 | BI18: =M18 -> #DIV/0! | BJ18: =AJ18 -> 0 | BK18: =AK18 -> #DIV/0! | BL18: =BH18+BJ18 -> 0 | BM18: =BI18+BK18 -> #DIV/0! | BO18: =Q18+AO18 -> #DIV/0! | BV18: 月 | BW18: =AX18 -> 6 | BZ18: =BY18/BX18 -> #DIV/0! | CB18: =CA18/BX18 -> #DIV/0! | CE18: =BY18+CA18+CC18+CD18 -> 0 | CF18: =CE18/BX18 -> #DIV/0! | CJ18: =SUM(CG18:CI18) -> 0 | CK18: =CE18/CJ18 -> #DIV/0! | CM18: 17.8 | CN18: 28.2 | CO18: 5 | CP18: 5 | CQ18: 5 | CR18: =SUM(CO18:CQ18)/3 -> 5 | CT18: 晴れ（25度以下） | CV18: 4 | DA18: ピコレへの切り返しで休業 | DF18: =SUM(DC18:DE18)/3 -> 0 | DH18: 晴れ（25度以下） | DJ18: 4 | DO18: 9
A19: 火 | B19: 7 | C19: =D19+F19+H19+J19 -> 0 | E19: =D19*T19 -> 0 | G19: =F19*U19 -> 0 | I19: =H19*V19 -> 0 | K19: =J19*W19 -> 0 | L19: =E19+G19+I19+K19 -> 0 | M19: =L19/C19 -> #DIV/0! | N19: ON2 | O19: 150 | Q19: =L19/P19 -> #DIV/0! | T19: 3300 | U19: 3800 | V19: 4800 | W19: 2000 | Y19: 火 | Z19: =B19 -> 7 | AA19: =AB19+AD19+AF19+AH19 -> 0 | AB19: =D19 -> 0 | AC19: =AB19*AR19 -> 0 | AD19: =F19 -> 0 | AE19: =AD19*AS19 -> 0 | AF19: =H19 -> 0 | AG19: =AF19*AT19 -> 0 | AH19: =J19 -> 0 | AI19: =AH19*AU19 -> 0 | AJ19: =AC19+AE19+AG19+AI19 -> 0 | AK19: =AJ19/AA19 -> #DIV/0! | AL19: =N19 -> ON2 | AM19: =O19 -> 150 | AN19: =P19 -> 0 | AO19: =(AJ19+BH19)/AN19 -> #DIV/0! | AR19: 1700 | AS19: 2200 | AT19: 2200 | AU19: 1400 | AW19: 火 | AX19: =B19 -> 7 | AY19: =C19 -> 0 | AZ19: 22 | BA19: =AZ19*BR19 -> 0 | BB19: 10 | BC19: =BB19*BS19 -> 0 | BD19: 6 | BE19: =BD19*BT19 -> 0 | BG19: =BF19*BU19 -> 0 | BH19: =L19 -> 0 | BI19: =M19 -> #DIV/0! | BJ19: =AJ19 -> 0 | BK19: =AK19 -> #DIV/0! | BL19: =BH19+BJ19 -> 0 | BM19: =BI19+BK19 -> #DIV/0! | BO19: =Q19+AO19 -> #DIV/0! | BV19: 火 | BW19: =AX19 -> 7 | BZ19: =BY19/BX19 -> #DIV/0! | CB19: =CA19/BX19 -> #DIV/0! | CE19: =BY19+CA19+CC19+CD19 -> 0 | CF19: =CE19/BX19 -> #DIV/0! | CJ19: =SUM(CG19:CI19) -> 0 | CK19: =CE19/CJ19 -> #DIV/0! | CM19: 20.1 | CN19: 26.5 | CO19: 3 | CP19: 3 | CQ19: 3 | CR19: =SUM(CO19:CQ19)/3 -> 3 | CT19: 晴れ（33度以上）曇25度以上 | CV19: 3 | DF19: =SUM(DC19:DE19)/3 -> 0 | DH19: 晴れ（33度以上）曇25度以上 | DJ19: 3 | DO19: 10
A20: 水 | B20: 8 | C20: =D20+F20+H20+J20 -> 0 | E20: =D20*T20 -> 0 | G20: =F20*U20 -> 0 | I20: =H20*V20 -> 0 | K20: =J20*W20 -> 0 | L20: =E20+G20+I20+K20 -> 0 | M20: =L20/C20 -> #DIV/0! | N20: ON2 | O20: 150 | Q20: =L20/P20 -> #DIV/0! | T20: 3300 | U20: 3800 | V20: 4800 | W20: 2000 | Y20: 水 | Z20: =B20 -> 8 | AA20: =AB20+AD20+AF20+AH20 -> 0 | AB20: =D20 -> 0 | AC20: =AB20*AR20 -> 0 | AD20: =F20 -> 0 | AE20: =AD20*AS20 -> 0 | AF20: =H20 -> 0 | AG20: =AF20*AT20 -> 0 | AH20: =J20 -> 0 | AI20: =AH20*AU20 -> 0 | AJ20: =AC20+AE20+AG20+AI20 -> 0 | AK20: =AJ20/AA20 -> #DIV/0! | AL20: =N20 -> ON2 | AM20: =O20 -> 150 | AN20: =P20 -> 0 | AO20: =(AJ20+BH20)/AN20 -> #DIV/0! | AR20: 1700 | AS20: 2200 | AT20: 2200 | AU20: 1400 | AW20: 水 | AX20: =B20 -> 8 | AY20: =C20 -> 0 | AZ20: 10 | BA20: =AZ20*BR20 -> 0 | BB20: 24 | BC20: =BB20*BS20 -> 0 | BD20: 12 | BE20: =BD20*BT20 -> 0 | BG20: =BF20*BU20 -> 0 | BH20: =L20 -> 0 | BI20: =M20 -> #DIV/0! | BJ20: =AJ20 -> 0 | BK20: =AK20 -> #DIV/0! | BL20: =BH20+BJ20 -> 0 | BM20: =BI20+BK20 -> #DIV/0! | BO20: =Q20+AO20 -> #DIV/0! | BV20: 水 | BW20: =AX20 -> 8 | BZ20: =BY20/BX20 -> #DIV/0! | CB20: =CA20/BX20 -> #DIV/0! | CE20: =BY20+CA20+CC20+CD20 -> 0 | CF20: =CE20/BX20 -> #DIV/0! | CJ20: =SUM(CG20:CI20) -> 0 | CK20: =CE20/CJ20 -> #DIV/0! | CM20: 19.2 | CN20: 27.2 | CO20: 5 | CP20: 3 | CQ20: 3 | CR20: =SUM(CO20:CQ20)/3 -> 3.6666667 | CT20: 曇 | CV20: 2 | DF20: =SUM(DC20:DE20)/3 -> 0 | DH20: 曇 | DJ20: 2 | DO20: 11
A21: 木 | B21: 9 | C21: =D21+F21+H21+J21 -> 0 | E21: =D21*T21 -> 0 | G21: =F21*U21 -> 0 | I21: =H21*V21 -> 0 | K21: =J21*W21 -> 0 | L21: =E21+G21+I21+K21 -> 0 | M21: =L21/C21 -> #DIV/0! | N21: ON2 | O21: 150 | Q21: =L21/P21 -> #DIV/0! | T21: 3300 | U21: 3800 | V21: 4800 | W21: 2000 | Y21: 木 | Z21: =B21 -> 9 | AA21: =AB21+AD21+AF21+AH21 -> 0 | AB21: =D21 -> 0 | AC21: =AB21*AR21 -> 0 | AD21: =F21 -> 0 | AE21: =AD21*AS21 -> 0 | AF21: =H21 -> 0 | AG21: =AF21*AT21 -> 0 | AH21: =J21 -> 0 | AI21: =AH21*AU21 -> 0 | AJ21: =AC21+AE21+AG21+AI21 -> 0 | AK21: =AJ21/AA21 -> #DIV/0! | AL21: =N21 -> ON2 | AM21: =O21 -> 150 | AN21: =P21 -> 0 | AO21: =(AJ21+BH21)/AN21 -> #DIV/0! | AR21: 1700 | AS21: 2200 | AT21: 2200 | AU21: 1400 | AW21: 木 | AX21: =B21 -> 9 | AY21: =C21 -> 0 | AZ21: 10 | BA21: =AZ21*BR21 -> 0 | BB21: 24 | BC21: =BB21*BS21 -> 0 | BD21: 12 | BE21: =BD21*BT21 -> 0 | BG21: =BF21*BU21 -> 0 | BH21: =L21 -> 0 | BI21: =M21 -> #DIV/0! | BJ21: =AJ21 -> 0 | BK21: =AK21 -> #DIV/0! | BL21: =BH21+BJ21 -> 0 | BM21: =BI21+BK21 -> #DIV/0! | BO21: =Q21+AO21 -> #DIV/0! | BV21: 木 | BW21: =AX21 -> 9 | BZ21: =BY21/BX21 -> #DIV/0! | CB21: =CA21/BX21 -> #DIV/0! | CE21: =BY21+CA21+CC21+CD21 -> 0 | CF21: =CE21/BX21 -> #DIV/0! | CJ21: =SUM(CG21:CI21) -> 0 | CK21: =CE21/CJ21 -> #DIV/0! | CM21: 18.3 | CN21: 28.8 | CO21: 5 | CP21: 3 | CQ21: 3 | CR21: =SUM(CO21:CQ21)/3 -> 3.6666667 | CT21: 雨 | CV21: 1 | DF21: =SUM(DC21:DE21)/3 -> 0 | DH21: 雨 | DJ21: 1 | DO21: 12
A22: 金 | B22: 10 | C22: =D22+F22+H22+J22 -> 0 | E22: =D22*T22 -> 0 | G22: =F22*U22 -> 0 | I22: =H22*V22 -> 0 | K22: =J22*W22 -> 0 | L22: =E22+G22+I22+K22 -> 0 | M22: =L22/C22 -> #DIV/0! | N22: ON1 | O22: 160 | Q22: =L22/P22 -> #DIV/0! | T22: 3300 | U22: 3800 | V22: 4800 | W22: 2000 | Y22: 金 | Z22: =B22 -> 10 | AA22: =AB22+AD22+AF22+AH22 -> 0 | AB22: =D22 -> 0 | AC22: =AB22*AR22 -> 0 | AD22: =F22 -> 0 | AE22: =AD22*AS22 -> 0 | AF22: =H22 -> 0 | AG22: =AF22*AT22 -> 0 | AH22: =J22 -> 0 | AI22: =AH22*AU22 -> 0 | AJ22: =AC22+AE22+AG22+AI22 -> 0 | AK22: =AJ22/AA22 -> #DIV/0! | AL22: =N22 -> ON1 | AM22: =O22 -> 160 | AN22: =P22 -> 0 | AO22: =(AJ22+BH22)/AN22 -> #DIV/0! | AR22: 1700 | AS22: 2200 | AT22: 2200 | AU22: 1400 | AW22: 金 | AX22: =B22 -> 10 | AY22: =C22 -> 0 | AZ22: 10 | BA22: =AZ22*BR22 -> 0 | BB22: 24 | BC22: =BB22*BS22 -> 0 | BD22: 12 | BE22: =BD22*BT22 -> 0 | BG22: =BF22*BU22 -> 0 | BH22: =L22 -> 0 | BI22: =M22 -> #DIV/0! | BJ22: =AJ22 -> 0 | BK22: =AK22 -> #DIV/0! | BL22: =BH22+BJ22 -> 0 | BM22: =BI22+BK22 -> #DIV/0! | BO22: =Q22+AO22 -> #DIV/0! | BV22: 金 | BW22: =AX22 -> 10 | BZ22: =BY22/BX22 -> #DIV/0! | CB22: =CA22/BX22 -> #DIV/0! | CE22: =BY22+CA22+CC22+CD22 -> 0 | CF22: =CE22/BX22 -> #DIV/0! | CJ22: =SUM(CG22:CI22) -> 0 | CK22: =CE22/CJ22 -> #DIV/0! | CM22: 16.3 | CN22: 27.9 | CO22: 5 | CP22: 5 | CQ22: 5 | CR22: =SUM(CO22:CQ22)/3 -> 5 | CT22: 豪雨・雷雨 | CV22: 0 | DF22: =SUM(DC22:DE22)/3 -> 0 | DH22: 豪雨・雷雨 | DJ22: 0 | DO22: 13
A23: 土 | B23: 11 | C23: =D23+F23+H23+J23 -> 0 | E23: =D23*T23 -> 0 | G23: =F23*U23 -> 0 | I23: =H23*V23 -> 0 | K23: =J23*W23 -> 0 | L23: =E23+G23+I23+K23 -> 0 | M23: =L23/C23 -> #DIV/0! | N23: TOP1 | O23: 180 | Q23: =L23/P23 -> #DIV/0! | T23: 3300 | U23: 3800 | V23: 4800 | W23: 2000 | Y23: 土 | Z23: =B23 -> 11 | AA23: =AB23+AD23+AF23+AH23 -> 0 | AB23: =D23 -> 0 | AC23: =AB23*AR23 -> 0 | AD23: =F23 -> 0 | AE23: =AD23*AS23 -> 0 | AF23: =H23 -> 0 | AG23: =AF23*AT23 -> 0 | AH23: =J23 -> 0 | AI23: =AH23*AU23 -> 0 | AJ23: =AC23+AE23+AG23+AI23 -> 0 | AK23: =AJ23/AA23 -> #DIV/0! | AL23: =N23 -> TOP1 | AM23: =O23 -> 180 | AN23: =P23 -> 0 | AO23: =(AJ23+BH23)/AN23 -> #DIV/0! | AR23: 1700 | AS23: 2200 | AT23: 2200 | AU23: 1400 | AW23: 土 | AX23: =B23 -> 11 | AY23: =C23 -> 0 | AZ23: 10 | BA23: =AZ23*BR23 -> 0 | BB23: 28 | BC23: =BB23*BS23 -> 0 | BD23: 12 | BE23: =BD23*BT23 -> 0 | BG23: =BF23*BU23 -> 0 | BH23: =L23 -> 0 | BI23: =M23 -> #DIV/0! | BJ23: =AJ23 -> 0 | BK23: =AK23 -> #DIV/0! | BL23: =BH23+BJ23 -> 0 | BM23: =BI23+BK23 -> #DIV/0! | BO23: =Q23+AO23 -> #DIV/0! | BV23: 土 | BW23: =AX23 -> 11 | BZ23: =BY23/BX23 -> #DIV/0! | CB23: =CA23/BX23 -> #DIV/0! | CE23: =BY23+CA23+CC23+CD23 -> 0 | CF23: =CE23/BX23 -> #DIV/0! | CJ23: =SUM(CG23:CI23) -> 0 | CK23: =CE23/CJ23 -> #DIV/0! | CM23: 18.9 | CN23: 23.8 | CO23: 1 | CP23: 1 | CQ23: 1 | CR23: =SUM(CO23:CQ23)/3 -> 1 | CT23: ※5.6月は18時は最低気温を採用。7月〜は最高気温を採用。 | DA23: 13.4 | DB23: 23.7 | DC23: 4 | DD23: 4 | DE23: 2 | DF23: =SUM(DC23:DE23)/3 -> 3.3333333 | DH23: ※5.6月は18時は最低気温を採用。7月〜は最高気温を採用。 | DO23: 14
A24: SUB TOTAL | C24: =SUM(C17:C23) -> 0 | D24: =SUM(D17:D23) -> 0 | E24: =SUM(E17:E23) -> 0 | F24: =SUM(F17:F23) -> 0 | G24: =SUM(G17:G23) -> 0 | H24: =SUM(H17:H23) -> 0 | I24: =SUM(I17:I23) -> 0 | J24: =SUM(J17:J23) -> 0 | ... L24: =SUM(L17:L23) -> 0 | M24: =L24/C24 -> #DIV/0! | O24: =SUM(O17:O23) -> 1110 | P24: =SUM(P17:P23) -> 0 | Q24: =L24/P24 -> #DIV/0! | T24: P/D | U24: =C24/W24 -> #DIV/0! | V24: 日にち | W24: 0 | Y24: SUB TOTAL | AA24: =SUM(AA17:AA23) -> 0 | AB24: =SUM(AB17:AB23) -> 0 | AC24: =SUM(AC17:AC23) -> 0 | AD24: =SUM(AD17:AD23) -> 0 | AE24: =SUM(AE17:AE23) -> 0 | AF24: =SUM(AF17:AF23) -> 0 | AG24: =SUM(AG17:AG23) -> 0 | AH24: =SUM(AH17:AH23) -> 0 | ... AJ24: =SUM(AJ17:AJ23) -> 0 | AK24: =AJ24/AA24 -> #DIV/0! | AM24: =SUM(AM17:AM23) -> 1110 | AN24: =SUM(AN17:AN23) -> 0 | AO24: =(AJ24+BH24)/AN24 -> #DIV/0! | AR24: P/D | AS24: =AA24/AU24 -> #DIV/0! | AT24: 日にち | AU24: =W24 -> 0 | AW24: SUB TOTAL | AY24: =C24 -> 0 | AZ24: =SUM(AZ17:AZ23) -> 84 | BA24: =SUM(BA17:BA23) -> 0 | BB24: =SUM(BB17:BB23) -> 120 | BC24: =SUM(BC17:BC23) -> 0 | BD24: =SUM(BD17:BD23) -> 60 | BE24: =SUM(BE17:BE23) -> 0 | BF24: =SUM(BF17:BF23) -> 0 | BG24: =SUM(BG17:BG23) -> 0 | BH24: =L24 -> 0 | BI24: =M24 -> #DIV/0! | BJ24: =AJ24 -> 0 | BK24: =AK24 -> #DIV/0! | BL24: =SUM(BL17:BL23) -> 0 | BM24: =BI24+BK24 -> #DIV/0! | BO24: =Q24+AO24 -> #DIV/0! | BR24: P/D | BS24: =AY24/BU24 -> #DIV/0! | BT24: 日にち | BU24: =W24 -> 0 | BV24: SUB TOTAL | BX24: =SUM(BX17:BX23) -> 65 | BY24: =SUM(BY17:BY23) -> 70550 | BZ24: =BY24/BX24 -> 1085.3846 | CA24: =SUM(CA17:CA23) -> 63000 | CB24: =CA24/BX24 -> 969.23077 | CC24: =SUM(CC17:CC23) -> 0 | CD24: =SUM(CD17:CD23) -> 0 | CE24: =BY24+CA24+CC24+CD24 -> 133550 | CF24: =CE24/BX24 -> 2054.6154 | CG24: =SUM(CG17:CG23) -> 0 | CH24: =SUM(CH17:CH23) -> 0 | CI24: =SUM(CI17:CI23) -> 0 | CJ24: =SUM(CJ17:CJ23) -> 0 | CK24: =CE24/CJ24 -> #DIV/0! | CL24: 7 | CM24: =SUM(CM17:CM23)/CL24 -> 18.757143 | CN24: =SUM(CN17:CN23)/CL24 -> 26.8 | CO24: =SUM(CO17:CO23)/CL24 -> 3.8571429 | CP24: =SUM(CP17:CP23)/CL24 -> 3.5714286 | CQ24: =SUM(CQ17:CQ23)/CL24 -> 3.2857143 | CR24: =SUM(CO24:CQ24)/3 -> 3.5714286 | CS24: 13 | CT24: =CE24/CL24 -> 19078.571 | CY24: ※1日平均売上 | CZ24: 2 | DA24: =SUM(DA17:DA23)/CZ24 -> 15.3 | DB24: =SUM(DB17:DB23)/CZ24 -> 27.6 | DC24: =SUM(DC17:DC23)/CZ24 -> 4.5 | DD24: =SUM(DD17:DD23)/CZ24 -> 4.5 | DE24: =SUM(DE17:DE23)/CZ24 -> 3.5 | DF24: =SUM(DC24:DE24)/3 -> 4.1666667 | DG24: 16 | DH24: =CV24/CZ24 -> 0 | DM24: ※1日平均売上
A25: 3rd week | Y25: 3rd week | AW25: 3rd week | BV25: 3rd week | CM25: =BV25 -> 3rd week | DA25: =CM25 -> 3rd week
A26: 曜日 | B26: 日にち | C26: 客数 | D26: MENU A 出卓 | E26: 売上 | F26: MENU B 出卓 | G26: 売上 | H26: MENU C 出卓 | I26: 売上 | J26: アラカルト利用数 | K26: 売上 | L26: 料理売上 | M26: 料理単価 | N26: モデルシフト | O26: モデルシフト時間数 | P26: 実時間数 | Q26: 人時売上高 | T26: A | U26: B | V26: C | W26: S | Y26: 曜日 | Z26: 日にち | AA26: 客数 | AB26: MENU A 出卓 | AC26: 売上 | AD26: MENU B 出卓 | AE26: 売上 | AF26: MENU C 出卓 | AG26: 売上 | AH26: アラカルト利用数 | AI26: 売上 | AJ26: 飲料売上 | AK26: 飲料単価 | AL26: モデルシフト | AM26: モデルシフト時間数 | AN26: 実時間数 | AO26: 人時売上高 | AR26: A | AS26: B | AT26: C | AU26: S | AW26: 曜日 | AX26: 日にち | AY26: 客数 | AZ26: MENU A 出卓 | BA26: 売上 | BB26: MENU B 出卓 | BC26: 売上 | BD26: MENU C 出卓 | BE26: 売上 | BF26: MENU S 出卓 | BG26: 売上 | BH26: 料理売上 | BI26: 料理単価 | BJ26: 飲料売上 | BK26: 飲料単価 | BL26: 合計売上予測 | BM26: 合計単価 | BO26: 人時売上高予測 | BR26: A | BS26: B | BT26: C | BU26: S | BV26: 曜日 | BW26: 日にち | BX26: 客数 | BY26: 料理売上 | BZ26: 料理単価 | CA26: 飲料売上 | CB26: 飲料単価 | CC26: その他売上 | CD26: 物販 | CE26: =BY26+CA26+CC26 -> #VALUE! | CF26: 合計単価 | CG26: サーフィンズ | CH26: forking | CI26: Timee | CJ26: 合計 | CK26: 人時売上高 | CM26: 最低 | CN26: 最高 | CO26: 12時 | CP26: 15時 | CQ26: 18時 | CR26: Ave | CT26: ■天候要因 | CV26: 評価点 | DA26: 最低 | DB26: 最高 | DC26: 12時 | DD26: 15時 | DE26: 18時 | DF26: Ave | DH26: ■天候要因 | DJ26: 評価点
A27: 日 | B27: 12 | C27: =D27+F27+H27+J27 -> 0 | E27: =D27*T27 -> 0 | G27: =F27*U27 -> 0 | I27: =H27*V27 -> 0 | K27: =J27*W27 -> 0 | L27: =E27+G27+I27+K27 -> 0 | M27: =L27/C27 -> #DIV/0! | N27: TOP2 | O27: 170 | Q27: =L27/P27 -> #DIV/0! | T27: 3300 | U27: 3800 | V27: 4800 | W27: 2000 | Y27: 日 | Z27: =B27 -> 12 | AA27: =AB27+AD27+AF27+AH27 -> 0 | AB27: =D27 -> 0 | AC27: =AB27*AR27 -> 0 | AD27: =F27 -> 0 | AE27: =AD27*AS27 -> 0 | AF27: =H27 -> 0 | AG27: =AF27*AT27 -> 0 | AH27: =J27 -> 0 | AI27: =AH27*AU27 -> 0 | AJ27: =AC27+AE27+AG27+AI27 -> 0 | AK27: =AJ27/AA27 -> #DIV/0! | AL27: =N27 -> TOP2 | AM27: =O27 -> 170 | AN27: =P27 -> 0 | AO27: =(AJ27+BH27)/AN27 -> #DIV/0! | AR27: 1700 | AS27: 2200 | AT27: 2200 | AU27: 1400 | AW27: 日 | AX27: =B27 -> 12 | AY27: =C27 -> 0 | BA27: =AZ27*BR27 -> 0 | BC27: =BB27*BS27 -> 0 | BE27: =BD27*BT27 -> 0 | BG27: =BF27*BU27 -> 0 | BH27: =L27 -> 0 | BI27: =M27 -> #DIV/0! | BJ27: =AJ27 -> 0 | BK27: =AK27 -> #DIV/0! | BL27: =BH27+BJ27 -> 0 | BM27: =BI27+BK27 -> #DIV/0! | BO27: =Q27+AO27 -> #DIV/0! | BV27: 日 | BW27: =AX27 -> 12 | BZ27: =BY27/BX27 -> #DIV/0! | CB27: =CA27/BX27 -> #DIV/0! | CE27: =BY27+CA27+CC27+CD27 -> 0 | CF27: =CE27/BX27 -> #DIV/0! | CJ27: =SUM(CG27:CI27) -> 0 | CK27: =CE27/CJ27 -> #DIV/0! | CM27: 17.5 | CN27: 24.2 | CO27: 5 | CP27: 4 | CQ27: 4 | CR27: =SUM(CO27:CQ27)/3 -> 4.3333333 | CT27: 晴れ（33度まで） | CV27: 5 | DA27: 16.6 | DB27: 19.3 | DC27: 1 | DD27: 2 | DE27: 4 | DF27: =SUM(DC27:DE27)/3 -> 2.3333333 | DH27: 晴れ（33度まで） | DJ27: 5 | DO27: 15
A28: 月 | B28: 13 | C28: =D28+F28+H28+J28 -> 0 | E28: =D28*T28 -> 0 | G28: =F28*U28 -> 0 | I28: =H28*V28 -> 0 | K28: =J28*W28 -> 0 | L28: =E28+G28+I28+K28 -> 0 | M28: =L28/C28 -> #DIV/0! | N28: ON2 | O28: 150 | Q28: =L28/P28 -> #DIV/0! | T28: 3300 | U28: 3800 | V28: 4800 | W28: 2000 | Y28: 月 | Z28: =B28 -> 13 | AA28: =AB28+AD28+AF28+AH28 -> 0 | AB28: =D28 -> 0 | AC28: =AB28*AR28 -> 0 | AD28: =F28 -> 0 | AE28: =AD28*AS28 -> 0 | AF28: =H28 -> 0 | AG28: =AF28*AT28 -> 0 | AH28: =J28 -> 0 | AI28: =AH28*AU28 -> 0 | AJ28: =AC28+AE28+AG28+AI28 -> 0 | AK28: =AJ28/AA28 -> #DIV/0! | AL28: =N28 -> ON2 | AM28: =O28 -> 150 | AN28: =P28 -> 0 | AO28: =(AJ28+BH28)/AN28 -> #DIV/0! | AR28: 1700 | AS28: 2200 | AT28: 2200 | AU28: 1400 | AW28: 月 | AX28: =B28 -> 13 | AY28: =C28 -> 0 | AZ28: 22 | BA28: =AZ28*BR28 -> 0 | BB28: 10 | BC28: =BB28*BS28 -> 0 | BD28: 6 | BE28: =BD28*BT28 -> 0 | BG28: =BF28*BU28 -> 0 | BH28: =L28 -> 0 | BI28: =M28 -> #DIV/0! | BJ28: =AJ28 -> 0 | BK28: =AK28 -> #DIV/0! | BL28: =BH28+BJ28 -> 0 | BM28: =BI28+BK28 -> #DIV/0! | BO28: =Q28+AO28 -> #DIV/0! | BV28: 月 | BW28: =AX28 -> 13 | BZ28: =BY28/BX28 -> #DIV/0! | CB28: =CA28/BX28 -> #DIV/0! | CE28: =BY28+CA28+CC28+CD28 -> 0 | CF28: =CE28/BX28 -> #DIV/0! | CJ28: =SUM(CG28:CI28) -> 0 | CK28: =CE28/CJ28 -> #DIV/0! | CM28: 15.8 | CN28: 28.5 | CO28: 5 | CP28: 5 | CQ28: 5 | CR28: =SUM(CO28:CQ28)/3 -> 5 | CT28: 晴れ（25度以下） | CV28: 4 | DA28: 12 | DB28: 23.6 | DC28: 4 | DD28: 2 | DE28: 2 | DF28: =SUM(DC28:DE28)/3 -> 2.6666667 | DH28: 晴れ（25度以下） | DJ28: 4 | DO28: 16
A29: 火 | B29: 14 | C29: =D29+F29+H29+J29 -> 0 | E29: =D29*T29 -> 0 | G29: =F29*U29 -> 0 | I29: =H29*V29 -> 0 | K29: =J29*W29 -> 0 | L29: =E29+G29+I29+K29 -> 0 | M29: =L29/C29 -> #DIV/0! | N29: ON2 | O29: 150 | Q29: =L29/P29 -> #DIV/0! | T29: 3300 | U29: 3800 | V29: 4800 | W29: 2000 | Y29: 火 | Z29: =B29 -> 14 | AA29: =AB29+AD29+AF29+AH29 -> 0 | AB29: =D29 -> 0 | AC29: =AB29*AR29 -> 0 | AD29: =F29 -> 0 | AE29: =AD29*AS29 -> 0 | AF29: =H29 -> 0 | AG29: =AF29*AT29 -> 0 | AH29: =J29 -> 0 | AI29: =AH29*AU29 -> 0 | AJ29: =AC29+AE29+AG29+AI29 -> 0 | AK29: =AJ29/AA29 -> #DIV/0! | AL29: =N29 -> ON2 | AM29: =O29 -> 150 | AN29: =P29 -> 0 | AO29: =(AJ29+BH29)/AN29 -> #DIV/0! | AR29: 1700 | AS29: 2200 | AT29: 2200 | AU29: 1400 | AW29: 火 | AX29: =B29 -> 14 | AY29: =C29 -> 0 | AZ29: 22 | BA29: =AZ29*BR29 -> 0 | BB29: 10 | BC29: =BB29*BS29 -> 0 | BD29: 6 | BE29: =BD29*BT29 -> 0 | BG29: =BF29*BU29 -> 0 | BH29: =L29 -> 0 | BI29: =M29 -> #DIV/0! | BJ29: =AJ29 -> 0 | BK29: =AK29 -> #DIV/0! | BL29: =BH29+BJ29 -> 0 | BM29: =BI29+BK29 -> #DIV/0! | BO29: =Q29+AO29 -> #DIV/0! | BV29: 火 | BW29: =AX29 -> 14 | BZ29: =BY29/BX29 -> #DIV/0! | CB29: =CA29/BX29 -> #DIV/0! | CE29: =BY29+CA29+CC29+CD29 -> 0 | CF29: =CE29/BX29 -> #DIV/0! | CJ29: =SUM(CG29:CI29) -> 0 | CK29: =CE29/CJ29 -> #DIV/0! | CR29: =SUM(CO29:CQ29)/3 -> 0 | CT29: 晴れ（33度以上）曇25度以上 | CV29: 3 | DA29: 18.2 | DB29: 24.7 | DC29: 4 | DD29: 2 | DE29: 4 | DF29: =SUM(DC29:DE29)/3 -> 3.3333333 | DH29: 晴れ（33度以上）曇25度以上 | DJ29: 3 | DO29: 17
A30: 水 | B30: 15 | C30: =D30+F30+H30+J30 -> 0 | E30: =D30*T30 -> 0 | G30: =F30*U30 -> 0 | I30: =H30*V30 -> 0 | K30: =J30*W30 -> 0 | L30: =E30+G30+I30+K30 -> 0 | M30: =L30/C30 -> #DIV/0! | N30: ON2 | O30: 150 | Q30: =L30/P30 -> #DIV/0! | T30: 3300 | U30: 3800 | V30: 4800 | W30: 2000 | Y30: 水 | Z30: =B30 -> 15 | AA30: =AB30+AD30+AF30+AH30 -> 0 | AB30: =D30 -> 0 | AC30: =AB30*AR30 -> 0 | AD30: =F30 -> 0 | AE30: =AD30*AS30 -> 0 | AF30: =H30 -> 0 | AG30: =AF30*AT30 -> 0 | AH30: =J30 -> 0 | AI30: =AH30*AU30 -> 0 | AJ30: =AC30+AE30+AG30+AI30 -> 0 | AK30: =AJ30/AA30 -> #DIV/0! | AL30: =N30 -> ON2 | AM30: =O30 -> 150 | AN30: =P30 -> 0 | AO30: =(AJ30+BH30)/AN30 -> #DIV/0! | AR30: 1700 | AS30: 2200 | AT30: 2200 | AU30: 1400 | AW30: 水 | AX30: =B30 -> 15 | AY30: =C30 -> 0 | AZ30: 10 | BA30: =AZ30*BR30 -> 0 | BB30: 24 | BC30: =BB30*BS30 -> 0 | BD30: 12 | BE30: =BD30*BT30 -> 0 | BG30: =BF30*BU30 -> 0 | BH30: =L30 -> 0 | BI30: =M30 -> #DIV/0! | BJ30: =AJ30 -> 0 | BK30: =AK30 -> #DIV/0! | BL30: =BH30+BJ30 -> 0 | BM30: =BI30+BK30 -> #DIV/0! | BO30: =Q30+AO30 -> #DIV/0! | BV30: 水 | BW30: =AX30 -> 15 | BZ30: =BY30/BX30 -> #DIV/0! | CB30: =CA30/BX30 -> #DIV/0! | CE30: =BY30+CA30+CC30+CD30 -> 0 | CF30: =CE30/BX30 -> #DIV/0! | CJ30: =SUM(CG30:CI30) -> 0 | CK30: =CE30/CJ30 -> #DIV/0! | CR30: =SUM(CO30:CQ30)/3 -> 0 | CT30: 曇 | CV30: 2 | DA30: 16.9 | DB30: 25 | DC30: 5 | DD30: 2 | DE30: 4 | DF30: =SUM(DC30:DE30)/3 -> 3.6666667 | DH30: 曇 | DJ30: 2 | DO30: 18
A31: 木 | B31: 16 | C31: =D31+F31+H31+J31 -> 0 | E31: =D31*T31 -> 0 | G31: =F31*U31 -> 0 | I31: =H31*V31 -> 0 | K31: =J31*W31 -> 0 | L31: =E31+G31+I31+K31 -> 0 | M31: =L31/C31 -> #DIV/0! | N31: ON2 | O31: 150 | Q31: =L31/P31 -> #DIV/0! | T31: 3300 | U31: 3800 | V31: 4800 | W31: 2000 | Y31: 木 | Z31: =B31 -> 16 | AA31: =AB31+AD31+AF31+AH31 -> 0 | AB31: =D31 -> 0 | AC31: =AB31*AR31 -> 0 | AD31: =F31 -> 0 | AE31: =AD31*AS31 -> 0 | AF31: =H31 -> 0 | AG31: =AF31*AT31 -> 0 | AH31: =J31 -> 0 | AI31: =AH31*AU31 -> 0 | AJ31: =AC31+AE31+AG31+AI31 -> 0 | AK31: =AJ31/AA31 -> #DIV/0! | AL31: =N31 -> ON2 | AM31: =O31 -> 150 | AN31: =P31 -> 0 | AO31: =(AJ31+BH31)/AN31 -> #DIV/0! | AR31: 1700 | AS31: 2200 | AT31: 2200 | AU31: 1400 | AW31: 木 | AX31: =B31 -> 16 | AY31: =C31 -> 0 | AZ31: 10 | BA31: =AZ31*BR31 -> 0 | BB31: 24 | BC31: =BB31*BS31 -> 0 | BD31: 12 | BE31: =BD31*BT31 -> 0 | BG31: =BF31*BU31 -> 0 | BH31: =L31 -> 0 | BI31: =M31 -> #DIV/0! | BJ31: =AJ31 -> 0 | BK31: =AK31 -> #DIV/0! | BL31: =BH31+BJ31 -> 0 | BM31: =BI31+BK31 -> #DIV/0! | BO31: =Q31+AO31 -> #DIV/0! | BV31: 木 | BW31: =AX31 -> 16 | BZ31: =BY31/BX31 -> #DIV/0! | CB31: =CA31/BX31 -> #DIV/0! | CE31: =BY31+CA31+CC31+CD31 -> 0 | CF31: =CE31/BX31 -> #DIV/0! | CJ31: =SUM(CG31:CI31) -> 0 | CK31: =CE31/CJ31 -> #DIV/0! | CR31: =SUM(CO31:CQ31)/3 -> 0 | CT31: 雨 | CV31: 1 | DA31: 14 | DB31: 23.7 | DC31: 4 | DD31: 4 | DE31: 4 | DF31: =SUM(DC31:DE31)/3 -> 4 | DH31: 雨 | DJ31: 1 | DO31: 19
A32: 金 | B32: 17 | C32: =D32+F32+H32+J32 -> 0 | E32: =D32*T32 -> 0 | G32: =F32*U32 -> 0 | I32: =H32*V32 -> 0 | K32: =J32*W32 -> 0 | L32: =E32+G32+I32+K32 -> 0 | M32: =L32/C32 -> #DIV/0! | N32: ON1 | O32: 160 | Q32: =L32/P32 -> #DIV/0! | T32: 3300 | U32: 3800 | V32: 4800 | W32: 2000 | Y32: 金 | Z32: =B32 -> 17 | AA32: =AB32+AD32+AF32+AH32 -> 0 | AB32: =D32 -> 0 | AC32: =AB32*AR32 -> 0 | AD32: =F32 -> 0 | AE32: =AD32*AS32 -> 0 | AF32: =H32 -> 0 | AG32: =AF32*AT32 -> 0 | AH32: =J32 -> 0 | AI32: =AH32*AU32 -> 0 | AJ32: =AC32+AE32+AG32+AI32 -> 0 | AK32: =AJ32/AA32 -> #DIV/0! | AL32: =N32 -> ON1 | AM32: =O32 -> 160 | AN32: =P32 -> 0 | AO32: =(AJ32+BH32)/AN32 -> #DIV/0! | AR32: 1700 | AS32: 2200 | AT32: 2200 | AU32: 1400 | AW32: 金 | AX32: =B32 -> 17 | AY32: =C32 -> 0 | AZ32: 10 | BA32: =AZ32*BR32 -> 0 | BB32: 24 | BC32: =BB32*BS32 -> 0 | BD32: 12 | BE32: =BD32*BT32 -> 0 | BG32: =BF32*BU32 -> 0 | BH32: =L32 -> 0 | BI32: =M32 -> #DIV/0! | BJ32: =AJ32 -> 0 | BK32: =AK32 -> #DIV/0! | BL32: =BH32+BJ32 -> 0 | BM32: =BI32+BK32 -> #DIV/0! | BO32: =Q32+AO32 -> #DIV/0! | BV32: 金 | BW32: =AX32 -> 17 | BZ32: =BY32/BX32 -> #DIV/0! | CB32: =CA32/BX32 -> #DIV/0! | CE32: =BY32+CA32+CC32+CD32 -> 0 | CF32: =CE32/BX32 -> #DIV/0! | CJ32: =SUM(CG32:CI32) -> 0 | CK32: =CE32/CJ32 -> #DIV/0! | CR32: =SUM(CO32:CQ32)/3 -> 0 | CT32: 豪雨・雷雨 | CV32: 0 | DA32: 16.3 | DB32: 23 | DC32: 1 | DD32: 1 | DE32: 2 | DF32: =SUM(DC32:DE32)/3 -> 1.3333333 | DH32: 豪雨・雷雨 | DJ32: 0 | DO32: 20
A33: 土 | B33: 18 | C33: =D33+F33+H33+J33 -> 0 | E33: =D33*T33 -> 0 | G33: =F33*U33 -> 0 | I33: =H33*V33 -> 0 | K33: =J33*W33 -> 0 | L33: =E33+G33+I33+K33 -> 0 | M33: =L33/C33 -> #DIV/0! | N33: TOP1 | O33: 180 | Q33: =L33/P33 -> #DIV/0! | T33: 3300 | U33: 3800 | V33: 4800 | W33: 2000 | Y33: 土 | Z33: =B33 -> 18 | AA33: =AB33+AD33+AF33+AH33 -> 0 | AB33: =D33 -> 0 | AC33: =AB33*AR33 -> 0 | AD33: =F33 -> 0 | AE33: =AD33*AS33 -> 0 | AF33: =H33 -> 0 | AG33: =AF33*AT33 -> 0 | AH33: =J33 -> 0 | AI33: =AH33*AU33 -> 0 | AJ33: =AC33+AE33+AG33+AI33 -> 0 | AK33: =AJ33/AA33 -> #DIV/0! | AL33: =N33 -> TOP1 | AM33: =O33 -> 180 | AN33: =P33 -> 0 | AO33: =(AJ33+BH33)/AN33 -> #DIV/0! | AR33: 1700 | AS33: 2200 | AT33: 2200 | AU33: 1400 | AW33: 土 | AX33: =B33 -> 18 | AY33: =C33 -> 0 | AZ33: 10 | BA33: =AZ33*BR33 -> 0 | BB33: 28 | BC33: =BB33*BS33 -> 0 | BD33: 12 | BE33: =BD33*BT33 -> 0 | BG33: =BF33*BU33 -> 0 | BH33: =L33 -> 0 | BI33: =M33 -> #DIV/0! | BJ33: =AJ33 -> 0 | BK33: =AK33 -> #DIV/0! | BL33: =BH33+BJ33 -> 0 | BM33: =BI33+BK33 -> #DIV/0! | BO33: =Q33+AO33 -> #DIV/0! | BV33: 土 | BW33: =AX33 -> 18 | BZ33: =BY33/BX33 -> #DIV/0! | CB33: =CA33/BX33 -> #DIV/0! | CE33: =BY33+CA33+CC33+CD33 -> 0 | CF33: =CE33/BX33 -> #DIV/0! | CJ33: =SUM(CG33:CI33) -> 0 | CK33: =CE33/CJ33 -> #DIV/0! | CR33: =SUM(CO33:CQ33)/3 -> 0 | CT33: ※5.6月は18時は最低気温を採用。7月〜は最高気温を採用。 | DA33: 13.4 | DB33: 17.2 | DC33: 2 | DD33: 2 | DE33: 2 | DF33: =SUM(DC33:DE33)/3 -> 2 | DH33: ※5.6月は18時は最低気温を採用。7月〜は最高気温を採用。 | DO33: 21
A34: SUB TOTAL | C34: =SUM(C27:C33) -> 0 | D34: =SUM(D27:D33) -> 0 | E34: =SUM(E27:E33) -> 0 | F34: =SUM(F27:F33) -> 0 | G34: =SUM(G27:G33) -> 0 | H34: =SUM(H27:H33) -> 0 | I34: =SUM(I27:I33) -> 0 | J34: =SUM(J27:J33) -> 0 | ... L34: =SUM(L27:L33) -> 0 | M34: =L34/C34 -> #DIV/0! | O34: =SUM(O27:O33) -> 1110 | P34: =SUM(P27:P33) -> 0 | Q34: =L34/P34 -> #DIV/0! | T34: P/D | U34: =C34/W34 -> #DIV/0! | V34: 日にち | W34: 0 | Y34: SUB TOTAL | AA34: =SUM(AA27:AA33) -> 0 | AB34: =SUM(AB27:AB33) -> 0 | AC34: =SUM(AC27:AC33) -> 0 | AD34: =SUM(AD27:AD33) -> 0 | AE34: =SUM(AE27:AE33) -> 0 | AF34: =SUM(AF27:AF33) -> 0 | AG34: =SUM(AG27:AG33) -> 0 | AH34: =SUM(AH27:AH33) -> 0 | ... AJ34: =SUM(AJ27:AJ33) -> 0 | AK34: =AJ34/AA34 -> #DIV/0! | AM34: =SUM(AM27:AM33) -> 1110 | AN34: =SUM(AN27:AN33) -> 0 | AO34: =(AJ34+BH34)/AN34 -> #DIV/0! | AR34: P/D | AS34: =AA34/AU34 -> #DIV/0! | AT34: 日にち | AU34: =W34 -> 0 | AW34: SUB TOTAL | AY34: =C34 -> 0 | AZ34: =SUM(AZ27:AZ33) -> 84 | BA34: =SUM(BA27:BA33) -> 0 | BB34: =SUM(BB27:BB33) -> 120 | BC34: =SUM(BC27:BC33) -> 0 | BD34: =SUM(BD27:BD33) -> 60 | BE34: =SUM(BE27:BE33) -> 0 | BF34: =SUM(BF27:BF33) -> 0 | BG34: =SUM(BG27:BG33) -> 0 | BH34: =L34 -> 0 | BI34: =M34 -> #DIV/0! | BJ34: =AJ34 -> 0 | BK34: =AK34 -> #DIV/0! | BL34: =SUM(BL27:BL33) -> 0 | BM34: =BI34+BK34 -> #DIV/0! | BO34: =Q34+AO34 -> #DIV/0! | BR34: P/D | BS34: =AY34/BU34 -> #DIV/0! | BT34: 日にち | BU34: =W34 -> 0 | BV34: SUB TOTAL | BX34: =SUM(BX27:BX33) -> 0 | BY34: =SUM(BY27:BY33) -> 0 | BZ34: =BY34/BX34 -> #DIV/0! | CA34: =SUM(CA27:CA33) -> 0 | CB34: =CA34/BX34 -> #DIV/0! | CC34: =SUM(CC27:CC33) -> 0 | CD34: =SUM(CD27:CD33) -> 0 | CE34: =BY34+CA34+CC34+CD34 -> 0 | CF34: =CE34/BX34 -> #DIV/0! | CG34: =SUM(CG27:CG33) -> 0 | CH34: =SUM(CH27:CH33) -> 0 | CI34: =SUM(CI27:CI33) -> 0 | CJ34: =SUM(CJ27:CJ33) -> 0 | CK34: =CE34/CJ34 -> #DIV/0! | CL34: 2 | CM34: =SUM(CM27:CM33)/CL34 -> 16.65 | CN34: =SUM(CN27:CN33)/CL34 -> 26.35 | CO34: =SUM(CO27:CO33)/CL34 -> 5 | CP34: =SUM(CP27:CP33)/CL34 -> 4.5 | CQ34: =SUM(CQ27:CQ33)/CL34 -> 4.5 | CR34: =SUM(CO34:CQ34)/3 -> 4.6666667 | CS34: 14 | CT34: =CE34/CL34 -> 0 | CY34: ※1日平均売上 | CZ34: 7 | DA34: =SUM(DA27:DA33)/CZ34 -> 15.342857 | DB34: =SUM(DB27:DB33)/CZ34 -> 22.357143 | DC34: =SUM(DC27:DC33)/CZ34 -> 3 | DD34: =SUM(DD27:DD33)/CZ34 -> 2.1428571 | DE34: =SUM(DE27:DE33)/CZ34 -> 3.1428571 | DF34: =SUM(DC34:DE34)/3 -> 2.7619048 | DG34: 17 | DH34: =CV34/CZ34 -> 0 | DM34: ※1日平均売上
A35: 4th week | Y35: 4th week | AW35: 4th week | BV35: 4th week | CM35: =BV35 -> 4th week | DA35: =CM35 -> 4th week
A36: 曜日 | B36: 日にち | C36: 客数 | D36: MENU A 出卓 | E36: 売上 | F36: MENU B 出卓 | G36: 売上 | H36: MENU C 出卓 | I36: 売上 | J36: アラカルト利用数 | K36: 売上 | L36: 料理売上 | M36: 料理単価 | N36: モデルシフト | O36: モデルシフト時間数 | P36: 実時間数 | Q36: 人時売上高 | T36: A | U36: B | V36: C | W36: S | Y36: 曜日 | Z36: 日にち | AA36: 客数 | AB36: MENU A 出卓 | AC36: 売上 | AD36: MENU B 出卓 | AE36: 売上 | AF36: MENU C 出卓 | AG36: 売上 | AH36: アラカルト利用数 | AI36: 売上 | AJ36: 飲料売上 | AK36: 飲料単価 | AL36: モデルシフト | AM36: モデルシフト時間数 | AN36: 実時間数 | AO36: 人時売上高 | AR36: A | AS36: B | AT36: C | AU36: S | AW36: 曜日 | AX36: 日にち | AY36: 客数 | AZ36: MENU A 出卓 | BA36: 売上 | BB36: MENU B 出卓 | BC36: 売上 | BD36: MENU C 出卓 | BE36: 売上 | BF36: MENU S 出卓 | BG36: 売上 | BH36: 料理売上 | BI36: 料理単価 | BJ36: 飲料売上 | BK36: 飲料単価 | BL36: 合計売上予測 | BM36: 合計単価 | BO36: 人時売上高予測 | BR36: A | BS36: B | BT36: C | BU36: S | BV36: 曜日 | BW36: 日にち | BX36: 客数 | BY36: 料理売上 | BZ36: 料理単価 | CA36: 飲料売上 | CB36: 飲料単価 | CC36: その他売上 | CD36: 物販 | CE36: 売上合計 | CF36: 合計単価 | CG36: サーフィンズ | CH36: forking | CI36: Timee | CJ36: 合計 | CK36: 人時売上高 | CM36: 最低 | CN36: 最高 | CO36: 12時 | CP36: 15時 | CQ36: 18時 | CR36: Ave | CT36: ■天候要因 | CV36: 評価点 | DA36: 最低 | DB36: 最高 | DC36: 12時 | DD36: 15時 | DE36: 18時 | DF36: Ave | DH36: ■天候要因 | DJ36: 評価点
A37: 日 | B37: 19 | C37: =D37+F37+H37+J37 -> 0 | E37: =D37*T37 -> 0 | G37: =F37*U37 -> 0 | I37: =H37*V37 -> 0 | K37: =J37*W37 -> 0 | L37: =E37+G37+I37+K37 -> 0 | M37: =L37/C37 -> #DIV/0! | N37: TOP2 | O37: 170 | Q37: =L37/P37 -> #DIV/0! | T37: 3300 | U37: 3800 | V37: 4800 | W37: 2000 | Y37: 日 | Z37: =B37 -> 19 | AA37: =AB37+AD37+AF37+AH37 -> 0 | AB37: =D37 -> 0 | AC37: =AB37*AR37 -> 0 | AD37: =F37 -> 0 | AE37: =AD37*AS37 -> 0 | AF37: =H37 -> 0 | AG37: =AF37*AT37 -> 0 | AH37: =J37 -> 0 | AI37: =AH37*AU37 -> 0 | AJ37: =AC37+AE37+AG37+AI37 -> 0 | AK37: =AJ37/AA37 -> #DIV/0! | AL37: =N37 -> TOP2 | AM37: =O37 -> 170 | AN37: =P37 -> 0 | AO37: =(AJ37+BH37)/AN37 -> #DIV/0! | AR37: 1700 | AS37: 2200 | AT37: 2200 | AU37: 1400 | AW37: 日 | AX37: =B37 -> 19 | AY37: =C37 -> 0 | BA37: =AZ37*BR37 -> 0 | BC37: =BB37*BS37 -> 0 | BE37: =BD37*BT37 -> 0 | BG37: =BF37*BU37 -> 0 | BH37: =L37 -> 0 | BI37: =M37 -> #DIV/0! | BJ37: =AJ37 -> 0 | BK37: =AK37 -> #DIV/0! | BL37: =BH37+BJ37 -> 0 | BM37: =BI37+BK37 -> #DIV/0! | BO37: =Q37+AO37 -> #DIV/0! | BV37: 日 | BW37: =AX37 -> 19 | BZ37: =BY37/BX37 -> #DIV/0! | CB37: =CA37/BX37 -> #DIV/0! | CE37: =BY37+CA37+CC37+CD37 -> 0 | CF37: =CE37/BX37 -> #DIV/0! | CJ37: =SUM(CG37:CI37) -> 0 | CK37: =CE37/CJ37 -> #DIV/0! | CR37: =SUM(CO37:CQ37)/3 -> 0 | CT37: 晴れ（33度まで） | CV37: 5 | DA37: 11.2 | DB37: 17.3 | DC37: 2 | DD37: 2 | DE37: 2 | DF37: =SUM(DC37:DE37)/3 -> 2 | DH37: 晴れ（33度まで） | DJ37: 5 | DO37: 22
A38: 月 | B38: 20 | C38: =D38+F38+H38+J38 -> 0 | E38: =D38*T38 -> 0 | G38: =F38*U38 -> 0 | I38: =H38*V38 -> 0 | K38: =J38*W38 -> 0 | L38: =E38+G38+I38+K38 -> 0 | M38: =L38/C38 -> #DIV/0! | N38: ON2 | O38: 150 | Q38: =L38/P38 -> #DIV/0! | T38: 3300 | U38: 3800 | V38: 4800 | W38: 2000 | Y38: 月 | Z38: =B38 -> 20 | AA38: =AB38+AD38+AF38+AH38 -> 0 | AB38: =D38 -> 0 | AC38: =AB38*AR38 -> 0 | AD38: =F38 -> 0 | AE38: =AD38*AS38 -> 0 | AF38: =H38 -> 0 | AG38: =AF38*AT38 -> 0 | AH38: =J38 -> 0 | AI38: =AH38*AU38 -> 0 | AJ38: =AC38+AE38+AG38+AI38 -> 0 | AK38: =AJ38/AA38 -> #DIV/0! | AL38: =N38 -> ON2 | AM38: =O38 -> 150 | AN38: =P38 -> 0 | AO38: =(AJ38+BH38)/AN38 -> #DIV/0! | AR38: 1700 | AS38: 2200 | AT38: 2200 | AU38: 1400 | AW38: 月 | AX38: =B38 -> 20 | AY38: =C38 -> 0 | AZ38: 22 | BA38: =AZ38*BR38 -> 0 | BB38: 10 | BC38: =BB38*BS38 -> 0 | BD38: 6 | BE38: =BD38*BT38 -> 0 | BG38: =BF38*BU38 -> 0 | BH38: =L38 -> 0 | BI38: =M38 -> #DIV/0! | BJ38: =AJ38 -> 0 | BK38: =AK38 -> #DIV/0! | BL38: =BH38+BJ38 -> 0 | BM38: =BI38+BK38 -> #DIV/0! | BO38: =Q38+AO38 -> #DIV/0! | BV38: 月 | BW38: =AX38 -> 20 | BZ38: =BY38/BX38 -> #DIV/0! | CB38: =CA38/BX38 -> #DIV/0! | CE38: =BY38+CA38+CC38+CD38 -> 0 | CF38: =CE38/BX38 -> #DIV/0! | CJ38: =SUM(CG38:CI38) -> 0 | CK38: =CE38/CJ38 -> #DIV/0! | CR38: =SUM(CO38:CQ38)/3 -> 0 | CT38: 晴れ（25度以下） | CV38: 4 | DA38: 10 | DB38: 19.8 | DC38: 4 | DD38: 4 | DE38: 4 | DF38: =SUM(DC38:DE38)/3 -> 4 | DH38: 晴れ（25度以下） | DJ38: 4 | DO38: 23
A39: 火 | B39: 21 | C39: =D39+F39+H39+J39 -> 0 | E39: =D39*T39 -> 0 | G39: =F39*U39 -> 0 | I39: =H39*V39 -> 0 | K39: =J39*W39 -> 0 | L39: =E39+G39+I39+K39 -> 0 | M39: =L39/C39 -> #DIV/0! | N39: ON2 | O39: 150 | Q39: =L39/P39 -> #DIV/0! | T39: 3300 | U39: 3800 | V39: 4800 | W39: 2000 | Y39: 火 | Z39: =B39 -> 21 | AA39: =AB39+AD39+AF39+AH39 -> 0 | AB39: =D39 -> 0 | AC39: =AB39*AR39 -> 0 | AD39: =F39 -> 0 | AE39: =AD39*AS39 -> 0 | AF39: =H39 -> 0 | AG39: =AF39*AT39 -> 0 | AH39: =J39 -> 0 | AI39: =AH39*AU39 -> 0 | AJ39: =AC39+AE39+AG39+AI39 -> 0 | AK39: =AJ39/AA39 -> #DIV/0! | AL39: =N39 -> ON2 | AM39: =O39 -> 150 | AN39: =P39 -> 0 | AO39: =(AJ39+BH39)/AN39 -> #DIV/0! | AR39: 1700 | AS39: 2200 | AT39: 2200 | AU39: 1400 | AW39: 火 | AX39: =B39 -> 21 | AY39: =C39 -> 0 | AZ39: 22 | BA39: =AZ39*BR39 -> 0 | BB39: 10 | BC39: =BB39*BS39 -> 0 | BD39: 6 | BE39: =BD39*BT39 -> 0 | BG39: =BF39*BU39 -> 0 | BH39: =L39 -> 0 | BI39: =M39 -> #DIV/0! | BJ39: =AJ39 -> 0 | BK39: =AK39 -> #DIV/0! | BL39: =BH39+BJ39 -> 0 | BM39: =BI39+BK39 -> #DIV/0! | BO39: =Q39+AO39 -> #DIV/0! | BV39: 火 | BW39: =AX39 -> 21 | BZ39: =BY39/BX39 -> #DIV/0! | CB39: =CA39/BX39 -> #DIV/0! | CE39: =BY39+CA39+CC39+CD39 -> 0 | CF39: =CE39/BX39 -> #DIV/0! | CJ39: =SUM(CG39:CI39) -> 0 | CK39: =CE39/CJ39 -> #DIV/0! | CR39: =SUM(CO39:CQ39)/3 -> 0 | CT39: 晴れ（33度以上）曇25度以上 | CV39: 3 | DA39: 10.1 | DB39: 22.2 | DC39: 4 | DD39: 4 | DE39: 4 | DF39: =SUM(DC39:DE39)/3 -> 4 | DH39: 晴れ（33度以上）曇25度以上 | DJ39: 3 | DO39: 24
A40: 水 | B40: 22 | C40: =D40+F40+H40+J40 -> 0 | E40: =D40*T40 -> 0 | G40: =F40*U40 -> 0 | I40: =H40*V40 -> 0 | K40: =J40*W40 -> 0 | L40: =E40+G40+I40+K40 -> 0 | M40: =L40/C40 -> #DIV/0! | N40: ON2 | O40: 150 | Q40: =L40/P40 -> #DIV/0! | T40: 3300 | U40: 3800 | V40: 4800 | W40: 2000 | Y40: 水 | Z40: =B40 -> 22 | AA40: =AB40+AD40+AF40+AH40 -> 0 | AB40: =D40 -> 0 | AC40: =AB40*AR40 -> 0 | AD40: =F40 -> 0 | AE40: =AD40*AS40 -> 0 | AF40: =H40 -> 0 | AG40: =AF40*AT40 -> 0 | AH40: =J40 -> 0 | AI40: =AH40*AU40 -> 0 | AJ40: =AC40+AE40+AG40+AI40 -> 0 | AK40: =AJ40/AA40 -> #DIV/0! | AL40: =N40 -> ON2 | AM40: =O40 -> 150 | AN40: =P40 -> 0 | AO40: =(AJ40+BH40)/AN40 -> #DIV/0! | AR40: 1700 | AS40: 2200 | AT40: 2200 | AU40: 1400 | AW40: 水 | AX40: =B40 -> 22 | AY40: =C40 -> 0 | AZ40: 10 | BA40: =AZ40*BR40 -> 0 | BB40: 24 | BC40: =BB40*BS40 -> 0 | BD40: 12 | BE40: =BD40*BT40 -> 0 | BG40: =BF40*BU40 -> 0 | BH40: =L40 -> 0 | BI40: =M40 -> #DIV/0! | BJ40: =AJ40 -> 0 | BK40: =AK40 -> #DIV/0! | BL40: =BH40+BJ40 -> 0 | BM40: =BI40+BK40 -> #DIV/0! | BO40: =Q40+AO40 -> #DIV/0! | BV40: 水 | BW40: =AX40 -> 22 | BZ40: =BY40/BX40 -> #DIV/0! | CB40: =CA40/BX40 -> #DIV/0! | CE40: =BY40+CA40+CC40+CD40 -> 0 | CF40: =CE40/BX40 -> #DIV/0! | CJ40: =SUM(CG40:CI40) -> 0 | CK40: =CE40/CJ40 -> #DIV/0! | CR40: =SUM(CO40:CQ40)/3 -> 0 | CT40: 曇 | CV40: 2 | DA40: 13.6 | DB40: 21 | DC40: 4 | DD40: 4 | DE40: 2 | DF40: =SUM(DC40:DE40)/3 -> 3.3333333 | DH40: 曇 | DJ40: 2 | DO40: 25
A41: 木 | B41: 23 | C41: =D41+F41+H41+J41 -> 0 | E41: =D41*T41 -> 0 | G41: =F41*U41 -> 0 | I41: =H41*V41 -> 0 | K41: =J41*W41 -> 0 | L41: =E41+G41+I41+K41 -> 0 | M41: =L41/C41 -> #DIV/0! | N41: ON2 | O41: 150 | Q41: =L41/P41 -> #DIV/0! | T41: 3300 | U41: 3800 | V41: 4800 | W41: 2000 | Y41: 木 | Z41: =B41 -> 23 | AA41: =AB41+AD41+AF41+AH41 -> 0 | AB41: =D41 -> 0 | AC41: =AB41*AR41 -> 0 | AD41: =F41 -> 0 | AE41: =AD41*AS41 -> 0 | AF41: =H41 -> 0 | AG41: =AF41*AT41 -> 0 | AH41: =J41 -> 0 | AI41: =AH41*AU41 -> 0 | AJ41: =AC41+AE41+AG41+AI41 -> 0 | AK41: =AJ41/AA41 -> #DIV/0! | AL41: =N41 -> ON2 | AM41: =O41 -> 150 | AN41: =P41 -> 0 | AO41: =(AJ41+BH41)/AN41 -> #DIV/0! | AR41: 1700 | AS41: 2200 | AT41: 2200 | AU41: 1400 | AW41: 木 | AX41: =B41 -> 23 | AY41: =C41 -> 0 | AZ41: 10 | BA41: =AZ41*BR41 -> 0 | BB41: 24 | BC41: =BB41*BS41 -> 0 | BD41: 12 | BE41: =BD41*BT41 -> 0 | BG41: =BF41*BU41 -> 0 | BH41: =L41 -> 0 | BI41: =M41 -> #DIV/0! | BJ41: =AJ41 -> 0 | BK41: =AK41 -> #DIV/0! | BL41: =BH41+BJ41 -> 0 | BM41: =BI41+BK41 -> #DIV/0! | BO41: =Q41+AO41 -> #DIV/0! | BV41: 木 | BW41: =AX41 -> 23 | BZ41: =BY41/BX41 -> #DIV/0! | CB41: =CA41/BX41 -> #DIV/0! | CE41: =BY41+CA41+CC41+CD41 -> 0 | CF41: =CE41/BX41 -> #DIV/0! | CJ41: =SUM(CG41:CI41) -> 0 | CK41: =CE41/CJ41 -> #DIV/0! | CR41: =SUM(CO41:CQ41)/3 -> 0 | CT41: 雨 | CV41: 1 | DA41: 17.3 | DB41: 24.4 | DC41: 4 | DD41: 4 | DE41: 4 | DF41: =SUM(DC41:DE41)/3 -> 4 | DH41: 雨 | DJ41: 1 | DO41: 26
A42: 金 | B42: 24 | C42: =D42+F42+H42+J42 -> 0 | E42: =D42*T42 -> 0 | G42: =F42*U42 -> 0 | I42: =H42*V42 -> 0 | K42: =J42*W42 -> 0 | L42: =E42+G42+I42+K42 -> 0 | M42: =L42/C42 -> #DIV/0! | N42: ON1 | O42: 160 | Q42: =L42/P42 -> #DIV/0! | T42: 3300 | U42: 3800 | V42: 4800 | W42: 2000 | Y42: 金 | Z42: =B42 -> 24 | AA42: =AB42+AD42+AF42+AH42 -> 0 | AB42: =D42 -> 0 | AC42: =AB42*AR42 -> 0 | AD42: =F42 -> 0 | AE42: =AD42*AS42 -> 0 | AF42: =H42 -> 0 | AG42: =AF42*AT42 -> 0 | AH42: =J42 -> 0 | AI42: =AH42*AU42 -> 0 | AJ42: =AC42+AE42+AG42+AI42 -> 0 | AK42: =AJ42/AA42 -> #DIV/0! | AL42: =N42 -> ON1 | AM42: =O42 -> 160 | AN42: =P42 -> 0 | AO42: =(AJ42+BH42)/AN42 -> #DIV/0! | AR42: 1700 | AS42: 2200 | AT42: 2200 | AU42: 1400 | AW42: 金 | AX42: =B42 -> 24 | AY42: =C42 -> 0 | AZ42: 10 | BA42: =AZ42*BR42 -> 0 | BB42: 24 | BC42: =BB42*BS42 -> 0 | BD42: 12 | BE42: =BD42*BT42 -> 0 | BG42: =BF42*BU42 -> 0 | BH42: =L42 -> 0 | BI42: =M42 -> #DIV/0! | BJ42: =AJ42 -> 0 | BK42: =AK42 -> #DIV/0! | BL42: =BH42+BJ42 -> 0 | BM42: =BI42+BK42 -> #DIV/0! | BO42: =Q42+AO42 -> #DIV/0! | BV42: 金 | BW42: =AX42 -> 24 | BZ42: =BY42/BX42 -> #DIV/0! | CB42: =CA42/BX42 -> #DIV/0! | CE42: =BY42+CA42+CC42+CD42 -> 0 | CF42: =CE42/BX42 -> #DIV/0! | CJ42: =SUM(CG42:CI42) -> 0 | CK42: =CE42/CJ42 -> #DIV/0! | CR42: =SUM(CO42:CQ42)/3 -> 0 | CT42: 豪雨・雷雨 | CV42: 0 | DA42: 17.8 | DB42: 23.8 | DC42: 2 | DD42: 4 | DE42: 4 | DF42: =SUM(DC42:DE42)/3 -> 3.3333333 | DH42: 豪雨・雷雨 | DJ42: 0 | DO42: 27
A43: 土 | B43: 25 | C43: =D43+F43+H43+J43 -> 0 | E43: =D43*T43 -> 0 | G43: =F43*U43 -> 0 | I43: =H43*V43 -> 0 | K43: =J43*W43 -> 0 | L43: =E43+G43+I43+K43 -> 0 | M43: =L43/C43 -> #DIV/0! | N43: TOP1 | O43: 180 | Q43: =L43/P43 -> #DIV/0! | T43: 3300 | U43: 3800 | V43: 4800 | W43: 2000 | Y43: 土 | Z43: =B43 -> 25 | AA43: =AB43+AD43+AF43+AH43 -> 0 | AB43: =D43 -> 0 | AC43: =AB43*AR43 -> 0 | AD43: =F43 -> 0 | AE43: =AD43*AS43 -> 0 | AF43: =H43 -> 0 | AG43: =AF43*AT43 -> 0 | AH43: =J43 -> 0 | AI43: =AH43*AU43 -> 0 | AJ43: =AC43+AE43+AG43+AI43 -> 0 | AK43: =AJ43/AA43 -> #DIV/0! | AL43: =N43 -> TOP1 | AM43: =O43 -> 180 | AN43: =P43 -> 0 | AO43: =(AJ43+BH43)/AN43 -> #DIV/0! | AR43: 1700 | AS43: 2200 | AT43: 2200 | AU43: 1400 | AW43: 土 | AX43: =B43 -> 25 | AY43: =C43 -> 0 | AZ43: 10 | BA43: =AZ43*BR43 -> 0 | BB43: 28 | BC43: =BB43*BS43 -> 0 | BD43: 12 | BE43: =BD43*BT43 -> 0 | BG43: =BF43*BU43 -> 0 | BH43: =L43 -> 0 | BI43: =M43 -> #DIV/0! | BJ43: =AJ43 -> 0 | BK43: =AK43 -> #DIV/0! | BL43: =BH43+BJ43 -> 0 | BM43: =BI43+BK43 -> #DIV/0! | BO43: =Q43+AO43 -> #DIV/0! | BV43: 土 | BW43: =AX43 -> 25 | BZ43: =BY43/BX43 -> #DIV/0! | CB43: =CA43/BX43 -> #DIV/0! | CE43: =BY43+CA43+CC43+CD43 -> 0 | CF43: =CE43/BX43 -> #DIV/0! | CJ43: =SUM(CG43:CI43) -> 0 | CK43: =CE43/CJ43 -> #DIV/0! | CR43: =SUM(CO43:CQ43)/3 -> 0 | CT43: ※5.6月は18時は最低気温を採用。7月〜は最高気温を採用。 | DA43: 16.2 | DB43: 22.5 | DC43: 4 | DD43: 4 | DE43: 4 | DF43: =SUM(DC43:DE43)/3 -> 4 | DH43: ※5.6月は18時は最低気温を採用。7月〜は最高気温を採用。 | DO43: 28
A44: SUB TOTAL | C44: =SUM(C37:C43) -> 0 | D44: =SUM(D37:D43) -> 0 | E44: =SUM(E37:E43) -> 0 | F44: =SUM(F37:F43) -> 0 | G44: =SUM(G37:G43) -> 0 | H44: =SUM(H37:H43) -> 0 | I44: =SUM(I37:I43) -> 0 | J44: =SUM(J37:J43) -> 0 | ... L44: =SUM(L37:L43) -> 0 | M44: =L44/C44 -> #DIV/0! | O44: =SUM(O37:O43) -> 1110 | P44: =SUM(P37:P43) -> 0 | Q44: =L44/P44 -> #DIV/0! | T44: P/D | U44: =C44/W44 -> #DIV/0! | V44: 日にち | W44: 0 | Y44: SUB TOTAL | AA44: =SUM(AA37:AA43) -> 0 | AB44: =SUM(AB37:AB43) -> 0 | AC44: =SUM(AC37:AC43) -> 0 | AD44: =SUM(AD37:AD43) -> 0 | AE44: =SUM(AE37:AE43) -> 0 | AF44: =SUM(AF37:AF43) -> 0 | AG44: =SUM(AG37:AG43) -> 0 | AH44: =SUM(AH37:AH43) -> 0 | ... AJ44: =SUM(AJ37:AJ43) -> 0 | AK44: =AJ44/AA44 -> #DIV/0! | AM44: =SUM(AM37:AM43) -> 1110 | AN44: =SUM(AN37:AN43) -> 0 | AO44: =(AJ44+BH44)/AN44 -> #DIV/0! | AR44: P/D | AS44: =AA44/AU44 -> #DIV/0! | AT44: 日にち | AU44: =W44 -> 0 | AW44: SUB TOTAL | AY44: =C44 -> 0 | AZ44: =SUM(AZ37:AZ43) -> 84 | BA44: =SUM(BA37:BA43) -> 0 | BB44: =SUM(BB37:BB43) -> 120 | BC44: =SUM(BC37:BC43) -> 0 | BD44: =SUM(BD37:BD43) -> 60 | BE44: =SUM(BE37:BE43) -> 0 | BF44: =SUM(BF37:BF43) -> 0 | BG44: =SUM(BG37:BG43) -> 0 | BH44: =L44 -> 0 | BI44: =M44 -> #DIV/0! | BJ44: =AJ44 -> 0 | BK44: =AK44 -> #DIV/0! | BL44: =SUM(BL37:BL43) -> 0 | BM44: =BI44+BK44 -> #DIV/0! | BO44: =Q44+AO44 -> #DIV/0! | BR44: P/D | BS44: =AY44/BU44 -> #DIV/0! | BT44: 日にち | BU44: =W44 -> 0 | BV44: SUB TOTAL | BX44: =SUM(BX37:BX43) -> 0 | BY44: =SUM(BY37:BY43) -> 0 | BZ44: =BY44/BX44 -> #DIV/0! | CA44: =SUM(CA37:CA43) -> 0 | CB44: =CA44/BX44 -> #DIV/0! | CC44: =SUM(CC37:CC43) -> 0 | CD44: =SUM(CD37:CD43) -> 0 | CE44: =BY44+CA44+CC44+CD44 -> 0 | CF44: =CE44/BX44 -> #DIV/0! | CG44: =SUM(CG37:CG43) -> 0 | CH44: =SUM(CH37:CH43) -> 0 | CI44: =SUM(CI37:CI43) -> 0 | CJ44: =SUM(CJ37:CJ43) -> 0 | CK44: =CE44/CJ44 -> #DIV/0! | CM44: =SUM(CM37:CM43)/CL44 -> #DIV/0! | CN44: =SUM(CN37:CN43)/CL44 -> #DIV/0! | CO44: =SUM(CO37:CO43)/CL44 -> #DIV/0! | CP44: =SUM(CP37:CP43)/CL44 -> #DIV/0! | CQ44: =SUM(CQ37:CQ43)/CL44 -> #DIV/0! | CR44: =SUM(CO44:CQ44)/3 -> #DIV/0! | CS44: ⑨ | CT44: =CE44/CL44 -> #DIV/0! | CY44: ※1日平均売上 | CZ44: 7 | DA44: =SUM(DA37:DA43)/CZ44 -> 13.742857 | DB44: =SUM(DB37:DB43)/CZ44 -> 21.571429 | DC44: =SUM(DC37:DC43)/CZ44 -> 3.4285714 | DD44: =SUM(DD37:DD43)/CZ44 -> 3.7142857 | DE44: =SUM(DE37:DE43)/CZ44 -> 3.4285714 | DF44: =SUM(DC44:DE44)/3 -> 3.5238095 | DH44: =CV44/CZ44 -> 0 | DM44: ※1日平均売上
A45: 5th week | Y45: 5th week | AW45: 5th week | BV45: 5th week | CM45: =BV45 -> 5th week | DA45: =CM45 -> 5th week
A46: 曜日 | B46: 日にち | C46: 客数 | D46: MENU A 出卓 | E46: 売上 | F46: MENU B 出卓 | G46: 売上 | H46: MENU C 出卓 | I46: 売上 | J46: アラカルト利用数 | K46: 売上 | L46: 料理売上 | M46: 料理単価 | N46: モデルシフト | O46: モデルシフト時間数 | P46: 実時間数 | Q46: 人時売上高 | T46: A | U46: B | V46: C | W46: S | Y46: 曜日 | Z46: 日にち | AA46: 客数 | AB46: MENU A 出卓 | AC46: 売上 | AD46: MENU B 出卓 | AE46: 売上 | AF46: MENU C 出卓 | AG46: 売上 | AH46: アラカルト利用数 | AI46: 売上 | AJ46: 飲料売上 | AK46: 飲料単価 | AL46: モデルシフト | AM46: モデルシフト時間数 | AN46: 実時間数 | AO46: 人時売上高 | AR46: A | AS46: B | AT46: C | AU46: S | AW46: 曜日 | AX46: 日にち | AY46: 客数 | AZ46: MENU A 出卓 | BA46: 売上 | BB46: MENU B 出卓 | BC46: 売上 | BD46: MENU C 出卓 | BE46: 売上 | BF46: MENU S 出卓 | BG46: 売上 | BH46: 料理売上 | BI46: 料理単価 | BJ46: 飲料売上 | BK46: 飲料単価 | BL46: 合計売上予測 | BM46: 合計単価 | BO46: 人時売上高予測 | BR46: A | BS46: B | BT46: C | BU46: S | BV46: 曜日 | BW46: 日にち | BX46: 客数 | BY46: 料理売上 | BZ46: 料理単価 | CA46: 飲料売上 | CB46: 飲料単価 | CC46: その他売上 | CD46: 物販 | CE46: 売上合計 | CF46: 合計単価 | CG46: サーフィンズ | CH46: forking | CI46: Timee | CJ46: 合計 | CK46: 人時売上高 | CM46: 最低 | CN46: 最高 | CO46: 12時 | CP46: 15時 | CQ46: 18時 | CR46: Ave | CT46: ■天候要因 | CV46: 評価点 | DA46: 最低 | DB46: 最高 | DC46: 12時 | DD46: 15時 | DE46: 18時 | DF46: Ave | DH46: ■天候要因 | DJ46: 評価点
A47: 日 | B47: 26 | C47: =D47+F47+H47+J47 -> 0 | E47: =D47*T47 -> 0 | G47: =F47*U47 -> 0 | I47: =H47*V47 -> 0 | K47: =J47*W47 -> 0 | L47: =E47+G47+I47+K47 -> 0 | M47: =L47/C47 -> #DIV/0! | N47: TOP2 | O47: 170 | Q47: =L47/P47 -> #DIV/0! | T47: 3300 | U47: 3800 | V47: 4800 | W47: 2000 | Y47: 日 | Z47: =B47 -> 26 | AA47: =AB47+AD47+AF47+AH47 -> 0 | AB47: =D47 -> 0 | AC47: =AB47*AR47 -> 0 | AD47: =F47 -> 0 | AE47: =AD47*AS47 -> 0 | AF47: =H47 -> 0 | AG47: =AF47*AT47 -> 0 | AH47: =J47 -> 0 | AI47: =AH47*AU47 -> 0 | AJ47: =AC47+AE47+AG47+AI47 -> 0 | AK47: =AJ47/AA47 -> #DIV/0! | AL47: =N47 -> TOP2 | AM47: =O47 -> 170 | AN47: =P47 -> 0 | AO47: =(AJ47+BH47)/AN47 -> #DIV/0! | AR47: 1700 | AS47: 2200 | AT47: 2200 | AU47: 1400 | AW47: 日 | AX47: =B47 -> 26 | AY47: =C47 -> 0 | BA47: =AZ47*BR47 -> 0 | BC47: =BB47*BS47 -> 0 | BE47: =BD47*BT47 -> 0 | BG47: =BF47*BU47 -> 0 | BH47: =L47 -> 0 | BI47: =M47 -> #DIV/0! | BJ47: =AJ47 -> 0 | BK47: =AK47 -> #DIV/0! | BL47: =BH47+BJ47 -> 0 | BM47: =BI47+BK47 -> #DIV/0! | BO47: =Q47+AO47 -> #DIV/0! | BV47: 日 | BW47: =AX47 -> 26 | BZ47: =BY47/BX47 -> #DIV/0! | CB47: =CA47/BX47 -> #DIV/0! | CE47: =BY47+CA47+CC47+CD47 -> 0 | CF47: =CE47/BX47 -> #DIV/0! | CJ47: =SUM(CG47:CI47) -> 0 | CK47: =CE47/CJ47 -> #DIV/0! | CR47: =SUM(CO47:CQ47)/3 -> 0 | CT47: 晴れ（33度まで） | CV47: 5 | DA47: 12.5 | DB47: 23 | DC47: 4 | DD47: 4 | DE47: 4 | DF47: =SUM(DC47:DE47)/3 -> 4 | DH47: 晴れ（33度まで） | DJ47: 5 | DO47: 29
A48: 月 | B48: 27 | C48: =D48+F48+H48+J48 -> 0 | E48: =D48*T48 -> 0 | G48: =F48*U48 -> 0 | I48: =H48*V48 -> 0 | K48: =J48*W48 -> 0 | L48: =E48+G48+I48+K48 -> 0 | M48: =L48/C48 -> #DIV/0! | N48: ON2 | O48: 150 | Q48: =L48/P48 -> #DIV/0! | T48: 3300 | U48: 3800 | V48: 4800 | W48: 2000 | Y48: 月 | Z48: =B48 -> 27 | AA48: =AB48+AD48+AF48+AH48 -> 0 | AB48: =D48 -> 0 | AC48: =AB48*AR48 -> 0 | AD48: =F48 -> 0 | AE48: =AD48*AS48 -> 0 | AF48: =H48 -> 0 | AG48: =AF48*AT48 -> 0 | AH48: =J48 -> 0 | AI48: =AH48*AU48 -> 0 | AJ48: =AC48+AE48+AG48+AI48 -> 0 | AK48: =AJ48/AA48 -> #DIV/0! | AL48: =N48 -> ON2 | AM48: =O48 -> 150 | AN48: =P48 -> 0 | AO48: =(AJ48+BH48)/AN48 -> #DIV/0! | AR48: 1700 | AS48: 2200 | AT48: 2200 | AU48: 1400 | AW48: 月 | AX48: =B48 -> 27 | AY48: =C48 -> 0 | AZ48: 22 | BA48: =AZ48*BR48 -> 0 | BB48: 10 | BC48: =BB48*BS48 -> 0 | BD48: 6 | BE48: =BD48*BT48 -> 0 | BG48: =BF48*BU48 -> 0 | BH48: =L48 -> 0 | BI48: =M48 -> #DIV/0! | BJ48: =AJ48 -> 0 | BK48: =AK48 -> #DIV/0! | BL48: =BH48+BJ48 -> 0 | BM48: =BI48+BK48 -> #DIV/0! | BO48: =Q48+AO48 -> #DIV/0! | BV48: 月 | BW48: =AX48 -> 27 | BZ48: =BY48/BX48 -> #DIV/0! | CB48: =CA48/BX48 -> #DIV/0! | CE48: =BY48+CA48+CC48+CD48 -> 0 | CF48: =CE48/BX48 -> #DIV/0! | CJ48: =SUM(CG48:CI48) -> 0 | CK48: =CE48/CJ48 -> #DIV/0! | CR48: =SUM(CO48:CQ48)/3 -> 0 | CT48: 晴れ（25度以下） | CV48: 4 | DA48: 14.3 | DB48: 22.3 | DC48: 4 | DD48: 4 | DE48: 4 | DF48: =SUM(DC48:DE48)/3 -> 4 | DH48: 晴れ（25度以下） | DJ48: 4 | DO48: 30
A49: 火 | B49: 28 | C49: =D49+F49+H49+J49 -> 0 | E49: =D49*T49 -> 0 | G49: =F49*U49 -> 0 | I49: =H49*V49 -> 0 | K49: =J49*W49 -> 0 | L49: =E49+G49+I49+K49 -> 0 | M49: =L49/C49 -> #DIV/0! | N49: ON2 | O49: 150 | Q49: =L49/P49 -> #DIV/0! | T49: 3300 | U49: 3800 | V49: 4800 | W49: 2000 | Y49: 火 | Z49: =B49 -> 28 | AA49: =AB49+AD49+AF49+AH49 -> 0 | AB49: =D49 -> 0 | AC49: =AB49*AR49 -> 0 | AD49: =F49 -> 0 | AE49: =AD49*AS49 -> 0 | AF49: =H49 -> 0 | AG49: =AF49*AT49 -> 0 | AH49: =J49 -> 0 | AI49: =AH49*AU49 -> 0 | AJ49: =AC49+AE49+AG49+AI49 -> 0 | AK49: =AJ49/AA49 -> #DIV/0! | AL49: =N49 -> ON2 | AM49: =O49 -> 150 | AN49: =P49 -> 0 | AO49: =(AJ49+BH49)/AN49 -> #DIV/0! | AR49: 1700 | AS49: 2200 | AT49: 2200 | AU49: 1400 | AW49: 火 | AX49: =B49 -> 28 | AY49: =C49 -> 0 | AZ49: 22 | BA49: =AZ49*BR49 -> 0 | BB49: 10 | BC49: =BB49*BS49 -> 0 | BD49: 6 | BE49: =BD49*BT49 -> 0 | BG49: =BF49*BU49 -> 0 | BH49: =L49 -> 0 | BI49: =M49 -> #DIV/0! | BJ49: =AJ49 -> 0 | BK49: =AK49 -> #DIV/0! | BL49: =BH49+BJ49 -> 0 | BM49: =BI49+BK49 -> #DIV/0! | BO49: =Q49+AO49 -> #DIV/0! | BV49: 火 | BW49: =AX49 -> 28 | BZ49: =BY49/BX49 -> #DIV/0! | CB49: =CA49/BX49 -> #DIV/0! | CE49: =BY49+CA49+CC49+CD49 -> 0 | CF49: =CE49/BX49 -> #DIV/0! | CJ49: =SUM(CG49:CI49) -> 0 | CK49: =CE49/CJ49 -> #DIV/0! | CR49: =SUM(CO49:CQ49)/3 -> 0 | CT49: 晴れ（33度以上）曇25度以上 | CV49: 3 | DF49: =SUM(DC49:DE49)/3 -> 0 | DH49: 晴れ（33度以上）曇25度以上 | DJ49: 3 | DO49: =B49 -> 28
A50: 水 | B50: 29 | C50: =D50+F50+H50+J50 -> 0 | E50: =D50*T50 -> 0 | G50: =F50*U50 -> 0 | I50: =H50*V50 -> 0 | K50: =J50*W50 -> 0 | L50: =E50+G50+I50+K50 -> 0 | M50: =L50/C50 -> #DIV/0! | N50: ON2 | O50: 150 | Q50: =L50/P50 -> #DIV/0! | T50: 3300 | U50: 3800 | V50: 4800 | W50: 2000 | Y50: 水 | Z50: =B50 -> 29 | AA50: =AB50+AD50+AF50+AH50 -> 0 | AB50: =D50 -> 0 | AC50: =AB50*AR50 -> 0 | AD50: =F50 -> 0 | AE50: =AD50*AS50 -> 0 | AF50: =H50 -> 0 | AG50: =AF50*AT50 -> 0 | AH50: =J50 -> 0 | AI50: =AH50*AU50 -> 0 | AJ50: =AC50+AE50+AG50+AI50 -> 0 | AK50: =AJ50/AA50 -> #DIV/0! | AL50: =N50 -> ON2 | AM50: =O50 -> 150 | AN50: =P50 -> 0 | AO50: =(AJ50+BH50)/AN50 -> #DIV/0! | AR50: 1700 | AS50: 2200 | AT50: 2200 | AU50: 1400 | AW50: 水 | AX50: =B50 -> 29 | AY50: =C50 -> 0 | AZ50: 10 | BA50: =AZ50*BR50 -> 0 | BB50: 24 | BC50: =BB50*BS50 -> 0 | BD50: 12 | BE50: =BD50*BT50 -> 0 | BG50: =BF50*BU50 -> 0 | BH50: =L50 -> 0 | BI50: =M50 -> #DIV/0! | BJ50: =AJ50 -> 0 | BK50: =AK50 -> #DIV/0! | BL50: =BH50+BJ50 -> 0 | BM50: =BI50+BK50 -> #DIV/0! | BO50: =Q50+AO50 -> #DIV/0! | BV50: 水 | BW50: =AX50 -> 29 | BZ50: =BY50/BX50 -> #DIV/0! | CB50: =CA50/BX50 -> #DIV/0! | CE50: =BY50+CA50+CC50+CD50 -> 0 | CF50: =CE50/BX50 -> #DIV/0! | CJ50: =SUM(CG50:CI50) -> 0 | CK50: =CE50/CJ50 -> #DIV/0! | CR50: =SUM(CO50:CQ50)/3 -> 0 | CT50: 曇 | CV50: 2 | DF50: =SUM(DC50:DE50)/3 -> 0 | DH50: 曇 | DJ50: 2 | DO50: 0
A51: 木 | B51: 30 | C51: =D51+F51+H51+J51 -> 0 | E51: =D51*T51 -> 0 | G51: =F51*U51 -> 0 | I51: =H51*V51 -> 0 | K51: =J51*W51 -> 0 | L51: =E51+G51+I51+K51 -> 0 | M51: =L51/C51 -> #DIV/0! | N51: ON2 | O51: 150 | Q51: =L51/P51 -> #DIV/0! | T51: 3300 | U51: 3800 | V51: 4800 | W51: 2000 | Y51: 木 | Z51: =B51 -> 30 | AA51: =AB51+AD51+AF51+AH51 -> 0 | AB51: =D51 -> 0 | AC51: =AB51*AR51 -> 0 | AD51: =F51 -> 0 | AE51: =AD51*AS51 -> 0 | AF51: =H51 -> 0 | AG51: =AF51*AT51 -> 0 | AH51: =J51 -> 0 | AI51: =AH51*AU51 -> 0 | AJ51: =AC51+AE51+AG51+AI51 -> 0 | AK51: =AJ51/AA51 -> #DIV/0! | AL51: =N51 -> ON2 | AM51: =O51 -> 150 | AN51: =P51 -> 0 | AO51: =(AJ51+BH51)/AN51 -> #DIV/0! | AR51: 1700 | AS51: 2200 | AT51: 2200 | AU51: 1400 | AW51: 木 | AX51: =B51 -> 30 | AY51: =C51 -> 0 | AZ51: 10 | BA51: =AZ51*BR51 -> 0 | BB51: 24 | BC51: =BB51*BS51 -> 0 | BD51: 12 | BE51: =BD51*BT51 -> 0 | BG51: =BF51*BU51 -> 0 | BH51: =L51 -> 0 | BI51: =M51 -> #DIV/0! | BJ51: =AJ51 -> 0 | BK51: =AK51 -> #DIV/0! | BL51: =BH51+BJ51 -> 0 | BM51: =BI51+BK51 -> #DIV/0! | BO51: =Q51+AO51 -> #DIV/0! | BV51: 木 | BW51: =AX51 -> 30 | BZ51: =BY51/BX51 -> #DIV/0! | CB51: =CA51/BX51 -> #DIV/0! | CE51: =BY51+CA51+CC51+CD51 -> 0 | CF51: =CE51/BX51 -> #DIV/0! | CJ51: =SUM(CG51:CI51) -> 0 | CK51: =CE51/CJ51 -> #DIV/0! | CR51: =SUM(CO51:CQ51)/3 -> 0 | CT51: 雨 | CV51: 1 | DF51: =SUM(DC51:DE51)/3 -> 0 | DH51: 雨 | DJ51: 1 | DO51: =B51 -> 30
A52: 金 | B52: 31 | C52: =D52+F52+H52+J52 -> 0 | E52: =D52*T52 -> 0 | G52: =F52*U52 -> 0 | I52: =H52*V52 -> 0 | K52: =J52*W52 -> 0 | L52: =E52+G52+I52+K52 -> 0 | M52: =L52/C52 -> #DIV/0! | N52: ON1 | O52: 160 | Q52: =L52/P52 -> #DIV/0! | T52: 3300 | U52: 3800 | V52: 4800 | W52: 2000 | Y52: 金 | Z52: =B52 -> 31 | AA52: =AB52+AD52+AF52+AH52 -> 0 | AB52: =D52 -> 0 | AC52: =AB52*AR52 -> 0 | AD52: =F52 -> 0 | AE52: =AD52*AS52 -> 0 | AF52: =H52 -> 0 | AG52: =AF52*AT52 -> 0 | AH52: =J52 -> 0 | AI52: =AH52*AU52 -> 0 | AJ52: =AC52+AE52+AG52+AI52 -> 0 | AK52: =AJ52/AA52 -> #DIV/0! | AL52: =N52 -> ON1 | AM52: =O52 -> 160 | AN52: =P52 -> 0 | AO52: =(AJ52+BH52)/AN52 -> #DIV/0! | AR52: 1700 | AS52: 2200 | AT52: 2200 | AU52: 1400 | AW52: 金 | AX52: =B52 -> 31 | AY52: =C52 -> 0 | AZ52: 10 | BA52: =AZ52*BR52 -> 0 | BB52: 24 | BC52: =BB52*BS52 -> 0 | BD52: 12 | BE52: =BD52*BT52 -> 0 | BG52: =BF52*BU52 -> 0 | BH52: =L52 -> 0 | BI52: =M52 -> #DIV/0! | BJ52: =AJ52 -> 0 | BK52: =AK52 -> #DIV/0! | BL52: =BH52+BJ52 -> 0 | BM52: =BI52+BK52 -> #DIV/0! | BO52: =Q52+AO52 -> #DIV/0! | BV52: 金 | BW52: =AX52 -> 31 | BZ52: =BY52/BX52 -> #DIV/0! | CB52: =CA52/BX52 -> #DIV/0! | CE52: =BY52+CA52+CC52+CD52 -> 0 | CF52: =CE52/BX52 -> #DIV/0! | CJ52: =SUM(CG52:CI52) -> 0 | CK52: =CE52/CJ52 -> #DIV/0! | CR52: =SUM(CO52:CQ52)/3 -> 0 | CT52: 豪雨・雷雨 | CV52: 0 | DF52: =SUM(DC52:DE52)/3 -> 0 | DH52: 豪雨・雷雨 | DJ52: 0 | DO52: =B52 -> 31 | DR52: çç
A53: 土 | C53: =D53+F53+H53+J53 -> 0 | E53: =D53*T53 -> 0 | G53: =F53*U53 -> 0 | I53: =H53*V53 -> 0 | K53: =J53*W53 -> 0 | L53: =E53+G53+I53+K53 -> 0 | M53: =L53/C53 -> #DIV/0! | N53: TOP1 | O53: 180 | Q53: =L53/P53 -> #DIV/0! | T53: 3300 | U53: 3800 | V53: 4800 | W53: 2000 | Y53: 土 | Z53: =B53 -> 0 | AA53: =AB53+AD53+AF53+AH53 -> 0 | AB53: =D53 -> 0 | AC53: =AB53*AR53 -> 0 | AD53: =F53 -> 0 | AE53: =AD53*AS53 -> 0 | AF53: =H53 -> 0 | AG53: =AF53*AT53 -> 0 | AH53: =J53 -> 0 | AI53: =AH53*AU53 -> 0 | AJ53: =AC53+AE53+AG53+AI53 -> 0 | AK53: =AJ53/AA53 -> #DIV/0! | AL53: =N53 -> TOP1 | AM53: =O53 -> 180 | AN53: =P53 -> 0 | AO53: =(AJ53+BH53)/AN53 -> #DIV/0! | AR53: 1700 | AS53: 2200 | AT53: 2200 | AU53: 1400 | AW53: 土 | AX53: =B53 -> 0 | AY53: =C53 -> 0 | AZ53: 10 | BA53: =AZ53*BR53 -> 0 | BB53: 28 | BC53: =BB53*BS53 -> 0 | BD53: 12 | BE53: =BD53*BT53 -> 0 | BG53: =BF53*BU53 -> 0 | BH53: =L53 -> 0 | BI53: =M53 -> #DIV/0! | BJ53: =AJ53 -> 0 | BK53: =AK53 -> #DIV/0! | BL53: =BH53+BJ53 -> 0 | BM53: =BI53+BK53 -> #DIV/0! | BO53: =Q53+AO53 -> #DIV/0! | BV53: 土 | BW53: =AX53 -> 0 | BZ53: =BY53/BX53 -> #DIV/0! | CB53: =CA53/BX53 -> #DIV/0! | CE53: =BY53+CA53+CC53+CD53 -> 0 | CF53: =CE53/BX53 -> #DIV/0! | CJ53: =SUM(CG53:CI53) -> 0 | CK53: =CE53/CJ53 -> #DIV/0! | CR53: =SUM(CO53:CQ53)/3 -> 0 | CT53: ※5.6月は18時は最低気温を採用。7月〜は最高気温を採用。 | DF53: =SUM(DC53:DE53)/3 -> 0 | DH53: ※5.6月は18時は最低気温を採用。7月〜は最高気温を採用。 | DO53: =B53 -> 0
A54: SUB TOTAL | C54: =SUM(C47:C53) -> 0 | D54: =SUM(D47:D53) -> 0 | E54: =SUM(E47:E53) -> 0 | F54: =SUM(F47:F53) -> 0 | G54: =SUM(G47:G53) -> 0 | H54: =SUM(H47:H53) -> 0 | I54: =SUM(I47:I53) -> 0 | J54: =SUM(J47:J53) -> 0 | ... L54: =SUM(L47:L53) -> 0 | M54: =L54/C54 -> #DIV/0! | O54: =SUM(O47:O53) -> 1110 | P54: =SUM(P47:P53) -> 0 | Q54: =L54/P54 -> #DIV/0! | T54: P/D | U54: =C54/W54 -> 0 | V54: 日にち | W54: 3 | Y54: SUB TOTAL | AA54: =SUM(AA47:AA53) -> 0 | AB54: =SUM(AB47:AB53) -> 0 | AC54: =SUM(AC47:AC53) -> 0 | AD54: =SUM(AD47:AD53) -> 0 | AE54: =SUM(AE47:AE53) -> 0 | AF54: =SUM(AF47:AF53) -> 0 | AG54: =SUM(AG47:AG53) -> 0 | AH54: =SUM(AH47:AH53) -> 0 | ... AJ54: =SUM(AJ47:AJ53) -> 0 | AK54: =AJ54/AA54 -> #DIV/0! | AM54: =SUM(AM47:AM53) -> 1110 | AN54: =SUM(AN47:AN53) -> 0 | AO54: =(AJ54+BH54)/AN54 -> #DIV/0! | AR54: P/D | AS54: =AA54/AU54 -> 0 | AT54: 日にち | AU54: =W54 -> 3 | AW54: SUB TOTAL | AY54: =C54 -> 0 | AZ54: =SUM(AZ47:AZ53) -> 84 | BA54: =SUM(BA47:BA53) -> 0 | BB54: =SUM(BB47:BB53) -> 120 | BC54: =SUM(BC47:BC53) -> 0 | BD54: =SUM(BD47:BD53) -> 60 | BE54: =SUM(BE47:BE53) -> 0 | BF54: =SUM(BF47:BF53) -> 0 | BG54: =SUM(BG47:BG53) -> 0 | BH54: =L54 -> 0 | BI54: =M54 -> #DIV/0! | BJ54: =AJ54 -> 0 | BK54: =AK54 -> #DIV/0! | BL54: =SUM(BL47:BL53) -> 0 | BM54: =BI54+BK54 -> #DIV/0! | BO54: =Q54+AO54 -> #DIV/0! | BR54: P/D | BS54: =AY54/BU54 -> 0 | BT54: 日にち | BU54: =W54 -> 3 | BV54: SUB TOTAL | BX54: =SUM(BX47:BX53) -> 0 | BY54: =SUM(BY47:BY53) -> 0 | BZ54: =BY54/BX54 -> #DIV/0! | CA54: =SUM(CA47:CA53) -> 0 | CB54: =CA54/BX54 -> #DIV/0! | CC54: =SUM(CC47:CC53) -> 0 | CD54: =SUM(CD47:CD53) -> 0 | CE54: =BY54+CA54+CC54+CD54 -> 0 | CF54: =CE54/BX54 -> #DIV/0! | CG54: =SUM(CG47:CG53) -> 0 | CH54: =SUM(CH47:CH53) -> 0 | CI54: =SUM(CI47:CI53) -> 0 | CJ54: =SUM(CJ47:CJ53) -> 0 | CK54: =CE54/CJ54 -> #DIV/0! | CM54: =SUM(CM47:CM53)/CL54 -> #DIV/0! | CN54: =SUM(CN47:CN53)/CL54 -> #DIV/0! | CO54: =SUM(CO47:CO53)/CL54 -> #DIV/0! | CP54: =SUM(CP47:CP53)/CL54 -> #DIV/0! | CQ54: =SUM(CQ47:CQ53)/CL54 -> #DIV/0! | CR54: =SUM(CO54:CQ54)/3 -> #DIV/0! | CS54: ➓ | CT54: =CE54/CL54 -> #DIV/0! | CY54: ※1日平均売上 | CZ54: 2 | DA54: =SUM(DA47:DA53)/CZ54 -> 13.4 | DB54: =SUM(DB47:DB53)/CZ54 -> 22.65 | DC54: =SUM(DC47:DC53)/CZ54 -> 4 | DD54: =SUM(DD47:DD53)/CZ54 -> 4 | DE54: =SUM(DE47:DE53)/CZ54 -> 4 | DF54: =SUM(DC54:DE54)/3 -> 4 | DH54: =CV54/CZ54 -> 0 | DM54: ※1日平均売上
A55: 6th week | Y55: 6th week | AW55: 6th week | BV55: 6th week | CM55: =BV55 -> 6th week | DA55: =CM55 -> 6th week
A56: 曜日 | B56: 日にち | C56: 客数 | D56: MENU A 出卓 | E56: 売上 | F56: MENU B 出卓 | G56: 売上 | H56: MENU C 出卓 | I56: 売上 | J56: アラカルト利用数 | K56: 売上 | L56: 料理売上 | M56: 料理単価 | N56: モデルシフト | O56: モデルシフト時間数 | P56: 実時間数 | Q56: 人時売上高 | T56: A | U56: B | V56: C | W56: S | Y56: 曜日 | Z56: 日にち | AA56: 客数 | AB56: MENU A 出卓 | AC56: 売上 | AD56: MENU B 出卓 | AE56: 売上 | AF56: MENU C 出卓 | AG56: 売上 | AH56: アラカルト利用数 | AI56: 売上 | AJ56: 飲料売上 | AK56: 飲料単価 | AL56: モデルシフト | AM56: モデルシフト時間数 | AN56: 実時間数 | AO56: 人時売上高 | AR56: A | AS56: B | AT56: C | AU56: S | AW56: 曜日 | AX56: 日にち | AY56: 客数 | AZ56: MENU A 出卓 | BA56: 売上 | BB56: MENU B 出卓 | BC56: 売上 | BD56: MENU C 出卓 | BE56: 売上 | BF56: MENU S 出卓 | BG56: 売上 | BH56: 料理売上 | BI56: 料理単価 | BJ56: 飲料売上 | BK56: 飲料単価 | BL56: 合計売上予測 | BM56: 合計単価 | BO56: 人時売上高予測 | BR56: A | BS56: B | BT56: C | BU56: S | BV56: 曜日 | BW56: 日にち | BX56: 客数 | BY56: 料理売上 | BZ56: 料理単価 | CA56: 飲料売上 | CB56: 飲料単価 | CC56: その他売上 | CD56: 物販 | CE56: 売上合計 | CF56: 合計単価 | CG56: サーフィンズ | CH56: forking | CI56: Timee | CJ56: 合計 | CK56: 人時売上高 | CM56: 最低 | CN56: 最高 | CO56: 12時 | CP56: 15時 | CQ56: 18時 | CR56: Ave | CT56: ■天候要因 | CV56: 評価点 | DA56: 最低 | DB56: 最高 | DC56: 12時 | DD56: 15時 | DE56: 18時 | DF56: Ave | DH56: ■天候要因 | DJ56: 評価点
A57: 日 | C57: =D57+F57+H57+J57 -> 0 | E57: =D57*T57 -> 0 | G57: =F57*U57 -> 0 | I57: =H57*V57 -> 0 | K57: =J57*W57 -> 0 | L57: =E57+G57+I57+K57 -> 0 | M57: =L57/C57 -> #DIV/0! | N57: TOP2 | O57: 170 | Q57: =L57/P57 -> #DIV/0! | T57: 3300 | U57: 3800 | V57: 4800 | W57: 2000 | Y57: 日 | Z57: =B57 -> 0 | AA57: =AB57+AD57+AF57+AH57 -> 0 | AB57: =D57 -> 0 | AC57: =AB57*AR57 -> 0 | AD57: =F57 -> 0 | AE57: =AD57*AS57 -> 0 | AF57: =H57 -> 0 | AG57: =AF57*AT57 -> 0 | AH57: =J57 -> 0 | AI57: =AH57*AU57 -> 0 | AJ57: =AC57+AE57+AG57+AI57 -> 0 | AK57: =AJ57/AA57 -> #DIV/0! | AL57: =N57 -> TOP2 | AM57: =O57 -> 170 | AN57: =P57 -> 0 | AO57: =(AJ57+BH57)/AN57 -> #DIV/0! | AR57: 1700 | AS57: 2200 | AT57: 2200 | AU57: 1400 | AW57: 日 | AX57: =B57 -> 0 | AY57: =C57 -> 0 | BA57: =AZ57*BR57 -> 0 | BC57: =BB57*BS57 -> 0 | BE57: =BD57*BT57 -> 0 | BG57: =BF57*BU57 -> 0 | BH57: =L57 -> 0 | BI57: =M57 -> #DIV/0! | BJ57: =AJ57 -> 0 | BK57: =AK57 -> #DIV/0! | BL57: =BH57+BJ57 -> 0 | BM57: =BI57+BK57 -> #DIV/0! | BO57: =Q57+AO57 -> #DIV/0! | BV57: 日 | BW57: =AX57 -> 0 | BZ57: =BY57/BX57 -> #DIV/0! | CB57: =CA57/BX57 -> #DIV/0! | CE57: =BY57+CA57+CC57+CD57 -> 0 | CF57: =CE57/BX57 -> #DIV/0! | CJ57: =SUM(CG57:CI57) -> 0 | CK57: =CE57/CJ57 -> #DIV/0! | CR57: =SUM(CO57:CQ57)/3 -> 0 | CT57: 晴れ（33度まで） | CV57: 5 | DF57: =SUM(DC57:DE57)/3 -> 0 | DH57: 晴れ（33度まで） | DJ57: 5
