Workbook

Sheet 料飲
A1: 令和７年度（第69期）事業予算 損益計算書 | AN1: 令和７年度（第69期）事業予算 損益計算書
AK2: [単位：千円(税抜)] | BM2: [単位：千円(税抜)] | BP2: [単位：千円(税抜)]
A3: 名称
T4: 大倉山 | AI4: 藻岩山 | AX4: テレビ塔 | BE4: 赤れんが テラス
E5: ﾇｰﾍﾞﾙﾌﾟｰｽ | J5: 大倉山ｶﾌｪ | O5: 大倉山ﾗｳﾝｼﾞ | Y5: ｽｷｰﾛｯｼﾞ食堂 | AD5: 藻岩山レストラン | AN5: ｶﾞｰﾃﾞﾝ | AS5: ﾋﾞｱｶﾞｰﾃﾞﾝ | BC5: ブリック | BD5: ルスツ羊蹄豚 | BF5: 料飲共通 | BK5: 料飲部合計 | BP5: 料飲部合計
E6: ①R7予算 | F6: ②R6決見 | G6: ①－② | H6: ③R6予算 | I6: ①－③ | J6: ①R7予算 | K6: ②R6決見 | L6: ①－② | M6: ③R6予算 | N6: ①－③ | O6: ①R7予算 | P6: ②R6決見 | Q6: ①－② | R6: ③R6予算 | S6: ①－③ | T6: ①R7予算 | U6: ②R6決見 | V6: ①－② | W6: ③R6予算 | X6: ①－③ | Y6: ①R7予算 | Z6: ②R6決見 | AA6: ①－② | AB6: ③R6予算 | AC6: ①－③ | AD6: ①R7予算 | AE6: ②R6決見 | AF6: ①－② | AG6: ③R6予算 | AH6: ①－③ | AI6: ①R7予算 | AJ6: ②R6決見 | AK6: ①－② | AL6: ③R6予算 | AM6: ①－③ | AN6: ①R7予算 | AO6: ①R6決見 | AP6: ①－② | AQ6: ③R6予算 | AR6: ①－③ | AS6: ①R7予算 | AT6: ①R6決見 | AU6: ①－② | AV6: ③R6予算 | AW6: ①－③ | AX6: ①R7予算 | AY6: ②R6決見 | AZ6: ①－② | BA6: ③R6予算 | BB6: ①－③ | BC6: ①R7予算 | BD6: ①R7予算 | BE6: ①R7予算 | BF6: ①R7予算 | BG6: ②R6決見 | BH6: ①－② | BI6: ③R6予算 | BJ6: ①－③ | BK6: ①R7予算 | BL6: ②R6決見 | BM6: ①－② | BN6: ③R6予算 | BO6: ①－③ | BP6: ①R7予算 | BQ6: ②R6決見 | BR6: ①－② | BS6: ③R6予算 | BT6: ①－③
A7: 総売上高 | E7: =+ﾇｰﾍﾞﾙﾌﾟｰｽ!W6/1000 -> 98216.5 | F7: 97828.758 | G7: =+E7-F7 -> 387.742 | H7: 89665 | I7: =+E7-H7 -> 8551.5 | J7: =+ｶﾌｪﾙﾎﾟ!W6/1000 -> 9212.097 | K7: 8192.423 | L7: =+J7-K7 -> 1019.674 | M7: 10007 | N7: =+J7-M7 -> -794.903 | O7: =+ｶﾌｪｾﾚｽﾃ!W6/1000 -> 19649 | P7: 18903.479 | Q7: =+O7-P7 -> 745.521 | R7: 15319 | S7: =+O7-R7 -> 4330 | T7: =+E7+J7+O7 -> 127077.6 | U7: =+F7+K7+P7 -> 124924.66 | V7: =+T7-U7 -> 2152.937 | W7: =+H7+M7+R7 -> 114991 | X7: =+T7-W7 -> 12086.597 | Y7: 0 | Z7: 23648.19 | AA7: =+Y7-Z7 -> -23648.19 | AB7: 20772 | AC7: =+Y7-AB7 -> -20772 | AD7: =+ｼﾞｭｴﾙｽﾞ!W6/1000 -> 164317.97 | AE7: 157913.61 | AF7: =+AD7-AE7 -> 6404.36 | AG7: 141204 | AH7: =+AD7-AG7 -> 23113.966 | AI7: =+Y7+AD7 -> 164317.97 | AJ7: =+Z7+AE7 -> 181561.8 | AK7: =+AI7-AJ7 -> -17243.83 | AL7: =+AB7+AG7 -> 161976 | AM7: =+AI7-AL7 -> 2341.966 | AN7: =+ｶﾞｰﾃﾞﾝ!W6/1000 -> 136763.17 | AO7: 132999.91 | AP7: =+AN7-AO7 -> 3763.265 | AQ7: 132211 | AR7: =+AN7-AQ7 -> 4552.172 | AS7: =+ﾋﾞｱｶﾞｰﾃﾞﾝ!W6/1000 -> 154408.3 | AT7: 140806.36 | AU7: =+AS7-AT7 -> 13601.935 | AV7: 136366 | AW7: =+AS7-AV7 -> 18042.295 | AX7: =+AN7+AS7 -> 291171.47 | AY7: =+AO7+AT7 -> 273806.27 | AZ7: =+AX7-AY7 -> 17365.2 | BA7: =+AQ7+AV7 -> 268577 | BB7: =+AX7-BA7 -> 22594.467 | BC7: =SUM(BC8:BC17) -> 75365.66 | BD7: =SUM(BD8:BD17) -> 50302.4 | BE7: =+BC7+BD7 -> 125668.06 | BF7: =+料飲共通!W6/1000 -> 0 | BG7: 0 | BH7: =+BF7-BG7 -> 0 | BI7: 0 | BJ7: =+BF7-BI7 -> 0 | BK7: =+T7+AI7+AX7+BE7+BF7 -> 708235.09 | BL7: =+U7+AJ7+AY7+BG7 -> 580292.72 | BM7: =+BK7-BL7 -> 127942.37 | BN7: =+W7+AL7+BA7+BI7 -> 545544 | BO7: =+BK7-BN7 -> 162691.09 | BP7: =+BK7-BE7 -> 582567.03 | BQ7: =+BL7-Z7 -> 556644.53 | BR7: =+BP7-BQ7 -> 25922.497 | BS7: =+BN7-AB7 -> 524772 | BT7: =+BP7-BS7 -> 57795.03
B8: 売上 | E8: =+ﾇｰﾍﾞﾙﾌﾟｰｽ!W7/1000 -> 98216.5 | F8: 97828.758 | G8: =+E8-F8 -> 387.742 | H8: 89665 | I8: =+E8-H8 -> 8551.5 | J8: =+ｶﾌｪﾙﾎﾟ!W7/1000 -> 9212.097 | K8: 8192.423 | L8: =+J8-K8 -> 1019.674 | M8: 10007 | N8: =+J8-M8 -> -794.903 | O8: =+ｶﾌｪｾﾚｽﾃ!W7/1000 -> 19649 | P8: 18903.479 | Q8: =+O8-P8 -> 745.521 | R8: 15319 | S8: =+O8-R8 -> 4330 | T8: =+E8+J8+O8 -> 127077.6 | U8: =+F8+K8+P8 -> 124924.66 | V8: =+T8-U8 -> 2152.937 | W8: =+H8+M8+R8 -> 114991 | X8: =+T8-W8 -> 12086.597 | Y8: 0 | Z8: 23648.19 | AA8: =+Y8-Z8 -> -23648.19 | AB8: 20772 | AC8: =+Y8-AB8 -> -20772 | AD8: =+ｼﾞｭｴﾙｽﾞ!W7/1000 -> 164317.97 | AE8: 157913.61 | AF8: =+AD8-AE8 -> 6404.36 | AG8: 141204 | AH8: =+AD8-AG8 -> 23113.966 | AI8: =+Y8+AD8 -> 164317.97 | AJ8: =+Z8+AE8 -> 181561.8 | AK8: =+AI8-AJ8 -> -17243.83 | AL8: =+AB8+AG8 -> 161976 | AM8: =+AI8-AL8 -> 2341.966 | AN8: =+ｶﾞｰﾃﾞﾝ!W7/1000 -> 136763.17 | AO8: 132999.91 | AP8: =+AN8-AO8 -> 3763.265 | AQ8: 132211 | AR8: =+AN8-AQ8 -> 4552.172 | AS8: =+ﾋﾞｱｶﾞｰﾃﾞﾝ!W7/1000 -> 154408.3 | AT8: 140806.36 | AU8: =+AS8-AT8 -> 13601.935 | AV8: 136366 | AW8: =+AS8-AV8 -> 18042.295 | AX8: =+AN8+AS8 -> 291171.47 | AY8: =+AO8+AT8 -> 273806.27 | AZ8: =+AX8-AY8 -> 17365.2 | BA8: =+AQ8+AV8 -> 268577 | BB8: =+AX8-BA8 -> 22594.467 | BC8: =+赤れんが!X8/1000 -> 75365.66 | BD8: =+赤れんが!Z8/1000 -> 50302.4 | BE8: =+BC8+BD8 -> 125668.06 | BF8: =+料飲共通!W7/1000 -> 0 | BG8: 0 | BH8: =+BF8-BG8 -> 0 | BI8: 0 | BJ8: =+BF8-BI8 -> 0 | BK8: =+T8+AI8+AX8+BE8+BF8 -> 708235.09 | BL8: =+U8+AJ8+AY8+BG8 -> 580292.72 | BM8: =+BK8-BL8 -> 127942.37 | BN8: =+W8+AL8+BA8+BI8 -> 545544 | BO8: =+BK8-BN8 -> 162691.09 | BP8: =+BK8-BE8 -> 582567.03 | BQ8: =+BL8-Z8 -> 556644.53 | BR8: =+BP8-BQ8 -> 25922.497 | BS8: =+BN8-AB8 -> 524772 | BT8: =+BP8-BS8 -> 57795.03
B9: 損保代理店収入 | E9: =+ﾇｰﾍﾞﾙﾌﾟｰｽ!W8/1000 -> 0 | F9: 0 | G9: =+E9-F9 -> 0 | H9: 0 | I9: =+E9-H9 -> 0 | J9: =+ｶﾌｪﾙﾎﾟ!W8/1000 -> 0 | K9: 0 | L9: =+J9-K9 -> 0 | M9: 0 | N9: =+J9-M9 -> 0 | O9: =+ｶﾌｪｾﾚｽﾃ!W8/1000 -> 0 | P9: 0 | Q9: =+O9-P9 -> 0 | R9: 0 | S9: =+O9-R9 -> 0 | T9: =+E9+J9+O9 -> 0 | U9: =+F9+K9+P9 -> 0 | V9: =+T9-U9 -> 0 | W9: =+H9+M9+R9 -> 0 | X9: =+T9-W9 -> 0 | Y9: 0 | Z9: 0 | AA9: =+Y9-Z9 -> 0 | AB9: 0 | AC9: =+Y9-AB9 -> 0 | AD9: =+ｼﾞｭｴﾙｽﾞ!W8/1000 -> 0 | AE9: 0 | AF9: =+AD9-AE9 -> 0 | AG9: 0 | AH9: =+AD9-AG9 -> 0 | AI9: =+Y9+AD9 -> 0 | AJ9: =+Z9+AE9 -> 0 | AK9: =+AI9-AJ9 -> 0 | AL9: =+AB9+AG9 -> 0 | AM9: =+AI9-AL9 -> 0 | AN9: =+ｶﾞｰﾃﾞﾝ!W8/1000 -> 0 | AO9: 0 | AP9: =+AN9-AO9 -> 0 | AQ9: 0 | AR9: =+AN9-AQ9 -> 0 | AS9: =+ﾋﾞｱｶﾞｰﾃﾞﾝ!W8/1000 -> 0 | AT9: 0 | AU9: =+AS9-AT9 -> 0 | AV9: 0 | AW9: =+AS9-AV9 -> 0 | AX9: =+AN9+AS9 -> 0 | AY9: =+AO9+AT9 -> 0 | AZ9: =+AX9-AY9 -> 0 | BA9: =+AQ9+AV9 -> 0 | BB9: =+AX9-BA9 -> 0 | BC9: 0 | BD9: 0 | BE9: =+BC9+BD9 -> 0 | BF9: =+料飲共通!W8/1000 -> 0 | BG9: 0 | BH9: =+BF9-BG9 -> 0 | BI9: 0 | BJ9: =+BF9-BI9 -> 0 | BK9: =+T9+AI9+AX9+BE9+BF9 -> 0 | BL9: =+U9+AJ9+AY9+BG9 -> 0 | BM9: =+BK9-BL9 -> 0 | BN9: =+W9+AL9+BA9+BI9 -> 0 | BO9: =+BK9-BN9 -> 0 | BP9: =+BK9-BE9 -> 0 | BQ9: =+BL9-Z9 -> 0 | BR9: =+BP9-BQ9 -> 0 | BS9: =+BN9-AB9 -> 0 | BT9: =+BP9-BS9 -> 0
B10: 販売手数料収入 | E10: =+ﾇｰﾍﾞﾙﾌﾟｰｽ!W9/1000 -> 0 | F10: 0 | G10: =+E10-F10 -> 0 | H10: 0 | I10: =+E10-H10 -> 0 | J10: =+ｶﾌｪﾙﾎﾟ!W9/1000 -> 0 | K10: 0 | L10: =+J10-K10 -> 0 | M10: 0 | N10: =+J10-M10 -> 0 | O10: =+ｶﾌｪｾﾚｽﾃ!W9/1000 -> 0 | P10: 0 | Q10: =+O10-P10 -> 0 | R10: 0 | S10: =+O10-R10 -> 0 | T10: =+E10+J10+O10 -> 0 | U10: =+F10+K10+P10 -> 0 | V10: =+T10-U10 -> 0 | W10: =+H10+M10+R10 -> 0 | X10: =+T10-W10 -> 0 | Y10: 0 | Z10: 0 | AA10: =+Y10-Z10 -> 0 | AB10: 0 | AC10: =+Y10-AB10 -> 0 | AD10: =+ｼﾞｭｴﾙｽﾞ!W9/1000 -> 0 | AE10: 0 | AF10: =+AD10-AE10 -> 0 | AG10: 0 | AH10: =+AD10-AG10 -> 0 | AI10: =+Y10+AD10 -> 0 | AJ10: =+Z10+AE10 -> 0 | AK10: =+AI10-AJ10 -> 0 | AL10: =+AB10+AG10 -> 0 | AM10: =+AI10-AL10 -> 0 | AN10: =+ｶﾞｰﾃﾞﾝ!W9/1000 -> 0 | AO10: 0 | AP10: =+AN10-AO10 -> 0 | AQ10: 0 | AR10: =+AN10-AQ10 -> 0 | AS10: =+ﾋﾞｱｶﾞｰﾃﾞﾝ!W9/1000 -> 0 | AT10: 0 | AU10: =+AS10-AT10 -> 0 | AV10: 0 | AW10: =+AS10-AV10 -> 0 | AX10: =+AN10+AS10 -> 0 | AY10: =+AO10+AT10 -> 0 | AZ10: =+AX10-AY10 -> 0 | BA10: =+AQ10+AV10 -> 0 | BB10: =+AX10-BA10 -> 0 | BC10: 0 | BD10: 0 | BE10: =+BC10+BD10 -> 0 | BF10: =+料飲共通!W9/1000 -> 0 | BG10: 0 | BH10: =+BF10-BG10 -> 0 | BI10: 0 | BJ10: =+BF10-BI10 -> 0 | BK10: =+T10+AI10+AX10+BE10+BF10 -> 0 | BL10: =+U10+AJ10+AY10+BG10 -> 0 | BM10: =+BK10-BL10 -> 0 | BN10: =+W10+AL10+BA10+BI10 -> 0 | BO10: =+BK10-BN10 -> 0 | BP10: =+BK10-BE10 -> 0 | BQ10: =+BL10-Z10 -> 0 | BR10: =+BP10-BQ10 -> 0 | BS10: =+BN10-AB10 -> 0 | BT10: =+BP10-BS10 -> 0
B11: 索道収入 | E11: =+ﾇｰﾍﾞﾙﾌﾟｰｽ!W10/1000 -> 0 | F11: 0 | G11: =+E11-F11 -> 0 | H11: 0 | I11: =+E11-H11 -> 0 | J11: =+ｶﾌｪﾙﾎﾟ!W10/1000 -> 0 | K11: 0 | L11: =+J11-K11 -> 0 | M11: 0 | N11: =+J11-M11 -> 0 | O11: =+ｶﾌｪｾﾚｽﾃ!W10/1000 -> 0 | P11: 0 | Q11: =+O11-P11 -> 0 | R11: 0 | S11: =+O11-R11 -> 0 | T11: =+E11+J11+O11 -> 0 | U11: =+F11+K11+P11 -> 0 | V11: =+T11-U11 -> 0 | W11: =+H11+M11+R11 -> 0 | X11: =+T11-W11 -> 0 | Y11: 0 | Z11: 0 | AA11: =+Y11-Z11 -> 0 | AB11: 0 | AC11: =+Y11-AB11 -> 0 | AD11: =+ｼﾞｭｴﾙｽﾞ!W10/1000 -> 0 | AE11: 0 | AF11: =+AD11-AE11 -> 0 | AG11: 0 | AH11: =+AD11-AG11 -> 0 | AI11: =+Y11+AD11 -> 0 | AJ11: =+Z11+AE11 -> 0 | AK11: =+AI11-AJ11 -> 0 | AL11: =+AB11+AG11 -> 0 | AM11: =+AI11-AL11 -> 0 | AN11: =+ｶﾞｰﾃﾞﾝ!W10/1000 -> 0 | AO11: 0 | AP11: =+AN11-AO11 -> 0 | AQ11: 0 | AR11: =+AN11-AQ11 -> 0 | AS11: =+ﾋﾞｱｶﾞｰﾃﾞﾝ!W10/1000 -> 0 | AT11: 0 | AU11: =+AS11-AT11 -> 0 | AV11: 0 | AW11: =+AS11-AV11 -> 0 | AX11: =+AN11+AS11 -> 0 | AY11: =+AO11+AT11 -> 0 | AZ11: =+AX11-AY11 -> 0 | BA11: =+AQ11+AV11 -> 0 | BB11: =+AX11-BA11 -> 0 | BC11: 0 | BD11: 0 | BE11: =+BC11+BD11 -> 0 | BF11: =+料飲共通!W10/1000 -> 0 | BG11: 0 | BH11: =+BF11-BG11 -> 0 | BI11: 0 | BJ11: =+BF11-BI11 -> 0 | BK11: =+T11+AI11+AX11+BE11+BF11 -> 0 | BL11: =+U11+AJ11+AY11+BG11 -> 0 | BM11: =+BK11-BL11 -> 0 | BN11: =+W11+AL11+BA11+BI11 -> 0 | BO11: =+BK11-BN11 -> 0 | BP11: =+BK11-BE11 -> 0 | BQ11: =+BL11-Z11 -> 0 | BR11: =+BP11-BQ11 -> 0 | BS11: =+BN11-AB11 -> 0 | BT11: =+BP11-BS11 -> 0
B12: 地代収入 | E12: =+ﾇｰﾍﾞﾙﾌﾟｰｽ!W11/1000 -> 0 | F12: 0 | G12: =+E12-F12 -> 0 | H12: 0 | I12: =+E12-H12 -> 0 | J12: =+ｶﾌｪﾙﾎﾟ!W11/1000 -> 0 | K12: 0 | L12: =+J12-K12 -> 0 | M12: 0 | N12: =+J12-M12 -> 0 | O12: =+ｶﾌｪｾﾚｽﾃ!W11/1000 -> 0 | P12: 0 | Q12: =+O12-P12 -> 0 | R12: 0 | S12: =+O12-R12 -> 0 | T12: =+E12+J12+O12 -> 0 | U12: =+F12+K12+P12 -> 0 | V12: =+T12-U12 -> 0 | W12: =+H12+M12+R12 -> 0 | X12: =+T12-W12 -> 0 | Y12: 0 | Z12: 0 | AA12: =+Y12-Z12 -> 0 | AB12: 0 | AC12: =+Y12-AB12 -> 0 | AD12: =+ｼﾞｭｴﾙｽﾞ!W11/1000 -> 0 | AE12: 0 | AF12: =+AD12-AE12 -> 0 | AG12: 0 | AH12: =+AD12-AG12 -> 0 | AI12: =+Y12+AD12 -> 0 | AJ12: =+Z12+AE12 -> 0 | AK12: =+AI12-AJ12 -> 0 | AL12: =+AB12+AG12 -> 0 | AM12: =+AI12-AL12 -> 0 | AN12: =+ｶﾞｰﾃﾞﾝ!W11/1000 -> 0 | AO12: 0 | AP12: =+AN12-AO12 -> 0 | AQ12: 0 | AR12: =+AN12-AQ12 -> 0 | AS12: =+ﾋﾞｱｶﾞｰﾃﾞﾝ!W11/1000 -> 0 | AT12: 0 | AU12: =+AS12-AT12 -> 0 | AV12: 0 | AW12: =+AS12-AV12 -> 0 | AX12: =+AN12+AS12 -> 0 | AY12: =+AO12+AT12 -> 0 | AZ12: =+AX12-AY12 -> 0 | BA12: =+AQ12+AV12 -> 0 | BB12: =+AX12-BA12 -> 0 | BC12: 0 | BD12: 0 | BE12: =+BC12+BD12 -> 0 | BF12: =+料飲共通!W11/1000 -> 0 | BG12: 0 | BH12: =+BF12-BG12 -> 0 | BI12: 0 | BJ12: =+BF12-BI12 -> 0 | BK12: =+T12+AI12+AX12+BE12+BF12 -> 0 | BL12: =+U12+AJ12+AY12+BG12 -> 0 | BM12: =+BK12-BL12 -> 0 | BN12: =+W12+AL12+BA12+BI12 -> 0 | BO12: =+BK12-BN12 -> 0 | BP12: =+BK12-BE12 -> 0 | BQ12: =+BL12-Z12 -> 0 | BR12: =+BP12-BQ12 -> 0 | BS12: =+BN12-AB12 -> 0 | BT12: =+BP12-BS12 -> 0
B13: 家賃収入 | E13: =+ﾇｰﾍﾞﾙﾌﾟｰｽ!W12/1000 -> 0 | F13: 0 | G13: =+E13-F13 -> 0 | H13: 0 | I13: =+E13-H13 -> 0 | J13: =+ｶﾌｪﾙﾎﾟ!W12/1000 -> 0 | K13: 0 | L13: =+J13-K13 -> 0 | M13: 0 | N13: =+J13-M13 -> 0 | O13: =+ｶﾌｪｾﾚｽﾃ!W12/1000 -> 0 | P13: 0 | Q13: =+O13-P13 -> 0 | R13: 0 | S13: =+O13-R13 -> 0 | T13: =+E13+J13+O13 -> 0 | U13: =+F13+K13+P13 -> 0 | V13: =+T13-U13 -> 0 | W13: =+H13+M13+R13 -> 0 | X13: =+T13-W13 -> 0 | Y13: 0 | Z13: 0 | AA13: =+Y13-Z13 -> 0 | AB13: 0 | AC13: =+Y13-AB13 -> 0 | AD13: =+ｼﾞｭｴﾙｽﾞ!W12/1000 -> 0 | AE13: 0 | AF13: =+AD13-AE13 -> 0 | AG13: 0 | AH13: =+AD13-AG13 -> 0 | AI13: =+Y13+AD13 -> 0 | AJ13: =+Z13+AE13 -> 0 | AK13: =+AI13-AJ13 -> 0 | AL13: =+AB13+AG13 -> 0 | AM13: =+AI13-AL13 -> 0 | AN13: =+ｶﾞｰﾃﾞﾝ!W12/1000 -> 0 | AO13: 0 | AP13: =+AN13-AO13 -> 0 | AQ13: 0 | AR13: =+AN13-AQ13 -> 0 | AS13: =+ﾋﾞｱｶﾞｰﾃﾞﾝ!W12/1000 -> 0 | AT13: 0 | AU13: =+AS13-AT13 -> 0 | AV13: 0 | AW13: =+AS13-AV13 -> 0 | AX13: =+AN13+AS13 -> 0 | AY13: =+AO13+AT13 -> 0 | AZ13: =+AX13-AY13 -> 0 | BA13: =+AQ13+AV13 -> 0 | BB13: =+AX13-BA13 -> 0 | BC13: 0 | BD13: 0 | BE13: =+BC13+BD13 -> 0 | BF13: =+料飲共通!W12/1000 -> 0 | BG13: 0 | BH13: =+BF13-BG13 -> 0 | BI13: 0 | BJ13: =+BF13-BI13 -> 0 | BK13: =+T13+AI13+AX13+BE13+BF13 -> 0 | BL13: =+U13+AJ13+AY13+BG13 -> 0 | BM13: =+BK13-BL13 -> 0 | BN13: =+W13+AL13+BA13+BI13 -> 0 | BO13: =+BK13-BN13 -> 0 | BP13: =+BK13-BE13 -> 0 | BQ13: =+BL13-Z13 -> 0 | BR13: =+BP13-BQ13 -> 0 | BS13: =+BN13-AB13 -> 0 | BT13: =+BP13-BS13 -> 0
B14: 駐車場収入 | E14: =+ﾇｰﾍﾞﾙﾌﾟｰｽ!W13/1000 -> 0 | F14: 0 | G14: =+E14-F14 -> 0 | H14: 0 | I14: =+E14-H14 -> 0 | J14: =+ｶﾌｪﾙﾎﾟ!W13/1000 -> 0 | K14: 0 | L14: =+J14-K14 -> 0 | M14: 0 | N14: =+J14-M14 -> 0 | O14: =+ｶﾌｪｾﾚｽﾃ!W13/1000 -> 0 | P14: 0 | Q14: =+O14-P14 -> 0 | R14: 0 | S14: =+O14-R14 -> 0 | T14: =+E14+J14+O14 -> 0 | U14: =+F14+K14+P14 -> 0 | V14: =+T14-U14 -> 0 | W14: =+H14+M14+R14 -> 0 | X14: =+T14-W14 -> 0 | Y14: 0 | Z14: 0 | AA14: =+Y14-Z14 -> 0 | AB14: 0 | AC14: =+Y14-AB14 -> 0 | AD14: =+ｼﾞｭｴﾙｽﾞ!W13/1000 -> 0 | AE14: 0 | AF14: =+AD14-AE14 -> 0 | AG14: 0 | AH14: =+AD14-AG14 -> 0 | AI14: =+Y14+AD14 -> 0 | AJ14: =+Z14+AE14 -> 0 | AK14: =+AI14-AJ14 -> 0 | AL14: =+AB14+AG14 -> 0 | AM14: =+AI14-AL14 -> 0 | AN14: =+ｶﾞｰﾃﾞﾝ!W13/1000 -> 0 | AO14: 0 | AP14: =+AN14-AO14 -> 0 | AQ14: 0 | AR14: =+AN14-AQ14 -> 0 | AS14: =+ﾋﾞｱｶﾞｰﾃﾞﾝ!W13/1000 -> 0 | AT14: 0 | AU14: =+AS14-AT14 -> 0 | AV14: 0 | AW14: =+AS14-AV14 -> 0 | AX14: =+AN14+AS14 -> 0 | AY14: =+AO14+AT14 -> 0 | AZ14: =+AX14-AY14 -> 0 | BA14: =+AQ14+AV14 -> 0 | BB14: =+AX14-BA14 -> 0 | BC14: 0 | BD14: 0 | BE14: =+BC14+BD14 -> 0 | BF14: =+料飲共通!W13/1000 -> 0 | BG14: 0 | BH14: =+BF14-BG14 -> 0 | BI14: 0 | BJ14: =+BF14-BI14 -> 0 | BK14: =+T14+AI14+AX14+BE14+BF14 -> 0 | BL14: =+U14+AJ14+AY14+BG14 -> 0 | BM14: =+BK14-BL14 -> 0 | BN14: =+W14+AL14+BA14+BI14 -> 0 | BO14: =+BK14-BN14 -> 0 | BP14: =+BK14-BE14 -> 0 | BQ14: =+BL14-Z14 -> 0 | BR14: =+BP14-BQ14 -> 0 | BS14: =+BN14-AB14 -> 0 | BT14: =+BP14-BS14 -> 0
B15: 受託料 | E15: =+ﾇｰﾍﾞﾙﾌﾟｰｽ!W14/1000 -> 0 | F15: 0 | G15: =+E15-F15 -> 0 | H15: 0 | I15: =+E15-H15 -> 0 | J15: =+ｶﾌｪﾙﾎﾟ!W14/1000 -> 0 | K15: 0 | L15: =+J15-K15 -> 0 | M15: 0 | N15: =+J15-M15 -> 0 | O15: =+ｶﾌｪｾﾚｽﾃ!W14/1000 -> 0 | P15: 0 | Q15: =+O15-P15 -> 0 | R15: 0 | S15: =+O15-R15 -> 0 | T15: =+E15+J15+O15 -> 0 | U15: =+F15+K15+P15 -> 0 | V15: =+T15-U15 -> 0 | W15: =+H15+M15+R15 -> 0 | X15: =+T15-W15 -> 0 | Y15: 0 | Z15: 0 | AA15: =+Y15-Z15 -> 0 | AB15: 0 | AC15: =+Y15-AB15 -> 0 | AD15: =+ｼﾞｭｴﾙｽﾞ!W14/1000 -> 0 | AE15: 0 | AF15: =+AD15-AE15 -> 0 | AG15: 0 | AH15: =+AD15-AG15 -> 0 | AI15: =+Y15+AD15 -> 0 | AJ15: =+Z15+AE15 -> 0 | AK15: =+AI15-AJ15 -> 0 | AL15: =+AB15+AG15 -> 0 | AM15: =+AI15-AL15 -> 0 | AN15: =+ｶﾞｰﾃﾞﾝ!W14/1000 -> 0 | AO15: 0 | AP15: =+AN15-AO15 -> 0 | AQ15: 0 | AR15: =+AN15-AQ15 -> 0 | AS15: =+ﾋﾞｱｶﾞｰﾃﾞﾝ!W14/1000 -> 0 | AT15: 0 | AU15: =+AS15-AT15 -> 0 | AV15: 0 | AW15: =+AS15-AV15 -> 0 | AX15: =+AN15+AS15 -> 0 | AY15: =+AO15+AT15 -> 0 | AZ15: =+AX15-AY15 -> 0 | BA15: =+AQ15+AV15 -> 0 | BB15: =+AX15-BA15 -> 0 | BC15: 0 | BD15: 0 | BE15: =+BC15+BD15 -> 0 | BF15: =+料飲共通!W14/1000 -> 0 | BG15: 0 | BH15: =+BF15-BG15 -> 0 | BI15: 0 | BJ15: =+BF15-BI15 -> 0 | BK15: =+T15+AI15+AX15+BE15+BF15 -> 0 | BL15: =+U15+AJ15+AY15+BG15 -> 0 | BM15: =+BK15-BL15 -> 0 | BN15: =+W15+AL15+BA15+BI15 -> 0 | BO15: =+BK15-BN15 -> 0 | BP15: =+BK15-BE15 -> 0 | BQ15: =+BL15-Z15 -> 0 | BR15: =+BP15-BQ15 -> 0 | BS15: =+BN15-AB15 -> 0 | BT15: =+BP15-BS15 -> 0
B16: 利用料金収入 | E16: =+ﾇｰﾍﾞﾙﾌﾟｰｽ!W15/1000 -> 0 | F16: 0 | G16: =+E16-F16 -> 0 | H16: 0 | I16: =+E16-H16 -> 0 | J16: =+ｶﾌｪﾙﾎﾟ!W15/1000 -> 0 | K16: 0 | L16: =+J16-K16 -> 0 | M16: 0 | N16: =+J16-M16 -> 0 | O16: =+ｶﾌｪｾﾚｽﾃ!W15/1000 -> 0 | P16: 0 | Q16: =+O16-P16 -> 0 | R16: 0 | S16: =+O16-R16 -> 0 | T16: =+E16+J16+O16 -> 0 | U16: =+F16+K16+P16 -> 0 | V16: =+T16-U16 -> 0 | W16: =+H16+M16+R16 -> 0 | X16: =+T16-W16 -> 0 | Y16: 0 | Z16: 0 | AA16: =+Y16-Z16 -> 0 | AB16: 0 | AC16: =+Y16-AB16 -> 0 | AD16: =+ｼﾞｭｴﾙｽﾞ!W15/1000 -> 0 | AE16: 0 | AF16: =+AD16-AE16 -> 0 | AG16: 0 | AH16: =+AD16-AG16 -> 0 | AI16: =+Y16+AD16 -> 0 | AJ16: =+Z16+AE16 -> 0 | AK16: =+AI16-AJ16 -> 0 | AL16: =+AB16+AG16 -> 0 | AM16: =+AI16-AL16 -> 0 | AN16: =+ｶﾞｰﾃﾞﾝ!W15/1000 -> 0 | AO16: 0 | AP16: =+AN16-AO16 -> 0 | AQ16: 0 | AR16: =+AN16-AQ16 -> 0 | AS16: =+ﾋﾞｱｶﾞｰﾃﾞﾝ!W15/1000 -> 0 | AT16: 0 | AU16: =+AS16-AT16 -> 0 | AV16: 0 | AW16: =+AS16-AV16 -> 0 | AX16: =+AN16+AS16 -> 0 | AY16: =+AO16+AT16 -> 0 | AZ16: =+AX16-AY16 -> 0 | BA16: =+AQ16+AV16 -> 0 | BB16: =+AX16-BA16 -> 0 | BC16: 0 | BD16: 0 | BE16: =+BC16+BD16 -> 0 | BF16: =+料飲共通!W15/1000 -> 0 | BG16: 0 | BH16: =+BF16-BG16 -> 0 | BI16: 0 | BJ16: =+BF16-BI16 -> 0 | BK16: =+T16+AI16+AX16+BE16+BF16 -> 0 | BL16: =+U16+AJ16+AY16+BG16 -> 0 | BM16: =+BK16-BL16 -> 0 | BN16: =+W16+AL16+BA16+BI16 -> 0 | BO16: =+BK16-BN16 -> 0 | BP16: =+BK16-BE16 -> 0 | BQ16: =+BL16-Z16 -> 0 | BR16: =+BP16-BQ16 -> 0 | BS16: =+BN16-AB16 -> 0 | BT16: =+BP16-BS16 -> 0
B17: 管理手数料収入 | E17: =+ﾇｰﾍﾞﾙﾌﾟｰｽ!W16/1000 -> 0 | F17: 0 | G17: =+E17-F17 -> 0 | H17: 0 | I17: =+E17-H17 -> 0 | J17: =+ｶﾌｪﾙﾎﾟ!W16/1000 -> 0 | K17: 0 | L17: =+J17-K17 -> 0 | M17: 0 | N17: =+J17-M17 -> 0 | O17: =+ｶﾌｪｾﾚｽﾃ!W16/1000 -> 0 | P17: 0 | Q17: =+O17-P17 -> 0 | R17: 0 | S17: =+O17-R17 -> 0 | T17: =+E17+J17+O17 -> 0 | U17: =+F17+K17+P17 -> 0 | V17: =+T17-U17 -> 0 | W17: =+H17+M17+R17 -> 0 | X17: =+T17-W17 -> 0 | Y17: 0 | Z17: 0 | AA17: =+Y17-Z17 -> 0 | AB17: 0 | AC17: =+Y17-AB17 -> 0 | AD17: =+ｼﾞｭｴﾙｽﾞ!W16/1000 -> 0 | AE17: 0 | AF17: =+AD17-AE17 -> 0 | AG17: 0 | AH17: =+AD17-AG17 -> 0 | AI17: =+Y17+AD17 -> 0 | AJ17: =+Z17+AE17 -> 0 | AK17: =+AI17-AJ17 -> 0 | AL17: =+AB17+AG17 -> 0 | AM17: =+AI17-AL17 -> 0 | AN17: =+ｶﾞｰﾃﾞﾝ!W16/1000 -> 0 | AO17: 0 | AP17: =+AN17-AO17 -> 0 | AQ17: 0 | AR17: =+AN17-AQ17 -> 0 | AS17: =+ﾋﾞｱｶﾞｰﾃﾞﾝ!W16/1000 -> 0 | AT17: 0 | AU17: =+AS17-AT17 -> 0 | AV17: 0 | AW17: =+AS17-AV17 -> 0 | AX17: =+AN17+AS17 -> 0 | AY17: =+AO17+AT17 -> 0 | AZ17: =+AX17-AY17 -> 0 | BA17: =+AQ17+AV17 -> 0 | BB17: =+AX17-BA17 -> 0 | BC17: 0 | BD17: 0 | BE17: =+BC17+BD17 -> 0 | BF17: =+料飲共通!W16/1000 -> 0 | BG17: 0 | BH17: =+BF17-BG17 -> 0 | BI17: 0 | BJ17: =+BF17-BI17 -> 0 | BK17: =+T17+AI17+AX17+BE17+BF17 -> 0 | BL17: =+U17+AJ17+AY17+BG17 -> 0 | BM17: =+BK17-BL17 -> 0 | BN17: =+W17+AL17+BA17+BI17 -> 0 | BO17: =+BK17-BN17 -> 0 | BP17: =+BK17-BE17 -> 0 | BQ17: =+BL17-Z17 -> 0 | BR17: =+BP17-BQ17 -> 0 | BS17: =+BN17-AB17 -> 0 | BT17: =+BP17-BS17 -> 0
A18: 売上原価 | E18: =+ﾇｰﾍﾞﾙﾌﾟｰｽ!W17/1000 -> 28482.785 | F18: 28320.083 | G18: =+E18-F18 -> 162.70169 | H18: 26899 | I18: =+E18-H18 -> 1583.785 | J18: =+ｶﾌｪﾙﾎﾟ!W17/1000 -> 2947.871 | K18: 2580.2876 | L18: =+J18-K18 -> 367.58342 | M18: 3102 | N18: =+J18-M18 -> -154.12896 | O18: =+ｶﾌｪｾﾚｽﾃ!W17/1000 -> 5992.945 | P18: 5770.5787 | Q18: =+O18-P18 -> 222.36626 | R18: 4519 | S18: =+O18-R18 -> 1473.945 | T18: =+E18+J18+O18 -> 37423.601 | U18: =+F18+K18+P18 -> 36670.95 | V18: =+T18-U18 -> 752.65136 | W18: =+H18+M18+R18 -> 34520 | X18: =+T18-W18 -> 2903.601 | Y18: 0 | Z18: 7881.9417 | AA18: =+Y18-Z18 -> -7881.9417 | AB18: 6854 | AC18: =+Y18-AB18 -> -6854 | AD18: =+ｼﾞｭｴﾙｽﾞ!W17/1000 -> 47241.415 | AE18: 44933.767 | AF18: =+AD18-AE18 -> 2307.6487 | AG18: 42361 | AH18: =+AD18-AG18 -> 4880.4152 | AI18: =+Y18+AD18 -> 47241.415 | AJ18: =+Z18+AE18 -> 52815.708 | AK18: =+AI18-AJ18 -> -5574.2931 | AL18: =+AB18+AG18 -> 49215 | AM18: =+AI18-AL18 -> -1973.5848 | AN18: =+ｶﾞｰﾃﾞﾝ!W17/1000 -> 42396.583 | AO18: 42039.85 | AP18: =+AN18-AO18 -> 356.7331 | AQ18: 39663 | AR18: =+AN18-AQ18 -> 2733.5833 | AS18: =+ﾋﾞｱｶﾞｰﾃﾞﾝ!W17/1000 -> 49044.367 | AT18: 43689.866 | AU18: =+AS18-AT18 -> 5354.5007 | AV18: 40909 | AW18: =+AS18-AV18 -> 8135.3667 | AX18: =+AN18+AS18 -> 91440.95 | AY18: =+AO18+AT18 -> 85729.716 | AZ18: =+AX18-AY18 -> 5711.2338 | BA18: =+AQ18+AV18 -> 80572 | BB18: =+AX18-BA18 -> 10868.95 | BC18: =+赤れんが!X18/1000 -> 21479 | BD18: =+赤れんが!Z18/1000 -> 17605.84 | BE18: =+BC18+BD18 -> 39084.84 | BF18: =+料飲共通!W17/1000 -> 0 | BG18: 0 | BH18: =+BF18-BG18 -> 0 | BI18: 0 | BJ18: =+BF18-BI18 -> 0 | BK18: =+T18+AI18+AX18+BE18+BF18 -> 215190.81 | BL18: =+U18+AJ18+AY18+BG18 -> 175216.37 | BM18: =+BK18-BL18 -> 39974.432 | BN18: =+W18+AL18+BA18+BI18 -> 164307 | BO18: =+BK18-BN18 -> 50883.806 | BP18: =+BK18-BE18 -> 176105.97 | BQ18: =+BL18-Z18 -> 167334.43 | BR18: =+BP18-BQ18 -> 8771.5338 | BS18: =+BN18-AB18 -> 157453 | BT18: =+BP18-BS18 -> 18652.966
A19: 売上総利益 | E19: =+ﾇｰﾍﾞﾙﾌﾟｰｽ!W18/1000 -> 69733.715 | F19: 69508.675 | G19: =+E19-F19 -> 225.04031 | H19: 62765 | I19: =+E19-H19 -> 6968.715 | J19: =+ｶﾌｪﾙﾎﾟ!W18/1000 -> 6264.226 | K19: 5612.1354 | L19: =+J19-K19 -> 652.09058 | M19: 6905 | N19: =+J19-M19 -> -640.77404 | O19: =+ｶﾌｪｾﾚｽﾃ!W18/1000 -> 13656.055 | P19: 13132.9 | Q19: =+O19-P19 -> 523.15474 | R19: 10800 | S19: =+O19-R19 -> 2856.055 | T19: =+E19+J19+O19 -> 89653.996 | U19: =+F19+K19+P19 -> 88253.71 | V19: =+T19-U19 -> 1400.2856 | W19: =+H19+M19+R19 -> 80470 | X19: =+T19-W19 -> 9183.996 | Y19: 0 | Z19: 15766.248 | AA19: =+Y19-Z19 -> -15766.248 | AB19: 13917 | AC19: =+Y19-AB19 -> -13917 | AD19: =+ｼﾞｭｴﾙｽﾞ!W18/1000 -> 117076.55 | AE19: 112979.84 | AF19: =+AD19-AE19 -> 4096.7113 | AG19: 98842 | AH19: =+AD19-AG19 -> 18234.551 | AI19: =+Y19+AD19 -> 117076.55 | AJ19: =+Z19+AE19 -> 128746.09 | AK19: =+AI19-AJ19 -> -11669.537 | AL19: =+AB19+AG19 -> 112759 | AM19: =+AI19-AL19 -> 4317.5508 | AN19: =+ｶﾞｰﾃﾞﾝ!W18/1000 -> 94366.589 | AO19: 90960.057 | AP19: =+AN19-AO19 -> 3406.5319 | AQ19: 92548 | AR19: =+AN19-AQ19 -> 1818.5887 | AS19: =+ﾋﾞｱｶﾞｰﾃﾞﾝ!W18/1000 -> 105363.93 | AT19: 97116.494 | AU19: =+AS19-AT19 -> 8247.4343 | AV19: 95456 | AW19: =+AS19-AV19 -> 9907.9283 | AX19: =+AN19+AS19 -> 199730.52 | AY19: =+AO19+AT19 -> 188076.55 | AZ19: =+AX19-AY19 -> 11653.966 | BA19: =+AQ19+AV19 -> 188004 | BB19: =+AX19-BA19 -> 11726.517 | BC19: =+BC7-BC18 -> 53886.66 | BD19: =+BD7-BD18 -> 32696.56 | BE19: =+BC19+BD19 -> 86583.22 | BF19: =+料飲共通!W18/1000 -> 0 | BG19: 0 | BH19: =+BF19-BG19 -> 0 | BI19: 0 | BJ19: =+BF19-BI19 -> 0 | BK19: =+T19+AI19+AX19+BE19+BF19 -> 493044.28 | BL19: =+U19+AJ19+AY19+BG19 -> 405076.35 | BM19: =+BK19-BL19 -> 87967.935 | BN19: =+W19+AL19+BA19+BI19 -> 381233 | BO19: =+BK19-BN19 -> 111811.28 | BP19: =+BK19-BE19 -> 406461.06 | BQ19: =+BL19-Z19 -> 389310.1 | BR19: =+BP19-BQ19 -> 17150.963 | BS19: =+BN19-AB19 -> 367316 | BT19: =+BP19-BS19 -> 39145.064
A20: 人件費 | E20: =+ﾇｰﾍﾞﾙﾌﾟｰｽ!W19/1000 -> 53667.197 | F20: 50619.247 | G20: =+E20-F20 -> 3047.95 | H20: 50248 | I20: =+E20-H20 -> 3419.197 | J20: =+ｶﾌｪﾙﾎﾟ!W19/1000 -> 2876.874 | K20: 3274.776 | L20: =+J20-K20 -> -397.902 | M20: 2838 | N20: =+J20-M20 -> 38.874 | O20: =+ｶﾌｪｾﾚｽﾃ!W19/1000 -> 2876.875 | P20: 3257.375 | Q20: =+O20-P20 -> -380.5 | R20: 2838 | S20: =+O20-R20 -> 38.875 | T20: =+E20+J20+O20 -> 59420.946 | U20: =+F20+K20+P20 -> 57151.398 | V20: =+T20-U20 -> 2269.548 | W20: =+H20+M20+R20 -> 55924 | X20: =+T20-W20 -> 3496.946 | Y20: 0 | Z20: 6101.9184 | AA20: =+Y20-Z20 -> -6101.9184 | AB20: 9311 | AC20: =+Y20-AB20 -> -9311 | AD20: =+ｼﾞｭｴﾙｽﾞ!W19/1000 -> 66777.382 | AE20: 64470.377 | AF20: =+AD20-AE20 -> 2307.0054 | AG20: 63978 | AH20: =+AD20-AG20 -> 2799.3824 | AI20: =+Y20+AD20 -> 66777.382 | AJ20: =+Z20+AE20 -> 70572.295 | AK20: =+AI20-AJ20 -> -3794.913 | AL20: =+AB20+AG20 -> 73289 | AM20: =+AI20-AL20 -> -6511.6176 | AN20: =+ｶﾞｰﾃﾞﾝ!Y19/1000 -> 58176.028 | AO20: 56094.852 | AP20: =+AN20-AO20 -> 2081.176 | AQ20: 61992 | AR20: =+AN20-AQ20 -> -3815.972 | AS20: =+ﾋﾞｱｶﾞｰﾃﾞﾝ!X19/1000 -> 24932.582 | AT20: 24040.651 | AU20: =+AS20-AT20 -> 891.93137 | AV20: 7352 | AW20: =+AS20-AV20 -> 17580.582 | AX20: =+AN20+AS20 -> 83108.61 | AY20: =+AO20+AT20 -> 80135.503 | AZ20: =+AX20-AY20 -> 2973.1074 | BA20: =+AQ20+AV20 -> 69344 | BB20: =+AX20-BA20 -> 13764.61 | BC20: =+BC21+BC22+BC23+BC27+BC30+BC31+BC32+BC36+BC37 -> 30146 | BD20: =+BD21+BD22+BD23+BD27+BD30+BD31+BD32+BD36+BD37 -> 16230 | BE20: =+BC20+BD20 -> 46376 | BF20: =+料飲共通!W19/1000 -> 25580.282 | BG20: 25495.928 | BH20: =+BF20-BG20 -> 84.354448 | BI20: 28147 | BJ20: =+BF20-BI20 -> -2566.7176 | BK20: =+T20+AI20+AX20+BE20+BF20 -> 281263.22 | BL20: =+U20+AJ20+AY20+BG20 -> 233355.12 | BM20: =+BK20-BL20 -> 47908.097 | BN20: =+W20+AL20+BA20+BI20 -> 226704 | BO20: =+BK20-BN20 -> 54559.221 | BP20: =+BK20-BE20 -> 234887.22 | BQ20: =+BL20-Z20 -> 227253.21 | BR20: =+BP20-BQ20 -> 7634.0152 | BS20: =+BN20-AB20 -> 217393 | BT20: =+BP20-BS20 -> 17494.221
B21: 役員報酬 | E21: =+ﾇｰﾍﾞﾙﾌﾟｰｽ!W20/1000 -> 0 | F21: 0 | G21: =+E21-F21 -> 0 | H21: 0 | I21: =+E21-H21 -> 0 | J21: =+ｶﾌｪﾙﾎﾟ!W20/1000 -> 0 | K21: 0 | L21: =+J21-K21 -> 0 | M21: 0 | N21: =+J21-M21 -> 0 | O21: =+ｶﾌｪｾﾚｽﾃ!W20/1000 -> 0 | P21: 0 | Q21: =+O21-P21 -> 0 | R21: 0 | S21: =+O21-R21 -> 0 | T21: =+E21+J21+O21 -> 0 | U21: =+F21+K21+P21 -> 0 | V21: =+T21-U21 -> 0 | W21: =+H21+M21+R21 -> 0 | X21: =+T21-W21 -> 0 | Y21: 0 | Z21: 0 | AA21: =+Y21-Z21 -> 0 | AB21: 0 | AC21: =+Y21-AB21 -> 0 | AD21: =+ｼﾞｭｴﾙｽﾞ!W20/1000 -> 0 | AE21: 0 | AF21: =+AD21-AE21 -> 0 | AG21: 0 | AH21: =+AD21-AG21 -> 0 | AI21: =+Y21+AD21 -> 0 | AJ21: =+Z21+AE21 -> 0 | AK21: =+AI21-AJ21 -> 0 | AL21: =+AB21+AG21 -> 0 | AM21: =+AI21-AL21 -> 0 | AN21: =+ｶﾞｰﾃﾞﾝ!Y20/1000 -> 0 | AO21: 0 | AP21: =+AN21-AO21 -> 0 | AQ21: 0 | AR21: =+AN21-AQ21 -> 0 | AS21: =+ﾋﾞｱｶﾞｰﾃﾞﾝ!X20/1000 -> 0 | AT21: 0 | AU21: =+AS21-AT21 -> 0 | AV21: 0 | AW21: =+AS21-AV21 -> 0 | AX21: =+AN21+AS21 -> 0 | AY21: =+AO21+AT21 -> 0 | AZ21: =+AX21-AY21 -> 0 | BA21: =+AQ21+AV21 -> 0 | BB21: =+AX21-BA21 -> 0 | BD21: 0 | BE21: =+BC21+BD21 -> 0 | BF21: =+料飲共通!W20/1000 -> 0 | BG21: 0 | BH21: =+BF21-BG21 -> 0 | BI21: 0 | BJ21: =+BF21-BI21 -> 0 | BK21: =+T21+AI21+AX21+BE21+BF21 -> 0 | BL21: =+U21+AJ21+AY21+BG21 -> 0 | BM21: =+BK21-BL21 -> 0 | BN21: =+W21+AL21+BA21+BI21 -> 0 | BO21: =+BK21-BN21 -> 0 | BP21: =+BK21-BE21 -> 0 | BQ21: =+BL21-Z21 -> 0 | BR21: =+BP21-BQ21 -> 0 | BS21: =+BN21-AB21 -> 0 | BT21: =+BP21-BS21 -> 0
B22: 社員給与費 | E22: =+ﾇｰﾍﾞﾙﾌﾟｰｽ!W21/1000 -> 0 | F22: 0 | G22: =+E22-F22 -> 0 | H22: 0 | I22: =+E22-H22 -> 0 | J22: =+ｶﾌｪﾙﾎﾟ!W21/1000 -> 0 | K22: 0 | L22: =+J22-K22 -> 0 | M22: 0 | N22: =+J22-M22 -> 0 | O22: =+ｶﾌｪｾﾚｽﾃ!W21/1000 -> 0 | P22: 0 | Q22: =+O22-P22 -> 0 | R22: 0 | S22: =+O22-R22 -> 0 | T22: =+E22+J22+O22 -> 0 | U22: =+F22+K22+P22 -> 0 | V22: =+T22-U22 -> 0 | W22: =+H22+M22+R22 -> 0 | X22: =+T22-W22 -> 0 | Y22: 0 | Z22: 0 | AA22: =+Y22-Z22 -> 0 | AB22: 0 | AC22: =+Y22-AB22 -> 0 | AD22: =+ｼﾞｭｴﾙｽﾞ!W21/1000 -> 0 | AE22: 13.1 | AF22: =+AD22-AE22 -> -13.1 | AG22: 0 | AH22: =+AD22-AG22 -> 0 | AI22: =+Y22+AD22 -> 0 | AJ22: =+Z22+AE22 -> 13.1 | AK22: =+AI22-AJ22 -> -13.1 | AL22: =+AB22+AG22 -> 0 | AM22: =+AI22-AL22 -> 0 | AN22: =+ｶﾞｰﾃﾞﾝ!Y21/1000 -> 0 | AO22: 0 | AP22: =+AN22-AO22 -> 0 | AQ22: 0 | AR22: =+AN22-AQ22 -> 0 | AS22: =+ﾋﾞｱｶﾞｰﾃﾞﾝ!X21/1000 -> 0 | AT22: 0 | AU22: =+AS22-AT22 -> 0 | AV22: 0 | AW22: =+AS22-AV22 -> 0 | AX22: =+AN22+AS22 -> 0 | AY22: =+AO22+AT22 -> 0 | AZ22: =+AX22-AY22 -> 0 | BA22: =+AQ22+AV22 -> 0 | BB22: =+AX22-BA22 -> 0 | BC22: 0 | BD22: 0 | BE22: =+BC22+BD22 -> 0 | BF22: =+料飲共通!W21/1000 -> 21846.07 | BG22: 21621.517 | BH22: =+BF22-BG22 -> 224.553 | BI22: 20811 | BJ22: =+BF22-BI22 -> 1035.07 | BK22: =+T22+AI22+AX22+BE22+BF22 -> 21846.07 | BL22: =+U22+AJ22+AY22+BG22 -> 21634.617 | BM22: =+BK22-BL22 -> 211.453 | BN22: =+W22+AL22+BA22+BI22 -> 20811 | BO22: =+BK22-BN22 -> 1035.07 | BP22: =+BK22-BE22 -> 21846.07 | BQ22: =+BL22-Z22 -> 21634.617 | BR22: =+BP22-BQ22 -> 211.453 | BS22: =+BN22-AB22 -> 20811 | BT22: =+BP22-BS22 -> 1035.07
B23: 専門等給与費 | E23: =+ﾇｰﾍﾞﾙﾌﾟｰｽ!W22/1000 -> 44651.64 | F23: 43294.594 | G23: =+E23-F23 -> 1357.046 | H23: 41992 | I23: =+E23-H23 -> 2659.64 | J23: =+ｶﾌｪﾙﾎﾟ!W22/1000 -> 2524.2 | K23: 2933.994 | L23: =+J23-K23 -> -409.794 | M23: 2532 | N23: =+J23-M23 -> -7.8 | O23: =+ｶﾌｪｾﾚｽﾃ!W22/1000 -> 2524.2 | P23: 2933.994 | Q23: =+O23-P23 -> -409.794 | R23: 2532 | S23: =+O23-R23 -> -7.8 | T23: =+E23+J23+O23 -> 49700.04 | U23: =+F23+K23+P23 -> 49162.582 | V23: =+T23-U23 -> 537.458 | W23: =+H23+M23+R23 -> 47056 | X23: =+T23-W23 -> 2644.04 | Y23: 0 | Z23: 5497.3054 | AA23: =+Y23-Z23 -> -5497.3054 | AB23: 8241 | AC23: =+Y23-AB23 -> -8241 | AD23: =+ｼﾞｭｴﾙｽﾞ!W22/1000 -> 55698.34 | AE23: 55178.98 | AF23: =+AD23-AE23 -> 519.36 | AG23: 54040 | AH23: =+AD23-AG23 -> 1658.34 | AI23: =+Y23+AD23 -> 55698.34 | AJ23: =+Z23+AE23 -> 60676.285 | AK23: =+AI23-AJ23 -> -4977.9454 | AL23: =+AB23+AG23 -> 62281 | AM23: =+AI23-AL23 -> -6582.66 | AN23: =+ｶﾞｰﾃﾞﾝ!Y22/1000 -> 49303.667 | AO23: 48006.785 | AP23: =+AN23-AO23 -> 1296.882 | AQ23: 53804 | AR23: =+AN23-AQ23 -> -4500.333 | AS23: =+ﾋﾞｱｶﾞｰﾃﾞﾝ!X22/1000 -> 21130.143 | AT23: 20574.337 | AU23: =+AS23-AT23 -> 555.806 | AV23: 6340 | AW23: =+AS23-AV23 -> 14790.143 | AX23: =+AN23+AS23 -> 70433.81 | AY23: =+AO23+AT23 -> 68581.122 | AZ23: =+AX23-AY23 -> 1852.688 | BA23: =+AQ23+AV23 -> 60144 | BB23: =+AX23-BA23 -> 10289.81 | BC23: =+赤れんが!X20/1000 -> 30146 | BD23: =+赤れんが!Z20/1000 -> 16230 | BE23: =+BC23+BD23 -> 46376 | BF23: =+料飲共通!W22/1000 -> 0 | BG23: 0 | BH23: =+BF23-BG23 -> 0 | BI23: 3150 | BJ23: =+BF23-BI23 -> -3150 | BK23: =+T23+AI23+AX23+BE23+BF23 -> 222208.19 | BL23: =+U23+AJ23+AY23+BG23 -> 178419.99 | BM23: =+BK23-BL23 -> 43788.201 | BN23: =+W23+AL23+BA23+BI23 -> 172631 | BO23: =+BK23-BN23 -> 49577.19 | BP23: =+BK23-BE23 -> 175832.19 | BQ23: =+BL23-Z23 -> 172922.68 | BR23: =+BP23-BQ23 -> 2909.506 | BS23: =+BN23-AB23 -> 164390 | BT23: =+BP23-BS23 -> 11442.19
C24: 専門 | E24: =+ﾇｰﾍﾞﾙﾌﾟｰｽ!W23/1000 -> 44462.64 | F24: 41495.924 | G24: =+E24-F24 -> 2966.716 | H24: 41110 | I24: =+E24-H24 -> 3352.64 | J24: =+ｶﾌｪﾙﾎﾟ!W23/1000 -> 0 | K24: 0 | L24: =+J24-K24 -> 0 | M24: 0 | N24: =+J24-M24 -> 0 | O24: =+ｶﾌｪｾﾚｽﾃ!W23/1000 -> 0 | P24: 0 | Q24: =+O24-P24 -> 0 | R24: 0 | S24: =+O24-R24 -> 0 | T24: =+E24+J24+O24 -> 44462.64 | U24: =+F24+K24+P24 -> 41495.924 | V24: =+T24-U24 -> 2966.716 | W24: =+H24+M24+R24 -> 41110 | X24: =+T24-W24 -> 3352.64 | Y24: 0 | Z24: 2105.471 | AA24: =+Y24-Z24 -> -2105.471 | AB24: 3747 | AC24: =+Y24-AB24 -> -3747 | AD24: =+ｼﾞｭｴﾙｽﾞ!W23/1000 -> 50391.64 | AE24: 49336.023 | AF24: =+AD24-AE24 -> 1055.617 | AG24: 46648 | AH24: =+AD24-AG24 -> 3743.64 | AI24: =+Y24+AD24 -> 50391.64 | AJ24: =+Z24+AE24 -> 51441.494 | AK24: =+AI24-AJ24 -> -1049.854 | AL24: =+AB24+AG24 -> 50395 | AM24: =+AI24-AL24 -> -3.36 | AN24: =+ｶﾞｰﾃﾞﾝ!W23/1000 -> 63275.81 | AO24: 40063.794 | AP24: =+AN24-AO24 -> 23212.016 | AQ24: 43908 | AR24: =+AN24-AQ24 -> 19367.81 | AS24: =+ﾋﾞｱｶﾞｰﾃﾞﾝ!W23/1000 -> 0 | AT24: 17170.198 | AU24: =+AS24-AT24 -> -17170.198 | AV24: 6340 | AW24: =+AS24-AV24 -> -6340 | AX24: =+AN24+AS24 -> 63275.81 | AY24: =+AO24+AT24 -> 57233.992 | AZ24: =+AX24-AY24 -> 6041.818 | BA24: =+AQ24+AV24 -> 50248 | BB24: =+AX24-BA24 -> 13027.81 | BC24: 0 | BD24: 0 | BE24: =+BC24+BD24 -> 0 | BF24: =+料飲共通!W23/1000 -> 0 | BG24: 0 | BH24: =+BF24-BG24 -> 0 | BI24: 0 | BJ24: =+BF24-BI24 -> 0 | BK24: =+T24+AI24+AX24+BE24+BF24 -> 158130.09 | BL24: =+U24+AJ24+AY24+BG24 -> 150171.41 | BM24: =+BK24-BL24 -> 7958.68 | BN24: =+W24+AL24+BA24+BI24 -> 141753 | BO24: =+BK24-BN24 -> 16377.09 | BP24: =+BK24-BE24 -> 158130.09 | BQ24: =+BL24-Z24 -> 148065.94 | BR24: =+BP24-BQ24 -> 10064.151 | BS24: =+BN24-AB24 -> 138006 | BT24: =+BP24-BS24 -> 20124.09
C25: 臨時 | E25: =+ﾇｰﾍﾞﾙﾌﾟｰｽ!W24/1000 -> 0 | F25: 0 | G25: =+E25-F25 -> 0 | H25: 0 | I25: =+E25-H25 -> 0 | J25: =+ｶﾌｪﾙﾎﾟ!W24/1000 -> 0 | K25: 0 | L25: =+J25-K25 -> 0 | M25: 0 | N25: =+J25-M25 -> 0 | O25: =+ｶﾌｪｾﾚｽﾃ!W24/1000 -> 0 | P25: 0 | Q25: =+O25-P25 -> 0 | R25: 0 | S25: =+O25-R25 -> 0 | T25: =+E25+J25+O25 -> 0 | U25: =+F25+K25+P25 -> 0 | V25: =+T25-U25 -> 0 | W25: =+H25+M25+R25 -> 0 | X25: =+T25-W25 -> 0 | Y25: 0 | Z25: 0 | AA25: =+Y25-Z25 -> 0 | AB25: 0 | AC25: =+Y25-AB25 -> 0 | AD25: =+ｼﾞｭｴﾙｽﾞ!W24/1000 -> 0 | AE25: 0 | AF25: =+AD25-AE25 -> 0 | AG25: 0 | AH25: =+AD25-AG25 -> 0 | AI25: =+Y25+AD25 -> 0 | AJ25: =+Z25+AE25 -> 0 | AK25: =+AI25-AJ25 -> 0 | AL25: =+AB25+AG25 -> 0 | AM25: =+AI25-AL25 -> 0 | AN25: =+ｶﾞｰﾃﾞﾝ!W24/1000 -> 0 | AO25: 0 | AP25: =+AN25-AO25 -> 0 | AQ25: 0 | AR25: =+AN25-AQ25 -> 0 | AS25: =+ﾋﾞｱｶﾞｰﾃﾞﾝ!W24/1000 -> 0 | AT25: 0 | AU25: =+AS25-AT25 -> 0 | AV25: 0 | AW25: =+AS25-AV25 -> 0 | AX25: =+AN25+AS25 -> 0 | AY25: =+AO25+AT25 -> 0 | AZ25: =+AX25-AY25 -> 0 | BA25: =+AQ25+AV25 -> 0 | BB25: =+AX25-BA25 -> 0 | BC25: 0 | BD25: 0 | BE25: =+BC25+BD25 -> 0 | BF25: =+料飲共通!W24/1000 -> 0 | BG25: 0 | BH25: =+BF25-BG25 -> 0 | BI25: 0 | BJ25: =+BF25-BI25 -> 0 | BK25: =+T25+AI25+AX25+BE25+BF25 -> 0 | BL25: =+U25+AJ25+AY25+BG25 -> 0 | BM25: =+BK25-BL25 -> 0 | BN25: =+W25+AL25+BA25+BI25 -> 0 | BO25: =+BK25-BN25 -> 0 | BP25: =+BK25-BE25 -> 0 | BQ25: =+BL25-Z25 -> 0 | BR25: =+BP25-BQ25 -> 0 | BS25: =+BN25-AB25 -> 0 | BT25: =+BP25-BS25 -> 0
C26: パート | E26: =+ﾇｰﾍﾞﾙﾌﾟｰｽ!W25/1000 -> 189 | F26: 1798.67 | G26: =+E26-F26 -> -1609.67 | H26: 882 | I26: =+E26-H26 -> -693 | J26: =+ｶﾌｪﾙﾎﾟ!W25/1000 -> 2524.2 | K26: 2933.994 | L26: =+J26-K26 -> -409.794 | M26: 2532 | N26: =+J26-M26 -> -7.8 | O26: =+ｶﾌｪｾﾚｽﾃ!W25/1000 -> 2524.2 | P26: 2933.994 | Q26: =+O26-P26 -> -409.794 | R26: 2532 | S26: =+O26-R26 -> -7.8 | T26: =+E26+J26+O26 -> 5237.4 | U26: =+F26+K26+P26 -> 7666.658 | V26: =+T26-U26 -> -2429.258 | W26: =+H26+M26+R26 -> 5946 | X26: =+T26-W26 -> -708.6 | Y26: 0 | Z26: 3391.8344 | AA26: =+Y26-Z26 -> -3391.8344 | AB26: 4494 | AC26: =+Y26-AB26 -> -4494 | AD26: =+ｼﾞｭｴﾙｽﾞ!W25/1000 -> 5306.7 | AE26: 5842.957 | AF26: =+AD26-AE26 -> -536.257 | AG26: 7392 | AH26: =+AD26-AG26 -> -2085.3 | AI26: =+Y26+AD26 -> 5306.7 | AJ26: =+Z26+AE26 -> 9234.7914 | AK26: =+AI26-AJ26 -> -3928.0914 | AL26: =+AB26+AG26 -> 11886 | AM26: =+AI26-AL26 -> -6579.3 | AN26: =+ｶﾞｰﾃﾞﾝ!W25/1000 -> 3528 | AO26: 7942.991 | AP26: =+AN26-AO26 -> -4414.991 | AQ26: 9896 | AR26: =+AN26-AQ26 -> -6368 | AS26: =+ﾋﾞｱｶﾞｰﾃﾞﾝ!W25/1000 -> 3630 | AT26: 3404.139 | AU26: =+AS26-AT26 -> 225.861 | AV26: 0 | AW26: =+AS26-AV26 -> 3630 | AX26: =+AN26+AS26 -> 7158 | AY26: =+AO26+AT26 -> 11347.13 | AZ26: =+AX26-AY26 -> -4189.13 | BA26: =+AQ26+AV26 -> 9896 | BB26: =+AX26-BA26 -> -2738 | BC26: 0 | BD26: 0 | BE26: =+BC26+BD26 -> 0 | BF26: =+料飲共通!W25/1000 -> 0 | BG26: 0 | BH26: =+BF26-BG26 -> 0 | BI26: 3150 | BJ26: =+BF26-BI26 -> -3150 | BK26: =+T26+AI26+AX26+BE26+BF26 -> 17702.1 | BL26: =+U26+AJ26+AY26+BG26 -> 28248.579 | BM26: =+BK26-BL26 -> -10546.479 | BN26: =+W26+AL26+BA26+BI26 -> 30878 | BO26: =+BK26-BN26 -> -13175.9 | BP26: =+BK26-BE26 -> 17702.1 | BQ26: =+BL26-Z26 -> 24856.745 | BR26: =+BP26-BQ26 -> -7154.645 | BS26: =+BN26-AB26 -> 26384 | BT26: =+BP26-BS26 -> -8681.9
B27: 退職金 | E27: =+ﾇｰﾍﾞﾙﾌﾟｰｽ!W26/1000 -> 0 | F27: 0 | G27: =+E27-F27 -> 0 | H27: 0 | I27: =+E27-H27 -> 0 | J27: =+ｶﾌｪﾙﾎﾟ!W26/1000 -> 0 | K27: 0 | L27: =+J27-K27 -> 0 | M27: 0 | N27: =+J27-M27 -> 0 | O27: =+ｶﾌｪｾﾚｽﾃ!W26/1000 -> 0 | P27: 0 | Q27: =+O27-P27 -> 0 | R27: 0 | S27: =+O27-R27 -> 0 | T27: =+E27+J27+O27 -> 0 | U27: =+F27+K27+P27 -> 0 | V27: =+T27-U27 -> 0 | W27: =+H27+M27+R27 -> 0 | X27: =+T27-W27 -> 0 | Y27: 0 | Z27: 0 | AA27: =+Y27-Z27 -> 0 | AB27: 0 | AC27: =+Y27-AB27 -> 0 | AD27: =+ｼﾞｭｴﾙｽﾞ!W26/1000 -> 0 | AE27: 0 | AF27: =+AD27-AE27 -> 0 | AG27: 0 | AH27: =+AD27-AG27 -> 0 | AI27: =+Y27+AD27 -> 0 | AJ27: =+Z27+AE27 -> 0 | AK27: =+AI27-AJ27 -> 0 | AL27: =+AB27+AG27 -> 0 | AM27: =+AI27-AL27 -> 0 | AN27: =+ｶﾞｰﾃﾞﾝ!Y26/1000 -> 0 | AO27: 0 | AP27: =+AN27-AO27 -> 0 | AQ27: 0 | AR27: =+AN27-AQ27 -> 0 | AS27: =+ﾋﾞｱｶﾞｰﾃﾞﾝ!X26/1000 -> 0 | AT27: 0 | AU27: =+AS27-AT27 -> 0 | AV27: 0 | AW27: =+AS27-AV27 -> 0 | AX27: =+AN27+AS27 -> 0 | AY27: =+AO27+AT27 -> 0 | AZ27: =+AX27-AY27 -> 0 | BA27: =+AQ27+AV27 -> 0 | BB27: =+AX27-BA27 -> 0 | BC27: 0 | BD27: 0 | BE27: =+BC27+BD27 -> 0 | BF27: =+料飲共通!W26/1000 -> 0 | BG27: 0 | BH27: =+BF27-BG27 -> 0 | BI27: 0 | BJ27: =+BF27-BI27 -> 0 | BK27: =+T27+AI27+AX27+BE27+BF27 -> 0 | BL27: =+U27+AJ27+AY27+BG27 -> 0 | BM27: =+BK27-BL27 -> 0 | BN27: =+W27+AL27+BA27+BI27 -> 0 | BO27: =+BK27-BN27 -> 0 | BP27: =+BK27-BE27 -> 0 | BQ27: =+BL27-Z27 -> 0 | BR27: =+BP27-BQ27 -> 0 | BS27: =+BN27-AB27 -> 0 | BT27: =+BP27-BS27 -> 0
C28: 役員 | E28: =+ﾇｰﾍﾞﾙﾌﾟｰｽ!W27/1000 -> 0 | F28: 0 | G28: =+E28-F28 -> 0 | H28: 0 | I28: =+E28-H28 -> 0 | J28: =+ｶﾌｪﾙﾎﾟ!W27/1000 -> 0 | K28: 0 | L28: =+J28-K28 -> 0 | M28: 0 | N28: =+J28-M28 -> 0 | O28: =+ｶﾌｪｾﾚｽﾃ!W27/1000 -> 0 | P28: 0 | Q28: =+O28-P28 -> 0 | R28: 0 | S28: =+O28-R28 -> 0 | T28: =+E28+J28+O28 -> 0 | U28: =+F28+K28+P28 -> 0 | V28: =+T28-U28 -> 0 | W28: =+H28+M28+R28 -> 0 | X28: =+T28-W28 -> 0 | Y28: 0 | Z28: 0 | AA28: =+Y28-Z28 -> 0 | AB28: 0 | AC28: =+Y28-AB28 -> 0 | AD28: =+ｼﾞｭｴﾙｽﾞ!W27/1000 -> 0 | AE28: 0 | AF28: =+AD28-AE28 -> 0 | AG28: 0 | AH28: =+AD28-AG28 -> 0 | AI28: =+Y28+AD28 -> 0 | AJ28: =+Z28+AE28 -> 0 | AK28: =+AI28-AJ28 -> 0 | AL28: =+AB28+AG28 -> 0 | AM28: =+AI28-AL28 -> 0 | AN28: =+ｶﾞｰﾃﾞﾝ!W27/1000 -> 0 | AO28: 0 | AP28: =+AN28-AO28 -> 0 | AQ28: 0 | AR28: =+AN28-AQ28 -> 0 | AS28: =+ﾋﾞｱｶﾞｰﾃﾞﾝ!W27/1000 -> 0 | AT28: 0 | AU28: =+AS28-AT28 -> 0 | AV28: 0 | AW28: =+AS28-AV28 -> 0 | AX28: =+AN28+AS28 -> 0 | AY28: =+AO28+AT28 -> 0 | AZ28: =+AX28-AY28 -> 0 | BA28: =+AQ28+AV28 -> 0 | BB28: =+AX28-BA28 -> 0 | BC28: 0 | BD28: 0 | BE28: =+BC28+BD28 -> 0 | BF28: =+料飲共通!W27/1000 -> 0 | BG28: 0 | BH28: =+BF28-BG28 -> 0 | BI28: 0 | BJ28: =+BF28-BI28 -> 0 | BK28: =+T28+AI28+AX28+BE28+BF28 -> 0 | BL28: =+U28+AJ28+AY28+BG28 -> 0 | BM28: =+BK28-BL28 -> 0 | BN28: =+W28+AL28+BA28+BI28 -> 0 | BO28: =+BK28-BN28 -> 0 | BP28: =+BK28-BE28 -> 0 | BQ28: =+BL28-Z28 -> 0 | BR28: =+BP28-BQ28 -> 0 | BS28: =+BN28-AB28 -> 0 | BT28: =+BP28-BS28 -> 0
C29: 社員 | E29: =+ﾇｰﾍﾞﾙﾌﾟｰｽ!W28/1000 -> 0 | F29: 0 | G29: =+E29-F29 -> 0 | H29: 0 | I29: =+E29-H29 -> 0 | J29: =+ｶﾌｪﾙﾎﾟ!W28/1000 -> 0 | K29: 0 | L29: =+J29-K29 -> 0 | M29: 0 | N29: =+J29-M29 -> 0 | O29: =+ｶﾌｪｾﾚｽﾃ!W28/1000 -> 0 | P29: 0 | Q29: =+O29-P29 -> 0 | R29: 0 | S29: =+O29-R29 -> 0 | T29: =+E29+J29+O29 -> 0 | U29: =+F29+K29+P29 -> 0 | V29: =+T29-U29 -> 0 | W29: =+H29+M29+R29 -> 0 | X29: =+T29-W29 -> 0 | Y29: 0 | Z29: 0 | AA29: =+Y29-Z29 -> 0 | AB29: 0 | AC29: =+Y29-AB29 -> 0 | AD29: =+ｼﾞｭｴﾙｽﾞ!W28/1000 -> 0 | AE29: 0 | AF29: =+AD29-AE29 -> 0 | AG29: 0 | AH29: =+AD29-AG29 -> 0 | AI29: =+Y29+AD29 -> 0 | AJ29: =+Z29+AE29 -> 0 | AK29: =+AI29-AJ29 -> 0 | AL29: =+AB29+AG29 -> 0 | AM29: =+AI29-AL29 -> 0 | AN29: =+ｶﾞｰﾃﾞﾝ!W28/1000 -> 0 | AO29: 0 | AP29: =+AN29-AO29 -> 0 | AQ29: 0 | AR29: =+AN29-AQ29 -> 0 | AS29: =+ﾋﾞｱｶﾞｰﾃﾞﾝ!W28/1000 -> 0 | AT29: 0 | AU29: =+AS29-AT29 -> 0 | AV29: 0 | AW29: =+AS29-AV29 -> 0 | AX29: =+AN29+AS29 -> 0 | AY29: =+AO29+AT29 -> 0 | AZ29: =+AX29-AY29 -> 0 | BA29: =+AQ29+AV29 -> 0 | BB29: =+AX29-BA29 -> 0 | BC29: 0 | BD29: 0 | BE29: =+BC29+BD29 -> 0 | BF29: =+料飲共通!W28/1000 -> 0 | BG29: 0 | BH29: =+BF29-BG29 -> 0 | BI29: 0 | BJ29: =+BF29-BI29 -> 0 | BK29: =+T29+AI29+AX29+BE29+BF29 -> 0 | BL29: =+U29+AJ29+AY29+BG29 -> 0 | BM29: =+BK29-BL29 -> 0 | BN29: =+W29+AL29+BA29+BI29 -> 0 | BO29: =+BK29-BN29 -> 0 | BP29: =+BK29-BE29 -> 0 | BQ29: =+BL29-Z29 -> 0 | BR29: =+BP29-BQ29 -> 0 | BS29: =+BN29-AB29 -> 0 | BT29: =+BP29-BS29 -> 0
B30: 法定福利費 | E30: =+ﾇｰﾍﾞﾙﾌﾟｰｽ!W29/1000 -> 7178.685 | F30: 5733.793 | G30: =+E30-F30 -> 1444.892 | H30: 6921 | I30: =+E30-H30 -> 257.68498 | J30: =+ｶﾌｪﾙﾎﾟ!W29/1000 -> 241.664 | K30: 245.156 | L30: =+J30-K30 -> -3.492 | M30: 240 | N30: =+J30-M30 -> 1.664 | O30: =+ｶﾌｪｾﾚｽﾃ!W29/1000 -> 241.665 | P30: 245.156 | Q30: =+O30-P30 -> -3.491 | R30: 240 | S30: =+O30-R30 -> 1.665 | T30: =+E30+J30+O30 -> 7662.014 | U30: =+F30+K30+P30 -> 6224.105 | V30: =+T30-U30 -> 1437.909 | W30: =+H30+M30+R30 -> 7401 | X30: =+T30-W30 -> 261.01398 | Y30: 0 | Z30: 361.254 | AA30: =+Y30-Z30 -> -361.254 | AB30: 689 | AC30: =+Y30-AB30 -> -689 | AD30: =+ｼﾞｭｴﾙｽﾞ!W29/1000 -> 8543.7104 | AE30: 7112.791 | AF30: =+AD30-AE30 -> 1430.9194 | AG30: 7741 | AH30: =+AD30-AG30 -> 802.71042 | AI30: =+Y30+AD30 -> 8543.7104 | AJ30: =+Z30+AE30 -> 7474.045 | AK30: =+AI30-AJ30 -> 1069.6654 | AL30: =+AB30+AG30 -> 8430 | AM30: =+AI30-AL30 -> 113.71042 | AN30: =+ｶﾞｰﾃﾞﾝ!Y29/1000 -> 6767.259 | AO30: 5805.373 | AP30: =+AN30-AO30 -> 961.886 | AQ30: 7759 | AR30: =+AN30-AQ30 -> -991.741 | AS30: =+ﾋﾞｱｶﾞｰﾃﾞﾝ!X29/1000 -> 2900.2534 | AT30: 2488.017 | AU30: =+AS30-AT30 -> 412.23637 | AV30: 880 | AW30: =+AS30-AV30 -> 2020.2534 | AX30: =+AN30+AS30 -> 9667.5124 | AY30: =+AO30+AT30 -> 8293.39 | AZ30: =+AX30-AY30 -> 1374.1224 | BA30: =+AQ30+AV30 -> 8639 | BB30: =+AX30-BA30 -> 1028.5124 | BC30: 0 | BD30: 0 | BE30: =+BC30+BD30 -> 0 | BF30: =+料飲共通!W29/1000 -> 3421.3564 | BG30: 3202.207 | BH30: =+BF30-BG30 -> 219.14945 | BI30: 3849 | BJ30: =+BF30-BI30 -> -427.64355 | BK30: =+T30+AI30+AX30+BE30+BF30 -> 29294.593 | BL30: =+U30+AJ30+AY30+BG30 -> 25193.747 | BM30: =+BK30-BL30 -> 4100.8462 | BN30: =+W30+AL30+BA30+BI30 -> 28319 | BO30: =+BK30-BN30 -> 975.59322 | BP30: =+BK30-BE30 -> 29294.593 | BQ30: =+BL30-Z30 -> 24832.493 | BR30: =+BP30-BQ30 -> 4462.1002 | BS30: =+BN30-AB30 -> 27630 | BT30: =+BP30-BS30 -> 1664.5932
B31: 退職年金掛金 | E31: =+ﾇｰﾍﾞﾙﾌﾟｰｽ!W30/1000 -> 52.8 | F31: 43.6 | G31: =+E31-F31 -> 9.2 | H31: 48 | I31: =+E31-H31 -> 4.8 | J31: =+ｶﾌｪﾙﾎﾟ!W30/1000 -> 0 | K31: 0 | L31: =+J31-K31 -> 0 | M31: 0 | N31: =+J31-M31 -> 0 | O31: =+ｶﾌｪｾﾚｽﾃ!W30/1000 -> 0 | P31: 0 | Q31: =+O31-P31 -> 0 | R31: 0 | S31: =+O31-R31 -> 0 | T31: =+E31+J31+O31 -> 52.8 | U31: =+F31+K31+P31 -> 43.6 | V31: =+T31-U31 -> 9.2 | W31: =+H31+M31+R31 -> 48 | X31: =+T31-W31 -> 4.8 | Y31: 0 | Z31: 2.4 | AA31: =+Y31-Z31 -> -2.4 | AB31: 3 | AC31: =+Y31-AB31 -> -3 | AD31: =+ｼﾞｭｴﾙｽﾞ!W30/1000 -> 62.4 | AE31: 51.2 | AF31: =+AD31-AE31 -> 11.2 | AG31: 57 | AH31: =+AD31-AG31 -> 5.4 | AI31: =+Y31+AD31 -> 62.4 | AJ31: =+Z31+AE31 -> 53.6 | AK31: =+AI31-AJ31 -> 8.8 | AL31: =+AB31+AG31 -> 60 | AM31: =+AI31-AL31 -> 2.4 | AN31: =+ｶﾞｰﾃﾞﾝ!Y30/1000 -> 50.4 | AO31: 50.12 | AP31: =+AN31-AO31 -> 0.28 | AQ31: 52 | AR31: =+AN31-AQ31 -> -1.6 | AS31: =+ﾋﾞｱｶﾞｰﾃﾞﾝ!X30/1000 -> 21.6 | AT31: 21.48 | AU31: =+AS31-AT31 -> 0.12 | AV31: 6 | AW31: =+AS31-AV31 -> 15.6 | AX31: =+AN31+AS31 -> 72 | AY31: =+AO31+AT31 -> 71.6 | AZ31: =+AX31-AY31 -> 0.4 | BA31: =+AQ31+AV31 -> 58 | BB31: =+AX31-BA31 -> 14 | BC31: 0 | BD31: 0 | BE31: =+BC31+BD31 -> 0 | BF31: =+料飲共通!W30/1000 -> 14.4 | BG31: 14.4 | BH31: =+BF31-BG31 -> 0 | BI31: 14 | BJ31: =+BF31-BI31 -> 0.4 | BK31: =+T31+AI31+AX31+BE31+BF31 -> 201.6 | BL31: =+U31+AJ31+AY31+BG31 -> 183.2 | BM31: =+BK31-BL31 -> 18.4 | BN31: =+W31+AL31+BA31+BI31 -> 180 | BO31: =+BK31-BN31 -> 21.6 | BP31: =+BK31-BE31 -> 201.6 | BQ31: =+BL31-Z31 -> 180.8 | BR31: =+BP31-BQ31 -> 20.8 | BS31: =+BN31-AB31 -> 177 | BT31: =+BP31-BS31 -> 24.6
B32: 福利厚生費 | E32: =+ﾇｰﾍﾞﾙﾌﾟｰｽ!W31/1000 -> 609.2 | F32: 489.014 | G32: =+E32-F32 -> 120.186 | H32: 322 | I32: =+E32-H32 -> 287.2 | J32: =+ｶﾌｪﾙﾎﾟ!W31/1000 -> 0 | K32: 17.4 | L32: =+J32-K32 -> -17.4 | M32: 0 | N32: =+J32-M32 -> 0 | O32: =+ｶﾌｪｾﾚｽﾃ!W31/1000 -> 0 | P32: 0 | Q32: =+O32-P32 -> 0 | R32: 0 | S32: =+O32-R32 -> 0 | T32: =+E32+J32+O32 -> 609.2 | U32: =+F32+K32+P32 -> 506.414 | V32: =+T32-U32 -> 102.786 | W32: =+H32+M32+R32 -> 322 | X32: =+T32-W32 -> 287.2 | Y32: 0 | Z32: 3.6 | AA32: =+Y32-Z32 -> -3.6 | AB32: 104 | AC32: =+Y32-AB32 -> -104 | AD32: =+ｼﾞｭｴﾙｽﾞ!W31/1000 -> 623.6 | AE32: 514.454 | AF32: =+AD32-AE32 -> 109.146 | AG32: 389 | AH32: =+AD32-AG32 -> 234.6 | AI32: =+Y32+AD32 -> 623.6 | AJ32: =+Z32+AE32 -> 518.054 | AK32: =+AI32-AJ32 -> 105.546 | AL32: =+AB32+AG32 -> 493 | AM32: =+AI32-AL32 -> 130.6 | AN32: =+ｶﾞｰﾃﾞﾝ!Y31/1000 -> 446.6 | AO32: 419.848 | AP32: =+AN32-AO32 -> 26.752 | AQ32: 329 | AR32: =+AN32-AQ32 -> 117.6 | AS32: =+ﾋﾞｱｶﾞｰﾃﾞﾝ!X31/1000 -> 191.4 | AT32: 179.935 | AU32: =+AS32-AT32 -> 11.465 | AV32: 9 | AW32: =+AS32-AV32 -> 182.4 | AX32: =+AN32+AS32 -> 638 | AY32: =+AO32+AT32 -> 599.783 | AZ32: =+AX32-AY32 -> 38.217 | BA32: =+AQ32+AV32 -> 338 | BB32: =+AX32-BA32 -> 300 | BC32: 0 | BD32: 0 | BE32: =+BC32+BD32 -> 0 | BF32: =+料飲共通!W31/1000 -> 61.6 | BG32: 424.6 | BH32: =+BF32-BG32 -> -363 | BI32: 21 | BJ32: =+BF32-BI32 -> 40.6 | BK32: =+T32+AI32+AX32+BE32+BF32 -> 1932.4 | BL32: =+U32+AJ32+AY32+BG32 -> 2048.851 | BM32: =+BK32-BL32 -> -116.451 | BN32: =+W32+AL32+BA32+BI32 -> 1174 | BO32: =+BK32-BN32 -> 758.4 | BP32: =+BK32-BE32 -> 1932.4 | BQ32: =+BL32-Z32 -> 2045.251 | BR32: =+BP32-BQ32 -> -112.851 | BS32: =+BN32-AB32 -> 1070 | BT32: =+BP32-BS32 -> 862.4
C33: 福利厚生費 | E33: =+ﾇｰﾍﾞﾙﾌﾟｰｽ!W32/1000 -> 79.2 | F33: 53.4 | G33: =+E33-F33 -> 25.8 | H33: 72 | I33: =+E33-H33 -> 7.2 | J33: =+ｶﾌｪﾙﾎﾟ!W32/1000 -> 0 | K33: 0 | L33: =+J33-K33 -> 0 | M33: 0 | N33: =+J33-M33 -> 0 | O33: =+ｶﾌｪｾﾚｽﾃ!W32/1000 -> 0 | P33: 0 | Q33: =+O33-P33 -> 0 | R33: 0 | S33: =+O33-R33 -> 0 | T33: =+E33+J33+O33 -> 79.2 | U33: =+F33+K33+P33 -> 53.4 | V33: =+T33-U33 -> 25.8 | W33: =+H33+M33+R33 -> 72 | X33: =+T33-W33 -> 7.2 | Y33: 0 | Z33: 3.6 | AA33: =+Y33-Z33 -> -3.6 | AB33: 4 | AC33: =+Y33-AB33 -> -4 | AD33: =+ｼﾞｭｴﾙｽﾞ!W32/1000 -> 93.6 | AE33: 65.4 | AF33: =+AD33-AE33 -> 28.2 | AG33: 86 | AH33: =+AD33-AG33 -> 7.6 | AI33: =+Y33+AD33 -> 93.6 | AJ33: =+Z33+AE33 -> 69 | AK33: =+AI33-AJ33 -> 24.6 | AL33: =+AB33+AG33 -> 90 | AM33: =+AI33-AL33 -> 3.6 | AN33: =+ｶﾞｰﾃﾞﾝ!W32/1000 -> 108 | AO33: 54.18 | AP33: =+AN33-AO33 -> 53.82 | AQ33: 79 | AR33: =+AN33-AQ33 -> 29 | AS33: =+ﾋﾞｱｶﾞｰﾃﾞﾝ!W32/1000 -> 0 | AT33: 23.22 | AU33: =+AS33-AT33 -> -23.22 | AV33: 9 | AW33: =+AS33-AV33 -> -9 | AX33: =+AN33+AS33 -> 108 | AY33: =+AO33+AT33 -> 77.4 | AZ33: =+AX33-AY33 -> 30.6 | BA33: =+AQ33+AV33 -> 88 | BB33: =+AX33-BA33 -> 20 | BC33: 0 | BD33: 0 | BE33: =+BC33+BD33 -> 0 | BF33: =+料飲共通!W32/1000 -> 21.6 | BG33: 31.6 | BH33: =+BF33-BG33 -> -10 | BI33: 21 | BJ33: =+BF33-BI33 -> 0.6 | BK33: =+T33+AI33+AX33+BE33+BF33 -> 302.4 | BL33: =+U33+AJ33+AY33+BG33 -> 231.4 | BM33: =+BK33-BL33 -> 71 | BN33: =+W33+AL33+BA33+BI33 -> 271 | BO33: =+BK33-BN33 -> 31.4 | BP33: =+BK33-BE33 -> 302.4 | BQ33: =+BL33-Z33 -> 227.8 | BR33: =+BP33-BQ33 -> 74.6 | BS33: =+BN33-AB33 -> 267 | BT33: =+BP33-BS33 -> 35.4
C34: 被服費 | E34: =+ﾇｰﾍﾞﾙﾌﾟｰｽ!W33/1000 -> 330 | F34: 228.34 | G34: =+E34-F34 -> 101.66 | H34: 250 | I34: =+E34-H34 -> 80 | J34: =+ｶﾌｪﾙﾎﾟ!W33/1000 -> 0 | K34: 17.4 | L34: =+J34-K34 -> -17.4 | M34: 0 | N34: =+J34-M34 -> 0 | O34: =+ｶﾌｪｾﾚｽﾃ!W33/1000 -> 0 | P34: 0 | Q34: =+O34-P34 -> 0 | R34: 0 | S34: =+O34-R34 -> 0 | T34: =+E34+J34+O34 -> 330 | U34: =+F34+K34+P34 -> 245.74 | V34: =+T34-U34 -> 84.26 | W34: =+H34+M34+R34 -> 250 | X34: =+T34-W34 -> 80 | Y34: 0 | Z34: 0 | AA34: =+Y34-Z34 -> 0 | AB34: 100 | AC34: =+Y34-AB34 -> -100 | AD34: =+ｼﾞｭｴﾙｽﾞ!W33/1000 -> 330 | AE34: 241.78 | AF34: =+AD34-AE34 -> 88.22 | AG34: 250 | AH34: =+AD34-AG34 -> 80 | AI34: =+Y34+AD34 -> 330 | AJ34: =+Z34+AE34 -> 241.78 | AK34: =+AI34-AJ34 -> 88.22 | AL34: =+AB34+AG34 -> 350 | AM34: =+AI34-AL34 -> -20 | AN34: =+ｶﾞｰﾃﾞﾝ!W33/1000 -> 330 | AO34: 221.85 | AP34: =+AN34-AO34 -> 108.15 | AQ34: 250 | AR34: =+AN34-AQ34 -> 80 | AS34: =+ﾋﾞｱｶﾞｰﾃﾞﾝ!W33/1000 -> 0 | AT34: 95.078 | AU34: =+AS34-AT34 -> -95.078 | AV34: 0 | AW34: =+AS34-AV34 -> 0 | AX34: =+AN34+AS34 -> 330 | AY34: =+AO34+AT34 -> 316.928 | AZ34: =+AX34-AY34 -> 13.072 | BA34: =+AQ34+AV34 -> 250 | BB34: =+AX34-BA34 -> 80 | BC34: 0 | BD34: 0 | BE34: =+BC34+BD34 -> 0 | BF34: =+料飲共通!W33/1000 -> 40 | BG34: 393 | BH34: =+BF34-BG34 -> -353 | BI34: 0 | BJ34: =+BF34-BI34 -> 40 | BK34: =+T34+AI34+AX34+BE34+BF34 -> 1030 | BL34: =+U34+AJ34+AY34+BG34 -> 1197.448 | BM34: =+BK34-BL34 -> -167.448 | BN34: =+W34+AL34+BA34+BI34 -> 850 | BO34: =+BK34-BN34 -> 180 | BP34: =+BK34-BE34 -> 1030 | BQ34: =+BL34-Z34 -> 1197.448 | BR34: =+BP34-BQ34 -> -167.448 | BS34: =+BN34-AB34 -> 750 | BT34: =+BP34-BS34 -> 280
C35: 研修費 | E35: =+ﾇｰﾍﾞﾙﾌﾟｰｽ!W34/1000 -> 200 | F35: 207.274 | G35: =+E35-F35 -> -7.274 | H35: 0 | I35: =+E35-H35 -> 200 | J35: =+ｶﾌｪﾙﾎﾟ!W34/1000 -> 0 | K35: 0 | L35: =+J35-K35 -> 0 | M35: 0 | N35: =+J35-M35 -> 0 | O35: =+ｶﾌｪｾﾚｽﾃ!W34/1000 -> 0 | P35: 0 | Q35: =+O35-P35 -> 0 | R35: 0 | S35: =+O35-R35 -> 0 | T35: =+E35+J35+O35 -> 200 | U35: =+F35+K35+P35 -> 207.274 | V35: =+T35-U35 -> -7.274 | W35: =+H35+M35+R35 -> 0 | X35: =+T35-W35 -> 200 | Y35: 0 | Z35: 0 | AA35: =+Y35-Z35 -> 0 | AB35: 0 | AC35: =+Y35-AB35 -> 0 | AD35: =+ｼﾞｭｴﾙｽﾞ!W34/1000 -> 200 | AE35: 207.274 | AF35: =+AD35-AE35 -> -7.274 | AG35: 53 | AH35: =+AD35-AG35 -> 147 | AI35: =+Y35+AD35 -> 200 | AJ35: =+Z35+AE35 -> 207.274 | AK35: =+AI35-AJ35 -> -7.274 | AL35: =+AB35+AG35 -> 53 | AM35: =+AI35-AL35 -> 147 | AN35: =+ｶﾞｰﾃﾞﾝ!W34/1000 -> 200 | AO35: 143.819 | AP35: =+AN35-AO35 -> 56.181 | AQ35: 0 | AR35: =+AN35-AQ35 -> 200 | AS35: =+ﾋﾞｱｶﾞｰﾃﾞﾝ!W34/1000 -> 0 | AT35: 61.636 | AU35: =+AS35-AT35 -> -61.636 | AV35: 0 | AW35: =+AS35-AV35 -> 0 | AX35: =+AN35+AS35 -> 200 | AY35: =+AO35+AT35 -> 205.455 | AZ35: =+AX35-AY35 -> -5.455 | BA35: =+AQ35+AV35 -> 0 | BB35: =+AX35-BA35 -> 200 | BC35: 0 | BD35: 0 | BE35: =+BC35+BD35 -> 0 | BF35: =+料飲共通!W34/1000 -> 0 | BG35: 0 | BH35: =+BF35-BG35 -> 0 | BI35: 0 | BJ35: =+BF35-BI35 -> 0 | BK35: =+T35+AI35+AX35+BE35+BF35 -> 600 | BL35: =+U35+AJ35+AY35+BG35 -> 620.003 | BM35: =+BK35-BL35 -> -20.003 | BN35: =+W35+AL35+BA35+BI35 -> 53 | BO35: =+BK35-BN35 -> 547 | BP35: =+BK35-BE35 -> 600 | BQ35: =+BL35-Z35 -> 620.003 | BR35: =+BP35-BQ35 -> -20.003 | BS35: =+BN35-AB35 -> 53 | BT35: =+BP35-BS35 -> 547
B36: 通勤費 | E36: =+ﾇｰﾍﾞﾙﾌﾟｰｽ!W35/1000 -> 1174.872 | F36: 1058.246 | G36: =+E36-F36 -> 116.626 | H36: 964 | I36: =+E36-H36 -> 210.872 | J36: =+ｶﾌｪﾙﾎﾟ!W35/1000 -> 111.01 | K36: 78.226 | L36: =+J36-K36 -> 32.784 | M36: 66 | N36: =+J36-M36 -> 45.01 | O36: =+ｶﾌｪｾﾚｽﾃ!W35/1000 -> 111.01 | P36: 78.225 | Q36: =+O36-P36 -> 32.785 | R36: 66 | S36: =+O36-R36 -> 45.01 | T36: =+E36+J36+O36 -> 1396.892 | U36: =+F36+K36+P36 -> 1214.697 | V36: =+T36-U36 -> 182.195 | W36: =+H36+M36+R36 -> 1096 | X36: =+T36-W36 -> 300.892 | Y36: 0 | Z36: 237.359 | AA36: =+Y36-Z36 -> -237.359 | AB36: 272 | AC36: =+Y36-AB36 -> -272 | AD36: =+ｼﾞｭｴﾙｽﾞ!W35/1000 -> 1849.332 | AE36: 1599.852 | AF36: =+AD36-AE36 -> 249.48 | AG36: 1748 | AH36: =+AD36-AG36 -> 101.332 | AI36: =+Y36+AD36 -> 1849.332 | AJ36: =+Z36+AE36 -> 1837.211 | AK36: =+AI36-AJ36 -> 12.121 | AL36: =+AB36+AG36 -> 2020 | AM36: =+AI36-AL36 -> -170.668 | AN36: =+ｶﾞｰﾃﾞﾝ!Y35/1000 -> 1608.102 | AO36: 1812.726 | AP36: =+AN36-AO36 -> -204.624 | AQ36: 45 | AR36: =+AN36-AQ36 -> 1563.102 | AS36: =+ﾋﾞｱｶﾞｰﾃﾞﾝ!X35/1000 -> 689.186 | AT36: 776.882 | AU36: =+AS36-AT36 -> -87.696 | AV36: 115 | AW36: =+AS36-AV36 -> 574.186 | AX36: =+AN36+AS36 -> 2297.288 | AY36: =+AO36+AT36 -> 2589.608 | AZ36: =+AX36-AY36 -> -292.32 | BA36: =+AQ36+AV36 -> 160 | BB36: =+AX36-BA36 -> 2137.288 | BC36: 0 | BD36: 0 | BE36: =+BC36+BD36 -> 0 | BF36: =+料飲共通!W35/1000 -> 236.856 | BG36: 233.204 | BH36: =+BF36-BG36 -> 3.652 | BI36: 300 | BJ36: =+BF36-BI36 -> -63.144 | BK36: =+T36+AI36+AX36+BE36+BF36 -> 5780.368 | BL36: =+U36+AJ36+AY36+BG36 -> 5874.72 | BM36: =+BK36-BL36 -> -94.352 | BN36: =+W36+AL36+BA36+BI36 -> 3576 | BO36: =+BK36-BN36 -> 2204.368 | BP36: =+BK36-BE36 -> 5780.368 | BQ36: =+BL36-Z36 -> 5637.361 | BR36: =+BP36-BQ36 -> 143.007 | BS36: =+BN36-AB36 -> 3304 | BT36: =+BP36-BS36 -> 2476.368
B37: 引当金繰入額 | E37: =+ﾇｰﾍﾞﾙﾌﾟｰｽ!W36/1000 -> 0 | F37: 0 | G37: =+E37-F37 -> 0 | H37: 0 | I37: =+E37-H37 -> 0 | J37: =+ｶﾌｪﾙﾎﾟ!W36/1000 -> 0 | K37: 0 | L37: =+J37-K37 -> 0 | M37: 0 | N37: =+J37-M37 -> 0 | O37: =+ｶﾌｪｾﾚｽﾃ!W36/1000 -> 0 | P37: 0 | Q37: =+O37-P37 -> 0 | R37: 0 | S37: =+O37-R37 -> 0 | T37: =+E37+J37+O37 -> 0 | U37: =+F37+K37+P37 -> 0 | V37: =+T37-U37 -> 0 | W37: =+H37+M37+R37 -> 0 | X37: =+T37-W37 -> 0 | Y37: 0 | Z37: 0 | AA37: =+Y37-Z37 -> 0 | AB37: 0 | AC37: =+Y37-AB37 -> 0 | AD37: =+ｼﾞｭｴﾙｽﾞ!W36/1000 -> 0 | AE37: 0 | AF37: =+AD37-AE37 -> 0 | AG37: 0 | AH37: =+AD37-AG37 -> 0 | AI37: =+Y37+AD37 -> 0 | AJ37: =+Z37+AE37 -> 0 | AK37: =+AI37-AJ37 -> 0 | AL37: =+AB37+AG37 -> 0 | AM37: =+AI37-AL37 -> 0 | AN37: =+ｶﾞｰﾃﾞﾝ!Y36/1000 -> 0 | AO37: 0 | AP37: =+AN37-AO37 -> 0 | AQ37: 0 | AR37: =+AN37-AQ37 -> 0 | AS37: =+ﾋﾞｱｶﾞｰﾃﾞﾝ!X36/1000 -> 0 | AT37: 0 | AU37: =+AS37-AT37 -> 0 | AV37: 0 | AW37: =+AS37-AV37 -> 0 | AX37: =+AN37+AS37 -> 0 | AY37: =+AO37+AT37 -> 0 | AZ37: =+AX37-AY37 -> 0 | BA37: =+AQ37+AV37 -> 0 | BB37: =+AX37-BA37 -> 0 | BC37: 0 | BD37: 0 | BE37: =+BC37+BD37 -> 0 | BF37: =+料飲共通!W36/1000 -> 0 | BG37: 0 | BH37: =+BF37-BG37 -> 0 | BI37: 0 | BJ37: =+BF37-BI37 -> 0 | BK37: =+T37+AI37+AX37+BE37+BF37 -> 0 | BL37: =+U37+AJ37+AY37+BG37 -> 0 | BM37: =+BK37-BL37 -> 0 | BN37: =+W37+AL37+BA37+BI37 -> 0 | BO37: =+BK37-BN37 -> 0 | BP37: =+BK37-BE37 -> 0 | BQ37: =+BL37-Z37 -> 0 | BR37: =+BP37-BQ37 -> 0 | BS37: =+BN37-AB37 -> 0 | BT37: =+BP37-BS37 -> 0
A38: 物件費 | E38: =+ﾇｰﾍﾞﾙﾌﾟｰｽ!W37/1000 -> 24819.605 | F38: 25544.036 | G38: =+E38-F38 -> -724.431 | H38: 25494 | I38: =+E38-H38 -> -674.395 | J38: =+ｶﾌｪﾙﾎﾟ!W37/1000 -> 2843.405 | K38: 2894.314 | L38: =+J38-K38 -> -50.909 | M38: 2427 | N38: =+J38-M38 -> 416.405 | O38: =+ｶﾌｪｾﾚｽﾃ!W37/1000 -> 1603.983 | P38: 1689.214 | Q38: =+O38-P38 -> -85.231 | R38: 1603 | S38: =+O38-R38 -> 0.983 | T38: =+E38+J38+O38 -> 29266.993 | U38: =+F38+K38+P38 -> 30127.564 | V38: =+T38-U38 -> -860.571 | W38: =+H38+M38+R38 -> 29524 | X38: =+T38-W38 -> -257.007 | Y38: 0 | Z38: 1675.444 | AA38: =+Y38-Z38 -> -1675.444 | AB38: 4630 | AC38: =+Y38-AB38 -> -4630 | AD38: =+ｼﾞｭｴﾙｽﾞ!W37/1000 -> 22752.677 | AE38: 26704.175 | AF38: =+AD38-AE38 -> -3951.498 | AG38: 21572 | AH38: =+AD38-AG38 -> 1180.677 | AI38: =+Y38+AD38 -> 22752.677 | AJ38: =+Z38+AE38 -> 28379.619 | AK38: =+AI38-AJ38 -> -5626.942 | AL38: =+AB38+AG38 -> 26202 | AM38: =+AI38-AL38 -> -3449.323 | AN38: =+ｶﾞｰﾃﾞﾝ!W37/1000 -> 34114.208 | AO38: 33508.397 | AP38: =+AN38-AO38 -> 605.811 | AQ38: 40233 | AR38: =+AN38-AQ38 -> -6118.792 | AS38: =+ﾋﾞｱｶﾞｰﾃﾞﾝ!W37/1000 -> 64246.364 | AT38: 76309.517 | AU38: =+AS38-AT38 -> -12063.153 | AV38: 61193 | AW38: =+AS38-AV38 -> 3053.364 | AX38: =+AN38+AS38 -> 98360.572 | AY38: =+AO38+AT38 -> 109817.91 | AZ38: =+AX38-AY38 -> -11457.342 | BA38: =+AQ38+AV38 -> 101426 | BB38: =+AX38-BA38 -> -3065.428 | BC38: =+BC39+BC40+BC41+BC42+BC47+BC51+BC58+BC59+BC62+BC63+BC64+BC65+BC66+BC67+BC68+BC71+BC72+BC73+BC79+BC80+BC81+BC84+BC85 -> 19363.931 | BD38: =+BD39+BD40+BD41+BD42+BD47+BD51+BD58+BD59+BD62+BD63+BD64+BD65+BD66+BD67+BD68+BD71+BD72+BD73+BD79+BD80+BD81+BD84+BD85 -> 12688.171 | BE38: =+BC38+BD38 -> 32052.103 | BF38: =+料飲共通!W37/1000 -> 2443.85 | BG38: 6057.29 | BH38: =+BF38-BG38 -> -3613.44 | BI38: 254 | BJ38: =+BF38-BI38 -> 2189.85 | BK38: =+T38+AI38+AX38+BE38+BF38 -> 184876.19 | BL38: =+U38+AJ38+AY38+BG38 -> 174382.39 | BM38: =+BK38-BL38 -> 10493.808 | BN38: =+W38+AL38+BA38+BI38 -> 157406 | BO38: =+BK38-BN38 -> 27470.195 | BP38: =+BK38-BE38 -> 152824.09 | BQ38: =+BL38-Z38 -> 172706.94 | BR38: =+BP38-BQ38 -> -19882.851 | BS38: =+BN38-AB38 -> 152776 | BT38: =+BP38-BS38 -> 48.092
B39: 消耗品費 | E39: =+ﾇｰﾍﾞﾙﾌﾟｰｽ!W38/1000 -> 2520 | F39: 2546.953 | G39: =+E39-F39 -> -26.953 | H39: 2676 | I39: =+E39-H39 -> -156 | J39: =+ｶﾌｪﾙﾎﾟ!W38/1000 -> 560 | K39: 459.645 | L39: =+J39-K39 -> 100.355 | M39: 566 | N39: =+J39-M39 -> -6 | O39: =+ｶﾌｪｾﾚｽﾃ!W38/1000 -> 60 | P39: 201.582 | Q39: =+O39-P39 -> -141.582 | R39: 155 | S39: =+O39-R39 -> -95 | T39: =+E39+J39+O39 -> 3140 | U39: =+F39+K39+P39 -> 3208.18 | V39: =+T39-U39 -> -68.18 | W39: =+H39+M39+R39 -> 3397 | X39: =+T39-W39 -> -257 | Y39: 0 | Z39: 764.064 | AA39: =+Y39-Z39 -> -764.064 | AB39: 1387 | AC39: =+Y39-AB39 -> -1387 | AD39: =+ｼﾞｭｴﾙｽﾞ!W38/1000 -> 3813.5 | AE39: 5192.905 | AF39: =+AD39-AE39 -> -1379.405 | AG39: 4159 | AH39: =+AD39-AG39 -> -345.5 | AI39: =+Y39+AD39 -> 3813.5 | AJ39: =+Z39+AE39 -> 5956.969 | AK39: =+AI39-AJ39 -> -2143.469 | AL39: =+AB39+AG39 -> 5546 | AM39: =+AI39-AL39 -> -1732.5 | AN39: =+ｶﾞｰﾃﾞﾝ!W38/1000 -> 2380 | AO39: 3248.671 | AP39: =+AN39-AO39 -> -868.671 | AQ39: 3763 | AR39: =+AN39-AQ39 -> -1383 | AS39: =+ﾋﾞｱｶﾞｰﾃﾞﾝ!W38/1000 -> 4439 | AT39: 4335.033 | AU39: =+AS39-AT39 -> 103.967 | AV39: 3276 | AW39: =+AS39-AV39 -> 1163 | AX39: =+AN39+AS39 -> 6819 | AY39: =+AO39+AT39 -> 7583.704 | AZ39: =+AX39-AY39 -> -764.704 | BA39: =+AQ39+AV39 -> 7039 | BB39: =+AX39-BA39 -> -220 | BC39: =+赤れんが!X39/1000 -> 1840.8903 | BD39: =+赤れんが!Z39/1000 -> 1186.5044 | BE39: =+BC39+BD39 -> 3027.3947 | BF39: =+料飲共通!W38/1000 -> 0 | BG39: 43.38 | BH39: =+BF39-BG39 -> -43.38 | BI39: 0 | BJ39: =+BF39-BI39 -> 0 | BK39: =+T39+AI39+AX39+BE39+BF39 -> 16799.895 | BL39: =+U39+AJ39+AY39+BG39 -> 16792.233 | BM39: =+BK39-BL39 -> 7.6616995 | BN39: =+W39+AL39+BA39+BI39 -> 15982 | BO39: =+BK39-BN39 -> 817.8947 | BP39: =+BK39-BE39 -> 13772.5 | BQ39: =+BL39-Z39 -> 16028.169 | BR39: =+BP39-BQ39 -> -2255.669 | BS39: =+BN39-AB39 -> 14595 | BT39: =+BP39-BS39 -> -822.5
B40: 事務用品費 | E40: =+ﾇｰﾍﾞﾙﾌﾟｰｽ!W39/1000 -> 260 | F40: 277.748 | G40: =+E40-F40 -> -17.748 | H40: 240 | I40: =+E40-H40 -> 20 | J40: =+ｶﾌｪﾙﾎﾟ!W39/1000 -> 0 | K40: 19.966 | L40: =+J40-K40 -> -19.966 | M40: 0 | N40: =+J40-M40 -> 0 | O40: =+ｶﾌｪｾﾚｽﾃ!W39/1000 -> 0 | P40: 0 | Q40: =+O40-P40 -> 0 | R40: 0 | S40: =+O40-R40 -> 0 | T40: =+E40+J40+O40 -> 260 | U40: =+F40+K40+P40 -> 297.714 | V40: =+T40-U40 -> -37.714 | W40: =+H40+M40+R40 -> 240 | X40: =+T40-W40 -> 20 | Y40: 0 | Z40: 0 | AA40: =+Y40-Z40 -> 0 | AB40: 0 | AC40: =+Y40-AB40 -> 0 | AD40: =+ｼﾞｭｴﾙｽﾞ!W39/1000 -> 300 | AE40: 211.303 | AF40: =+AD40-AE40 -> 88.697 | AG40: 260 | AH40: =+AD40-AG40 -> 40 | AI40: =+Y40+AD40 -> 300 | AJ40: =+Z40+AE40 -> 211.303 | AK40: =+AI40-AJ40 -> 88.697 | AL40: =+AB40+AG40 -> 260 | AM40: =+AI40-AL40 -> 40 | AN40: =+ｶﾞｰﾃﾞﾝ!W39/1000 -> 300 | AO40: 361.703 | AP40: =+AN40-AO40 -> -61.703 | AQ40: 300 | AR40: =+AN40-AQ40 -> 0 | AS40: =+ﾋﾞｱｶﾞｰﾃﾞﾝ!W39/1000 -> 50 | AT40: 10.797 | AU40: =+AS40-AT40 -> 39.203 | AV40: 0 | AW40: =+AS40-AV40 -> 50 | AX40: =+AN40+AS40 -> 350 | AY40: =+AO40+AT40 -> 372.5 | AZ40: =+AX40-AY40 -> -22.5 | BA40: =+AQ40+AV40 -> 300 | BB40: =+AX40-BA40 -> 50 | BC40: =+赤れんが!X40/1000 -> 204.96244 | BD40: =+赤れんが!Z40/1000 -> 0 | BE40: =+BC40+BD40 -> 204.96244 | BF40: =+料飲共通!W39/1000 -> 0 | BG40: 0 | BH40: =+BF40-BG40 -> 0 | BI40: 0 | BJ40: =+BF40-BI40 -> 0 | BK40: =+T40+AI40+AX40+BE40+BF40 -> 1114.9624 | BL40: =+U40+AJ40+AY40+BG40 -> 881.517 | BM40: =+BK40-BL40 -> 233.44544 | BN40: =+W40+AL40+BA40+BI40 -> 800 | BO40: =+BK40-BN40 -> 314.96244 | BP40: =+BK40-BE40 -> 910 | BQ40: =+BL40-Z40 -> 881.517 | BR40: =+BP40-BQ40 -> 28.483 | BS40: =+BN40-AB40 -> 800 | BT40: =+BP40-BS40 -> 110
B41: 図書購入費 | E41: =+ﾇｰﾍﾞﾙﾌﾟｰｽ!W40/1000 -> 0 | F41: 0 | G41: =+E41-F41 -> 0 | H41: 0 | I41: =+E41-H41 -> 0 | J41: =+ｶﾌｪﾙﾎﾟ!W40/1000 -> 0 | K41: 0 | L41: =+J41-K41 -> 0 | M41: 0 | N41: =+J41-M41 -> 0 | O41: =+ｶﾌｪｾﾚｽﾃ!W40/1000 -> 0 | P41: 0 | Q41: =+O41-P41 -> 0 | R41: 0 | S41: =+O41-R41 -> 0 | T41: =+E41+J41+O41 -> 0 | U41: =+F41+K41+P41 -> 0 | V41: =+T41-U41 -> 0 | W41: =+H41+M41+R41 -> 0 | X41: =+T41-W41 -> 0 | Y41: 0 | Z41: 0 | AA41: =+Y41-Z41 -> 0 | AB41: 0 | AC41: =+Y41-AB41 -> 0 | AD41: =+ｼﾞｭｴﾙｽﾞ!W40/1000 -> 0 | AE41: 0 | AF41: =+AD41-AE41 -> 0 | AG41: 0 | AH41: =+AD41-AG41 -> 0 | AI41: =+Y41+AD41 -> 0 | AJ41: =+Z41+AE41 -> 0 | AK41: =+AI41-AJ41 -> 0 | AL41: =+AB41+AG41 -> 0 | AM41: =+AI41-AL41 -> 0 | AN41: =+ｶﾞｰﾃﾞﾝ!W40/1000 -> 0 | AO41: 0 | AP41: =+AN41-AO41 -> 0 | AQ41: 0 | AR41: =+AN41-AQ41 -> 0 | AS41: =+ﾋﾞｱｶﾞｰﾃﾞﾝ!W40/1000 -> 0 | AT41: 0 | AU41: =+AS41-AT41 -> 0 | AV41: 0 | AW41: =+AS41-AV41 -> 0 | AX41: =+AN41+AS41 -> 0 | AY41: =+AO41+AT41 -> 0 | AZ41: =+AX41-AY41 -> 0 | BA41: =+AQ41+AV41 -> 0 | BB41: =+AX41-BA41 -> 0 | BC41: 0 | BD41: 0 | BE41: =+BC41+BD41 -> 0 | BF41: =+料飲共通!W40/1000 -> 0 | BG41: 0 | BH41: =+BF41-BG41 -> 0 | BI41: 0 | BJ41: =+BF41-BI41 -> 0 | BK41: =+T41+AI41+AX41+BE41+BF41 -> 0 | BL41: =+U41+AJ41+AY41+BG41 -> 0 | BM41: =+BK41-BL41 -> 0 | BN41: =+W41+AL41+BA41+BI41 -> 0 | BO41: =+BK41-BN41 -> 0 | BP41: =+BK41-BE41 -> 0 | BQ41: =+BL41-Z41 -> 0 | BR41: =+BP41-BQ41 -> 0 | BS41: =+BN41-AB41 -> 0 | BT41: =+BP41-BS41 -> 0
B42: 賃借料 | E42: =+ﾇｰﾍﾞﾙﾌﾟｰｽ!W41/1000 -> 425.1 | F42: 433.729 | G42: =+E42-F42 -> -8.629 | H42: 387 | I42: =+E42-H42 -> 38.1 | J42: =+ｶﾌｪﾙﾎﾟ!W41/1000 -> 72.7 | K42: 48.99 | L42: =+J42-K42 -> 23.71 | M42: 41 | N42: =+J42-M42 -> 31.7 | O42: =+ｶﾌｪｾﾚｽﾃ!W41/1000 -> 1021.964 | P42: 1021.964 | Q42: =+O42-P42 -> 0 | R42: 1035 | S42: =+O42-R42 -> -13.036 | T42: =+E42+J42+O42 -> 1519.764 | U42: =+F42+K42+P42 -> 1504.683 | V42: =+T42-U42 -> 15.081 | W42: =+H42+M42+R42 -> 1463 | X42: =+T42-W42 -> 56.764 | Y42: 0 | Z42: 60 | AA42: =+Y42-Z42 -> -60 | AB42: 100 | AC42: =+Y42-AB42 -> -100 | AD42: =+ｼﾞｭｴﾙｽﾞ!W41/1000 -> 641.32 | AE42: 599.519 | AF42: =+AD42-AE42 -> 41.801 | AG42: 553 | AH42: =+AD42-AG42 -> 88.32 | AI42: =+Y42+AD42 -> 641.32 | AJ42: =+Z42+AE42 -> 659.519 | AK42: =+AI42-AJ42 -> -18.199 | AL42: =+AB42+AG42 -> 653 | AM42: =+AI42-AL42 -> -11.68 | AN42: =+ｶﾞｰﾃﾞﾝ!W41/1000 -> 12497.46 | AO42: 12237.548 | AP42: =+AN42-AO42 -> 259.912 | AQ42: 12260 | AR42: =+AN42-AQ42 -> 237.46 | AS42: =+ﾋﾞｱｶﾞｰﾃﾞﾝ!W41/1000 -> 14123.5 | AT42: 14123.5 | AU42: =+AS42-AT42 -> 0 | AV42: 13615 | AW42: =+AS42-AV42 -> 508.5 | AX42: =+AN42+AS42 -> 26620.96 | AY42: =+AO42+AT42 -> 26361.048 | AZ42: =+AX42-AY42 -> 259.912 | BA42: =+AQ42+AV42 -> 25875 | BB42: =+AX42-BA42 -> 745.96 | BC42: =SUM(BC43:BC46) -> 8999.714 | BD42: =SUM(BD43:BD46) -> 6634.7985 | BE42: =+BC42+BD42 -> 15634.512 | BF42: =+料飲共通!W41/1000 -> 0 | BG42: 12.623 | BH42: =+BF42-BG42 -> -12.623 | BI42: 0 | BJ42: =+BF42-BI42 -> 0 | BK42: =+T42+AI42+AX42+BE42+BF42 -> 44416.556 | BL42: =+U42+AJ42+AY42+BG42 -> 28537.873 | BM42: =+BK42-BL42 -> 15878.683 | BN42: =+W42+AL42+BA42+BI42 -> 27991 | BO42: =+BK42-BN42 -> 16425.556 | BP42: =+BK42-BE42 -> 28782.044 | BQ42: =+BL42-Z42 -> 28477.873 | BR42: =+BP42-BQ42 -> 304.171 | BS42: =+BN42-AB42 -> 27891 | BT42: =+BP42-BS42 -> 891.044
C43: 土地使用料 | E43: =+ﾇｰﾍﾞﾙﾌﾟｰｽ!W42/1000 -> 0 | F43: 0 | G43: =+E43-F43 -> 0 | H43: 0 | I43: =+E43-H43 -> 0 | J43: =+ｶﾌｪﾙﾎﾟ!W42/1000 -> 0 | K43: 0 | L43: =+J43-K43 -> 0 | M43: 0 | N43: =+J43-M43 -> 0 | O43: =+ｶﾌｪｾﾚｽﾃ!W42/1000 -> 0 | P43: 0 | Q43: =+O43-P43 -> 0 | R43: 0 | S43: =+O43-R43 -> 0 | T43: =+E43+J43+O43 -> 0 | U43: =+F43+K43+P43 -> 0 | V43: =+T43-U43 -> 0 | W43: =+H43+M43+R43 -> 0 | X43: =+T43-W43 -> 0 | Y43: 0 | Z43: 0 | AA43: =+Y43-Z43 -> 0 | AB43: 0 | AC43: =+Y43-AB43 -> 0 | AD43: =+ｼﾞｭｴﾙｽﾞ!W42/1000 -> 0 | AE43: 0 | AF43: =+AD43-AE43 -> 0 | AG43: 0 | AH43: =+AD43-AG43 -> 0 | AI43: =+Y43+AD43 -> 0 | AJ43: =+Z43+AE43 -> 0 | AK43: =+AI43-AJ43 -> 0 | AL43: =+AB43+AG43 -> 0 | AM43: =+AI43-AL43 -> 0 | AN43: =+ｶﾞｰﾃﾞﾝ!W42/1000 -> 0 | AO43: 0 | AP43: =+AN43-AO43 -> 0 | AQ43: 0 | AR43: =+AN43-AQ43 -> 0 | AS43: =+ﾋﾞｱｶﾞｰﾃﾞﾝ!W42/1000 -> 0 | AT43: 0 | AU43: =+AS43-AT43 -> 0 | AV43: 0 | AW43: =+AS43-AV43 -> 0 | AX43: =+AN43+AS43 -> 0 | AY43: =+AO43+AT43 -> 0 | AZ43: =+AX43-AY43 -> 0 | BA43: =+AQ43+AV43 -> 0 | BB43: =+AX43-BA43 -> 0 | BC43: 0 | BD43: 0 | BE43: =+BC43+BD43 -> 0 | BF43: =+料飲共通!W42/1000 -> 0 | BG43: 0 | BH43: =+BF43-BG43 -> 0 | BI43: 0 | BJ43: =+BF43-BI43 -> 0 | BK43: =+T43+AI43+AX43+BE43+BF43 -> 0 | BL43: =+U43+AJ43+AY43+BG43 -> 0 | BM43: =+BK43-BL43 -> 0 | BN43: =+W43+AL43+BA43+BI43 -> 0 | BO43: =+BK43-BN43 -> 0 | BP43: =+BK43-BE43 -> 0 | BQ43: =+BL43-Z43 -> 0 | BR43: =+BP43-BQ43 -> 0 | BS43: =+BN43-AB43 -> 0 | BT43: =+BP43-BS43 -> 0
C44: 建物使用料 | E44: =+ﾇｰﾍﾞﾙﾌﾟｰｽ!W43/1000 -> 0 | F44: 0 | G44: =+E44-F44 -> 0 | H44: 0 | I44: =+E44-H44 -> 0 | J44: =+ｶﾌｪﾙﾎﾟ!W43/1000 -> 0 | K44: 0 | L44: =+J44-K44 -> 0 | M44: 0 | N44: =+J44-M44 -> 0 | O44: =+ｶﾌｪｾﾚｽﾃ!W43/1000 -> 1021.964 | P44: 1021.964 | Q44: =+O44-P44 -> 0 | R44: 255 | S44: =+O44-R44 -> 766.964 | T44: =+E44+J44+O44 -> 1021.964 | U44: =+F44+K44+P44 -> 1021.964 | V44: =+T44-U44 -> 0 | W44: =+H44+M44+R44 -> 255 | X44: =+T44-W44 -> 766.964 | Y44: 0 | Z44: 0 | AA44: =+Y44-Z44 -> 0 | AB44: 0 | AC44: =+Y44-AB44 -> 0 | AD44: =+ｼﾞｭｴﾙｽﾞ!W43/1000 -> 0 | AE44: 0 | AF44: =+AD44-AE44 -> 0 | AG44: 0 | AH44: =+AD44-AG44 -> 0 | AI44: =+Y44+AD44 -> 0 | AJ44: =+Z44+AE44 -> 0 | AK44: =+AI44-AJ44 -> 0 | AL44: =+AB44+AG44 -> 0 | AM44: =+AI44-AL44 -> 0 | AN44: =+ｶﾞｰﾃﾞﾝ!W43/1000 -> 11558.46 | AO44: 11558.46 | AP44: =+AN44-AO44 -> 0 | AQ44: 11558 | AR44: =+AN44-AQ44 -> 0.46 | AS44: =+ﾋﾞｱｶﾞｰﾃﾞﾝ!W43/1000 -> 0 | AT44: 0 | AU44: =+AS44-AT44 -> 0 | AV44: 13515 | AW44: =+AS44-AV44 -> -13515 | AX44: =+AN44+AS44 -> 11558.46 | AY44: =+AO44+AT44 -> 11558.46 | AZ44: =+AX44-AY44 -> 0 | BA44: =+AQ44+AV44 -> 25073 | BB44: =+AX44-BA44 -> -13514.54 | BC44: =+赤れんが!X44/1000 -> 7913.3943 | BD44: =+赤れんが!Z44/1000 -> 6539.312 | BE44: =+BC44+BD44 -> 14452.706 | BF44: =+料飲共通!W43/1000 -> 0 | BG44: 0 | BH44: =+BF44-BG44 -> 0 | BI44: 0 | BJ44: =+BF44-BI44 -> 0 | BK44: =+T44+AI44+AX44+BE44+BF44 -> 27033.13 | BL44: =+U44+AJ44+AY44+BG44 -> 12580.424 | BM44: =+BK44-BL44 -> 14452.706 | BN44: =+W44+AL44+BA44+BI44 -> 25328 | BO44: =+BK44-BN44 -> 1705.1303 | BP44: =+BK44-BE44 -> 12580.424 | BQ44: =+BL44-Z44 -> 12580.424 | BR44: =+BP44-BQ44 -> 0 | BS44: =+BN44-AB44 -> 25328 | BT44: =+BP44-BS44 -> -12747.576
C45: 施設使用料 | E45: =+ﾇｰﾍﾞﾙﾌﾟｰｽ!W44/1000 -> 0 | F45: 0 | G45: =+E45-F45 -> 0 | H45: 0 | I45: =+E45-H45 -> 0 | J45: =+ｶﾌｪﾙﾎﾟ!W44/1000 -> 0 | K45: 0 | L45: =+J45-K45 -> 0 | M45: 0 | N45: =+J45-M45 -> 0 | O45: =+ｶﾌｪｾﾚｽﾃ!W44/1000 -> 0 | P45: 0 | Q45: =+O45-P45 -> 0 | R45: 780 | S45: =+O45-R45 -> -780 | T45: =+E45+J45+O45 -> 0 | U45: =+F45+K45+P45 -> 0 | V45: =+T45-U45 -> 0 | W45: =+H45+M45+R45 -> 780 | X45: =+T45-W45 -> -780 | Y45: 0 | Z45: 0 | AA45: =+Y45-Z45 -> 0 | AB45: 0 | AC45: =+Y45-AB45 -> 0 | AD45: =+ｼﾞｭｴﾙｽﾞ!W44/1000 -> 0 | AE45: 0 | AF45: =+AD45-AE45 -> 0 | AG45: 0 | AH45: =+AD45-AG45 -> 0 | AI45: =+Y45+AD45 -> 0 | AJ45: =+Z45+AE45 -> 0 | AK45: =+AI45-AJ45 -> 0 | AL45: =+AB45+AG45 -> 0 | AM45: =+AI45-AL45 -> 0 | AN45: =+ｶﾞｰﾃﾞﾝ!W44/1000 -> 0 | AO45: 0 | AP45: =+AN45-AO45 -> 0 | AQ45: 0 | AR45: =+AN45-AQ45 -> 0 | AS45: =+ﾋﾞｱｶﾞｰﾃﾞﾝ!W44/1000 -> 14050 | AT45: 14050 | AU45: =+AS45-AT45 -> 0 | AV45: 0 | AW45: =+AS45-AV45 -> 14050 | AX45: =+AN45+AS45 -> 14050 | AY45: =+AO45+AT45 -> 14050 | AZ45: =+AX45-AY45 -> 0 | BA45: =+AQ45+AV45 -> 0 | BB45: =+AX45-BA45 -> 14050 | BC45: =+赤れんが!X45/1000 -> 701.508 | BD45: =+赤れんが!Z45/1000 -> 0 | BE45: =+BC45+BD45 -> 701.508 | BF45: =+料飲共通!W44/1000 -> 0 | BG45: 12.623 | BH45: =+BF45-BG45 -> -12.623 | BI45: 0 | BJ45: =+BF45-BI45 -> 0 | BK45: =+T45+AI45+AX45+BE45+BF45 -> 14751.508 | BL45: =+U45+AJ45+AY45+BG45 -> 14062.623 | BM45: =+BK45-BL45 -> 688.885 | BN45: =+W45+AL45+BA45+BI45 -> 780 | BO45: =+BK45-BN45 -> 13971.508 | BP45: =+BK45-BE45 -> 14050 | BQ45: =+BL45-Z45 -> 14062.623 | BR45: =+BP45-BQ45 -> -12.623 | BS45: =+BN45-AB45 -> 780 | BT45: =+BP45-BS45 -> 13270
C46: リース料 | E46: =+ﾇｰﾍﾞﾙﾌﾟｰｽ!W45/1000 -> 425.1 | F46: 433.729 | G46: =+E46-F46 -> -8.629 | H46: 387 | I46: =+E46-H46 -> 38.1 | J46: =+ｶﾌｪﾙﾎﾟ!W45/1000 -> 72.7 | K46: 48.99 | L46: =+J46-K46 -> 23.71 | M46: 41 | N46: =+J46-M46 -> 31.7 | O46: =+ｶﾌｪｾﾚｽﾃ!W45/1000 -> 0 | P46: 0 | Q46: =+O46-P46 -> 0 | R46: 0 | S46: =+O46-R46 -> 0 | T46: =+E46+J46+O46 -> 497.8 | U46: =+F46+K46+P46 -> 482.719 | V46: =+T46-U46 -> 15.081 | W46: =+H46+M46+R46 -> 428 | X46: =+T46-W46 -> 69.8 | Y46: 0 | Z46: 60 | AA46: =+Y46-Z46 -> -60 | AB46: 100 | AC46: =+Y46-AB46 -> -100 | AD46: =+ｼﾞｭｴﾙｽﾞ!W45/1000 -> 641.32 | AE46: 599.519 | AF46: =+AD46-AE46 -> 41.801 | AG46: 553 | AH46: =+AD46-AG46 -> 88.32 | AI46: =+Y46+AD46 -> 641.32 | AJ46: =+Z46+AE46 -> 659.519 | AK46: =+AI46-AJ46 -> -18.199 | AL46: =+AB46+AG46 -> 653 | AM46: =+AI46-AL46 -> -11.68 | AN46: =+ｶﾞｰﾃﾞﾝ!W45/1000 -> 939 | AO46: 679.088 | AP46: =+AN46-AO46 -> 259.912 | AQ46: 702 | AR46: =+AN46-AQ46 -> 237 | AS46: =+ﾋﾞｱｶﾞｰﾃﾞﾝ!W45/1000 -> 73.5 | AT46: 73.5 | AU46: =+AS46-AT46 -> 0 | AV46: 100 | AW46: =+AS46-AV46 -> -26.5 | AX46: =+AN46+AS46 -> 1012.5 | AY46: =+AO46+AT46 -> 752.588 | AZ46: =+AX46-AY46 -> 259.912 | BA46: =+AQ46+AV46 -> 802 | BB46: =+AX46-BA46 -> 210.5 | BC46: =+赤れんが!X46/1000 -> 384.81166 | BD46: =+赤れんが!Z46/1000 -> 95.48653 | BE46: =+BC46+BD46 -> 480.29819 | BF46: =+料飲共通!W45/1000 -> 0 | BG46: 0 | BH46: =+BF46-BG46 -> 0 | BI46: 0 | BJ46: =+BF46-BI46 -> 0 | BK46: =+T46+AI46+AX46+BE46+BF46 -> 2631.9182 | BL46: =+U46+AJ46+AY46+BG46 -> 1894.826 | BM46: =+BK46-BL46 -> 737.09219 | BN46: =+W46+AL46+BA46+BI46 -> 1883 | BO46: =+BK46-BN46 -> 748.91819 | BP46: =+BK46-BE46 -> 2151.62 | BQ46: =+BL46-Z46 -> 1834.826 | BR46: =+BP46-BQ46 -> 316.794 | BS46: =+BN46-AB46 -> 1783 | BT46: =+BP46-BS46 -> 368.62
B47: 保険料 | E47: =+ﾇｰﾍﾞﾙﾌﾟｰｽ!W46/1000 -> 38.21 | F47: 38.21 | G47: =+E47-F47 -> 0 | H47: 40 | I47: =+E47-H47 -> -1.79 | J47: =+ｶﾌｪﾙﾎﾟ!W46/1000 -> 4.21 | K47: 4.21 | L47: =+J47-K47 -> 0 | M47: 0 | N47: =+J47-M47 -> 4.21 | O47: =+ｶﾌｪｾﾚｽﾃ!W46/1000 -> 4.21 | P47: 4.21 | Q47: =+O47-P47 -> 0 | R47: 0 | S47: =+O47-R47 -> 4.21 | T47: =+E47+J47+O47 -> 46.63 | U47: =+F47+K47+P47 -> 46.63 | V47: =+T47-U47 -> 0 | W47: =+H47+M47+R47 -> 40 | X47: =+T47-W47 -> 6.63 | Y47: 0 | Z47: 18.21 | AA47: =+Y47-Z47 -> -18.21 | AB47: 22 | AC47: =+Y47-AB47 -> -22 | AD47: =+ｼﾞｭｴﾙｽﾞ!W46/1000 -> 7.718 | AE47: 7.718 | AF47: =+AD47-AE47 -> 0 | AG47: 13 | AH47: =+AD47-AG47 -> -5.282 | AI47: =+Y47+AD47 -> 7.718 | AJ47: =+Z47+AE47 -> 25.928 | AK47: =+AI47-AJ47 -> -18.21 | AL47: =+AB47+AG47 -> 35 | AM47: =+AI47-AL47 -> -27.282 | AN47: =+ｶﾞｰﾃﾞﾝ!W46/1000 -> 4.21 | AO47: 4.21 | AP47: =+AN47-AO47 -> 0 | AQ47: 47 | AR47: =+AN47-AQ47 -> -42.79 | AS47: =+ﾋﾞｱｶﾞｰﾃﾞﾝ!W46/1000 -> 0 | AT47: 4.21 | AU47: =+AS47-AT47 -> -4.21 | AV47: 0 | AW47: =+AS47-AV47 -> 0 | AX47: =+AN47+AS47 -> 4.21 | AY47: =+AO47+AT47 -> 8.42 | AZ47: =+AX47-AY47 -> -4.21 | BA47: =+AQ47+AV47 -> 47 | BB47: =+AX47-BA47 -> -42.79 | BC47: =+赤れんが!X47/1000 -> 16.712 | BD47: =+赤れんが!Z47/1000 -> 16.712 | BE47: =+BC47+BD47 -> 33.424 | BF47: =+料飲共通!W46/1000 -> 0 | BG47: 0 | BH47: =+BF47-BG47 -> 0 | BI47: 0 | BJ47: =+BF47-BI47 -> 0 | BK47: =+T47+AI47+AX47+BE47+BF47 -> 91.982 | BL47: =+U47+AJ47+AY47+BG47 -> 80.978 | BM47: =+BK47-BL47 -> 11.004 | BN47: =+W47+AL47+BA47+BI47 -> 122 | BO47: =+BK47-BN47 -> -30.018 | BP47: =+BK47-BE47 -> 58.558 | BQ47: =+BL47-Z47 -> 62.768 | BR47: =+BP47-BQ47 -> -4.21 | BS47: =+BN47-AB47 -> 100 | BT47: =+BP47-BS47 -> -41.442
C48: 火災保険料 | E48: =+ﾇｰﾍﾞﾙﾌﾟｰｽ!W47/1000 -> 0 | F48: 0 | G48: =+E48-F48 -> 0 | H48: 0 | I48: =+E48-H48 -> 0 | J48: =+ｶﾌｪﾙﾎﾟ!W47/1000 -> 0 | K48: 0 | L48: =+J48-K48 -> 0 | M48: 0 | N48: =+J48-M48 -> 0 | O48: =+ｶﾌｪｾﾚｽﾃ!W47/1000 -> 0 | P48: 0 | Q48: =+O48-P48 -> 0 | R48: 0 | S48: =+O48-R48 -> 0 | T48: =+E48+J48+O48 -> 0 | U48: =+F48+K48+P48 -> 0 | V48: =+T48-U48 -> 0 | W48: =+H48+M48+R48 -> 0 | X48: =+T48-W48 -> 0 | Y48: 0 | Z48: 0 | AA48: =+Y48-Z48 -> 0 | AB48: 0 | AC48: =+Y48-AB48 -> 0 | AD48: =+ｼﾞｭｴﾙｽﾞ!W47/1000 -> 3.508 | AE48: 3.508 | AF48: =+AD48-AE48 -> 0 | AG48: 3 | AH48: =+AD48-AG48 -> 0.508 | AI48: =+Y48+AD48 -> 3.508 | AJ48: =+Z48+AE48 -> 3.508 | AK48: =+AI48-AJ48 -> 0 | AL48: =+AB48+AG48 -> 3 | AM48: =+AI48-AL48 -> 0.508 | AN48: =+ｶﾞｰﾃﾞﾝ!W47/1000 -> 0 | AO48: 0 | AP48: =+AN48-AO48 -> 0 | AQ48: 37 | AR48: =+AN48-AQ48 -> -37 | AS48: =+ﾋﾞｱｶﾞｰﾃﾞﾝ!W47/1000 -> 0 | AT48: 0 | AU48: =+AS48-AT48 -> 0 | AV48: 0 | AW48: =+AS48-AV48 -> 0 | AX48: =+AN48+AS48 -> 0 | AY48: =+AO48+AT48 -> 0 | AZ48: =+AX48-AY48 -> 0 | BA48: =+AQ48+AV48 -> 37 | BB48: =+AX48-BA48 -> -37 | BC48: =+料飲共通!H47/1000 -> 0 | BD48: =+料飲共通!I47/1000 -> 0 | BE48: =+BC48+BD48 -> 0 | BF48: =+料飲共通!W47/1000 -> 0 | BG48: 0 | BH48: =+BF48-BG48 -> 0 | BI48: 0 | BJ48: =+BF48-BI48 -> 0 | BK48: =+T48+AI48+AX48+BE48+BF48 -> 3.508 | BL48: =+U48+AJ48+AY48+BG48 -> 3.508 | BM48: =+BK48-BL48 -> 0 | BN48: =+W48+AL48+BA48+BI48 -> 40 | BO48: =+BK48-BN48 -> -36.492 | BP48: =+BK48-BE48 -> 3.508 | BQ48: =+BL48-Z48 -> 3.508 | BR48: =+BP48-BQ48 -> 0 | BS48: =+BN48-AB48 -> 40 | BT48: =+BP48-BS48 -> -36.492
C49: 賠償保険料 | E49: =+ﾇｰﾍﾞﾙﾌﾟｰｽ!W48/1000 -> 34 | F49: 34 | G49: =+E49-F49 -> 0 | H49: 34 | I49: =+E49-H49 -> 0 | J49: =+ｶﾌｪﾙﾎﾟ!W48/1000 -> 4.21 | K49: 0 | L49: =+J49-K49 -> 4.21 | M49: 0 | N49: =+J49-M49 -> 4.21 | O49: =+ｶﾌｪｾﾚｽﾃ!W48/1000 -> 0 | P49: 0 | Q49: =+O49-P49 -> 0 | R49: 0 | S49: =+O49-R49 -> 0 | T49: =+E49+J49+O49 -> 38.21 | U49: =+F49+K49+P49 -> 34 | V49: =+T49-U49 -> 4.21 | W49: =+H49+M49+R49 -> 34 | X49: =+T49-W49 -> 4.21 | Y49: 0 | Z49: 14 | AA49: =+Y49-Z49 -> -14 | AB49: 22 | AC49: =+Y49-AB49 -> -22 | AD49: =+ｼﾞｭｴﾙｽﾞ!W48/1000 -> 0 | AE49: 0 | AF49: =+AD49-AE49 -> 0 | AG49: 0 | AH49: =+AD49-AG49 -> 0 | AI49: =+Y49+AD49 -> 0 | AJ49: =+Z49+AE49 -> 14 | AK49: =+AI49-AJ49 -> -14 | AL49: =+AB49+AG49 -> 22 | AM49: =+AI49-AL49 -> -22 | AN49: =+ｶﾞｰﾃﾞﾝ!W48/1000 -> 0 | AO49: 0 | AP49: =+AN49-AO49 -> 0 | AQ49: 0 | AR49: =+AN49-AQ49 -> 0 | AS49: =+ﾋﾞｱｶﾞｰﾃﾞﾝ!W48/1000 -> 0 | AT49: 0 | AU49: =+AS49-AT49 -> 0 | AV49: 0 | AW49: =+AS49-AV49 -> 0 | AX49: =+AN49+AS49 -> 0 | AY49: =+AO49+AT49 -> 0 | AZ49: =+AX49-AY49 -> 0 | BA49: =+AQ49+AV49 -> 0 | BB49: =+AX49-BA49 -> 0 | BC49: =+料飲共通!H48/1000 -> 0 | BD49: =+料飲共通!I48/1000 -> 0 | BE49: =+BC49+BD49 -> 0 | BF49: =+料飲共通!W48/1000 -> 0 | BG49: 0 | BH49: =+BF49-BG49 -> 0 | BI49: 0 | BJ49: =+BF49-BI49 -> 0 | BK49: =+T49+AI49+AX49+BE49+BF49 -> 38.21 | BL49: =+U49+AJ49+AY49+BG49 -> 48 | BM49: =+BK49-BL49 -> -9.79 | BN49: =+W49+AL49+BA49+BI49 -> 56 | BO49: =+BK49-BN49 -> -17.79 | BP49: =+BK49-BE49 -> 38.21 | BQ49: =+BL49-Z49 -> 34 | BR49: =+BP49-BQ49 -> 4.21 | BS49: =+BN49-AB49 -> 34 | BT49: =+BP49-BS49 -> 4.21
C50: 動産保険料 | E50: =+ﾇｰﾍﾞﾙﾌﾟｰｽ!W49/1000 -> 4.21 | F50: 4.21 | G50: =+E50-F50 -> 0 | H50: 6 | I50: =+E50-H50 -> -1.79 | J50: =+ｶﾌｪﾙﾎﾟ!W49/1000 -> 0 | K50: 4.21 | L50: =+J50-K50 -> -4.21 | M50: 0 | N50: =+J50-M50 -> 0 | O50: =+ｶﾌｪｾﾚｽﾃ!W49/1000 -> 4.21 | P50: 4.21 | Q50: =+O50-P50 -> 0 | R50: 0 | S50: =+O50-R50 -> 4.21 | T50: =+E50+J50+O50 -> 8.42 | U50: =+F50+K50+P50 -> 12.63 | V50: =+T50-U50 -> -4.21 | W50: =+H50+M50+R50 -> 6 | X50: =+T50-W50 -> 2.42 | Y50: 0 | Z50: 4.21 | AA50: =+Y50-Z50 -> -4.21 | AB50: 0 | AC50: =+Y50-AB50 -> 0 | AD50: =+ｼﾞｭｴﾙｽﾞ!W49/1000 -> 4.21 | AE50: 4.21 | AF50: =+AD50-AE50 -> 0 | AG50: 10 | AH50: =+AD50-AG50 -> -5.79 | AI50: =+Y50+AD50 -> 4.21 | AJ50: =+Z50+AE50 -> 8.42 | AK50: =+AI50-AJ50 -> -4.21 | AL50: =+AB50+AG50 -> 10 | AM50: =+AI50-AL50 -> -5.79 | AN50: =+ｶﾞｰﾃﾞﾝ!W49/1000 -> 4.21 | AO50: 4.21 | AP50: =+AN50-AO50 -> 0 | AQ50: 10 | AR50: =+AN50-AQ50 -> -5.79 | AS50: =+ﾋﾞｱｶﾞｰﾃﾞﾝ!W49/1000 -> 0 | AT50: 4.21 | AU50: =+AS50-AT50 -> -4.21 | AV50: 0 | AW50: =+AS50-AV50 -> 0 | AX50: =+AN50+AS50 -> 4.21 | AY50: =+AO50+AT50 -> 8.42 | AZ50: =+AX50-AY50 -> -4.21 | BA50: =+AQ50+AV50 -> 10 | BB50: =+AX50-BA50 -> -5.79 | BC50: =+料飲共通!H49/1000 -> 0 | BD50: =+料飲共通!I49/1000 -> 0 | BE50: =+BC50+BD50 -> 0 | BF50: =+料飲共通!W49/1000 -> 0 | BG50: 0 | BH50: =+BF50-BG50 -> 0 | BI50: 0 | BJ50: =+BF50-BI50 -> 0 | BK50: =+T50+AI50+AX50+BE50+BF50 -> 16.84 | BL50: =+U50+AJ50+AY50+BG50 -> 29.47 | BM50: =+BK50-BL50 -> -12.63 | BN50: =+W50+AL50+BA50+BI50 -> 26 | BO50: =+BK50-BN50 -> -9.16 | BP50: =+BK50-BE50 -> 16.84 | BQ50: =+BL50-Z50 -> 25.26 | BR50: =+BP50-BQ50 -> -8.42 | BS50: =+BN50-AB50 -> 26 | BT50: =+BP50-BS50 -> -9.16
B51: 修繕費 | E51: =+ﾇｰﾍﾞﾙﾌﾟｰｽ!W50/1000 -> 0 | F51: 450 | G51: =+E51-F51 -> -450 | H51: 900 | I51: =+E51-H51 -> -900 | J51: =+ｶﾌｪﾙﾎﾟ!W50/1000 -> 0 | K51: 0 | L51: =+J51-K51 -> 0 | M51: 97 | N51: =+J51-M51 -> -97 | O51: =+ｶﾌｪｾﾚｽﾃ!W50/1000 -> 0 | P51: 0 | Q51: =+O51-P51 -> 0 | R51: 0 | S51: =+O51-R51 -> 0 | T51: =+E51+J51+O51 -> 0 | U51: =+F51+K51+P51 -> 450 | V51: =+T51-U51 -> -450 | W51: =+H51+M51+R51 -> 997 | X51: =+T51-W51 -> -997 | Y51: 0 | Z51: 0 | AA51: =+Y51-Z51 -> 0 | AB51: 540 | AC51: =+Y51-AB51 -> -540 | AD51: =+ｼﾞｭｴﾙｽﾞ!W50/1000 -> 0 | AE51: 848.03 | AF51: =+AD51-AE51 -> -848.03 | AG51: 600 | AH51: =+AD51-AG51 -> -600 | AI51: =+Y51+AD51 -> 0 | AJ51: =+Z51+AE51 -> 848.03 | AK51: =+AI51-AJ51 -> -848.03 | AL51: =+AB51+AG51 -> 1140 | AM51: =+AI51-AL51 -> -1140 | AN51: =+ｶﾞｰﾃﾞﾝ!W50/1000 -> 0 | AO51: 437.25 | AP51: =+AN51-AO51 -> -437.25 | AQ51: 960 | AR51: =+AN51-AQ51 -> -960 | AS51: =+ﾋﾞｱｶﾞｰﾃﾞﾝ!W50/1000 -> 150 | AT51: 28 | AU51: =+AS51-AT51 -> 122 | AV51: 50 | AW51: =+AS51-AV51 -> 100 | AX51: =+AN51+AS51 -> 150 | AY51: =+AO51+AT51 -> 465.25 | AZ51: =+AX51-AY51 -> -315.25 | BA51: =+AQ51+AV51 -> 1010 | BB51: =+AX51-BA51 -> -860 | BC51: =+赤れんが!X51/1000 -> 0 | BD51: =+赤れんが!Z51/1000 -> 0 | BE51: =+BC51+BD51 -> 0 | BF51: =+料飲共通!W50/1000 -> 0 | BG51: 0 | BH51: =+BF51-BG51 -> 0 | BI51: 0 | BJ51: =+BF51-BI51 -> 0 | BK51: =+T51+AI51+AX51+BE51+BF51 -> 150 | BL51: =+U51+AJ51+AY51+BG51 -> 1763.28 | BM51: =+BK51-BL51 -> -1613.28 | BN51: =+W51+AL51+BA51+BI51 -> 3147 | BO51: =+BK51-BN51 -> -2997 | BP51: =+BK51-BE51 -> 150 | BQ51: =+BL51-Z51 -> 1763.28 | BR51: =+BP51-BQ51 -> -1613.28 | BS51: =+BN51-AB51 -> 2607 | BT51: =+BP51-BS51 -> -2457
C52: 建物 | E52: =+ﾇｰﾍﾞﾙﾌﾟｰｽ!W51/1000 -> 0 | F52: 0 | G52: =+E52-F52 -> 0 | H52: 0 | I52: =+E52-H52 -> 0 | J52: =+ｶﾌｪﾙﾎﾟ!W51/1000 -> 0 | K52: 0 | L52: =+J52-K52 -> 0 | M52: 0 | N52: =+J52-M52 -> 0 | O52: =+ｶﾌｪｾﾚｽﾃ!W51/1000 -> 0 | P52: 0 | Q52: =+O52-P52 -> 0 | R52: 0 | S52: =+O52-R52 -> 0 | T52: =+E52+J52+O52 -> 0 | U52: =+F52+K52+P52 -> 0 | V52: =+T52-U52 -> 0 | W52: =+H52+M52+R52 -> 0 | X52: =+T52-W52 -> 0 | Y52: 0 | Z52: 0 | AA52: =+Y52-Z52 -> 0 | AB52: 0 | AC52: =+Y52-AB52 -> 0 | AD52: =+ｼﾞｭｴﾙｽﾞ!W51/1000 -> 0 | AE52: 0 | AF52: =+AD52-AE52 -> 0 | AG52: 0 | AH52: =+AD52-AG52 -> 0 | AI52: =+Y52+AD52 -> 0 | AJ52: =+Z52+AE52 -> 0 | AK52: =+AI52-AJ52 -> 0 | AL52: =+AB52+AG52 -> 0 | AM52: =+AI52-AL52 -> 0 | AN52: =+ｶﾞｰﾃﾞﾝ!W51/1000 -> 0 | AO52: 0 | AP52: =+AN52-AO52 -> 0 | AQ52: 0 | AR52: =+AN52-AQ52 -> 0 | AS52: =+ﾋﾞｱｶﾞｰﾃﾞﾝ!W51/1000 -> 0 | AT52: 0 | AU52: =+AS52-AT52 -> 0 | AV52: 0 | AW52: =+AS52-AV52 -> 0 | AX52: =+AN52+AS52 -> 0 | AY52: =+AO52+AT52 -> 0 | AZ52: =+AX52-AY52 -> 0 | BA52: =+AQ52+AV52 -> 0 | BB52: =+AX52-BA52 -> 0 | BC52: =+料飲共通!H51/1000 -> 0 | BD52: =+料飲共通!I51/1000 -> 0 | BE52: =+BC52+BD52 -> 0 | BF52: =+料飲共通!W51/1000 -> 0 | BG52: 0 | BH52: =+BF52-BG52 -> 0 | BI52: 0 | BJ52: =+BF52-BI52 -> 0 | BK52: =+T52+AI52+AX52+BE52+BF52 -> 0 | BL52: =+U52+AJ52+AY52+BG52 -> 0 | BM52: =+BK52-BL52 -> 0 | BN52: =+W52+AL52+BA52+BI52 -> 0 | BO52: =+BK52-BN52 -> 0 | BP52: =+BK52-BE52 -> 0 | BQ52: =+BL52-Z52 -> 0 | BR52: =+BP52-BQ52 -> 0 | BS52: =+BN52-AB52 -> 0 | BT52: =+BP52-BS52 -> 0
C53: 建物付属設備 | E53: =+ﾇｰﾍﾞﾙﾌﾟｰｽ!W52/1000 -> 0 | F53: 0 | G53: =+E53-F53 -> 0 | H53: 0 | I53: =+E53-H53 -> 0 | J53: =+ｶﾌｪﾙﾎﾟ!W52/1000 -> 0 | K53: 0 | L53: =+J53-K53 -> 0 | M53: 0 | N53: =+J53-M53 -> 0 | O53: =+ｶﾌｪｾﾚｽﾃ!W52/1000 -> 0 | P53: 0 | Q53: =+O53-P53 -> 0 | R53: 0 | S53: =+O53-R53 -> 0 | T53: =+E53+J53+O53 -> 0 | U53: =+F53+K53+P53 -> 0 | V53: =+T53-U53 -> 0 | W53: =+H53+M53+R53 -> 0 | X53: =+T53-W53 -> 0 | Y53: 0 | Z53: 0 | AA53: =+Y53-Z53 -> 0 | AB53: 0 | AC53: =+Y53-AB53 -> 0 | AD53: =+ｼﾞｭｴﾙｽﾞ!W52/1000 -> 0 | AE53: 250 | AF53: =+AD53-AE53 -> -250 | AG53: 500 | AH53: =+AD53-AG53 -> -500 | AI53: =+Y53+AD53 -> 0 | AJ53: =+Z53+AE53 -> 250 | AK53: =+AI53-AJ53 -> -250 | AL53: =+AB53+AG53 -> 500 | AM53: =+AI53-AL53 -> -500 | AN53: =+ｶﾞｰﾃﾞﾝ!W52/1000 -> 0 | AO53: 0 | AP53: =+AN53-AO53 -> 0 | AQ53: 860 | AR53: =+AN53-AQ53 -> -860 | AS53: =+ﾋﾞｱｶﾞｰﾃﾞﾝ!W52/1000 -> 0 | AT53: 0 | AU53: =+AS53-AT53 -> 0 | AV53: 0 | AW53: =+AS53-AV53 -> 0 | AX53: =+AN53+AS53 -> 0 | AY53: =+AO53+AT53 -> 0 | AZ53: =+AX53-AY53 -> 0 | BA53: =+AQ53+AV53 -> 860 | BB53: =+AX53-BA53 -> -860 | BC53: =+料飲共通!H52/1000 -> 0 | BD53: =+料飲共通!I52/1000 -> 0 | BE53: =+BC53+BD53 -> 0 | BF53: =+料飲共通!W52/1000 -> 0 | BG53: 0 | BH53: =+BF53-BG53 -> 0 | BI53: 0 | BJ53: =+BF53-BI53 -> 0 | BK53: =+T53+AI53+AX53+BE53+BF53 -> 0 | BL53: =+U53+AJ53+AY53+BG53 -> 250 | BM53: =+BK53-BL53 -> -250 | BN53: =+W53+AL53+BA53+BI53 -> 1360 | BO53: =+BK53-BN53 -> -1360 | BP53: =+BK53-BE53 -> 0 | BQ53: =+BL53-Z53 -> 250 | BR53: =+BP53-BQ53 -> -250 | BS53: =+BN53-AB53 -> 1360 | BT53: =+BP53-BS53 -> -1360
C54: 構築物 | E54: =+ﾇｰﾍﾞﾙﾌﾟｰｽ!W53/1000 -> 0 | F54: 0 | G54: =+E54-F54 -> 0 | H54: 0 | I54: =+E54-H54 -> 0 | J54: =+ｶﾌｪﾙﾎﾟ!W53/1000 -> 0 | K54: 0 | L54: =+J54-K54 -> 0 | M54: 0 | N54: =+J54-M54 -> 0 | O54: =+ｶﾌｪｾﾚｽﾃ!W53/1000 -> 0 | P54: 0 | Q54: =+O54-P54 -> 0 | R54: 0 | S54: =+O54-R54 -> 0 | T54: =+E54+J54+O54 -> 0 | U54: =+F54+K54+P54 -> 0 | V54: =+T54-U54 -> 0 | W54: =+H54+M54+R54 -> 0 | X54: =+T54-W54 -> 0 | Y54: 0 | Z54: 0 | AA54: =+Y54-Z54 -> 0 | AB54: 0 | AC54: =+Y54-AB54 -> 0 | AD54: =+ｼﾞｭｴﾙｽﾞ!W53/1000 -> 0 | AE54: 0 | AF54: =+AD54-AE54 -> 0 | AG54: 0 | AH54: =+AD54-AG54 -> 0 | AI54: =+Y54+AD54 -> 0 | AJ54: =+Z54+AE54 -> 0 | AK54: =+AI54-AJ54 -> 0 | AL54: =+AB54+AG54 -> 0 | AM54: =+AI54-AL54 -> 0 | AN54: =+ｶﾞｰﾃﾞﾝ!W53/1000 -> 0 | AO54: 0 | AP54: =+AN54-AO54 -> 0 | AQ54: 0 | AR54: =+AN54-AQ54 -> 0 | AS54: =+ﾋﾞｱｶﾞｰﾃﾞﾝ!W53/1000 -> 0 | AT54: 0 | AU54: =+AS54-AT54 -> 0 | AV54: 0 | AW54: =+AS54-AV54 -> 0 | AX54: =+AN54+AS54 -> 0 | AY54: =+AO54+AT54 -> 0 | AZ54: =+AX54-AY54 -> 0 | BA54: =+AQ54+AV54 -> 0 | BB54: =+AX54-BA54 -> 0 | BC54: =+料飲共通!H53/1000 -> 0 | BD54: =+料飲共通!I53/1000 -> 0 | BE54: =+BC54+BD54 -> 0 | BF54: =+料飲共通!W53/1000 -> 0 | BG54: 0 | BH54: =+BF54-BG54 -> 0 | BI54: 0 | BJ54: =+BF54-BI54 -> 0 | BK54: =+T54+AI54+AX54+BE54+BF54 -> 0 | BL54: =+U54+AJ54+AY54+BG54 -> 0 | BM54: =+BK54-BL54 -> 0 | BN54: =+W54+AL54+BA54+BI54 -> 0 | BO54: =+BK54-BN54 -> 0 | BP54: =+BK54-BE54 -> 0 | BQ54: =+BL54-Z54 -> 0 | BR54: =+BP54-BQ54 -> 0 | BS54: =+BN54-AB54 -> 0 | BT54: =+BP54-BS54 -> 0
C55: 機械 | E55: =+ﾇｰﾍﾞﾙﾌﾟｰｽ!W54/1000 -> 0 | F55: 0 | G55: =+E55-F55 -> 0 | H55: 0 | I55: =+E55-H55 -> 0 | J55: =+ｶﾌｪﾙﾎﾟ!W54/1000 -> 0 | K55: 0 | L55: =+J55-K55 -> 0 | M55: 0 | N55: =+J55-M55 -> 0 | O55: =+ｶﾌｪｾﾚｽﾃ!W54/1000 -> 0 | P55: 0 | Q55: =+O55-P55 -> 0 | R55: 0 | S55: =+O55-R55 -> 0 | T55: =+E55+J55+O55 -> 0 | U55: =+F55+K55+P55 -> 0 | V55: =+T55-U55 -> 0 | W55: =+H55+M55+R55 -> 0 | X55: =+T55-W55 -> 0 | Y55: 0 | Z55: 0 | AA55: =+Y55-Z55 -> 0 | AB55: 0 | AC55: =+Y55-AB55 -> 0 | AD55: =+ｼﾞｭｴﾙｽﾞ!W54/1000 -> 0 | AE55: 0 | AF55: =+AD55-AE55 -> 0 | AG55: 0 | AH55: =+AD55-AG55 -> 0 | AI55: =+Y55+AD55 -> 0 | AJ55: =+Z55+AE55 -> 0 | AK55: =+AI55-AJ55 -> 0 | AL55: =+AB55+AG55 -> 0 | AM55: =+AI55-AL55 -> 0 | AN55: =+ｶﾞｰﾃﾞﾝ!W54/1000 -> 0 | AO55: 0 | AP55: =+AN55-AO55 -> 0 | AQ55: 0 | AR55: =+AN55-AQ55 -> 0 | AS55: =+ﾋﾞｱｶﾞｰﾃﾞﾝ!W54/1000 -> 0 | AT55: 0 | AU55: =+AS55-AT55 -> 0 | AV55: 0 | AW55: =+AS55-AV55 -> 0 | AX55: =+AN55+AS55 -> 0 | AY55: =+AO55+AT55 -> 0 | AZ55: =+AX55-AY55 -> 0 | BA55: =+AQ55+AV55 -> 0 | BB55: =+AX55-BA55 -> 0 | BC55: =+料飲共通!H54/1000 -> 0 | BD55: =+料飲共通!I54/1000 -> 0 | BE55: =+BC55+BD55 -> 0 | BF55: =+料飲共通!W54/1000 -> 0 | BG55: 0 | BH55: =+BF55-BG55 -> 0 | BI55: 0 | BJ55: =+BF55-BI55 -> 0 | BK55: =+T55+AI55+AX55+BE55+BF55 -> 0 | BL55: =+U55+AJ55+AY55+BG55 -> 0 | BM55: =+BK55-BL55 -> 0 | BN55: =+W55+AL55+BA55+BI55 -> 0 | BO55: =+BK55-BN55 -> 0 | BP55: =+BK55-BE55 -> 0 | BQ55: =+BL55-Z55 -> 0 | BR55: =+BP55-BQ55 -> 0 | BS55: =+BN55-AB55 -> 0 | BT55: =+BP55-BS55 -> 0
C56: 器具備品 | E56: =+ﾇｰﾍﾞﾙﾌﾟｰｽ!W55/1000 -> 0 | F56: 450 | G56: =+E56-F56 -> -450 | H56: 900 | I56: =+E56-H56 -> -900 | J56: =+ｶﾌｪﾙﾎﾟ!W55/1000 -> 0 | K56: 0 | L56: =+J56-K56 -> 0 | M56: 97 | N56: =+J56-M56 -> -97 | O56: =+ｶﾌｪｾﾚｽﾃ!W55/1000 -> 0 | P56: 0 | Q56: =+O56-P56 -> 0 | R56: 0 | S56: =+O56-R56 -> 0 | T56: =+E56+J56+O56 -> 0 | U56: =+F56+K56+P56 -> 450 | V56: =+T56-U56 -> -450 | W56: =+H56+M56+R56 -> 997 | X56: =+T56-W56 -> -997 | Y56: 0 | Z56: 0 | AA56: =+Y56-Z56 -> 0 | AB56: 540 | AC56: =+Y56-AB56 -> -540 | AD56: =+ｼﾞｭｴﾙｽﾞ!W55/1000 -> 0 | AE56: 598.03 | AF56: =+AD56-AE56 -> -598.03 | AG56: 100 | AH56: =+AD56-AG56 -> -100 | AI56: =+Y56+AD56 -> 0 | AJ56: =+Z56+AE56 -> 598.03 | AK56: =+AI56-AJ56 -> -598.03 | AL56: =+AB56+AG56 -> 640 | AM56: =+AI56-AL56 -> -640 | AN56: =+ｶﾞｰﾃﾞﾝ!W55/1000 -> 0 | AO56: 437.25 | AP56: =+AN56-AO56 -> -437.25 | AQ56: 100 | AR56: =+AN56-AQ56 -> -100 | AS56: =+ﾋﾞｱｶﾞｰﾃﾞﾝ!W55/1000 -> 150 | AT56: 28 | AU56: =+AS56-AT56 -> 122 | AV56: 50 | AW56: =+AS56-AV56 -> 100 | AX56: =+AN56+AS56 -> 150 | AY56: =+AO56+AT56 -> 465.25 | AZ56: =+AX56-AY56 -> -315.25 | BA56: =+AQ56+AV56 -> 150 | BB56: =+AX56-BA56 -> 0 | BC56: =+料飲共通!H55/1000 -> 0 | BD56: =+料飲共通!I55/1000 -> 0 | BE56: =+BC56+BD56 -> 0 | BF56: =+料飲共通!W55/1000 -> 0 | BG56: 0 | BH56: =+BF56-BG56 -> 0 | BI56: 0 | BJ56: =+BF56-BI56 -> 0 | BK56: =+T56+AI56+AX56+BE56+BF56 -> 150 | BL56: =+U56+AJ56+AY56+BG56 -> 1513.28 | BM56: =+BK56-BL56 -> -1363.28 | BN56: =+W56+AL56+BA56+BI56 -> 1787 | BO56: =+BK56-BN56 -> -1637 | BP56: =+BK56-BE56 -> 150 | BQ56: =+BL56-Z56 -> 1513.28 | BR56: =+BP56-BQ56 -> -1363.28 | BS56: =+BN56-AB56 -> 1247 | BT56: =+BP56-BS56 -> -1097
C57: 車両 | E57: =+ﾇｰﾍﾞﾙﾌﾟｰｽ!W56/1000 -> 0 | F57: 0 | G57: =+E57-F57 -> 0 | H57: 0 | I57: =+E57-H57 -> 0 | J57: =+ｶﾌｪﾙﾎﾟ!W56/1000 -> 0 | K57: 0 | L57: =+J57-K57 -> 0 | M57: 0 | N57: =+J57-M57 -> 0 | O57: =+ｶﾌｪｾﾚｽﾃ!W56/1000 -> 0 | P57: 0 | Q57: =+O57-P57 -> 0 | R57: 0 | S57: =+O57-R57 -> 0 | T57: =+E57+J57+O57 -> 0 | U57: =+F57+K57+P57 -> 0 | V57: =+T57-U57 -> 0 | W57: =+H57+M57+R57 -> 0 | X57: =+T57-W57 -> 0 | Y57: 0 | Z57: 0 | AA57: =+Y57-Z57 -> 0 | AB57: 0 | AC57: =+Y57-AB57 -> 0 | AD57: =+ｼﾞｭｴﾙｽﾞ!W56/1000 -> 0 | AE57: 0 | AF57: =+AD57-AE57 -> 0 | AG57: 0 | AH57: =+AD57-AG57 -> 0 | AI57: =+Y57+AD57 -> 0 | AJ57: =+Z57+AE57 -> 0 | AK57: =+AI57-AJ57 -> 0 | AL57: =+AB57+AG57 -> 0 | AM57: =+AI57-AL57 -> 0 | AN57: =+ｶﾞｰﾃﾞﾝ!W56/1000 -> 0 | AO57: 0 | AP57: =+AN57-AO57 -> 0 | AQ57: 0 | AR57: =+AN57-AQ57 -> 0 | AS57: =+ﾋﾞｱｶﾞｰﾃﾞﾝ!W56/1000 -> 0 | AT57: 0 | AU57: =+AS57-AT57 -> 0 | AV57: 0 | AW57: =+AS57-AV57 -> 0 | AX57: =+AN57+AS57 -> 0 | AY57: =+AO57+AT57 -> 0 | AZ57: =+AX57-AY57 -> 0 | BA57: =+AQ57+AV57 -> 0 | BB57: =+AX57-BA57 -> 0 | BC57: =+料飲共通!H56/1000 -> 0 | BD57: =+料飲共通!I56/1000 -> 0 | BE57: =+BC57+BD57 -> 0 | BF57: =+料飲共通!W56/1000 -> 0 | BG57: 0 | BH57: =+BF57-BG57 -> 0 | BI57: 0 | BJ57: =+BF57-BI57 -> 0 | BK57: =+T57+AI57+AX57+BE57+BF57 -> 0 | BL57: =+U57+AJ57+AY57+BG57 -> 0 | BM57: =+BK57-BL57 -> 0 | BN57: =+W57+AL57+BA57+BI57 -> 0 | BO57: =+BK57-BN57 -> 0 | BP57: =+BK57-BE57 -> 0 | BQ57: =+BL57-Z57 -> 0 | BR57: =+BP57-BQ57 -> 0 | BS57: =+BN57-AB57 -> 0 | BT57: =+BP57-BS57 -> 0
B58: 車両運搬費 | E58: =+ﾇｰﾍﾞﾙﾌﾟｰｽ!W57/1000 -> 0 | F58: 0 | G58: =+E58-F58 -> 0 | H58: 0 | I58: =+E58-H58 -> 0 | J58: =+ｶﾌｪﾙﾎﾟ!W57/1000 -> 0 | K58: 0 | L58: =+J58-K58 -> 0 | M58: 0 | N58: =+J58-M58 -> 0 | O58: =+ｶﾌｪｾﾚｽﾃ!W57/1000 -> 0 | P58: 0 | Q58: =+O58-P58 -> 0 | R58: 0 | S58: =+O58-R58 -> 0 | T58: =+E58+J58+O58 -> 0 | U58: =+F58+K58+P58 -> 0 | V58: =+T58-U58 -> 0 | W58: =+H58+M58+R58 -> 0 | X58: =+T58-W58 -> 0 | Y58: 0 | Z58: 0 | AA58: =+Y58-Z58 -> 0 | AB58: 0 | AC58: =+Y58-AB58 -> 0 | AD58: =+ｼﾞｭｴﾙｽﾞ!W57/1000 -> 0 | AE58: 0 | AF58: =+AD58-AE58 -> 0 | AG58: 0 | AH58: =+AD58-AG58 -> 0 | AI58: =+Y58+AD58 -> 0 | AJ58: =+Z58+AE58 -> 0 | AK58: =+AI58-AJ58 -> 0 | AL58: =+AB58+AG58 -> 0 | AM58: =+AI58-AL58 -> 0 | AN58: =+ｶﾞｰﾃﾞﾝ!W57/1000 -> 0 | AO58: 0 | AP58: =+AN58-AO58 -> 0 | AQ58: 0 | AR58: =+AN58-AQ58 -> 0 | AS58: =+ﾋﾞｱｶﾞｰﾃﾞﾝ!W57/1000 -> 0 | AT58: 0 | AU58: =+AS58-AT58 -> 0 | AV58: 0 | AW58: =+AS58-AV58 -> 0 | AX58: =+AN58+AS58 -> 0 | AY58: =+AO58+AT58 -> 0 | AZ58: =+AX58-AY58 -> 0 | BA58: =+AQ58+AV58 -> 0 | BB58: =+AX58-BA58 -> 0 | BC58: 0 | BD58: 0 | BE58: =+BC58+BD58 -> 0 | BF58: =+料飲共通!W57/1000 -> 0 | BG58: 0 | BH58: =+BF58-BG58 -> 0 | BI58: 0 | BJ58: =+BF58-BI58 -> 0 | BK58: =+T58+AI58+AX58+BE58+BF58 -> 0 | BL58: =+U58+AJ58+AY58+BG58 -> 0 | BM58: =+BK58-BL58 -> 0 | BN58: =+W58+AL58+BA58+BI58 -> 0 | BO58: =+BK58-BN58 -> 0 | BP58: =+BK58-BE58 -> 0 | BQ58: =+BL58-Z58 -> 0 | BR58: =+BP58-BQ58 -> 0 | BS58: =+BN58-AB58 -> 0 | BT58: =+BP58-BS58 -> 0
B59: 印刷製本費 | E59: =+ﾇｰﾍﾞﾙﾌﾟｰｽ!W58/1000 -> 414 | F59: 154.068 | G59: =+E59-F59 -> 259.932 | H59: 259 | I59: =+E59-H59 -> 155 | J59: =+ｶﾌｪﾙﾎﾟ!W58/1000 -> 0 | K59: 0 | L59: =+J59-K59 -> 0 | M59: 0 | N59: =+J59-M59 -> 0 | O59: =+ｶﾌｪｾﾚｽﾃ!W58/1000 -> 0 | P59: 0 | Q59: =+O59-P59 -> 0 | R59: 0 | S59: =+O59-R59 -> 0 | T59: =+E59+J59+O59 -> 414 | U59: =+F59+K59+P59 -> 154.068 | V59: =+T59-U59 -> 259.932 | W59: =+H59+M59+R59 -> 259 | X59: =+T59-W59 -> 155 | Y59: 0 | Z59: 0 | AA59: =+Y59-Z59 -> 0 | AB59: 0 | AC59: =+Y59-AB59 -> 0 | AD59: =+ｼﾞｭｴﾙｽﾞ!W58/1000 -> 390 | AE59: 259.267 | AF59: =+AD59-AE59 -> 130.733 | AG59: 181 | AH59: =+AD59-AG59 -> 209 | AI59: =+Y59+AD59 -> 390 | AJ59: =+Z59+AE59 -> 259.267 | AK59: =+AI59-AJ59 -> 130.733 | AL59: =+AB59+AG59 -> 181 | AM59: =+AI59-AL59 -> 209 | AN59: =+ｶﾞｰﾃﾞﾝ!W58/1000 -> 141 | AO59: 193.867 | AP59: =+AN59-AO59 -> -52.867 | AQ59: 130 | AR59: =+AN59-AQ59 -> 11 | AS59: =+ﾋﾞｱｶﾞｰﾃﾞﾝ!W58/1000 -> 261 | AT59: 0 | AU59: =+AS59-AT59 -> 261 | AV59: 240 | AW59: =+AS59-AV59 -> 21 | AX59: =+AN59+AS59 -> 402 | AY59: =+AO59+AT59 -> 193.867 | AZ59: =+AX59-AY59 -> 208.133 | BA59: =+AQ59+AV59 -> 370 | BB59: =+AX59-BA59 -> 32 | BC59: =+赤れんが!X59/1000 -> 109.85658 | BD59: =+赤れんが!Z59/1000 -> 0 | BE59: =+BC59+BD59 -> 109.85658 | BF59: =+料飲共通!W58/1000 -> 60 | BG59: 238.01 | BH59: =+BF59-BG59 -> -178.01 | BI59: 0 | BJ59: =+BF59-BI59 -> 60 | BK59: =+T59+AI59+AX59+BE59+BF59 -> 1375.8566 | BL59: =+U59+AJ59+AY59+BG59 -> 845.212 | BM59: =+BK59-BL59 -> 530.64458 | BN59: =+W59+AL59+BA59+BI59 -> 810 | BO59: =+BK59-BN59 -> 565.85658 | BP59: =+BK59-BE59 -> 1266 | BQ59: =+BL59-Z59 -> 845.212 | BR59: =+BP59-BQ59 -> 420.788 | BS59: =+BN59-AB59 -> 810 | BT59: =+BP59-BS59 -> 456
C60: 印刷製本費 | E60: =+ﾇｰﾍﾞﾙﾌﾟｰｽ!W59/1000 -> 414 | F60: 154.068 | G60: =+E60-F60 -> 259.932 | H60: 259 | I60: =+E60-H60 -> 155 | J60: =+ｶﾌｪﾙﾎﾟ!W59/1000 -> 0 | K60: 0 | L60: =+J60-K60 -> 0 | M60: 0 | N60: =+J60-M60 -> 0 | O60: =+ｶﾌｪｾﾚｽﾃ!W59/1000 -> 0 | P60: 0 | Q60: =+O60-P60 -> 0 | R60: 0 | S60: =+O60-R60 -> 0 | T60: =+E60+J60+O60 -> 414 | U60: =+F60+K60+P60 -> 154.068 | V60: =+T60-U60 -> 259.932 | W60: =+H60+M60+R60 -> 259 | X60: =+T60-W60 -> 155 | Y60: 0 | Z60: 0 | AA60: =+Y60-Z60 -> 0 | AB60: 0 | AC60: =+Y60-AB60 -> 0 | AD60: =+ｼﾞｭｴﾙｽﾞ!W59/1000 -> 390 | AE60: 259.267 | AF60: =+AD60-AE60 -> 130.733 | AG60: 181 | AH60: =+AD60-AG60 -> 209 | AI60: =+Y60+AD60 -> 390 | AJ60: =+Z60+AE60 -> 259.267 | AK60: =+AI60-AJ60 -> 130.733 | AL60: =+AB60+AG60 -> 181 | AM60: =+AI60-AL60 -> 209 | AN60: =+ｶﾞｰﾃﾞﾝ!W59/1000 -> 141 | AO60: 193.867 | AP60: =+AN60-AO60 -> -52.867 | AQ60: 130 | AR60: =+AN60-AQ60 -> 11 | AS60: =+ﾋﾞｱｶﾞｰﾃﾞﾝ!W59/1000 -> 261 | AT60: 0 | AU60: =+AS60-AT60 -> 261 | AV60: 240 | AW60: =+AS60-AV60 -> 21 | AX60: =+AN60+AS60 -> 402 | AY60: =+AO60+AT60 -> 193.867 | AZ60: =+AX60-AY60 -> 208.133 | BA60: =+AQ60+AV60 -> 370 | BB60: =+AX60-BA60 -> 32 | BC60: =+料飲共通!H59/1000 -> 0 | BD60: =+料飲共通!I59/1000 -> 0 | BE60: =+BC60+BD60 -> 0 | BF60: =+料飲共通!W59/1000 -> 60 | BG60: 238.01 | BH60: =+BF60-BG60 -> -178.01 | BI60: 0 | BJ60: =+BF60-BI60 -> 60 | BK60: =+T60+AI60+AX60+BE60+BF60 -> 1266 | BL60: =+U60+AJ60+AY60+BG60 -> 845.212 | BM60: =+BK60-BL60 -> 420.788 | BN60: =+W60+AL60+BA60+BI60 -> 810 | BO60: =+BK60-BN60 -> 456 | BP60: =+BK60-BE60 -> 1266 | BQ60: =+BL60-Z60 -> 845.212 | BR60: =+BP60-BQ60 -> 420.788 | BS60: =+BN60-AB60 -> 810 | BT60: =+BP60-BS60 -> 456
C61: 乗車券帳票費 | E61: =+ﾇｰﾍﾞﾙﾌﾟｰｽ!W60/1000 -> 0 | F61: 0 | G61: =+E61-F61 -> 0 | H61: 0 | I61: =+E61-H61 -> 0 | J61: =+ｶﾌｪﾙﾎﾟ!W60/1000 -> 0 | K61: 0 | L61: =+J61-K61 -> 0 | M61: 0 | N61: =+J61-M61 -> 0 | O61: =+ｶﾌｪｾﾚｽﾃ!W60/1000 -> 0 | P61: 0 | Q61: =+O61-P61 -> 0 | R61: 0 | S61: =+O61-R61 -> 0 | T61: =+E61+J61+O61 -> 0 | U61: =+F61+K61+P61 -> 0 | V61: =+T61-U61 -> 0 | W61: =+H61+M61+R61 -> 0 | X61: =+T61-W61 -> 0 | Y61: 0 | Z61: 0 | AA61: =+Y61-Z61 -> 0 | AB61: 0 | AC61: =+Y61-AB61 -> 0 | AD61: =+ｼﾞｭｴﾙｽﾞ!W60/1000 -> 0 | AE61: 0 | AF61: =+AD61-AE61 -> 0 | AG61: 0 | AH61: =+AD61-AG61 -> 0 | AI61: =+Y61+AD61 -> 0 | AJ61: =+Z61+AE61 -> 0 | AK61: =+AI61-AJ61 -> 0 | AL61: =+AB61+AG61 -> 0 | AM61: =+AI61-AL61 -> 0 | AN61: =+ｶﾞｰﾃﾞﾝ!W60/1000 -> 0 | AO61: 0 | AP61: =+AN61-AO61 -> 0 | AQ61: 0 | AR61: =+AN61-AQ61 -> 0 | AS61: =+ﾋﾞｱｶﾞｰﾃﾞﾝ!W60/1000 -> 0 | AT61: 0 | AU61: =+AS61-AT61 -> 0 | AV61: 0 | AW61: =+AS61-AV61 -> 0 | AX61: =+AN61+AS61 -> 0 | AY61: =+AO61+AT61 -> 0 | AZ61: =+AX61-AY61 -> 0 | BA61: =+AQ61+AV61 -> 0 | BB61: =+AX61-BA61 -> 0 | BC61: =+料飲共通!H60/1000 -> 0 | BD61: =+料飲共通!I60/1000 -> 0 | BE61: =+BC61+BD61 -> 0 | BF61: =+料飲共通!W60/1000 -> 0 | BG61: 0 | BH61: =+BF61-BG61 -> 0 | BI61: 0 | BJ61: =+BF61-BI61 -> 0 | BK61: =+T61+AI61+AX61+BE61+BF61 -> 0 | BL61: =+U61+AJ61+AY61+BG61 -> 0 | BM61: =+BK61-BL61 -> 0 | BN61: =+W61+AL61+BA61+BI61 -> 0 | BO61: =+BK61-BN61 -> 0 | BP61: =+BK61-BE61 -> 0 | BQ61: =+BL61-Z61 -> 0 | BR61: =+BP61-BQ61 -> 0 | BS61: =+BN61-AB61 -> 0 | BT61: =+BP61-BS61 -> 0
B62: 清掃衛生費 | E62: =+ﾇｰﾍﾞﾙﾌﾟｰｽ!W61/1000 -> 984 | F62: 978.632 | G62: =+E62-F62 -> 5.368 | H62: 852 | I62: =+E62-H62 -> 132 | J62: =+ｶﾌｪﾙﾎﾟ!W61/1000 -> 30.5 | K62: 27.502 | L62: =+J62-K62 -> 2.998 | M62: 60 | N62: =+J62-M62 -> -29.5 | O62: =+ｶﾌｪｾﾚｽﾃ!W61/1000 -> 0 | P62: 0 | Q62: =+O62-P62 -> 0 | R62: 10 | S62: =+O62-R62 -> -10 | T62: =+E62+J62+O62 -> 1014.5 | U62: =+F62+K62+P62 -> 1006.134 | V62: =+T62-U62 -> 8.366 | W62: =+H62+M62+R62 -> 922 | X62: =+T62-W62 -> 92.5 | Y62: 0 | Z62: 37.3 | AA62: =+Y62-Z62 -> -37.3 | AB62: 0 | AC62: =+Y62-AB62 -> 0 | AD62: =+ｼﾞｭｴﾙｽﾞ!W61/1000 -> 764 | AE62: 772.628 | AF62: =+AD62-AE62 -> -8.628 | AG62: 579 | AH62: =+AD62-AG62 -> 185 | AI62: =+Y62+AD62 -> 764 | AJ62: =+Z62+AE62 -> 809.928 | AK62: =+AI62-AJ62 -> -45.928 | AL62: =+AB62+AG62 -> 579 | AM62: =+AI62-AL62 -> 185 | AN62: =+ｶﾞｰﾃﾞﾝ!W61/1000 -> 622.4 | AO62: 419.098 | AP62: =+AN62-AO62 -> 203.302 | AQ62: 300 | AR62: =+AN62-AQ62 -> 322.4 | AS62: =+ﾋﾞｱｶﾞｰﾃﾞﾝ!W61/1000 -> 700 | AT62: 661.811 | AU62: =+AS62-AT62 -> 38.189 | AV62: 400 | AW62: =+AS62-AV62 -> 300 | AX62: =+AN62+AS62 -> 1322.4 | AY62: =+AO62+AT62 -> 1080.909 | AZ62: =+AX62-AY62 -> 241.491 | BA62: =+AQ62+AV62 -> 700 | BB62: =+AX62-BA62 -> 622.4 | BC62: =+赤れんが!X62/1000 -> 237.48586 | BD62: =+赤れんが!Z62/1000 -> 123.05793 | BE62: =+BC62+BD62 -> 360.54379 | BF62: =+料飲共通!W61/1000 -> 0 | BG62: 0 | BH62: =+BF62-BG62 -> 0 | BI62: 0 | BJ62: =+BF62-BI62 -> 0 | BK62: =+T62+AI62+AX62+BE62+BF62 -> 3461.4438 | BL62: =+U62+AJ62+AY62+BG62 -> 2896.971 | BM62: =+BK62-BL62 -> 564.47279 | BN62: =+W62+AL62+BA62+BI62 -> 2201 | BO62: =+BK62-BN62 -> 1260.4438 | BP62: =+BK62-BE62 -> 3100.9 | BQ62: =+BL62-Z62 -> 2859.671 | BR62: =+BP62-BQ62 -> 241.229 | BS62: =+BN62-AB62 -> 2201 | BT62: =+BP62-BS62 -> 899.9
B63: 事務会議費 | E63: =+ﾇｰﾍﾞﾙﾌﾟｰｽ!W62/1000 -> 0 | F63: 0 | G63: =+E63-F63 -> 0 | H63: 0 | I63: =+E63-H63 -> 0 | J63: =+ｶﾌｪﾙﾎﾟ!W62/1000 -> 0 | K63: 0 | L63: =+J63-K63 -> 0 | M63: 0 | N63: =+J63-M63 -> 0 | O63: =+ｶﾌｪｾﾚｽﾃ!W62/1000 -> 0 | P63: 0 | Q63: =+O63-P63 -> 0 | R63: 0 | S63: =+O63-R63 -> 0 | T63: =+E63+J63+O63 -> 0 | U63: =+F63+K63+P63 -> 0 | V63: =+T63-U63 -> 0 | W63: =+H63+M63+R63 -> 0 | X63: =+T63-W63 -> 0 | Y63: 0 | Z63: 0 | AA63: =+Y63-Z63 -> 0 | AB63: 0 | AC63: =+Y63-AB63 -> 0 | AD63: =+ｼﾞｭｴﾙｽﾞ!W62/1000 -> 0 | AE63: 0 | AF63: =+AD63-AE63 -> 0 | AG63: 0 | AH63: =+AD63-AG63 -> 0 | AI63: =+Y63+AD63 -> 0 | AJ63: =+Z63+AE63 -> 0 | AK63: =+AI63-AJ63 -> 0 | AL63: =+AB63+AG63 -> 0 | AM63: =+AI63-AL63 -> 0 | AN63: =+ｶﾞｰﾃﾞﾝ!W62/1000 -> 0 | AO63: 0 | AP63: =+AN63-AO63 -> 0 | AQ63: 0 | AR63: =+AN63-AQ63 -> 0 | AS63: =+ﾋﾞｱｶﾞｰﾃﾞﾝ!W62/1000 -> 0 | AT63: 0 | AU63: =+AS63-AT63 -> 0 | AV63: 0 | AW63: =+AS63-AV63 -> 0 | AX63: =+AN63+AS63 -> 0 | AY63: =+AO63+AT63 -> 0 | AZ63: =+AX63-AY63 -> 0 | BA63: =+AQ63+AV63 -> 0 | BB63: =+AX63-BA63 -> 0 | BC63: 0 | BD63: 0 | BE63: =+BC63+BD63 -> 0 | BF63: =+料飲共通!W62/1000 -> 0 | BG63: 0 | BH63: =+BF63-BG63 -> 0 | BI63: 0 | BJ63: =+BF63-BI63 -> 0 | BK63: =+T63+AI63+AX63+BE63+BF63 -> 0 | BL63: =+U63+AJ63+AY63+BG63 -> 0 | BM63: =+BK63-BL63 -> 0 | BN63: =+W63+AL63+BA63+BI63 -> 0 | BO63: =+BK63-BN63 -> 0 | BP63: =+BK63-BE63 -> 0 | BQ63: =+BL63-Z63 -> 0 | BR63: =+BP63-BQ63 -> 0 | BS63: =+BN63-AB63 -> 0 | BT63: =+BP63-BS63 -> 0
B64: 租税公課 | E64: =+ﾇｰﾍﾞﾙﾌﾟｰｽ!W63/1000 -> 148.5 | F64: 149.5 | G64: =+E64-F64 -> -1 | H64: 202 | I64: =+E64-H64 -> -53.5 | J64: =+ｶﾌｪﾙﾎﾟ!W63/1000 -> 23.5 | K64: 23.5 | L64: =+J64-K64 -> 0 | M64: 26 | N64: =+J64-M64 -> -2.5 | O64: =+ｶﾌｪｾﾚｽﾃ!W63/1000 -> 9.7 | P64: 9.7 | Q64: =+O64-P64 -> 0 | R64: 0 | S64: =+O64-R64 -> 9.7 | T64: =+E64+J64+O64 -> 181.7 | U64: =+F64+K64+P64 -> 182.7 | V64: =+T64-U64 -> -1 | W64: =+H64+M64+R64 -> 228 | X64: =+T64-W64 -> -46.3 | Y64: 0 | Z64: 0 | AA64: =+Y64-Z64 -> 0 | AB64: 0 | AC64: =+Y64-AB64 -> 0 | AD64: =+ｼﾞｭｴﾙｽﾞ!W63/1000 -> 76.3 | AE64: 76.3 | AF64: =+AD64-AE64 -> 0 | AG64: 379 | AH64: =+AD64-AG64 -> -302.7 | AI64: =+Y64+AD64 -> 76.3 | AJ64: =+Z64+AE64 -> 76.3 | AK64: =+AI64-AJ64 -> 0 | AL64: =+AB64+AG64 -> 379 | AM64: =+AI64-AL64 -> -302.7 | AN64: =+ｶﾞｰﾃﾞﾝ!W63/1000 -> 260 | AO64: 276 | AP64: =+AN64-AO64 -> -16 | AQ64: 811 | AR64: =+AN64-AQ64 -> -551 | AS64: =+ﾋﾞｱｶﾞｰﾃﾞﾝ!W63/1000 -> 26.9 | AT64: 24.4 | AU64: =+AS64-AT64 -> 2.5 | AV64: 4 | AW64: =+AS64-AV64 -> 22.9 | AX64: =+AN64+AS64 -> 286.9 | AY64: =+AO64+AT64 -> 300.4 | AZ64: =+AX64-AY64 -> -13.5 | BA64: =+AQ64+AV64 -> 815 | BB64: =+AX64-BA64 -> -528.1 | BC64: =+赤れんが!X64/1000 -> 323.4 | BD64: =+赤れんが!Z64/1000 -> 58.8 | BE64: =+BC64+BD64 -> 382.2 | BF64: =+料飲共通!W63/1000 -> 0 | BG64: 0 | BH64: =+BF64-BG64 -> 0 | BI64: 0 | BJ64: =+BF64-BI64 -> 0 | BK64: =+T64+AI64+AX64+BE64+BF64 -> 927.1 | BL64: =+U64+AJ64+AY64+BG64 -> 559.4 | BM64: =+BK64-BL64 -> 367.7 | BN64: =+W64+AL64+BA64+BI64 -> 1422 | BO64: =+BK64-BN64 -> -494.9 | BP64: =+BK64-BE64 -> 544.9 | BQ64: =+BL64-Z64 -> 559.4 | BR64: =+BP64-BQ64 -> -14.5 | BS64: =+BN64-AB64 -> 1422 | BT64: =+BP64-BS64 -> -877.1
B65: 会費負担金 | E65: =+ﾇｰﾍﾞﾙﾌﾟｰｽ!W64/1000 -> 130 | F65: 84 | G65: =+E65-F65 -> 46 | H65: 200 | I65: =+E65-H65 -> -70 | J65: =+ｶﾌｪﾙﾎﾟ!W64/1000 -> 0 | K65: 0 | L65: =+J65-K65 -> 0 | M65: 0 | N65: =+J65-M65 -> 0 | O65: =+ｶﾌｪｾﾚｽﾃ!W64/1000 -> 0 | P65: 0 | Q65: =+O65-P65 -> 0 | R65: 0 | S65: =+O65-R65 -> 0 | T65: =+E65+J65+O65 -> 130 | U65: =+F65+K65+P65 -> 84 | V65: =+T65-U65 -> 46 | W65: =+H65+M65+R65 -> 200 | X65: =+T65-W65 -> -70 | Y65: 0 | Z65: 0 | AA65: =+Y65-Z65 -> 0 | AB65: 0 | AC65: =+Y65-AB65 -> 0 | AD65: =+ｼﾞｭｴﾙｽﾞ!W64/1000 -> 135 | AE65: 47 | AF65: =+AD65-AE65 -> 88 | AG65: 151 | AH65: =+AD65-AG65 -> -16 | AI65: =+Y65+AD65 -> 135 | AJ65: =+Z65+AE65 -> 47 | AK65: =+AI65-AJ65 -> 88 | AL65: =+AB65+AG65 -> 151 | AM65: =+AI65-AL65 -> -16 | AN65: =+ｶﾞｰﾃﾞﾝ!W64/1000 -> 165 | AO65: 196.25 | AP65: =+AN65-AO65 -> -31.25 | AQ65: 240 | AR65: =+AN65-AQ65 -> -75 | AS65: =+ﾋﾞｱｶﾞｰﾃﾞﾝ!W64/1000 -> 0 | AT65: 0 | AU65: =+AS65-AT65 -> 0 | AV65: 0 | AW65: =+AS65-AV65 -> 0 | AX65: =+AN65+AS65 -> 165 | AY65: =+AO65+AT65 -> 196.25 | AZ65: =+AX65-AY65 -> -31.25 | BA65: =+AQ65+AV65 -> 240 | BB65: =+AX65-BA65 -> -75 | BC65: =+赤れんが!X65/1000 -> 0 | BD65: =+赤れんが!Z65/1000 -> 0 | BE65: =+BC65+BD65 -> 0 | BF65: =+料飲共通!W64/1000 -> 15 | BG65: 0 | BH65: =+BF65-BG65 -> 15 | BI65: 0 | BJ65: =+BF65-BI65 -> 15 | BK65: =+T65+AI65+AX65+BE65+BF65 -> 445 | BL65: =+U65+AJ65+AY65+BG65 -> 327.25 | BM65: =+BK65-BL65 -> 117.75 | BN65: =+W65+AL65+BA65+BI65 -> 591 | BO65: =+BK65-BN65 -> -146 | BP65: =+BK65-BE65 -> 445 | BQ65: =+BL65-Z65 -> 327.25 | BR65: =+BP65-BQ65 -> 117.75 | BS65: =+BN65-AB65 -> 591 | BT65: =+BP65-BS65 -> -146
B66: 委託料 | E66: =+ﾇｰﾍﾞﾙﾌﾟｰｽ!W65/1000 -> 2991.44 | F66: 3012.278 | G66: =+E66-F66 -> -20.838 | H66: 2156 | I66: =+E66-H66 -> 835.44 | J66: =+ｶﾌｪﾙﾎﾟ!W65/1000 -> 184 | K66: 287.6 | L66: =+J66-K66 -> -103.6 | M66: 25 | N66: =+J66-M66 -> 159 | O66: =+ｶﾌｪｾﾚｽﾃ!W65/1000 -> 290 | P66: 168 | Q66: =+O66-P66 -> 122 | R66: 133 | S66: =+O66-R66 -> 157 | T66: =+E66+J66+O66 -> 3465.44 | U66: =+F66+K66+P66 -> 3467.878 | V66: =+T66-U66 -> -2.438 | W66: =+H66+M66+R66 -> 2314 | X66: =+T66-W66 -> 1151.44 | Y66: 0 | Z66: 795.87 | AA66: =+Y66-Z66 -> -795.87 | AB66: 779 | AC66: =+Y66-AB66 -> -779 | AD66: =+ｼﾞｭｴﾙｽﾞ!W65/1000 -> 3997.44 | AE66: 3786.086 | AF66: =+AD66-AE66 -> 211.354 | AG66: 3182 | AH66: =+AD66-AG66 -> 815.44 | AI66: =+Y66+AD66 -> 3997.44 | AJ66: =+Z66+AE66 -> 4581.956 | AK66: =+AI66-AJ66 -> -584.516 | AL66: =+AB66+AG66 -> 3961 | AM66: =+AI66-AL66 -> 36.44 | AN66: =+ｶﾞｰﾃﾞﾝ!W65/1000 -> 5337.64 | AO66: 4937.143 | AP66: =+AN66-AO66 -> 400.497 | AQ66: 6648 | AR66: =+AN66-AQ66 -> -1310.36 | AS66: =+ﾋﾞｱｶﾞｰﾃﾞﾝ!W65/1000 -> 39740.5 | AT66: 53569.193 | AU66: =+AS66-AT66 -> -13828.693 | AV66: 41306 | AW66: =+AS66-AV66 -> -1565.5 | AX66: =+AN66+AS66 -> 45078.14 | AY66: =+AO66+AT66 -> 58506.336 | AZ66: =+AX66-AY66 -> -13428.196 | BA66: =+AQ66+AV66 -> 47954 | BB66: =+AX66-BA66 -> -2875.86 | BC66: =+赤れんが!X66/1000 -> 2114.0649 | BD66: =+赤れんが!Z66/1000 -> 1206.0342 | BE66: =+BC66+BD66 -> 3320.0991 | BF66: =+料飲共通!W65/1000 -> 909.75 | BG66: 1008.3 | BH66: =+BF66-BG66 -> -98.55 | BI66: 81 | BJ66: =+BF66-BI66 -> 828.75 | BK66: =+T66+AI66+AX66+BE66+BF66 -> 56770.869 | BL66: =+U66+AJ66+AY66+BG66 -> 67564.47 | BM66: =+BK66-BL66 -> -10793.601 | BN66: =+W66+AL66+BA66+BI66 -> 54310 | BO66: =+BK66-BN66 -> 2460.8691 | BP66: =+BK66-BE66 -> 53450.77 | BQ66: =+BL66-Z66 -> 66768.6 | BR66: =+BP66-BQ66 -> -13317.83 | BS66: =+BN66-AB66 -> 53531 | BT66: =+BP66-BS66 -> -80.23
B67: 除雪費 | E67: =+ﾇｰﾍﾞﾙﾌﾟｰｽ!W66/1000 -> 0 | F67: 0 | G67: =+E67-F67 -> 0 | H67: 0 | I67: =+E67-H67 -> 0 | J67: =+ｶﾌｪﾙﾎﾟ!W66/1000 -> 0 | K67: 0 | L67: =+J67-K67 -> 0 | M67: 0 | N67: =+J67-M67 -> 0 | O67: =+ｶﾌｪｾﾚｽﾃ!W66/1000 -> 0 | P67: 0 | Q67: =+O67-P67 -> 0 | R67: 0 | S67: =+O67-R67 -> 0 | T67: =+E67+J67+O67 -> 0 | U67: =+F67+K67+P67 -> 0 | V67: =+T67-U67 -> 0 | W67: =+H67+M67+R67 -> 0 | X67: =+T67-W67 -> 0 | Y67: 0 | Z67: 0 | AA67: =+Y67-Z67 -> 0 | AB67: 0 | AC67: =+Y67-AB67 -> 0 | AD67: =+ｼﾞｭｴﾙｽﾞ!W66/1000 -> 0 | AE67: 0 | AF67: =+AD67-AE67 -> 0 | AG67: 0 | AH67: =+AD67-AG67 -> 0 | AI67: =+Y67+AD67 -> 0 | AJ67: =+Z67+AE67 -> 0 | AK67: =+AI67-AJ67 -> 0 | AL67: =+AB67+AG67 -> 0 | AM67: =+AI67-AL67 -> 0 | AN67: =+ｶﾞｰﾃﾞﾝ!W66/1000 -> 0 | AO67: 0 | AP67: =+AN67-AO67 -> 0 | AQ67: 0 | AR67: =+AN67-AQ67 -> 0 | AS67: =+ﾋﾞｱｶﾞｰﾃﾞﾝ!W66/1000 -> 0 | AT67: 0 | AU67: =+AS67-AT67 -> 0 | AV67: 0 | AW67: =+AS67-AV67 -> 0 | AX67: =+AN67+AS67 -> 0 | AY67: =+AO67+AT67 -> 0 | AZ67: =+AX67-AY67 -> 0 | BA67: =+AQ67+AV67 -> 0 | BB67: =+AX67-BA67 -> 0 | BC67: 0 | BD67: 0 | BE67: =+BC67+BD67 -> 0 | BF67: =+料飲共通!W66/1000 -> 0 | BG67: 0 | BH67: =+BF67-BG67 -> 0 | BI67: 0 | BJ67: =+BF67-BI67 -> 0 | BK67: =+T67+AI67+AX67+BE67+BF67 -> 0 | BL67: =+U67+AJ67+AY67+BG67 -> 0 | BM67: =+BK67-BL67 -> 0 | BN67: =+W67+AL67+BA67+BI67 -> 0 | BO67: =+BK67-BN67 -> 0 | BP67: =+BK67-BE67 -> 0 | BQ67: =+BL67-Z67 -> 0 | BR67: =+BP67-BQ67 -> 0 | BS67: =+BN67-AB67 -> 0 | BT67: =+BP67-BS67 -> 0
B68: 販売促進費 | E68: =+ﾇｰﾍﾞﾙﾌﾟｰｽ!W67/1000 -> 5175.328 | F68: 4398.504 | G68: =+E68-F68 -> 776.824 | H68: 5321 | I68: =+E68-H68 -> -145.672 | J68: =+ｶﾌｪﾙﾎﾟ!W67/1000 -> 160 | K68: 181.733 | L68: =+J68-K68 -> -21.733 | M68: 74 | N68: =+J68-M68 -> 86 | O68: =+ｶﾌｪｾﾚｽﾃ!W67/1000 -> 160 | P68: 226.328 | Q68: =+O68-P68 -> -66.328 | R68: 93 | S68: =+O68-R68 -> 67 | T68: =+E68+J68+O68 -> 5495.328 | U68: =+F68+K68+P68 -> 4806.565 | V68: =+T68-U68 -> 688.763 | W68: =+H68+M68+R68 -> 5488 | X68: =+T68-W68 -> 7.328 | Y68: 0 | Z68: 0 | AA68: =+Y68-Z68 -> 0 | AB68: 0 | AC68: =+Y68-AB68 -> 0 | AD68: =+ｼﾞｭｴﾙｽﾞ!W67/1000 -> 4544.599 | AE68: 4887.84 | AF68: =+AD68-AE68 -> -343.241 | AG68: 3710 | AH68: =+AD68-AG68 -> 834.599 | AI68: =+Y68+AD68 -> 4544.599 | AJ68: =+Z68+AE68 -> 4887.84 | AK68: =+AI68-AJ68 -> -343.241 | AL68: =+AB68+AG68 -> 3710 | AM68: =+AI68-AL68 -> 834.599 | AN68: =+ｶﾞｰﾃﾞﾝ!W67/1000 -> 3853.22 | AO68: 3323.886 | AP68: =+AN68-AO68 -> 529.334 | AQ68: 3601 | AR68: =+AN68-AQ68 -> 252.22 | AS68: =+ﾋﾞｱｶﾞｰﾃﾞﾝ!W67/1000 -> 1920 | AT68: 1930.256 | AU68: =+AS68-AT68 -> -10.256 | AV68: 1329 | AW68: =+AS68-AV68 -> 591 | AX68: =+AN68+AS68 -> 5773.22 | AY68: =+AO68+AT68 -> 5254.142 | AZ68: =+AX68-AY68 -> 519.078 | BA68: =+AQ68+AV68 -> 4930 | BB68: =+AX68-BA68 -> 843.22 | BC68: =+赤れんが!X68/1000 -> 2334.0828 | BD68: =+赤れんが!Z68/1000 -> 1808.5031 | BE68: =+BC68+BD68 -> 4142.5859 | BF68: =+料飲共通!W67/1000 -> 11.5 | BG68: 11.5 | BH68: =+BF68-BG68 -> 0 | BI68: 0 | BJ68: =+BF68-BI68 -> 11.5 | BK68: =+T68+AI68+AX68+BE68+BF68 -> 19967.233 | BL68: =+U68+AJ68+AY68+BG68 -> 14960.047 | BM68: =+BK68-BL68 -> 5007.1859 | BN68: =+W68+AL68+BA68+BI68 -> 14128 | BO68: =+BK68-BN68 -> 5839.2329 | BP68: =+BK68-BE68 -> 15824.647 | BQ68: =+BL68-Z68 -> 14960.047 | BR68: =+BP68-BQ68 -> 864.6 | BS68: =+BN68-AB68 -> 14128 | BT68: =+BP68-BS68 -> 1696.647
C69: 販売促進費 | E69: =+ﾇｰﾍﾞﾙﾌﾟｰｽ!W68/1000 -> 5175.328 | F69: 4398.504 | G69: =+E69-F69 -> 776.824 | H69: 5321 | I69: =+E69-H69 -> -145.672 | J69: =+ｶﾌｪﾙﾎﾟ!W68/1000 -> 160 | K69: 181.733 | L69: =+J69-K69 -> -21.733 | M69: 74 | N69: =+J69-M69 -> 86 | O69: =+ｶﾌｪｾﾚｽﾃ!W68/1000 -> 160 | P69: 226.328 | Q69: =+O69-P69 -> -66.328 | R69: 93 | S69: =+O69-R69 -> 67 | T69: =+E69+J69+O69 -> 5495.328 | U69: =+F69+K69+P69 -> 4806.565 | V69: =+T69-U69 -> 688.763 | W69: =+H69+M69+R69 -> 5488 | X69: =+T69-W69 -> 7.328 | Y69: 0 | Z69: 0 | AA69: =+Y69-Z69 -> 0 | AB69: 0 | AC69: =+Y69-AB69 -> 0 | AD69: =+ｼﾞｭｴﾙｽﾞ!W68/1000 -> 4544.599 | AE69: 4887.84 | AF69: =+AD69-AE69 -> -343.241 | AG69: 3710 | AH69: =+AD69-AG69 -> 834.599 | AI69: =+Y69+AD69 -> 4544.599 | AJ69: =+Z69+AE69 -> 4887.84 | AK69: =+AI69-AJ69 -> -343.241 | AL69: =+AB69+AG69 -> 3710 | AM69: =+AI69-AL69 -> 834.599 | AN69: =+ｶﾞｰﾃﾞﾝ!W68/1000 -> 3853.22 | AO69: 3323.886 | AP69: =+AN69-AO69 -> 529.334 | AQ69: 3601 | AR69: =+AN69-AQ69 -> 252.22 | AS69: =+ﾋﾞｱｶﾞｰﾃﾞﾝ!W68/1000 -> 1920 | AT69: 1930.256 | AU69: =+AS69-AT69 -> -10.256 | AV69: 1329 | AW69: =+AS69-AV69 -> 591 | AX69: =+AN69+AS69 -> 5773.22 | AY69: =+AO69+AT69 -> 5254.142 | AZ69: =+AX69-AY69 -> 519.078 | BA69: =+AQ69+AV69 -> 4930 | BB69: =+AX69-BA69 -> 843.22 | BC69: =+料飲共通!H68/1000 -> 0 | BD69: =+料飲共通!I68/1000 -> 0 | BE69: =+BC69+BD69 -> 0 | BF69: =+料飲共通!W68/1000 -> 11.5 | BG69: 11.5 | BH69: =+BF69-BG69 -> 0 | BI69: 0 | BJ69: =+BF69-BI69 -> 11.5 | BK69: =+T69+AI69+AX69+BE69+BF69 -> 15824.647 | BL69: =+U69+AJ69+AY69+BG69 -> 14960.047 | BM69: =+BK69-BL69 -> 864.6 | BN69: =+W69+AL69+BA69+BI69 -> 14128 | BO69: =+BK69-BN69 -> 1696.647 | BP69: =+BK69-BE69 -> 15824.647 | BQ69: =+BL69-Z69 -> 14960.047 | BR69: =+BP69-BQ69 -> 864.6 | BS69: =+BN69-AB69 -> 14128 | BT69: =+BP69-BS69 -> 1696.647
C70: 乗車券販売手数料 | E70: =+ﾇｰﾍﾞﾙﾌﾟｰｽ!W69/1000 -> 0 | F70: 0 | G70: =+E70-F70 -> 0 | H70: 0 | I70: =+E70-H70 -> 0 | J70: =+ｶﾌｪﾙﾎﾟ!W69/1000 -> 0 | K70: 0 | L70: =+J70-K70 -> 0 | M70: 0 | N70: =+J70-M70 -> 0 | O70: =+ｶﾌｪｾﾚｽﾃ!W69/1000 -> 0 | P70: 0 | Q70: =+O70-P70 -> 0 | R70: 0 | S70: =+O70-R70 -> 0 | T70: =+E70+J70+O70 -> 0 | U70: =+F70+K70+P70 -> 0 | V70: =+T70-U70 -> 0 | W70: =+H70+M70+R70 -> 0 | X70: =+T70-W70 -> 0 | Y70: 0 | Z70: 0 | AA70: =+Y70-Z70 -> 0 | AB70: 0 | AC70: =+Y70-AB70 -> 0 | AD70: =+ｼﾞｭｴﾙｽﾞ!W69/1000 -> 0 | AE70: 0 | AF70: =+AD70-AE70 -> 0 | AG70: 0 | AH70: =+AD70-AG70 -> 0 | AI70: =+Y70+AD70 -> 0 | AJ70: =+Z70+AE70 -> 0 | AK70: =+AI70-AJ70 -> 0 | AL70: =+AB70+AG70 -> 0 | AM70: =+AI70-AL70 -> 0 | AN70: =+ｶﾞｰﾃﾞﾝ!W69/1000 -> 0 | AO70: 0 | AP70: =+AN70-AO70 -> 0 | AQ70: 0 | AR70: =+AN70-AQ70 -> 0 | AS70: =+ﾋﾞｱｶﾞｰﾃﾞﾝ!W69/1000 -> 0 | AT70: 0 | AU70: =+AS70-AT70 -> 0 | AV70: 0 | AW70: =+AS70-AV70 -> 0 | AX70: =+AN70+AS70 -> 0 | AY70: =+AO70+AT70 -> 0 | AZ70: =+AX70-AY70 -> 0 | BA70: =+AQ70+AV70 -> 0 | BB70: =+AX70-BA70 -> 0 | BC70: =+料飲共通!H69/1000 -> 0 | BD70: =+料飲共通!I69/1000 -> 0 | BE70: =+BC70+BD70 -> 0 | BF70: =+料飲共通!W69/1000 -> 0 | BG70: 0 | BH70: =+BF70-BG70 -> 0 | BI70: 0 | BJ70: =+BF70-BI70 -> 0 | BK70: =+T70+AI70+AX70+BE70+BF70 -> 0 | BL70: =+U70+AJ70+AY70+BG70 -> 0 | BM70: =+BK70-BL70 -> 0 | BN70: =+W70+AL70+BA70+BI70 -> 0 | BO70: =+BK70-BN70 -> 0 | BP70: =+BK70-BE70 -> 0 | BQ70: =+BL70-Z70 -> 0 | BR70: =+BP70-BQ70 -> 0 | BS70: =+BN70-AB70 -> 0 | BT70: =+BP70-BS70 -> 0
B71: 旅費交通費 | E71: =+ﾇｰﾍﾞﾙﾌﾟｰｽ!W70/1000 -> 250 | F71: 80.721 | G71: =+E71-F71 -> 169.279 | H71: 36 | I71: =+E71-H71 -> 214 | J71: =+ｶﾌｪﾙﾎﾟ!W70/1000 -> 0 | K71: 0 | L71: =+J71-K71 -> 0 | M71: 0 | N71: =+J71-M71 -> 0 | O71: =+ｶﾌｪｾﾚｽﾃ!W70/1000 -> 0 | P71: 0 | Q71: =+O71-P71 -> 0 | R71: 0 | S71: =+O71-R71 -> 0 | T71: =+E71+J71+O71 -> 250 | U71: =+F71+K71+P71 -> 80.721 | V71: =+T71-U71 -> 169.279 | W71: =+H71+M71+R71 -> 36 | X71: =+T71-W71 -> 214 | Y71: 0 | Z71: 0 | AA71: =+Y71-Z71 -> 0 | AB71: 0 | AC71: =+Y71-AB71 -> 0 | AD71: =+ｼﾞｭｴﾙｽﾞ!W70/1000 -> 129 | AE71: 97.238 | AF71: =+AD71-AE71 -> 31.762 | AG71: 56 | AH71: =+AD71-AG71 -> 73 | AI71: =+Y71+AD71 -> 129 | AJ71: =+Z71+AE71 -> 97.238 | AK71: =+AI71-AJ71 -> 31.762 | AL71: =+AB71+AG71 -> 56 | AM71: =+AI71-AL71 -> 73 | AN71: =+ｶﾞｰﾃﾞﾝ!W70/1000 -> 182.728 | AO71: 279.23 | AP71: =+AN71-AO71 -> -96.502 | AQ71: 29 | AR71: =+AN71-AQ71 -> 153.728 | AS71: =+ﾋﾞｱｶﾞｰﾃﾞﾝ!W70/1000 -> 0 | AT71: 0 | AU71: =+AS71-AT71 -> 0 | AV71: 0 | AW71: =+AS71-AV71 -> 0 | AX71: =+AN71+AS71 -> 182.728 | AY71: =+AO71+AT71 -> 279.23 | AZ71: =+AX71-AY71 -> -96.502 | BA71: =+AQ71+AV71 -> 29 | BB71: =+AX71-BA71 -> 153.728 | BC71: =+赤れんが!X71/1000 -> 0 | BD71: =+赤れんが!Z71/1000 -> 0 | BE71: =+BC71+BD71 -> 0 | BF71: =+料飲共通!W70/1000 -> 818 | BG71: 576.535 | BH71: =+BF71-BG71 -> 241.465 | BI71: 111 | BJ71: =+BF71-BI71 -> 707 | BK71: =+T71+AI71+AX71+BE71+BF71 -> 1379.728 | BL71: =+U71+AJ71+AY71+BG71 -> 1033.724 | BM71: =+BK71-BL71 -> 346.004 | BN71: =+W71+AL71+BA71+BI71 -> 232 | BO71: =+BK71-BN71 -> 1147.728 | BP71: =+BK71-BE71 -> 1379.728 | BQ71: =+BL71-Z71 -> 1033.724 | BR71: =+BP71-BQ71 -> 346.004 | BS71: =+BN71-AB71 -> 232 | BT71: =+BP71-BS71 -> 1147.728
B72: 通信連絡費 | E72: =+ﾇｰﾍﾞﾙﾌﾟｰｽ!W71/1000 -> 362.6 | F72: 328.707 | G72: =+E72-F72 -> 33.893 | H72: 374 | I72: =+E72-H72 -> -11.4 | J72: =+ｶﾌｪﾙﾎﾟ!W71/1000 -> 500 | K72: 524.735 | L72: =+J72-K72 -> -24.735 | M72: 291 | N72: =+J72-M72 -> 209 | O72: =+ｶﾌｪｾﾚｽﾃ!W71/1000 -> 58.109 | P72: 57.43 | Q72: =+O72-P72 -> 0.679 | R72: 87 | S72: =+O72-R72 -> -28.891 | T72: =+E72+J72+O72 -> 920.709 | U72: =+F72+K72+P72 -> 910.872 | V72: =+T72-U72 -> 9.837 | W72: =+H72+M72+R72 -> 752 | X72: =+T72-W72 -> 168.709 | Y72: 0 | Z72: 0 | AA72: =+Y72-Z72 -> 0 | AB72: 34 | AC72: =+Y72-AB72 -> -34 | AD72: =+ｼﾞｭｴﾙｽﾞ!W71/1000 -> 1275.8 | AE72: 1233.747 | AF72: =+AD72-AE72 -> 42.053 | AG72: 1208 | AH72: =+AD72-AG72 -> 67.8 | AI72: =+Y72+AD72 -> 1275.8 | AJ72: =+Z72+AE72 -> 1233.747 | AK72: =+AI72-AJ72 -> 42.053 | AL72: =+AB72+AG72 -> 1242 | AM72: =+AI72-AL72 -> 33.8 | AN72: =+ｶﾞｰﾃﾞﾝ!W71/1000 -> 808.55 | AO72: 815.112 | AP72: =+AN72-AO72 -> -6.562 | AQ72: 803 | AR72: =+AN72-AQ72 -> 5.55 | AS72: =+ﾋﾞｱｶﾞｰﾃﾞﾝ!W71/1000 -> 77.764 | AT72: 140.818 | AU72: =+AS72-AT72 -> -63.054 | AV72: 140 | AW72: =+AS72-AV72 -> -62.236 | AX72: =+AN72+AS72 -> 886.314 | AY72: =+AO72+AT72 -> 955.93 | AZ72: =+AX72-AY72 -> -69.616 | BA72: =+AQ72+AV72 -> 943 | BB72: =+AX72-BA72 -> -56.686 | BC72: =+赤れんが!X72/1000 -> 461.89095 | BD72: =+赤れんが!Z72/1000 -> 196.50123 | BE72: =+BC72+BD72 -> 658.39218 | BF72: =+料飲共通!W71/1000 -> 189.6 | BG72: 159.353 | BH72: =+BF72-BG72 -> 30.247 | BI72: 62 | BJ72: =+BF72-BI72 -> 127.6 | BK72: =+T72+AI72+AX72+BE72+BF72 -> 3930.8152 | BL72: =+U72+AJ72+AY72+BG72 -> 3259.902 | BM72: =+BK72-BL72 -> 670.91318 | BN72: =+W72+AL72+BA72+BI72 -> 2999 | BO72: =+BK72-BN72 -> 931.81518 | BP72: =+BK72-BE72 -> 3272.423 | BQ72: =+BL72-Z72 -> 3259.902 | BR72: =+BP72-BQ72 -> 12.521 | BS72: =+BN72-AB72 -> 2965 | BT72: =+BP72-BS72 -> 307.423
B73: 水道光熱費 | E73: =+ﾇｰﾍﾞﾙﾌﾟｰｽ!W72/1000 -> 8670.711 | F73: 8738.934 | G73: =+E73-F73 -> -68.223 | H73: 8860 | I73: =+E73-H73 -> -189.289 | J73: =+ｶﾌｪﾙﾎﾟ!W72/1000 -> 1238.495 | K73: 1248.433 | L73: =+J73-K73 -> -9.938 | M73: 1242 | N73: =+J73-M73 -> -3.505 | O73: =+ｶﾌｪｾﾚｽﾃ!W72/1000 -> 0 | P73: 0 | Q73: =+O73-P73 -> 0 | R73: 0 | S73: =+O73-R73 -> 0 | T73: =+E73+J73+O73 -> 9909.206 | U73: =+F73+K73+P73 -> 9987.367 | V73: =+T73-U73 -> -78.161 | W73: =+H73+M73+R73 -> 10102 | X73: =+T73-W73 -> -192.794 | Y73: 0 | Z73: 0 | AA73: =+Y73-Z73 -> 0 | AB73: 1766 | AC73: =+Y73-AB73 -> -1766 | AD73: =+ｼﾞｭｴﾙｽﾞ!W72/1000 -> 4240 | AE73: 4587.879 | AF73: =+AD73-AE73 -> -347.879 | AG73: 4090 | AH73: =+AD73-AG73 -> 150 | AI73: =+Y73+AD73 -> 4240 | AJ73: =+Z73+AE73 -> 4587.879 | AK73: =+AI73-AJ73 -> -347.879 | AL73: =+AB73+AG73 -> 5856 | AM73: =+AI73-AL73 -> -1616 | AN73: =+ｶﾞｰﾃﾞﾝ!W72/1000 -> 5040 | AO73: 5003.9 | AP73: =+AN73-AO73 -> 36.1 | AQ73: 5282 | AR73: =+AN73-AQ73 -> -242 | AS73: =+ﾋﾞｱｶﾞｰﾃﾞﾝ!W72/1000 -> 890 | AT73: 836.447 | AU73: =+AS73-AT73 -> 53.553 | AV73: 435 | AW73: =+AS73-AV73 -> 455 | AX73: =+AN73+AS73 -> 5930 | AY73: =+AO73+AT73 -> 5840.347 | AZ73: =+AX73-AY73 -> 89.653 | BA73: =+AQ73+AV73 -> 5717 | BB73: =+AX73-BA73 -> 213 | BC73: =+赤れんが!X73/1000 -> 2703.61 | BD73: =+赤れんが!Z73/1000 -> 1457.26 | BE73: =+BC73+BD73 -> 4160.87 | BF73: =+料飲共通!W72/1000 -> 0 | BG73: 0 | BH73: =+BF73-BG73 -> 0 | BI73: 0 | BJ73: =+BF73-BI73 -> 0 | BK73: =+T73+AI73+AX73+BE73+BF73 -> 24240.076 | BL73: =+U73+AJ73+AY73+BG73 -> 20415.593 | BM73: =+BK73-BL73 -> 3824.483 | BN73: =+W73+AL73+BA73+BI73 -> 21675 | BO73: =+BK73-BN73 -> 2565.076 | BP73: =+BK73-BE73 -> 20079.206 | BQ73: =+BL73-Z73 -> 20415.593 | BR73: =+BP73-BQ73 -> -336.387 | BS73: =+BN73-AB73 -> 19909 | BT73: =+BP73-BS73 -> 170.206
C74: 電灯使用料 | E74: =+ﾇｰﾍﾞﾙﾌﾟｰｽ!W73/1000 -> 4679.99 | F74: 4698.583 | G74: =+E74-F74 -> -18.593 | H74: 5067 | I74: =+E74-H74 -> -387.01 | J74: =+ｶﾌｪﾙﾎﾟ!W73/1000 -> 668.571 | K74: 671.228 | L74: =+J74-K74 -> -2.657 | M74: 679 | N74: =+J74-M74 -> -10.429 | O74: =+ｶﾌｪｾﾚｽﾃ!W73/1000 -> 0 | P74: 0 | Q74: =+O74-P74 -> 0 | R74: 0 | S74: =+O74-R74 -> 0 | T74: =+E74+J74+O74 -> 5348.561 | U74: =+F74+K74+P74 -> 5369.811 | V74: =+T74-U74 -> -21.25 | W74: =+H74+M74+R74 -> 5746 | X74: =+T74-W74 -> -397.439 | Y74: 0 | Z74: 0 | AA74: =+Y74-Z74 -> 0 | AB74: 440 | AC74: =+Y74-AB74 -> -440 | AD74: =+ｼﾞｭｴﾙｽﾞ!W73/1000 -> 3750 | AE74: 4109.295 | AF74: =+AD74-AE74 -> -359.295 | AG74: 3640 | AH74: =+AD74-AG74 -> 110 | AI74: =+Y74+AD74 -> 3750 | AJ74: =+Z74+AE74 -> 4109.295 | AK74: =+AI74-AJ74 -> -359.295 | AL74: =+AB74+AG74 -> 4080 | AM74: =+AI74-AL74 -> -330 | AN74: =+ｶﾞｰﾃﾞﾝ!W73/1000 -> 3600 | AO74: 3394.806 | AP74: =+AN74-AO74 -> 205.194 | AQ74: 3600 | AR74: =+AN74-AQ74 -> 0 | AS74: =+ﾋﾞｱｶﾞｰﾃﾞﾝ!W73/1000 -> 525 | AT74: 491.906 | AU74: =+AS74-AT74 -> 33.094 | AV74: 300 | AW74: =+AS74-AV74 -> 225 | AX74: =+AN74+AS74 -> 4125 | AY74: =+AO74+AT74 -> 3886.712 | AZ74: =+AX74-AY74 -> 238.288 | BA74: =+AQ74+AV74 -> 3900 | BB74: =+AX74-BA74 -> 225 | BC74: =+料飲共通!H73/1000 -> 0 | BD74: =+料飲共通!I73/1000 -> 0 | BE74: =+BC74+BD74 -> 0 | BF74: =+料飲共通!W73/1000 -> 0 | BG74: 0 | BH74: =+BF74-BG74 -> 0 | BI74: 0 | BJ74: =+BF74-BI74 -> 0 | BK74: =+T74+AI74+AX74+BE74+BF74 -> 13223.561 | BL74: =+U74+AJ74+AY74+BG74 -> 13365.818 | BM74: =+BK74-BL74 -> -142.257 | BN74: =+W74+AL74+BA74+BI74 -> 13726 | BO74: =+BK74-BN74 -> -502.439 | BP74: =+BK74-BE74 -> 13223.561 | BQ74: =+BL74-Z74 -> 13365.818 | BR74: =+BP74-BQ74 -> -142.257 | BS74: =+BN74-AB74 -> 13286 | BT74: =+BP74-BS74 -> -62.439
C75: 水道使用料 | E75: =+ﾇｰﾍﾞﾙﾌﾟｰｽ!W74/1000 -> 549.415 | F75: 613.869 | G75: =+E75-F75 -> -64.454 | H75: 543 | I75: =+E75-H75 -> 6.415 | J75: =+ｶﾌｪﾙﾎﾟ!W74/1000 -> 78.299 | K75: 87.695 | L75: =+J75-K75 -> -9.396 | M75: 62 | N75: =+J75-M75 -> 16.299 | O75: =+ｶﾌｪｾﾚｽﾃ!W74/1000 -> 0 | P75: 0 | Q75: =+O75-P75 -> 0 | R75: 0 | S75: =+O75-R75 -> 0 | T75: =+E75+J75+O75 -> 627.714 | U75: =+F75+K75+P75 -> 701.564 | V75: =+T75-U75 -> -73.85 | W75: =+H75+M75+R75 -> 605 | X75: =+T75-W75 -> 22.714 | Y75: 0 | Z75: 0 | AA75: =+Y75-Z75 -> 0 | AB75: 672 | AC75: =+Y75-AB75 -> -672 | AD75: =+ｼﾞｭｴﾙｽﾞ!W74/1000 -> 490 | AE75: 478.584 | AF75: =+AD75-AE75 -> 11.416 | AG75: 450 | AH75: =+AD75-AG75 -> 40 | AI75: =+Y75+AD75 -> 490 | AJ75: =+Z75+AE75 -> 478.584 | AK75: =+AI75-AJ75 -> 11.416 | AL75: =+AB75+AG75 -> 1122 | AM75: =+AI75-AL75 -> -632 | AN75: =+ｶﾞｰﾃﾞﾝ!W74/1000 -> 720 | AO75: 619.57 | AP75: =+AN75-AO75 -> 100.43 | AQ75: 780 | AR75: =+AN75-AQ75 -> -60 | AS75: =+ﾋﾞｱｶﾞｰﾃﾞﾝ!W74/1000 -> 215 | AT75: 206.741 | AU75: =+AS75-AT75 -> 8.259 | AV75: 135 | AW75: =+AS75-AV75 -> 80 | AX75: =+AN75+AS75 -> 935 | AY75: =+AO75+AT75 -> 826.311 | AZ75: =+AX75-AY75 -> 108.689 | BA75: =+AQ75+AV75 -> 915 | BB75: =+AX75-BA75 -> 20 | BC75: =+料飲共通!H74/1000 -> 0 | BD75: =+料飲共通!I74/1000 -> 0 | BE75: =+BC75+BD75 -> 0 | BF75: =+料飲共通!W74/1000 -> 0 | BG75: 0 | BH75: =+BF75-BG75 -> 0 | BI75: 0 | BJ75: =+BF75-BI75 -> 0 | BK75: =+T75+AI75+AX75+BE75+BF75 -> 2052.714 | BL75: =+U75+AJ75+AY75+BG75 -> 2006.459 | BM75: =+BK75-BL75 -> 46.255 | BN75: =+W75+AL75+BA75+BI75 -> 2642 | BO75: =+BK75-BN75 -> -589.286 | BP75: =+BK75-BE75 -> 2052.714 | BQ75: =+BL75-Z75 -> 2006.459 | BR75: =+BP75-BQ75 -> 46.255 | BS75: =+BN75-AB75 -> 1970 | BT75: =+BP75-BS75 -> 82.714
C76: ガス使用料 | E76: =+ﾇｰﾍﾞﾙﾌﾟｰｽ!W75/1000 -> 3441.306 | F76: 3426.482 | G76: =+E76-F76 -> 14.824 | H76: 3250 | I76: =+E76-H76 -> 191.306 | J76: =+ｶﾌｪﾙﾎﾟ!W75/1000 -> 491.625 | K76: 489.51 | L76: =+J76-K76 -> 2.115 | M76: 0 | N76: =+J76-M76 -> 491.625 | O76: =+ｶﾌｪｾﾚｽﾃ!W75/1000 -> 0 | P76: 0 | Q76: =+O76-P76 -> 0 | R76: 0 | S76: =+O76-R76 -> 0 | T76: =+E76+J76+O76 -> 3932.931 | U76: =+F76+K76+P76 -> 3915.992 | V76: =+T76-U76 -> 16.939 | W76: =+H76+M76+R76 -> 3250 | X76: =+T76-W76 -> 682.931 | Y76: 0 | Z76: 0 | AA76: =+Y76-Z76 -> 0 | AB76: 276 | AC76: =+Y76-AB76 -> -276 | AD76: =+ｼﾞｭｴﾙｽﾞ!W75/1000 -> 0 | AE76: 0 | AF76: =+AD76-AE76 -> 0 | AG76: 0 | AH76: =+AD76-AG76 -> 0 | AI76: =+Y76+AD76 -> 0 | AJ76: =+Z76+AE76 -> 0 | AK76: =+AI76-AJ76 -> 0 | AL76: =+AB76+AG76 -> 276 | AM76: =+AI76-AL76 -> -276 | AN76: =+ｶﾞｰﾃﾞﾝ!W75/1000 -> 720 | AO76: 989.524 | AP76: =+AN76-AO76 -> -269.524 | AQ76: 902 | AR76: =+AN76-AQ76 -> -182 | AS76: =+ﾋﾞｱｶﾞｰﾃﾞﾝ!W75/1000 -> 150 | AT76: 137.8 | AU76: =+AS76-AT76 -> 12.2 | AV76: 0 | AW76: =+AS76-AV76 -> 150 | AX76: =+AN76+AS76 -> 870 | AY76: =+AO76+AT76 -> 1127.324 | AZ76: =+AX76-AY76 -> -257.324 | BA76: =+AQ76+AV76 -> 902 | BB76: =+AX76-BA76 -> -32 | BC76: =+料飲共通!H75/1000 -> 0 | BD76: =+料飲共通!I75/1000 -> 0 | BE76: =+BC76+BD76 -> 0 | BF76: =+料飲共通!W75/1000 -> 0 | BG76: 0 | BH76: =+BF76-BG76 -> 0 | BI76: 0 | BJ76: =+BF76-BI76 -> 0 | BK76: =+T76+AI76+AX76+BE76+BF76 -> 4802.931 | BL76: =+U76+AJ76+AY76+BG76 -> 5043.316 | BM76: =+BK76-BL76 -> -240.385 | BN76: =+W76+AL76+BA76+BI76 -> 4428 | BO76: =+BK76-BN76 -> 374.931 | BP76: =+BK76-BE76 -> 4802.931 | BQ76: =+BL76-Z76 -> 5043.316 | BR76: =+BP76-BQ76 -> -240.385 | BS76: =+BN76-AB76 -> 4152 | BT76: =+BP76-BS76 -> 650.931
C77: 暖房燃料費 | E77: =+ﾇｰﾍﾞﾙﾌﾟｰｽ!W76/1000 -> 0 | F77: 0 | G77: =+E77-F77 -> 0 | H77: 0 | I77: =+E77-H77 -> 0 | J77: =+ｶﾌｪﾙﾎﾟ!W76/1000 -> 0 | K77: 0 | L77: =+J77-K77 -> 0 | M77: 500 | N77: =+J77-M77 -> -500 | O77: =+ｶﾌｪｾﾚｽﾃ!W76/1000 -> 0 | P77: 0 | Q77: =+O77-P77 -> 0 | R77: 0 | S77: =+O77-R77 -> 0 | T77: =+E77+J77+O77 -> 0 | U77: =+F77+K77+P77 -> 0 | V77: =+T77-U77 -> 0 | W77: =+H77+M77+R77 -> 500 | X77: =+T77-W77 -> -500 | Y77: 0 | Z77: 0 | AA77: =+Y77-Z77 -> 0 | AB77: 377 | AC77: =+Y77-AB77 -> -377 | AD77: =+ｼﾞｭｴﾙｽﾞ!W76/1000 -> 0 | AE77: 0 | AF77: =+AD77-AE77 -> 0 | AG77: 0 | AH77: =+AD77-AG77 -> 0 | AI77: =+Y77+AD77 -> 0 | AJ77: =+Z77+AE77 -> 0 | AK77: =+AI77-AJ77 -> 0 | AL77: =+AB77+AG77 -> 377 | AM77: =+AI77-AL77 -> -377 | AN77: =+ｶﾞｰﾃﾞﾝ!W76/1000 -> 0 | AO77: 0 | AP77: =+AN77-AO77 -> 0 | AQ77: 0 | AR77: =+AN77-AQ77 -> 0 | AS77: =+ﾋﾞｱｶﾞｰﾃﾞﾝ!W76/1000 -> 0 | AT77: 0 | AU77: =+AS77-AT77 -> 0 | AV77: 0 | AW77: =+AS77-AV77 -> 0 | AX77: =+AN77+AS77 -> 0 | AY77: =+AO77+AT77 -> 0 | AZ77: =+AX77-AY77 -> 0 | BA77: =+AQ77+AV77 -> 0 | BB77: =+AX77-BA77 -> 0 | BC77: =+料飲共通!H76/1000 -> 0 | BD77: =+料飲共通!I76/1000 -> 0 | BE77: =+BC77+BD77 -> 0 | BF77: =+料飲共通!W76/1000 -> 0 | BG77: 0 | BH77: =+BF77-BG77 -> 0 | BI77: 0 | BJ77: =+BF77-BI77 -> 0 | BK77: =+T77+AI77+AX77+BE77+BF77 -> 0 | BL77: =+U77+AJ77+AY77+BG77 -> 0 | BM77: =+BK77-BL77 -> 0 | BN77: =+W77+AL77+BA77+BI77 -> 877 | BO77: =+BK77-BN77 -> -877 | BP77: =+BK77-BE77 -> 0 | BQ77: =+BL77-Z77 -> 0 | BR77: =+BP77-BQ77 -> 0 | BS77: =+BN77-AB77 -> 500 | BT77: =+BP77-BS77 -> -500
C78: 電力使用料 | E78: =+ﾇｰﾍﾞﾙﾌﾟｰｽ!W77/1000 -> 0 | F78: 0 | G78: =+E78-F78 -> 0 | H78: 0 | I78: =+E78-H78 -> 0 | J78: =+ｶﾌｪﾙﾎﾟ!W77/1000 -> 0 | K78: 0 | L78: =+J78-K78 -> 0 | M78: 0 | N78: =+J78-M78 -> 0 | O78: =+ｶﾌｪｾﾚｽﾃ!W77/1000 -> 0 | P78: 0 | Q78: =+O78-P78 -> 0 | R78: 0 | S78: =+O78-R78 -> 0 | T78: =+E78+J78+O78 -> 0 | U78: =+F78+K78+P78 -> 0 | V78: =+T78-U78 -> 0 | W78: =+H78+M78+R78 -> 0 | X78: =+T78-W78 -> 0 | Y78: 0 | Z78: 0 | AA78: =+Y78-Z78 -> 0 | AB78: 0 | AC78: =+Y78-AB78 -> 0 | AD78: =+ｼﾞｭｴﾙｽﾞ!W77/1000 -> 0 | AE78: 0 | AF78: =+AD78-AE78 -> 0 | AG78: 0 | AH78: =+AD78-AG78 -> 0 | AI78: =+Y78+AD78 -> 0 | AJ78: =+Z78+AE78 -> 0 | AK78: =+AI78-AJ78 -> 0 | AL78: =+AB78+AG78 -> 0 | AM78: =+AI78-AL78 -> 0 | AN78: =+ｶﾞｰﾃﾞﾝ!W77/1000 -> 0 | AO78: 0 | AP78: =+AN78-AO78 -> 0 | AQ78: 0 | AR78: =+AN78-AQ78 -> 0 | AS78: =+ﾋﾞｱｶﾞｰﾃﾞﾝ!W77/1000 -> 0 | AT78: 0 | AU78: =+AS78-AT78 -> 0 | AV78: 0 | AW78: =+AS78-AV78 -> 0 | AX78: =+AN78+AS78 -> 0 | AY78: =+AO78+AT78 -> 0 | AZ78: =+AX78-AY78 -> 0 | BA78: =+AQ78+AV78 -> 0 | BB78: =+AX78-BA78 -> 0 | BC78: =+料飲共通!H77/1000 -> 0 | BD78: =+料飲共通!I77/1000 -> 0 | BE78: =+BC78+BD78 -> 0 | BF78: =+料飲共通!W77/1000 -> 0 | BG78: 0 | BH78: =+BF78-BG78 -> 0 | BI78: 0 | BJ78: =+BF78-BI78 -> 0 | BK78: =+T78+AI78+AX78+BE78+BF78 -> 0 | BL78: =+U78+AJ78+AY78+BG78 -> 0 | BM78: =+BK78-BL78 -> 0 | BN78: =+W78+AL78+BA78+BI78 -> 0 | BO78: =+BK78-BN78 -> 0 | BP78: =+BK78-BE78 -> 0 | BQ78: =+BL78-Z78 -> 0 | BR78: =+BP78-BQ78 -> 0 | BS78: =+BN78-AB78 -> 0 | BT78: =+BP78-BS78 -> 0
B79: 諸手数料 | E79: =+ﾇｰﾍﾞﾙﾌﾟｰｽ!W78/1000 -> 29.716 | F79: 26.716 | G79: =+E79-F79 -> 3 | H79: 30 | I79: =+E79-H79 -> -0.284 | J79: =+ｶﾌｪﾙﾎﾟ!W78/1000 -> 0 | K79: 0 | L79: =+J79-K79 -> 0 | M79: 0 | N79: =+J79-M79 -> 0 | O79: =+ｶﾌｪｾﾚｽﾃ!W78/1000 -> 0 | P79: 0 | Q79: =+O79-P79 -> 0 | R79: 0 | S79: =+O79-R79 -> 0 | T79: =+E79+J79+O79 -> 29.716 | U79: =+F79+K79+P79 -> 26.716 | V79: =+T79-U79 -> 3 | W79: =+H79+M79+R79 -> 30 | X79: =+T79-W79 -> -0.284 | Y79: 0 | Z79: 0 | AA79: =+Y79-Z79 -> 0 | AB79: 0 | AC79: =+Y79-AB79 -> 0 | AD79: =+ｼﾞｭｴﾙｽﾞ!W78/1000 -> 18 | AE79: 21.081 | AF79: =+AD79-AE79 -> -3.081 | AG79: 12 | AH79: =+AD79-AG79 -> 6 | AI79: =+Y79+AD79 -> 18 | AJ79: =+Z79+AE79 -> 21.081 | AK79: =+AI79-AJ79 -> -3.081 | AL79: =+AB79+AG79 -> 12 | AM79: =+AI79-AL79 -> 6 | AN79: =+ｶﾞｰﾃﾞﾝ!W78/1000 -> 42 | AO79: 30.462 | AP79: =+AN79-AO79 -> 11.538 | AQ79: 15 | AR79: =+AN79-AQ79 -> 27 | AS79: =+ﾋﾞｱｶﾞｰﾃﾞﾝ!W78/1000 -> 17.7 | AT79: 0.2 | AU79: =+AS79-AT79 -> 17.5 | AV79: 17 | AW79: =+AS79-AV79 -> 0.7 | AX79: =+AN79+AS79 -> 59.7 | AY79: =+AO79+AT79 -> 30.662 | AZ79: =+AX79-AY79 -> 29.038 | BA79: =+AQ79+AV79 -> 32 | BB79: =+AX79-BA79 -> 27.7 | BC79: =+赤れんが!X79/1000 -> 17.261582 | BD79: =+赤れんが!Z79/1000 -> 0 | BE79: =+BC79+BD79 -> 17.261582 | BF79: =+料飲共通!W78/1000 -> 0 | BG79: 0 | BH79: =+BF79-BG79 -> 0 | BI79: 0 | BJ79: =+BF79-BI79 -> 0 | BK79: =+T79+AI79+AX79+BE79+BF79 -> 124.67758 | BL79: =+U79+AJ79+AY79+BG79 -> 78.459 | BM79: =+BK79-BL79 -> 46.218582 | BN79: =+W79+AL79+BA79+BI79 -> 74 | BO79: =+BK79-BN79 -> 50.677582 | BP79: =+BK79-BE79 -> 107.416 | BQ79: =+BL79-Z79 -> 78.459 | BR79: =+BP79-BQ79 -> 28.957 | BS79: =+BN79-AB79 -> 74 | BT79: =+BP79-BS79 -> 33.416
B80: 広告宣伝費 | E80: =+ﾇｰﾍﾞﾙﾌﾟｰｽ!W79/1000 -> 2420 | F80: 3845.336 | G80: =+E80-F80 -> -1425.336 | H80: 2956 | I80: =+E80-H80 -> -536 | J80: =+ｶﾌｪﾙﾎﾟ!W79/1000 -> 70 | K80: 68 | L80: =+J80-K80 -> 2 | M80: 0 | N80: =+J80-M80 -> 70 | O80: =+ｶﾌｪｾﾚｽﾃ!W79/1000 -> 0 | P80: 0 | Q80: =+O80-P80 -> 0 | R80: 88 | S80: =+O80-R80 -> -88 | T80: =+E80+J80+O80 -> 2490 | U80: =+F80+K80+P80 -> 3913.336 | V80: =+T80-U80 -> -1423.336 | W80: =+H80+M80+R80 -> 3044 | X80: =+T80-W80 -> -554 | Y80: 0 | Z80: 0 | AA80: =+Y80-Z80 -> 0 | AB80: 0 | AC80: =+Y80-AB80 -> 0 | AD80: =+ｼﾞｭｴﾙｽﾞ!W79/1000 -> 2420 | AE80: 4075.634 | AF80: =+AD80-AE80 -> -1655.634 | AG80: 2435 | AH80: =+AD80-AG80 -> -15 | AI80: =+Y80+AD80 -> 2420 | AJ80: =+Z80+AE80 -> 4075.634 | AK80: =+AI80-AJ80 -> -1655.634 | AL80: =+AB80+AG80 -> 2435 | AM80: =+AI80-AL80 -> -15 | AN80: =+ｶﾞｰﾃﾞﾝ!W79/1000 -> 2480 | AO80: 1744.067 | AP80: =+AN80-AO80 -> 735.933 | AQ80: 5040 | AR80: =+AN80-AQ80 -> -2560 | AS80: =+ﾋﾞｱｶﾞｰﾃﾞﾝ!W79/1000 -> 1850 | AT80: 644.852 | AU80: =+AS80-AT80 -> 1205.148 | AV80: 380 | AW80: =+AS80-AV80 -> 1470 | AX80: =+AN80+AS80 -> 4330 | AY80: =+AO80+AT80 -> 2388.919 | AZ80: =+AX80-AY80 -> 1941.081 | BA80: =+AQ80+AV80 -> 5420 | BB80: =+AX80-BA80 -> -1090 | BC80: 0 | BD80: 0 | BE80: =+BC80+BD80 -> 0 | BF80: =+料飲共通!W79/1000 -> 400 | BG80: 3992.1 | BH80: =+BF80-BG80 -> -3592.1 | BI80: 0 | BJ80: =+BF80-BI80 -> 400 | BK80: =+T80+AI80+AX80+BE80+BF80 -> 9640 | BL80: =+U80+AJ80+AY80+BG80 -> 14369.989 | BM80: =+BK80-BL80 -> -4729.989 | BN80: =+W80+AL80+BA80+BI80 -> 10899 | BO80: =+BK80-BN80 -> -1259 | BP80: =+BK80-BE80 -> 9640 | BQ80: =+BL80-Z80 -> 14369.989 | BR80: =+BP80-BQ80 -> -4729.989 | BS80: =+BN80-AB80 -> 10899 | BT80: =+BP80-BS80 -> -1259
B81: 交際費 | E81: =+ﾇｰﾍﾞﾙﾌﾟｰｽ!W80/1000 -> 0 | F81: 0 | G81: =+E81-F81 -> 0 | H81: 0 | I81: =+E81-H81 -> 0 | J81: =+ｶﾌｪﾙﾎﾟ!W80/1000 -> 0 | K81: 0 | L81: =+J81-K81 -> 0 | M81: 0 | N81: =+J81-M81 -> 0 | O81: =+ｶﾌｪｾﾚｽﾃ!W80/1000 -> 0 | P81: 0 | Q81: =+O81-P81 -> 0 | R81: 0 | S81: =+O81-R81 -> 0 | T81: =+E81+J81+O81 -> 0 | U81: =+F81+K81+P81 -> 0 | V81: =+T81-U81 -> 0 | W81: =+H81+M81+R81 -> 0 | X81: =+T81-W81 -> 0 | Y81: 0 | Z81: 0 | AA81: =+Y81-Z81 -> 0 | AB81: 0 | AC81: =+Y81-AB81 -> 0 | AD81: =+ｼﾞｭｴﾙｽﾞ!W80/1000 -> 0 | AE81: 0 | AF81: =+AD81-AE81 -> 0 | AG81: 0 | AH81: =+AD81-AG81 -> 0 | AI81: =+Y81+AD81 -> 0 | AJ81: =+Z81+AE81 -> 0 | AK81: =+AI81-AJ81 -> 0 | AL81: =+AB81+AG81 -> 0 | AM81: =+AI81-AL81 -> 0 | AN81: =+ｶﾞｰﾃﾞﾝ!W80/1000 -> 0 | AO81: 0 | AP81: =+AN81-AO81 -> 0 | AQ81: 0 | AR81: =+AN81-AQ81 -> 0 | AS81: =+ﾋﾞｱｶﾞｰﾃﾞﾝ!W80/1000 -> 0 | AT81: 0 | AU81: =+AS81-AT81 -> 0 | AV81: 0 | AW81: =+AS81-AV81 -> 0 | AX81: =+AN81+AS81 -> 0 | AY81: =+AO81+AT81 -> 0 | AZ81: =+AX81-AY81 -> 0 | BA81: =+AQ81+AV81 -> 0 | BB81: =+AX81-BA81 -> 0 | BC81: 0 | BD81: 0 | BE81: =+BC81+BD81 -> 0 | BF81: =+料飲共通!W80/1000 -> 40 | BG81: 15.489 | BH81: =+BF81-BG81 -> 24.511 | BI81: 0 | BJ81: =+BF81-BI81 -> 40 | BK81: =+T81+AI81+AX81+BE81+BF81 -> 40 | BL81: =+U81+AJ81+AY81+BG81 -> 15.489 | BM81: =+BK81-BL81 -> 24.511 | BN81: =+W81+AL81+BA81+BI81 -> 0 | BO81: =+BK81-BN81 -> 40 | BP81: =+BK81-BE81 -> 40 | BQ81: =+BL81-Z81 -> 15.489 | BR81: =+BP81-BQ81 -> 24.511 | BS81: =+BN81-AB81 -> 0 | BT81: =+BP81-BS81 -> 40
C82: 接待交際費 | E82: =+ﾇｰﾍﾞﾙﾌﾟｰｽ!W81/1000 -> 0 | F82: 0 | G82: =+E82-F82 -> 0 | H82: 0 | I82: =+E82-H82 -> 0 | J82: =+ｶﾌｪﾙﾎﾟ!W81/1000 -> 0 | K82: 0 | L82: =+J82-K82 -> 0 | M82: 0 | N82: =+J82-M82 -> 0 | O82: =+ｶﾌｪｾﾚｽﾃ!W81/1000 -> 0 | P82: 0 | Q82: =+O82-P82 -> 0 | R82: 0 | S82: =+O82-R82 -> 0 | T82: =+E82+J82+O82 -> 0 | U82: =+F82+K82+P82 -> 0 | V82: =+T82-U82 -> 0 | W82: =+H82+M82+R82 -> 0 | X82: =+T82-W82 -> 0 | Y82: 0 | Z82: 0 | AA82: =+Y82-Z82 -> 0 | AB82: 0 | AC82: =+Y82-AB82 -> 0 | AD82: =+ｼﾞｭｴﾙｽﾞ!W81/1000 -> 0 | AE82: 0 | AF82: =+AD82-AE82 -> 0 | AG82: 0 | AH82: =+AD82-AG82 -> 0 | AI82: =+Y82+AD82 -> 0 | AJ82: =+Z82+AE82 -> 0 | AK82: =+AI82-AJ82 -> 0 | AL82: =+AB82+AG82 -> 0 | AM82: =+AI82-AL82 -> 0 | AN82: =+ｶﾞｰﾃﾞﾝ!W81/1000 -> 0 | AO82: 0 | AP82: =+AN82-AO82 -> 0 | AQ82: 0 | AR82: =+AN82-AQ82 -> 0 | AS82: =+ﾋﾞｱｶﾞｰﾃﾞﾝ!W81/1000 -> 0 | AT82: 0 | AU82: =+AS82-AT82 -> 0 | AV82: 0 | AW82: =+AS82-AV82 -> 0 | AX82: =+AN82+AS82 -> 0 | AY82: =+AO82+AT82 -> 0 | AZ82: =+AX82-AY82 -> 0 | BA82: =+AQ82+AV82 -> 0 | BB82: =+AX82-BA82 -> 0 | BC82: =+料飲共通!H81/1000 -> 0 | BD82: =+料飲共通!I81/1000 -> 0 | BE82: =+BC82+BD82 -> 0 | BF82: =+料飲共通!W81/1000 -> 40 | BG82: 15.489 | BH82: =+BF82-BG82 -> 24.511 | BI82: 0 | BJ82: =+BF82-BI82 -> 40 | BK82: =+T82+AI82+AX82+BE82+BF82 -> 40 | BL82: =+U82+AJ82+AY82+BG82 -> 15.489 | BM82: =+BK82-BL82 -> 24.511 | BN82: =+W82+AL82+BA82+BI82 -> 0 | BO82: =+BK82-BN82 -> 40 | BP82: =+BK82-BE82 -> 40 | BQ82: =+BL82-Z82 -> 15.489 | BR82: =+BP82-BQ82 -> 24.511 | BS82: =+BN82-AB82 -> 0 | BT82: =+BP82-BS82 -> 40
C83: 贈答用品費 | E83: =+ﾇｰﾍﾞﾙﾌﾟｰｽ!W82/1000 -> 0 | F83: 0 | G83: =+E83-F83 -> 0 | H83: 0 | I83: =+E83-H83 -> 0 | J83: =+ｶﾌｪﾙﾎﾟ!W82/1000 -> 0 | K83: 0 | L83: =+J83-K83 -> 0 | M83: 0 | N83: =+J83-M83 -> 0 | O83: =+ｶﾌｪｾﾚｽﾃ!W82/1000 -> 0 | P83: 0 | Q83: =+O83-P83 -> 0 | R83: 0 | S83: =+O83-R83 -> 0 | T83: =+E83+J83+O83 -> 0 | U83: =+F83+K83+P83 -> 0 | V83: =+T83-U83 -> 0 | W83: =+H83+M83+R83 -> 0 | X83: =+T83-W83 -> 0 | Y83: 0 | Z83: 0 | AA83: =+Y83-Z83 -> 0 | AB83: 0 | AC83: =+Y83-AB83 -> 0 | AD83: =+ｼﾞｭｴﾙｽﾞ!W82/1000 -> 0 | AE83: 0 | AF83: =+AD83-AE83 -> 0 | AG83: 0 | AH83: =+AD83-AG83 -> 0 | AI83: =+Y83+AD83 -> 0 | AJ83: =+Z83+AE83 -> 0 | AK83: =+AI83-AJ83 -> 0 | AL83: =+AB83+AG83 -> 0 | AM83: =+AI83-AL83 -> 0 | AN83: =+ｶﾞｰﾃﾞﾝ!W82/1000 -> 0 | AO83: 0 | AP83: =+AN83-AO83 -> 0 | AQ83: 0 | AR83: =+AN83-AQ83 -> 0 | AS83: =+ﾋﾞｱｶﾞｰﾃﾞﾝ!W82/1000 -> 0 | AT83: 0 | AU83: =+AS83-AT83 -> 0 | AV83: 0 | AW83: =+AS83-AV83 -> 0 | AX83: =+AN83+AS83 -> 0 | AY83: =+AO83+AT83 -> 0 | AZ83: =+AX83-AY83 -> 0 | BA83: =+AQ83+AV83 -> 0 | BB83: =+AX83-BA83 -> 0 | BC83: =+料飲共通!H82/1000 -> 0 | BD83: =+料飲共通!I82/1000 -> 0 | BE83: =+BC83+BD83 -> 0 | BF83: =+料飲共通!W82/1000 -> 0 | BG83: 0 | BH83: =+BF83-BG83 -> 0 | BI83: 0 | BJ83: =+BF83-BI83 -> 0 | BK83: =+T83+AI83+AX83+BE83+BF83 -> 0 | BL83: =+U83+AJ83+AY83+BG83 -> 0 | BM83: =+BK83-BL83 -> 0 | BN83: =+W83+AL83+BA83+BI83 -> 0 | BO83: =+BK83-BN83 -> 0 | BP83: =+BK83-BE83 -> 0 | BQ83: =+BL83-Z83 -> 0 | BR83: =+BP83-BQ83 -> 0 | BS83: =+BN83-AB83 -> 0 | BT83: =+BP83-BS83 -> 0
B84: 寄付金 | E84: =+ﾇｰﾍﾞﾙﾌﾟｰｽ!W83/1000 -> 0 | F84: 0 | G84: =+E84-F84 -> 0 | H84: 0 | I84: =+E84-H84 -> 0 | J84: =+ｶﾌｪﾙﾎﾟ!W83/1000 -> 0 | K84: 0 | L84: =+J84-K84 -> 0 | M84: 0 | N84: =+J84-M84 -> 0 | O84: =+ｶﾌｪｾﾚｽﾃ!W83/1000 -> 0 | P84: 0 | Q84: =+O84-P84 -> 0 | R84: 0 | S84: =+O84-R84 -> 0 | T84: =+E84+J84+O84 -> 0 | U84: =+F84+K84+P84 -> 0 | V84: =+T84-U84 -> 0 | W84: =+H84+M84+R84 -> 0 | X84: =+T84-W84 -> 0 | Y84: 0 | Z84: 0 | AA84: =+Y84-Z84 -> 0 | AB84: 0 | AC84: =+Y84-AB84 -> 0 | AD84: =+ｼﾞｭｴﾙｽﾞ!W83/1000 -> 0 | AE84: 0 | AF84: =+AD84-AE84 -> 0 | AG84: 0 | AH84: =+AD84-AG84 -> 0 | AI84: =+Y84+AD84 -> 0 | AJ84: =+Z84+AE84 -> 0 | AK84: =+AI84-AJ84 -> 0 | AL84: =+AB84+AG84 -> 0 | AM84: =+AI84-AL84 -> 0 | AN84: =+ｶﾞｰﾃﾞﾝ!W83/1000 -> 0 | AO84: 0 | AP84: =+AN84-AO84 -> 0 | AQ84: 0 | AR84: =+AN84-AQ84 -> 0 | AS84: =+ﾋﾞｱｶﾞｰﾃﾞﾝ!W83/1000 -> 0 | AT84: 0 | AU84: =+AS84-AT84 -> 0 | AV84: 0 | AW84: =+AS84-AV84 -> 0 | AX84: =+AN84+AS84 -> 0 | AY84: =+AO84+AT84 -> 0 | AZ84: =+AX84-AY84 -> 0 | BA84: =+AQ84+AV84 -> 0 | BB84: =+AX84-BA84 -> 0 | BC84: 0 | BD84: 0 | BE84: =+BC84+BD84 -> 0 | BF84: =+料飲共通!W83/1000 -> 0 | BG84: 0 | BH84: =+BF84-BG84 -> 0 | BI84: 0 | BJ84: =+BF84-BI84 -> 0 | BK84: =+T84+AI84+AX84+BE84+BF84 -> 0 | BL84: =+U84+AJ84+AY84+BG84 -> 0 | BM84: =+BK84-BL84 -> 0 | BN84: =+W84+AL84+BA84+BI84 -> 0 | BO84: =+BK84-BN84 -> 0 | BP84: =+BK84-BE84 -> 0 | BQ84: =+BL84-Z84 -> 0 | BR84: =+BP84-BQ84 -> 0 | BS84: =+BN84-AB84 -> 0 | BT84: =+BP84-BS84 -> 0
B85: 雑費用 | E85: =+ﾇｰﾍﾞﾙﾌﾟｰｽ!W84/1000 -> 0 | F85: 0 | G85: =+E85-F85 -> 0 | H85: 0 | I85: =+E85-H85 -> 0 | J85: =+ｶﾌｪﾙﾎﾟ!W84/1000 -> 0 | K85: 0 | L85: =+J85-K85 -> 0 | M85: 0 | N85: =+J85-M85 -> 0 | O85: =+ｶﾌｪｾﾚｽﾃ!W84/1000 -> 0 | P85: 0 | Q85: =+O85-P85 -> 0 | R85: 0 | S85: =+O85-R85 -> 0 | T85: =+E85+J85+O85 -> 0 | U85: =+F85+K85+P85 -> 0 | V85: =+T85-U85 -> 0 | W85: =+H85+M85+R85 -> 0 | X85: =+T85-W85 -> 0 | Y85: 0 | Z85: 0 | AA85: =+Y85-Z85 -> 0 | AB85: 0 | AC85: =+Y85-AB85 -> 0 | AD85: =+ｼﾞｭｴﾙｽﾞ!W84/1000 -> 0 | AE85: 0 | AF85: =+AD85-AE85 -> 0 | AG85: 0 | AH85: =+AD85-AG85 -> 0 | AI85: =+Y85+AD85 -> 0 | AJ85: =+Z85+AE85 -> 0 | AK85: =+AI85-AJ85 -> 0 | AL85: =+AB85+AG85 -> 0 | AM85: =+AI85-AL85 -> 0 | AN85: =+ｶﾞｰﾃﾞﾝ!W84/1000 -> 0 | AO85: 0 | AP85: =+AN85-AO85 -> 0 | AQ85: 0 | AR85: =+AN85-AQ85 -> 0 | AS85: =+ﾋﾞｱｶﾞｰﾃﾞﾝ!W84/1000 -> 0 | AT85: 0 | AU85: =+AS85-AT85 -> 0 | AV85: 0 | AW85: =+AS85-AV85 -> 0 | AX85: =+AN85+AS85 -> 0 | AY85: =+AO85+AT85 -> 0 | AZ85: =+AX85-AY85 -> 0 | BA85: =+AQ85+AV85 -> 0 | BB85: =+AX85-BA85 -> 0 | BC85: 0 | BD85: 0 | BE85: =+BC85+BD85 -> 0 | BF85: =+料飲共通!W84/1000 -> 0 | BG85: 0 | BH85: =+BF85-BG85 -> 0 | BI85: 0 | BJ85: =+BF85-BI85 -> 0 | BK85: =+T85+AI85+AX85+BE85+BF85 -> 0 | BL85: =+U85+AJ85+AY85+BG85 -> 0 | BM85: =+BK85-BL85 -> 0 | BN85: =+W85+AL85+BA85+BI85 -> 0 | BO85: =+BK85-BN85 -> 0 | BP85: =+BK85-BE85 -> 0 | BQ85: =+BL85-Z85 -> 0 | BR85: =+BP85-BQ85 -> 0 | BS85: =+BN85-AB85 -> 0 | BT85: =+BP85-BS85 -> 0
A86: 減価償却費 | E86: =+ﾇｰﾍﾞﾙﾌﾟｰｽ!W85/1000 -> 5815.056 | F86: 7349.53 | G86: =+E86-F86 -> -1534.474 | H86: 7293 | I86: =+E86-H86 -> -1477.944 | J86: =+ｶﾌｪﾙﾎﾟ!W85/1000 -> 684.883 | K86: 684.883 | L86: =+J86-K86 -> 0 | M86: 621 | N86: =+J86-M86 -> 63.883 | O86: =+ｶﾌｪｾﾚｽﾃ!W85/1000 -> 513.109 | P86: 513.109 | Q86: =+O86-P86 -> 0 | R86: 513 | S86: =+O86-R86 -> 0.109 | T86: =+E86+J86+O86 -> 7013.048 | U86: =+F86+K86+P86 -> 8547.522 | V86: =+T86-U86 -> -1534.474 | W86: =+H86+M86+R86 -> 8427 | X86: =+T86-W86 -> -1413.952 | Y86: 0 | Z86: 117.948 | AA86: =+Y86-Z86 -> -117.948 | AB86: 788 | AC86: =+Y86-AB86 -> -788 | AD86: =+ｼﾞｭｴﾙｽﾞ!W85/1000 -> 3560.82 | AE86: 3325.659 | AF86: =+AD86-AE86 -> 235.161 | AG86: 4110 | AH86: =+AD86-AG86 -> -549.18 | AI86: =+Y86+AD86 -> 3560.82 | AJ86: =+Z86+AE86 -> 3443.607 | AK86: =+AI86-AJ86 -> 117.213 | AL86: =+AB86+AG86 -> 4898 | AM86: =+AI86-AL86 -> -1337.18 | AN86: =+ｶﾞｰﾃﾞﾝ!W85/1000 -> 10698.156 | AO86: 11819.724 | AP86: =+AN86-AO86 -> -1121.568 | AQ86: 12106 | AR86: =+AN86-AQ86 -> -1407.844 | AS86: =+ﾋﾞｱｶﾞｰﾃﾞﾝ!W85/1000 -> 384.173 | AT86: 384.173 | AU86: =+AS86-AT86 -> 0 | AV86: 210 | AW86: =+AS86-AV86 -> 174.173 | AX86: =+AN86+AS86 -> 11082.329 | AY86: =+AO86+AT86 -> 12203.897 | AZ86: =+AX86-AY86 -> -1121.568 | BA86: =+AQ86+AV86 -> 12316 | BB86: =+AX86-BA86 -> -1233.671 | BC86: =SUM(BC87:BC97) -> 2476.1313 | BD86: =SUM(BD87:BD97) -> 488.46155 | BE86: =+BC86+BD86 -> 2964.5928 | BF86: =+料飲共通!W85/1000 -> 0 | BG86: 0 | BH86: =+BF86-BG86 -> 0 | BI86: 50 | BJ86: =+BF86-BI86 -> -50 | BK86: =+T86+AI86+AX86+BE86+BF86 -> 24620.79 | BL86: =+U86+AJ86+AY86+BG86 -> 24195.026 | BM86: =+BK86-BL86 -> 425.7638 | BN86: =+W86+AL86+BA86+BI86 -> 25691 | BO86: =+BK86-BN86 -> -1070.2102 | BP86: =+BK86-BE86 -> 21656.197 | BQ86: =+BL86-Z86 -> 24077.078 | BR86: =+BP86-BQ86 -> -2420.881 | BS86: =+BN86-AB86 -> 24903 | BT86: =+BP86-BS86 -> -3246.803
B87: 建物 | E87: =+ﾇｰﾍﾞﾙﾌﾟｰｽ!W86/1000 -> 0 | F87: 0 | G87: =+E87-F87 -> 0 | H87: 0 | I87: =+E87-H87 -> 0 | J87: =+ｶﾌｪﾙﾎﾟ!W86/1000 -> 0 | K87: 0 | L87: =+J87-K87 -> 0 | M87: 0 | N87: =+J87-M87 -> 0 | O87: =+ｶﾌｪｾﾚｽﾃ!W86/1000 -> 0 | P87: 0 | Q87: =+O87-P87 -> 0 | R87: 0 | S87: =+O87-R87 -> 0 | T87: =+E87+J87+O87 -> 0 | U87: =+F87+K87+P87 -> 0 | V87: =+T87-U87 -> 0 | W87: =+H87+M87+R87 -> 0 | X87: =+T87-W87 -> 0 | Y87: 0 | Z87: 0 | AA87: =+Y87-Z87 -> 0 | AB87: 0 | AC87: =+Y87-AB87 -> 0 | AD87: =+ｼﾞｭｴﾙｽﾞ!W86/1000 -> 338.068 | AE87: 338.068 | AF87: =+AD87-AE87 -> 0 | AG87: 338 | AH87: =+AD87-AG87 -> 0.068 | AI87: =+Y87+AD87 -> 338.068 | AJ87: =+Z87+AE87 -> 338.068 | AK87: =+AI87-AJ87 -> 0 | AL87: =+AB87+AG87 -> 338 | AM87: =+AI87-AL87 -> 0.068 | AN87: =+ｶﾞｰﾃﾞﾝ!W86/1000 -> 0 | AO87: 0 | AP87: =+AN87-AO87 -> 0 | AQ87: 0 | AR87: =+AN87-AQ87 -> 0 | AS87: =+ﾋﾞｱｶﾞｰﾃﾞﾝ!W86/1000 -> 0 | AT87: 0 | AU87: =+AS87-AT87 -> 0 | AV87: 0 | AW87: =+AS87-AV87 -> 0 | AX87: =+AN87+AS87 -> 0 | AY87: =+AO87+AT87 -> 0 | AZ87: =+AX87-AY87 -> 0 | BA87: =+AQ87+AV87 -> 0 | BB87: =+AX87-BA87 -> 0 | BC87: =+赤れんが!X87/1000 -> 256.41026 | BD87: =+赤れんが!Z87/1000 -> 38.461538 | BE87: =+BC87+BD87 -> 294.87179 | BF87: =+料飲共通!W86/1000 -> 0 | BG87: 0 | BH87: =+BF87-BG87 -> 0 | BI87: 0 | BJ87: =+BF87-BI87 -> 0 | BK87: =+T87+AI87+AX87+BE87+BF87 -> 632.93979 | BL87: =+U87+AJ87+AY87+BG87 -> 338.068 | BM87: =+BK87-BL87 -> 294.87179 | BN87: =+W87+AL87+BA87+BI87 -> 338 | BO87: =+BK87-BN87 -> 294.93979 | BP87: =+BK87-BE87 -> 338.068 | BQ87: =+BL87-Z87 -> 338.068 | BR87: =+BP87-BQ87 -> 0 | BS87: =+BN87-AB87 -> 338 | BT87: =+BP87-BS87 -> 0.068
B88: 建物附属設備 | E88: =+ﾇｰﾍﾞﾙﾌﾟｰｽ!W87/1000 -> 583.333 | F88: 0 | G88: =+E88-F88 -> 583.333 | H88: 0 | I88: =+E88-H88 -> 583.333 | J88: =+ｶﾌｪﾙﾎﾟ!W87/1000 -> 0 | K88: 0 | L88: =+J88-K88 -> 0 | M88: 0 | N88: =+J88-M88 -> 0 | O88: =+ｶﾌｪｾﾚｽﾃ!W87/1000 -> 257.803 | P88: 257.803 | Q88: =+O88-P88 -> 0 | R88: 257 | S88: =+O88-R88 -> 0.803 | T88: =+E88+J88+O88 -> 841.136 | U88: =+F88+K88+P88 -> 257.803 | V88: =+T88-U88 -> 583.333 | W88: =+H88+M88+R88 -> 257 | X88: =+T88-W88 -> 584.136 | Y88: 0 | Z88: 0 | AA88: =+Y88-Z88 -> 0 | AB88: 125 | AC88: =+Y88-AB88 -> -125 | AD88: =+ｼﾞｭｴﾙｽﾞ!W87/1000 -> 958.957 | AE88: 553.957 | AF88: =+AD88-AE88 -> 405 | AG88: 1334 | AH88: =+AD88-AG88 -> -375.043 | AI88: =+Y88+AD88 -> 958.957 | AJ88: =+Z88+AE88 -> 553.957 | AK88: =+AI88-AJ88 -> 405 | AL88: =+AB88+AG88 -> 1459 | AM88: =+AI88-AL88 -> -500.043 | AN88: =+ｶﾞｰﾃﾞﾝ!W87/1000 -> 5652.58 | AO88: 7090.461 | AP88: =+AN88-AO88 -> -1437.881 | AQ88: 7511 | AR88: =+AN88-AQ88 -> -1858.42 | AS88: =+ﾋﾞｱｶﾞｰﾃﾞﾝ!W87/1000 -> 0 | AT88: 0 | AU88: =+AS88-AT88 -> 0 | AV88: 0 | AW88: =+AS88-AV88 -> 0 | AX88: =+AN88+AS88 -> 5652.58 | AY88: =+AO88+AT88 -> 7090.461 | AZ88: =+AX88-AY88 -> -1437.881 | BA88: =+AQ88+AV88 -> 7511 | BB88: =+AX88-BA88 -> -1858.42 | BC88: =+赤れんが!X88/1000 -> 1000 | BD88: =+赤れんが!Z88/1000 -> 150 | BE88: =+BC88+BD88 -> 1150 | BF88: =+料飲共通!W87/1000 -> 0 | BG88: 0 | BH88: =+BF88-BG88 -> 0 | BI88: 0 | BJ88: =+BF88-BI88 -> 0 | BK88: =+T88+AI88+AX88+BE88+BF88 -> 8602.673 | BL88: =+U88+AJ88+AY88+BG88 -> 7902.221 | BM88: =+BK88-BL88 -> 700.452 | BN88: =+W88+AL88+BA88+BI88 -> 9227 | BO88: =+BK88-BN88 -> -624.327 | BP88: =+BK88-BE88 -> 7452.673 | BQ88: =+BL88-Z88 -> 7902.221 | BR88: =+BP88-BQ88 -> -449.548 | BS88: =+BN88-AB88 -> 9102 | BT88: =+BP88-BS88 -> -1649.327
B89: 構築物 | E89: =+ﾇｰﾍﾞﾙﾌﾟｰｽ!W88/1000 -> 0 | F89: 0 | G89: =+E89-F89 -> 0 | H89: 0 | I89: =+E89-H89 -> 0 | J89: =+ｶﾌｪﾙﾎﾟ!W88/1000 -> 0 | K89: 0 | L89: =+J89-K89 -> 0 | M89: 0 | N89: =+J89-M89 -> 0 | O89: =+ｶﾌｪｾﾚｽﾃ!W88/1000 -> 0 | P89: 0 | Q89: =+O89-P89 -> 0 | R89: 0 | S89: =+O89-R89 -> 0 | T89: =+E89+J89+O89 -> 0 | U89: =+F89+K89+P89 -> 0 | V89: =+T89-U89 -> 0 | W89: =+H89+M89+R89 -> 0 | X89: =+T89-W89 -> 0 | Y89: 0 | Z89: 0 | AA89: =+Y89-Z89 -> 0 | AB89: 0 | AC89: =+Y89-AB89 -> 0 | AD89: =+ｼﾞｭｴﾙｽﾞ!W88/1000 -> 0 | AE89: 0 | AF89: =+AD89-AE89 -> 0 | AG89: 0 | AH89: =+AD89-AG89 -> 0 | AI89: =+Y89+AD89 -> 0 | AJ89: =+Z89+AE89 -> 0 | AK89: =+AI89-AJ89 -> 0 | AL89: =+AB89+AG89 -> 0 | AM89: =+AI89-AL89 -> 0 | AN89: =+ｶﾞｰﾃﾞﾝ!W88/1000 -> 0 | AO89: 0 | AP89: =+AN89-AO89 -> 0 | AQ89: 0 | AR89: =+AN89-AQ89 -> 0 | AS89: =+ﾋﾞｱｶﾞｰﾃﾞﾝ!W88/1000 -> 0 | AT89: 0 | AU89: =+AS89-AT89 -> 0 | AV89: 0 | AW89: =+AS89-AV89 -> 0 | AX89: =+AN89+AS89 -> 0 | AY89: =+AO89+AT89 -> 0 | AZ89: =+AX89-AY89 -> 0 | BA89: =+AQ89+AV89 -> 0 | BB89: =+AX89-BA89 -> 0 | BC89: =+料飲共通!H88/1000 -> 0 | BD89: =+料飲共通!I88/1000 -> 0 | BE89: =+BC89+BD89 -> 0 | BF89: =+料飲共通!W88/1000 -> 0 | BG89: 0 | BH89: =+BF89-BG89 -> 0 | BI89: 0 | BJ89: =+BF89-BI89 -> 0 | BK89: =+T89+AI89+AX89+BE89+BF89 -> 0 | BL89: =+U89+AJ89+AY89+BG89 -> 0 | BM89: =+BK89-BL89 -> 0 | BN89: =+W89+AL89+BA89+BI89 -> 0 | BO89: =+BK89-BN89 -> 0 | BP89: =+BK89-BE89 -> 0 | BQ89: =+BL89-Z89 -> 0 | BR89: =+BP89-BQ89 -> 0 | BS89: =+BN89-AB89 -> 0 | BT89: =+BP89-BS89 -> 0
B90: 機械・装置 | E90: =+ﾇｰﾍﾞﾙﾌﾟｰｽ!W89/1000 -> 500 | F90: 0 | G90: =+E90-F90 -> 500 | H90: 0 | I90: =+E90-H90 -> 500 | J90: =+ｶﾌｪﾙﾎﾟ!W89/1000 -> 180.557 | K90: 180.557 | L90: =+J90-K90 -> 0 | M90: 180 | N90: =+J90-M90 -> 0.557 | O90: =+ｶﾌｪｾﾚｽﾃ!W89/1000 -> 0 | P90: 0 | Q90: =+O90-P90 -> 0 | R90: 0 | S90: =+O90-R90 -> 0 | T90: =+E90+J90+O90 -> 680.557 | U90: =+F90+K90+P90 -> 180.557 | V90: =+T90-U90 -> 500 | W90: =+H90+M90+R90 -> 180 | X90: =+T90-W90 -> 500.557 | Y90: 0 | Z90: 0 | AA90: =+Y90-Z90 -> 0 | AB90: 0 | AC90: =+Y90-AB90 -> 0 | AD90: =+ｼﾞｭｴﾙｽﾞ!W89/1000 -> 175.1 | AE90: 175.1 | AF90: =+AD90-AE90 -> 0 | AG90: 175 | AH90: =+AD90-AG90 -> 0.1 | AI90: =+Y90+AD90 -> 175.1 | AJ90: =+Z90+AE90 -> 175.1 | AK90: =+AI90-AJ90 -> 0 | AL90: =+AB90+AG90 -> 175 | AM90: =+AI90-AL90 -> 0.1 | AN90: =+ｶﾞｰﾃﾞﾝ!W89/1000 -> 403.782 | AO90: 143.366 | AP90: =+AN90-AO90 -> 260.416 | AQ90: 143 | AR90: =+AN90-AQ90 -> 260.782 | AS90: =+ﾋﾞｱｶﾞｰﾃﾞﾝ!W89/1000 -> 0 | AT90: 0 | AU90: =+AS90-AT90 -> 0 | AV90: 0 | AW90: =+AS90-AV90 -> 0 | AX90: =+AN90+AS90 -> 403.782 | AY90: =+AO90+AT90 -> 143.366 | AZ90: =+AX90-AY90 -> 260.416 | BA90: =+AQ90+AV90 -> 143 | BB90: =+AX90-BA90 -> 260.782 | BC90: =+料飲共通!H89/1000 -> 0 | BD90: =+料飲共通!I89/1000 -> 0 | BE90: =+BC90+BD90 -> 0 | BF90: =+料飲共通!W89/1000 -> 0 | BG90: 0 | BH90: =+BF90-BG90 -> 0 | BI90: 0 | BJ90: =+BF90-BI90 -> 0 | BK90: =+T90+AI90+AX90+BE90+BF90 -> 1259.439 | BL90: =+U90+AJ90+AY90+BG90 -> 499.023 | BM90: =+BK90-BL90 -> 760.416 | BN90: =+W90+AL90+BA90+BI90 -> 498 | BO90: =+BK90-BN90 -> 761.439 | BP90: =+BK90-BE90 -> 1259.439 | BQ90: =+BL90-Z90 -> 499.023 | BR90: =+BP90-BQ90 -> 760.416 | BS90: =+BN90-AB90 -> 498 | BT90: =+BP90-BS90 -> 761.439
B91: 器具備品 | E91: =+ﾇｰﾍﾞﾙﾌﾟｰｽ!W90/1000 -> 4445.38 | F91: 7063.188 | G91: =+E91-F91 -> -2617.808 | H91: 7063 | I91: =+E91-H91 -> -2617.62 | J91: =+ｶﾌｪﾙﾎﾟ!W90/1000 -> 440.993 | K91: 440.993 | L91: =+J91-K91 -> 0 | M91: 440 | N91: =+J91-M91 -> 0.993 | O91: =+ｶﾌｪｾﾚｽﾃ!W90/1000 -> 255.306 | P91: 255.306 | Q91: =+O91-P91 -> 0 | R91: 255 | S91: =+O91-R91 -> 0.306 | T91: =+E91+J91+O91 -> 5141.679 | U91: =+F91+K91+P91 -> 7759.487 | V91: =+T91-U91 -> -2617.808 | W91: =+H91+M91+R91 -> 7758 | X91: =+T91-W91 -> -2616.321 | Y91: 0 | Z91: 0 | AA91: =+Y91-Z91 -> 0 | AB91: 545 | AC91: =+Y91-AB91 -> -545 | AD91: =+ｼﾞｭｴﾙｽﾞ!W90/1000 -> 1769.326 | AE91: 1841.336 | AF91: =+AD91-AE91 -> -72.01 | AG91: 2103 | AH91: =+AD91-AG91 -> -333.674 | AI91: =+Y91+AD91 -> 1769.326 | AJ91: =+Z91+AE91 -> 1841.336 | AK91: =+AI91-AJ91 -> -72.01 | AL91: =+AB91+AG91 -> 2648 | AM91: =+AI91-AL91 -> -878.674 | AN91: =+ｶﾞｰﾃﾞﾝ!W90/1000 -> 3349.202 | AO91: 3293.326 | AP91: =+AN91-AO91 -> 55.876 | AQ91: 3274 | AR91: =+AN91-AQ91 -> 75.202 | AS91: =+ﾋﾞｱｶﾞｰﾃﾞﾝ!W90/1000 -> 120.84 | AT91: 120.84 | AU91: =+AS91-AT91 -> 0 | AV91: 210 | AW91: =+AS91-AV91 -> -89.16 | AX91: =+AN91+AS91 -> 3470.042 | AY91: =+AO91+AT91 -> 3414.166 | AZ91: =+AX91-AY91 -> 55.876 | BA91: =+AQ91+AV91 -> 3484 | BB91: =+AX91-BA91 -> -13.958 | BC91: =+赤れんが!X91/1000 -> 500 | BD91: =+赤れんが!Y91/1000 -> 6.6343213e-06 | BE91: =+BC91+BD91 -> 500.00001 | BF91: =+料飲共通!W90/1000 -> 0 | BG91: 0 | BH91: =+BF91-BG91 -> 0 | BI91: 50 | BJ91: =+BF91-BI91 -> -50 | BK91: =+T91+AI91+AX91+BE91+BF91 -> 10881.047 | BL91: =+U91+AJ91+AY91+BG91 -> 13014.989 | BM91: =+BK91-BL91 -> -2133.942 | BN91: =+W91+AL91+BA91+BI91 -> 13940 | BO91: =+BK91-BN91 -> -3058.953 | BP91: =+BK91-BE91 -> 10381.047 | BQ91: =+BL91-Z91 -> 13014.989 | BR91: =+BP91-BQ91 -> -2633.942 | BS91: =+BN91-AB91 -> 13395 | BT91: =+BP91-BS91 -> -3013.953
B92: 車両 | E92: =+ﾇｰﾍﾞﾙﾌﾟｰｽ!W91/1000 -> 0 | F92: 0 | G92: =+E92-F92 -> 0 | H92: 0 | I92: =+E92-H92 -> 0 | J92: =+ｶﾌｪﾙﾎﾟ!W91/1000 -> 0 | K92: 0 | L92: =+J92-K92 -> 0 | M92: 0 | N92: =+J92-M92 -> 0 | O92: =+ｶﾌｪｾﾚｽﾃ!W91/1000 -> 0 | P92: 0 | Q92: =+O92-P92 -> 0 | R92: 0 | S92: =+O92-R92 -> 0 | T92: =+E92+J92+O92 -> 0 | U92: =+F92+K92+P92 -> 0 | V92: =+T92-U92 -> 0 | W92: =+H92+M92+R92 -> 0 | X92: =+T92-W92 -> 0 | Y92: 0 | Z92: 0 | AA92: =+Y92-Z92 -> 0 | AB92: 0 | AC92: =+Y92-AB92 -> 0 | AD92: =+ｼﾞｭｴﾙｽﾞ!W91/1000 -> 0 | AE92: 0 | AF92: =+AD92-AE92 -> 0 | AG92: 0 | AH92: =+AD92-AG92 -> 0 | AI92: =+Y92+AD92 -> 0 | AJ92: =+Z92+AE92 -> 0 | AK92: =+AI92-AJ92 -> 0 | AL92: =+AB92+AG92 -> 0 | AM92: =+AI92-AL92 -> 0 | AN92: =+ｶﾞｰﾃﾞﾝ!W91/1000 -> 0 | AO92: 0 | AP92: =+AN92-AO92 -> 0 | AQ92: 0 | AR92: =+AN92-AQ92 -> 0 | AS92: =+ﾋﾞｱｶﾞｰﾃﾞﾝ!W91/1000 -> 0 | AT92: 0 | AU92: =+AS92-AT92 -> 0 | AV92: 0 | AW92: =+AS92-AV92 -> 0 | AX92: =+AN92+AS92 -> 0 | AY92: =+AO92+AT92 -> 0 | AZ92: =+AX92-AY92 -> 0 | BA92: =+AQ92+AV92 -> 0 | BB92: =+AX92-BA92 -> 0 | BC92: =+料飲共通!H91/1000 -> 0 | BD92: =+料飲共通!I91/1000 -> 0 | BE92: =+BC92+BD92 -> 0 | BF92: =+料飲共通!W91/1000 -> 0 | BG92: 0 | BH92: =+BF92-BG92 -> 0 | BI92: 0 | BJ92: =+BF92-BI92 -> 0 | BK92: =+T92+AI92+AX92+BE92+BF92 -> 0 | BL92: =+U92+AJ92+AY92+BG92 -> 0 | BM92: =+BK92-BL92 -> 0 | BN92: =+W92+AL92+BA92+BI92 -> 0 | BO92: =+BK92-BN92 -> 0 | BP92: =+BK92-BE92 -> 0 | BQ92: =+BL92-Z92 -> 0 | BR92: =+BP92-BQ92 -> 0 | BS92: =+BN92-AB92 -> 0 | BT92: =+BP92-BS92 -> 0
B93: 少額資産 | E93: =+ﾇｰﾍﾞﾙﾌﾟｰｽ!W92/1000 -> 218.344 | F93: 218.342 | G93: =+E93-F93 -> 0.002 | H93: 162 | I93: =+E93-H93 -> 56.344 | J93: =+ｶﾌｪﾙﾎﾟ!W92/1000 -> 63.333 | K93: 63.333 | L93: =+J93-K93 -> 0 | M93: 0 | N93: =+J93-M93 -> 63.333 | O93: =+ｶﾌｪｾﾚｽﾃ!W92/1000 -> 0 | P93: 0 | Q93: =+O93-P93 -> 0 | R93: 0 | S93: =+O93-R93 -> 0 | T93: =+E93+J93+O93 -> 281.677 | U93: =+F93+K93+P93 -> 281.675 | V93: =+T93-U93 -> 0.002 | W93: =+H93+M93+R93 -> 162 | X93: =+T93-W93 -> 119.677 | Y93: 0 | Z93: 117.948 | AA93: =+Y93-Z93 -> -117.948 | AB93: 117 | AC93: =+Y93-AB93 -> -117 | AD93: =+ｼﾞｭｴﾙｽﾞ!W92/1000 -> 319.369 | AE93: 417.198 | AF93: =+AD93-AE93 -> -97.829 | AG93: 160 | AH93: =+AD93-AG93 -> 159.369 | AI93: =+Y93+AD93 -> 319.369 | AJ93: =+Z93+AE93 -> 535.146 | AK93: =+AI93-AJ93 -> -215.777 | AL93: =+AB93+AG93 -> 277 | AM93: =+AI93-AL93 -> 42.369 | AN93: =+ｶﾞｰﾃﾞﾝ!W92/1000 -> 1292.592 | AO93: 1292.571 | AP93: =+AN93-AO93 -> 0.021 | AQ93: 1177 | AR93: =+AN93-AQ93 -> 115.592 | AS93: =+ﾋﾞｱｶﾞｰﾃﾞﾝ!W92/1000 -> 263.333 | AT93: 263.333 | AU93: =+AS93-AT93 -> 0 | AV93: 0 | AW93: =+AS93-AV93 -> 263.333 | AX93: =+AN93+AS93 -> 1555.925 | AY93: =+AO93+AT93 -> 1555.904 | AZ93: =+AX93-AY93 -> 0.021 | BA93: =+AQ93+AV93 -> 1177 | BB93: =+AX93-BA93 -> 378.925 | BC93: =+料飲共通!H92/1000 -> 0 | BD93: =+料飲共通!I92/1000 -> 0 | BE93: =+BC93+BD93 -> 0 | BF93: =+料飲共通!W92/1000 -> 0 | BG93: 0 | BH93: =+BF93-BG93 -> 0 | BI93: 0 | BJ93: =+BF93-BI93 -> 0 | BK93: =+T93+AI93+AX93+BE93+BF93 -> 2156.971 | BL93: =+U93+AJ93+AY93+BG93 -> 2372.725 | BM93: =+BK93-BL93 -> -215.754 | BN93: =+W93+AL93+BA93+BI93 -> 1616 | BO93: =+BK93-BN93 -> 540.971 | BP93: =+BK93-BE93 -> 2156.971 | BQ93: =+BL93-Z93 -> 2254.777 | BR93: =+BP93-BQ93 -> -97.806 | BS93: =+BN93-AB93 -> 1499 | BT93: =+BP93-BS93 -> 657.971
B94: 商標権 | E94: =+ﾇｰﾍﾞﾙﾌﾟｰｽ!W93/1000 -> 0 | F94: 0 | G94: =+E94-F94 -> 0 | H94: 0 | I94: =+E94-H94 -> 0 | J94: =+ｶﾌｪﾙﾎﾟ!W93/1000 -> 0 | K94: 0 | L94: =+J94-K94 -> 0 | M94: 0 | N94: =+J94-M94 -> 0 | O94: =+ｶﾌｪｾﾚｽﾃ!W93/1000 -> 0 | P94: 0 | Q94: =+O94-P94 -> 0 | R94: 0 | S94: =+O94-R94 -> 0 | T94: =+E94+J94+O94 -> 0 | U94: =+F94+K94+P94 -> 0 | V94: =+T94-U94 -> 0 | W94: =+H94+M94+R94 -> 0 | X94: =+T94-W94 -> 0 | Y94: 0 | Z94: 0 | AA94: =+Y94-Z94 -> 0 | AB94: 0 | AC94: =+Y94-AB94 -> 0 | AD94: =+ｼﾞｭｴﾙｽﾞ!W93/1000 -> 0 | AE94: 0 | AF94: =+AD94-AE94 -> 0 | AG94: 0 | AH94: =+AD94-AG94 -> 0 | AI94: =+Y94+AD94 -> 0 | AJ94: =+Z94+AE94 -> 0 | AK94: =+AI94-AJ94 -> 0 | AL94: =+AB94+AG94 -> 0 | AM94: =+AI94-AL94 -> 0 | AN94: =+ｶﾞｰﾃﾞﾝ!W93/1000 -> 0 | AO94: 0 | AP94: =+AN94-AO94 -> 0 | AQ94: 0 | AR94: =+AN94-AQ94 -> 0 | AS94: =+ﾋﾞｱｶﾞｰﾃﾞﾝ!W93/1000 -> 0 | AT94: 0 | AU94: =+AS94-AT94 -> 0 | AV94: 0 | AW94: =+AS94-AV94 -> 0 | AX94: =+AN94+AS94 -> 0 | AY94: =+AO94+AT94 -> 0 | AZ94: =+AX94-AY94 -> 0 | BA94: =+AQ94+AV94 -> 0 | BB94: =+AX94-BA94 -> 0 | BC94: =+赤れんが!X94/1000 -> 719.721 | BD94: =+赤れんが!Z94/1000 -> 300 | BE94: =+BC94+BD94 -> 1019.721 | BF94: =+料飲共通!W93/1000 -> 0 | BG94: 0 | BH94: =+BF94-BG94 -> 0 | BI94: 0 | BJ94: =+BF94-BI94 -> 0 | BK94: =+T94+AI94+AX94+BE94+BF94 -> 1019.721 | BL94: =+U94+AJ94+AY94+BG94 -> 0 | BM94: =+BK94-BL94 -> 1019.721 | BN94: =+W94+AL94+BA94+BI94 -> 0 | BO94: =+BK94-BN94 -> 1019.721 | BP94: =+BK94-BE94 -> 0 | BQ94: =+BL94-Z94 -> 0 | BR94: =+BP94-BQ94 -> 0 | BS94: =+BN94-AB94 -> 0 | BT94: =+BP94-BS94 -> 0
B95: ソフトウェア | E95: =+ﾇｰﾍﾞﾙﾌﾟｰｽ!W94/1000 -> 67.999 | F95: 68 | G95: =+E95-F95 -> -0.001 | H95: 68 | I95: =+E95-H95 -> -0.001 | J95: =+ｶﾌｪﾙﾎﾟ!W94/1000 -> 0 | K95: 0 | L95: =+J95-K95 -> 0 | M95: 0 | N95: =+J95-M95 -> 0 | O95: =+ｶﾌｪｾﾚｽﾃ!W94/1000 -> 0 | P95: 0 | Q95: =+O95-P95 -> 0 | R95: 0 | S95: =+O95-R95 -> 0 | T95: =+E95+J95+O95 -> 67.999 | U95: =+F95+K95+P95 -> 68 | V95: =+T95-U95 -> -0.001 | W95: =+H95+M95+R95 -> 68 | X95: =+T95-W95 -> -0.001 | Y95: 0 | Z95: 0 | AA95: =+Y95-Z95 -> 0 | AB95: 0 | AC95: =+Y95-AB95 -> 0 | AD95: =+ｼﾞｭｴﾙｽﾞ!W94/1000 -> 0 | AE95: 0 | AF95: =+AD95-AE95 -> 0 | AG95: 0 | AH95: =+AD95-AG95 -> 0 | AI95: =+Y95+AD95 -> 0 | AJ95: =+Z95+AE95 -> 0 | AK95: =+AI95-AJ95 -> 0 | AL95: =+AB95+AG95 -> 0 | AM95: =+AI95-AL95 -> 0 | AN95: =+ｶﾞｰﾃﾞﾝ!W94/1000 -> 0 | AO95: 0 | AP95: =+AN95-AO95 -> 0 | AQ95: 0 | AR95: =+AN95-AQ95 -> 0 | AS95: =+ﾋﾞｱｶﾞｰﾃﾞﾝ!W94/1000 -> 0 | AT95: 0 | AU95: =+AS95-AT95 -> 0 | AV95: 0 | AW95: =+AS95-AV95 -> 0 | AX95: =+AN95+AS95 -> 0 | AY95: =+AO95+AT95 -> 0 | AZ95: =+AX95-AY95 -> 0 | BA95: =+AQ95+AV95 -> 0 | BB95: =+AX95-BA95 -> 0 | BC95: =+料飲共通!H94/1000 -> 0 | BD95: =+料飲共通!I94/1000 -> 0 | BE95: =+BC95+BD95 -> 0 | BF95: =+料飲共通!W94/1000 -> 0 | BG95: 0 | BH95: =+BF95-BG95 -> 0 | BI95: 0 | BJ95: =+BF95-BI95 -> 0 | BK95: =+T95+AI95+AX95+BE95+BF95 -> 67.999 | BL95: =+U95+AJ95+AY95+BG95 -> 68 | BM95: =+BK95-BL95 -> -0.001 | BN95: =+W95+AL95+BA95+BI95 -> 68 | BO95: =+BK95-BN95 -> -0.001 | BP95: =+BK95-BE95 -> 67.999 | BQ95: =+BL95-Z95 -> 68 | BR95: =+BP95-BQ95 -> -0.001 | BS95: =+BN95-AB95 -> 68 | BT95: =+BP95-BS95 -> -0.001
B96: 長期前払費用 | E96: =+ﾇｰﾍﾞﾙﾌﾟｰｽ!W95/1000 -> 0 | F96: 0 | G96: =+E96-F96 -> 0 | H96: 0 | I96: =+E96-H96 -> 0 | J96: =+ｶﾌｪﾙﾎﾟ!W95/1000 -> 0 | K96: 0 | L96: =+J96-K96 -> 0 | M96: 0 | N96: =+J96-M96 -> 0 | O96: =+ｶﾌｪｾﾚｽﾃ!W95/1000 -> 0 | P96: 0 | Q96: =+O96-P96 -> 0 | R96: 0 | S96: =+O96-R96 -> 0 | T96: =+E96+J96+O96 -> 0 | U96: =+F96+K96+P96 -> 0 | V96: =+T96-U96 -> 0 | W96: =+H96+M96+R96 -> 0 | X96: =+T96-W96 -> 0 | Y96: 0 | Z96: 0 | AA96: =+Y96-Z96 -> 0 | AB96: 0 | AC96: =+Y96-AB96 -> 0 | AD96: =+ｼﾞｭｴﾙｽﾞ!W95/1000 -> 0 | AE96: 0 | AF96: =+AD96-AE96 -> 0 | AG96: 0 | AH96: =+AD96-AG96 -> 0 | AI96: =+Y96+AD96 -> 0 | AJ96: =+Z96+AE96 -> 0 | AK96: =+AI96-AJ96 -> 0 | AL96: =+AB96+AG96 -> 0 | AM96: =+AI96-AL96 -> 0 | AN96: =+ｶﾞｰﾃﾞﾝ!W95/1000 -> 0 | AO96: 0 | AP96: =+AN96-AO96 -> 0 | AQ96: 0 | AR96: =+AN96-AQ96 -> 0 | AS96: =+ﾋﾞｱｶﾞｰﾃﾞﾝ!W95/1000 -> 0 | AT96: 0 | AU96: =+AS96-AT96 -> 0 | AV96: 0 | AW96: =+AS96-AV96 -> 0 | AX96: =+AN96+AS96 -> 0 | AY96: =+AO96+AT96 -> 0 | AZ96: =+AX96-AY96 -> 0 | BA96: =+AQ96+AV96 -> 0 | BB96: =+AX96-BA96 -> 0 | BC96: =+料飲共通!H95/1000 -> 0 | BD96: =+料飲共通!I95/1000 -> 0 | BE96: =+BC96+BD96 -> 0 | BF96: =+料飲共通!W95/1000 -> 0 | BG96: 0 | BH96: =+BF96-BG96 -> 0 | BI96: 0 | BJ96: =+BF96-BI96 -> 0 | BK96: =+T96+AI96+AX96+BE96+BF96 -> 0 | BL96: =+U96+AJ96+AY96+BG96 -> 0 | BM96: =+BK96-BL96 -> 0 | BN96: =+W96+AL96+BA96+BI96 -> 0 | BO96: =+BK96-BN96 -> 0 | BP96: =+BK96-BE96 -> 0 | BQ96: =+BL96-Z96 -> 0 | BR96: =+BP96-BQ96 -> 0 | BS96: =+BN96-AB96 -> 0 | BT96: =+BP96-BS96 -> 0
B97: リース資産 | E97: =+ﾇｰﾍﾞﾙﾌﾟｰｽ!W96/1000 -> 0 | F97: 0 | G97: =+E97-F97 -> 0 | H97: 0 | I97: =+E97-H97 -> 0 | J97: =+ｶﾌｪﾙﾎﾟ!W96/1000 -> 0 | K97: 0 | L97: =+J97-K97 -> 0 | M97: 0 | N97: =+J97-M97 -> 0 | O97: =+ｶﾌｪｾﾚｽﾃ!W96/1000 -> 0 | P97: 0 | Q97: =+O97-P97 -> 0 | R97: 0 | S97: =+O97-R97 -> 0 | T97: =+E97+J97+O97 -> 0 | U97: =+F97+K97+P97 -> 0 | V97: =+T97-U97 -> 0 | W97: =+H97+M97+R97 -> 0 | X97: =+T97-W97 -> 0 | Y97: 0 | Z97: 0 | AA97: =+Y97-Z97 -> 0 | AB97: 0 | AC97: =+Y97-AB97 -> 0 | AD97: =+ｼﾞｭｴﾙｽﾞ!W96/1000 -> 0 | AE97: 0 | AF97: =+AD97-AE97 -> 0 | AG97: 0 | AH97: =+AD97-AG97 -> 0 | AI97: =+Y97+AD97 -> 0 | AJ97: =+Z97+AE97 -> 0 | AK97: =+AI97-AJ97 -> 0 | AL97: =+AB97+AG97 -> 0 | AM97: =+AI97-AL97 -> 0 | AN97: =+ｶﾞｰﾃﾞﾝ!W96/1000 -> 0 | AO97: 0 | AP97: =+AN97-AO97 -> 0 | AQ97: 0 | AR97: =+AN97-AQ97 -> 0 | AS97: =+ﾋﾞｱｶﾞｰﾃﾞﾝ!W96/1000 -> 0 | AT97: 0 | AU97: =+AS97-AT97 -> 0 | AV97: 0 | AW97: =+AS97-AV97 -> 0 | AX97: =+AN97+AS97 -> 0 | AY97: =+AO97+AT97 -> 0 | AZ97: =+AX97-AY97 -> 0 | BA97: =+AQ97+AV97 -> 0 | BB97: =+AX97-BA97 -> 0 | BC97: =+料飲共通!H96/1000 -> 0 | BD97: =+料飲共通!I96/1000 -> 0 | BE97: =+BC97+BD97 -> 0 | BF97: =+料飲共通!W96/1000 -> 0 | BG97: 0 | BH97: =+BF97-BG97 -> 0 | BI97: 0 | BJ97: =+BF97-BI97 -> 0 | BK97: =+T97+AI97+AX97+BE97+BF97 -> 0 | BL97: =+U97+AJ97+AY97+BG97 -> 0 | BM97: =+BK97-BL97 -> 0 | BN97: =+W97+AL97+BA97+BI97 -> 0 | BO97: =+BK97-BN97 -> 0 | BP97: =+BK97-BE97 -> 0 | BQ97: =+BL97-Z97 -> 0 | BR97: =+BP97-BQ97 -> 0 | BS97: =+BN97-AB97 -> 0 | BT97: =+BP97-BS97 -> 0
A98: 販売費・一般管理費 | E98: =+ﾇｰﾍﾞﾙﾌﾟｰｽ!W97/1000 -> 84301.858 | F98: 83512.813 | G98: =+E98-F98 -> 789.04498 | H98: 83036 | I98: =+E98-H98 -> 1265.858 | J98: =+ｶﾌｪﾙﾎﾟ!W97/1000 -> 6405.162 | K98: 6853.973 | L98: =+J98-K98 -> -448.811 | M98: 5887 | N98: =+J98-M98 -> 518.162 | O98: =+ｶﾌｪｾﾚｽﾃ!W97/1000 -> 4993.967 | P98: 5459.698 | Q98: =+O98-P98 -> -465.731 | R98: 4955 | S98: =+O98-R98 -> 38.967 | T98: =+E98+J98+O98 -> 95700.987 | U98: =+F98+K98+P98 -> 95826.484 | V98: =+T98-U98 -> -125.49702 | W98: =+H98+M98+R98 -> 93878 | X98: =+T98-W98 -> 1822.987 | Y98: 0 | Z98: 7895.3104 | AA98: =+Y98-Z98 -> -7895.3104 | AB98: 14731 | AC98: =+Y98-AB98 -> -14731 | AD98: =+ｼﾞｭｴﾙｽﾞ!W97/1000 -> 93090.879 | AE98: 94500.211 | AF98: =+AD98-AE98 -> -1409.3316 | AG98: 89661 | AH98: =+AD98-AG98 -> 3429.8794 | AI98: =+Y98+AD98 -> 93090.879 | AJ98: =+Z98+AE98 -> 102395.52 | AK98: =+AI98-AJ98 -> -9304.642 | AL98: =+AB98+AG98 -> 104392 | AM98: =+AI98-AL98 -> -11301.121 | AN98: =+AN20+AN38+AN86 -> 102988.39 | AO98: 101422.97 | AP98: =+AN98-AO98 -> 1565.419 | AQ98: 114332 | AR98: =+AN98-AQ98 -> -11343.608 | AS98: =+AS20+AS38+AS86 -> 89563.119 | AT98: 100734.34 | AU98: =+AS98-AT98 -> -11171.222 | AV98: 68756 | AW98: =+AS98-AV98 -> 20807.119 | AX98: =+AN98+AS98 -> 192551.51 | AY98: =+AO98+AT98 -> 202157.31 | AZ98: =+AX98-AY98 -> -9605.8026 | BA98: =+AQ98+AV98 -> 183088 | BB98: =+AX98-BA98 -> 9463.5114 | BC98: =+BC20+BC38+BC86 -> 51986.063 | BD98: =+BD20+BD38+BD86 -> 29406.633 | BE98: =+BC98+BD98 -> 81392.696 | BF98: =+料飲共通!W97/1000 -> 28024.132 | BG98: 31553.218 | BH98: =+BF98-BG98 -> -3529.0856 | BI98: 28451 | BJ98: =+BF98-BI98 -> -426.86755 | BK98: =+T98+AI98+AX98+BE98+BF98 -> 490760.21 | BL98: =+U98+AJ98+AY98+BG98 -> 431932.54 | BM98: =+BK98-BL98 -> 58827.668 | BN98: =+W98+AL98+BA98+BI98 -> 409809 | BO98: =+BK98-BN98 -> 80951.206 | BP98: =+BK98-BE98 -> 409367.51 | BQ98: =+BL98-Z98 -> 424037.23 | BR98: =+BP98-BQ98 -> -14669.717 | BS98: =+BN98-AB98 -> 395078 | BT98: =+BP98-BS98 -> 14289.51
A99: 営業利益 | E99: =+ﾇｰﾍﾞﾙﾌﾟｰｽ!W98/1000 -> -14568.143 | F99: -14004.138 | G99: =+E99-F99 -> -564.00467 | H99: -20270 | I99: =+E99-H99 -> 5701.857 | J99: =+ｶﾌｪﾙﾎﾟ!W98/1000 -> -140.93604 | K99: -1241.8376 | L99: =+J99-K99 -> 1100.9016 | M99: 1018 | N99: =+J99-M99 -> -1158.936 | O99: =+ｶﾌｪｾﾚｽﾃ!W98/1000 -> 8662.088 | P99: 7673.2023 | Q99: =+O99-P99 -> 988.88574 | R99: 5845 | S99: =+O99-R99 -> 2817.088 | T99: =+E99+J99+O99 -> -6046.991 | U99: =+F99+K99+P99 -> -7572.7737 | V99: =+T99-U99 -> 1525.7827 | W99: =+H99+M99+R99 -> -13407 | X99: =+T99-W99 -> 7360.009 | Y99: 0 | Z99: 7870.9379 | AA99: =+Y99-Z99 -> -7870.9379 | AB99: -813 | AC99: =+Y99-AB99 -> 813 | AD99: =+ｼﾞｭｴﾙｽﾞ!W98/1000 -> 23985.671 | AE99: 18479.628 | AF99: =+AD99-AE99 -> 5506.0429 | AG99: 9181 | AH99: =+AD99-AG99 -> 14804.671 | AI99: =+Y99+AD99 -> 23985.671 | AJ99: =+Z99+AE99 -> 26350.566 | AK99: =+AI99-AJ99 -> -2364.895 | AL99: =+AB99+AG99 -> 8368 | AM99: =+AI99-AL99 -> 15617.671 | AN99: =+AN19-AN98 -> -8621.8033 | AO99: -10462.916 | AP99: =+AN99-AO99 -> 1841.1129 | AQ99: -21784 | AR99: =+AN99-AQ99 -> 13162.197 | AS99: =+AS19-AS98 -> 15800.809 | AT99: -3617.847 | AU99: =+AS99-AT99 -> 19418.656 | AV99: 26699 | AW99: =+AS99-AV99 -> -10898.191 | AX99: =+AN99+AS99 -> 7179.0056 | AY99: =+AO99+AT99 -> -14080.763 | AZ99: =+AX99-AY99 -> 21259.769 | BA99: =+AQ99+AV99 -> 4915 | BB99: =+AX99-BA99 -> 2264.0056 | BC99: =+BC19-BC98 -> 1900.5974 | BD99: =+BD19-BD98 -> 3289.927 | BE99: =+BC99+BD99 -> 5190.5244 | BF99: =+料飲共通!W98/1000 -> -28024.132 | BG99: -31553.218 | BH99: =+BF99-BG99 -> 3529.0856 | BI99: -28451 | BJ99: =+BF99-BI99 -> 426.86755 | BK99: =+T99+AI99+AX99+BE99+BF99 -> 2284.0779 | BL99: =+U99+AJ99+AY99+BG99 -> -26856.189 | BM99: =+BK99-BL99 -> 29140.266 | BN99: =+W99+AL99+BA99+BI99 -> -28575 | BO99: =+BK99-BN99 -> 30859.078 | BP99: =+BK99-BE99 -> -2906.4465 | BQ99: =+BL99-Z99 -> -34727.126 | BR99: =+BP99-BQ99 -> 31820.68 | BS99: =+BN99-AB99 -> -27762 | BT99: =+BP99-BS99 -> 24855.554
A100: 営業外収益 | E100: =+ﾇｰﾍﾞﾙﾌﾟｰｽ!W99/1000 -> 85.542 | F100: 85.542 | G100: =+E100-F100 -> 0 | H100: 94 | I100: =+E100-H100 -> -8.458 | J100: =+ｶﾌｪﾙﾎﾟ!W99/1000 -> 0 | K100: 0 | L100: =+J100-K100 -> 0 | M100: 1 | N100: =+J100-M100 -> -1 | O100: =+ｶﾌｪｾﾚｽﾃ!W99/1000 -> 0 | P100: 0 | Q100: =+O100-P100 -> 0 | R100: 3 | S100: =+O100-R100 -> -3 | T100: =+E100+J100+O100 -> 85.542 | U100: =+F100+K100+P100 -> 85.542 | V100: =+T100-U100 -> 0 | W100: =+H100+M100+R100 -> 98 | X100: =+T100-W100 -> -12.458 | Y100: 0 | Z100: 0 | AA100: =+Y100-Z100 -> 0 | AB100: 0 | AC100: =+Y100-AB100 -> 0 | AD100: =+ｼﾞｭｴﾙｽﾞ!W99/1000 -> 480.93 | AE100: 480.93 | AF100: =+AD100-AE100 -> 0 | AG100: 2889 | AH100: =+AD100-AG100 -> -2408.07 | AI100: =+Y100+AD100 -> 480.93 | AJ100: =+Z100+AE100 -> 480.93 | AK100: =+AI100-AJ100 -> 0 | AL100: =+AB100+AG100 -> 2889 | AM100: =+AI100-AL100 -> -2408.07 | AN100: =+ｶﾞｰﾃﾞﾝ!W99/1000 -> 41.814 | AO100: 41.814 | AP100: =+AN100-AO100 -> 0 | AQ100: 27 | AR100: =+AN100-AQ100 -> 14.814 | AS100: =+ﾋﾞｱｶﾞｰﾃﾞﾝ!W99/1000 -> 0 | AT100: 0 | AU100: =+AS100-AT100 -> 0 | AV100: 3 | AW100: =+AS100-AV100 -> -3 | AX100: =+AN100+AS100 -> 41.814 | AY100: =+AO100+AT100 -> 41.814 | AZ100: =+AX100-AY100 -> 0 | BA100: =+AQ100+AV100 -> 30 | BB100: =+AX100-BA100 -> 11.814 | BC100: 0 | BD100: 0 | BE100: =+BC100+BD100 -> 0 | BF100: =+料飲共通!W99/1000 -> 15 | BG100: 15 | BH100: =+BF100-BG100 -> 0 | BI100: 0 | BJ100: =+BF100-BI100 -> 15 | BK100: =+T100+AI100+AX100+BE100+BF100 -> 623.286 | BL100: =+U100+AJ100+AY100+BG100 -> 623.286 | BM100: =+BK100-BL100 -> 0 | BN100: =+W100+AL100+BA100+BI100 -> 3017 | BO100: =+BK100-BN100 -> -2393.714 | BP100: =+BK100-BE100 -> 623.286 | BQ100: =+BL100-Z100 -> 623.286 | BR100: =+BP100-BQ100 -> 0 | BS100: =+BN100-AB100 -> 3017 | BT100: =+BP100-BS100 -> -2393.714
...

Sheet 料飲共通
A1: ■（Ｒ７年度）事業予算入力用
A3: 部門 料飲共通
A4: コード | B4: 名称 | K4: 令和 7年 4月 | L4: 令和 7年 5月 | M4: 令和 7年 6月 | N4: 令和 7年 7月 | O4: 令和 7年 8月 | P4: 令和 7年 9月 | Q4: 令和 7年 10月 | R4: 令和 7年 11月 | S4: 令和 7年 12月 | T4: 令和 8年 1月 | U4: 令和 8年 2月 | V4: 令和 8年 3月 | W4: 合計
K5: ①当期実績 | L5: ①当期実績 | M5: ①当期実績 | N5: ①当期実績 | O5: ①当期実績 | P5: ①当期実績 | Q5: ①当期実績 | R5: ①当期実績 | S5: ①当期実績 | T5: ①当期実績 | U5: ①当期実績 | V5: ①当期実績 | W5: ①当期実績
A6: 10000 | B6: 総売上高 | K6: =SUM(K7:K16) -> 0 | L6: =SUM(L7:L16) -> 0 | M6: =SUM(M7:M16) -> 0 | N6: =SUM(N7:N16) -> 0 | O6: =SUM(O7:O16) -> 0 | P6: =SUM(P7:P16) -> 0 | Q6: =SUM(Q7:Q16) -> 0 | R6: =SUM(R7:R16) -> 0 | ... V6: =SUM(V7:V16) -> 0 | W6: =SUM(K6:V6) -> 0
A7: 10001 | C7: 売上 | K7: 0 | L7: 0 | M7: 0 | N7: 0 | O7: 0 | P7: 0 | Q7: 0 | R7: 0 | S7: 0 | T7: 0 | U7: 0 | V7: 0 | W7: =SUM(K7:V7) -> 0
A8: 10002 | C8: 損保代理店収入 | K8: 0 | L8: 0 | M8: 0 | N8: 0 | O8: 0 | P8: 0 | Q8: 0 | R8: 0 | S8: 0 | T8: 0 | U8: 0 | V8: 0 | W8: =SUM(K8:V8) -> 0
A9: 10003 | C9: 販売手数料収入 | K9: 0 | L9: 0 | M9: 0 | N9: 0 | O9: 0 | P9: 0 | Q9: 0 | R9: 0 | S9: 0 | T9: 0 | U9: 0 | V9: 0 | W9: =SUM(K9:V9) -> 0
A10: 10004 | C10: 索道収入 | K10: 0 | L10: 0 | M10: 0 | N10: 0 | O10: 0 | P10: 0 | Q10: 0 | R10: 0 | S10: 0 | T10: 0 | U10: 0 | V10: 0 | W10: =SUM(K10:V10) -> 0
A11: 10005 | C11: 地代収入 | K11: 0 | L11: 0 | M11: 0 | N11: 0 | O11: 0 | P11: 0 | Q11: 0 | R11: 0 | S11: 0 | T11: 0 | U11: 0 | V11: 0 | W11: =SUM(K11:V11) -> 0
A12: 10006 | C12: 家賃収入 | K12: 0 | L12: 0 | M12: 0 | N12: 0 | O12: 0 | P12: 0 | Q12: 0 | R12: 0 | S12: 0 | T12: 0 | U12: 0 | V12: 0 | W12: =SUM(K12:V12) -> 0
A13: 10007 | C13: 駐車場収入 | K13: 0 | L13: 0 | M13: 0 | N13: 0 | O13: 0 | P13: 0 | Q13: 0 | R13: 0 | S13: 0 | T13: 0 | U13: 0 | V13: 0 | W13: =SUM(K13:V13) -> 0
A14: 10008 | C14: 受託料 | K14: 0 | L14: 0 | M14: 0 | N14: 0 | O14: 0 | P14: 0 | Q14: 0 | R14: 0 | S14: 0 | T14: 0 | U14: 0 | V14: 0 | W14: =SUM(K14:V14) -> 0
A15: 10009 | C15: 利用料金収入 | K15: 0 | L15: 0 | M15: 0 | N15: 0 | O15: 0 | P15: 0 | Q15: 0 | R15: 0 | S15: 0 | T15: 0 | U15: 0 | V15: 0 | W15: =SUM(K15:V15) -> 0
A16: 10010 | C16: 管理手数料収入 | K16: 0 | L16: 0 | M16: 0 | N16: 0 | O16: 0 | P16: 0 | Q16: 0 | R16: 0 | S16: 0 | T16: 0 | U16: 0 | V16: 0 | W16: =SUM(K16:V16) -> 0
A17: 20000 | B17: 売上原価 | K17: 0 | L17: 0 | M17: 0 | N17: 0 | O17: 0 | P17: 0 | Q17: 0 | R17: 0 | S17: 0 | T17: 0 | U17: 0 | V17: 0 | W17: =SUM(K17:V17) -> 0
A18: 30000 | B18: 売上総利益 | K18: =K6-K17 -> 0 | L18: =L6-L17 -> 0 | M18: =M6-M17 -> 0 | N18: =N6-N17 -> 0 | O18: =O6-O17 -> 0 | P18: =P6-P17 -> 0 | Q18: =Q6-Q17 -> 0 | R18: =R6-R17 -> 0 | ... V18: =V6-V17 -> 0 | W18: =SUM(K18:V18) -> 0
A19: 41000 | B19: 人件費 | K19: =SUM(K20:K22,K26,K29:K31,K35:K36) -> 1413826 | L19: =SUM(L20:L22,L26,L29:L31,L35:L36) -> 1563519 | M19: =SUM(M20:M22,M26,M29:M31,M35:M36) -> 4176417 | N19: =SUM(N20:N22,N26,N29:N31,N35:N36) -> 1952116.4 | O19: =SUM(O20:O22,O26,O29:O31,O35:O36) -> 1563519 | P19: =SUM(P20:P22,P26,P29:P31,P35:P36) -> 1563519 | Q19: =SUM(Q20:Q22,Q26,Q29:Q31,Q35:Q36) -> 2087682 | R19: =SUM(R20:R22,R26,R29:R31,R35:R36) -> 1642043.4 | ... V19: =SUM(V20:V22,V26,V29:V31,V35:V36) -> 1764317 | W19: =SUM(K19:V19) -> 25580282
A20: 41010 | C20: 役員報酬 | K20: 0 | L20: 0 | M20: 0 | N20: 0 | O20: 0 | P20: 0 | Q20: 0 | R20: 0 | S20: 0 | T20: 0 | U20: 0 | V20: 0 | W20: =SUM(K20:V20) -> 0
A21: 41020 | C21: 社員給与費 | K21: 1334450 | L21: 1334450 | M21: 3915635 | N21: 1334450 | O21: 1334450 | P21: 1334450 | Q21: 1852250 | R21: 1334450 | S21: 4046195 | T21: 1345420 | U21: 1334450 | V21: 1345420 | W21: =SUM(K21:V21) -> 21846070
A22: 41030 | C22: 専門等給与費 | K22: =SUM(K23:K25) -> 0 | L22: =SUM(L23:L25) -> 0 | M22: =SUM(M23:M25) -> 0 | N22: =SUM(N23:N25) -> 0 | O22: =SUM(O23:O25) -> 0 | P22: =SUM(P23:P25) -> 0 | Q22: =SUM(Q23:Q25) -> 0 | R22: =SUM(R23:R25) -> 0 | ... V22: =SUM(V23:V25) -> 0 | W22: =SUM(K22:V22) -> 0
A23: 41031 | D23: 専門 | K23: 0 | L23: 0 | M23: 0 | N23: 0 | O23: 0 | P23: 0 | Q23: 0 | R23: 0 | S23: 0 | T23: 0 | U23: 0 | V23: 0 | W23: =SUM(K23:V23) -> 0
A24: 41032 | D24: 臨時 | K24: 0 | L24: 0 | M24: 0 | N24: 0 | O24: 0 | P24: 0 | Q24: 0 | R24: 0 | S24: 0 | T24: 0 | U24: 0 | V24: 0 | W24: =SUM(K24:V24) -> 0
A25: 41033 | D25: パート | K25: 0 | L25: 0 | M25: 0 | N25: 0 | O25: 0 | P25: 0 | Q25: 0 | R25: 0 | S25: 0 | T25: 0 | U25: 0 | V25: 0 | W25: =SUM(K25:V25) -> 0
A26: 41040 | C26: 退職金 | K26: 0 | L26: 0 | M26: 0 | N26: 0 | O26: 0 | P26: 0 | Q26: 0 | R26: 0 | S26: 0 | T26: 0 | U26: 0 | V26: 0 | W26: =SUM(K26:V26) -> 0
A27: 41041 | D27: 役員 | W27: =SUM(K27:V27) -> 0
A28: 41042 | D28: 社員 | W28: =SUM(K28:V28) -> 0
A29: 41050 | C29: 法定福利費 | K29: 16638 | L29: 206331 | M29: 238044 | N29: 594928.4 | O29: 206331 | P29: 206331 | Q29: 212694 | R29: 284855.37 | S29: 239646 | T29: 613067.68 | U29: 206331 | V29: 396159 | W29: =SUM(K29:V29) -> 3421356.4
A30: 41060 | C30: 退職年金掛金 | K30: 1200 | L30: 1200 | M30: 1200 | N30: 1200 | O30: 1200 | P30: 1200 | Q30: 1200 | R30: 1200 | S30: 1200 | T30: 1200 | U30: 1200 | V30: 1200 | W30: =SUM(K30:V30) -> 14400
A31: 41070 | C31: 福利厚生費 | K31: =SUM(K32:K34) -> 41800 | L31: =SUM(L32:L34) -> 1800 | M31: =SUM(M32:M34) -> 1800 | N31: =SUM(N32:N34) -> 1800 | O31: =SUM(O32:O34) -> 1800 | P31: =SUM(P32:P34) -> 1800 | Q31: =SUM(Q32:Q34) -> 1800 | R31: =SUM(R32:R34) -> 1800 | ... V31: =SUM(V32:V34) -> 1800 | W31: =SUM(K31:V31) -> 61600
A32: 41071 | D32: 福利厚生費 | K32: 1800 | L32: 1800 | M32: 1800 | N32: 1800 | O32: 1800 | P32: 1800 | Q32: 1800 | R32: 1800 | S32: 1800 | T32: 1800 | U32: 1800 | V32: 1800 | W32: =SUM(K32:V32) -> 21600
A33: 41072 | D33: 被服費 | K33: 40000 | L33: 0 | M33: 0 | N33: 0 | O33: 0 | P33: 0 | Q33: 0 | R33: 0 | S33: 0 | T33: 0 | U33: 0 | V33: 0 | W33: =SUM(K33:V33) -> 40000
A34: 41073 | D34: 研修費 | U34: 0 | V34: 0 | W34: =SUM(K34:V34) -> 0
A35: 41080 | C35: 通勤費 | K35: 19738 | L35: 19738 | M35: 19738 | N35: 19738 | O35: 19738 | P35: 19738 | Q35: 19738 | R35: 19738 | S35: 19738 | T35: 19738 | U35: 19738 | V35: 19738 | W35: =SUM(K35:V35) -> 236856
A36: 41090 | C36: 引当金繰入額 | W36: =SUM(K36:V36) -> 0
A37: 42000 | B37: 物件費 | K37: =SUM(K38:K41,K46,K50,K57:K58,K61:K67,K70:K72,K78:K80,K83:K84) -> 70300 | L37: =SUM(L38:L41,L46,L50,L57:L58,L61:L67,L70:L72,L78:L80,L83:L84) -> 75300 | M37: =SUM(M38:M41,M46,M50,M57:M58,M61:M67,M70:M72,M78:M80,M83:M84) -> 260800 | N37: =SUM(N38:N41,N46,N50,N57:N58,N61:N67,N70:N72,N78:N80,N83:N84) -> 100300 | O37: =SUM(O38:O41,O46,O50,O57:O58,O61:O67,O70:O72,O78:O80,O83:O84) -> 104550 | P37: =SUM(P38:P41,P46,P50,P57:P58,P61:P67,P70:P72,P78:P80,P83:P84) -> 130300 | Q37: =SUM(Q38:Q41,Q46,Q50,Q57:Q58,Q61:Q67,Q70:Q72,Q78:Q80,Q83:Q84) -> 50800 | R37: =SUM(R38:R41,R46,R50,R57:R58,R61:R67,R70:R72,R78:R80,R83:R84) -> 475300 | ... V37: =SUM(V38:V41,V46,V50,V57:V58,V61:V67,V70:V72,V78:V80,V83:V84) -> 246300 | W37: =SUM(K37:V37) -> 2443850
A38: 42010 | C38: 消耗品費 | K38: 0 | L38: 0 | M38: 0 | N38: 0 | O38: 0 | P38: 0 | Q38: 0 | R38: 0 | S38: 0 | T38: 0 | U38: 0 | V38: 0 | W38: =SUM(K38:V38) -> 0
A39: 42020 | C39: 事務用品費 | K39: 0 | L39: 0 | M39: 0 | N39: 0 | O39: 0 | P39: 0 | Q39: 0 | R39: 0 | S39: 0 | T39: 0 | U39: 0 | V39: 0 | W39: =SUM(K39:V39) -> 0
A40: 42030 | C40: 図書購入費 | K40: 0 | L40: 0 | M40: 0 | N40: 0 | O40: 0 | P40: 0 | Q40: 0 | R40: 0 | S40: 0 | T40: 0 | U40: 0 | V40: 0 | W40: =SUM(K40:V40) -> 0
A41: 42040 | C41: 賃借料 | K41: =SUM(K42:K45) -> 0 | L41: =SUM(L42:L45) -> 0 | M41: =SUM(M42:M45) -> 0 | N41: =SUM(N42:N45) -> 0 | O41: =SUM(O42:O45) -> 0 | P41: =SUM(P42:P45) -> 0 | Q41: =SUM(Q42:Q45) -> 0 | R41: =SUM(R42:R45) -> 0 | ... V41: =SUM(V42:V45) -> 0 | W41: =SUM(K41:V41) -> 0
A42: 42041 | D42: 土地使用料 | K42: 0 | L42: 0 | M42: 0 | N42: 0 | O42: 0 | P42: 0 | Q42: 0 | R42: 0 | S42: 0 | T42: 0 | U42: 0 | V42: 0 | W42: =SUM(K42:V42) -> 0
A43: 42042 | D43: 建物使用料 | K43: 0 | L43: 0 | M43: 0 | N43: 0 | O43: 0 | P43: 0 | Q43: 0 | R43: 0 | S43: 0 | T43: 0 | U43: 0 | V43: 0 | W43: =SUM(K43:V43) -> 0
A44: 42043 | D44: 施設使用料 | K44: 0 | L44: 0 | M44: 0 | N44: 0 | O44: 0 | P44: 0 | Q44: 0 | R44: 0 | S44: 0 | T44: 0 | U44: 0 | V44: 0 | W44: =SUM(K44:V44) -> 0
A45: 42044 | D45: リース料 | K45: 0 | L45: 0 | M45: 0 | N45: 0 | O45: 0 | P45: 0 | Q45: 0 | R45: 0 | S45: 0 | T45: 0 | U45: 0 | V45: 0 | W45: =SUM(K45:V45) -> 0
A46: 42050 | C46: 保険料 | K46: =SUM(K47:K49) -> 0 | L46: =SUM(L47:L49) -> 0 | M46: =SUM(M47:M49) -> 0 | N46: =SUM(N47:N49) -> 0 | O46: =SUM(O47:O49) -> 0 | P46: =SUM(P47:P49) -> 0 | Q46: =SUM(Q47:Q49) -> 0 | R46: =SUM(R47:R49) -> 0 | ... V46: =SUM(V47:V49) -> 0 | W46: =SUM(K46:V46) -> 0
A47: 42051 | D47: 火災保険料 | K47: 0 | L47: 0 | M47: 0 | N47: 0 | O47: 0 | P47: 0 | Q47: 0 | R47: 0 | S47: 0 | T47: 0 | U47: 0 | V47: 0 | W47: =SUM(K47:V47) -> 0
A48: 42052 | D48: 賠償保険料 | K48: 0 | L48: 0 | M48: 0 | N48: 0 | O48: 0 | P48: 0 | Q48: 0 | R48: 0 | S48: 0 | T48: 0 | U48: 0 | V48: 0 | W48: =SUM(K48:V48) -> 0
A49: 42053 | D49: 動産保険料 | K49: 0 | L49: 0 | M49: 0 | N49: 0 | O49: 0 | P49: 0 | Q49: 0 | R49: 0 | S49: 0 | T49: 0 | U49: 0 | V49: 0 | W49: =SUM(K49:V49) -> 0
A50: 42060 | C50: 修繕費 | K50: =SUM(K51:K56) -> 0 | L50: =SUM(L51:L56) -> 0 | M50: =SUM(M51:M56) -> 0 | N50: =SUM(N51:N56) -> 0 | O50: =SUM(O51:O56) -> 0 | P50: =SUM(P51:P56) -> 0 | Q50: =SUM(Q51:Q56) -> 0 | R50: =SUM(R51:R56) -> 0 | ... V50: =SUM(V51:V56) -> 0 | W50: =SUM(K50:V50) -> 0
A51: 42061 | D51: 建物 | K51: 0 | L51: 0 | M51: 0 | N51: 0 | O51: 0 | P51: 0 | Q51: 0 | R51: 0 | S51: 0 | T51: 0 | U51: 0 | V51: 0 | W51: =SUM(K51:V51) -> 0
A52: 42062 | D52: 建物付属設備 | K52: 0 | L52: 0 | M52: 0 | N52: 0 | O52: 0 | P52: 0 | Q52: 0 | R52: 0 | S52: 0 | T52: 0 | U52: 0 | V52: 0 | W52: =SUM(K52:V52) -> 0
A53: 42063 | D53: 構築物 | K53: 0 | L53: 0 | M53: 0 | N53: 0 | O53: 0 | P53: 0 | Q53: 0 | R53: 0 | S53: 0 | T53: 0 | U53: 0 | V53: 0 | W53: =SUM(K53:V53) -> 0
A54: 42064 | D54: 機械 | K54: 0 | L54: 0 | M54: 0 | N54: 0 | O54: 0 | P54: 0 | Q54: 0 | R54: 0 | S54: 0 | T54: 0 | U54: 0 | V54: 0 | W54: =SUM(K54:V54) -> 0
A55: 42065 | D55: 器具備品 | K55: 0 | L55: 0 | M55: 0 | N55: 0 | O55: 0 | P55: 0 | Q55: 0 | R55: 0 | S55: 0 | T55: 0 | U55: 0 | V55: 0 | W55: =SUM(K55:V55) -> 0
A56: 42066 | D56: 車両 | K56: 0 | L56: 0 | M56: 0 | N56: 0 | O56: 0 | P56: 0 | Q56: 0 | R56: 0 | S56: 0 | T56: 0 | U56: 0 | V56: 0 | W56: =SUM(K56:V56) -> 0
A57: 42070 | C57: 車両運搬費 | K57: 0 | L57: 0 | M57: 0 | N57: 0 | O57: 0 | P57: 0 | Q57: 0 | R57: 0 | S57: 0 | T57: 0 | U57: 0 | V57: 0 | W57: =SUM(K57:V57) -> 0
A58: 42080 | C58: 印刷製本費 | K58: =SUM(K59:K60) -> 20000 | L58: =SUM(L59:L60) -> 0 | M58: =SUM(M59:M60) -> 0 | N58: =SUM(N59:N60) -> 0 | O58: =SUM(O59:O60) -> 0 | P58: =SUM(P59:P60) -> 20000 | Q58: =SUM(Q59:Q60) -> 0 | R58: =SUM(R59:R60) -> 0 | ... V58: =SUM(V59:V60) -> 0 | W58: =SUM(K58:V58) -> 60000
A59: 42081 | D59: 印刷製本費 | K59: 20000 | L59: 0 | M59: 0 | N59: 0 | O59: 0 | P59: 20000 | Q59: 0 | R59: 0 | S59: 0 | T59: 20000 | U59: 0 | V59: 0 | W59: =SUM(K59:V59) -> 60000
A60: 42082 | D60: 乗車券帳票費 | K60: 0 | L60: 0 | M60: 0 | N60: 0 | O60: 0 | P60: 0 | Q60: 0 | R60: 0 | S60: 0 | T60: 0 | U60: 0 | V60: 0 | W60: =SUM(K60:V60) -> 0
A61: 42090 | C61: 清掃衛生費 | K61: 0 | L61: 0 | M61: 0 | N61: 0 | O61: 0 | P61: 0 | Q61: 0 | R61: 0 | S61: 0 | T61: 0 | U61: 0 | V61: 0 | W61: =SUM(K61:V61) -> 0
A62: 42100 | C62: 事務会議費 | K62: 0 | L62: 0 | M62: 0 | N62: 0 | O62: 0 | P62: 0 | Q62: 0 | R62: 0 | S62: 0 | T62: 0 | U62: 0 | V62: 0 | W62: =SUM(K62:V62) -> 0
A63: 42110 | C63: 租税公課 | K63: 0 | L63: 0 | M63: 0 | N63: 0 | O63: 0 | P63: 0 | Q63: 0 | R63: 0 | S63: 0 | T63: 0 | U63: 0 | V63: 0 | W63: =SUM(K63:V63) -> 0
A64: 42120 | C64: 会費負担金 | K64: 0 | L64: 0 | M64: 0 | N64: 0 | O64: 0 | P64: 0 | Q64: 0 | R64: 0 | S64: 15000 | T64: 0 | U64: 0 | V64: 0 | W64: =SUM(K64:V64) -> 15000
A65: 42130 | C65: 委託料 | K65: 7500 | L65: 32000 | M65: 7500 | N65: 32000 | O65: 36250 | P65: 32000 | Q65: 7500 | R65: 32000 | S65: 168500 | T65: 193000 | U65: 168500 | V65: 193000 | W65: =SUM(K65:V65) -> 909750
A66: 42140 | C66: 除雪費 | K66: 0 | L66: 0 | M66: 0 | N66: 0 | O66: 0 | P66: 0 | Q66: 0 | R66: 0 | S66: 0 | T66: 0 | U66: 0 | V66: 0 | W66: =SUM(K66:V66) -> 0
A67: 42150 | C67: 販売促進費 | K67: =SUM(K68:K69) -> 500 | L67: =SUM(L68:L69) -> 1000 | M67: =SUM(M68:M69) -> 1000 | N67: =SUM(N68:N69) -> 1000 | O67: =SUM(O68:O69) -> 1000 | P67: =SUM(P68:P69) -> 1000 | Q67: =SUM(Q68:Q69) -> 1000 | R67: =SUM(R68:R69) -> 1000 | ... V67: =SUM(V68:V69) -> 1000 | W67: =SUM(K67:V67) -> 11500
A68: 42151 | D68: 販売促進費 | K68: 500 | L68: 1000 | M68: 1000 | N68: 1000 | O68: 1000 | P68: 1000 | Q68: 1000 | R68: 1000 | S68: 1000 | T68: 1000 | U68: 1000 | V68: 1000 | W68: =SUM(K68:V68) -> 11500
A69: 42152 | D69: 乗車券販売手数料 | K69: 0 | L69: 0 | M69: 0 | N69: 0 | O69: 0 | P69: 0 | Q69: 0 | R69: 0 | S69: 0 | T69: 0 | U69: 0 | V69: 0 | W69: =SUM(K69:V69) -> 0
A70: 42160 | C70: 旅費交通費 | K70: 26500 | L70: 26500 | M70: 226500 | N70: 51500 | O70: 51500 | P70: 51500 | Q70: 26500 | R70: 26500 | S70: 51500 | T70: 26500 | U70: 226500 | V70: 26500 | W70: =SUM(K70:V70) -> 818000
A71: 42170 | C71: 通信連絡費 | K71: 15800 | L71: 15800 | M71: 15800 | N71: 15800 | O71: 15800 | P71: 15800 | Q71: 15800 | R71: 15800 | S71: 15800 | T71: 15800 | U71: 15800 | V71: 15800 | W71: =SUM(K71:V71) -> 189600
A72: 42180 | C72: 水道光熱費 | K72: =SUM(K73:K77) -> 0 | L72: =SUM(L73:L77) -> 0 | M72: =SUM(M73:M77) -> 0 | N72: =SUM(N73:N77) -> 0 | O72: =SUM(O73:O77) -> 0 | P72: =SUM(P73:P77) -> 0 | Q72: =SUM(Q73:Q77) -> 0 | R72: =SUM(R73:R77) -> 0 | ... V72: =SUM(V73:V77) -> 0 | W72: =SUM(K72:V72) -> 0
A73: 42181 | D73: 電灯使用料 | K73: 0 | L73: 0 | M73: 0 | N73: 0 | O73: 0 | P73: 0 | Q73: 0 | R73: 0 | S73: 0 | T73: 0 | U73: 0 | V73: 0 | W73: =SUM(K73:V73) -> 0
A74: 42182 | D74: 水道使用料 | K74: 0 | L74: 0 | M74: 0 | N74: 0 | O74: 0 | P74: 0 | Q74: 0 | R74: 0 | S74: 0 | T74: 0 | U74: 0 | V74: 0 | W74: =SUM(K74:V74) -> 0
A75: 42183 | D75: ガス使用料 | K75: 0 | L75: 0 | M75: 0 | N75: 0 | O75: 0 | P75: 0 | Q75: 0 | R75: 0 | S75: 0 | T75: 0 | U75: 0 | V75: 0 | W75: =SUM(K75:V75) -> 0
A76: 42184 | D76: 暖房燃料費 | K76: 0 | L76: 0 | M76: 0 | N76: 0 | O76: 0 | P76: 0 | Q76: 0 | R76: 0 | S76: 0 | T76: 0 | U76: 0 | V76: 0 | W76: =SUM(K76:V76) -> 0
A77: 42185 | D77: 電力使用料 | K77: 0 | L77: 0 | M77: 0 | N77: 0 | O77: 0 | P77: 0 | Q77: 0 | R77: 0 | S77: 0 | T77: 0 | U77: 0 | V77: 0 | W77: =SUM(K77:V77) -> 0
A78: 42190 | C78: 諸手数料 | K78: 0 | L78: 0 | M78: 0 | N78: 0 | O78: 0 | P78: 0 | Q78: 0 | R78: 0 | S78: 0 | T78: 0 | U78: 0 | V78: 0 | W78: =SUM(K78:V78) -> 0
A79: 42200 | C79: 広告宣伝費 | K79: 0 | L79: 0 | M79: 0 | N79: 0 | O79: 0 | P79: 0 | Q79: 0 | R79: 400000 | S79: 0 | T79: 0 | U79: 0 | V79: 0 | W79: =SUM(K79:V79) -> 400000
A80: 42210 | C80: 交際費 | K80: =SUM(K81:K82) -> 0 | L80: =SUM(L81:L82) -> 0 | M80: =SUM(M81:M82) -> 10000 | N80: =SUM(N81:N82) -> 0 | O80: =SUM(O81:O82) -> 0 | P80: =SUM(P81:P82) -> 10000 | Q80: =SUM(Q81:Q82) -> 0 | R80: =SUM(R81:R82) -> 0 | ... V80: =SUM(V81:V82) -> 10000 | W80: =SUM(K80:V80) -> 40000
A81: 42211 | D81: 接待交際費 | K81: 0 | L81: 0 | M81: 10000 | N81: 0 | O81: 0 | P81: 10000 | Q81: 0 | R81: 0 | S81: 10000 | T81: 0 | U81: 0 | V81: 10000 | W81: =SUM(K81:V81) -> 40000
A82: 42212 | D82: 贈答用品費 | K82: 0 | L82: 0 | M82: 0 | N82: 0 | O82: 0 | P82: 0 | Q82: 0 | R82: 0 | S82: 0 | T82: 0 | U82: 0 | V82: 0 | W82: =SUM(K82:V82) -> 0
A83: 42220 | C83: 寄付金 | K83: 0 | L83: 0 | M83: 0 | N83: 0 | O83: 0 | P83: 0 | Q83: 0 | R83: 0 | S83: 0 | T83: 0 | U83: 0 | V83: 0 | W83: =SUM(K83:V83) -> 0
A84: 42230 | C84: 雑費用 | K84: 0 | L84: 0 | M84: 0 | N84: 0 | O84: 0 | P84: 0 | Q84: 0 | R84: 0 | S84: 0 | T84: 0 | U84: 0 | V84: 0 | W84: =SUM(K84:V84) -> 0
A85: 43000 | B85: 減価償却費 | K85: =SUM(K86:K96) -> 0 | L85: =SUM(L86:L96) -> 0 | M85: =SUM(M86:M96) -> 0 | N85: =SUM(N86:N96) -> 0 | O85: =SUM(O86:O96) -> 0 | P85: =SUM(P86:P96) -> 0 | Q85: =SUM(Q86:Q96) -> 0 | R85: =SUM(R86:R96) -> 0 | ... V85: =SUM(V86:V96) -> 0 | W85: =SUM(K85:V85) -> 0
A86: 43010 | C86: 建物 | K86: 0 | L86: 0 | M86: 0 | N86: 0 | O86: 0 | P86: 0 | Q86: 0 | R86: 0 | S86: 0 | T86: 0 | U86: 0 | V86: 0 | W86: =SUM(K86:V86) -> 0
A87: 43020 | C87: 建物附属設備 | K87: 0 | L87: 0 | M87: 0 | N87: 0 | O87: 0 | P87: 0 | Q87: 0 | R87: 0 | S87: 0 | T87: 0 | U87: 0 | V87: 0 | W87: =SUM(K87:V87) -> 0
A88: 43030 | C88: 構築物 | K88: 0 | L88: 0 | M88: 0 | N88: 0 | O88: 0 | P88: 0 | Q88: 0 | R88: 0 | S88: 0 | T88: 0 | U88: 0 | V88: 0 | W88: =SUM(K88:V88) -> 0
A89: 43040 | C89: 機械・装置 | K89: 0 | L89: 0 | M89: 0 | N89: 0 | O89: 0 | P89: 0 | Q89: 0 | R89: 0 | S89: 0 | T89: 0 | U89: 0 | V89: 0 | W89: =SUM(K89:V89) -> 0
A90: 43050 | C90: 器具備品 | K90: 0 | L90: 0 | M90: 0 | N90: 0 | O90: 0 | P90: 0 | Q90: 0 | R90: 0 | S90: 0 | T90: 0 | U90: 0 | V90: 0 | W90: =SUM(K90:V90) -> 0
A91: 43060 | C91: 車両 | K91: 0 | L91: 0 | M91: 0 | N91: 0 | O91: 0 | P91: 0 | Q91: 0 | R91: 0 | S91: 0 | T91: 0 | U91: 0 | V91: 0 | W91: =SUM(K91:V91) -> 0
A92: 43070 | C92: 少額資産 | K92: 0 | L92: 0 | M92: 0 | N92: 0 | O92: 0 | P92: 0 | Q92: 0 | R92: 0 | S92: 0 | T92: 0 | U92: 0 | V92: 0 | W92: =SUM(K92:V92) -> 0
A93: 43080 | C93: 商標権 | K93: 0 | L93: 0 | M93: 0 | N93: 0 | O93: 0 | P93: 0 | Q93: 0 | R93: 0 | S93: 0 | T93: 0 | U93: 0 | V93: 0 | W93: =SUM(K93:V93) -> 0
A94: 43090 | C94: ソフトウェア | K94: 0 | L94: 0 | M94: 0 | N94: 0 | O94: 0 | P94: 0 | Q94: 0 | R94: 0 | S94: 0 | T94: 0 | U94: 0 | V94: 0 | W94: =SUM(K94:V94) -> 0
A95: 43100 | C95: 長期前払費用 | K95: 0 | L95: 0 | M95: 0 | N95: 0 | O95: 0 | P95: 0 | Q95: 0 | R95: 0 | S95: 0 | T95: 0 | U95: 0 | V95: 0 | W95: =SUM(K95:V95) -> 0
A96: 43110 | C96: リース資産 | K96: 0 | L96: 0 | M96: 0 | N96: 0 | O96: 0 | P96: 0 | Q96: 0 | R96: 0 | S96: 0 | T96: 0 | U96: 0 | V96: 0 | W96: =SUM(K96:V96) -> 0
A97: 40000 | B97: 販売費・一般管理費 | K97: =K37+K19+K85 -> 1484126 | L97: =L37+L19+L85 -> 1638819 | M97: =M37+M19+M85 -> 4437217 | N97: =N37+N19+N85 -> 2052416.4 | O97: =O37+O19+O85 -> 1668069 | P97: =P37+P19+P85 -> 1693819 | Q97: =Q37+Q19+Q85 -> 2138482 | R97: =R37+R19+R85 -> 2117343.4 | ... V97: =V37+V19+V85 -> 2010617 | W97: =SUM(K97:V97) -> 28024132
A98: 50000 | B98: 営業利益 | K98: =K18-K97 -> -1484126 | L98: =L18-L97 -> -1638819 | M98: =M18-M97 -> -4437217 | N98: =N18-N97 -> -2052416.4 | O98: =O18-O97 -> -1668069 | P98: =P18-P97 -> -1693819 | Q98: =Q18-Q97 -> -2138482 | R98: =R18-R97 -> -2117343.4 | ... V98: =V18-V97 -> -2010617 | W98: =SUM(K98:V98) -> -28024132
A99: 61000 | B99: 営業外収益 | K99: =SUM(K100,K104:K106) -> 10000 | L99: =SUM(L100,L104:L106) -> 0 | M99: =SUM(M100,M104:M106) -> 0 | N99: =SUM(N100,N104:N106) -> 0 | O99: =SUM(O100,O104:O106) -> 5000 | P99: =SUM(P100,P104:P106) -> 0 | Q99: =SUM(Q100,Q104:Q106) -> 0 | R99: =SUM(R100,R104:R106) -> 0 | ... V99: =SUM(V100,V104:V106) -> 0 | W99: =SUM(K99:V99) -> 15000
A100: 61010 | C100: 受取利息 | K100: =SUM(K101:K103) -> 0 | L100: =SUM(L101:L103) -> 0 | M100: =SUM(M101:M103) -> 0 | N100: =SUM(N101:N103) -> 0 | O100: =SUM(O101:O103) -> 0 | P100: =SUM(P101:P103) -> 0 | Q100: =SUM(Q101:Q103) -> 0 | R100: =SUM(R101:R103) -> 0 | ... V100: =SUM(V101:V103) -> 0 | W100: =SUM(K100:V100) -> 0
A101: 61011 | D101: 定期預金 | K101: 0 | L101: 0 | M101: 0 | N101: 0 | O101: 0 | P101: 0 | Q101: 0 | R101: 0 | S101: 0 | T101: 0 | U101: 0 | V101: 0 | W101: =SUM(K101:V101) -> 0
...

Sheet ﾇｰﾍﾞﾙﾌﾟｰｽ
A1: ■（Ｒ７年度）事業予算入力用
A3: 部門 ﾇｰﾍﾞﾙﾌﾟｰｽ
A4: コード | B4: 名称 | K4: 令和 7年 4月 | L4: 令和 7年 5月 | M4: 令和 7年 6月 | N4: 令和 7年 7月 | O4: 令和 7年 8月 | P4: 令和 7年 9月 | Q4: 令和 7年 10月 | R4: 令和 7年 11月 | S4: 令和 7年 12月 | T4: 令和 8年 1月 | U4: 令和 8年 2月 | V4: 令和 8年 3月 | W4: 合計
K5: ①当期実績 | L5: ①当期実績 | M5: ①当期実績 | N5: ①当期実績 | O5: ①当期実績 | P5: ①当期実績 | Q5: ①当期実績 | R5: ①当期実績 | S5: ①当期実績 | T5: ①当期実績 | U5: ①当期実績 | V5: ①当期実績 | W5: ①当期実績
A6: 10000 | B6: 総売上高 | K6: =SUM(K7:K16) -> 4894000 | L6: =SUM(L7:L16) -> 8210000 | M6: =SUM(M7:M16) -> 9617000 | N6: =SUM(N7:N16) -> 9017000 | O6: =SUM(O7:O16) -> 10237500 | P6: =SUM(P7:P16) -> 10015000 | Q6: =SUM(Q7:Q16) -> 9529000 | R6: =SUM(R7:R16) -> 8475000 | ... V6: =SUM(V7:V16) -> 5570000 | W6: =SUM(K6:V6) -> 98216500
A7: 10001 | C7: 売上 | K7: 4894000 | L7: 8210000 | M7: 9617000 | N7: 9017000 | O7: 10237500 | P7: 10015000 | Q7: 9529000 | R7: 8475000 | S7: 11092000 | T7: 5400000 | U7: 6160000 | V7: 5570000 | W7: =SUM(K7:V7) -> 98216500
A8: 10002 | C8: 損保代理店収入 | K8: 0 | L8: 0 | M8: 0 | N8: 0 | O8: 0 | P8: 0 | Q8: 0 | R8: 0 | S8: 0 | T8: 0 | U8: 0 | V8: 0 | W8: =SUM(K8:V8) -> 0
A9: 10003 | C9: 販売手数料収入 | K9: 0 | L9: 0 | M9: 0 | N9: 0 | O9: 0 | P9: 0 | Q9: 0 | R9: 0 | S9: 0 | T9: 0 | U9: 0 | V9: 0 | W9: =SUM(K9:V9) -> 0
A10: 10004 | C10: 索道収入 | K10: 0 | L10: 0 | M10: 0 | N10: 0 | O10: 0 | P10: 0 | Q10: 0 | R10: 0 | S10: 0 | T10: 0 | U10: 0 | V10: 0 | W10: =SUM(K10:V10) -> 0
A11: 10005 | C11: 地代収入 | K11: 0 | L11: 0 | M11: 0 | N11: 0 | O11: 0 | P11: 0 | Q11: 0 | R11: 0 | S11: 0 | T11: 0 | U11: 0 | V11: 0 | W11: =SUM(K11:V11) -> 0
A12: 10006 | C12: 家賃収入 | K12: 0 | L12: 0 | M12: 0 | N12: 0 | O12: 0 | P12: 0 | Q12: 0 | R12: 0 | S12: 0 | T12: 0 | U12: 0 | V12: 0 | W12: =SUM(K12:V12) -> 0
A13: 10007 | C13: 駐車場収入 | K13: 0 | L13: 0 | M13: 0 | N13: 0 | O13: 0 | P13: 0 | Q13: 0 | R13: 0 | S13: 0 | T13: 0 | U13: 0 | V13: 0 | W13: =SUM(K13:V13) -> 0
A14: 10008 | C14: 受託料 | K14: 0 | L14: 0 | M14: 0 | N14: 0 | O14: 0 | P14: 0 | Q14: 0 | R14: 0 | S14: 0 | T14: 0 | U14: 0 | V14: 0 | W14: =SUM(K14:V14) -> 0
A15: 10009 | C15: 利用料金収入 | K15: 0 | L15: 0 | M15: 0 | N15: 0 | O15: 0 | P15: 0 | Q15: 0 | R15: 0 | S15: 0 | T15: 0 | U15: 0 | V15: 0 | W15: =SUM(K15:V15) -> 0
A16: 10010 | C16: 管理手数料収入 | K16: 0 | L16: 0 | M16: 0 | N16: 0 | O16: 0 | P16: 0 | Q16: 0 | R16: 0 | S16: 0 | T16: 0 | U16: 0 | V16: 0 | W16: =SUM(K16:V16) -> 0
A17: 20000 | B17: 売上原価 | K17: =K7*0.29 -> 1419260 | L17: =L7*0.29 -> 2380900 | M17: =M7*0.29 -> 2788930 | N17: =N7*0.29 -> 2614930 | O17: =O7*0.29 -> 2968875 | P17: =P7*0.29 -> 2904350 | Q17: =Q7*0.29 -> 2763410 | R17: =R7*0.29 -> 2457750 | ... V17: =V7*0.29 -> 1615300 | W17: =SUM(K17:V17) -> 28482785
A18: 30000 | B18: 売上総利益 | K18: =K6-K17 -> 3474740 | L18: =L6-L17 -> 5829100 | M18: =M6-M17 -> 6828070 | N18: =N6-N17 -> 6402070 | O18: =O6-O17 -> 7268625 | P18: =P6-P17 -> 7110650 | Q18: =Q6-Q17 -> 6765590 | R18: =R6-R17 -> 6017250 | ... V18: =V6-V17 -> 3954700 | W18: =SUM(K18:V18) -> 69733715
A19: 41000 | B19: 人件費 | K19: =SUM(K20:K22,K26,K29:K31,K35:K36) -> 3392673 | L19: =SUM(L20:L22,L26,L29:L31,L35:L36) -> 3635335 | M19: =SUM(M20:M22,M26,M29:M31,M35:M36) -> 6259465 | N19: =SUM(N20:N22,N26,N29:N31,N35:N36) -> 4301300.2 | O19: =SUM(O20:O22,O26,O29:O31,O35:O36) -> 3927721 | P19: =SUM(P20:P22,P26,P29:P31,P35:P36) -> 3635335 | Q19: =SUM(Q20:Q22,Q26,Q29:Q31,Q35:Q36) -> 3815933 | R19: =SUM(R20:R22,R26,R29:R31,R35:R36) -> 3662197.5 | ... V19: =SUM(V20:V22,V26,V29:V31,V35:V36) -> 4013069 | W19: =SUM(K19:V19) -> 53667197
A20: 41010 | C20: 役員報酬 | K20: 0 | L20: 0 | M20: 0 | N20: 0 | O20: 0 | P20: 0 | Q20: 0 | R20: 0 | S20: 0 | T20: 0 | U20: 0 | V20: 0 | W20: =SUM(K20:V20) -> 0
A21: 41020 | C21: 社員給与費 | K21: 0 | L21: 0 | M21: 0 | N21: 0 | O21: 0 | P21: 0 | Q21: 0 | R21: 0 | S21: 0 | T21: 0 | U21: 0 | V21: 0 | W21: =SUM(K21:V21) -> 0
A22: 41030 | C22: 専門等給与費 | K22: =SUM(K23:K25) -> 2916720 | L22: =SUM(L23:L25) -> 3028750 | M22: =SUM(M23:M25) -> 5621030 | N22: =SUM(N23:N25) -> 3317590 | O22: =SUM(O23:O25) -> 3317590 | P22: =SUM(P23:P25) -> 3028750 | Q22: =SUM(Q23:Q25) -> 3207150 | R22: =SUM(R23:R25) -> 3028750 | ... V22: =SUM(V23:V25) -> 2948220 | W22: =SUM(K22:V22) -> 44651640
A23: 41031 | D23: 専門 | K23: 2916720 | L23: 3013000 | M23: 5605280 | N23: 3301840 | O23: 3301840 | P23: 3013000 | Q23: 3191400 | R23: 3013000 | S23: 8163840 | T23: 3013000 | U23: 3013000 | V23: 2916720 | W23: =SUM(K23:V23) -> 44462640
A24: 41032 | D24: 臨時 | K24: 0 | L24: 0 | M24: 0 | N24: 0 | O24: 0 | P24: 0 | Q24: 0 | R24: 0 | S24: 0 | T24: 0 | U24: 0 | V24: 0 | W24: =SUM(K24:V24) -> 0
A25: 41033 | D25: パート | K25: 0 | L25: 15750 | M25: 15750 | N25: 15750 | O25: 15750 | P25: 15750 | Q25: 15750 | R25: 15750 | S25: 15750 | T25: 15750 | U25: 15750 | V25: 31500 | W25: =SUM(K25:V25) -> 189000
A26: 41040 | C26: 退職金 | K26: 0 | L26: 0 | M26: 0 | N26: 0 | O26: 0 | P26: 0 | Q26: 0 | R26: 0 | S26: 0 | T26: 0 | U26: 0 | V26: 0 | W26: =SUM(K26:V26) -> 0
A27: 41041 | D27: 役員 | W27: =SUM(K27:V27) -> 0
A28: 41042 | D28: 社員 | W28: =SUM(K28:V28) -> 0
A29: 41050 | C29: 法定福利費 | K29: 37047 | L29: 497679 | M29: 529529 | N29: 874804.2 | O29: 501225 | P29: 497679 | Q29: 499877 | R29: 524541.48 | S29: 560961 | T29: 1201720.3 | U29: 497679 | V29: 955943 | W29: =SUM(K29:V29) -> 7178685
A30: 41060 | C30: 退職年金掛金 | K30: 4400 | L30: 4400 | M30: 4400 | N30: 4400 | O30: 4400 | P30: 4400 | Q30: 4400 | R30: 4400 | S30: 4400 | T30: 4400 | U30: 4400 | V30: 4400 | W30: =SUM(K30:V30) -> 52800
A31: 41070 | C31: 福利厚生費 | K31: =SUM(K32:K34) -> 336600 | L31: =SUM(L32:L34) -> 6600 | M31: =SUM(M32:M34) -> 6600 | N31: =SUM(N32:N34) -> 6600 | O31: =SUM(O32:O34) -> 6600 | P31: =SUM(P32:P34) -> 6600 | Q31: =SUM(Q32:Q34) -> 6600 | R31: =SUM(R32:R34) -> 6600 | ... V31: =SUM(V32:V34) -> 6600 | W31: =SUM(K31:V31) -> 609200
A32: 41071 | D32: 福利厚生費 | K32: 6600 | L32: 6600 | M32: 6600 | N32: 6600 | O32: 6600 | P32: 6600 | Q32: 6600 | R32: 6600 | S32: 6600 | T32: 6600 | U32: 6600 | V32: 6600 | W32: =SUM(K32:V32) -> 79200
A33: 41072 | D33: 被服費 | K33: 330000 | L33: 0 | M33: 0 | N33: 0 | O33: 0 | P33: 0 | Q33: 0 | R33: 0 | S33: 0 | T33: 0 | U33: 0 | V33: 0 | W33: =SUM(K33:V33) -> 330000
A34: 41073 | D34: 研修費 | K34: 0 | L34: 0 | M34: 0 | N34: 0 | O34: 0 | P34: 0 | Q34: 0 | R34: 0 | S34: 0 | T34: 200000 | U34: 0 | V34: 0 | W34: =SUM(K34:V34) -> 200000
A35: 41080 | C35: 通勤費 | K35: 97906 | L35: 97906 | M35: 97906 | N35: 97906 | O35: 97906 | P35: 97906 | Q35: 97906 | R35: 97906 | S35: 97906 | T35: 97906 | U35: 97906 | V35: 97906 | W35: =SUM(K35:V35) -> 1174872
A36: 41090 | C36: 引当金繰入額 | W36: =SUM(K36:V36) -> 0
A37: 42000 | B37: 物件費 | K37: =SUM(K38:K41,K46,K50,K57:K58,K61:K67,K70:K72,K78:K80,K83:K84) -> 1807850 | L37: =SUM(L38:L41,L46,L50,L57:L58,L61:L67,L70:L72,L78:L80,L83:L84) -> 1287589 | M37: =SUM(M38:M41,M46,M50,M57:M58,M61:M67,M70:M72,M78:M80,M83:M84) -> 2224399 | N37: =SUM(N38:N41,N46,N50,N57:N58,N61:N67,N70:N72,N78:N80,N83:N84) -> 2051844 | O37: =SUM(O38:O41,O46,O50,O57:O58,O61:O67,O70:O72,O78:O80,O83:O84) -> 1912822 | P37: =SUM(P38:P41,P46,P50,P57:P58,P61:P67,P70:P72,P78:P80,P83:P84) -> 2007787 | Q37: =SUM(Q38:Q41,Q46,Q50,Q57:Q58,Q61:Q67,Q70:Q72,Q78:Q80,Q83:Q84) -> 2403587 | R37: =SUM(R38:R41,R46,R50,R57:R58,R61:R67,R70:R72,R78:R80,R83:R84) -> 2516615 | ... V37: =SUM(V38:V41,V46,V50,V57:V58,V61:V67,V70:V72,V78:V80,V83:V84) -> 1753283 | W37: =SUM(K37:V37) -> 24819605
A38: 42010 | C38: 消耗品費 | K38: 290000 | L38: 30000 | M38: 180000 | N38: 430000 | O38: 280000 | P38: 30000 | Q38: 380000 | R38: 330000 | S38: 280000 | T38: 230000 | U38: 30000 | V38: 30000 | W38: =SUM(K38:V38) -> 2520000
A39: 42020 | C39: 事務用品費 | K39: 0 | L39: 20000 | M39: 20000 | N39: 20000 | O39: 20000 | P39: 40000 | Q39: 20000 | R39: 20000 | S39: 20000 | T39: 20000 | U39: 20000 | V39: 40000 | W39: =SUM(K39:V39) -> 260000
A40: 42030 | C40: 図書購入費 | K40: 0 | L40: 0 | M40: 0 | N40: 0 | O40: 0 | P40: 0 | Q40: 0 | R40: 0 | S40: 0 | T40: 0 | U40: 0 | V40: 0 | W40: =SUM(K40:V40) -> 0
A41: 42040 | C41: 賃借料 | K41: =SUM(K42:K45) -> 32300 | L41: =SUM(L42:L45) -> 34300 | M41: =SUM(M42:M45) -> 35300 | N41: =SUM(N42:N45) -> 36300 | O41: =SUM(O42:O45) -> 45800 | P41: =SUM(P42:P45) -> 36300 | Q41: =SUM(Q42:Q45) -> 35300 | R41: =SUM(R42:R45) -> 34300 | ... V41: =SUM(V42:V45) -> 32300 | W41: =SUM(K41:V41) -> 425100
A42: 42041 | D42: 土地使用料 | K42: 0 | L42: 0 | M42: 0 | N42: 0 | O42: 0 | P42: 0 | Q42: 0 | R42: 0 | S42: 0 | T42: 0 | U42: 0 | V42: 0 | W42: =SUM(K42:V42) -> 0
A43: 42042 | D43: 建物使用料 | K43: 0 | L43: 0 | M43: 0 | N43: 0 | O43: 0 | P43: 0 | Q43: 0 | R43: 0 | S43: 0 | T43: 0 | U43: 0 | V43: 0 | W43: =SUM(K43:V43) -> 0
A44: 42043 | D44: 施設使用料 | K44: 0 | L44: 0 | M44: 0 | N44: 0 | O44: 0 | P44: 0 | Q44: 0 | R44: 0 | S44: 0 | T44: 0 | U44: 0 | V44: 0 | W44: =SUM(K44:V44) -> 0
A45: 42044 | D45: リース料 | K45: 32300 | L45: 34300 | M45: 35300 | N45: 36300 | O45: 45800 | P45: 36300 | Q45: 35300 | R45: 34300 | S45: 36300 | T45: 32300 | U45: 34300 | V45: 32300 | W45: =SUM(K45:V45) -> 425100
A46: 42050 | C46: 保険料 | K46: =SUM(K47:K49) -> 4210 | L46: =SUM(L47:L49) -> 0 | M46: =SUM(M47:M49) -> 0 | N46: =SUM(N47:N49) -> 0 | O46: =SUM(O47:O49) -> 0 | P46: =SUM(P47:P49) -> 0 | Q46: =SUM(Q47:Q49) -> 0 | R46: =SUM(R47:R49) -> 0 | ... V46: =SUM(V47:V49) -> 34000 | W46: =SUM(K46:V46) -> 38210
A47: 42051 | D47: 火災保険料 | K47: 0 | L47: 0 | M47: 0 | N47: 0 | O47: 0 | P47: 0 | Q47: 0 | R47: 0 | S47: 0 | T47: 0 | U47: 0 | V47: 0 | W47: =SUM(K47:V47) -> 0
A48: 42052 | D48: 賠償保険料 | K48: 0 | L48: 0 | M48: 0 | N48: 0 | O48: 0 | P48: 0 | Q48: 0 | R48: 0 | S48: 0 | T48: 0 | U48: 0 | V48: 34000 | W48: =SUM(K48:V48) -> 34000
A49: 42053 | D49: 動産保険料 | K49: 4210 | L49: 0 | M49: 0 | N49: 0 | O49: 0 | P49: 0 | Q49: 0 | R49: 0 | S49: 0 | T49: 0 | U49: 0 | V49: 0 | W49: =SUM(K49:V49) -> 4210
A50: 42060 | C50: 修繕費 | K50: =SUM(K51:K56) -> 0 | L50: =SUM(L51:L56) -> 0 | M50: =SUM(M51:M56) -> 0 | N50: =SUM(N51:N56) -> 0 | O50: =SUM(O51:O56) -> 0 | P50: =SUM(P51:P56) -> 0 | Q50: =SUM(Q51:Q56) -> 0 | R50: =SUM(R51:R56) -> 0 | ... V50: =SUM(V51:V56) -> 0 | W50: =SUM(K50:V50) -> 0
A51: 42061 | D51: 建物 | K51: 0 | L51: 0 | M51: 0 | N51: 0 | O51: 0 | P51: 0 | Q51: 0 | R51: 0 | S51: 0 | T51: 0 | U51: 0 | V51: 0 | W51: =SUM(K51:V51) -> 0
A52: 42062 | D52: 建物付属設備 | K52: 0 | L52: 0 | M52: 0 | N52: 0 | O52: 0 | P52: 0 | Q52: 0 | R52: 0 | S52: 0 | T52: 0 | U52: 0 | V52: 0 | W52: =SUM(K52:V52) -> 0
A53: 42063 | D53: 構築物 | K53: 0 | L53: 0 | M53: 0 | N53: 0 | O53: 0 | P53: 0 | Q53: 0 | R53: 0 | S53: 0 | T53: 0 | U53: 0 | V53: 0 | W53: =SUM(K53:V53) -> 0
A54: 42064 | D54: 機械 | K54: 0 | L54: 0 | M54: 0 | N54: 0 | O54: 0 | P54: 0 | Q54: 0 | R54: 0 | S54: 0 | T54: 0 | U54: 0 | V54: 0 | W54: =SUM(K54:V54) -> 0
A55: 42065 | D55: 器具備品 | K55: 0 | L55: 0 | M55: 0 | N55: 0 | O55: 0 | P55: 0 | Q55: 0 | R55: 0 | S55: 0 | T55: 0 | U55: 0 | V55: 0 | W55: =SUM(K55:V55) -> 0
A56: 42066 | D56: 車両 | K56: 0 | L56: 0 | M56: 0 | N56: 0 | O56: 0 | P56: 0 | Q56: 0 | R56: 0 | S56: 0 | T56: 0 | U56: 0 | V56: 0 | W56: =SUM(K56:V56) -> 0
A57: 42070 | C57: 車両運搬費 | K57: 0 | L57: 0 | M57: 0 | N57: 0 | O57: 0 | P57: 0 | Q57: 0 | R57: 0 | S57: 0 | T57: 0 | U57: 0 | V57: 0 | W57: =SUM(K57:V57) -> 0
A58: 42080 | C58: 印刷製本費 | K58: =SUM(K59:K60) -> 40000 | L58: =SUM(L59:L60) -> 0 | M58: =SUM(M59:M60) -> 0 | N58: =SUM(N59:N60) -> 20000 | O58: =SUM(O59:O60) -> 0 | P58: =SUM(P59:P60) -> 187000 | Q58: =SUM(Q59:Q60) -> 20000 | R58: =SUM(R59:R60) -> 40000 | ... V58: =SUM(V59:V60) -> 87000 | W58: =SUM(K58:V58) -> 414000
A59: 42081 | D59: 印刷製本費 | K59: 40000 | L59: 0 | M59: 0 | N59: 20000 | O59: 0 | P59: 187000 | Q59: 20000 | R59: 40000 | S59: 0 | T59: 20000 | U59: 0 | V59: 87000 | W59: =SUM(K59:V59) -> 414000
A60: 42082 | D60: 乗車券帳票費 | K60: 0 | L60: 0 | M60: 0 | N60: 0 | O60: 0 | P60: 0 | Q60: 0 | R60: 0 | S60: 0 | T60: 0 | U60: 0 | V60: 0 | W60: =SUM(K60:V60) -> 0
A61: 42090 | C61: 清掃衛生費 | K61: 89000 | L61: 97000 | M61: 72000 | N61: 72000 | O61: 72000 | P61: 102000 | Q61: 72000 | R61: 107000 | S61: 72000 | T61: 90000 | U61: 60000 | V61: 79000 | W61: =SUM(K61:V61) -> 984000
A62: 42100 | C62: 事務会議費 | K62: 0 | L62: 0 | M62: 0 | N62: 0 | O62: 0 | P62: 0 | Q62: 0 | R62: 0 | S62: 0 | T62: 0 | U62: 0 | V62: 0 | W62: =SUM(K62:V62) -> 0
A63: 42110 | C63: 租税公課 | K63: 136500 | L63: 2000 | M63: 0 | N63: 0 | O63: 0 | P63: 0 | Q63: 0 | R63: 0 | S63: 0 | T63: 0 | U63: 0 | V63: 10000 | W63: =SUM(K63:V63) -> 148500
A64: 42120 | C64: 会費負担金 | K64: 0 | L64: 0 | M64: 0 | N64: 0 | O64: 0 | P64: 0 | Q64: 130000 | R64: 0 | S64: 0 | T64: 0 | U64: 0 | V64: 0 | W64: =SUM(K64:V64) -> 130000
A65: 42130 | C65: 委託料 | K65: 420620 | L65: 204620 | M65: 239620 | N65: 234620 | O65: 234620 | P65: 254620 | Q65: 254620 | R65: 234620 | S65: 279620 | T65: 214620 | U65: 214620 | V65: 204620 | W65: =SUM(K65:V65) -> 2991440
A66: 42140 | C66: 除雪費 | K66: 0 | L66: 0 | M66: 0 | N66: 0 | O66: 0 | P66: 0 | Q66: 0 | R66: 0 | S66: 0 | T66: 0 | U66: 0 | V66: 0 | W66: =SUM(K66:V66) -> 0
A67: 42150 | C67: 販売促進費 | K67: =SUM(K68:K69) -> 114903 | L67: =SUM(L68:L69) -> 298659 | M67: =SUM(M68:M69) -> 344112 | N67: =SUM(N68:N69) -> 553392 | O67: =SUM(O68:O69) -> 364890 | P67: =SUM(P68:P69) -> 419069 | Q67: =SUM(Q68:Q69) -> 424190 | R67: =SUM(R68:R69) -> 1015220 | ... V67: =SUM(V68:V69) -> 261240 | W67: =SUM(K67:V67) -> 5175328
A68: 42151 | D68: 販売促進費 | K68: 114903 | L68: 298659 | M68: 344112 | N68: 553392 | O68: 364890 | P68: 419069 | Q68: 424190 | R68: 1015220 | S68: 769063 | T68: 298306 | U68: 312284 | V68: 261240 | W68: =SUM(K68:V68) -> 5175328
A69: 42152 | D69: 乗車券販売手数料 | K69: 0 | L69: 0 | M69: 0 | N69: 0 | O69: 0 | P69: 0 | Q69: 0 | R69: 0 | S69: 0 | T69: 0 | U69: 0 | V69: 0 | W69: =SUM(K69:V69) -> 0
A70: 42160 | C70: 旅費交通費 | K70: 5500 | L70: 3500 | M70: 3500 | N70: 4000 | O70: 4000 | P70: 4000 | Q70: 4000 | R70: 5000 | S70: 4000 | T70: 4500 | U70: 203500 | V70: 4500 | W70: =SUM(K70:V70) -> 250000
A71: 42170 | C71: 通信連絡費 | K71: 8800 | L71: 28700 | M71: 31900 | N71: 28700 | O71: 28700 | P71: 28700 | Q71: 28700 | R71: 33700 | S71: 28700 | T71: 33700 | U71: 28700 | V71: 53600 | W71: =SUM(K71:V71) -> 362600
A72: 42180 | C72: 水道光熱費 | K72: =SUM(K73:K77) -> 629862 | L72: =SUM(L73:L77) -> 531145 | M72: =SUM(M73:M77) -> 660357 | N72: =SUM(N73:N77) -> 615012 | O72: =SUM(O73:O77) -> 824256 | P72: =SUM(P73:P77) -> 669188 | Q72: =SUM(Q73:Q77) -> 597277 | R72: =SUM(R73:R77) -> 659275 | ... V72: =SUM(V73:V77) -> 879523 | W72: =SUM(K72:V72) -> 8670711
A73: 42181 | D73: 電灯使用料 | K73: 376891 | L73: 339642 | M73: 377495 | N73: 389730 | O73: 423600 | P73: 431088 | Q73: 366887 | R73: 370706 | S73: 361180 | T73: 408314 | U73: 415371 | V73: 419086 | W73: =SUM(K73:V73) -> 4679990
A74: 42182 | D74: 水道使用料 | K74: 0 | L74: 0 | M74: 92820 | N74: 0 | O74: 96595 | P74: 0 | Q74: 90000 | R74: 0 | S74: 90000 | T74: 0 | U74: 90000 | V74: 90000 | W74: =SUM(K74:V74) -> 549415
A75: 42183 | D75: ガス使用料 | K75: 252971 | L75: 191503 | M75: 190042 | N75: 225282 | O75: 304061 | P75: 238100 | Q75: 140390 | R75: 288569 | S75: 388078 | T75: 442939 | U75: 408934 | V75: 370437 | W75: =SUM(K75:V75) -> 3441306
A76: 42184 | D76: 暖房燃料費 | K76: 0 | L76: 0 | M76: 0 | N76: 0 | O76: 0 | P76: 0 | Q76: 0 | R76: 0 | S76: 0 | T76: 0 | U76: 0 | V76: 0 | W76: =SUM(K76:V76) -> 0
A77: 42185 | D77: 電力使用料 | K77: 0 | L77: 0 | M77: 0 | N77: 0 | O77: 0 | P77: 0 | Q77: 0 | R77: 0 | S77: 0 | T77: 0 | U77: 0 | V77: 0 | W77: =SUM(K77:V77) -> 0
A78: 42190 | C78: 諸手数料 | K78: 1155 | L78: 2665 | M78: 2610 | N78: 2820 | O78: 3556 | P78: 1910 | Q78: 2500 | R78: 2500 | S78: 2500 | T78: 2500 | U78: 2500 | V78: 2500 | W78: =SUM(K78:V78) -> 29716
A79: 42200 | C79: 広告宣伝費 | K79: 35000 | L79: 35000 | M79: 635000 | N79: 35000 | O79: 35000 | P79: 235000 | Q79: 435000 | R79: 35000 | S79: 435000 | T79: 435000 | U79: 35000 | V79: 35000 | W79: =SUM(K79:V79) -> 2420000
A80: 42210 | C80: 交際費 | K80: =SUM(K81:K82) -> 0 | L80: =SUM(L81:L82) -> 0 | M80: =SUM(M81:M82) -> 0 | N80: =SUM(N81:N82) -> 0 | O80: =SUM(O81:O82) -> 0 | P80: =SUM(P81:P82) -> 0 | Q80: =SUM(Q81:Q82) -> 0 | R80: =SUM(R81:R82) -> 0 | ... V80: =SUM(V81:V82) -> 0 | W80: =SUM(K80:V80) -> 0
A81: 42211 | D81: 接待交際費 | K81: 0 | L81: 0 | M81: 0 | N81: 0 | O81: 0 | P81: 0 | Q81: 0 | R81: 0 | S81: 0 | T81: 0 | U81: 0 | V81: 0 | W81: =SUM(K81:V81) -> 0
A82: 42212 | D82: 贈答用品費 | K82: 0 | L82: 0 | M82: 0 | N82: 0 | O82: 0 | P82: 0 | Q82: 0 | R82: 0 | S82: 0 | T82: 0 | U82: 0 | V82: 0 | W82: =SUM(K82:V82) -> 0
A83: 42220 | C83: 寄付金 | K83: 0 | L83: 0 | M83: 0 | N83: 0 | O83: 0 | P83: 0 | Q83: 0 | R83: 0 | S83: 0 | T83: 0 | U83: 0 | V83: 0 | W83: =SUM(K83:V83) -> 0
A84: 42230 | C84: 雑費用 | K84: 0 | L84: 0 | M84: 0 | N84: 0 | O84: 0 | P84: 0 | Q84: 0 | R84: 0 | S84: 0 | T84: 0 | U84: 0 | V84: 0 | W84: =SUM(K84:V84) -> 0
A85: 43000 | B85: 減価償却費 | K85: =SUM(K86:K96) -> 680401 | L85: =SUM(L86:L96) -> 680401 | M85: =SUM(M86:M96) -> 448820 | N85: =SUM(N86:N96) -> 448795 | O85: =SUM(O86:O96) -> 448795 | P85: =SUM(P86:P96) -> 448795 | Q85: =SUM(Q86:Q96) -> 448795 | R85: =SUM(R86:R96) -> 448795 | ... V85: =SUM(V86:V96) -> 417451 | W85: =SUM(K85:V85) -> 5815056
A86: 43010 | C86: 建物 | K86: 0 | L86: 0 | M86: 0 | N86: 0 | O86: 0 | P86: 0 | Q86: 0 | R86: 0 | S86: 0 | T86: 0 | U86: 0 | V86: 0 | W86: =SUM(K86:V86) -> 0
A87: 43020 | C87: 建物附属設備 | K87: 0 | L87: 0 | M87: 58333 | N87: 58333 | O87: 58333 | P87: 58333 | Q87: 58333 | R87: 58333 | S87: 58333 | T87: 58333 | U87: 58333 | V87: 58336 | W87: =SUM(K87:V87) -> 583333
A88: 43030 | C88: 構築物 | K88: 0 | L88: 0 | M88: 0 | N88: 0 | O88: 0 | P88: 0 | Q88: 0 | R88: 0 | S88: 0 | T88: 0 | U88: 0 | V88: 0 | W88: =SUM(K88:V88) -> 0
A89: 43040 | C89: 機械・装置 | K89: 41666 | L89: 41666 | M89: 41666 | N89: 41666 | O89: 41666 | P89: 41666 | Q89: 41666 | R89: 41666 | S89: 41666 | T89: 41666 | U89: 41666 | V89: 41674 | W89: =SUM(K89:V89) -> 500000
A90: 43050 | C90: 器具備品 | K90: 614874 | L90: 614874 | M90: 324960 | N90: 324935 | O90: 324935 | P90: 324935 | Q90: 324935 | R90: 324935 | S90: 324935 | T90: 324935 | U90: 322558 | V90: 293569 | W90: =SUM(K90:V90) -> 4445380
A91: 43060 | C91: 車両 | K91: 0 | L91: 0 | M91: 0 | N91: 0 | O91: 0 | P91: 0 | Q91: 0 | R91: 0 | S91: 0 | T91: 0 | U91: 0 | V91: 0 | W91: =SUM(K91:V91) -> 0
A92: 43070 | C92: 少額資産 | K92: 18195 | L92: 18195 | M92: 18195 | N92: 18195 | O92: 18195 | P92: 18195 | Q92: 18195 | R92: 18195 | S92: 18195 | T92: 18195 | U92: 18195 | V92: 18199 | W92: =SUM(K92:V92) -> 218344
A93: 43080 | C93: 商標権 | K93: 0 | L93: 0 | M93: 0 | N93: 0 | O93: 0 | P93: 0 | Q93: 0 | R93: 0 | S93: 0 | T93: 0 | U93: 0 | V93: 0 | W93: =SUM(K93:V93) -> 0
A94: 43090 | C94: ソフトウェア | K94: 5666 | L94: 5666 | M94: 5666 | N94: 5666 | O94: 5666 | P94: 5666 | Q94: 5666 | R94: 5666 | S94: 5666 | T94: 5666 | U94: 5666 | V94: 5673 | W94: =SUM(K94:V94) -> 67999
A95: 43100 | C95: 長期前払費用 | K95: 0 | L95: 0 | M95: 0 | N95: 0 | O95: 0 | P95: 0 | Q95: 0 | R95: 0 | S95: 0 | T95: 0 | U95: 0 | V95: 0 | W95: =SUM(K95:V95) -> 0
A96: 43110 | C96: リース資産 | K96: 0 | L96: 0 | M96: 0 | N96: 0 | O96: 0 | P96: 0 | Q96: 0 | R96: 0 | S96: 0 | T96: 0 | U96: 0 | V96: 0 | W96: =SUM(K96:V96) -> 0
A97: 40000 | B97: 販売費・一般管理費 | K97: =K37+K19+K85 -> 5880924 | L97: =L37+L19+L85 -> 5603325 | M97: =M37+M19+M85 -> 8932684 | N97: =N37+N19+N85 -> 6801939.2 | O97: =O37+O19+O85 -> 6289338 | P97: =P37+P19+P85 -> 6091917 | Q97: =Q37+Q19+Q85 -> 6668315 | R97: =R37+R19+R85 -> 6627607.5 | ... V97: =V37+V19+V85 -> 6183803 | W97: =SUM(K97:V97) -> 84301858
A98: 50000 | B98: 営業利益 | K98: =K18-K97 -> -2406184 | L98: =L18-L97 -> 225775 | M98: =M18-M97 -> -2104614 | N98: =N18-N97 -> -399869.2 | O98: =O18-O97 -> 979287 | P98: =P18-P97 -> 1018733 | Q98: =Q18-Q97 -> 97275 | R98: =R18-R97 -> -610357.48 | ... V98: =V18-V97 -> -2229103 | W98: =SUM(K98:V98) -> -14568143
A99: 61000 | B99: 営業外収益 | K99: =SUM(K100,K104:K106) -> 12025 | L99: =SUM(L100,L104:L106) -> 62843 | M99: =SUM(M100,M104:M106) -> 0 | N99: =SUM(N100,N104:N106) -> 337 | O99: =SUM(O100,O104:O106) -> 0 | P99: =SUM(P100,P104:P106) -> 10337 | Q99: =SUM(Q100,Q104:Q106) -> 0 | R99: =SUM(R100,R104:R106) -> 0 | ... V99: =SUM(V100,V104:V106) -> 0 | W99: =SUM(K99:V99) -> 85542
A100: 61010 | C100: 受取利息 | K100: =SUM(K101:K103) -> 0 | L100: =SUM(L101:L103) -> 0 | M100: =SUM(M101:M103) -> 0 | N100: =SUM(N101:N103) -> 0 | O100: =SUM(O101:O103) -> 0 | P100: =SUM(P101:P103) -> 0 | Q100: =SUM(Q101:Q103) -> 0 | R100: =SUM(R101:R103) -> 0 | ... V100: =SUM(V101:V103) -> 0 | W100: =SUM(K100:V100) -> 0
A101: 61011 | D101: 定期預金 | K101: 0 | L101: 0 | M101: 0 | N101: 0 | O101: 0 | P101: 0 | Q101: 0 | R101: 0 | S101: 0 | T101: 0 | U101: 0 | V101: 0 | W101: =SUM(K101:V101) -> 0
...

Sheet ｶﾌｪﾙﾎﾟ
A1: ■（Ｒ７年度）事業予算入力用
A3: 部門 ｶﾌｪﾙﾎﾟ
A4: コード | B4: 名称 | K4: 令和 7年 4月 | L4: 令和 7年 5月 | M4: 令和 7年 6月 | N4: 令和 7年 7月 | O4: 令和 7年 8月 | P4: 令和 7年 9月 | Q4: 令和 7年 10月 | R4: 令和 7年 11月 | S4: 令和 7年 12月 | T4: 令和 8年 1月 | U4: 令和 8年 2月 | V4: 令和 8年 3月 | W4: 合計
K5: ①当期実績 | L5: ①当期実績 | M5: ①当期実績 | N5: ①当期実績 | O5: ①当期実績 | P5: ①当期実績 | Q5: ①当期実績 | R5: ①当期実績 | S5: ①当期実績 | T5: ①当期実績 | U5: ①当期実績 | V5: ①当期実績 | W5: ①当期実績
A6: 10000 | B6: 総売上高 | K6: =SUM(K7:K16) -> 694132 | L6: =SUM(L7:L16) -> 779647 | M6: =SUM(M7:M16) -> 652567 | N6: =SUM(N7:N16) -> 727786 | O6: =SUM(O7:O16) -> 1181051 | P6: =SUM(P7:P16) -> 689072 | Q6: =SUM(Q7:Q16) -> 1025101 | R6: =SUM(R7:R16) -> 413778 | ... V6: =SUM(V7:V16) -> 668465 | W6: =SUM(K6:V6) -> 9212097
A7: 10001 | C7: 売上 | K7: 694132 | L7: 779647 | M7: 652567 | N7: 727786 | O7: 1181051 | P7: 689072 | Q7: 1025101 | R7: 413778 | S7: 537498 | T7: 1103983 | U7: 739017 | V7: 668465 | W7: =SUM(K7:V7) -> 9212097
A8: 10002 | C8: 損保代理店収入 | K8: 0 | L8: 0 | M8: 0 | N8: 0 | O8: 0 | P8: 0 | Q8: 0 | R8: 0 | S8: 0 | T8: 0 | U8: 0 | V8: 0 | W8: =SUM(K8:V8) -> 0
A9: 10003 | C9: 販売手数料収入 | K9: 0 | L9: 0 | M9: 0 | N9: 0 | O9: 0 | P9: 0 | Q9: 0 | R9: 0 | S9: 0 | T9: 0 | U9: 0 | V9: 0 | W9: =SUM(K9:V9) -> 0
A10: 10004 | C10: 索道収入 | K10: 0 | L10: 0 | M10: 0 | N10: 0 | O10: 0 | P10: 0 | Q10: 0 | R10: 0 | S10: 0 | T10: 0 | U10: 0 | V10: 0 | W10: =SUM(K10:V10) -> 0
A11: 10005 | C11: 地代収入 | K11: 0 | L11: 0 | M11: 0 | N11: 0 | O11: 0 | P11: 0 | Q11: 0 | R11: 0 | S11: 0 | T11: 0 | U11: 0 | V11: 0 | W11: =SUM(K11:V11) -> 0
A12: 10006 | C12: 家賃収入 | K12: 0 | L12: 0 | M12: 0 | N12: 0 | O12: 0 | P12: 0 | Q12: 0 | R12: 0 | S12: 0 | T12: 0 | U12: 0 | V12: 0 | W12: =SUM(K12:V12) -> 0
A13: 10007 | C13: 駐車場収入 | K13: 0 | L13: 0 | M13: 0 | N13: 0 | O13: 0 | P13: 0 | Q13: 0 | R13: 0 | S13: 0 | T13: 0 | U13: 0 | V13: 0 | W13: =SUM(K13:V13) -> 0
A14: 10008 | C14: 受託料 | K14: 0 | L14: 0 | M14: 0 | N14: 0 | O14: 0 | P14: 0 | Q14: 0 | R14: 0 | S14: 0 | T14: 0 | U14: 0 | V14: 0 | W14: =SUM(K14:V14) -> 0
A15: 10009 | C15: 利用料金収入 | K15: 0 | L15: 0 | M15: 0 | N15: 0 | O15: 0 | P15: 0 | Q15: 0 | R15: 0 | S15: 0 | T15: 0 | U15: 0 | V15: 0 | W15: =SUM(K15:V15) -> 0
A16: 10010 | C16: 管理手数料収入 | K16: 0 | L16: 0 | M16: 0 | N16: 0 | O16: 0 | P16: 0 | Q16: 0 | R16: 0 | S16: 0 | T16: 0 | U16: 0 | V16: 0 | W16: =SUM(K16:V16) -> 0
A17: 20000 | B17: 売上原価 | K17: =K7*0.32 -> 222122.24 | L17: =L7*0.32 -> 249487.04 | M17: =M7*0.32 -> 208821.44 | N17: =N7*0.32 -> 232891.52 | O17: =O7*0.32 -> 377936.32 | P17: =P7*0.32 -> 220503.04 | Q17: =Q7*0.32 -> 328032.32 | R17: =R7*0.32 -> 132408.96 | ... V17: =V7*0.32 -> 213908.8 | W17: =SUM(K17:V17) -> 2947871
A18: 30000 | B18: 売上総利益 | K18: =K6-K17 -> 472009.76 | L18: =L6-L17 -> 530159.96 | M18: =M6-M17 -> 443745.56 | N18: =N6-N17 -> 494894.48 | O18: =O6-O17 -> 803114.68 | P18: =P6-P17 -> 468568.96 | Q18: =Q6-Q17 -> 697068.68 | R18: =R6-R17 -> 281369.04 | ... V18: =V6-V17 -> 454556.2 | W18: =SUM(K18:V18) -> 6264226
A19: 41000 | B19: 人件費 | K19: =SUM(K20:K22,K26,K29:K31,K35:K36) -> 0 | L19: =SUM(L20:L22,L26,L29:L31,L35:L36) -> 399053 | M19: =SUM(M20:M22,M26,M29:M31,M35:M36) -> 405429 | N19: =SUM(N20:N22,N26,N29:N31,N35:N36) -> 416059 | O19: =SUM(O20:O22,O26,O29:O31,O35:O36) -> 410744 | P19: =SUM(P20:P22,P26,P29:P31,P35:P36) -> 530853 | Q19: =SUM(Q20:Q22,Q26,Q29:Q31,Q35:Q36) -> 530853 | R19: =SUM(R20:R22,R26,R29:R31,R35:R36) -> 518098 | ... V19: =SUM(V20:V22,V26,V29:V31,V35:V36) -> -1857685 | W19: =SUM(K19:V19) -> 2876874
A20: 41010 | C20: 役員報酬 | K20: 0 | L20: 0 | M20: 0 | N20: 0 | O20: 0 | P20: 0 | Q20: 0 | R20: 0 | S20: 0 | T20: 0 | U20: 0 | V20: 0 | W20: =SUM(K20:V20) -> 0
A21: 41020 | C21: 社員給与費 | K21: 0 | L21: 0 | M21: 0 | N21: 0 | O21: 0 | P21: 0 | Q21: 0 | R21: 0 | S21: 0 | T21: 0 | U21: 0 | V21: 0 | W21: =SUM(K21:V21) -> 0
A22: 41030 | C22: 専門等給与費 | K22: =SUM(K23:K25) -> 0 | L22: =SUM(L23:L25) -> 357000 | M22: =SUM(M23:M25) -> 363300 | N22: =SUM(N23:N25) -> 373800 | O22: =SUM(O23:O25) -> 368550 | P22: =SUM(P23:P25) -> 463575 | Q22: =SUM(Q23:Q25) -> 463575 | R22: =SUM(R23:R25) -> 450975 | ... V22: =SUM(V23:V25) -> -1639050 | W22: =SUM(K22:V22) -> 2524200
A23: 41031 | D23: 専門 | K23: 0 | L23: 0 | M23: 0 | N23: 0 | O23: 0 | P23: 0 | Q23: 0 | R23: 0 | S23: 0 | T23: 0 | U23: 0 | V23: 0 | W23: =SUM(K23:V23) -> 0
A24: 41032 | D24: 臨時 | K24: 0 | L24: 0 | M24: 0 | N24: 0 | O24: 0 | P24: 0 | Q24: 0 | R24: 0 | S24: 0 | T24: 0 | U24: 0 | V24: 0 | W24: =SUM(K24:V24) -> 0
A25: 41033 | D25: パート | K25: 0 | L25: 357000 | M25: 363300 | N25: 373800 | O25: 368550 | P25: 463575 | Q25: 463575 | R25: 450975 | S25: 437325 | T25: 442575 | U25: 442575 | V25: =885150-2524200 -> -1639050 | W25: =SUM(K25:V25) -> 2524200
A26: 41040 | C26: 退職金 | K26: 0 | L26: 0 | M26: 0 | N26: 0 | O26: 0 | P26: 0 | Q26: 0 | R26: 0 | S26: 0 | T26: 0 | U26: 0 | V26: 0 | W26: =SUM(K26:V26) -> 0
A27: 41041 | D27: 役員 | W27: =SUM(K27:V27) -> 0
A28: 41042 | D28: 社員 | W28: =SUM(K28:V28) -> 0
A29: 41050 | C29: 法定福利費 | K29: 0 | L29: 25970 | M29: 26046 | N29: 26176 | O29: 26111 | P29: 47567 | Q29: 47567 | R29: 47412 | S29: 47244 | T29: 47309 | U29: 47309 | V29: =94618-241665 -> -147047 | W29: =SUM(K29:V29) -> 241664
A30: 41060 | C30: 退職年金掛金 | K30: 0 | L30: 0 | M30: 0 | N30: 0 | O30: 0 | P30: 0 | Q30: 0 | R30: 0 | S30: 0 | T30: 0 | U30: 0 | V30: 0 | W30: =SUM(K30:V30) -> 0
