Workbook

Sheet 料飲
F1: ２０２５(令和７)年度 第６９期 決算見込 損益計算書
AK2: [単位：千円(税抜)] | BY2: [単位：千円(税抜)]
A3: 名称
T4: 大倉山 | AI4: 藻岩山 | AX4: テレビ塔 | BM4: 赤れんがテラス
E5: ﾇｰﾍﾞﾙﾌﾟｰｽ | J5: 大倉山ｶﾌｪ | O5: 大倉山ﾗｳﾝｼﾞ | Y5: ｽｷｰﾛｯｼﾞ食堂 | AD5: 藻岩山レストラン | AN5: ｶﾞｰﾃﾞﾝ | AS5: ﾋﾞｱｶﾞｰﾃﾞﾝ | BC5: ブリック | BH5: 羊蹄ぶた | BR5: 料飲共通 | BW5: 料飲部合計
E6: ①R7予算 | F6: ②R7決見 | G6: ②－① | H6: ③R6実績 | I6: ②－③ | J6: ①R7予算 | K6: ②R7決見 | L6: ②－① | M6: ③R6実績 | N6: ②－③ | O6: ①R7予算 | P6: ②R7決見 | Q6: ②－① | R6: ③R6実績 | S6: ②－③ | T6: ①R7予算 | U6: ②R7決見 | V6: ②－① | W6: ③R6実績 | X6: ②－③ | Y6: ①R7予算 | Z6: ②R7決見 | AA6: ②－① | AB6: ③R6実績 | AC6: ②－③ | AD6: ①R7予算 | AE6: ②R7決見 | AF6: ②－① | AG6: ③R6実績 | AH6: ②－③ | AI6: ①R7予算 | AJ6: ②R7決見 | AK6: ②－① | AL6: ③R6実績 | AM6: ②－③ | AN6: ①R7予算 | AO6: ②R7決見 | AP6: ②－① | AQ6: ③R6実績 | AR6: ②－③ | AS6: ①R7予算 | AT6: ②R7決見 | AU6: ②－① | AV6: ③R6実績 | AW6: ②－③ | AX6: ①R7予算 | AY6: ②R7決見 | AZ6: ②－① | BA6: ③R6実績 | BB6: ②－③ | BC6: ①R7予算 | BD6: ②R7決見 | BE6: ②－① | BF6: ③R6実績 | BG6: ②－③ | BH6: ①R7予算 | BI6: ②R7決見 | BJ6: ②－① | BK6: ③R6実績 | BL6: ②－③ | BM6: ①R7予算 | BN6: ②R7決見 | BO6: ②－① | BP6: ③R6実績 | BQ6: ②－③ | BR6: ①R7予算 | BS6: ②R7決見 | BT6: ②－① | BU6: ③R6実績 | BV6: ②－③ | BW6: ①R7予算 | BX6: ②R7決見 | BY6: ②－① | BZ6: ③R6実績 | CA6: ②－③
A7: 総売上高 | E7: 98216.5 | F7: =+ﾇｰﾍﾞﾙﾌﾟｰｽ!W6/1000 -> 101506.71 | G7: =+E7-F7 -> -3290.205 | H7: 100726 | I7: =+E7-H7 -> -2509.5 | J7: 9212.097 | K7: =+ｶﾌｪﾙﾎﾟ!W6/1000 -> 8565.626 | L7: =+J7-K7 -> 646.471 | M7: 8389 | N7: =+J7-M7 -> 823.097 | O7: 19649 | P7: =+ｶﾌｪｾﾚｽﾃ!W6/1000 -> 20165.808 | Q7: =+O7-P7 -> -516.808 | R7: 19505 | S7: =+O7-R7 -> 144 | T7: =+E7+J7+O7 -> 127077.6 | U7: =+F7+K7+P7 -> 130238.14 | V7: =+T7-U7 -> -3160.542 | W7: =+H7+M7+R7 -> 128620 | X7: =+T7-W7 -> -1542.403 | AA7: =+Y7-Z7 -> 0 | AB7: 23760 | AC7: =+Y7-AB7 -> -23760 | AD7: 164317.97 | AE7: =+ｼﾞｭｴﾙｽﾞ!W6/1000 -> 167135.97 | AF7: =+AD7-AE7 -> -2818.005 | AG7: 162532 | AH7: =+AD7-AG7 -> 1785.966 | AI7: =+Y7+AD7 -> 164317.97 | AJ7: =+Z7+AE7 -> 167135.97 | AK7: =+AI7-AJ7 -> -2818.005 | AL7: =+AB7+AG7 -> 186292 | AM7: =+AI7-AL7 -> -21974.034 | AN7: 136763.17 | AO7: =+ｶﾞｰﾃﾞﾝ!W6/1000 -> 154985.14 | AP7: =+AN7-AO7 -> -18221.971 | AQ7: 136981 | AR7: =+AN7-AQ7 -> -217.828 | AS7: 154408.3 | AT7: =+ﾋﾞｱｶﾞｰﾃﾞﾝ!W6/1000 -> 178615.74 | AU7: =+AS7-AT7 -> -24207.444 | AV7: 139737 | AW7: =+AS7-AV7 -> 14671.295 | AX7: =+AN7+AS7 -> 291171.47 | AY7: =+AO7+AT7 -> 333600.88 | AZ7: =+AX7-AY7 -> -42429.415 | BA7: =+AQ7+AV7 -> 276718 | BB7: =+AX7-BA7 -> 14453.467 | BC7: 75365.66 | BD7: =+ブリック!W6/1000 -> 61370.735 | BE7: =+BC7-BD7 -> 13994.925 | BG7: =+BC7-BF7 -> 75365.66 | BH7: 50302.4 | BI7: =+ルスツ羊蹄ぶた!W6/1000 -> 34511.1 | BJ7: =+BH7-BI7 -> 15791.3 | BL7: =+BH7-BK7 -> 50302.4 | BM7: =+BC7+BH7 -> 125668.06 | BN7: =+BD7+BI7 -> 95881.835 | BO7: =+BM7-BN7 -> 29786.225 | BP7: =+BF7+BK7 -> 0 | BQ7: =+BM7-BP7 -> 125668.06 | BR7: 0 | BS7: =+料飲共通!W6/1000 -> 0 | BT7: =+BR7-BS7 -> 0 | BU7: 0 | BV7: =+BR7-BU7 -> 0 | BW7: =+T7+AI7+AX7+BM7+BR7 -> 708235.09 | BX7: =+U7+AJ7+AY7+BN7+BS7 -> 726856.83 | BY7: =+BW7-BX7 -> -18621.737 | BZ7: =+W7+AL7+BA7+BP7+BU7 -> 591630 | CA7: =+BW7-BZ7 -> 116605.09
B8: 売上 | E8: 98216.5 | F8: =+ﾇｰﾍﾞﾙﾌﾟｰｽ!W7/1000 -> 101506.71 | G8: =+E8-F8 -> -3290.205 | H8: 100726 | I8: =+E8-H8 -> -2509.5 | J8: 9212.097 | K8: =+ｶﾌｪﾙﾎﾟ!W7/1000 -> 8565.626 | L8: =+J8-K8 -> 646.471 | M8: 8389 | N8: =+J8-M8 -> 823.097 | O8: 19649 | P8: =+ｶﾌｪｾﾚｽﾃ!W7/1000 -> 20165.808 | Q8: =+O8-P8 -> -516.808 | R8: 19505 | S8: =+O8-R8 -> 144 | T8: =+E8+J8+O8 -> 127077.6 | U8: =+F8+K8+P8 -> 130238.14 | V8: =+T8-U8 -> -3160.542 | W8: =+H8+M8+R8 -> 128620 | X8: =+T8-W8 -> -1542.403 | AA8: =+Y8-Z8 -> 0 | AB8: 23760 | AC8: =+Y8-AB8 -> -23760 | AD8: 164317.97 | AE8: =+ｼﾞｭｴﾙｽﾞ!W7/1000 -> 167135.97 | AF8: =+AD8-AE8 -> -2818.005 | AG8: 162532 | AH8: =+AD8-AG8 -> 1785.966 | AI8: =+Y8+AD8 -> 164317.97 | AJ8: =+Z8+AE8 -> 167135.97 | AK8: =+AI8-AJ8 -> -2818.005 | AL8: =+AB8+AG8 -> 186292 | AM8: =+AI8-AL8 -> -21974.034 | AN8: 136763.17 | AO8: =+ｶﾞｰﾃﾞﾝ!W7/1000 -> 154985.14 | AP8: =+AN8-AO8 -> -18221.971 | AQ8: 136981 | AR8: =+AN8-AQ8 -> -217.828 | AS8: 154408.3 | AT8: =+ﾋﾞｱｶﾞｰﾃﾞﾝ!W7/1000 -> 178615.74 | AU8: =+AS8-AT8 -> -24207.444 | AV8: 139737 | AW8: =+AS8-AV8 -> 14671.295 | AX8: =+AN8+AS8 -> 291171.47 | AY8: =+AO8+AT8 -> 333600.88 | AZ8: =+AX8-AY8 -> -42429.415 | BA8: =+AQ8+AV8 -> 276718 | BB8: =+AX8-BA8 -> 14453.467 | BC8: 75365.66 | BD8: =+ブリック!W7/1000 -> 61370.735 | BE8: =+BC8-BD8 -> 13994.925 | BG8: =+BC8-BF8 -> 75365.66 | BH8: 50302.4 | BI8: =+ルスツ羊蹄ぶた!W7/1000 -> 34511.1 | BJ8: =+BH8-BI8 -> 15791.3 | BL8: =+BH8-BK8 -> 50302.4 | BM8: =+BC8+BH8 -> 125668.06 | BN8: =+BD8+BI8 -> 95881.835 | BO8: =+BM8-BN8 -> 29786.225 | BP8: =+BF8+BK8 -> 0 | BQ8: =+BM8-BP8 -> 125668.06 | BR8: 0 | BS8: =+料飲共通!W7/1000 -> 0 | BT8: =+BR8-BS8 -> 0 | BU8: 0 | BV8: =+BR8-BU8 -> 0 | BW8: =+T8+AI8+AX8+BM8+BR8 -> 708235.09 | BX8: =+U8+AJ8+AY8+BN8+BS8 -> 726856.83 | BY8: =+BW8-BX8 -> -18621.737 | BZ8: =+W8+AL8+BA8+BU8 -> 591630 | CA8: =+BW8-BZ8 -> 116605.09
B9: 損保代理店収入 | E9: 0 | F9: =+ﾇｰﾍﾞﾙﾌﾟｰｽ!W8/1000 -> 0 | G9: =+E9-F9 -> 0 | H9: 0 | I9: =+E9-H9 -> 0 | J9: 0 | K9: =+ｶﾌｪﾙﾎﾟ!W8/1000 -> 0 | L9: =+J9-K9 -> 0 | M9: 0 | N9: =+J9-M9 -> 0 | O9: 0 | P9: =+ｶﾌｪｾﾚｽﾃ!W8/1000 -> 0 | Q9: =+O9-P9 -> 0 | R9: 0 | S9: =+O9-R9 -> 0 | T9: =+E9+J9+O9 -> 0 | U9: =+F9+K9+P9 -> 0 | V9: =+T9-U9 -> 0 | W9: =+H9+M9+R9 -> 0 | X9: =+T9-W9 -> 0 | AA9: =+Y9-Z9 -> 0 | AB9: 0 | AC9: =+Y9-AB9 -> 0 | AD9: 0 | AE9: =+ｼﾞｭｴﾙｽﾞ!W8/1000 -> 0 | AF9: =+AD9-AE9 -> 0 | AG9: 0 | AH9: =+AD9-AG9 -> 0 | AI9: =+Y9+AD9 -> 0 | AJ9: =+Z9+AE9 -> 0 | AK9: =+AI9-AJ9 -> 0 | AL9: =+AB9+AG9 -> 0 | AM9: =+AI9-AL9 -> 0 | AN9: 0 | AO9: =+ｶﾞｰﾃﾞﾝ!W8/1000 -> 0 | AP9: =+AN9-AO9 -> 0 | AQ9: 0 | AR9: =+AN9-AQ9 -> 0 | AS9: 0 | AT9: =+ﾋﾞｱｶﾞｰﾃﾞﾝ!W8/1000 -> 0 | AU9: =+AS9-AT9 -> 0 | AV9: 0 | AW9: =+AS9-AV9 -> 0 | AX9: =+AN9+AS9 -> 0 | AY9: =+AO9+AT9 -> 0 | AZ9: =+AX9-AY9 -> 0 | BA9: =+AQ9+AV9 -> 0 | BB9: =+AX9-BA9 -> 0 | BC9: 0 | BD9: =+ブリック!W8/1000 -> 0 | BE9: =+BC9-BD9 -> 0 | BG9: =+BC9-BF9 -> 0 | BH9: 0 | BI9: =+ルスツ羊蹄ぶた!W8/1000 -> 0 | BJ9: =+BH9-BI9 -> 0 | BL9: =+BH9-BK9 -> 0 | BM9: =+BC9+BH9 -> 0 | BN9: =+BD9+BI9 -> 0 | BO9: =+BM9-BN9 -> 0 | BP9: =+BF9+BK9 -> 0 | BQ9: =+BM9-BP9 -> 0 | BR9: 0 | BS9: =+料飲共通!W8/1000 -> 0 | BT9: =+BR9-BS9 -> 0 | BU9: 0 | BV9: =+BR9-BU9 -> 0 | BW9: =+T9+AI9+AX9+BM9+BR9 -> 0 | BX9: =+U9+AJ9+AY9+BN9+BS9 -> 0 | BY9: =+BW9-BX9 -> 0 | BZ9: =+W9+AL9+BA9+BU9 -> 0 | CA9: =+BW9-BZ9 -> 0
B10: 販売手数料収入 | E10: 0 | F10: =+ﾇｰﾍﾞﾙﾌﾟｰｽ!W9/1000 -> 0 | G10: =+E10-F10 -> 0 | H10: 0 | I10: =+E10-H10 -> 0 | J10: 0 | K10: =+ｶﾌｪﾙﾎﾟ!W9/1000 -> 0 | L10: =+J10-K10 -> 0 | M10: 0 | N10: =+J10-M10 -> 0 | O10: 0 | P10: =+ｶﾌｪｾﾚｽﾃ!W9/1000 -> 0 | Q10: =+O10-P10 -> 0 | R10: 0 | S10: =+O10-R10 -> 0 | T10: =+E10+J10+O10 -> 0 | U10: =+F10+K10+P10 -> 0 | V10: =+T10-U10 -> 0 | W10: =+H10+M10+R10 -> 0 | X10: =+T10-W10 -> 0 | AA10: =+Y10-Z10 -> 0 | AB10: 0 | AC10: =+Y10-AB10 -> 0 | AD10: 0 | AE10: =+ｼﾞｭｴﾙｽﾞ!W9/1000 -> 0 | AF10: =+AD10-AE10 -> 0 | AG10: 0 | AH10: =+AD10-AG10 -> 0 | AI10: =+Y10+AD10 -> 0 | AJ10: =+Z10+AE10 -> 0 | AK10: =+AI10-AJ10 -> 0 | AL10: =+AB10+AG10 -> 0 | AM10: =+AI10-AL10 -> 0 | AN10: 0 | AO10: =+ｶﾞｰﾃﾞﾝ!W9/1000 -> 0 | AP10: =+AN10-AO10 -> 0 | AQ10: 0 | AR10: =+AN10-AQ10 -> 0 | AS10: 0 | AT10: =+ﾋﾞｱｶﾞｰﾃﾞﾝ!W9/1000 -> 0 | AU10: =+AS10-AT10 -> 0 | AV10: 0 | AW10: =+AS10-AV10 -> 0 | AX10: =+AN10+AS10 -> 0 | AY10: =+AO10+AT10 -> 0 | AZ10: =+AX10-AY10 -> 0 | BA10: =+AQ10+AV10 -> 0 | BB10: =+AX10-BA10 -> 0 | BC10: 0 | BD10: =+ブリック!W9/1000 -> 0 | BE10: =+BC10-BD10 -> 0 | BG10: =+BC10-BF10 -> 0 | BH10: 0 | BI10: =+ルスツ羊蹄ぶた!W9/1000 -> 0 | BJ10: =+BH10-BI10 -> 0 | BL10: =+BH10-BK10 -> 0 | BM10: =+BC10+BH10 -> 0 | BN10: =+BD10+BI10 -> 0 | BO10: =+BM10-BN10 -> 0 | BP10: =+BF10+BK10 -> 0 | BQ10: =+BM10-BP10 -> 0 | BR10: 0 | BS10: =+料飲共通!W9/1000 -> 0 | BT10: =+BR10-BS10 -> 0 | BU10: 0 | BV10: =+BR10-BU10 -> 0 | BW10: =+T10+AI10+AX10+BM10+BR10 -> 0 | BX10: =+U10+AJ10+AY10+BN10+BS10 -> 0 | BY10: =+BW10-BX10 -> 0 | BZ10: =+W10+AL10+BA10+BU10 -> 0 | CA10: =+BW10-BZ10 -> 0
B11: 索道収入 | E11: 0 | F11: =+ﾇｰﾍﾞﾙﾌﾟｰｽ!W10/1000 -> 0 | G11: =+E11-F11 -> 0 | H11: 0 | I11: =+E11-H11 -> 0 | J11: 0 | K11: =+ｶﾌｪﾙﾎﾟ!W10/1000 -> 0 | L11: =+J11-K11 -> 0 | M11: 0 | N11: =+J11-M11 -> 0 | O11: 0 | P11: =+ｶﾌｪｾﾚｽﾃ!W10/1000 -> 0 | Q11: =+O11-P11 -> 0 | R11: 0 | S11: =+O11-R11 -> 0 | T11: =+E11+J11+O11 -> 0 | U11: =+F11+K11+P11 -> 0 | V11: =+T11-U11 -> 0 | W11: =+H11+M11+R11 -> 0 | X11: =+T11-W11 -> 0 | AA11: =+Y11-Z11 -> 0 | AB11: 0 | AC11: =+Y11-AB11 -> 0 | AD11: 0 | AE11: =+ｼﾞｭｴﾙｽﾞ!W10/1000 -> 0 | AF11: =+AD11-AE11 -> 0 | AG11: 0 | AH11: =+AD11-AG11 -> 0 | AI11: =+Y11+AD11 -> 0 | AJ11: =+Z11+AE11 -> 0 | AK11: =+AI11-AJ11 -> 0 | AL11: =+AB11+AG11 -> 0 | AM11: =+AI11-AL11 -> 0 | AN11: 0 | AO11: =+ｶﾞｰﾃﾞﾝ!W10/1000 -> 0 | AP11: =+AN11-AO11 -> 0 | AQ11: 0 | AR11: =+AN11-AQ11 -> 0 | AS11: 0 | AT11: =+ﾋﾞｱｶﾞｰﾃﾞﾝ!W10/1000 -> 0 | AU11: =+AS11-AT11 -> 0 | AV11: 0 | AW11: =+AS11-AV11 -> 0 | AX11: =+AN11+AS11 -> 0 | AY11: =+AO11+AT11 -> 0 | AZ11: =+AX11-AY11 -> 0 | BA11: =+AQ11+AV11 -> 0 | BB11: =+AX11-BA11 -> 0 | BC11: 0 | BD11: =+ブリック!W10/1000 -> 0 | BE11: =+BC11-BD11 -> 0 | BG11: =+BC11-BF11 -> 0 | BH11: 0 | BI11: =+ルスツ羊蹄ぶた!W10/1000 -> 0 | BJ11: =+BH11-BI11 -> 0 | BL11: =+BH11-BK11 -> 0 | BM11: =+BC11+BH11 -> 0 | BN11: =+BD11+BI11 -> 0 | BO11: =+BM11-BN11 -> 0 | BP11: =+BF11+BK11 -> 0 | BQ11: =+BM11-BP11 -> 0 | BR11: 0 | BS11: =+料飲共通!W10/1000 -> 0 | BT11: =+BR11-BS11 -> 0 | BU11: 0 | BV11: =+BR11-BU11 -> 0 | BW11: =+T11+AI11+AX11+BM11+BR11 -> 0 | BX11: =+U11+AJ11+AY11+BN11+BS11 -> 0 | BY11: =+BW11-BX11 -> 0 | BZ11: =+W11+AL11+BA11+BU11 -> 0 | CA11: =+BW11-BZ11 -> 0
B12: 地代収入 | E12: 0 | F12: =+ﾇｰﾍﾞﾙﾌﾟｰｽ!W11/1000 -> 0 | G12: =+E12-F12 -> 0 | H12: 0 | I12: =+E12-H12 -> 0 | J12: 0 | K12: =+ｶﾌｪﾙﾎﾟ!W11/1000 -> 0 | L12: =+J12-K12 -> 0 | M12: 0 | N12: =+J12-M12 -> 0 | O12: 0 | P12: =+ｶﾌｪｾﾚｽﾃ!W11/1000 -> 0 | Q12: =+O12-P12 -> 0 | R12: 0 | S12: =+O12-R12 -> 0 | T12: =+E12+J12+O12 -> 0 | U12: =+F12+K12+P12 -> 0 | V12: =+T12-U12 -> 0 | W12: =+H12+M12+R12 -> 0 | X12: =+T12-W12 -> 0 | AA12: =+Y12-Z12 -> 0 | AB12: 0 | AC12: =+Y12-AB12 -> 0 | AD12: 0 | AE12: =+ｼﾞｭｴﾙｽﾞ!W11/1000 -> 0 | AF12: =+AD12-AE12 -> 0 | AG12: 0 | AH12: =+AD12-AG12 -> 0 | AI12: =+Y12+AD12 -> 0 | AJ12: =+Z12+AE12 -> 0 | AK12: =+AI12-AJ12 -> 0 | AL12: =+AB12+AG12 -> 0 | AM12: =+AI12-AL12 -> 0 | AN12: 0 | AO12: =+ｶﾞｰﾃﾞﾝ!W11/1000 -> 0 | AP12: =+AN12-AO12 -> 0 | AQ12: 0 | AR12: =+AN12-AQ12 -> 0 | AS12: 0 | AT12: =+ﾋﾞｱｶﾞｰﾃﾞﾝ!W11/1000 -> 0 | AU12: =+AS12-AT12 -> 0 | AV12: 0 | AW12: =+AS12-AV12 -> 0 | AX12: =+AN12+AS12 -> 0 | AY12: =+AO12+AT12 -> 0 | AZ12: =+AX12-AY12 -> 0 | BA12: =+AQ12+AV12 -> 0 | BB12: =+AX12-BA12 -> 0 | BC12: 0 | BD12: =+ブリック!W11/1000 -> 0 | BE12: =+BC12-BD12 -> 0 | BG12: =+BC12-BF12 -> 0 | BH12: 0 | BI12: =+ルスツ羊蹄ぶた!W11/1000 -> 0 | BJ12: =+BH12-BI12 -> 0 | BL12: =+BH12-BK12 -> 0 | BM12: =+BC12+BH12 -> 0 | BN12: =+BD12+BI12 -> 0 | BO12: =+BM12-BN12 -> 0 | BP12: =+BF12+BK12 -> 0 | BQ12: =+BM12-BP12 -> 0 | BR12: 0 | BS12: =+料飲共通!W11/1000 -> 0 | BT12: =+BR12-BS12 -> 0 | BU12: 0 | BV12: =+BR12-BU12 -> 0 | BW12: =+T12+AI12+AX12+BM12+BR12 -> 0 | BX12: =+U12+AJ12+AY12+BN12+BS12 -> 0 | BY12: =+BW12-BX12 -> 0 | BZ12: =+W12+AL12+BA12+BU12 -> 0 | CA12: =+BW12-BZ12 -> 0
B13: 家賃収入 | E13: 0 | F13: =+ﾇｰﾍﾞﾙﾌﾟｰｽ!W12/1000 -> 0 | G13: =+E13-F13 -> 0 | H13: 0 | I13: =+E13-H13 -> 0 | J13: 0 | K13: =+ｶﾌｪﾙﾎﾟ!W12/1000 -> 0 | L13: =+J13-K13 -> 0 | M13: 0 | N13: =+J13-M13 -> 0 | O13: 0 | P13: =+ｶﾌｪｾﾚｽﾃ!W12/1000 -> 0 | Q13: =+O13-P13 -> 0 | R13: 0 | S13: =+O13-R13 -> 0 | T13: =+E13+J13+O13 -> 0 | U13: =+F13+K13+P13 -> 0 | V13: =+T13-U13 -> 0 | W13: =+H13+M13+R13 -> 0 | X13: =+T13-W13 -> 0 | AA13: =+Y13-Z13 -> 0 | AB13: 0 | AC13: =+Y13-AB13 -> 0 | AD13: 0 | AE13: =+ｼﾞｭｴﾙｽﾞ!W12/1000 -> 0 | AF13: =+AD13-AE13 -> 0 | AG13: 0 | AH13: =+AD13-AG13 -> 0 | AI13: =+Y13+AD13 -> 0 | AJ13: =+Z13+AE13 -> 0 | AK13: =+AI13-AJ13 -> 0 | AL13: =+AB13+AG13 -> 0 | AM13: =+AI13-AL13 -> 0 | AN13: 0 | AO13: =+ｶﾞｰﾃﾞﾝ!W12/1000 -> 0 | AP13: =+AN13-AO13 -> 0 | AQ13: 0 | AR13: =+AN13-AQ13 -> 0 | AS13: 0 | AT13: =+ﾋﾞｱｶﾞｰﾃﾞﾝ!W12/1000 -> 0 | AU13: =+AS13-AT13 -> 0 | AV13: 0 | AW13: =+AS13-AV13 -> 0 | AX13: =+AN13+AS13 -> 0 | AY13: =+AO13+AT13 -> 0 | AZ13: =+AX13-AY13 -> 0 | BA13: =+AQ13+AV13 -> 0 | BB13: =+AX13-BA13 -> 0 | BC13: 0 | BD13: =+ブリック!W12/1000 -> 0 | BE13: =+BC13-BD13 -> 0 | BG13: =+BC13-BF13 -> 0 | BH13: 0 | BI13: =+ルスツ羊蹄ぶた!W12/1000 -> 0 | BJ13: =+BH13-BI13 -> 0 | BL13: =+BH13-BK13 -> 0 | BM13: =+BC13+BH13 -> 0 | BN13: =+BD13+BI13 -> 0 | BO13: =+BM13-BN13 -> 0 | BP13: =+BF13+BK13 -> 0 | BQ13: =+BM13-BP13 -> 0 | BR13: 0 | BS13: =+料飲共通!W12/1000 -> 0 | BT13: =+BR13-BS13 -> 0 | BU13: 0 | BV13: =+BR13-BU13 -> 0 | BW13: =+T13+AI13+AX13+BM13+BR13 -> 0 | BX13: =+U13+AJ13+AY13+BN13+BS13 -> 0 | BY13: =+BW13-BX13 -> 0 | BZ13: =+W13+AL13+BA13+BU13 -> 0 | CA13: =+BW13-BZ13 -> 0
B14: 駐車場収入 | E14: 0 | F14: =+ﾇｰﾍﾞﾙﾌﾟｰｽ!W13/1000 -> 0 | G14: =+E14-F14 -> 0 | H14: 0 | I14: =+E14-H14 -> 0 | J14: 0 | K14: =+ｶﾌｪﾙﾎﾟ!W13/1000 -> 0 | L14: =+J14-K14 -> 0 | M14: 0 | N14: =+J14-M14 -> 0 | O14: 0 | P14: =+ｶﾌｪｾﾚｽﾃ!W13/1000 -> 0 | Q14: =+O14-P14 -> 0 | R14: 0 | S14: =+O14-R14 -> 0 | T14: =+E14+J14+O14 -> 0 | U14: =+F14+K14+P14 -> 0 | V14: =+T14-U14 -> 0 | W14: =+H14+M14+R14 -> 0 | X14: =+T14-W14 -> 0 | AA14: =+Y14-Z14 -> 0 | AB14: 0 | AC14: =+Y14-AB14 -> 0 | AD14: 0 | AE14: =+ｼﾞｭｴﾙｽﾞ!W13/1000 -> 0 | AF14: =+AD14-AE14 -> 0 | AG14: 0 | AH14: =+AD14-AG14 -> 0 | AI14: =+Y14+AD14 -> 0 | AJ14: =+Z14+AE14 -> 0 | AK14: =+AI14-AJ14 -> 0 | AL14: =+AB14+AG14 -> 0 | AM14: =+AI14-AL14 -> 0 | AN14: 0 | AO14: =+ｶﾞｰﾃﾞﾝ!W13/1000 -> 0 | AP14: =+AN14-AO14 -> 0 | AQ14: 0 | AR14: =+AN14-AQ14 -> 0 | AS14: 0 | AT14: =+ﾋﾞｱｶﾞｰﾃﾞﾝ!W13/1000 -> 0 | AU14: =+AS14-AT14 -> 0 | AV14: 0 | AW14: =+AS14-AV14 -> 0 | AX14: =+AN14+AS14 -> 0 | AY14: =+AO14+AT14 -> 0 | AZ14: =+AX14-AY14 -> 0 | BA14: =+AQ14+AV14 -> 0 | BB14: =+AX14-BA14 -> 0 | BC14: 0 | BD14: =+ブリック!W13/1000 -> 0 | BE14: =+BC14-BD14 -> 0 | BG14: =+BC14-BF14 -> 0 | BH14: 0 | BI14: =+ルスツ羊蹄ぶた!W13/1000 -> 0 | BJ14: =+BH14-BI14 -> 0 | BL14: =+BH14-BK14 -> 0 | BM14: =+BC14+BH14 -> 0 | BN14: =+BD14+BI14 -> 0 | BO14: =+BM14-BN14 -> 0 | BP14: =+BF14+BK14 -> 0 | BQ14: =+BM14-BP14 -> 0 | BR14: 0 | BS14: =+料飲共通!W13/1000 -> 0 | BT14: =+BR14-BS14 -> 0 | BU14: 0 | BV14: =+BR14-BU14 -> 0 | BW14: =+T14+AI14+AX14+BM14+BR14 -> 0 | BX14: =+U14+AJ14+AY14+BN14+BS14 -> 0 | BY14: =+BW14-BX14 -> 0 | BZ14: =+W14+AL14+BA14+BU14 -> 0 | CA14: =+BW14-BZ14 -> 0
B15: 受託料 | E15: 0 | F15: =+ﾇｰﾍﾞﾙﾌﾟｰｽ!W14/1000 -> 0 | G15: =+E15-F15 -> 0 | H15: 0 | I15: =+E15-H15 -> 0 | J15: 0 | K15: =+ｶﾌｪﾙﾎﾟ!W14/1000 -> 0 | L15: =+J15-K15 -> 0 | M15: 0 | N15: =+J15-M15 -> 0 | O15: 0 | P15: =+ｶﾌｪｾﾚｽﾃ!W14/1000 -> 0 | Q15: =+O15-P15 -> 0 | R15: 0 | S15: =+O15-R15 -> 0 | T15: =+E15+J15+O15 -> 0 | U15: =+F15+K15+P15 -> 0 | V15: =+T15-U15 -> 0 | W15: =+H15+M15+R15 -> 0 | X15: =+T15-W15 -> 0 | AA15: =+Y15-Z15 -> 0 | AB15: 0 | AC15: =+Y15-AB15 -> 0 | AD15: 0 | AE15: =+ｼﾞｭｴﾙｽﾞ!W14/1000 -> 0 | AF15: =+AD15-AE15 -> 0 | AG15: 0 | AH15: =+AD15-AG15 -> 0 | AI15: =+Y15+AD15 -> 0 | AJ15: =+Z15+AE15 -> 0 | AK15: =+AI15-AJ15 -> 0 | AL15: =+AB15+AG15 -> 0 | AM15: =+AI15-AL15 -> 0 | AN15: 0 | AO15: =+ｶﾞｰﾃﾞﾝ!W14/1000 -> 0 | AP15: =+AN15-AO15 -> 0 | AQ15: 0 | AR15: =+AN15-AQ15 -> 0 | AS15: 0 | AT15: =+ﾋﾞｱｶﾞｰﾃﾞﾝ!W14/1000 -> 0 | AU15: =+AS15-AT15 -> 0 | AV15: 0 | AW15: =+AS15-AV15 -> 0 | AX15: =+AN15+AS15 -> 0 | AY15: =+AO15+AT15 -> 0 | AZ15: =+AX15-AY15 -> 0 | BA15: =+AQ15+AV15 -> 0 | BB15: =+AX15-BA15 -> 0 | BC15: 0 | BD15: =+ブリック!W14/1000 -> 0 | BE15: =+BC15-BD15 -> 0 | BG15: =+BC15-BF15 -> 0 | BH15: 0 | BI15: =+ルスツ羊蹄ぶた!W14/1000 -> 0 | BJ15: =+BH15-BI15 -> 0 | BL15: =+BH15-BK15 -> 0 | BM15: =+BC15+BH15 -> 0 | BN15: =+BD15+BI15 -> 0 | BO15: =+BM15-BN15 -> 0 | BP15: =+BF15+BK15 -> 0 | BQ15: =+BM15-BP15 -> 0 | BR15: 0 | BS15: =+料飲共通!W14/1000 -> 0 | BT15: =+BR15-BS15 -> 0 | BU15: 0 | BV15: =+BR15-BU15 -> 0 | BW15: =+T15+AI15+AX15+BM15+BR15 -> 0 | BX15: =+U15+AJ15+AY15+BN15+BS15 -> 0 | BY15: =+BW15-BX15 -> 0 | BZ15: =+W15+AL15+BA15+BU15 -> 0 | CA15: =+BW15-BZ15 -> 0
B16: 利用料金収入 | E16: 0 | F16: =+ﾇｰﾍﾞﾙﾌﾟｰｽ!W15/1000 -> 0 | G16: =+E16-F16 -> 0 | H16: 0 | I16: =+E16-H16 -> 0 | J16: 0 | K16: =+ｶﾌｪﾙﾎﾟ!W15/1000 -> 0 | L16: =+J16-K16 -> 0 | M16: 0 | N16: =+J16-M16 -> 0 | O16: 0 | P16: =+ｶﾌｪｾﾚｽﾃ!W15/1000 -> 0 | Q16: =+O16-P16 -> 0 | R16: 0 | S16: =+O16-R16 -> 0 | T16: =+E16+J16+O16 -> 0 | U16: =+F16+K16+P16 -> 0 | V16: =+T16-U16 -> 0 | W16: =+H16+M16+R16 -> 0 | X16: =+T16-W16 -> 0 | AA16: =+Y16-Z16 -> 0 | AB16: 0 | AC16: =+Y16-AB16 -> 0 | AD16: 0 | AE16: =+ｼﾞｭｴﾙｽﾞ!W15/1000 -> 0 | AF16: =+AD16-AE16 -> 0 | AG16: 0 | AH16: =+AD16-AG16 -> 0 | AI16: =+Y16+AD16 -> 0 | AJ16: =+Z16+AE16 -> 0 | AK16: =+AI16-AJ16 -> 0 | AL16: =+AB16+AG16 -> 0 | AM16: =+AI16-AL16 -> 0 | AN16: 0 | AO16: =+ｶﾞｰﾃﾞﾝ!W15/1000 -> 0 | AP16: =+AN16-AO16 -> 0 | AQ16: 0 | AR16: =+AN16-AQ16 -> 0 | AS16: 0 | AT16: =+ﾋﾞｱｶﾞｰﾃﾞﾝ!W15/1000 -> 0 | AU16: =+AS16-AT16 -> 0 | AV16: 0 | AW16: =+AS16-AV16 -> 0 | AX16: =+AN16+AS16 -> 0 | AY16: =+AO16+AT16 -> 0 | AZ16: =+AX16-AY16 -> 0 | BA16: =+AQ16+AV16 -> 0 | BB16: =+AX16-BA16 -> 0 | BC16: 0 | BD16: =+ブリック!W15/1000 -> 0 | BE16: =+BC16-BD16 -> 0 | BG16: =+BC16-BF16 -> 0 | BH16: 0 | BI16: =+ルスツ羊蹄ぶた!W15/1000 -> 0 | BJ16: =+BH16-BI16 -> 0 | BL16: =+BH16-BK16 -> 0 | BM16: =+BC16+BH16 -> 0 | BN16: =+BD16+BI16 -> 0 | BO16: =+BM16-BN16 -> 0 | BP16: =+BF16+BK16 -> 0 | BQ16: =+BM16-BP16 -> 0 | BR16: 0 | BS16: =+料飲共通!W15/1000 -> 0 | BT16: =+BR16-BS16 -> 0 | BU16: 0 | BV16: =+BR16-BU16 -> 0 | BW16: =+T16+AI16+AX16+BM16+BR16 -> 0 | BX16: =+U16+AJ16+AY16+BN16+BS16 -> 0 | BY16: =+BW16-BX16 -> 0 | BZ16: =+W16+AL16+BA16+BU16 -> 0 | CA16: =+BW16-BZ16 -> 0
B17: 管理手数料収入 | E17: 0 | F17: =+ﾇｰﾍﾞﾙﾌﾟｰｽ!W16/1000 -> 0 | G17: =+E17-F17 -> 0 | H17: 0 | I17: =+E17-H17 -> 0 | J17: 0 | K17: =+ｶﾌｪﾙﾎﾟ!W16/1000 -> 0 | L17: =+J17-K17 -> 0 | M17: 0 | N17: =+J17-M17 -> 0 | O17: 0 | P17: =+ｶﾌｪｾﾚｽﾃ!W16/1000 -> 0 | Q17: =+O17-P17 -> 0 | R17: 0 | S17: =+O17-R17 -> 0 | T17: =+E17+J17+O17 -> 0 | U17: =+F17+K17+P17 -> 0 | V17: =+T17-U17 -> 0 | W17: =+H17+M17+R17 -> 0 | X17: =+T17-W17 -> 0 | AA17: =+Y17-Z17 -> 0 | AB17: 0 | AC17: =+Y17-AB17 -> 0 | AD17: 0 | AE17: =+ｼﾞｭｴﾙｽﾞ!W16/1000 -> 0 | AF17: =+AD17-AE17 -> 0 | AG17: 0 | AH17: =+AD17-AG17 -> 0 | AI17: =+Y17+AD17 -> 0 | AJ17: =+Z17+AE17 -> 0 | AK17: =+AI17-AJ17 -> 0 | AL17: =+AB17+AG17 -> 0 | AM17: =+AI17-AL17 -> 0 | AN17: 0 | AO17: =+ｶﾞｰﾃﾞﾝ!W16/1000 -> 0 | AP17: =+AN17-AO17 -> 0 | AQ17: 0 | AR17: =+AN17-AQ17 -> 0 | AS17: 0 | AT17: =+ﾋﾞｱｶﾞｰﾃﾞﾝ!W16/1000 -> 0 | AU17: =+AS17-AT17 -> 0 | AV17: 0 | AW17: =+AS17-AV17 -> 0 | AX17: =+AN17+AS17 -> 0 | AY17: =+AO17+AT17 -> 0 | AZ17: =+AX17-AY17 -> 0 | BA17: =+AQ17+AV17 -> 0 | BB17: =+AX17-BA17 -> 0 | BC17: 0 | BD17: =+ブリック!W16/1000 -> 0 | BE17: =+BC17-BD17 -> 0 | BG17: =+BC17-BF17 -> 0 | BH17: 0 | BI17: =+ルスツ羊蹄ぶた!W16/1000 -> 0 | BJ17: =+BH17-BI17 -> 0 | BL17: =+BH17-BK17 -> 0 | BM17: =+BC17+BH17 -> 0 | BN17: =+BD17+BI17 -> 0 | BO17: =+BM17-BN17 -> 0 | BP17: =+BF17+BK17 -> 0 | BQ17: =+BM17-BP17 -> 0 | BR17: 0 | BS17: =+料飲共通!W16/1000 -> 0 | BT17: =+BR17-BS17 -> 0 | BU17: 0 | BV17: =+BR17-BU17 -> 0 | BW17: =+T17+AI17+AX17+BM17+BR17 -> 0 | BX17: =+U17+AJ17+AY17+BN17+BS17 -> 0 | BY17: =+BW17-BX17 -> 0 | BZ17: =+W17+AL17+BA17+BU17 -> 0 | CA17: =+BW17-BZ17 -> 0
A18: 売上原価 | E18: 28482.785 | F18: =+ﾇｰﾍﾞﾙﾌﾟｰｽ!W17/1000 -> 29413.918 | G18: =+E18-F18 -> -931.13294 | H18: 27854 | I18: =+E18-H18 -> 628.785 | J18: 2947.871 | K18: =+ｶﾌｪﾙﾎﾟ!W17/1000 -> 8029.1284 | L18: =+J18-K18 -> -5081.2574 | M18: 2583 | N18: =+J18-M18 -> 364.87104 | O18: 5992.945 | P18: =+ｶﾌｪｾﾚｽﾃ!W17/1000 -> 6150.5714 | Q18: =+O18-P18 -> -157.62644 | R18: 6094 | S18: =+O18-R18 -> -101.055 | T18: =+E18+J18+O18 -> 37423.601 | U18: =+F18+K18+P18 -> 43593.618 | V18: =+T18-U18 -> -6170.0167 | W18: =+H18+M18+R18 -> 36531 | X18: =+T18-W18 -> 892.60104 | AA18: =+Y18-Z18 -> 0 | AB18: 414 | AC18: =+Y18-AB18 -> -414 | AD18: 47241.415 | AE18: =+ｼﾞｭｴﾙｽﾞ!W17/1000 -> 50638.731 | AF18: =+AD18-AE18 -> -3397.3161 | AG18: 47293 | AH18: =+AD18-AG18 -> -51.584775 | AI18: =+Y18+AD18 -> 47241.415 | AJ18: =+Z18+AE18 -> 50638.731 | AK18: =+AI18-AJ18 -> -3397.3161 | AL18: =+AB18+AG18 -> 47707 | AM18: =+AI18-AL18 -> -465.58478 | AN18: 42396.583 | AO18: =+ｶﾞｰﾃﾞﾝ!W17/1000 -> 53089.448 | AP18: =+AN18-AO18 -> -10692.865 | AQ18: 43158 | AR18: =+AN18-AQ18 -> -761.41668 | AS18: 49044.367 | AT18: =+ﾋﾞｱｶﾞｰﾃﾞﾝ!W17/1000 -> 60924.351 | AU18: =+AS18-AT18 -> -11879.984 | AV18: 43625 | AW18: =+AS18-AV18 -> 5419.3667 | AX18: =+AN18+AS18 -> 91440.95 | AY18: =+AO18+AT18 -> 114013.8 | AZ18: =+AX18-AY18 -> -22572.849 | BA18: =+AQ18+AV18 -> 86783 | BB18: =+AX18-BA18 -> 4657.95 | BC18: 21479 | BD18: =+ブリック!W17/1000 -> 24163.422 | BE18: =+BC18-BD18 -> -2684.4221 | BG18: =+BC18-BF18 -> 21479 | BH18: 17605.84 | BI18: =+ルスツ羊蹄ぶた!W17/1000 -> 12854.093 | BJ18: =+BH18-BI18 -> 4751.7471 | BL18: =+BH18-BK18 -> 17605.84 | BM18: =+BC18+BH18 -> 39084.84 | BN18: =+BD18+BI18 -> 37017.515 | BO18: =+BM18-BN18 -> 2067.325 | BP18: =+BF18+BK18 -> 0 | BQ18: =+BM18-BP18 -> 39084.84 | BR18: 0 | BS18: =+料飲共通!W17/1000 -> 0 | BT18: =+BR18-BS18 -> 0 | BU18: 0 | BV18: =+BR18-BU18 -> 0 | BW18: =+T18+AI18+AX18+BM18+BR18 -> 215190.81 | BX18: =+U18+AJ18+AY18+BN18+BS18 -> 245263.66 | BY18: =+BW18-BX18 -> -30072.857 | BZ18: =+W18+AL18+BA18+BU18 -> 171021 | CA18: =+BW18-BZ18 -> 44169.806
A19: 売上総利益 | E19: 69733.715 | F19: =+ﾇｰﾍﾞﾙﾌﾟｰｽ!W18/1000 -> 72092.787 | G19: =+E19-F19 -> -2359.0721 | H19: 72872 | I19: =+E19-H19 -> -3138.285 | J19: 6264.226 | K19: =+ｶﾌｪﾙﾎﾟ!W18/1000 -> 536.4976 | L19: =+J19-K19 -> 5727.7284 | M19: 5807 | N19: =+J19-M19 -> 457.22596 | O19: 13656.055 | P19: =+ｶﾌｪｾﾚｽﾃ!W18/1000 -> 14015.237 | Q19: =+O19-P19 -> -359.18156 | R19: 13411 | S19: =+O19-R19 -> 245.055 | T19: =+E19+J19+O19 -> 89653.996 | U19: =+F19+K19+P19 -> 86644.521 | V19: =+T19-U19 -> 3009.4747 | W19: =+H19+M19+R19 -> 92090 | X19: =+T19-W19 -> -2436.004 | AA19: =+Y19-Z19 -> 0 | AB19: 23346 | AC19: =+Y19-AB19 -> -23346 | AD19: 117076.55 | AE19: =+ｼﾞｭｴﾙｽﾞ!W18/1000 -> 116497.24 | AF19: =+AD19-AE19 -> 579.31106 | AG19: 115239 | AH19: =+AD19-AG19 -> 1837.5508 | AI19: =+Y19+AD19 -> 117076.55 | AJ19: =+Z19+AE19 -> 116497.24 | AK19: =+AI19-AJ19 -> 579.31106 | AL19: =+AB19+AG19 -> 138585 | AM19: =+AI19-AL19 -> -21508.449 | AN19: 94366.589 | AO19: =+ｶﾞｰﾃﾞﾝ!W18/1000 -> 101895.69 | AP19: =+AN19-AO19 -> -7529.1059 | AQ19: 93824 | AR19: =+AN19-AQ19 -> 542.58868 | AS19: 105363.93 | AT19: =+ﾋﾞｱｶﾞｰﾃﾞﾝ!W18/1000 -> 117691.39 | AU19: =+AS19-AT19 -> -12327.46 | AV19: 96113 | AW19: =+AS19-AV19 -> 9250.9283 | AX19: =+AN19+AS19 -> 199730.52 | AY19: =+AO19+AT19 -> 219587.08 | AZ19: =+AX19-AY19 -> -19856.566 | BA19: =+AQ19+AV19 -> 189937 | BB19: =+AX19-BA19 -> 9793.517 | BC19: 53886.66 | BD19: =+ブリック!W18/1000 -> 37207.313 | BE19: =+BC19-BD19 -> 16679.347 | BG19: =+BC19-BF19 -> 53886.66 | BH19: 32696.56 | BI19: =+ルスツ羊蹄ぶた!W18/1000 -> 21657.007 | BJ19: =+BH19-BI19 -> 11039.553 | BL19: =+BH19-BK19 -> 32696.56 | BM19: =+BC19+BH19 -> 86583.22 | BN19: =+BD19+BI19 -> 58864.32 | BO19: =+BM19-BN19 -> 27718.9 | BP19: =+BF19+BK19 -> 0 | BQ19: =+BM19-BP19 -> 86583.22 | BR19: 0 | BS19: =+料飲共通!W18/1000 -> 0 | BT19: =+BR19-BS19 -> 0 | BU19: 0 | BV19: =+BR19-BU19 -> 0 | BW19: =+T19+AI19+AX19+BM19+BR19 -> 493044.28 | BX19: =+U19+AJ19+AY19+BN19+BS19 -> 481593.16 | BY19: =+BW19-BX19 -> 11451.12 | BZ19: =+W19+AL19+BA19+BU19 -> 420612 | CA19: =+BW19-BZ19 -> 72432.284
A20: 人件費 | E20: 53667.197 | F20: =+ﾇｰﾍﾞﾙﾌﾟｰｽ!W19/1000 -> 63993.442 | G20: =+E20-F20 -> -10326.245 | H20: 51376 | I20: =+E20-H20 -> 2291.197 | J20: 2876.874 | K20: =+ｶﾌｪﾙﾎﾟ!W19/1000 -> 6217.763 | L20: =+J20-K20 -> -3340.889 | M20: 3200 | N20: =+J20-M20 -> -323.126 | O20: 2876.875 | P20: =+ｶﾌｪｾﾚｽﾃ!W19/1000 -> 0 | Q20: =+O20-P20 -> 2876.875 | R20: 3200 | S20: =+O20-R20 -> -323.125 | T20: =+E20+J20+O20 -> 59420.946 | U20: =+F20+K20+P20 -> 70211.205 | V20: =+T20-U20 -> -10790.259 | W20: =+H20+M20+R20 -> 57776 | X20: =+T20-W20 -> 1644.946 | AA20: =+Y20-Z20 -> 0 | AB20: 5606 | AC20: =+Y20-AB20 -> -5606 | AD20: 66777.382 | AE20: =+ｼﾞｭｴﾙｽﾞ!W19/1000 -> 60085.083 | AF20: =+AD20-AE20 -> 6692.2994 | AG20: 64580 | AH20: =+AD20-AG20 -> 2197.3824 | AI20: =+Y20+AD20 -> 66777.382 | AJ20: =+Z20+AE20 -> 60085.083 | AK20: =+AI20-AJ20 -> 6692.2994 | AL20: =+AB20+AG20 -> 70186 | AM20: =+AI20-AL20 -> -3408.6176 | AN20: 58176.028 | AO20: =+ｶﾞｰﾃﾞﾝ!W19/1000 -> 72410.586 | AP20: =+AN20-AO20 -> -14234.558 | AQ20: 76468 | AR20: =+AN20-AQ20 -> -18291.972 | AS20: 24932.582 | AT20: =+ﾋﾞｱｶﾞｰﾃﾞﾝ!W19/1000 -> 7713.721 | AU20: =+AS20-AT20 -> 17218.861 | AV20: 3911 | AW20: =+AS20-AV20 -> 21021.582 | AX20: =+AN20+AS20 -> 83108.61 | AY20: =+AO20+AT20 -> 80124.307 | AZ20: =+AX20-AY20 -> 2984.3034 | BA20: =+AQ20+AV20 -> 80379 | BB20: =+AX20-BA20 -> 2729.6104 | BC20: 30146 | BD20: =+ブリック!W19/1000 -> 42858.783 | BE20: =+BC20-BD20 -> -12712.783 | BG20: =+BC20-BF20 -> 30146 | BH20: 16230 | BI20: =+ルスツ羊蹄ぶた!W19/1000 -> 8098.068 | BJ20: =+BH20-BI20 -> 8131.932 | BL20: =+BH20-BK20 -> 16230 | BM20: =+BC20+BH20 -> 46376 | BN20: =+BD20+BI20 -> 50956.851 | BO20: =+BM20-BN20 -> -4580.851 | BP20: =+BF20+BK20 -> 0 | BQ20: =+BM20-BP20 -> 46376 | BR20: 25580.282 | BS20: =+料飲共通!W19/1000 -> 44752.275 | BT20: =+BR20-BS20 -> -19171.993 | BU20: 25666 | BV20: =+BR20-BU20 -> -85.717552 | BW20: =+T20+AI20+AX20+BM20+BR20 -> 281263.22 | BX20: =+U20+AJ20+AY20+BN20+BS20 -> 306129.72 | BY20: =+BW20-BX20 -> -24866.5 | BZ20: =+W20+AL20+BA20+BU20 -> 234007 | CA20: =+BW20-BZ20 -> 47256.221
B21: 役員報酬 | E21: 0 | F21: =+ﾇｰﾍﾞﾙﾌﾟｰｽ!W20/1000 -> 0 | G21: =+E21-F21 -> 0 | H21: 0 | I21: =+E21-H21 -> 0 | J21: 0 | K21: =+ｶﾌｪﾙﾎﾟ!W20/1000 -> 0 | L21: =+J21-K21 -> 0 | M21: 0 | N21: =+J21-M21 -> 0 | O21: 0 | P21: =+ｶﾌｪｾﾚｽﾃ!W20/1000 -> 0 | Q21: =+O21-P21 -> 0 | R21: 0 | S21: =+O21-R21 -> 0 | T21: =+E21+J21+O21 -> 0 | U21: =+F21+K21+P21 -> 0 | V21: =+T21-U21 -> 0 | W21: =+H21+M21+R21 -> 0 | X21: =+T21-W21 -> 0 | AA21: =+Y21-Z21 -> 0 | AB21: 0 | AC21: =+Y21-AB21 -> 0 | AD21: 0 | AE21: =+ｼﾞｭｴﾙｽﾞ!W20/1000 -> 0 | AF21: =+AD21-AE21 -> 0 | AG21: 0 | AH21: =+AD21-AG21 -> 0 | AI21: =+Y21+AD21 -> 0 | AJ21: =+Z21+AE21 -> 0 | AK21: =+AI21-AJ21 -> 0 | AL21: =+AB21+AG21 -> 0 | AM21: =+AI21-AL21 -> 0 | AN21: 0 | AO21: =+ｶﾞｰﾃﾞﾝ!W20/1000 -> 0 | AP21: =+AN21-AO21 -> 0 | AQ21: 0 | AR21: =+AN21-AQ21 -> 0 | AS21: 0 | AT21: =+ﾋﾞｱｶﾞｰﾃﾞﾝ!W20/1000 -> 0 | AU21: =+AS21-AT21 -> 0 | AV21: 0 | AW21: =+AS21-AV21 -> 0 | AX21: =+AN21+AS21 -> 0 | AY21: =+AO21+AT21 -> 0 | AZ21: =+AX21-AY21 -> 0 | BA21: =+AQ21+AV21 -> 0 | BB21: =+AX21-BA21 -> 0 | BD21: =+ブリック!W20/1000 -> 0 | BE21: =+BC21-BD21 -> 0 | BG21: =+BC21-BF21 -> 0 | BH21: 0 | BI21: =+ルスツ羊蹄ぶた!W20/1000 -> 0 | BJ21: =+BH21-BI21 -> 0 | BL21: =+BH21-BK21 -> 0 | BM21: =+BC21+BH21 -> 0 | BN21: =+BD21+BI21 -> 0 | BO21: =+BM21-BN21 -> 0 | BP21: =+BF21+BK21 -> 0 | BQ21: =+BM21-BP21 -> 0 | BR21: 0 | BS21: =+料飲共通!W20/1000 -> 0 | BT21: =+BR21-BS21 -> 0 | BU21: 0 | BV21: =+BR21-BU21 -> 0 | BW21: =+T21+AI21+AX21+BM21+BR21 -> 0 | BX21: =+U21+AJ21+AY21+BN21+BS21 -> 0 | BY21: =+BW21-BX21 -> 0 | BZ21: =+W21+AL21+BA21+BU21 -> 0 | CA21: =+BW21-BZ21 -> 0
B22: 社員給与費 | E22: 0 | F22: =+ﾇｰﾍﾞﾙﾌﾟｰｽ!W21/1000 -> 0 | G22: =+E22-F22 -> 0 | H22: 0 | I22: =+E22-H22 -> 0 | J22: 0 | K22: =+ｶﾌｪﾙﾎﾟ!W21/1000 -> 0 | L22: =+J22-K22 -> 0 | M22: 0 | N22: =+J22-M22 -> 0 | O22: 0 | P22: =+ｶﾌｪｾﾚｽﾃ!W21/1000 -> 0 | Q22: =+O22-P22 -> 0 | R22: 0 | S22: =+O22-R22 -> 0 | T22: =+E22+J22+O22 -> 0 | U22: =+F22+K22+P22 -> 0 | V22: =+T22-U22 -> 0 | W22: =+H22+M22+R22 -> 0 | X22: =+T22-W22 -> 0 | AA22: =+Y22-Z22 -> 0 | AB22: 0 | AC22: =+Y22-AB22 -> 0 | AD22: 0 | AE22: =+ｼﾞｭｴﾙｽﾞ!W21/1000 -> 0 | AF22: =+AD22-AE22 -> 0 | AG22: 13 | AH22: =+AD22-AG22 -> -13 | AI22: =+Y22+AD22 -> 0 | AJ22: =+Z22+AE22 -> 0 | AK22: =+AI22-AJ22 -> 0 | AL22: =+AB22+AG22 -> 13 | AM22: =+AI22-AL22 -> -13 | AN22: 0 | AO22: =+ｶﾞｰﾃﾞﾝ!W21/1000 -> 0 | AP22: =+AN22-AO22 -> 0 | AQ22: 0 | AR22: =+AN22-AQ22 -> 0 | AS22: 0 | AT22: =+ﾋﾞｱｶﾞｰﾃﾞﾝ!W21/1000 -> 0 | AU22: =+AS22-AT22 -> 0 | AV22: 0 | AW22: =+AS22-AV22 -> 0 | AX22: =+AN22+AS22 -> 0 | AY22: =+AO22+AT22 -> 0 | AZ22: =+AX22-AY22 -> 0 | BA22: =+AQ22+AV22 -> 0 | BB22: =+AX22-BA22 -> 0 | BC22: 0 | BD22: =+ブリック!W21/1000 -> 0 | BE22: =+BC22-BD22 -> 0 | BG22: =+BC22-BF22 -> 0 | BH22: 0 | BI22: =+ルスツ羊蹄ぶた!W21/1000 -> 0 | BJ22: =+BH22-BI22 -> 0 | BL22: =+BH22-BK22 -> 0 | BM22: =+BC22+BH22 -> 0 | BN22: =+BD22+BI22 -> 0 | BO22: =+BM22-BN22 -> 0 | BP22: =+BF22+BK22 -> 0 | BQ22: =+BM22-BP22 -> 0 | BR22: 21846.07 | BS22: =+料飲共通!W21/1000 -> 39163.253 | BT22: =+BR22-BS22 -> -17317.183 | BU22: 21667 | BV22: =+BR22-BU22 -> 179.07 | BW22: =+T22+AI22+AX22+BM22+BR22 -> 21846.07 | BX22: =+U22+AJ22+AY22+BN22+BS22 -> 39163.253 | BY22: =+BW22-BX22 -> -17317.183 | BZ22: =+W22+AL22+BA22+BU22 -> 21680 | CA22: =+BW22-BZ22 -> 166.07
B23: 専門等給与費 | E23: 44651.64 | F23: =+ﾇｰﾍﾞﾙﾌﾟｰｽ!W22/1000 -> 55669.735 | G23: =+E23-F23 -> -11018.095 | H23: 44167 | I23: =+E23-H23 -> 484.64 | J23: 2524.2 | K23: =+ｶﾌｪﾙﾎﾟ!W22/1000 -> 5559.69 | L23: =+J23-K23 -> -3035.49 | M23: 2876 | N23: =+J23-M23 -> -351.8 | O23: 2524.2 | P23: =+ｶﾌｪｾﾚｽﾃ!W22/1000 -> 0 | Q23: =+O23-P23 -> 2524.2 | R23: 2876 | S23: =+O23-R23 -> -351.8 | T23: =+E23+J23+O23 -> 49700.04 | U23: =+F23+K23+P23 -> 61229.425 | V23: =+T23-U23 -> -11529.385 | W23: =+H23+M23+R23 -> 49919 | X23: =+T23-W23 -> -218.96 | AA23: =+Y23-Z23 -> 0 | AB23: 5123 | AC23: =+Y23-AB23 -> -5123 | AD23: 55698.34 | AE23: =+ｼﾞｭｴﾙｽﾞ!W22/1000 -> 53261.927 | AF23: =+AD23-AE23 -> 2436.413 | AG23: 55579 | AH23: =+AD23-AG23 -> 119.34 | AI23: =+Y23+AD23 -> 55698.34 | AJ23: =+Z23+AE23 -> 53261.927 | AK23: =+AI23-AJ23 -> 2436.413 | AL23: =+AB23+AG23 -> 60702 | AM23: =+AI23-AL23 -> -5003.66 | AN23: 49303.667 | AO23: =+ｶﾞｰﾃﾞﾝ!W22/1000 -> 63994.874 | AP23: =+AN23-AO23 -> -14691.207 | AQ23: 65357 | AR23: =+AN23-AQ23 -> -16053.333 | AS23: 21130.143 | AT23: =+ﾋﾞｱｶﾞｰﾃﾞﾝ!W22/1000 -> 7101.482 | AU23: =+AS23-AT23 -> 14028.661 | AV23: 3509 | AW23: =+AS23-AV23 -> 17621.143 | AX23: =+AN23+AS23 -> 70433.81 | AY23: =+AO23+AT23 -> 71096.356 | AZ23: =+AX23-AY23 -> -662.546 | BA23: =+AQ23+AV23 -> 68866 | BB23: =+AX23-BA23 -> 1567.81 | BC23: 30146 | BD23: =+ブリック!W22/1000 -> 37204.666 | BE23: =+BC23-BD23 -> -7058.666 | BG23: =+BC23-BF23 -> 30146 | BH23: 16230 | BI23: =+ルスツ羊蹄ぶた!W22/1000 -> 6766.442 | BJ23: =+BH23-BI23 -> 9463.558 | BL23: =+BH23-BK23 -> 16230 | BM23: =+BC23+BH23 -> 46376 | BN23: =+BD23+BI23 -> 43971.108 | BO23: =+BM23-BN23 -> 2404.892 | BP23: =+BF23+BK23 -> 0 | BQ23: =+BM23-BP23 -> 46376 | BR23: 0 | BS23: =+料飲共通!W22/1000 -> 75.35 | BT23: =+BR23-BS23 -> -75.35 | BU23: 0 | BV23: =+BR23-BU23 -> 0 | BW23: =+T23+AI23+AX23+BM23+BR23 -> 222208.19 | BX23: =+U23+AJ23+AY23+BN23+BS23 -> 229634.17 | BY23: =+BW23-BX23 -> -7425.976 | BZ23: =+W23+AL23+BA23+BU23 -> 179487 | CA23: =+BW23-BZ23 -> 42721.19
C24: 専門 | E24: 44462.64 | F24: =+ﾇｰﾍﾞﾙﾌﾟｰｽ!W23/1000 -> 52395.561 | G24: =+E24-F24 -> -7932.921 | H24: 42160 | I24: =+E24-H24 -> 2302.64 | J24: 0 | K24: =+ｶﾌｪﾙﾎﾟ!W23/1000 -> 0 | L24: =+J24-K24 -> 0 | M24: 0 | N24: =+J24-M24 -> 0 | O24: 0 | P24: =+ｶﾌｪｾﾚｽﾃ!W23/1000 -> 0 | Q24: =+O24-P24 -> 0 | R24: 0 | S24: =+O24-R24 -> 0 | T24: =+E24+J24+O24 -> 44462.64 | U24: =+F24+K24+P24 -> 52395.561 | V24: =+T24-U24 -> -7932.921 | W24: =+H24+M24+R24 -> 42160 | X24: =+T24-W24 -> 2302.64 | AA24: =+Y24-Z24 -> 0 | AB24: 2118 | AC24: =+Y24-AB24 -> -2118 | AD24: 50391.64 | AE24: =+ｼﾞｭｴﾙｽﾞ!W23/1000 -> 48027.976 | AF24: =+AD24-AE24 -> 2363.664 | AG24: 49913 | AH24: =+AD24-AG24 -> 478.64 | AI24: =+Y24+AD24 -> 50391.64 | AJ24: =+Z24+AE24 -> 48027.976 | AK24: =+AI24-AJ24 -> 2363.664 | AL24: =+AB24+AG24 -> 52031 | AM24: =+AI24-AL24 -> -1639.36 | AN24: 63275.81 | AO24: =+ｶﾞｰﾃﾞﾝ!W23/1000 -> 52404.985 | AP24: =+AN24-AO24 -> 10870.825 | AQ24: 57262 | AR24: =+AN24-AQ24 -> 6013.81 | AS24: 0 | AT24: =+ﾋﾞｱｶﾞｰﾃﾞﾝ!W23/1000 -> 0 | AU24: =+AS24-AT24 -> 0 | AV24: 0 | AW24: =+AS24-AV24 -> 0 | AX24: =+AN24+AS24 -> 63275.81 | AY24: =+AO24+AT24 -> 52404.985 | AZ24: =+AX24-AY24 -> 10870.825 | BA24: =+AQ24+AV24 -> 57262 | BB24: =+AX24-BA24 -> 6013.81 | BC24: 0 | BD24: =+ブリック!W23/1000 -> 36008.561 | BE24: =+BC24-BD24 -> -36008.561 | BG24: =+BC24-BF24 -> 0 | BH24: 0 | BI24: =+ルスツ羊蹄ぶた!W23/1000 -> 2705.268 | BJ24: =+BH24-BI24 -> -2705.268 | BL24: =+BH24-BK24 -> 0 | BM24: =+BC24+BH24 -> 0 | BN24: =+BD24+BI24 -> 38713.829 | BO24: =+BM24-BN24 -> -38713.829 | BP24: =+BF24+BK24 -> 0 | BQ24: =+BM24-BP24 -> 0 | BR24: 0 | BS24: =+料飲共通!W23/1000 -> 0 | BT24: =+BR24-BS24 -> 0 | BU24: 0 | BV24: =+BR24-BU24 -> 0 | BW24: =+T24+AI24+AX24+BM24+BR24 -> 158130.09 | BX24: =+U24+AJ24+AY24+BN24+BS24 -> 191542.35 | BY24: =+BW24-BX24 -> -33412.261 | BZ24: =+W24+AL24+BA24+BU24 -> 151453 | CA24: =+BW24-BZ24 -> 6677.09
C25: 臨時 | E25: 0 | F25: =+ﾇｰﾍﾞﾙﾌﾟｰｽ!W24/1000 -> 2746.879 | G25: =+E25-F25 -> -2746.879 | H25: 0 | I25: =+E25-H25 -> 0 | J25: 0 | K25: =+ｶﾌｪﾙﾎﾟ!W24/1000 -> 0 | L25: =+J25-K25 -> 0 | M25: 0 | N25: =+J25-M25 -> 0 | O25: 0 | P25: =+ｶﾌｪｾﾚｽﾃ!W24/1000 -> 0 | Q25: =+O25-P25 -> 0 | R25: 0 | S25: =+O25-R25 -> 0 | T25: =+E25+J25+O25 -> 0 | U25: =+F25+K25+P25 -> 2746.879 | V25: =+T25-U25 -> -2746.879 | W25: =+H25+M25+R25 -> 0 | X25: =+T25-W25 -> 0 | AA25: =+Y25-Z25 -> 0 | AB25: 0 | AC25: =+Y25-AB25 -> 0 | AD25: 0 | AE25: =+ｼﾞｭｴﾙｽﾞ!W24/1000 -> 901.71 | AF25: =+AD25-AE25 -> -901.71 | AG25: 0 | AH25: =+AD25-AG25 -> 0 | AI25: =+Y25+AD25 -> 0 | AJ25: =+Z25+AE25 -> 901.71 | AK25: =+AI25-AJ25 -> -901.71 | AL25: =+AB25+AG25 -> 0 | AM25: =+AI25-AL25 -> 0 | AN25: 0 | AO25: =+ｶﾞｰﾃﾞﾝ!W24/1000 -> 3382.787 | AP25: =+AN25-AO25 -> -3382.787 | AQ25: 0 | AR25: =+AN25-AQ25 -> 0 | AS25: 0 | AT25: =+ﾋﾞｱｶﾞｰﾃﾞﾝ!W24/1000 -> 7101.482 | AU25: =+AS25-AT25 -> -7101.482 | AV25: 0 | AW25: =+AS25-AV25 -> 0 | AX25: =+AN25+AS25 -> 0 | AY25: =+AO25+AT25 -> 10484.269 | AZ25: =+AX25-AY25 -> -10484.269 | BA25: =+AQ25+AV25 -> 0 | BB25: =+AX25-BA25 -> 0 | BC25: 0 | BD25: =+ブリック!W24/1000 -> 30.807 | BE25: =+BC25-BD25 -> -30.807 | BG25: =+BC25-BF25 -> 0 | BH25: 0 | BI25: =+ルスツ羊蹄ぶた!W24/1000 -> 32.025 | BJ25: =+BH25-BI25 -> -32.025 | BL25: =+BH25-BK25 -> 0 | BM25: =+BC25+BH25 -> 0 | BN25: =+BD25+BI25 -> 62.832 | BO25: =+BM25-BN25 -> -62.832 | BP25: =+BF25+BK25 -> 0 | BQ25: =+BM25-BP25 -> 0 | BR25: 0 | BS25: =+料飲共通!W24/1000 -> 0 | BT25: =+BR25-BS25 -> 0 | BU25: 0 | BV25: =+BR25-BU25 -> 0 | BW25: =+T25+AI25+AX25+BM25+BR25 -> 0 | BX25: =+U25+AJ25+AY25+BN25+BS25 -> 14195.69 | BY25: =+BW25-BX25 -> -14195.69 | BZ25: =+W25+AL25+BA25+BU25 -> 0 | CA25: =+BW25-BZ25 -> 0
C26: パート | E26: 189 | F26: =+ﾇｰﾍﾞﾙﾌﾟｰｽ!W25/1000 -> 527.295 | G26: =+E26-F26 -> -338.295 | H26: 2007 | I26: =+E26-H26 -> -1818 | J26: 2524.2 | K26: =+ｶﾌｪﾙﾎﾟ!W25/1000 -> 5559.69 | L26: =+J26-K26 -> -3035.49 | M26: 2876 | N26: =+J26-M26 -> -351.8 | O26: 2524.2 | P26: =+ｶﾌｪｾﾚｽﾃ!W25/1000 -> 0 | Q26: =+O26-P26 -> 2524.2 | R26: 2876 | S26: =+O26-R26 -> -351.8 | T26: =+E26+J26+O26 -> 5237.4 | U26: =+F26+K26+P26 -> 6086.985 | V26: =+T26-U26 -> -849.585 | W26: =+H26+M26+R26 -> 7759 | X26: =+T26-W26 -> -2521.6 | AA26: =+Y26-Z26 -> 0 | AB26: 3005 | AC26: =+Y26-AB26 -> -3005 | AD26: 5306.7 | AE26: =+ｼﾞｭｴﾙｽﾞ!W25/1000 -> 4332.241 | AF26: =+AD26-AE26 -> 974.459 | AG26: 5666 | AH26: =+AD26-AG26 -> -359.3 | AI26: =+Y26+AD26 -> 5306.7 | AJ26: =+Z26+AE26 -> 4332.241 | AK26: =+AI26-AJ26 -> 974.459 | AL26: =+AB26+AG26 -> 8671 | AM26: =+AI26-AL26 -> -3364.3 | AN26: 3528 | AO26: =+ｶﾞｰﾃﾞﾝ!W25/1000 -> 8207.102 | AP26: =+AN26-AO26 -> -4679.102 | AQ26: 8095 | AR26: =+AN26-AQ26 -> -4567 | AS26: 3630 | AT26: =+ﾋﾞｱｶﾞｰﾃﾞﾝ!W25/1000 -> 0 | AU26: =+AS26-AT26 -> 3630 | AV26: 3509 | AW26: =+AS26-AV26 -> 121 | AX26: =+AN26+AS26 -> 7158 | AY26: =+AO26+AT26 -> 8207.102 | AZ26: =+AX26-AY26 -> -1049.102 | BA26: =+AQ26+AV26 -> 11604 | BB26: =+AX26-BA26 -> -4446 | BC26: 0 | BD26: =+ブリック!W25/1000 -> 1165.298 | BE26: =+BC26-BD26 -> -1165.298 | BG26: =+BC26-BF26 -> 0 | BH26: 0 | BI26: =+ルスツ羊蹄ぶた!W25/1000 -> 4029.149 | BJ26: =+BH26-BI26 -> -4029.149 | BL26: =+BH26-BK26 -> 0 | BM26: =+BC26+BH26 -> 0 | BN26: =+BD26+BI26 -> 5194.447 | BO26: =+BM26-BN26 -> -5194.447 | BP26: =+BF26+BK26 -> 0 | BQ26: =+BM26-BP26 -> 0 | BR26: 0 | BS26: =+料飲共通!W25/1000 -> 75.35 | BT26: =+BR26-BS26 -> -75.35 | BU26: 0 | BV26: =+BR26-BU26 -> 0 | BW26: =+T26+AI26+AX26+BM26+BR26 -> 17702.1 | BX26: =+U26+AJ26+AY26+BN26+BS26 -> 23896.125 | BY26: =+BW26-BX26 -> -6194.025 | BZ26: =+W26+AL26+BA26+BU26 -> 28034 | CA26: =+BW26-BZ26 -> -10331.9
B27: 退職金 | E27: 0 | F27: =+ﾇｰﾍﾞﾙﾌﾟｰｽ!W26/1000 -> 0 | G27: =+E27-F27 -> 0 | H27: 0 | I27: =+E27-H27 -> 0 | J27: 0 | K27: =+ｶﾌｪﾙﾎﾟ!W26/1000 -> 0 | L27: =+J27-K27 -> 0 | M27: 0 | N27: =+J27-M27 -> 0 | O27: 0 | P27: =+ｶﾌｪｾﾚｽﾃ!W26/1000 -> 0 | Q27: =+O27-P27 -> 0 | R27: 0 | S27: =+O27-R27 -> 0 | T27: =+E27+J27+O27 -> 0 | U27: =+F27+K27+P27 -> 0 | V27: =+T27-U27 -> 0 | W27: =+H27+M27+R27 -> 0 | X27: =+T27-W27 -> 0 | AA27: =+Y27-Z27 -> 0 | AB27: 0 | AC27: =+Y27-AB27 -> 0 | AD27: 0 | AE27: =+ｼﾞｭｴﾙｽﾞ!W26/1000 -> 0 | AF27: =+AD27-AE27 -> 0 | AG27: 0 | AH27: =+AD27-AG27 -> 0 | AI27: =+Y27+AD27 -> 0 | AJ27: =+Z27+AE27 -> 0 | AK27: =+AI27-AJ27 -> 0 | AL27: =+AB27+AG27 -> 0 | AM27: =+AI27-AL27 -> 0 | AN27: 0 | AO27: =+ｶﾞｰﾃﾞﾝ!W26/1000 -> 0 | AP27: =+AN27-AO27 -> 0 | AQ27: 0 | AR27: =+AN27-AQ27 -> 0 | AS27: 0 | AT27: =+ﾋﾞｱｶﾞｰﾃﾞﾝ!W26/1000 -> 0 | AU27: =+AS27-AT27 -> 0 | AV27: 0 | AW27: =+AS27-AV27 -> 0 | AX27: =+AN27+AS27 -> 0 | AY27: =+AO27+AT27 -> 0 | AZ27: =+AX27-AY27 -> 0 | BA27: =+AQ27+AV27 -> 0 | BB27: =+AX27-BA27 -> 0 | BC27: 0 | BD27: =+ブリック!W26/1000 -> 0 | BE27: =+BC27-BD27 -> 0 | BG27: =+BC27-BF27 -> 0 | BH27: 0 | BI27: =+ルスツ羊蹄ぶた!W26/1000 -> 0 | BJ27: =+BH27-BI27 -> 0 | BL27: =+BH27-BK27 -> 0 | BM27: =+BC27+BH27 -> 0 | BN27: =+BD27+BI27 -> 0 | BO27: =+BM27-BN27 -> 0 | BP27: =+BF27+BK27 -> 0 | BQ27: =+BM27-BP27 -> 0 | BR27: 0 | BS27: =+料飲共通!W26/1000 -> 0 | BT27: =+BR27-BS27 -> 0 | BU27: 0 | BV27: =+BR27-BU27 -> 0 | BW27: =+T27+AI27+AX27+BM27+BR27 -> 0 | BX27: =+U27+AJ27+AY27+BN27+BS27 -> 0 | BY27: =+BW27-BX27 -> 0 | BZ27: =+W27+AL27+BA27+BU27 -> 0 | CA27: =+BW27-BZ27 -> 0
C28: 役員 | E28: 0 | F28: =+ﾇｰﾍﾞﾙﾌﾟｰｽ!W27/1000 -> 0 | G28: =+E28-F28 -> 0 | H28: 0 | I28: =+E28-H28 -> 0 | J28: 0 | K28: =+ｶﾌｪﾙﾎﾟ!W27/1000 -> 0 | L28: =+J28-K28 -> 0 | M28: 0 | N28: =+J28-M28 -> 0 | O28: 0 | P28: =+ｶﾌｪｾﾚｽﾃ!W27/1000 -> 0 | Q28: =+O28-P28 -> 0 | R28: 0 | S28: =+O28-R28 -> 0 | T28: =+E28+J28+O28 -> 0 | U28: =+F28+K28+P28 -> 0 | V28: =+T28-U28 -> 0 | W28: =+H28+M28+R28 -> 0 | X28: =+T28-W28 -> 0 | AA28: =+Y28-Z28 -> 0 | AB28: 0 | AC28: =+Y28-AB28 -> 0 | AD28: 0 | AE28: =+ｼﾞｭｴﾙｽﾞ!W27/1000 -> 0 | AF28: =+AD28-AE28 -> 0 | AG28: 0 | AH28: =+AD28-AG28 -> 0 | AI28: =+Y28+AD28 -> 0 | AJ28: =+Z28+AE28 -> 0 | AK28: =+AI28-AJ28 -> 0 | AL28: =+AB28+AG28 -> 0 | AM28: =+AI28-AL28 -> 0 | AN28: 0 | AO28: =+ｶﾞｰﾃﾞﾝ!W27/1000 -> 0 | AP28: =+AN28-AO28 -> 0 | AQ28: 0 | AR28: =+AN28-AQ28 -> 0 | AS28: 0 | AT28: =+ﾋﾞｱｶﾞｰﾃﾞﾝ!W27/1000 -> 0 | AU28: =+AS28-AT28 -> 0 | AV28: 0 | AW28: =+AS28-AV28 -> 0 | AX28: =+AN28+AS28 -> 0 | AY28: =+AO28+AT28 -> 0 | AZ28: =+AX28-AY28 -> 0 | BA28: =+AQ28+AV28 -> 0 | BB28: =+AX28-BA28 -> 0 | BC28: 0 | BD28: =+ブリック!W27/1000 -> 0 | BE28: =+BC28-BD28 -> 0 | BG28: =+BC28-BF28 -> 0 | BH28: 0 | BI28: =+ルスツ羊蹄ぶた!W27/1000 -> 0 | BJ28: =+BH28-BI28 -> 0 | BL28: =+BH28-BK28 -> 0 | BM28: =+BC28+BH28 -> 0 | BN28: =+BD28+BI28 -> 0 | BO28: =+BM28-BN28 -> 0 | BP28: =+BF28+BK28 -> 0 | BQ28: =+BM28-BP28 -> 0 | BR28: 0 | BS28: =+料飲共通!W27/1000 -> 0 | BT28: =+BR28-BS28 -> 0 | BU28: 0 | BV28: =+BR28-BU28 -> 0 | BW28: =+T28+AI28+AX28+BM28+BR28 -> 0 | BX28: =+U28+AJ28+AY28+BN28+BS28 -> 0 | BY28: =+BW28-BX28 -> 0 | BZ28: =+W28+AL28+BA28+BU28 -> 0 | CA28: =+BW28-BZ28 -> 0
C29: 社員 | E29: 0 | F29: =+ﾇｰﾍﾞﾙﾌﾟｰｽ!W28/1000 -> 0 | G29: =+E29-F29 -> 0 | H29: 0 | I29: =+E29-H29 -> 0 | J29: 0 | K29: =+ｶﾌｪﾙﾎﾟ!W28/1000 -> 0 | L29: =+J29-K29 -> 0 | M29: 0 | N29: =+J29-M29 -> 0 | O29: 0 | P29: =+ｶﾌｪｾﾚｽﾃ!W28/1000 -> 0 | Q29: =+O29-P29 -> 0 | R29: 0 | S29: =+O29-R29 -> 0 | T29: =+E29+J29+O29 -> 0 | U29: =+F29+K29+P29 -> 0 | V29: =+T29-U29 -> 0 | W29: =+H29+M29+R29 -> 0 | X29: =+T29-W29 -> 0 | AA29: =+Y29-Z29 -> 0 | AB29: 0 | AC29: =+Y29-AB29 -> 0 | AD29: 0 | AE29: =+ｼﾞｭｴﾙｽﾞ!W28/1000 -> 0 | AF29: =+AD29-AE29 -> 0 | AG29: 0 | AH29: =+AD29-AG29 -> 0 | AI29: =+Y29+AD29 -> 0 | AJ29: =+Z29+AE29 -> 0 | AK29: =+AI29-AJ29 -> 0 | AL29: =+AB29+AG29 -> 0 | AM29: =+AI29-AL29 -> 0 | AN29: 0 | AO29: =+ｶﾞｰﾃﾞﾝ!W28/1000 -> 0 | AP29: =+AN29-AO29 -> 0 | AQ29: 0 | AR29: =+AN29-AQ29 -> 0 | AS29: 0 | AT29: =+ﾋﾞｱｶﾞｰﾃﾞﾝ!W28/1000 -> 0 | AU29: =+AS29-AT29 -> 0 | AV29: 0 | AW29: =+AS29-AV29 -> 0 | AX29: =+AN29+AS29 -> 0 | AY29: =+AO29+AT29 -> 0 | AZ29: =+AX29-AY29 -> 0 | BA29: =+AQ29+AV29 -> 0 | BB29: =+AX29-BA29 -> 0 | BC29: 0 | BD29: =+ブリック!W28/1000 -> 0 | BE29: =+BC29-BD29 -> 0 | BG29: =+BC29-BF29 -> 0 | BH29: 0 | BI29: =+ルスツ羊蹄ぶた!W28/1000 -> 0 | BJ29: =+BH29-BI29 -> 0 | BL29: =+BH29-BK29 -> 0 | BM29: =+BC29+BH29 -> 0 | BN29: =+BD29+BI29 -> 0 | BO29: =+BM29-BN29 -> 0 | BP29: =+BF29+BK29 -> 0 | BQ29: =+BM29-BP29 -> 0 | BR29: 0 | BS29: =+料飲共通!W28/1000 -> 0 | BT29: =+BR29-BS29 -> 0 | BU29: 0 | BV29: =+BR29-BU29 -> 0 | BW29: =+T29+AI29+AX29+BM29+BR29 -> 0 | BX29: =+U29+AJ29+AY29+BN29+BS29 -> 0 | BY29: =+BW29-BX29 -> 0 | BZ29: =+W29+AL29+BA29+BU29 -> 0 | CA29: =+BW29-BZ29 -> 0
B30: 法定福利費 | E30: 7178.685 | F30: =+ﾇｰﾍﾞﾙﾌﾟｰｽ!W29/1000 -> 6257.241 | G30: =+E30-F30 -> 921.44398 | H30: 5897 | I30: =+E30-H30 -> 1281.685 | J30: 241.664 | K30: =+ｶﾌｪﾙﾎﾟ!W29/1000 -> 501.876 | L30: =+J30-K30 -> -260.212 | M30: 245 | N30: =+J30-M30 -> -3.336 | O30: 241.665 | P30: =+ｶﾌｪｾﾚｽﾃ!W29/1000 -> 0 | Q30: =+O30-P30 -> 241.665 | R30: 245 | S30: =+O30-R30 -> -3.335 | T30: =+E30+J30+O30 -> 7662.014 | U30: =+F30+K30+P30 -> 6759.117 | V30: =+T30-U30 -> 902.89698 | W30: =+H30+M30+R30 -> 6387 | X30: =+T30-W30 -> 1275.014 | AA30: =+Y30-Z30 -> 0 | AB30: 298 | AC30: =+Y30-AB30 -> -298 | AD30: 8543.7104 | AE30: =+ｼﾞｭｴﾙｽﾞ!W29/1000 -> 5404.554 | AF30: =+AD30-AE30 -> 3139.1564 | AG30: 7053 | AH30: =+AD30-AG30 -> 1490.7104 | AI30: =+Y30+AD30 -> 8543.7104 | AJ30: =+Z30+AE30 -> 5404.554 | AK30: =+AI30-AJ30 -> 3139.1564 | AL30: =+AB30+AG30 -> 7351 | AM30: =+AI30-AL30 -> 1192.7104 | AN30: 6767.259 | AO30: =+ｶﾞｰﾃﾞﾝ!W29/1000 -> 5387.882 | AP30: =+AN30-AO30 -> 1379.377 | AQ30: 8223 | AR30: =+AN30-AQ30 -> -1455.741 | AS30: 2900.2534 | AT30: =+ﾋﾞｱｶﾞｰﾃﾞﾝ!W29/1000 -> 0 | AU30: =+AS30-AT30 -> 2900.2534 | AV30: 0 | AW30: =+AS30-AV30 -> 2900.2534 | AX30: =+AN30+AS30 -> 9667.5124 | AY30: =+AO30+AT30 -> 5387.882 | AZ30: =+AX30-AY30 -> 4279.6304 | BA30: =+AQ30+AV30 -> 8223 | BB30: =+AX30-BA30 -> 1444.5124 | BC30: 0 | BD30: =+ブリック!W29/1000 -> 3972.631 | BE30: =+BC30-BD30 -> -3972.631 | BG30: =+BC30-BF30 -> 0 | BH30: 0 | BI30: =+ルスツ羊蹄ぶた!W29/1000 -> 275.313 | BJ30: =+BH30-BI30 -> -275.313 | BL30: =+BH30-BK30 -> 0 | BM30: =+BC30+BH30 -> 0 | BN30: =+BD30+BI30 -> 4247.944 | BO30: =+BM30-BN30 -> -4247.944 | BP30: =+BF30+BK30 -> 0 | BQ30: =+BM30-BP30 -> 0 | BR30: 3421.3564 | BS30: =+料飲共通!W29/1000 -> 4534.958 | BT30: =+BR30-BS30 -> -1113.6016 | BU30: 3322 | BV30: =+BR30-BU30 -> 99.356448 | BW30: =+T30+AI30+AX30+BM30+BR30 -> 29294.593 | BX30: =+U30+AJ30+AY30+BN30+BS30 -> 26334.455 | BY30: =+BW30-BX30 -> 2960.1382 | BZ30: =+W30+AL30+BA30+BU30 -> 25283 | CA30: =+BW30-BZ30 -> 4011.5932
B31: 退職年金掛金 | E31: 52.8 | F31: =+ﾇｰﾍﾞﾙﾌﾟｰｽ!W30/1000 -> 68 | G31: =+E31-F31 -> -15.2 | H31: 47 | I31: =+E31-H31 -> 5.8 | J31: 0 | K31: =+ｶﾌｪﾙﾎﾟ!W30/1000 -> 0 | L31: =+J31-K31 -> 0 | M31: 0 | N31: =+J31-M31 -> 0 | O31: 0 | P31: =+ｶﾌｪｾﾚｽﾃ!W30/1000 -> 0 | Q31: =+O31-P31 -> 0 | R31: 0 | S31: =+O31-R31 -> 0 | T31: =+E31+J31+O31 -> 52.8 | U31: =+F31+K31+P31 -> 68 | V31: =+T31-U31 -> -15.2 | W31: =+H31+M31+R31 -> 47 | X31: =+T31-W31 -> 5.8 | AA31: =+Y31-Z31 -> 0 | AB31: 0 | AC31: =+Y31-AB31 -> 0 | AD31: 62.4 | AE31: =+ｼﾞｭｴﾙｽﾞ!W30/1000 -> 88.8 | AF31: =+AD31-AE31 -> -26.4 | AG31: 51 | AH31: =+AD31-AG31 -> 11.4 | AI31: =+Y31+AD31 -> 62.4 | AJ31: =+Z31+AE31 -> 88.8 | AK31: =+AI31-AJ31 -> -26.4 | AL31: =+AB31+AG31 -> 51 | AM31: =+AI31-AL31 -> 11.4 | AN31: 50.4 | AO31: =+ｶﾞｰﾃﾞﾝ!W30/1000 -> 66.8 | AP31: =+AN31-AO31 -> -16.4 | AQ31: 70 | AR31: =+AN31-AQ31 -> -19.6 | AS31: 21.6 | AT31: =+ﾋﾞｱｶﾞｰﾃﾞﾝ!W30/1000 -> 0 | AU31: =+AS31-AT31 -> 21.6 | AV31: 0 | AW31: =+AS31-AV31 -> 21.6 | AX31: =+AN31+AS31 -> 72 | AY31: =+AO31+AT31 -> 66.8 | AZ31: =+AX31-AY31 -> 5.2 | BA31: =+AQ31+AV31 -> 70 | BB31: =+AX31-BA31 -> 2 | BC31: 0 | BD31: =+ブリック!W30/1000 -> 24.2 | BE31: =+BC31-BD31 -> -24.2 | BG31: =+BC31-BF31 -> 0 | BH31: 0 | BI31: =+ルスツ羊蹄ぶた!W30/1000 -> -0.8 | BJ31: =+BH31-BI31 -> 0.8 | BL31: =+BH31-BK31 -> 0 | BM31: =+BC31+BH31 -> 0 | BN31: =+BD31+BI31 -> 23.4 | BO31: =+BM31-BN31 -> -23.4 | BP31: =+BF31+BK31 -> 0 | BQ31: =+BM31-BP31 -> 0 | BR31: 14.4 | BS31: =+料飲共通!W30/1000 -> 20 | BT31: =+BR31-BS31 -> -5.6 | BU31: 14 | BV31: =+BR31-BU31 -> 0.4 | BW31: =+T31+AI31+AX31+BM31+BR31 -> 201.6 | BX31: =+U31+AJ31+AY31+BN31+BS31 -> 267 | BY31: =+BW31-BX31 -> -65.4 | BZ31: =+W31+AL31+BA31+BU31 -> 182 | CA31: =+BW31-BZ31 -> 19.6
B32: 福利厚生費 | E32: 609.2 | F32: =+ﾇｰﾍﾞﾙﾌﾟｰｽ!W31/1000 -> 392.02 | G32: =+E32-F32 -> 217.18 | H32: 111 | I32: =+E32-H32 -> 498.2 | J32: 0 | K32: =+ｶﾌｪﾙﾎﾟ!W31/1000 -> 0 | L32: =+J32-K32 -> 0 | M32: 9 | N32: =+J32-M32 -> -9 | O32: 0 | P32: =+ｶﾌｪｾﾚｽﾃ!W31/1000 -> 0 | Q32: =+O32-P32 -> 0 | R32: 9 | S32: =+O32-R32 -> -9 | T32: =+E32+J32+O32 -> 609.2 | U32: =+F32+K32+P32 -> 392.02 | V32: =+T32-U32 -> 217.18 | W32: =+H32+M32+R32 -> 129 | X32: =+T32-W32 -> 480.2 | AA32: =+Y32-Z32 -> 0 | AB32: 0 | AC32: =+Y32-AB32 -> 0 | AD32: 623.6 | AE32: =+ｼﾞｭｴﾙｽﾞ!W31/1000 -> 209.55 | AF32: =+AD32-AE32 -> 414.05 | AG32: 249 | AH32: =+AD32-AG32 -> 374.6 | AI32: =+Y32+AD32 -> 623.6 | AJ32: =+Z32+AE32 -> 209.55 | AK32: =+AI32-AJ32 -> 414.05 | AL32: =+AB32+AG32 -> 249 | AM32: =+AI32-AL32 -> 374.6 | AN32: 446.6 | AO32: =+ｶﾞｰﾃﾞﾝ!W31/1000 -> 261.156 | AP32: =+AN32-AO32 -> 185.444 | AQ32: 516 | AR32: =+AN32-AQ32 -> -69.4 | AS32: 191.4 | AT32: =+ﾋﾞｱｶﾞｰﾃﾞﾝ!W31/1000 -> 0 | AU32: =+AS32-AT32 -> 191.4 | AV32: 0 | AW32: =+AS32-AV32 -> 191.4 | AX32: =+AN32+AS32 -> 638 | AY32: =+AO32+AT32 -> 261.156 | AZ32: =+AX32-AY32 -> 376.844 | BA32: =+AQ32+AV32 -> 516 | BB32: =+AX32-BA32 -> 122 | BC32: 0 | BD32: =+ブリック!W31/1000 -> 570.027 | BE32: =+BC32-BD32 -> -570.027 | BG32: =+BC32-BF32 -> 0 | BH32: 0 | BI32: =+ルスツ羊蹄ぶた!W31/1000 -> 480.961 | BJ32: =+BH32-BI32 -> -480.961 | BL32: =+BH32-BK32 -> 0 | BM32: =+BC32+BH32 -> 0 | BN32: =+BD32+BI32 -> 1050.988 | BO32: =+BM32-BN32 -> -1050.988 | BP32: =+BF32+BK32 -> 0 | BQ32: =+BM32-BP32 -> 0 | BR32: 61.6 | BS32: =+料飲共通!W31/1000 -> 264.054 | BT32: =+BR32-BS32 -> -202.454 | BU32: 430 | BV32: =+BR32-BU32 -> -368.4 | BW32: =+T32+AI32+AX32+BM32+BR32 -> 1932.4 | BX32: =+U32+AJ32+AY32+BN32+BS32 -> 2177.768 | BY32: =+BW32-BX32 -> -245.368 | BZ32: =+W32+AL32+BA32+BU32 -> 1324 | CA32: =+BW32-BZ32 -> 608.4
C33: 福利厚生費 | E33: 79.2 | F33: =+ﾇｰﾍﾞﾙﾌﾟｰｽ!W32/1000 -> 69 | G33: =+E33-F33 -> 10.2 | H33: 56 | I33: =+E33-H33 -> 23.2 | J33: 0 | K33: =+ｶﾌｪﾙﾎﾟ!W32/1000 -> 0 | L33: =+J33-K33 -> 0 | M33: 0 | N33: =+J33-M33 -> 0 | O33: 0 | P33: =+ｶﾌｪｾﾚｽﾃ!W32/1000 -> 0 | Q33: =+O33-P33 -> 0 | R33: 0 | S33: =+O33-R33 -> 0 | T33: =+E33+J33+O33 -> 79.2 | U33: =+F33+K33+P33 -> 69 | V33: =+T33-U33 -> 10.2 | W33: =+H33+M33+R33 -> 56 | X33: =+T33-W33 -> 23.2 | AA33: =+Y33-Z33 -> 0 | AB33: 0 | AC33: =+Y33-AB33 -> 0 | AD33: 93.6 | AE33: =+ｼﾞｭｴﾙｽﾞ!W32/1000 -> 85.8 | AF33: =+AD33-AE33 -> 7.8 | AG33: 65 | AH33: =+AD33-AG33 -> 28.6 | AI33: =+Y33+AD33 -> 93.6 | AJ33: =+Z33+AE33 -> 85.8 | AK33: =+AI33-AJ33 -> 7.8 | AL33: =+AB33+AG33 -> 65 | AM33: =+AI33-AL33 -> 28.6 | AN33: 108 | AO33: =+ｶﾞｰﾃﾞﾝ!W32/1000 -> 92.596 | AP33: =+AN33-AO33 -> 15.404 | AQ33: 75 | AR33: =+AN33-AQ33 -> 33 | AS33: 0 | AT33: =+ﾋﾞｱｶﾞｰﾃﾞﾝ!W32/1000 -> 0 | AU33: =+AS33-AT33 -> 0 | AV33: 0 | AW33: =+AS33-AV33 -> 0 | AX33: =+AN33+AS33 -> 108 | AY33: =+AO33+AT33 -> 92.596 | AZ33: =+AX33-AY33 -> 15.404 | BA33: =+AQ33+AV33 -> 75 | BB33: =+AX33-BA33 -> 33 | BC33: 0 | BD33: =+ブリック!W32/1000 -> 56.892 | BE33: =+BC33-BD33 -> -56.892 | BG33: =+BC33-BF33 -> 0 | BH33: 0 | BI33: =+ルスツ羊蹄ぶた!W32/1000 -> -0.6 | BJ33: =+BH33-BI33 -> 0.6 | BL33: =+BH33-BK33 -> 0 | BM33: =+BC33+BH33 -> 0 | BN33: =+BD33+BI33 -> 56.292 | BO33: =+BM33-BN33 -> -56.292 | BP33: =+BF33+BK33 -> 0 | BQ33: =+BM33-BP33 -> 0 | BR33: 21.6 | BS33: =+料飲共通!W32/1000 -> 67.604 | BT33: =+BR33-BS33 -> -46.004 | BU33: 32 | BV33: =+BR33-BU33 -> -10.4 | BW33: =+T33+AI33+AX33+BM33+BR33 -> 302.4 | BX33: =+U33+AJ33+AY33+BN33+BS33 -> 371.292 | BY33: =+BW33-BX33 -> -68.892 | BZ33: =+W33+AL33+BA33+BU33 -> 228 | CA33: =+BW33-BZ33 -> 74.4
C34: 被服費 | E34: 330 | F34: =+ﾇｰﾍﾞﾙﾌﾟｰｽ!W33/1000 -> 323.02 | G34: =+E34-F34 -> 6.98 | H34: 48 | I34: =+E34-H34 -> 282 | J34: 0 | K34: =+ｶﾌｪﾙﾎﾟ!W33/1000 -> 0 | L34: =+J34-K34 -> 0 | M34: 9 | N34: =+J34-M34 -> -9 | O34: 0 | P34: =+ｶﾌｪｾﾚｽﾃ!W33/1000 -> 0 | Q34: =+O34-P34 -> 0 | R34: 9 | S34: =+O34-R34 -> -9 | T34: =+E34+J34+O34 -> 330 | U34: =+F34+K34+P34 -> 323.02 | V34: =+T34-U34 -> 6.98 | W34: =+H34+M34+R34 -> 66 | X34: =+T34-W34 -> 264 | AA34: =+Y34-Z34 -> 0 | AB34: 0 | AC34: =+Y34-AB34 -> 0 | AD34: 330 | AE34: =+ｼﾞｭｴﾙｽﾞ!W33/1000 -> 123.75 | AF34: =+AD34-AE34 -> 206.25 | AG34: 177 | AH34: =+AD34-AG34 -> 153 | AI34: =+Y34+AD34 -> 330 | AJ34: =+Z34+AE34 -> 123.75 | AK34: =+AI34-AJ34 -> 206.25 | AL34: =+AB34+AG34 -> 177 | AM34: =+AI34-AL34 -> 153 | AN34: 330 | AO34: =+ｶﾞｰﾃﾞﾝ!W33/1000 -> 168.56 | AP34: =+AN34-AO34 -> 161.44 | AQ34: 436 | AR34: =+AN34-AQ34 -> -106 | AS34: 0 | AT34: =+ﾋﾞｱｶﾞｰﾃﾞﾝ!W33/1000 -> 0 | AU34: =+AS34-AT34 -> 0 | AV34: 0 | AW34: =+AS34-AV34 -> 0 | AX34: =+AN34+AS34 -> 330 | AY34: =+AO34+AT34 -> 168.56 | AZ34: =+AX34-AY34 -> 161.44 | BA34: =+AQ34+AV34 -> 436 | BB34: =+AX34-BA34 -> -106 | BC34: 0 | BD34: =+ブリック!W33/1000 -> 513.135 | BE34: =+BC34-BD34 -> -513.135 | BG34: =+BC34-BF34 -> 0 | BH34: 0 | BI34: =+ルスツ羊蹄ぶた!W33/1000 -> 472.47 | BJ34: =+BH34-BI34 -> -472.47 | BL34: =+BH34-BK34 -> 0 | BM34: =+BC34+BH34 -> 0 | BN34: =+BD34+BI34 -> 985.605 | BO34: =+BM34-BN34 -> -985.605 | BP34: =+BF34+BK34 -> 0 | BQ34: =+BM34-BP34 -> 0 | BR34: 40 | BS34: =+料飲共通!W33/1000 -> 196.45 | BT34: =+BR34-BS34 -> -156.45 | BU34: 398 | BV34: =+BR34-BU34 -> -358 | BW34: =+T34+AI34+AX34+BM34+BR34 -> 1030 | BX34: =+U34+AJ34+AY34+BN34+BS34 -> 1797.385 | BY34: =+BW34-BX34 -> -767.385 | BZ34: =+W34+AL34+BA34+BU34 -> 1077 | CA34: =+BW34-BZ34 -> -47
C35: 研修費 | E35: 200 | F35: =+ﾇｰﾍﾞﾙﾌﾟｰｽ!W34/1000 -> 0 | G35: =+E35-F35 -> 200 | H35: 7 | I35: =+E35-H35 -> 193 | J35: 0 | K35: =+ｶﾌｪﾙﾎﾟ!W34/1000 -> 0 | L35: =+J35-K35 -> 0 | M35: 0 | N35: =+J35-M35 -> 0 | O35: 0 | P35: =+ｶﾌｪｾﾚｽﾃ!W34/1000 -> 0 | Q35: =+O35-P35 -> 0 | R35: 0 | S35: =+O35-R35 -> 0 | T35: =+E35+J35+O35 -> 200 | U35: =+F35+K35+P35 -> 0 | V35: =+T35-U35 -> 200 | W35: =+H35+M35+R35 -> 7 | X35: =+T35-W35 -> 193 | AA35: =+Y35-Z35 -> 0 | AB35: 0 | AC35: =+Y35-AB35 -> 0 | AD35: 200 | AE35: =+ｼﾞｭｴﾙｽﾞ!W34/1000 -> 0 | AF35: =+AD35-AE35 -> 200 | AG35: 7 | AH35: =+AD35-AG35 -> 193 | AI35: =+Y35+AD35 -> 200 | AJ35: =+Z35+AE35 -> 0 | AK35: =+AI35-AJ35 -> 200 | AL35: =+AB35+AG35 -> 7 | AM35: =+AI35-AL35 -> 193 | AN35: 200 | AO35: =+ｶﾞｰﾃﾞﾝ!W34/1000 -> 0 | AP35: =+AN35-AO35 -> 200 | AQ35: 5 | AR35: =+AN35-AQ35 -> 195 | AS35: 0 | AT35: =+ﾋﾞｱｶﾞｰﾃﾞﾝ!W34/1000 -> 0 | AU35: =+AS35-AT35 -> 0 | AV35: 0 | AW35: =+AS35-AV35 -> 0 | AX35: =+AN35+AS35 -> 200 | AY35: =+AO35+AT35 -> 0 | AZ35: =+AX35-AY35 -> 200 | BA35: =+AQ35+AV35 -> 5 | BB35: =+AX35-BA35 -> 195 | BC35: 0 | BD35: =+ブリック!W34/1000 -> 0 | BE35: =+BC35-BD35 -> 0 | BG35: =+BC35-BF35 -> 0 | BH35: 0 | BI35: =+ルスツ羊蹄ぶた!W34/1000 -> 9.091 | BJ35: =+BH35-BI35 -> -9.091 | BL35: =+BH35-BK35 -> 0 | BM35: =+BC35+BH35 -> 0 | BN35: =+BD35+BI35 -> 9.091 | BO35: =+BM35-BN35 -> -9.091 | BP35: =+BF35+BK35 -> 0 | BQ35: =+BM35-BP35 -> 0 | BR35: 0 | BS35: =+料飲共通!W34/1000 -> 0 | BT35: =+BR35-BS35 -> 0 | BU35: 0 | BV35: =+BR35-BU35 -> 0 | BW35: =+T35+AI35+AX35+BM35+BR35 -> 600 | BX35: =+U35+AJ35+AY35+BN35+BS35 -> 9.091 | BY35: =+BW35-BX35 -> 590.909 | BZ35: =+W35+AL35+BA35+BU35 -> 19 | CA35: =+BW35-BZ35 -> 581
B36: 通勤費 | E36: 1174.872 | F36: =+ﾇｰﾍﾞﾙﾌﾟｰｽ!W35/1000 -> 1606.446 | G36: =+E36-F36 -> -431.574 | H36: 1154 | I36: =+E36-H36 -> 20.872 | J36: 111.01 | K36: =+ｶﾌｪﾙﾎﾟ!W35/1000 -> 156.197 | L36: =+J36-K36 -> -45.187 | M36: 70 | N36: =+J36-M36 -> 41.01 | O36: 111.01 | P36: =+ｶﾌｪｾﾚｽﾃ!W35/1000 -> 0 | Q36: =+O36-P36 -> 111.01 | R36: 70 | S36: =+O36-R36 -> 41.01 | T36: =+E36+J36+O36 -> 1396.892 | U36: =+F36+K36+P36 -> 1762.643 | V36: =+T36-U36 -> -365.751 | W36: =+H36+M36+R36 -> 1294 | X36: =+T36-W36 -> 102.892 | AA36: =+Y36-Z36 -> 0 | AB36: 185 | AC36: =+Y36-AB36 -> -185 | AD36: 1849.332 | AE36: =+ｼﾞｭｴﾙｽﾞ!W35/1000 -> 1120.252 | AF36: =+AD36-AE36 -> 729.08 | AG36: 1634 | AH36: =+AD36-AG36 -> 215.332 | AI36: =+Y36+AD36 -> 1849.332 | AJ36: =+Z36+AE36 -> 1120.252 | AK36: =+AI36-AJ36 -> 729.08 | AL36: =+AB36+AG36 -> 1819 | AM36: =+AI36-AL36 -> 30.332 | AN36: 1608.102 | AO36: =+ｶﾞｰﾃﾞﾝ!W35/1000 -> 2699.874 | AP36: =+AN36-AO36 -> -1091.772 | AQ36: 2302 | AR36: =+AN36-AQ36 -> -693.898 | AS36: 689.186 | AT36: =+ﾋﾞｱｶﾞｰﾃﾞﾝ!W35/1000 -> 612.239 | AU36: =+AS36-AT36 -> 76.947 | AV36: 401 | AW36: =+AS36-AV36 -> 288.186 | AX36: =+AN36+AS36 -> 2297.288 | AY36: =+AO36+AT36 -> 3312.113 | AZ36: =+AX36-AY36 -> -1014.825 | BA36: =+AQ36+AV36 -> 2703 | BB36: =+AX36-BA36 -> -405.712 | BC36: 0 | BD36: =+ブリック!W35/1000 -> 1087.259 | BE36: =+BC36-BD36 -> -1087.259 | BG36: =+BC36-BF36 -> 0 | BH36: 0 | BI36: =+ルスツ羊蹄ぶた!W35/1000 -> 576.152 | BJ36: =+BH36-BI36 -> -576.152 | BL36: =+BH36-BK36 -> 0 | BM36: =+BC36+BH36 -> 0 | BN36: =+BD36+BI36 -> 1663.411 | BO36: =+BM36-BN36 -> -1663.411 | BP36: =+BF36+BK36 -> 0 | BQ36: =+BM36-BP36 -> 0 | BR36: 236.856 | BS36: =+料飲共通!W35/1000 -> 694.66 | BT36: =+BR36-BS36 -> -457.804 | BU36: 233 | BV36: =+BR36-BU36 -> 3.856 | BW36: =+T36+AI36+AX36+BM36+BR36 -> 5780.368 | BX36: =+U36+AJ36+AY36+BN36+BS36 -> 8553.079 | BY36: =+BW36-BX36 -> -2772.711 | BZ36: =+W36+AL36+BA36+BU36 -> 6049 | CA36: =+BW36-BZ36 -> -268.632
B37: 引当金繰入額 | E37: 0 | F37: =+ﾇｰﾍﾞﾙﾌﾟｰｽ!W36/1000 -> 0 | G37: =+E37-F37 -> 0 | H37: 0 | I37: =+E37-H37 -> 0 | J37: 0 | K37: =+ｶﾌｪﾙﾎﾟ!W36/1000 -> 0 | L37: =+J37-K37 -> 0 | M37: 0 | N37: =+J37-M37 -> 0 | O37: 0 | P37: =+ｶﾌｪｾﾚｽﾃ!W36/1000 -> 0 | Q37: =+O37-P37 -> 0 | R37: 0 | S37: =+O37-R37 -> 0 | T37: =+E37+J37+O37 -> 0 | U37: =+F37+K37+P37 -> 0 | V37: =+T37-U37 -> 0 | W37: =+H37+M37+R37 -> 0 | X37: =+T37-W37 -> 0 | AA37: =+Y37-Z37 -> 0 | AB37: 0 | AC37: =+Y37-AB37 -> 0 | AD37: 0 | AE37: =+ｼﾞｭｴﾙｽﾞ!W36/1000 -> 0 | AF37: =+AD37-AE37 -> 0 | AG37: 0 | AH37: =+AD37-AG37 -> 0 | AI37: =+Y37+AD37 -> 0 | AJ37: =+Z37+AE37 -> 0 | AK37: =+AI37-AJ37 -> 0 | AL37: =+AB37+AG37 -> 0 | AM37: =+AI37-AL37 -> 0 | AN37: 0 | AO37: =+ｶﾞｰﾃﾞﾝ!W36/1000 -> 0 | AP37: =+AN37-AO37 -> 0 | AQ37: 0 | AR37: =+AN37-AQ37 -> 0 | AS37: 0 | AT37: =+ﾋﾞｱｶﾞｰﾃﾞﾝ!W36/1000 -> 0 | AU37: =+AS37-AT37 -> 0 | AV37: 0 | AW37: =+AS37-AV37 -> 0 | AX37: =+AN37+AS37 -> 0 | AY37: =+AO37+AT37 -> 0 | AZ37: =+AX37-AY37 -> 0 | BA37: =+AQ37+AV37 -> 0 | BB37: =+AX37-BA37 -> 0 | BC37: 0 | BD37: =+ブリック!W36/1000 -> 0 | BE37: =+BC37-BD37 -> 0 | BG37: =+BC37-BF37 -> 0 | BH37: 0 | BI37: =+ルスツ羊蹄ぶた!W36/1000 -> 0 | BJ37: =+BH37-BI37 -> 0 | BL37: =+BH37-BK37 -> 0 | BM37: =+BC37+BH37 -> 0 | BN37: =+BD37+BI37 -> 0 | BO37: =+BM37-BN37 -> 0 | BP37: =+BF37+BK37 -> 0 | BQ37: =+BM37-BP37 -> 0 | BR37: 0 | BS37: =+料飲共通!W36/1000 -> 0 | BT37: =+BR37-BS37 -> 0 | BU37: 0 | BV37: =+BR37-BU37 -> 0 | BW37: =+T37+AI37+AX37+BM37+BR37 -> 0 | BX37: =+U37+AJ37+AY37+BN37+BS37 -> 0 | BY37: =+BW37-BX37 -> 0 | BZ37: =+W37+AL37+BA37+BU37 -> 0 | CA37: =+BW37-BZ37 -> 0
A38: 物件費 | E38: 24819.605 | F38: =+ﾇｰﾍﾞﾙﾌﾟｰｽ!W37/1000 -> 22075.142 | G38: =+E38-F38 -> 2744.463 | H38: 24156 | I38: =+E38-H38 -> 663.605 | J38: 2843.405 | K38: =+ｶﾌｪﾙﾎﾟ!W37/1000 -> 2688.842 | L38: =+J38-K38 -> 154.563 | M38: 2898 | N38: =+J38-M38 -> -54.595 | O38: 1603.983 | P38: =+ｶﾌｪｾﾚｽﾃ!W37/1000 -> 1619.286 | Q38: =+O38-P38 -> -15.303 | R38: 1666 | S38: =+O38-R38 -> -62.017 | T38: =+E38+J38+O38 -> 29266.993 | U38: =+F38+K38+P38 -> 26383.27 | V38: =+T38-U38 -> 2883.723 | W38: =+H38+M38+R38 -> 28720 | X38: =+T38-W38 -> 546.993 | AA38: =+Y38-Z38 -> 0 | AB38: 1367 | AC38: =+Y38-AB38 -> -1367 | AD38: 22752.677 | AE38: =+ｼﾞｭｴﾙｽﾞ!W37/1000 -> 20235.614 | AF38: =+AD38-AE38 -> 2517.063 | AG38: 25991 | AH38: =+AD38-AG38 -> -3238.323 | AI38: =+Y38+AD38 -> 22752.677 | AJ38: =+Z38+AE38 -> 20235.614 | AK38: =+AI38-AJ38 -> 2517.063 | AL38: =+AB38+AG38 -> 27358 | AM38: =+AI38-AL38 -> -4605.323 | AN38: 34114.208 | AO38: =+ｶﾞｰﾃﾞﾝ!W37/1000 -> 34477.414 | AP38: =+AN38-AO38 -> -363.206 | AQ38: 36345 | AR38: =+AN38-AQ38 -> -2230.792 | AS38: 64246.364 | AT38: =+ﾋﾞｱｶﾞｰﾃﾞﾝ!W37/1000 -> 71458.464 | AU38: =+AS38-AT38 -> -7212.1 | AV38: 77278 | AW38: =+AS38-AV38 -> -13031.636 | AX38: =+AN38+AS38 -> 98360.572 | AY38: =+AO38+AT38 -> 105935.88 | AZ38: =+AX38-AY38 -> -7575.306 | BA38: =+AQ38+AV38 -> 113623 | BB38: =+AX38-BA38 -> -15262.428 | BC38: 19363.931 | BD38: =+ブリック!W37/1000 -> 30152.734 | BE38: =+BC38-BD38 -> -10788.803 | BG38: =+BC38-BF38 -> 19363.931 | BH38: 12688.171 | BI38: =+ルスツ羊蹄ぶた!W37/1000 -> 12579.179 | BJ38: =+BH38-BI38 -> 108.99246 | BL38: =+BH38-BK38 -> 12688.171 | BM38: =+BC38+BH38 -> 32052.103 | BN38: =+BD38+BI38 -> 42731.913 | BO38: =+BM38-BN38 -> -10679.81 | BP38: =+BF38+BK38 -> 0 | BQ38: =+BM38-BP38 -> 32052.103 | BR38: 2443.85 | BS38: =+料飲共通!W37/1000 -> 4455.652 | BT38: =+BR38-BS38 -> -2011.802 | BU38: 7980 | BV38: =+BR38-BU38 -> -5536.15 | BW38: =+T38+AI38+AX38+BM38+BR38 -> 184876.19 | BX38: =+U38+AJ38+AY38+BN38+BS38 -> 199742.33 | BY38: =+BW38-BX38 -> -14866.132 | BZ38: =+W38+AL38+BA38+BU38 -> 177681 | CA38: =+BW38-BZ38 -> 7195.1948
B39: 消耗品費 | E39: 2520 | F39: =+ﾇｰﾍﾞﾙﾌﾟｰｽ!W38/1000 -> 1774.83 | G39: =+E39-F39 -> 745.17 | H39: 2806 | I39: =+E39-H39 -> -286 | J39: 560 | K39: =+ｶﾌｪﾙﾎﾟ!W38/1000 -> 602.035 | L39: =+J39-K39 -> -42.035 | M39: 512 | N39: =+J39-M39 -> 48 | O39: 60 | P39: =+ｶﾌｪｾﾚｽﾃ!W38/1000 -> 30 | Q39: =+O39-P39 -> 30 | R39: 202 | S39: =+O39-R39 -> -142 | T39: =+E39+J39+O39 -> 3140 | U39: =+F39+K39+P39 -> 2406.865 | V39: =+T39-U39 -> 733.135 | W39: =+H39+M39+R39 -> 3520 | X39: =+T39-W39 -> -380 | AA39: =+Y39-Z39 -> 0 | AB39: 620 | AC39: =+Y39-AB39 -> -620 | AD39: 3813.5 | AE39: =+ｼﾞｭｴﾙｽﾞ!W38/1000 -> 3469.764 | AF39: =+AD39-AE39 -> 343.736 | AG39: 5864 | AH39: =+AD39-AG39 -> -2050.5 | AI39: =+Y39+AD39 -> 3813.5 | AJ39: =+Z39+AE39 -> 3469.764 | AK39: =+AI39-AJ39 -> 343.736 | AL39: =+AB39+AG39 -> 6484 | AM39: =+AI39-AL39 -> -2670.5 | AN39: 2380 | AO39: =+ｶﾞｰﾃﾞﾝ!W38/1000 -> 2493.685 | AP39: =+AN39-AO39 -> -113.685 | AQ39: 4106 | AR39: =+AN39-AQ39 -> -1726 | AS39: 4439 | AT39: =+ﾋﾞｱｶﾞｰﾃﾞﾝ!W38/1000 -> 5235.503 | AU39: =+AS39-AT39 -> -796.503 | AV39: 4405 | AW39: =+AS39-AV39 -> 34 | AX39: =+AN39+AS39 -> 6819 | AY39: =+AO39+AT39 -> 7729.188 | AZ39: =+AX39-AY39 -> -910.188 | BA39: =+AQ39+AV39 -> 8511 | BB39: =+AX39-BA39 -> -1692 | BC39: 1840.8903 | BD39: =+ブリック!W38/1000 -> 7297.141 | BE39: =+BC39-BD39 -> -5456.2507 | BG39: =+BC39-BF39 -> 1840.8903 | BH39: 1186.5044 | BI39: =+ルスツ羊蹄ぶた!W38/1000 -> 1346.436 | BJ39: =+BH39-BI39 -> -159.93157 | BL39: =+BH39-BK39 -> 1186.5044 | BM39: =+BC39+BH39 -> 3027.3947 | BN39: =+BD39+BI39 -> 8643.577 | BO39: =+BM39-BN39 -> -5616.1823 | BP39: =+BF39+BK39 -> 0 | BQ39: =+BM39-BP39 -> 3027.3947 | BR39: 0 | BS39: =+料飲共通!W38/1000 -> 579.2 | BT39: =+BR39-BS39 -> -579.2 | BU39: 0 | BV39: =+BR39-BU39 -> 0 | BW39: =+T39+AI39+AX39+BM39+BR39 -> 16799.895 | BX39: =+U39+AJ39+AY39+BN39+BS39 -> 22828.594 | BY39: =+BW39-BX39 -> -6028.6993 | BZ39: =+W39+AL39+BA39+BU39 -> 18515 | CA39: =+BW39-BZ39 -> -1715.1053
B40: 事務用品費 | E40: 260 | F40: =+ﾇｰﾍﾞﾙﾌﾟｰｽ!W39/1000 -> 291.009 | G40: =+E40-F40 -> -31.009 | H40: 268 | I40: =+E40-H40 -> -8 | J40: 0 | K40: =+ｶﾌｪﾙﾎﾟ!W39/1000 -> 0 | L40: =+J40-K40 -> 0 | M40: 19 | N40: =+J40-M40 -> -19 | O40: 0 | P40: =+ｶﾌｪｾﾚｽﾃ!W39/1000 -> 0 | Q40: =+O40-P40 -> 0 | R40: 0 | S40: =+O40-R40 -> 0 | T40: =+E40+J40+O40 -> 260 | U40: =+F40+K40+P40 -> 291.009 | V40: =+T40-U40 -> -31.009 | W40: =+H40+M40+R40 -> 287 | X40: =+T40-W40 -> -27 | AA40: =+Y40-Z40 -> 0 | AB40: 0 | AC40: =+Y40-AB40 -> 0 | AD40: 300 | AE40: =+ｼﾞｭｴﾙｽﾞ!W39/1000 -> 233.404 | AF40: =+AD40-AE40 -> 66.596 | AG40: 266 | AH40: =+AD40-AG40 -> 34 | AI40: =+Y40+AD40 -> 300 | AJ40: =+Z40+AE40 -> 233.404 | AK40: =+AI40-AJ40 -> 66.596 | AL40: =+AB40+AG40 -> 266 | AM40: =+AI40-AL40 -> 34 | AN40: 300 | AO40: =+ｶﾞｰﾃﾞﾝ!W39/1000 -> 401.336 | AP40: =+AN40-AO40 -> -101.336 | AQ40: 392 | AR40: =+AN40-AQ40 -> -92 | AS40: 50 | AT40: =+ﾋﾞｱｶﾞｰﾃﾞﾝ!W39/1000 -> 36.377 | AU40: =+AS40-AT40 -> 13.623 | AV40: 11 | AW40: =+AS40-AV40 -> 39 | AX40: =+AN40+AS40 -> 350 | AY40: =+AO40+AT40 -> 437.713 | AZ40: =+AX40-AY40 -> -87.713 | BA40: =+AQ40+AV40 -> 403 | BB40: =+AX40-BA40 -> -53 | BC40: 204.96244 | BD40: =+ブリック!W39/1000 -> 42.528 | BE40: =+BC40-BD40 -> 162.43444 | BG40: =+BC40-BF40 -> 204.96244 | BH40: 0 | BI40: =+ルスツ羊蹄ぶた!W39/1000 -> 17.77 | BJ40: =+BH40-BI40 -> -17.77 | BL40: =+BH40-BK40 -> 0 | BM40: =+BC40+BH40 -> 204.96244 | BN40: =+BD40+BI40 -> 60.298 | BO40: =+BM40-BN40 -> 144.66444 | BP40: =+BF40+BK40 -> 0 | BQ40: =+BM40-BP40 -> 204.96244 | BR40: 0 | BS40: =+料飲共通!W39/1000 -> 0.8 | BT40: =+BR40-BS40 -> -0.8 | BU40: 0 | BV40: =+BR40-BU40 -> 0 | BW40: =+T40+AI40+AX40+BM40+BR40 -> 1114.9624 | BX40: =+U40+AJ40+AY40+BN40+BS40 -> 1023.224 | BY40: =+BW40-BX40 -> 91.738439 | BZ40: =+W40+AL40+BA40+BU40 -> 956 | CA40: =+BW40-BZ40 -> 158.96244
B41: 図書購入費 | E41: 0 | F41: =+ﾇｰﾍﾞﾙﾌﾟｰｽ!W40/1000 -> 0 | G41: =+E41-F41 -> 0 | H41: 0 | I41: =+E41-H41 -> 0 | J41: 0 | K41: =+ｶﾌｪﾙﾎﾟ!W40/1000 -> 0 | L41: =+J41-K41 -> 0 | M41: 0 | N41: =+J41-M41 -> 0 | O41: 0 | P41: =+ｶﾌｪｾﾚｽﾃ!W40/1000 -> 0 | Q41: =+O41-P41 -> 0 | R41: 0 | S41: =+O41-R41 -> 0 | T41: =+E41+J41+O41 -> 0 | U41: =+F41+K41+P41 -> 0 | V41: =+T41-U41 -> 0 | W41: =+H41+M41+R41 -> 0 | X41: =+T41-W41 -> 0 | AA41: =+Y41-Z41 -> 0 | AB41: 0 | AC41: =+Y41-AB41 -> 0 | AD41: 0 | AE41: =+ｼﾞｭｴﾙｽﾞ!W40/1000 -> 0 | AF41: =+AD41-AE41 -> 0 | AG41: 0 | AH41: =+AD41-AG41 -> 0 | AI41: =+Y41+AD41 -> 0 | AJ41: =+Z41+AE41 -> 0 | AK41: =+AI41-AJ41 -> 0 | AL41: =+AB41+AG41 -> 0 | AM41: =+AI41-AL41 -> 0 | AN41: 0 | AO41: =+ｶﾞｰﾃﾞﾝ!W40/1000 -> 0 | AP41: =+AN41-AO41 -> 0 | AQ41: 0 | AR41: =+AN41-AQ41 -> 0 | AS41: 0 | AT41: =+ﾋﾞｱｶﾞｰﾃﾞﾝ!W40/1000 -> 0 | AU41: =+AS41-AT41 -> 0 | AV41: 0 | AW41: =+AS41-AV41 -> 0 | AX41: =+AN41+AS41 -> 0 | AY41: =+AO41+AT41 -> 0 | AZ41: =+AX41-AY41 -> 0 | BA41: =+AQ41+AV41 -> 0 | BB41: =+AX41-BA41 -> 0 | BC41: 0 | BD41: =+ブリック!W40/1000 -> 7.505 | BE41: =+BC41-BD41 -> -7.505 | BG41: =+BC41-BF41 -> 0 | BH41: 0 | BI41: =+ルスツ羊蹄ぶた!W40/1000 -> 0 | BJ41: =+BH41-BI41 -> 0 | BL41: =+BH41-BK41 -> 0 | BM41: =+BC41+BH41 -> 0 | BN41: =+BD41+BI41 -> 7.505 | BO41: =+BM41-BN41 -> -7.505 | BP41: =+BF41+BK41 -> 0 | BQ41: =+BM41-BP41 -> 0 | BR41: 0 | BS41: =+料飲共通!W40/1000 -> 1.67 | BT41: =+BR41-BS41 -> -1.67 | BU41: 0 | BV41: =+BR41-BU41 -> 0 | BW41: =+T41+AI41+AX41+BM41+BR41 -> 0 | BX41: =+U41+AJ41+AY41+BN41+BS41 -> 9.175 | BY41: =+BW41-BX41 -> -9.175 | BZ41: =+W41+AL41+BA41+BU41 -> 0 | CA41: =+BW41-BZ41 -> 0
B42: 賃借料 | E42: 425.1 | F42: =+ﾇｰﾍﾞﾙﾌﾟｰｽ!W41/1000 -> 1225.43 | G42: =+E42-F42 -> -800.33 | H42: 509 | I42: =+E42-H42 -> -83.9 | J42: 72.7 | K42: =+ｶﾌｪﾙﾎﾟ!W41/1000 -> 68.45 | L42: =+J42-K42 -> 4.25 | M42: 49 | N42: =+J42-M42 -> 23.7 | O42: 1021.964 | P42: =+ｶﾌｪｾﾚｽﾃ!W41/1000 -> 1034.782 | Q42: =+O42-P42 -> -12.818 | R42: 1022 | S42: =+O42-R42 -> -0.036 | T42: =+E42+J42+O42 -> 1519.764 | U42: =+F42+K42+P42 -> 2328.662 | V42: =+T42-U42 -> -808.898 | W42: =+H42+M42+R42 -> 1580 | X42: =+T42-W42 -> -60.236 | AA42: =+Y42-Z42 -> 0 | AB42: 0 | AC42: =+Y42-AB42 -> 0 | AD42: 641.32 | AE42: =+ｼﾞｭｴﾙｽﾞ!W41/1000 -> 573.147 | AF42: =+AD42-AE42 -> 68.173 | AG42: 564 | AH42: =+AD42-AG42 -> 77.32 | AI42: =+Y42+AD42 -> 641.32 | AJ42: =+Z42+AE42 -> 573.147 | AK42: =+AI42-AJ42 -> 68.173 | AL42: =+AB42+AG42 -> 564 | AM42: =+AI42-AL42 -> 77.32 | AN42: 12497.46 | AO42: =+ｶﾞｰﾃﾞﾝ!W41/1000 -> 12637.057 | AP42: =+AN42-AO42 -> -139.597 | AQ42: 12235 | AR42: =+AN42-AQ42 -> 262.46 | AS42: 14123.5 | AT42: =+ﾋﾞｱｶﾞｰﾃﾞﾝ!W41/1000 -> 15862.32 | AU42: =+AS42-AT42 -> -1738.82 | AV42: 14574 | AW42: =+AS42-AV42 -> -450.5 | AX42: =+AN42+AS42 -> 26620.96 | AY42: =+AO42+AT42 -> 28499.377 | AZ42: =+AX42-AY42 -> -1878.417 | BA42: =+AQ42+AV42 -> 26809 | BB42: =+AX42-BA42 -> -188.04 | BC42: 8999.714 | BD42: =+ブリック!W41/1000 -> 8542.213 | BE42: =+BC42-BD42 -> 457.50096 | BG42: =+BC42-BF42 -> 8999.714 | BH42: 6634.7985 | BI42: =+ルスツ羊蹄ぶた!W41/1000 -> 5263.188 | BJ42: =+BH42-BI42 -> 1371.6105 | BL42: =+BH42-BK42 -> 6634.7985 | BM42: =+BC42+BH42 -> 15634.512 | BN42: =+BD42+BI42 -> 13805.401 | BO42: =+BM42-BN42 -> 1829.1115 | BP42: =+BF42+BK42 -> 0 | BQ42: =+BM42-BP42 -> 15634.512 | BR42: 0 | BS42: =+料飲共通!W41/1000 -> 0 | BT42: =+BR42-BS42 -> 0 | BU42: 13 | BV42: =+BR42-BU42 -> -13 | BW42: =+T42+AI42+AX42+BM42+BR42 -> 44416.556 | BX42: =+U42+AJ42+AY42+BN42+BS42 -> 45206.587 | BY42: =+BW42-BX42 -> -790.03051 | BZ42: =+W42+AL42+BA42+BU42 -> 28966 | CA42: =+BW42-BZ42 -> 15450.556
C43: 土地使用料 | E43: 0 | F43: =+ﾇｰﾍﾞﾙﾌﾟｰｽ!W42/1000 -> 0 | G43: =+E43-F43 -> 0 | H43: 0 | I43: =+E43-H43 -> 0 | J43: 0 | K43: =+ｶﾌｪﾙﾎﾟ!W42/1000 -> 0 | L43: =+J43-K43 -> 0 | M43: 0 | N43: =+J43-M43 -> 0 | O43: 0 | P43: =+ｶﾌｪｾﾚｽﾃ!W42/1000 -> 0 | Q43: =+O43-P43 -> 0 | R43: 0 | S43: =+O43-R43 -> 0 | T43: =+E43+J43+O43 -> 0 | U43: =+F43+K43+P43 -> 0 | V43: =+T43-U43 -> 0 | W43: =+H43+M43+R43 -> 0 | X43: =+T43-W43 -> 0 | AA43: =+Y43-Z43 -> 0 | AB43: 0 | AC43: =+Y43-AB43 -> 0 | AD43: 0 | AE43: =+ｼﾞｭｴﾙｽﾞ!W42/1000 -> 0 | AF43: =+AD43-AE43 -> 0 | AG43: 0 | AH43: =+AD43-AG43 -> 0 | AI43: =+Y43+AD43 -> 0 | AJ43: =+Z43+AE43 -> 0 | AK43: =+AI43-AJ43 -> 0 | AL43: =+AB43+AG43 -> 0 | AM43: =+AI43-AL43 -> 0 | AN43: 0 | AO43: =+ｶﾞｰﾃﾞﾝ!W42/1000 -> 0 | AP43: =+AN43-AO43 -> 0 | AQ43: 0 | AR43: =+AN43-AQ43 -> 0 | AS43: 0 | AT43: =+ﾋﾞｱｶﾞｰﾃﾞﾝ!W42/1000 -> 0 | AU43: =+AS43-AT43 -> 0 | AV43: 0 | AW43: =+AS43-AV43 -> 0 | AX43: =+AN43+AS43 -> 0 | AY43: =+AO43+AT43 -> 0 | AZ43: =+AX43-AY43 -> 0 | BA43: =+AQ43+AV43 -> 0 | BB43: =+AX43-BA43 -> 0 | BC43: 0 | BD43: =+ブリック!W42/1000 -> 0 | BE43: =+BC43-BD43 -> 0 | BG43: =+BC43-BF43 -> 0 | BH43: 0 | BI43: =+ルスツ羊蹄ぶた!W42/1000 -> 0 | BJ43: =+BH43-BI43 -> 0 | BL43: =+BH43-BK43 -> 0 | BM43: =+BC43+BH43 -> 0 | BN43: =+BD43+BI43 -> 0 | BO43: =+BM43-BN43 -> 0 | BP43: =+BF43+BK43 -> 0 | BQ43: =+BM43-BP43 -> 0 | BR43: 0 | BS43: =+料飲共通!W42/1000 -> 0 | BT43: =+BR43-BS43 -> 0 | BU43: 0 | BV43: =+BR43-BU43 -> 0 | BW43: =+T43+AI43+AX43+BM43+BR43 -> 0 | BX43: =+U43+AJ43+AY43+BN43+BS43 -> 0 | BY43: =+BW43-BX43 -> 0 | BZ43: =+W43+AL43+BA43+BU43 -> 0 | CA43: =+BW43-BZ43 -> 0
C44: 建物使用料 | E44: 0 | F44: =+ﾇｰﾍﾞﾙﾌﾟｰｽ!W43/1000 -> 0 | G44: =+E44-F44 -> 0 | H44: 0 | I44: =+E44-H44 -> 0 | J44: 0 | K44: =+ｶﾌｪﾙﾎﾟ!W43/1000 -> 0 | L44: =+J44-K44 -> 0 | M44: 0 | N44: =+J44-M44 -> 0 | O44: 1021.964 | P44: =+ｶﾌｪｾﾚｽﾃ!W43/1000 -> 1034.782 | Q44: =+O44-P44 -> -12.818 | R44: 1022 | S44: =+O44-R44 -> -0.036 | T44: =+E44+J44+O44 -> 1021.964 | U44: =+F44+K44+P44 -> 1034.782 | V44: =+T44-U44 -> -12.818 | W44: =+H44+M44+R44 -> 1022 | X44: =+T44-W44 -> -0.036 | AA44: =+Y44-Z44 -> 0 | AB44: 0 | AC44: =+Y44-AB44 -> 0 | AD44: 0 | AE44: =+ｼﾞｭｴﾙｽﾞ!W43/1000 -> 0 | AF44: =+AD44-AE44 -> 0 | AG44: 0 | AH44: =+AD44-AG44 -> 0 | AI44: =+Y44+AD44 -> 0 | AJ44: =+Z44+AE44 -> 0 | AK44: =+AI44-AJ44 -> 0 | AL44: =+AB44+AG44 -> 0 | AM44: =+AI44-AL44 -> 0 | AN44: 11558.46 | AO44: =+ｶﾞｰﾃﾞﾝ!W43/1000 -> 11558.461 | AP44: =+AN44-AO44 -> -0.001 | AQ44: 11558 | AR44: =+AN44-AQ44 -> 0.46 | AS44: 0 | AT44: =+ﾋﾞｱｶﾞｰﾃﾞﾝ!W43/1000 -> 0 | AU44: =+AS44-AT44 -> 0 | AV44: 0 | AW44: =+AS44-AV44 -> 0 | AX44: =+AN44+AS44 -> 11558.46 | AY44: =+AO44+AT44 -> 11558.461 | AZ44: =+AX44-AY44 -> -0.001 | BA44: =+AQ44+AV44 -> 11558 | BB44: =+AX44-BA44 -> 0.46 | BC44: 7913.3943 | BD44: =+ブリック!W43/1000 -> 8182.699 | BE44: =+BC44-BD44 -> -269.3047 | BG44: =+BC44-BF44 -> 7913.3943 | BH44: 6539.312 | BI44: =+ルスツ羊蹄ぶた!W43/1000 -> 5263.188 | BJ44: =+BH44-BI44 -> 1276.124 | BL44: =+BH44-BK44 -> 6539.312 | BM44: =+BC44+BH44 -> 14452.706 | BN44: =+BD44+BI44 -> 13445.887 | BO44: =+BM44-BN44 -> 1006.8193 | BP44: =+BF44+BK44 -> 0 | BQ44: =+BM44-BP44 -> 14452.706 | BR44: 0 | BS44: =+料飲共通!W43/1000 -> 0 | BT44: =+BR44-BS44 -> 0 | BU44: 0 | BV44: =+BR44-BU44 -> 0 | BW44: =+T44+AI44+AX44+BM44+BR44 -> 27033.13 | BX44: =+U44+AJ44+AY44+BN44+BS44 -> 26039.13 | BY44: =+BW44-BX44 -> 994.0003 | BZ44: =+W44+AL44+BA44+BU44 -> 12580 | CA44: =+BW44-BZ44 -> 14453.13
C45: 施設使用料 | E45: 0 | F45: =+ﾇｰﾍﾞﾙﾌﾟｰｽ!W44/1000 -> 0 | G45: =+E45-F45 -> 0 | H45: 0 | I45: =+E45-H45 -> 0 | J45: 0 | K45: =+ｶﾌｪﾙﾎﾟ!W44/1000 -> 0 | L45: =+J45-K45 -> 0 | M45: 0 | N45: =+J45-M45 -> 0 | O45: 0 | P45: =+ｶﾌｪｾﾚｽﾃ!W44/1000 -> 0 | Q45: =+O45-P45 -> 0 | R45: 0 | S45: =+O45-R45 -> 0 | T45: =+E45+J45+O45 -> 0 | U45: =+F45+K45+P45 -> 0 | V45: =+T45-U45 -> 0 | W45: =+H45+M45+R45 -> 0 | X45: =+T45-W45 -> 0 | AA45: =+Y45-Z45 -> 0 | AB45: 0 | AC45: =+Y45-AB45 -> 0 | AD45: 0 | AE45: =+ｼﾞｭｴﾙｽﾞ!W44/1000 -> 0 | AF45: =+AD45-AE45 -> 0 | AG45: 0 | AH45: =+AD45-AG45 -> 0 | AI45: =+Y45+AD45 -> 0 | AJ45: =+Z45+AE45 -> 0 | AK45: =+AI45-AJ45 -> 0 | AL45: =+AB45+AG45 -> 0 | AM45: =+AI45-AL45 -> 0 | AN45: 0 | AO45: =+ｶﾞｰﾃﾞﾝ!W44/1000 -> 0 | AP45: =+AN45-AO45 -> 0 | AQ45: 0 | AR45: =+AN45-AQ45 -> 0 | AS45: 14050 | AT45: =+ﾋﾞｱｶﾞｰﾃﾞﾝ!W44/1000 -> 15659.091 | AU45: =+AS45-AT45 -> -1609.091 | AV45: 14500 | AW45: =+AS45-AV45 -> -450 | AX45: =+AN45+AS45 -> 14050 | AY45: =+AO45+AT45 -> 15659.091 | AZ45: =+AX45-AY45 -> -1609.091 | BA45: =+AQ45+AV45 -> 14500 | BB45: =+AX45-BA45 -> -450 | BC45: 701.508 | BD45: =+ブリック!W44/1000 -> 0 | BE45: =+BC45-BD45 -> 701.508 | BG45: =+BC45-BF45 -> 701.508 | BH45: 0 | BI45: =+ルスツ羊蹄ぶた!W44/1000 -> 0 | BJ45: =+BH45-BI45 -> 0 | BL45: =+BH45-BK45 -> 0 | BM45: =+BC45+BH45 -> 701.508 | BN45: =+BD45+BI45 -> 0 | BO45: =+BM45-BN45 -> 701.508 | BP45: =+BF45+BK45 -> 0 | BQ45: =+BM45-BP45 -> 701.508 | BR45: 0 | BS45: =+料飲共通!W44/1000 -> 0 | BT45: =+BR45-BS45 -> 0 | BU45: 13 | BV45: =+BR45-BU45 -> -13 | BW45: =+T45+AI45+AX45+BM45+BR45 -> 14751.508 | BX45: =+U45+AJ45+AY45+BN45+BS45 -> 15659.091 | BY45: =+BW45-BX45 -> -907.583 | BZ45: =+W45+AL45+BA45+BU45 -> 14513 | CA45: =+BW45-BZ45 -> 238.508
C46: リース料 | E46: 425.1 | F46: =+ﾇｰﾍﾞﾙﾌﾟｰｽ!W45/1000 -> 1225.43 | G46: =+E46-F46 -> -800.33 | H46: 509 | I46: =+E46-H46 -> -83.9 | J46: 72.7 | K46: =+ｶﾌｪﾙﾎﾟ!W45/1000 -> 68.45 | L46: =+J46-K46 -> 4.25 | M46: 49 | N46: =+J46-M46 -> 23.7 | O46: 0 | P46: =+ｶﾌｪｾﾚｽﾃ!W45/1000 -> 0 | Q46: =+O46-P46 -> 0 | R46: 0 | S46: =+O46-R46 -> 0 | T46: =+E46+J46+O46 -> 497.8 | U46: =+F46+K46+P46 -> 1293.88 | V46: =+T46-U46 -> -796.08 | W46: =+H46+M46+R46 -> 558 | X46: =+T46-W46 -> -60.2 | AA46: =+Y46-Z46 -> 0 | AB46: 0 | AC46: =+Y46-AB46 -> 0 | AD46: 641.32 | AE46: =+ｼﾞｭｴﾙｽﾞ!W45/1000 -> 573.147 | AF46: =+AD46-AE46 -> 68.173 | AG46: 564 | AH46: =+AD46-AG46 -> 77.32 | AI46: =+Y46+AD46 -> 641.32 | AJ46: =+Z46+AE46 -> 573.147 | AK46: =+AI46-AJ46 -> 68.173 | AL46: =+AB46+AG46 -> 564 | AM46: =+AI46-AL46 -> 77.32 | AN46: 939 | AO46: =+ｶﾞｰﾃﾞﾝ!W45/1000 -> 1078.596 | AP46: =+AN46-AO46 -> -139.596 | AQ46: 677 | AR46: =+AN46-AQ46 -> 262 | AS46: 73.5 | AT46: =+ﾋﾞｱｶﾞｰﾃﾞﾝ!W45/1000 -> 203.229 | AU46: =+AS46-AT46 -> -129.729 | AV46: 74 | AW46: =+AS46-AV46 -> -0.5 | AX46: =+AN46+AS46 -> 1012.5 | AY46: =+AO46+AT46 -> 1281.825 | AZ46: =+AX46-AY46 -> -269.325 | BA46: =+AQ46+AV46 -> 751 | BB46: =+AX46-BA46 -> 261.5 | BC46: 384.81166 | BD46: =+ブリック!W45/1000 -> 359.514 | BE46: =+BC46-BD46 -> 25.297662 | BG46: =+BC46-BF46 -> 384.81166 | BH46: 95.48653 | BI46: =+ルスツ羊蹄ぶた!W45/1000 -> 0 | BJ46: =+BH46-BI46 -> 95.48653 | BL46: =+BH46-BK46 -> 95.48653 | BM46: =+BC46+BH46 -> 480.29819 | BN46: =+BD46+BI46 -> 359.514 | BO46: =+BM46-BN46 -> 120.78419 | BP46: =+BF46+BK46 -> 0 | BQ46: =+BM46-BP46 -> 480.29819 | BR46: 0 | BS46: =+料飲共通!W45/1000 -> 0 | BT46: =+BR46-BS46 -> 0 | BU46: 0 | BV46: =+BR46-BU46 -> 0 | BW46: =+T46+AI46+AX46+BM46+BR46 -> 2631.9182 | BX46: =+U46+AJ46+AY46+BN46+BS46 -> 3508.366 | BY46: =+BW46-BX46 -> -876.44781 | BZ46: =+W46+AL46+BA46+BU46 -> 1873 | CA46: =+BW46-BZ46 -> 758.91819
B47: 保険料 | E47: 38.21 | F47: =+ﾇｰﾍﾞﾙﾌﾟｰｽ!W46/1000 -> 2.947 | G47: =+E47-F47 -> 35.263 | H47: 72 | I47: =+E47-H47 -> -33.79 | J47: 4.21 | K47: =+ｶﾌｪﾙﾎﾟ!W46/1000 -> 2.947 | L47: =+J47-K47 -> 1.263 | M47: 10 | N47: =+J47-M47 -> -5.79 | O47: 4.21 | P47: =+ｶﾌｪｾﾚｽﾃ!W46/1000 -> 2.947 | Q47: =+O47-P47 -> 1.263 | R47: 17 | S47: =+O47-R47 -> -12.79 | T47: =+E47+J47+O47 -> 46.63 | U47: =+F47+K47+P47 -> 8.841 | V47: =+T47-U47 -> 37.789 | W47: =+H47+M47+R47 -> 99 | X47: =+T47-W47 -> -52.37 | AA47: =+Y47-Z47 -> 0 | AB47: 20 | AC47: =+Y47-AB47 -> -20 | AD47: 7.718 | AE47: =+ｼﾞｭｴﾙｽﾞ!W46/1000 -> 22.267 | AF47: =+AD47-AE47 -> -14.549 | AG47: 117 | AH47: =+AD47-AG47 -> -109.282 | AI47: =+Y47+AD47 -> 7.718 | AJ47: =+Z47+AE47 -> 22.267 | AK47: =+AI47-AJ47 -> -14.549 | AL47: =+AB47+AG47 -> 137 | AM47: =+AI47-AL47 -> -129.282 | AN47: 4.21 | AO47: =+ｶﾞｰﾃﾞﾝ!W46/1000 -> 2.947 | AP47: =+AN47-AO47 -> 1.263 | AQ47: 134 | AR47: =+AN47-AQ47 -> -129.79 | AS47: 0 | AT47: =+ﾋﾞｱｶﾞｰﾃﾞﾝ!W46/1000 -> 2.947 | AU47: =+AS47-AT47 -> -2.947 | AV47: 99 | AW47: =+AS47-AV47 -> -99 | AX47: =+AN47+AS47 -> 4.21 | AY47: =+AO47+AT47 -> 5.894 | AZ47: =+AX47-AY47 -> -1.684 | BA47: =+AQ47+AV47 -> 233 | BB47: =+AX47-BA47 -> -228.79 | BC47: 16.712 | BD47: =+ブリック!W46/1000 -> 2.947 | BE47: =+BC47-BD47 -> 13.765 | BG47: =+BC47-BF47 -> 16.712 | BH47: 16.712 | BI47: =+ルスツ羊蹄ぶた!W46/1000 -> 7.504 | BJ47: =+BH47-BI47 -> 9.208 | BL47: =+BH47-BK47 -> 16.712 | BM47: =+BC47+BH47 -> 33.424 | BN47: =+BD47+BI47 -> 10.451 | BO47: =+BM47-BN47 -> 22.973 | BP47: =+BF47+BK47 -> 0 | BQ47: =+BM47-BP47 -> 33.424 | BR47: 0 | BS47: =+料飲共通!W46/1000 -> 0 | BT47: =+BR47-BS47 -> 0 | BU47: 0 | BV47: =+BR47-BU47 -> 0 | BW47: =+T47+AI47+AX47+BM47+BR47 -> 91.982 | BX47: =+U47+AJ47+AY47+BN47+BS47 -> 47.453 | BY47: =+BW47-BX47 -> 44.529 | BZ47: =+W47+AL47+BA47+BU47 -> 469 | CA47: =+BW47-BZ47 -> -377.018
C48: 火災保険料 | E48: 0 | F48: =+ﾇｰﾍﾞﾙﾌﾟｰｽ!W47/1000 -> 0 | G48: =+E48-F48 -> 0 | H48: 0 | I48: =+E48-H48 -> 0 | J48: 0 | K48: =+ｶﾌｪﾙﾎﾟ!W47/1000 -> 0 | L48: =+J48-K48 -> 0 | M48: 0 | N48: =+J48-M48 -> 0 | O48: 0 | P48: =+ｶﾌｪｾﾚｽﾃ!W47/1000 -> 0 | Q48: =+O48-P48 -> 0 | R48: 0 | S48: =+O48-R48 -> 0 | T48: =+E48+J48+O48 -> 0 | U48: =+F48+K48+P48 -> 0 | V48: =+T48-U48 -> 0 | W48: =+H48+M48+R48 -> 0 | X48: =+T48-W48 -> 0 | AA48: =+Y48-Z48 -> 0 | AB48: 0 | AC48: =+Y48-AB48 -> 0 | AD48: 3.508 | AE48: =+ｼﾞｭｴﾙｽﾞ!W47/1000 -> 0 | AF48: =+AD48-AE48 -> 3.508 | AG48: 4 | AH48: =+AD48-AG48 -> -0.492 | AI48: =+Y48+AD48 -> 3.508 | AJ48: =+Z48+AE48 -> 0 | AK48: =+AI48-AJ48 -> 3.508 | AL48: =+AB48+AG48 -> 4 | AM48: =+AI48-AL48 -> -0.492 | AN48: 0 | AO48: =+ｶﾞｰﾃﾞﾝ!W47/1000 -> 0 | AP48: =+AN48-AO48 -> 0 | AQ48: 38 | AR48: =+AN48-AQ48 -> -38 | AS48: 0 | AT48: =+ﾋﾞｱｶﾞｰﾃﾞﾝ!W47/1000 -> 0 | AU48: =+AS48-AT48 -> 0 | AV48: 0 | AW48: =+AS48-AV48 -> 0 | AX48: =+AN48+AS48 -> 0 | AY48: =+AO48+AT48 -> 0 | AZ48: =+AX48-AY48 -> 0 | BA48: =+AQ48+AV48 -> 38 | BB48: =+AX48-BA48 -> -38 | BC48: 0 | BD48: =+ブリック!W47/1000 -> 0 | BE48: =+BC48-BD48 -> 0 | BG48: =+BC48-BF48 -> 0 | BH48: 0 | BI48: =+ルスツ羊蹄ぶた!W47/1000 -> 0 | BJ48: =+BH48-BI48 -> 0 | BL48: =+BH48-BK48 -> 0 | BM48: =+BC48+BH48 -> 0 | BN48: =+BD48+BI48 -> 0 | BO48: =+BM48-BN48 -> 0 | BP48: =+BF48+BK48 -> 0 | BQ48: =+BM48-BP48 -> 0 | BR48: 0 | BS48: =+料飲共通!W47/1000 -> 0 | BT48: =+BR48-BS48 -> 0 | BU48: 0 | BV48: =+BR48-BU48 -> 0 | BW48: =+T48+AI48+AX48+BM48+BR48 -> 3.508 | BX48: =+U48+AJ48+AY48+BN48+BS48 -> 0 | BY48: =+BW48-BX48 -> 3.508 | BZ48: =+W48+AL48+BA48+BU48 -> 42 | CA48: =+BW48-BZ48 -> -38.492
C49: 賠償保険料 | E49: 34 | F49: =+ﾇｰﾍﾞﾙﾌﾟｰｽ!W48/1000 -> 0 | G49: =+E49-F49 -> 34 | H49: 68 | I49: =+E49-H49 -> -34 | J49: 4.21 | K49: =+ｶﾌｪﾙﾎﾟ!W48/1000 -> 0 | L49: =+J49-K49 -> 4.21 | M49: 6 | N49: =+J49-M49 -> -1.79 | O49: 0 | P49: =+ｶﾌｪｾﾚｽﾃ!W48/1000 -> 0 | Q49: =+O49-P49 -> 0 | R49: 13 | S49: =+O49-R49 -> -13 | T49: =+E49+J49+O49 -> 38.21 | U49: =+F49+K49+P49 -> 0 | V49: =+T49-U49 -> 38.21 | W49: =+H49+M49+R49 -> 87 | X49: =+T49-W49 -> -48.79 | AA49: =+Y49-Z49 -> 0 | AB49: 16 | AC49: =+Y49-AB49 -> -16 | AD49: 0 | AE49: =+ｼﾞｭｴﾙｽﾞ!W48/1000 -> 19.32 | AF49: =+AD49-AE49 -> -19.32 | AG49: 110 | AH49: =+AD49-AG49 -> -110 | AI49: =+Y49+AD49 -> 0 | AJ49: =+Z49+AE49 -> 19.32 | AK49: =+AI49-AJ49 -> -19.32 | AL49: =+AB49+AG49 -> 126 | AM49: =+AI49-AL49 -> -126 | AN49: 0 | AO49: =+ｶﾞｰﾃﾞﾝ!W48/1000 -> 0 | AP49: =+AN49-AO49 -> 0 | AQ49: 93 | AR49: =+AN49-AQ49 -> -93 | AS49: 0 | AT49: =+ﾋﾞｱｶﾞｰﾃﾞﾝ!W48/1000 -> 0 | AU49: =+AS49-AT49 -> 0 | AV49: 94 | AW49: =+AS49-AV49 -> -94 | AX49: =+AN49+AS49 -> 0 | AY49: =+AO49+AT49 -> 0 | AZ49: =+AX49-AY49 -> 0 | BA49: =+AQ49+AV49 -> 187 | BB49: =+AX49-BA49 -> -187 | BC49: 0 | BD49: =+ブリック!W48/1000 -> 0 | BE49: =+BC49-BD49 -> 0 | BG49: =+BC49-BF49 -> 0 | BH49: 0 | BI49: =+ルスツ羊蹄ぶた!W48/1000 -> 0 | BJ49: =+BH49-BI49 -> 0 | BL49: =+BH49-BK49 -> 0 | BM49: =+BC49+BH49 -> 0 | BN49: =+BD49+BI49 -> 0 | BO49: =+BM49-BN49 -> 0 | BP49: =+BF49+BK49 -> 0 | BQ49: =+BM49-BP49 -> 0 | BR49: 0 | BS49: =+料飲共通!W48/1000 -> 0 | BT49: =+BR49-BS49 -> 0 | BU49: 0 | BV49: =+BR49-BU49 -> 0 | BW49: =+T49+AI49+AX49+BM49+BR49 -> 38.21 | BX49: =+U49+AJ49+AY49+BN49+BS49 -> 19.32 | BY49: =+BW49-BX49 -> 18.89 | BZ49: =+W49+AL49+BA49+BU49 -> 400 | CA49: =+BW49-BZ49 -> -361.79
C50: 動産保険料 | E50: 4.21 | F50: =+ﾇｰﾍﾞﾙﾌﾟｰｽ!W49/1000 -> 2.947 | G50: =+E50-F50 -> 1.263 | H50: 4 | I50: =+E50-H50 -> 0.21 | J50: 0 | K50: =+ｶﾌｪﾙﾎﾟ!W49/1000 -> 2.947 | L50: =+J50-K50 -> -2.947 | M50: 4 | N50: =+J50-M50 -> -4 | O50: 4.21 | P50: =+ｶﾌｪｾﾚｽﾃ!W49/1000 -> 2.947 | Q50: =+O50-P50 -> 1.263 | R50: 4 | S50: =+O50-R50 -> 0.21 | T50: =+E50+J50+O50 -> 8.42 | U50: =+F50+K50+P50 -> 8.841 | V50: =+T50-U50 -> -0.421 | W50: =+H50+M50+R50 -> 12 | X50: =+T50-W50 -> -3.58 | AA50: =+Y50-Z50 -> 0 | AB50: 4 | AC50: =+Y50-AB50 -> -4 | AD50: 4.21 | AE50: =+ｼﾞｭｴﾙｽﾞ!W49/1000 -> 2.947 | AF50: =+AD50-AE50 -> 1.263 | AG50: 4 | AH50: =+AD50-AG50 -> 0.21 | AI50: =+Y50+AD50 -> 4.21 | AJ50: =+Z50+AE50 -> 2.947 | AK50: =+AI50-AJ50 -> 1.263 | AL50: =+AB50+AG50 -> 8 | AM50: =+AI50-AL50 -> -3.79 | AN50: 4.21 | AO50: =+ｶﾞｰﾃﾞﾝ!W49/1000 -> 2.947 | AP50: =+AN50-AO50 -> 1.263 | AQ50: 4 | AR50: =+AN50-AQ50 -> 0.21 | AS50: 0 | AT50: =+ﾋﾞｱｶﾞｰﾃﾞﾝ!W49/1000 -> 2.947 | AU50: =+AS50-AT50 -> -2.947 | AV50: 4 | AW50: =+AS50-AV50 -> -4 | AX50: =+AN50+AS50 -> 4.21 | AY50: =+AO50+AT50 -> 5.894 | AZ50: =+AX50-AY50 -> -1.684 | BA50: =+AQ50+AV50 -> 8 | BB50: =+AX50-BA50 -> -3.79 | BC50: 0 | BD50: =+ブリック!W49/1000 -> 2.947 | BE50: =+BC50-BD50 -> -2.947 | BG50: =+BC50-BF50 -> 0 | BH50: 0 | BI50: =+ルスツ羊蹄ぶた!W49/1000 -> 7.504 | BJ50: =+BH50-BI50 -> -7.504 | BL50: =+BH50-BK50 -> 0 | BM50: =+BC50+BH50 -> 0 | BN50: =+BD50+BI50 -> 10.451 | BO50: =+BM50-BN50 -> -10.451 | BP50: =+BF50+BK50 -> 0 | BQ50: =+BM50-BP50 -> 0 | BR50: 0 | BS50: =+料飲共通!W49/1000 -> 0 | BT50: =+BR50-BS50 -> 0 | BU50: 0 | BV50: =+BR50-BU50 -> 0 | BW50: =+T50+AI50+AX50+BM50+BR50 -> 16.84 | BX50: =+U50+AJ50+AY50+BN50+BS50 -> 28.133 | BY50: =+BW50-BX50 -> -11.293 | BZ50: =+W50+AL50+BA50+BU50 -> 28 | CA50: =+BW50-BZ50 -> -11.16
B51: 修繕費 | E51: 0 | F51: =+ﾇｰﾍﾞﾙﾌﾟｰｽ!W50/1000 -> 79.9 | G51: =+E51-F51 -> -79.9 | H51: 0 | I51: =+E51-H51 -> 0 | J51: 0 | K51: =+ｶﾌｪﾙﾎﾟ!W50/1000 -> 0 | L51: =+J51-K51 -> 0 | M51: 0 | N51: =+J51-M51 -> 0 | O51: 0 | P51: =+ｶﾌｪｾﾚｽﾃ!W50/1000 -> 0 | Q51: =+O51-P51 -> 0 | R51: 0 | S51: =+O51-R51 -> 0 | T51: =+E51+J51+O51 -> 0 | U51: =+F51+K51+P51 -> 79.9 | V51: =+T51-U51 -> -79.9 | W51: =+H51+M51+R51 -> 0 | X51: =+T51-W51 -> 0 | AA51: =+Y51-Z51 -> 0 | AB51: 0 | AC51: =+Y51-AB51 -> 0 | AD51: 0 | AE51: =+ｼﾞｭｴﾙｽﾞ!W50/1000 -> 50.33 | AF51: =+AD51-AE51 -> -50.33 | AG51: 452 | AH51: =+AD51-AG51 -> -452 | AI51: =+Y51+AD51 -> 0 | AJ51: =+Z51+AE51 -> 50.33 | AK51: =+AI51-AJ51 -> -50.33 | AL51: =+AB51+AG51 -> 452 | AM51: =+AI51-AL51 -> -452 | AN51: 0 | AO51: =+ｶﾞｰﾃﾞﾝ!W50/1000 -> 157.7 | AP51: =+AN51-AO51 -> -157.7 | AQ51: 437 | AR51: =+AN51-AQ51 -> -437 | AS51: 150 | AT51: =+ﾋﾞｱｶﾞｰﾃﾞﾝ!W50/1000 -> 0 | AU51: =+AS51-AT51 -> 150 | AV51: 28 | AW51: =+AS51-AV51 -> 122 | AX51: =+AN51+AS51 -> 150 | AY51: =+AO51+AT51 -> 157.7 | AZ51: =+AX51-AY51 -> -7.7 | BA51: =+AQ51+AV51 -> 465 | BB51: =+AX51-BA51 -> -315 | BC51: 0 | BD51: =+ブリック!W50/1000 -> 240 | BE51: =+BC51-BD51 -> -240 | BG51: =+BC51-BF51 -> 0 | BH51: 0 | BI51: =+ルスツ羊蹄ぶた!W50/1000 -> 460 | BJ51: =+BH51-BI51 -> -460 | BL51: =+BH51-BK51 -> 0 | BM51: =+BC51+BH51 -> 0 | BN51: =+BD51+BI51 -> 700 | BO51: =+BM51-BN51 -> -700 | BP51: =+BF51+BK51 -> 0 | BQ51: =+BM51-BP51 -> 0 | BR51: 0 | BS51: =+料飲共通!W50/1000 -> 0 | BT51: =+BR51-BS51 -> 0 | BU51: 0 | BV51: =+BR51-BU51 -> 0 | BW51: =+T51+AI51+AX51+BM51+BR51 -> 150 | BX51: =+U51+AJ51+AY51+BN51+BS51 -> 987.93 | BY51: =+BW51-BX51 -> -837.93 | BZ51: =+W51+AL51+BA51+BU51 -> 917 | CA51: =+BW51-BZ51 -> -767
C52: 建物 | E52: 0 | F52: =+ﾇｰﾍﾞﾙﾌﾟｰｽ!W51/1000 -> 0 | G52: =+E52-F52 -> 0 | H52: 0 | I52: =+E52-H52 -> 0 | J52: 0 | K52: =+ｶﾌｪﾙﾎﾟ!W51/1000 -> 0 | L52: =+J52-K52 -> 0 | M52: 0 | N52: =+J52-M52 -> 0 | O52: 0 | P52: =+ｶﾌｪｾﾚｽﾃ!W51/1000 -> 0 | Q52: =+O52-P52 -> 0 | R52: 0 | S52: =+O52-R52 -> 0 | T52: =+E52+J52+O52 -> 0 | U52: =+F52+K52+P52 -> 0 | V52: =+T52-U52 -> 0 | W52: =+H52+M52+R52 -> 0 | X52: =+T52-W52 -> 0 | AA52: =+Y52-Z52 -> 0 | AB52: 0 | AC52: =+Y52-AB52 -> 0 | AD52: 0 | AE52: =+ｼﾞｭｴﾙｽﾞ!W51/1000 -> 0 | AF52: =+AD52-AE52 -> 0 | AG52: 0 | AH52: =+AD52-AG52 -> 0 | AI52: =+Y52+AD52 -> 0 | AJ52: =+Z52+AE52 -> 0 | AK52: =+AI52-AJ52 -> 0 | AL52: =+AB52+AG52 -> 0 | AM52: =+AI52-AL52 -> 0 | AN52: 0 | AO52: =+ｶﾞｰﾃﾞﾝ!W51/1000 -> 0 | AP52: =+AN52-AO52 -> 0 | AQ52: 0 | AR52: =+AN52-AQ52 -> 0 | AS52: 0 | AT52: =+ﾋﾞｱｶﾞｰﾃﾞﾝ!W51/1000 -> 0 | AU52: =+AS52-AT52 -> 0 | AV52: 0 | AW52: =+AS52-AV52 -> 0 | AX52: =+AN52+AS52 -> 0 | AY52: =+AO52+AT52 -> 0 | AZ52: =+AX52-AY52 -> 0 | BA52: =+AQ52+AV52 -> 0 | BB52: =+AX52-BA52 -> 0 | BC52: 0 | BD52: =+ブリック!W51/1000 -> 0 | BE52: =+BC52-BD52 -> 0 | BG52: =+BC52-BF52 -> 0 | BH52: 0 | BI52: =+ルスツ羊蹄ぶた!W51/1000 -> 0 | BJ52: =+BH52-BI52 -> 0 | BL52: =+BH52-BK52 -> 0 | BM52: =+BC52+BH52 -> 0 | BN52: =+BD52+BI52 -> 0 | BO52: =+BM52-BN52 -> 0 | BP52: =+BF52+BK52 -> 0 | BQ52: =+BM52-BP52 -> 0 | BR52: 0 | BS52: =+料飲共通!W51/1000 -> 0 | BT52: =+BR52-BS52 -> 0 | BU52: 0 | BV52: =+BR52-BU52 -> 0 | BW52: =+T52+AI52+AX52+BM52+BR52 -> 0 | BX52: =+U52+AJ52+AY52+BN52+BS52 -> 0 | BY52: =+BW52-BX52 -> 0 | BZ52: =+W52+AL52+BA52+BU52 -> 0 | CA52: =+BW52-BZ52 -> 0
C53: 建物付属設備 | E53: 0 | F53: =+ﾇｰﾍﾞﾙﾌﾟｰｽ!W52/1000 -> 0 | G53: =+E53-F53 -> 0 | H53: 0 | I53: =+E53-H53 -> 0 | J53: 0 | K53: =+ｶﾌｪﾙﾎﾟ!W52/1000 -> 0 | L53: =+J53-K53 -> 0 | M53: 0 | N53: =+J53-M53 -> 0 | O53: 0 | P53: =+ｶﾌｪｾﾚｽﾃ!W52/1000 -> 0 | Q53: =+O53-P53 -> 0 | R53: 0 | S53: =+O53-R53 -> 0 | T53: =+E53+J53+O53 -> 0 | U53: =+F53+K53+P53 -> 0 | V53: =+T53-U53 -> 0 | W53: =+H53+M53+R53 -> 0 | X53: =+T53-W53 -> 0 | AA53: =+Y53-Z53 -> 0 | AB53: 0 | AC53: =+Y53-AB53 -> 0 | AD53: 0 | AE53: =+ｼﾞｭｴﾙｽﾞ!W52/1000 -> 19.9 | AF53: =+AD53-AE53 -> -19.9 | AG53: 0 | AH53: =+AD53-AG53 -> 0 | AI53: =+Y53+AD53 -> 0 | AJ53: =+Z53+AE53 -> 19.9 | AK53: =+AI53-AJ53 -> -19.9 | AL53: =+AB53+AG53 -> 0 | AM53: =+AI53-AL53 -> 0 | AN53: 0 | AO53: =+ｶﾞｰﾃﾞﾝ!W52/1000 -> 40 | AP53: =+AN53-AO53 -> -40 | AQ53: 139 | AR53: =+AN53-AQ53 -> -139 | AS53: 0 | AT53: =+ﾋﾞｱｶﾞｰﾃﾞﾝ!W52/1000 -> 0 | AU53: =+AS53-AT53 -> 0 | AV53: 28 | AW53: =+AS53-AV53 -> -28 | AX53: =+AN53+AS53 -> 0 | AY53: =+AO53+AT53 -> 40 | AZ53: =+AX53-AY53 -> -40 | BA53: =+AQ53+AV53 -> 167 | BB53: =+AX53-BA53 -> -167 | BC53: 0 | BD53: =+ブリック!W52/1000 -> 240 | BE53: =+BC53-BD53 -> -240 | BG53: =+BC53-BF53 -> 0 | BH53: 0 | BI53: =+ルスツ羊蹄ぶた!W52/1000 -> 460 | BJ53: =+BH53-BI53 -> -460 | BL53: =+BH53-BK53 -> 0 | BM53: =+BC53+BH53 -> 0 | BN53: =+BD53+BI53 -> 700 | BO53: =+BM53-BN53 -> -700 | BP53: =+BF53+BK53 -> 0 | BQ53: =+BM53-BP53 -> 0 | BR53: 0 | BS53: =+料飲共通!W52/1000 -> 0 | BT53: =+BR53-BS53 -> 0 | BU53: 0 | BV53: =+BR53-BU53 -> 0 | BW53: =+T53+AI53+AX53+BM53+BR53 -> 0 | BX53: =+U53+AJ53+AY53+BN53+BS53 -> 759.9 | BY53: =+BW53-BX53 -> -759.9 | BZ53: =+W53+AL53+BA53+BU53 -> 167 | CA53: =+BW53-BZ53 -> -167
C54: 構築物 | E54: 0 | F54: =+ﾇｰﾍﾞﾙﾌﾟｰｽ!W53/1000 -> 0 | G54: =+E54-F54 -> 0 | H54: 0 | I54: =+E54-H54 -> 0 | J54: 0 | K54: =+ｶﾌｪﾙﾎﾟ!W53/1000 -> 0 | L54: =+J54-K54 -> 0 | M54: 0 | N54: =+J54-M54 -> 0 | O54: 0 | P54: =+ｶﾌｪｾﾚｽﾃ!W53/1000 -> 0 | Q54: =+O54-P54 -> 0 | R54: 0 | S54: =+O54-R54 -> 0 | T54: =+E54+J54+O54 -> 0 | U54: =+F54+K54+P54 -> 0 | V54: =+T54-U54 -> 0 | W54: =+H54+M54+R54 -> 0 | X54: =+T54-W54 -> 0 | AA54: =+Y54-Z54 -> 0 | AB54: 0 | AC54: =+Y54-AB54 -> 0 | AD54: 0 | AE54: =+ｼﾞｭｴﾙｽﾞ!W53/1000 -> 0 | AF54: =+AD54-AE54 -> 0 | AG54: 0 | AH54: =+AD54-AG54 -> 0 | AI54: =+Y54+AD54 -> 0 | AJ54: =+Z54+AE54 -> 0 | AK54: =+AI54-AJ54 -> 0 | AL54: =+AB54+AG54 -> 0 | AM54: =+AI54-AL54 -> 0 | AN54: 0 | AO54: =+ｶﾞｰﾃﾞﾝ!W53/1000 -> 0 | AP54: =+AN54-AO54 -> 0 | AQ54: 0 | AR54: =+AN54-AQ54 -> 0 | AS54: 0 | AT54: =+ﾋﾞｱｶﾞｰﾃﾞﾝ!W53/1000 -> 0 | AU54: =+AS54-AT54 -> 0 | AV54: 0 | AW54: =+AS54-AV54 -> 0 | AX54: =+AN54+AS54 -> 0 | AY54: =+AO54+AT54 -> 0 | AZ54: =+AX54-AY54 -> 0 | BA54: =+AQ54+AV54 -> 0 | BB54: =+AX54-BA54 -> 0 | BC54: 0 | BD54: =+ブリック!W53/1000 -> 0 | BE54: =+BC54-BD54 -> 0 | BG54: =+BC54-BF54 -> 0 | BH54: 0 | BI54: =+ルスツ羊蹄ぶた!W53/1000 -> 0 | BJ54: =+BH54-BI54 -> 0 | BL54: =+BH54-BK54 -> 0 | BM54: =+BC54+BH54 -> 0 | BN54: =+BD54+BI54 -> 0 | BO54: =+BM54-BN54 -> 0 | BP54: =+BF54+BK54 -> 0 | BQ54: =+BM54-BP54 -> 0 | BR54: 0 | BS54: =+料飲共通!W53/1000 -> 0 | BT54: =+BR54-BS54 -> 0 | BU54: 0 | BV54: =+BR54-BU54 -> 0 | BW54: =+T54+AI54+AX54+BM54+BR54 -> 0 | BX54: =+U54+AJ54+AY54+BN54+BS54 -> 0 | BY54: =+BW54-BX54 -> 0 | BZ54: =+W54+AL54+BA54+BU54 -> 0 | CA54: =+BW54-BZ54 -> 0
C55: 機械 | E55: 0 | F55: =+ﾇｰﾍﾞﾙﾌﾟｰｽ!W54/1000 -> 0 | G55: =+E55-F55 -> 0 | H55: 0 | I55: =+E55-H55 -> 0 | J55: 0 | K55: =+ｶﾌｪﾙﾎﾟ!W54/1000 -> 0 | L55: =+J55-K55 -> 0 | M55: 0 | N55: =+J55-M55 -> 0 | O55: 0 | P55: =+ｶﾌｪｾﾚｽﾃ!W54/1000 -> 0 | Q55: =+O55-P55 -> 0 | R55: 0 | S55: =+O55-R55 -> 0 | T55: =+E55+J55+O55 -> 0 | U55: =+F55+K55+P55 -> 0 | V55: =+T55-U55 -> 0 | W55: =+H55+M55+R55 -> 0 | X55: =+T55-W55 -> 0 | AA55: =+Y55-Z55 -> 0 | AB55: 0 | AC55: =+Y55-AB55 -> 0 | AD55: 0 | AE55: =+ｼﾞｭｴﾙｽﾞ!W54/1000 -> 0 | AF55: =+AD55-AE55 -> 0 | AG55: 0 | AH55: =+AD55-AG55 -> 0 | AI55: =+Y55+AD55 -> 0 | AJ55: =+Z55+AE55 -> 0 | AK55: =+AI55-AJ55 -> 0 | AL55: =+AB55+AG55 -> 0 | AM55: =+AI55-AL55 -> 0 | AN55: 0 | AO55: =+ｶﾞｰﾃﾞﾝ!W54/1000 -> 0 | AP55: =+AN55-AO55 -> 0 | AQ55: 0 | AR55: =+AN55-AQ55 -> 0 | AS55: 0 | AT55: =+ﾋﾞｱｶﾞｰﾃﾞﾝ!W54/1000 -> 0 | AU55: =+AS55-AT55 -> 0 | AV55: 0 | AW55: =+AS55-AV55 -> 0 | AX55: =+AN55+AS55 -> 0 | AY55: =+AO55+AT55 -> 0 | AZ55: =+AX55-AY55 -> 0 | BA55: =+AQ55+AV55 -> 0 | BB55: =+AX55-BA55 -> 0 | BC55: 0 | BD55: =+ブリック!W54/1000 -> 0 | BE55: =+BC55-BD55 -> 0 | BG55: =+BC55-BF55 -> 0 | BH55: 0 | BI55: =+ルスツ羊蹄ぶた!W54/1000 -> 0 | BJ55: =+BH55-BI55 -> 0 | BL55: =+BH55-BK55 -> 0 | BM55: =+BC55+BH55 -> 0 | BN55: =+BD55+BI55 -> 0 | BO55: =+BM55-BN55 -> 0 | BP55: =+BF55+BK55 -> 0 | BQ55: =+BM55-BP55 -> 0 | BR55: 0 | BS55: =+料飲共通!W54/1000 -> 0 | BT55: =+BR55-BS55 -> 0 | BU55: 0 | BV55: =+BR55-BU55 -> 0 | BW55: =+T55+AI55+AX55+BM55+BR55 -> 0 | BX55: =+U55+AJ55+AY55+BN55+BS55 -> 0 | BY55: =+BW55-BX55 -> 0 | BZ55: =+W55+AL55+BA55+BU55 -> 0 | CA55: =+BW55-BZ55 -> 0
C56: 器具備品 | E56: 0 | F56: =+ﾇｰﾍﾞﾙﾌﾟｰｽ!W55/1000 -> 79.9 | G56: =+E56-F56 -> -79.9 | H56: 0 | I56: =+E56-H56 -> 0 | J56: 0 | K56: =+ｶﾌｪﾙﾎﾟ!W55/1000 -> 0 | L56: =+J56-K56 -> 0 | M56: 0 | N56: =+J56-M56 -> 0 | O56: 0 | P56: =+ｶﾌｪｾﾚｽﾃ!W55/1000 -> 0 | Q56: =+O56-P56 -> 0 | R56: 0 | S56: =+O56-R56 -> 0 | T56: =+E56+J56+O56 -> 0 | U56: =+F56+K56+P56 -> 79.9 | V56: =+T56-U56 -> -79.9 | W56: =+H56+M56+R56 -> 0 | X56: =+T56-W56 -> 0 | AA56: =+Y56-Z56 -> 0 | AB56: 0 | AC56: =+Y56-AB56 -> 0 | AD56: 0 | AE56: =+ｼﾞｭｴﾙｽﾞ!W55/1000 -> 30.43 | AF56: =+AD56-AE56 -> -30.43 | AG56: 452 | AH56: =+AD56-AG56 -> -452 | AI56: =+Y56+AD56 -> 0 | AJ56: =+Z56+AE56 -> 30.43 | AK56: =+AI56-AJ56 -> -30.43 | AL56: =+AB56+AG56 -> 452 | AM56: =+AI56-AL56 -> -452 | AN56: 0 | AO56: =+ｶﾞｰﾃﾞﾝ!W55/1000 -> 117.7 | AP56: =+AN56-AO56 -> -117.7 | AQ56: 298 | AR56: =+AN56-AQ56 -> -298 | AS56: 150 | AT56: =+ﾋﾞｱｶﾞｰﾃﾞﾝ!W55/1000 -> 0 | AU56: =+AS56-AT56 -> 150 | AV56: 0 | AW56: =+AS56-AV56 -> 150 | AX56: =+AN56+AS56 -> 150 | AY56: =+AO56+AT56 -> 117.7 | AZ56: =+AX56-AY56 -> 32.3 | BA56: =+AQ56+AV56 -> 298 | BB56: =+AX56-BA56 -> -148 | BC56: 0 | BD56: =+ブリック!W55/1000 -> 0 | BE56: =+BC56-BD56 -> 0 | BG56: =+BC56-BF56 -> 0 | BH56: 0 | BI56: =+ルスツ羊蹄ぶた!W55/1000 -> 0 | BJ56: =+BH56-BI56 -> 0 | BL56: =+BH56-BK56 -> 0 | BM56: =+BC56+BH56 -> 0 | BN56: =+BD56+BI56 -> 0 | BO56: =+BM56-BN56 -> 0 | BP56: =+BF56+BK56 -> 0 | BQ56: =+BM56-BP56 -> 0 | BR56: 0 | BS56: =+料飲共通!W55/1000 -> 0 | BT56: =+BR56-BS56 -> 0 | BU56: 0 | BV56: =+BR56-BU56 -> 0 | BW56: =+T56+AI56+AX56+BM56+BR56 -> 150 | BX56: =+U56+AJ56+AY56+BN56+BS56 -> 228.03 | BY56: =+BW56-BX56 -> -78.03 | BZ56: =+W56+AL56+BA56+BU56 -> 750 | CA56: =+BW56-BZ56 -> -600
C57: 車両 | E57: 0 | F57: =+ﾇｰﾍﾞﾙﾌﾟｰｽ!W56/1000 -> 0 | G57: =+E57-F57 -> 0 | H57: 0 | I57: =+E57-H57 -> 0 | J57: 0 | K57: =+ｶﾌｪﾙﾎﾟ!W56/1000 -> 0 | L57: =+J57-K57 -> 0 | M57: 0 | N57: =+J57-M57 -> 0 | O57: 0 | P57: =+ｶﾌｪｾﾚｽﾃ!W56/1000 -> 0 | Q57: =+O57-P57 -> 0 | R57: 0 | S57: =+O57-R57 -> 0 | T57: =+E57+J57+O57 -> 0 | U57: =+F57+K57+P57 -> 0 | V57: =+T57-U57 -> 0 | W57: =+H57+M57+R57 -> 0 | X57: =+T57-W57 -> 0 | AA57: =+Y57-Z57 -> 0 | AB57: 0 | AC57: =+Y57-AB57 -> 0 | AD57: 0 | AE57: =+ｼﾞｭｴﾙｽﾞ!W56/1000 -> 0 | AF57: =+AD57-AE57 -> 0 | AG57: 0 | AH57: =+AD57-AG57 -> 0 | AI57: =+Y57+AD57 -> 0 | AJ57: =+Z57+AE57 -> 0 | AK57: =+AI57-AJ57 -> 0 | AL57: =+AB57+AG57 -> 0 | AM57: =+AI57-AL57 -> 0 | AN57: 0 | AO57: =+ｶﾞｰﾃﾞﾝ!W56/1000 -> 0 | AP57: =+AN57-AO57 -> 0 | AQ57: 0 | AR57: =+AN57-AQ57 -> 0 | AS57: 0 | AT57: =+ﾋﾞｱｶﾞｰﾃﾞﾝ!W56/1000 -> 0 | AU57: =+AS57-AT57 -> 0 | AV57: 0 | AW57: =+AS57-AV57 -> 0 | AX57: =+AN57+AS57 -> 0 | AY57: =+AO57+AT57 -> 0 | AZ57: =+AX57-AY57 -> 0 | BA57: =+AQ57+AV57 -> 0 | BB57: =+AX57-BA57 -> 0 | BC57: 0 | BD57: =+ブリック!W56/1000 -> 0 | BE57: =+BC57-BD57 -> 0 | BG57: =+BC57-BF57 -> 0 | BH57: 0 | BI57: =+ルスツ羊蹄ぶた!W56/1000 -> 0 | BJ57: =+BH57-BI57 -> 0 | BL57: =+BH57-BK57 -> 0 | BM57: =+BC57+BH57 -> 0 | BN57: =+BD57+BI57 -> 0 | BO57: =+BM57-BN57 -> 0 | BP57: =+BF57+BK57 -> 0 | BQ57: =+BM57-BP57 -> 0 | BR57: 0 | BS57: =+料飲共通!W56/1000 -> 0 | BT57: =+BR57-BS57 -> 0 | BU57: 0 | BV57: =+BR57-BU57 -> 0 | BW57: =+T57+AI57+AX57+BM57+BR57 -> 0 | BX57: =+U57+AJ57+AY57+BN57+BS57 -> 0 | BY57: =+BW57-BX57 -> 0 | BZ57: =+W57+AL57+BA57+BU57 -> 0 | CA57: =+BW57-BZ57 -> 0
B58: 車両運搬費 | E58: 0 | F58: =+ﾇｰﾍﾞﾙﾌﾟｰｽ!W57/1000 -> 0 | G58: =+E58-F58 -> 0 | H58: 0 | I58: =+E58-H58 -> 0 | J58: 0 | K58: =+ｶﾌｪﾙﾎﾟ!W57/1000 -> 0 | L58: =+J58-K58 -> 0 | M58: 0 | N58: =+J58-M58 -> 0 | O58: 0 | P58: =+ｶﾌｪｾﾚｽﾃ!W57/1000 -> 0 | Q58: =+O58-P58 -> 0 | R58: 0 | S58: =+O58-R58 -> 0 | T58: =+E58+J58+O58 -> 0 | U58: =+F58+K58+P58 -> 0 | V58: =+T58-U58 -> 0 | W58: =+H58+M58+R58 -> 0 | X58: =+T58-W58 -> 0 | AA58: =+Y58-Z58 -> 0 | AB58: 0 | AC58: =+Y58-AB58 -> 0 | AD58: 0 | AE58: =+ｼﾞｭｴﾙｽﾞ!W57/1000 -> 286.66 | AF58: =+AD58-AE58 -> -286.66 | AG58: 0 | AH58: =+AD58-AG58 -> 0 | AI58: =+Y58+AD58 -> 0 | AJ58: =+Z58+AE58 -> 286.66 | AK58: =+AI58-AJ58 -> -286.66 | AL58: =+AB58+AG58 -> 0 | AM58: =+AI58-AL58 -> 0 | AN58: 0 | AO58: =+ｶﾞｰﾃﾞﾝ!W57/1000 -> 0 | AP58: =+AN58-AO58 -> 0 | AQ58: 0 | AR58: =+AN58-AQ58 -> 0 | AS58: 0 | AT58: =+ﾋﾞｱｶﾞｰﾃﾞﾝ!W57/1000 -> 0 | AU58: =+AS58-AT58 -> 0 | AV58: 0 | AW58: =+AS58-AV58 -> 0 | AX58: =+AN58+AS58 -> 0 | AY58: =+AO58+AT58 -> 0 | AZ58: =+AX58-AY58 -> 0 | BA58: =+AQ58+AV58 -> 0 | BB58: =+AX58-BA58 -> 0 | BC58: 0 | BD58: =+ブリック!W57/1000 -> 0 | BE58: =+BC58-BD58 -> 0 | BG58: =+BC58-BF58 -> 0 | BH58: 0 | BI58: =+ルスツ羊蹄ぶた!W57/1000 -> 0 | BJ58: =+BH58-BI58 -> 0 | BL58: =+BH58-BK58 -> 0 | BM58: =+BC58+BH58 -> 0 | BN58: =+BD58+BI58 -> 0 | BO58: =+BM58-BN58 -> 0 | BP58: =+BF58+BK58 -> 0 | BQ58: =+BM58-BP58 -> 0 | BR58: 0 | BS58: =+料飲共通!W57/1000 -> 0 | BT58: =+BR58-BS58 -> 0 | BU58: 0 | BV58: =+BR58-BU58 -> 0 | BW58: =+T58+AI58+AX58+BM58+BR58 -> 0 | BX58: =+U58+AJ58+AY58+BN58+BS58 -> 286.66 | BY58: =+BW58-BX58 -> -286.66 | BZ58: =+W58+AL58+BA58+BU58 -> 0 | CA58: =+BW58-BZ58 -> 0
B59: 印刷製本費 | E59: 414 | F59: =+ﾇｰﾍﾞﾙﾌﾟｰｽ!W58/1000 -> 107.84 | G59: =+E59-F59 -> 306.16 | H59: 139 | I59: =+E59-H59 -> 275 | J59: 0 | K59: =+ｶﾌｪﾙﾎﾟ!W58/1000 -> 0 | L59: =+J59-K59 -> 0 | M59: 0 | N59: =+J59-M59 -> 0 | O59: 0 | P59: =+ｶﾌｪｾﾚｽﾃ!W58/1000 -> 0 | Q59: =+O59-P59 -> 0 | R59: 0 | S59: =+O59-R59 -> 0 | T59: =+E59+J59+O59 -> 414 | U59: =+F59+K59+P59 -> 107.84 | V59: =+T59-U59 -> 306.16 | W59: =+H59+M59+R59 -> 139 | X59: =+T59-W59 -> 275 | AA59: =+Y59-Z59 -> 0 | AB59: 0 | AC59: =+Y59-AB59 -> 0 | AD59: 390 | AE59: =+ｼﾞｭｴﾙｽﾞ!W58/1000 -> 25.98 | AF59: =+AD59-AE59 -> 364.02 | AG59: 173 | AH59: =+AD59-AG59 -> 217 | AI59: =+Y59+AD59 -> 390 | AJ59: =+Z59+AE59 -> 25.98 | AK59: =+AI59-AJ59 -> 364.02 | AL59: =+AB59+AG59 -> 173 | AM59: =+AI59-AL59 -> 217 | AN59: 141 | AO59: =+ｶﾞｰﾃﾞﾝ!W58/1000 -> 40.22 | AP59: =+AN59-AO59 -> 100.78 | AQ59: 189 | AR59: =+AN59-AQ59 -> -48 | AS59: 261 | AT59: =+ﾋﾞｱｶﾞｰﾃﾞﾝ!W58/1000 -> 174 | AU59: =+AS59-AT59 -> 87 | AV59: 0 | AW59: =+AS59-AV59 -> 261 | AX59: =+AN59+AS59 -> 402 | AY59: =+AO59+AT59 -> 214.22 | AZ59: =+AX59-AY59 -> 187.78 | BA59: =+AQ59+AV59 -> 189 | BB59: =+AX59-BA59 -> 213 | BC59: 109.85658 | BD59: =+ブリック!W58/1000 -> 178.98 | BE59: =+BC59-BD59 -> -69.123424 | BG59: =+BC59-BF59 -> 109.85658 | BH59: 0 | BI59: =+ルスツ羊蹄ぶた!W58/1000 -> 0 | BJ59: =+BH59-BI59 -> 0 | BL59: =+BH59-BK59 -> 0 | BM59: =+BC59+BH59 -> 109.85658 | BN59: =+BD59+BI59 -> 178.98 | BO59: =+BM59-BN59 -> -69.123424 | BP59: =+BF59+BK59 -> 0 | BQ59: =+BM59-BP59 -> 109.85658 | BR59: 60 | BS59: =+料飲共通!W58/1000 -> 114.35 | BT59: =+BR59-BS59 -> -54.35 | BU59: 168 | BV59: =+BR59-BU59 -> -108 | BW59: =+T59+AI59+AX59+BM59+BR59 -> 1375.8566 | BX59: =+U59+AJ59+AY59+BN59+BS59 -> 641.37 | BY59: =+BW59-BX59 -> 734.48658 | BZ59: =+W59+AL59+BA59+BU59 -> 669 | CA59: =+BW59-BZ59 -> 706.85658
C60: 印刷製本費 | E60: 414 | F60: =+ﾇｰﾍﾞﾙﾌﾟｰｽ!W59/1000 -> 107.84 | G60: =+E60-F60 -> 306.16 | H60: 139 | I60: =+E60-H60 -> 275 | J60: 0 | K60: =+ｶﾌｪﾙﾎﾟ!W59/1000 -> 0 | L60: =+J60-K60 -> 0 | M60: 0 | N60: =+J60-M60 -> 0 | O60: 0 | P60: =+ｶﾌｪｾﾚｽﾃ!W59/1000 -> 0 | Q60: =+O60-P60 -> 0 | R60: 0 | S60: =+O60-R60 -> 0 | T60: =+E60+J60+O60 -> 414 | U60: =+F60+K60+P60 -> 107.84 | V60: =+T60-U60 -> 306.16 | W60: =+H60+M60+R60 -> 139 | X60: =+T60-W60 -> 275 | AA60: =+Y60-Z60 -> 0 | AB60: 0 | AC60: =+Y60-AB60 -> 0 | AD60: 390 | AE60: =+ｼﾞｭｴﾙｽﾞ!W59/1000 -> 25.98 | AF60: =+AD60-AE60 -> 364.02 | AG60: 173 | AH60: =+AD60-AG60 -> 217 | AI60: =+Y60+AD60 -> 390 | AJ60: =+Z60+AE60 -> 25.98 | AK60: =+AI60-AJ60 -> 364.02 | AL60: =+AB60+AG60 -> 173 | AM60: =+AI60-AL60 -> 217 | AN60: 141 | AO60: =+ｶﾞｰﾃﾞﾝ!W59/1000 -> 40.22 | AP60: =+AN60-AO60 -> 100.78 | AQ60: 189 | AR60: =+AN60-AQ60 -> -48 | AS60: 261 | AT60: =+ﾋﾞｱｶﾞｰﾃﾞﾝ!W59/1000 -> 174 | AU60: =+AS60-AT60 -> 87 | AV60: 0 | AW60: =+AS60-AV60 -> 261 | AX60: =+AN60+AS60 -> 402 | AY60: =+AO60+AT60 -> 214.22 | AZ60: =+AX60-AY60 -> 187.78 | BA60: =+AQ60+AV60 -> 189 | BB60: =+AX60-BA60 -> 213 | BC60: 0 | BD60: =+ブリック!W59/1000 -> 178.98 | BE60: =+BC60-BD60 -> -178.98 | BG60: =+BC60-BF60 -> 0 | BH60: 0 | BI60: =+ルスツ羊蹄ぶた!W59/1000 -> 0 | BJ60: =+BH60-BI60 -> 0 | BL60: =+BH60-BK60 -> 0 | BM60: =+BC60+BH60 -> 0 | BN60: =+BD60+BI60 -> 178.98 | BO60: =+BM60-BN60 -> -178.98 | BP60: =+BF60+BK60 -> 0 | BQ60: =+BM60-BP60 -> 0 | BR60: 60 | BS60: =+料飲共通!W59/1000 -> 114.35 | BT60: =+BR60-BS60 -> -54.35 | BU60: 168 | BV60: =+BR60-BU60 -> -108 | BW60: =+T60+AI60+AX60+BM60+BR60 -> 1266 | BX60: =+U60+AJ60+AY60+BN60+BS60 -> 641.37 | BY60: =+BW60-BX60 -> 624.63 | BZ60: =+W60+AL60+BA60+BU60 -> 669 | CA60: =+BW60-BZ60 -> 597
C61: 乗車券帳票費 | E61: 0 | F61: =+ﾇｰﾍﾞﾙﾌﾟｰｽ!W60/1000 -> 0 | G61: =+E61-F61 -> 0 | H61: 0 | I61: =+E61-H61 -> 0 | J61: 0 | K61: =+ｶﾌｪﾙﾎﾟ!W60/1000 -> 0 | L61: =+J61-K61 -> 0 | M61: 0 | N61: =+J61-M61 -> 0 | O61: 0 | P61: =+ｶﾌｪｾﾚｽﾃ!W60/1000 -> 0 | Q61: =+O61-P61 -> 0 | R61: 0 | S61: =+O61-R61 -> 0 | T61: =+E61+J61+O61 -> 0 | U61: =+F61+K61+P61 -> 0 | V61: =+T61-U61 -> 0 | W61: =+H61+M61+R61 -> 0 | X61: =+T61-W61 -> 0 | AA61: =+Y61-Z61 -> 0 | AB61: 0 | AC61: =+Y61-AB61 -> 0 | AD61: 0 | AE61: =+ｼﾞｭｴﾙｽﾞ!W60/1000 -> 0 | AF61: =+AD61-AE61 -> 0 | AG61: 0 | AH61: =+AD61-AG61 -> 0 | AI61: =+Y61+AD61 -> 0 | AJ61: =+Z61+AE61 -> 0 | AK61: =+AI61-AJ61 -> 0 | AL61: =+AB61+AG61 -> 0 | AM61: =+AI61-AL61 -> 0 | AN61: 0 | AO61: =+ｶﾞｰﾃﾞﾝ!W60/1000 -> 0 | AP61: =+AN61-AO61 -> 0 | AQ61: 0 | AR61: =+AN61-AQ61 -> 0 | AS61: 0 | AT61: =+ﾋﾞｱｶﾞｰﾃﾞﾝ!W60/1000 -> 0 | AU61: =+AS61-AT61 -> 0 | AV61: 0 | AW61: =+AS61-AV61 -> 0 | AX61: =+AN61+AS61 -> 0 | AY61: =+AO61+AT61 -> 0 | AZ61: =+AX61-AY61 -> 0 | BA61: =+AQ61+AV61 -> 0 | BB61: =+AX61-BA61 -> 0 | BC61: 0 | BD61: =+ブリック!W60/1000 -> 0 | BE61: =+BC61-BD61 -> 0 | BG61: =+BC61-BF61 -> 0 | BH61: 0 | BI61: =+ルスツ羊蹄ぶた!W60/1000 -> 0 | BJ61: =+BH61-BI61 -> 0 | BL61: =+BH61-BK61 -> 0 | BM61: =+BC61+BH61 -> 0 | BN61: =+BD61+BI61 -> 0 | BO61: =+BM61-BN61 -> 0 | BP61: =+BF61+BK61 -> 0 | BQ61: =+BM61-BP61 -> 0 | BR61: 0 | BS61: =+料飲共通!W60/1000 -> 0 | BT61: =+BR61-BS61 -> 0 | BU61: 0 | BV61: =+BR61-BU61 -> 0 | BW61: =+T61+AI61+AX61+BM61+BR61 -> 0 | BX61: =+U61+AJ61+AY61+BN61+BS61 -> 0 | BY61: =+BW61-BX61 -> 0 | BZ61: =+W61+AL61+BA61+BU61 -> 0 | CA61: =+BW61-BZ61 -> 0
B62: 清掃衛生費 | E62: 984 | F62: =+ﾇｰﾍﾞﾙﾌﾟｰｽ!W61/1000 -> 387.039 | G62: =+E62-F62 -> 596.961 | H62: 898 | I62: =+E62-H62 -> 86 | J62: 30.5 | K62: =+ｶﾌｪﾙﾎﾟ!W61/1000 -> 24.204 | L62: =+J62-K62 -> 6.296 | M62: 28 | N62: =+J62-M62 -> 2.5 | O62: 0 | P62: =+ｶﾌｪｾﾚｽﾃ!W61/1000 -> 0 | Q62: =+O62-P62 -> 0 | R62: 0 | S62: =+O62-R62 -> 0 | T62: =+E62+J62+O62 -> 1014.5 | U62: =+F62+K62+P62 -> 411.243 | V62: =+T62-U62 -> 603.257 | W62: =+H62+M62+R62 -> 926 | X62: =+T62-W62 -> 88.5 | AA62: =+Y62-Z62 -> 0 | AB62: 48 | AC62: =+Y62-AB62 -> -48 | AD62: 764 | AE62: =+ｼﾞｭｴﾙｽﾞ!W61/1000 -> 653.464 | AF62: =+AD62-AE62 -> 110.536 | AG62: 842 | AH62: =+AD62-AG62 -> -78 | AI62: =+Y62+AD62 -> 764 | AJ62: =+Z62+AE62 -> 653.464 | AK62: =+AI62-AJ62 -> 110.536 | AL62: =+AB62+AG62 -> 890 | AM62: =+AI62-AL62 -> -126 | AN62: 622.4 | AO62: =+ｶﾞｰﾃﾞﾝ!W61/1000 -> 521.157 | AP62: =+AN62-AO62 -> 101.243 | AQ62: 619 | AR62: =+AN62-AQ62 -> 3.4 | AS62: 700 | AT62: =+ﾋﾞｱｶﾞｰﾃﾞﾝ!W61/1000 -> 810.652 | AU62: =+AS62-AT62 -> -110.652 | AV62: 662 | AW62: =+AS62-AV62 -> 38 | AX62: =+AN62+AS62 -> 1322.4 | AY62: =+AO62+AT62 -> 1331.809 | AZ62: =+AX62-AY62 -> -9.409 | BA62: =+AQ62+AV62 -> 1281 | BB62: =+AX62-BA62 -> 41.4 | BC62: 237.48586 | BD62: =+ブリック!W61/1000 -> 233.925 | BE62: =+BC62-BD62 -> 3.5608606 | BG62: =+BC62-BF62 -> 237.48586 | BH62: 123.05793 | BI62: =+ルスツ羊蹄ぶた!W61/1000 -> 51.266 | BJ62: =+BH62-BI62 -> 71.791929 | BL62: =+BH62-BK62 -> 123.05793 | BM62: =+BC62+BH62 -> 360.54379 | BN62: =+BD62+BI62 -> 285.191 | BO62: =+BM62-BN62 -> 75.35279 | BP62: =+BF62+BK62 -> 0 | BQ62: =+BM62-BP62 -> 360.54379 | BR62: 0 | BS62: =+料飲共通!W61/1000 -> 0 | BT62: =+BR62-BS62 -> 0 | BU62: 0 | BV62: =+BR62-BU62 -> 0 | BW62: =+T62+AI62+AX62+BM62+BR62 -> 3461.4438 | BX62: =+U62+AJ62+AY62+BN62+BS62 -> 2681.707 | BY62: =+BW62-BX62 -> 779.73679 | BZ62: =+W62+AL62+BA62+BU62 -> 3097 | CA62: =+BW62-BZ62 -> 364.44379
B63: 事務会議費 | E63: 0 | F63: =+ﾇｰﾍﾞﾙﾌﾟｰｽ!W62/1000 -> 0 | G63: =+E63-F63 -> 0 | H63: 0 | I63: =+E63-H63 -> 0 | J63: 0 | K63: =+ｶﾌｪﾙﾎﾟ!W62/1000 -> 0 | L63: =+J63-K63 -> 0 | M63: 0 | N63: =+J63-M63 -> 0 | O63: 0 | P63: =+ｶﾌｪｾﾚｽﾃ!W62/1000 -> 0 | Q63: =+O63-P63 -> 0 | R63: 0 | S63: =+O63-R63 -> 0 | T63: =+E63+J63+O63 -> 0 | U63: =+F63+K63+P63 -> 0 | V63: =+T63-U63 -> 0 | W63: =+H63+M63+R63 -> 0 | X63: =+T63-W63 -> 0 | AA63: =+Y63-Z63 -> 0 | AB63: 0 | AC63: =+Y63-AB63 -> 0 | AD63: 0 | AE63: =+ｼﾞｭｴﾙｽﾞ!W62/1000 -> 0 | AF63: =+AD63-AE63 -> 0 | AG63: 0 | AH63: =+AD63-AG63 -> 0 | AI63: =+Y63+AD63 -> 0 | AJ63: =+Z63+AE63 -> 0 | AK63: =+AI63-AJ63 -> 0 | AL63: =+AB63+AG63 -> 0 | AM63: =+AI63-AL63 -> 0 | AN63: 0 | AO63: =+ｶﾞｰﾃﾞﾝ!W62/1000 -> 0 | AP63: =+AN63-AO63 -> 0 | AQ63: 0 | AR63: =+AN63-AQ63 -> 0 | AS63: 0 | AT63: =+ﾋﾞｱｶﾞｰﾃﾞﾝ!W62/1000 -> 0 | AU63: =+AS63-AT63 -> 0 | AV63: 0 | AW63: =+AS63-AV63 -> 0 | AX63: =+AN63+AS63 -> 0 | AY63: =+AO63+AT63 -> 0 | AZ63: =+AX63-AY63 -> 0 | BA63: =+AQ63+AV63 -> 0 | BB63: =+AX63-BA63 -> 0 | BC63: 0 | BD63: =+ブリック!W62/1000 -> 0 | BE63: =+BC63-BD63 -> 0 | BG63: =+BC63-BF63 -> 0 | BH63: 0 | BI63: =+ルスツ羊蹄ぶた!W62/1000 -> 0 | BJ63: =+BH63-BI63 -> 0 | BL63: =+BH63-BK63 -> 0 | BM63: =+BC63+BH63 -> 0 | BN63: =+BD63+BI63 -> 0 | BO63: =+BM63-BN63 -> 0 | BP63: =+BF63+BK63 -> 0 | BQ63: =+BM63-BP63 -> 0 | BR63: 0 | BS63: =+料飲共通!W62/1000 -> 17.652 | BT63: =+BR63-BS63 -> -17.652 | BU63: 0 | BV63: =+BR63-BU63 -> 0 | BW63: =+T63+AI63+AX63+BM63+BR63 -> 0 | BX63: =+U63+AJ63+AY63+BN63+BS63 -> 17.652 | BY63: =+BW63-BX63 -> -17.652 | BZ63: =+W63+AL63+BA63+BU63 -> 0 | CA63: =+BW63-BZ63 -> 0
B64: 租税公課 | E64: 148.5 | F64: =+ﾇｰﾍﾞﾙﾌﾟｰｽ!W63/1000 -> 3 | G64: =+E64-F64 -> 145.5 | H64: 144 | I64: =+E64-H64 -> 4.5 | J64: 23.5 | K64: =+ｶﾌｪﾙﾎﾟ!W63/1000 -> 0 | L64: =+J64-K64 -> 23.5 | M64: 24 | N64: =+J64-M64 -> -0.5 | O64: 9.7 | P64: =+ｶﾌｪｾﾚｽﾃ!W63/1000 -> 0 | Q64: =+O64-P64 -> 9.7 | R64: 10 | S64: =+O64-R64 -> -0.3 | T64: =+E64+J64+O64 -> 181.7 | U64: =+F64+K64+P64 -> 3 | V64: =+T64-U64 -> 178.7 | W64: =+H64+M64+R64 -> 178 | X64: =+T64-W64 -> 3.7 | AA64: =+Y64-Z64 -> 0 | AB64: 0 | AC64: =+Y64-AB64 -> 0 | AD64: 76.3 | AE64: =+ｼﾞｭｴﾙｽﾞ!W63/1000 -> 72.35 | AF64: =+AD64-AE64 -> 3.95 | AG64: 76 | AH64: =+AD64-AG64 -> 0.3 | AI64: =+Y64+AD64 -> 76.3 | AJ64: =+Z64+AE64 -> 72.35 | AK64: =+AI64-AJ64 -> 3.95 | AL64: =+AB64+AG64 -> 76 | AM64: =+AI64-AL64 -> 0.3 | AN64: 260 | AO64: =+ｶﾞｰﾃﾞﾝ!W63/1000 -> 18.3 | AP64: =+AN64-AO64 -> 241.7 | AQ64: 272 | AR64: =+AN64-AQ64 -> -12 | AS64: 26.9 | AT64: =+ﾋﾞｱｶﾞｰﾃﾞﾝ!W63/1000 -> 0 | AU64: =+AS64-AT64 -> 26.9 | AV64: 24 | AW64: =+AS64-AV64 -> 2.9 | AX64: =+AN64+AS64 -> 286.9 | AY64: =+AO64+AT64 -> 18.3 | AZ64: =+AX64-AY64 -> 268.6 | BA64: =+AQ64+AV64 -> 296 | BB64: =+AX64-BA64 -> -9.1 | BC64: 323.4 | BD64: =+ブリック!W63/1000 -> 4.05 | BE64: =+BC64-BD64 -> 319.35 | BG64: =+BC64-BF64 -> 323.4 | BH64: 58.8 | BI64: =+ルスツ羊蹄ぶた!W63/1000 -> 0 | BJ64: =+BH64-BI64 -> 58.8 | BL64: =+BH64-BK64 -> 58.8 | BM64: =+BC64+BH64 -> 382.2 | BN64: =+BD64+BI64 -> 4.05 | BO64: =+BM64-BN64 -> 378.15 | BP64: =+BF64+BK64 -> 0 | BQ64: =+BM64-BP64 -> 382.2 | BR64: 0 | BS64: =+料飲共通!W63/1000 -> 0 | BT64: =+BR64-BS64 -> 0 | BU64: 0 | BV64: =+BR64-BU64 -> 0 | BW64: =+T64+AI64+AX64+BM64+BR64 -> 927.1 | BX64: =+U64+AJ64+AY64+BN64+BS64 -> 97.7 | BY64: =+BW64-BX64 -> 829.4 | BZ64: =+W64+AL64+BA64+BU64 -> 550 | CA64: =+BW64-BZ64 -> 377.1
B65: 会費負担金 | E65: 130 | F65: =+ﾇｰﾍﾞﾙﾌﾟｰｽ!W64/1000 -> 180 | G65: =+E65-F65 -> -50 | H65: 74 | I65: =+E65-H65 -> 56 | J65: 0 | K65: =+ｶﾌｪﾙﾎﾟ!W64/1000 -> 0 | L65: =+J65-K65 -> 0 | M65: 0 | N65: =+J65-M65 -> 0 | O65: 0 | P65: =+ｶﾌｪｾﾚｽﾃ!W64/1000 -> 0 | Q65: =+O65-P65 -> 0 | R65: 0 | S65: =+O65-R65 -> 0 | T65: =+E65+J65+O65 -> 130 | U65: =+F65+K65+P65 -> 180 | V65: =+T65-U65 -> -50 | W65: =+H65+M65+R65 -> 74 | X65: =+T65-W65 -> 56 | AA65: =+Y65-Z65 -> 0 | AB65: 0 | AC65: =+Y65-AB65 -> 0 | AD65: 135 | AE65: =+ｼﾞｭｴﾙｽﾞ!W64/1000 -> 115 | AF65: =+AD65-AE65 -> 20 | AG65: 37 | AH65: =+AD65-AG65 -> 98 | AI65: =+Y65+AD65 -> 135 | AJ65: =+Z65+AE65 -> 115 | AK65: =+AI65-AJ65 -> 20 | AL65: =+AB65+AG65 -> 37 | AM65: =+AI65-AL65 -> 98 | AN65: 165 | AO65: =+ｶﾞｰﾃﾞﾝ!W64/1000 -> 65 | AP65: =+AN65-AO65 -> 100 | AQ65: 66 | AR65: =+AN65-AQ65 -> 99 | AS65: 0 | AT65: =+ﾋﾞｱｶﾞｰﾃﾞﾝ!W64/1000 -> 0 | AU65: =+AS65-AT65 -> 0 | AV65: 0 | AW65: =+AS65-AV65 -> 0 | AX65: =+AN65+AS65 -> 165 | AY65: =+AO65+AT65 -> 65 | AZ65: =+AX65-AY65 -> 100 | BA65: =+AQ65+AV65 -> 66 | BB65: =+AX65-BA65 -> 99 | BC65: 0 | BD65: =+ブリック!W64/1000 -> 15 | BE65: =+BC65-BD65 -> -15 | BG65: =+BC65-BF65 -> 0 | BH65: 0 | BI65: =+ルスツ羊蹄ぶた!W64/1000 -> 0 | BJ65: =+BH65-BI65 -> 0 | BL65: =+BH65-BK65 -> 0 | BM65: =+BC65+BH65 -> 0 | BN65: =+BD65+BI65 -> 15 | BO65: =+BM65-BN65 -> -15 | BP65: =+BF65+BK65 -> 0 | BQ65: =+BM65-BP65 -> 0 | BR65: 15 | BS65: =+料飲共通!W64/1000 -> 190 | BT65: =+BR65-BS65 -> -175 | BU65: 15 | BV65: =+BR65-BU65 -> 0 | BW65: =+T65+AI65+AX65+BM65+BR65 -> 445 | BX65: =+U65+AJ65+AY65+BN65+BS65 -> 565 | BY65: =+BW65-BX65 -> -120 | BZ65: =+W65+AL65+BA65+BU65 -> 192 | CA65: =+BW65-BZ65 -> 253
B66: 委託料 | E66: 2991.44 | F66: =+ﾇｰﾍﾞﾙﾌﾟｰｽ!W65/1000 -> 4029.252 | G66: =+E66-F66 -> -1037.812 | H66: 3284 | I66: =+E66-H66 -> -292.56 | J66: 184 | K66: =+ｶﾌｪﾙﾎﾟ!W65/1000 -> 197 | L66: =+J66-K66 -> -13 | M66: 284 | N66: =+J66-M66 -> -100 | O66: 290 | P66: =+ｶﾌｪｾﾚｽﾃ!W65/1000 -> 218 | Q66: =+O66-P66 -> 72 | R66: 168 | S66: =+O66-R66 -> 122 | T66: =+E66+J66+O66 -> 3465.44 | U66: =+F66+K66+P66 -> 4444.252 | V66: =+T66-U66 -> -978.812 | W66: =+H66+M66+R66 -> 3736 | X66: =+T66-W66 -> -270.56 | AA66: =+Y66-Z66 -> 0 | AB66: 679 | AC66: =+Y66-AB66 -> -679 | AD66: 3997.44 | AE66: =+ｼﾞｭｴﾙｽﾞ!W65/1000 -> 3766.975 | AF66: =+AD66-AE66 -> 230.465 | AG66: 4936 | AH66: =+AD66-AG66 -> -938.56 | AI66: =+Y66+AD66 -> 3997.44 | AJ66: =+Z66+AE66 -> 3766.975 | AK66: =+AI66-AJ66 -> 230.465 | AL66: =+AB66+AG66 -> 5615 | AM66: =+AI66-AL66 -> -1617.56 | AN66: 5337.64 | AO66: =+ｶﾞｰﾃﾞﾝ!W65/1000 -> 6455.123 | AP66: =+AN66-AO66 -> -1117.483 | AQ66: 6251 | AR66: =+AN66-AQ66 -> -913.36 | AS66: 39740.5 | AT66: =+ﾋﾞｱｶﾞｰﾃﾞﾝ!W65/1000 -> 45669.087 | AU66: =+AS66-AT66 -> -5928.587 | AV66: 53569 | AW66: =+AS66-AV66 -> -13828.5 | AX66: =+AN66+AS66 -> 45078.14 | AY66: =+AO66+AT66 -> 52124.21 | AZ66: =+AX66-AY66 -> -7046.07 | BA66: =+AQ66+AV66 -> 59820 | BB66: =+AX66-BA66 -> -14741.86 | BC66: 2114.0649 | BD66: =+ブリック!W65/1000 -> 4337.954 | BE66: =+BC66-BD66 -> -2223.8891 | BG66: =+BC66-BF66 -> 2114.0649 | BH66: 1206.0342 | BI66: =+ルスツ羊蹄ぶた!W65/1000 -> 1313.563 | BJ66: =+BH66-BI66 -> -107.52878 | BL66: =+BH66-BK66 -> 1206.0342 | BM66: =+BC66+BH66 -> 3320.0991 | BN66: =+BD66+BI66 -> 5651.517 | BO66: =+BM66-BN66 -> -2331.4179 | BP66: =+BF66+BK66 -> 0 | BQ66: =+BM66-BP66 -> 3320.0991 | BR66: 909.75 | BS66: =+料飲共通!W65/1000 -> 1124.1 | BT66: =+BR66-BS66 -> -214.35 | BU66: 1151 | BV66: =+BR66-BU66 -> -241.25 | BW66: =+T66+AI66+AX66+BM66+BR66 -> 56770.869 | BX66: =+U66+AJ66+AY66+BN66+BS66 -> 67111.054 | BY66: =+BW66-BX66 -> -10340.185 | BZ66: =+W66+AL66+BA66+BU66 -> 70322 | CA66: =+BW66-BZ66 -> -13551.131
B67: 除雪費 | E67: 0 | F67: =+ﾇｰﾍﾞﾙﾌﾟｰｽ!W66/1000 -> 0 | G67: =+E67-F67 -> 0 | H67: 0 | I67: =+E67-H67 -> 0 | J67: 0 | K67: =+ｶﾌｪﾙﾎﾟ!W66/1000 -> 0 | L67: =+J67-K67 -> 0 | M67: 0 | N67: =+J67-M67 -> 0 | O67: 0 | P67: =+ｶﾌｪｾﾚｽﾃ!W66/1000 -> 0 | Q67: =+O67-P67 -> 0 | R67: 0 | S67: =+O67-R67 -> 0 | T67: =+E67+J67+O67 -> 0 | U67: =+F67+K67+P67 -> 0 | V67: =+T67-U67 -> 0 | W67: =+H67+M67+R67 -> 0 | X67: =+T67-W67 -> 0 | AA67: =+Y67-Z67 -> 0 | AB67: 0 | AC67: =+Y67-AB67 -> 0 | AD67: 0 | AE67: =+ｼﾞｭｴﾙｽﾞ!W66/1000 -> 0 | AF67: =+AD67-AE67 -> 0 | AG67: 0 | AH67: =+AD67-AG67 -> 0 | AI67: =+Y67+AD67 -> 0 | AJ67: =+Z67+AE67 -> 0 | AK67: =+AI67-AJ67 -> 0 | AL67: =+AB67+AG67 -> 0 | AM67: =+AI67-AL67 -> 0 | AN67: 0 | AO67: =+ｶﾞｰﾃﾞﾝ!W66/1000 -> 0 | AP67: =+AN67-AO67 -> 0 | AQ67: 0 | AR67: =+AN67-AQ67 -> 0 | AS67: 0 | AT67: =+ﾋﾞｱｶﾞｰﾃﾞﾝ!W66/1000 -> 0 | AU67: =+AS67-AT67 -> 0 | AV67: 0 | AW67: =+AS67-AV67 -> 0 | AX67: =+AN67+AS67 -> 0 | AY67: =+AO67+AT67 -> 0 | AZ67: =+AX67-AY67 -> 0 | BA67: =+AQ67+AV67 -> 0 | BB67: =+AX67-BA67 -> 0 | BC67: 0 | BD67: =+ブリック!W66/1000 -> 0 | BE67: =+BC67-BD67 -> 0 | BG67: =+BC67-BF67 -> 0 | BH67: 0 | BI67: =+ルスツ羊蹄ぶた!W66/1000 -> 0 | BJ67: =+BH67-BI67 -> 0 | BL67: =+BH67-BK67 -> 0 | BM67: =+BC67+BH67 -> 0 | BN67: =+BD67+BI67 -> 0 | BO67: =+BM67-BN67 -> 0 | BP67: =+BF67+BK67 -> 0 | BQ67: =+BM67-BP67 -> 0 | BR67: 0 | BS67: =+料飲共通!W66/1000 -> 0 | BT67: =+BR67-BS67 -> 0 | BU67: 0 | BV67: =+BR67-BU67 -> 0 | BW67: =+T67+AI67+AX67+BM67+BR67 -> 0 | BX67: =+U67+AJ67+AY67+BN67+BS67 -> 0 | BY67: =+BW67-BX67 -> 0 | BZ67: =+W67+AL67+BA67+BU67 -> 0 | CA67: =+BW67-BZ67 -> 0
B68: 販売促進費 | E68: 5175.328 | F68: =+ﾇｰﾍﾞﾙﾌﾟｰｽ!W67/1000 -> 3798.322 | G68: =+E68-F68 -> 1377.006 | H68: 4755 | I68: =+E68-H68 -> 420.328 | J68: 160 | K68: =+ｶﾌｪﾙﾎﾟ!W67/1000 -> 124.171 | L68: =+J68-K68 -> 35.829 | M68: 163 | N68: =+J68-M68 -> -3 | O68: 160 | P68: =+ｶﾌｪｾﾚｽﾃ!W67/1000 -> 278.736 | Q68: =+O68-P68 -> -118.736 | R68: 189 | S68: =+O68-R68 -> -29 | T68: =+E68+J68+O68 -> 5495.328 | U68: =+F68+K68+P68 -> 4201.229 | V68: =+T68-U68 -> 1294.099 | W68: =+H68+M68+R68 -> 5107 | X68: =+T68-W68 -> 388.328 | AA68: =+Y68-Z68 -> 0 | AB68: 0 | AC68: =+Y68-AB68 -> 0 | AD68: 4544.599 | AE68: =+ｼﾞｭｴﾙｽﾞ!W67/1000 -> 4480.224 | AF68: =+AD68-AE68 -> 64.375 | AG68: 4848 | AH68: =+AD68-AG68 -> -303.401 | AI68: =+Y68+AD68 -> 4544.599 | AJ68: =+Z68+AE68 -> 4480.224 | AK68: =+AI68-AJ68 -> 64.375 | AL68: =+AB68+AG68 -> 4848 | AM68: =+AI68-AL68 -> -303.401 | AN68: 3853.22 | AO68: =+ｶﾞｰﾃﾞﾝ!W67/1000 -> 3911.221 | AP68: =+AN68-AO68 -> -58.001 | AQ68: 3589 | AR68: =+AN68-AQ68 -> 264.22 | AS68: 1920 | AT68: =+ﾋﾞｱｶﾞｰﾃﾞﾝ!W67/1000 -> 2650.353 | AU68: =+AS68-AT68 -> -730.353 | AV68: 1930 | AW68: =+AS68-AV68 -> -10 | AX68: =+AN68+AS68 -> 5773.22 | AY68: =+AO68+AT68 -> 6561.574 | AZ68: =+AX68-AY68 -> -788.354 | BA68: =+AQ68+AV68 -> 5519 | BB68: =+AX68-BA68 -> 254.22 | BC68: 2334.0828 | BD68: =+ブリック!W67/1000 -> 2594.407 | BE68: =+BC68-BD68 -> -260.3242 | BG68: =+BC68-BF68 -> 2334.0828 | BH68: 1808.5031 | BI68: =+ルスツ羊蹄ぶた!W67/1000 -> 922.353 | BJ68: =+BH68-BI68 -> 886.15012 | BL68: =+BH68-BK68 -> 1808.5031 | BM68: =+BC68+BH68 -> 4142.5859 | BN68: =+BD68+BI68 -> 3516.76 | BO68: =+BM68-BN68 -> 625.82592 | BP68: =+BF68+BK68 -> 0 | BQ68: =+BM68-BP68 -> 4142.5859 | BR68: 11.5 | BS68: =+料飲共通!W67/1000 -> 9 | BT68: =+BR68-BS68 -> 2.5 | BU68: 117 | BV68: =+BR68-BU68 -> -105.5 | BW68: =+T68+AI68+AX68+BM68+BR68 -> 19967.233 | BX68: =+U68+AJ68+AY68+BN68+BS68 -> 18768.787 | BY68: =+BW68-BX68 -> 1198.4459 | BZ68: =+W68+AL68+BA68+BU68 -> 15591 | CA68: =+BW68-BZ68 -> 4376.2329
C69: 販売促進費 | E69: 5175.328 | F69: =+ﾇｰﾍﾞﾙﾌﾟｰｽ!W68/1000 -> 3798.322 | G69: =+E69-F69 -> 1377.006 | H69: 4755 | I69: =+E69-H69 -> 420.328 | J69: 160 | K69: =+ｶﾌｪﾙﾎﾟ!W68/1000 -> 124.171 | L69: =+J69-K69 -> 35.829 | M69: 163 | N69: =+J69-M69 -> -3 | O69: 160 | P69: =+ｶﾌｪｾﾚｽﾃ!W68/1000 -> 278.736 | Q69: =+O69-P69 -> -118.736 | R69: 189 | S69: =+O69-R69 -> -29 | T69: =+E69+J69+O69 -> 5495.328 | U69: =+F69+K69+P69 -> 4201.229 | V69: =+T69-U69 -> 1294.099 | W69: =+H69+M69+R69 -> 5107 | X69: =+T69-W69 -> 388.328 | AA69: =+Y69-Z69 -> 0 | AB69: 0 | AC69: =+Y69-AB69 -> 0 | AD69: 4544.599 | AE69: =+ｼﾞｭｴﾙｽﾞ!W68/1000 -> 4480.224 | AF69: =+AD69-AE69 -> 64.375 | AG69: 4848 | AH69: =+AD69-AG69 -> -303.401 | AI69: =+Y69+AD69 -> 4544.599 | AJ69: =+Z69+AE69 -> 4480.224 | AK69: =+AI69-AJ69 -> 64.375 | AL69: =+AB69+AG69 -> 4848 | AM69: =+AI69-AL69 -> -303.401 | AN69: 3853.22 | AO69: =+ｶﾞｰﾃﾞﾝ!W68/1000 -> 3911.221 | AP69: =+AN69-AO69 -> -58.001 | AQ69: 3589 | AR69: =+AN69-AQ69 -> 264.22 | AS69: 1920 | AT69: =+ﾋﾞｱｶﾞｰﾃﾞﾝ!W68/1000 -> 2650.353 | AU69: =+AS69-AT69 -> -730.353 | AV69: 1930 | AW69: =+AS69-AV69 -> -10 | AX69: =+AN69+AS69 -> 5773.22 | AY69: =+AO69+AT69 -> 6561.574 | AZ69: =+AX69-AY69 -> -788.354 | BA69: =+AQ69+AV69 -> 5519 | BB69: =+AX69-BA69 -> 254.22 | BC69: 0 | BD69: =+ブリック!W68/1000 -> 2594.407 | BE69: =+BC69-BD69 -> -2594.407 | BG69: =+BC69-BF69 -> 0 | BH69: 0 | BI69: =+ルスツ羊蹄ぶた!W68/1000 -> 922.353 | BJ69: =+BH69-BI69 -> -922.353 | BL69: =+BH69-BK69 -> 0 | BM69: =+BC69+BH69 -> 0 | BN69: =+BD69+BI69 -> 3516.76 | BO69: =+BM69-BN69 -> -3516.76 | BP69: =+BF69+BK69 -> 0 | BQ69: =+BM69-BP69 -> 0 | BR69: 11.5 | BS69: =+料飲共通!W68/1000 -> 9 | BT69: =+BR69-BS69 -> 2.5 | BU69: 117 | BV69: =+BR69-BU69 -> -105.5 | BW69: =+T69+AI69+AX69+BM69+BR69 -> 15824.647 | BX69: =+U69+AJ69+AY69+BN69+BS69 -> 18768.787 | BY69: =+BW69-BX69 -> -2944.14 | BZ69: =+W69+AL69+BA69+BU69 -> 15591 | CA69: =+BW69-BZ69 -> 233.647
C70: 乗車券販売手数料 | E70: 0 | F70: =+ﾇｰﾍﾞﾙﾌﾟｰｽ!W69/1000 -> 0 | G70: =+E70-F70 -> 0 | H70: 0 | I70: =+E70-H70 -> 0 | J70: 0 | K70: =+ｶﾌｪﾙﾎﾟ!W69/1000 -> 0 | L70: =+J70-K70 -> 0 | M70: 0 | N70: =+J70-M70 -> 0 | O70: 0 | P70: =+ｶﾌｪｾﾚｽﾃ!W69/1000 -> 0 | Q70: =+O70-P70 -> 0 | R70: 0 | S70: =+O70-R70 -> 0 | T70: =+E70+J70+O70 -> 0 | U70: =+F70+K70+P70 -> 0 | V70: =+T70-U70 -> 0 | W70: =+H70+M70+R70 -> 0 | X70: =+T70-W70 -> 0 | AA70: =+Y70-Z70 -> 0 | AB70: 0 | AC70: =+Y70-AB70 -> 0 | AD70: 0 | AE70: =+ｼﾞｭｴﾙｽﾞ!W69/1000 -> 0 | AF70: =+AD70-AE70 -> 0 | AG70: 0 | AH70: =+AD70-AG70 -> 0 | AI70: =+Y70+AD70 -> 0 | AJ70: =+Z70+AE70 -> 0 | AK70: =+AI70-AJ70 -> 0 | AL70: =+AB70+AG70 -> 0 | AM70: =+AI70-AL70 -> 0 | AN70: 0 | AO70: =+ｶﾞｰﾃﾞﾝ!W69/1000 -> 0 | AP70: =+AN70-AO70 -> 0 | AQ70: 0 | AR70: =+AN70-AQ70 -> 0 | AS70: 0 | AT70: =+ﾋﾞｱｶﾞｰﾃﾞﾝ!W69/1000 -> 0 | AU70: =+AS70-AT70 -> 0 | AV70: 0 | AW70: =+AS70-AV70 -> 0 | AX70: =+AN70+AS70 -> 0 | AY70: =+AO70+AT70 -> 0 | AZ70: =+AX70-AY70 -> 0 | BA70: =+AQ70+AV70 -> 0 | BB70: =+AX70-BA70 -> 0 | BC70: 0 | BD70: =+ブリック!W69/1000 -> 0 | BE70: =+BC70-BD70 -> 0 | BG70: =+BC70-BF70 -> 0 | BH70: 0 | BI70: =+ルスツ羊蹄ぶた!W69/1000 -> 0 | BJ70: =+BH70-BI70 -> 0 | BL70: =+BH70-BK70 -> 0 | BM70: =+BC70+BH70 -> 0 | BN70: =+BD70+BI70 -> 0 | BO70: =+BM70-BN70 -> 0 | BP70: =+BF70+BK70 -> 0 | BQ70: =+BM70-BP70 -> 0 | BR70: 0 | BS70: =+料飲共通!W69/1000 -> 0 | BT70: =+BR70-BS70 -> 0 | BU70: 0 | BV70: =+BR70-BU70 -> 0 | BW70: =+T70+AI70+AX70+BM70+BR70 -> 0 | BX70: =+U70+AJ70+AY70+BN70+BS70 -> 0 | BY70: =+BW70-BX70 -> 0 | BZ70: =+W70+AL70+BA70+BU70 -> 0 | CA70: =+BW70-BZ70 -> 0
B71: 旅費交通費 | E71: 250 | F71: =+ﾇｰﾍﾞﾙﾌﾟｰｽ!W70/1000 -> 83.257 | G71: =+E71-F71 -> 166.743 | H71: 77 | I71: =+E71-H71 -> 173 | J71: 0 | K71: =+ｶﾌｪﾙﾎﾟ!W70/1000 -> 0 | L71: =+J71-K71 -> 0 | M71: 0 | N71: =+J71-M71 -> 0 | O71: 0 | P71: =+ｶﾌｪｾﾚｽﾃ!W70/1000 -> 0 | Q71: =+O71-P71 -> 0 | R71: 0 | S71: =+O71-R71 -> 0 | T71: =+E71+J71+O71 -> 250 | U71: =+F71+K71+P71 -> 83.257 | V71: =+T71-U71 -> 166.743 | W71: =+H71+M71+R71 -> 77 | X71: =+T71-W71 -> 173 | AA71: =+Y71-Z71 -> 0 | AB71: 0 | AC71: =+Y71-AB71 -> 0 | AD71: 129 | AE71: =+ｼﾞｭｴﾙｽﾞ!W70/1000 -> 99.83 | AF71: =+AD71-AE71 -> 29.17 | AG71: 177 | AH71: =+AD71-AG71 -> -48 | AI71: =+Y71+AD71 -> 129 | AJ71: =+Z71+AE71 -> 99.83 | AK71: =+AI71-AJ71 -> 29.17 | AL71: =+AB71+AG71 -> 177 | AM71: =+AI71-AL71 -> -48 | AN71: 182.728 | AO71: =+ｶﾞｰﾃﾞﾝ!W70/1000 -> 526.912 | AP71: =+AN71-AO71 -> -344.184 | AQ71: 335 | AR71: =+AN71-AQ71 -> -152.272 | AS71: 0 | AT71: =+ﾋﾞｱｶﾞｰﾃﾞﾝ!W70/1000 -> 0 | AU71: =+AS71-AT71 -> 0 | AV71: 0 | AW71: =+AS71-AV71 -> 0 | AX71: =+AN71+AS71 -> 182.728 | AY71: =+AO71+AT71 -> 526.912 | AZ71: =+AX71-AY71 -> -344.184 | BA71: =+AQ71+AV71 -> 335 | BB71: =+AX71-BA71 -> -152.272 | BC71: 0 | BD71: =+ブリック!W70/1000 -> 8.629 | BE71: =+BC71-BD71 -> -8.629 | BG71: =+BC71-BF71 -> 0 | BH71: 0 | BI71: =+ルスツ羊蹄ぶた!W70/1000 -> 0 | BJ71: =+BH71-BI71 -> 0 | BL71: =+BH71-BK71 -> 0 | BM71: =+BC71+BH71 -> 0 | BN71: =+BD71+BI71 -> 8.629 | BO71: =+BM71-BN71 -> -8.629 | BP71: =+BF71+BK71 -> 0 | BQ71: =+BM71-BP71 -> 0 | BR71: 818 | BS71: =+料飲共通!W70/1000 -> 953.513 | BT71: =+BR71-BS71 -> -135.513 | BU71: 1100 | BV71: =+BR71-BU71 -> -282 | BW71: =+T71+AI71+AX71+BM71+BR71 -> 1379.728 | BX71: =+U71+AJ71+AY71+BN71+BS71 -> 1672.141 | BY71: =+BW71-BX71 -> -292.413 | BZ71: =+W71+AL71+BA71+BU71 -> 1689 | CA71: =+BW71-BZ71 -> -309.272
B72: 通信連絡費 | E72: 362.6 | F72: =+ﾇｰﾍﾞﾙﾌﾟｰｽ!W71/1000 -> 226.107 | G72: =+E72-F72 -> 136.493 | H72: 303 | I72: =+E72-H72 -> 59.6 | J72: 500 | K72: =+ｶﾌｪﾙﾎﾟ!W71/1000 -> 450.1 | L72: =+J72-K72 -> 49.9 | M72: 470 | N72: =+J72-M72 -> 30 | O72: 58.109 | P72: =+ｶﾌｪｾﾚｽﾃ!W71/1000 -> 54.821 | Q72: =+O72-P72 -> 3.288 | R72: 58 | S72: =+O72-R72 -> 0.109 | T72: =+E72+J72+O72 -> 920.709 | U72: =+F72+K72+P72 -> 731.028 | V72: =+T72-U72 -> 189.681 | W72: =+H72+M72+R72 -> 831 | X72: =+T72-W72 -> 89.709 | AA72: =+Y72-Z72 -> 0 | AB72: 0 | AC72: =+Y72-AB72 -> 0 | AD72: 1275.8 | AE72: =+ｼﾞｭｴﾙｽﾞ!W71/1000 -> 1053.705 | AF72: =+AD72-AE72 -> 222.095 | AG72: 1265 | AH72: =+AD72-AG72 -> 10.8 | AI72: =+Y72+AD72 -> 1275.8 | AJ72: =+Z72+AE72 -> 1053.705 | AK72: =+AI72-AJ72 -> 222.095 | AL72: =+AB72+AG72 -> 1265 | AM72: =+AI72-AL72 -> 10.8 | AN72: 808.55 | AO72: =+ｶﾞｰﾃﾞﾝ!W71/1000 -> 608.566 | AP72: =+AN72-AO72 -> 199.984 | AQ72: 814 | AR72: =+AN72-AQ72 -> -5.45 | AS72: 77.764 | AT72: =+ﾋﾞｱｶﾞｰﾃﾞﾝ!W71/1000 -> 83.535 | AU72: =+AS72-AT72 -> -5.771 | AV72: 110 | AW72: =+AS72-AV72 -> -32.236 | AX72: =+AN72+AS72 -> 886.314 | AY72: =+AO72+AT72 -> 692.101 | AZ72: =+AX72-AY72 -> 194.213 | BA72: =+AQ72+AV72 -> 924 | BB72: =+AX72-BA72 -> -37.686 | BC72: 461.89095 | BD72: =+ブリック!W71/1000 -> 462.164 | BE72: =+BC72-BD72 -> -0.27304654 | BG72: =+BC72-BF72 -> 461.89095 | BH72: 196.50123 | BI72: =+ルスツ羊蹄ぶた!W71/1000 -> 304.339 | BJ72: =+BH72-BI72 -> -107.83777 | BL72: =+BH72-BK72 -> 196.50123 | BM72: =+BC72+BH72 -> 658.39218 | BN72: =+BD72+BI72 -> 766.503 | BO72: =+BM72-BN72 -> -108.11082 | BP72: =+BF72+BK72 -> 0 | BQ72: =+BM72-BP72 -> 658.39218 | BR72: 189.6 | BS72: =+料飲共通!W71/1000 -> 391.518 | BT72: =+BR72-BS72 -> -201.918 | BU72: 166 | BV72: =+BR72-BU72 -> 23.6 | BW72: =+T72+AI72+AX72+BM72+BR72 -> 3930.8152 | BX72: =+U72+AJ72+AY72+BN72+BS72 -> 3634.855 | BY72: =+BW72-BX72 -> 295.96018 | BZ72: =+W72+AL72+BA72+BU72 -> 3186 | CA72: =+BW72-BZ72 -> 744.81518
B73: 水道光熱費 | E73: 8670.711 | F73: =+ﾇｰﾍﾞﾙﾌﾟｰｽ!W72/1000 -> 8555.376 | G73: =+E73-F73 -> 115.335 | H73: 8898 | I73: =+E73-H73 -> -227.289 | J73: 1238.495 | K73: =+ｶﾌｪﾙﾎﾟ!W72/1000 -> 1219.935 | L73: =+J73-K73 -> 18.56 | M73: 1271 | N73: =+J73-M73 -> -32.505 | O73: 0 | P73: =+ｶﾌｪｾﾚｽﾃ!W72/1000 -> 0 | Q73: =+O73-P73 -> 0 | R73: 0 | S73: =+O73-R73 -> 0 | T73: =+E73+J73+O73 -> 9909.206 | U73: =+F73+K73+P73 -> 9775.311 | V73: =+T73-U73 -> 133.895 | W73: =+H73+M73+R73 -> 10169 | X73: =+T73-W73 -> -259.794 | AA73: =+Y73-Z73 -> 0 | AB73: 0 | AC73: =+Y73-AB73 -> 0 | AD73: 4240 | AE73: =+ｼﾞｭｴﾙｽﾞ!W72/1000 -> 4247.828 | AF73: =+AD73-AE73 -> -7.828 | AG73: 4129 | AH73: =+AD73-AG73 -> 111 | AI73: =+Y73+AD73 -> 4240 | AJ73: =+Z73+AE73 -> 4247.828 | AK73: =+AI73-AJ73 -> -7.828 | AL73: =+AB73+AG73 -> 4129 | AM73: =+AI73-AL73 -> 111 | AN73: 5040 | AO73: =+ｶﾞｰﾃﾞﾝ!W72/1000 -> 5334.301 | AP73: =+AN73-AO73 -> -294.301 | AQ73: 5512 | AR73: =+AN73-AQ73 -> -472 | AS73: 890 | AT73: =+ﾋﾞｱｶﾞｰﾃﾞﾝ!W72/1000 -> 772.58 | AU73: =+AS73-AT73 -> 117.42 | AV73: 1081 | AW73: =+AS73-AV73 -> -191 | AX73: =+AN73+AS73 -> 5930 | AY73: =+AO73+AT73 -> 6106.881 | AZ73: =+AX73-AY73 -> -176.881 | BA73: =+AQ73+AV73 -> 6593 | BB73: =+AX73-BA73 -> -663 | BC73: 2703.61 | BD73: =+ブリック!W72/1000 -> 2778.719 | BE73: =+BC73-BD73 -> -75.109 | BG73: =+BC73-BF73 -> 2703.61 | BH73: 1457.26 | BI73: =+ルスツ羊蹄ぶた!W72/1000 -> 1664.48 | BJ73: =+BH73-BI73 -> -207.22 | BL73: =+BH73-BK73 -> 1457.26 | BM73: =+BC73+BH73 -> 4160.87 | BN73: =+BD73+BI73 -> 4443.199 | BO73: =+BM73-BN73 -> -282.329 | BP73: =+BF73+BK73 -> 0 | BQ73: =+BM73-BP73 -> 4160.87 | BR73: 0 | BS73: =+料飲共通!W72/1000 -> 0 | BT73: =+BR73-BS73 -> 0 | BU73: 0 | BV73: =+BR73-BU73 -> 0 | BW73: =+T73+AI73+AX73+BM73+BR73 -> 24240.076 | BX73: =+U73+AJ73+AY73+BN73+BS73 -> 24573.219 | BY73: =+BW73-BX73 -> -333.143 | BZ73: =+W73+AL73+BA73+BU73 -> 20891 | CA73: =+BW73-BZ73 -> 3349.076
C74: 電灯使用料 | E74: 4679.99 | F74: =+ﾇｰﾍﾞﾙﾌﾟｰｽ!W73/1000 -> 4842.35 | G74: =+E74-F74 -> -162.36 | H74: 4763 | I74: =+E74-H74 -> -83.01 | J74: 668.571 | K74: =+ｶﾌｪﾙﾎﾟ!W73/1000 -> 691.766 | L74: =+J74-K74 -> -23.195 | M74: 680 | N74: =+J74-M74 -> -11.429 | O74: 0 | P74: =+ｶﾌｪｾﾚｽﾃ!W73/1000 -> 0 | Q74: =+O74-P74 -> 0 | R74: 0 | S74: =+O74-R74 -> 0 | T74: =+E74+J74+O74 -> 5348.561 | U74: =+F74+K74+P74 -> 5534.116 | V74: =+T74-U74 -> -185.555 | W74: =+H74+M74+R74 -> 5443 | X74: =+T74-W74 -> -94.439 | AA74: =+Y74-Z74 -> 0 | AB74: 0 | AC74: =+Y74-AB74 -> 0 | AD74: 3750 | AE74: =+ｼﾞｭｴﾙｽﾞ!W73/1000 -> 3749.251 | AF74: =+AD74-AE74 -> 0.749 | AG74: 3674 | AH74: =+AD74-AG74 -> 76 | AI74: =+Y74+AD74 -> 3750 | AJ74: =+Z74+AE74 -> 3749.251 | AK74: =+AI74-AJ74 -> 0.749 | AL74: =+AB74+AG74 -> 3674 | AM74: =+AI74-AL74 -> 76 | AN74: 3600 | AO74: =+ｶﾞｰﾃﾞﾝ!W73/1000 -> 3685.204 | AP74: =+AN74-AO74 -> -85.204 | AQ74: 3724 | AR74: =+AN74-AQ74 -> -124 | AS74: 525 | AT74: =+ﾋﾞｱｶﾞｰﾃﾞﾝ!W73/1000 -> 542.983 | AU74: =+AS74-AT74 -> -17.983 | AV74: 690 | AW74: =+AS74-AV74 -> -165 | AX74: =+AN74+AS74 -> 4125 | AY74: =+AO74+AT74 -> 4228.187 | AZ74: =+AX74-AY74 -> -103.187 | BA74: =+AQ74+AV74 -> 4414 | BB74: =+AX74-BA74 -> -289 | BC74: 0 | BD74: =+ブリック!W73/1000 -> 481.495 | BE74: =+BC74-BD74 -> -481.495 | BG74: =+BC74-BF74 -> 0 | BH74: 0 | BI74: =+ルスツ羊蹄ぶた!W73/1000 -> 365.297 | BJ74: =+BH74-BI74 -> -365.297 | BL74: =+BH74-BK74 -> 0 | BM74: =+BC74+BH74 -> 0 | BN74: =+BD74+BI74 -> 846.792 | BO74: =+BM74-BN74 -> -846.792 | BP74: =+BF74+BK74 -> 0 | BQ74: =+BM74-BP74 -> 0 | BR74: 0 | BS74: =+料飲共通!W73/1000 -> 0 | BT74: =+BR74-BS74 -> 0 | BU74: 0 | BV74: =+BR74-BU74 -> 0 | BW74: =+T74+AI74+AX74+BM74+BR74 -> 13223.561 | BX74: =+U74+AJ74+AY74+BN74+BS74 -> 14358.346 | BY74: =+BW74-BX74 -> -1134.785 | BZ74: =+W74+AL74+BA74+BU74 -> 13531 | CA74: =+BW74-BZ74 -> -307.439
C75: 水道使用料 | E75: 549.415 | F75: =+ﾇｰﾍﾞﾙﾌﾟｰｽ!W74/1000 -> 567.408 | G75: =+E75-F75 -> -17.993 | H75: 575 | I75: =+E75-H75 -> -25.585 | J75: 78.299 | K75: =+ｶﾌｪﾙﾎﾟ!W74/1000 -> 78.789 | L75: =+J75-K75 -> -0.49 | M75: 82 | N75: =+J75-M75 -> -3.701 | O75: 0 | P75: =+ｶﾌｪｾﾚｽﾃ!W74/1000 -> 0 | Q75: =+O75-P75 -> 0 | R75: 0 | S75: =+O75-R75 -> 0 | T75: =+E75+J75+O75 -> 627.714 | U75: =+F75+K75+P75 -> 646.197 | V75: =+T75-U75 -> -18.483 | W75: =+H75+M75+R75 -> 657 | X75: =+T75-W75 -> -29.286 | AA75: =+Y75-Z75 -> 0 | AB75: 0 | AC75: =+Y75-AB75 -> 0 | AD75: 490 | AE75: =+ｼﾞｭｴﾙｽﾞ!W74/1000 -> 498.577 | AF75: =+AD75-AE75 -> -8.577 | AG75: 455 | AH75: =+AD75-AG75 -> 35 | AI75: =+Y75+AD75 -> 490 | AJ75: =+Z75+AE75 -> 498.577 | AK75: =+AI75-AJ75 -> -8.577 | AL75: =+AB75+AG75 -> 455 | AM75: =+AI75-AL75 -> 35 | AN75: 720 | AO75: =+ｶﾞｰﾃﾞﾝ!W74/1000 -> 637.32 | AP75: =+AN75-AO75 -> 82.68 | AQ75: 742 | AR75: =+AN75-AQ75 -> -22 | AS75: 215 | AT75: =+ﾋﾞｱｶﾞｰﾃﾞﾝ!W74/1000 -> 229.597 | AU75: =+AS75-AT75 -> -14.597 | AV75: 247 | AW75: =+AS75-AV75 -> -32 | AX75: =+AN75+AS75 -> 935 | AY75: =+AO75+AT75 -> 866.917 | AZ75: =+AX75-AY75 -> 68.083 | BA75: =+AQ75+AV75 -> 989 | BB75: =+AX75-BA75 -> -54 | BC75: 0 | BD75: =+ブリック!W74/1000 -> 268 | BE75: =+BC75-BD75 -> -268 | BG75: =+BC75-BF75 -> 0 | BH75: 0 | BI75: =+ルスツ羊蹄ぶた!W74/1000 -> 369.4 | BJ75: =+BH75-BI75 -> -369.4 | BL75: =+BH75-BK75 -> 0 | BM75: =+BC75+BH75 -> 0 | BN75: =+BD75+BI75 -> 637.4 | BO75: =+BM75-BN75 -> -637.4 | BP75: =+BF75+BK75 -> 0 | BQ75: =+BM75-BP75 -> 0 | BR75: 0 | BS75: =+料飲共通!W74/1000 -> 0 | BT75: =+BR75-BS75 -> 0 | BU75: 0 | BV75: =+BR75-BU75 -> 0 | BW75: =+T75+AI75+AX75+BM75+BR75 -> 2052.714 | BX75: =+U75+AJ75+AY75+BN75+BS75 -> 2649.091 | BY75: =+BW75-BX75 -> -596.377 | BZ75: =+W75+AL75+BA75+BU75 -> 2101 | CA75: =+BW75-BZ75 -> -48.286
C76: ガス使用料 | E76: 3441.306 | F76: =+ﾇｰﾍﾞﾙﾌﾟｰｽ!W75/1000 -> 3145.618 | G76: =+E76-F76 -> 295.688 | H76: 3560 | I76: =+E76-H76 -> -118.694 | J76: 491.625 | K76: =+ｶﾌｪﾙﾎﾟ!W75/1000 -> 449.38 | L76: =+J76-K76 -> 42.245 | M76: 509 | N76: =+J76-M76 -> -17.375 | O76: 0 | P76: =+ｶﾌｪｾﾚｽﾃ!W75/1000 -> 0 | Q76: =+O76-P76 -> 0 | R76: 0 | S76: =+O76-R76 -> 0 | T76: =+E76+J76+O76 -> 3932.931 | U76: =+F76+K76+P76 -> 3594.998 | V76: =+T76-U76 -> 337.933 | W76: =+H76+M76+R76 -> 4069 | X76: =+T76-W76 -> -136.069 | AA76: =+Y76-Z76 -> 0 | AB76: 0 | AC76: =+Y76-AB76 -> 0 | AD76: 0 | AE76: =+ｼﾞｭｴﾙｽﾞ!W75/1000 -> 0 | AF76: =+AD76-AE76 -> 0 | AG76: 0 | AH76: =+AD76-AG76 -> 0 | AI76: =+Y76+AD76 -> 0 | AJ76: =+Z76+AE76 -> 0 | AK76: =+AI76-AJ76 -> 0 | AL76: =+AB76+AG76 -> 0 | AM76: =+AI76-AL76 -> 0 | AN76: 720 | AO76: =+ｶﾞｰﾃﾞﾝ!W75/1000 -> 1011.777 | AP76: =+AN76-AO76 -> -291.777 | AQ76: 1046 | AR76: =+AN76-AQ76 -> -326 | AS76: 150 | AT76: =+ﾋﾞｱｶﾞｰﾃﾞﾝ!W75/1000 -> 0 | AU76: =+AS76-AT76 -> 150 | AV76: 138 | AW76: =+AS76-AV76 -> 12 | AX76: =+AN76+AS76 -> 870 | AY76: =+AO76+AT76 -> 1011.777 | AZ76: =+AX76-AY76 -> -141.777 | BA76: =+AQ76+AV76 -> 1184 | BB76: =+AX76-BA76 -> -314 | BC76: 0 | BD76: =+ブリック!W75/1000 -> 576.898 | BE76: =+BC76-BD76 -> -576.898 | BG76: =+BC76-BF76 -> 0 | BH76: 0 | BI76: =+ルスツ羊蹄ぶた!W75/1000 -> 689.256 | BJ76: =+BH76-BI76 -> -689.256 | BL76: =+BH76-BK76 -> 0 | BM76: =+BC76+BH76 -> 0 | BN76: =+BD76+BI76 -> 1266.154 | BO76: =+BM76-BN76 -> -1266.154 | BP76: =+BF76+BK76 -> 0 | BQ76: =+BM76-BP76 -> 0 | BR76: 0 | BS76: =+料飲共通!W75/1000 -> 0 | BT76: =+BR76-BS76 -> 0 | BU76: 0 | BV76: =+BR76-BU76 -> 0 | BW76: =+T76+AI76+AX76+BM76+BR76 -> 4802.931 | BX76: =+U76+AJ76+AY76+BN76+BS76 -> 5872.929 | BY76: =+BW76-BX76 -> -1069.998 | BZ76: =+W76+AL76+BA76+BU76 -> 5253 | CA76: =+BW76-BZ76 -> -450.069
C77: 暖房燃料費 | E77: 0 | F77: =+ﾇｰﾍﾞﾙﾌﾟｰｽ!W76/1000 -> 0 | G77: =+E77-F77 -> 0 | H77: 0 | I77: =+E77-H77 -> 0 | J77: 0 | K77: =+ｶﾌｪﾙﾎﾟ!W76/1000 -> 0 | L77: =+J77-K77 -> 0 | M77: 0 | N77: =+J77-M77 -> 0 | O77: 0 | P77: =+ｶﾌｪｾﾚｽﾃ!W76/1000 -> 0 | Q77: =+O77-P77 -> 0 | R77: 0 | S77: =+O77-R77 -> 0 | T77: =+E77+J77+O77 -> 0 | U77: =+F77+K77+P77 -> 0 | V77: =+T77-U77 -> 0 | W77: =+H77+M77+R77 -> 0 | X77: =+T77-W77 -> 0 | AA77: =+Y77-Z77 -> 0 | AB77: 0 | AC77: =+Y77-AB77 -> 0 | AD77: 0 | AE77: =+ｼﾞｭｴﾙｽﾞ!W76/1000 -> 0 | AF77: =+AD77-AE77 -> 0 | AG77: 0 | AH77: =+AD77-AG77 -> 0 | AI77: =+Y77+AD77 -> 0 | AJ77: =+Z77+AE77 -> 0 | AK77: =+AI77-AJ77 -> 0 | AL77: =+AB77+AG77 -> 0 | AM77: =+AI77-AL77 -> 0 | AN77: 0 | AO77: =+ｶﾞｰﾃﾞﾝ!W76/1000 -> 0 | AP77: =+AN77-AO77 -> 0 | AQ77: 0 | AR77: =+AN77-AQ77 -> 0 | AS77: 0 | AT77: =+ﾋﾞｱｶﾞｰﾃﾞﾝ!W76/1000 -> 0 | AU77: =+AS77-AT77 -> 0 | AV77: 6 | AW77: =+AS77-AV77 -> -6 | AX77: =+AN77+AS77 -> 0 | AY77: =+AO77+AT77 -> 0 | AZ77: =+AX77-AY77 -> 0 | BA77: =+AQ77+AV77 -> 6 | BB77: =+AX77-BA77 -> -6 | BC77: 0 | BD77: =+ブリック!W76/1000 -> 0 | BE77: =+BC77-BD77 -> 0 | BG77: =+BC77-BF77 -> 0 | BH77: 0 | BI77: =+ルスツ羊蹄ぶた!W76/1000 -> 0 | BJ77: =+BH77-BI77 -> 0 | BL77: =+BH77-BK77 -> 0 | BM77: =+BC77+BH77 -> 0 | BN77: =+BD77+BI77 -> 0 | BO77: =+BM77-BN77 -> 0 | BP77: =+BF77+BK77 -> 0 | BQ77: =+BM77-BP77 -> 0 | BR77: 0 | BS77: =+料飲共通!W76/1000 -> 0 | BT77: =+BR77-BS77 -> 0 | BU77: 0 | BV77: =+BR77-BU77 -> 0 | BW77: =+T77+AI77+AX77+BM77+BR77 -> 0 | BX77: =+U77+AJ77+AY77+BN77+BS77 -> 0 | BY77: =+BW77-BX77 -> 0 | BZ77: =+W77+AL77+BA77+BU77 -> 6 | CA77: =+BW77-BZ77 -> -6
C78: 電力使用料 | E78: 0 | F78: =+ﾇｰﾍﾞﾙﾌﾟｰｽ!W77/1000 -> 0 | G78: =+E78-F78 -> 0 | H78: 0 | I78: =+E78-H78 -> 0 | J78: 0 | K78: =+ｶﾌｪﾙﾎﾟ!W77/1000 -> 0 | L78: =+J78-K78 -> 0 | M78: 0 | N78: =+J78-M78 -> 0 | O78: 0 | P78: =+ｶﾌｪｾﾚｽﾃ!W77/1000 -> 0 | Q78: =+O78-P78 -> 0 | R78: 0 | S78: =+O78-R78 -> 0 | T78: =+E78+J78+O78 -> 0 | U78: =+F78+K78+P78 -> 0 | V78: =+T78-U78 -> 0 | W78: =+H78+M78+R78 -> 0 | X78: =+T78-W78 -> 0 | AA78: =+Y78-Z78 -> 0 | AB78: 0 | AC78: =+Y78-AB78 -> 0 | AD78: 0 | AE78: =+ｼﾞｭｴﾙｽﾞ!W77/1000 -> 0 | AF78: =+AD78-AE78 -> 0 | AG78: 0 | AH78: =+AD78-AG78 -> 0 | AI78: =+Y78+AD78 -> 0 | AJ78: =+Z78+AE78 -> 0 | AK78: =+AI78-AJ78 -> 0 | AL78: =+AB78+AG78 -> 0 | AM78: =+AI78-AL78 -> 0 | AN78: 0 | AO78: =+ｶﾞｰﾃﾞﾝ!W77/1000 -> 0 | AP78: =+AN78-AO78 -> 0 | AQ78: 0 | AR78: =+AN78-AQ78 -> 0 | AS78: 0 | AT78: =+ﾋﾞｱｶﾞｰﾃﾞﾝ!W77/1000 -> 0 | AU78: =+AS78-AT78 -> 0 | AV78: 0 | AW78: =+AS78-AV78 -> 0 | AX78: =+AN78+AS78 -> 0 | AY78: =+AO78+AT78 -> 0 | AZ78: =+AX78-AY78 -> 0 | BA78: =+AQ78+AV78 -> 0 | BB78: =+AX78-BA78 -> 0 | BC78: 0 | BD78: =+ブリック!W77/1000 -> 1452.326 | BE78: =+BC78-BD78 -> -1452.326 | BG78: =+BC78-BF78 -> 0 | BH78: 0 | BI78: =+ルスツ羊蹄ぶた!W77/1000 -> 240.527 | BJ78: =+BH78-BI78 -> -240.527 | BL78: =+BH78-BK78 -> 0 | BM78: =+BC78+BH78 -> 0 | BN78: =+BD78+BI78 -> 1692.853 | BO78: =+BM78-BN78 -> -1692.853 | BP78: =+BF78+BK78 -> 0 | BQ78: =+BM78-BP78 -> 0 | BR78: 0 | BS78: =+料飲共通!W77/1000 -> 0 | BT78: =+BR78-BS78 -> 0 | BU78: 0 | BV78: =+BR78-BU78 -> 0 | BW78: =+T78+AI78+AX78+BM78+BR78 -> 0 | BX78: =+U78+AJ78+AY78+BN78+BS78 -> 1692.853 | BY78: =+BW78-BX78 -> -1692.853 | BZ78: =+W78+AL78+BA78+BU78 -> 0 | CA78: =+BW78-BZ78 -> 0
B79: 諸手数料 | E79: 29.716 | F79: =+ﾇｰﾍﾞﾙﾌﾟｰｽ!W78/1000 -> 0.833 | G79: =+E79-F79 -> 28.883 | H79: 23 | I79: =+E79-H79 -> 6.716 | J79: 0 | K79: =+ｶﾌｪﾙﾎﾟ!W78/1000 -> 0 | L79: =+J79-K79 -> 0 | M79: 0 | N79: =+J79-M79 -> 0 | O79: 0 | P79: =+ｶﾌｪｾﾚｽﾃ!W78/1000 -> 0 | Q79: =+O79-P79 -> 0 | R79: 0 | S79: =+O79-R79 -> 0 | T79: =+E79+J79+O79 -> 29.716 | U79: =+F79+K79+P79 -> 0.833 | V79: =+T79-U79 -> 28.883 | W79: =+H79+M79+R79 -> 23 | X79: =+T79-W79 -> 6.716 | AA79: =+Y79-Z79 -> 0 | AB79: 0 | AC79: =+Y79-AB79 -> 0 | AD79: 18 | AE79: =+ｼﾞｭｴﾙｽﾞ!W78/1000 -> 11.186 | AF79: =+AD79-AE79 -> 6.814 | AG79: 18 | AH79: =+AD79-AG79 -> 0 | AI79: =+Y79+AD79 -> 18 | AJ79: =+Z79+AE79 -> 11.186 | AK79: =+AI79-AJ79 -> 6.814 | AL79: =+AB79+AG79 -> 18 | AM79: =+AI79-AL79 -> 0 | AN79: 42 | AO79: =+ｶﾞｰﾃﾞﾝ!W78/1000 -> 30.089 | AP79: =+AN79-AO79 -> 11.911 | AQ79: 32 | AR79: =+AN79-AQ79 -> 10 | AS79: 17.7 | AT79: =+ﾋﾞｱｶﾞｰﾃﾞﾝ!W78/1000 -> 16.11 | AU79: =+AS79-AT79 -> 1.59 | AV79: 0 | AW79: =+AS79-AV79 -> 17.7 | AX79: =+AN79+AS79 -> 59.7 | AY79: =+AO79+AT79 -> 46.199 | AZ79: =+AX79-AY79 -> 13.501 | BA79: =+AQ79+AV79 -> 32 | BB79: =+AX79-BA79 -> 27.7 | BC79: 17.261582 | BD79: =+ブリック!W78/1000 -> 849.572 | BE79: =+BC79-BD79 -> -832.31042 | BG79: =+BC79-BF79 -> 17.261582 | BH79: 0 | BI79: =+ルスツ羊蹄ぶた!W78/1000 -> 685.78 | BJ79: =+BH79-BI79 -> -685.78 | BL79: =+BH79-BK79 -> 0 | BM79: =+BC79+BH79 -> 17.261582 | BN79: =+BD79+BI79 -> 1535.352 | BO79: =+BM79-BN79 -> -1518.0904 | BP79: =+BF79+BK79 -> 0 | BQ79: =+BM79-BP79 -> 17.261582 | BR79: 0 | BS79: =+料飲共通!W78/1000 -> 0 | BT79: =+BR79-BS79 -> 0 | BU79: 0 | BV79: =+BR79-BU79 -> 0 | BW79: =+T79+AI79+AX79+BM79+BR79 -> 124.67758 | BX79: =+U79+AJ79+AY79+BN79+BS79 -> 1593.57 | BY79: =+BW79-BX79 -> -1468.8924 | BZ79: =+W79+AL79+BA79+BU79 -> 73 | CA79: =+BW79-BZ79 -> 51.677582
B80: 広告宣伝費 | E80: 2420 | F80: =+ﾇｰﾍﾞﾙﾌﾟｰｽ!W79/1000 -> 1330 | G80: =+E80-F80 -> 1090 | H80: 1907 | I80: =+E80-H80 -> 513 | J80: 70 | K80: =+ｶﾌｪﾙﾎﾟ!W79/1000 -> 0 | L80: =+J80-K80 -> 70 | M80: 68 | N80: =+J80-M80 -> 2 | O80: 0 | P80: =+ｶﾌｪｾﾚｽﾃ!W79/1000 -> 0 | Q80: =+O80-P80 -> 0 | R80: 0 | S80: =+O80-R80 -> 0 | T80: =+E80+J80+O80 -> 2490 | U80: =+F80+K80+P80 -> 1330 | V80: =+T80-U80 -> 1160 | W80: =+H80+M80+R80 -> 1975 | X80: =+T80-W80 -> 515 | AA80: =+Y80-Z80 -> 0 | AB80: 0 | AC80: =+Y80-AB80 -> 0 | AD80: 2420 | AE80: =+ｼﾞｭｴﾙｽﾞ!W79/1000 -> 1073.5 | AF80: =+AD80-AE80 -> 1346.5 | AG80: 2223 | AH80: =+AD80-AG80 -> 197 | AI80: =+Y80+AD80 -> 2420 | AJ80: =+Z80+AE80 -> 1073.5 | AK80: =+AI80-AJ80 -> 1346.5 | AL80: =+AB80+AG80 -> 2223 | AM80: =+AI80-AL80 -> 197 | AN80: 2480 | AO80: =+ｶﾞｰﾃﾞﾝ!W79/1000 -> 1270.8 | AP80: =+AN80-AO80 -> 1209.2 | AQ80: 1361 | AR80: =+AN80-AQ80 -> 1119 | AS80: 1850 | AT80: =+ﾋﾞｱｶﾞｰﾃﾞﾝ!W79/1000 -> 145 | AU80: =+AS80-AT80 -> 1705 | AV80: 785 | AW80: =+AS80-AV80 -> 1065 | AX80: =+AN80+AS80 -> 4330 | AY80: =+AO80+AT80 -> 1415.8 | AZ80: =+AX80-AY80 -> 2914.2 | BA80: =+AQ80+AV80 -> 2146 | BB80: =+AX80-BA80 -> 2184 | BC80: 0 | BD80: =+ブリック!W79/1000 -> 2557 | BE80: =+BC80-BD80 -> -2557 | BG80: =+BC80-BF80 -> 0 | BH80: 0 | BI80: =+ルスツ羊蹄ぶた!W79/1000 -> 542.5 | BJ80: =+BH80-BI80 -> -542.5 | BL80: =+BH80-BK80 -> 0 | BM80: =+BC80+BH80 -> 0 | BN80: =+BD80+BI80 -> 3099.5 | BO80: =+BM80-BN80 -> -3099.5 | BP80: =+BF80+BK80 -> 0 | BQ80: =+BM80-BP80 -> 0 | BR80: 400 | BS80: =+料飲共通!W79/1000 -> 1071.7 | BT80: =+BR80-BS80 -> -671.7 | BU80: 4475 | BV80: =+BR80-BU80 -> -4075 | BW80: =+T80+AI80+AX80+BM80+BR80 -> 9640 | BX80: =+U80+AJ80+AY80+BN80+BS80 -> 7990.5 | BY80: =+BW80-BX80 -> 1649.5 | BZ80: =+W80+AL80+BA80+BU80 -> 10819 | CA80: =+BW80-BZ80 -> -1179
B81: 交際費 | E81: 0 | F81: =+ﾇｰﾍﾞﾙﾌﾟｰｽ!W80/1000 -> 0 | G81: =+E81-F81 -> 0 | H81: 0 | I81: =+E81-H81 -> 0 | J81: 0 | K81: =+ｶﾌｪﾙﾎﾟ!W80/1000 -> 0 | L81: =+J81-K81 -> 0 | M81: 0 | N81: =+J81-M81 -> 0 | O81: 0 | P81: =+ｶﾌｪｾﾚｽﾃ!W80/1000 -> 0 | Q81: =+O81-P81 -> 0 | R81: 0 | S81: =+O81-R81 -> 0 | T81: =+E81+J81+O81 -> 0 | U81: =+F81+K81+P81 -> 0 | V81: =+T81-U81 -> 0 | W81: =+H81+M81+R81 -> 0 | X81: =+T81-W81 -> 0 | AA81: =+Y81-Z81 -> 0 | AB81: 0 | AC81: =+Y81-AB81 -> 0 | AD81: 0 | AE81: =+ｼﾞｭｴﾙｽﾞ!W80/1000 -> 0 | AF81: =+AD81-AE81 -> 0 | AG81: 3 | AH81: =+AD81-AG81 -> -3 | AI81: =+Y81+AD81 -> 0 | AJ81: =+Z81+AE81 -> 0 | AK81: =+AI81-AJ81 -> 0 | AL81: =+AB81+AG81 -> 3 | AM81: =+AI81-AL81 -> -3 | AN81: 0 | AO81: =+ｶﾞｰﾃﾞﾝ!W80/1000 -> 0 | AP81: =+AN81-AO81 -> 0 | AQ81: 0 | AR81: =+AN81-AQ81 -> 0 | AS81: 0 | AT81: =+ﾋﾞｱｶﾞｰﾃﾞﾝ!W80/1000 -> 0 | AU81: =+AS81-AT81 -> 0 | AV81: 0 | AW81: =+AS81-AV81 -> 0 | AX81: =+AN81+AS81 -> 0 | AY81: =+AO81+AT81 -> 0 | AZ81: =+AX81-AY81 -> 0 | BA81: =+AQ81+AV81 -> 0 | BB81: =+AX81-BA81 -> 0 | BC81: 0 | BD81: =+ブリック!W80/1000 -> 0 | BE81: =+BC81-BD81 -> 0 | BG81: =+BC81-BF81 -> 0 | BH81: 0 | BI81: =+ルスツ羊蹄ぶた!W80/1000 -> 0 | BJ81: =+BH81-BI81 -> 0 | BL81: =+BH81-BK81 -> 0 | BM81: =+BC81+BH81 -> 0 | BN81: =+BD81+BI81 -> 0 | BO81: =+BM81-BN81 -> 0 | BP81: =+BF81+BK81 -> 0 | BQ81: =+BM81-BP81 -> 0 | BR81: 40 | BS81: =+料飲共通!W80/1000 -> 2.149 | BT81: =+BR81-BS81 -> 37.851 | BU81: 774 | BV81: =+BR81-BU81 -> -734 | BW81: =+T81+AI81+AX81+BM81+BR81 -> 40 | BX81: =+U81+AJ81+AY81+BN81+BS81 -> 2.149 | BY81: =+BW81-BX81 -> 37.851 | BZ81: =+W81+AL81+BA81+BU81 -> 777 | CA81: =+BW81-BZ81 -> -737
C82: 接待交際費 | E82: 0 | F82: =+ﾇｰﾍﾞﾙﾌﾟｰｽ!W81/1000 -> 0 | G82: =+E82-F82 -> 0 | H82: 0 | I82: =+E82-H82 -> 0 | J82: 0 | K82: =+ｶﾌｪﾙﾎﾟ!W81/1000 -> 0 | L82: =+J82-K82 -> 0 | M82: 0 | N82: =+J82-M82 -> 0 | O82: 0 | P82: =+ｶﾌｪｾﾚｽﾃ!W81/1000 -> 0 | Q82: =+O82-P82 -> 0 | R82: 0 | S82: =+O82-R82 -> 0 | T82: =+E82+J82+O82 -> 0 | U82: =+F82+K82+P82 -> 0 | V82: =+T82-U82 -> 0 | W82: =+H82+M82+R82 -> 0 | X82: =+T82-W82 -> 0 | AA82: =+Y82-Z82 -> 0 | AB82: 0 | AC82: =+Y82-AB82 -> 0 | AD82: 0 | AE82: =+ｼﾞｭｴﾙｽﾞ!W81/1000 -> 0 | AF82: =+AD82-AE82 -> 0 | AG82: 0 | AH82: =+AD82-AG82 -> 0 | AI82: =+Y82+AD82 -> 0 | AJ82: =+Z82+AE82 -> 0 | AK82: =+AI82-AJ82 -> 0 | AL82: =+AB82+AG82 -> 0 | AM82: =+AI82-AL82 -> 0 | AN82: 0 | AO82: =+ｶﾞｰﾃﾞﾝ!W81/1000 -> 0 | AP82: =+AN82-AO82 -> 0 | AQ82: 0 | AR82: =+AN82-AQ82 -> 0 | AS82: 0 | AT82: =+ﾋﾞｱｶﾞｰﾃﾞﾝ!W81/1000 -> 0 | AU82: =+AS82-AT82 -> 0 | AV82: 0 | AW82: =+AS82-AV82 -> 0 | AX82: =+AN82+AS82 -> 0 | AY82: =+AO82+AT82 -> 0 | AZ82: =+AX82-AY82 -> 0 | BA82: =+AQ82+AV82 -> 0 | BB82: =+AX82-BA82 -> 0 | BC82: 0 | BD82: =+ブリック!W81/1000 -> 0 | BE82: =+BC82-BD82 -> 0 | BG82: =+BC82-BF82 -> 0 | BH82: 0 | BI82: =+ルスツ羊蹄ぶた!W81/1000 -> 0 | BJ82: =+BH82-BI82 -> 0 | BL82: =+BH82-BK82 -> 0 | BM82: =+BC82+BH82 -> 0 | BN82: =+BD82+BI82 -> 0 | BO82: =+BM82-BN82 -> 0 | BP82: =+BF82+BK82 -> 0 | BQ82: =+BM82-BP82 -> 0 | BR82: 40 | BS82: =+料飲共通!W81/1000 -> 2.149 | BT82: =+BR82-BS82 -> 37.851 | BU82: 774 | BV82: =+BR82-BU82 -> -734 | BW82: =+T82+AI82+AX82+BM82+BR82 -> 40 | BX82: =+U82+AJ82+AY82+BN82+BS82 -> 2.149 | BY82: =+BW82-BX82 -> 37.851 | BZ82: =+W82+AL82+BA82+BU82 -> 774 | CA82: =+BW82-BZ82 -> -734
C83: 贈答用品費 | E83: 0 | F83: =+ﾇｰﾍﾞﾙﾌﾟｰｽ!W82/1000 -> 0 | G83: =+E83-F83 -> 0 | H83: 0 | I83: =+E83-H83 -> 0 | J83: 0 | K83: =+ｶﾌｪﾙﾎﾟ!W82/1000 -> 0 | L83: =+J83-K83 -> 0 | M83: 0 | N83: =+J83-M83 -> 0 | O83: 0 | P83: =+ｶﾌｪｾﾚｽﾃ!W82/1000 -> 0 | Q83: =+O83-P83 -> 0 | R83: 0 | S83: =+O83-R83 -> 0 | T83: =+E83+J83+O83 -> 0 | U83: =+F83+K83+P83 -> 0 | V83: =+T83-U83 -> 0 | W83: =+H83+M83+R83 -> 0 | X83: =+T83-W83 -> 0 | AA83: =+Y83-Z83 -> 0 | AB83: 0 | AC83: =+Y83-AB83 -> 0 | AD83: 0 | AE83: =+ｼﾞｭｴﾙｽﾞ!W82/1000 -> 0 | AF83: =+AD83-AE83 -> 0 | AG83: 3 | AH83: =+AD83-AG83 -> -3 | AI83: =+Y83+AD83 -> 0 | AJ83: =+Z83+AE83 -> 0 | AK83: =+AI83-AJ83 -> 0 | AL83: =+AB83+AG83 -> 3 | AM83: =+AI83-AL83 -> -3 | AN83: 0 | AO83: =+ｶﾞｰﾃﾞﾝ!W82/1000 -> 0 | AP83: =+AN83-AO83 -> 0 | AQ83: 0 | AR83: =+AN83-AQ83 -> 0 | AS83: 0 | AT83: =+ﾋﾞｱｶﾞｰﾃﾞﾝ!W82/1000 -> 0 | AU83: =+AS83-AT83 -> 0 | AV83: 0 | AW83: =+AS83-AV83 -> 0 | AX83: =+AN83+AS83 -> 0 | AY83: =+AO83+AT83 -> 0 | AZ83: =+AX83-AY83 -> 0 | BA83: =+AQ83+AV83 -> 0 | BB83: =+AX83-BA83 -> 0 | BC83: 0 | BD83: =+ブリック!W82/1000 -> 0 | BE83: =+BC83-BD83 -> 0 | BG83: =+BC83-BF83 -> 0 | BH83: 0 | BI83: =+ルスツ羊蹄ぶた!W82/1000 -> 0 | BJ83: =+BH83-BI83 -> 0 | BL83: =+BH83-BK83 -> 0 | BM83: =+BC83+BH83 -> 0 | BN83: =+BD83+BI83 -> 0 | BO83: =+BM83-BN83 -> 0 | BP83: =+BF83+BK83 -> 0 | BQ83: =+BM83-BP83 -> 0 | BR83: 0 | BS83: =+料飲共通!W82/1000 -> 0 | BT83: =+BR83-BS83 -> 0 | BU83: 0 | BV83: =+BR83-BU83 -> 0 | BW83: =+T83+AI83+AX83+BM83+BR83 -> 0 | BX83: =+U83+AJ83+AY83+BN83+BS83 -> 0 | BY83: =+BW83-BX83 -> 0 | BZ83: =+W83+AL83+BA83+BU83 -> 3 | CA83: =+BW83-BZ83 -> -3
B84: 寄付金 | E84: 0 | F84: =+ﾇｰﾍﾞﾙﾌﾟｰｽ!W83/1000 -> 0 | G84: =+E84-F84 -> 0 | H84: 0 | I84: =+E84-H84 -> 0 | J84: 0 | K84: =+ｶﾌｪﾙﾎﾟ!W83/1000 -> 0 | L84: =+J84-K84 -> 0 | M84: 0 | N84: =+J84-M84 -> 0 | O84: 0 | P84: =+ｶﾌｪｾﾚｽﾃ!W83/1000 -> 0 | Q84: =+O84-P84 -> 0 | R84: 0 | S84: =+O84-R84 -> 0 | T84: =+E84+J84+O84 -> 0 | U84: =+F84+K84+P84 -> 0 | V84: =+T84-U84 -> 0 | W84: =+H84+M84+R84 -> 0 | X84: =+T84-W84 -> 0 | AA84: =+Y84-Z84 -> 0 | AB84: 0 | AC84: =+Y84-AB84 -> 0 | AD84: 0 | AE84: =+ｼﾞｭｴﾙｽﾞ!W83/1000 -> 0 | AF84: =+AD84-AE84 -> 0 | AG84: 0 | AH84: =+AD84-AG84 -> 0 | AI84: =+Y84+AD84 -> 0 | AJ84: =+Z84+AE84 -> 0 | AK84: =+AI84-AJ84 -> 0 | AL84: =+AB84+AG84 -> 0 | AM84: =+AI84-AL84 -> 0 | AN84: 0 | AO84: =+ｶﾞｰﾃﾞﾝ!W83/1000 -> 0 | AP84: =+AN84-AO84 -> 0 | AQ84: 0 | AR84: =+AN84-AQ84 -> 0 | AS84: 0 | AT84: =+ﾋﾞｱｶﾞｰﾃﾞﾝ!W83/1000 -> 0 | AU84: =+AS84-AT84 -> 0 | AV84: 0 | AW84: =+AS84-AV84 -> 0 | AX84: =+AN84+AS84 -> 0 | AY84: =+AO84+AT84 -> 0 | AZ84: =+AX84-AY84 -> 0 | BA84: =+AQ84+AV84 -> 0 | BB84: =+AX84-BA84 -> 0 | BC84: 0 | BD84: =+ブリック!W83/1000 -> 0 | BE84: =+BC84-BD84 -> 0 | BG84: =+BC84-BF84 -> 0 | BH84: 0 | BI84: =+ルスツ羊蹄ぶた!W83/1000 -> 0 | BJ84: =+BH84-BI84 -> 0 | BL84: =+BH84-BK84 -> 0 | BM84: =+BC84+BH84 -> 0 | BN84: =+BD84+BI84 -> 0 | BO84: =+BM84-BN84 -> 0 | BP84: =+BF84+BK84 -> 0 | BQ84: =+BM84-BP84 -> 0 | BR84: 0 | BS84: =+料飲共通!W83/1000 -> 0 | BT84: =+BR84-BS84 -> 0 | BU84: 0 | BV84: =+BR84-BU84 -> 0 | BW84: =+T84+AI84+AX84+BM84+BR84 -> 0 | BX84: =+U84+AJ84+AY84+BN84+BS84 -> 0 | BY84: =+BW84-BX84 -> 0 | BZ84: =+W84+AL84+BA84+BU84 -> 0 | CA84: =+BW84-BZ84 -> 0
B85: 雑費用 | E85: 0 | F85: =+ﾇｰﾍﾞﾙﾌﾟｰｽ!W84/1000 -> 0 | G85: =+E85-F85 -> 0 | H85: 0 | I85: =+E85-H85 -> 0 | J85: 0 | K85: =+ｶﾌｪﾙﾎﾟ!W84/1000 -> 0 | L85: =+J85-K85 -> 0 | M85: 0 | N85: =+J85-M85 -> 0 | O85: 0 | P85: =+ｶﾌｪｾﾚｽﾃ!W84/1000 -> 0 | Q85: =+O85-P85 -> 0 | R85: 0 | S85: =+O85-R85 -> 0 | T85: =+E85+J85+O85 -> 0 | U85: =+F85+K85+P85 -> 0 | V85: =+T85-U85 -> 0 | W85: =+H85+M85+R85 -> 0 | X85: =+T85-W85 -> 0 | AA85: =+Y85-Z85 -> 0 | AB85: 0 | AC85: =+Y85-AB85 -> 0 | AD85: 0 | AE85: =+ｼﾞｭｴﾙｽﾞ!W84/1000 -> 0 | AF85: =+AD85-AE85 -> 0 | AG85: 0 | AH85: =+AD85-AG85 -> 0 | AI85: =+Y85+AD85 -> 0 | AJ85: =+Z85+AE85 -> 0 | AK85: =+AI85-AJ85 -> 0 | AL85: =+AB85+AG85 -> 0 | AM85: =+AI85-AL85 -> 0 | AN85: 0 | AO85: =+ｶﾞｰﾃﾞﾝ!W84/1000 -> 3 | AP85: =+AN85-AO85 -> -3 | AQ85: 0 | AR85: =+AN85-AQ85 -> 0 | AS85: 0 | AT85: =+ﾋﾞｱｶﾞｰﾃﾞﾝ!W84/1000 -> 0 | AU85: =+AS85-AT85 -> 0 | AV85: 0 | AW85: =+AS85-AV85 -> 0 | AX85: =+AN85+AS85 -> 0 | AY85: =+AO85+AT85 -> 3 | AZ85: =+AX85-AY85 -> -3 | BA85: =+AQ85+AV85 -> 0 | BB85: =+AX85-BA85 -> 0 | BC85: 0 | BD85: =+ブリック!W84/1000 -> 0 | BE85: =+BC85-BD85 -> 0 | BG85: =+BC85-BF85 -> 0 | BH85: 0 | BI85: =+ルスツ羊蹄ぶた!W84/1000 -> 0 | BJ85: =+BH85-BI85 -> 0 | BL85: =+BH85-BK85 -> 0 | BM85: =+BC85+BH85 -> 0 | BN85: =+BD85+BI85 -> 0 | BO85: =+BM85-BN85 -> 0 | BP85: =+BF85+BK85 -> 0 | BQ85: =+BM85-BP85 -> 0 | BR85: 0 | BS85: =+料飲共通!W84/1000 -> 0 | BT85: =+BR85-BS85 -> 0 | BU85: 0 | BV85: =+BR85-BU85 -> 0 | BW85: =+T85+AI85+AX85+BM85+BR85 -> 0 | BX85: =+U85+AJ85+AY85+BN85+BS85 -> 3 | BY85: =+BW85-BX85 -> -3 | BZ85: =+W85+AL85+BA85+BU85 -> 0 | CA85: =+BW85-BZ85 -> 0
A86: 減価償却費 | E86: 5815.056 | F86: =+ﾇｰﾍﾞﾙﾌﾟｰｽ!W85/1000 -> 4460.376 | G86: =+E86-F86 -> 1354.68 | H86: 7350 | I86: =+E86-H86 -> -1534.944 | J86: 684.883 | K86: =+ｶﾌｪﾙﾎﾟ!W85/1000 -> 684.883 | L86: =+J86-K86 -> 0 | M86: 685 | N86: =+J86-M86 -> -0.117 | O86: 513.109 | P86: =+ｶﾌｪｾﾚｽﾃ!W85/1000 -> 513.109 | Q86: =+O86-P86 -> 0 | R86: 513 | S86: =+O86-R86 -> 0.109 | T86: =+E86+J86+O86 -> 7013.048 | U86: =+F86+K86+P86 -> 5658.368 | V86: =+T86-U86 -> 1354.68 | W86: =+H86+M86+R86 -> 8548 | X86: =+T86-W86 -> -1534.952 | AA86: =+Y86-Z86 -> 0 | AB86: 0 | AC86: =+Y86-AB86 -> 0 | AD86: 3560.82 | AE86: =+ｼﾞｭｴﾙｽﾞ!W85/1000 -> 3600.544 | AF86: =+AD86-AE86 -> -39.724 | AG86: 3317 | AH86: =+AD86-AG86 -> 243.82 | AI86: =+Y86+AD86 -> 3560.82 | AJ86: =+Z86+AE86 -> 3600.544 | AK86: =+AI86-AJ86 -> -39.724 | AL86: =+AB86+AG86 -> 3317 | AM86: =+AI86-AL86 -> 243.82 | AN86: 10698.156 | AO86: =+ｶﾞｰﾃﾞﾝ!W85/1000 -> 12814.711 | AP86: =+AN86-AO86 -> -2116.555 | AQ86: 11899 | AR86: =+AN86-AQ86 -> -1200.844 | AS86: 384.173 | AT86: =+ﾋﾞｱｶﾞｰﾃﾞﾝ!W85/1000 -> 1135.221 | AU86: =+AS86-AT86 -> -751.048 | AV86: 384 | AW86: =+AS86-AV86 -> 0.173 | AX86: =+AN86+AS86 -> 11082.329 | AY86: =+AO86+AT86 -> 13949.932 | AZ86: =+AX86-AY86 -> -2867.603 | BA86: =+AQ86+AV86 -> 12283 | BB86: =+AX86-BA86 -> -1200.671 | BC86: 2476.1313 | BD86: =+ブリック!W85/1000 -> 3824.404 | BE86: =+BC86-BD86 -> -1348.2727 | BG86: =+BC86-BF86 -> 2476.1313 | BH86: 488.46155 | BI86: =+ルスツ羊蹄ぶた!W85/1000 -> 565.813 | BJ86: =+BH86-BI86 -> -77.351455 | BL86: =+BH86-BK86 -> 488.46155 | BM86: =+BC86+BH86 -> 2964.5928 | BN86: =+BD86+BI86 -> 4390.217 | BO86: =+BM86-BN86 -> -1425.6242 | BP86: =+BF86+BK86 -> 0 | BQ86: =+BM86-BP86 -> 2964.5928 | BR86: 0 | BS86: =+料飲共通!W85/1000 -> 120 | BT86: =+BR86-BS86 -> -120 | BU86: 0 | BV86: =+BR86-BU86 -> 0 | BW86: =+T86+AI86+AX86+BM86+BR86 -> 24620.79 | BX86: =+U86+AJ86+AY86+BN86+BS86 -> 27719.061 | BY86: =+BW86-BX86 -> -3098.2712 | BZ86: =+W86+AL86+BA86+BU86 -> 24148 | CA86: =+BW86-BZ86 -> 472.7898
B87: 建物 | E87: 0 | F87: =+ﾇｰﾍﾞﾙﾌﾟｰｽ!W86/1000 -> 0 | G87: =+E87-F87 -> 0 | H87: 0 | I87: =+E87-H87 -> 0 | J87: 0 | K87: =+ｶﾌｪﾙﾎﾟ!W86/1000 -> 0 | L87: =+J87-K87 -> 0 | M87: 0 | N87: =+J87-M87 -> 0 | O87: 0 | P87: =+ｶﾌｪｾﾚｽﾃ!W86/1000 -> 0 | Q87: =+O87-P87 -> 0 | R87: 0 | S87: =+O87-R87 -> 0 | T87: =+E87+J87+O87 -> 0 | U87: =+F87+K87+P87 -> 0 | V87: =+T87-U87 -> 0 | W87: =+H87+M87+R87 -> 0 | X87: =+T87-W87 -> 0 | AA87: =+Y87-Z87 -> 0 | AB87: 0 | AC87: =+Y87-AB87 -> 0 | AD87: 338.068 | AE87: =+ｼﾞｭｴﾙｽﾞ!W86/1000 -> 338.068 | AF87: =+AD87-AE87 -> 0 | AG87: 338 | AH87: =+AD87-AG87 -> 0.068 | AI87: =+Y87+AD87 -> 338.068 | AJ87: =+Z87+AE87 -> 338.068 | AK87: =+AI87-AJ87 -> 0 | AL87: =+AB87+AG87 -> 338 | AM87: =+AI87-AL87 -> 0.068 | AN87: 0 | AO87: =+ｶﾞｰﾃﾞﾝ!W86/1000 -> 0 | AP87: =+AN87-AO87 -> 0 | AQ87: 0 | AR87: =+AN87-AQ87 -> 0 | AS87: 0 | AT87: =+ﾋﾞｱｶﾞｰﾃﾞﾝ!W86/1000 -> 0 | AU87: =+AS87-AT87 -> 0 | AV87: 0 | AW87: =+AS87-AV87 -> 0 | AX87: =+AN87+AS87 -> 0 | AY87: =+AO87+AT87 -> 0 | AZ87: =+AX87-AY87 -> 0 | BA87: =+AQ87+AV87 -> 0 | BB87: =+AX87-BA87 -> 0 | BC87: 256.41026 | BD87: =+ブリック!W86/1000 -> 651.674 | BE87: =+BC87-BD87 -> -395.26374 | BG87: =+BC87-BF87 -> 256.41026 | BH87: 38.461538 | BI87: =+ルスツ羊蹄ぶた!W86/1000 -> 0 | BJ87: =+BH87-BI87 -> 38.461538 | BL87: =+BH87-BK87 -> 38.461538 | BM87: =+BC87+BH87 -> 294.87179 | BN87: =+BD87+BI87 -> 651.674 | BO87: =+BM87-BN87 -> -356.80221 | BP87: =+BF87+BK87 -> 0 | BQ87: =+BM87-BP87 -> 294.87179 | BR87: 0 | BS87: =+料飲共通!W86/1000 -> 0 | BT87: =+BR87-BS87 -> 0 | BU87: 0 | BV87: =+BR87-BU87 -> 0 | BW87: =+T87+AI87+AX87+BM87+BR87 -> 632.93979 | BX87: =+U87+AJ87+AY87+BN87+BS87 -> 989.742 | BY87: =+BW87-BX87 -> -356.80221 | BZ87: =+W87+AL87+BA87+BU87 -> 338 | CA87: =+BW87-BZ87 -> 294.93979
B88: 建物附属設備 | E88: 583.333 | F88: =+ﾇｰﾍﾞﾙﾌﾟｰｽ!W87/1000 -> 0 | G88: =+E88-F88 -> 583.333 | H88: 0 | I88: =+E88-H88 -> 583.333 | J88: 0 | K88: =+ｶﾌｪﾙﾎﾟ!W87/1000 -> 0 | L88: =+J88-K88 -> 0 | M88: 0 | N88: =+J88-M88 -> 0 | O88: 257.803 | P88: =+ｶﾌｪｾﾚｽﾃ!W87/1000 -> 257.803 | Q88: =+O88-P88 -> 0 | R88: 258 | S88: =+O88-R88 -> -0.197 | T88: =+E88+J88+O88 -> 841.136 | U88: =+F88+K88+P88 -> 257.803 | V88: =+T88-U88 -> 583.333 | W88: =+H88+M88+R88 -> 258 | X88: =+T88-W88 -> 583.136 | AA88: =+Y88-Z88 -> 0 | AB88: 0 | AC88: =+Y88-AB88 -> 0 | AD88: 958.957 | AE88: =+ｼﾞｭｴﾙｽﾞ!W87/1000 -> 553.957 | AF88: =+AD88-AE88 -> 405 | AG88: 554 | AH88: =+AD88-AG88 -> 404.957 | AI88: =+Y88+AD88 -> 958.957 | AJ88: =+Z88+AE88 -> 553.957 | AK88: =+AI88-AJ88 -> 405 | AL88: =+AB88+AG88 -> 554 | AM88: =+AI88-AL88 -> 404.957 | AN88: 5652.58 | AO88: =+ｶﾞｰﾃﾞﾝ!W87/1000 -> 7719.109 | AP88: =+AN88-AO88 -> -2066.529 | AQ88: 7021 | AR88: =+AN88-AQ88 -> -1368.42 | AS88: 0 | AT88: =+ﾋﾞｱｶﾞｰﾃﾞﾝ!W87/1000 -> 0 | AU88: =+AS88-AT88 -> 0 | AV88: 0 | AW88: =+AS88-AV88 -> 0 | AX88: =+AN88+AS88 -> 5652.58 | AY88: =+AO88+AT88 -> 7719.109 | AZ88: =+AX88-AY88 -> -2066.529 | BA88: =+AQ88+AV88 -> 7021 | BB88: =+AX88-BA88 -> -1368.42 | BC88: 1000 | BD88: =+ブリック!W87/1000 -> 2205.833 | BE88: =+BC88-BD88 -> -1205.833 | BG88: =+BC88-BF88 -> 1000 | BH88: 150 | BI88: =+ルスツ羊蹄ぶた!W87/1000 -> 398.605 | BJ88: =+BH88-BI88 -> -248.605 | BL88: =+BH88-BK88 -> 150 | BM88: =+BC88+BH88 -> 1150 | BN88: =+BD88+BI88 -> 2604.438 | BO88: =+BM88-BN88 -> -1454.438 | BP88: =+BF88+BK88 -> 0 | BQ88: =+BM88-BP88 -> 1150 | BR88: 0 | BS88: =+料飲共通!W87/1000 -> 0 | BT88: =+BR88-BS88 -> 0 | BU88: 0 | BV88: =+BR88-BU88 -> 0 | BW88: =+T88+AI88+AX88+BM88+BR88 -> 8602.673 | BX88: =+U88+AJ88+AY88+BN88+BS88 -> 11135.307 | BY88: =+BW88-BX88 -> -2532.634 | BZ88: =+W88+AL88+BA88+BU88 -> 7833 | CA88: =+BW88-BZ88 -> 769.673
B89: 構築物 | E89: 0 | F89: =+ﾇｰﾍﾞﾙﾌﾟｰｽ!W88/1000 -> 0 | G89: =+E89-F89 -> 0 | H89: 0 | I89: =+E89-H89 -> 0 | J89: 0 | K89: =+ｶﾌｪﾙﾎﾟ!W88/1000 -> 0 | L89: =+J89-K89 -> 0 | M89: 0 | N89: =+J89-M89 -> 0 | O89: 0 | P89: =+ｶﾌｪｾﾚｽﾃ!W88/1000 -> 0 | Q89: =+O89-P89 -> 0 | R89: 0 | S89: =+O89-R89 -> 0 | T89: =+E89+J89+O89 -> 0 | U89: =+F89+K89+P89 -> 0 | V89: =+T89-U89 -> 0 | W89: =+H89+M89+R89 -> 0 | X89: =+T89-W89 -> 0 | AA89: =+Y89-Z89 -> 0 | AB89: 0 | AC89: =+Y89-AB89 -> 0 | AD89: 0 | AE89: =+ｼﾞｭｴﾙｽﾞ!W88/1000 -> 0 | AF89: =+AD89-AE89 -> 0 | AG89: 0 | AH89: =+AD89-AG89 -> 0 | AI89: =+Y89+AD89 -> 0 | AJ89: =+Z89+AE89 -> 0 | AK89: =+AI89-AJ89 -> 0 | AL89: =+AB89+AG89 -> 0 | AM89: =+AI89-AL89 -> 0 | AN89: 0 | AO89: =+ｶﾞｰﾃﾞﾝ!W88/1000 -> 0 | AP89: =+AN89-AO89 -> 0 | AQ89: 0 | AR89: =+AN89-AQ89 -> 0 | AS89: 0 | AT89: =+ﾋﾞｱｶﾞｰﾃﾞﾝ!W88/1000 -> 0 | AU89: =+AS89-AT89 -> 0 | AV89: 0 | AW89: =+AS89-AV89 -> 0 | AX89: =+AN89+AS89 -> 0 | AY89: =+AO89+AT89 -> 0 | AZ89: =+AX89-AY89 -> 0 | BA89: =+AQ89+AV89 -> 0 | BB89: =+AX89-BA89 -> 0 | BC89: 0 | BD89: =+ブリック!W88/1000 -> 0 | BE89: =+BC89-BD89 -> 0 | BG89: =+BC89-BF89 -> 0 | BH89: 0 | BI89: =+ルスツ羊蹄ぶた!W88/1000 -> 0 | BJ89: =+BH89-BI89 -> 0 | BL89: =+BH89-BK89 -> 0 | BM89: =+BC89+BH89 -> 0 | BN89: =+BD89+BI89 -> 0 | BO89: =+BM89-BN89 -> 0 | BP89: =+BF89+BK89 -> 0 | BQ89: =+BM89-BP89 -> 0 | BR89: 0 | BS89: =+料飲共通!W88/1000 -> 0 | BT89: =+BR89-BS89 -> 0 | BU89: 0 | BV89: =+BR89-BU89 -> 0 | BW89: =+T89+AI89+AX89+BM89+BR89 -> 0 | BX89: =+U89+AJ89+AY89+BN89+BS89 -> 0 | BY89: =+BW89-BX89 -> 0 | BZ89: =+W89+AL89+BA89+BU89 -> 0 | CA89: =+BW89-BZ89 -> 0
B90: 機械・装置 | E90: 500 | F90: =+ﾇｰﾍﾞﾙﾌﾟｰｽ!W89/1000 -> 0 | G90: =+E90-F90 -> 500 | H90: 0 | I90: =+E90-H90 -> 500 | J90: 180.557 | K90: =+ｶﾌｪﾙﾎﾟ!W89/1000 -> 180.557 | L90: =+J90-K90 -> 0 | M90: 181 | N90: =+J90-M90 -> -0.443 | O90: 0 | P90: =+ｶﾌｪｾﾚｽﾃ!W89/1000 -> 0 | Q90: =+O90-P90 -> 0 | R90: 0 | S90: =+O90-R90 -> 0 | T90: =+E90+J90+O90 -> 680.557 | U90: =+F90+K90+P90 -> 180.557 | V90: =+T90-U90 -> 500 | W90: =+H90+M90+R90 -> 181 | X90: =+T90-W90 -> 499.557 | AA90: =+Y90-Z90 -> 0 | AB90: 0 | AC90: =+Y90-AB90 -> 0 | AD90: 175.1 | AE90: =+ｼﾞｭｴﾙｽﾞ!W89/1000 -> 175.1 | AF90: =+AD90-AE90 -> 0 | AG90: 175 | AH90: =+AD90-AG90 -> 0.1 | AI90: =+Y90+AD90 -> 175.1 | AJ90: =+Z90+AE90 -> 175.1 | AK90: =+AI90-AJ90 -> 0 | AL90: =+AB90+AG90 -> 175 | AM90: =+AI90-AL90 -> 0.1 | AN90: 403.782 | AO90: =+ｶﾞｰﾃﾞﾝ!W89/1000 -> 197.321 | AP90: =+AN90-AO90 -> 206.461 | AQ90: 143 | AR90: =+AN90-AQ90 -> 260.782 | AS90: 0 | AT90: =+ﾋﾞｱｶﾞｰﾃﾞﾝ!W89/1000 -> 0 | AU90: =+AS90-AT90 -> 0 | AV90: 0 | AW90: =+AS90-AV90 -> 0 | AX90: =+AN90+AS90 -> 403.782 | AY90: =+AO90+AT90 -> 197.321 | AZ90: =+AX90-AY90 -> 206.461 | BA90: =+AQ90+AV90 -> 143 | BB90: =+AX90-BA90 -> 260.782 | BC90: 0 | BD90: =+ブリック!W89/1000 -> 0 | BE90: =+BC90-BD90 -> 0 | BG90: =+BC90-BF90 -> 0 | BH90: 0 | BI90: =+ルスツ羊蹄ぶた!W89/1000 -> 0 | BJ90: =+BH90-BI90 -> 0 | BL90: =+BH90-BK90 -> 0 | BM90: =+BC90+BH90 -> 0 | BN90: =+BD90+BI90 -> 0 | BO90: =+BM90-BN90 -> 0 | BP90: =+BF90+BK90 -> 0 | BQ90: =+BM90-BP90 -> 0 | BR90: 0 | BS90: =+料飲共通!W89/1000 -> 0 | BT90: =+BR90-BS90 -> 0 | BU90: 0 | BV90: =+BR90-BU90 -> 0 | BW90: =+T90+AI90+AX90+BM90+BR90 -> 1259.439 | BX90: =+U90+AJ90+AY90+BN90+BS90 -> 552.978 | BY90: =+BW90-BX90 -> 706.461 | BZ90: =+W90+AL90+BA90+BU90 -> 499 | CA90: =+BW90-BZ90 -> 760.439
B91: 器具備品 | E91: 4445.38 | F91: =+ﾇｰﾍﾞﾙﾌﾟｰｽ!W90/1000 -> 4125.38 | G91: =+E91-F91 -> 320 | H91: 7063 | I91: =+E91-H91 -> -2617.62 | J91: 440.993 | K91: =+ｶﾌｪﾙﾎﾟ!W90/1000 -> 440.993 | L91: =+J91-K91 -> 0 | M91: 441 | N91: =+J91-M91 -> -0.007 | O91: 255.306 | P91: =+ｶﾌｪｾﾚｽﾃ!W90/1000 -> 255.306 | Q91: =+O91-P91 -> 0 | R91: 255 | S91: =+O91-R91 -> 0.306 | T91: =+E91+J91+O91 -> 5141.679 | U91: =+F91+K91+P91 -> 4821.679 | V91: =+T91-U91 -> 320 | W91: =+H91+M91+R91 -> 7759 | X91: =+T91-W91 -> -2617.321 | AA91: =+Y91-Z91 -> 0 | AB91: 0 | AC91: =+Y91-AB91 -> 0 | AD91: 1769.326 | AE91: =+ｼﾞｭｴﾙｽﾞ!W90/1000 -> 1653.52 | AF91: =+AD91-AE91 -> 115.806 | AG91: 1845 | AH91: =+AD91-AG91 -> -75.674 | AI91: =+Y91+AD91 -> 1769.326 | AJ91: =+Z91+AE91 -> 1653.52 | AK91: =+AI91-AJ91 -> 115.806 | AL91: =+AB91+AG91 -> 1845 | AM91: =+AI91-AL91 -> -75.674 | AN91: 3349.202 | AO91: =+ｶﾞｰﾃﾞﾝ!W90/1000 -> 3410.702 | AP91: =+AN91-AO91 -> -61.5 | AQ91: 3310 | AR91: =+AN91-AQ91 -> 39.202 | AS91: 120.84 | AT91: =+ﾋﾞｱｶﾞｰﾃﾞﾝ!W90/1000 -> 772.992 | AU91: =+AS91-AT91 -> -652.152 | AV91: 121 | AW91: =+AS91-AV91 -> -0.16 | AX91: =+AN91+AS91 -> 3470.042 | AY91: =+AO91+AT91 -> 4183.694 | AZ91: =+AX91-AY91 -> -713.652 | BA91: =+AQ91+AV91 -> 3431 | BB91: =+AX91-BA91 -> 39.042 | BC91: 500 | BD91: =+ブリック!W90/1000 -> 679.822 | BE91: =+BC91-BD91 -> -179.822 | BG91: =+BC91-BF91 -> 500 | BH91: 6.6343213e-06 | BI91: =+ルスツ羊蹄ぶた!W90/1000 -> 17.054 | BJ91: =+BH91-BI91 -> -17.053993 | BL91: =+BH91-BK91 -> 6.6343213e-06 | BM91: =+BC91+BH91 -> 500.00001 | BN91: =+BD91+BI91 -> 696.876 | BO91: =+BM91-BN91 -> -196.87599 | BP91: =+BF91+BK91 -> 0 | BQ91: =+BM91-BP91 -> 500.00001 | BR91: 0 | BS91: =+料飲共通!W90/1000 -> 0 | BT91: =+BR91-BS91 -> 0 | BU91: 0 | BV91: =+BR91-BU91 -> 0 | BW91: =+T91+AI91+AX91+BM91+BR91 -> 10881.047 | BX91: =+U91+AJ91+AY91+BN91+BS91 -> 11355.769 | BY91: =+BW91-BX91 -> -474.72199 | BZ91: =+W91+AL91+BA91+BU91 -> 13035 | CA91: =+BW91-BZ91 -> -2153.953
B92: 車両 | E92: 0 | F92: =+ﾇｰﾍﾞﾙﾌﾟｰｽ!W91/1000 -> 0 | G92: =+E92-F92 -> 0 | H92: 0 | I92: =+E92-H92 -> 0 | J92: 0 | K92: =+ｶﾌｪﾙﾎﾟ!W91/1000 -> 0 | L92: =+J92-K92 -> 0 | M92: 0 | N92: =+J92-M92 -> 0 | O92: 0 | P92: =+ｶﾌｪｾﾚｽﾃ!W91/1000 -> 0 | Q92: =+O92-P92 -> 0 | R92: 0 | S92: =+O92-R92 -> 0 | T92: =+E92+J92+O92 -> 0 | U92: =+F92+K92+P92 -> 0 | V92: =+T92-U92 -> 0 | W92: =+H92+M92+R92 -> 0 | X92: =+T92-W92 -> 0 | AA92: =+Y92-Z92 -> 0 | AB92: 0 | AC92: =+Y92-AB92 -> 0 | AD92: 0 | AE92: =+ｼﾞｭｴﾙｽﾞ!W91/1000 -> 420.098 | AF92: =+AD92-AE92 -> -420.098 | AG92: 0 | AH92: =+AD92-AG92 -> 0 | AI92: =+Y92+AD92 -> 0 | AJ92: =+Z92+AE92 -> 420.098 | AK92: =+AI92-AJ92 -> -420.098 | AL92: =+AB92+AG92 -> 0 | AM92: =+AI92-AL92 -> 0 | AN92: 0 | AO92: =+ｶﾞｰﾃﾞﾝ!W91/1000 -> 0 | AP92: =+AN92-AO92 -> 0 | AQ92: 0 | AR92: =+AN92-AQ92 -> 0 | AS92: 0 | AT92: =+ﾋﾞｱｶﾞｰﾃﾞﾝ!W91/1000 -> 0 | AU92: =+AS92-AT92 -> 0 | AV92: 0 | AW92: =+AS92-AV92 -> 0 | AX92: =+AN92+AS92 -> 0 | AY92: =+AO92+AT92 -> 0 | AZ92: =+AX92-AY92 -> 0 | BA92: =+AQ92+AV92 -> 0 | BB92: =+AX92-BA92 -> 0 | BC92: 0 | BD92: =+ブリック!W91/1000 -> 0 | BE92: =+BC92-BD92 -> 0 | BG92: =+BC92-BF92 -> 0 | BH92: 0 | BI92: =+ルスツ羊蹄ぶた!W91/1000 -> 0 | BJ92: =+BH92-BI92 -> 0 | BL92: =+BH92-BK92 -> 0 | BM92: =+BC92+BH92 -> 0 | BN92: =+BD92+BI92 -> 0 | BO92: =+BM92-BN92 -> 0 | BP92: =+BF92+BK92 -> 0 | BQ92: =+BM92-BP92 -> 0 | BR92: 0 | BS92: =+料飲共通!W91/1000 -> 0 | BT92: =+BR92-BS92 -> 0 | BU92: 0 | BV92: =+BR92-BU92 -> 0 | BW92: =+T92+AI92+AX92+BM92+BR92 -> 0 | BX92: =+U92+AJ92+AY92+BN92+BS92 -> 420.098 | BY92: =+BW92-BX92 -> -420.098 | BZ92: =+W92+AL92+BA92+BU92 -> 0 | CA92: =+BW92-BZ92 -> 0
B93: 少額資産 | E93: 218.344 | F93: =+ﾇｰﾍﾞﾙﾌﾟｰｽ!W92/1000 -> 266.997 | G93: =+E93-F93 -> -48.653 | H93: 218 | I93: =+E93-H93 -> 0.344 | J93: 63.333 | K93: =+ｶﾌｪﾙﾎﾟ!W92/1000 -> 63.333 | L93: =+J93-K93 -> 0 | M93: 63 | N93: =+J93-M93 -> 0.333 | O93: 0 | P93: =+ｶﾌｪｾﾚｽﾃ!W92/1000 -> 0 | Q93: =+O93-P93 -> 0 | R93: 0 | S93: =+O93-R93 -> 0 | T93: =+E93+J93+O93 -> 281.677 | U93: =+F93+K93+P93 -> 330.33 | V93: =+T93-U93 -> -48.653 | W93: =+H93+M93+R93 -> 281 | X93: =+T93-W93 -> 0.677 | AA93: =+Y93-Z93 -> 0 | AB93: 0 | AC93: =+Y93-AB93 -> 0 | AD93: 319.369 | AE93: =+ｼﾞｭｴﾙｽﾞ!W92/1000 -> 459.801 | AF93: =+AD93-AE93 -> -140.432 | AG93: 405 | AH93: =+AD93-AG93 -> -85.631 | AI93: =+Y93+AD93 -> 319.369 | AJ93: =+Z93+AE93 -> 459.801 | AK93: =+AI93-AJ93 -> -140.432 | AL93: =+AB93+AG93 -> 405 | AM93: =+AI93-AL93 -> -85.631 | AN93: 1292.592 | AO93: =+ｶﾞｰﾃﾞﾝ!W92/1000 -> 1487.579 | AP93: =+AN93-AO93 -> -194.987 | AQ93: 1424 | AR93: =+AN93-AQ93 -> -131.408 | AS93: 263.333 | AT93: =+ﾋﾞｱｶﾞｰﾃﾞﾝ!W92/1000 -> 362.229 | AU93: =+AS93-AT93 -> -98.896 | AV93: 263 | AW93: =+AS93-AV93 -> 0.333 | AX93: =+AN93+AS93 -> 1555.925 | AY93: =+AO93+AT93 -> 1849.808 | AZ93: =+AX93-AY93 -> -293.883 | BA93: =+AQ93+AV93 -> 1687 | BB93: =+AX93-BA93 -> -131.075 | BC93: 0 | BD93: =+ブリック!W92/1000 -> 287.075 | BE93: =+BC93-BD93 -> -287.075 | BG93: =+BC93-BF93 -> 0 | BH93: 0 | BI93: =+ルスツ羊蹄ぶた!W92/1000 -> 150.154 | BJ93: =+BH93-BI93 -> -150.154 | BL93: =+BH93-BK93 -> 0 | BM93: =+BC93+BH93 -> 0 | BN93: =+BD93+BI93 -> 437.229 | BO93: =+BM93-BN93 -> -437.229 | BP93: =+BF93+BK93 -> 0 | BQ93: =+BM93-BP93 -> 0 | BR93: 0 | BS93: =+料飲共通!W92/1000 -> 120 | BT93: =+BR93-BS93 -> -120 | BU93: 0 | BV93: =+BR93-BU93 -> 0 | BW93: =+T93+AI93+AX93+BM93+BR93 -> 2156.971 | BX93: =+U93+AJ93+AY93+BN93+BS93 -> 3197.168 | BY93: =+BW93-BX93 -> -1040.197 | BZ93: =+W93+AL93+BA93+BU93 -> 2373 | CA93: =+BW93-BZ93 -> -216.029
B94: 商標権 | E94: 0 | F94: =+ﾇｰﾍﾞﾙﾌﾟｰｽ!W93/1000 -> 0 | G94: =+E94-F94 -> 0 | H94: 0 | I94: =+E94-H94 -> 0 | J94: 0 | K94: =+ｶﾌｪﾙﾎﾟ!W93/1000 -> 0 | L94: =+J94-K94 -> 0 | M94: 0 | N94: =+J94-M94 -> 0 | O94: 0 | P94: =+ｶﾌｪｾﾚｽﾃ!W93/1000 -> 0 | Q94: =+O94-P94 -> 0 | R94: 0 | S94: =+O94-R94 -> 0 | T94: =+E94+J94+O94 -> 0 | U94: =+F94+K94+P94 -> 0 | V94: =+T94-U94 -> 0 | W94: =+H94+M94+R94 -> 0 | X94: =+T94-W94 -> 0 | AA94: =+Y94-Z94 -> 0 | AB94: 0 | AC94: =+Y94-AB94 -> 0 | AD94: 0 | AE94: =+ｼﾞｭｴﾙｽﾞ!W93/1000 -> 0 | AF94: =+AD94-AE94 -> 0 | AG94: 0 | AH94: =+AD94-AG94 -> 0 | AI94: =+Y94+AD94 -> 0 | AJ94: =+Z94+AE94 -> 0 | AK94: =+AI94-AJ94 -> 0 | AL94: =+AB94+AG94 -> 0 | AM94: =+AI94-AL94 -> 0 | AN94: 0 | AO94: =+ｶﾞｰﾃﾞﾝ!W93/1000 -> 0 | AP94: =+AN94-AO94 -> 0 | AQ94: 0 | AR94: =+AN94-AQ94 -> 0 | AS94: 0 | AT94: =+ﾋﾞｱｶﾞｰﾃﾞﾝ!W93/1000 -> 0 | AU94: =+AS94-AT94 -> 0 | AV94: 0 | AW94: =+AS94-AV94 -> 0 | AX94: =+AN94+AS94 -> 0 | AY94: =+AO94+AT94 -> 0 | AZ94: =+AX94-AY94 -> 0 | BA94: =+AQ94+AV94 -> 0 | BB94: =+AX94-BA94 -> 0 | BC94: 719.721 | BD94: =+ブリック!W93/1000 -> 0 | BE94: =+BC94-BD94 -> 719.721 | BG94: =+BC94-BF94 -> 719.721 | BH94: 300 | BI94: =+ルスツ羊蹄ぶた!W93/1000 -> 0 | BJ94: =+BH94-BI94 -> 300 | BL94: =+BH94-BK94 -> 300 | BM94: =+BC94+BH94 -> 1019.721 | BN94: =+BD94+BI94 -> 0 | BO94: =+BM94-BN94 -> 1019.721 | BP94: =+BF94+BK94 -> 0 | BQ94: =+BM94-BP94 -> 1019.721 | BR94: 0 | BS94: =+料飲共通!W93/1000 -> 0 | BT94: =+BR94-BS94 -> 0 | BU94: 0 | BV94: =+BR94-BU94 -> 0 | BW94: =+T94+AI94+AX94+BM94+BR94 -> 1019.721 | BX94: =+U94+AJ94+AY94+BN94+BS94 -> 0 | BY94: =+BW94-BX94 -> 1019.721 | BZ94: =+W94+AL94+BA94+BU94 -> 0 | CA94: =+BW94-BZ94 -> 1019.721
B95: ソフトウェア | E95: 67.999 | F95: =+ﾇｰﾍﾞﾙﾌﾟｰｽ!W94/1000 -> 67.999 | G95: =+E95-F95 -> 0 | H95: 68 | I95: =+E95-H95 -> -0.001 | J95: 0 | K95: =+ｶﾌｪﾙﾎﾟ!W94/1000 -> 0 | L95: =+J95-K95 -> 0 | M95: 0 | N95: =+J95-M95 -> 0 | O95: 0 | P95: =+ｶﾌｪｾﾚｽﾃ!W94/1000 -> 0 | Q95: =+O95-P95 -> 0 | R95: 0 | S95: =+O95-R95 -> 0 | T95: =+E95+J95+O95 -> 67.999 | U95: =+F95+K95+P95 -> 67.999 | V95: =+T95-U95 -> 0 | W95: =+H95+M95+R95 -> 68 | X95: =+T95-W95 -> -0.001 | AA95: =+Y95-Z95 -> 0 | AB95: 0 | AC95: =+Y95-AB95 -> 0 | AD95: 0 | AE95: =+ｼﾞｭｴﾙｽﾞ!W94/1000 -> 0 | AF95: =+AD95-AE95 -> 0 | AG95: 0 | AH95: =+AD95-AG95 -> 0 | AI95: =+Y95+AD95 -> 0 | AJ95: =+Z95+AE95 -> 0 | AK95: =+AI95-AJ95 -> 0 | AL95: =+AB95+AG95 -> 0 | AM95: =+AI95-AL95 -> 0 | AN95: 0 | AO95: =+ｶﾞｰﾃﾞﾝ!W94/1000 -> 0 | AP95: =+AN95-AO95 -> 0 | AQ95: 0 | AR95: =+AN95-AQ95 -> 0 | AS95: 0 | AT95: =+ﾋﾞｱｶﾞｰﾃﾞﾝ!W94/1000 -> 0 | AU95: =+AS95-AT95 -> 0 | AV95: 0 | AW95: =+AS95-AV95 -> 0 | AX95: =+AN95+AS95 -> 0 | AY95: =+AO95+AT95 -> 0 | AZ95: =+AX95-AY95 -> 0 | BA95: =+AQ95+AV95 -> 0 | BB95: =+AX95-BA95 -> 0 | BC95: 0 | BD95: =+ブリック!W94/1000 -> 0 | BE95: =+BC95-BD95 -> 0 | BG95: =+BC95-BF95 -> 0 | BH95: 0 | BI95: =+ルスツ羊蹄ぶた!W94/1000 -> 0 | BJ95: =+BH95-BI95 -> 0 | BL95: =+BH95-BK95 -> 0 | BM95: =+BC95+BH95 -> 0 | BN95: =+BD95+BI95 -> 0 | BO95: =+BM95-BN95 -> 0 | BP95: =+BF95+BK95 -> 0 | BQ95: =+BM95-BP95 -> 0 | BR95: 0 | BS95: =+料飲共通!W94/1000 -> 0 | BT95: =+BR95-BS95 -> 0 | BU95: 0 | BV95: =+BR95-BU95 -> 0 | BW95: =+T95+AI95+AX95+BM95+BR95 -> 67.999 | BX95: =+U95+AJ95+AY95+BN95+BS95 -> 67.999 | BY95: =+BW95-BX95 -> 0 | BZ95: =+W95+AL95+BA95+BU95 -> 68 | CA95: =+BW95-BZ95 -> -0.001
B96: 長期前払費用 | E96: 0 | F96: =+ﾇｰﾍﾞﾙﾌﾟｰｽ!W95/1000 -> 0 | G96: =+E96-F96 -> 0 | H96: 0 | I96: =+E96-H96 -> 0 | J96: 0 | K96: =+ｶﾌｪﾙﾎﾟ!W95/1000 -> 0 | L96: =+J96-K96 -> 0 | M96: 0 | N96: =+J96-M96 -> 0 | O96: 0 | P96: =+ｶﾌｪｾﾚｽﾃ!W95/1000 -> 0 | Q96: =+O96-P96 -> 0 | R96: 0 | S96: =+O96-R96 -> 0 | T96: =+E96+J96+O96 -> 0 | U96: =+F96+K96+P96 -> 0 | V96: =+T96-U96 -> 0 | W96: =+H96+M96+R96 -> 0 | X96: =+T96-W96 -> 0 | AA96: =+Y96-Z96 -> 0 | AB96: 0 | AC96: =+Y96-AB96 -> 0 | AD96: 0 | AE96: =+ｼﾞｭｴﾙｽﾞ!W95/1000 -> 0 | AF96: =+AD96-AE96 -> 0 | AG96: 0 | AH96: =+AD96-AG96 -> 0 | AI96: =+Y96+AD96 -> 0 | AJ96: =+Z96+AE96 -> 0 | AK96: =+AI96-AJ96 -> 0 | AL96: =+AB96+AG96 -> 0 | AM96: =+AI96-AL96 -> 0 | AN96: 0 | AO96: =+ｶﾞｰﾃﾞﾝ!W95/1000 -> 0 | AP96: =+AN96-AO96 -> 0 | AQ96: 0 | AR96: =+AN96-AQ96 -> 0 | AS96: 0 | AT96: =+ﾋﾞｱｶﾞｰﾃﾞﾝ!W95/1000 -> 0 | AU96: =+AS96-AT96 -> 0 | AV96: 0 | AW96: =+AS96-AV96 -> 0 | AX96: =+AN96+AS96 -> 0 | AY96: =+AO96+AT96 -> 0 | AZ96: =+AX96-AY96 -> 0 | BA96: =+AQ96+AV96 -> 0 | BB96: =+AX96-BA96 -> 0 | BC96: 0 | BD96: =+ブリック!W95/1000 -> 0 | BE96: =+BC96-BD96 -> 0 | BG96: =+BC96-BF96 -> 0 | BH96: 0 | BI96: =+ルスツ羊蹄ぶた!W95/1000 -> 0 | BJ96: =+BH96-BI96 -> 0 | BL96: =+BH96-BK96 -> 0 | BM96: =+BC96+BH96 -> 0 | BN96: =+BD96+BI96 -> 0 | BO96: =+BM96-BN96 -> 0 | BP96: =+BF96+BK96 -> 0 | BQ96: =+BM96-BP96 -> 0 | BR96: 0 | BS96: =+料飲共通!W95/1000 -> 0 | BT96: =+BR96-BS96 -> 0 | BU96: 0 | BV96: =+BR96-BU96 -> 0 | BW96: =+T96+AI96+AX96+BM96+BR96 -> 0 | BX96: =+U96+AJ96+AY96+BN96+BS96 -> 0 | BY96: =+BW96-BX96 -> 0 | BZ96: =+W96+AL96+BA96+BU96 -> 0 | CA96: =+BW96-BZ96 -> 0
B97: リース資産 | E97: 0 | F97: =+ﾇｰﾍﾞﾙﾌﾟｰｽ!W96/1000 -> 0 | G97: =+E97-F97 -> 0 | H97: 0 | I97: =+E97-H97 -> 0 | J97: 0 | K97: =+ｶﾌｪﾙﾎﾟ!W96/1000 -> 0 | L97: =+J97-K97 -> 0 | M97: 0 | N97: =+J97-M97 -> 0 | O97: 0 | P97: =+ｶﾌｪｾﾚｽﾃ!W96/1000 -> 0 | Q97: =+O97-P97 -> 0 | R97: 0 | S97: =+O97-R97 -> 0 | T97: =+E97+J97+O97 -> 0 | U97: =+F97+K97+P97 -> 0 | V97: =+T97-U97 -> 0 | W97: =+H97+M97+R97 -> 0 | X97: =+T97-W97 -> 0 | AA97: =+Y97-Z97 -> 0 | AB97: 0 | AC97: =+Y97-AB97 -> 0 | AD97: 0 | AE97: =+ｼﾞｭｴﾙｽﾞ!W96/1000 -> 0 | AF97: =+AD97-AE97 -> 0 | AG97: 0 | AH97: =+AD97-AG97 -> 0 | AI97: =+Y97+AD97 -> 0 | AJ97: =+Z97+AE97 -> 0 | AK97: =+AI97-AJ97 -> 0 | AL97: =+AB97+AG97 -> 0 | AM97: =+AI97-AL97 -> 0 | AN97: 0 | AO97: =+ｶﾞｰﾃﾞﾝ!W96/1000 -> 0 | AP97: =+AN97-AO97 -> 0 | AQ97: 0 | AR97: =+AN97-AQ97 -> 0 | AS97: 0 | AT97: =+ﾋﾞｱｶﾞｰﾃﾞﾝ!W96/1000 -> 0 | AU97: =+AS97-AT97 -> 0 | AV97: 0 | AW97: =+AS97-AV97 -> 0 | AX97: =+AN97+AS97 -> 0 | AY97: =+AO97+AT97 -> 0 | AZ97: =+AX97-AY97 -> 0 | BA97: =+AQ97+AV97 -> 0 | BB97: =+AX97-BA97 -> 0 | BC97: 0 | BD97: =+ブリック!W96/1000 -> 0 | BE97: =+BC97-BD97 -> 0 | BG97: =+BC97-BF97 -> 0 | BH97: 0 | BI97: =+ルスツ羊蹄ぶた!W96/1000 -> 0 | BJ97: =+BH97-BI97 -> 0 | BL97: =+BH97-BK97 -> 0 | BM97: =+BC97+BH97 -> 0 | BN97: =+BD97+BI97 -> 0 | BO97: =+BM97-BN97 -> 0 | BP97: =+BF97+BK97 -> 0 | BQ97: =+BM97-BP97 -> 0 | BR97: 0 | BS97: =+料飲共通!W96/1000 -> 0 | BT97: =+BR97-BS97 -> 0 | BU97: 0 | BV97: =+BR97-BU97 -> 0 | BW97: =+T97+AI97+AX97+BM97+BR97 -> 0 | BX97: =+U97+AJ97+AY97+BN97+BS97 -> 0 | BY97: =+BW97-BX97 -> 0 | BZ97: =+W97+AL97+BA97+BU97 -> 0 | CA97: =+BW97-BZ97 -> 0
A98: 販売費・一般管理費 | E98: 84301.858 | F98: =+ﾇｰﾍﾞﾙﾌﾟｰｽ!W97/1000 -> 90528.96 | G98: =+E98-F98 -> -6227.102 | H98: 82882 | I98: =+E98-H98 -> 1419.858 | J98: 6405.162 | K98: =+ｶﾌｪﾙﾎﾟ!W97/1000 -> 9591.488 | L98: =+J98-K98 -> -3186.326 | M98: 6782 | N98: =+J98-M98 -> -376.838 | O98: 4993.967 | P98: =+ｶﾌｪｾﾚｽﾃ!W97/1000 -> 2132.395 | Q98: =+O98-P98 -> 2861.572 | R98: 5378 | S98: =+O98-R98 -> -384.033 | T98: =+E98+J98+O98 -> 95700.987 | U98: =+F98+K98+P98 -> 102252.84 | V98: =+T98-U98 -> -6551.856 | W98: =+H98+M98+R98 -> 95042 | X98: =+T98-W98 -> 658.98698 | AA98: =+Y98-Z98 -> 0 | AB98: 6973 | AC98: =+Y98-AB98 -> -6973 | AD98: 93090.879 | AE98: =+ｼﾞｭｴﾙｽﾞ!W97/1000 -> 83921.241 | AF98: =+AD98-AE98 -> 9169.6384 | AG98: 93887 | AH98: =+AD98-AG98 -> -796.12058 | AI98: =+Y98+AD98 -> 93090.879 | AJ98: =+Z98+AE98 -> 83921.241 | AK98: =+AI98-AJ98 -> 9169.6384 | AL98: =+AB98+AG98 -> 100860 | AM98: =+AI98-AL98 -> -7769.1206 | AN98: 102988.39 | AO98: =+ｶﾞｰﾃﾞﾝ!W97/1000 -> 119702.71 | AP98: =+AN98-AO98 -> -16714.319 | AQ98: 124711 | AR98: =+AN98-AQ98 -> -21722.608 | AS98: 89563.119 | AT98: =+ﾋﾞｱｶﾞｰﾃﾞﾝ!W97/1000 -> 80307.406 | AU98: =+AS98-AT98 -> 9255.7134 | AV98: 81573 | AW98: =+AS98-AV98 -> 7990.1194 | AX98: =+AN98+AS98 -> 192551.51 | AY98: =+AO98+AT98 -> 200010.12 | AZ98: =+AX98-AY98 -> -7458.6056 | BA98: =+AQ98+AV98 -> 206284 | BB98: =+AX98-BA98 -> -13732.489 | BC98: 51986.063 | BD98: =+ブリック!W97/1000 -> 76835.921 | BE98: =+BC98-BD98 -> -24849.858 | BG98: =+BC98-BF98 -> 51986.063 | BH98: 29406.633 | BI98: =+ルスツ羊蹄ぶた!W97/1000 -> 21243.06 | BJ98: =+BH98-BI98 -> 8163.573 | BL98: =+BH98-BK98 -> 29406.633 | BM98: =+BC98+BH98 -> 81392.696 | BN98: =+BD98+BI98 -> 98078.981 | BO98: =+BM98-BN98 -> -16686.285 | BP98: =+BF98+BK98 -> 0 | BQ98: =+BM98-BP98 -> 81392.696 | BR98: 28024.132 | BS98: =+料飲共通!W97/1000 -> 49327.927 | BT98: =+BR98-BS98 -> -21303.795 | BU98: 33646 | BV98: =+BR98-BU98 -> -5621.8676 | BW98: =+T98+AI98+AX98+BM98+BR98 -> 490760.21 | BX98: =+U98+AJ98+AY98+BN98+BS98 -> 533591.11 | BY98: =+BW98-BX98 -> -42830.903 | BZ98: =+W98+AL98+BA98+BU98 -> 435832 | CA98: =+BW98-BZ98 -> 54928.206
A99: 営業利益 | E99: -14568.143 | F99: =+ﾇｰﾍﾞﾙﾌﾟｰｽ!W98/1000 -> -18436.173 | G99: =+E99-F99 -> 3868.03 | H99: -10011 | I99: =+E99-H99 -> -4557.143 | J99: -140.93604 | K99: =+ｶﾌｪﾙﾎﾟ!W98/1000 -> -9054.9904 | L99: =+J99-K99 -> 8914.0544 | M99: -976 | N99: =+J99-M99 -> 835.06396 | O99: 8662.088 | P99: =+ｶﾌｪｾﾚｽﾃ!W98/1000 -> 11882.842 | Q99: =+O99-P99 -> -3220.7536 | R99: 8033 | S99: =+O99-R99 -> 629.088 | T99: =+E99+J99+O99 -> -6046.991 | U99: =+F99+K99+P99 -> -15608.322 | V99: =+T99-U99 -> 9561.3308 | W99: =+H99+M99+R99 -> -2954 | X99: =+T99-W99 -> -3092.991 | AA99: =+Y99-Z99 -> 0 | AB99: 16373 | AC99: =+Y99-AB99 -> -16373 | AD99: 23985.671 | AE99: =+ｼﾞｭｴﾙｽﾞ!W98/1000 -> 32575.999 | AF99: =+AD99-AE99 -> -8590.3274 | AG99: 21352 | AH99: =+AD99-AG99 -> 2633.6714 | AI99: =+Y99+AD99 -> 23985.671 | AJ99: =+Z99+AE99 -> 32575.999 | AK99: =+AI99-AJ99 -> -8590.3274 | AL99: =+AB99+AG99 -> 37725 | AM99: =+AI99-AL99 -> -13739.329 | AN99: -8621.8033 | AO99: =+ｶﾞｰﾃﾞﾝ!W98/1000 -> -17807.016 | AP99: =+AN99-AO99 -> 9185.2131 | AQ99: -30887 | AR99: =+AN99-AQ99 -> 22265.197 | AS99: 15800.809 | AT99: =+ﾋﾞｱｶﾞｰﾃﾞﾝ!W98/1000 -> 37383.982 | AU99: =+AS99-AT99 -> -21583.173 | AV99: 14540 | AW99: =+AS99-AV99 -> 1260.809 | AX99: =+AN99+AS99 -> 7179.0056 | AY99: =+AO99+AT99 -> 19576.966 | AZ99: =+AX99-AY99 -> -12397.96 | BA99: =+AQ99+AV99 -> -16347 | BB99: =+AX99-BA99 -> 23526.006 | BC99: 1900.5974 | BD99: =+ブリック!W98/1000 -> -39628.608 | BE99: =+BC99-BD99 -> 41529.206 | BG99: =+BC99-BF99 -> 1900.5974 | BH99: 3289.927 | BI99: =+ルスツ羊蹄ぶた!W98/1000 -> 413.94714 | BJ99: =+BH99-BI99 -> 2875.9799 | BL99: =+BH99-BK99 -> 3289.927 | BM99: =+BC99+BH99 -> 5190.5244 | BN99: =+BD99+BI99 -> -39214.661 | BO99: =+BM99-BN99 -> 44405.185 | BP99: =+BF99+BK99 -> 0 | BQ99: =+BM99-BP99 -> 5190.5244 | BR99: -28024.132 | BS99: =+料飲共通!W98/1000 -> -49327.927 | BT99: =+BR99-BS99 -> 21303.795 | BU99: -33646 | BV99: =+BR99-BU99 -> 5621.8676 | BW99: =+T99+AI99+AX99+BM99+BR99 -> 2284.0779 | BX99: =+U99+AJ99+AY99+BN99+BS99 -> -51997.945 | BY99: =+BW99-BX99 -> 54282.023 | BZ99: =+W99+AL99+BA99+BU99 -> -15222 | CA99: =+BW99-BZ99 -> 17506.078
A100: 営業外収益 | E100: 85.542 | F100: =+ﾇｰﾍﾞﾙﾌﾟｰｽ!W99/1000 -> 66.888 | G100: =+E100-F100 -> 18.654 | H100: 321 | I100: =+E100-H100 -> -235.458 | J100: 0 | K100: =+ｶﾌｪﾙﾎﾟ!W99/1000 -> 17.728 | L100: =+J100-K100 -> -17.728 | M100: 1 | N100: =+J100-M100 -> -1 | O100: 0 | P100: =+ｶﾌｪｾﾚｽﾃ!W99/1000 -> 0 | Q100: =+O100-P100 -> 0 | R100: 0 | S100: =+O100-R100 -> 0 | T100: =+E100+J100+O100 -> 85.542 | U100: =+F100+K100+P100 -> 84.616 | V100: =+T100-U100 -> 0.926 | W100: =+H100+M100+R100 -> 322 | X100: =+T100-W100 -> -236.458 | AA100: =+Y100-Z100 -> 0 | AB100: 0 | AC100: =+Y100-AB100 -> 0 | AD100: 480.93 | AE100: =+ｼﾞｭｴﾙｽﾞ!W99/1000 -> 0.391 | AF100: =+AD100-AE100 -> 480.539 | AG100: 209 | AH100: =+AD100-AG100 -> 271.93 | AI100: =+Y100+AD100 -> 480.93 | AJ100: =+Z100+AE100 -> 0.391 | AK100: =+AI100-AJ100 -> 480.539 | AL100: =+AB100+AG100 -> 209 | AM100: =+AI100-AL100 -> 271.93 | AN100: 41.814 | AO100: =+ｶﾞｰﾃﾞﾝ!W99/1000 -> 12.091 | AP100: =+AN100-AO100 -> 29.723 | AQ100: 106 | AR100: =+AN100-AQ100 -> -64.186 | AS100: 0 | AT100: =+ﾋﾞｱｶﾞｰﾃﾞﾝ!W99/1000 -> 200 | AU100: =+AS100-AT100 -> -200 | AV100: 1409 | AW100: =+AS100-AV100 -> -1409 | AX100: =+AN100+AS100 -> 41.814 | AY100: =+AO100+AT100 -> 212.091 | AZ100: =+AX100-AY100 -> -170.277 | BA100: =+AQ100+AV100 -> 1515 | BB100: =+AX100-BA100 -> -1473.186 | BC100: 0 | BD100: =+ブリック!W99/1000 -> 0 | BE100: =+BC100-BD100 -> 0 | BG100: =+BC100-BF100 -> 0 | BH100: 0 | BI100: =+ルスツ羊蹄ぶた!W99/1000 -> 0 | BJ100: =+BH100-BI100 -> 0 | BL100: =+BH100-BK100 -> 0 | BM100: =+BC100+BH100 -> 0 | BN100: =+BD100+BI100 -> 0 | BO100: =+BM100-BN100 -> 0 | BP100: =+BF100+BK100 -> 0 | BQ100: =+BM100-BP100 -> 0 | BR100: 15 | BS100: =+料飲共通!W99/1000 -> 90.91 | BT100: =+BR100-BS100 -> -75.91 | BU100: 15 | BV100: =+BR100-BU100 -> 0 | BW100: =+T100+AI100+AX100+BM100+BR100 -> 623.286 | BX100: =+U100+AJ100+AY100+BN100+BS100 -> 388.008 | BY100: =+BW100-BX100 -> 235.278 | BZ100: =+W100+AL100+BA100+BU100 -> 2061 | CA100: =+BW100-BZ100 -> -1437.714
...

Sheet 料飲共通
A1: ■（Ｒ７年度）決見入力用 | V1: 料飲計 | W1: =X1+ﾇｰﾍﾞﾙﾌﾟｰｽ!X1+ｶﾌｪﾙﾎﾟ!X1+ｶﾌｪｾﾚｽﾃ!X1+ｼﾞｭｴﾙｽﾞ!X1+ｶﾞｰﾃﾞﾝ!X1+ﾋﾞｱｶﾞｰﾃﾞﾝ!X1+#REF! -> #REF! | X1: =SUM(K6:P6) -> 0
A3: 部門 料飲共通
A4: コード | B4: 名称 | K4: 令和 7年 4月 | L4: 令和 7年 5月 | M4: 令和 7年 6月 | N4: 令和 7年 7月 | O4: 令和 7年 8月 | P4: 令和 7年 9月 | Q4: 令和 7年 10月 | R4: 令和 7年 11月 | S4: 令和 7年 12月 | T4: 令和 8年 1月 | U4: 令和 8年 2月 | V4: 令和 8年 3月 | W4: 合計
K5: ①当期実績 | L5: ①当期実績 | M5: ①当期実績 | N5: ①当期実績 | O5: ①当期実績 | P5: ①当期実績 | Q5: ①当期実績 | R5: ①当期実績 | S5: ①当期実績 | T5: ①当期実績 | U5: ①当期実績 | V5: ①当期実績 | W5: ①当期実績
A6: 10000 | B6: 総売上高 | K6: =SUM(K7:K16) -> 0 | L6: =SUM(L7:L16) -> 0 | M6: =SUM(M7:M16) -> 0 | N6: =SUM(N7:N16) -> 0 | O6: =SUM(O7:O16) -> 0 | P6: =SUM(P7:P16) -> 0 | Q6: =SUM(Q7:Q16) -> 0 | R6: =SUM(R7:R16) -> 0 | ... V6: =SUM(V7:V16) -> 0 | W6: =SUM(K6:V6) -> 0
A7: 10001 | C7: 売上 | K7: 0 | L7: 0 | M7: 0 | N7: 0 | O7: 0 | P7: 0 | Q7: 0 | R7: 0 | S7: 0 | T7: 0 | U7: 0 | V7: 0 | W7: =SUM(K7:V7) -> 0
A8: 10002 | C8: 損保代理店収入 | K8: 0 | L8: 0 | M8: 0 | N8: 0 | O8: 0 | P8: 0 | Q8: 0 | R8: 0 | S8: 0 | T8: 0 | U8: 0 | V8: 0 | W8: =SUM(K8:V8) -> 0
A9: 10003 | C9: 販売手数料収入 | K9: 0 | L9: 0 | M9: 0 | N9: 0 | O9: 0 | P9: 0 | Q9: 0 | R9: 0 | S9: 0 | T9: 0 | U9: 0 | V9: 0 | W9: =SUM(K9:V9) -> 0
A10: 10004 | C10: 索道収入 | K10: 0 | L10: 0 | M10: 0 | N10: 0 | O10: 0 | P10: 0 | Q10: 0 | R10: 0 | S10: 0 | T10: 0 | U10: 0 | V10: 0 | W10: =SUM(K10:V10) -> 0
A11: 10005 | C11: 地代収入 | K11: 0 | L11: 0 | M11: 0 | N11: 0 | O11: 0 | P11: 0 | Q11: 0 | R11: 0 | S11: 0 | T11: 0 | U11: 0 | V11: 0 | W11: =SUM(K11:V11) -> 0
A12: 10006 | C12: 家賃収入 | K12: 0 | L12: 0 | M12: 0 | N12: 0 | O12: 0 | P12: 0 | Q12: 0 | R12: 0 | S12: 0 | T12: 0 | U12: 0 | V12: 0 | W12: =SUM(K12:V12) -> 0
A13: 10007 | C13: 駐車場収入 | K13: 0 | L13: 0 | M13: 0 | N13: 0 | O13: 0 | P13: 0 | Q13: 0 | R13: 0 | S13: 0 | T13: 0 | U13: 0 | V13: 0 | W13: =SUM(K13:V13) -> 0
A14: 10008 | C14: 受託料 | K14: 0 | L14: 0 | M14: 0 | N14: 0 | O14: 0 | P14: 0 | Q14: 0 | R14: 0 | S14: 0 | T14: 0 | U14: 0 | V14: 0 | W14: =SUM(K14:V14) -> 0
A15: 10009 | C15: 利用料金収入 | K15: 0 | L15: 0 | M15: 0 | N15: 0 | O15: 0 | P15: 0 | Q15: 0 | R15: 0 | S15: 0 | T15: 0 | U15: 0 | V15: 0 | W15: =SUM(K15:V15) -> 0
A16: 10010 | C16: 管理手数料収入 | K16: 0 | L16: 0 | M16: 0 | N16: 0 | O16: 0 | P16: 0 | Q16: 0 | R16: 0 | S16: 0 | T16: 0 | U16: 0 | V16: 0 | W16: =SUM(K16:V16) -> 0
A17: 20000 | B17: 売上原価 | K17: 0 | L17: 0 | M17: 0 | N17: 0 | O17: 0 | P17: 0 | Q17: 0 | R17: 0 | S17: 0 | T17: 0 | U17: 0 | V17: 0 | W17: =SUM(K17:V17) -> 0
A18: 30000 | B18: 売上総利益 | K18: =K6-K17 -> 0 | L18: =L6-L17 -> 0 | M18: =M6-M17 -> 0 | N18: =N6-N17 -> 0 | O18: =O6-O17 -> 0 | P18: =P6-P17 -> 0 | Q18: =Q6-Q17 -> 0 | R18: =R6-R17 -> 0 | ... V18: =V6-V17 -> 0 | W18: =SUM(K18:V18) -> 0
A19: 41000 | B19: 人件費 | K19: =SUM(K20:K22,K26,K29:K31,K35:K36) -> 2386237 | L19: =SUM(L20:L22,L26,L29:L31,L35:L36) -> 2305287 | M19: =SUM(M20:M22,M26,M29:M31,M35:M36) -> 7599611 | N19: =SUM(N20:N22,N26,N29:N31,N35:N36) -> 3490479 | O19: =SUM(O20:O22,O26,O29:O31,O35:O36) -> 2595707 | P19: =SUM(P20:P22,P26,P29:P31,P35:P36) -> 3171737 | Q19: =SUM(Q20:Q22,Q26,Q29:Q31,Q35:Q36) -> 3627377 | R19: =SUM(R20:R22,R26,R29:R31,R35:R36) -> 2574945 | ... V19: =SUM(V20:V22,V26,V29:V31,V35:V36) -> 3098926 | W19: =SUM(K19:V19) -> 44752275
A20: 41010 | C20: 役員報酬 | W20: =SUM(K20:V20) -> 0
A21: 41020 | C21: 社員給与費 | K21: 2253550 | L21: 2247346 | M21: 6924848 | N21: 2413738 | O21: 2477170 | P21: 2417693 | Q21: 3212961 | R21: 2511881 | S21: 7514872 | T21: 2580438 | U21: 2304378 | V21: 2304378 | W21: =SUM(K21:V21) -> 39163253
A22: 41030 | C22: 専門等給与費 | K22: =SUM(K23:K25) -> 0 | L22: =SUM(L23:L25) -> 0 | M22: =SUM(M23:M25) -> 0 | N22: =SUM(N23:N25) -> 0 | O22: =SUM(O23:O25) -> 55000 | P22: =SUM(P23:P25) -> 20350 | Q22: =SUM(Q23:Q25) -> 0 | R22: =SUM(R23:R25) -> 0 | ... V22: =SUM(V23:V25) -> 0 | W22: =SUM(K22:V22) -> 75350
A23: 41031 | D23: 専門 | W23: =SUM(K23:V23) -> 0
A24: 41032 | D24: 臨時 | W24: =SUM(K24:V24) -> 0
A25: 41033 | D25: パート | K25: 0 | L25: 0 | M25: 0 | N25: 0 | O25: 55000 | P25: 20350 | Q25: 0 | R25: 0 | S25: 0 | T25: 0 | W25: =SUM(K25:V25) -> 75350
A26: 41040 | C26: 退職金 | K26: 0 | L26: 0 | M26: 0 | N26: 0 | O26: 0 | P26: 0 | Q26: 0 | R26: 0 | S26: 0 | T26: 0 | U26: 0 | V26: 0 | W26: =SUM(K26:V26) -> 0
A27: 41041 | D27: 役員 | W27: =SUM(K27:V27) -> 0
A28: 41042 | D28: 社員 | W28: =SUM(K28:V28) -> 0
A29: 41050 | C29: 法定福利費 | K29: 0 | L29: 0 | M29: 607972 | N29: 980677 | O29: 0 | P29: 669484 | Q29: 351352 | R29: 0 | S29: 476895 | T29: 351352 | U29: 365742 | V29: =365742*2 -> 731484 | W29: =SUM(K29:V29) -> 4534958
A30: 41060 | C30: 退職年金掛金 | K30: 1200 | L30: 1200 | M30: 1200 | N30: 1200 | O30: 1200 | P30: 2000 | Q30: 2000 | R30: 2000 | S30: 2000 | T30: 2000 | U30: 2000 | V30: 2000 | W30: =SUM(K30:V30) -> 20000
A31: 41070 | C31: 福利厚生費 | K31: =SUM(K32:K34) -> 79150 | L31: =SUM(L32:L34) -> 4404 | M31: =SUM(M32:M34) -> 1800 | N31: =SUM(N32:N34) -> 36800 | O31: =SUM(O32:O34) -> 1800 | P31: =SUM(P32:P34) -> 3000 | Q31: =SUM(Q32:Q34) -> 3000 | R31: =SUM(R32:R34) -> 3000 | ... V31: =SUM(V32:V34) -> 3000 | W31: =SUM(K31:V31) -> 264054
A32: 41071 | D32: 福利厚生費 | K32: 1800 | L32: 4404 | M32: 1800 | N32: 36800 | O32: 1800 | P32: 3000 | Q32: 3000 | R32: 3000 | S32: 3000 | T32: 3000 | U32: 3000 | V32: 3000 | W32: =SUM(K32:V32) -> 67604
A33: 41072 | D33: 被服費 | K33: 77350 | L33: 0 | M33: 0 | N33: 0 | O33: 0 | P33: 0 | Q33: 0 | R33: 0 | S33: 119100 | T33: 0 | W33: =SUM(K33:V33) -> 196450
A34: 41073 | D34: 研修費 | W34: =SUM(K34:V34) -> 0
A35: 41080 | C35: 通勤費 | K35: 52337 | L35: 52337 | M35: 63791 | N35: 58064 | O35: 60537 | P35: 59210 | Q35: 58064 | R35: 58064 | S35: 58064 | T35: 58064 | U35: 58064 | V35: 58064 | W35: =SUM(K35:V35) -> 694660
A36: 41090 | C36: 引当金繰入額 | W36: =SUM(K36:V36) -> 0
A37: 42000 | B37: 物件費 | K37: =SUM(K38:K41,K46,K50,K57:K58,K61:K67,K70:K72,K78:K80,K83:K84) -> 101146 | L37: =SUM(L38:L41,L46,L50,L57:L58,L61:L67,L70:L72,L78:L80,L83:L84) -> 131605 | M37: =SUM(M38:M41,M46,M50,M57:M58,M61:M67,M70:M72,M78:M80,M83:M84) -> 204854 | N37: =SUM(N38:N41,N46,N50,N57:N58,N61:N67,N70:N72,N78:N80,N83:N84) -> 473643 | O37: =SUM(O38:O41,O46,O50,O57:O58,O61:O67,O70:O72,O78:O80,O83:O84) -> 116817 | P37: =SUM(P38:P41,P46,P50,P57:P58,P61:P67,P70:P72,P78:P80,P83:P84) -> 655512 | Q37: =SUM(Q38:Q41,Q46,Q50,Q57:Q58,Q61:Q67,Q70:Q72,Q78:Q80,Q83:Q84) -> 919340 | R37: =SUM(R38:R41,R46,R50,R57:R58,R61:R67,R70:R72,R78:R80,R83:R84) -> 164922 | ... V37: =SUM(V38:V41,V46,V50,V57:V58,V61:V67,V70:V72,V78:V80,V83:V84) -> 77800 | W37: =SUM(K37:V37) -> 4455652
A38: 42010 | C38: 消耗品費 | K38: 0 | L38: 16339 | M38: 92010 | N38: 216000 | O38: 0 | P38: 0 | Q38: 254851 | R38: 0 | S38: 0 | T38: 0 | U38: 0 | V38: 0 | W38: =SUM(K38:V38) -> 579200
A39: 42020 | C39: 事務用品費 | K39: 0 | L39: 800 | M39: 0 | N39: 0 | O39: 0 | P39: 0 | Q39: 0 | R39: 0 | S39: 0 | T39: 0 | U39: 0 | V39: 0 | W39: =SUM(K39:V39) -> 800
A40: 42030 | C40: 図書購入費 | K40: 0 | L40: 0 | M40: 0 | N40: 0 | O40: 0 | P40: 0 | Q40: 1670 | R40: 0 | S40: 0 | T40: 0 | U40: 0 | V40: 0 | W40: =SUM(K40:V40) -> 1670
A41: 42040 | C41: 賃借料 | K41: =SUM(K42:K45) -> 0 | L41: =SUM(L42:L45) -> 0 | M41: =SUM(M42:M45) -> 0 | N41: =SUM(N42:N45) -> 0 | O41: =SUM(O42:O45) -> 0 | P41: =SUM(P42:P45) -> 0 | Q41: =SUM(Q42:Q45) -> 0 | R41: =SUM(R42:R45) -> 0 | ... V41: =SUM(V42:V45) -> 0 | W41: =SUM(K41:V41) -> 0
A42: 42041 | D42: 土地使用料 | K42: 0 | L42: 0 | M42: 0 | N42: 0 | O42: 0 | P42: 0 | Q42: 0 | R42: 0 | S42: 0 | T42: 0 | U42: 0 | V42: 0 | W42: =SUM(K42:V42) -> 0
A43: 42042 | D43: 建物使用料 | K43: 0 | L43: 0 | M43: 0 | N43: 0 | O43: 0 | P43: 0 | Q43: 0 | R43: 0 | S43: 0 | T43: 0 | U43: 0 | V43: 0 | W43: =SUM(K43:V43) -> 0
A44: 42043 | D44: 施設使用料 | K44: 0 | L44: 0 | M44: 0 | N44: 0 | O44: 0 | P44: 0 | Q44: 0 | R44: 0 | S44: 0 | T44: 0 | U44: 0 | V44: 0 | W44: =SUM(K44:V44) -> 0
A45: 42044 | D45: リース料 | K45: 0 | L45: 0 | M45: 0 | N45: 0 | O45: 0 | P45: 0 | Q45: 0 | R45: 0 | S45: 0 | T45: 0 | U45: 0 | V45: 0 | W45: =SUM(K45:V45) -> 0
A46: 42050 | C46: 保険料 | K46: =SUM(K47:K49) -> 0 | L46: =SUM(L47:L49) -> 0 | M46: =SUM(M47:M49) -> 0 | N46: =SUM(N47:N49) -> 0 | O46: =SUM(O47:O49) -> 0 | P46: =SUM(P47:P49) -> 0 | Q46: =SUM(Q47:Q49) -> 0 | R46: =SUM(R47:R49) -> 0 | ... V46: =SUM(V47:V49) -> 0 | W46: =SUM(K46:V46) -> 0
A47: 42051 | D47: 火災保険料 | K47: 0 | L47: 0 | M47: 0 | N47: 0 | O47: 0 | P47: 0 | Q47: 0 | R47: 0 | S47: 0 | T47: 0 | U47: 0 | V47: 0 | W47: =SUM(K47:V47) -> 0
A48: 42052 | D48: 賠償保険料 | K48: 0 | L48: 0 | M48: 0 | N48: 0 | O48: 0 | P48: 0 | Q48: 0 | R48: 0 | S48: 0 | T48: 0 | U48: 0 | V48: 0 | W48: =SUM(K48:V48) -> 0
A49: 42053 | D49: 動産保険料 | K49: 0 | L49: 0 | M49: 0 | N49: 0 | O49: 0 | P49: 0 | Q49: 0 | R49: 0 | S49: 0 | T49: 0 | U49: 0 | V49: 0 | W49: =SUM(K49:V49) -> 0
A50: 42060 | C50: 修繕費 | K50: =SUM(K51:K56) -> 0 | L50: =SUM(L51:L56) -> 0 | M50: =SUM(M51:M56) -> 0 | N50: =SUM(N51:N56) -> 0 | O50: =SUM(O51:O56) -> 0 | P50: =SUM(P51:P56) -> 0 | Q50: =SUM(Q51:Q56) -> 0 | R50: =SUM(R51:R56) -> 0 | ... V50: =SUM(V51:V56) -> 0 | W50: =SUM(K50:V50) -> 0
A51: 42061 | D51: 建物 | K51: 0 | L51: 0 | M51: 0 | N51: 0 | O51: 0 | P51: 0 | Q51: 0 | R51: 0 | S51: 0 | T51: 0 | U51: 0 | V51: 0 | W51: =SUM(K51:V51) -> 0
A52: 42062 | D52: 建物付属設備 | K52: 0 | L52: 0 | M52: 0 | N52: 0 | O52: 0 | P52: 0 | Q52: 0 | R52: 0 | S52: 0 | T52: 0 | U52: 0 | V52: 0 | W52: =SUM(K52:V52) -> 0
A53: 42063 | D53: 構築物 | K53: 0 | L53: 0 | M53: 0 | N53: 0 | O53: 0 | P53: 0 | Q53: 0 | R53: 0 | S53: 0 | T53: 0 | U53: 0 | V53: 0 | W53: =SUM(K53:V53) -> 0
A54: 42064 | D54: 機械 | K54: 0 | L54: 0 | M54: 0 | N54: 0 | O54: 0 | P54: 0 | Q54: 0 | R54: 0 | S54: 0 | T54: 0 | U54: 0 | V54: 0 | W54: =SUM(K54:V54) -> 0
A55: 42065 | D55: 器具備品 | K55: 0 | L55: 0 | M55: 0 | N55: 0 | O55: 0 | P55: 0 | Q55: 0 | R55: 0 | S55: 0 | T55: 0 | U55: 0 | V55: 0 | W55: =SUM(K55:V55) -> 0
A56: 42066 | D56: 車両 | K56: 0 | L56: 0 | M56: 0 | N56: 0 | O56: 0 | P56: 0 | Q56: 0 | R56: 0 | S56: 0 | T56: 0 | U56: 0 | V56: 0 | W56: =SUM(K56:V56) -> 0
A57: 42070 | C57: 車両運搬費 | K57: 0 | L57: 0 | M57: 0 | N57: 0 | O57: 0 | P57: 0 | Q57: 0 | R57: 0 | S57: 0 | T57: 0 | U57: 0 | V57: 0 | W57: =SUM(K57:V57) -> 0
A58: 42080 | C58: 印刷製本費 | K58: =SUM(K59:K60) -> 71350 | L58: =SUM(L59:L60) -> 33000 | M58: =SUM(M59:M60) -> 0 | N58: =SUM(N59:N60) -> 0 | O58: =SUM(O59:O60) -> 0 | P58: =SUM(P59:P60) -> 0 | Q58: =SUM(Q59:Q60) -> 0 | R58: =SUM(R59:R60) -> 10000 | ... V58: =SUM(V59:V60) -> 0 | W58: =SUM(K58:V58) -> 114350
A59: 42081 | D59: 印刷製本費 | K59: 71350 | L59: 33000 | M59: 0 | N59: 0 | O59: 0 | P59: 0 | Q59: 0 | R59: 10000 | S59: 0 | T59: 0 | U59: 0 | V59: 0 | W59: =SUM(K59:V59) -> 114350
A60: 42082 | D60: 乗車券帳票費 | K60: 0 | L60: 0 | M60: 0 | N60: 0 | O60: 0 | P60: 0 | Q60: 0 | R60: 0 | S60: 0 | T60: 0 | U60: 0 | V60: 0 | W60: =SUM(K60:V60) -> 0
A61: 42090 | C61: 清掃衛生費 | K61: 0 | L61: 0 | M61: 0 | N61: 0 | O61: 0 | P61: 0 | Q61: 0 | R61: 0 | S61: 0 | T61: 0 | U61: 0 | V61: 0 | W61: =SUM(K61:V61) -> 0
A62: 42100 | C62: 事務会議費 | K62: 0 | L62: 0 | M62: 0 | N62: 0 | O62: 0 | P62: 0 | Q62: 17652 | R62: 0 | S62: 0 | T62: 0 | U62: 0 | V62: 0 | W62: =SUM(K62:V62) -> 17652
A63: 42110 | C63: 租税公課 | K63: 0 | L63: 0 | M63: 0 | N63: 0 | O63: 0 | P63: 0 | Q63: 0 | R63: 0 | S63: 0 | T63: 0 | U63: 0 | V63: 0 | W63: =SUM(K63:V63) -> 0
A64: 42120 | C64: 会費負担金 | K64: 0 | L64: 0 | M64: 0 | N64: 75000 | O64: 0 | P64: 0 | Q64: 0 | R64: 0 | S64: 115000 | T64: 0 | U64: 0 | V64: 0 | W64: =SUM(K64:V64) -> 190000
A65: 42130 | C65: 委託料 | K65: 7500 | L65: 31850 | M65: 36000 | N65: 20450 | O65: 13450 | P65: 27100 | Q65: 7500 | R65: 7500 | S65: 701250 | T65: 132000 | U65: 107500 | V65: 32000 | W65: =SUM(K65:V65) -> 1124100
A66: 42140 | C66: 除雪費 | K66: 0 | L66: 0 | M66: 0 | N66: 0 | O66: 0 | P66: 0 | Q66: 0 | R66: 0 | S66: 0 | T66: 0 | U66: 0 | V66: 0 | W66: =SUM(K66:V66) -> 0
A67: 42150 | C67: 販売促進費 | K67: =SUM(K68:K69) -> 1000 | L67: =SUM(L68:L69) -> 1000 | M67: =SUM(M68:M69) -> 1000 | N67: =SUM(N68:N69) -> 1000 | O67: =SUM(O68:O69) -> 1000 | P67: =SUM(P68:P69) -> 1000 | Q67: =SUM(Q68:Q69) -> 1000 | R67: =SUM(R68:R69) -> 1000 | ... V67: =SUM(V68:V69) -> 0 | W67: =SUM(K67:V67) -> 9000
A68: 42151 | D68: 販売促進費 | K68: 1000 | L68: 1000 | M68: 1000 | N68: 1000 | O68: 1000 | P68: 1000 | Q68: 1000 | R68: 1000 | S68: 1000 | T68: 0 | U68: 0 | V68: 0 | W68: =SUM(K68:V68) -> 9000
A69: 42152 | D69: 乗車券販売手数料 | K69: 0 | L69: 0 | M69: 0 | N69: 0 | O69: 0 | P69: 0 | Q69: 0 | R69: 0 | S69: 0 | T69: 0 | U69: 0 | V69: 0 | W69: =SUM(K69:V69) -> 0
A70: 42160 | C70: 旅費交通費 | K70: 21296 | L70: 33057 | M70: 74398 | N70: 41193 | O70: 57367 | P70: 40213 | Q70: 81400 | R70: 94168 | S70: 9421 | T70: 34000 | U70: 433000 | V70: 34000 | W70: =SUM(K70:V70) -> 953513
A71: 42170 | C71: 通信連絡費 | K71: 0 | L71: 15559 | M71: 1446 | N71: 0 | O71: 0 | P71: 187199 | Q71: 46418 | R71: 52254 | S71: 53242 | T71: 11800 | U71: 11800 | V71: 11800 | W71: =SUM(K71:V71) -> 391518
A72: 42180 | C72: 水道光熱費 | K72: =SUM(K73:K77) -> 0 | L72: =SUM(L73:L77) -> 0 | M72: =SUM(M73:M77) -> 0 | N72: =SUM(N73:N77) -> 0 | O72: =SUM(O73:O77) -> 0 | P72: =SUM(P73:P77) -> 0 | Q72: =SUM(Q73:Q77) -> 0 | R72: =SUM(R73:R77) -> 0 | ... V72: =SUM(V73:V77) -> 0 | W72: =SUM(K72:V72) -> 0
A73: 42181 | D73: 電灯使用料 | K73: 0 | L73: 0 | M73: 0 | N73: 0 | O73: 0 | P73: 0 | Q73: 0 | R73: 0 | S73: 0 | T73: 0 | U73: 0 | V73: 0 | W73: =SUM(K73:V73) -> 0
A74: 42182 | D74: 水道使用料 | K74: 0 | L74: 0 | M74: 0 | N74: 0 | O74: 0 | P74: 0 | Q74: 0 | R74: 0 | S74: 0 | T74: 0 | U74: 0 | V74: 0 | W74: =SUM(K74:V74) -> 0
A75: 42183 | D75: ガス使用料 | K75: 0 | L75: 0 | M75: 0 | N75: 0 | O75: 0 | P75: 0 | Q75: 0 | R75: 0 | S75: 0 | T75: 0 | U75: 0 | V75: 0 | W75: =SUM(K75:V75) -> 0
A76: 42184 | D76: 暖房燃料費 | K76: 0 | L76: 0 | M76: 0 | N76: 0 | O76: 0 | P76: 0 | Q76: 0 | R76: 0 | S76: 0 | T76: 0 | U76: 0 | V76: 0 | W76: =SUM(K76:V76) -> 0
A77: 42185 | D77: 電力使用料 | K77: 0 | L77: 0 | M77: 0 | N77: 0 | O77: 0 | P77: 0 | Q77: 0 | R77: 0 | S77: 0 | T77: 0 | U77: 0 | V77: 0 | W77: =SUM(K77:V77) -> 0
A78: 42190 | C78: 諸手数料 | K78: 0 | L78: 0 | M78: 0 | N78: 0 | O78: 0 | P78: 0 | Q78: 0 | R78: 0 | S78: 0 | T78: 0 | U78: 0 | V78: 0 | W78: =SUM(K78:V78) -> 0
A79: 42200 | C79: 広告宣伝費 | K79: 0 | L79: 0 | M79: 0 | N79: 120000 | O79: 45000 | P79: 400000 | Q79: 506700 | R79: 0 | S79: 0 | T79: 0 | U79: 0 | V79: 0 | W79: =SUM(K79:V79) -> 1071700
A80: 42210 | C80: 交際費 | K80: =SUM(K81:K82) -> 0 | L80: =SUM(L81:L82) -> 0 | M80: =SUM(M81:M82) -> 0 | N80: =SUM(N81:N82) -> 0 | O80: =SUM(O81:O82) -> 0 | P80: =SUM(P81:P82) -> 0 | Q80: =SUM(Q81:Q82) -> 2149 | R80: =SUM(R81:R82) -> 0 | ... V80: =SUM(V81:V82) -> 0 | W80: =SUM(K80:V80) -> 2149
A81: 42211 | D81: 接待交際費 | K81: 0 | L81: 0 | M81: 0 | N81: 0 | O81: 0 | P81: 0 | Q81: 2149 | R81: 0 | S81: 0 | T81: 0 | U81: 0 | V81: 0 | W81: =SUM(K81:V81) -> 2149
A82: 42212 | D82: 贈答用品費 | K82: 0 | L82: 0 | M82: 0 | N82: 0 | O82: 0 | P82: 0 | Q82: 0 | R82: 0 | S82: 0 | T82: 0 | U82: 0 | V82: 0 | W82: =SUM(K82:V82) -> 0
A83: 42220 | C83: 寄付金 | K83: 0 | L83: 0 | M83: 0 | N83: 0 | O83: 0 | P83: 0 | Q83: 0 | R83: 0 | S83: 0 | T83: 0 | U83: 0 | V83: 0 | W83: =SUM(K83:V83) -> 0
A84: 42230 | C84: 雑費用 | K84: 0 | L84: 0 | M84: 0 | N84: 0 | O84: 0 | P84: 0 | Q84: 0 | R84: 0 | S84: 0 | T84: 0 | U84: 0 | V84: 0 | W84: =SUM(K84:V84) -> 0
A85: 43000 | B85: 減価償却費 | K85: =SUM(K86:K96) -> 0 | L85: =SUM(L86:L96) -> 0 | M85: =SUM(M86:M96) -> 0 | N85: =SUM(N86:N96) -> 0 | O85: =SUM(O86:O96) -> 0 | P85: =SUM(P86:P96) -> 0 | Q85: =SUM(Q86:Q96) -> 20000 | R85: =SUM(R86:R96) -> 20000 | ... V85: =SUM(V86:V96) -> 20000 | W85: =SUM(K85:V85) -> 120000
A86: 43010 | C86: 建物 | W86: =SUM(K86:V86) -> 0
A87: 43020 | C87: 建物附属設備 | W87: =SUM(K87:V87) -> 0
A88: 43030 | C88: 構築物 | W88: =SUM(K88:V88) -> 0
A89: 43040 | C89: 機械・装置 | W89: =SUM(K89:V89) -> 0
A90: 43050 | C90: 器具備品 | W90: =SUM(K90:V90) -> 0
A91: 43060 | C91: 車両 | W91: =SUM(K91:V91) -> 0
A92: 43070 | C92: 少額資産 | K92: 0 | L92: 0 | M92: 0 | N92: 0 | O92: 0 | P92: 0 | Q92: 20000 | R92: 20000 | S92: 20000 | T92: 20000 | U92: 20000 | V92: 20000 | W92: =SUM(K92:V92) -> 120000
A93: 43080 | C93: 商標権 | W93: =SUM(K93:V93) -> 0
A94: 43090 | C94: ソフトウェア | W94: =SUM(K94:V94) -> 0
A95: 43100 | C95: 長期前払費用 | W95: =SUM(K95:V95) -> 0
A96: 43110 | C96: リース資産 | W96: =SUM(K96:V96) -> 0
A97: 40000 | B97: 販売費・一般管理費 | K97: =K37+K19+K85 -> 2487383 | L97: =L37+L19+L85 -> 2436892 | M97: =M37+M19+M85 -> 7804465 | N97: =N37+N19+N85 -> 3964122 | O97: =O37+O19+O85 -> 2712524 | P97: =P37+P19+P85 -> 3827249 | Q97: =Q37+Q19+Q85 -> 4566717 | R97: =R37+R19+R85 -> 2759867 | ... V97: =V37+V19+V85 -> 3196726 | W97: =SUM(K97:V97) -> 49327927
A98: 50000 | B98: 営業利益 | K98: =K18-K97 -> -2487383 | L98: =L18-L97 -> -2436892 | M98: =M18-M97 -> -7804465 | N98: =N18-N97 -> -3964122 | O98: =O18-O97 -> -2712524 | P98: =P18-P97 -> -3827249 | Q98: =Q18-Q97 -> -4566717 | R98: =R18-R97 -> -2759867 | ... V98: =V18-V97 -> -3196726 | W98: =SUM(K98:V98) -> -49327927
A99: 61000 | B99: 営業外収益 | K99: =SUM(K100,K104:K106) -> 0 | L99: =SUM(L100,L104:L106) -> 0 | M99: =SUM(M100,M104:M106) -> 0 | N99: =SUM(N100,N104:N106) -> 0 | O99: =SUM(O100,O104:O106) -> 0 | P99: =SUM(P100,P104:P106) -> 0 | Q99: =SUM(Q100,Q104:Q106) -> 90910 | R99: =SUM(R100,R104:R106) -> 0 | ... V99: =SUM(V100,V104:V106) -> 0 | W99: =SUM(K99:V99) -> 90910
A100: 61010 | C100: 受取利息 | K100: =SUM(K101:K103) -> 0 | L100: =SUM(L101:L103) -> 0 | M100: =SUM(M101:M103) -> 0 | N100: =SUM(N101:N103) -> 0 | O100: =SUM(O101:O103) -> 0 | P100: =SUM(P101:P103) -> 0 | Q100: =SUM(Q101:Q103) -> 0 | R100: =SUM(R101:R103) -> 0 | ... V100: =SUM(V101:V103) -> 0 | W100: =SUM(K100:V100) -> 0
A101: 61011 | D101: 定期預金 | W101: =SUM(K101:V101) -> 0
...

Sheet ﾇｰﾍﾞﾙﾌﾟｰｽ
A1: ■（Ｒ７年度）決見入力用 | X1: =SUM(K6:P6) -> 56965279
A3: 部門 ﾇｰﾍﾞﾙﾌﾟｰｽ
A4: コード | B4: 名称 | K4: 令和 7年 4月 | L4: 令和 7年 5月 | M4: 令和 7年 6月 | N4: 令和 7年 7月 | O4: 令和 7年 8月 | P4: 令和 7年 9月 | Q4: 令和 7年 10月 | R4: 令和 7年 11月 | S4: 令和 7年 12月 | T4: 令和 8年 1月 | U4: 令和 8年 2月 | V4: 令和 8年 3月 | W4: 合計
K5: ①当期実績 | L5: ①当期実績 | M5: ①当期実績 | N5: ①当期実績 | O5: ①当期実績 | P5: ①当期実績 | Q5: ①当期実績 | R5: ①当期実績 | S5: ①当期実績 | T5: ①当期実績 | U5: ①当期実績 | V5: ①当期実績 | W5: ①当期実績
A6: 10000 | B6: 総売上高 | K6: =SUM(K7:K16) -> 6617246 | L6: =SUM(L7:L16) -> 9674692 | M6: =SUM(M7:M16) -> 11211197 | N6: =SUM(N7:N16) -> 11386193 | O6: =SUM(O7:O16) -> 10032696 | P6: =SUM(P7:P16) -> 8043255 | Q6: =SUM(Q7:Q16) -> 8014887 | R6: =SUM(R7:R16) -> 8111329 | ... V6: =SUM(V7:V16) -> 5778135 | W6: =SUM(K6:V6) -> 101506705
A7: 10001 | C7: 売上 | K7: 6617246 | L7: 9674692 | M7: 11211197 | N7: 11386193 | O7: 10032696 | P7: 8043255 | Q7: 8014887 | R7: 8111329 | S7: 11008524 | T7: 5016623 | U7: 6611928 | V7: 5778135 | W7: =SUM(K7:V7) -> 101506705
A8: 10002 | C8: 損保代理店収入 | W8: =SUM(K8:V8) -> 0
A9: 10003 | C9: 販売手数料収入 | W9: =SUM(K9:V9) -> 0
A10: 10004 | C10: 索道収入 | W10: =SUM(K10:V10) -> 0
A11: 10005 | C11: 地代収入 | W11: =SUM(K11:V11) -> 0
A12: 10006 | C12: 家賃収入 | W12: =SUM(K12:V12) -> 0
A13: 10007 | C13: 駐車場収入 | W13: =SUM(K13:V13) -> 0
A14: 10008 | C14: 受託料 | W14: =SUM(K14:V14) -> 0
A15: 10009 | C15: 利用料金収入 | W15: =SUM(K15:V15) -> 0
A16: 10010 | C16: 管理手数料収入 | W16: =SUM(K16:V16) -> 0
A17: 20000 | B17: 売上原価 | K17: 1921100 | L17: 3165547 | M17: 2873716 | N17: 3410085 | O17: 2708957 | P17: 2358119 | Q17: 2783378 | R17: 1938045 | S17: 3207032 | T17: =T7*0.29 -> 1454820.7 | U17: =U7*0.29 -> 1917459.1 | V17: =V7*0.29 -> 1675659.1 | W17: =SUM(K17:V17) -> 29413918
A18: 30000 | B18: 売上総利益 | K18: =K6-K17 -> 4696146 | L18: =L6-L17 -> 6509145 | M18: =M6-M17 -> 8337481 | N18: =N6-N17 -> 7976108 | O18: =O6-O17 -> 7323739 | P18: =P6-P17 -> 5685136 | Q18: =Q6-Q17 -> 5231509 | R18: =R6-R17 -> 6173284 | ... V18: =V6-V17 -> 4102475.9 | W18: =SUM(K18:V18) -> 72092787
A19: 41000 | B19: 人件費 | K19: =SUM(K20:K22,K26,K29:K31,K35:K36) -> 3158420 | L19: =SUM(L20:L22,L26,L29:L31,L35:L36) -> 3442426 | M19: =SUM(M20:M22,M26,M29:M31,M35:M36) -> 7477766 | N19: =SUM(N20:N22,N26,N29:N31,N35:N36) -> 5440658 | O19: =SUM(O20:O22,O26,O29:O31,O35:O36) -> 4628298 | P19: =SUM(P20:P22,P26,P29:P31,P35:P36) -> 5244813 | Q19: =SUM(Q20:Q22,Q26,Q29:Q31,Q35:Q36) -> 4697409 | R19: =SUM(R20:R22,R26,R29:R31,R35:R36) -> 3924961 | ... V19: =SUM(V20:V22,V26,V29:V31,V35:V36) -> 5305968 | W19: =SUM(K19:V19) -> 63993442
A20: 41010 | C20: 役員報酬 | W20: =SUM(K20:V20) -> 0
A21: 41020 | C21: 社員給与費 | W21: =SUM(K21:V21) -> 0
A22: 41030 | C22: 専門等給与費 | K22: =SUM(K23:K25) -> 3059610 | L22: =SUM(L23:L25) -> 3321525 | M22: =SUM(M23:M25) -> 6400225 | N22: =SUM(N23:N25) -> 4234871 | O22: =SUM(O23:O25) -> 4461943 | P22: =SUM(P23:P25) -> 4065487 | Q22: =SUM(Q23:Q25) -> 4081512 | R22: =SUM(R23:R25) -> 3788416 | ... V22: =SUM(V23:V25) -> 3896495 | W22: =SUM(K22:V22) -> 55669735
A23: 41031 | D23: 専門 | K23: 3059610 | L23: 3098741 | M23: 6071782 | N23: 3837778 | O23: 4000839 | P23: 3639087 | Q23: 3750989 | R23: 3450389 | S23: 9726836 | T23: 4149452 | U23: 3805029 | V23: 3805029 | W23: =SUM(K23:V23) -> 52395561
A24: 41032 | D24: 臨時 | K24: 0 | L24: 164441 | M24: 266492 | N24: 282706 | O24: 446336 | P24: 401592 | Q24: 303222 | R24: 328127 | S24: 296959 | T24: 257004 | W24: =SUM(K24:V24) -> 2746879
A25: 41033 | D25: パート | K25: 0 | L25: 58343 | M25: 61951 | N25: 114387 | O25: 14768 | P25: 24808 | Q25: 27301 | R25: 9900 | S25: 42413 | T25: 36225 | U25: 45733 | V25: =45733*2 -> 91466 | W25: =SUM(K25:V25) -> 527295
A26: 41040 | C26: 退職金 | K26: 0 | L26: 0 | M26: 0 | N26: 0 | O26: 0 | P26: 0 | Q26: 0 | R26: 0 | S26: 0 | T26: 0 | U26: 0 | V26: 0 | W26: =SUM(K26:V26) -> 0
A27: 41041 | D27: 役員 | W27: =SUM(K27:V27) -> 0
A28: 41042 | D28: 社員 | W28: =SUM(K28:V28) -> 0
A29: 41050 | C29: 法定福利費 | K29: 0 | L29: 0 | M29: 919975 | N29: 876398 | O29: 0 | P29: 1014388 | Q29: 478505 | R29: 0 | S29: 522599 | T29: 553051 | U29: 630775 | V29: =630775*2 -> 1261550 | W29: =SUM(K29:V29) -> 6257241
A30: 41060 | C30: 退職年金掛金 | K30: 4600 | L30: 4600 | M30: 5600 | N30: 5600 | O30: 5600 | P30: 6000 | Q30: 6000 | R30: 6000 | S30: 6000 | T30: 6000 | U30: 6000 | V30: 6000 | W30: =SUM(K30:V30) -> 68000
A31: 41070 | C31: 福利厚生費 | K31: =SUM(K32:K34) -> 5400 | L31: =SUM(L32:L34) -> 5400 | M31: =SUM(M32:M34) -> 5400 | N31: =SUM(N32:N34) -> 159170 | O31: =SUM(O32:O34) -> 5400 | P31: =SUM(P32:P34) -> 6000 | Q31: =SUM(Q32:Q34) -> 6000 | R31: =SUM(R32:R34) -> 6000 | ... V31: =SUM(V32:V34) -> 6000 | W31: =SUM(K31:V31) -> 392020
A32: 41071 | D32: 福利厚生費 | K32: 5400 | L32: 5400 | M32: 5400 | N32: 5400 | O32: 5400 | P32: 6000 | Q32: 6000 | R32: 6000 | S32: 6000 | T32: 6000 | U32: 6000 | V32: 6000 | W32: =SUM(K32:V32) -> 69000
A33: 41072 | D33: 被服費 | K33: 0 | L33: 0 | M33: 0 | N33: 153770 | O33: 0 | P33: 0 | Q33: 0 | R33: 0 | S33: 169250 | T33: 0 | W33: =SUM(K33:V33) -> 323020
A34: 41073 | D34: 研修費 | W34: =SUM(K34:V34) -> 0
A35: 41080 | C35: 通勤費 | K35: 88810 | L35: 110901 | M35: 146566 | N35: 164619 | O35: 155355 | P35: 152938 | Q35: 125392 | R35: 124545 | S35: 129551 | T35: 135923 | U35: 135923 | V35: 135923 | W35: =SUM(K35:V35) -> 1606446
A36: 41090 | C36: 引当金繰入額 | W36: =SUM(K36:V36) -> 0
A37: 42000 | B37: 物件費 | K37: =SUM(K38:K41,K46,K50,K57:K58,K61:K67,K70:K72,K78:K80,K83:K84) -> 1173578 | L37: =SUM(L38:L41,L46,L50,L57:L58,L61:L67,L70:L72,L78:L80,L83:L84) -> 1575141 | M37: =SUM(M38:M41,M46,M50,M57:M58,M61:M67,M70:M72,M78:M80,M83:M84) -> 1940389 | N37: =SUM(N38:N41,N46,N50,N57:N58,N61:N67,N70:N72,N78:N80,N83:N84) -> 1532529 | O37: =SUM(O38:O41,O46,O50,O57:O58,O61:O67,O70:O72,O78:O80,O83:O84) -> 2043332 | P37: =SUM(P38:P41,P46,P50,P57:P58,P61:P67,P70:P72,P78:P80,P83:P84) -> 2061531 | Q37: =SUM(Q38:Q41,Q46,Q50,Q57:Q58,Q61:Q67,Q70:Q72,Q78:Q80,Q83:Q84) -> 1973446 | R37: =SUM(R38:R41,R46,R50,R57:R58,R61:R67,R70:R72,R78:R80,R83:R84) -> 2031045 | ... V37: =SUM(V38:V41,V46,V50,V57:V58,V61:V67,V70:V72,V78:V80,V83:V84) -> 1854283 | W37: =SUM(K37:V37) -> 22075142
A38: 42010 | C38: 消耗品費 | K38: 139692 | L38: 23460 | M38: 238410 | N38: 55889 | O38: 43091 | P38: 45660 | Q38: 279950 | R38: 440411 | S38: 284687 | T38: 178580 | U38: 25000 | V38: 20000 | W38: =SUM(K38:V38) -> 1774830
A39: 42020 | C39: 事務用品費 | K39: 0 | L39: 44193 | M39: 21825 | N39: 29075 | O39: 25711 | P39: 24204 | Q39: 33915 | R39: 16109 | S39: 15977 | T39: 20000 | U39: 20000 | V39: 40000 | W39: =SUM(K39:V39) -> 291009
A40: 42030 | C40: 図書購入費 | K40: 0 | L40: 0 | M40: 0 | N40: 0 | O40: 0 | P40: 0 | Q40: 0 | R40: 0 | S40: 0 | T40: 0 | U40: 0 | V40: 0 | W40: =SUM(K40:V40) -> 0
A41: 42040 | C41: 賃借料 | K41: =SUM(K42:K45) -> 33585 | L41: =SUM(L42:L45) -> 53183 | M41: =SUM(M42:M45) -> 216240 | N41: =SUM(N42:N45) -> 129895 | O41: =SUM(O42:O45) -> 133270 | P41: =SUM(P42:P45) -> 134656 | Q41: =SUM(Q42:Q45) -> 122648 | R41: =SUM(R42:R45) -> 123115 | ... V41: =SUM(V42:V45) -> 32300 | W41: =SUM(K41:V41) -> 1225430
A42: 42041 | D42: 土地使用料 | K42: 0 | L42: 0 | M42: 0 | N42: 0 | O42: 0 | P42: 0 | Q42: 0 | R42: 0 | S42: 0 | T42: 0 | U42: 0 | V42: 0 | W42: =SUM(K42:V42) -> 0
A43: 42042 | D43: 建物使用料 | K43: 0 | L43: 0 | M43: 0 | N43: 0 | O43: 0 | P43: 0 | Q43: 0 | R43: 0 | S43: 0 | T43: 0 | U43: 0 | V43: 0 | W43: =SUM(K43:V43) -> 0
A44: 42043 | D44: 施設使用料 | K44: 0 | L44: 0 | M44: 0 | N44: 0 | O44: 0 | P44: 0 | Q44: 0 | R44: 0 | S44: 0 | T44: 0 | U44: 0 | V44: 0 | W44: =SUM(K44:V44) -> 0
A45: 42044 | D45: リース料 | K45: 33585 | L45: 53183 | M45: 216240 | N45: 129895 | O45: 133270 | P45: 134656 | Q45: 122648 | R45: 123115 | S45: 122238 | T45: 90000 | U45: 34300 | V45: 32300 | W45: =SUM(K45:V45) -> 1225430
A46: 42050 | C46: 保険料 | K46: =SUM(K47:K49) -> 2947 | L46: =SUM(L47:L49) -> 0 | M46: =SUM(M47:M49) -> 0 | N46: =SUM(N47:N49) -> 0 | O46: =SUM(O47:O49) -> 0 | P46: =SUM(P47:P49) -> 0 | Q46: =SUM(Q47:Q49) -> 0 | R46: =SUM(R47:R49) -> 0 | ... V46: =SUM(V47:V49) -> 0 | W46: =SUM(K46:V46) -> 2947
A47: 42051 | D47: 火災保険料 | K47: 0 | L47: 0 | M47: 0 | N47: 0 | O47: 0 | P47: 0 | Q47: 0 | R47: 0 | S47: 0 | T47: 0 | U47: 0 | V47: 0 | W47: =SUM(K47:V47) -> 0
A48: 42052 | D48: 賠償保険料 | R48: 0 | S48: 0 | T48: 0 | U48: 0 | V48: 0 | W48: =SUM(K48:V48) -> 0
A49: 42053 | D49: 動産保険料 | K49: 2947 | L49: 0 | M49: 0 | N49: 0 | O49: 0 | P49: 0 | Q49: 0 | R49: 0 | S49: 0 | T49: 0 | U49: 0 | V49: 0 | W49: =SUM(K49:V49) -> 2947
A50: 42060 | C50: 修繕費 | K50: =SUM(K51:K56) -> 0 | L50: =SUM(L51:L56) -> 0 | M50: =SUM(M51:M56) -> 0 | N50: =SUM(N51:N56) -> 0 | O50: =SUM(O51:O56) -> 0 | P50: =SUM(P51:P56) -> 0 | Q50: =SUM(Q51:Q56) -> 0 | R50: =SUM(R51:R56) -> 79900 | ... V50: =SUM(V51:V56) -> 0 | W50: =SUM(K50:V50) -> 79900
A51: 42061 | D51: 建物 | K51: 0 | L51: 0 | M51: 0 | N51: 0 | O51: 0 | P51: 0 | Q51: 0 | R51: 0 | S51: 0 | T51: 0 | U51: 0 | V51: 0 | W51: =SUM(K51:V51) -> 0
A52: 42062 | D52: 建物付属設備 | K52: 0 | L52: 0 | M52: 0 | N52: 0 | O52: 0 | P52: 0 | Q52: 0 | R52: 0 | S52: 0 | T52: 0 | U52: 0 | V52: 0 | W52: =SUM(K52:V52) -> 0
A53: 42063 | D53: 構築物 | K53: 0 | L53: 0 | M53: 0 | N53: 0 | O53: 0 | P53: 0 | Q53: 0 | R53: 0 | S53: 0 | T53: 0 | U53: 0 | V53: 0 | W53: =SUM(K53:V53) -> 0
A54: 42064 | D54: 機械 | K54: 0 | L54: 0 | M54: 0 | N54: 0 | O54: 0 | P54: 0 | Q54: 0 | R54: 0 | S54: 0 | T54: 0 | U54: 0 | V54: 0 | W54: =SUM(K54:V54) -> 0
A55: 42065 | D55: 器具備品 | K55: 0 | L55: 0 | M55: 0 | N55: 0 | O55: 0 | P55: 0 | Q55: 0 | R55: 79900 | S55: 0 | T55: 0 | U55: 0 | V55: 0 | W55: =SUM(K55:V55) -> 79900
A56: 42066 | D56: 車両 | K56: 0 | L56: 0 | M56: 0 | N56: 0 | O56: 0 | P56: 0 | Q56: 0 | R56: 0 | S56: 0 | T56: 0 | U56: 0 | V56: 0 | W56: =SUM(K56:V56) -> 0
A57: 42070 | C57: 車両運搬費 | K57: 0 | L57: 0 | M57: 0 | N57: 0 | O57: 0 | P57: 0 | Q57: 0 | R57: 0 | S57: 0 | T57: 0 | U57: 0 | V57: 0 | W57: =SUM(K57:V57) -> 0
A58: 42080 | C58: 印刷製本費 | K58: =SUM(K59:K60) -> 84200 | L58: =SUM(L59:L60) -> 0 | M58: =SUM(M59:M60) -> 0 | N58: =SUM(N59:N60) -> 10000 | O58: =SUM(O59:O60) -> 13640 | P58: =SUM(P59:P60) -> 0 | Q58: =SUM(Q59:Q60) -> 0 | R58: =SUM(R59:R60) -> 0 | ... V58: =SUM(V59:V60) -> 0 | W58: =SUM(K58:V58) -> 107840
A59: 42081 | D59: 印刷製本費 | K59: 84200 | L59: 0 | M59: 0 | N59: 10000 | O59: 13640 | P59: 0 | Q59: 0 | R59: 0 | S59: 0 | T59: 0 | U59: 0 | V59: 0 | W59: =SUM(K59:V59) -> 107840
A60: 42082 | D60: 乗車券帳票費 | K60: 0 | L60: 0 | M60: 0 | N60: 0 | O60: 0 | P60: 0 | Q60: 0 | R60: 0 | S60: 0 | T60: 0 | U60: 0 | V60: 0 | W60: =SUM(K60:V60) -> 0
A61: 42090 | C61: 清掃衛生費 | K61: 0 | L61: 27704 | M61: 17623 | N61: 15268 | O61: 15586 | P61: 35799 | Q61: 80760 | R61: 14374 | S61: 11125 | T61: 50000 | U61: 59900 | V61: 58900 | W61: =SUM(K61:V61) -> 387039
A62: 42100 | C62: 事務会議費 | K62: 0 | L62: 0 | M62: 0 | N62: 0 | O62: 0 | P62: 0 | Q62: 0 | R62: 0 | S62: 0 | T62: 0 | U62: 0 | V62: 0 | W62: =SUM(K62:V62) -> 0
A63: 42110 | C63: 租税公課 | K63: 0 | L63: 0 | M63: 0 | N63: 1000 | O63: 0 | P63: 0 | Q63: 2000 | R63: 0 | S63: 0 | T63: 0 | U63: 0 | V63: 0 | W63: =SUM(K63:V63) -> 3000
A64: 42120 | C64: 会費負担金 | K64: 0 | L64: 50000 | M64: 0 | N64: 0 | O64: 0 | P64: 0 | Q64: 0 | R64: 0 | S64: 30000 | T64: 100000 | U64: 0 | V64: 0 | W64: =SUM(K64:V64) -> 180000
A65: 42130 | C65: 委託料 | K65: 174730 | L65: 341465 | M65: 357807 | N65: 395170 | O65: 426257 | P65: 386573 | Q65: 348374 | R65: 338552 | S65: 531464 | T65: 279620 | U65: 224620 | V65: 224620 | W65: =SUM(K65:V65) -> 4029252
A66: 42140 | C66: 除雪費 | K66: 0 | L66: 0 | M66: 0 | N66: 0 | O66: 0 | P66: 0 | Q66: 0 | R66: 0 | S66: 0 | T66: 0 | U66: 0 | V66: 0 | W66: =SUM(K66:V66) -> 0
A67: 42150 | C67: 販売促進費 | K67: =SUM(K68:K69) -> 259640 | L67: =SUM(L68:L69) -> 296511 | M67: =SUM(M68:M69) -> 292145 | N67: =SUM(N68:N69) -> 230930 | O67: =SUM(O68:O69) -> 417822 | P67: =SUM(P68:P69) -> 343053 | Q67: =SUM(Q68:Q69) -> 266810 | R67: =SUM(R68:R69) -> 245999 | ... V67: =SUM(V68:V69) -> 269340 | W67: =SUM(K67:V67) -> 3798322
A68: 42151 | D68: 販売促進費 | K68: 259640 | L68: 296511 | M68: 292145 | N68: 230930 | O68: 417822 | P68: 343053 | Q68: 266810 | R68: 245999 | S68: 328682 | T68: 537806 | U68: 309584 | V68: 269340 | W68: =SUM(K68:V68) -> 3798322
A69: 42152 | D69: 乗車券販売手数料 | K69: 0 | L69: 0 | M69: 0 | N69: 0 | O69: 0 | P69: 0 | Q69: 0 | R69: 0 | S69: 0 | T69: 0 | U69: 0 | V69: 0 | W69: =SUM(K69:V69) -> 0
A70: 42160 | C70: 旅費交通費 | K70: 12700 | L70: 7646 | M70: 4528 | N70: 10464 | O70: 22172 | P70: 5028 | Q70: 10219 | R70: 0 | S70: 0 | T70: 3500 | U70: 3500 | V70: 3500 | W70: =SUM(K70:V70) -> 83257
A71: 42170 | C71: 通信連絡費 | K71: 660 | L71: 20883 | M71: 21604 | N71: 9503 | O71: 9624 | P71: 17054 | Q71: 17551 | R71: 10365 | S71: 10363 | T71: 31200 | U71: 26200 | V71: 51100 | W71: =SUM(K71:V71) -> 226107
A72: 42180 | C72: 水道光熱費 | K72: =SUM(K73:K77) -> 440409 | L72: =SUM(L73:L77) -> 685056 | M72: =SUM(M73:M77) -> 745191 | N72: =SUM(N73:N77) -> 620335 | O72: =SUM(O73:O77) -> 779124 | P72: =SUM(P73:P77) -> 703898 | Q72: =SUM(Q73:Q77) -> 678173 | R72: =SUM(R73:R77) -> 537180 | ... V72: =SUM(V73:V77) -> 879523 | W72: =SUM(K72:V72) -> 8555376
A73: 42181 | D73: 電灯使用料 | K73: 440409 | L73: 375559 | M73: 414620 | N73: 415324 | O73: 429467 | P73: 395239 | Q73: 362459 | R73: 370795 | S73: 395707 | T73: 408314 | U73: 415371 | V73: 419086 | W73: =SUM(K73:V73) -> 4842350
A74: 42182 | D74: 水道使用料 | K74: 0 | L74: 0 | M74: 101054 | N74: 0 | O74: 96595 | P74: 0 | Q74: 102425 | R74: 0 | S74: 87334 | T74: 0 | U74: 90000 | V74: 90000 | W74: =SUM(K74:V74) -> 567408
A75: 42183 | D75: ガス使用料 | K75: 0 | L75: 309497 | M75: 229517 | N75: 205011 | O75: 253062 | P75: 308659 | Q75: 213289 | R75: 166385 | S75: 237888 | T75: 442939 | U75: 408934 | V75: 370437 | W75: =SUM(K75:V75) -> 3145618
A76: 42184 | D76: 暖房燃料費 | K76: 0 | L76: 0 | M76: 0 | N76: 0 | O76: 0 | P76: 0 | Q76: 0 | R76: 0 | S76: 0 | T76: 0 | U76: 0 | V76: 0 | W76: =SUM(K76:V76) -> 0
A77: 42185 | D77: 電力使用料 | K77: 0 | L77: 0 | M77: 0 | N77: 0 | O77: 0 | P77: 0 | Q77: 0 | R77: 0 | S77: 0 | T77: 0 | U77: 0 | V77: 0 | W77: =SUM(K77:V77) -> 0
A78: 42190 | C78: 諸手数料 | K78: 15 | L78: 40 | M78: 16 | N78: 0 | O78: 35 | P78: 606 | Q78: 46 | R78: 40 | S78: 35 | T78: 0 | U78: 0 | V78: 0 | W78: =SUM(K78:V78) -> 833
A79: 42200 | C79: 広告宣伝費 | K79: 25000 | L79: 25000 | M79: 25000 | N79: 25000 | O79: 157000 | P79: 365000 | Q79: 133000 | R79: 225000 | S79: 25000 | T79: 25000 | U79: 25000 | V79: 275000 | W79: =SUM(K79:V79) -> 1330000
A80: 42210 | C80: 交際費 | K80: =SUM(K81:K82) -> 0 | L80: =SUM(L81:L82) -> 0 | M80: =SUM(M81:M82) -> 0 | N80: =SUM(N81:N82) -> 0 | O80: =SUM(O81:O82) -> 0 | P80: =SUM(P81:P82) -> 0 | Q80: =SUM(Q81:Q82) -> 0 | R80: =SUM(R81:R82) -> 0 | ... V80: =SUM(V81:V82) -> 0 | W80: =SUM(K80:V80) -> 0
A81: 42211 | D81: 接待交際費 | K81: 0 | L81: 0 | M81: 0 | N81: 0 | O81: 0 | P81: 0 | Q81: 0 | R81: 0 | S81: 0 | T81: 0 | U81: 0 | V81: 0 | W81: =SUM(K81:V81) -> 0
A82: 42212 | D82: 贈答用品費 | K82: 0 | L82: 0 | M82: 0 | N82: 0 | O82: 0 | P82: 0 | Q82: 0 | R82: 0 | S82: 0 | T82: 0 | U82: 0 | V82: 0 | W82: =SUM(K82:V82) -> 0
A83: 42220 | C83: 寄付金 | K83: 0 | L83: 0 | M83: 0 | N83: 0 | O83: 0 | P83: 0 | Q83: 0 | R83: 0 | S83: 0 | T83: 0 | U83: 0 | V83: 0 | W83: =SUM(K83:V83) -> 0
A84: 42230 | C84: 雑費用 | K84: 0 | L84: 0 | M84: 0 | N84: 0 | O84: 0 | P84: 0 | Q84: 0 | R84: 0 | S84: 0 | T84: 0 | U84: 0 | V84: 0 | W84: =SUM(K84:V84) -> 0
A85: 43000 | B85: 減価償却費 | K85: =SUM(K86:K96) -> 612069 | L85: =SUM(L86:L96) -> 612069 | M85: =SUM(M86:M96) -> 322155 | N85: =SUM(N86:N96) -> 322130 | O85: =SUM(O86:O96) -> 322130 | P85: =SUM(P86:P96) -> 322130 | Q85: =SUM(Q86:Q96) -> 322130 | R85: =SUM(R86:R96) -> 331860 | ... V85: =SUM(V86:V96) -> 300500 | W85: =SUM(K85:V85) -> 4460376
A86: 43010 | C86: 建物 | W86: =SUM(K86:V86) -> 0
A87: 43020 | C87: 建物附属設備 | W87: =SUM(K87:V87) -> 0
A88: 43030 | C88: 構築物 | W88: =SUM(K88:V88) -> 0
A89: 43040 | C89: 機械・装置 | W89: =SUM(K89:V89) -> 0
A90: 43050 | C90: 器具備品 | K90: 588208 | L90: 588208 | M90: 298294 | N90: 298269 | O90: 298269 | P90: 298269 | Q90: 298269 | R90: 298269 | S90: 298269 | T90: 298269 | U90: 295892 | V90: 266895 | W90: =SUM(K90:V90) -> 4125380
A91: 43060 | C91: 車両 | W91: =SUM(K91:V91) -> 0
A92: 43070 | C92: 少額資産 | K92: 18195 | L92: 18195 | M92: 18195 | N92: 18195 | O92: 18195 | P92: 18195 | Q92: 18195 | R92: 27925 | S92: 27925 | T92: 27925 | U92: 27925 | V92: 27932 | W92: =SUM(K92:V92) -> 266997
A93: 43080 | C93: 商標権 | W93: =SUM(K93:V93) -> 0
A94: 43090 | C94: ソフトウェア | K94: 5666 | L94: 5666 | M94: 5666 | N94: 5666 | O94: 5666 | P94: 5666 | Q94: 5666 | R94: 5666 | S94: 5666 | T94: 5666 | U94: 5666 | V94: 5673 | W94: =SUM(K94:V94) -> 67999
A95: 43100 | C95: 長期前払費用 | W95: =SUM(K95:V95) -> 0
A96: 43110 | C96: リース資産 | W96: =SUM(K96:V96) -> 0
A97: 40000 | B97: 販売費・一般管理費 | K97: =K37+K19+K85 -> 4944067 | L97: =L37+L19+L85 -> 5629636 | M97: =M37+M19+M85 -> 9740310 | N97: =N37+N19+N85 -> 7295317 | O97: =O37+O19+O85 -> 6993760 | P97: =P37+P19+P85 -> 7628474 | Q97: =Q37+Q19+Q85 -> 6992985 | R97: =R37+R19+R85 -> 6287866 | ... V97: =V37+V19+V85 -> 7460751 | W97: =SUM(K97:V97) -> 90528960
A98: 50000 | B98: 営業利益 | K98: =K18-K97 -> -247921 | L98: =L18-L97 -> 879509 | M98: =M18-M97 -> -1402829 | N98: =N18-N97 -> 680791 | O98: =O18-O97 -> 329979 | P98: =P18-P97 -> -1943338 | Q98: =Q18-Q97 -> -1761476 | R98: =R18-R97 -> -114582 | ... V98: =V18-V97 -> -3358275.1 | W98: =SUM(K98:V98) -> -18436173
