Workbook

Sheet レビュー
A1: 【R5 さっぽろテレビ塔ビアガーデン振り返り】
A2: ①売上 | I2: 単位：円 | K2: ①コメント
A3: 月 | B3: 実績 | C3: 予算 | D3: 予算比 | E3: 差異 | F3: 予測 | G3: 予測比 | H3: 差異 | I3: 1日平均売上 | J3: 平均気温 | K3: 売上については左記の通り、対予算123.9％にて終了いたしました。コロナ禍前の2019年と比較しても対比125.4％（+22,223千円）の結果となりました。これまで1億円の大台に達したことはなかったということです。その大きな要因としてはスタッフの頑張りはもちろんですが、やはり史上稀に見る猛暑となったことが挙げられます。特に6月と8月は気象庁の観測史上最高値を記録し、7月においても史上2番目の平均気温となりました。ただ、天候要因については影響値として一定の条件下で記録していかなければならないもので、いかにこの天候要因を限定的にできるか？というのが引き続きの課題となります。※各月に天候要因を数値化したものを載せています。次年度へ向け今年度のデータを活かし、テーブル配置・スタッフアサインメント・予約システム再構築・RPA/DX 促進・メニューラインナップの見直し等により、さらにポテンシャルを引き出し売上を積み上げられると認識しています。
A4: 5 | B4: 1795227.3 | C4: 6890000 | D4: =B4/C4 -> 0.26055548 | E4: =B4-C4 -> -5094772.7 | F4: 1963000 | G4: =B4/F4 -> 0.91453249 | H4: =B4-F4 -> -167772.73 | I4: =B4/S4 -> 359045.45 | J4: 13.8℃ | S4: 5
A5: 6 | B5: 19049727 | C5: 25440000 | D5: =B5/C5 -> 0.74881003 | E5: =B5-C5 -> -6390272.7 | F5: 17338000 | G5: =B5/F5 -> 1.0987269 | H5: =B5-F5 -> 1711727.3 | I5: =B5/S5 -> 634990.91 | J5: 19.3℃ | S5: 30
A6: 7 | B6: 44856909 | C6: 25440000 | D6: =B6/C6 -> 1.7632433 | E6: =B6-C6 -> 19416909 | F6: 35016000 | G6: =B6/F6 -> 1.2810404 | H6: =B6-F6 -> 9840909.1 | I6: =B6/S6 -> 1446997.1 | J6: 23.8℃ | S6: 31
A7: 8 | B7: 44863045 | C7: 25440000 | D7: =B7/C7 -> 1.7634845 | E7: =B7-C7 -> 19423045 | F7: 39760000 | G7: =B7/F7 -> 1.1283462 | H7: =B7-F7 -> 5103045.5 | I7: =B7/S7 -> 1447195 | J7: 26.7℃ | S7: 31
A8: 9 | B8: 4058727.3 | C8: 9275000 | D8: =B8/C8 -> 0.43759863 | E8: =B8-C8 -> -5216272.7 | F8: 4300000 | G8: =B8/F8 -> 0.94389006 | H8: =B8-F8 -> -241272.73 | I8: =B8/S8 -> 1352909.1 | J8: 24.7℃ | S8: 3
A9: TOTAL | B9: =SUM(B4:B8) -> 1.1462364e+08 | C9: =SUM(C4:C8) -> 92485000 | D9: =B9/C9 -> 1.2393754 | E9: =B9-C9 -> 22138636 | F9: =SUM(F4:F8) -> 98377000 | G9: =B9/F9 -> 1.1651467 | H9: =B9-F9 -> 16246636 | I9: =B9/S9 -> 1146236.4 | S9: 100
A11: ②客数 | I11: 単位：名 | K11: ②コメント
A12: 月 | B12: 実績 | C12: 予算 | D12: 予算比 | E12: 差異 | F12: 予測 | G12: 予測比 | H12: 差異 | I12: 1日平均 | K12: 入客実績は左記の通りです。7/21（金）から8/16（土）の間で開催された大通りビアガーデン期間中も1日平均405名の入客となり、客数減少懸念は杞憂となりました。過去開催の数値によると盆明けは下降線を辿るはずでしたが、①にもある通り観測史上最高の平均気温となったことやチケットの駆け込み利用もあり、勢いを保ったまま最終日まで賑わいが続きました。シーズン設定をして6月末までは20:30クローズ、7月1日〜は21:30クローズとしたことは大きな成果に繋がったと考えています。7/22（土）が717名の来場とピーク、また、この週（7月第4週・通期では第9週）が最大の売上・入客となりました。次年度は予約システムをさらに活用し、入客を引き上げたいと考えています。
A13: 5 | B13: 506 | C13: 1300 | D13: =B13/C13 -> 0.38923077 | E13: =B13-C13 -> -794 | F13: 395 | G13: =B13/F13 -> 1.2810127 | H13: =B13-F13 -> 111 | I13: =B13/S13 -> 101.2 | S13: 5
A14: 6 | B14: 5309 | C14: 4800 | D14: =B14/C14 -> 1.1060417 | E14: =B14-C14 -> 509 | F14: 3450 | G14: =B14/F14 -> 1.5388406 | H14: =B14-F14 -> 1859 | I14: =B14/S14 -> 176.96667 | S14: 30
A15: 7 | B15: 11036 | C15: 4800 | D15: =B15/C15 -> 2.2991667 | E15: =B15-C15 -> 6236 | F15: 7050 | G15: =B15/F15 -> 1.5653901 | H15: =B15-F15 -> 3986 | I15: =B15/S15 -> 356 | S15: 31
A16: 8 | B16: 11093 | C16: 4800 | D16: =B16/C16 -> 2.3110417 | E16: =B16-C16 -> 6293 | F16: 8100 | G16: =B16/F16 -> 1.3695062 | H16: =B16-F16 -> 2993 | I16: =B16/S16 -> 357.83871 | S16: 31
A17: 9 | B17: 974 | C17: 1750 | D17: =B17/C17 -> 0.55657143 | E17: =B17-C17 -> -776 | F17: 880 | G17: =B17/F17 -> 1.1068182 | H17: =B17-F17 -> 94 | I17: =B17/S17 -> 324.66667 | S17: 3
A18: TOTAL | B18: =SUM(B13:B17) -> 28918 | C18: =SUM(C13:C17) -> 17450 | D18: =B18/C18 -> 1.657192 | E18: =B18-C18 -> 11468 | F18: =SUM(F13:F17) -> 19875 | G18: =B18/F18 -> 1.4549937 | H18: =B18-F18 -> 9043 | I18: =B18/S18 -> 289.18 | S18: 100
A20: ③-1 客単価 | I20: 単位：円 | K20: ③コメント
A21: 月 | B21: 実績 | C21: 予算 | D21: 予算比 | E21: 差異 | F21: 予測 | G21: 予測比 | H21: 差異 | K21: 通期での客単価は3,964円にて着地いたしました。予算設定時点では80%がプラン利用を想定しての数値でしたので、予算値からはマイナスとなっています。最終的にプラン利用率は53.6%となり、アラカルト（単品）利用率を上回りました。左記データから読み取れるのは、とてもシンプルですが、パッサージュ（フリー入客）利用率が高いと客単価が下がるという事実と、予約数を高めることにより客単価が伸びるという事実です。このことから、次年度は今回25％程であった予約利用率を35％程度まで引き上げることで、いわゆる「値上げ」の必要がなく、客単価と入客の天秤関係を限定的にしながら、【入客を高めつつ客単価も引き上げることができる】という伸び代を確認することができました。また今回はテーブルチェックを導入し、専用LPと紐付けして予約受注を行ったことにより、約83%の方がWebから予約をしてくださいました。これまでの開催は全て電話予約で対応し紙台帳管理をしていたという課題を、予約システム導入によって解決できた大きな成果と認められます。現地オペレーションとの連携を高めていけば、まだまだこうしたシステムを活かすことができます。今年度実績を基にし、人員発注と人員配置、予約システムの強みをさらに引き出しての予約受注強化（相性が良いと見られるLINE/L-STEPの活用など）や、天候要件の影響値を最小化（※悪天候時でも当日キャンセルは2割に満たない）していくことで、次年度は客席拡大、スタッフ増員に強気で臨むことができます。設備を含めて改善しつつ、さらに客単価を10％程度引き上げることで、売上も今年度の1日平均114万円から130万円（合計1億3,000万円）までは伸ばすことができると確信しています。
A22: 5 | B22: =B4/B13 -> 3547.88 | C22: 5300 | D22: =B22/C22 -> 0.66941132 | E22: =B22-C22 -> -1752.12 | F22: 4970 | G22: =B22/F22 -> 0.71385915 | H22: =B22-F22 -> -1422.12
A23: 6 | B23: =B5/B14 -> 3588.195 | C23: 5300 | D23: =B23/C23 -> 0.67701793 | E23: =B23-C23 -> -1711.805 | F23: 5026 | G23: =B23/F23 -> 0.71392658 | H23: =B23-F23 -> -1437.805
A24: 7 | B24: =B6/B15 -> 4064.5985 | C24: 5300 | D24: =B24/C24 -> 0.76690538 | E24: =B24-C24 -> -1235.4015 | F24: 4967 | G24: =B24/F24 -> 0.81832062 | H24: =B24-F24 -> -902.4015
A25: 8 | B25: =B7/B16 -> 4044.2662 | C25: 5300 | D25: =B25/C25 -> 0.7630691 | E25: =B25-C25 -> -1255.7338 | F25: 4909 | G25: =B25/F25 -> 0.82384727 | H25: =B25-F25 -> -864.73376
A26: 9 | B26: =B8/B17 -> 4167.0711 | C26: 5300 | D26: =B26/C26 -> 0.78623983 | E26: =B26-C26 -> -1132.9289 | F26: 4886 | G26: =B26/F26 -> 0.85285942 | H26: =B26-F26 -> -718.92888
A27: TOTAL | B27: =B9/B18 -> 3963.747 | C27: =C9/C18 -> 5300 | D27: =B27/C27 -> 0.7478768 | E27: =B27-C27 -> -1336.253 | F27: =F9/F18 -> 4949.7862 | G27: =B27/F27 -> 0.80079157 | H27: =B27-F27 -> -986.03914
A29: ③-2 プラン出卓数と月別プラン利用率
A30: 月 | B30: 客数 | C30: 5,500プラン | D30: 利用率 | E30: 6,600プラン | F30: 利用率 | G30: 8,800プラン | H30: 利用率 | I30: 小計
A31: 5 | B31: 506 | C31: 205 | D31: =C31/B31 -> 0.40513834 | E31: 7 | F31: =E31/B31 -> 0.013833992 | G31: 2 | H31: =G31/B31 -> 0.0039525692 | I31: =C31+E31+G31 -> 214
A32: 6 | B32: 5309 | C32: 2074 | D32: =C32/B32 -> 0.39065737 | E32: 80 | F32: =E32/B32 -> 0.015068751 | G32: 9 | H32: =G32/B32 -> 0.0016952345 | I32: =C32+E32+G32 -> 2163
A33: 7 | B33: 11036 | C33: 5792 | D33: =C33/B33 -> 0.52482784 | E33: 190 | F33: =E33/B33 -> 0.017216383 | G33: 161 | H33: =G33/B33 -> 0.014588619 | I33: =C33+E33+G33 -> 6143
A34: 8 | B34: 11093 | C34: 5149 | D34: =C34/B34 -> 0.46416659 | E34: 271 | F34: =E34/B34 -> 0.024429821 | G34: 77 | H34: =G34/B34 -> 0.0069413143 | I34: =C34+E34+G34 -> 5497
A35: 9 | B35: 974 | C35: 314 | D35: =C35/B35 -> 0.32238193 | E35: 34 | F35: =E35/B35 -> 0.034907598 | G35: 9 | H35: =G35/B35 -> 0.0092402464 | I35: =C35+E35+G35 -> 357
A36: TOTAL | B36: =SUM(B31:B35) -> 28918 | C36: =SUM(C31:C35) -> 13534 | D36: =C36/B36 -> 0.468013 | E36: =SUM(E31:E35) -> 582 | F36: =E36/B36 -> 0.020125873 | G36: =SUM(G31:G35) -> 258 | H36: =G36/B36 -> 0.0089217788 | I36: =C36+E36+G36 -> 14374
A37: 月 | B37: 客数 | C37: チケットプラン | D37: 利用率 | E37: プラン合計 | F37: 利用率 | G37: アラカルト利用 | H37: 利用率
A38: 5 | B38: 506 | C38: 0 | D38: =C38/B38 -> 0 | E38: =C38+I31 -> 214 | F38: =E38/B38 -> 0.4229249 | G38: =B38-E38 -> 292 | H38: =G38/B38 -> 0.5770751 | K38: ④memo
A39: 6 | B39: 5309 | C39: 0 | D39: =C39/B39 -> 0 | E39: =C39+I32 -> 2163 | F39: =E39/B39 -> 0.40742136 | G39: =B39-E39 -> 3146 | H39: =G39/B39 -> 0.59257864 | K39: 設備・備品課題※情報共有前 ◆英字メニュー ◆テーブル番号札（視認性・会計） ◆会計カード（プラスチック札）の作成 ◆会計の仕方がわからない ◆キャッシュレス決済が行えることの告知 ◆エクスキューズ（場内案内・トイレ・会計方法など） ◆飲み放題と単品オーダーの判別がつきづらい ◆床清掃の定期スケジュールと不定期実施のオペレーション ◆ワインの利用方法と場所 ◆ワインコーナーにローズマリーのプランター設置 ◆イベント開催 ◆キャッシャー増設検討 ◆ジョッキのサイズ ◆グラス洗浄マシンとの相性 ◆鍋洗い機（高圧洗浄機）の複数洗浄機導入 ◆Wi-Fi環境 ◆問い合わせ専用電話の設置
A40: 7 | B40: 11036 | C40: 107 | D40: =C40/B40 -> 0.0096955419 | E40: =C40+I33 -> 6250 | F40: =E40/B40 -> 0.56632838 | G40: =B40-E40 -> 4786 | H40: =G40/B40 -> 0.43367162
A41: 8 | B41: 11093 | C41: 765 | D41: =C41/B41 -> 0.068962409 | E41: =C41+I34 -> 6262 | F41: =E41/B41 -> 0.56450014 | G41: =B41-E41 -> 4831 | H41: =G41/B41 -> 0.43549986
A42: 9 | B42: 974 | C42: 240 | D42: =C42/B42 -> 0.24640657 | E42: =C42+I35 -> 597 | F42: =E42/B42 -> 0.61293634 | G42: =B42-E42 -> 377 | H42: =G42/B42 -> 0.38706366
A43: TOTAL | B43: =SUM(B38:B42) -> 28918 | C43: =SUM(C38:C42) -> 1112 | D43: =C43/B43 -> 0.038453558 | E43: =SUM(E38:E42) -> 15486 | F43: =E43/B43 -> 0.53551421 | G43: =SUM(G38:G42) -> 13432 | H43: =G43/B43 -> 0.46448579
A45: ③-3 Web予約受注率
A46: 月 | B46: 組数 | C46: TC | D46: 利用率 | E46: 電話 | F46: 利用率 | G46: パッサージュ | H46: 利用率 | I46: Web予約率
A47: 5 | B47: 122 | C47: 13 | D47: =C47/B47 -> 0.10655738 | E47: 16 | F47: =E47/B47 -> 0.13114754 | G47: =B47-C47-E47 -> 93 | H47: =G47/B47 -> 0.76229508 | I47: =C47/(C47+E47) -> 0.44827586
A48: 6 | B48: 2015 | C48: 240 | D48: =C48/B48 -> 0.1191067 | E48: 51 | F48: =E48/B48 -> 0.025310174 | G48: =B48-C48-E48 -> 1724 | H48: =G48/B48 -> 0.85558313 | I48: =C48/(C48+E48) -> 0.82474227
A49: 7 | B49: 3542 | C49: 674 | D49: =C49/B49 -> 0.19028797 | E49: 160 | F49: =E49/B49 -> 0.045172219 | G49: =B49-C49-E49 -> 2708 | H49: =G49/B49 -> 0.76453981 | I49: =C49/(C49+E49) -> 0.80815348
A50: 8 | B50: 3618 | C50: 885 | D50: =C50/B50 -> 0.24461028 | E50: 156 | F50: =E50/B50 -> 0.043117745 | G50: =B50-C50-E50 -> 2577 | H50: =G50/B50 -> 0.71227197 | I50: =C50/(C50+E50) -> 0.85014409
A51: 9 | B51: 340 | C51: 125 | D51: =C51/B51 -> 0.36764706 | E51: 19 | F51: =E51/B51 -> 0.055882353 | G51: =B51-C51-E51 -> 196 | H51: =G51/B51 -> 0.57647059 | I51: =C51/(C51+E51) -> 0.86805556
A52: TOTAL | B52: =SUM(B47:B51) -> 9637 | C52: =SUM(C47:C51) -> 1937 | D52: =C52/B52 -> 0.20099616 | E52: =SUM(E47:E51) -> 402 | F52: =E52/B52 -> 0.041714226 | G52: =SUM(G47:G51) -> 7298 | H52: =G52/B52 -> 0.75728961 | I52: =C52/(C52+E52) -> 0.82813168

Sheet 計画値・予測・実績進捗
A1: ■R5年さっぽろテレビ塔ビアガーデン売上計画（予算）・売上予測・実績進捗確認表
B2: 計画値 | E2: 予測値 | K2: 実績進捗（派遣分のみ） | R2: ノヴェロさん請求内容 | Y2: 家賃 | AA2: 概算（仮置き）
A3: 月 | B3: 売上予算 | C3: 客数 | D3: 客単価 | E3: 労働時間（予測値） | F3: 人時生産性 | G3: 想定人件費 | H3: 人件費率 | I3: 売上予測 | J3: 対予算 | K3: 売上実績 | L3: 対予測 | M3: 対予算 | N3: 実労働時間 | O3: 人時生産性 | P3: 概算人件費率 | Q3: 派遣人件費（リザルト） | R3: 人件費 | S3: 営業日数 | T3: 拘束時間 | U3: 残業時間 | V3: 人件費合計 | W3: 交通費合計 | X3: 合計 | Y3: 家賃 | Z3: 1日 | AA3: =K9 -> 1.1462364e+08
A4: 5 | B4: 6890000 | C4: 1300 | D4: =B4/C4 -> 5300 | E4: 310 | F4: =I4/E4 -> 6332.2581 | G4: =E4*R4 -> 526437.81 | H4: =G4/B4 -> 0.076406068 | I4: 1963000 | J4: =I4/B4 -> 0.28490566 | K4: ='2023.5月実績'!P93 -> 1795227.3 | L4: =K4/I4 -> 0.91453249 | M4: =K4/B4 -> 0.26055548 | N4: =T4+U4 -> 488 | O4: =K4/N4 -> 3678.7444 | P4: =Q4/K4 -> 0.46162122 | Q4: =X4 -> 828715 | R4: =Q4/N4 -> 1698.1865 | S4: 5 | T4: 479.5 | U4: 8.5 | V4: 759715 | W4: 69000 | X4: =V4+W4 -> 828715 | Y4: 150000 | Z4: 30000 | AA4: =AA3*23.8% -> 27280425 | AB4: 人件費
A5: 6 | B5: 25440000 | C5: 4800 | D5: =B5/C5 -> 5300 | E5: 3555 | F5: =I5/E5 -> 4877.0745 | G5: =E5*R5 -> 6025477.3 | H5: =G5/B5 -> 0.23685052 | I5: 17338000 | J5: =I5/B5 -> 0.68152516 | K5: ='2023.6月実績'!P93 -> 19049727 | L5: =K5/I5 -> 1.0987269 | M5: =K5/B5 -> 0.74881003 | N5: =2946+32.5 -> 2978.5 | O5: =K5/N5 -> 6395.7453 | P5: =Q5/K5 -> 0.26500904 | Q5: =X5 -> 5048350 | R5: =Q5/N5 -> 1694.9303 | S5: 30 | T5: 2946 | U5: 32.5 | V5: 4629350 | W5: 419000 | X5: =V5+W5 -> 5048350 | Y5: 2250000 | Z5: 75000 | AA5: =AA3*31.5% -> 36106445 | AB5: 材料費
A6: 7 | B6: 25440000 | C6: 4800 | D6: =B6/C6 -> 5300 | E6: 4940 | F6: =I6/E6 -> 7088.2591 | G6: =E6*R6 -> 8385722.9 | H6: =G6/B6 -> 0.32962747 | I6: 35016000 | J6: =I6/B6 -> 1.3764151 | K6: ='2023.7月実績'!L93 -> 44856909 | L6: =K6/I6 -> 1.2810404 | M6: =K6/B6 -> 1.7632433 | N6: =4281.75+241.75 -> 4523.5 | O6: =K6/N6 -> 9916.4163 | P6: =Q6/K6 -> 0.17118228 | Q6: =X6 -> 7678708 | R6: =Q6/N6 -> 1697.5148 | S6: 31 | T6: 4281.75 | U6: 241.75 | V6: 7105708 | W6: 573000 | X6: =V6+W6 -> 7678708 | Y6: 3100000 | Z6: 100000 | AA6: =AA3*7% -> 8023654.5 | AB6: 消耗品費
A7: 8 | B7: 25440000 | C7: 4800 | D7: =B7/C7 -> 5300 | E7: 5080 | F7: =I7/E7 -> 7826.7717 | G7: =E7*R7 -> 9144000 | H7: =G7/B7 -> 0.35943396 | I7: 39760000 | J7: =I7/B7 -> 1.5628931 | K7: ='2023.8月実績'!L93 -> 44863045 | L7: =K7/I7 -> 1.1283462 | M7: =K7/B7 -> 1.7634845 | N7: =T7+U7 -> 4935.5 | O7: =K7/N7 -> 9089.8684 | P7: =Q7/K7 -> 0.20105169 | Q7: =X7 -> 9019791 | R7: 1800 | S7: 31 | T7: 4717.25 | U7: 218.25 | V7: 8392791 | W7: 627000 | X7: =V7+W7 -> 9019791 | Y7: 3100000 | Z7: 100000 | AA7: =AA3*15% -> 17193545 | AB7: イニシャル
A8: 9 | B8: 9275000 | C8: 1750 | D8: =B8/C8 -> 5300 | E8: 510 | F8: =I8/E8 -> 8431.3725 | G8: =E8*R8 -> 950482.65 | H8: =G8/B8 -> 0.10247791 | I8: 4300000 | J8: =I8/B8 -> 0.46361186 | K8: ='2023.9月実績'!L93 -> 4058727.3 | L8: =K8/I8 -> 0.94389006 | M8: =K8/B8 -> 0.43759863 | N8: =T8+U8 -> 551 | O8: =K8/N8 -> 7366.1112 | P8: =Q8/K8 -> 0.25300887 | Q8: =X8 -> 1026894 | R8: =Q8/N8 -> 1863.6915 | S8: 3 | T8: 506 | U8: 45 | V8: 958894 | W8: 68000 | X8: =V8+W8 -> 1026894 | Y8: 90000 | Z8: 30000 | AA8: =Y9 -> 8690000 | AB8: 家賃
A9: TOTAL | B9: =SUM(B4:B8) -> 92485000 | C9: =SUM(C4:C8) -> 17450 | D9: =B9/C9 -> 5300 | E9: =SUM(E4:E8) -> 14395 | F9: =I9/E9 -> 6834.1091 | G9: =E9*R9 -> 25211100 | H9: =G9/B9 -> 0.27259663 | I9: =SUM(I4:I8) -> 98377000 | J9: =I9/B9 -> 1.0637076 | K9: =SUM(K4:K8) -> 1.1462364e+08 | L9: =K9/I9 -> 1.1651467 | M9: =K9/B9 -> 1.2393754 | N9: =SUM(N4:N8) -> 13476.5 | O9: =K9/N9 -> 8505.4455 | P9: =Q9/K9 -> 0.20591266 | Q9: =SUM(Q4:Q8) -> 23602458 | R9: =Q9/N9 -> 1751.3789 | S9: =SUM(S4:S8) -> 100 | T9: =SUM(T4:T8) -> 12930.5 | U9: =SUM(U4:U8) -> 546 | V9: =SUM(V4:V8) -> 21846458 | W9: =SUM(W4:W8) -> 1756000 | X9: =SUM(X4:X8) -> 23602458 | Y9: =SUM(Y4:Y8) -> 8690000 | Z9: =SUM(Z4:Z8) -> 335000 | AA9: =AA3*5% -> 5731181.8 | AB9: 流動固定費
B10: 92485000 | C10: 提出予算 | G10: ※ノヴェロ派遣分のみ算出 | I10: ※天気要因見込まず算出 | K10: 43710 | L10: 終了時点の進捗状況 | N10: =K9/S10 -> 1146236.4 | O10: =K9-B10 -> 22138636 | P10: =K9/B10 -> 1.2393754 | S10: 100 | X10: =X9/K9 -> 0.20591266 | AA10: =AA3-AA4-AA5-AA6-AA7-AA8-AA9 -> 11598384 | AB10: 利益
B11: =B9-B10 -> 0 | C11: 差異 | D11: ※予算値は115日計算でP/D（1日平均）804千円にて積み上げ。予測は100日営業、各施策と季節波動を効かせて算出。
I14: 100000000 | J14: 予算まで | K14: =B9-K9 -> -22138636 | L14: 12 | M14: =K14/L14 -> -1844886.4 | N14: 2019 | O14: 58190982 | P14: =K9/O14 -> 1.9697835
I15: 111111111 | J15: 予測まで | K15: =I9-K9 -> -16246636 | L15: 12 | M15: =K15/L15 -> -1353886.4 | N15: 2018 | O15: 44179221 | P15: =K9/O15 -> 2.5945147
J16: 一億円まで | K16: =I14-K9 -> -14623636 | L16: 12 | M16: =K16/L16 -> -1218636.4 | N16: 平均 | O16: =(O14+O15)/2 -> 51185102 | P16: =K9/O16 -> 2.2393945
G17: 2019年度 | J17: 一億一千万まで | K17: =I15-K9 -> -3512525.4 | L17: 12 | M17: =K17/L17 -> -292710.45
G18: 91399704 | H18: =K6-K7 -> -6136.3636 | I18: 945247 | J18: =I18-H18 -> 951383.36 | K18: =K9 -> 1.1462364e+08 | L18: =K18/G18 -> 1.254092 | M18: =K18-G18 -> 23223932
L25: 5187 | M25: 6717 | N25: =M25-L25 -> 1530 | O25: =M25/L25 -> 1.2949682
L26: 992 | M26: 1941 | N26: =M26-L26 -> 949 | O26: =M26/L26 -> 1.9566532
L27: 318 | M27: 2503 | N27: =M27-L27 -> 2185 | O27: =M27/L27 -> 7.8710692
L28: =SUM(L25:L27) -> 6497 | M28: =SUM(M25:M27) -> 11161 | N28: =SUM(N25:N27) -> 4664 | O28: =M28/L28 -> 1.7178698

Sheet 2023.9月実績
A1: ■R5年度 ビアガーデン売上実績
A2: 43708 | L2: =L14+L24+L34+L44+L54+L64 -> 4387600 | R2: 10
A3: FOOD | C3: ビアガーデン9月 実績TOTAL | N3: 客数 | R3: 売上
A4: 予算 | C4: 実績 | E4: 客数 | G4: 客単価 | I4: 売上予算 | L4: 9275000 | M4: 1日平均 | R4: =L4/R2 -> 927500 | T4: 天候要因（売上との関連性を数値化する）
A5: 1st week | C5: 1st week | T5: =C5 -> 1st week
A6: 曜日 | B6: 日にち | C6: 曜日 | D6: 日にち | E6: 客数 | F6: 料理売上 | G6: 料理単価 | H6: 飲料売上 | I6: 飲料単価 | J6: テント利用料 | K6: 物販 | L6: 売上合計 | M6: 合計単価 | N6: サーフィンズ | O6: forking | P6: Timee | Q6: 合計 | R6: 人時売上高 | T6: 最低 | U6: 最高 | V6: 12時 | W6: 15時 | X6: 18時 | Y6: Ave | AA6: ■天候要因 | AC6: 評価点
A7: 日 | C7: 日 | D7: =#REF! -> #REF! | E7: 263 | F7: 799050 | G7: =F7/E7 -> 3038.2129 | H7: 430900 | I7: =H7/E7 -> 1638.403 | J7: 14850 | L7: =F7+H7+J7 -> 1244800 | M7: =L7/E7 -> 4733.0798 | R7: =L7/Q7 -> #DIV/0! | T7: 24.9 | U7: 27 | V7: 3 | W7: 1 | X7: 1 | Y7: =SUM(V7:X7)/3 -> 1.6666667 | AA7: 晴れ（33度まで） | AC7: 5
A8: 月 | C8: 月 | D8: =#REF! -> #REF! | E8: 368 | F8: 1077700 | G8: =F8/E8 -> 2928.5326 | H8: 588200 | I8: =H8/E8 -> 1598.3696 | J8: 31350 | L8: =F8+H8+J8 -> 1697250 | M8: =L8/E8 -> 4612.0924 | R8: =L8/Q8 -> #DIV/0! | T8: 20.7 | U8: 29.1 | V8: 5 | W8: 1 | X8: 5 | Y8: =SUM(V8:X8)/3 -> 3.6666667 | AA8: 晴れ（25度以下） | AC8: 4
A9: 火 | C9: 火 | D9: =#REF! -> #REF! | E9: 343 | F9: 973500 | G9: =F9/E9 -> 2838.1924 | H9: 518250 | I9: =H9/E9 -> 1510.9329 | J9: 30800 | L9: =F9+H9+J9 -> 1522550 | M9: =L9/E9 -> 4438.9213 | R9: =L9/Q9 -> #DIV/0! | T9: 18.6 | U9: 29.8 | V9: 5 | W9: 5 | X9: 5 | Y9: =SUM(V9:X9)/3 -> 5 | AA9: 晴れ（33度以上）曇25度以上 | AC9: 3
A10: 水 | C10: 水 | D10: =#REF! -> #REF! | F10: 0 | G10: =F10/E10 -> #DIV/0! | H10: 0 | I10: =H10/E10 -> #DIV/0! | L10: =F10+H10+J10 -> 0 | M10: =L10/E10 -> #DIV/0! | R10: =L10/Q10 -> #DIV/0! | Y10: =SUM(V10:X10)/3 -> 0 | AA10: 曇 | AC10: 2
A11: 木 | C11: 木 | D11: =#REF! -> #REF! | G11: =F11/E11 -> #DIV/0! | I11: =H11/E11 -> #DIV/0! | L11: =F11+H11+J11 -> 0 | M11: =L11/E11 -> #DIV/0! | R11: =L11/Q11 -> #DIV/0! | Y11: =SUM(V11:X11)/3 -> 0 | AA11: 雨 | AC11: 1
A12: 金 | B12: 1 | C12: 金 | D12: =#REF! -> #REF! | G12: =F12/E12 -> #DIV/0! | I12: =H12/E12 -> #DIV/0! | L12: =F12+H12+J12 -> 0 | M12: =L12/E12 -> #DIV/0! | R12: =L12/Q12 -> #DIV/0! | Y12: =SUM(V12:X12)/3 -> 0 | AA12: 豪雨・雷雨 | AC12: 0
A13: 土 | B13: 2 | C13: 土 | D13: =#REF! -> #REF! | G13: =F13/E13 -> #DIV/0! | I13: =H13/E13 -> #DIV/0! | J13: 0 | L13: =F13+H13+J13 -> 0 | M13: =L13/E13 -> #DIV/0! | R13: =L13/Q13 -> #DIV/0! | Y13: =SUM(V13:X13)/3 -> 0 | AA13: ※5.6月は18時は最低気温を採用。7月〜は最高気温を採用。
A14: SUB TOTAL | C14: SUB TOTAL | E14: =SUM(E7:E13) -> 974 | F14: =SUM(F7:F13) -> 2850250 | G14: =F14/E14 -> 2926.3347 | H14: =SUM(H7:H13) -> 1537350 | I14: =H14/E14 -> 1578.3881 | J14: =I14/F14 -> 0.00055377181 | L14: =F14+H14 -> 4387600 | M14: =L14/E14 -> 4504.7228 | Q14: =SUM(Q7:Q13) -> 0 | R14: =L14/Q14 -> #DIV/0! | S14: 3 | T14: =SUM(T7:T13)/S14 -> 21.4 | U14: =SUM(U7:U13)/S14 -> 28.633333 | V14: =SUM(V7:V13)/S14 -> 4.3333333 | W14: =SUM(W7:W13)/S14 -> 2.3333333 | X14: =SUM(X7:X13)/S14 -> 3.6666667 | Y14: =SUM(V14:X14)/3 -> 3.4444444 | Z14: 15 | AA14: =L14/S14 -> 1462533.3 | AF14: ※1日平均売上
A15: 2nd week | C15: 2nd week | T15: =C15 -> 2nd week
A16: 曜日 | B16: 日にち | C16: 曜日 | D16: 日にち | E16: 客数 | F16: 料理売上 | G16: 料理単価 | H16: 飲料売上 | I16: 飲料単価 | J16: テント利用料 | K16: 物販 | L16: 売上合計 | M16: 合計単価 | N16: サーフィンズ | O16: forking | P16: Timee | Q16: 合計 | R16: 人時売上高 | T16: 最低 | U16: 最高 | V16: 12時 | W16: 15時 | X16: 18時 | Y16: Ave | AA16: ■天候要因 | AC16: 評価点
A17: 日 | B17: 3 | C17: 日 | D17: =#REF! -> #REF! | G17: =F17/E17 -> #DIV/0! | I17: =H17/E17 -> #DIV/0! | L17: =F17+H17+J17 -> 0 | M17: =L17/E17 -> #DIV/0! | R17: =L17/Q17 -> #DIV/0! | Y17: =SUM(V17:X17)/3 -> 0 | AA17: 晴れ（33度まで） | AC17: 5
A18: 月 | B18: 4 | C18: 月 | D18: =#REF! -> #REF! | G18: =F18/E18 -> #DIV/0! | I18: =H18/E18 -> #DIV/0! | L18: =F18+H18+J18 -> 0 | M18: =L18/E18 -> #DIV/0! | R18: =L18/Q18 -> #DIV/0! | Y18: =SUM(V18:X18)/3 -> 0 | AA18: 晴れ（25度以下） | AC18: 4
A19: 火 | B19: 5 | C19: 火 | D19: =#REF! -> #REF! | G19: =F19/E19 -> #DIV/0! | I19: =H19/E19 -> #DIV/0! | L19: =F19+H19+J19 -> 0 | M19: =L19/E19 -> #DIV/0! | R19: =L19/Q19 -> #DIV/0! | Y19: =SUM(V19:X19)/3 -> 0 | AA19: 晴れ（33度以上）曇25度以上 | AC19: 3
A20: 水 | B20: 6 | C20: 水 | D20: =#REF! -> #REF! | G20: =F20/E20 -> #DIV/0! | I20: =H20/E20 -> #DIV/0! | L20: =F20+H20+J20 -> 0 | M20: =L20/E20 -> #DIV/0! | R20: =L20/Q20 -> #DIV/0! | Y20: =SUM(V20:X20)/3 -> 0 | AA20: 曇 | AC20: 2
A21: 木 | B21: 7 | C21: 木 | D21: =#REF! -> #REF! | G21: =F21/E21 -> #DIV/0! | I21: =H21/E21 -> #DIV/0! | L21: =F21+H21+J21 -> 0 | M21: =L21/E21 -> #DIV/0! | R21: =L21/Q21 -> #DIV/0! | Y21: =SUM(V21:X21)/3 -> 0 | AA21: 雨 | AC21: 1
A22: 金 | B22: 8 | C22: 金 | D22: =#REF! -> #REF! | G22: =F22/E22 -> #DIV/0! | I22: =H22/E22 -> #DIV/0! | L22: =F22+H22+J22 -> 0 | M22: =L22/E22 -> #DIV/0! | R22: =L22/Q22 -> #DIV/0! | Y22: =SUM(V22:X22)/3 -> 0 | AA22: 豪雨・雷雨 | AC22: 0
A23: 土 | B23: 9 | C23: 土 | D23: =#REF! -> #REF! | G23: =F23/E23 -> #DIV/0! | I23: =H23/E23 -> #DIV/0! | J23: 0 | L23: =F23+H23+J23 -> 0 | M23: =L23/E23 -> #DIV/0! | R23: =L23/Q23 -> #DIV/0! | Y23: =SUM(V23:X23)/3 -> 0 | AA23: ※5.6月は18時は最低気温を採用。7月〜は最高気温を採用。
A24: SUB TOTAL | C24: SUB TOTAL | E24: =SUM(E17:E23) -> 0 | F24: =SUM(F17:F23) -> 0 | G24: =F24/E24 -> #DIV/0! | H24: =SUM(H17:H23) -> 0 | I24: =H24/E24 -> #DIV/0! | J24: =I24/F24 -> #DIV/0! | L24: =F24+H24 -> 0 | M24: =L24/E24 -> #DIV/0! | Q24: =SUM(Q17:Q23) -> 0 | R24: =L24/Q24 -> #DIV/0! | T24: =SUM(T17:T23)/S24 -> #DIV/0! | U24: =SUM(U17:U23)/S24 -> #DIV/0! | V24: =SUM(V17:V23)/S24 -> #DIV/0! | W24: =SUM(W17:W23)/S24 -> #DIV/0! | X24: =SUM(X17:X23)/S24 -> #DIV/0! | Y24: =SUM(V24:X24)/3 -> #DIV/0!
A25: 3rd week | C25: 3rd week | T25: =C25 -> 3rd week
A26: 曜日 | B26: 日にち | C26: 曜日 | D26: 日にち | E26: 客数 | F26: 料理売上 | G26: 料理単価 | H26: 飲料売上 | I26: 飲料単価 | J26: テント利用料 | K26: 物販 | L26: 売上合計 | M26: 合計単価 | N26: サーフィンズ | O26: forking | P26: Timee | Q26: 合計 | R26: 人時売上高 | T26: 最低 | U26: 最高 | V26: 12時 | W26: 15時 | X26: 18時 | Y26: Ave | AA26: ■天候要因 | AC26: 評価点
A27: 日 | B27: 10 | C27: 日 | D27: =#REF! -> #REF! | G27: =F27/E27 -> #DIV/0! | I27: =H27/E27 -> #DIV/0! | L27: =F27+H27+J27 -> 0 | M27: =L27/E27 -> #DIV/0! | R27: =L27/Q27 -> #DIV/0! | Y27: =SUM(V27:X27)/3 -> 0 | AA27: 晴れ（33度まで） | AC27: 5
A28: 月 | B28: 11 | C28: 月 | D28: =#REF! -> #REF! | G28: =F28/E28 -> #DIV/0! | I28: =H28/E28 -> #DIV/0! | L28: =F28+H28+J28 -> 0 | M28: =L28/E28 -> #DIV/0! | R28: =L28/Q28 -> #DIV/0! | Y28: =SUM(V28:X28)/3 -> 0 | AA28: 晴れ（25度以下） | AC28: 4
A29: 火 | B29: 12 | C29: 火 | D29: =#REF! -> #REF! | G29: =F29/E29 -> #DIV/0! | I29: =H29/E29 -> #DIV/0! | L29: =F29+H29+J29 -> 0 | M29: =L29/E29 -> #DIV/0! | R29: =L29/Q29 -> #DIV/0! | Y29: =SUM(V29:X29)/3 -> 0 | AA29: 晴れ（33度以上）曇25度以上 | AC29: 3
A30: 水 | B30: 13 | C30: 水 | D30: =#REF! -> #REF! | G30: =F30/E30 -> #DIV/0! | I30: =H30/E30 -> #DIV/0! | L30: =F30+H30+J30 -> 0 | M30: =L30/E30 -> #DIV/0! | R30: =L30/Q30 -> #DIV/0! | Y30: =SUM(V30:X30)/3 -> 0 | AA30: 曇 | AC30: 2
A31: 木 | B31: 14 | C31: 木 | D31: =#REF! -> #REF! | G31: =F31/E31 -> #DIV/0! | I31: =H31/E31 -> #DIV/0! | L31: =F31+H31+J31 -> 0 | M31: =L31/E31 -> #DIV/0! | R31: =L31/Q31 -> #DIV/0! | Y31: =SUM(V31:X31)/3 -> 0 | AA31: 雨 | AC31: 1
A32: 金 | B32: 15 | C32: 金 | D32: =#REF! -> #REF! | G32: =F32/E32 -> #DIV/0! | I32: =H32/E32 -> #DIV/0! | L32: =F32+H32+J32 -> 0 | M32: =L32/E32 -> #DIV/0! | R32: =L32/Q32 -> #DIV/0! | Y32: =SUM(V32:X32)/3 -> 0 | AA32: 豪雨・雷雨 | AC32: 0
A33: 土 | B33: 16 | C33: 土 | D33: =#REF! -> #REF! | G33: =F33/E33 -> #DIV/0! | I33: =H33/E33 -> #DIV/0! | J33: 0 | L33: =F33+H33+J33 -> 0 | M33: =L33/E33 -> #DIV/0! | R33: =L33/Q33 -> #DIV/0! | Y33: =SUM(V33:X33)/3 -> 0 | AA33: ※5.6月は18時は最低気温を採用。7月〜は最高気温を採用。
A34: SUB TOTAL | C34: SUB TOTAL | E34: =SUM(E27:E33) -> 0 | F34: =SUM(F27:F33) -> 0 | G34: =F34/E34 -> #DIV/0! | H34: =SUM(H27:H33) -> 0 | I34: =H34/E34 -> #DIV/0! | J34: =I34/F34 -> #DIV/0! | L34: =F34+H34 -> 0 | M34: =L34/E34 -> #DIV/0! | Q34: =SUM(Q27:Q33) -> 0 | R34: =L34/Q34 -> #DIV/0! | T34: =SUM(T27:T33)/S34 -> #DIV/0! | U34: =SUM(U27:U33)/S34 -> #DIV/0! | V34: =SUM(V27:V33)/S34 -> #DIV/0! | W34: =SUM(W27:W33)/S34 -> #DIV/0! | X34: =SUM(X27:X33)/S34 -> #DIV/0! | Y34: =SUM(V34:X34)/3 -> #DIV/0!
A35: 4th week | C35: 4th week | T35: =C35 -> 4th week
A36: 曜日 | B36: 日にち | C36: 曜日 | D36: 日にち | E36: 客数 | F36: 料理売上 | G36: 料理単価 | H36: 飲料売上 | I36: 飲料単価 | J36: テント利用料 | K36: 物販 | L36: 売上合計 | M36: 合計単価 | N36: サーフィンズ | O36: forking | P36: Timee | Q36: 合計 | R36: 人時売上高 | T36: 最低 | U36: 最高 | V36: 12時 | W36: 15時 | X36: 18時 | Y36: Ave | AA36: ■天候要因 | AC36: 評価点
A37: 日 | B37: 17 | C37: 日 | D37: =#REF! -> #REF! | G37: =F37/E37 -> #DIV/0! | I37: =H37/E37 -> #DIV/0! | L37: =F37+H37+J37 -> 0 | M37: =L37/E37 -> #DIV/0! | R37: =L37/Q37 -> #DIV/0! | Y37: =SUM(V37:X37)/3 -> 0 | AA37: 晴れ（33度まで） | AC37: 5
A38: 月 | B38: 18 | C38: 月 | D38: =#REF! -> #REF! | G38: =F38/E38 -> #DIV/0! | I38: =H38/E38 -> #DIV/0! | L38: =F38+H38+J38 -> 0 | M38: =L38/E38 -> #DIV/0! | R38: =L38/Q38 -> #DIV/0! | Y38: =SUM(V38:X38)/3 -> 0 | AA38: 晴れ（25度以下） | AC38: 4
A39: 火 | B39: 19 | C39: 火 | D39: =#REF! -> #REF! | G39: =F39/E39 -> #DIV/0! | I39: =H39/E39 -> #DIV/0! | L39: =F39+H39+J39 -> 0 | M39: =L39/E39 -> #DIV/0! | R39: =L39/Q39 -> #DIV/0! | Y39: =SUM(V39:X39)/3 -> 0 | AA39: 晴れ（33度以上）曇25度以上 | AC39: 3
A40: 水 | B40: 20 | C40: 水 | D40: =#REF! -> #REF! | G40: =F40/E40 -> #DIV/0! | I40: =H40/E40 -> #DIV/0! | L40: =F40+H40+J40 -> 0 | M40: =L40/E40 -> #DIV/0! | R40: =L40/Q40 -> #DIV/0! | Y40: =SUM(V40:X40)/3 -> 0 | AA40: 曇 | AC40: 2
A41: 木 | B41: 21 | C41: 木 | D41: =#REF! -> #REF! | G41: =F41/E41 -> #DIV/0! | I41: =H41/E41 -> #DIV/0! | L41: =F41+H41+J41 -> 0 | M41: =L41/E41 -> #DIV/0! | R41: =L41/Q41 -> #DIV/0! | Y41: =SUM(V41:X41)/3 -> 0 | AA41: 雨 | AC41: 1
A42: 金 | B42: 22 | C42: 金 | D42: =#REF! -> #REF! | G42: =F42/E42 -> #DIV/0! | I42: =H42/E42 -> #DIV/0! | L42: =F42+H42+J42 -> 0 | M42: =L42/E42 -> #DIV/0! | R42: =L42/Q42 -> #DIV/0! | Y42: =SUM(V42:X42)/3 -> 0 | AA42: 豪雨・雷雨 | AC42: 0
A43: 土 | B43: 23 | C43: 土 | D43: =#REF! -> #REF! | G43: =F43/E43 -> #DIV/0! | I43: =H43/E43 -> #DIV/0! | J43: 0 | L43: =F43+H43+J43 -> 0 | M43: =L43/E43 -> #DIV/0! | R43: =L43/Q43 -> #DIV/0! | Y43: =SUM(V43:X43)/3 -> 0 | AA43: ※5.6月は18時は最低気温を採用。7月〜は最高気温を採用。
A44: SUB TOTAL | C44: SUB TOTAL | E44: =SUM(E37:E43) -> 0 | F44: =SUM(F37:F43) -> 0 | G44: =F44/E44 -> #DIV/0! | H44: =SUM(H37:H43) -> 0 | I44: =H44/E44 -> #DIV/0! | J44: =I44/F44 -> #DIV/0! | L44: =F44+H44 -> 0 | M44: =L44/E44 -> #DIV/0! | R44: =L44/Q44 -> #DIV/0! | T44: =SUM(T37:T43)/S44 -> #DIV/0! | U44: =SUM(U37:U43)/S44 -> #DIV/0! | V44: =SUM(V37:V43)/S44 -> #DIV/0! | W44: =SUM(W37:W43)/S44 -> #DIV/0! | X44: =SUM(X37:X43)/S44 -> #DIV/0! | Y44: =SUM(V44:X44)/3 -> #DIV/0!
A45: 5th week | C45: 5th week | T45: =C45 -> 5th week
A46: 曜日 | B46: 日にち | C46: 曜日 | D46: 日にち | E46: 客数 | F46: 料理売上 | G46: 料理単価 | H46: 飲料売上 | I46: 飲料単価 | J46: テント利用料 | K46: 物販 | L46: 売上合計 | M46: 合計単価 | N46: サーフィンズ | O46: forking | P46: Timee | Q46: 合計 | R46: 人時売上高 | T46: 最低 | U46: 最高 | V46: 12時 | W46: 15時 | X46: 18時 | Y46: Ave | AA46: ■天候要因 | AC46: 評価点
A47: 日 | B47: 24 | C47: 日 | D47: =#REF! -> #REF! | G47: =F47/E47 -> #DIV/0! | I47: =H47/E47 -> #DIV/0! | L47: =F47+H47+J47 -> 0 | M47: =L47/E47 -> #DIV/0! | R47: =L47/Q47 -> #DIV/0! | Y47: =SUM(V47:X47)/3 -> 0 | AA47: 晴れ（33度まで） | AC47: 5
A48: 月 | B48: 25 | C48: 月 | D48: =#REF! -> #REF! | G48: =F48/E48 -> #DIV/0! | I48: =H48/E48 -> #DIV/0! | L48: =F48+H48+J48 -> 0 | M48: =L48/E48 -> #DIV/0! | R48: =L48/Q48 -> #DIV/0! | Y48: =SUM(V48:X48)/3 -> 0 | AA48: 晴れ（25度以下） | AC48: 4
A49: 火 | B49: 26 | C49: 火 | D49: =#REF! -> #REF! | G49: =F49/E49 -> #DIV/0! | I49: =H49/E49 -> #DIV/0! | L49: =F49+H49+J49 -> 0 | M49: =L49/E49 -> #DIV/0! | R49: =L49/Q49 -> #DIV/0! | Y49: =SUM(V49:X49)/3 -> 0 | AA49: 晴れ（33度以上）曇25度以上 | AC49: 3
A50: 水 | B50: 27 | C50: 水 | D50: =#REF! -> #REF! | G50: =F50/E50 -> #DIV/0! | I50: =H50/E50 -> #DIV/0! | L50: =F50+H50+J50 -> 0 | M50: =L50/E50 -> #DIV/0! | R50: =L50/Q50 -> #DIV/0! | Y50: =SUM(V50:X50)/3 -> 0 | AA50: 曇 | AC50: 2
A51: 木 | B51: 28 | C51: 木 | D51: =#REF! -> #REF! | G51: =F51/E51 -> #DIV/0! | I51: =H51/E51 -> #DIV/0! | L51: =F51+H51+J51 -> 0 | M51: =L51/E51 -> #DIV/0! | R51: =L51/Q51 -> #DIV/0! | Y51: =SUM(V51:X51)/3 -> 0 | AA51: 雨 | AC51: 1
A52: 金 | B52: 29 | C52: 金 | D52: =#REF! -> #REF! | G52: =F52/E52 -> #DIV/0! | H52: 0 | I52: =H52/E52 -> #DIV/0! | L52: =F52+H52+J52 -> 0 | M52: =L52/E52 -> #DIV/0! | R52: =L52/Q52 -> #DIV/0! | Y52: =SUM(V52:X52)/3 -> 0 | AA52: 豪雨・雷雨 | AC52: 0
A53: 土 | B53: 30 | C53: 土 | D53: =#REF! -> #REF! | G53: =F53/E53 -> #DIV/0! | H53: 0 | I53: =H53/E53 -> #DIV/0! | J53: 0 | L53: =F53+H53+J53 -> 0 | M53: =L53/E53 -> #DIV/0! | R53: =L53/Q53 -> #DIV/0! | Y53: =SUM(V53:X53)/3 -> 0 | AA53: ※5.6月は18時は最低気温を採用。7月〜は最高気温を採用。
A54: SUB TOTAL | C54: SUB TOTAL | E54: =SUM(E47:E53) -> 0 | F54: =SUM(F47:F53) -> 0 | G54: =F54/E54 -> #DIV/0! | H54: =SUM(H47:H53) -> 0 | I54: =H54/E54 -> #DIV/0! | J54: =I54/F54 -> #DIV/0! | L54: =F54+H54 -> 0 | M54: =L54/E54 -> #DIV/0! | R54: =L54/Q54 -> #DIV/0! | T54: =SUM(T47:T53)/S54 -> #DIV/0! | U54: =SUM(U47:U53)/S54 -> #DIV/0! | V54: =SUM(V47:V53)/S54 -> #DIV/0! | W54: =SUM(W47:W53)/S54 -> #DIV/0! | X54: =SUM(X47:X53)/S54 -> #DIV/0! | Y54: =SUM(V54:X54)/3 -> #DIV/0!
A55: 6th week | C55: 6th week | T55: =C55 -> 6th week
A56: 曜日 | B56: 日にち | C56: 曜日 | D56: 日にち | E56: 客数 | F56: 料理売上 | G56: 料理単価 | H56: 飲料売上 | I56: 飲料単価 | J56: テント利用料 | K56: 物販 | L56: 売上合計 | M56: 合計単価 | N56: サーフィンズ | O56: forking | P56: Timee | Q56: 合計 | R56: 人時売上高 | T56: 最低 | U56: 最高 | V56: 12時 | W56: 15時 | X56: 18時 | Y56: Ave | AA56: ■天候要因 | AC56: 評価点
A57: 日 | C57: 日 | D57: =#REF! -> #REF! | G57: =F57/E57 -> #DIV/0! | I57: =H57/E57 -> #DIV/0! | L57: =F57+H57+J57 -> 0 | M57: =L57/E57 -> #DIV/0! | R57: =L57/Q57 -> #DIV/0! | Y57: =SUM(V57:X57)/3 -> 0 | AA57: 晴れ（33度まで） | AC57: 5
A58: 月 | C58: 月 | D58: =#REF! -> #REF! | G58: =F58/E58 -> #DIV/0! | I58: =H58/E58 -> #DIV/0! | L58: =F58+H58+J58 -> 0 | M58: =L58/E58 -> #DIV/0! | R58: =L58/Q58 -> #DIV/0! | Y58: =SUM(V58:X58)/3 -> 0 | AA58: 晴れ（25度以下） | AC58: 4
A59: 火 | C59: 火 | D59: =#REF! -> #REF! | G59: =F59/E59 -> #DIV/0! | I59: =H59/E59 -> #DIV/0! | L59: =F59+H59+J59 -> 0 | M59: =L59/E59 -> #DIV/0! | R59: =L59/Q59 -> #DIV/0! | Y59: =SUM(V59:X59)/3 -> 0 | AA59: 晴れ（33度以上）曇25度以上 | AC59: 3
A60: 水 | C60: 水 | D60: =#REF! -> #REF! | G60: =F60/E60 -> #DIV/0! | I60: =H60/E60 -> #DIV/0! | L60: =F60+H60+J60 -> 0 | M60: =L60/E60 -> #DIV/0! | R60: =L60/Q60 -> #DIV/0! | Y60: =SUM(V60:X60)/3 -> 0 | AA60: 曇 | AC60: 2
A61: 木 | C61: 木 | D61: =#REF! -> #REF! | G61: =F61/E61 -> #DIV/0! | I61: =H61/E61 -> #DIV/0! | L61: =F61+H61+J61 -> 0 | M61: =L61/E61 -> #DIV/0! | R61: =L61/Q61 -> #DIV/0! | Y61: =SUM(V61:X61)/3 -> 0 | AA61: 雨 | AC61: 1
A62: 金 | C62: 金 | D62: =#REF! -> #REF! | G62: =F62/E62 -> #DIV/0! | H62: 0 | I62: =H62/E62 -> #DIV/0! | L62: =F62+H62+J62 -> 0 | M62: =L62/E62 -> #DIV/0! | R62: =L62/Q62 -> #DIV/0! | Y62: =SUM(V62:X62)/3 -> 0 | AA62: 豪雨・雷雨 | AC62: 0
A63: 土 | C63: 土 | D63: =#REF! -> #REF! | G63: =F63/E63 -> #DIV/0! | H63: 0 | I63: =H63/E63 -> #DIV/0! | J63: 0 | L63: =F63+H63+J63 -> 0 | M63: =L63/E63 -> #DIV/0! | R63: =L63/Q63 -> #DIV/0! | Y63: =SUM(V63:X63)/3 -> 0 | AA63: ※5.6月は18時は最低気温を採用。7月〜は最高気温を採用。
A64: SUB TOTAL | C64: SUB TOTAL | E64: =SUM(E57:E63) -> 0 | F64: =SUM(F57:F63) -> 0 | G64: =F64/E64 -> #DIV/0! | H64: =SUM(H57:H63) -> 0 | I64: =H64/E64 -> #DIV/0! | J64: =I64/F64 -> #DIV/0! | L64: =F64+H64 -> 0 | M64: =L64/E64 -> #DIV/0! | R64: =L64/Q64 -> #DIV/0! | T64: =SUM(T57:T63)/S64 -> #DIV/0! | U64: =SUM(U57:U63)/S64 -> #DIV/0! | V64: =SUM(V57:V63)/S64 -> #DIV/0! | W64: =SUM(W57:W63)/S64 -> #DIV/0! | X64: =SUM(X57:X63)/S64 -> #DIV/0! | Y64: =SUM(V64:X64)/3 -> #DIV/0!
A65: TOTAL | C65: TOTAL | T65: =C65 -> TOTAL
A66: 曜日 | B66: 日数 | C66: 曜日 | D66: 日数 | E66: 客数 | F66: 料理売上 | G66: 料理単価 | H66: 飲料売上 | I66: 飲料単価 | J66: テント利用料 | K66: 物販 | L66: 売上合計 | M66: 合計単価 | N66: サーフィンズ | O66: forking | P66: Timee | Q66: 合計 | R66: 人時売上高 | T66: 最低 | U66: 最高 | V66: 12時 | W66: 15時 | X66: 18時 | Y66: Ave
A67: 日 | C67: 日 | E67: =E7+E17+E27+E37+E47+E57 -> 263 | F67: =F7+F17+F27+F37+F47+F57 -> 799050 | G67: =F67/E67 -> 3038.2129 | H67: =H7+H17+H27+H37+H47+H57 -> 430900 | I67: =H67/E67 -> 1638.403 | L67: =L7+L17+L27+L37+L47+L57 -> 1244800 | M67: =M7+M17+M27+M37+M47+M57 -> #DIV/0! | Q67: =Q7+Q17+Q27+Q37+Q47+Q57 -> 0 | R67: =L67/Q67 -> #DIV/0! | T67: =T7+T17+T27+T37+T47+T57 -> 24.9 | U67: =U7+U17+U27+U37+U47+U57 -> 27 | V67: =V7+V17+V37+V47+V27+V57 -> 3 | W67: =W7+W17+W37+W47+W27+W57 -> 1 | X67: =X7+X17+X37+X47+X27+X57 -> 1 | Y67: =SUM(V67:X67)/3 -> 1.6666667
A68: 月 | C68: 月 | E68: =E8+E18+E28+E38+E48+E58 -> 368 | F68: =F8+F18+F28+F38+F48+F58 -> 1077700 | G68: =F68/E68 -> 2928.5326 | H68: =H8+H18+H28+H38+H48+H58 -> 588200 | I68: =H68/E68 -> 1598.3696 | L68: =L8+L18+L28+L38+L48+L58 -> 1697250 | M68: =M8+M18+M28+M38+M48+M58 -> #DIV/0! | Q68: =Q8+Q18+Q28+Q38+Q48+Q58 -> 0 | R68: =L68/Q68 -> #DIV/0! | T68: =T8+T18+T28+T38+T48+T58 -> 20.7 | U68: =U8+U18+U28+U38+U48+U58 -> 29.1 | V68: =V8+V18+V38+V48+V28+V58 -> 5 | W68: =W8+W18+W38+W48+W28+W58 -> 1 | X68: =X8+X18+X38+X48+X28+X58 -> 5 | Y68: =SUM(V68:X68)/3 -> 3.6666667
A69: 火 | C69: 火 | E69: =E9+E19+E29+E39+E49+E59 -> 343 | F69: =F9+F19+F29+F39+F49+F59 -> 973500 | G69: =F69/E69 -> 2838.1924 | H69: =H9+H19+H29+H39+H49+H59 -> 518250 | I69: =H69/E69 -> 1510.9329 | L69: =L9+L19+L29+L39+L49+L59 -> 1522550 | M69: =M9+M19+M29+M39+M49+M59 -> #DIV/0! | Q69: =Q9+Q19+Q29+Q39+Q49+Q59 -> 0 | R69: =L69/Q69 -> #DIV/0! | T69: =T9+T19+T29+T39+T49+T59 -> 18.6 | U69: =U9+U19+U29+U39+U49+U59 -> 29.8 | V69: =V9+V19+V39+V49+V29+V59 -> 5 | W69: =W9+W19+W39+W49+W29+W59 -> 5 | X69: =X9+X19+X39+X49+X29+X59 -> 5 | Y69: =SUM(V69:X69)/3 -> 5
A70: 水 | C70: 水 | E70: =E10+E20+E30+E40+E50+E60 -> 0 | F70: =F10+F20+F30+F40+F50+F60 -> 0 | G70: =F70/E70 -> #DIV/0! | H70: =H10+H20+H30+H40+H50+H60 -> 0 | I70: =H70/E70 -> #DIV/0! | L70: =L10+L20+L30+L40+L50+L60 -> 0 | M70: =M10+M20+M30+M40+M50+M60 -> #DIV/0! | Q70: =Q10+Q20+Q30+Q40+Q50+Q60 -> 0 | R70: =L70/Q70 -> #DIV/0! | T70: =T10+T20+T30+T40+T50+T60 -> 0 | U70: =U10+U20+U30+U40+U50+U60 -> 0 | V70: =V10+V20+V40+V50+V30+V60 -> 0 | W70: =W10+W20+W40+W50+W30+W60 -> 0 | X70: =X10+X20+X40+X50+X30+X60 -> 0 | Y70: =SUM(V70:X70)/3 -> 0
A71: 木 | C71: 木 | E71: =E21+E11+E31+E41+E51+E61 -> 0 | F71: =F21+F11+F31+F41+F51+F61 -> 0 | G71: =F71/E71 -> #DIV/0! | H71: =H21+H11+H31+H41+H51+H61 -> 0 | I71: =H71/E71 -> #DIV/0! | L71: =L21+L11+L31+L41+L51+L61 -> 0 | M71: =M21+M11+M31+M41+M51+M61 -> #DIV/0! | Q71: =Q21+Q11+Q31+Q41+Q51+Q61 -> 0 | R71: =L71/Q71 -> #DIV/0! | T71: =T11+T21+T31+T41+T51+T61 -> 0 | U71: =U11+U21+U31+U41+U51+U61 -> 0 | V71: =V11+V21+V41+V51+V31+V61 -> 0 | W71: =W11+W21+W41+W51+W31+W61 -> 0 | X71: =X11+X21+X41+X51+X31+X61 -> 0 | Y71: =SUM(V71:X71)/3 -> 0
A72: 金 | C72: 金 | E72: =E12+E22+E32+E42+E52+E62 -> 0 | F72: =F12+F22+F32+F42+F52+F62 -> 0 | G72: =F72/E72 -> #DIV/0! | H72: =H12+H22+H32+H42+H52+H62 -> 0 | I72: =H72/E72 -> #DIV/0! | L72: =L12+L22+L32+L42+L52+L62 -> 0 | M72: =M12+M22+M32+M42+M52+M62 -> #DIV/0! | Q72: =Q12+Q22+Q32+Q42+Q52+Q62 -> 0 | R72: =L72/Q72 -> #DIV/0! | T72: =T12+T22+T32+T42+T52+T62 -> 0 | U72: =U12+U22+U32+U42+U52+U62 -> 0 | V72: =V12+V22+V42+V52+V32+V62 -> 0 | W72: =W12+W22+W42+W52+W32+W62 -> 0 | X72: =X12+X22+X42+X52+X32+X62 -> 0 | Y72: =SUM(V72:X72)/3 -> 0
A73: 土 | C73: 土 | E73: =E13+E23+E33+E43+E53+E63 -> 0 | F73: =F13+F23+F33+F43+F53+F63 -> 0 | G73: =F73/E73 -> #DIV/0! | H73: =H13+H23+H33+H43+H53+H63 -> 0 | I73: =H73/E73 -> #DIV/0! | L73: =L13+L23+L33+L43+L53+L63 -> 0 | M73: =M13+M23+M33+M43+M53+M63 -> #DIV/0! | Q73: =Q13+Q23+Q33+Q43+Q53+Q63 -> 0 | R73: =L73/Q73 -> #DIV/0! | S73: 3 | T73: =T13+T23+T33+T43+T53+T63 -> 0 | U73: =U13+U23+U33+U43+U53+U63 -> 0 | V73: =V13+V23+V43+V53+V33+V63 -> 0 | W73: =W13+W23+W43+W53+W33+W63 -> 0 | X73: =X13+X23+X43+X53+X33+X63 -> 0 | Y73: =SUM(V73:X73)/3 -> 0
A74: TOTAL | B74: =SUM(B67:B73) -> 0 | C74: TOTAL | D74: =SUM(D67:D73) -> 0 | E74: =SUM(E67:E73) -> 974 | F74: =SUM(F67:F73) -> 2850250 | G74: =F74/E74 -> 2926.3347 | H74: =SUM(H67:H73) -> 1537350 | I74: =H74/E74 -> 1578.3881 | L74: =SUM(L67:L73) -> 4464600 | M74: =L74/E74 -> 4583.7782 | Q74: =SUM(Q67:Q73) -> 0 | R74: =L74/Q74 -> #DIV/0! | T74: =SUM(T67:T73)/S73 -> 21.4 | U74: =SUM(U67:U73)/S73 -> 28.633333 | V74: =SUM(V67:V73)/S73 -> 4.3333333 | W74: =SUM(W67:W73)/S73 -> 2.3333333 | X74: =SUM(X67:X73)/S73 -> 3.6666667 | Y74: =SUM(V74:X74)/3 -> 3.4444444
A75: ■対比 | C75: ■対比
A77: ランチ | C77: ランチ | E77: 予算
E78: ランチ
E79: 客数 | H79: F売上 | L79: B売上
H80: =#REF!*E80 -> #REF! | L80: =#REF!*E80 -> #REF!
E82: ■予算差異
E83: 客数 | H83: F売上 | L83: B売上
E84: =E74-E80 -> 974 | H84: =H74-H80 -> #REF! | L84: =L74-L80 -> #REF!
E85: =E74/E80 -> #DIV/0! | H85: =H74/H80 -> #REF! | L85: =L74/L80 -> #REF!
E86: ■前年値（数値残っていない休業）
E87: 客数 | H87: F売上 | L87: B売上
E89: ■前年差異
E90: 客数 | H90: F売上 | L90: B売上
E91: =E74-E88 -> 974 | H91: =H74-H88 -> 1537350 | L91: =L74-L88 -> 4464600
E92: =E74/E88 -> #DIV/0! | H92: =H74/H88 -> #DIV/0! | L92: =L74/L88 -> #DIV/0!
A93: 構成比率 | J93: 税抜売上 | L93: =L74/1.1 -> 4058727.3 | M93: 対予測達成率

Sheet 9月時間帯別売上実績 
A1: ■9月時間帯別売上実績&曜日別売上実績
A2: 営業日 | B2: ランチ | E2: アイドル | G2: ディナー | L2: 合計
B3: 12時 | C3: 13時 | D3: 14時 | E3: 15時 | F3: 16時 | G3: 17時 | H3: 18時 | I3: 19時 | J3: 20時 | K3: 21時
A4: 2023/09/01(金) | B4: 194750 | C4: 66600 | D4: 7050 | E4: 25050 | F4: 231550 | G4: 78150 | H4: 264250 | I4: 316650 | J4: 60750 | K4: 0 | L4: =SUM(B4:K4) -> 1244800
A5: 2023/09/02(土) | B5: 239400 | C5: 217250 | D5: 103500 | E5: 145950 | F5: 256100 | G5: 312700 | H5: 259150 | I5: 135700 | J5: 27500 | K5: 0 | L5: =SUM(B5:K5) -> 1697250
A6: 2023/09/03(日) | B6: 235000 | C6: 232850 | D6: 102400 | E6: 54600 | F6: 212550 | G6: 300300 | H6: 181000 | I6: 150450 | J6: 31400 | K6: 22000 | L6: =SUM(B6:K6) -> 1522550
A7: 2023/09/04(月) | L7: =SUM(B7:K7) -> 0
A8: 2023/09/05(火) | L8: =SUM(B8:K8) -> 0
A9: 2023/09/06(水) | L9: =SUM(B9:K9) -> 0
A10: 2023/09/07(木) | L10: =SUM(B10:K10) -> 0
A11: 2023/09/08(金) | L11: =SUM(B11:K11) -> 0
A12: 2023/09/09(土) | L12: =SUM(B12:K12) -> 0
A13: 2023/09/10(日) | L13: =SUM(B13:K13) -> 0
A14: 2023/09/11(月) | L14: =SUM(B14:K14) -> 0
A15: 2023/09/12(火) | L15: =SUM(B15:K15) -> 0
A16: 2023/09/13(水) | L16: =SUM(B16:K16) -> 0
A17: 2023/09/14(木) | L17: =SUM(B17:K17) -> 0
A18: 2023/09/15(金) | L18: =SUM(B18:K18) -> 0
... A33: 2023/09/30(土) | L33: =SUM(B33:K33) -> 0
L34: =SUM(B34:K34) -> 0
A35: 【合計】 | B35: =SUM(B4:B34) -> 669150 | C35: =SUM(C4:C34) -> 516700 | D35: =SUM(D4:D34) -> 212950 | E35: =SUM(E4:E34) -> 225600 | F35: =SUM(F4:F34) -> 700200 | G35: =SUM(G4:G34) -> 691150 | H35: =SUM(H4:H34) -> 704400 | I35: =SUM(I4:I34) -> 602800 | ... K35: =SUM(K4:K34) -> 22000 | L35: =SUM(B35:K35) -> 4464600
B36: =B35+C35+D35 -> 1398800 | E36: =E35+F35 -> 925800 | G36: =G35+H35+I35+J35+K35 -> 2140000 | L36: =SUM(B36:J36) -> 4464600
A37: 売上比率 | B37: =B36/L36 -> 0.31330914 | E37: =E36/L36 -> 0.2073646 | G37: =G36/L36 -> 0.47932626 | L37: =SUM(B37:J37) -> 1
A39: ■9月曜日別売上平均
A40: 【日曜日 平均】 | B40: 235000 | C40: 232850 | D40: 102400 | E40: 54600 | F40: 212550 | G40: 300300 | H40: 181000 | I40: 150450 | J40: 31400 | K40: 22000 | L40: =SUM(B40:K40) -> 1522550
A41: 【月曜日 平均】 | B41: 0 | C41: 0 | D41: 0 | E41: 0 | F41: 0 | G41: 0 | H41: 0 | I41: 0 | J41: 0 | K41: 0 | L41: 0
A42: 【火曜日 平均】 | B42: 0 | C42: 0 | D42: 0 | E42: 0 | F42: 0 | G42: 0 | H42: 0 | I42: 0 | J42: 0 | K42: 0 | L42: 0
A43: 【水曜日 平均】 | B43: 0 | C43: 0 | D43: 0 | E43: 0 | F43: 0 | G43: 0 | H43: 0 | I43: 0 | J43: 0 | K43: 0 | L43: 0
A44: 【木曜日 平均】 | B44: 0 | C44: 0 | D44: 0 | E44: 0 | F44: 0 | G44: 0 | H44: 0 | I44: 0 | J44: 0 | K44: 0 | L44: 0
A45: 【金曜日 平均】 | B45: 194750 | C45: 66600 | D45: 7050 | E45: 25050 | F45: 231550 | G45: 78150 | H45: 264250 | I45: 316650 | J45: 60750 | K45: 0 | L45: =SUM(B45:K45) -> 1244800
A46: 【土曜日 平均】 | B46: 239400 | C46: 217250 | D46: 103500 | E46: 145950 | F46: 256100 | G46: 312700 | H46: 259150 | I46: 135700 | J46: 27500 | K46: 0 | L46: =SUM(B46:K46) -> 1697250
A47: ■9月曜日別売上合計
A48: 【日曜日 合計】 | B48: 235000 | C48: 232850 | D48: 102400 | E48: 54600 | F48: 212550 | G48: 300300 | H48: 181000 | I48: 150450 | J48: 31400 | K48: 22000 | L48: 1522550
A49: 【月曜日 合計】 | B49: 0 | C49: 0 | D49: 0 | E49: 0 | F49: 0 | G49: 0 | H49: 0 | I49: 0 | J49: 0 | K49: 0 | L49: 0
A50: 【火曜日 合計】 | B50: 0 | C50: 0 | D50: 0 | E50: 0 | F50: 0 | G50: 0 | H50: 0 | I50: 0 | J50: 0 | K50: 0 | L50: 0
A51: 【水曜日 合計】 | B51: 0 | C51: 0 | D51: 0 | E51: 0 | F51: 0 | G51: 0 | H51: 0 | I51: 0 | J51: 0 | K51: 0 | L51: 0
A52: 【木曜日 合計】 | B52: 0 | C52: 0 | D52: 0 | E52: 0 | F52: 0 | G52: 0 | H52: 0 | I52: 0 | J52: 0 | K52: 0 | L52: 0
A53: 【金曜日 合計】 | B53: 194750 | C53: 66600 | D53: 7050 | E53: 25050 | F53: 231550 | G53: 78150 | H53: 264250 | I53: 316650 | J53: 60750 | K53: 0 | L53: 1244800
A54: 【土曜日 合計】 | B54: 239400 | C54: 217250 | D54: 103500 | E54: 145950 | F54: 256100 | G54: 312700 | H54: 259150 | I54: 135700 | J54: 27500 | K54: 0 | L54: 1697250

Sheet 2023.8月実績
A1: ■R5年度 ビアガーデン売上実績
A2: 8月 | R2: 31
C3: ビアガーデン8月 TOTAL実績 | N3: 客数 | R3: 売上
C4: 実績 | E4: 客数 | G4: 客単価 | I4: 売上予算 | M4: 1日平均 | T4: 天候要因（売上との関連性を数値化する）
A5: 1st week | C5: 1st week | T5: =C5 -> 1st week
A6: 曜日 | B6: 日にち | C6: 曜日 | D6: 日にち | E6: 客数 | F6: 料理売上 | G6: 料理単価 | H6: 飲料売上 | I6: 飲料単価 | J6: テント利用料 | K6: 物販 | L6: 売上合計 | M6: 合計単価 | N6: サーフィンズ | O6: forking | P6: Timee | Q6: 合計 | R6: 人時売上高 | T6: 最低 | U6: 最高 | V6: 12時 | W6: 15時 | X6: 18時 | Y6: Ave | AA6: ■天候要因 | AC6: 評価点
A7: 日 | C7: 日 | D7: =B7 -> 0 | G7: =F7/E7 -> #DIV/0! | I7: =H7/E7 -> #DIV/0! | J7: 0 | L7: =F7+H7+J7 -> 0 | M7: =L7/E7 -> #DIV/0! | R7: =L7/Q7 -> #DIV/0! | Y7: =SUM(V7:X7)/3 -> 0 | AA7: 晴れ（33度まで） | AC7: 5
A8: 月 | C8: 月 | D8: =B8 -> 0 | G8: =F8/E8 -> #DIV/0! | I8: =H8/E8 -> #DIV/0! | J8: 0 | L8: =F8+H8+J8 -> 0 | M8: =L8/E8 -> #DIV/0! | R8: =L8/Q8 -> #DIV/0! | Y8: =SUM(V8:X8)/3 -> 0 | AA8: 晴れ（25度以下） | AC8: 4
A9: 火 | B9: 1 | C9: 火 | D9: =B9 -> 1 | E9: 342 | F9: 997050 | G9: =F9/E9 -> 2915.3509 | H9: 560500 | I9: =H9/E9 -> 1638.8889 | J9: 25300 | L9: =F9+H9+J9 -> 1582850 | M9: =L9/E9 -> 4628.2164 | Q9: 156.5 | R9: =L9/Q9 -> 10114.058 | T9: 21.5 | U9: 31.1 | V9: 5 | W9: 3 | X9: 5 | Y9: =SUM(V9:X9)/3 -> 4.3333333 | AA9: 晴れ（33度以上）曇25度以上 | AC9: 3
A10: 水 | B10: 2 | C10: 水 | D10: =B10 -> 2 | E10: 310 | F10: 891200 | G10: =F10/E10 -> 2874.8387 | H10: 522250 | I10: =H10/E10 -> 1684.6774 | J10: 14850 | L10: =F10+H10+J10 -> 1428300 | M10: =L10/E10 -> 4607.4194 | Q10: 135 | R10: =L10/Q10 -> 10580 | T10: 24.2 | U10: 34 | V10: 3 | W10: 3 | X10: 3 | Y10: =SUM(V10:X10)/3 -> 3 | AA10: 曇 | AC10: 2
A11: 木 | B11: 3 | C11: 木 | D11: =B11 -> 3 | E11: 316 | F11: 790400 | G11: =F11/E11 -> 2501.2658 | H11: 442100 | I11: =H11/E11 -> 1399.0506 | J11: 30250 | L11: =F11+H11+J11 -> 1262750 | M11: =L11/E11 -> 3996.0443 | Q11: 173.5 | R11: =L11/Q11 -> 7278.098 | T11: 25.6 | U11: 32.2 | V11: 3 | W11: 3 | X11: 5 | Y11: =SUM(V11:X11)/3 -> 3.6666667 | AA11: 雨 | AC11: 1
A12: 金 | B12: 4 | C12: 金 | D12: =B12 -> 4 | E12: 343 | F12: 1098200 | G12: =F12/E12 -> 3201.7493 | H12: 626650 | I12: =H12/E12 -> 1826.9679 | J12: 14300 | L12: =F12+H12+J12 -> 1739150 | M12: =L12/E12 -> 5070.4082 | Q12: 163 | R12: =L12/Q12 -> 10669.632 | T12: 27.1 | U12: 31 | V12: 3 | W12: 3 | X12: 1 | Y12: =SUM(V12:X12)/3 -> 2.3333333 | AA12: 豪雨・雷雨 | AC12: 0
A13: 土 | B13: 5 | C13: 土 | D13: =B13 -> 5 | E13: 570 | F13: 1661250 | G13: =F13/E13 -> 2914.4737 | H13: 912750 | I13: =H13/E13 -> 1601.3158 | J13: 64350 | L13: =F13+H13+J13 -> 2638350 | M13: =L13/E13 -> 4628.6842 | Q13: 185.5 | R13: =L13/Q13 -> 14222.911 | T13: 22.9 | U13: 29.4 | V13: 3 | W13: 1 | X13: 3 | Y13: =SUM(V13:X13)/3 -> 2.3333333 | AA13: ※5.6月は18時は最低気温を採用。7月〜は最高気温を採用。
A14: SUB TOTAL | C14: SUB TOTAL | E14: =SUM(E7:E13) -> 1881 | F14: =SUM(F7:F13) -> 5438100 | G14: =F14/E14 -> 2891.0686 | H14: =SUM(H7:H13) -> 3064250 | I14: =H14/E14 -> 1629.0537 | J14: =SUM(J7:J13) -> 149050 | L14: =F14+H14 -> 8502350 | M14: =L14/E14 -> 4520.1223 | Q14: =SUM(Q7:Q13) -> 813.5 | R14: =L14/Q14 -> 10451.567 | S14: 5 | T14: =SUM(T7:T13)/S14 -> 24.26 | U14: =SUM(U7:U13)/S14 -> 31.54 | V14: =SUM(V7:V13)/S14 -> 3.4 | W14: =SUM(W7:W13)/S14 -> 2.6 | X14: =SUM(X7:X13)/S14 -> 3.4 | Y14: =SUM(V14:X14)/3 -> 3.1333333 | Z14: 11 | AA14: =L14/S14 -> 1700470 | AF14: ※1日平均売上
A15: 2nd week | C15: 2nd week | T15: =C15 -> 2nd week
A16: 曜日 | B16: 日にち | C16: 曜日 | D16: 日にち | E16: 客数 | F16: 料理売上 | G16: 料理単価 | H16: 飲料売上 | I16: 飲料単価 | J16: テント利用料 | K16: 物販 | L16: 売上合計 | M16: 合計単価 | N16: サーフィンズ | O16: forking | P16: Timee | Q16: 合計 | R16: 人時売上高 | T16: 最低 | U16: 最高 | V16: 12時 | W16: 15時 | X16: 18時 | Y16: Ave | AA16: ■天候要因 | AC16: 評価点
A17: 日 | B17: 6 | C17: 日 | D17: =B17 -> 6 | E17: 288 | F17: 735050 | G17: =F17/E17 -> 2552.2569 | H17: 368900 | I17: =H17/E17 -> 1280.9028 | J17: 3850 | L17: =F17+H17+J17 -> 1107800 | M17: =L17/E17 -> 3846.5278 | Q17: 187.5 | R17: =L17/Q17 -> 5908.2667 | T17: 22.2 | U17: 25.7 | V17: 1 | W17: 3 | X17: 1 | Y17: =SUM(V17:X17)/3 -> 1.6666667 | AA17: 晴れ（33度まで） | AC17: 5
A18: 月 | B18: 7 | C18: 月 | D18: =B18 -> 7 | E18: 322 | F18: 941600 | G18: =F18/E18 -> 2924.2236 | H18: 478900 | I18: =H18/E18 -> 1487.2671 | J18: 20900 | L18: =F18+H18+J18 -> 1441400 | M18: =L18/E18 -> 4476.3975 | Q18: 163 | R18: =L18/Q18 -> 8842.9448 | T18: 19.7 | U18: 26.1 | V18: 3 | W18: 3 | X18: 3 | Y18: =SUM(V18:X18)/3 -> 3 | AA18: 晴れ（25度以下） | AC18: 4
A19: 火 | B19: 8 | C19: 火 | D19: =B19 -> 8 | E19: 376 | F19: 1277000 | G19: =F19/E19 -> 3396.2766 | H19: 652650 | I19: =H19/E19 -> 1735.7713 | J19: 25300 | L19: =F19+H19+J19 -> 1954950 | M19: =L19/E19 -> 5199.3351 | Q19: 165 | R19: =L19/Q19 -> 11848.182 | T19: 23.3 | U19: 27.7 | V19: 1 | W19: 1 | X19: 5 | Y19: =SUM(V19:X19)/3 -> 2.3333333 | AA19: 晴れ（33度以上）曇25度以上 | AC19: 3
A20: 水 | B20: 9 | C20: 水 | D20: =B20 -> 9 | E20: 391 | F20: 1076850 | G20: =F20/E20 -> 2754.0921 | H20: 577750 | I20: =H20/E20 -> 1477.6215 | J20: 30800 | L20: =F20+H20+J20 -> 1685400 | M20: =L20/E20 -> 4310.4859 | Q20: 189 | R20: =L20/Q20 -> 8917.4603 | T20: 24.5 | U20: 30.8 | V20: 1 | W20: 3 | X20: 5 | Y20: =SUM(V20:X20)/3 -> 3 | AA20: 曇 | AC20: 2
A21: 木 | B21: 10 | C21: 木 | D21: =B21 -> 10 | E21: 441 | F21: 1244400 | G21: =F21/E21 -> 2821.7687 | H21: 662400 | I21: =H21/E21 -> 1502.0408 | J21: 15950 | L21: =F21+H21+J21 -> 1922750 | M21: =L21/E21 -> 4359.9773 | Q21: 184.5 | R21: =L21/Q21 -> 10421.409 | T21: 25.7 | U21: 31.1 | V21: 5 | W21: 5 | X21: 5 | Y21: =SUM(V21:X21)/3 -> 5 | AA21: 雨 | AC21: 1
A22: 金 | B22: 11 | C22: 金 | D22: =B22 -> 11 | E22: 447 | F22: 1408500 | G22: =F22/E22 -> 3151.0067 | H22: 788400 | I22: =H22/E22 -> 1763.7584 | J22: 30250 | L22: =F22+H22+J22 -> 2227150 | M22: =L22/E22 -> 4982.4385 | Q22: 184.5 | R22: =L22/Q22 -> 12071.274 | T22: 24.7 | U22: 32.3 | V22: 5 | W22: 5 | X22: 5 | Y22: =SUM(V22:X22)/3 -> 5 | AA22: 豪雨・雷雨 | AC22: 0
A23: 土 | B23: 12 | C23: 土 | D23: =B23 -> 12 | E23: 505 | F23: 1494050 | G23: =F23/E23 -> 2958.5149 | H23: 825500 | I23: =H23/E23 -> 1634.6535 | J23: 7150 | L23: =F23+H23+J23 -> 2326700 | M23: =L23/E23 -> 4607.3267 | R23: =L23/Q23 -> #DIV/0! | T23: 23.3 | U23: 32 | V23: 5 | W23: 5 | X23: 5 | Y23: =SUM(V23:X23)/3 -> 5 | AA23: ※5.6月は18時は最低気温を採用。7月〜は最高気温を採用。
A24: SUB TOTAL | C24: SUB TOTAL | E24: =SUM(E17:E23) -> 2770 | F24: =SUM(F17:F23) -> 8177450 | G24: =F24/E24 -> 2952.148 | H24: =SUM(H17:H23) -> 4354500 | I24: =H24/E24 -> 1572.0217 | J24: =SUM(J17:J23) -> 134200 | L24: =F24+H24 -> 12531950 | M24: =L24/E24 -> 4524.1697 | Q24: =SUM(Q17:Q23) -> 1073.5 | R24: =L24/Q24 -> 11673.917 | S24: 7 | T24: =SUM(T17:T23)/S24 -> 23.342857 | U24: =SUM(U17:U23)/S24 -> 29.385714 | V24: =SUM(V17:V23)/S24 -> 3 | W24: =SUM(W17:W23)/S24 -> 3.5714286 | X24: =SUM(X17:X23)/S24 -> 4.1428571 | Y24: =SUM(V24:X24)/3 -> 3.5714286 | Z24: 12 | AA24: =L24/S24 -> 1790278.6 | AF24: ※1日平均売上
A25: 3rd week | C25: 3rd week | T25: =C25 -> 3rd week
A26: 曜日 | B26: 日にち | C26: 曜日 | D26: 日にち | E26: 客数 | F26: 料理売上 | G26: 料理単価 | H26: 飲料売上 | I26: 飲料単価 | J26: テント利用料 | K26: 物販 | L26: 売上合計 | M26: 合計単価 | N26: サーフィンズ | O26: forking | P26: Timee | Q26: 合計 | R26: 人時売上高 | T26: 最低 | U26: 最高 | V26: 12時 | W26: 15時 | X26: 18時 | Y26: Ave | AA26: ■天候要因 | AC26: 評価点
A27: 日 | B27: 13 | C27: 日 | D27: =B27 -> 13 | E27: 527 | F27: 1473850 | G27: =F27/E27 -> 2796.6793 | H27: 799500 | I27: =H27/E27 -> 1517.0778 | J27: 11000 | L27: =F27+H27+J27 -> 2284350 | M27: =L27/E27 -> 4334.63 | R27: =L27/Q27 -> #DIV/0! | T27: 23.5 | U27: 30.5 | V27: 3 | W27: 5 | X27: 5 | Y27: =SUM(V27:X27)/3 -> 4.3333333 | AA27: 晴れ（33度まで） | AC27: 5
A28: 月 | B28: 14 | C28: 月 | D28: =B28 -> 14 | E28: 456 | F28: 1247650 | G28: =F28/E28 -> 2736.0746 | H28: 677000 | I28: =H28/E28 -> 1484.6491 | J28: 16500 | L28: =F28+H28+J28 -> 1941150 | M28: =L28/E28 -> 4256.9079 | R28: =L28/Q28 -> #DIV/0! | T28: 23.1 | U28: 30.7 | V28: 5 | W28: 3 | X28: 3 | Y28: =SUM(V28:X28)/3 -> 3.6666667 | AA28: 晴れ（25度以下） | AC28: 4
A29: 火 | B29: 15 | C29: 火 | D29: =B29 -> 15 | E29: 477 | F29: 1324650 | G29: =F29/E29 -> 2777.044 | H29: 665650 | I29: =H29/E29 -> 1395.4927 | J29: 21450 | L29: =F29+H29+J29 -> 2011750 | M29: =L29/E29 -> 4217.5052 | R29: =L29/Q29 -> #DIV/0! | T29: 22.5 | U29: 30 | V29: 5 | W29: 3 | X29: 3 | Y29: =SUM(V29:X29)/3 -> 3.6666667 | AA29: 晴れ（33度以上）曇25度以上 | AC29: 3
A30: 水 | B30: 16 | C30: 水 | D30: =B30 -> 16 | E30: 215 | F30: 538250 | G30: =F30/E30 -> 2503.4884 | H30: 295400 | I30: =H30/E30 -> 1373.9535 | J30: 6050 | L30: =F30+H30+J30 -> 839700 | M30: =L30/E30 -> 3905.5814 | R30: =L30/Q30 -> #DIV/0! | T30: 23.2 | U30: 26.5 | V30: 1 | W30: 1 | X30: 3 | Y30: =SUM(V30:X30)/3 -> 1.6666667 | AA30: 曇 | AC30: 2
A31: 木 | B31: 17 | C31: 木 | D31: =B31 -> 17 | E31: 277 | F31: 589350 | G31: =F31/E31 -> 2127.6173 | H31: 383500 | I31: =H31/E31 -> 1384.4765 | J31: 2200 | L31: =F31+H31+J31 -> 975050 | M31: =L31/E31 -> 3520.0361 | R31: =L31/Q31 -> #DIV/0! | T31: 25.2 | U31: 31.1 | V31: 5 | W31: 1 | X31: 1 | Y31: =SUM(V31:X31)/3 -> 2.3333333 | AA31: 雨 | AC31: 1
A32: 金 | B32: 18 | C32: 金 | D32: =B32 -> 18 | E32: 387 | F32: 1137850 | G32: =F32/E32 -> 2940.1809 | H32: 661650 | I32: =H32/E32 -> 1709.6899 | J32: 29150 | L32: =F32+H32+J32 -> 1828650 | M32: =L32/E32 -> 4725.1938 | R32: =L32/Q32 -> #DIV/0! | T32: 23.4 | U32: 31 | V32: 3 | W32: 1 | X32: 3 | Y32: =SUM(V32:X32)/3 -> 2.3333333 | AA32: 豪雨・雷雨 | AC32: 0
A33: 土 | B33: 19 | C33: 土 | D33: =B33 -> 19 | E33: 515 | F33: 1463750 | G33: =F33/E33 -> 2842.233 | H33: 817750 | I33: =H33/E33 -> 1587.8641 | J33: 20900 | L33: =F33+H33+J33 -> 2302400 | M33: =L33/E33 -> 4470.6796 | R33: =L33/Q33 -> #DIV/0! | T33: 22.9 | U33: 32.2 | V33: 3 | W33: 3 | X33: 5 | Y33: =SUM(V33:X33)/3 -> 3.6666667 | AA33: ※5.6月は18時は最低気温を採用。7月〜は最高気温を採用。
A34: SUB TOTAL | C34: SUB TOTAL | E34: =SUM(E27:E33) -> 2854 | F34: =SUM(F27:F33) -> 7775350 | G34: =F34/E34 -> 2724.3693 | H34: =SUM(H27:H33) -> 4300450 | I34: =H34/E34 -> 1506.815 | J34: =SUM(J27:J33) -> 107250 | L34: =F34+H34 -> 12075800 | M34: =L34/E34 -> 4231.1843 | Q34: =SUM(Q27:Q33) -> 0 | R34: =L34/Q34 -> #DIV/0! | S34: 7 | T34: =SUM(T27:T33)/S34 -> 23.4 | U34: =SUM(U27:U33)/S34 -> 30.285714 | V34: =SUM(V27:V33)/S34 -> 3.5714286 | W34: =SUM(W27:W33)/S34 -> 2.4285714 | X34: =SUM(X27:X33)/S34 -> 3.2857143 | Y34: =SUM(V34:X34)/3 -> 3.0952381 | Z34: 13 | AA34: =L34/S34 -> 1725114.3 | AF34: ※1日平均売上
A35: 4th week | C35: 4th week | T35: =C35 -> 4th week
A36: 曜日 | B36: 日にち | C36: 曜日 | D36: 日にち | E36: 客数 | F36: 料理売上 | G36: 料理単価 | H36: 飲料売上 | I36: 飲料単価 | J36: テント利用料 | K36: 物販 | L36: 売上合計 | M36: 合計単価 | N36: サーフィンズ | O36: forking | P36: Timee | Q36: 合計 | R36: 人時売上高 | T36: 最低 | U36: 最高 | V36: 12時 | W36: 15時 | X36: 18時 | Y36: Ave | AA36: ■天候要因 | AC36: 評価点
A37: 日 | B37: 20 | C37: 日 | D37: =B37 -> 20 | E37: 428 | F37: 1143400 | G37: =F37/E37 -> 2671.4953 | H37: 637950 | I37: =H37/E37 -> 1490.5374 | J37: 16500 | L37: =F37+H37+J37 -> 1797850 | M37: =L37/E37 -> 4200.5841 | R37: =L37/Q37 -> #DIV/0! | T37: 24.4 | U37: 29.8 | V37: 1 | W37: 5 | X37: 3 | Y37: =SUM(V37:X37)/3 -> 3 | AA37: 晴れ（33度まで） | AC37: 5
A38: 月 | B38: 21 | C38: 月 | D38: =B38 -> 21 | E38: 329 | F38: 866000 | G38: =F38/E38 -> 2632.2188 | H38: 481500 | I38: =H38/E38 -> 1463.5258 | J38: 8250 | L38: =F38+H38+J38 -> 1355750 | M38: =L38/E38 -> 4120.8207 | R38: =L38/Q38 -> #DIV/0! | T38: 23.9 | U38: 32.4 | V38: 5 | W38: 5 | X38: 4 | Y38: =SUM(V38:X38)/3 -> 4.6666667 | AA38: 晴れ（25度以下） | AC38: 4
A39: 火 | B39: 22 | C39: 火 | D39: =B39 -> 22 | E39: 281 | F39: 832300 | G39: =F39/E39 -> 2961.9217 | H39: 475750 | I39: =H39/E39 -> 1693.0605 | J39: 4950 | L39: =F39+H39+J39 -> 1313000 | M39: =L39/E39 -> 4672.5979 | R39: =L39/Q39 -> #DIV/0! | T39: 24.7 | U39: 33.2 | V39: 3 | W39: 3 | X39: 4 | Y39: =SUM(V39:X39)/3 -> 3.3333333 | AA39: 晴れ（33度以上）曇25度以上 | AC39: 3
A40: 水 | B40: 23 | C40: 水 | D40: =B40 -> 23 | E40: 258 | F40: 784400 | G40: =F40/E40 -> 3040.3101 | H40: 451600 | I40: =H40/E40 -> 1750.3876 | J40: 4400 | L40: =F40+H40+J40 -> 1240400 | M40: =L40/E40 -> 4807.7519 | R40: =L40/Q40 -> #DIV/0! | T40: 26.2 | U40: 36.3 | V40: 3 | W40: 3 | X40: 4 | Y40: =SUM(V40:X40)/3 -> 3.3333333 | AA40: 曇 | AC40: 2
A41: 木 | B41: 24 | C41: 木 | D41: =B41 -> 24 | E41: 230 | F41: 738550 | G41: =F41/E41 -> 3211.087 | H41: 408850 | I41: =H41/E41 -> 1777.6087 | J41: 18700 | L41: =F41+H41+J41 -> 1166100 | M41: =L41/E41 -> 5070 | R41: =L41/Q41 -> #DIV/0! | T41: 26.3 | U41: 35 | V41: 3 | W41: 1 | X41: 4 | Y41: =SUM(V41:X41)/3 -> 2.6666667 | AA41: 雨 | AC41: 1
A42: 金 | B42: 25 | C42: 金 | D42: =B42 -> 25 | E42: 265 | F42: 848850 | G42: =F42/E42 -> 3203.2075 | H42: 452650 | I42: =H42/E42 -> 1708.1132 | J42: 22550 | L42: =F42+H42+J42 -> 1324050 | M42: =L42/E42 -> 4996.4151 | R42: =L42/Q42 -> #DIV/0! | T42: 26 | U42: 34.7 | V42: 3 | W42: 3 | X42: 4 | Y42: =SUM(V42:X42)/3 -> 3.3333333 | AA42: 豪雨・雷雨 | AC42: 0
A43: 土 | B43: 26 | C43: 土 | D43: =B43 -> 26 | E43: 407 | F43: 1102550 | G43: =F43/E43 -> 2708.9681 | H43: 639200 | I43: =H43/E43 -> 1570.516 | J43: 39050 | L43: =F43+H43+J43 -> 1780800 | M43: =L43/E43 -> 4375.43 | R43: =L43/Q43 -> #DIV/0! | T43: 26.7 | U43: 35.6 | V43: 3 | W43: 3 | X43: 4 | Y43: =SUM(V43:X43)/3 -> 3.3333333 | AA43: ※5.6月は18時は最低気温を採用。7月〜は最高気温を採用。
A44: SUB TOTAL | C44: SUB TOTAL | E44: =SUM(E37:E43) -> 2198 | F44: =SUM(F37:F43) -> 6316050 | G44: =F44/E44 -> 2873.5441 | H44: =SUM(H37:H43) -> 3547500 | I44: =H44/E44 -> 1613.9672 | J44: =SUM(J37:J43) -> 114400 | L44: =F44+H44 -> 9863550 | M44: =L44/E44 -> 4487.5114 | Q44: =SUM(Q37:Q43) -> 0 | R44: =L44/Q44 -> #DIV/0! | S44: 7 | T44: =SUM(T37:T43)/S44 -> 25.457143 | U44: =SUM(U37:U43)/S44 -> 33.857143 | V44: =SUM(V37:V43)/S44 -> 3 | W44: =SUM(W37:W43)/S44 -> 3.2857143 | X44: =SUM(X37:X43)/S44 -> 3.8571429 | Y44: =SUM(V44:X44)/3 -> 3.3809524 | Z44: 14 | AA44: =L44/S44 -> 1409078.6 | AF44: ※1日平均売上
A45: 5th week | C45: 5th week | T45: =C45 -> 5th week
A46: 曜日 | B46: 日にち | C46: 曜日 | D46: 日にち | E46: 客数 | F46: 料理売上 | G46: 料理単価 | H46: 飲料売上 | I46: 飲料単価 | J46: テント利用料 | K46: 物販 | L46: 売上合計 | M46: 合計単価 | N46: サーフィンズ | O46: forking | P46: Timee | Q46: 合計 | R46: 人時売上高 | T46: 最低 | U46: 最高 | V46: 12時 | W46: 15時 | X46: 18時 | Y46: Ave | AA46: ■天候要因 | AC46: 評価点
A47: 日 | B47: 27 | C47: 日 | D47: =B47 -> 27 | E47: 341 | F47: 1007250 | G47: =F47/E47 -> 2953.8123 | H47: 556800 | I47: =H47/E47 -> 1632.8446 | J47: 30800 | L47: =F47+H47+J47 -> 1594850 | M47: =L47/E47 -> 4676.9795 | R47: =L47/Q47 -> #DIV/0! | T47: 26.4 | U47: 30.7 | V47: 1 | W47: 1 | X47: 3 | Y47: =SUM(V47:X47)/3 -> 1.6666667 | AA47: 晴れ（33度まで） | AC47: 5
A48: 月 | B48: 28 | C48: 月 | D48: =B48 -> 28 | E48: 209 | F48: 547500 | G48: =F48/E48 -> 2619.6172 | H48: 282400 | I48: =H48/E48 -> 1351.1962 | J48: 2200 | L48: =F48+H48+J48 -> 832100 | M48: =L48/E48 -> 3981.3397 | R48: =L48/Q48 -> #DIV/0! | T48: 23.3 | U48: 27.8 | V48: 5 | W48: 5 | X48: 5 | Y48: =SUM(V48:X48)/3 -> 5 | AA48: 晴れ（25度以下） | AC48: 4
A49: 火 | B49: 29 | C49: 火 | D49: =B49 -> 29 | E49: 259 | F49: 771850 | G49: =F49/E49 -> 2980.1158 | H49: 411350 | I49: =H49/E49 -> 1588.2239 | J49: 1100 | L49: =F49+H49+J49 -> 1184300 | M49: =L49/E49 -> 4572.5869 | R49: =L49/Q49 -> #DIV/0! | T49: 21.2 | U49: 27.2 | V49: 3 | W49: 3 | X49: 3 | Y49: =SUM(V49:X49)/3 -> 3 | AA49: 晴れ（33度以上）曇25度以上 | AC49: 3
A50: 水 | B50: 30 | C50: 水 | D50: =B50 -> 30 | E50: 322 | F50: 741700 | G50: =F50/E50 -> 2303.4161 | H50: 425200 | I50: =H50/E50 -> 1320.4969 | J50: 49500 | L50: =F50+H50+J50 -> 1216400 | M50: =L50/E50 -> 3777.6398 | R50: =L50/Q50 -> #DIV/0! | T50: 22.3 | U50: 27.7 | V50: 5 | W50: 5 | X50: 5 | Y50: =SUM(V50:X50)/3 -> 5 | AA50: 曇 | AC50: 2
A51: 木 | B51: 31 | C51: 木 | D51: =B51 -> 31 | E51: 259 | F51: 650700 | G51: =F51/E51 -> 2512.3552 | H51: 362800 | I51: =H51/E51 -> 1400.7722 | J51: 29650 | L51: =F51+H51+J51 -> 1043150 | M51: =L51/E51 -> 4027.6062 | R51: =L51/Q51 -> #DIV/0! | T51: 23.5 | U51: 31.1 | V51: 5 | W51: 5 | X51: 3 | Y51: =SUM(V51:X51)/3 -> 4.3333333 | AA51: 雨 | AC51: 1
A52: 金 | C52: 金 | D52: =B52 -> 0 | G52: =F52/E52 -> #DIV/0! | H52: 0 | I52: =H52/E52 -> #DIV/0! | L52: =F52+H52+J52 -> 0 | M52: =L52/E52 -> #DIV/0! | R52: =L52/Q52 -> #DIV/0! | Y52: =SUM(V52:X52)/3 -> 0 | AA52: 豪雨・雷雨 | AC52: 0
A53: 土 | C53: 土 | D53: =B53 -> 0 | G53: =F53/E53 -> #DIV/0! | H53: 0 | I53: =H53/E53 -> #DIV/0! | L53: =F53+H53+J53 -> 0 | M53: =L53/E53 -> #DIV/0! | R53: =L53/Q53 -> #DIV/0! | Y53: =SUM(V53:X53)/3 -> 0 | AA53: ※5.6月は18時は最低気温を採用。7月〜は最高気温を採用。
A54: SUB TOTAL | C54: SUB TOTAL | E54: =SUM(E47:E53) -> 1390 | F54: =SUM(F47:F53) -> 3719000 | G54: =F54/E54 -> 2675.5396 | H54: =SUM(H47:H53) -> 2038550 | I54: =H54/E54 -> 1466.5827 | J54: =SUM(J47:J53) -> 113250 | L54: =F54+H54 -> 5757550 | M54: =L54/E54 -> 4142.1223 | Q54: =SUM(Q47:Q53) -> 0 | R54: =L54/Q54 -> #DIV/0! | S54: 5 | T54: =SUM(T47:T53)/S54 -> 23.34 | U54: =SUM(U47:U53)/S54 -> 28.9 | V54: =SUM(V47:V53)/S54 -> 3.8 | W54: =SUM(W47:W53)/S54 -> 3.8 | X54: =SUM(X47:X53)/S54 -> 3.8 | Y54: =SUM(V54:X54)/3 -> 3.8 | Z54: 15 | AA54: =L54/S54 -> 1151510 | AF54: ※1日平均売上
A55: 6th week | C55: 6th week | T55: =C55 -> 6th week
A56: 曜日 | B56: 日にち | C56: 曜日 | D56: 日にち | E56: 客数 | F56: 料理売上 | G56: 料理単価 | H56: 飲料売上 | I56: 飲料単価 | J56: テント利用料 | K56: 物販 | L56: 売上合計 | M56: 合計単価 | N56: サーフィンズ | O56: forking | P56: Timee | Q56: 合計 | R56: 人時売上高 | T56: 最低 | U56: 最高 | V56: 12時 | W56: 15時 | X56: 18時 | Y56: Ave | AA56: ■天候要因 | AC56: 評価点
A57: 日 | C57: 日 | D57: =B57 -> 0 | G57: =F57/E57 -> #DIV/0! | I57: =H57/E57 -> #DIV/0! | J57: 0 | L57: =F57+H57+J57 -> 0 | M57: =L57/E57 -> #DIV/0! | R57: =L57/Q57 -> #DIV/0! | Y57: =SUM(V57:X57)/3 -> 0 | AA57: 晴れ（33度まで） | AC57: 5
A58: 月 | C58: 月 | D58: =B58 -> 0 | G58: =F58/E58 -> #DIV/0! | I58: =H58/E58 -> #DIV/0! | J58: 0 | L58: =F58+H58+J58 -> 0 | M58: =L58/E58 -> #DIV/0! | R58: =L58/Q58 -> #DIV/0! | Y58: =SUM(V58:X58)/3 -> 0 | AA58: 晴れ（25度以下） | AC58: 4
A59: 火 | C59: 火 | D59: =B59 -> 0 | G59: =F59/E59 -> #DIV/0! | I59: =H59/E59 -> #DIV/0! | J59: 0 | L59: =F59+H59+J59 -> 0 | M59: =L59/E59 -> #DIV/0! | R59: =L59/Q59 -> #DIV/0! | Y59: =SUM(V59:X59)/3 -> 0 | AA59: 晴れ（33度以上）曇25度以上 | AC59: 3
A60: 水 | C60: 水 | D60: =B60 -> 0 | G60: =F60/E60 -> #DIV/0! | I60: =H60/E60 -> #DIV/0! | J60: 0 | L60: =F60+H60+J60 -> 0 | M60: =L60/E60 -> #DIV/0! | R60: =L60/Q60 -> #DIV/0! | Y60: =SUM(V60:X60)/3 -> 0 | AA60: 曇 | AC60: 2
A61: 木 | C61: 木 | D61: =B61 -> 0 | G61: =F61/E61 -> #DIV/0! | I61: =H61/E61 -> #DIV/0! | L61: =F61+H61+J61 -> 0 | M61: =L61/E61 -> #DIV/0! | R61: =L61/Q61 -> #DIV/0! | Y61: =SUM(V61:X61)/3 -> 0 | AA61: 雨 | AC61: 1
A62: 金 | C62: 金 | D62: =B62 -> 0 | G62: =F62/E62 -> #DIV/0! | H62: 0 | I62: =H62/E62 -> #DIV/0! | L62: =F62+H62+J62 -> 0 | M62: =L62/E62 -> #DIV/0! | R62: =L62/Q62 -> #DIV/0! | Y62: =SUM(V62:X62)/3 -> 0 | AA62: 豪雨・雷雨 | AC62: 0
A63: 土 | C63: 土 | D63: =B63 -> 0 | G63: =F63/E63 -> #DIV/0! | H63: 0 | I63: =H63/E63 -> #DIV/0! | L63: =F63+H63+J63 -> 0 | M63: =L63/E63 -> #DIV/0! | R63: =L63/Q63 -> #DIV/0! | Y63: =SUM(V63:X63)/3 -> 0 | AA63: ※5.6月は18時は最低気温を採用。7月〜は最高気温を採用。
A64: SUB TOTAL | C64: SUB TOTAL | E64: =SUM(E57:E63) -> 0 | F64: =SUM(F57:F63) -> 0 | G64: =F64/E64 -> #DIV/0! | H64: =SUM(H57:H63) -> 0 | I64: =H64/E64 -> #DIV/0! | J64: =SUM(J57:J63) -> 0 | L64: =F64+H64 -> 0 | M64: =L64/E64 -> #DIV/0! | Q64: =SUM(Q57:Q63) -> 0 | R64: =L64/Q64 -> #DIV/0! | T64: =SUM(T57:T63)/S64 -> #DIV/0! | U64: =SUM(U57:U63)/S64 -> #DIV/0! | V64: =SUM(V57:V63)/S64 -> #DIV/0! | W64: =SUM(W57:W63)/S64 -> #DIV/0! | X64: =SUM(X57:X63)/S64 -> #DIV/0! | Y64: =SUM(V64:X64)/3 -> #DIV/0! | AA64: =L64/S64 -> #DIV/0!
A65: TOTAL | C65: TOTAL | T65: =C65 -> TOTAL
A66: 曜日 | B66: 日数 | C66: 曜日 | D66: 日数 | E66: 客数 | F66: 料理売上 | G66: 料理単価 | H66: 飲料売上 | I66: 飲料単価 | J66: その他売上 | K66: 物販 | L66: 売上合計 | M66: 合計単価 | N66: サーフィンズ | O66: forking | P66: Timee | Q66: 合計 | R66: 人時売上高 | T66: 最低 | U66: 最高 | V66: 12時 | W66: 15時 | X66: 18時 | Y66: Ave
A67: 日 | C67: 日 | E67: =E7+E17+E27+E37+E47+E57 -> 1584 | F67: =F7+F17+F27+F37+F47+F57 -> 4359550 | G67: =F67/E67 -> 2752.2412 | H67: =H7+H17+H27+H37+H47+H57 -> 2363150 | I67: =H67/E67 -> 1491.8876 | J67: =J7+J17+J27+J37+J47+J57 -> 62150 | L67: =L7+L17+L27+L37+L47+L57 -> 6784850 | M67: =M7+M17+M27+M37+M47+M57 -> #DIV/0! | Q67: =Q7+Q17+Q27+Q37+Q47+Q57 -> 187.5 | R67: =L67/Q67 -> 36185.867 | T67: =T7+T17+T27+T37+T47+T57 -> 96.5 | U67: =U7+U17+U27+U37+U47+U57 -> 116.7 | V67: =V7+V17+V37+V47+V27+V57 -> 6 | W67: =W7+W17+W37+W47+W27+W57 -> 14 | X67: =X7+X17+X37+X47+X27+X57 -> 12 | Y67: =SUM(V67:X67)/3 -> 10.666667
A68: 月 | C68: 月 | E68: =E8+E18+E28+E38+E48+E58 -> 1316 | F68: =F8+F18+F28+F38+F48+F58 -> 3602750 | G68: =F68/E68 -> 2737.652 | H68: =H8+H18+H28+H38+H48+H58 -> 1919800 | I68: =H68/E68 -> 1458.8146 | J68: =J8+J18+J28+J38+J48+J58 -> 47850 | L68: =L8+L18+L28+L38+L48+L58 -> 5570400 | M68: =M8+M18+M28+M38+M48+M58 -> #DIV/0! | Q68: =Q8+Q18+Q28+Q38+Q48+Q58 -> 163 | R68: =L68/Q68 -> 34174.233 | T68: =T8+T18+T28+T38+T48+T58 -> 90 | U68: =U8+U18+U28+U38+U48+U58 -> 117 | V68: =V8+V18+V38+V48+V28+V58 -> 18 | W68: =W8+W18+W38+W48+W28+W58 -> 16 | X68: =X8+X18+X38+X48+X28+X58 -> 15 | Y68: =SUM(V68:X68)/3 -> 16.333333
A69: 火 | C69: 火 | E69: =E9+E19+E29+E39+E49+E59 -> 1735 | F69: =F9+F19+F29+F39+F49+F59 -> 5202850 | G69: =F69/E69 -> 2998.7608 | H69: =H9+H19+H29+H39+H49+H59 -> 2765900 | I69: =H69/E69 -> 1594.1787 | J69: =J9+J19+J29+J39+J49+J59 -> 78100 | L69: =L9+L19+L29+L39+L49+L59 -> 8046850 | M69: =M9+M19+M29+M39+M49+M59 -> #DIV/0! | Q69: =Q9+Q19+Q29+Q39+Q49+Q59 -> 321.5 | R69: =L69/Q69 -> 25029.082 | T69: =T9+T19+T29+T39+T49+T59 -> 113.2 | U69: =U9+U19+U29+U39+U49+U59 -> 149.2 | V69: =V9+V19+V39+V49+V29+V59 -> 17 | W69: =W9+W19+W39+W49+W29+W59 -> 13 | X69: =X9+X19+X39+X49+X29+X59 -> 20 | Y69: =SUM(V69:X69)/3 -> 16.666667
A70: 水 | C70: 水 | E70: =E10+E20+E30+E40+E50+E60 -> 1496 | F70: =F10+F20+F30+F40+F50+F60 -> 4032400 | G70: =F70/E70 -> 2695.4545 | H70: =H10+H20+H30+H40+H50+H60 -> 2272200 | I70: =H70/E70 -> 1518.8503 | J70: =J10+J20+J30+J40+J50+J60 -> 105600 | L70: =L10+L20+L30+L40+L50+L60 -> 6410200 | M70: =M10+M20+M30+M40+M50+M60 -> #DIV/0! | Q70: =Q10+Q20+Q30+Q40+Q50+Q60 -> 324 | R70: =L70/Q70 -> 19784.568 | T70: =T10+T20+T30+T40+T50+T60 -> 120.4 | U70: =U10+U20+U30+U40+U50+U60 -> 155.3 | V70: =V10+V20+V40+V50+V30+V60 -> 13 | W70: =W10+W20+W40+W50+W30+W60 -> 15 | X70: =X10+X20+X40+X50+X30+X60 -> 20 | Y70: =SUM(V70:X70)/3 -> 16
A71: 木 | C71: 木 | E71: =E21+E11+E31+E41+E51+E61 -> 1523 | F71: =F21+F11+F31+F41+F51+F61 -> 4013400 | G71: =F71/E71 -> 2635.1937 | H71: =H21+H11+H31+H41+H51+H61 -> 2259650 | I71: =H71/E71 -> 1483.6835 | J71: =J21+J11+J31+J41+J51+J61 -> 96750 | L71: =L21+L11+L31+L41+L51+L61 -> 6369800 | M71: =M21+M11+M31+M41+M51+M61 -> #DIV/0! | Q71: =Q21+Q11+Q31+Q41+Q51+Q61 -> 358 | R71: =L71/Q71 -> 17792.737 | T71: =T11+T21+T31+T41+T51+T61 -> 126.3 | U71: =U11+U21+U31+U41+U51+U61 -> 160.5 | V71: =V11+V21+V41+V51+V31+V61 -> 21 | W71: =W11+W21+W41+W51+W31+W61 -> 15 | X71: =X11+X21+X41+X51+X31+X61 -> 18 | Y71: =SUM(V71:X71)/3 -> 18
A72: 金 | C72: 金 | E72: =E12+E22+E32+E42+E52+E62 -> 1442 | F72: =F12+F22+F32+F42+F52+F62 -> 4493400 | G72: =F72/E72 -> 3116.0888 | H72: =H12+H22+H32+H42+H52+H62 -> 2529350 | I72: =H72/E72 -> 1754.0569 | J72: =J12+J22+J32+J42+J52+J62 -> 96250 | L72: =L12+L22+L32+L42+L52+L62 -> 7119000 | M72: =M12+M22+M32+M42+M52+M62 -> #DIV/0! | Q72: =Q12+Q22+Q32+Q42+Q52+Q62 -> 347.5 | R72: =L72/Q72 -> 20486.331 | T72: =T12+T22+T32+T42+T52+T62 -> 101.2 | U72: =U12+U22+U32+U42+U52+U62 -> 129 | V72: =V12+V22+V42+V52+V32+V62 -> 14 | W72: =W12+W22+W42+W52+W32+W62 -> 12 | X72: =X12+X22+X42+X52+X32+X62 -> 13 | Y72: =SUM(V72:X72)/3 -> 13
A73: 土 | C73: 土 | E73: =E13+E23+E33+E43+E53+E63 -> 1997 | F73: =F13+F23+F33+F43+F53+F63 -> 5721600 | G73: =F73/E73 -> 2865.0976 | H73: =H13+H23+H33+H43+H53+H63 -> 3195200 | I73: =H73/E73 -> 1600 | J73: =J13+J23+J33+J43+J53+J63 -> 131450 | L73: =L13+L23+L33+L43+L53+L63 -> 9048250 | M73: =M13+M23+M33+M43+M53+M63 -> #DIV/0! | Q73: =Q13+Q23+Q33+Q43+Q53+Q63 -> 185.5 | R73: =L73/Q73 -> 48777.628 | S73: =S14+S24+S34+S44+S54+S64 -> 31 | T73: =T13+T23+T33+T43+T53+T63 -> 95.8 | U73: =U13+U23+U33+U43+U53+U63 -> 129.2 | V73: =V13+V23+V43+V53+V33+V63 -> 14 | W73: =W13+W23+W43+W53+W33+W63 -> 12 | X73: =X13+X23+X43+X53+X33+X63 -> 17 | Y73: =SUM(V73:X73)/3 -> 14.333333
A74: TOTAL | B74: =SUM(B67:B73) -> 0 | C74: TOTAL | D74: =SUM(D67:D73) -> 0 | E74: =SUM(E67:E73) -> 11093 | F74: =SUM(F67:F73) -> 31425950 | G74: =F74/E74 -> 2832.9532 | H74: =SUM(H67:H73) -> 17305250 | I74: =H74/E74 -> 1560.0153 | J74: =SUM(J67:J73) -> 618150 | L74: =SUM(L67:L73) -> 49349350 | M74: =L74/E74 -> 4448.6929 | Q74: =SUM(Q67:Q73) -> 1887 | R74: =L74/Q74 -> 26152.279 | T74: =SUM(T67:T73)/S73 -> 23.980645 | U74: =SUM(U67:U73)/S73 -> 30.867742 | V74: =SUM(V67:V73)/S73 -> 3.3225806 | W74: =SUM(W67:W73)/S73 -> 3.1290323 | X74: =SUM(X67:X73)/S73 -> 3.7096774 | Y74: =SUM(V74:X74)/3 -> 3.3870968
A75: ■対比 | C75: ■対比
A77: ランチ | C77: ランチ | E77: 予算
E78: ランチ
E79: 客数 | H79: F売上 | L79: B売上
H80: =#REF!*E80 -> #REF! | L80: =#REF!*E80 -> #REF!
E82: ■予算差異
E83: 客数 | H83: F売上 | L83: B売上
E84: =E74-E80 -> 11093 | H84: =H74-H80 -> #REF! | L84: =L74-L80 -> #REF!
E85: =E74/E80 -> #DIV/0! | H85: =H74/H80 -> #REF! | L85: =L74/L80 -> #REF!
E86: ■前年値（数値残っていない休業）
E87: 客数 | H87: F売上 | L87: B売上
E89: ■前年差異
E90: 客数 | H90: F売上 | L90: B売上
E91: =E74-E88 -> 11093 | H91: =H74-H88 -> 17305250 | L91: =L74-L88 -> 49349350
E92: =E74/E88 -> #DIV/0! | H92: =H74/H88 -> #DIV/0! | L92: =L74/L88 -> #DIV/0!
A93: 構成比率 | J93: 税抜売上 | L93: =L74/1.1 -> 44863045 | M93: 対予測達成率
A98: ■モデルシフト
A99: モデルシフト カテゴリー
A100: TOP1
A101: TOP2
A102: ON1
A103: ON2
A104: ショルダー
A105: OFF1
A106: OFF2

Sheet 8月時間帯別売上実績
A1: ■8月時間帯別売上実績&曜日別売上実績
A2: 営業日 | B2: ランチ | E2: アイドル | G2: ディナー | L2: 合計
B3: 12時 | C3: 13時 | D3: 14時 | E3: 15時 | F3: 16時 | G3: 17時 | H3: 18時 | I3: 19時 | J3: 20時 | K3: 21時
A4: 2023/08/01(火) | B4: 91250 | C4: 106800 | D4: 75450 | E4: 91300 | F4: 205250 | G4: 297850 | H4: 429050 | I4: 182450 | J4: 96850 | K4: 6600 | L4: =SUM(B4:K4) -> 1582850
A5: 2023/08/02(水) | B5: 106100 | C5: 24700 | D5: 32400 | E5: 18700 | F5: 135450 | G5: 159700 | H5: 458500 | I5: 380650 | J5: 86700 | K5: 22700 | L5: =SUM(B5:K5) -> 1425600
A6: 2023/08/03(木) | B6: 85550 | C6: 20250 | D6: 35100 | E6: 74900 | F6: 38500 | G6: 369750 | H6: 335250 | I6: 233650 | J6: 67400 | K6: 2400 | L6: =SUM(B6:K6) -> 1262750
A7: 2023/08/04(金) | B7: 17000 | C7: 62450 | D7: 73800 | E7: 52750 | F7: 51750 | G7: 291750 | H7: 383800 | I7: 626050 | J7: 179800 | K7: 0 | L7: =SUM(B7:K7) -> 1739150
A8: 2023/08/05(土) | B8: 184450 | C8: 147250 | D8: 249500 | E8: 163000 | F8: 298700 | G8: 288150 | H8: 643950 | I8: 430650 | J8: 221700 | K8: 11000 | L8: =SUM(B8:K8) -> 2638350
A9: 2023/08/06(日) | B9: 173450 | C9: 55150 | D9: 87700 | E9: 99750 | F9: 156150 | G9: 175750 | H9: 200900 | I9: 109600 | J9: 49350 | K9: 0 | L9: =SUM(B9:K9) -> 1107800
A10: 2023/08/07(月) | B10: 89150 | C10: 72150 | D10: 50900 | E10: 91350 | F10: 64900 | G10: 129600 | H10: 359100 | I10: 454800 | J10: 125350 | K10: 4100 | L10: =SUM(B10:K10) -> 1441400
A11: 2023/08/08(火) | B11: 114150 | C11: 83800 | D11: 33400 | E11: 261100 | F11: 24350 | G11: 177950 | H11: 277350 | I11: 947450 | J11: 33500 | K11: 1900 | L11: =SUM(B11:K11) -> 1954950
A12: 2023/08/09(水) | B12: 109200 | C12: 127200 | D12: 50050 | E12: 32100 | F12: 91000 | G12: 460650 | H12: 294500 | I12: 489500 | J12: 30500 | K12: 700 | L12: =SUM(B12:K12) -> 1685400
A13: 2023/08/10(木) | B13: 149900 | C13: 78700 | D13: 110150 | E13: 88650 | F13: 17200 | G13: 356150 | H13: 388600 | I13: 672250 | J13: 40550 | K13: 20600 | L13: =SUM(B13:K13) -> 1922750
A14: 2023/08/11(金) | B14: 222350 | C14: 186300 | D14: 118600 | E14: 164800 | F14: 323800 | G14: 355100 | H14: 314350 | I14: 370850 | J14: 139700 | K14: 16500 | L14: =SUM(B14:K14) -> 2212350
A15: 2023/08/12(土) | B15: 190750 | C15: 188900 | D15: 80000 | E15: 159200 | F15: 276900 | G15: 270700 | H15: 532250 | I15: 442950 | J15: 145600 | K15: 1400 | L15: =SUM(B15:K15) -> 2288650
... A35: 【合計】 | B35: 4475650 | C35: 2891150 | D35: 2486550 | E35: 2963100 | F35: 3846550 | G35: 7404300 | H35: 11686300 | I35: 10435900 | J35: 2573050 | K35: 437950 | L35: =SUM(B35:K35) -> 49200500
B36: =B35+C35+D35 -> 9853350 | E36: =E35+F35 -> 6809650 | G36: =G35+H35+I35+J35+K35 -> 32537500 | L36: =SUM(B36:J36) -> 49200500
A37: 売上比率 | B37: =B36/L36 -> 0.20026931 | E37: =E36/L36 -> 0.13840611 | G37: =G36/L36 -> 0.66132458 | L37: =SUM(B37:J37) -> 1
B38: =B37+E37 -> 0.33867542
A39: ■8月曜日別売上平均
A40: 【日曜日 平均】 | B40: 239863 | C40: 88563 | D40: 120463 | E40: 133100 | F40: 205088 | G40: 238850 | H40: 344575 | I40: 215263 | J40: 88325 | K40: 9650 | L40: 1683738
A41: 【月曜日 平均】 | B41: 144000 | C41: 107238 | D41: 62075 | E41: 80950 | F41: 94963 | G41: 160600 | H41: 349425 | I41: 309275 | J41: 76575 | K41: 3375 | L41: 1388475
A42: 【火曜日 平均】 | B42: 127130 | C42: 77950 | D42: 66420 | E42: 115550 | F42: 110380 | G42: 303330 | H42: 367310 | I42: 344420 | J42: 58300 | K42: 33740 | L42: 1604530
A43: 【水曜日 平均】 | B43: 85960 | C43: 81620 | D43: 41720 | E43: 48950 | F43: 71550 | G43: 232000 | H43: 350420 | I43: 302200 | J43: 49200 | K43: 17880 | L43: 1281500
A44: 【木曜日 平均】 | B44: 93620 | C44: 61620 | D44: 46860 | E44: 69820 | F44: 35190 | G44: 228310 | H44: 327460 | I44: 361040 | J44: 36900 | K44: 12600 | L44: 1273420
A45: 【金曜日 平均】 | B45: 111188 | C45: 90725 | D45: 71688 | E45: 84538 | F45: 129525 | G45: 238125 | H45: 406375 | I45: 483000 | J45: 154013 | K45: 6875 | L45: 1776050
A46: 【土曜日 平均】 | B46: 240475 | C46: 159775 | D46: 173663 | E46: 149288 | F46: 260663 | G46: 258950 | H46: 514713 | I46: 341863 | J46: 143850 | K46: 9313 | L46: 2252550
A47: ■8月曜日別売上合計
A48: 【日曜日 合計】 | B48: 959450 | C48: 354250 | D48: 481850 | E48: 532400 | F48: 820350 | G48: 955400 | H48: 1378300 | I48: 861050 | J48: 353300 | K48: 38600 | L48: 6734950
A49: 【月曜日 合計】 | B49: 576000 | C49: 428950 | D49: 248300 | E49: 323800 | F49: 379850 | G49: 642400 | H49: 1397700 | I49: 1237100 | J49: 306300 | K49: 13500 | L49: 5553900
A50: 【火曜日 合計】 | B50: 635650 | C50: 389750 | D50: 332100 | E50: 577750 | F50: 551900 | G50: 1516650 | H50: 1836550 | I50: 1722100 | J50: 291500 | K50: 168700 | L50: 8022650
A51: 【水曜日 合計】 | B51: 429800 | C51: 408100 | D51: 208600 | E51: 244750 | F51: 357750 | G51: 1160000 | H51: 1752100 | I51: 1511000 | J51: 246000 | K51: 89400 | L51: 6407500
A52: 【木曜日 合計】 | B52: 468100 | C52: 308100 | D52: 234300 | E52: 349100 | F52: 175950 | G52: 1141550 | H52: 1637300 | I52: 1805200 | J52: 184500 | K52: 63000 | L52: 6367100
A53: 【金曜日 合計】 | B53: 444750 | C53: 362900 | D53: 286750 | E53: 338150 | F53: 518100 | G53: 952500 | H53: 1625500 | I53: 1932000 | J53: 616050 | K53: 27500 | L53: 7104200
A54: 【土曜日 合計】 | B54: 961900 | C54: 639100 | D54: 694650 | E54: 597150 | F54: 1042650 | G54: 1035800 | H54: 2058850 | I54: 1367450 | J54: 575400 | K54: 37250 | L54: 9010200

Sheet 2023.7月実績
A1: ■R5年度 ビアガーデン売上実績
A2: 7月 | L2: =L14+L24+L34+L44+L54+L64 -> 48885000 | R2: 31
A3: FOOD予測 | C3: ビアガーデン7月 TOTAL実績 | N3: 客数 | R3: 売上
A4: 予算 | C4: 実績 | E4: 客数 | G4: 客単価 | I4: 売上予算 | L4: 25440000 | M4: 1日平均 | R4: =L4/R2 -> 820645.16 | T4: 天候要因（売上との関連性を数値化する）
A5: 1st week | C5: 1st week | T5: =C5 -> 1st week
A6: 曜日 | B6: 日にち | C6: 曜日 | D6: 日にち | E6: 客数 | F6: 料理売上 | G6: 料理単価 | H6: 飲料売上 | I6: 飲料単価 | J6: テント利用料 | K6: 物販 | L6: 売上合計 | M6: 合計単価 | N6: サーフィンズ | O6: forking | P6: Timee | Q6: 合計 | R6: 人時売上高 | T6: 最低 | U6: 最高 | V6: 12時 | W6: 15時 | X6: 18時 | Y6: Ave | AA6: ■天候要因 | AC6: 評価点
A7: 日 | C7: 日 | D7: =B7 -> 0 | G7: =F7/E7 -> #DIV/0! | I7: =H7/E7 -> #DIV/0! | L7: =F7+H7+J7 -> 0 | M7: =L7/E7 -> #DIV/0! | R7: =L7/Q7 -> #DIV/0! | Y7: =SUM(V7:X7)/3 -> 0 | AA7: 晴れ（33度まで） | AC7: 5
A8: 月 | C8: 月 | D8: =B8 -> 0 | G8: =F8/E8 -> #DIV/0! | I8: =H8/E8 -> #DIV/0! | L8: =F8+H8+J8 -> 0 | M8: =L8/E8 -> #DIV/0! | R8: =L8/Q8 -> #DIV/0! | Y8: =SUM(V8:X8)/3 -> 0 | AA8: 晴れ（25度以下） | AC8: 4
A9: 火 | C9: 火 | D9: =B9 -> 0 | G9: =F9/E9 -> #DIV/0! | I9: =H9/E9 -> #DIV/0! | L9: =F9+H9+J9 -> 0 | M9: =L9/E9 -> #DIV/0! | R9: =L9/Q9 -> #DIV/0! | Y9: =SUM(V9:X9)/3 -> 0 | AA9: 晴れ（33度以上）曇25度以上 | AC9: 3
A10: 水 | C10: 水 | D10: =B10 -> 0 | G10: =F10/E10 -> #DIV/0! | I10: =H10/E10 -> #DIV/0! | L10: =F10+H10+J10 -> 0 | M10: =L10/E10 -> #DIV/0! | R10: =L10/Q10 -> #DIV/0! | Y10: =SUM(V10:X10)/3 -> 0 | AA10: 曇 | AC10: 2
A11: 木 | C11: 木 | D11: =B11 -> 0 | G11: =F11/E11 -> #DIV/0! | I11: =H11/E11 -> #DIV/0! | L11: =F11+H11+J11 -> 0 | M11: =L11/E11 -> #DIV/0! | R11: =L11/Q11 -> #DIV/0! | Y11: =SUM(V11:X11)/3 -> 0 | AA11: 雨 | AC11: 1
A12: 金 | C12: 金 | D12: =B12 -> 0 | G12: =F12/E12 -> #DIV/0! | I12: =H12/E12 -> #DIV/0! | L12: =F12+H12+J12 -> 0 | M12: =L12/E12 -> #DIV/0! | R12: =L12/Q12 -> #DIV/0! | Y12: =SUM(V12:X12)/3 -> 0 | AA12: 豪雨・雷雨 | AC12: 0
A13: 土 | B13: 1 | C13: 土 | D13: =B13 -> 1 | E13: 217 | F13: 655350 | G13: =F13/E13 -> 3020.0461 | H13: 331800 | I13: =H13/E13 -> 1529.0323 | J13: 26950 | L13: =F13+H13+J13 -> 1014100 | M13: =L13/E13 -> 4673.2719 | Q13: 151 | R13: =L13/Q13 -> 6715.894 | T13: 19.6 | U13: 21.2 | V13: 2 | W13: 4 | X13: 4 | Y13: =SUM(V13:X13)/3 -> 3.3333333 | AA13: ※5.6月は18時は最低気温を採用。7月〜は最高気温を採用。
A14: SUB TOTAL | C14: SUB TOTAL | E14: =SUM(E7:E13) -> 217 | F14: =SUM(F7:F13) -> 655350 | G14: =F14/E14 -> 3020.0461 | H14: =SUM(H7:H13) -> 331800 | I14: =H14/E14 -> 1529.0323 | J14: =SUM(J7:J13) -> 26950 | L14: =F14+H14 -> 987150 | M14: =L14/E14 -> 4549.0783 | Q14: =SUM(Q7:Q13) -> 151 | R14: =L14/Q14 -> 6537.4172 | S14: 1 | T14: =SUM(T7:T13)/S14 -> 19.6 | U14: =SUM(U7:U13)/S14 -> 21.2 | V14: =SUM(V7:V13)/S14 -> 2 | W14: =SUM(W7:W13)/S14 -> 4 | X14: =SUM(X7:X13)/S14 -> 4 | Y14: =SUM(V14:X14)/3 -> 3.3333333 | Z14: ⑥ | AA14: =L14/S14 -> 987150 | AF14: ※1日平均売上
A15: 2nd week | C15: 2nd week | T15: =C15 -> 2nd week | AF15: ※1日平均売上
A16: 曜日 | B16: 日にち | C16: 曜日 | D16: 日にち | E16: 客数 | F16: 料理売上 | G16: 料理単価 | H16: 飲料売上 | I16: 飲料単価 | J16: テント利用料 | K16: 物販 | L16: 売上合計 | M16: 合計単価 | N16: サーフィンズ | O16: forking | P16: Timee | Q16: 合計 | R16: 人時売上高 | T16: 最低 | U16: 最高 | V16: 12時 | W16: 15時 | X16: 18時 | Y16: Ave | AA16: ■天候要因 | AC16: 評価点
A17: 日 | B17: 2 | C17: 日 | D17: =B17 -> 2 | E17: 279 | F17: 753250 | G17: =F17/E17 -> 2699.8208 | H17: 387100 | I17: =H17/E17 -> 1387.4552 | J17: 12100 | L17: =F17+H17+J17 -> 1152450 | M17: =L17/E17 -> 4130.6452 | Q17: 151 | R17: =L17/Q17 -> 7632.1192 | T17: 17 | U17: 22.9 | V17: 4 | W17: 3 | X17: 2 | Y17: =SUM(V17:X17)/3 -> 3 | AA17: 晴れ（33度まで） | AC17: 5
A18: 月 | B18: 3 | C18: 月 | D18: =B18 -> 3 | E18: 154 | F18: 408400 | G18: =F18/E18 -> 2651.9481 | H18: 253650 | I18: =H18/E18 -> 1647.0779 | J18: 5500 | L18: =F18+H18+J18 -> 667550 | M18: =L18/E18 -> 4334.7403 | Q18: 145 | R18: =L18/Q18 -> 4603.7931 | T18: 17.7 | U18: 23.9 | V18: 4 | W18: 4 | X18: 4 | Y18: =SUM(V18:X18)/3 -> 4 | AA18: 晴れ（25度以下） | AC18: 4
A19: 火 | B19: 4 | C19: 火 | D19: =B19 -> 4 | E19: 201 | F19: 483850 | G19: =F19/E19 -> 2407.2139 | H19: 319300 | I19: =H19/E19 -> 1588.5572 | J19: 4950 | L19: =F19+H19+J19 -> 808100 | M19: =L19/E19 -> 4020.398 | Q19: 145 | R19: =L19/Q19 -> 5573.1034 | T19: 18.2 | U19: 24.8 | V19: 4 | W19: 4 | X19: 4 | Y19: =SUM(V19:X19)/3 -> 4 | AA19: 晴れ（33度以上）曇25度以上 | AC19: 3
A20: 水 | B20: 5 | C20: 水 | D20: =B20 -> 5 | E20: 264 | F20: 712150 | G20: =F20/E20 -> 2697.5379 | H20: 379450 | I20: =H20/E20 -> 1437.3106 | J20: 3850 | L20: =F20+H20+J20 -> 1095450 | M20: =L20/E20 -> 4149.4318 | Q20: 145 | R20: =L20/Q20 -> 7554.8276 | T20: 18 | U20: 27.4 | V20: 5 | W20: 5 | X20: 4 | Y20: =SUM(V20:X20)/3 -> 4.6666667 | AA20: 曇 | AC20: 2
A21: 木 | B21: 6 | C21: 木 | D21: =B21 -> 6 | E21: 305 | F21: 1036850 | G21: =F21/E21 -> 3399.5082 | H21: 558700 | I21: =H21/E21 -> 1831.8033 | J21: 11000 | L21: =F21+H21+J21 -> 1606550 | M21: =L21/E21 -> 5267.377 | Q21: 151 | R21: =L21/Q21 -> 10639.404 | T21: 18.4 | U21: 25.2 | V21: 3 | W21: 1 | X21: 1 | Y21: =SUM(V21:X21)/3 -> 1.6666667 | AA21: 雨 | AC21: 1
A22: 金 | B22: 7 | C22: 金 | D22: =B22 -> 7 | E22: 392 | F22: 1074950 | G22: =F22/E22 -> 2742.2194 | H22: 681300 | I22: =H22/E22 -> 1738.0102 | J22: 20350 | L22: =F22+H22+J22 -> 1776600 | M22: =L22/E22 -> 4532.1429 | Q22: 165.5 | R22: =L22/Q22 -> 10734.743 | T22: 19.2 | U22: 26.1 | V22: 3 | W22: 5 | X22: 5 | Y22: =SUM(V22:X22)/3 -> 4.3333333 | AA22: 豪雨・雷雨 | AC22: 0
A23: 土 | B23: 8 | C23: 土 | D23: =B23 -> 8 | E23: 565 | F23: 1584500 | G23: =F23/E23 -> 2804.4248 | H23: 944950 | I23: =H23/E23 -> 1672.4779 | J23: 13750 | L23: =F23+H23+J23 -> 2543200 | M23: =L23/E23 -> 4501.2389 | Q23: 165.5 | R23: =L23/Q23 -> 15366.767 | T23: 19.6 | U23: 31.4 | V23: 5 | W23: 5 | X23: 5 | Y23: =SUM(V23:X23)/3 -> 5 | AA23: ※5.6月は18時は最低気温を採用。7月〜は最高気温を採用。
A24: SUB TOTAL | C24: SUB TOTAL | E24: =SUM(E17:E23) -> 2160 | F24: =SUM(F17:F23) -> 6053950 | G24: =F24/E24 -> 2802.7546 | H24: =SUM(H17:H23) -> 3524450 | I24: =H24/E24 -> 1631.6898 | J24: =SUM(J17:J23) -> 71500 | L24: =F24+H24 -> 9578400 | M24: =L24/E24 -> 4434.4444 | Q24: =SUM(Q17:Q23) -> 1068 | R24: =L24/Q24 -> 8968.5393 | S24: 7 | T24: =SUM(T17:T23)/S24 -> 18.3 | U24: =SUM(U17:U23)/S24 -> 25.957143 | V24: =SUM(V17:V23)/S24 -> 4 | W24: =SUM(W17:W23)/S24 -> 3.8571429 | X24: =SUM(X17:X23)/S24 -> 3.5714286 | Y24: =SUM(V24:X24)/3 -> 3.8095238 | Z24: ⑦ | AA24: =L24/S24 -> 1368342.9 | AF24: ※1日平均売上
A25: 3rd week | C25: 3rd week | T25: =C25 -> 3rd week
A26: 曜日 | B26: 日にち | C26: 曜日 | D26: 日にち | E26: 客数 | F26: 料理売上 | G26: 料理単価 | H26: 飲料売上 | I26: 飲料単価 | J26: テント利用料 | K26: 物販 | L26: 売上合計 | M26: 合計単価 | N26: サーフィンズ | O26: forking | P26: Timee | Q26: 合計 | R26: 人時売上高 | T26: 最低 | U26: 最高 | V26: 12時 | W26: 15時 | X26: 18時 | Y26: Ave | AA26: ■天候要因 | AC26: 評価点
A27: 日 | B27: 9 | C27: 日 | D27: =B27 -> 9 | E27: 513 | F27: 1444350 | G27: =F27/E27 -> 2815.4971 | H27: 831600 | I27: =H27/E27 -> 1621.0526 | J27: 14850 | L27: =F27+H27+J27 -> 2290800 | M27: =L27/E27 -> 4465.4971 | Q27: 165.5 | R27: =L27/Q27 -> 13841.692 | T27: 21.3 | U27: 31.4 | V27: 1 | W27: 3 | X27: 5 | Y27: =SUM(V27:X27)/3 -> 3 | AA27: 晴れ（33度まで） | AC27: 5
A28: 月 | B28: 10 | C28: 月 | D28: =B28 -> 10 | E28: 293 | F28: 747400 | G28: =F28/E28 -> 2550.8532 | H28: 455750 | I28: =H28/E28 -> 1555.4608 | J28: 6050 | L28: =F28+H28+J28 -> 1209200 | M28: =L28/E28 -> 4126.9625 | Q28: 126 | R28: =L28/Q28 -> 9596.8254 | T28: 20.9 | U28: 28.4 | V28: 3 | W28: 3 | X28: 3 | Y28: =SUM(V28:X28)/3 -> 3 | AA28: 晴れ（25度以下） | AC28: 4
A29: 火 | B29: 11 | C29: 火 | D29: =B29 -> 11 | E29: 181 | F29: 529650 | G29: =F29/E29 -> 2926.2431 | H29: 266300 | I29: =H29/E29 -> 1471.2707 | J29: 13200 | L29: =F29+H29+J29 -> 809150 | M29: =L29/E29 -> 4470.442 | Q29: 126 | R29: =L29/Q29 -> 6421.8254 | T29: 22.3 | U29: 30.2 | V29: 5 | W29: 3 | X29: 3 | Y29: =SUM(V29:X29)/3 -> 3.6666667 | AA29: 晴れ（33度以上）曇25度以上 | AC29: 3
A30: 水 | B30: 12 | C30: 水 | D30: =B30 -> 12 | E30: 175 | F30: 518650 | G30: =F30/E30 -> 2963.7143 | H30: 266050 | I30: =H30/E30 -> 1520.2857 | J30: 12650 | L30: =F30+H30+J30 -> 797350 | M30: =L30/E30 -> 4556.2857 | Q30: 125 | R30: =L30/Q30 -> 6378.8 | T30: 21.4 | U30: 26.1 | V30: 1 | W30: 1 | X30: 1 | Y30: =SUM(V30:X30)/3 -> 1 | AA30: 曇 | AC30: 2
A31: 木 | B31: 13 | C31: 木 | D31: =B31 -> 13 | E31: 220 | F31: 610100 | G31: =F31/E31 -> 2773.1818 | H31: 339550 | I31: =H31/E31 -> 1543.4091 | J31: 1100 | L31: =F31+H31+J31 -> 950750 | M31: =L31/E31 -> 4321.5909 | Q31: 145 | R31: =L31/Q31 -> 6556.8966 | T31: 21 | U31: 26.7 | V31: 3 | W31: 3 | X31: 3 | Y31: =SUM(V31:X31)/3 -> 3 | AA31: 雨 | AC31: 1
A32: 金 | B32: 14 | C32: 金 | D32: =B32 -> 14 | E32: 373 | F32: 1107700 | G32: =F32/E32 -> 2969.7051 | H32: 596850 | I32: =H32/E32 -> 1600.134 | J32: 12100 | L32: =F32+H32+J32 -> 1716650 | M32: =L32/E32 -> 4602.2788 | Q32: 151 | R32: =L32/Q32 -> 11368.543 | T32: 20 | U32: 25.4 | V32: 3 | W32: 5 | X32: 1 | Y32: =SUM(V32:X32)/3 -> 3 | AA32: 豪雨・雷雨 | AC32: 0
A33: 土 | B33: 15 | C33: 土 | D33: =B33 -> 15 | E33: 252 | F33: 797100 | G33: =F33/E33 -> 3163.0952 | H33: 410750 | I33: =H33/E33 -> 1629.9603 | J33: 30250 | L33: =F33+H33+J33 -> 1238100 | M33: =L33/E33 -> 4913.0952 | Q33: 165.5 | R33: =L33/Q33 -> 7480.9668 | T33: 19.4 | U33: 21.4 | V33: 1 | W33: 1 | X33: 1 | Y33: =SUM(V33:X33)/3 -> 1 | AA33: ※5.6月は18時は最低気温を採用。7月〜は最高気温を採用。
A34: SUB TOTAL | C34: SUB TOTAL | E34: =SUM(E27:E33) -> 2007 | F34: =SUM(F27:F33) -> 5754950 | G34: =F34/E34 -> 2867.439 | H34: =SUM(H27:H33) -> 3166850 | I34: =H34/E34 -> 1577.9023 | J34: =SUM(J27:J33) -> 90200 | L34: =F34+H34 -> 8921800 | M34: =L34/E34 -> 4445.3413 | Q34: =SUM(Q27:Q33) -> 1004 | R34: =L34/Q34 -> 8886.255 | S34: 7 | T34: =SUM(T27:T33)/S34 -> 20.9 | U34: =SUM(U27:U33)/S34 -> 27.085714 | V34: =SUM(V27:V33)/S34 -> 2.4285714 | W34: =SUM(W27:W33)/S34 -> 2.7142857 | X34: =SUM(X27:X33)/S34 -> 2.4285714 | Y34: =SUM(V34:X34)/3 -> 2.5238095 | Z34: ⑧ | AA34: =L34/S34 -> 1274542.9 | AF34: ※1日平均売上
A35: 4th week | C35: 4th week | T35: =C35 -> 4th week
A36: 曜日 | B36: 日にち | C36: 曜日 | D36: 日にち | E36: 客数 | F36: 料理売上 | G36: 料理単価 | H36: 飲料売上 | I36: 飲料単価 | J36: テント利用料 | K36: 物販 | L36: 売上合計 | M36: 合計単価 | N36: サーフィンズ | O36: forking | P36: Timee | Q36: 合計 | R36: 人時売上高 | T36: 最低 | U36: 最高 | V36: 12時 | W36: 15時 | X36: 18時 | Y36: Ave | AA36: ■天候要因 | AC36: 評価点
A37: 日 | B37: 16 | C37: 日 | D37: =B37 -> 16 | E37: 660 | F37: 1804850 | G37: =F37/E37 -> 2734.6212 | H37: 1029900 | I37: =H37/E37 -> 1560.4545 | J37: 24750 | L37: =F37+H37+J37 -> 2859500 | M37: =L37/E37 -> 4332.5758 | Q37: 165.5 | R37: =L37/Q37 -> 17277.946 | T37: 20.1 | U37: 28 | V37: 5 | W37: 3 | X37: 3 | Y37: =SUM(V37:X37)/3 -> 3.6666667 | AA37: 晴れ（33度まで） | AC37: 5
A38: 月 | B38: 17 | C38: 月 | D38: =B38 -> 17 | E38: 353 | F38: 924150 | G38: =F38/E38 -> 2617.9887 | H38: 514000 | I38: =H38/E38 -> 1456.0907 | J38: 14850 | L38: =F38+H38+J38 -> 1453000 | M38: =L38/E38 -> 4116.1473 | Q38: 124.5 | R38: =L38/Q38 -> 11670.683 | T38: 21.7 | U38: 26 | V38: 3 | W38: 3 | X38: 3 | Y38: =SUM(V38:X38)/3 -> 3 | AA38: 晴れ（25度以下） | AC38: 4
A39: 火 | B39: 18 | C39: 火 | D39: =B39 -> 18 | E39: 280 | F39: 721150 | G39: =F39/E39 -> 2575.5357 | H39: 391100 | I39: =H39/E39 -> 1396.7857 | J39: 12650 | L39: =F39+H39+J39 -> 1124900 | M39: =L39/E39 -> 4017.5 | Q39: 126 | R39: =L39/Q39 -> 8927.7778 | T39: 19.2 | U39: 24.7 | V39: 2 | W39: 2 | X39: 3 | Y39: =SUM(V39:X39)/3 -> 2.3333333 | AA39: 晴れ（33度以上）曇25度以上 | AC39: 3
A40: 水 | B40: 19 | C40: 水 | D40: =B40 -> 19 | E40: 410 | F40: 1169800 | G40: =F40/E40 -> 2853.1707 | H40: 639000 | I40: =H40/E40 -> 1558.5366 | J40: 15400 | L40: =F40+H40+J40 -> 1824200 | M40: =L40/E40 -> 4449.2683 | Q40: 126 | R40: =L40/Q40 -> 14477.778 | T40: 19.4 | U40: 25 | V40: 3 | W40: 5 | X40: 5 | Y40: =SUM(V40:X40)/3 -> 4.3333333 | AA40: 曇 | AC40: 2
A41: 木 | B41: 20 | C41: 木 | D41: =B41 -> 20 | E41: 440 | F41: 1200400 | G41: =F41/E41 -> 2728.1818 | H41: 703650 | I41: =H41/E41 -> 1599.2045 | J41: 12100 | L41: =F41+H41+J41 -> 1916150 | M41: =L41/E41 -> 4354.8864 | Q41: 143.5 | R41: =L41/Q41 -> 13352.962 | T41: 20.1 | U41: 27.9 | V41: 5 | W41: 5 | X41: 5 | Y41: =SUM(V41:X41)/3 -> 5 | AA41: 雨 | AC41: 1
A42: 金 | B42: 21 | C42: 金 | D42: =B42 -> 21 | E42: 509 | F42: 1506700 | G42: =F42/E42 -> 2960.1179 | H42: 809450 | I42: =H42/E42 -> 1590.275 | J42: 28600 | L42: =F42+H42+J42 -> 2344750 | M42: =L42/E42 -> 4606.5815 | Q42: 149 | R42: =L42/Q42 -> 15736.577 | T42: 19.3 | U42: 28.6 | V42: 5 | W42: 5 | X42: 3 | Y42: =SUM(V42:X42)/3 -> 4.3333333 | AA42: 豪雨・雷雨 | AC42: 0
A43: 土 | B43: 22 | C43: 土 | D43: =B43 -> 22 | E43: 717 | F43: 2006050 | G43: =F43/E43 -> 2797.8382 | H43: 996400 | I43: =H43/E43 -> 1389.6792 | J43: 11000 | L43: =F43+H43+J43 -> 3013450 | M43: =L43/E43 -> 4202.8591 | Q43: 170.5 | R43: =L43/Q43 -> 17674.194 | T43: 18.2 | U43: 29.4 | V43: 5 | W43: 5 | X43: 5 | Y43: =SUM(V43:X43)/3 -> 5 | AA43: ※5.6月は18時は最低気温を採用。7月〜は最高気温を採用。
A44: SUB TOTAL | C44: SUB TOTAL | E44: =SUM(E37:E43) -> 3369 | F44: =SUM(F37:F43) -> 9333100 | G44: =F44/E44 -> 2770.2879 | H44: =SUM(H37:H43) -> 5083500 | I44: =H44/E44 -> 1508.9047 | J44: =SUM(J37:J43) -> 119350 | L44: =F44+H44 -> 14416600 | M44: =L44/E44 -> 4279.1926 | Q44: =SUM(Q37:Q43) -> 1005 | R44: =L44/Q44 -> 14344.876 | S44: 7 | T44: =SUM(T37:T43)/S44 -> 19.714286 | U44: =SUM(U37:U43)/S44 -> 27.085714 | V44: =SUM(V37:V43)/S44 -> 4 | W44: =SUM(W37:W43)/S44 -> 4 | X44: =SUM(X37:X43)/S44 -> 3.8571429 | Y44: =SUM(V44:X44)/3 -> 3.952381 | Z44: ⑨ | AA44: =L44/S44 -> 2059514.3 | AF44: ※1日平均売上
A45: 5th week | C45: 5th week | T45: =C45 -> 5th week
A46: 曜日 | B46: 日にち | C46: 曜日 | D46: 日にち | E46: 客数 | F46: 料理売上 | G46: 料理単価 | H46: 飲料売上 | I46: 飲料単価 | J46: テント利用料 | K46: 物販 | L46: 売上合計 | M46: 合計単価 | N46: サーフィンズ | O46: forking | P46: Timee | Q46: 合計 | R46: 人時売上高 | T46: 最低 | U46: 最高 | V46: 12時 | W46: 15時 | X46: 18時 | Y46: Ave | AA46: ■天候要因 | AC46: 評価点
A47: 日 | B47: 23 | C47: 日 | D47: =B47 -> 23 | E47: 453 | F47: 1227450 | G47: =F47/E47 -> 2709.6026 | H47: 618100 | I47: =H47/E47 -> 1364.4592 | J47: 11000 | L47: =F47+H47+J47 -> 1856550 | M47: =L47/E47 -> 4098.3444 | Q47: 173.5 | R47: =L47/Q47 -> 10700.576 | T47: 21.2 | U47: 28.3 | V47: 5 | W47: 5 | X47: 5 | Y47: =SUM(V47:X47)/3 -> 5 | AA47: 晴れ（33度まで） | AC47: 5
A48: 月 | B48: 24 | C48: 月 | D48: =B48 -> 24 | E48: 314 | F48: 870800 | G48: =F48/E48 -> 2773.2484 | H48: 476550 | I48: =H48/E48 -> 1517.6752 | J48: 24750 | L48: =F48+H48+J48 -> 1372100 | M48: =L48/E48 -> 4369.7452 | Q48: 124.5 | R48: =L48/Q48 -> 11020.884 | T48: 22.7 | U48: 29.2 | V48: 3 | W48: 3 | X48: 3 | Y48: =SUM(V48:X48)/3 -> 3 | AA48: 晴れ（25度以下） | AC48: 4
A49: 火 | B49: 25 | C49: 火 | D49: =B49 -> 25 | E49: 315 | F49: 1021400 | G49: =F49/E49 -> 3242.5397 | H49: 573500 | I49: =H49/E49 -> 1820.6349 | J49: 6050 | L49: =F49+H49+J49 -> 1600950 | M49: =L49/E49 -> 5082.381 | Q49: 124.5 | R49: =L49/Q49 -> 12859.036 | T49: 24.8 | U49: 29.8 | V49: 1 | W49: 3 | X49: 1 | Y49: =SUM(V49:X49)/3 -> 1.6666667 | AA49: 晴れ（33度以上）曇25度以上 | AC49: 3
A50: 水 | B50: 26 | C50: 水 | D50: =B50 -> 26 | E50: 334 | F50: 860500 | G50: =F50/E50 -> 2576.3473 | H50: 520450 | I50: =H50/E50 -> 1558.2335 | J50: 10450 | L50: =F50+H50+J50 -> 1391400 | M50: =L50/E50 -> 4165.8683 | Q50: 125.5 | R50: =L50/Q50 -> 11086.853 | T50: 24 | U50: 32.7 | V50: 5 | W50: 5 | X50: 5 | Y50: =SUM(V50:X50)/3 -> 5 | AA50: 曇 | AC50: 2
A51: 木 | B51: 27 | C51: 木 | D51: =B51 -> 27 | E51: 335 | F51: 1048850 | G51: =F51/E51 -> 3130.8955 | H51: 578250 | I51: =H51/E51 -> 1726.1194 | J51: 13750 | L51: =F51+H51+J51 -> 1640850 | M51: =L51/E51 -> 4898.0597 | Q51: 171 | R51: =L51/Q51 -> 9595.614 | T51: 23.9 | U51: 32.9 | V51: 3 | W51: 5 | X51: 5 | Y51: =SUM(V51:X51)/3 -> 4.3333333 | AA51: 雨 | AC51: 1
A52: 金 | B52: 28 | C52: 金 | D52: =B52 -> 28 | E52: 410 | F52: 1340600 | G52: =F52/E52 -> 3269.7561 | H52: 737300 | I52: =H52/E52 -> 1798.2927 | J52: 37400 | L52: =F52+H52+J52 -> 2115300 | M52: =L52/E52 -> 5159.2683 | Q52: 162 | R52: =L52/Q52 -> 13057.407 | T52: 24.4 | U52: 33.7 | V52: 3 | W52: 5 | X52: 5 | Y52: =SUM(V52:X52)/3 -> 4.3333333 | AA52: 豪雨・雷雨 | AC52: 0
A53: 土 | B53: 29 | C53: 土 | D53: =B53 -> 29 | E53: 487 | F53: 1599500 | G53: =F53/E53 -> 3284.3943 | H53: 885150 | I53: =H53/E53 -> 1817.5565 | J53: 28600 | L53: =F53+H53+J53 -> 2513250 | M53: =L53/E53 -> 5160.6776 | Q53: 167 | R53: =L53/Q53 -> 15049.401 | T53: 24.9 | U53: 34.4 | V53: 3 | W53: 3 | X53: 3 | Y53: =SUM(V53:X53)/3 -> 3 | AA53: ※5.6月は18時は最低気温を採用。7月〜は最高気温を採用。
A54: SUB TOTAL | C54: SUB TOTAL | E54: =SUM(E47:E53) -> 2648 | F54: =SUM(F47:F53) -> 7969100 | G54: =F54/E54 -> 3009.4789 | H54: =SUM(H47:H53) -> 4389300 | I54: =H54/E54 -> 1657.5906 | J54: =SUM(J47:J53) -> 132000 | L54: =F54+H54 -> 12358400 | M54: =L54/E54 -> 4667.0695 | Q54: =SUM(Q47:Q53) -> 1048 | R54: =L54/Q54 -> 11792.366 | S54: 7 | T54: =SUM(T47:T53)/S54 -> 23.7 | U54: =SUM(U47:U53)/S54 -> 31.571429 | V54: =SUM(V47:V53)/S54 -> 3.2857143 | W54: =SUM(W47:W53)/S54 -> 4.1428571 | X54: =SUM(X47:X53)/S54 -> 3.8571429 | Y54: =SUM(V54:X54)/3 -> 3.7619048 | Z54: ➓ | AA54: =L54/S54 -> 1765485.7 | AF54: ※1日平均売上
A55: 6th week | C55: 6th week | T55: =C55 -> 6th week
A56: 曜日 | B56: 日にち | C56: 曜日 | D56: 日にち | E56: 客数 | F56: 料理売上 | G56: 料理単価 | H56: 飲料売上 | I56: 飲料単価 | J56: テント利用料 | K56: 物販 | L56: 売上合計 | M56: 合計単価 | N56: サーフィンズ | O56: forking | P56: Timee | Q56: 合計 | R56: 人時売上高 | T56: 最低 | U56: 最高 | V56: 12時 | W56: 15時 | X56: 18時 | Y56: Ave | AA56: ■天候要因 | AC56: 評価点
A57: 日 | B57: 30 | C57: 日 | D57: =B57 -> 30 | E57: 389 | F57: 1051700 | G57: =F57/E57 -> 2703.599 | H57: 601750 | I57: =H57/E57 -> 1546.9152 | J57: 9900 | L57: =F57+H57+J57 -> 1663350 | M57: =L57/E57 -> 4275.964 | Q57: 178 | R57: =L57/Q57 -> 9344.6629 | T57: 26 | U57: 29.9 | V57: 5 | W57: 5 | X57: 5 | Y57: =SUM(V57:X57)/3 -> 5 | AA57: 晴れ（33度まで） | AC57: 5
A58: 月 | B58: 31 | C58: 月 | D58: =B58 -> 31 | E58: 246 | F58: 638850 | G58: =F58/E58 -> 2596.9512 | H58: 330350 | I58: =H58/E58 -> 1342.8862 | J58: 7700 | L58: =F58+H58+J58 -> 976900 | M58: =L58/E58 -> 3971.1382 | Q58: 124.5 | R58: =L58/Q58 -> 7846.5863 | T58: 25.8 | U58: 28.2 | V58: 1 | W58: 1 | X58: 1 | Y58: =SUM(V58:X58)/3 -> 1 | AA58: 晴れ（25度以下） | AC58: 4
A59: 火 | C59: 火 | D59: =B59 -> 0 | G59: =F59/E59 -> #DIV/0! | I59: =H59/E59 -> #DIV/0! | L59: =F59+H59+J59 -> 0 | M59: =L59/E59 -> #DIV/0! | R59: =L59/Q59 -> #DIV/0! | Y59: =SUM(V59:X59)/3 -> 0 | AA59: 晴れ（33度以上）曇25度以上 | AC59: 3
A60: 水 | C60: 水 | D60: =B60 -> 0 | G60: =F60/E60 -> #DIV/0! | I60: =H60/E60 -> #DIV/0! | L60: =F60+H60+J60 -> 0 | M60: =L60/E60 -> #DIV/0! | R60: =L60/Q60 -> #DIV/0! | Y60: =SUM(V60:X60)/3 -> 0 | AA60: 曇 | AC60: 2
A61: 木 | C61: 木 | D61: =B61 -> 0 | G61: =F61/E61 -> #DIV/0! | I61: =H61/E61 -> #DIV/0! | L61: =F61+H61+J61 -> 0 | M61: =L61/E61 -> #DIV/0! | R61: =L61/Q61 -> #DIV/0! | Y61: =SUM(V61:X61)/3 -> 0 | AA61: 雨 | AC61: 1
A62: 金 | C62: 金 | D62: =B62 -> 0 | G62: =F62/E62 -> #DIV/0! | H62: 0 | I62: =H62/E62 -> #DIV/0! | L62: =F62+H62+J62 -> 0 | M62: =L62/E62 -> #DIV/0! | R62: =L62/Q62 -> #DIV/0! | Y62: =SUM(V62:X62)/3 -> 0 | AA62: 豪雨・雷雨 | AC62: 0
A63: 土 | C63: 土 | D63: =B63 -> 0 | G63: =F63/E63 -> #DIV/0! | H63: 0 | I63: =H63/E63 -> #DIV/0! | J63: 0 | L63: =F63+H63+J63 -> 0 | M63: =L63/E63 -> #DIV/0! | R63: =L63/Q63 -> #DIV/0! | Y63: =SUM(V63:X63)/3 -> 0 | AA63: ※5.6月は18時は最低気温を採用。7月〜は最高気温を採用。
A64: SUB TOTAL | C64: SUB TOTAL | E64: =SUM(E57:E63) -> 635 | F64: =SUM(F57:F63) -> 1690550 | G64: =F64/E64 -> 2662.2835 | H64: =SUM(H57:H63) -> 932100 | I64: =H64/E64 -> 1467.874 | J64: =SUM(J57:J63) -> 17600 | L64: =F64+H64 -> 2622650 | M64: =L64/E64 -> 4130.1575 | Q64: =SUM(Q57:Q63) -> 302.5 | R64: =L64/Q64 -> 8669.9174 | S64: 2 | T64: =SUM(T57:T63)/S64 -> 25.9 | U64: =SUM(U57:U63)/S64 -> 29.05 | V64: =SUM(V57:V63)/S64 -> 3 | W64: =SUM(W57:W63)/S64 -> 3 | X64: =SUM(X57:X63)/S64 -> 3 | Y64: =SUM(V64:X64)/3 -> 3 | Z64: 11 | AA64: =L64/S64 -> 1311325 | AF64: ※1日平均売上
A65: TOTAL | C65: TOTAL | T65: =C65 -> TOTAL
A66: 曜日 | B66: 日数 | C66: 曜日 | D66: 日数 | E66: 客数 | F66: 料理売上 | G66: 料理単価 | H66: 飲料売上 | I66: 飲料単価 | J66: テント利用料 | K66: 物販 | L66: 売上合計 | M66: 合計単価 | N66: サーフィンズ | O66: forking | P66: Timee | Q66: 合計 | R66: 人時売上高 | T66: 最低 | U66: 最高 | V66: 12時 | W66: 15時 | X66: 18時 | Y66: Ave
A67: 日 | C67: 日 | E67: =E7+E17+E27+E37+E47+E57 -> 2294 | F67: =F7+F17+F27+F37+F47+F57 -> 6281600 | G67: =F67/E67 -> 2738.2738 | H67: =H7+H17+H27+H37+H47+H57 -> 3468450 | I67: =H67/E67 -> 1511.966 | J67: =J7+J17+J27+J37+J47+J57 -> 72600 | L67: =L7+L17+L27+L37+L47+L57 -> 9822650 | M67: =M7+M17+M27+M37+M47+M57 -> #DIV/0! | Q67: =Q7+Q17+Q27+Q37+Q47+Q57 -> 833.5 | R67: =L67/Q67 -> 11784.823 | T67: =T7+T17+T27+T37+T47+T57 -> 105.6 | U67: =U7+U17+U27+U37+U47+U57 -> 140.5 | V67: =V7+V17+V37+V47+V27+V57 -> 20 | W67: =W7+W17+W37+W47+W27+W57 -> 19 | X67: =X7+X17+X37+X47+X27+X57 -> 20 | Y67: =SUM(V67:X67)/3 -> 19.666667
A68: 月 | C68: 月 | E68: =E8+E18+E28+E38+E48+E58 -> 1360 | F68: =F8+F18+F28+F38+F48+F58 -> 3589600 | G68: =F68/E68 -> 2639.4118 | H68: =H8+H18+H28+H38+H48+H58 -> 2030300 | I68: =H68/E68 -> 1492.8676 | J68: =J8+J18+J28+J38+J48+J58 -> 58850 | L68: =L8+L18+L28+L38+L48+L58 -> 5678750 | M68: =M8+M18+M28+M38+M48+M58 -> #DIV/0! | Q68: =Q8+Q18+Q28+Q38+Q48+Q58 -> 644.5 | R68: =L68/Q68 -> 8811.0939 | T68: =T8+T18+T28+T38+T48+T58 -> 108.8 | U68: =U8+U18+U28+U38+U48+U58 -> 135.7 | V68: =V8+V18+V38+V48+V28+V58 -> 14 | W68: =W8+W18+W38+W48+W28+W58 -> 14 | X68: =X8+X18+X38+X48+X28+X58 -> 14 | Y68: =SUM(V68:X68)/3 -> 14
A69: 火 | C69: 火 | E69: =E9+E19+E29+E39+E49+E59 -> 977 | F69: =F9+F19+F29+F39+F49+F59 -> 2756050 | G69: =F69/E69 -> 2820.9314 | H69: =H9+H19+H29+H39+H49+H59 -> 1550200 | I69: =H69/E69 -> 1586.694 | J69: =J9+J19+J29+J39+J49+J59 -> 36850 | L69: =L9+L19+L29+L39+L49+L59 -> 4343100 | M69: =M9+M19+M29+M39+M49+M59 -> #DIV/0! | Q69: =Q9+Q19+Q29+Q39+Q49+Q59 -> 521.5 | R69: =L69/Q69 -> 8328.092 | T69: =T9+T19+T29+T39+T49+T59 -> 84.5 | U69: =U9+U19+U29+U39+U49+U59 -> 109.5 | V69: =V9+V19+V39+V49+V29+V59 -> 12 | W69: =W9+W19+W39+W49+W29+W59 -> 12 | X69: =X9+X19+X39+X49+X29+X59 -> 11 | Y69: =SUM(V69:X69)/3 -> 11.666667
A70: 水 | C70: 水 | E70: =E10+E20+E30+E40+E50+E60 -> 1183 | F70: =F10+F20+F30+F40+F50+F60 -> 3261100 | G70: =F70/E70 -> 2756.6357 | H70: =H10+H20+H30+H40+H50+H60 -> 1804950 | I70: =H70/E70 -> 1525.7396 | J70: =J10+J20+J30+J40+J50+J60 -> 42350 | L70: =L10+L20+L30+L40+L50+L60 -> 5108400 | M70: =M10+M20+M30+M40+M50+M60 -> #DIV/0! | Q70: =Q10+Q20+Q30+Q40+Q50+Q60 -> 521.5 | R70: =L70/Q70 -> 9795.5896 | T70: =T10+T20+T30+T40+T50+T60 -> 82.8 | U70: =U10+U20+U30+U40+U50+U60 -> 111.2 | V70: =V10+V20+V40+V50+V30+V60 -> 14 | W70: =W10+W20+W40+W50+W30+W60 -> 16 | X70: =X10+X20+X40+X50+X30+X60 -> 15 | Y70: =SUM(V70:X70)/3 -> 15
A71: 木 | C71: 木 | E71: =E21+E11+E31+E41+E51+E61 -> 1300 | F71: =F21+F11+F31+F41+F51+F61 -> 3896200 | G71: =F71/E71 -> 2997.0769 | H71: =H21+H11+H31+H41+H51+H61 -> 2180150 | I71: =H71/E71 -> 1677.0385 | J71: =J21+J11+J31+J41+J51+J61 -> 37950 | L71: =L21+L11+L31+L41+L51+L61 -> 6114300 | M71: =M21+M11+M31+M41+M51+M61 -> #DIV/0! | Q71: =Q21+Q11+Q31+Q41+Q51+Q61 -> 610.5 | R71: =L71/Q71 -> 10015.233 | T71: =T11+T21+T31+T41+T51+T61 -> 83.4 | U71: =U11+U21+U31+U41+U51+U61 -> 112.7 | V71: =V11+V21+V41+V51+V31+V61 -> 14 | W71: =W11+W21+W41+W51+W31+W61 -> 14 | X71: =X11+X21+X41+X51+X31+X61 -> 14 | Y71: =SUM(V71:X71)/3 -> 14
A72: 金 | C72: 金 | E72: =E12+E22+E32+E42+E52+E62 -> 1684 | F72: =F12+F22+F32+F42+F52+F62 -> 5029950 | G72: =F72/E72 -> 2986.9062 | H72: =H12+H22+H32+H42+H52+H62 -> 2824900 | I72: =H72/E72 -> 1677.4941 | J72: =J12+J22+J32+J42+J52+J62 -> 98450 | L72: =L12+L22+L32+L42+L52+L62 -> 7953300 | M72: =M12+M22+M32+M42+M52+M62 -> #DIV/0! | Q72: =Q12+Q22+Q32+Q42+Q52+Q62 -> 627.5 | R72: =L72/Q72 -> 12674.582 | T72: =T12+T22+T32+T42+T52+T62 -> 82.9 | U72: =U12+U22+U32+U42+U52+U62 -> 113.8 | V72: =V12+V22+V42+V52+V32+V62 -> 14 | W72: =W12+W22+W42+W52+W32+W62 -> 20 | X72: =X12+X22+X42+X52+X32+X62 -> 14 | Y72: =SUM(V72:X72)/3 -> 16
A73: 土 | C73: 土 | E73: =E13+E23+E33+E43+E53+E63 -> 2238 | F73: =F13+F23+F33+F43+F53+F63 -> 6642500 | G73: =F73/E73 -> 2968.0518 | H73: =H13+H23+H33+H43+H53+H63 -> 3569050 | I73: =H73/E73 -> 1594.7498 | J73: =J13+J23+J33+J43+J53+J63 -> 110550 | L73: =L13+L23+L33+L43+L53+L63 -> 10322100 | M73: =M13+M23+M33+M43+M53+M63 -> #DIV/0! | Q73: =Q13+Q23+Q33+Q43+Q53+Q63 -> 819.5 | R73: =L73/Q73 -> 12595.607 | S73: =S14+S24+S34+S44+S54+S64 -> 31 | T73: =T13+T23+T33+T43+T53+T63 -> 101.7 | U73: =U13+U23+U33+U43+U53+U63 -> 137.8 | V73: =V13+V23+V43+V53+V33+V63 -> 16 | W73: =W13+W23+W43+W53+W33+W63 -> 18 | X73: =X13+X23+X43+X53+X33+X63 -> 18 | Y73: =SUM(V73:X73)/3 -> 17.333333
A74: TOTAL | B74: =SUM(B67:B73) -> 0 | C74: TOTAL | D74: =SUM(D67:D73) -> 0 | E74: =SUM(E67:E73) -> 11036 | F74: =SUM(F67:F73) -> 31457000 | G74: =F74/E74 -> 2850.3987 | H74: =SUM(H67:H73) -> 17428000 | I74: =H74/E74 -> 1579.1954 | J74: =SUM(J67:J73) -> 457600 | L74: =SUM(L67:L73) -> 49342600 | M74: =L74/E74 -> 4471.0584 | Q74: =SUM(Q67:Q73) -> 4578.5 | R74: =L74/Q74 -> 10777.023 | T74: =SUM(T67:T73)/S73 -> 20.958065 | U74: =SUM(U67:U73)/S73 -> 27.780645 | V74: =SUM(V67:V73)/S73 -> 3.3548387 | W74: =SUM(W67:W73)/S73 -> 3.6451613 | X74: =SUM(X67:X73)/S73 -> 3.4193548 | Y74: =SUM(V74:X74)/3 -> 3.4731183
A75: ■対比 | C75: ■対比
A77: ランチ | C77: ランチ | E77: 予算
E78: ランチ
E79: 客数 | H79: F売上 | L79: B売上
H80: =#REF!*E80 -> #REF! | L80: =#REF!*E80 -> #REF!
E82: ■予算差異
E83: 客数 | H83: F売上 | L83: B売上
E84: =E74-E80 -> 11036 | H84: =H74-H80 -> #REF! | L84: =L74-L80 -> #REF!
E85: =E74/E80 -> #DIV/0! | H85: =H74/H80 -> #REF! | L85: =L74/L80 -> #REF!
E86: ■前年値（数値残っていない休業）
E87: 客数 | H87: F売上 | L87: B売上
E89: ■前年差異
E90: 客数 | H90: F売上 | L90: B売上
E91: =E74-E88 -> 11036 | H91: =H74-H88 -> 17428000 | L91: =L74-L88 -> 49342600
E92: =E74/E88 -> #DIV/0! | H92: =H74/H88 -> #DIV/0! | L92: =L74/L88 -> #DIV/0!
A93: 構成比率 | J93: 税抜売上 | L93: =L74/1.1 -> 44856909 | M93: 対予測達成率 | Q93: =L93/#REF! -> #REF! | R93: =L93-#REF! -> #REF!
H95: 売上総合計（レストラン+テイク） | R95: =R74+#REF! -> #REF!
A98: ■モデルシフト
A99: モデルシフト カテゴリー
A100: TOP1
A101: TOP2
A102: ON1
A103: ON2
A104: ショルダー
A105: OFF1
A106: OFF2

Sheet 7月時間帯別売上実績
A1: ■7月 時間帯別売上実績&曜日別売上実績
A2: 営業日 | B2: ランチ | E2: アイドル | G2: ディナー | L2: 合計
B3: 12時 | C3: 13時 | D3: 14時 | E3: 15時 | F3: 16時 | G3: 17時 | H3: 18時 | I3: 19時 | J3: 20時 | K3: 21時
A4: 2023/07/01(土) | B4: 85900 | C4: 86450 | D4: 105050 | E4: 37400 | F4: 90900 | G4: 190750 | H4: 209850 | I4: 175750 | J4: 32050 | K4: 0 | L4: =SUM(B4:K4) -> 1014100
A5: 2023/07/02(日) | B5: 198200 | C5: 152300 | D5: 93700 | E5: 87100 | F5: 118300 | G5: 119500 | H5: 138100 | I5: 150000 | J5: 91250 | K5: 4000 | L5: =SUM(B5:K5) -> 1152450
A6: 2023/07/03(月) | B6: 147150 | C6: 29000 | D6: 47450 | E6: 88800 | F6: 54900 | G6: 104400 | H6: 152850 | I6: 21900 | J6: 17000 | K6: 4100 | L6: =SUM(B6:K6) -> 667550
A7: 2023/07/04(火) | B7: 126250 | C7: 58800 | D7: 45800 | E7: 61400 | F7: 96550 | G7: 90550 | H7: 124950 | I7: 173050 | J7: 30750 | K7: 0 | L7: =SUM(B7:K7) -> 808100
A8: 2023/07/05(水) | B8: 110250 | C8: 71900 | D8: 154900 | E8: 106950 | F8: 66500 | G8: 73650 | H8: 310950 | I8: 167950 | J8: 32400 | K8: 0 | L8: =SUM(B8:K8) -> 1095450
A9: 2023/07/06(木) | B9: 129400 | C9: 73000 | D9: 47700 | E9: 38400 | F9: 15650 | G9: 108900 | H9: 22000 | I9: 0 | J9: 1127500 | K9: 44000 | L9: =SUM(B9:K9) -> 1606550
A10: 2023/07/07(金) | B10: 127450 | C10: 114550 | D10: 62300 | E10: 63800 | F10: 228350 | G10: 219450 | H10: 432850 | I10: 385450 | J10: 101400 | K10: 41000 | L10: =SUM(B10:K10) -> 1776600
A11: 2023/07/08(土) | B11: 327200 | C11: 236300 | D11: 233000 | E11: 299900 | F11: 149100 | G11: 272100 | H11: 293050 | I11: 373300 | J11: 357550 | K11: 1700 | L11: =SUM(B11:K11) -> 2543200
A12: 2023/07/09(日) | B12: 10150 | C12: 193350 | D12: 482800 | E12: 263150 | F12: 195750 | G12: 331000 | H12: 258150 | I12: 485100 | J12: 69250 | K12: 2100 | L12: =SUM(B12:K12) -> 2290800
A13: 2023/07/10(月) | B13: 147900 | C13: 76900 | D13: 79850 | E13: 99850 | F13: 52450 | G13: 160700 | H13: 349400 | I13: 175850 | J13: 66300 | K13: 0 | L13: =SUM(B13:K13) -> 1209200
A14: 2023/07/11(火) | B14: 143400 | C14: 128800 | D14: 44600 | E14: 3200 | F14: 40300 | G14: 119000 | H14: 76150 | I14: 235250 | J14: 18450 | K14: 0 | L14: =SUM(B14:K14) -> 809150
A15: 2023/07/12(水) | B15: 168150 | C15: 63000 | D15: 13700 | E15: 9900 | F15: 27250 | G15: 203000 | H15: 175600 | I15: 55250 | J15: 71500 | K15: 10000 | L15: =SUM(B15:K15) -> 797350
... A34: 2023/07/31(月) | B34: 60900 | C34: 64450 | D34: 18500 | E34: 35000 | F34: 67550 | G34: 52850 | H34: 275300 | I34: 273300 | J34: 121650 | K34: 7400 | L34: =SUM(B34:K34) -> 976900
A35: 【合計】 | B35: 5247250 | C35: 3312550 | D35: 3229150 | E35: 2946900 | F35: 4324150 | G35: =SUM(G4:G34) -> 6173650 | H35: =SUM(H4:H34) -> 9383850 | I35: =SUM(I4:I34) -> 7930200 | J35: =SUM(J4:J34) -> 4636050 | K35: =SUM(K4:K34) -> 2146750 | L35: =SUM(B35:K35) -> 49330500
B36: =B35+C35+D35 -> 11788950 | E36: =E35+F35 -> 7271050 | G36: =G35+H35+I35+J35+K35 -> 30270500 | L36: =SUM(B36:J36) -> 49330500
A37: 売上比率 | B37: =B36/L36 -> 0.23897893 | E37: =E36/L36 -> 0.14739461 | G37: =G36/L36 -> 0.61362646 | L37: =SUM(B37:J37) -> 1
B38: =B37+E37 -> 0.38637354
A39: ■7月 曜日別売上平均
A40: 【日曜日 平均】 | B40: 245810 | C40: 187620 | D40: 240050 | E40: 175930 | F40: 191250 | G40: 281960 | H40: 242400 | I40: 296560 | J40: 88325 | K40: 9650 | L40: 1962110
A41: 【月曜日 平均】 | B41: 152610 | C41: 64150 | D41: 68710 | E41: 76690 | F41: 78090 | G41: 151720 | H41: 237460 | I41: 208100 | J41: 76575 | K41: 3375 | L41: 1135750
A42: 【火曜日 平均】 | B42: 114813 | C42: 76238 | D42: 61850 | E42: 44550 | F42: 77900 | G42: 111163 | H42: 164713 | I42: 288563 | J42: 58300 | K42: 33740 | L42: 1085775
A43: 【水曜日 平均】 | B43: 165325 | C43: 72463 | D43: 81388 | E43: 52263 | F43: 78325 | G43: 172775 | H43: 280338 | I43: 128113 | J43: 49200 | K43: 17880 | L43: 1277100
A44: 【木曜日 平均】 | B44: 104000 | C44: 70513 | D44: 64213 | E44: 61550 | F44: 174588 | G44: 114563 | H44: 336663 | I44: 146513 | J44: 36900 | K44: 12600 | L44: 1528575
A45: 【金曜日 平均】 | B45: 134900 | C45: 126713 | D45: 62750 | E45: 84625 | F45: 153775 | G45: 288163 | H45: 475388 | I45: 403900 | J45: 154013 | K45: 6875 | L45: 1988325
A46: 【土曜日 平均】 | B46: 235800 | C46: 134000 | D46: 120910 | E46: 142370 | F46: 207820 | G46: 251720 | H46: 391230 | I46: 307710 | J46: 143850 | K46: 9313 | L46: 2064420 | N46: 2064420
A47: ■7月 曜日別売上合計
A48: 【日曜日 合計】 | B48: 959450 | C48: 354250 | D48: 481850 | E48: 532400 | F48: 820350 | G48: 955400 | H48: 1378300 | I48: 861050 | J48: 353300 | K48: 38600 | L48: 9810550
A49: 【月曜日 合計】 | B49: 576000 | C49: 428950 | D49: 248300 | E49: 323800 | F49: 379850 | G49: 642400 | H49: 1397700 | I49: 1237100 | J49: 306300 | K49: 13500 | L49: 5678750
A50: 【火曜日 合計】 | B50: 635650 | C50: 389750 | D50: 332100 | E50: 577750 | F50: 551900 | G50: 1516650 | H50: 1836550 | I50: 1722100 | J50: 291500 | K50: 168700 | L50: 4343100
A51: 【水曜日 合計】 | B51: 429800 | C51: 408100 | D51: 208600 | E51: 244750 | F51: 357750 | G51: 1160000 | H51: 1752100 | I51: 1511000 | J51: 246000 | K51: 89400 | L51: 5108400
A52: 【木曜日 合計】 | B52: 468100 | C52: 308100 | D52: 234300 | E52: 349100 | F52: 175950 | G52: 1141550 | H52: 1637300 | I52: 1805200 | J52: 184500 | K52: 63000 | L52: 6114300
A53: 【金曜日 合計】 | B53: 444750 | C53: 362900 | D53: 286750 | E53: 338150 | F53: 518100 | G53: 952500 | H53: 1625500 | I53: 1932000 | J53: 616050 | K53: 27500 | L53: 7953300
A54: 【土曜日 合計】 | B54: 961900 | C54: 639100 | D54: 694650 | E54: 597150 | F54: 1042650 | G54: 1035800 | H54: 2058850 | I54: 1367450 | J54: 575400 | K54: 37250 | L54: 10322100 | N54: 10322100

Sheet 2023.6月実績
A1: ■R5年度 ビアガーデン売上実績
A2: 6月 | P2: =P14+P24+P34+P44+P54+P64 -> 20844700 | V2: 30
A3: FOOD予測 | G3: ビアガーデン6月 TOTAL実績 | R3: 客数 | V3: 売上
A4: 予算 | G4: 実績 | I4: 客数 | K4: 客単価 | M4: 売上予算 | P4: 25440000 | Q4: 1日平均 | V4: =P4/V2 -> 848000 | X4: 天候要因（売上との関連性を数値化する）
A5: 1st week | G5: 1st week | X5: =G5 -> 1st week
A6: 曜日 | B6: 日にち | C6: A | D6: B | E6: C | F6: S | G6: 曜日 | H6: 日にち | I6: 客数 | J6: 料理売上 | K6: 料理単価 | L6: 飲料売上 | M6: 飲料単価 | N6: テント利用料 | O6: 物販 | P6: 売上合計 | Q6: 合計単価 | R6: サーフィンズ | S6: forking | T6: Timee | U6: 合計 | V6: 人時売上高 | X6: 最低 | Y6: 最高 | Z6: 12時 | AA6: 15時 | AB6: 18時 | AC6: Ave | AE6: ■天候要因 | AG6: 評価点
A7: 日 | G7: 日 | H7: =B7 -> 0 | J7: 0 | K7: =J7/I7 -> #DIV/0! | L7: 0 | M7: =L7/I7 -> #DIV/0! | P7: =J7+L7+N7 -> 0 | Q7: =P7/I7 -> #DIV/0! | V7: =P7/U7 -> #DIV/0! | AC7: =SUM(Z7:AB7)/3 -> 0 | AE7: 晴れ（33度まで） | AG7: 5
A8: 月 | G8: 月 | H8: =B8 -> 0 | J8: 0 | K8: =J8/I8 -> #DIV/0! | L8: 0 | M8: =L8/I8 -> #DIV/0! | P8: =J8+L8+N8 -> 0 | Q8: =P8/I8 -> #DIV/0! | V8: =P8/U8 -> #DIV/0! | AC8: =SUM(Z8:AB8)/3 -> 0 | AE8: 晴れ（25度以下） | AG8: 4
A9: 火 | G9: 火 | H9: =B9 -> 0 | J9: 0 | K9: =J9/I9 -> #DIV/0! | L9: 0 | M9: =L9/I9 -> #DIV/0! | P9: =J9+L9+N9 -> 0 | Q9: =P9/I9 -> #DIV/0! | V9: =P9/U9 -> #DIV/0! | AC9: =SUM(Z9:AB9)/3 -> 0 | AE9: 晴れ（33度以上）曇25度以上 | AG9: 3
A10: 水 | G10: 水 | H10: =B10 -> 0 | J10: 0 | K10: =J10/I10 -> #DIV/0! | L10: 0 | M10: =L10/I10 -> #DIV/0! | P10: =J10+L10+N10 -> 0 | Q10: =P10/I10 -> #DIV/0! | V10: =P10/U10 -> #DIV/0! | AC10: =SUM(Z10:AB10)/3 -> 0 | AE10: 曇 | AG10: 2
A11: 木 | B11: 1 | G11: 木 | H11: =B11 -> 1 | I11: 122 | J11: 267250 | K11: =J11/I11 -> 2190.5738 | L11: 165950 | M11: =L11/I11 -> 1360.2459 | P11: =J11+L11+N11 -> 433200 | Q11: =P11/I11 -> 3550.8197 | U11: 82.5 | V11: =P11/U11 -> 5250.9091 | X11: 9.6 | Y11: 24.7 | Z11: 4 | AA11: 4 | AB11: 4 | AC11: =SUM(Z11:AB11)/3 -> 4 | AE11: 雨 | AG11: 1
A12: 金 | B12: 2 | G12: 金 | H12: =B12 -> 2 | I12: 86 | J12: 251600 | K12: =J12/I12 -> 2925.5814 | L12: 138150 | M12: =L12/I12 -> 1606.3953 | N12: 3300 | P12: =J12+L12+N12 -> 393050 | Q12: =P12/I12 -> 4570.3488 | U12: 80 | V12: =P12/U12 -> 4913.125 | X12: 15.4 | Y12: 21.9 | Z12: 4 | AA12: 4 | AB12: 1 | AC12: =SUM(Z12:AB12)/3 -> 3 | AE12: 豪雨・雷雨 | AG12: 0
A13: 土 | B13: 3 | G13: 土 | H13: =B13 -> 3 | I13: 89 | J13: 211600 | K13: =J13/I13 -> 2377.5281 | L13: 127000 | M13: =L13/I13 -> 1426.9663 | N13: 3850 | P13: =J13+L13+N13 -> 342450 | Q13: =P13/I13 -> 3847.7528 | U13: 97.25 | V13: =P13/U13 -> 3521.3368 | X13: 13.6 | Y13: 16.4 | Z13: 1 | AA13: 1 | AB13: 4 | AC13: =SUM(Z13:AB13)/3 -> 2 | AE13: ※5.6月は18時は最低気温を採用。7月〜は最高気温を採用。
A14: SUB TOTAL | C14: P/D | D14: =#REF!/F14 -> #REF! | E14: 日にち | F14: =#REF! -> #REF! | G14: SUB TOTAL | I14: =SUM(I7:I13) -> 297 | J14: =SUM(J7:J13) -> 730450 | K14: =J14/I14 -> 2459.4276 | L14: =SUM(L7:L13) -> 431100 | M14: =L14/I14 -> 1451.5152 | N14: =SUM(N7:N13) -> 7150 | P14: =J14+L14 -> 1161550 | Q14: =P14/I14 -> 3910.9428 | U14: =SUM(U7:U13) -> 259.75 | V14: =P14/U14 -> 4471.7998 | W14: 3 | X14: =SUM(X7:X13)/W14 -> 12.866667 | Y14: =SUM(Y7:Y13)/W14 -> 21 | Z14: =SUM(Z7:Z13)/W14 -> 3 | AA14: =SUM(AA7:AA13)/W14 -> 3 | AB14: =SUM(AB7:AB13)/W14 -> 3 | AC14: =SUM(Z14:AB14)/3 -> 3 | AD14: ② | AE14: =P14/W14 -> 387183.33 | AJ14: ※1日平均売上
A15: 2nd week | G15: 2nd week | X15: =G15 -> 2nd week
A16: 曜日 | B16: 日にち | C16: A | D16: B | E16: C | F16: S | G16: 曜日 | H16: 日にち | I16: 客数 | J16: 料理売上 | K16: 料理単価 | L16: 飲料売上 | M16: 飲料単価 | N16: テント利用料 | O16: 物販 | P16: 売上合計 | Q16: 合計単価 | R16: サーフィンズ | S16: forking | T16: Timee | U16: 合計 | V16: 人時売上高 | X16: 最低 | Y16: 最高 | Z16: 12時 | AA16: 15時 | AB16: 18時 | AC16: Ave | AE16: ■天候要因 | AG16: 評価点
A17: 日 | B17: 4 | G17: 日 | H17: =B17 -> 4 | I17: 65 | J17: 141300 | K17: =J17/I17 -> 2173.8462 | L17: 91750 | M17: =L17/I17 -> 1411.5385 | N17: 1650 | P17: =J17+L17+N17 -> 234700 | Q17: =P17/I17 -> 3610.7692 | U17: 93.75 | V17: =P17/U17 -> 2503.4667 | X17: 8.2 | Y17: 17.4 | Z17: 1 | AA17: 1 | AB17: 4 | AC17: =SUM(Z17:AB17)/3 -> 2 | AE17: 晴れ（33度まで） | AG17: 5
A18: 月 | B18: 5 | G18: 月 | H18: =B18 -> 5 | I18: 29 | J18: 72850 | K18: =J18/I18 -> 2512.069 | L18: 31500 | M18: =L18/I18 -> 1086.2069 | N18: 1100 | P18: =J18+L18+N18 -> 105450 | Q18: =P18/I18 -> 3636.2069 | U18: 77.75 | V18: =P18/#REF! -> #REF! | X18: 8.9 | Y18: 17.7 | Z18: 2 | AA18: 1 | AB18: 4 | AC18: =SUM(Z18:AB18)/3 -> 2.3333333 | AE18: 晴れ（25度以下） | AG18: 4
A19: 火 | B19: 6 | G19: 火 | H19: =B19 -> 6 | I19: 63 | J19: 164050 | K19: =J19/I19 -> 2603.9683 | L19: 90300 | M19: =L19/I19 -> 1433.3333 | P19: =J19+L19+N19 -> 254350 | Q19: =P19/I19 -> 4037.3016 | U19: 81.75 | V19: =P19/U18 -> 3271.3826 | X19: 10.9 | Y19: 22.5 | Z19: 1 | AA19: 1 | AB19: 4 | AC19: =SUM(Z19:AB19)/3 -> 2 | AE19: 晴れ（33度以上）曇25度以上 | AG19: 3
A20: 水 | B20: 7 | G20: 水 | H20: =B20 -> 7 | I20: 43 | J20: 120750 | K20: =J20/I20 -> 2808.1395 | L20: 58900 | M20: =L20/I20 -> 1369.7674 | N20: 1100 | P20: =J20+L20+N20 -> 180750 | Q20: =P20/I20 -> 4203.4884 | U20: 81 | V20: =P20/U20 -> 2231.4815 | X20: 15.5 | Y20: 20.6 | Z20: 1 | AA20: 1 | AB20: 2 | AC20: =SUM(Z20:AB20)/3 -> 1.3333333 | AE20: 曇 | AG20: 2
A21: 木 | B21: 8 | G21: 木 | H21: =B21 -> 8 | I21: 132 | J21: 294300 | K21: =J21/I21 -> 2229.5455 | L21: 213750 | M21: =L21/I21 -> 1619.3182 | P21: =J21+L21+N21 -> 508050 | Q21: =P21/I21 -> 3848.8636 | U21: 84.5 | V21: =P21/U21 -> 6012.426 | X21: 14.3 | Y21: 26.2 | Z21: 5 | AA21: 5 | AB21: 4 | AC21: =SUM(Z21:AB21)/3 -> 4.6666667 | AE21: 雨 | AG21: 1
A22: 金 | B22: 9 | G22: 金 | H22: =B22 -> 9 | I22: 44 | J22: 101050 | K22: =J22/I22 -> 2296.5909 | L22: 67800 | M22: =L22/I22 -> 1540.9091 | N22: 2750 | P22: =J22+L22+N22 -> 171600 | Q22: =P22/I22 -> 3900 | U22: 77 | V22: =P22/U22 -> 2228.5714 | X22: 16.4 | Y22: 19.2 | Z22: 1 | AA22: 1 | AB22: 1 | AC22: =SUM(Z22:AB22)/3 -> 1 | AE22: 豪雨・雷雨 | AG22: 0
A23: 土 | B23: 10 | G23: 土 | H23: =B23 -> 10 | I23: 251 | J23: 475300 | K23: =J23/I23 -> 1893.6255 | L23: 298450 | M23: =L23/I23 -> 1189.0438 | N23: 2200 | P23: =J23+L23+N23 -> 775950 | Q23: =P23/I23 -> 3091.4343 | U23: 107 | V23: =P23/U23 -> 7251.8692 | X23: 15.3 | Y23: 19.2 | Z23: 4 | AA23: 4 | AB23: 4 | AC23: =SUM(Z23:AB23)/3 -> 4 | AE23: ※5.6月は18時は最低気温を採用。7月〜は最高気温を採用。
A24: SUB TOTAL | C24: P/D | D24: =#REF!/F24 -> #REF! | E24: 日にち | F24: =#REF! -> #REF! | G24: SUB TOTAL | I24: =SUM(I17:I23) -> 627 | J24: =SUM(J17:J23) -> 1369600 | K24: =J24/I24 -> 2184.37 | L24: =SUM(L17:L23) -> 852450 | M24: =L24/I24 -> 1359.5694 | N24: =SUM(N17:N23) -> 8800 | P24: =J24+L24 -> 2222050 | Q24: =P24/I24 -> 3543.9394 | U24: =SUM(U17:U23) -> 602.75 | V24: =P24/U24 -> 3686.5201 | W24: 7 | X24: =SUM(X17:X23)/W24 -> 12.785714 | Y24: =SUM(Y17:Y23)/W24 -> 20.4 | Z24: =SUM(Z17:Z23)/W24 -> 2.1428571 | AA24: =SUM(AA17:AA23)/W24 -> 2 | AB24: =SUM(AB17:AB23)/W24 -> 3.2857143 | AC24: =SUM(Z24:AB24)/3 -> 2.4761905 | AD24: ③ | AE24: =P24/W24 -> 317435.71 | AJ24: ※1日平均売上
A25: 3rd week | G25: 3rd week | X25: =G25 -> 3rd week
A26: 曜日 | B26: 日にち | C26: A | D26: B | E26: C | F26: S | G26: 曜日 | H26: 日にち | I26: 客数 | J26: 料理売上 | K26: 料理単価 | L26: 飲料売上 | M26: 飲料単価 | N26: テント利用料 | O26: 物販 | P26: 売上合計 | Q26: 合計単価 | R26: サーフィンズ | S26: forking | T26: Timee | U26: 合計 | V26: 人時売上高 | X26: 最低 | Y26: 最高 | Z26: 12時 | AA26: 15時 | AB26: 18時 | AC26: Ave | AE26: ■天候要因 | AG26: 評価点
A27: 日 | B27: 11 | G27: 日 | H27: =B27 -> 11 | I27: 357 | J27: 883900 | K27: =J27/I27 -> 2475.9104 | L27: 474900 | M27: =L27/I27 -> 1330.2521 | N27: 10450 | P27: =J27+L27+N27 -> 1369250 | Q27: =P27/I27 -> 3835.4342 | U27: 112 | V27: =P27/U27 -> 12225.446 | X27: 13.4 | Y27: 24.2 | Z27: 4 | AA27: 4 | AB27: 4 | AC27: =SUM(Z27:AB27)/3 -> 4 | AE27: 晴れ（33度まで） | AG27: 5
A28: 月 | B28: 12 | G28: 月 | H28: =B28 -> 12 | I28: 133 | J28: 326800 | K28: =J28/I28 -> 2457.1429 | L28: 207900 | M28: =L28/I28 -> 1563.1579 | N28: 0 | P28: =J28+L28+N28 -> 534700 | Q28: =P28/I28 -> 4020.3008 | U28: 77 | V28: =P28/U28 -> 6944.1558 | X28: 15.7 | Y28: 25.6 | Z28: 5 | AA28: 5 | AB28: 4 | AC28: =SUM(Z28:AB28)/3 -> 4.6666667 | AE28: 晴れ（25度以下） | AG28: 4
A29: 火 | B29: 13 | G29: 火 | H29: =B29 -> 13 | I29: 82 | J29: 198000 | K29: =J29/I29 -> 2414.6341 | L29: 108850 | M29: =L29/I29 -> 1327.439 | N29: 0 | P29: =J29+L29+N29 -> 306850 | Q29: =P29/I29 -> 3742.0732 | U29: 83 | V29: =P29/U29 -> 3696.988 | X29: 16.9 | Y29: 21.9 | Z29: 2 | AA29: 2 | AB29: 2 | AC29: =SUM(Z29:AB29)/3 -> 2 | AE29: 晴れ（33度以上）曇25度以上 | AG29: 3
A30: 水 | B30: 14 | G30: 水 | H30: =B30 -> 14 | I30: 140 | J30: 250550 | K30: =J30/I30 -> 1789.6429 | L30: 164400 | M30: =L30/I30 -> 1174.2857 | N30: 0 | P30: =J30+L30+N30 -> 414950 | Q30: =P30/I30 -> 2963.9286 | U30: 81.75 | V30: =P30/U30 -> 5075.841 | X30: 16.5 | Y30: 23.2 | Z30: 1 | AA30: 4 | AB30: 4 | AC30: =SUM(Z30:AB30)/3 -> 3 | AE30: 曇 | AG30: 2
A31: 木 | B31: 15 | G31: 木 | H31: =B31 -> 15 | I31: 302 | J31: 879850 | K31: =J31/I31 -> 2913.4106 | L31: 491900 | M31: =L31/I31 -> 1628.8079 | N31: 0 | P31: =J31+L31+N31 -> 1371750 | Q31: =P31/I31 -> 4542.2185 | U31: 116 | V31: =P31/U31 -> 11825.431 | X31: 16 | Y31: 26.5 | Z31: 5 | AA31: 5 | AB31: 4 | AC31: =SUM(Z31:AB31)/3 -> 4.6666667 | AE31: 雨 | AG31: 1
A32: 金 | B32: 16 | G32: 金 | H32: =B32 -> 16 | I32: 219 | J32: 535200 | K32: =J32/I32 -> 2443.8356 | L32: 338000 | M32: =L32/I32 -> 1543.379 | N32: 1650 | P32: =J32+L32+N32 -> 874850 | Q32: =P32/I32 -> 3994.7489 | U32: 99.75 | V32: =P32/U32 -> 8770.4261 | X32: 17.3 | Y32: 27.3 | Z32: 5 | AA32: 5 | AB32: 3 | AC32: =SUM(Z32:AB32)/3 -> 4.3333333 | AE32: 豪雨・雷雨 | AG32: 0
A33: 土 | B33: 17 | G33: 土 | H33: =B33 -> 17 | I33: 443 | J33: 1093200 | K33: =J33/I33 -> 2467.7201 | L33: 666750 | M33: =L33/I33 -> 1505.079 | N33: 11000 | P33: =J33+L33+N33 -> 1770950 | Q33: =P33/I33 -> 3997.6298 | U33: 110.5 | V33: =P33/U33 -> 16026.697 | X33: 16.9 | Y33: 28.7 | Z33: 5 | AA33: 5 | AB33: 4 | AC33: =SUM(Z33:AB33)/3 -> 4.6666667 | AE33: ※5.6月は18時は最低気温を採用。7月〜は最高気温を採用。
A34: SUB TOTAL | C34: P/D | D34: =#REF!/F34 -> #REF! | E34: 日にち | F34: =#REF! -> #REF! | G34: SUB TOTAL | I34: =SUM(I27:I33) -> 1676 | J34: =SUM(J27:J33) -> 4167500 | K34: =J34/I34 -> 2486.5752 | L34: =SUM(L27:L33) -> 2452700 | M34: =L34/I34 -> 1463.4248 | N34: =SUM(N27:N33) -> 23100 | P34: =J34+L34 -> 6620200 | Q34: =P34/I34 -> 3950 | U34: =SUM(U27:U33) -> 680 | V34: =P34/U34 -> 9735.5882 | W34: 7 | X34: =SUM(X27:X33)/W34 -> 16.1 | Y34: =SUM(Y27:Y33)/W34 -> 25.342857 | Z34: =SUM(Z27:Z33)/W34 -> 3.8571429 | AA34: =SUM(AA27:AA33)/W34 -> 4.2857143 | AB34: =SUM(AB27:AB33)/W34 -> 3.5714286 | AC34: =SUM(Z34:AB34)/3 -> 3.9047619 | AD34: ④ | AE34: =P34/W34 -> 945742.86 | AJ34: ※1日平均売上
A35: 4th week | G35: 4th week | X35: =G35 -> 4th week
A36: 曜日 | B36: 日にち | C36: A | D36: B | E36: C | F36: S | G36: 曜日 | H36: 日にち | I36: 客数 | J36: 料理売上 | K36: 料理単価 | L36: 飲料売上 | M36: 飲料単価 | N36: テント利用料 | O36: 物販 | P36: 売上合計 | Q36: 合計単価 | R36: サーフィンズ | S36: forking | T36: Timee | U36: 合計 | V36: 人時売上高 | X36: 最低 | Y36: 最高 | Z36: 12時 | AA36: 15時 | AB36: 18時 | AC36: Ave | AE36: ■天候要因 | AG36: 評価点
A37: 日 | B37: 18 | G37: 日 | H37: =B37 -> 18 | I37: 137 | J37: 388350 | K37: =J37/I37 -> 2834.6715 | L37: 197550 | M37: =L37/I37 -> 1441.9708 | N37: 4400 | P37: =J37+L37+N37 -> 590300 | Q37: =P37/I37 -> 4308.7591 | U37: 104.75 | V37: =P37/U37 -> 5635.3222 | X37: 17.4 | Y37: 21.5 | Z37: 1 | AA37: 2 | AB37: 4 | AC37: =SUM(Z37:AB37)/3 -> 2.3333333 | AE37: 晴れ（33度まで） | AG37: 5
A38: 月 | B38: 19 | G38: 月 | H38: =B38 -> 19 | I38: 132 | J38: 344400 | K38: =J38/I38 -> 2609.0909 | L38: 207700 | M38: =L38/I38 -> 1573.4848 | N38: 8800 | P38: =J38+L38+N38 -> 560900 | Q38: =P38/I38 -> 4249.2424 | U38: 77.5 | V38: =P38/U38 -> 7237.4194 | X38: 14.7 | Y38: 20 | Z38: 4 | AA38: 4 | AB38: 4 | AC38: =SUM(Z38:AB38)/3 -> 4 | AE38: 晴れ（25度以下） | AG38: 4
A39: 火 | B39: 20 | G39: 火 | H39: =B39 -> 20 | I39: 169 | J39: 438050 | K39: =J39/I39 -> 2592.0118 | L39: 268950 | M39: =L39/I39 -> 1591.4201 | N39: 5500 | P39: =J39+L39+N39 -> 712500 | Q39: =P39/I39 -> 4215.9763 | U39: 82.25 | V39: =P39/U39 -> 8662.614 | X39: 13.8 | Y39: 23.6 | Z39: 4 | AA39: 4 | AB39: 4 | AC39: =SUM(Z39:AB39)/3 -> 4 | AE39: 晴れ（33度以上）曇25度以上 | AG39: 3
A40: 水 | B40: 21 | G40: 水 | H40: =B40 -> 21 | I40: 200 | J40: 509950 | K40: =J40/I40 -> 2549.75 | L40: 326300 | M40: =L40/I40 -> 1631.5 | N40: 3300 | P40: =J40+L40+N40 -> 839550 | Q40: =P40/I40 -> 4197.75 | U40: 84.75 | V40: =P40/U40 -> 9906.1947 | X40: 14.5 | Y40: 28.2 | Z40: 5 | AA40: 5 | AB40: 4 | AC40: =SUM(Z40:AB40)/3 -> 4.6666667 | AE40: 曇 | AG40: 2
A41: 木 | B41: 22 | G41: 木 | H41: =B41 -> 22 | I41: 149 | J41: 335050 | K41: =J41/I41 -> 2248.6577 | L41: 199500 | M41: =L41/I41 -> 1338.9262 | N41: 0 | P41: =J41+L41+N41 -> 534550 | Q41: =P41/I41 -> 3587.5839 | U41: 99.75 | V41: =P41/U41 -> 5358.8972 | X41: 17.1 | Y41: 24.5 | Z41: 4 | AA41: 4 | AB41: 4 | AC41: =SUM(Z41:AB41)/3 -> 4 | AE41: 雨 | AG41: 1
A42: 金 | B42: 23 | G42: 金 | H42: =B42 -> 23 | I42: 160 | J42: 434850 | K42: =J42/I42 -> 2717.8125 | L42: 222300 | M42: =L42/I42 -> 1389.375 | N42: 14850 | P42: =J42+L42+N42 -> 672000 | Q42: =P42/I42 -> 4200 | U42: 99.75 | V42: =P42/U42 -> 6736.8421 | X42: 18.4 | Y42: 26 | Z42: 3 | AA42: 3 | AB42: 4 | AC42: =SUM(Z42:AB42)/3 -> 3.3333333 | AE42: 豪雨・雷雨 | AG42: 0
A43: 土 | B43: 24 | G43: 土 | H43: =B43 -> 24 | I43: 413 | J43: 1040950 | K43: =J43/I43 -> 2520.46 | L43: 632850 | M43: =L43/I43 -> 1532.3245 | N43: 4400 | P43: =J43+L43+N43 -> 1678200 | Q43: =P43/I43 -> 4063.4383 | U43: 122.25 | V43: =P43/U43 -> 13727.607 | X43: 16.8 | Y43: 25.3 | Z43: 5 | AA43: 5 | AB43: 4 | AC43: =SUM(Z43:AB43)/3 -> 4.6666667 | AE43: ※5.6月は18時は最低気温を採用。7月〜は最高気温を採用。
A44: SUB TOTAL | C44: P/D | D44: =#REF!/F44 -> #REF! | E44: 日にち | F44: =#REF! -> #REF! | G44: SUB TOTAL | I44: =SUM(I37:I43) -> 1360 | J44: =SUM(J37:J43) -> 3491600 | K44: =J44/I44 -> 2567.3529 | L44: =SUM(L37:L43) -> 2055150 | M44: =L44/I44 -> 1511.1397 | N44: =SUM(N37:N43) -> 41250 | P44: =J44+L44 -> 5546750 | Q44: =P44/I44 -> 4078.4926 | U44: =SUM(U37:U43) -> 671 | V44: =P44/U44 -> 8266.3934 | W44: 7 | X44: =SUM(X37:X43)/W44 -> 16.1 | Y44: =SUM(Y37:Y43)/W44 -> 24.157143 | Z44: =SUM(Z37:Z43)/W44 -> 3.7142857 | AA44: =SUM(AA37:AA43)/W44 -> 3.8571429 | AB44: =SUM(AB37:AB43)/W44 -> 4 | AC44: =SUM(Z44:AB44)/3 -> 3.8571429 | AD44: ⑤ | AE44: =P44/W44 -> 792392.86 | AJ44: ※1日平均売上
A45: 5th week | G45: 5th week | X45: =G45 -> 5th week
A46: 曜日 | B46: 日にち | C46: A | D46: B | E46: C | F46: S | G46: 曜日 | H46: 日にち | I46: 客数 | J46: 料理売上 | K46: 料理単価 | L46: 飲料売上 | M46: 飲料単価 | N46: テント利用料 | O46: 物販 | P46: 売上合計 | Q46: 合計単価 | R46: サーフィンズ | S46: forking | T46: Timee | U46: 合計 | V46: 人時売上高 | X46: 最低 | Y46: 最高 | Z46: 12時 | AA46: 15時 | AB46: 18時 | AC46: Ave | AE46: ■天候要因 | AG46: 評価点
A47: 日 | B47: 25 | G47: 日 | H47: =B47 -> 25 | I47: 435 | J47: 1115450 | K47: =J47/I47 -> 2564.2529 | L47: 675450 | M47: =L47/I47 -> 1552.7586 | N47: 2200 | P47: =J47+L47+N47 -> 1793100 | Q47: =P47/I47 -> 4122.069 | U47: 131.75 | V47: =P47/U47 -> 13609.867 | X47: 16.3 | Y47: 27.9 | Z47: 5 | AA47: 5 | AB47: 4 | AC47: =SUM(Z47:AB47)/3 -> 4.6666667 | AE47: 晴れ（33度まで） | AG47: 5
A48: 月 | B48: 26 | G48: 月 | H48: =B48 -> 26 | I48: 210 | J48: 441450 | K48: =J48/I48 -> 2102.1429 | L48: 292650 | M48: =L48/I48 -> 1393.5714 | N48: 2200 | P48: =J48+L48+N48 -> 736300 | Q48: =P48/I48 -> 3506.1905 | U48: 104.25 | V48: =P48/U48 -> 7062.8297 | X48: 17.6 | Y48: 28.3 | Z48: 5 | AA48: 5 | AB48: 4 | AC48: =SUM(Z48:AB48)/3 -> 4.6666667 | AE48: 晴れ（25度以下） | AG48: 4
A49: 火 | B49: 27 | G49: 火 | H49: =B49 -> 27 | I49: 259 | J49: 660050 | K49: =J49/I49 -> 2548.4556 | L49: 435850 | M49: =L49/I49 -> 1682.8185 | N49: 6600 | P49: =J49+L49+N49 -> 1102500 | Q49: =P49/I49 -> 4256.7568 | U49: 102 | V49: =P49/U49 -> 10808.824 | X49: 17.9 | Y49: 31.2 | Z49: 5 | AA49: 5 | AB49: 4 | AC49: =SUM(Z49:AB49)/3 -> 4.6666667 | AE49: 晴れ（33度以上）曇25度以上 | AG49: 3
A50: 水 | B50: 28 | G50: 水 | H50: =B50 -> 28 | I50: 240 | J50: 564400 | K50: =J50/I50 -> 2351.6667 | L50: 332600 | M50: =L50/I50 -> 1385.8333 | N50: 0 | P50: =J50+L50+N50 -> 897000 | Q50: =P50/I50 -> 3737.5 | U50: 114.25 | V50: =P50/U50 -> 7851.2035 | X50: 20.5 | Y50: 29.2 | Z50: 1 | AA50: 3 | AB50: 4 | AC50: =SUM(Z50:AB50)/3 -> 2.6666667 | AE50: 曇 | AG50: 2
A51: 木 | B51: 29 | G51: 木 | H51: =B51 -> 29 | I51: 87 | J51: 190300 | K51: =J51/I51 -> 2187.3563 | L51: 145100 | M51: =L51/I51 -> 1667.8161 | N51: 5500 | P51: =J51+L51+N51 -> 340900 | Q51: =P51/I51 -> 3918.3908 | U51: 85 | V51: =P51/U51 -> 4010.5882 | X51: 21.3 | Y51: 28.2 | Z51: 1 | AA51: 3 | AB51: 1 | AC51: =SUM(Z51:AB51)/3 -> 1.6666667 | AE51: 雨 | AG51: 1
A52: 金 | B52: 30 | G52: 金 | H52: =B52 -> 30 | I52: 118 | J52: 282200 | K52: =J52/I52 -> 2391.5254 | L52: 158650 | M52: =L52/I52 -> 1344.4915 | N52: 13200 | P52: =J52+L52+N52 -> 454050 | Q52: =P52/I52 -> 3847.8814 | U52: 118.5 | V52: =P52/U52 -> 3831.6456 | X52: 20.7 | Y52: 25.7 | Z52: 3 | AA52: 1 | AB52: 2 | AC52: =SUM(Z52:AB52)/3 -> 2 | AE52: 豪雨・雷雨 | AG52: 0
A53: 土 | G53: 土 | H53: =B53 -> 0 | K53: =J53/I53 -> #DIV/0! | L53: 0 | M53: =L53/I53 -> #DIV/0! | N53: 0 | P53: =J53+L53+N53 -> 0 | Q53: =P53/I53 -> #DIV/0! | V53: =P53/U53 -> #DIV/0! | AC53: =SUM(Z53:AB53)/3 -> 0 | AE53: ※5.6月は18時は最低気温を採用。7月〜は最高気温を採用。
A54: SUB TOTAL | C54: P/D | D54: =#REF!/F54 -> #REF! | E54: 日にち | F54: =#REF! -> #REF! | G54: SUB TOTAL | I54: =SUM(I47:I53) -> 1349 | J54: =SUM(J47:J53) -> 3253850 | K54: =J54/I54 -> 2412.046 | L54: =SUM(L47:L53) -> 2040300 | M54: =L54/I54 -> 1512.4537 | N54: =SUM(N47:N53) -> 29700 | P54: =J54+L54 -> 5294150 | Q54: =P54/I54 -> 3924.4996 | U54: =SUM(U47:U53) -> 655.75 | V54: =P54/U54 -> 8073.4274 | W54: 6 | X54: =SUM(X47:X53)/W54 -> 19.05 | Y54: =SUM(Y47:Y53)/W54 -> 28.416667 | Z54: =SUM(Z47:Z53)/W54 -> 3.3333333 | AA54: =SUM(AA47:AA53)/W54 -> 3.6666667 | AB54: =SUM(AB47:AB53)/W54 -> 3.1666667 | AC54: =SUM(Z54:AB54)/3 -> 3.3888889 | AD54: ⑥ | AE54: =P54/W54 -> 882358.33 | AJ54: ※1日平均売上
A55: 6th week | G55: 6th week | X55: =G55 -> 6th week
A56: 曜日 | B56: 日にち | C56: A | D56: B | E56: C | F56: S | G56: 曜日 | H56: 日にち | I56: 客数 | J56: 料理売上 | K56: 料理単価 | L56: 飲料売上 | M56: 飲料単価 | N56: テント利用料 | O56: 物販 | P56: 売上合計 | Q56: 合計単価 | R56: サーフィンズ | S56: forking | T56: Timee | U56: 合計 | V56: 人時売上高 | X56: 最低 | Y56: 最高 | Z56: 12時 | AA56: 15時 | AB56: 18時 | AC56: Ave | AE56: ■天候要因 | AG56: 評価点
A57: 日 | G57: 日 | H57: =B57 -> 0 | K57: =J57/I57 -> #DIV/0! | M57: =L57/I57 -> #DIV/0! | P57: =J57+L57+N57 -> 0 | Q57: =P57/I57 -> #DIV/0! | V57: =P57/U57 -> #DIV/0! | AC57: =SUM(Z57:AB57)/3 -> 0 | AE57: 晴れ（33度まで） | AG57: 5
A58: 月 | G58: 月 | H58: =B58 -> 0 | K58: =J58/I58 -> #DIV/0! | M58: =L58/I58 -> #DIV/0! | P58: =J58+L58+N58 -> 0 | Q58: =P58/I58 -> #DIV/0! | V58: =P58/U58 -> #DIV/0! | AC58: =SUM(Z58:AB58)/3 -> 0 | AE58: 晴れ（25度以下） | AG58: 4
A59: 火 | G59: 火 | H59: =B59 -> 0 | K59: =J59/I59 -> #DIV/0! | M59: =L59/I59 -> #DIV/0! | P59: =J59+L59+N59 -> 0 | Q59: =P59/I59 -> #DIV/0! | V59: =P59/U59 -> #DIV/0! | AC59: =SUM(Z59:AB59)/3 -> 0 | AE59: 晴れ（33度以上）曇25度以上 | AG59: 3
A60: 水 | G60: 水 | H60: =B60 -> 0 | K60: =J60/I60 -> #DIV/0! | M60: =L60/I60 -> #DIV/0! | P60: =J60+L60+N60 -> 0 | Q60: =P60/I60 -> #DIV/0! | V60: =P60/U60 -> #DIV/0! | AC60: =SUM(Z60:AB60)/3 -> 0 | AE60: 曇 | AG60: 2
A61: 木 | G61: 木 | H61: =B61 -> 0 | K61: =J61/I61 -> #DIV/0! | M61: =L61/I61 -> #DIV/0! | P61: =J61+L61+N61 -> 0 | Q61: =P61/I61 -> #DIV/0! | V61: =P61/U61 -> #DIV/0! | AC61: =SUM(Z61:AB61)/3 -> 0 | AE61: 雨 | AG61: 1
A62: 金 | G62: 金 | H62: =B62 -> 0 | K62: =J62/I62 -> #DIV/0! | L62: 0 | M62: =L62/I62 -> #DIV/0! | P62: =J62+L62+N62 -> 0 | Q62: =P62/I62 -> #DIV/0! | V62: =P62/U62 -> #DIV/0! | AC62: =SUM(Z62:AB62)/3 -> 0 | AE62: 豪雨・雷雨 | AG62: 0
A63: 土 | G63: 土 | H63: =B63 -> 0 | K63: =J63/I63 -> #DIV/0! | L63: 0 | M63: =L63/I63 -> #DIV/0! | N63: 0 | P63: =J63+L63+N63 -> 0 | Q63: =P63/I63 -> #DIV/0! | V63: =P63/U63 -> #DIV/0! | AC63: =SUM(Z63:AB63)/3 -> 0 | AE63: ※5.6月は18時は最低気温を採用。7月〜は最高気温を採用。
A64: SUB TOTAL | C64: P/D | D64: =#REF!/F64 -> #REF! | E64: 日にち | F64: =#REF! -> #REF! | G64: SUB TOTAL | I64: =SUM(I57:I63) -> 0 | J64: =SUM(J57:J63) -> 0 | K64: =J64/I64 -> #DIV/0! | L64: =SUM(L57:L63) -> 0 | M64: =L64/I64 -> #DIV/0! | N64: =SUM(N57:N63) -> 0 | P64: =J64+L64 -> 0 | Q64: =P64/I64 -> #DIV/0! | U64: =SUM(U57:U63) -> 0 | V64: =P64/U64 -> #DIV/0! | X64: =SUM(X57:X63)/W64 -> #DIV/0! | Y64: =SUM(Y57:Y63)/W64 -> #DIV/0! | Z64: =SUM(Z57:Z63)/W64 -> #DIV/0! | AA64: =SUM(AA57:AA63)/W64 -> #DIV/0! | AB64: =SUM(AB57:AB63)/W64 -> #DIV/0! | AC64: =SUM(Z64:AB64)/3 -> #DIV/0! | AE64: =P64/W64 -> #DIV/0!
A65: TOTAL | G65: TOTAL | X65: =G65 -> TOTAL
A66: 曜日 | B66: 日数 | G66: 曜日 | H66: 日数 | I66: 客数 | J66: 料理売上 | K66: 料理単価 | L66: 飲料売上 | M66: 飲料単価 | N66: テント利用料 | O66: 物販 | P66: 売上合計 | Q66: 合計単価 | R66: サーフィンズ | S66: forking | T66: Timee | U66: 合計 | V66: 人時売上高 | X66: 最低 | Y66: 最高 | Z66: 12時 | AA66: 15時 | AB66: 18時 | AC66: Ave
A67: 日 | G67: 日 | I67: =I7+I17+I27+I37+I47+I57 -> 994 | J67: =J7+J17+J27+J37+J47+J57 -> 2529000 | K67: =J67/I67 -> 2544.2656 | L67: =L7+L17+L27+L37+L47+L57 -> 1439650 | M67: =L67/I67 -> 1448.34 | N67: =N7+N17+N27+N37+N47+N57 -> 18700 | P67: =P7+P17+P27+P37+P47+P57 -> 3987350 | Q67: =Q7+Q17+Q27+Q37+Q47+Q57 -> #DIV/0! | U67: =U7+U17+U27+U37+U47+U57 -> 442.25 | V67: =P67/U67 -> 9016.0543 | X67: =X7+X17+X27+X37+X47+X57 -> 55.3 | Y67: =Y7+Y17+Y27+Y37+Y47+Y57 -> 91 | Z67: =Z7+Z17+Z37+Z47+Z27+Z57 -> 11 | AA67: =AA7+AA17+AA37+AA47+AA27+AA57 -> 12 | AB67: =AB7+AB17+AB37+AB47+AB27+AB57 -> 16 | AC67: =SUM(Z67:AB67)/3 -> 13
A68: 月 | G68: 月 | I68: =I8+I18+I28+I38+I48+I58 -> 504 | J68: =J8+J18+J28+J38+J48+J58 -> 1185500 | K68: =J68/I68 -> 2352.1825 | L68: =L8+L18+L28+L38+L48+L58 -> 739750 | M68: =L68/I68 -> 1467.7579 | N68: =N8+N18+N28+N38+N48+N58 -> 12100 | P68: =P8+P18+P28+P38+P48+P58 -> 1937350 | Q68: =Q8+Q18+Q28+Q38+Q48+Q58 -> #DIV/0! | U68: =U8+U18+U28+U38+U48+U58 -> 336.5 | V68: =P68/U68 -> 5757.3551 | X68: =X8+X18+X28+X38+X48+X58 -> 56.9 | Y68: =Y8+Y18+Y28+Y38+Y48+Y58 -> 91.6 | Z68: =Z8+Z18+Z38+Z48+Z28+Z58 -> 16 | AA68: =AA8+AA18+AA38+AA48+AA28+AA58 -> 15 | AB68: =AB8+AB18+AB38+AB48+AB28+AB58 -> 16 | AC68: =SUM(Z68:AB68)/3 -> 15.666667
A69: 火 | G69: 火 | I69: =I9+I19+I29+I39+I49+I59 -> 573 | J69: =J9+J19+J29+J39+J49+J59 -> 1460150 | K69: =J69/I69 -> 2548.2548 | L69: =L9+L19+L29+L39+L49+L59 -> 903950 | M69: =L69/I69 -> 1577.5742 | N69: =N9+N19+N29+N39+N49+N59 -> 12100 | P69: =P9+P19+P29+P39+P49+P59 -> 2376200 | Q69: =Q9+Q19+Q29+Q39+Q49+Q59 -> #DIV/0! | U69: =U9+U19+U29+U39+U49+U59 -> 349 | V69: =P69/U69 -> 6808.596 | X69: =X9+X19+X29+X39+X49+X59 -> 59.5 | Y69: =Y9+Y19+Y29+Y39+Y49+Y59 -> 99.2 | Z69: =Z9+Z19+Z39+Z49+Z29+Z59 -> 12 | AA69: =AA9+AA19+AA39+AA49+AA29+AA59 -> 12 | AB69: =AB9+AB19+AB39+AB49+AB29+AB59 -> 14 | AC69: =SUM(Z69:AB69)/3 -> 12.666667
A70: 水 | G70: 水 | I70: =I10+I20+I30+I40+I50+I60 -> 623 | J70: =J10+J20+J30+J40+J50+J60 -> 1445650 | K70: =J70/I70 -> 2320.4655 | L70: =L10+L20+L30+L40+L50+L60 -> 882200 | M70: =L70/I70 -> 1416.0514 | N70: =N10+N20+N30+N40+N50+N60 -> 4400 | P70: =P10+P20+P30+P40+P50+P60 -> 2332250 | Q70: =Q10+Q20+Q30+Q40+Q50+Q60 -> #DIV/0! | U70: =U10+U20+U30+U40+U50+U60 -> 361.75 | V70: =P70/U70 -> 6447.132 | X70: =X10+X20+X30+X40+X50+X60 -> 67 | Y70: =Y10+Y20+Y30+Y40+Y50+Y60 -> 101.2 | Z70: =Z10+Z20+Z40+Z50+Z30+Z60 -> 8 | AA70: =AA10+AA20+AA40+AA50+AA30+AA60 -> 13 | AB70: =AB10+AB20+AB40+AB50+AB30+AB60 -> 14 | AC70: =SUM(Z70:AB70)/3 -> 11.666667
A71: 木 | G71: 木 | I71: =I21+I11+I31+I41+I51+I61 -> 792 | J71: =J21+J11+J31+J41+J51+J61 -> 1966750 | K71: =J71/I71 -> 2483.2702 | L71: =L21+L11+L31+L41+L51+L61 -> 1216200 | M71: =L71/I71 -> 1535.6061 | N71: =N21+N11+N31+N41+N51+N61 -> 5500 | P71: =P21+P11+P31+P41+P51+P61 -> 3188450 | Q71: =Q21+Q11+Q31+Q41+Q51+Q61 -> #DIV/0! | U71: =U21+U11+U31+U41+U51+U61 -> 467.75 | V71: =P71/U71 -> 6816.5687 | X71: =X11+X21+X31+X41+X51+X61 -> 78.3 | Y71: =Y11+Y21+Y31+Y41+Y51+Y61 -> 130.1 | Z71: =Z11+Z21+Z41+Z51+Z31+Z61 -> 19 | AA71: =AA11+AA21+AA41+AA51+AA31+AA61 -> 21 | AB71: =AB11+AB21+AB41+AB51+AB31+AB61 -> 17 | AC71: =SUM(Z71:AB71)/3 -> 19
A72: 金 | G72: 金 | I72: =I12+I22+I32+I42+I52+I62 -> 627 | J72: =J12+J22+J32+J42+J52+J62 -> 1604900 | K72: =J72/I72 -> 2559.6491 | L72: =L12+L22+L32+L42+L52+L62 -> 924900 | M72: =L72/I72 -> 1475.1196 | N72: =N12+N22+N32+N42+N52+N62 -> 35750 | P72: =P12+P22+P32+P42+P52+P62 -> 2565550 | Q72: =Q12+Q22+Q32+Q42+Q52+Q62 -> #DIV/0! | U72: =U12+U22+U32+U42+U52+U62 -> 475 | V72: =P72/U72 -> 5401.1579 | X72: =X12+X22+X32+X42+X52+X62 -> 88.2 | Y72: =Y12+Y22+Y32+Y42+Y52+Y62 -> 120.1 | Z72: =Z12+Z22+Z42+Z52+Z32+Z62 -> 16 | AA72: =AA12+AA22+AA42+AA52+AA32+AA62 -> 14 | AB72: =AB12+AB22+AB42+AB52+AB32+AB62 -> 11 | AC72: =SUM(Z72:AB72)/3 -> 13.666667
A73: 土 | G73: 土 | I73: =I13+I23+I33+I43+I53+I63 -> 1196 | J73: =J13+J23+J33+J43+J53+J63 -> 2821050 | K73: =J73/I73 -> 2358.7375 | L73: =L13+L23+L33+L43+L53+L63 -> 1725050 | M73: =L73/I73 -> 1442.3495 | N73: =N13+N23+N33+N43+N53+N63 -> 21450 | P73: =P13+P23+P33+P43+P53+P63 -> 4567550 | Q73: =Q13+Q23+Q33+Q43+Q53+Q63 -> #DIV/0! | U73: =U13+U23+U33+U43+U53+U63 -> 437 | V73: =P73/U73 -> 10452.059 | W73: =W14+W24+W34+W44+W54+W64 -> 30 | X73: =X13+X23+X33+X43+X53+X63 -> 62.6 | Y73: =Y13+Y23+Y33+Y43+Y53+Y63 -> 89.6 | Z73: =Z13+Z23+Z43+Z53+Z33+Z63 -> 15 | AA73: =AA13+AA23+AA43+AA53+AA33+AA63 -> 15 | AB73: =AB13+AB23+AB43+AB53+AB33+AB63 -> 16 | AC73: =SUM(Z73:AB73)/3 -> 15.333333
A74: TOTAL | B74: =SUM(B67:B73) -> 0 | C74: P/D | D74: =#REF!/F74 -> #REF! | E74: 日にち | F74: =#REF! -> #REF! | G74: TOTAL | H74: =SUM(H67:H73) -> 0 | I74: =SUM(I67:I73) -> 5309 | J74: =SUM(J67:J73) -> 13013000 | K74: =J74/I74 -> 2451.1207 | L74: =SUM(L67:L73) -> 7831700 | M74: =L74/I74 -> 1475.1742 | N74: =SUM(N67:N73) -> 110000 | P74: =SUM(P67:P73) -> 20954700 | Q74: =P74/I74 -> 3947.0145 | U74: =SUM(U67:U73) -> 2869.25 | V74: =P74/U74 -> 7303.1977 | X74: =SUM(X67:X73)/W73 -> 15.593333 | Y74: =SUM(Y67:Y73)/W73 -> 24.093333 | Z74: =SUM(Z67:Z73)/W73 -> 3.2333333 | AA74: =SUM(AA67:AA73)/W73 -> 3.4 | AB74: =SUM(AB67:AB73)/W73 -> 3.4666667 | AC74: =SUM(Z74:AB74)/3 -> 3.3666667
A75: ■対比 | G75: ■対比
A77: ランチ | G77: ランチ | I77: 予算
I78: ランチ
I79: 客数 | L79: F売上 | P79: B売上
L80: =#REF!*I80 -> #REF! | P80: =#REF!*I80 -> #REF!
I82: ■予算差異
I83: 客数 | L83: F売上 | P83: B売上
I84: =I74-I80 -> 5309 | L84: =L74-L80 -> #REF! | P84: =P74-P80 -> #REF!
I85: =I74/I80 -> #DIV/0! | L85: =L74/L80 -> #REF! | P85: =P74/P80 -> #REF!
I86: ■前年値（数値残っていない休業）
I87: 客数 | L87: F売上 | P87: B売上
I89: ■前年差異
I90: 客数 | L90: F売上 | P90: B売上
I91: =I74-I88 -> 5309 | L91: =L74-L88 -> 7831700 | P91: =P74-P88 -> 20954700
I92: =I74/I88 -> #DIV/0! | L92: =L74/L88 -> #DIV/0! | P92: =P74/P88 -> #DIV/0!
A93: 構成比率 | N93: 税抜売上 | P93: =P74/1.1 -> 19049727 | Q93: 対予測達成率 | U93: =P93/#REF! -> #REF! | V93: =P93-#REF! -> #REF!
L95: 売上総合計（レストラン+テイク） | V95: =V74+#REF! -> #REF!
A98: ■モデルシフト
A99: モデルシフト カテゴリー
A100: TOP1
A101: TOP2
A102: ON1
A103: ON2
A104: ショルダー
A105: OFF1
A106: OFF2

Sheet 6月時間帯別売上実績
A1: ■6月 時間帯別売上実績&曜日別売上実績
A2: 営業日 | B2: ランチ | E2: アイドル | G2: ディナー | L2: 合計
B3: 12時 | C3: 13時 | D3: 14時 | E3: 15時 | F3: 16時 | G3: 17時 | H3: 18時 | I3: 19時 | J3: 20時 | K3: 21時
A4: 2023/06/01(木) | B4: 60500 | C4: 68450 | D4: 33000 | E4: 20200 | F4: 12000 | G4: 64600 | H4: 125650 | I4: 48200 | J4: 600 | K4: 0 | L4: 433200
A5: 2023/06/02(金) | B5: 81300 | C5: 29350 | D5: 23600 | E5: 5700 | F5: 34250 | G5: 47700 | H5: 96800 | I5: 74350 | J5: 0 | K5: 0 | L5: 393050
A6: 2023/06/03(土) | B6: 71500 | C6: 12350 | D6: 28700 | E6: 41450 | F6: 32900 | G6: 90350 | H6: 62400 | I6: 2800 | J6: 0 | K6: 0 | L6: 342450
A7: 2023/06/04(日) | B7: 56250 | C7: 50150 | D7: 4350 | E7: 2800 | F7: 11000 | G7: 38500 | H7: 26700 | I7: 44950 | J7: 0 | K7: 0 | L7: 234700
A8: 2023/06/05(月) | B8: 32650 | C8: 28600 | D8: 5500 | E8: 12700 | F8: 0 | G8: 8200 | H8: 11000 | I8: 6800 | J8: 0 | K8: 0 | L8: 105450
A9: 2023/06/06(火) | B9: 22850 | C9: 39800 | D9: 13300 | E9: 23300 | F9: 21500 | G9: 2800 | H9: 104650 | I9: 20450 | J9: 5700 | K9: 0 | L9: 254350
A10: 2023/06/07(水) | B10: 39050 | C10: 11000 | D10: 10500 | E10: 17700 | F10: 21400 | G10: 24400 | H10: 56700 | I10: 0 | J10: 0 | K10: 0 | L10: 180750
A11: 2023/06/08(木) | B11: 76400 | C11: 70600 | D11: 43450 | E11: 35850 | F11: 20500 | G11: 74550 | H11: 124000 | I11: 51300 | J11: 11400 | K11: 0 | L11: 508050
A12: 2023/06/09(金) | B12: 6050 | C12: 0 | D12: 4400 | E12: 2450 | F12: 13700 | G12: 53650 | H12: 52850 | I12: 27500 | J12: 0 | K12: 0 | L12: 160600
A13: 2023/06/10(土) | B13: 145700 | C13: 164600 | D13: 96000 | E13: 27750 | F13: 86000 | G13: 82950 | H13: 99100 | I13: 67400 | J13: 5250 | K13: 1200 | L13: 775950
A14: 2023/06/11(日) | B14: 288600 | C14: 163300 | D14: 153000 | E14: 149900 | F14: 152250 | G14: 130300 | H14: 183250 | I14: 107050 | J14: 41600 | K14: 0 | L14: 1369250
A15: 2023/06/12(月) | B15: 179650 | C15: 51350 | D15: 64800 | E15: 24150 | F15: 38500 | G15: 84250 | H15: 58500 | I15: 31450 | J15: 2050 | K15: 0 | L15: 534700
... A33: 2023/06/30(金) | B33: 54700 | C33: 52700 | D33: 35650 | E33: 20300 | F33: 0 | G33: 163650 | H33: 89550 | I33: 36300 | J33: 1200 | K33: 0 | L33: 454050
A35: 【合計】 | B35: =SUM(B4:B34) -> 3144500 | C35: =SUM(C4:C34) -> 2472300 | D35: =SUM(D4:D34) -> 1643200 | E35: =SUM(E4:E34) -> 1514300 | F35: =SUM(F4:F34) -> 1786800 | G35: =SUM(G4:G34) -> 2973400 | H35: =SUM(H4:H34) -> 4267350 | I35: =SUM(I4:I34) -> 1902950 | ... K35: =SUM(K4:K34) -> 51250 | L35: =SUM(B35:K35) -> 20917150
B36: =B35+C35+D35 -> 7260000 | E36: =E35+F35 -> 3301100 | G36: =G35+H35+I35+J35+K35 -> 10356050 | L36: =SUM(B36:J36) -> 20917150
A37: 売上比率 | B37: =B36/L36 -> 0.34708361 | E37: =E36/L36 -> 0.15781787 | G37: =G36/L36 -> 0.49509852 | L37: =SUM(B37:J37) -> 1
B38: =B37+E37 -> 0.50490148
A39: ■6月 曜日別売上平均
A40: 【日曜日 平均】 | B40: 197025 | C40: 173963 | D40: 100375 | E40: 95788 | F40: 102350 | G40: 103775 | H40: 125200 | I40: 83988 | J40: 14375 | K40: 0 | L40: 996838
A41: 【月曜日 平均】 | B41: 98538 | C41: 51113 | D41: 43825 | E41: 25650 | F41: 45500 | G41: 78175 | H41: 108388 | I41: 31238 | J41: 1913 | K41: 0 | L41: 484338
A42: 【火曜日 平均】 | B42: 93875 | C42: 76000 | D42: 38013 | E42: 48338 | F42: 53063 | G42: 69763 | H42: 156413 | I42: 53500 | J42: 5088 | K42: 0 | L42: 594050
A43: 【水曜日 平均】 | B43: 70988 | C43: 48775 | D43: 33625 | E43: 43138 | F43: 55313 | G43: 107338 | H43: 143850 | I43: 70213 | J43: 9300 | K43: 525 | L43: 583063
A44: 【木曜日 平均】 | B44: 74300 | C44: 76810 | D44: 34770 | E44: 39650 | F44: 25850 | G44: 63500 | H44: 99670 | I44: 32630 | J44: 188830 | K44: 0 | L44: 636010
A45: 【金曜日 平均】 | B45: 45470 | C45: 31290 | D45: 30360 | E45: 14710 | F45: 35670 | G45: 111100 | H45: 160050 | I45: 70090 | J45: 3830 | K45: 4710 | L45: 507280
A46: 【土曜日 平均】 | B46: 175988 | C46: 133100 | D46: 113550 | E46: 97713 | F46: 113575 | G46: 166050 | H46: 208338 | I46: 108400 | J46: 18775 | K46: 6400 | L46: 1141888
A47: ■6月 曜日別売上合計
A48: 【日曜日 合計】 | B48: 788100 | C48: 695850 | D48: 401500 | E48: 383150 | F48: 409400 | G48: 415100 | H48: 500800 | I48: 335950 | J48: 57500 | K48: 0 | L48: 3987350
A49: 【月曜日 合計】 | B49: 394150 | C49: 204450 | D49: 175300 | E49: 102600 | F49: 182000 | G49: 312700 | H49: 433550 | I49: 124950 | J49: 7650 | K49: 0 | L49: 1937350
A50: 【火曜日 合計】 | B50: 375500 | C50: 304000 | D50: 152050 | E50: 193350 | F50: 212250 | G50: 279050 | H50: 625650 | I50: 214000 | J50: 20350 | K50: 0 | L50: 2376200
A51: 【水曜日 合計】 | B51: 283950 | C51: 195100 | D51: 134500 | E51: 172550 | F51: 221250 | G51: 429350 | H51: 575400 | I51: 280850 | J51: 37200 | K51: 2100 | L51: 2332250
A52: 【木曜日 合計】 | B52: 371500 | C52: 384050 | D52: 173850 | E52: 198250 | F52: 129250 | G52: 317500 | H52: 498350 | I52: 163150 | J52: 944150 | K52: 0 | L52: 3180050
A53: 【金曜日 合計】 | B53: 227350 | C53: 156450 | D53: 151800 | E53: 73550 | F53: 178350 | G53: 555500 | H53: 800250 | I53: 350450 | J53: 19150 | K53: 23550 | L53: 2536400
A54: 【土曜日 合計】 | B54: 703950 | C54: 532400 | D54: 454200 | E54: 390850 | F54: 454300 | G54: 664200 | H54: 833350 | I54: 433600 | J54: 75100 | K54: 25600 | L54: 4567550

Sheet 2023.5月実績
A1: ■R5年度 ビアガーデン売上実績
A2: 5月
A3: FOOD予測 | G3: ビアガーデン5月 TOTAL実績 | R3: 客数 | V3: 売上
A4: 予算 | G4: 実績 | I4: 客数 | K4: 客単価 | M4: 売上 | Q4: 1日平均 | X4: 天候要因（売上との関連性を数値化する）
A5: 1st week | G5: 1st week | X5: =G5 -> 1st week
A6: 曜日 | B6: 日にち | C6: A | D6: B | E6: C | F6: S | G6: 曜日 | H6: 日にち | I6: 客数 | J6: 料理売上 | K6: 料理単価 | L6: 飲料売上 | M6: 飲料単価 | N6: テント利用料 | O6: 物販 | P6: 売上合計 | Q6: 合計単価 | R6: サーフィンズ | S6: forking | T6: Timee | U6: 合計 | V6: 人時売上高 | X6: 最低 | Y6: 最高 | Z6: 12時 | AA6: 15時 | AB6: 18時 | AC6: Ave | AE6: ■天候要因 | AG6: 評価点
A7: 日 | G7: 日 | H7: =B7 -> 0 | J7: 0 | K7: =J7/I7 -> #DIV/0! | L7: 0 | M7: =L7/I7 -> #DIV/0! | P7: =J7+L7+N7 -> 0 | Q7: =P7/I7 -> #DIV/0! | V7: =P7/U7 -> #DIV/0! | AC7: =SUM(Z7:AB7)/3 -> 0 | AE7: 晴れ（33度まで） | AG7: 5
A8: 月 | B8: 1 | G8: 月 | H8: =B8 -> 1 | J8: 0 | K8: =J8/I8 -> #DIV/0! | L8: 0 | M8: =L8/I8 -> #DIV/0! | P8: =J8+L8+N8 -> 0 | Q8: =P8/I8 -> #DIV/0! | V8: =P8/U8 -> #DIV/0! | AC8: =SUM(Z8:AB8)/3 -> 0 | AE8: 晴れ（25度以下） | AG8: 4
A9: 火 | B9: 2 | G9: 火 | H9: =B9 -> 2 | J9: 0 | K9: =J9/I9 -> #DIV/0! | L9: 0 | M9: =L9/I9 -> #DIV/0! | P9: =J9+L9+N9 -> 0 | Q9: =P9/I9 -> #DIV/0! | V9: =P9/U9 -> #DIV/0! | AC9: =SUM(Z9:AB9)/3 -> 0 | AE9: 晴れ（33度以上）曇25度以上 | AG9: 3
A10: 水 | B10: 3 | G10: 水 | H10: =B10 -> 3 | J10: 0 | K10: =J10/I10 -> #DIV/0! | L10: 0 | M10: =L10/I10 -> #DIV/0! | P10: =J10+L10+N10 -> 0 | Q10: =P10/I10 -> #DIV/0! | V10: =P10/U10 -> #DIV/0! | AC10: =SUM(Z10:AB10)/3 -> 0 | AE10: 曇 | AG10: 2
A11: 木 | B11: 4 | G11: 木 | H11: =B11 -> 4 | J11: 0 | K11: =J11/I11 -> #DIV/0! | L11: 0 | M11: =L11/I11 -> #DIV/0! | P11: =J11+L11+N11 -> 0 | Q11: =P11/I11 -> #DIV/0! | V11: =P11/U11 -> #DIV/0! | AC11: =SUM(Z11:AB11)/3 -> 0 | AE11: 雨 | AG11: 1
A12: 金 | B12: 5 | G12: 金 | H12: =B12 -> 5 | J12: 0 | K12: =J12/I12 -> #DIV/0! | L12: 0 | M12: =L12/I12 -> #DIV/0! | P12: =J12+L12+N12 -> 0 | Q12: =P12/I12 -> #DIV/0! | V12: =P12/U12 -> #DIV/0! | AC12: =SUM(Z12:AB12)/3 -> 0 | AE12: 豪雨・雷雨 | AG12: 0
A13: 土 | B13: 6 | G13: 土 | H13: =B13 -> 6 | J13: 0 | K13: =J13/I13 -> #DIV/0! | L13: 0 | M13: =L13/I13 -> #DIV/0! | N13: 0 | P13: =J13+L13+N13 -> 0 | Q13: =P13/I13 -> #DIV/0! | V13: =P13/U13 -> #DIV/0! | AC13: =SUM(Z13:AB13)/3 -> 0 | AE13: ※5.6月は18時は最低気温を採用。7月〜は最高気温を採用。
A14: SUB TOTAL | C14: P/D | D14: =#REF!/F14 -> #REF! | E14: 日にち | F14: =#REF! -> #REF! | G14: SUB TOTAL | I14: =SUM(I7:I13) -> 0 | J14: =SUM(J7:J13) -> 0 | K14: =J14/I14 -> #DIV/0! | L14: =SUM(L7:L13) -> 0 | M14: =L14/I14 -> #DIV/0! | N14: =M14/J14 -> #DIV/0! | P14: =J14+L14 -> 0 | Q14: =P14/I14 -> #DIV/0! | V14: =P14/U14 -> #DIV/0! | X14: =SUM(X7:X13)/W14 -> #DIV/0! | Y14: =SUM(Y7:Y13)/W14 -> #DIV/0! | Z14: =SUM(Z7:Z13)/W14 -> #DIV/0! | AA14: =SUM(AA7:AA13)/W14 -> #DIV/0! | AB14: =SUM(AB7:AB13)/W14 -> #DIV/0! | AC14: =SUM(Z14:AB14)/3 -> #DIV/0!
A15: 2nd week | G15: 2nd week | X15: =G15 -> 2nd week
A16: 曜日 | B16: 日にち | C16: A | D16: B | E16: C | F16: S | G16: 曜日 | H16: 日にち | I16: 客数 | J16: 料理売上 | K16: 料理単価 | L16: 飲料売上 | M16: 飲料単価 | N16: テント利用料 | O16: 物販 | P16: 売上合計 | Q16: 合計単価 | R16: サーフィンズ | S16: forking | T16: Timee | U16: 合計 | V16: 人時売上高 | X16: 最低 | Y16: 最高 | Z16: 12時 | AA16: 15時 | AB16: 18時 | AC16: Ave | AE16: ■天候要因 | AG16: 評価点
A17: 日 | B17: 7 | G17: 日 | H17: =B17 -> 7 | J17: 0 | K17: =J17/I17 -> #DIV/0! | L17: 0 | M17: =L17/I17 -> #DIV/0! | P17: =J17+L17+N17 -> 0 | Q17: =P17/I17 -> #DIV/0! | V17: =P17/U17 -> #DIV/0! | AC17: =SUM(Z17:AB17)/3 -> 0 | AE17: 晴れ（33度まで） | AG17: 5
A18: 月 | B18: 8 | G18: 月 | H18: =B18 -> 8 | J18: 0 | K18: =J18/I18 -> #DIV/0! | L18: 0 | M18: =L18/I18 -> #DIV/0! | P18: =J18+L18+N18 -> 0 | Q18: =P18/I18 -> #DIV/0! | V18: =P18/U18 -> #DIV/0! | AC18: =SUM(Z18:AB18)/3 -> 0 | AE18: 晴れ（25度以下） | AG18: 4
A19: 火 | B19: 9 | G19: 火 | H19: =B19 -> 9 | J19: 0 | K19: =J19/I19 -> #DIV/0! | L19: 0 | M19: =L19/I19 -> #DIV/0! | P19: =J19+L19+N19 -> 0 | Q19: =P19/I19 -> #DIV/0! | V19: =P19/U19 -> #DIV/0! | AC19: =SUM(Z19:AB19)/3 -> 0 | AE19: 晴れ（33度以上）曇25度以上 | AG19: 3
A20: 水 | B20: 10 | G20: 水 | H20: =B20 -> 10 | J20: 0 | K20: =J20/I20 -> #DIV/0! | L20: 0 | M20: =L20/I20 -> #DIV/0! | P20: =J20+L20+N20 -> 0 | Q20: =P20/I20 -> #DIV/0! | V20: =P20/U20 -> #DIV/0! | AC20: =SUM(Z20:AB20)/3 -> 0 | AE20: 曇 | AG20: 2
A21: 木 | B21: 11 | G21: 木 | H21: =B21 -> 11 | J21: 0 | K21: =J21/I21 -> #DIV/0! | L21: 0 | M21: =L21/I21 -> #DIV/0! | P21: =J21+L21+N21 -> 0 | Q21: =P21/I21 -> #DIV/0! | V21: =P21/U21 -> #DIV/0! | AC21: =SUM(Z21:AB21)/3 -> 0 | AE21: 雨 | AG21: 1
A22: 金 | B22: 12 | G22: 金 | H22: =B22 -> 12 | J22: 0 | K22: =J22/I22 -> #DIV/0! | L22: 0 | M22: =L22/I22 -> #DIV/0! | P22: =J22+L22+N22 -> 0 | Q22: =P22/I22 -> #DIV/0! | V22: =P22/U22 -> #DIV/0! | AC22: =SUM(Z22:AB22)/3 -> 0 | AE22: 豪雨・雷雨 | AG22: 0
A23: 土 | B23: 13 | G23: 土 | H23: =B23 -> 13 | J23: 0 | K23: =J23/I23 -> #DIV/0! | L23: 0 | M23: =L23/I23 -> #DIV/0! | N23: 0 | P23: =J23+L23+N23 -> 0 | Q23: =P23/I23 -> #DIV/0! | V23: =P23/U23 -> #DIV/0! | AC23: =SUM(Z23:AB23)/3 -> 0 | AE23: ※5.6月は18時は最低気温を採用。7月〜は最高気温を採用。
A24: SUB TOTAL | C24: P/D | D24: =#REF!/F24 -> #REF! | E24: 日にち | F24: =#REF! -> #REF! | G24: SUB TOTAL | I24: =SUM(I17:I23) -> 0 | J24: =SUM(J17:J23) -> 0 | K24: =J24/I24 -> #DIV/0! | L24: =SUM(L17:L23) -> 0 | M24: =L24/I24 -> #DIV/0! | N24: =M24/J24 -> #DIV/0! | P24: =J24+L24 -> 0 | Q24: =P24/I24 -> #DIV/0! | V24: =P24/U24 -> #DIV/0! | X24: =SUM(X17:X23)/W24 -> #DIV/0! | Y24: =SUM(Y17:Y23)/W24 -> #DIV/0! | Z24: =SUM(Z17:Z23)/W24 -> #DIV/0! | AA24: =SUM(AA17:AA23)/W24 -> #DIV/0! | AB24: =SUM(AB17:AB23)/W24 -> #DIV/0! | AC24: =SUM(Z24:AB24)/3 -> #DIV/0!
A25: 3rd week | G25: 3rd week | X25: =G25 -> 3rd week
A26: 曜日 | B26: 日にち | C26: A | D26: B | E26: C | F26: S | G26: 曜日 | H26: 日にち | I26: 客数 | J26: 料理売上 | K26: 料理単価 | L26: 飲料売上 | M26: 飲料単価 | N26: テント利用料 | O26: 物販 | P26: 売上合計 | Q26: 合計単価 | R26: サーフィンズ | S26: forking | T26: Timee | U26: 合計 | V26: 人時売上高 | X26: 最低 | Y26: 最高 | Z26: 12時 | AA26: 15時 | AB26: 18時 | AC26: Ave | AE26: ■天候要因 | AG26: 評価点
A27: 日 | B27: 14 | G27: 日 | H27: =B27 -> 14 | J27: 0 | K27: =J27/I27 -> #DIV/0! | L27: 0 | M27: =L27/I27 -> #DIV/0! | P27: =J27+L27+N27 -> 0 | Q27: =P27/I27 -> #DIV/0! | V27: =P27/U27 -> #DIV/0! | AC27: =SUM(Z27:AB27)/3 -> 0 | AE27: 晴れ（33度まで） | AG27: 5
A28: 月 | B28: 15 | G28: 月 | H28: =B28 -> 15 | J28: 0 | K28: =J28/I28 -> #DIV/0! | L28: 0 | M28: =L28/I28 -> #DIV/0! | P28: =J28+L28+N28 -> 0 | Q28: =P28/I28 -> #DIV/0! | V28: =P28/U28 -> #DIV/0! | AC28: =SUM(Z28:AB28)/3 -> 0 | AE28: 晴れ（25度以下） | AG28: 4
A29: 火 | B29: 16 | G29: 火 | H29: =B29 -> 16 | J29: 0 | K29: =J29/I29 -> #DIV/0! | L29: 0 | M29: =L29/I29 -> #DIV/0! | P29: =J29+L29+N29 -> 0 | Q29: =P29/I29 -> #DIV/0! | V29: =P29/U29 -> #DIV/0! | AC29: =SUM(Z29:AB29)/3 -> 0 | AE29: 晴れ（33度以上）曇25度以上 | AG29: 3
A30: 水 | B30: 17 | G30: 水 | H30: =B30 -> 17 | J30: 0 | K30: =J30/I30 -> #DIV/0! | L30: 0 | M30: =L30/I30 -> #DIV/0! | P30: =J30+L30+N30 -> 0 | Q30: =P30/I30 -> #DIV/0! | V30: =P30/U30 -> #DIV/0! | AC30: =SUM(Z30:AB30)/3 -> 0 | AE30: 曇 | AG30: 2
A31: 木 | B31: 18 | G31: 木 | H31: =B31 -> 18 | J31: 0 | K31: =J31/I31 -> #DIV/0! | L31: 0 | M31: =L31/I31 -> #DIV/0! | P31: =J31+L31+N31 -> 0 | Q31: =P31/I31 -> #DIV/0! | V31: =P31/U31 -> #DIV/0! | AC31: =SUM(Z31:AB31)/3 -> 0 | AE31: 雨 | AG31: 1
A32: 金 | B32: 19 | G32: 金 | H32: =B32 -> 19 | J32: 0 | K32: =J32/I32 -> #DIV/0! | L32: 0 | M32: =L32/I32 -> #DIV/0! | P32: =J32+L32+N32 -> 0 | Q32: =P32/I32 -> #DIV/0! | V32: =P32/U32 -> #DIV/0! | AC32: =SUM(Z32:AB32)/3 -> 0 | AE32: 豪雨・雷雨 | AG32: 0
A33: 土 | B33: 20 | G33: 土 | H33: =B33 -> 20 | J33: 0 | K33: =J33/I33 -> #DIV/0! | L33: 0 | M33: =L33/I33 -> #DIV/0! | N33: 0 | P33: =J33+L33+N33 -> 0 | Q33: =P33/I33 -> #DIV/0! | V33: =P33/U33 -> #DIV/0! | AC33: =SUM(Z33:AB33)/3 -> 0 | AE33: ※5.6月は18時は最低気温を採用。7月〜は最高気温を採用。
A34: SUB TOTAL | C34: P/D | D34: =#REF!/F34 -> #REF! | E34: 日にち | F34: =#REF! -> #REF! | G34: SUB TOTAL | I34: =SUM(I27:I33) -> 0 | J34: =SUM(J27:J33) -> 0 | K34: =J34/I34 -> #DIV/0! | L34: =SUM(L27:L33) -> 0 | M34: =L34/I34 -> #DIV/0! | N34: =M34/J34 -> #DIV/0! | P34: =J34+L34 -> 0 | Q34: =P34/I34 -> #DIV/0! | V34: =P34/U34 -> #DIV/0! | X34: =SUM(X27:X33)/W34 -> #DIV/0! | Y34: =SUM(Y27:Y33)/W34 -> #DIV/0! | Z34: =SUM(Z27:Z33)/W34 -> #DIV/0! | AA34: =SUM(AA27:AA33)/W34 -> #DIV/0! | AB34: =SUM(AB27:AB33)/W34 -> #DIV/0! | AC34: =SUM(Z34:AB34)/3 -> #DIV/0!
A35: 4th week | G35: 4th week | X35: =G35 -> 4th week
A36: 曜日 | B36: 日にち | C36: A | D36: B | E36: C | F36: S | G36: 曜日 | H36: 日にち | I36: 客数 | J36: 料理売上 | K36: 料理単価 | L36: 飲料売上 | M36: 飲料単価 | N36: テント利用料 | O36: 物販 | P36: 売上合計 | Q36: 合計単価 | R36: サーフィンズ | S36: forking | T36: Timee | U36: 合計 | V36: 人時売上高 | X36: 最低 | Y36: 最高 | Z36: 12時 | AA36: 15時 | AB36: 18時 | AC36: Ave | AE36: ■天候要因 | AG36: 評価点
A37: 日 | B37: 21 | G37: 日 | H37: =B37 -> 21 | J37: 0 | K37: =J37/I37 -> #DIV/0! | L37: 0 | M37: =L37/I37 -> #DIV/0! | P37: =J37+L37+N37 -> 0 | Q37: =P37/I37 -> #DIV/0! | V37: =P37/U37 -> #DIV/0! | AC37: =SUM(Z37:AB37)/3 -> 0 | AE37: 晴れ（33度まで） | AG37: 5
A38: 月 | B38: 22 | G38: 月 | H38: =B38 -> 22 | J38: 0 | K38: =J38/I38 -> #DIV/0! | L38: 0 | M38: =L38/I38 -> #DIV/0! | P38: =J38+L38+N38 -> 0 | Q38: =P38/I38 -> #DIV/0! | V38: =P38/U38 -> #DIV/0! | AC38: =SUM(Z38:AB38)/3 -> 0 | AE38: 晴れ（25度以下） | AG38: 4
A39: 火 | B39: 23 | G39: 火 | H39: =B39 -> 23 | J39: 0 | K39: =J39/I39 -> #DIV/0! | L39: 0 | M39: =L39/I39 -> #DIV/0! | P39: =J39+L39+N39 -> 0 | Q39: =P39/I39 -> #DIV/0! | V39: =P39/U39 -> #DIV/0! | AC39: =SUM(Z39:AB39)/3 -> 0 | AE39: 晴れ（33度以上）曇25度以上 | AG39: 3
A40: 水 | B40: 24 | G40: 水 | H40: =B40 -> 24 | J40: 0 | K40: =J40/I40 -> #DIV/0! | L40: 0 | M40: =L40/I40 -> #DIV/0! | P40: =J40+L40+N40 -> 0 | Q40: =P40/I40 -> #DIV/0! | V40: =P40/U40 -> #DIV/0! | AC40: =SUM(Z40:AB40)/3 -> 0 | AE40: 曇 | AG40: 2
A41: 木 | B41: 25 | G41: 木 | H41: =B41 -> 25 | J41: 0 | K41: =J41/I41 -> #DIV/0! | L41: 0 | M41: =L41/I41 -> #DIV/0! | P41: =J41+L41+N41 -> 0 | Q41: =P41/I41 -> #DIV/0! | V41: =P41/U41 -> #DIV/0! | AC41: =SUM(Z41:AB41)/3 -> 0 | AE41: 雨 | AG41: 1
A42: 金 | B42: 26 | G42: 金 | H42: =B42 -> 26 | J42: 0 | K42: =J42/I42 -> #DIV/0! | L42: 0 | M42: =L42/I42 -> #DIV/0! | P42: =J42+L42+N42 -> 0 | Q42: =P42/I42 -> #DIV/0! | V42: =P42/U42 -> #DIV/0! | AC42: =SUM(Z42:AB42)/3 -> 0 | AE42: 豪雨・雷雨 | AG42: 0
A43: 土 | B43: 27 | G43: 土 | H43: =B43 -> 27 | I43: 247 | J43: 554550 | K43: =J43/I43 -> 2245.1417 | L43: 329450 | M43: =L43/I43 -> 1333.8057 | N43: 0 | P43: =J43+L43+N43 -> 884000 | Q43: =P43/I43 -> 3578.9474 | U43: 118.75 | V43: =P43/U43 -> 7444.2105 | X43: 15.4 | Y43: 25.8 | Z43: 5 | AA43: 5 | AB43: 4 | AC43: =SUM(Z43:AB43)/3 -> 4.6666667 | AE43: ※5.6月は18時は最低気温を採用。7月〜は最高気温を採用。
A44: SUB TOTAL | C44: P/D | D44: =#REF!/F44 -> #REF! | E44: 日にち | F44: =#REF! -> #REF! | G44: SUB TOTAL | I44: =SUM(I37:I43) -> 247 | J44: =SUM(J37:J43) -> 554550 | K44: =J44/I44 -> 2245.1417 | L44: =SUM(L37:L43) -> 329450 | M44: =L44/I44 -> 1333.8057 | N44: =M44/J44 -> 0.0024052036 | P44: =J44+L44 -> 884000 | Q44: =P44/I44 -> 3578.9474 | U44: =SUM(U37:U43) -> 118.75 | V44: =P44/U44 -> 7444.2105 | W44: 1 | X44: =SUM(X37:X43)/W44 -> 15.4 | Y44: =SUM(Y37:Y43)/W44 -> 25.8 | Z44: =SUM(Z37:Z43)/W44 -> 5 | AA44: =SUM(AA37:AA43)/W44 -> 5 | AB44: =SUM(AB37:AB43)/W44 -> 4 | AC44: =SUM(Z44:AB44)/3 -> 4.6666667 | AD44: ① | AE44: =P44/W44 -> 884000 | AJ44: ※1日平均売上
A45: 5th week | G45: 5th week | X45: =G45 -> 5th week
A46: 曜日 | B46: 日にち | C46: A | D46: B | E46: C | F46: S | G46: 曜日 | H46: 日にち | I46: 客数 | J46: 料理売上 | K46: 料理単価 | L46: 飲料売上 | M46: 飲料単価 | N46: テント利用料 | O46: 物販 | P46: 売上合計 | Q46: 合計単価 | R46: サーフィンズ | S46: forking | T46: Timee | U46: 合計 | V46: 人時売上高 | X46: 最低 | Y46: 最高 | Z46: 12時 | AA46: 15時 | AB46: 18時 | AC46: Ave | AE46: ■天候要因 | AG46: 評価点
A47: 日 | B47: 28 | G47: 日 | H47: =B47 -> 28 | I47: 130 | J47: 385200 | K47: =J47/I47 -> 2963.0769 | L47: 191000 | M47: =L47/I47 -> 1469.2308 | P47: =J47+L47+N47 -> 576200 | Q47: =P47/I47 -> 4432.3077 | U47: 100.5 | V47: =P47/U47 -> 5733.3333 | X47: 15.8 | Y47: 23 | Z47: 1 | AA47: 1 | AB47: 1 | AC47: =SUM(Z47:AB47)/3 -> 1 | AE47: 晴れ（33度まで） | AG47: 5
A48: 月 | B48: 29 | G48: 月 | H48: =B48 -> 29 | I48: 40 | J48: 132100 | K48: =J48/I48 -> 3302.5 | L48: 65700 | M48: =L48/I48 -> 1642.5 | P48: =J48+L48+N48 -> 197800 | Q48: =P48/I48 -> 4945 | U48: 70.5 | V48: =P48/U48 -> 2805.6738 | X48: 14 | Y48: 16.4 | Z48: 2 | AA48: 2 | AB48: 2 | AC48: =SUM(Z48:AB48)/3 -> 2 | AE48: 晴れ（25度以下） | AG48: 4
A49: 火 | B49: 30 | G49: 火 | H49: =B49 -> 30 | I49: 19 | J49: 47200 | K49: =J49/I49 -> 2484.2105 | L49: 27700 | M49: =L49/I49 -> 1457.8947 | P49: =J49+L49+N49 -> 74900 | Q49: =P49/I49 -> 3942.1053 | U49: 69.75 | V49: =P49/U49 -> 1073.8351 | X49: 10.2 | Y49: 15.1 | Z49: 2 | AA49: 1 | AB49: 1 | AC49: =SUM(Z49:AB49)/3 -> 1.3333333 | AE49: 晴れ（33度以上）曇25度以上 | AG49: 3
A50: 水 | B50: 31 | G50: 水 | H50: =B50 -> 31 | I50: 70 | J50: 154250 | K50: =J50/I50 -> 2203.5714 | L50: 87600 | M50: =L50/I50 -> 1251.4286 | P50: =J50+L50+N50 -> 241850 | Q50: =P50/I50 -> 3455 | U50: 73 | V50: =P50/U50 -> 3313.0137 | X50: 8 | Y50: 19.6 | Z50: 4 | AA50: 4 | AB50: 4 | AC50: =SUM(Z50:AB50)/3 -> 4 | AE50: 曇 | AG50: 2
A51: 木 | G51: 木 | H51: =B51 -> 0 | J51: 0 | K51: =J51/I51 -> #DIV/0! | L51: 0 | M51: =L51/I51 -> #DIV/0! | P51: =J51+L51+N51 -> 0 | Q51: =P51/I51 -> #DIV/0! | V51: =P51/U51 -> #DIV/0! | AC51: =SUM(Z51:AB51)/3 -> 0 | AE51: 雨 | AG51: 1
A52: 金 | G52: 金 | H52: =B52 -> 0 | J52: 0 | K52: =J52/I52 -> #DIV/0! | L52: 0 | M52: =L52/I52 -> #DIV/0! | P52: =J52+L52+N52 -> 0 | Q52: =P52/I52 -> #DIV/0! | V52: =P52/U52 -> #DIV/0! | AC52: =SUM(Z52:AB52)/3 -> 0 | AE52: 豪雨・雷雨 | AG52: 0
A53: 土 | G53: 土 | H53: =B53 -> 0 | J53: 0 | K53: =J53/I53 -> #DIV/0! | L53: 0 | M53: =L53/I53 -> #DIV/0! | N53: 0 | P53: =J53+L53+N53 -> 0 | Q53: =P53/I53 -> #DIV/0! | V53: =P53/U53 -> #DIV/0! | AC53: =SUM(Z53:AB53)/3 -> 0 | AE53: ※5.6月は18時は最低気温を採用。7月〜は最高気温を採用。
A54: SUB TOTAL | C54: P/D | D54: =#REF!/F54 -> #REF! | E54: 日にち | F54: =#REF! -> #REF! | G54: SUB TOTAL | I54: =SUM(I47:I53) -> 259 | J54: =SUM(J47:J53) -> 718750 | K54: =J54/I54 -> 2775.0965 | L54: =SUM(L47:L53) -> 372000 | M54: =L54/I54 -> 1436.2934 | N54: =M54/J54 -> 0.0019983213 | P54: =J54+L54 -> 1090750 | Q54: =P54/I54 -> 4211.39 | U54: =SUM(U47:U53) -> 313.75 | V54: =P54/U54 -> 3476.494 | W54: 4 | X54: =SUM(X47:X53)/W54 -> 12 | Y54: =SUM(Y47:Y53)/W54 -> 18.525 | Z54: =SUM(Z47:Z53)/W54 -> 2.25 | AA54: =SUM(AA47:AA53)/W54 -> 2 | AB54: =SUM(AB47:AB53)/W54 -> 2 | AC54: =SUM(Z54:AB54)/3 -> 2.0833333 | AD54: ② | AE54: =P54/W54 -> 272687.5 | AJ54: ※1日平均売上
A55: 6th week | G55: 6th week | X55: =G55 -> 6th week
A56: 曜日 | B56: 日にち | C56: A | D56: B | E56: C | F56: S | G56: 曜日 | H56: 日にち | I56: 客数 | J56: 料理売上 | K56: 料理単価 | L56: 飲料売上 | M56: 飲料単価 | N56: テント利用料 | O56: 物販 | P56: 売上合計 | Q56: 合計単価 | R56: サーフィンズ | S56: forking | T56: Timee | U56: 合計 | V56: 人時売上高 | X56: 最低 | Y56: 最高 | Z56: 12時 | AA56: 15時 | AB56: 18時 | AC56: Ave | AE56: ■天候要因 | AG56: 評価点
A57: 日 | G57: 日 | H57: =B57 -> 0 | J57: 0 | K57: =#REF! -> #REF! | L57: 0 | M57: =#REF! -> #REF! | P57: =J57+L57+N57 -> 0 | Q57: =P57/I57 -> #DIV/0! | V57: =P57/U57 -> #DIV/0! | AC57: =SUM(Z57:AB57)/3 -> 0 | AE57: 晴れ（33度まで） | AG57: 5
A58: 月 | G58: 月 | H58: =B58 -> 0 | J58: 0 | K58: =#REF! -> #REF! | L58: 0 | M58: =#REF! -> #REF! | P58: =J58+L58+N58 -> 0 | Q58: =P58/I58 -> #DIV/0! | V58: =P58/U58 -> #DIV/0! | AC58: =SUM(Z58:AB58)/3 -> 0 | AE58: 晴れ（25度以下） | AG58: 4
A59: 火 | G59: 火 | H59: =B59 -> 0 | J59: 0 | K59: =#REF! -> #REF! | L59: 0 | M59: =#REF! -> #REF! | P59: =J59+L59+N59 -> 0 | Q59: =P59/I59 -> #DIV/0! | V59: =P59/U59 -> #DIV/0! | AC59: =SUM(Z59:AB59)/3 -> 0 | AE59: 晴れ（33度以上）曇25度以上 | AG59: 3
A60: 水 | G60: 水 | H60: =B60 -> 0 | J60: 0 | K60: =#REF! -> #REF! | L60: 0 | M60: =#REF! -> #REF! | P60: =J60+L60+N60 -> 0 | Q60: =P60/I60 -> #DIV/0! | V60: =P60/U60 -> #DIV/0! | AC60: =SUM(Z60:AB60)/3 -> 0 | AE60: 曇 | AG60: 2
A61: 木 | G61: 木 | H61: =B61 -> 0 | J61: 0 | K61: =#REF! -> #REF! | L61: 0 | M61: =#REF! -> #REF! | P61: =J61+L61+N61 -> 0 | Q61: =P61/I61 -> #DIV/0! | V61: =P61/U61 -> #DIV/0! | AC61: =SUM(Z61:AB61)/3 -> 0 | AE61: 雨 | AG61: 1
A62: 金 | G62: 金 | H62: =B62 -> 0 | J62: 0 | K62: =#REF! -> #REF! | L62: 0 | M62: =#REF! -> #REF! | P62: =J62+L62+N62 -> 0 | Q62: =P62/I62 -> #DIV/0! | V62: =P62/U62 -> #DIV/0! | AC62: =SUM(Z62:AB62)/3 -> 0 | AE62: 豪雨・雷雨 | AG62: 0
A63: 土 | G63: 土 | H63: =B63 -> 0 | K63: =J63/I63 -> #DIV/0! | M63: =L63/I63 -> #DIV/0! | N63: 0 | P63: =J63+L63+N63 -> 0 | Q63: =P63/I63 -> #DIV/0! | V63: =P63/U63 -> #DIV/0! | AC63: =SUM(Z63:AB63)/3 -> 0 | AE63: ※5.6月は18時は最低気温を採用。7月〜は最高気温を採用。
A64: SUB TOTAL | C64: P/D | D64: =#REF!/F64 -> #REF! | E64: 日にち | F64: =#REF! -> #REF! | G64: SUB TOTAL | I64: =SUM(I57:I63) -> 0 | J64: =SUM(J57:J63) -> 0 | K64: =J64/I64 -> #DIV/0! | L64: =SUM(L57:L63) -> 0 | M64: =L64/I64 -> #DIV/0! | N64: =M64/J64 -> #DIV/0! | P64: =J64+L64 -> 0 | Q64: =P64/I64 -> #DIV/0! | U64: =SUM(U57:U63) -> 0 | V64: =P64/U64 -> #DIV/0! | X64: =SUM(X57:X63)/W64 -> #DIV/0! | Y64: =SUM(Y57:Y63)/W64 -> #DIV/0! | Z64: =SUM(Z57:Z63)/W64 -> #DIV/0! | AA64: =SUM(AA57:AA63)/W64 -> #DIV/0! | AB64: =SUM(AB57:AB63)/W64 -> #DIV/0! | AC64: =SUM(Z64:AB64)/3 -> #DIV/0! | AE64: =P64/W64 -> #DIV/0! | AJ64: ※1日平均売上
A65: TOTAL | G65: TOTAL | X65: =G65 -> TOTAL
A66: 曜日 | B66: 日数 | G66: 曜日 | H66: 日数 | I66: 客数 | J66: 料理売上 | K66: 料理単価 | L66: 飲料売上 | M66: 飲料単価 | N66: テント利用料 | O66: 物販 | P66: 売上合計 | Q66: 合計単価 | R66: サーフィンズ | S66: forking | T66: Timee | U66: 合計 | V66: 人時売上高 | X66: 最低 | Y66: 最高 | Z66: 12時 | AA66: 15時 | AB66: 18時 | AC66: Ave
A67: 日 | G67: 日 | I67: =I7+I17+I27+I37+I47+I57 -> 130 | J67: =J7+J17+J27+J37+J47+J57 -> 385200 | K67: =J67/I67 -> 2963.0769 | L67: =L7+L17+L27+L37+L47+L57 -> 191000 | M67: =L67/I67 -> 1469.2308 | P67: =P7+P17+P27+P37+P47+P57 -> 576200 | Q67: =Q7+Q17+Q27+Q37+Q47+Q57 -> #DIV/0! | U67: =U7+U17+U27+U37+U47+U57 -> 100.5 | V67: =P67/U67 -> 5733.3333 | X67: =X7+X17+X27+X37+X47+X57 -> 15.8 | Y67: =Y7+Y17+Y27+Y37+Y47+Y57 -> 23 | Z67: =Z7+Z17+Z37+Z47+Z27+Z57 -> 1 | AA67: =AA7+AA17+AA37+AA47+AA27+AA57 -> 1 | AB67: =AB7+AB17+AB37+AB47+AB27+AB57 -> 1 | AC67: =SUM(Z67:AB67)/3 -> 1
A68: 月 | G68: 月 | I68: =I8+I18+I28+I38+I48+I58 -> 40 | J68: =J8+J18+J28+J38+J48+J58 -> 132100 | K68: =J68/I68 -> 3302.5 | L68: =L8+L18+L28+L38+L48+L58 -> 65700 | M68: =L68/I68 -> 1642.5 | P68: =P8+P18+P28+P38+P48+P58 -> 197800 | Q68: =Q8+Q18+Q28+Q38+Q48+Q58 -> #DIV/0! | U68: =U8+U18+U28+U38+U48+U58 -> 70.5 | V68: =P68/U68 -> 2805.6738 | X68: =X8+X18+X28+X38+X48+X58 -> 14 | Y68: =Y8+Y18+Y28+Y38+Y48+Y58 -> 16.4 | Z68: =Z8+Z18+Z38+Z48+Z28+Z58 -> 2 | AA68: =AA8+AA18+AA38+AA48+AA28+AA58 -> 2 | AB68: =AB8+AB18+AB38+AB48+AB28+AB58 -> 2 | AC68: =SUM(Z68:AB68)/3 -> 2
A69: 火 | G69: 火 | I69: =I9+I19+I29+I39+I49+I59 -> 19 | J69: =J9+J19+J29+J39+J49+J59 -> 47200 | K69: =J69/I69 -> 2484.2105 | L69: =L9+L19+L29+L39+L49+L59 -> 27700 | M69: =L69/I69 -> 1457.8947 | P69: =P9+P19+P29+P39+P49+P59 -> 74900 | Q69: =Q9+Q19+Q29+Q39+Q49+Q59 -> #DIV/0! | U69: =U9+U19+U29+U39+U49+U59 -> 69.75 | V69: =P69/U69 -> 1073.8351 | X69: =X9+X19+X29+X39+X49+X59 -> 10.2 | Y69: =Y9+Y19+Y29+Y39+Y49+Y59 -> 15.1 | Z69: =Z9+Z19+Z39+Z49+Z29+Z59 -> 2 | AA69: =AA9+AA19+AA39+AA49+AA29+AA59 -> 1 | AB69: =AB9+AB19+AB39+AB49+AB29+AB59 -> 1 | AC69: =SUM(Z69:AB69)/3 -> 1.3333333
A70: 水 | G70: 水 | I70: =I10+I20+I30+I40+I50+I60 -> 70 | J70: =J10+J20+J30+J40+J50+J60 -> 154250 | K70: =J70/I70 -> 2203.5714 | L70: =L10+L20+L30+L40+L50+L60 -> 87600 | M70: =L70/I70 -> 1251.4286 | P70: =P10+P20+P30+P40+P50+P60 -> 241850 | Q70: =Q10+Q20+Q30+Q40+Q50+Q60 -> #DIV/0! | U70: =U10+U20+U30+U40+U50+U60 -> 73 | V70: =P70/U70 -> 3313.0137 | X70: =X10+X20+X30+X40+X50+X60 -> 8 | Y70: =Y10+Y20+Y30+Y40+Y50+Y60 -> 19.6 | Z70: =Z10+Z20+Z40+Z50+Z30+Z60 -> 4 | AA70: =AA10+AA20+AA40+AA50+AA30+AA60 -> 4 | AB70: =AB10+AB20+AB40+AB50+AB30+AB60 -> 4 | AC70: =SUM(Z70:AB70)/3 -> 4
A71: 木 | G71: 木 | I71: =I21+I11+I31+I41+I51+I61 -> 0 | J71: =J21+J11+J31+J41+J51+J61 -> 0 | K71: =J71/I71 -> #DIV/0! | L71: =L21+L11+L31+L41+L51+L61 -> 0 | M71: =L71/I71 -> #DIV/0! | P71: =P21+P11+P31+P41+P51+P61 -> 0 | Q71: =Q21+Q11+Q31+Q41+Q51+Q61 -> #DIV/0! | U71: =U21+U11+U31+U41+U51+U61 -> 0 | V71: =P71/U71 -> #DIV/0! | X71: =X11+X21+X31+X41+X51+X61 -> 0 | Y71: =Y11+Y21+Y31+Y41+Y51+Y61 -> 0 | Z71: =Z11+Z21+Z41+Z51+Z31+Z61 -> 0 | AA71: =AA11+AA21+AA41+AA51+AA31+AA61 -> 0 | AB71: =AB11+AB21+AB41+AB51+AB31+AB61 -> 0 | AC71: =SUM(Z71:AB71)/3 -> 0
A72: 金 | G72: 金 | I72: =I12+I22+I32+I42+I52+I62 -> 0 | J72: =J12+J22+J32+J42+J52+J62 -> 0 | K72: =J72/I72 -> #DIV/0! | L72: =L12+L22+L32+L42+L52+L62 -> 0 | M72: =L72/I72 -> #DIV/0! | P72: =P12+P22+P32+P42+P52+P62 -> 0 | Q72: =Q12+Q22+Q32+Q42+Q52+Q62 -> #DIV/0! | U72: =U12+U22+U32+U42+U52+U62 -> 0 | V72: =P72/U72 -> #DIV/0! | X72: =X12+X22+X32+X42+X52+X62 -> 0 | Y72: =Y12+Y22+Y32+Y42+Y52+Y62 -> 0 | Z72: =Z12+Z22+Z42+Z52+Z32+Z62 -> 0 | AA72: =AA12+AA22+AA42+AA52+AA32+AA62 -> 0 | AB72: =AB12+AB22+AB42+AB52+AB32+AB62 -> 0 | AC72: =SUM(Z72:AB72)/3 -> 0
A73: 土 | G73: 土 | I73: =I13+I23+I33+I43+I53+I63 -> 247 | J73: =J13+J23+J33+J43+J53+J63 -> 554550 | K73: =J73/I73 -> 2245.1417 | L73: =L13+L23+L33+L43+L53+L63 -> 329450 | M73: =L73/I73 -> 1333.8057 | P73: =P13+P23+P33+P43+P53+P63 -> 884000 | Q73: =Q13+Q23+Q33+Q43+Q53+Q63 -> #DIV/0! | U73: =U13+U23+U33+U43+U53+U63 -> 118.75 | V73: =P73/U73 -> 7444.2105 | W73: =W14+W24+W34+W44+W54+W64 -> 5 | X73: =X13+X23+X33+X43+X53+X63 -> 15.4 | Y73: =Y13+Y23+Y33+Y43+Y53+Y63 -> 25.8 | Z73: =Z13+Z23+Z43+Z53+Z33+Z63 -> 5 | AA73: =AA13+AA23+AA43+AA53+AA33+AA63 -> 5 | AB73: =AB13+AB23+AB43+AB53+AB33+AB63 -> 4 | AC73: =SUM(Z73:AB73)/3 -> 4.6666667
A74: TOTAL | B74: =SUM(B67:B73) -> 0 | C74: P/D | D74: =#REF!/F74 -> #REF! | E74: 日にち | F74: =#REF! -> #REF! | G74: TOTAL | H74: =SUM(H67:H73) -> 0 | I74: =SUM(I67:I73) -> 506 | J74: =SUM(J67:J73) -> 1273300 | K74: =J74/I74 -> 2516.4032 | L74: =SUM(L67:L73) -> 701450 | M74: =L74/I74 -> 1386.2648 | P74: =SUM(P67:P73) -> 1974750 | Q74: =P74/I74 -> 3902.668 | U74: =SUM(U67:U73) -> 432.5 | V74: =P74/U74 -> 4565.896 | X74: =SUM(X67:X73)/W73 -> 12.68 | Y74: =SUM(Y67:Y73)/W73 -> 19.98 | Z74: =SUM(Z67:Z73)/W73 -> 2.8 | AA74: =SUM(AA67:AA73)/W73 -> 2.6 | AB74: =SUM(AB67:AB73)/W73 -> 2.4 | AC74: =SUM(Z74:AB74)/3 -> 2.6
A75: ■対比 | G75: ■対比
A77: ランチ | G77: ランチ | I77: 予算
I78: ランチ
I79: 客数 | L79: F売上 | P79: B売上
L80: =#REF!*I80 -> #REF! | P80: =#REF!*I80 -> #REF!
I82: ■予算差異
I83: 客数 | L83: F売上 | P83: B売上
I84: =I74-I80 -> 506 | L84: =L74-L80 -> #REF! | P84: =P74-P80 -> #REF!
I85: =I74/I80 -> #DIV/0! | L85: =L74/L80 -> #REF! | P85: =P74/P80 -> #REF!
I86: ■前年値（数値残っていない休業）
I87: 客数 | L87: F売上 | P87: B売上
I89: ■前年差異
I90: 客数 | L90: F売上 | P90: B売上
I91: =I74-I88 -> 506 | L91: =L74-L88 -> 701450 | P91: =P74-P88 -> 1974750
I92: =I74/I88 -> #DIV/0! | L92: =L74/L88 -> #DIV/0! | P92: =P74/P88 -> #DIV/0!
A93: 構成比率 | N93: 税抜売上 | P93: =P74/1.1 -> 1795227.3 | Q93: 対予測達成率 | U93: =P93/#REF! -> #REF! | V93: =P93-#REF! -> #REF!
L95: 売上総合計（レストラン+テイク）
A98: ■モデルシフト
A99: モデルシフト カテゴリー
A100: TOP1
A101: TOP2
A102: ON1
A103: ON2
A104: ショルダー
A105: OFF1
A106: OFF2

Sheet 5月時間帯別売上実績
A1: ■5月 時間帯別売上実績&曜日別売上実績
A2: 営業日 | B2: ランチ | E2: アイドル | G2: ディナー | L2: 合計
B3: 12時 | C3: 13時 | D3: 14時 | E3: 15時 | F3: 16時 | G3: 17時 | H3: 18時 | I3: 19時 | J3: 20時 | K3: 21時
A4: 2023/05/01(月)
A5: 2023/05/02(火)
A6: 2023/05/03(水)
A7: 2023/05/04(木)
A8: 2023/05/05(金)
A9: 2023/05/06(土)
A10: 2023/05/07(日)
A11: 2023/05/08(月)
A12: 2023/05/09(火)
A13: 2023/05/10(水)
A14: 2023/05/11(木)
A15: 2023/05/12(金)
... A29: 2023/05/26(金)
A30: 2023/05/27(土) | B30: 65600 | C30: 78450 | D30: 87000 | E30: 105350 | F30: 56850 | G30: 158500 | H30: 158250 | I30: 130350 | J30: 43650 | K30: 0 | L30: 884000
A31: 2023/05/28(日) | B31: 102550 | C31: 84050 | D31: 104400 | E31: 70350 | F31: 35700 | G31: 66400 | H31: 99850 | I31: 7400 | J31: 5500 | K31: 0 | L31: 576200
A32: 2023/05/29(月) | B32: 29100 | C32: 36350 | D32: 0 | E32: 0 | F32: 6850 | G32: 48800 | H32: 38500 | I32: 5200 | J32: 33000 | K32: 0 | L32: 197800
A33: 2023/05/30(火) | B33: 31400 | C33: 3400 | D33: 0 | E33: 5700 | F33: 12400 | G33: 11000 | H33: 11000 | I33: 0 | J33: 0 | K33: 0 | L33: 74900
A34: 2023/05/31(水) | B34: 78050 | C34: 20500 | D34: 2450 | E34: 21300 | F34: 17250 | G34: 45300 | H34: 11750 | I34: 16400 | J34: 28850 | L34: 241850
A35: 【合計】 | B35: 306700 | C35: 222750 | D35: 193850 | E35: 202700 | F35: 129050 | G35: 330000 | H35: 319350 | I35: 159350 | J35: 111000 | K35: =SUM(K4:K34) -> 0 | L35: 1974750
B36: =B35+C35+D35 -> 723300 | E36: =E35+F35 -> 331750 | G36: =G35+H35+I35+J35+K35 -> 919700 | L36: =SUM(B36:J36) -> 1974750
A37: 売上比率 | B37: =B36/L36 -> 0.36627421 | E37: =E36/L36 -> 0.16799595 | G37: =G36/L36 -> 0.46572984 | L37: =SUM(B37:J37) -> 1
B38: =B37+E37 -> 0.53427016
A39: ■5月 曜日別売上平均
A40: 【日曜日 平均】 | B40: 102550 | C40: 84050 | D40: 104400 | E40: 70350 | F40: 35700 | G40: 66400 | H40: 99850 | I40: 7400 | J40: 5500 | K40: 0 | L40: 576200
A41: 【月曜日 平均】 | B41: 29100 | C41: 36350 | D41: 0 | E41: 0 | F41: 6850 | G41: 48800 | H41: 38500 | I41: 5200 | J41: 33000 | K41: 0 | L41: 197800
A42: 【火曜日 平均】 | B42: 31400 | C42: 3400 | D42: 0 | E42: 5700 | F42: 12400 | G42: 11000 | H42: 11000 | I42: 0 | J42: 0 | K42: 0 | L42: 74900
A43: 【水曜日 平均】 | B43: 78050 | C43: 20500 | D43: 2450 | E43: 21300 | F43: 17250 | G43: 45300 | H43: 11750 | I43: 16400 | J43: 28850 | L43: 241850
A44: 【木曜日 平均】 | B44: 0 | C44: 0 | D44: 0 | E44: 0 | F44: 0 | G44: 0 | H44: 0 | I44: 0 | J44: 0 | K44: 0 | L44: 0
A45: 【金曜日 平均】 | B45: 0 | C45: 0 | D45: 0 | E45: 0 | F45: 0 | G45: 0 | H45: 0 | I45: 0 | J45: 0 | K45: 0 | L45: 0
A46: 【土曜日 平均】 | B46: 65600 | C46: 78450 | D46: 87000 | E46: 105350 | F46: 56850 | G46: 158500 | H46: 158250 | I46: 130350 | J46: 43650 | K46: 0 | L46: 884000
A47: ■5月 曜日別売上合計
A48: 【日曜日 合計】 | B48: 102550 | C48: 84050 | D48: 104400 | E48: 70350 | F48: 35700 | G48: 66400 | H48: 99850 | I48: 7400 | J48: 5500 | K48: 0 | L48: 576200
A49: 【月曜日 合計】 | B49: 29100 | C49: 36350 | D49: 0 | E49: 0 | F49: 6850 | G49: 48800 | H49: 38500 | I49: 5200 | J49: 33000 | K49: 0 | L49: 197800
A50: 【火曜日 合計】 | B50: 31400 | C50: 3400 | D50: 0 | E50: 5700 | F50: 12400 | G50: 11000 | H50: 11000 | I50: 0 | J50: 0 | K50: 0 | L50: 74900
A51: 【水曜日 合計】 | B51: 78050 | C51: 20500 | D51: 2450 | E51: 21300 | F51: 17250 | G51: 45300 | H51: 11750 | I51: 16400 | J51: 28850 | K51: 0 | L51: 241850
A52: 【木曜日 合計】 | B52: 0 | C52: 0 | D52: 0 | E52: 0 | F52: 0 | G52: 0 | H52: 0 | I52: 0 | J52: 0 | K52: 0 | L52: 0
A53: 【金曜日 合計】 | B53: 0 | C53: 0 | D53: 0 | E53: 0 | F53: 0 | G53: 0 | H53: 0 | I53: 0 | J53: 0 | K53: 0 | L53: 0
A54: 【土曜日 合計】 | B54: 65600 | C54: 78450 | D54: 87000 | E54: 105350 | F54: 56850 | G54: 158500 | H54: 158250 | I54: 130350 | J54: 43650 | K54: 0 | L54: 884000
