Workbook

Sheet 2024レビュー
A1: 【R6 さっぽろテレビ塔ビアガーデン（ピコレワインガーデン）振り返り】
A2: ①売上 | I2: 単位：円 | J2: 平均気温 | L2: ①コメント
A3: 月 | B3: 実績 | C3: 予算 | D3: 予算比 | E3: 差異 | F3: 予測 | G3: 予測比 | H3: 差異 | I3: 1日平均売上 | J3: LOW | K3: HIGH | V3: BG営業天候指数 | Y3: 2024 | Z3: 平均気温 | AB3: 2023 | AC3: 平均気温 | AE3: 差異 | AF3: 平均気温
A4: 4 | B4: 499227 | C4: 260000 | D4: =B4/C4 -> 1.9201038 | E4: =B4-C4 -> 239227 | F4: 260000 | G4: =B4/F4 -> 1.9201038 | H4: =B4-F4 -> 239227 | I4: =B4/T4 -> 124806.75 | T4: 4 | U4: 月 | V4: 2024 | W4: 2023 | Y4: 月 | Z4: LOW | AA4: HIGH | AB4: 月 | AC4: LOW | AD4: HIGH | AE4: 月 | AF4: LOW | AG4: HIGH | AJ4: 2024 | AK4: 期 間 | AL4: 日 数 | AM4: 売 上 | AN4: 客 数 | AO4: 客単価 | AP4: 2023 | AQ4: 期 間 | AR4: 日 数 | AS4: 売 上 | AT4: 客 数 | AU4: 客単価 | AV4: 売 上 前 年 比 | AX4: 客 数 前 年 比 | AZ4: 客 単 価 前 年 比
A5: 5 | B5: 2919145 | C5: 1851200 | D5: =B5/C5 -> 1.5768934 | E5: =B5-C5 -> 1067945 | F5: 1851200 | G5: =B5/F5 -> 1.5768934 | H5: =B5-F5 -> 1067945 | I5: =B5/T5 -> 121631.04 | J5: 11.6℃ | K5: 17.0℃ | T5: 24 | U5: 4 | V5: 1.33 | W5: 2.1 | X5: =V5/W5 -> 0.63333333 | Y5: 4 | AB5: 4 | AE5: 4 | AF5: =Z5-AC5 -> 0 | AG5: =AA5-AD5 -> 0 | AJ5: 4~5 | AK5: PC 4/27-5/19 | AL5: 23 | AM5: 2939522 | AN5: 2348 | AO5: =AM5/AN5 -> 1251.9259 | AP5: 4~5 | AQ5: PC営業なし | AR5: 0 | AS5: 0 | AT5: 0 | AU5: =AS5/AT5 -> #DIV/0! | AV5: =AM5-AS5 -> 2939522 | AW5: =AM5/AS5 -> #DIV/0! | AX5: =AN5-AT5 -> 2348 | AY5: =AN5/AT5 -> #DIV/0! | AZ5: =AO5-AU5 -> #DIV/0! | BA5: =AO5/AU5 -> #DIV/0!
A6: 6 | B6: 19194436 | C6: 25690000 | D6: =B6/C6 -> 0.74715594 | E6: =B6-C6 -> -6495564 | F6: 22000000 | G6: =B6/F6 -> 0.87247436 | H6: =B6-F6 -> -2805564 | I6: =B6/T6 -> 639814.53 | J6: 15.6℃ | K6: 23.9℃ | T6: 30 | U6: 5 | V6: 2.78 | W6: 3.37 | X6: =V6/W6 -> 0.82492582 | Y6: 5 | Z6: 11.6 | AA6: 17 | AB6: 5 | AC6: 12.7 | AD6: 20 | AE6: 5 | AF6: =Z6-AC6 -> -1.1 | AG6: =AA6-AD6 -> -3 | AJ6: 5 | AK6: BG 5/27-5/31 | AL6: 5 | AM6: 477807 | AN6: 133 | AO6: =AM6/AN6 -> 3592.5338 | AP6: 5 | AQ6: BG 5/27-5/31 | AR6: 5 | AS6: 1795227.3 | AT6: 506 | AU6: =AS6/AT6 -> 3547.88 | AV6: =AM6-AS6 -> -1317420.3 | AW6: =AM6/AS6 -> 0.26615404 | AX6: =AN6-AT6 -> -373 | AY6: =AN6/AT6 -> 0.26284585 | AZ6: =AO6-AU6 -> 44.653849 | BA6: =AO6/AU6 -> 1.0125861
A7: 7 | B7: 47613345 | C7: 51610000 | D7: =B7/C7 -> 0.92256045 | E7: =B7-C7 -> -3996655 | F7: 50000000 | G7: =B7/F7 -> 0.9522669 | H7: =B7-F7 -> -2386655 | I7: =B7/T7 -> 1535914.4 | J7: 20.5℃ | K7: 28.0℃ | T7: 31 | U7: 6 | V7: 3.19 | W7: 3.49 | X7: =V7/W7 -> 0.91404011 | Y7: 6 | Z7: 15.6 | AA7: 23.9 | AB7: 6 | AC7: 15.6 | AD7: 24.1 | AE7: 6 | AF7: =Z7-AC7 -> 0 | AG7: =AA7-AD7 -> -0.2 | AJ7: 6 | AK7: BG フル営業 | AL7: 30 | AM7: 19170665 | AN7: 5174 | AO7: =AM7/AN7 -> 3705.1923 | AP7: 6 | AQ7: BG フル営業 | AR7: 30 | AS7: 19049727 | AT7: 5309 | AU7: =AS7/AT7 -> 3588.195 | AV7: =AM7-AS7 -> 120937.73 | AW7: =AM7/AS7 -> 1.0063485 | AX7: =AN7-AT7 -> -135 | AY7: =AN7/AT7 -> 0.97457148 | AZ7: =AO7-AU7 -> 116.9973 | BA7: =AO7/AU7 -> 1.0326062
A8: 8 | B8: 55874978 | C8: 49500000 | D8: =B8/C8 -> 1.1287874 | E8: =B8-C8 -> 6374978 | F8: 50000000 | G8: =B8/F8 -> 1.1174996 | H8: =B8-F8 -> 5874978 | I8: =B8/T8 -> 1802418.6 | J8: 22.0℃ | K8: 28.4℃ | T8: 31 | U8: 7 | V8: 3.04 | W8: 3.39 | X8: =V8/W8 -> 0.89675516 | Y8: 7 | Z8: 20.5 | AA8: 28 | AB8: 7 | AC8: 21 | AD8: 27.8 | AE8: 7 | AF8: =Z8-AC8 -> -0.5 | AG8: =AA8-AD8 -> 0.2 | AJ8: 7 | AK8: BG フル営業 | AL8: 31 | AM8: 47598067 | AN8: 11438 | AO8: =AM8/AN8 -> 4161.3977 | AP8: 7 | AQ8: BG フル営業 | AR8: 31 | AS8: 44856909 | AT8: 11036 | AU8: =AS8/AT8 -> 4064.5985 | AV8: =AM8-AS8 -> 2741157.9 | AW8: =AM8/AS8 -> 1.0611089 | AX8: =AN8-AT8 -> 402 | AY8: =AN8/AT8 -> 1.0364262 | AZ8: =AO8-AU8 -> 96.799205 | BA8: =AO8/AU8 -> 1.0238152
A9: 9 | B9: 12350827 | C9: 7000000 | D9: =B9/C9 -> 1.7644039 | E9: =B9-C9 -> 5350827 | F9: 8000000 | G9: =B9/F9 -> 1.5438534 | H9: =B9-F9 -> 4350827 | I9: =B9/T9 -> 494033.08 | J9: 15.6℃ | K9: 24.0℃ | T9: 25 | U9: 8 | V9: 3.55 | W9: 3.44 | X9: =V9/W9 -> 1.0319767 | Y9: 8 | Z9: 22 | AA9: 28.4 | AB9: 8 | AC9: 24 | AD9: 30.9 | AE9: 8 | AF9: =Z9-AC9 -> -2 | AG9: =AA9-AD9 -> -2.5 | AJ9: 8 | AK9: BG フル営業 | AL9: 31 | AM9: 55870570 | AN9: 13891 | AO9: =AM9/AN9 -> 4022.0697 | AP9: 8 | AQ9: BG フル営業 | AR9: 31 | AS9: 44860591 | AT9: 11093 | AU9: =AS9/AT9 -> 4044.045 | AV9: =AM9-AS9 -> 11009979 | AW9: =AM9/AS9 -> 1.2454265 | AX9: =AN9-AT9 -> 2798 | AY9: =AN9/AT9 -> 1.2522311 | AZ9: =AO9-AU9 -> -21.97529 | BA9: =AO9/AU9 -> 0.99456601
A10: 10 | B10: 1454318 | C10: 455000 | D10: =B10/C10 -> 3.1963033 | E10: =B10-C10 -> 999318 | F10: 692727 | G10: =B10/F10 -> 2.09941 | H10: =B10-F10 -> 761591 | I10: =B10/T10 -> 242386.33 | J10: 13.7℃ | K10: 20.7℃ | T10: 6 | U10: 9 | V10: 2.72 | W10: - | X10: =V10/W10 -> #VALUE! | Y10: 9 | Z10: 15.6 | AA10: 24 | AB10: 9 | AC10: 21.4 | AD10: 28.6 | AE10: 9 | AF10: =Z10-AC10 -> -5.8 | AG10: =AA10-AD10 -> -4.6 | AJ10: 9 | AK10: BG 9/1-9/8 | AL10: 8 | AM10: 8816632 | AN10: 2410 | AO10: =AM10/AN10 -> 3658.3535 | AP10: 9 | AQ10: BG 9/1-9/3 | AR10: 8 | AS10: 4058727.3 | AT10: =263+385+76 -> 724 | AU10: =AS10/AT10 -> 5605.9769 | AV10: =AM10-AS10 -> 4757904.7 | AW10: =AM10/AS10 -> 2.1722652 | AX10: =AN10-AT10 -> 1686 | AY10: =AN10/AT10 -> 3.3287293 | AZ10: =AO10-AU10 -> -1947.6234 | BA10: =AO10/AU10 -> 0.65258091
A11: TOTAL | B11: =SUM(B4:B10) -> 139906276 | C11: =SUM(C4:C10) -> 136366200 | D11: =B11/C11 -> 1.0259601 | E11: =B11-C11 -> 3540076 | F11: =SUM(F4:F10) -> 132803927 | G11: =B11/F11 -> 1.05348 | H11: =B11-F11 -> 7102349 | I11: =B11/T11 -> 926531.63 | T11: =SUM(T4:T10) -> 151 | U11: 10 | V11: =SUM(V5:V10)/6 -> 2.7683333 | W11: =SUM(W5:W10)/5 -> 3.158 | X11: =V11/W11 -> 0.87660967 | Y11: 10 | Z11: 13.7 | AA11: 20.7 | AB11: 10 | AE11: 10 | AF11: =Z11-AC11 -> 13.7 | AG11: =AA11-AD11 -> 20.7 | AJ11: 9~10 | AK11: PC-BG 秋営業 9/14-10/6 | AL11: 23 | AM11: 4982837 | AN11: 1704 | AO11: =AM11/AN11 -> 2924.2001 | AP11: 9~10 | AQ11: PC 9/9-10/1 | AR11: 23 | AS11: 1489815.5 | AT11: 1365 | AU11: =AS11/AT11 -> 1091.4399 | AV11: =AM11-AS11 -> 3493021.5 | AW11: =AM11/AS11 -> 3.3446002 | AX11: =AN11-AT11 -> 339 | AY11: =AN11/AT11 -> 1.2483516 | AZ11: =AO11-AU11 -> 1832.7602 | BA11: =AO11/AU11 -> 2.6792132
AJ12: ビアガのみ105日 | AL12: =AL7+AL6+AL8+AL9+AL10 -> 105 | AM12: =AM7+AM6+AM8+AM9+AM10 -> 131933741 | AN12: =AN7+AN6+AN8+AN9+AN10 -> 33046 | AO12: =AM12/AN12 -> 3992.427 | AP12: ビアガのみ105日 | AR12: =AR7+AR6+AR8+AR9+AR10 -> 105 | AS12: =AS7+AS6+AS8+AS9+AS10 -> 1.1462118e+08 | AT12: =AT7+AT6+AT8+AT9+AT10 -> 28668 | AU12: =AS12/AT12 -> 3998.2274 | AV12: =AM12-AS12 -> 17312559 | AW12: =AM12/AS12 -> 1.1510415 | AX12: =AN12-AT12 -> 4378 | AY12: =AN12/AT12 -> 1.1527138 | AZ12: =AO12-AU12 -> -5.8004049 | BA12: =AO12/AU12 -> 0.99854926
A13: ②客数 | I13: 単位：名 | L13: ②コメント | V13: =V11-W11 -> -0.38966667 | AJ13: ピコレ&ピコレ共催 | AL13: =AL5+AL11 -> 46 | AM13: =AM5+AM11 -> 7922359 | AN13: =AN5+AN11 -> 4052 | AO13: =AM13/AN13 -> 1955.1725 | AP13: ピコレ&ピコレ共催 | AR13: =AR5+AR11 -> 23 | AS13: =AS5+AS11 -> 1489815.5 | AT13: =AT5+AT11 -> 1365 | AU13: =AS13/AT13 -> 1091.4399 | AV13: =AM13-AS13 -> 6432543.5 | AW13: =AM13/AS13 -> 5.3176781 | AX13: =AN13-AT13 -> 2687 | AY13: =AN13/AT13 -> 2.9684982 | AZ13: =AO13-AU13 -> 863.73261 | BA13: =AO13/AU13 -> 1.7913698
A14: 月 | B14: 実績 | C14: 予算 | D14: 予算比 | E14: 差異 | F14: 予測 | G14: 予測比 | H14: 差異 | I14: 1日平均 | V14: 2369 | AJ14: 総合計 | AL14: =SUM(AL5:AL11) -> 151 | AM14: =SUM(AM5:AM11) -> 139856100 | AN14: =SUM(AN5:AN11) -> 37098 | AO14: =AM14/AN14 -> 3769.9094 | AP14: 総合計 | AR14: =SUM(AR5:AR11) -> 128 | AS14: =SUM(AS5:AS11) -> 1.16111e+08 | AT14: =SUM(AT5:AT11) -> 30033 | AU14: =AS14/AT14 -> 3866.1139 | AV14: =AM14-AS14 -> 23745103 | AW14: =AM14/AS14 -> 1.2045035 | AX14: =AN14-AT14 -> 7065 | AY14: =AN14/AT14 -> 1.2352412 | AZ14: =AO14-AU14 -> -96.204421 | BA14: =AO14/AU14 -> 0.97511599
A15: 4 | B15: 379 | C15: 200 | D15: =B15/C15 -> 1.895 | E15: =B15-C15 -> 179 | F15: 395 | G15: =B15/F15 -> 0.95949367 | H15: =B15-F15 -> -16 | I15: =B15/T15 -> 75.8 | T15: 5
A16: 5 | B16: =133+1236+223+278+120 -> 1990 | C16: 520 | D16: =B16/C16 -> 3.8269231 | E16: =B16-C16 -> 1470 | F16: 372 | G16: =B16/F16 -> 5.3494624 | H16: =B16-F16 -> 1618 | I16: =B16/T16 -> #DIV/0! | V16: 133
A17: 6 | B17: 5174 | C17: 7000 | D17: =B17/C17 -> 0.73914286 | E17: =B17-C17 -> -1826 | F17: 5558 | G17: =B17/F17 -> 0.9309104 | H17: =B17-F17 -> -384 | I17: =B17/T17 -> 172.46667 | T17: 30 | V17: =V14-V16 -> 2236
A18: 7 | B18: 11438 | C18: 13000 | D18: =B18/C18 -> 0.87984615 | E18: =B18-C18 -> -1562 | F18: 12016 | G18: =B18/F18 -> 0.95189747 | H18: =B18-F18 -> -578 | I18: =B18/T18 -> 368.96774 | T18: 31
A19: 8 | B19: 13891 | C19: 12500 | D19: =B19/C19 -> 1.11128 | E19: =B19-C19 -> 1391 | F19: 12386 | G19: =B19/F19 -> 1.1215082 | H19: =B19-F19 -> 1505 | I19: =B19/T19 -> 448.09677 | T19: 31
A20: 9 | B20: 3458 | C20: 2000 | D20: =B20/C20 -> 1.729 | E20: =B20-C20 -> 1458 | F20: 1976 | G20: =B20/F20 -> 1.75 | H20: =B20-F20 -> 1482 | I20: =B20/T20 -> #DIV/0!
A21: 10 | B21: 538 | C21: 350 | D21: =B21/C21 -> 1.5371429 | E21: =B21-C21 -> 188 | F21: 194 | G21: =B21/F21 -> 2.7731959 | H21: =B21-F21 -> 344 | I21: =B21/T21 -> 179.33333 | T21: 3
A22: TOTAL | B22: =SUM(B15:B21) -> 36868 | C22: =SUM(C15:C21) -> 35570 | D22: =B22/C22 -> 1.0364914 | E22: =B22-C22 -> 1298 | F22: =SUM(F15:F21) -> 32897 | G22: =B22/F22 -> 1.1207101 | H22: =B22-F22 -> 3971 | I22: =B22/T22 -> 368.68 | T22: 100
A24: ③-1 客単価 | I24: 単位：円 | L24: ③コメント
A25: 月 | B25: 実績 | C25: 予算 | D25: 予算比 | E25: 差異 | F25: 予測 | G25: 予測比 | H25: 差異
A26: 4 | B26: =B4/B15 -> 1317.2216 | C26: 1300 | D26: =B26/C26 -> 1.0132474 | E26: =B26-C26 -> 17.221636 | F26: =F4/F15 -> 658.22785 | G26: =B26/F26 -> 2.0011636 | H26: =B26-F26 -> 658.99379
A27: 5 | B27: =B5/B16 -> 1466.907 | C27: 3500 | D27: =B27/C27 -> 0.4191163 | E27: =B27-C27 -> -2033.093 | F27: =F5/F16 -> 4976.3441 | G27: =B27/F27 -> 0.29477605 | H27: =B27-F27 -> -3509.4371
A28: 6 | B28: =B6/B17 -> 3709.7866 | C28: 3600 | D28: =B28/C28 -> 1.0304963 | E28: =B28-C28 -> 109.78663 | F28: =F6/F17 -> 3958.2584 | G28: =B28/F28 -> 0.937227 | H28: =B28-F28 -> -248.47174
A29: 7 | B29: =B7/B18 -> 4162.7334 | C29: 3900 | D29: =B29/C29 -> 1.0673675 | E29: =B29-C29 -> 262.73343 | F29: =F7/F18 -> 4161.1185 | G29: =B29/F29 -> 1.0003881 | H29: =B29-F29 -> 1.6149238
A30: 8 | B30: =B8/B19 -> 4022.387 | C30: 3900 | D30: =B30/C30 -> 1.0313813 | E30: =B30-C30 -> 122.38701 | F30: =F8/F19 -> 4036.8158 | G30: =B30/F30 -> 0.99642571 | H30: =B30-F30 -> -14.428747
A31: 9 | B31: =B9/B20 -> 3571.6677 | C31: 3500 | D31: =B31/C31 -> 1.0204765 | E31: =B31-C31 -> 71.667727 | F31: =F9/F20 -> 4048.583 | G31: =B31/F31 -> 0.88220193 | H31: =B31-F31 -> -476.91527
A32: 10 | B32: =B10/B21 -> 2703.1933 | C32: 1300 | D32: =B32/C32 -> 2.0793795 | E32: =B32-C32 -> 1403.1933 | F32: =F10/F21 -> 3570.7577 | G32: =B32/F32 -> 0.75703632 | H32: =B32-F32 -> -867.56442
A33: TOTAL | B33: =B11/B22 -> 3794.7889 | C33: =C11/C22 -> 3833.7419 | D33: =B33/C33 -> 0.98983942 | E33: =B33-C33 -> -38.953049 | F33: =F11/F22 -> 4036.9616 | G33: =B33/F33 -> 0.94001113 | H33: =B33-F33 -> -242.17277
A35: ③-2 プラン出卓数と月別プラン利用率
A36: 月 | B36: 客数 | C36: 5,500プラン | D36: 利用率 | E36: 6,600プラン | F36: 利用率 | G36: 8,800プラン | H36: 利用率 | I36: 小計
A37: 4 | B37: 379 | C37: 0 | D37: =C37/B37 -> 0 | E37: 0 | F37: =E37/B37 -> 0 | G37: 0 | H37: =G37/B37 -> 0 | I37: =C37+E37+G37 -> 0
A38: 5 | B38: =133+1236+223+278+120 -> 1990 | C38: 59 | D38: =C38/B38 -> 0.029648241 | E38: 0 | F38: =E38/B38 -> 0 | G38: 4 | H38: =G38/B38 -> 0.0020100503 | I38: =C38+E38+G38 -> 63
A39: 6 | B39: 5174 | C39: 2281 | D39: =C39/B39 -> 0.44085814 | E39: 58 | F39: =E39/B39 -> 0.011209896 | G39: 17 | H39: =G39/B39 -> 0.0032856591 | I39: =C39+E39+G39 -> 2356
A40: 7 | B40: 11438 | C40: 5791 | D40: =C40/B40 -> 0.50629481 | E40: 226 | F40: =E40/B40 -> 0.019758699 | G40: 167 | H40: =G40/B40 -> 0.014600455 | I40: =C40+E40+G40 -> 6184
A41: 8 | B41: 13891 | C41: 6305 | D41: =C41/B41 -> 0.45389101 | E41: 397 | F41: =E41/B41 -> 0.028579656 | G41: 140 | H41: =G41/B41 -> 0.010078468 | I41: =C41+E41+G41 -> 6842
A42: 9 | B42: 3458 | C42: 863 | D42: =C42/B42 -> 0.24956622 | E42: 37 | F42: =E42/B42 -> 0.010699826 | G42: 2 | H42: =G42/B42 -> 0.000578369 | I42: =C42+E42+G42 -> 902
A43: 10 | B43: 538 | C43: 150 | D43: =C43/B43 -> 0.27881041 | E43: 0 | F43: =E43/B43 -> 0 | G43: 0 | H43: =G43/B43 -> 0 | I43: =C43+E43+G43 -> 150
A44: TOTAL | B44: =SUM(B37:B43) -> 36868 | C44: =SUM(C37:C43) -> 15449 | D44: =C44/B44 -> 0.41903548 | E44: =SUM(E37:E43) -> 718 | F44: =E44/B44 -> 0.019474883 | G44: =SUM(G37:G43) -> 330 | H44: =G44/B44 -> 0.0089508517 | I44: =C44+E44+G44 -> 16497
A45: 月 | B45: 客数 | C45: チケットプラン | D45: 利用率 | E45: プラン合計 | F45: 利用率 | G45: アラカルト利用 | H45: 利用率
A46: 4 | B46: 379 | C46: 0 | D46: =C46/B46 -> 0 | E46: =C46+I37 -> 0 | F46: =E46/B46 -> 0 | G46: =B46-E46 -> 379 | H46: =G46/B46 -> 1 | L46: ④memo
A47: 5 | B47: =133+1236+223+278+120 -> 1990 | C47: 0 | D47: =C47/B47 -> 0 | E47: =C47+I38 -> 63 | F47: =E47/B47 -> 0.031658291 | G47: =B47-E47 -> 1927 | H47: =G47/B47 -> 0.96834171
A48: 6 | B48: 5174 | C48: 182 | D48: =C48/B48 -> 0.035175879 | E48: =C48+I39 -> 2538 | F48: =E48/B48 -> 0.49052957 | G48: =B48-E48 -> 2636 | H48: =G48/B48 -> 0.50947043
A49: 7 | B49: 11438 | C49: 757 | D49: =C49/B49 -> 0.066182899 | E49: =C49+I40 -> 6941 | F49: =E49/B49 -> 0.60683686 | G49: =B49-E49 -> 4497 | H49: =G49/B49 -> 0.39316314
A50: 8 | B50: 13891 | C50: 1287 | D50: =C50/B50 -> 0.092649917 | E50: =C50+I41 -> 8129 | F50: =E50/B50 -> 0.58519905 | G50: =B50-E50 -> 5762 | H50: =G50/B50 -> 0.41480095
A51: 9 | B51: 3458 | C51: 405 | D51: =C51/B51 -> 0.11711972 | E51: =C51+I42 -> 1307 | F51: =E51/B51 -> 0.37796414 | G51: =B51-E51 -> 2151 | H51: =G51/B51 -> 0.62203586
A52: 10 | B52: 538 | C52: 50 | D52: =C52/B52 -> 0.092936803 | E52: =C52+I43 -> 200 | F52: =E52/B52 -> 0.37174721 | G52: =B52-E52 -> 338 | H52: =G52/B52 -> 0.62825279
A53: TOTAL | B53: =SUM(B46:B52) -> 36868 | C53: =SUM(C46:C52) -> 2681 | D53: =C53/B53 -> 0.072718889 | E53: =SUM(E46:E52) -> 19178 | F53: =E53/B53 -> 0.5201801 | G53: =SUM(G46:G52) -> 17690 | H53: =G53/B53 -> 0.4798199
A55: ③-3 Web予約受注率
A56: 月 | B56: 人数 | C56: TC | D56: TC利用率 | E56: 電話 | F56: 電話利用率 | G56: パッサージュ | H56: 利用率 | I56: 予約利用率
A57: 4 | B57: 379 | C57: 0 | D57: =C57/B57 -> 0 | E57: 0 | F57: =E57/B57 -> 0 | G57: =B57-C57-E57 -> 379 | H57: =G57/B57 -> 1 | I57: =C57/(C57+E57) -> #DIV/0!
A58: 5 | B58: =133+1236+223+278+120 -> 1990 | C58: 25 | D58: =C58/B58 -> 0.012562814 | E58: 16 | F58: =E58/B58 -> 0.008040201 | G58: =B58-C58-E58 -> 1949 | H58: =G58/B58 -> 0.97939698 | I58: =C58/(C58+E58) -> 0.6097561
A59: 6 | B59: 5174 | C59: 1281 | D59: =C59/B59 -> 0.24758407 | E59: 507 | F59: =E59/B59 -> 0.09798995 | G59: =B59-C59-E59 -> 3386 | H59: =G59/B59 -> 0.65442598 | I59: =C59/(C59+E59) -> 0.71644295
A60: 7 | B60: 11438 | C60: 3566 | D60: =C60/B60 -> 0.31176779 | E60: 2029 | F60: =E60/B60 -> 0.17739115 | G60: =B60-C60-E60 -> 5843 | H60: =G60/B60 -> 0.51084106 | I60: =C60/(C60+E60) -> 0.63735478
A61: 8 | B61: 13891 | C61: 4639 | D61: =C61/B61 -> 0.33395724 | E61: 2010 | F61: =E61/B61 -> 0.14469801 | G61: =B61-C61-E61 -> 7242 | H61: =G61/B61 -> 0.52134476 | I61: =C61/(C61+E61) -> 0.6976989
A62: 9 | B62: 3458 | C62: 910 | D62: =C62/B62 -> 0.26315789 | E62: 343 | F62: =E62/B62 -> 0.099190283 | G62: =B62-C62-E62 -> 2205 | H62: =G62/B62 -> 0.63765182 | I62: =C62/(C62+E62) -> 0.72625698
A63: 10 | B63: 538 | C63: 72 | D63: =C63/B63 -> 0.133829 | E63: 65 | F63: =E63/B63 -> 0.12081784 | G63: =B63-C63-E63 -> 401 | H63: =G63/B63 -> 0.74535316 | I63: =C63/(C63+E63) -> 0.52554745
A64: TOTAL | B64: =SUM(B57:B63) -> 36868 | C64: =SUM(C57:C63) -> 10493 | D64: =C64/B64 -> 0.28460996 | E64: =SUM(E57:E63) -> 4970 | F64: =E64/B64 -> 0.13480525 | G64: =SUM(G57:G63) -> 21405 | H64: =G64/B64 -> 0.58058479 | I64: =C64/(C64+E64) -> 0.6785876
A67: 2024 | B67: 期間 | C67: 売上 | D67: 値引き | E67: 税抜売上 | F67: 税込売上 | G67: 値引き | H67: 税込売上合計
A68: 4~5 | B68: ピコレ4/27-5/19 | C68: 2939522 | D68: 4040 | E68: =C68-D68 -> 2935482 | F68: 3232260 | G68: 4040 | H68: =F68-G68 -> 3228220 | I68: 23 | J68: =1969+379 -> 2348 | L68: =H68/J68 -> 1374.8807
A69: 5 | B69: ビアガ5/27-5/31 | C69: 477807 | D69: 3480 | E69: =C69-D69 -> 474327 | F69: 525570 | G69: 3480 | H69: =F69-G69 -> 522090 | I69: 5 | J69: 133 | L69: =H69/J69 -> 3925.4887 | S69: 115000000 | T69: =S69*0.13 -> 14950000 | V69: 13
A70: 6 | B70: ビアガフル | C70: 19170665 | D70: 26790 | E70: =C70-D70 -> 19143875 | F70: 21087090 | G70: 26790 | H70: =F70-G70 -> 21060300 | I70: 30 | J70: 5174 | L70: =H70/J70 -> 4070.4097 | S70: 139757096 | T70: =S70*0.13 -> 18168422 | V70: 13
A71: 7 | B71: ビアガフル | C71: 47598067 | D71: 17800 | E71: =C71-D71 -> 47580267 | F71: 52356880 | G71: 17800 | H71: =F71-G71 -> 52339080 | I71: 31 | J71: 11438 | L71: =H71/J71 -> 4575.8944 | S71: 91500000 | T71: =S71*0.13 -> 11895000 | V71: 13
A72: 8 | B72: ビアガフル | C72: 55870570 | D72: 5980 | E72: =C72-D72 -> 55864590 | F72: 61456496 | G72: 5980 | H72: =F72-G72 -> 61450516 | I72: 31 | J72: 13891 | L72: =H72/J72 -> 4423.7647 | S72: 139757096 | T72: =S72*0.105 -> 14674495 | V72: 11
A73: 9 | B73: ビアガ9/1-9/8 | C73: 8816632 | D73: 5700 | E73: =C73-D73 -> 8810932 | F73: 9698100 | G73: 5700 | H73: =F73-G73 -> 9692400 | I73: 8 | J73: 2410 | L73: =H73/J73 -> 4021.7427 | S73: =S72-S71 -> 48257096 | T73: =T72-T71 -> 2779495.1
A74: 9~10 | B74: ピコレ共催アキノジン | C74: 4982837 | D74: 1100 | E74: =C74-D74 -> 4981737 | F74: 5480760 | G74: 1100 | H74: =F74-G74 -> 5479660 | I74: 23 | J74: =1196+508 -> 1704 | L74: =H74/J74 -> 3215.7629 | S74: 150000000 | T74: =S74*0.11 -> 16500000 | V74: 11
B75: ビアガのみ105日 | C75: =C70+C69+C71+C72+C73 -> 131933741 | D75: =D70+D69+D71+D72+D73 -> 59750 | E75: =E70+E69+E71+E72+E73 -> 131873991 | F75: =F70+F69+F71+F72+F73 -> 145124136 | G75: =G70+G69+G71+G72+G73 -> 59750 | H75: =H70+H69+H71+H72+H73 -> 145064386 | I75: =I70+I69+I71+I72+I73 -> 105
A76: チケット未食売り上げ | C76: 953750 | E76: 953750 | F76: =E76*1.1 -> 1049125 | H76: =F76-G76 -> 1049125 | I76: 23 | J76: =1196+508 -> 1704 | L76: =H76/J76 -> 615.68369
B77: ピコレ&ピコレ共催 | C77: =C68+C74 -> 7922359 | D77: =D68+D74 -> 5140 | E77: =E68+E74 -> 7917219 | F77: =F68+F74 -> 8713020 | G77: =G68+G74 -> 5140 | H77: =H68+H74 -> 8707880 | I77: =I68+I74 -> 46
B78: 総合計 | C78: =SUM(C68:C74)+C76 -> 140809850 | D78: =SUM(D68:D74) -> 64890 | E78: =SUM(E68:E74)+E76 -> 140744960 | F78: =SUM(F68:F74) -> 153837156 | G78: =SUM(G68:G74) -> 64890 | H78: =SUM(H68:H74)+H76 -> 154821391 | I78: =SUM(I68:I74) -> 151 | J78: =SUM(J68:J77) -> 38802 | L78: =H78/J78 -> 3990.0364
A80: 2023 | B80: 期間 | C80: 売上 | D80: 値引き | E80: 税抜売上 | F80: 税込売上 | G80: 値引き | H80: 税込売上合計
A81: 4~5 | B81: ピコレ参戦なし | E81: =C81-D81 -> 0 | H81: =F81-G81 -> 0 | I81: 0 | L81: =H81/J81 -> #DIV/0!
A82: 5 | B82: ビアガ5/27-5/31 | C82: =F82/1.1 -> 1795227.3 | E82: =C82-D82 -> 1795227.3 | F82: 1974750 | H82: =F82-G82 -> 1974750 | I82: 5 | J82: 506 | L82: =H82/J82 -> 3902.668
A83: 6 | B83: ビアガフル | C83: =F83/1.1 -> 19049727 | E83: =C83-D83 -> 19049727 | F83: 20954700 | H83: =F83-G83 -> 20954700 | I83: 30 | J83: 5309 | L83: =H83/J83 -> 3947.0145
A84: 7 | B84: ビアガフル | C84: =F84/1.1 -> 44856909 | E84: =C84-D84 -> 44856909 | F84: 49342600 | H84: =F84-G84 -> 49342600 | I84: 31 | J84: 11036 | L84: =H84/J84 -> 4471.0584
A85: 8 | B85: ビアガフル | C85: =F85/1.1 -> 44860591 | E85: =C85-D85 -> 44860591 | F85: 49346650 | H85: =F85-G85 -> 49346650 | I85: 31 | J85: 11093 | L85: =H85/J85 -> 4448.4495
A86: 9 | B86: ビアガ9/1-9/3 | C86: =F86/1.1 -> 4058727.3 | E86: =C86-D86 -> 4058727.3 | F86: 4464600 | H86: =F86-G86 -> 4464600 | I86: 3 | J86: =263+385+76 -> 724 | L86: =H86/J86 -> 6166.5746
A87: 9~10 | B87: ピコレ | C87: =F87/1.1 -> 1489815.5 | E87: =C87-D87 -> 1489815.5 | F87: 1638797 | H87: =F87-G87 -> 1638797 | I87: 23 | J87: 1365 | L87: =H87/J87 -> 1200.5839
B88: ビアガのみ105日 | C88: =C83+C82+C84+C85+C86 -> 1.1462118e+08 | D88: =D83+D82+D84+D85+D86 -> 0 | E88: =E83+E82+E84+E85+E86 -> 1.1462118e+08 | F88: =F83+F82+F84+F85+F86 -> 126083300 | G88: =G83+G82+G84+G85+G86 -> 0 | H88: =H83+H82+H84+H85+H86 -> 126083300 | I88: =I83+I82+I84+I85+I86 -> 100
B89: ピコレ&ピコレ共催 | C89: =C81+C87 -> 1489815.5 | D89: =D81+D87 -> 0 | E89: =E81+E87 -> 1489815.5 | F89: =F81+F87 -> 1638797 | G89: =G81+G87 -> 0 | H89: =H81+H87 -> 1638797 | I89: =I81+I87 -> 23
B90: 総合計 | C90: =SUM(C81:C87) -> 1.16111e+08 | D90: =SUM(D81:D87) -> 0 | E90: =SUM(E81:E87) -> 1.16111e+08 | F90: =SUM(F81:F87) -> 127722097 | G90: =SUM(G81:G87) -> 0 | H90: =SUM(H81:H87) -> 127722097 | I90: =SUM(I81:I87) -> 123 | J90: =SUM(J81:J89) -> 30033 | L90: =H90/J90 -> 4252.7252
E92: =E75/E90 -> 1.135758
E93: =E75-E90 -> 15762994

Sheet 2023レビュー
A1: 【R5 さっぽろテレビ塔ビアガーデン振り返り】
A2: ①売上 | I2: 単位：円 | J2: 平均気温 | L2: ①コメント
A3: 月 | B3: 実績 | C3: 予算 | D3: 予算比 | E3: 差異 | F3: 予測 | G3: 予測比 | H3: 差異 | I3: 1日平均売上 | J3: LOW | K3: HIGH | L3: 売上については左記の通り、対予算123.9％にて終了いたしました。コロナ禍前の2019年と比較しても対比125.4％（+22,223千円）の結果となりました。これまで1億円の大台に達したことはなかったということです。その大きな要因としてはスタッフの頑張りはもちろんですが、やはり史上稀に見る猛暑となったことが挙げられます。特に6月と8月は気象庁の観測史上最高値を記録し、7月においても史上2番目の平均気温となりました。ただ、天候要因については影響値として一定の条件下で記録していかなければならないもので、いかにこの天候要因を限定的にできるか？というのが引き続きの課題となります。※各月に天候要因を数値化したものを載せています。次年度へ向け今年度のデータを活かし、テーブル配置・スタッフアサインメント・予約システム再構築・RPA/DX 促進・メニューラインナップの見直し等により、さらにポテンシャルを引き出し売上を積み上げられると認識しています。
A4: 5 | B4: 1795227.3 | C4: 6890000 | D4: =B4/C4 -> 0.26055548 | E4: =B4-C4 -> -5094772.7 | F4: 1963000 | G4: =B4/F4 -> 0.91453249 | H4: =B4-F4 -> -167772.73 | I4: =B4/T4 -> 359045.45 | T4: 5
A5: 6 | B5: 19049727 | C5: 25440000 | D5: =B5/C5 -> 0.74881003 | E5: =B5-C5 -> -6390272.7 | F5: 17338000 | G5: =B5/F5 -> 1.0987269 | H5: =B5-F5 -> 1711727.3 | I5: =B5/T5 -> 634990.91 | J5: 12.7℃ | K5: 20.0℃ | T5: 30
A6: 7 | B6: 44856909 | C6: 25440000 | D6: =B6/C6 -> 1.7632433 | E6: =B6-C6 -> 19416909 | F6: 35016000 | G6: =B6/F6 -> 1.2810404 | H6: =B6-F6 -> 9840909.1 | I6: =B6/T6 -> 1446997.1 | J6: 15.6℃ | K6: 24.1℃ | T6: 31
A7: 8 | B7: 44863045 | C7: 25440000 | D7: =B7/C7 -> 1.7634845 | E7: =B7-C7 -> 19423045 | F7: 39760000 | G7: =B7/F7 -> 1.1283462 | H7: =B7-F7 -> 5103045.5 | I7: =B7/T7 -> 1447195 | J7: 21.0℃ | K7: 27.8℃ | T7: 31
A8: 9 | B8: 4058727.3 | C8: 9275000 | D8: =B8/C8 -> 0.43759863 | E8: =B8-C8 -> -5216272.7 | F8: 4300000 | G8: =B8/F8 -> 0.94389006 | H8: =B8-F8 -> -241272.73 | I8: =B8/T8 -> 1352909.1 | J8: 24.0℃ | K8: 30.9℃ | T8: 3
A9: TOTAL | B9: =SUM(B4:B8) -> 1.1462364e+08 | C9: =SUM(C4:C8) -> 92485000 | D9: =B9/C9 -> 1.2393754 | E9: =B9-C9 -> 22138636 | F9: =SUM(F4:F8) -> 98377000 | G9: =B9/F9 -> 1.1651467 | H9: =B9-F9 -> 16246636 | I9: =B9/T9 -> 1146236.4 | J9: 21.4℃ | K9: 28.6℃ | T9: 100
A11: ②客数 | I11: 単位：名 | L11: ②コメント
A12: 月 | B12: 実績 | C12: 予算 | D12: 予算比 | E12: 差異 | F12: 予測 | G12: 予測比 | H12: 差異 | I12: 1日平均 | L12: 入客実績は左記の通りです。7/21（金）から8/16（土）の間で開催された大通りビアガーデン期間中も1日平均405名の入客となり、客数減少懸念は杞憂となりました。過去開催の数値によると盆明けは下降線を辿るはずでしたが、①にもある通り観測史上最高の平均気温となったことやチケットの駆け込み利用もあり、勢いを保ったまま最終日まで賑わいが続きました。シーズン設定をして6月末までは20:30クローズ、7月1日〜は21:30クローズとしたことは大きな成果に繋がったと考えています。7/22（土）が717名の来場とピーク、また、この週（7月第4週・通期では第9週）が最大の売上・入客となりました。次年度は予約システムをさらに活用し、入客を引き上げたいと考えています。
A13: 5 | B13: 506 | C13: 1300 | D13: =B13/C13 -> 0.38923077 | E13: =B13-C13 -> -794 | F13: 395 | G13: =B13/F13 -> 1.2810127 | H13: =B13-F13 -> 111 | I13: =B13/T13 -> 101.2 | T13: 5
A14: 6 | B14: 5309 | C14: 4800 | D14: =B14/C14 -> 1.1060417 | E14: =B14-C14 -> 509 | F14: 3450 | G14: =B14/F14 -> 1.5388406 | H14: =B14-F14 -> 1859 | I14: =B14/T14 -> 176.96667 | T14: 30
A15: 7 | B15: 11036 | C15: 4800 | D15: =B15/C15 -> 2.2991667 | E15: =B15-C15 -> 6236 | F15: 7050 | G15: =B15/F15 -> 1.5653901 | H15: =B15-F15 -> 3986 | I15: =B15/T15 -> 356 | T15: 31
A16: 8 | B16: 11093 | C16: 4800 | D16: =B16/C16 -> 2.3110417 | E16: =B16-C16 -> 6293 | F16: 8100 | G16: =B16/F16 -> 1.3695062 | H16: =B16-F16 -> 2993 | I16: =B16/T16 -> 357.83871 | T16: 31
A17: 9 | B17: 974 | C17: 1750 | D17: =B17/C17 -> 0.55657143 | E17: =B17-C17 -> -776 | F17: 880 | G17: =B17/F17 -> 1.1068182 | H17: =B17-F17 -> 94 | I17: =B17/T17 -> 324.66667 | T17: 3
A18: TOTAL | B18: =SUM(B13:B17) -> 28918 | C18: =SUM(C13:C17) -> 17450 | D18: =B18/C18 -> 1.657192 | E18: =B18-C18 -> 11468 | F18: =SUM(F13:F17) -> 19875 | G18: =B18/F18 -> 1.4549937 | H18: =B18-F18 -> 9043 | I18: =B18/T18 -> 289.18 | T18: 100
A20: ③-1 客単価 | I20: 単位：円 | L20: ③コメント
A21: 月 | B21: 実績 | C21: 予算 | D21: 予算比 | E21: 差異 | F21: 予測 | G21: 予測比 | H21: 差異 | L21: 通期での客単価は3,964円にて着地いたしました。予算設定時点では80%がプラン利用を想定しての数値でしたので、予算値からはマイナスとなっています。最終的にプラン利用率は53.6%となり、アラカルト（単品）利用率を上回りました。左記データから読み取れるのは、とてもシンプルですが、パッサージュ（フリー入客）利用率が高いと客単価が下がるという事実と、予約数を高めることにより客単価が伸びるという事実です。このことから、次年度は今回25％程であった予約利用率を35％程度まで引き上げることで、いわゆる「値上げ」の必要がなく、客単価と入客の天秤関係を限定的にしながら、【入客を高めつつ客単価も引き上げることができる】という伸び代を確認することができました。また今回はテーブルチェックを導入し、専用LPと紐付けして予約受注を行ったことにより、約83%の方がWebから予約をしてくださいました。これまでの開催は全て電話予約で対応し紙台帳管理をしていたという課題を、予約システム導入によって解決できた大きな成果と認められます。現地オペレーションとの連携を高めていけば、まだまだこうしたシステムを活かすことができます。今年度実績を基にし、人員発注と人員配置、予約システムの強みをさらに引き出しての予約受注強化（相性が良いと見られるLINE/L-STEPの活用など）や、天候要件の影響値を最小化（※悪天候時でも当日キャンセルは2割に満たない）していくことで、次年度は客席拡大、スタッフ増員に強気で臨むことができます。設備を含めて改善しつつ、さらに客単価を10％程度引き上げることで、売上も今年度の1日平均114万円から130万円（合計1億3,000万円）までは伸ばすことができると確信しています。
A22: 5 | B22: =B4/B13 -> 3547.88 | C22: 5300 | D22: =B22/C22 -> 0.66941132 | E22: =B22-C22 -> -1752.12 | F22: 4970 | G22: =B22/F22 -> 0.71385915 | H22: =B22-F22 -> -1422.12
A23: 6 | B23: =B5/B14 -> 3588.195 | C23: 5300 | D23: =B23/C23 -> 0.67701793 | E23: =B23-C23 -> -1711.805 | F23: 5026 | G23: =B23/F23 -> 0.71392658 | H23: =B23-F23 -> -1437.805
A24: 7 | B24: =B6/B15 -> 4064.5985 | C24: 5300 | D24: =B24/C24 -> 0.76690538 | E24: =B24-C24 -> -1235.4015 | F24: 4967 | G24: =B24/F24 -> 0.81832062 | H24: =B24-F24 -> -902.4015
A25: 8 | B25: =B7/B16 -> 4044.2662 | C25: 5300 | D25: =B25/C25 -> 0.7630691 | E25: =B25-C25 -> -1255.7338 | F25: 4909 | G25: =B25/F25 -> 0.82384727 | H25: =B25-F25 -> -864.73376
A26: 9 | B26: =B8/B17 -> 4167.0711 | C26: 5300 | D26: =B26/C26 -> 0.78623983 | E26: =B26-C26 -> -1132.9289 | F26: 4886 | G26: =B26/F26 -> 0.85285942 | H26: =B26-F26 -> -718.92888
A27: TOTAL | B27: =B9/B18 -> 3963.747 | C27: =C9/C18 -> 5300 | D27: =B27/C27 -> 0.7478768 | E27: =B27-C27 -> -1336.253 | F27: =F9/F18 -> 4949.7862 | G27: =B27/F27 -> 0.80079157 | H27: =B27-F27 -> -986.03914
A29: ③-2 プラン出卓数と月別プラン利用率
A30: 月 | B30: 客数 | C30: 5,500プラン | D30: 利用率 | E30: 6,600プラン | F30: 利用率 | G30: 8,800プラン | H30: 利用率 | I30: 小計
A31: 5 | B31: 506 | C31: 205 | D31: =C31/B31 -> 0.40513834 | E31: 7 | F31: =E31/B31 -> 0.013833992 | G31: 2 | H31: =G31/B31 -> 0.0039525692 | I31: =C31+E31+G31 -> 214
A32: 6 | B32: 5309 | C32: 2074 | D32: =C32/B32 -> 0.39065737 | E32: 80 | F32: =E32/B32 -> 0.015068751 | G32: 9 | H32: =G32/B32 -> 0.0016952345 | I32: =C32+E32+G32 -> 2163
A33: 7 | B33: 11036 | C33: 5792 | D33: =C33/B33 -> 0.52482784 | E33: 190 | F33: =E33/B33 -> 0.017216383 | G33: 161 | H33: =G33/B33 -> 0.014588619 | I33: =C33+E33+G33 -> 6143
A34: 8 | B34: 11093 | C34: 5149 | D34: =C34/B34 -> 0.46416659 | E34: 271 | F34: =E34/B34 -> 0.024429821 | G34: 77 | H34: =G34/B34 -> 0.0069413143 | I34: =C34+E34+G34 -> 5497
A35: 9 | B35: 974 | C35: 314 | D35: =C35/B35 -> 0.32238193 | E35: 34 | F35: =E35/B35 -> 0.034907598 | G35: 9 | H35: =G35/B35 -> 0.0092402464 | I35: =C35+E35+G35 -> 357
A36: TOTAL | B36: =SUM(B31:B35) -> 28918 | C36: =SUM(C31:C35) -> 13534 | D36: =C36/B36 -> 0.468013 | E36: =SUM(E31:E35) -> 582 | F36: =E36/B36 -> 0.020125873 | G36: =SUM(G31:G35) -> 258 | H36: =G36/B36 -> 0.0089217788 | I36: =C36+E36+G36 -> 14374
A37: 月 | B37: 客数 | C37: チケットプラン | D37: 利用率 | E37: プラン合計 | F37: 利用率 | G37: アラカルト利用 | H37: 利用率
A38: 5 | B38: 506 | C38: 0 | D38: =C38/B38 -> 0 | E38: =C38+I31 -> 214 | F38: =E38/B38 -> 0.4229249 | G38: =B38-E38 -> 292 | H38: =G38/B38 -> 0.5770751 | L38: ④memo
A39: 6 | B39: 5309 | C39: 0 | D39: =C39/B39 -> 0 | E39: =C39+I32 -> 2163 | F39: =E39/B39 -> 0.40742136 | G39: =B39-E39 -> 3146 | H39: =G39/B39 -> 0.59257864 | L39: 設備・備品課題※情報共有前 ◆英字メニュー ◆テーブル番号札（視認性・会計） ◆会計カード（プラスチック札）の作成 ◆会計の仕方がわからない ◆キャッシュレス決済が行えることの告知 ◆エクスキューズ（場内案内・トイレ・会計方法など） ◆飲み放題と単品オーダーの判別がつきづらい ◆床清掃の定期スケジュールと不定期実施のオペレーション ◆ワインの利用方法と場所 ◆ワインコーナーにローズマリーのプランター設置 ◆イベント開催 ◆キャッシャー増設検討 ◆ジョッキのサイズ ◆グラス洗浄マシンとの相性 ◆鍋洗い機（高圧洗浄機）の複数洗浄機導入 ◆Wi-Fi環境 ◆問い合わせ専用電話の設置
A40: 7 | B40: 11036 | C40: 107 | D40: =C40/B40 -> 0.0096955419 | E40: =C40+I33 -> 6250 | F40: =E40/B40 -> 0.56632838 | G40: =B40-E40 -> 4786 | H40: =G40/B40 -> 0.43367162
A41: 8 | B41: 11093 | C41: 765 | D41: =C41/B41 -> 0.068962409 | E41: =C41+I34 -> 6262 | F41: =E41/B41 -> 0.56450014 | G41: =B41-E41 -> 4831 | H41: =G41/B41 -> 0.43549986
A42: 9 | B42: 974 | C42: 240 | D42: =C42/B42 -> 0.24640657 | E42: =C42+I35 -> 597 | F42: =E42/B42 -> 0.61293634 | G42: =B42-E42 -> 377 | H42: =G42/B42 -> 0.38706366
A43: TOTAL | B43: =SUM(B38:B42) -> 28918 | C43: =SUM(C38:C42) -> 1112 | D43: =C43/B43 -> 0.038453558 | E43: =SUM(E38:E42) -> 15486 | F43: =E43/B43 -> 0.53551421 | G43: =SUM(G38:G42) -> 13432 | H43: =G43/B43 -> 0.46448579
A45: ③-3 Web予約受注率
A46: 月 | B46: 組数 | C46: TC | D46: 利用率 | E46: 電話 | F46: 利用率 | G46: パッサージュ | H46: 利用率 | I46: Web予約率
A47: 5 | B47: 122 | C47: 13 | D47: =C47/B47 -> 0.10655738 | E47: 16 | F47: =E47/B47 -> 0.13114754 | G47: =B47-C47-E47 -> 93 | H47: =G47/B47 -> 0.76229508 | I47: =C47/(C47+E47) -> 0.44827586
A48: 6 | B48: 2015 | C48: 240 | D48: =C48/B48 -> 0.1191067 | E48: 51 | F48: =E48/B48 -> 0.025310174 | G48: =B48-C48-E48 -> 1724 | H48: =G48/B48 -> 0.85558313 | I48: =C48/(C48+E48) -> 0.82474227
A49: 7 | B49: 3542 | C49: 674 | D49: =C49/B49 -> 0.19028797 | E49: 160 | F49: =E49/B49 -> 0.045172219 | G49: =B49-C49-E49 -> 2708 | H49: =G49/B49 -> 0.76453981 | I49: =C49/(C49+E49) -> 0.80815348
A50: 8 | B50: 3618 | C50: 885 | D50: =C50/B50 -> 0.24461028 | E50: 156 | F50: =E50/B50 -> 0.043117745 | G50: =B50-C50-E50 -> 2577 | H50: =G50/B50 -> 0.71227197 | I50: =C50/(C50+E50) -> 0.85014409
A51: 9 | B51: 340 | C51: 125 | D51: =C51/B51 -> 0.36764706 | E51: 19 | F51: =E51/B51 -> 0.055882353 | G51: =B51-C51-E51 -> 196 | H51: =G51/B51 -> 0.57647059 | I51: =C51/(C51+E51) -> 0.86805556
A52: TOTAL | B52: =SUM(B47:B51) -> 9637 | C52: =SUM(C47:C51) -> 1937 | D52: =C52/B52 -> 0.20099616 | E52: =SUM(E47:E51) -> 402 | F52: =E52/B52 -> 0.041714226 | G52: =SUM(G47:G51) -> 7298 | H52: =G52/B52 -> 0.75728961 | I52: =C52/(C52+E52) -> 0.82813168
E55: =E43*300 -> 4645800 | F55: ＝

Sheet 天候指数対比
B2: 4月 天候指数対比 <気象庁資料マクロクリマ> | F2: 平均気温 最高 15.7℃ （13.5℃）最低 6.5℃（5.5℃） カッコ内は前年値 <M-4th> | P2: 8月 天候指数対比 <現地ミクロクリマ> | T2: 平均気温 最高 28.4℃ （30.9℃）最低 22.0℃（24.0℃） カッコ内は前年値 <M-1st>
B3: 天候状況 | E3: ポイント | F3: 2024日数＊3 | G3: 2024合計 | H3: 比率 | I3: 2023日数＊3 | J3: 2023合計 | K3: 比率 | L3: 前年差異 | P3: 天候状況 | S3: ポイント | T3: 2024日数＊3 | U3: 2024合計 | V3: 比率 | W3: 2023日数＊3 | X3: 2023合計 | Y3: 比率 | Z3: 前年差異
B4: ポジティブ | C4: 晴れ（33度まで） | E4: 5 | F4: 0 | G4: =E4*F4 -> 0 | H4: =(F4+F5+F6)/F10 -> #DIV/0! | I4: 0 | J4: =E4*I4 -> 0 | K4: =(I4+I5+I6)/I10 -> #DIV/0! | L4: =F4-I4 -> 0 | M4: =G4-J4 -> 0 | N4: =H4-K4 -> #DIV/0! | P4: ポジティブ | Q4: 晴れ（33度まで） | S4: 5 | T4: 27 | U4: =S4*T4 -> 135 | V4: =(T4+T5+T6)/T10 -> 0.69892473 | W4: 31 | X4: =S4*W4 -> 155 | Y4: =(W4+W5+W6)/W10 -> 0.82795699 | Z4: =T4-W4 -> -4 | AA4: =U4-X4 -> -20 | AB4: =V4-Y4 -> -0.12903226
C5: 晴れ（25度以下） | E5: 4 | F5: 0 | G5: =E5*F5 -> 0 | I5: 0 | J5: =E5*I5 -> 0 | L5: =F5-I5 -> 0 | M5: =G5-J5 -> 0 | Q5: 晴れ（25度以下） | S5: 4 | T5: 0 | U5: =S5*T5 -> 0 | W5: 6 | X5: =S5*W5 -> 24 | Z5: =T5-W5 -> -6 | AA5: =U5-X5 -> -24
C6: 晴れ（33度以上15以下） 曇25度以上 | E6: 3 | F6: 0 | G6: =E6*F6 -> 0 | I6: 0 | J6: =E6*I6 -> 0 | L6: =F6-I6 -> 0 | M6: =G6-J6 -> 0 | Q6: 晴れ（33度以上15以下） 曇25度以上 | S6: 3 | T6: 38 | U6: =S6*T6 -> 114 | W6: 40 | X6: =S6*W6 -> 120 | Z6: =T6-W6 -> -2 | AA6: =U6-X6 -> -6
B7: ネガティブ | C7: 曇 | E7: 2 | F7: 0 | G7: =E7*F7 -> 0 | H7: =(F7+F8+F9)/F10 -> #DIV/0! | I7: 0 | J7: =E7*I7 -> 0 | K7: =(I7+I8+I9)/I10 -> #DIV/0! | L7: =F7-I7 -> 0 | M7: =G7-J7 -> 0 | N7: =H7-K7 -> #DIV/0! | P7: ネガティブ | Q7: 曇 | S7: 2 | T7: 6 | U7: =S7*T7 -> 12 | V7: =(T7+T8+T9)/T10 -> 0.30107527 | W7: 0 | X7: =S7*W7 -> 0 | Y7: =(W7+W8+W9)/W10 -> 0.17204301 | Z7: =T7-W7 -> 6 | AA7: =U7-X7 -> 12 | AB7: =V7-Y7 -> 0.12903226
C8: 雨 | E8: 1 | F8: 0 | G8: =E8*F8 -> 0 | I8: 0 | J8: =E8*I8 -> 0 | L8: =F8-I8 -> 0 | M8: =G8-J8 -> 0 | Q8: 雨 | S8: 1 | T8: 22 | U8: =S8*T8 -> 22 | W8: 16 | X8: =S8*W8 -> 16 | Z8: =T8-W8 -> 6 | AA8: =U8-X8 -> 6
C9: 豪雨・雷雨 | E9: 0 | F9: 0 | G9: =E9*F9 -> 0 | J9: =E9*I9 -> 0 | L9: =F9-I9 -> 0 | M9: =G9-J9 -> 0 | Q9: 豪雨・雷雨 | S9: 0 | T9: 0 | U9: =S9*T9 -> 0 | W9: 0 | X9: =S9*W9 -> 0 | Z9: =T9-W9 -> 0 | AA9: =U9-X9 -> 0
B10: TOTAL | F10: =SUM(F4:F9) -> 0 | G10: =SUM(G4:G9) -> 0 | H10: =H4+H7 -> #DIV/0! | I10: =SUM(I4:I9) -> 0 | J10: =SUM(J4:J9) -> 0 | K10: =K4+K7 -> #DIV/0! | L10: =SUM(L4:L9) -> 0 | M10: =SUM(M4:M9) -> 0 | N10: =G10/J10 -> #DIV/0! | P10: TOTAL | T10: =SUM(T4:T9) -> 93 | U10: =SUM(U4:U9) -> 283 | V10: =V4+V7 -> 1 | W10: =SUM(W4:W9) -> 93 | X10: =SUM(X4:X9) -> 315 | Y10: =Y4+Y7 -> 1 | Z10: =SUM(Z4:Z9) -> 0 | AA10: =SUM(AA4:AA9) -> -32 | AB10: =U10/X10 -> 0.8984127
F11: =G10/F10 -> #DIV/0! | I11: =J10/I10 -> #DIV/0! | L11: =F11-I11 -> #DIV/0! | N11: =F11/I11 -> #DIV/0! | T11: =U10/T10 -> 3.0430108 | W11: =X10/W10 -> 3.3870968 | Z11: =T11-W11 -> -0.34408602 | AB11: =T11/W11 -> 0.8984127
B13: 5月 天候指数対比 <現地ミクロクリマ> | F13: 平均気温 最高 17.0℃ （20.0℃）最低 11.6℃（12.7℃） カッコ内は前年値 <M-4th> | P13: 9月 天候指数対比 <現地ミクロクリマ> | T13: 平均気温 最高 24.0℃ （28.6℃）最低 15.6℃（21.4℃） カッコ内は前年値 <M- 2nd>
B14: 天候状況 | E14: ポイント | F14: 2024日数＊3 | G14: 2024合計 | H14: 比率 | I14: 2023日数＊3 | J14: 2023合計 | K14: 比率 | L14: 前年差異 | P14: 天候状況 | S14: ポイント | T14: 2024日数＊3 | U14: 2024合計 | V14: 比率 | W14: 2023日数＊3 | X14: 2023合計 | Y14: 比率 | Z14: 前年差異
B15: ポジティブ | C15: 晴れ（33度まで） | E15: 5 | F15: 0 | G15: =E15*F15 -> 0 | H15: =(F15+F16+F17)/F21 -> 0.066666667 | I15: 2 | J15: =E15*I15 -> 10 | K15: =(I15+I16+I17)/I21 -> 0.4 | L15: =F15-I15 -> -2 | M15: =G15-J15 -> -10 | N15: =H15-K15 -> -0.33333333 | P15: ポジティブ | Q15: 晴れ（33度まで） | S15: 5 | T15: 16 | U15: =S15*T15 -> 80 | V15: =(T15+T16+T17)/T21 -> 0.74666667 | W15: 5 | X15: =S15*W15 -> 25 | Y15: =(W15+W16+W17)/W21 -> 0.66666667 | Z15: =T15-W15 -> 11 | AA15: =U15-X15 -> 55 | AB15: =V15-Y15 -> 0.08
C16: 晴れ（25度以下） | E16: 4 | F16: 0 | G16: =E16*F16 -> 0 | I16: 4 | J16: =E16*I16 -> 16 | L16: =F16-I16 -> -4 | M16: =G16-J16 -> -16 | Q16: 晴れ（25度以下） | S16: 4 | T16: 32 | U16: =S16*T16 -> 128 | W16: 0 | X16: =S16*W16 -> 0 | Z16: =T16-W16 -> 32 | AA16: =U16-X16 -> 128
C17: 晴れ（33度以上15以下） 曇25度以上 | E17: 3 | F17: 1 | G17: =E17*F17 -> 3 | I17: 0 | J17: =E17*I17 -> 0 | L17: =F17-I17 -> 1 | M17: =G17-J17 -> 3 | Q17: 晴れ（33度以上15以下） 曇25度以上 | S17: 3 | T17: 8 | U17: =S17*T17 -> 24 | W17: 1 | X17: =S17*W17 -> 3 | Z17: =T17-W17 -> 7 | AA17: =U17-X17 -> 21
B18: ネガティブ | C18: 曇 | E18: 2 | F18: 5 | G18: =E18*F18 -> 10 | H18: =(F18+F19+F20)/F21 -> 0.93333333 | I18: 4 | J18: =E18*I18 -> 8 | K18: =(I18+I19+I20)/I21 -> 0.6 | L18: =F18-I18 -> 1 | M18: =G18-J18 -> 2 | N18: =H18-K18 -> 0.33333333 | P18: ネガティブ | Q18: 曇 | S18: 2 | T18: 15 | U18: =S18*T18 -> 30 | V18: =(T18+T19+T20)/T21 -> 0.25333333 | W18: 0 | X18: =S18*W18 -> 0 | Y18: =(W18+W19+W20)/W21 -> 0.33333333 | Z18: =T18-W18 -> 15 | AA18: =U18-X18 -> 30 | AB18: =V18-Y18 -> -0.08
C19: 雨 | E19: 1 | F19: 7 | G19: =E19*F19 -> 7 | I19: 5 | J19: =E19*I19 -> 5 | L19: =F19-I19 -> 2 | M19: =G19-J19 -> 2 | Q19: 雨 | S19: 1 | T19: 4 | U19: =S19*T19 -> 4 | W19: 3 | X19: =S19*W19 -> 3 | Z19: =T19-W19 -> 1 | AA19: =U19-X19 -> 1
C20: 豪雨・雷雨 | E20: 0 | F20: 2 | G20: =E20*F20 -> 0 | J20: =E20*I20 -> 0 | L20: =F20-I20 -> 2 | M20: =G20-J20 -> 0 | Q20: 豪雨・雷雨 | S20: 0 | T20: 0 | U20: =S20*T20 -> 0 | X20: =S20*W20 -> 0 | Z20: =T20-W20 -> 0 | AA20: =U20-X20 -> 0
B21: TOTAL | F21: =SUM(F15:F20) -> 15 | G21: =SUM(G15:G20) -> 20 | H21: =H15+H18 -> 1 | I21: =SUM(I15:I20) -> 15 | J21: =SUM(J15:J20) -> 39 | K21: =K15+K18 -> 1 | L21: =SUM(L15:L20) -> 0 | M21: =SUM(M15:M20) -> -19 | N21: =G21/J21 -> 0.51282051 | P21: TOTAL | T21: =SUM(T15:T20) -> 75 | U21: =SUM(U15:U20) -> 266 | V21: =V15+V18 -> 1 | W21: =SUM(W15:W20) -> 9 | X21: =SUM(X15:X20) -> 31 | Y21: =Y15+Y18 -> 1 | Z21: =SUM(Z15:Z20) -> 66 | AA21: =SUM(AA15:AA20) -> 235 | AB21: =U21/X21 -> 8.5806452
F22: =G21/F21 -> 1.3333333 | I22: =J21/I21 -> 2.6 | L22: =F22-I22 -> -1.2666667 | N22: =F22/I22 -> 0.51282051 | T22: =U21/T21 -> 3.5466667 | W22: =X21/W21 -> 3.4444444 | Z22: =T22-W22 -> 0.10222222 | AB22: =T22/W22 -> 1.0296774
B24: 6月 天候指数対比 <現地ミクロクリマ> | F24: 平均気温 最高 23.9℃ （24.1℃）最低 15.6℃（15.6℃） カッコ内は前年値 <M-3rd> | P24: 10月 天候指数対比 <気象庁資料マクロクリマ> | T24: 平均気温 最高 18.3℃ （17.9℃）最低 9.0℃（9.3℃） カッコ内は前年値 <M-5th>
B25: 天候状況 | E25: ポイント | F25: 2024日数＊3 | G25: 2024合計 | H25: 比率 | I25: 2023日数＊3 | J25: 2023合計 | K25: 比率 | L25: 前年差異 | P25: 天候状況 | S25: ポイント | T25: 2024日数＊3 | U25: 2024合計 | V25: 比率 | W25: 2023日数＊3 | X25: 2023合計 | Y25: 比率 | Z25: 前年差異
B26: ポジティブ | C26: 晴れ（33度まで） | E26: 5 | F26: 13 | G26: =E26*F26 -> 65 | H26: =(F26+F27+F28)/F32 -> 0.48888889 | I26: 20 | J26: =E26*I26 -> 100 | K26: =(I26+I27+I28)/I32 -> 0.71111111 | L26: =F26-I26 -> -7 | M26: =G26-J26 -> -35 | N26: =H26-K26 -> -0.22222222 | P26: ポジティブ | Q26: 晴れ（33度まで） | S26: 5 | T26: 2 | U26: =S26*T26 -> 10 | V26: =(T26+T27+T28)/T32 -> 0.38888889 | W26: 0 | X26: =S26*W26 -> 0 | Y26: =(W26+W27+W28)/W32 -> #DIV/0! | Z26: =T26-W26 -> 2 | AA26: =U26-X26 -> 10 | AB26: =V26-Y26 -> #DIV/0!
C27: 晴れ（25度以下） | E27: 4 | F27: 16 | G27: =E27*F27 -> 64 | I27: 38 | J27: =E27*I27 -> 152 | L27: =F27-I27 -> -22 | M27: =G27-J27 -> -88 | Q27: 晴れ（25度以下） | S27: 4 | T27: 5 | U27: =S27*T27 -> 20 | W27: 0 | X27: =S27*W27 -> 0 | Z27: =T27-W27 -> 5 | AA27: =U27-X27 -> 20
C28: 晴れ（33度以上15以下） 曇25度以上 | E28: 3 | F28: 15 | G28: =E28*F28 -> 45 | I28: 6 | J28: =E28*I28 -> 18 | L28: =F28-I28 -> 9 | M28: =G28-J28 -> 27 | Q28: 晴れ（33度以上15以下） 曇25度以上 | S28: 3 | T28: 0 | U28: =S28*T28 -> 0 | W28: 0 | X28: =S28*W28 -> 0 | Z28: =T28-W28 -> 0 | AA28: =U28-X28 -> 0
B29: ネガティブ | C29: 曇 | E29: 2 | F29: 30 | G29: =E29*F29 -> 60 | H29: =(F29+F30+F31)/F32 -> 0.51111111 | I29: 7 | J29: =E29*I29 -> 14 | K29: =(I29+I30+I31)/I32 -> 0.28888889 | L29: =F29-I29 -> 23 | M29: =G29-J29 -> 46 | N29: =H29-K29 -> 0.22222222 | P29: ネガティブ | Q29: 曇 | S29: 2 | T29: 8 | U29: =S29*T29 -> 16 | V29: =(T29+T30+T31)/T32 -> 0.61111111 | W29: 0 | X29: =S29*W29 -> 0 | Y29: =(W29+W30+W31)/W32 -> #DIV/0! | Z29: =T29-W29 -> 8 | AA29: =U29-X29 -> 16 | AB29: =V29-Y29 -> #DIV/0!
C30: 雨 | E30: 1 | F30: 15 | G30: =E30*F30 -> 15 | I30: 19 | J30: =E30*I30 -> 19 | L30: =F30-I30 -> -4 | M30: =G30-J30 -> -4 | Q30: 雨 | S30: 1 | T30: 3 | U30: =S30*T30 -> 3 | W30: 0 | X30: =S30*W30 -> 0 | Z30: =T30-W30 -> 3 | AA30: =U30-X30 -> 3
C31: 豪雨・雷雨 | E31: 0 | F31: 1 | G31: =E31*F31 -> 0 | I31: 0 | J31: =E31*I31 -> 0 | L31: =F31-I31 -> 1 | M31: =G31-J31 -> 0 | Q31: 豪雨・雷雨 | S31: 0 | T31: 0 | U31: =S31*T31 -> 0 | W31: 0 | X31: =S31*W31 -> 0 | Z31: =T31-W31 -> 0 | AA31: =U31-X31 -> 0
B32: TOTAL | F32: =SUM(F26:F31) -> 90 | G32: =SUM(G26:G31) -> 249 | H32: =H26+H29 -> 1 | I32: =SUM(I26:I31) -> 90 | J32: =SUM(J26:J31) -> 303 | K32: =K26+K29 -> 1 | L32: =SUM(L26:L31) -> 0 | M32: =SUM(M26:M31) -> -54 | N32: =G32/J32 -> 0.82178218 | P32: TOTAL | T32: =SUM(T26:T31) -> 18 | U32: =SUM(U26:U31) -> 49 | V32: =V26+V29 -> 1 | W32: =SUM(W26:W31) -> 0 | X32: =SUM(X26:X31) -> 0 | Y32: =Y26+Y29 -> #DIV/0! | Z32: =SUM(Z26:Z31) -> 18 | AA32: =SUM(AA26:AA31) -> 49 | AB32: =U32/X32 -> #DIV/0!
F33: =G32/F32 -> 2.7666667 | I33: =J32/I32 -> 3.3666667 | L33: =F33-I33 -> -0.6 | N33: =F33/I33 -> 0.82178218 | T33: =U32/T32 -> 2.7222222 | W33: =X32/W32 -> #DIV/0! | Z33: =T33-W33 -> #DIV/0! | AB33: =T33/W33 -> #DIV/0!
B35: 7月 天候指数対比 <現地ミクロクリマ> | F35: 平均気温 最高 28.0℃ （27.8℃）最低 20.5℃（21.0℃） カッコ内は前年値 <M-1st> | P35: TOTAL 天候指数 対比
B36: 天候状況 | E36: ポイント | F36: 2024日数＊3 | G36: 2024合計 | H36: 比率 | I36: 2023日数＊3 | J36: 2023合計 | K36: 比率 | L36: 前年差異 | P36: 天候状況 | S36: ポイント | T36: 2024日数＊3 | U36: 2024合計 | V36: 比率 | W36: 2023日数＊3 | X36: 2023合計 | Y36: 比率 | Z36: 前年差異
B37: ポジティブ | C37: 晴れ（33度まで） | E37: 5 | F37: 26 | G37: =E37*F37 -> 130 | H37: =(F37+F38+F39)/F43 -> 0.74193548 | I37: 35 | J37: =E37*I37 -> 175 | K37: =(I37+I38+I39)/I43 -> 0.79569892 | L37: =F37-I37 -> -9 | M37: =G37-J37 -> -45 | N37: =H37-K37 -> -0.053763441 | P37: ポジティブ | Q37: 晴れ（33度まで） | S37: 5 | T37: =F4+F15+F26+F37+T4+T15+T26 -> 84 | U37: =S37*T37 -> 420 | V37: =(T37+T38+T39)/T43 -> 0.63020833 | W37: =I4+I15+I26+I37+W4+W15+W26 -> 93 | X37: =S37*W37 -> 465 | Y37: =(W37+W38+W39)/W43 -> 0.75666667 | Z37: =T37-W37 -> -9 | AA37: =U37-X37 -> -45 | AB37: =V37-Y37 -> -0.12645833
C38: 晴れ（25度以下） | E38: 4 | F38: 5 | G38: =E38*F38 -> 20 | I38: 10 | J38: =E38*I38 -> 40 | L38: =F38-I38 -> -5 | M38: =G38-J38 -> -20 | Q38: 晴れ（25度以下） | S38: 4 | T38: =F5+F16+F27+F38+T5+T16+T27 -> 58 | U38: =S38*T38 -> 232 | W38: =I5+I16+I27+I38+W5+W16+W27 -> 58 | X38: =S38*W38 -> 232 | Z38: =T38-W38 -> 0 | AA38: =U38-X38 -> 0
C39: 晴れ（33度以上15以下） 曇25度以上 | E39: 3 | F39: 38 | G39: =E39*F39 -> 114 | I39: 29 | J39: =E39*I39 -> 87 | L39: =F39-I39 -> 9 | M39: =G39-J39 -> 27 | Q39: 晴れ（33度以上15以下） 曇25度以上 | S39: 3 | T39: =F6+F17+F28+F39+T6+T17+T28 -> 100 | U39: =S39*T39 -> 300 | W39: =I6+I17+I28+I39+W6+W17+W28 -> 76 | X39: =S39*W39 -> 228 | Z39: =T39-W39 -> 24 | AA39: =U39-X39 -> 72
B40: ネガティブ | C40: 曇 | E40: 2 | F40: 9 | G40: =E40*F40 -> 18 | H40: =(F40+F41+F42)/F43 -> 0.25806452 | I40: 4 | J40: =E40*I40 -> 8 | K40: =(I40+I41+I42)/I43 -> 0.20430108 | L40: =F40-I40 -> 5 | M40: =G40-J40 -> 10 | N40: =H40-K40 -> 0.053763441 | P40: ネガティブ | Q40: 曇 | S40: 2 | T40: =F7+F18+F29+F40+T7+T18+T29 -> 73 | U40: =S40*T40 -> 146 | V40: =(T40+T41+T42)/T43 -> 0.36979167 | W40: =I7+I18+I29+I40+W7+W18+W29 -> 15 | X40: =S40*W40 -> 30 | Y40: =(W40+W41+W42)/W43 -> 0.24333333 | Z40: =T40-W40 -> 58 | AA40: =U40-X40 -> 116 | AB40: =V40-Y40 -> 0.12645833
C41: 雨 | E41: 1 | F41: 15 | G41: =E41*F41 -> 15 | I41: 15 | J41: =E41*I41 -> 15 | L41: =F41-I41 -> 0 | M41: =G41-J41 -> 0 | Q41: 雨 | S41: 1 | T41: =F8+F19+F30+F41+T8+T19+T30 -> 66 | U41: =S41*T41 -> 66 | W41: =I8+I19+I30+I41+W8+W19+W30 -> 58 | X41: =S41*W41 -> 58 | Z41: =T41-W41 -> 8 | AA41: =U41-X41 -> 8
C42: 豪雨・雷雨 | E42: 0 | F42: 0 | G42: =E42*F42 -> 0 | J42: =E42*I42 -> 0 | L42: =F42-I42 -> 0 | M42: =G42-J42 -> 0 | Q42: 豪雨・雷雨 | S42: 0 | T42: =F9+F20+F31+F42+T9+T20+T31 -> 3 | U42: =S42*T42 -> 0 | W42: =I9+I20+I31+I42+W9+W20+W31 -> 0 | X42: =S42*W42 -> 0 | Z42: =T42-W42 -> 3 | AA42: =U42-X42 -> 0
B43: TOTAL | F43: =SUM(F37:F42) -> 93 | G43: =SUM(G37:G42) -> 297 | H43: =H37+H40 -> 1 | I43: =SUM(I37:I42) -> 93 | J43: =SUM(J37:J42) -> 325 | K43: =K37+K40 -> 1 | L43: =SUM(L37:L42) -> 0 | M43: =SUM(M37:M42) -> -28 | N43: =G43/J43 -> 0.91384615 | P43: TOTAL | T43: =SUM(T37:T42) -> 384 | U43: =SUM(U37:U42) -> 1164 | V43: =V37+V40 -> 1 | W43: =SUM(W37:W42) -> 300 | X43: =SUM(X37:X42) -> 1013 | Y43: =Y37+Y40 -> 1 | Z43: =SUM(Z37:Z42) -> 84 | AA43: =SUM(AA37:AA42) -> 151 | AB43: =U43/X43 -> 1.1490622
F44: =G43/F43 -> 3.1935484 | I44: =J43/I43 -> 3.4946237 | L44: =F44-I44 -> -0.30107527 | N44: =F44/I44 -> 0.91384615 | T44: =U43/T43 -> 3.03125 | W44: =X43/W43 -> 3.3766667 | Z44: =T44-W44 -> -0.34541667 | AB44: =T44/W44 -> 0.89770484

Sheet 2024計画値・予測・実績進捗
A1: ■R6年 ポップアップ ヒツジニワイン / さっぽろテレビ塔ビアガーデン売上計画（予算）・売上予測（9/8まで）・実績進捗確認表
B2: 計画値 | E2: 予測値（目標値） | K2: 実績進捗（派遣分のみ） | R2: ノヴェロさん請求内容 | Z2: 家賃 | AB2: 概算（仮置き）
A3: 月 | B3: 売上予算 | C3: 客数 | D3: 客単価 | E3: 労働時間（予測値） | F3: 人時生産性 | G3: 想定人件費 | H3: 人件費率 | I3: 売上予測 | J3: 対予算 | K3: 売上実績 | L3: 対予測 | M3: 対予算 | N3: 実労働時間 | O3: 人時生産性 | P3: 概算人件費率 | Q3: 派遣人件費（リザルト） | R3: 人件費 | S3: 営業日数 | T3: 拘束時間 | U3: 残業時間 | V3: 人件費合計 | W3: 交通費合計 | X3: 手当 | Y3: 合計 | Z3: 家賃 | AA3: 1日 | AB3: =K11 -> 1.3990628e+08
A4: 4 | B4: 260000 | C4: 200 | D4: =B4/C4 -> 1300 | E4: 200 | F4: =I4/E4 -> 1300 | G4: =E4*R4 -> #DIV/0! | H4: =G4/B4 -> #DIV/0! | I4: 260000 | J4: =I4/B4 -> 1 | K4: 499227 | L4: =K4/I4 -> 1.9201038 | M4: =K4/B4 -> 1.9201038 | N4: =T4+U4 -> 0 | O4: =K4/N4 -> #DIV/0! | P4: =Q4/K4 -> 0 | Q4: =Y4 -> 0 | R4: =Q4/N4 -> #DIV/0! | Y4: =V4+W4 -> 0 | AA4: 30000 | AB4: =AB3*23.8% -> 33297694 | AC4: 人件費 | AH4: 499227
A5: 5 | B5: 1851200 | C5: 520 | D5: =B5/C5 -> 3560 | E5: 550 | F5: =I5/E5 -> 3365.8182 | G5: =E5*R5 -> 991969.37 | H5: =G5/B5 -> 0.53585208 | I5: 1851200 | J5: =I5/B5 -> 1 | K5: 2919145 | L5: =K5/I5 -> 1.5768934 | M5: =K5/B5 -> 1.5768934 | N5: =T5+U5 -> 579.5 | O5: =K5/N5 -> 5037.3512 | P5: =Q5/K5 -> 0.35804148 | Q5: =Y5 -> 1045175 | R5: =Q5/N5 -> 1803.5807 | S5: 5 | T5: 579.5 | U5: 0 | V5: 956175 | W5: 89000 | Y5: =V5+W5+X5 -> 1045175 | AA5: 30000 | AD5: 時給＋交通費 | AH5: 2919145
A6: 6 | B6: 25690000 | C6: 7000 | D6: =B6/C6 -> 3670 | E6: 4500 | F6: =I6/E6 -> 4888.8889 | G6: =E6*R6 -> 8136786.5 | H6: =G6/B6 -> 0.31672972 | I6: 22000000 | J6: =I6/B6 -> 0.85636434 | K6: ='2024.6月実績'!O93 -> 19194436 | L6: =K6/I6 -> 0.87247438 | M6: =K6/B6 -> 0.74715595 | N6: =T6+U6 -> 3587.5 | O6: =K6/N6 -> 5350.3655 | P6: =Q6/K6 -> 0.3379535 | Q6: =Y6 -> 6486827 | R6: =Q6/N6 -> 1808.1748 | S6: 30 | T6: 3580.5 | U6: 7 | V6: 5939877 | W6: 545000 | X6: 1950 | Y6: =V6+W6+X6 -> 6486827 | AA6: 75000 | AD6: Timee | AF6: Forking | AM6: 157
A7: 7 | B7: 51610000 | C7: 13000 | D7: =B7/C7 -> 3970 | E7: 5600 | F7: =I7/E7 -> 8928.5714 | G7: =E7*R7 -> 9577580.9 | H7: =G7/B7 -> 0.18557607 | I7: 50000000 | J7: =I7/B7 -> 0.9688045 | K7: ='2024.7月実績'!L93 -> 47613345 | L7: =K7/I7 -> 0.95226691 | M7: =K7/B7 -> 0.92256046 | N7: =T7+AD7+AF7+U7 -> 5099.25 | O7: =K7/N7 -> 9337.3232 | P7: =Q7/K7 -> 0.18316623 | Q7: =AH7 -> 8721157 | R7: =Q7/N7 -> 1710.2823 | S7: 31 | T7: 4084.25 | U7: 32 | V7: 7019597 | W7: 583000 | X7: 13738 | Y7: =V7+W7+X7 -> 7616335 | AA7: 100000 | AB7: =AB3*31.5% -> 44070477 | AC7: 材料費 | AD7: 335 | AE7: 391038 | AF7: 648 | AG7: 713784 | AH7: =Y7+AE7+AG7 -> 8721157
A8: 8 | B8: 49500000 | C8: 12500 | D8: =B8/C8 -> 3960 | E8: 5600 | F8: =I8/E8 -> 8928.5714 | G8: =E8*R8 -> 9756392.1 | H8: =G8/B8 -> 0.19709883 | I8: 50000000 | J8: =I8/B8 -> 1.010101 | K8: ='2024.8月実績'!M93 -> 55874978 | L8: =K8/I8 -> 1.1174996 | M8: =K8/B8 -> 1.1287874 | N8: =T8+U8+AD8+AF8 -> 5407 | O8: =K8/N8 -> 10333.822 | P8: =Q8/K8 -> 0.16859326 | Q8: =AH8 -> 9420145 | R8: =Q8/N8 -> 1742.2129 | S8: 31 | T8: 4444 | U8: 39 | V8: 7728270 | W8: 633000 | X8: 11262 | Y8: =V8+W8+X8 -> 8372532 | AA8: 100000 | AB8: =AB3*7% -> 9793439.4 | AC8: 消耗品費 | AD8: 48 | AE8: 52747 | AF8: 876 | AG8: 994866 | AH8: =Y8+AE8+AG8 -> 9420145
A9: 9 | B9: 7000000 | C9: 2000 | D9: =B9/C9 -> 3500 | E9: 1400 | F9: =I9/E9 -> 5714.2857 | G9: =E9*R9 -> 2660000 | H9: =G9/B9 -> 0.38 | I9: 8000000 | J9: =I9/B9 -> 1.1428571 | K9: ='2024.9月実績'!L93 -> 12350827 | L9: =K9/I9 -> 1.5438534 | M9: =K9/B9 -> 1.7644039 | N9: =T9+U9 -> 1065 | O9: =K9/N9 -> 11597.021 | P9: =Q9/K9 -> 0.2531934 | Q9: =AH9 -> 3127148 | R9: 1900 | S9: 8 | T9: 1063 | U9: 2 | V9: 1866106 | W9: 150000 | X9: 1350 | Y9: =V9+W9+X9 -> 2017456 | AA9: 30000 | AB9: 25266300 | AC9: イニシャル | AE9: =51100+5700 -> 56800 | AG9: 1052892 | AH9: =Y9+AE9+AG9 -> 3127148 | AJ9: 17040
A10: 10 | B10: 455000 | C10: 350 | D10: =B10/C10 -> 1300 | E10: 100 | F10: =I10/E10 -> #REF! | G10: =E10*R10 -> 190000 | H10: =G10/B10 -> 0.41758242 | I10: ='2024.10月実績'!#REF! -> #REF! | J10: =I10/B10 -> #REF! | K10: ='2024.10月実績'!L93 -> 1454318.2 | L10: =K10/I10 -> #REF! | M10: =K10/B10 -> 3.1963037 | N10: =T10+U10 -> 0 | O10: =K10/N10 -> #DIV/0! | P10: =Q10/K10 -> 0 | Q10: =Y10 -> 0 | R10: 1900 | Y10: =V10+W10 -> 0 | AA10: 30000 | AB10: 14000000 | AC10: 家賃 | AG10: 408303 | AI10: 業務委託＆スキマ人件費費用圧縮対策
A11: TOTAL | B11: =SUM(B4:B10) -> 136366200 | C11: =SUM(C4:C10) -> 35570 | D11: =B11/C11 -> 3833.7419 | E11: =SUM(E4:E10) -> 17950 | F11: =I11/E11 -> #REF! | G11: =E11*R11 -> 32847878 | H11: =G11/B11 -> 0.24087991 | I11: =SUM(I4:I10) -> #REF! | J11: =I11/B11 -> #REF! | K11: =SUM(K4:K10) -> 1.3990628e+08 | L11: =K11/I11 -> #REF! | M11: =K11/B11 -> 1.0259601 | N11: =SUM(N4:N10) -> 15738.25 | O11: =K11/N11 -> 8889.5702 | P11: =Q11/K11 -> 0.20585532 | Q11: =SUM(Q4:Q10) -> 28800452 | R11: =Q11/N11 -> 1829.9653 | S11: =SUM(S4:S10) -> 105 | T11: =SUM(T4:T10) -> 13751.25 | U11: =SUM(U4:U10) -> 80 | V11: =SUM(V4:V10) -> 23510025 | W11: =SUM(W4:W10) -> 2000000 | Y11: =SUM(Y4:Y10) -> 25538325 | Z11: =SUM(Z4:Z10) -> 0 | AA11: =SUM(AA4:AA10) -> 395000 | AB11: =AB3*5% -> 6995313.9 | AC11: 流動固定費 | AE11: =SUM(AE7:AE10) -> 500585 | AG11: =SUM(AG7:AG10) -> 3169845 | AI11: =AE11+AG11 -> 3670430 | AJ11: =AI11/AI13 -> 0.11303758 | AK11: =AI11/AL11 -> 2251.7975 | AL11: 1630 | AM11: =AK11/AK13 -> 0.12517081 | AN11: 5000 | AO11: 1650 | AP11: =AN11*AO11 -> 8250000 | AQ11: =AN11/AN13 -> 0.2792984 | AR11: =AP11/AP13 -> 0.25380117
B12: 136366200 | C12: 提出予算 | I12: ※天気要因見込まず算出 | K12: 44109 | L12: 終了時点の進捗状況 | N12: =K11/S12 -> 1399062.8 | O12: =K11-B12 -> 3540077.5 | P12: =K11/B12 -> 1.0259601 | Q12: =Q11/K11 -> 0.20585532 | S12: 100 | Y12: =Y11/K11 -> 0.18253881 | AB12: =AB3-AB4-AB7-AB8-AB9-AB10-AB11 -> 6483052.7 | AC12: 利益 | AI12: =Q11 -> 28800452 | AJ12: =AI12/AI13 -> 0.88696242 | AK12: 15738 | AL12: =AI12/AK12 -> 1829.9944 | AM12: =AK12/AK13 -> 0.87482919 | AN12: 12902 | AO12: 1880 | AP12: =AN12*AO12 -> 24255760 | AQ12: =AN12/AN13 -> 0.7207016 | AR12: =AP12/AP13 -> 0.74619883
B13: =B11-B12 -> 0 | C13: 差異 | AG13: 140800000 | AI13: =SUM(AI11:AI12) -> 32470882 | AJ13: =AI13/AG13 -> 0.23061706 | AK13: =SUM(AK11:AK12) -> 17989.798 | AL13: =(AL11+AL12)/2 -> 1729.9972 | AN13: =SUM(AN11:AN12) -> 17902 | AO13: =(AO11+AO12)/2 -> 1765 | AP13: =SUM(AP11:AP12) -> 32505760
I16: 100000000 | J16: 予算まで | K16: =B11-K11 -> -3540077.5 | L16: 12 | M16: =K16/L16 -> -295006.45 | N16: 2019 | O16: 58190982 | P16: =K11/O16 -> 2.4042605 | V16: 税込
B17: =B7+B8 -> 101110000 | C17: =K7+K8 -> 1.0348832e+08 | D17: =C17-B17 -> 2378323.6 | I17: 111111111 | J17: 予測まで | K17: =I11-K11 -> #REF! | L17: 12 | M17: =K17/L17 -> #REF! | N17: 2018 | O17: 44179221 | P17: =K11/O17 -> 3.1667891 | U17: 5 | V17: 1149692
J18: 一億円まで | K18: =I16-K11 -> -39906277 | L18: 12 | M18: =K18/L18 -> -3325523.1 | N18: 平均 | O18: =(O16+O17)/2 -> 51185102 | P18: =K11/O18 -> 2.7333398 | U18: 6 | V18: 7135509
G19: 2019年度 | J19: 一億一千万まで | K19: =I17-K11 -> -28795166 | L19: 12 | M19: =K19/L19 -> -2399597.2 | U19: 7 | V19: 8381268
G20: 91399704 | H20: =K8-K9 -> 43524151 | I20: 945247 | J20: =I20-H20 -> -42578904 | K20: =K11 -> 1.3990628e+08 | L20: =K20/G20 -> 1.5307082 | M20: =K20-G20 -> 48506573 | U20: 8 | V20: 9209785
U21: 9 | V21: 2219201
V22: =SUM(V17:V21) -> 28095455
I23: 115000000 | K23: =K11 -> 1.3990628e+08 | L23: =K23/I23 -> 1.2165763 | N23: =K23*1.1 -> 1.5389691e+08
M24: 150000000 | N24: =M24*10/110 -> 13636364 | O24: =M24-N24 -> 1.3636364e+08 | P24: =K11-O24 -> 3542641.1
A25: ■大通りビアガーデン2024 実績
A26: 推計 | B26: 2019 | C26: ー | D26: 2023 | E26: 2024 | F26: 2006 | H26: 2019 | I26: =G20 -> 91399704 | J26: =K11/I26 -> 1.5307082 | K26: =K11-I26 -> 48506573
A27: 来場者数 | B27: 1170000 | D27: 886000 | E27: 902000 | F27: 1523000 | H27: 2023 | I27: 114623699 | J27: =K11/I27 -> 1.2205703 | K27: =K11-I27 -> 25282578 | L27: 5187 | M27: 6717 | N27: =M27-L27 -> 1530 | O27: =M27/L27 -> 1.2949682
A28: 前年比 | B28: - | D28: 75.8 | E28: 101.8 | F28: =F27/E27 -> 1.6884701 | L28: 992 | M28: 1941 | N28: =M28-L28 -> 949 | O28: =M28/L28 -> 1.9566532
A29: ビール消費量（L） | B29: 441456 | D29: 334182 | E29: 340050 | F29: 574842 | L29: 318 | M29: 2503 | N29: =M29-L29 -> 2185 | O29: =M29/L29 -> 7.8710692
A30: 前年比 | B30: - | D30: 75.7 | E30: =E29/D29 -> 1.0175593 | F30: =F29/E29 -> 1.6904632 | L30: =SUM(L27:L29) -> 6497 | M30: =SUM(M27:M29) -> 11161 | N30: =SUM(N27:N29) -> 4664 | O30: =M30/L30 -> 1.7178698
A31: 20L樽本数 | B31: =B29/20 -> 22072.8 | D31: =D29/20 -> 16709.1 | E31: =E29/20 -> 17002.5 | F31: =F29/20 -> 28742.1 | J31: 2024 | K31: 期間 | L31: 売上 | M31: 値引き | N31: 税抜売上 | O31: 税込売上 | P31: 値引き | Q31: 税込売上合計
A32: 前年比 | D32: =D31/B31 -> 0.75699957 | E32: =E31/D31 -> 1.0175593 | F32: =F31/E31 -> 1.6904632 | J32: 4~5 | K32: ピコレ4/27-5/19 | L32: 2939522 | M32: 4040 | N32: =L32-M32 -> 2935482 | O32: 3232260 | P32: 4040 | Q32: =O32-P32 -> 3228220 | R32: 23
A33: ビール原価金額 | B33: =B31*9000 -> 198655200 | C33: 原価率想定 | D33: =D31*9000 -> 150381900 | E33: =E31*9700 -> 164924250 | F33: =F31*9000 -> 258678900 | J33: 5 | K33: ビアガ5/27-5/31 | L33: 477807 | M33: 3480 | N33: =L33-M33 -> 474327 | O33: 525570 | P33: 3480 | Q33: =O33-P33 -> 522090 | R33: 5
A34: ビール売上推定金額 | B34: =B33*3.5 -> 695293200 | C34: =B33/B34 -> 0.28571429 | D34: =D33*3.5 -> 526336650 | E34: =E33*3.5 -> 577234875 | F34: =F33*3.5 -> 905376150 | J34: 6 | K34: ビアガフル | L34: 19170665 | M34: 26790 | N34: =L34-M34 -> 19143875 | O34: 21087090 | P34: 26790 | Q34: =O34-P34 -> 21060300 | R34: 30
A35: ひとり当たりのビール購入額 | B35: =B34/B27 -> 594.26769 | C35: =C34/C27 -> #DIV/0! | D35: =D34/D27 -> 594.05942 | E35: =E34/E27 -> 639.94997 | F35: =F34/F27 -> 594.46891 | J35: 7 | K35: ビアガフル | L35: 47598067 | M35: 17800 | N35: =L35-M35 -> 47580267 | O35: 52356880 | P35: 17800 | Q35: =O35-P35 -> 52339080 | R35: 31
A36: 客単価想定 | B36: 1300 | D36: 1300 | E36: 1300 | F36: 1300 | J36: 8 | K36: ビアガフル | L36: 55870570 | M36: 5980 | N36: =L36-M36 -> 55864590 | O36: 61456496 | P36: 5980 | Q36: =O36-P36 -> 61450516 | R36: 31
A37: 推定売上額 | B37: =B27*B36 -> 1521000000 | D37: =D27*D36 -> 1151800000 | E37: =E27*E36 -> 1172600000 | F37: =F27*F36 -> 1979900000 | J37: 9 | K37: ビアガ9/1-9/8 | L37: 8816632 | M37: 5700 | N37: =L37-M37 -> 8810932 | O37: 9698100 | P37: 5700 | Q37: =O37-P37 -> 9692400 | R37: 8
J38: 9~10 | K38: ピコレ共催アキノジン | L38: 4982837 | M38: 1100 | N38: =L38-M38 -> 4981737 | O38: 5480760 | P38: 1100 | Q38: =O38-P38 -> 5479660 | R38: 23
K39: ビアガのみ105日 | L39: =L34+L33+L35+L36+L37 -> 131933741 | M39: =M34+M33+M35+M36+M37 -> 59750 | N39: =N34+N33+N35+N36+N37 -> 131873991 | O39: =O34+O33+O35+O36+O37 -> 145124136 | P39: =P34+P33+P35+P36+P37 -> 59750 | Q39: =Q34+Q33+Q35+Q36+Q37 -> 145064386 | R39: =R34+R33+R35+R36+R37 -> 105
K40: ピコレ&ピコレ共催 | L40: =L32+L38 -> 7922359 | M40: =M32+M38 -> 5140 | N40: =N32+N38 -> 7917219 | O40: =O32+O38 -> 8713020 | P40: =P32+P38 -> 5140 | Q40: =Q32+Q38 -> 8707880 | R40: =R32+R38 -> 46
K41: 総合計 | L41: =SUM(L32:L38) -> 139856100 | M41: =SUM(M32:M38) -> 64890 | N41: =SUM(N32:N38) -> 139791210 | O41: =SUM(O32:O38) -> 153837156 | P41: =SUM(P32:P38) -> 64890 | Q41: =SUM(Q32:Q38) -> 153772266 | R41: =SUM(R32:R38) -> 151
J43: 2023 | K43: 期間 | L43: 売上 | M43: 値引き | N43: 税抜売上 | O43: 税込売上 | P43: 値引き | Q43: 税込売上合計
J44: 4~5 | K44: ピコレ参戦なし | N44: =L44-M44 -> 0 | Q44: =O44-P44 -> 0 | R44: 0
J45: 5 | K45: ビアガ5/27-5/31 | L45: =O45/1.1 -> 1795227.3 | N45: =L45-M45 -> 1795227.3 | O45: 1974750 | Q45: =O45-P45 -> 1974750 | R45: 5 | S45: 506
J46: 6 | K46: ビアガフル | L46: =O46/1.1 -> 19049727 | N46: =L46-M46 -> 19049727 | O46: 20954700 | Q46: =O46-P46 -> 20954700 | R46: 30 | S46: 5309
J47: 7 | K47: ビアガフル | L47: =O47/1.1 -> 44856909 | N47: =L47-M47 -> 44856909 | O47: 49342600 | Q47: =O47-P47 -> 49342600 | R47: 31 | S47: 11036
J48: 8 | K48: ビアガフル | L48: =O48/1.1 -> 44860591 | N48: =L48-M48 -> 44860591 | O48: 49346650 | Q48: =O48-P48 -> 49346650 | R48: 31 | S48: 11093
J49: 9 | K49: ビアガ9/1-9/3 | L49: =O49/1.1 -> 8816454.5 | N49: =L49-M49 -> 8816454.5 | O49: 9698100 | Q49: =O49-P49 -> 9698100 | R49: 3 | S49: 263
J50: 9~10 | K50: ピコレ | L50: 1487994 | N50: =L50-M50 -> 1487994 | O50: 1636793 | P50: 4040 | Q50: =O50-P50 -> 1632753 | R50: 0
K51: ビアガのみ105日 | L51: =L46+L45+L47+L48+L49 -> 1.1937891e+08 | M51: =M46+M45+M47+M48+M49 -> 0 | N51: =N46+N45+N47+N48+N49 -> 1.1937891e+08 | O51: =O46+O45+O47+O48+O49 -> 131316800 | P51: =P46+P45+P47+P48+P49 -> 0 | Q51: =Q46+Q45+Q47+Q48+Q49 -> 131316800 | R51: =R46+R45+R47+R48+R49 -> 100
K52: ピコレ&ピコレ共催 | L52: =L44+L50 -> 1487994 | M52: =M44+M50 -> 0 | N52: =N44+N50 -> 1487994 | O52: =O44+O50 -> 1636793 | P52: =P44+P50 -> 4040 | Q52: =Q44+Q50 -> 1632753 | R52: =R44+R50 -> 0
K53: 総合計 | L53: =SUM(L44:L50) -> 1.208669e+08 | M53: =SUM(M44:M50) -> 0 | N53: =SUM(N44:N50) -> 1.208669e+08 | O53: =SUM(O44:O50) -> 132953593 | P53: =SUM(P44:P50) -> 4040 | Q53: =SUM(Q44:Q50) -> 132949553 | R53: =SUM(R44:R50) -> 100

Sheet 2024.10月実績
A1: ■R6年度 ピコレ＆ビアガーデン売上実績
A2: 10月 | L2: =L14+L24+L34+L44+L54+L64 -> 1599750 | R2: 10
A3: FOOD | C3: ビアガーデン10月 実績TOTAL | N3: 客数 | R3: 売上
A4: 予算 | C4: 実績 | E4: 客数 | G4: 客単価 | I4: 売上予算 | L4: 9275000 | M4: 1日平均 | R4: =L4/R2 -> 927500 | T4: 天候要因（売上との関連性を数値化する）
A5: 1st week | C5: 1st week | T5: =C5 -> 1st week
A6: 曜日 | B6: 日にち | C6: 曜日 | D6: 日にち | E6: 客数 | F6: 料理売上 | G6: 料理単価 | H6: 飲料売上 | I6: 飲料単価 | J6: テント利用料 | K6: 物販 | L6: 売上合計 | M6: 合計単価 | N6: サーフィンズ | O6: forking | P6: Timee | Q6: 合計 | R6: 人時売上高 | T6: 最低 | U6: 最高 | V6: 12時 | W6: 15時 | X6: 18時 | Y6: Ave | AA6: ■天候要因 | AC6: 評価点
A7: 日 | C7: 日 | D7: =B7 -> 0 | G7: =F7/E7 -> #DIV/0! | I7: =H7/E7 -> #DIV/0! | L7: =F7+H7+J7 -> 0 | M7: =L7/E7 -> #DIV/0! | R7: =L7/Q7 -> #DIV/0! | Y7: =SUM(V7:X7)/3 -> 0 | AA7: 晴れ（33度まで） | AC7: 5
A8: 月 | C8: 月 | D8: =B8 -> 0 | G8: =F8/E8 -> #DIV/0! | I8: =H8/E8 -> #DIV/0! | L8: =F8+H8+J8 -> 0 | M8: =L8/E8 -> #DIV/0! | R8: =L8/Q8 -> #DIV/0! | Y8: =SUM(V8:X8)/3 -> 0 | AA8: 晴れ（25度以下） | AC8: 4
A9: 火 | B9: 1 | C9: 火 | D9: =B9 -> 1 | E9: 66 | F9: 125600 | G9: =F9/E9 -> 1903.0303 | H9: 67050 | I9: =H9/E9 -> 1015.9091 | L9: =F9+H9+J9 -> 192650 | M9: =L9/E9 -> 2918.9394 | R9: =L9/Q9 -> #DIV/0! | T9: 15.1 | U9: 26.3 | V9: 5 | W9: 5 | X9: 4 | Y9: =SUM(V9:X9)/3 -> 4.6666667 | AA9: 晴れ（33度以上）曇25度以上 | AC9: 3
A10: 水 | B10: 2 | C10: 水 | D10: =B10 -> 2 | E10: 30 | F10: 78300 | G10: =F10/E10 -> 2610 | H10: 42700 | I10: =H10/E10 -> 1423.3333 | L10: =F10+H10+J10 -> 121000 | M10: =L10/E10 -> 4033.3333 | R10: =L10/Q10 -> #DIV/0! | T10: 18.2 | U10: 22 | V10: 2 | W10: 1 | X10: 2 | Y10: =SUM(V10:X10)/3 -> 1.6666667 | AA10: 曇 | AC10: 2
A11: 木 | B11: 3 | C11: 木 | D11: =B11 -> 3 | E11: 44 | F11: 72200 | G11: =F11/E11 -> 1640.9091 | H11: 44400 | I11: =H11/E11 -> 1009.0909 | L11: =F11+H11+J11 -> 116600 | M11: =L11/E11 -> 2650 | R11: =L11/Q11 -> #DIV/0! | T11: 12.1 | U11: 16.8 | V11: 2 | W11: 2 | X11: 2 | Y11: =SUM(V11:X11)/3 -> 2 | AA11: 雨 | AC11: 1
A12: 金 | B12: 4 | C12: 金 | D12: =B12 -> 4 | E12: 20 | F12: 38750 | G12: =F12/E12 -> 1937.5 | H12: 31350 | I12: =H12/E12 -> 1567.5 | L12: =F12+H12+J12 -> 70100 | M12: =L12/E12 -> 3505 | R12: =L12/Q12 -> #DIV/0! | T12: 12 | U12: 15.2 | V12: 2 | W12: 1 | X12: 1 | Y12: =SUM(V12:X12)/3 -> 1.3333333 | AA12: 豪雨・雷雨 | AC12: 0
A13: 土 | B13: 5 | C13: 土 | D13: =B13 -> 5 | E13: 181 | F13: 287100 | G13: =F13/E13 -> 1586.1878 | H13: 161100 | I13: =H13/E13 -> 890.05525 | J13: 0 | L13: =F13+H13+J13 -> 448200 | M13: =L13/E13 -> 2476.2431 | R13: =L13/Q13 -> #DIV/0! | T13: 14.1 | U13: 21.3 | V13: 4 | W13: 4 | X13: 4 | Y13: =SUM(V13:X13)/3 -> 4 | AA13: ※5.6月は18時は最低気温を採用。7月〜は最高気温を採用。
A14: SUB TOTAL | C14: SUB TOTAL | E14: =SUM(E7:E13) -> 341 | F14: =SUM(F7:F13) -> 601950 | G14: =F14/E14 -> 1765.2493 | H14: =SUM(H7:H13) -> 346600 | I14: =H14/E14 -> 1016.4223 | J14: =I14/F14 -> 0.0016885494 | L14: =F14+H14 -> 948550 | M14: =L14/E14 -> 2781.6716 | Q14: =SUM(Q7:Q13) -> 0 | R14: =L14/Q14 -> #DIV/0! | S14: 5 | T14: =SUM(T7:T13)/S14 -> 14.3 | U14: =SUM(U7:U13)/S14 -> 20.32 | V14: =SUM(V7:V13)/S14 -> 3 | W14: =SUM(W7:W13)/S14 -> 2.6 | X14: =SUM(X7:X13)/S14 -> 2.6 | Y14: =SUM(V14:X14)/3 -> 2.7333333 | Z14: 15 | AA14: =L14/S14 -> 189710 | AF14: ※1日平均売上
A15: 2nd week | C15: 2nd week | T15: =C15 -> 2nd week
A16: 曜日 | B16: 日にち | C16: 曜日 | D16: 日にち | E16: 客数 | F16: 料理売上 | G16: 料理単価 | H16: 飲料売上 | I16: 飲料単価 | J16: テント利用料 | K16: 物販 | L16: 売上合計 | M16: 合計単価 | N16: サーフィンズ | O16: forking | P16: Timee | Q16: 合計 | R16: 人時売上高 | T16: 最低 | U16: 最高 | V16: 12時 | W16: 15時 | X16: 18時 | Y16: Ave | AA16: ■天候要因 | AC16: 評価点
A17: 日 | B17: 6 | C17: 日 | D17: =B17 -> 6 | E17: 197 | F17: 409700 | G17: =F17/E17 -> 2079.6954 | H17: 241500 | I17: =H17/E17 -> 1225.8883 | L17: =F17+H17+J17 -> 651200 | M17: =L17/E17 -> 3305.5838 | R17: =L17/Q17 -> #DIV/0! | T17: 10.9 | U17: 22.5 | V17: 4 | W17: 2 | X17: 2 | Y17: =SUM(V17:X17)/3 -> 2.6666667 | AA17: 晴れ（33度まで） | AC17: 5
A18: 月 | C18: 月 | D18: =B18 -> 0 | G18: =F18/E18 -> #DIV/0! | I18: =H18/E18 -> #DIV/0! | L18: =F18+H18+J18 -> 0 | M18: =L18/E18 -> #DIV/0! | R18: =L18/Q18 -> #DIV/0! | Y18: =SUM(V18:X18)/3 -> 0 | AA18: 晴れ（25度以下） | AC18: 4
A19: 火 | C19: 火 | D19: =B19 -> 0 | G19: =F19/E19 -> #DIV/0! | I19: =H19/E19 -> #DIV/0! | L19: =F19+H19+J19 -> 0 | M19: =L19/E19 -> #DIV/0! | R19: =L19/Q19 -> #DIV/0! | Y19: =SUM(V19:X19)/3 -> 0 | AA19: 晴れ（33度以上）曇25度以上 | AC19: 3
A20: 水 | C20: 水 | D20: =B20 -> 0 | G20: =F20/E20 -> #DIV/0! | I20: =H20/E20 -> #DIV/0! | L20: =F20+H20+J20 -> 0 | M20: =L20/E20 -> #DIV/0! | R20: =L20/Q20 -> #DIV/0! | Y20: =SUM(V20:X20)/3 -> 0 | AA20: 曇 | AC20: 2
A21: 木 | C21: 木 | D21: =B21 -> 0 | G21: =F21/E21 -> #DIV/0! | I21: =H21/E21 -> #DIV/0! | L21: =F21+H21+J21 -> 0 | M21: =L21/E21 -> #DIV/0! | R21: =L21/Q21 -> #DIV/0! | Y21: =SUM(V21:X21)/3 -> 0 | AA21: 雨 | AC21: 1
A22: 金 | C22: 金 | D22: =B22 -> 0 | G22: =F22/E22 -> #DIV/0! | I22: =H22/E22 -> #DIV/0! | L22: =F22+H22+J22 -> 0 | M22: =L22/E22 -> #DIV/0! | R22: =L22/Q22 -> #DIV/0! | Y22: =SUM(V22:X22)/3 -> 0 | AA22: 豪雨・雷雨 | AC22: 0
A23: 土 | C23: 土 | D23: =B23 -> 0 | G23: =F23/E23 -> #DIV/0! | I23: =H23/E23 -> #DIV/0! | J23: 0 | L23: =F23+H23+J23 -> 0 | M23: =L23/E23 -> #DIV/0! | R23: =L23/Q23 -> #DIV/0! | Y23: =SUM(V23:X23)/3 -> 0 | AA23: ※5.6月は18時は最低気温を採用。7月〜は最高気温を採用。
A24: SUB TOTAL | C24: SUB TOTAL | E24: =SUM(E17:E23) -> 197 | F24: =SUM(F17:F23) -> 409700 | G24: =F24/E24 -> 2079.6954 | H24: =SUM(H17:H23) -> 241500 | I24: =H24/E24 -> 1225.8883 | J24: =I24/F24 -> 0.0029921609 | L24: =F24+H24 -> 651200 | M24: =L24/E24 -> 3305.5838 | Q24: =SUM(Q17:Q23) -> 0 | R24: =L24/Q24 -> #DIV/0! | S24: 1 | T24: =SUM(T17:T23)/S24 -> 10.9 | U24: =SUM(U17:U23)/S24 -> 22.5 | V24: =SUM(V17:V23)/S24 -> 4 | W24: =SUM(W17:W23)/S24 -> 2 | X24: =SUM(X17:X23)/S24 -> 2 | Y24: =SUM(V24:X24)/3 -> 2.6666667
A25: 3rd week | C25: 3rd week | T25: =C25 -> 3rd week
A26: 曜日 | B26: 日にち | C26: 曜日 | D26: 日にち | E26: 客数 | F26: 料理売上 | G26: 料理単価 | H26: 飲料売上 | I26: 飲料単価 | J26: テント利用料 | K26: 物販 | L26: 売上合計 | M26: 合計単価 | N26: サーフィンズ | O26: forking | P26: Timee | Q26: 合計 | R26: 人時売上高 | T26: 最低 | U26: 最高 | V26: 12時 | W26: 15時 | X26: 18時 | Y26: Ave | AA26: ■天候要因 | AC26: 評価点
A27: 日 | C27: 日 | D27: =B27 -> 0 | G27: =F27/E27 -> #DIV/0! | I27: =H27/E27 -> #DIV/0! | L27: =F27+H27+J27 -> 0 | M27: =L27/E27 -> #DIV/0! | R27: =L27/Q27 -> #DIV/0! | Y27: =SUM(V27:X27)/3 -> 0 | AA27: 晴れ（33度まで） | AC27: 5
A28: 月 | C28: 月 | D28: =B28 -> 0 | G28: =F28/E28 -> #DIV/0! | I28: =H28/E28 -> #DIV/0! | L28: =F28+H28+J28 -> 0 | M28: =L28/E28 -> #DIV/0! | R28: =L28/Q28 -> #DIV/0! | Y28: =SUM(V28:X28)/3 -> 0 | AA28: 晴れ（25度以下） | AC28: 4
A29: 火 | C29: 火 | D29: =B29 -> 0 | G29: =F29/E29 -> #DIV/0! | I29: =H29/E29 -> #DIV/0! | L29: =F29+H29+J29 -> 0 | M29: =L29/E29 -> #DIV/0! | R29: =L29/Q29 -> #DIV/0! | Y29: =SUM(V29:X29)/3 -> 0 | AA29: 晴れ（33度以上）曇25度以上 | AC29: 3
A30: 水 | C30: 水 | D30: =B30 -> 0 | G30: =F30/E30 -> #DIV/0! | I30: =H30/E30 -> #DIV/0! | L30: =F30+H30+J30 -> 0 | M30: =L30/E30 -> #DIV/0! | R30: =L30/Q30 -> #DIV/0! | Y30: =SUM(V30:X30)/3 -> 0 | AA30: 曇 | AC30: 2
A31: 木 | C31: 木 | D31: =B31 -> 0 | G31: =F31/E31 -> #DIV/0! | I31: =H31/E31 -> #DIV/0! | L31: =F31+H31+J31 -> 0 | M31: =L31/E31 -> #DIV/0! | R31: =L31/Q31 -> #DIV/0! | Y31: =SUM(V31:X31)/3 -> 0 | AA31: 雨 | AC31: 1
A32: 金 | C32: 金 | D32: =B32 -> 0 | G32: =F32/E32 -> #DIV/0! | I32: =H32/E32 -> #DIV/0! | L32: =F32+H32+J32 -> 0 | M32: =L32/E32 -> #DIV/0! | R32: =L32/Q32 -> #DIV/0! | Y32: =SUM(V32:X32)/3 -> 0 | AA32: 豪雨・雷雨 | AC32: 0
A33: 土 | C33: 土 | D33: =B33 -> 0 | G33: =F33/E33 -> #DIV/0! | I33: =H33/E33 -> #DIV/0! | J33: 0 | L33: =F33+H33+J33 -> 0 | M33: =L33/E33 -> #DIV/0! | R33: =L33/Q33 -> #DIV/0! | Y33: =SUM(V33:X33)/3 -> 0 | AA33: ※5.6月は18時は最低気温を採用。7月〜は最高気温を採用。
A34: SUB TOTAL | C34: SUB TOTAL | E34: =SUM(E27:E33) -> 0 | F34: =SUM(F27:F33) -> 0 | G34: =F34/E34 -> #DIV/0! | H34: =SUM(H27:H33) -> 0 | I34: =H34/E34 -> #DIV/0! | J34: =I34/F34 -> #DIV/0! | L34: =F34+H34 -> 0 | M34: =L34/E34 -> #DIV/0! | Q34: =SUM(Q27:Q33) -> 0 | R34: =L34/Q34 -> #DIV/0! | T34: =SUM(T27:T33)/S34 -> #DIV/0! | U34: =SUM(U27:U33)/S34 -> #DIV/0! | V34: =SUM(V27:V33)/S34 -> #DIV/0! | W34: =SUM(W27:W33)/S34 -> #DIV/0! | X34: =SUM(X27:X33)/S34 -> #DIV/0! | Y34: =SUM(V34:X34)/3 -> #DIV/0!
A35: 4th week | C35: 4th week | T35: =C35 -> 4th week
A36: 曜日 | B36: 日にち | C36: 曜日 | D36: 日にち | E36: 客数 | F36: 料理売上 | G36: 料理単価 | H36: 飲料売上 | I36: 飲料単価 | J36: テント利用料 | K36: 物販 | L36: 売上合計 | M36: 合計単価 | N36: サーフィンズ | O36: forking | P36: Timee | Q36: 合計 | R36: 人時売上高 | T36: 最低 | U36: 最高 | V36: 12時 | W36: 15時 | X36: 18時 | Y36: Ave | AA36: ■天候要因 | AC36: 評価点
A37: 日 | C37: 日 | D37: =B37 -> 0 | G37: =F37/E37 -> #DIV/0! | I37: =H37/E37 -> #DIV/0! | L37: =F37+H37+J37 -> 0 | M37: =L37/E37 -> #DIV/0! | R37: =L37/Q37 -> #DIV/0! | Y37: =SUM(V37:X37)/3 -> 0 | AA37: 晴れ（33度まで） | AC37: 5
A38: 月 | C38: 月 | D38: =B38 -> 0 | G38: =F38/E38 -> #DIV/0! | I38: =H38/E38 -> #DIV/0! | L38: =F38+H38+J38 -> 0 | M38: =L38/E38 -> #DIV/0! | R38: =L38/Q38 -> #DIV/0! | Y38: =SUM(V38:X38)/3 -> 0 | AA38: 晴れ（25度以下） | AC38: 4
A39: 火 | C39: 火 | D39: =B39 -> 0 | G39: =F39/E39 -> #DIV/0! | I39: =H39/E39 -> #DIV/0! | L39: =F39+H39+J39 -> 0 | M39: =L39/E39 -> #DIV/0! | R39: =L39/Q39 -> #DIV/0! | Y39: =SUM(V39:X39)/3 -> 0 | AA39: 晴れ（33度以上）曇25度以上 | AC39: 3
A40: 水 | C40: 水 | D40: =B40 -> 0 | G40: =F40/E40 -> #DIV/0! | I40: =H40/E40 -> #DIV/0! | L40: =F40+H40+J40 -> 0 | M40: =L40/E40 -> #DIV/0! | R40: =L40/Q40 -> #DIV/0! | Y40: =SUM(V40:X40)/3 -> 0 | AA40: 曇 | AC40: 2
A41: 木 | C41: 木 | D41: =B41 -> 0 | G41: =F41/E41 -> #DIV/0! | I41: =H41/E41 -> #DIV/0! | L41: =F41+H41+J41 -> 0 | M41: =L41/E41 -> #DIV/0! | R41: =L41/Q41 -> #DIV/0! | Y41: =SUM(V41:X41)/3 -> 0 | AA41: 雨 | AC41: 1
A42: 金 | C42: 金 | D42: =B42 -> 0 | G42: =F42/E42 -> #DIV/0! | I42: =H42/E42 -> #DIV/0! | L42: =F42+H42+J42 -> 0 | M42: =L42/E42 -> #DIV/0! | R42: =L42/Q42 -> #DIV/0! | Y42: =SUM(V42:X42)/3 -> 0 | AA42: 豪雨・雷雨 | AC42: 0
A43: 土 | C43: 土 | D43: =B43 -> 0 | G43: =F43/E43 -> #DIV/0! | I43: =H43/E43 -> #DIV/0! | J43: 0 | L43: =F43+H43+J43 -> 0 | M43: =L43/E43 -> #DIV/0! | R43: =L43/Q43 -> #DIV/0! | Y43: =SUM(V43:X43)/3 -> 0 | AA43: ※5.6月は18時は最低気温を採用。7月〜は最高気温を採用。
A44: SUB TOTAL | C44: SUB TOTAL | E44: =SUM(E37:E43) -> 0 | F44: =SUM(F37:F43) -> 0 | G44: =F44/E44 -> #DIV/0! | H44: =SUM(H37:H43) -> 0 | I44: =H44/E44 -> #DIV/0! | J44: =I44/F44 -> #DIV/0! | L44: =F44+H44 -> 0 | M44: =L44/E44 -> #DIV/0! | R44: =L44/Q44 -> #DIV/0! | T44: =SUM(T37:T43)/S44 -> #DIV/0! | U44: =SUM(U37:U43)/S44 -> #DIV/0! | V44: =SUM(V37:V43)/S44 -> #DIV/0! | W44: =SUM(W37:W43)/S44 -> #DIV/0! | X44: =SUM(X37:X43)/S44 -> #DIV/0! | Y44: =SUM(V44:X44)/3 -> #DIV/0!
A45: 5th week | C45: 5th week | T45: =C45 -> 5th week
A46: 曜日 | B46: 日にち | C46: 曜日 | D46: 日にち | E46: 客数 | F46: 料理売上 | G46: 料理単価 | H46: 飲料売上 | I46: 飲料単価 | J46: テント利用料 | K46: 物販 | L46: 売上合計 | M46: 合計単価 | N46: サーフィンズ | O46: forking | P46: Timee | Q46: 合計 | R46: 人時売上高 | T46: 最低 | U46: 最高 | V46: 12時 | W46: 15時 | X46: 18時 | Y46: Ave | AA46: ■天候要因 | AC46: 評価点
A47: 日 | C47: 日 | D47: =B47 -> 0 | G47: =F47/E47 -> #DIV/0! | I47: =H47/E47 -> #DIV/0! | L47: =F47+H47+J47 -> 0 | M47: =L47/E47 -> #DIV/0! | R47: =L47/Q47 -> #DIV/0! | Y47: =SUM(V47:X47)/3 -> 0 | AA47: 晴れ（33度まで） | AC47: 5
A48: 月 | C48: 月 | D48: =B48 -> 0 | G48: =F48/E48 -> #DIV/0! | I48: =H48/E48 -> #DIV/0! | L48: =F48+H48+J48 -> 0 | M48: =L48/E48 -> #DIV/0! | R48: =L48/Q48 -> #DIV/0! | Y48: =SUM(V48:X48)/3 -> 0 | AA48: 晴れ（25度以下） | AC48: 4
A49: 火 | C49: 火 | D49: =B49 -> 0 | G49: =F49/E49 -> #DIV/0! | I49: =H49/E49 -> #DIV/0! | L49: =F49+H49+J49 -> 0 | M49: =L49/E49 -> #DIV/0! | R49: =L49/Q49 -> #DIV/0! | Y49: =SUM(V49:X49)/3 -> 0 | AA49: 晴れ（33度以上）曇25度以上 | AC49: 3
A50: 水 | C50: 水 | D50: =B50 -> 0 | G50: =F50/E50 -> #DIV/0! | I50: =H50/E50 -> #DIV/0! | L50: =F50+H50+J50 -> 0 | M50: =L50/E50 -> #DIV/0! | R50: =L50/Q50 -> #DIV/0! | Y50: =SUM(V50:X50)/3 -> 0 | AA50: 曇 | AC50: 2
A51: 木 | C51: 木 | D51: =B51 -> 0 | G51: =F51/E51 -> #DIV/0! | I51: =H51/E51 -> #DIV/0! | L51: =F51+H51+J51 -> 0 | M51: =L51/E51 -> #DIV/0! | R51: =L51/Q51 -> #DIV/0! | Y51: =SUM(V51:X51)/3 -> 0 | AA51: 雨 | AC51: 1
A52: 金 | C52: 金 | D52: =B52 -> 0 | G52: =F52/E52 -> #DIV/0! | H52: 0 | I52: =H52/E52 -> #DIV/0! | L52: =F52+H52+J52 -> 0 | M52: =L52/E52 -> #DIV/0! | R52: =L52/Q52 -> #DIV/0! | Y52: =SUM(V52:X52)/3 -> 0 | AA52: 豪雨・雷雨 | AC52: 0
A53: 土 | C53: 土 | D53: =B53 -> 0 | G53: =F53/E53 -> #DIV/0! | H53: 0 | I53: =H53/E53 -> #DIV/0! | J53: 0 | L53: =F53+H53+J53 -> 0 | M53: =L53/E53 -> #DIV/0! | R53: =L53/Q53 -> #DIV/0! | Y53: =SUM(V53:X53)/3 -> 0 | AA53: ※5.6月は18時は最低気温を採用。7月〜は最高気温を採用。
A54: SUB TOTAL | C54: SUB TOTAL | E54: =SUM(E47:E53) -> 0 | F54: =SUM(F47:F53) -> 0 | G54: =F54/E54 -> #DIV/0! | H54: =SUM(H47:H53) -> 0 | I54: =H54/E54 -> #DIV/0! | J54: =I54/F54 -> #DIV/0! | L54: =F54+H54 -> 0 | M54: =L54/E54 -> #DIV/0! | R54: =L54/Q54 -> #DIV/0! | T54: =SUM(T47:T53)/S54 -> #DIV/0! | U54: =SUM(U47:U53)/S54 -> #DIV/0! | V54: =SUM(V47:V53)/S54 -> #DIV/0! | W54: =SUM(W47:W53)/S54 -> #DIV/0! | X54: =SUM(X47:X53)/S54 -> #DIV/0! | Y54: =SUM(V54:X54)/3 -> #DIV/0!
A55: 6th week | C55: 6th week | T55: =C55 -> 6th week
A56: 曜日 | B56: 日にち | C56: 曜日 | D56: 日にち | E56: 客数 | F56: 料理売上 | G56: 料理単価 | H56: 飲料売上 | I56: 飲料単価 | J56: テント利用料 | K56: 物販 | L56: 売上合計 | M56: 合計単価 | N56: サーフィンズ | O56: forking | P56: Timee | Q56: 合計 | R56: 人時売上高 | T56: 最低 | U56: 最高 | V56: 12時 | W56: 15時 | X56: 18時 | Y56: Ave | AA56: ■天候要因 | AC56: 評価点
A57: 日 | C57: 日 | D57: =B57 -> 0 | G57: =F57/E57 -> #DIV/0! | I57: =H57/E57 -> #DIV/0! | L57: =F57+H57+J57 -> 0 | M57: =L57/E57 -> #DIV/0! | R57: =L57/Q57 -> #DIV/0! | Y57: =SUM(V57:X57)/3 -> 0 | AA57: 晴れ（33度まで） | AC57: 5
A58: 月 | C58: 月 | D58: =B58 -> 0 | G58: =F58/E58 -> #DIV/0! | I58: =H58/E58 -> #DIV/0! | L58: =F58+H58+J58 -> 0 | M58: =L58/E58 -> #DIV/0! | R58: =L58/Q58 -> #DIV/0! | Y58: =SUM(V58:X58)/3 -> 0 | AA58: 晴れ（25度以下） | AC58: 4
A59: 火 | C59: 火 | D59: =B59 -> 0 | G59: =F59/E59 -> #DIV/0! | I59: =H59/E59 -> #DIV/0! | L59: =F59+H59+J59 -> 0 | M59: =L59/E59 -> #DIV/0! | R59: =L59/Q59 -> #DIV/0! | Y59: =SUM(V59:X59)/3 -> 0 | AA59: 晴れ（33度以上）曇25度以上 | AC59: 3
A60: 水 | C60: 水 | D60: =B60 -> 0 | G60: =F60/E60 -> #DIV/0! | I60: =H60/E60 -> #DIV/0! | L60: =F60+H60+J60 -> 0 | M60: =L60/E60 -> #DIV/0! | R60: =L60/Q60 -> #DIV/0! | Y60: =SUM(V60:X60)/3 -> 0 | AA60: 曇 | AC60: 2
A61: 木 | C61: 木 | D61: =B61 -> 0 | G61: =F61/E61 -> #DIV/0! | I61: =H61/E61 -> #DIV/0! | L61: =F61+H61+J61 -> 0 | M61: =L61/E61 -> #DIV/0! | R61: =L61/Q61 -> #DIV/0! | Y61: =SUM(V61:X61)/3 -> 0 | AA61: 雨 | AC61: 1
A62: 金 | C62: 金 | D62: =B62 -> 0 | G62: =F62/E62 -> #DIV/0! | H62: 0 | I62: =H62/E62 -> #DIV/0! | L62: =F62+H62+J62 -> 0 | M62: =L62/E62 -> #DIV/0! | R62: =L62/Q62 -> #DIV/0! | Y62: =SUM(V62:X62)/3 -> 0 | AA62: 豪雨・雷雨 | AC62: 0
A63: 土 | C63: 土 | D63: =B63 -> 0 | G63: =F63/E63 -> #DIV/0! | H63: 0 | I63: =H63/E63 -> #DIV/0! | J63: 0 | L63: =F63+H63+J63 -> 0 | M63: =L63/E63 -> #DIV/0! | R63: =L63/Q63 -> #DIV/0! | Y63: =SUM(V63:X63)/3 -> 0 | AA63: ※5.6月は18時は最低気温を採用。7月〜は最高気温を採用。
A64: SUB TOTAL | C64: SUB TOTAL | E64: =SUM(E57:E63) -> 0 | F64: =SUM(F57:F63) -> 0 | G64: =F64/E64 -> #DIV/0! | H64: =SUM(H57:H63) -> 0 | I64: =H64/E64 -> #DIV/0! | J64: =I64/F64 -> #DIV/0! | L64: =F64+H64 -> 0 | M64: =L64/E64 -> #DIV/0! | R64: =L64/Q64 -> #DIV/0! | T64: =SUM(T57:T63)/S64 -> #DIV/0! | U64: =SUM(U57:U63)/S64 -> #DIV/0! | V64: =SUM(V57:V63)/S64 -> #DIV/0! | W64: =SUM(W57:W63)/S64 -> #DIV/0! | X64: =SUM(X57:X63)/S64 -> #DIV/0! | Y64: =SUM(V64:X64)/3 -> #DIV/0!
A65: TOTAL | C65: TOTAL | T65: =C65 -> TOTAL
A66: 曜日 | B66: 日数 | C66: 曜日 | D66: 日にち | E66: 客数 | F66: 料理売上 | G66: 料理単価 | H66: 飲料売上 | I66: 飲料単価 | J66: テント利用料 | K66: 物販 | L66: 売上合計 | M66: 合計単価 | N66: サーフィンズ | O66: forking | P66: Timee | Q66: 合計 | R66: 人時売上高 | T66: 最低 | U66: 最高 | V66: 12時 | W66: 15時 | X66: 18時 | Y66: Ave | AA66: 2024年 9月 天候実績
A67: 日 | C67: 日 | E67: =E7+E17+E27+E37+E47+E57 -> 197 | F67: =F7+F17+F27+F37+F47+F57 -> 409700 | G67: =F67/E67 -> 2079.6954 | H67: =H7+H17+H27+H37+H47+H57 -> 241500 | I67: =H67/E67 -> 1225.8883 | L67: =L7+L17+L27+L37+L47+L57 -> 651200 | M67: =M7+M17+M27+M37+M47+M57 -> #DIV/0! | Q67: =Q7+Q17+Q27+Q37+Q47+Q57 -> 0 | R67: =L67/Q67 -> #DIV/0! | T67: =T7+T17+T27+T37+T47+T57 -> 10.9 | U67: =U7+U17+U27+U37+U47+U57 -> 22.5 | V67: =V7+V17+V37+V47+V27+V57 -> 4 | W67: =W7+W17+W37+W47+W27+W57 -> 2 | X67: =X7+X17+X37+X47+X27+X57 -> 2 | Y67: =SUM(V67:X67)/3 -> 2.6666667 | AA67: 天候状況 | AC67: ポイント | AD67: 2024日数 | AE67: 2024合計 | AF67: 比率
A68: 月 | C68: 月 | E68: =E8+E18+E28+E38+E48+E58 -> 0 | F68: =F8+F18+F28+F38+F48+F58 -> 0 | G68: =F68/E68 -> #DIV/0! | H68: =H8+H18+H28+H38+H48+H58 -> 0 | I68: =H68/E68 -> #DIV/0! | L68: =L8+L18+L28+L38+L48+L58 -> 0 | M68: =M8+M18+M28+M38+M48+M58 -> #DIV/0! | Q68: =Q8+Q18+Q28+Q38+Q48+Q58 -> 0 | R68: =L68/Q68 -> #DIV/0! | T68: =T8+T18+T28+T38+T48+T58 -> 0 | U68: =U8+U18+U28+U38+U48+U58 -> 0 | V68: =V8+V18+V38+V48+V28+V58 -> 0 | W68: =W8+W18+W38+W48+W28+W58 -> 0 | X68: =X8+X18+X38+X48+X28+X58 -> 0 | Y68: =SUM(V68:X68)/3 -> 0 | AA68: 晴れ（33度まで） | AC68: 5 | AD68: 2 | AE68: =AC68*AD68 -> 10 | AF68: =(AD68+AD69+AD70)/AD74 -> 0.38888889
A69: 火 | C69: 火 | E69: =E9+E19+E29+E39+E49+E59 -> 66 | F69: =F9+F19+F29+F39+F49+F59 -> 125600 | G69: =F69/E69 -> 1903.0303 | H69: =H9+H19+H29+H39+H49+H59 -> 67050 | I69: =H69/E69 -> 1015.9091 | L69: =L9+L19+L29+L39+L49+L59 -> 192650 | M69: =M9+M19+M29+M39+M49+M59 -> #DIV/0! | Q69: =Q9+Q19+Q29+Q39+Q49+Q59 -> 0 | R69: =L69/Q69 -> #DIV/0! | T69: =T9+T19+T29+T39+T49+T59 -> 15.1 | U69: =U9+U19+U29+U39+U49+U59 -> 26.3 | V69: =V9+V19+V39+V49+V29+V59 -> 5 | W69: =W9+W19+W39+W49+W29+W59 -> 5 | X69: =X9+X19+X39+X49+X29+X59 -> 4 | Y69: =SUM(V69:X69)/3 -> 4.6666667 | AA69: 晴れ（25度以下） | AC69: 4 | AD69: 5 | AE69: =AC69*AD69 -> 20
A70: 水 | C70: 水 | E70: =E10+E20+E30+E40+E50+E60 -> 30 | F70: =F10+F20+F30+F40+F50+F60 -> 78300 | G70: =F70/E70 -> 2610 | H70: =H10+H20+H30+H40+H50+H60 -> 42700 | I70: =H70/E70 -> 1423.3333 | L70: =L10+L20+L30+L40+L50+L60 -> 121000 | M70: =M10+M20+M30+M40+M50+M60 -> #DIV/0! | Q70: =Q10+Q20+Q30+Q40+Q50+Q60 -> 0 | R70: =L70/Q70 -> #DIV/0! | T70: =T10+T20+T30+T40+T50+T60 -> 18.2 | U70: =U10+U20+U30+U40+U50+U60 -> 22 | V70: =V10+V20+V40+V50+V30+V60 -> 2 | W70: =W10+W20+W40+W50+W30+W60 -> 1 | X70: =X10+X20+X40+X50+X30+X60 -> 2 | Y70: =SUM(V70:X70)/3 -> 1.6666667 | AA70: 晴れ（33度以上15以下） 曇25度以上 | AC70: 3 | AD70: 0 | AE70: =AC70*AD70 -> 0
A71: 木 | C71: 木 | E71: =E21+E11+E31+E41+E51+E61 -> 44 | F71: =F21+F11+F31+F41+F51+F61 -> 72200 | G71: =F71/E71 -> 1640.9091 | H71: =H21+H11+H31+H41+H51+H61 -> 44400 | I71: =H71/E71 -> 1009.0909 | L71: =L21+L11+L31+L41+L51+L61 -> 116600 | M71: =M21+M11+M31+M41+M51+M61 -> #DIV/0! | Q71: =Q21+Q11+Q31+Q41+Q51+Q61 -> 0 | R71: =L71/Q71 -> #DIV/0! | T71: =T11+T21+T31+T41+T51+T61 -> 12.1 | U71: =U11+U21+U31+U41+U51+U61 -> 16.8 | V71: =V11+V21+V41+V51+V31+V61 -> 2 | W71: =W11+W21+W41+W51+W31+W61 -> 2 | X71: =X11+X21+X41+X51+X31+X61 -> 2 | Y71: =SUM(V71:X71)/3 -> 2 | AA71: 曇 | AC71: 2 | AD71: 8 | AE71: =AC71*AD71 -> 16 | AF71: =(AD71+AD72+AD73)/AD74 -> 0.61111111
A72: 金 | C72: 金 | E72: =E12+E22+E32+E42+E52+E62 -> 20 | F72: =F12+F22+F32+F42+F52+F62 -> 38750 | G72: =F72/E72 -> 1937.5 | H72: =H12+H22+H32+H42+H52+H62 -> 31350 | I72: =H72/E72 -> 1567.5 | L72: =L12+L22+L32+L42+L52+L62 -> 70100 | M72: =M12+M22+M32+M42+M52+M62 -> #DIV/0! | Q72: =Q12+Q22+Q32+Q42+Q52+Q62 -> 0 | R72: =L72/Q72 -> #DIV/0! | T72: =T12+T22+T32+T42+T52+T62 -> 12 | U72: =U12+U22+U32+U42+U52+U62 -> 15.2 | V72: =V12+V22+V42+V52+V32+V62 -> 2 | W72: =W12+W22+W42+W52+W32+W62 -> 1 | X72: =X12+X22+X42+X52+X32+X62 -> 1 | Y72: =SUM(V72:X72)/3 -> 1.3333333 | AA72: 雨 | AC72: 1 | AD72: 3 | AE72: =AC72*AD72 -> 3
A73: 土 | C73: 土 | E73: =E13+E23+E33+E43+E53+E63 -> 181 | F73: =F13+F23+F33+F43+F53+F63 -> 287100 | G73: =F73/E73 -> 1586.1878 | H73: =H13+H23+H33+H43+H53+H63 -> 161100 | I73: =H73/E73 -> 890.05525 | L73: =L13+L23+L33+L43+L53+L63 -> 448200 | M73: =M13+M23+M33+M43+M53+M63 -> #DIV/0! | Q73: =Q13+Q23+Q33+Q43+Q53+Q63 -> 0 | R73: =L73/Q73 -> #DIV/0! | S73: =S14+S24 -> 6 | T73: =T13+T23+T33+T43+T53+T63 -> 14.1 | U73: =U13+U23+U33+U43+U53+U63 -> 21.3 | V73: =V13+V23+V43+V53+V33+V63 -> 4 | W73: =W13+W23+W43+W53+W33+W63 -> 4 | X73: =X13+X23+X43+X53+X33+X63 -> 4 | Y73: =SUM(V73:X73)/3 -> 4 | AA73: 豪雨・雷雨 | AC73: 0 | AE73: =AC73*AD73 -> 0
A74: TOTAL | B74: =SUM(B67:B73) -> 0 | C74: TOTAL | D74: =SUM(D67:D73) -> 0 | E74: =SUM(E67:E73) -> 538 | F74: =SUM(F67:F73) -> 1011650 | G74: =F74/E74 -> 1880.3903 | H74: =SUM(H67:H73) -> 588100 | I74: =H74/E74 -> 1093.1227 | L74: =SUM(L67:L73) -> 1599750 | M74: =L74/E74 -> 2973.513 | Q74: =SUM(Q67:Q73) -> 0 | R74: =L74/Q74 -> #DIV/0! | T74: =SUM(T67:T73)/S73 -> 13.733333 | U74: =SUM(U67:U73)/S73 -> 20.683333 | V74: =SUM(V67:V73)/S73 -> 3.1666667 | W74: =SUM(W67:W73)/S73 -> 2.5 | X74: =SUM(X67:X73)/S73 -> 2.5 | Y74: =SUM(V74:X74)/3 -> 2.7222222 | AA74: TOTAL | AD74: =SUM(AD68:AD73) -> 18 | AE74: =SUM(AE68:AE73) -> 49 | AF74: =AF68+AF71 -> 1
A75: ■対比 | C75: ■対比
A77: ランチ | C77: ランチ | E77: 予算
E78: ランチ
E79: 客数 | H79: F売上 | L79: B売上
H80: =#REF!*E80 -> #REF! | L80: =#REF!*E80 -> #REF!
E82: ■予算差異
E83: 客数 | H83: F売上 | L83: B売上
E84: =E74-E80 -> 538 | H84: =H74-H80 -> #REF! | L84: =L74-L80 -> #REF!
E85: =E74/E80 -> #DIV/0! | H85: =H74/H80 -> #REF! | L85: =L74/L80 -> #REF!
E86: ■前年値（数値残っていない休業）
E87: 客数 | H87: F売上 | L87: B売上
E89: ■前年差異
E90: 客数 | H90: F売上 | L90: B売上
E91: =E74-E88 -> 538 | H91: =H74-H88 -> 588100 | L91: =L74-L88 -> 1599750
E92: =E74/E88 -> #DIV/0! | H92: =H74/H88 -> #DIV/0! | L92: =L74/L88 -> #DIV/0!
A93: 構成比率 | J93: 税抜売上 | L93: =L74/1.1 -> 1454318.2 | M93: 対予測達成率 | Q93: =L93/#REF! -> #REF! | R93: =L93-#REF! -> #REF! | AB93: =L93/AP93 -> 0.076343255 | AD93: =AE74/AD74 -> 2.7222222 | AP93: 19049727
J94: =J74/1.1 -> 0 | M94: 合計予算進捗 | Q94: ウチその他対比
H95: 売上合計予算対比 | M95: =L93/#REF! -> #REF! | Q95: =J94/#REF! -> #REF! | R95: =L93-#REF! -> #REF!
A98: ■モデルシフト
A99: モデルシフト カテゴリー
A100: TOP1
A101: TOP2
A102: ON1
A103: ON2
A104: ショルダー
A105: OFF1
...

Sheet 2024.9月実績
A1: ■R6年度 ピコレ＆ビアガーデン売上実績
A2: 9月 | L2: =L14+L24+L34+L44+L54+L64 -> #DIV/0! | R2: 10
A3: FOOD | C3: ビアガーデン9月 実績TOTAL | N3: 客数 | R3: 売上
A4: 予算 | C4: 実績 | E4: 客数 | G4: 客単価 | I4: 売上予算 | L4: 9275000 | M4: 1日平均 | R4: =L4/R2 -> 927500 | T4: 天候要因（売上との関連性を数値化する） | AH4: 天候要因（売上との関連性を数値化する）
A5: 1st week | C5: 1st week | T5: =C5 -> 1st week | AH5: =U5 -> 0
A6: 曜日 | B6: 日にち | C6: 曜日 | D6: 日にち | E6: 客数 | F6: 料理売上 | G6: 料理単価 | H6: 飲料売上 | I6: 飲料単価 | J6: テント利用料 | K6: 物販 | L6: 売上合計 | M6: 合計単価 | N6: サーフィンズ | O6: forking | P6: Timee | Q6: 合計 | R6: 人時売上高 | T6: 最低 | U6: 最高 | V6: 12時 | W6: 15時 | X6: 18時 | Y6: Ave | AA6: ■天候要因 | AC6: 評価点 | AH6: 最低 | AI6: 最高 | AJ6: 12時 | AK6: 15時 | AL6: 18時 | AM6: Ave | AO6: ■天候要因 | AQ6: 評価点
A7: 日 | B7: 1 | C7: 日 | D7: =B7 -> 1 | E7: 468 | F7: 1213450 | G7: =F7/E7 -> 2592.8419 | H7: 629350 | I7: =H7/E7 -> 1344.765 | J7: 10010 | L7: =F7+H7+J7+K7 -> 1852810 | M7: =L7/E7 -> 3958.9957 | R7: =L7/Q7 -> #DIV/0! | T7: 18.3 | U7: 29 | V7: 5 | W7: 5 | X7: 3 | Y7: =SUM(V7:X7)/3 -> 4.3333333 | AA7: 晴れ（33度まで） | AC7: 5 | AH7: 24.9 | AI7: 27 | AJ7: 3 | AK7: 1 | AL7: 1 | AM7: =SUM(AJ7:AL7)/3 -> 1.6666667 | AO7: 晴れ（33度まで） | AQ7: 5
A8: 月 | B8: 2 | C8: 月 | D8: =B8 -> 2 | E8: 92 | F8: 253250 | G8: =F8/E8 -> 2752.7174 | H8: 134900 | I8: =H8/E8 -> 1466.3043 | J8: 4400 | L8: =F8+H8+J8+K8 -> 392550 | M8: =L8/E8 -> 4266.8478 | R8: =L8/Q8 -> #DIV/0! | T8: 18.8 | U8: 27 | V8: 3 | W8: 3 | X8: 1 | Y8: =SUM(V8:X8)/3 -> 2.3333333 | AA8: 晴れ（25度以下） | AC8: 4 | AH8: 20.7 | AI8: 29.1 | AJ8: 5 | AK8: 1 | AL8: 5 | AM8: =SUM(AJ8:AL8)/3 -> 3.6666667 | AO8: 晴れ（25度以下） | AQ8: 4
A9: 火 | B9: 3 | C9: 火 | D9: =B9 -> 3 | E9: 194 | F9: 576050 | G9: =F9/E9 -> 2969.3299 | H9: 326000 | I9: =H9/E9 -> 1680.4124 | J9: 2310 | L9: =F9+H9+J9+K9 -> 904360 | M9: =L9/E9 -> 4661.6495 | R9: =L9/Q9 -> #DIV/0! | T9: 18.2 | U9: 27.8 | V9: 5 | W9: 5 | X9: 5 | Y9: =SUM(V9:X9)/3 -> 5 | AA9: 晴れ（33度以上）曇25度以上 | AC9: 3 | AH9: 18.6 | AI9: 29.8 | AJ9: 5 | AK9: 5 | AL9: 5 | AM9: =SUM(AJ9:AL9)/3 -> 5 | AO9: 晴れ（33度以上）曇25度以上 | AQ9: 3
A10: 水 | B10: 4 | C10: 水 | D10: =B10 -> 4 | E10: 269 | F10: 809510 | G10: =F10/E10 -> 3009.3309 | H10: 441600 | I10: =H10/E10 -> 1641.6357 | J10: 19250 | K10: 2970 | L10: =F10+H10+J10+K10 -> 1273330 | M10: =L10/E10 -> 4733.5688 | R10: =L10/Q10 -> #DIV/0! | T10: 16.8 | U10: 28.6 | V10: 5 | W10: 5 | X10: 5 | Y10: =SUM(V10:X10)/3 -> 5 | AA10: 曇 | AC10: 2 | AM10: =SUM(AJ10:AL10)/3 -> 0 | AO10: 曇 | AQ10: 2
A11: 木 | B11: 5 | C11: 木 | D11: =B11 -> 5 | E11: 186 | F11: 488650 | G11: =F11/E11 -> 2627.1505 | H11: 291050 | I11: =H11/E11 -> 1564.7849 | J11: 10450 | L11: =F11+H11+J11+K11 -> 790150 | M11: =L11/E11 -> 4248.1183 | R11: =L11/Q11 -> #DIV/0! | T11: 20.4 | U11: 27.6 | V11: 3 | W11: 3 | X11: 3 | Y11: =SUM(V11:X11)/3 -> 3 | AA11: 雨 | AC11: 1 | AM11: =SUM(AJ11:AL11)/3 -> 0 | AO11: 雨 | AQ11: 1
A12: 金 | B12: 6 | C12: 金 | D12: =B12 -> 6 | E12: 325 | F12: 781000 | G12: =F12/E12 -> 2403.0769 | H12: 432250 | I12: =H12/E12 -> 1330 | J12: 6380 | L12: =F12+H12+J12+K12 -> 1219630 | M12: =L12/E12 -> 3752.7077 | R12: =L12/Q12 -> #DIV/0! | T12: 19.6 | U12: 25.9 | V12: 5 | W12: 5 | X12: 3 | Y12: =SUM(V12:X12)/3 -> 4.3333333 | AA12: 豪雨・雷雨 | AC12: 0 | AM12: =SUM(AJ12:AL12)/3 -> 0 | AO12: 豪雨・雷雨 | AQ12: 0
A13: 土 | B13: 7 | C13: 土 | D13: =B13 -> 7 | E13: 452 | F13: 1366800 | G13: =F13/E13 -> 3023.8938 | H13: 704550 | I13: =H13/E13 -> 1558.7389 | J13: 40920 | L13: =F13+H13+J13+K13 -> 2112270 | M13: =L13/E13 -> 4673.1637 | R13: =L13/Q13 -> #DIV/0! | T13: 15.8 | U13: 26.7 | V13: 5 | W13: 5 | X13: 3 | Y13: =SUM(V13:X13)/3 -> 4.3333333 | AA13: ※5.6月は18時は最低気温を採用。7月〜は最高気温を採用。 | AM13: =SUM(AJ13:AL13)/3 -> 0 | AO13: ※5.6月は18時は最低気温を採用。7月〜は最高気温を採用。
A14: SUB TOTAL | C14: SUB TOTAL | E14: =SUM(E7:E13) -> 1986 | F14: =SUM(F7:F13) -> 5488710 | G14: =F14/E14 -> 2763.7009 | H14: =SUM(H7:H13) -> 2959700 | I14: =H14/E14 -> 1490.282 | J14: =SUM(J7:J13) -> 93720 | K14: =SUM(K7:K13) -> 2970 | L14: =F14+H14+J14+K14 -> 8545100 | M14: =L14/E14 -> 4302.6687 | Q14: =SUM(Q7:Q13) -> 0 | R14: =L14/Q14 -> #DIV/0! | S14: 7 | T14: =SUM(T7:T13)/S14 -> 18.271429 | U14: =SUM(U7:U13)/S14 -> 27.514286 | V14: =SUM(V7:V13)/S14 -> 4.4285714 | W14: =SUM(W7:W13)/S14 -> 4.4285714 | X14: =SUM(X7:X13)/S14 -> 3.2857143 | Y14: =SUM(V14:X14)/3 -> 4.047619 | Z14: 15 | AA14: =L14/S14 -> 1220728.6 | AF14: ※1日平均売上 | AG14: 3 | AH14: =SUM(AH7:AH13)/AG14 -> 21.4 | AI14: =SUM(AI7:AI13)/AG14 -> 28.633333 | AJ14: =SUM(AJ7:AJ13)/AG14 -> 4.3333333 | AK14: =SUM(AK7:AK13)/AG14 -> 2.3333333 | AL14: =SUM(AL7:AL13)/AG14 -> 3.6666667 | AM14: =SUM(AJ14:AL14)/3 -> 3.4444444 | AN14: 15 | AO14: 1462533
A15: 2nd week | C15: 2nd week | T15: =C15 -> 2nd week | AH15: =U15 -> 0
A16: 曜日 | B16: 日にち | C16: 曜日 | D16: 日にち | E16: 客数 | F16: 料理売上 | G16: 料理単価 | H16: 飲料売上 | I16: 飲料単価 | J16: テント利用料 | K16: 物販 | L16: 売上合計 | M16: 合計単価 | N16: サーフィンズ | O16: forking | P16: Timee | Q16: 合計 | R16: 人時売上高 | T16: 最低 | U16: 最高 | V16: 12時 | W16: 15時 | X16: 18時 | Y16: Ave | AA16: ■天候要因 | AC16: 評価点 | AH16: 最低 | AI16: 最高 | AJ16: 12時 | AK16: 15時 | AL16: 18時 | AM16: Ave | AO16: ■天候要因 | AQ16: 評価点
A17: 日 | B17: 8 | C17: 日 | D17: =B17 -> 8 | E17: 279 | F17: 722650 | G17: =F17/E17 -> 2590.1434 | H17: 419000 | I17: =H17/E17 -> 1501.7921 | J17: 17050 | L17: =F17+H17+J17+K17 -> 1158700 | M17: =L17/E17 -> 4153.0466 | R17: =L17/Q17 -> #DIV/0! | T17: 17.2 | U17: 31.5 | V17: 5 | W17: 5 | X17: 5 | Y17: =SUM(V17:X17)/3 -> 5 | AA17: 晴れ（33度まで） | AC17: 5 | AM17: =SUM(AJ17:AL17)/3 -> 0 | AO17: 晴れ（33度まで） | AQ17: 5
A18: 月 | B18: 9 | C18: 月 | D18: =B18 -> 9 | G18: =F18/E18 -> #DIV/0! | I18: =H18/E18 -> #DIV/0! | L18: =F18+H18+J18+K18 -> 0 | M18: =L18/E18 -> #DIV/0! | R18: =L18/Q18 -> #DIV/0! | Y18: =SUM(V18:X18)/3 -> 0 | AA18: 晴れ（25度以下） | AC18: 4 | AM18: =SUM(AJ18:AL18)/3 -> 0 | AO18: 晴れ（25度以下） | AQ18: 4
A19: 火 | B19: 10 | C19: 火 | D19: =B19 -> 10 | G19: =F19/E19 -> #DIV/0! | I19: =H19/E19 -> #DIV/0! | L19: =F19+H19+J19+K19 -> 0 | M19: =L19/E19 -> #DIV/0! | R19: =L19/Q19 -> #DIV/0! | Y19: =SUM(V19:X19)/3 -> 0 | AA19: 晴れ（33度以上）曇25度以上 | AC19: 3 | AM19: =SUM(AJ19:AL19)/3 -> 0 | AO19: 晴れ（33度以上）曇25度以上 | AQ19: 3
A20: 水 | B20: 11 | C20: 水 | D20: =B20 -> 11 | G20: =F20/E20 -> #DIV/0! | I20: =H20/E20 -> #DIV/0! | L20: =F20+H20+J20+K20 -> 0 | M20: =L20/E20 -> #DIV/0! | R20: =L20/Q20 -> #DIV/0! | Y20: =SUM(V20:X20)/3 -> 0 | AA20: 曇 | AC20: 2 | AM20: =SUM(AJ20:AL20)/3 -> 0 | AO20: 曇 | AQ20: 2
A21: 木 | B21: 12 | C21: 木 | D21: =B21 -> 12 | G21: =F21/E21 -> #DIV/0! | I21: =H21/E21 -> #DIV/0! | L21: =F21+H21+J21+K21 -> 0 | M21: =L21/E21 -> #DIV/0! | R21: =L21/Q21 -> #DIV/0! | Y21: =SUM(V21:X21)/3 -> 0 | AA21: 雨 | AC21: 1 | AM21: =SUM(AJ21:AL21)/3 -> 0 | AO21: 雨 | AQ21: 1
A22: 金 | B22: 13 | C22: 金 | D22: =B22 -> 13 | G22: =F22/E22 -> #DIV/0! | I22: =H22/E22 -> #DIV/0! | L22: =F22+H22+J22+K22 -> 0 | M22: =L22/E22 -> #DIV/0! | R22: =L22/Q22 -> #DIV/0! | Y22: =SUM(V22:X22)/3 -> 0 | AA22: 豪雨・雷雨 | AC22: 0 | AM22: =SUM(AJ22:AL22)/3 -> 0 | AO22: 豪雨・雷雨 | AQ22: 0
A23: 土 | B23: 14 | C23: 土 | D23: =B23 -> 14 | E23: 144 | F23: 336600 | G23: =F23/E23 -> 2337.5 | H23: 170600 | I23: =H23/E23 -> 1184.7222 | J23: 3080 | L23: =F23+H23+J23+K23 -> 510280 | M23: =L23/E23 -> 3543.6111 | R23: =L23/Q23 -> #DIV/0! | T23: 13.4 | U23: 23.7 | V23: 4 | W23: 4 | X23: 2 | Y23: =SUM(V23:X23)/3 -> 3.3333333 | AA23: ※5.6月は18時は最低気温を採用。7月〜は最高気温を採用。 | AM23: =SUM(AJ23:AL23)/3 -> 0 | AO23: ※5.6月は18時は最低気温を採用。7月〜は最高気温を採用。
A24: SUB TOTAL | C24: SUB TOTAL | E24: =SUM(E17:E23) -> 423 | F24: =SUM(F17:F23) -> 1059250 | G24: =F24/E24 -> 2504.1371 | H24: =SUM(H17:H23) -> 589600 | I24: =H24/E24 -> 1393.8534 | J24: =SUM(J17:J23) -> 20130 | K24: =SUM(K17:K23) -> 0 | L24: =F24+H24+J24+K24 -> 1668980 | M24: =L24/E24 -> 3945.5792 | Q24: =SUM(Q17:Q23) -> 0 | R24: =L24/Q24 -> #DIV/0! | S24: 2 | T24: =SUM(T17:T23)/S24 -> 15.3 | U24: =SUM(U17:U23)/S24 -> 27.6 | V24: =SUM(V17:V23)/S24 -> 4.5 | W24: =SUM(W17:W23)/S24 -> 4.5 | X24: =SUM(X17:X23)/S24 -> 3.5 | Y24: =SUM(V24:X24)/3 -> 4.1666667 | Z24: 16 | AA24: =L24/S24 -> 834490 | AH24: =SUM(AH17:AH23)/AG24 -> #DIV/0! | AI24: =SUM(AI17:AI23)/AG24 -> #DIV/0! | AJ24: =SUM(AJ17:AJ23)/AG24 -> #DIV/0! | AK24: =SUM(AK17:AK23)/AG24 -> #DIV/0! | AL24: =SUM(AL17:AL23)/AG24 -> #DIV/0! | AM24: =SUM(AJ24:AL24)/3 -> #DIV/0!
A25: 3rd week | C25: 3rd week | T25: =C25 -> 3rd week | AH25: =U25 -> 0
A26: 曜日 | B26: 日にち | C26: 曜日 | D26: 日にち | E26: 客数 | F26: 料理売上 | G26: 料理単価 | H26: 飲料売上 | I26: 飲料単価 | J26: テント利用料 | K26: 物販 | L26: 売上合計 | M26: 合計単価 | N26: サーフィンズ | O26: forking | P26: Timee | Q26: 合計 | R26: 人時売上高 | T26: 最低 | U26: 最高 | V26: 12時 | W26: 15時 | X26: 18時 | Y26: Ave | AA26: ■天候要因 | AC26: 評価点 | AH26: 最低 | AI26: 最高 | AJ26: 12時 | AK26: 15時 | AL26: 18時 | AM26: Ave | AO26: ■天候要因 | AQ26: 評価点
A27: 日 | B27: 15 | C27: 日 | D27: =B27 -> 15 | E27: 57 | F27: 123650 | G27: =F27/E27 -> 2169.2982 | H27: 26050 | I27: =H27/E27 -> 457.01754 | L27: =F27+H27+J27+K27 -> 149700 | M27: =L27/E27 -> 2626.3158 | R27: =L27/Q27 -> #DIV/0! | T27: 16.6 | U27: 19.3 | V27: 1 | W27: 2 | X27: 4 | Y27: =SUM(V27:X27)/3 -> 2.3333333 | AA27: 晴れ（33度まで） | AC27: 5 | AM27: =SUM(AJ27:AL27)/3 -> 0 | AO27: 晴れ（33度まで） | AQ27: 5
A28: 月 | B28: 16 | C28: 月 | D28: =B28 -> 16 | E28: 89 | F28: 188750 | G28: =F28/E28 -> 2120.7865 | H28: 103150 | I28: =H28/E28 -> 1158.9888 | J28: 1100 | L28: =F28+H28+J28+K28 -> 293000 | M28: =L28/E28 -> 3292.1348 | R28: =L28/Q28 -> #DIV/0! | T28: 12 | U28: 23.6 | V28: 4 | W28: 2 | X28: 2 | Y28: =SUM(V28:X28)/3 -> 2.6666667 | AA28: 晴れ（25度以下） | AC28: 4 | AM28: =SUM(AJ28:AL28)/3 -> 0 | AO28: 晴れ（25度以下） | AQ28: 4
A29: 火 | B29: 17 | C29: 火 | D29: =B29 -> 17 | E29: 25 | F29: 68450 | G29: =F29/E29 -> 2738 | H29: 41450 | I29: =H29/E29 -> 1658 | L29: =F29+H29+J29+K29 -> 109900 | M29: =L29/E29 -> 4396 | R29: =L29/Q29 -> #DIV/0! | T29: 18.2 | U29: 24.7 | V29: 4 | W29: 2 | X29: 4 | Y29: =SUM(V29:X29)/3 -> 3.3333333 | AA29: 晴れ（33度以上）曇25度以上 | AC29: 3 | AM29: =SUM(AJ29:AL29)/3 -> 0 | AO29: 晴れ（33度以上）曇25度以上 | AQ29: 3
A30: 水 | B30: 18 | C30: 水 | D30: =B30 -> 18 | E30: 87 | F30: 191400 | G30: =F30/E30 -> 2200 | H30: 107450 | I30: =H30/E30 -> 1235.0575 | L30: =F30+H30+J30+K30 -> 298850 | M30: =L30/E30 -> 3435.0575 | R30: =L30/Q30 -> #DIV/0! | T30: 16.9 | U30: 25 | V30: 5 | W30: 2 | X30: 4 | Y30: =SUM(V30:X30)/3 -> 3.6666667 | AA30: 曇 | AC30: 2 | AM30: =SUM(AJ30:AL30)/3 -> 0 | AO30: 曇 | AQ30: 2
A31: 木 | B31: 19 | C31: 木 | D31: =B31 -> 19 | E31: 39 | F31: 43350 | G31: =F31/E31 -> 1111.5385 | H31: 47450 | I31: =H31/E31 -> 1216.6667 | L31: =F31+H31+J31+K31 -> 90800 | M31: =L31/E31 -> 2328.2051 | R31: =L31/Q31 -> #DIV/0! | T31: 14 | U31: 23.7 | V31: 4 | W31: 4 | X31: 4 | Y31: =SUM(V31:X31)/3 -> 4 | AA31: 雨 | AC31: 1 | AM31: =SUM(AJ31:AL31)/3 -> 0 | AO31: 雨 | AQ31: 1
A32: 金 | B32: 20 | C32: 金 | D32: =B32 -> 20 | E32: 54 | F32: 135400 | G32: =F32/E32 -> 2507.4074 | H32: 73100 | I32: =H32/E32 -> 1353.7037 | L32: =F32+H32+J32+K32 -> 208500 | M32: =L32/E32 -> 3861.1111 | R32: =L32/Q32 -> #DIV/0! | T32: 16.3 | U32: 23 | V32: 1 | W32: 1 | X32: 2 | Y32: =SUM(V32:X32)/3 -> 1.3333333 | AA32: 豪雨・雷雨 | AC32: 0 | AM32: =SUM(AJ32:AL32)/3 -> 0 | AO32: 豪雨・雷雨 | AQ32: 0
A33: 土 | B33: 21 | C33: 土 | D33: =B33 -> 21 | E33: 67 | F33: 171700 | G33: =F33/E33 -> 2562.6866 | H33: 94700 | I33: =H33/E33 -> 1413.4328 | J33: 13860 | L33: =F33+H33+J33+K33 -> 280260 | M33: =L33/E33 -> 4182.9851 | R33: =L33/Q33 -> #DIV/0! | T33: 13.4 | U33: 17.2 | V33: 2 | W33: 2 | X33: 2 | Y33: =SUM(V33:X33)/3 -> 2 | AA33: ※5.6月は18時は最低気温を採用。7月〜は最高気温を採用。 | AM33: =SUM(AJ33:AL33)/3 -> 0 | AO33: ※5.6月は18時は最低気温を採用。7月〜は最高気温を採用。
A34: SUB TOTAL | C34: SUB TOTAL | E34: =SUM(E27:E33) -> 418 | F34: =SUM(F27:F33) -> 922700 | G34: =F34/E34 -> 2207.4163 | H34: =SUM(H27:H33) -> 493350 | I34: =H34/E34 -> 1180.2632 | J34: =I34/F34 -> 0.0012791407 | K34: =SUM(K27:K33) -> 0 | L34: =F34+H34+J34+K34 -> 1416050 | M34: =L34/E34 -> 3387.6794 | Q34: =SUM(Q27:Q33) -> 0 | R34: =L34/Q34 -> #DIV/0! | S34: 7 | T34: =SUM(T27:T33)/S34 -> 15.342857 | U34: =SUM(U27:U33)/S34 -> 22.357143 | V34: =SUM(V27:V33)/S34 -> 3 | W34: =SUM(W27:W33)/S34 -> 2.1428571 | X34: =SUM(X27:X33)/S34 -> 3.1428571 | Y34: =SUM(V34:X34)/3 -> 2.7619048 | Z34: 17 | AA34: =L34/S34 -> 202292.86 | AH34: =SUM(AH27:AH33)/AG34 -> #DIV/0! | AI34: =SUM(AI27:AI33)/AG34 -> #DIV/0! | AJ34: =SUM(AJ27:AJ33)/AG34 -> #DIV/0! | AK34: =SUM(AK27:AK33)/AG34 -> #DIV/0! | AL34: =SUM(AL27:AL33)/AG34 -> #DIV/0! | AM34: =SUM(AJ34:AL34)/3 -> #DIV/0!
A35: 4th week | C35: 4th week | T35: =C35 -> 4th week | AH35: =U35 -> 0
A36: 曜日 | B36: 日にち | C36: 曜日 | D36: 日にち | E36: 客数 | F36: 料理売上 | G36: 料理単価 | H36: 飲料売上 | I36: 飲料単価 | J36: テント利用料 | K36: 物販 | L36: 売上合計 | M36: 合計単価 | N36: サーフィンズ | O36: forking | P36: Timee | Q36: 合計 | R36: 人時売上高 | T36: 最低 | U36: 最高 | V36: 12時 | W36: 15時 | X36: 18時 | Y36: Ave | AA36: ■天候要因 | AC36: 評価点 | AH36: 最低 | AI36: 最高 | AJ36: 12時 | AK36: 15時 | AL36: 18時 | AM36: Ave | AO36: ■天候要因 | AQ36: 評価点
A37: 日 | B37: 22 | C37: 日 | D37: =B37 -> 22 | E37: 95 | F37: 216250 | G37: =F37/E37 -> 2276.3158 | H37: 128300 | I37: =H37/E37 -> 1350.5263 | J37: 2310 | L37: =F37+H37+J37+K37 -> 346860 | M37: =L37/E37 -> 3651.1579 | R37: =L37/Q37 -> #DIV/0! | T37: 11.2 | U37: 17.3 | V37: 2 | W37: 2 | X37: 2 | Y37: =SUM(V37:X37)/3 -> 2 | AA37: 晴れ（33度まで） | AC37: 5 | AM37: =SUM(AJ37:AL37)/3 -> 0 | AO37: 晴れ（33度まで） | AQ37: 5
A38: 月 | B38: 23 | C38: 月 | D38: =B38 -> 23 | E38: 109 | F38: 183400 | G38: =F38/E38 -> 1682.5688 | H38: 124550 | I38: =H38/E38 -> 1142.6606 | L38: =F38+H38+J38+K38 -> 307950 | M38: =L38/E38 -> 2825.2294 | R38: =L38/Q38 -> #DIV/0! | T38: 10 | U38: 19.8 | V38: 4 | W38: 4 | X38: 4 | Y38: =SUM(V38:X38)/3 -> 4 | AA38: 晴れ（25度以下） | AC38: 4 | AM38: =SUM(AJ38:AL38)/3 -> 0 | AO38: 晴れ（25度以下） | AQ38: 4
A39: 火 | B39: 24 | C39: 火 | D39: =B39 -> 24 | E39: 45 | F39: 75400 | G39: =F39/E39 -> 1675.5556 | H39: 40000 | I39: =H39/E39 -> 888.88889 | L39: =F39+H39+J39+K39 -> 115400 | M39: =L39/E39 -> 2564.4444 | R39: =L39/Q39 -> #DIV/0! | T39: 10.1 | U39: 22.2 | V39: 4 | W39: 4 | X39: 4 | Y39: =SUM(V39:X39)/3 -> 4 | AA39: 晴れ（33度以上）曇25度以上 | AC39: 3 | AM39: =SUM(AJ39:AL39)/3 -> 0 | AO39: 晴れ（33度以上）曇25度以上 | AQ39: 3
A40: 水 | B40: 25 | C40: 水 | D40: =B40 -> 25 | E40: 40 | F40: 83000 | G40: =F40/E40 -> 2075 | H40: 52400 | I40: =H40/E40 -> 1310 | L40: =F40+H40+J40+K40 -> 135400 | M40: =L40/E40 -> 3385 | R40: =L40/Q40 -> #DIV/0! | T40: 13.6 | U40: 21 | V40: 4 | W40: 4 | X40: 2 | Y40: =SUM(V40:X40)/3 -> 3.3333333 | AA40: 曇 | AC40: 2 | AM40: =SUM(AJ40:AL40)/3 -> 0 | AO40: 曇 | AQ40: 2
A41: 木 | B41: 26 | C41: 木 | D41: =B41 -> 26 | E41: 49 | F41: 106650 | G41: =F41/E41 -> 2176.5306 | H41: 57100 | I41: =H41/E41 -> 1165.3061 | L41: =F41+H41+J41+K41 -> 163750 | M41: =L41/E41 -> 3341.8367 | R41: =L41/Q41 -> #DIV/0! | T41: 17.3 | U41: 24.4 | V41: 4 | W41: 4 | X41: 4 | Y41: =SUM(V41:X41)/3 -> 4 | AA41: 雨 | AC41: 1 | AM41: =SUM(AJ41:AL41)/3 -> 0 | AO41: 雨 | AQ41: 1
A42: 金 | B42: 27 | C42: 金 | D42: =B42 -> 27 | E42: 93 | F42: 161650 | G42: =F42/E42 -> 1738.172 | H42: 93900 | I42: =H42/E42 -> 1009.6774 | L42: =F42+H42+J42+K42 -> 255550 | M42: =L42/E42 -> 2747.8495 | R42: =L42/Q42 -> #DIV/0! | T42: 17.8 | U42: 23.8 | V42: 2 | W42: 4 | X42: 4 | Y42: =SUM(V42:X42)/3 -> 3.3333333 | AA42: 豪雨・雷雨 | AC42: 0 | AM42: =SUM(AJ42:AL42)/3 -> 0 | AO42: 豪雨・雷雨 | AQ42: 0
A43: 土 | B43: 28 | C43: 土 | D43: =B43 -> 28 | E43: 81 | F43: 99200 | G43: =F43/E43 -> 1224.6914 | H43: 87750 | I43: =H43/E43 -> 1083.3333 | K43: 5940 | L43: =F43+H43+J43+K43 -> 192890 | M43: =L43/E43 -> 2381.358 | R43: =L43/Q43 -> #DIV/0! | T43: 16.2 | U43: 22.5 | V43: 4 | W43: 4 | X43: 4 | Y43: =SUM(V43:X43)/3 -> 4 | AA43: ※5.6月は18時は最低気温を採用。7月〜は最高気温を採用。 | AM43: =SUM(AJ43:AL43)/3 -> 0 | AO43: ※5.6月は18時は最低気温を採用。7月〜は最高気温を採用。
A44: SUB TOTAL | C44: SUB TOTAL | E44: =SUM(E37:E43) -> 512 | F44: =SUM(F37:F43) -> 925550 | G44: =F44/E44 -> 1807.7148 | H44: =SUM(H37:H43) -> 584000 | I44: =H44/E44 -> 1140.625 | J44: =I44/F44 -> 0.0012323753 | K44: =SUM(K37:K43) -> 5940 | L44: =F44+H44+J44+K44 -> 1515490 | M44: =L44/E44 -> 2959.9414 | R44: =L44/Q44 -> #DIV/0! | S44: 7 | T44: =SUM(T37:T43)/S44 -> 13.742857 | U44: =SUM(U37:U43)/S44 -> 21.571429 | V44: =SUM(V37:V43)/S44 -> 3.4285714 | W44: =SUM(W37:W43)/S44 -> 3.7142857 | X44: =SUM(X37:X43)/S44 -> 3.4285714 | Y44: =SUM(V44:X44)/3 -> 3.5238095 | AH44: =SUM(AH37:AH43)/AG44 -> #DIV/0! | AI44: =SUM(AI37:AI43)/AG44 -> #DIV/0! | AJ44: =SUM(AJ37:AJ43)/AG44 -> #DIV/0! | AK44: =SUM(AK37:AK43)/AG44 -> #DIV/0! | AL44: =SUM(AL37:AL43)/AG44 -> #DIV/0! | AM44: =SUM(AJ44:AL44)/3 -> #DIV/0!
A45: 5th week | C45: 5th week | T45: =C45 -> 5th week | AH45: =U45 -> 0
A46: 曜日 | B46: 日にち | C46: 曜日 | D46: 日にち | E46: 客数 | F46: 料理売上 | G46: 料理単価 | H46: 飲料売上 | I46: 飲料単価 | J46: テント利用料 | K46: 物販 | L46: 売上合計 | M46: 合計単価 | N46: サーフィンズ | O46: forking | P46: Timee | Q46: 合計 | R46: 人時売上高 | T46: 最低 | U46: 最高 | V46: 12時 | W46: 15時 | X46: 18時 | Y46: Ave | AA46: ■天候要因 | AC46: 評価点 | AH46: 最低 | AI46: 最高 | AJ46: 12時 | AK46: 15時 | AL46: 18時 | AM46: Ave | AO46: ■天候要因 | AQ46: 評価点
A47: 日 | B47: 29 | C47: 日 | D47: =B47 -> 29 | E47: 73 | F47: 147650 | G47: =F47/E47 -> 2022.6027 | H47: 89150 | I47: =H47/E47 -> 1221.2329 | L47: =F47+H47+J47+K47 -> 236800 | M47: =L47/E47 -> 3243.8356 | R47: =L47/Q47 -> #DIV/0! | T47: 12.5 | U47: 23 | V47: 4 | W47: 4 | X47: 4 | Y47: =SUM(V47:X47)/3 -> 4 | AA47: 晴れ（33度まで） | AC47: 5 | AM47: =SUM(AJ47:AL47)/3 -> 0 | AO47: 晴れ（33度まで） | AQ47: 5
A48: 月 | B48: 30 | C48: 月 | D48: =B48 -> 30 | E48: 46 | F48: 125200 | G48: =F48/E48 -> 2721.7391 | H48: 58050 | I48: =H48/E48 -> 1261.9565 | K48: 2970 | L48: =F48+H48+J48+K48 -> 186220 | M48: =L48/E48 -> 4048.2609 | R48: =L48/Q48 -> #DIV/0! | T48: 14.3 | U48: 22.3 | V48: 4 | W48: 4 | X48: 4 | Y48: =SUM(V48:X48)/3 -> 4 | AA48: 晴れ（25度以下） | AC48: 4 | AM48: =SUM(AJ48:AL48)/3 -> 0 | AO48: 晴れ（25度以下） | AQ48: 4
A49: 火 | B49: 31 | C49: 火 | D49: =B49 -> 31 | G49: =F49/E49 -> #DIV/0! | I49: =H49/E49 -> #DIV/0! | L49: =F49+H49+J49+K49 -> 0 | M49: =L49/E49 -> #DIV/0! | R49: =L49/Q49 -> #DIV/0! | Y49: =SUM(V49:X49)/3 -> 0 | AA49: 晴れ（33度以上）曇25度以上 | AC49: 3 | AM49: =SUM(AJ49:AL49)/3 -> 0 | AO49: 晴れ（33度以上）曇25度以上 | AQ49: 3
A50: 水 | C50: 水 | D50: =B50 -> 0 | G50: =F50/E50 -> #DIV/0! | I50: =H50/E50 -> #DIV/0! | L50: =F50+H50+J50+K50 -> 0 | M50: =L50/E50 -> #DIV/0! | R50: =L50/Q50 -> #DIV/0! | Y50: =SUM(V50:X50)/3 -> 0 | AA50: 曇 | AC50: 2 | AM50: =SUM(AJ50:AL50)/3 -> 0 | AO50: 曇 | AQ50: 2
A51: 木 | C51: 木 | D51: =B51 -> 0 | G51: =F51/E51 -> #DIV/0! | I51: =H51/E51 -> #DIV/0! | L51: =F51+H51+J51+K51 -> 0 | M51: =L51/E51 -> #DIV/0! | R51: =L51/Q51 -> #DIV/0! | Y51: =SUM(V51:X51)/3 -> 0 | AA51: 雨 | AC51: 1 | AM51: =SUM(AJ51:AL51)/3 -> 0 | AO51: 雨 | AQ51: 1
A52: 金 | C52: 金 | D52: =B52 -> 0 | G52: =F52/E52 -> #DIV/0! | H52: 0 | I52: =H52/E52 -> #DIV/0! | L52: =F52+H52+J52+K52 -> 0 | M52: =L52/E52 -> #DIV/0! | R52: =L52/Q52 -> #DIV/0! | Y52: =SUM(V52:X52)/3 -> 0 | AA52: 豪雨・雷雨 | AC52: 0 | AM52: =SUM(AJ52:AL52)/3 -> 0 | AO52: 豪雨・雷雨 | AQ52: 0
A53: 土 | C53: 土 | D53: =B53 -> 0 | G53: =F53/E53 -> #DIV/0! | H53: 0 | I53: =H53/E53 -> #DIV/0! | J53: 0 | L53: =F53+H53+J53+K53 -> 0 | M53: =L53/E53 -> #DIV/0! | R53: =L53/Q53 -> #DIV/0! | Y53: =SUM(V53:X53)/3 -> 0 | AA53: ※5.6月は18時は最低気温を採用。7月〜は最高気温を採用。 | AM53: =SUM(AJ53:AL53)/3 -> 0 | AO53: ※5.6月は18時は最低気温を採用。7月〜は最高気温を採用。
A54: SUB TOTAL | C54: SUB TOTAL | E54: =SUM(E47:E53) -> 119 | F54: =SUM(F47:F53) -> 272850 | G54: =F54/E54 -> 2292.8571 | H54: =SUM(H47:H53) -> 147200 | I54: =H54/E54 -> 1236.9748 | J54: =I54/F54 -> 0.0045335341 | K54: =SUM(K47:K53) -> 2970 | L54: =F54+H54+J54+K54 -> 423020 | M54: =L54/E54 -> 3554.79 | R54: =L54/Q54 -> #DIV/0! | S54: 2 | T54: =SUM(T47:T53)/S54 -> 13.4 | U54: =SUM(U47:U53)/S54 -> 22.65 | V54: =SUM(V47:V53)/S54 -> 4 | W54: =SUM(W47:W53)/S54 -> 4 | X54: =SUM(X47:X53)/S54 -> 4 | Y54: =SUM(V54:X54)/3 -> 4 | AH54: =SUM(AH47:AH53)/AG54 -> #DIV/0! | AI54: =SUM(AI47:AI53)/AG54 -> #DIV/0! | AJ54: =SUM(AJ47:AJ53)/AG54 -> #DIV/0! | AK54: =SUM(AK47:AK53)/AG54 -> #DIV/0! | AL54: =SUM(AL47:AL53)/AG54 -> #DIV/0! | AM54: =SUM(AJ54:AL54)/3 -> #DIV/0!
A55: 6th week | C55: 6th week | T55: =C55 -> 6th week | AH55: =U55 -> 0
A56: 曜日 | B56: 日にち | C56: 曜日 | D56: 日にち | E56: 客数 | F56: 料理売上 | G56: 料理単価 | H56: 飲料売上 | I56: 飲料単価 | J56: テント利用料 | K56: 物販 | L56: 売上合計 | M56: 合計単価 | N56: サーフィンズ | O56: forking | P56: Timee | Q56: 合計 | R56: 人時売上高 | T56: 最低 | U56: 最高 | V56: 12時 | W56: 15時 | X56: 18時 | Y56: Ave | AA56: ■天候要因 | AC56: 評価点 | AH56: 最低 | AI56: 最高 | AJ56: 12時 | AK56: 15時 | AL56: 18時 | AM56: Ave | AO56: ■天候要因 | AQ56: 評価点
A57: 日 | C57: 日 | D57: =B57 -> 0 | G57: =F57/E57 -> #DIV/0! | I57: =H57/E57 -> #DIV/0! | L57: =F57+H57+J57+K57 -> 0 | M57: =L57/E57 -> #DIV/0! | R57: =L57/Q57 -> #DIV/0! | Y57: =SUM(V57:X57)/3 -> 0 | AA57: 晴れ（33度まで） | AC57: 5 | AM57: =SUM(AJ57:AL57)/3 -> 0 | AO57: 晴れ（33度まで） | AQ57: 5
A58: 月 | C58: 月 | D58: =B58 -> 0 | G58: =F58/E58 -> #DIV/0! | I58: =H58/E58 -> #DIV/0! | L58: =F58+H58+J58+K58 -> 0 | M58: =L58/E58 -> #DIV/0! | R58: =L58/Q58 -> #DIV/0! | Y58: =SUM(V58:X58)/3 -> 0 | AA58: 晴れ（25度以下） | AC58: 4 | AM58: =SUM(AJ58:AL58)/3 -> 0 | AO58: 晴れ（25度以下） | AQ58: 4
A59: 火 | C59: 火 | D59: =B59 -> 0 | G59: =F59/E59 -> #DIV/0! | I59: =H59/E59 -> #DIV/0! | L59: =F59+H59+J59+K59 -> 0 | M59: =L59/E59 -> #DIV/0! | R59: =L59/Q59 -> #DIV/0! | Y59: =SUM(V59:X59)/3 -> 0 | AA59: 晴れ（33度以上）曇25度以上 | AC59: 3 | AM59: =SUM(AJ59:AL59)/3 -> 0 | AO59: 晴れ（33度以上）曇25度以上 | AQ59: 3
A60: 水 | C60: 水 | D60: =B60 -> 0 | G60: =F60/E60 -> #DIV/0! | I60: =H60/E60 -> #DIV/0! | L60: =F60+H60+J60+K60 -> 0 | M60: =L60/E60 -> #DIV/0! | R60: =L60/Q60 -> #DIV/0! | Y60: =SUM(V60:X60)/3 -> 0 | AA60: 曇 | AC60: 2 | AM60: =SUM(AJ60:AL60)/3 -> 0 | AO60: 曇 | AQ60: 2
A61: 木 | C61: 木 | D61: =B61 -> 0 | G61: =F61/E61 -> #DIV/0! | I61: =H61/E61 -> #DIV/0! | L61: =F61+H61+J61+K61 -> 0 | M61: =L61/E61 -> #DIV/0! | R61: =L61/Q61 -> #DIV/0! | Y61: =SUM(V61:X61)/3 -> 0 | AA61: 雨 | AC61: 1 | AM61: =SUM(AJ61:AL61)/3 -> 0 | AO61: 雨 | AQ61: 1
A62: 金 | C62: 金 | D62: =B62 -> 0 | G62: =F62/E62 -> #DIV/0! | H62: 0 | I62: =H62/E62 -> #DIV/0! | L62: =F62+H62+J62+K62 -> 0 | M62: =L62/E62 -> #DIV/0! | R62: =L62/Q62 -> #DIV/0! | Y62: =SUM(V62:X62)/3 -> 0 | AA62: 豪雨・雷雨 | AC62: 0 | AM62: =SUM(AJ62:AL62)/3 -> 0 | AO62: 豪雨・雷雨 | AQ62: 0
A63: 土 | C63: 土 | D63: =B63 -> 0 | G63: =F63/E63 -> #DIV/0! | H63: 0 | I63: =H63/E63 -> #DIV/0! | J63: 0 | L63: =F63+H63+J63+K63 -> 0 | M63: =L63/E63 -> #DIV/0! | R63: =L63/Q63 -> #DIV/0! | Y63: =SUM(V63:X63)/3 -> 0 | AA63: ※5.6月は18時は最低気温を採用。7月〜は最高気温を採用。 | AM63: =SUM(AJ63:AL63)/3 -> 0 | AO63: ※5.6月は18時は最低気温を採用。7月〜は最高気温を採用。
A64: SUB TOTAL | C64: SUB TOTAL | E64: =SUM(E57:E63) -> 0 | F64: =SUM(F57:F63) -> 0 | G64: =F64/E64 -> #DIV/0! | H64: =SUM(H57:H63) -> 0 | I64: =H64/E64 -> #DIV/0! | J64: =I64/F64 -> #DIV/0! | K64: =SUM(K57:K63) -> 0 | L64: =F64+H64+J64+K64 -> #DIV/0! | M64: =L64/E64 -> #DIV/0! | R64: =L64/Q64 -> #DIV/0! | T64: =SUM(T57:T63)/S64 -> #DIV/0! | U64: =SUM(U57:U63)/S64 -> #DIV/0! | V64: =SUM(V57:V63)/S64 -> #DIV/0! | W64: =SUM(W57:W63)/S64 -> #DIV/0! | X64: =SUM(X57:X63)/S64 -> #DIV/0! | Y64: =SUM(V64:X64)/3 -> #DIV/0! | AH64: =SUM(AH57:AH63)/AG64 -> #DIV/0! | AI64: =SUM(AI57:AI63)/AG64 -> #DIV/0! | AJ64: =SUM(AJ57:AJ63)/AG64 -> #DIV/0! | AK64: =SUM(AK57:AK63)/AG64 -> #DIV/0! | AL64: =SUM(AL57:AL63)/AG64 -> #DIV/0! | AM64: =SUM(AJ64:AL64)/3 -> #DIV/0!
A65: TOTAL | C65: TOTAL | T65: =C65 -> TOTAL | AH65: =U65 -> 0
A66: 曜日 | B66: 日数 | C66: 曜日 | D66: 日にち | E66: 客数 | F66: 料理売上 | G66: 料理単価 | H66: 飲料売上 | I66: 飲料単価 | J66: テント利用料 | K66: 物販 | L66: 売上合計 | M66: 合計単価 | N66: サーフィンズ | O66: forking | P66: Timee | Q66: 合計 | R66: 人時売上高 | T66: 最低 | U66: 最高 | V66: 12時 | W66: 15時 | X66: 18時 | Y66: Ave | AA66: 2024年 9月 天候実績 | AH66: 最低 | AI66: 最高 | AJ66: 12時 | AK66: 15時 | AL66: 18時 | AM66: Ave | AO66: 2024年 3月 天候実績
A67: 日 | C67: 日 | E67: =E7+E17+E27+E37+E47+E57 -> 972 | F67: =F7+F17+F27+F37+F47+F57 -> 2423650 | G67: =F67/E67 -> 2493.4671 | H67: =H7+H17+H27+H37+H47+H57 -> 1291850 | I67: =H67/E67 -> 1329.0638 | J67: =J7+J17+J27+J37+J47+J57 -> 29370 | K67: =K7+K17+K27+K37+K47+K57 -> 0 | L67: =L7+L17+L27+L37+L47+L57 -> 3744870 | M67: =M7+M17+M27+M37+M47+M57 -> #DIV/0! | Q67: =Q7+Q17+Q27+Q37+Q47+Q57 -> 0 | R67: =L67/Q67 -> #DIV/0! | T67: =T7+T17+T27+T37+T47+T57 -> 75.8 | U67: =U7+U17+U27+U37+U47+U57 -> 120.1 | V67: =V7+V17+V37+V47+V27+V57 -> 17 | W67: =W7+W17+W37+W47+W27+W57 -> 18 | X67: =X7+X17+X37+X47+X27+X57 -> 18 | Y67: =SUM(V67:X67)/3 -> 17.666667 | AA67: 天候状況 | AC67: ポイント | AD67: 2024日数 | AE67: 2024合計 | AF67: 比率 | AH67: =AH7+AH17+AH27+AH37+AH47+AH57 -> 24.9 | AI67: =AI7+AI17+AI27+AI37+AI47+AI57 -> 27 | AJ67: =AJ7+AJ17+AJ37+AJ47+AJ27+AJ57 -> 3 | AK67: =AK7+AK17+AK37+AK47+AK27+AK57 -> 1 | AL67: =AL7+AL17+AL37+AL47+AL27+AL57 -> 1 | AM67: =SUM(AJ67:AL67)/3 -> 1.6666667 | AO67: 天候状況 | AQ67: ポイント | AR67: 2024日数 | AS67: 2024合計 | AT67: 比率
A68: 月 | C68: 月 | E68: =E8+E18+E28+E38+E48+E58 -> 336 | F68: =F8+F18+F28+F38+F48+F58 -> 750600 | G68: =F68/E68 -> 2233.9286 | H68: =H8+H18+H28+H38+H48+H58 -> 420650 | I68: =H68/E68 -> 1251.9345 | J68: =J8+J18+J28+J38+J48+J58 -> 5500 | K68: =K8+K18+K28+K38+K48+K58 -> 2970 | L68: =L8+L18+L28+L38+L48+L58 -> 1179720 | M68: =M8+M18+M28+M38+M48+M58 -> #DIV/0! | Q68: =Q8+Q18+Q28+Q38+Q48+Q58 -> 0 | R68: =L68/Q68 -> #DIV/0! | T68: =T8+T18+T28+T38+T48+T58 -> 55.1 | U68: =U8+U18+U28+U38+U48+U58 -> 92.7 | V68: =V8+V18+V38+V48+V28+V58 -> 15 | W68: =W8+W18+W38+W48+W28+W58 -> 13 | X68: =X8+X18+X38+X48+X28+X58 -> 11 | Y68: =SUM(V68:X68)/3 -> 13 | AA68: 晴れ（33度まで） | AC68: 5 | AD68: 16 | AE68: =AC68*AD68 -> 80 | AF68: =(AD68+AD69+AD70)/AD74 -> 0.74666667 | AH68: =AH8+AH18+AH28+AH38+AH48+AH58 -> 20.7 | AI68: =AI8+AI18+AI28+AI38+AI48+AI58 -> 29.1 | AJ68: =AJ8+AJ18+AJ38+AJ48+AJ28+AJ58 -> 5 | AK68: =AK8+AK18+AK38+AK48+AK28+AK58 -> 1 | AL68: =AL8+AL18+AL38+AL48+AL28+AL58 -> 5 | AM68: =SUM(AJ68:AL68)/3 -> 3.6666667 | AO68: 晴れ（33度まで） | AQ68: 5 | AR68: 5 | AS68: =AQ68*AR68 -> 25 | AT68: =(AR68+AR69+AR70)/AR74 -> 0.66666667
A69: 火 | C69: 火 | E69: =E9+E19+E29+E39+E49+E59 -> 264 | F69: =F9+F19+F29+F39+F49+F59 -> 719900 | G69: =F69/E69 -> 2726.8939 | H69: =H9+H19+H29+H39+H49+H59 -> 407450 | I69: =H69/E69 -> 1543.3712 | J69: =J9+J19+J29+J39+J49+J59 -> 2310 | K69: =K9+K19+K29+K39+K49+K59 -> 0 | L69: =L9+L19+L29+L39+L49+L59 -> 1129660 | M69: =M9+M19+M29+M39+M49+M59 -> #DIV/0! | Q69: =Q9+Q19+Q29+Q39+Q49+Q59 -> 0 | R69: =L69/Q69 -> #DIV/0! | T69: =T9+T19+T29+T39+T49+T59 -> 46.5 | U69: =U9+U19+U29+U39+U49+U59 -> 74.7 | V69: =V9+V19+V39+V49+V29+V59 -> 13 | W69: =W9+W19+W39+W49+W29+W59 -> 11 | X69: =X9+X19+X39+X49+X29+X59 -> 13 | Y69: =SUM(V69:X69)/3 -> 12.333333 | AA69: 晴れ（25度以下） | AC69: 4 | AD69: 32 | AE69: =AC69*AD69 -> 128 | AH69: =AH9+AH19+AH29+AH39+AH49+AH59 -> 18.6 | AI69: =AI9+AI19+AI29+AI39+AI49+AI59 -> 29.8 | AJ69: =AJ9+AJ19+AJ39+AJ49+AJ29+AJ59 -> 5 | AK69: =AK9+AK19+AK39+AK49+AK29+AK59 -> 5 | AL69: =AL9+AL19+AL39+AL49+AL29+AL59 -> 5 | AM69: =SUM(AJ69:AL69)/3 -> 5 | AO69: 晴れ（25度以下） | AQ69: 4 | AS69: =AQ69*AR69 -> 0
A70: 水 | C70: 水 | E70: =E10+E20+E30+E40+E50+E60 -> 396 | F70: =F10+F20+F30+F40+F50+F60 -> 1083910 | G70: =F70/E70 -> 2737.1465 | H70: =H10+H20+H30+H40+H50+H60 -> 601450 | I70: =H70/E70 -> 1518.8131 | J70: =J10+J20+J30+J40+J50+J60 -> 19250 | K70: =K10+K20+K30+K40+K50+K60 -> 2970 | L70: =L10+L20+L30+L40+L50+L60 -> 1707580 | M70: =M10+M20+M30+M40+M50+M60 -> #DIV/0! | Q70: =Q10+Q20+Q30+Q40+Q50+Q60 -> 0 | R70: =L70/Q70 -> #DIV/0! | T70: =T10+T20+T30+T40+T50+T60 -> 47.3 | U70: =U10+U20+U30+U40+U50+U60 -> 74.6 | V70: =V10+V20+V40+V50+V30+V60 -> 14 | W70: =W10+W20+W40+W50+W30+W60 -> 11 | X70: =X10+X20+X40+X50+X30+X60 -> 11 | Y70: =SUM(V70:X70)/3 -> 12 | AA70: 晴れ（33度以上15以下） 曇25度以上 | AC70: 3 | AD70: 8 | AE70: =AC70*AD70 -> 24 | AH70: =AH10+AH20+AH30+AH40+AH50+AH60 -> 0 | AI70: =AI10+AI20+AI30+AI40+AI50+AI60 -> 0 | AJ70: =AJ10+AJ20+AJ40+AJ50+AJ30+AJ60 -> 0 | AK70: =AK10+AK20+AK40+AK50+AK30+AK60 -> 0 | AL70: =AL10+AL20+AL40+AL50+AL30+AL60 -> 0 | AM70: =SUM(AJ70:AL70)/3 -> 0 | AO70: 晴れ（33度以上15以下） 曇25度以上 | AQ70: 3 | AR70: 1 | AS70: =AQ70*AR70 -> 3
A71: 木 | C71: 木 | E71: =E21+E11+E31+E41+E51+E61 -> 274 | F71: =F21+F11+F31+F41+F51+F61 -> 638650 | G71: =F71/E71 -> 2330.8394 | H71: =H21+H11+H31+H41+H51+H61 -> 395600 | I71: =H71/E71 -> 1443.7956 | J71: =J21+J11+J31+J41+J51+J61 -> 10450 | K71: =K21+K11+K31+K41+K51+K61 -> 0 | L71: =L21+L11+L31+L41+L51+L61 -> 1044700 | M71: =M21+M11+M31+M41+M51+M61 -> #DIV/0! | Q71: =Q21+Q11+Q31+Q41+Q51+Q61 -> 0 | R71: =L71/Q71 -> #DIV/0! | T71: =T11+T21+T31+T41+T51+T61 -> 51.7 | U71: =U11+U21+U31+U41+U51+U61 -> 75.7 | V71: =V11+V21+V41+V51+V31+V61 -> 11 | W71: =W11+W21+W41+W51+W31+W61 -> 11 | X71: =X11+X21+X41+X51+X31+X61 -> 11 | Y71: =SUM(V71:X71)/3 -> 11 | AA71: 曇 | AC71: 2 | AD71: 15 | AE71: =AC71*AD71 -> 30 | AF71: =(AD71+AD72+AD73)/AD74 -> 0.25333333 | AH71: =AH11+AH21+AH31+AH41+AH51+AH61 -> 0 | AI71: =AI11+AI21+AI31+AI41+AI51+AI61 -> 0 | AJ71: =AJ11+AJ21+AJ41+AJ51+AJ31+AJ61 -> 0 | AK71: =AK11+AK21+AK41+AK51+AK31+AK61 -> 0 | AL71: =AL11+AL21+AL41+AL51+AL31+AL61 -> 0 | AM71: =SUM(AJ71:AL71)/3 -> 0 | AO71: 曇 | AQ71: 2 | AS71: =AQ71*AR71 -> 0 | AT71: =(AR71+AR72+AR73)/AR74 -> 0.33333333
A72: 金 | C72: 金 | E72: =E12+E22+E32+E42+E52+E62 -> 472 | F72: =F12+F22+F32+F42+F52+F62 -> 1078050 | G72: =F72/E72 -> 2284.0042 | H72: =H12+H22+H32+H42+H52+H62 -> 599250 | I72: =H72/E72 -> 1269.5975 | J72: =J12+J22+J32+J42+J52+J62 -> 6380 | K72: =K12+K22+K32+K42+K52+K62 -> 0 | L72: =L12+L22+L32+L42+L52+L62 -> 1683680 | M72: =M12+M22+M32+M42+M52+M62 -> #DIV/0! | Q72: =Q12+Q22+Q32+Q42+Q52+Q62 -> 0 | R72: =L72/Q72 -> #DIV/0! | T72: =T12+T22+T32+T42+T52+T62 -> 53.7 | U72: =U12+U22+U32+U42+U52+U62 -> 72.7 | V72: =V12+V22+V42+V52+V32+V62 -> 8 | W72: =W12+W22+W42+W52+W32+W62 -> 10 | X72: =X12+X22+X42+X52+X32+X62 -> 9 | Y72: =SUM(V72:X72)/3 -> 9 | AA72: 雨 | AC72: 1 | AD72: 4 | AE72: =AC72*AD72 -> 4 | AH72: =AH12+AH22+AH32+AH42+AH52+AH62 -> 0 | AI72: =AI12+AI22+AI32+AI42+AI52+AI62 -> 0 | AJ72: =AJ12+AJ22+AJ42+AJ52+AJ32+AJ62 -> 0 | AK72: =AK12+AK22+AK42+AK52+AK32+AK62 -> 0 | AL72: =AL12+AL22+AL42+AL52+AL32+AL62 -> 0 | AM72: =SUM(AJ72:AL72)/3 -> 0 | AO72: 雨 | AQ72: 1 | AR72: 3 | AS72: =AQ72*AR72 -> 3
A73: 土 | C73: 土 | E73: =E13+E23+E33+E43+E53+E63 -> 744 | F73: =F13+F23+F33+F43+F53+F63 -> 1974300 | G73: =F73/E73 -> 2653.629 | H73: =H13+H23+H33+H43+H53+H63 -> 1057600 | I73: =H73/E73 -> 1421.5054 | J73: =J13+J23+J33+J43+J53+J63 -> 57860 | K73: =K13+K23+K33+K43+K53+K63 -> 5940 | L73: =L13+L23+L33+L43+L53+L63 -> 3095700 | M73: =M13+M23+M33+M43+M53+M63 -> #DIV/0! | Q73: =Q13+Q23+Q33+Q43+Q53+Q63 -> 0 | R73: =L73/Q73 -> #DIV/0! | S73: =S14+S24+S34+S44+S54 -> 25 | T73: =T13+T23+T33+T43+T53+T63 -> 58.8 | U73: =U13+U23+U33+U43+U53+U63 -> 90.1 | V73: =V13+V23+V43+V53+V33+V63 -> 15 | W73: =W13+W23+W43+W53+W33+W63 -> 15 | X73: =X13+X23+X43+X53+X33+X63 -> 11 | Y73: =SUM(V73:X73)/3 -> 13.666667 | AA73: 豪雨・雷雨 | AC73: 0 | AE73: =AC73*AD73 -> 0 | AG73: 3 | AH73: =AH13+AH23+AH33+AH43+AH53+AH63 -> 0 | AI73: =AI13+AI23+AI33+AI43+AI53+AI63 -> 0 | AJ73: =AJ13+AJ23+AJ43+AJ53+AJ33+AJ63 -> 0 | AK73: =AK13+AK23+AK43+AK53+AK33+AK63 -> 0 | AL73: =AL13+AL23+AL43+AL53+AL33+AL63 -> 0 | AM73: =SUM(AJ73:AL73)/3 -> 0 | AO73: 豪雨・雷雨 | AQ73: 0 | AS73: =AQ73*AR73 -> 0
A74: TOTAL | B74: =SUM(B67:B73) -> 0 | C74: TOTAL | D74: =SUM(D67:D73) -> 0 | E74: =SUM(E67:E73) -> 3458 | F74: =SUM(F67:F73) -> 8669060 | G74: =F74/E74 -> 2506.9578 | H74: =SUM(H67:H73) -> 4773850 | I74: =H74/E74 -> 1380.5234 | J74: =SUM(J67:J73) -> 131120 | K74: =SUM(K67:K73) -> 11880 | L74: =SUM(L67:L73) -> 13585910 | M74: =L74/E74 -> 3928.8346 | Q74: =SUM(Q67:Q73) -> 0 | R74: =L74/Q74 -> #DIV/0! | T74: =SUM(T67:T73)/S73 -> 15.556 | U74: =SUM(U67:U73)/S73 -> 24.024 | V74: =SUM(V67:V73)/S73 -> 3.72 | W74: =SUM(W67:W73)/S73 -> 3.56 | X74: =SUM(X67:X73)/S73 -> 3.36 | Y74: =SUM(V74:X74)/3 -> 3.5466667 | AA74: TOTAL | AD74: =SUM(AD68:AD73) -> 75 | AE74: =SUM(AE68:AE73) -> 266 | AF74: =AF68+AF71 -> 1 | AH74: =SUM(AH67:AH73)/AG73 -> 21.4 | AI74: =SUM(AI67:AI73)/AG73 -> 28.633333 | AJ74: =SUM(AJ67:AJ73)/AG73 -> 4.3333333 | AK74: =SUM(AK67:AK73)/AG73 -> 2.3333333 | AL74: =SUM(AL67:AL73)/AG73 -> 3.6666667 | AM74: =SUM(AJ74:AL74)/3 -> 3.4444444 | AO74: TOTAL | AR74: =SUM(AR68:AR73) -> 9 | AS74: =SUM(AS68:AS73) -> 31 | AT74: =AT68+AT71 -> 1
A75: ■対比 | C75: ■対比
A77: ランチ | C77: ランチ | E77: 予算
E78: ランチ
E79: 客数 | H79: F売上 | L79: B売上
H80: =#REF!*E80 -> #REF! | L80: =#REF!*E80 -> #REF!
E82: ■予算差異
E83: 客数 | H83: F売上 | L83: B売上
E84: =E74-E80 -> 3458 | H84: =H74-H80 -> #REF! | L84: =L74-L80 -> #REF!
E85: =E74/E80 -> #DIV/0! | H85: =H74/H80 -> #REF! | L85: =L74/L80 -> #REF!
E86: ■前年値（数値残っていない休業）
E87: 客数 | H87: F売上 | L87: B売上
E89: ■前年差異
E90: 客数 | H90: F売上 | L90: B売上
E91: =E74-E88 -> 3458 | H91: =H74-H88 -> 4773850 | L91: =L74-L88 -> 13585910
E92: =E74/E88 -> #DIV/0! | H92: =H74/H88 -> #DIV/0! | L92: =L74/L88 -> #DIV/0!
A93: 構成比率 | F93: =F74/1.1 -> 7880963.6 | H93: =H74/1.1 -> 4339863.6 | J93: 税抜売上 | L93: =L74/1.1 -> 12350827 | M93: 対予測達成率 | Q93: =L93/#REF! -> #REF! | R93: =L93-#REF! -> #REF! | AB93: =L93/AP93 -> #DIV/0! | AD93: =AE74/AD74 -> 3.5466667 | AP93: =AC93/BD93 -> #DIV/0! | AR93: =AS74/AR74 -> 3.4444444
J94: =J74/1.1 -> 119200 | M94: 合計予算進捗 | Q94: ウチその他対比
H95: 売上合計予算対比 | M95: =L93/#REF! -> #REF! | Q95: =J94/#REF! -> #REF! | R95: =L93-#REF! -> #REF!
A98: ■モデルシフト
A99: モデルシフト カテゴリー
A100: TOP1 | J100: 538
A101: TOP2 | J101: =E74 -> 3458
A102: ON1 | J102: ='2024.8月実績'!F74 -> 13891
A103: ON2 | J103: ='2024.7月実績'!E74 -> 11438
A104: ショルダー | J104: 5174
A105: OFF1 | J105: ='2024.5月実績'!I74 -> 133
...

Sheet 2024.8月実績
A1: ■R6年度 ビアガーデン売上実績
A2: 8月 | M2: =M14+M24+M34+M44+M54+M64 -> 61462476 | S2: 31
A3: FOOD予測 | D3: ビアガーデン8月 TOTAL実績 | O3: 客数 | S3: 売上
A4: 予算 | D4: 実績 | F4: 客数 | H4: 客単価 | J4: 売上予算 | N4: 1日平均 | S4: =M4/S2 -> 0 | U4: 天候要因（売上との関連性を数値化する） | AI4: 天候要因（売上との関連性を数値化する）
A5: 1st week | D5: 1st week | U5: =D5 -> 1st week | AI5: =U5 -> 1st week
A6: 曜日 | B6: 日にち | C6: S | D6: 曜日 | E6: 日にち | F6: 客数 | G6: 料理売上 | H6: 料理単価 | I6: 飲料売上 | J6: 飲料単価 | K6: その他売上 | L6: 物販 | M6: 売上合計 | N6: 合計単価 | R6: 労働時間数 | S6: 人時売上高 | U6: 最低 | V6: 最高 | W6: 12時 | X6: 15時 | Y6: 18時 | Z6: Ave | AB6: ■天候要因 | AD6: 評価点 | AI6: 最低 | AJ6: 最高 | AK6: 12時 | AL6: 15時 | AM6: 18時 | AN6: Ave | AP6: ■天候要因 | AR6: 評価点
A7: 日 | D7: 日 | E7: =B7 -> 0 | H7: =G7/F7 -> #DIV/0! | J7: =I7/F7 -> #DIV/0! | M7: =G7+I7+K7+L7 -> 0 | N7: =M7/F7 -> #DIV/0! | S7: =M7/R7 -> #DIV/0! | Z7: =SUM(W7:Y7)/3 -> 0 | AB7: 晴れ（33度まで） | AD7: 5 | AN7: =SUM(AK7:AM7)/3 -> 0 | AP7: 晴れ（33度まで） | AR7: 5
A8: 月 | D8: 月 | E8: =B8 -> 0 | H8: =G8/F8 -> #DIV/0! | J8: =I8/F8 -> #DIV/0! | M8: =G8+I8+K8+L8 -> 0 | N8: =M8/F8 -> #DIV/0! | S8: =M8/R8 -> #DIV/0! | Z8: =SUM(W8:Y8)/3 -> 0 | AB8: 晴れ（25度以下） | AD8: 4 | AN8: =SUM(AK8:AM8)/3 -> 0 | AP8: 晴れ（25度以下） | AR8: 4
A9: 火 | D9: 火 | E9: =B9 -> 0 | H9: =G9/F9 -> #DIV/0! | J9: =I9/F9 -> #DIV/0! | M9: =G9+I9+K9+L9 -> 0 | N9: =M9/F9 -> #DIV/0! | S9: =M9/R9 -> #DIV/0! | Z9: =SUM(W9:Y9)/3 -> 0 | AB9: 晴れ（33度以上）曇25度以上 | AD9: 3 | AI9: 21.5 | AJ9: 31.1 | AK9: 5 | AL9: 3 | AM9: 5 | AN9: =SUM(AK9:AM9)/3 -> 4.3333333 | AP9: 晴れ（33度以上）曇25度以上 | AR9: 3
A10: 水 | D10: 水 | E10: =B10 -> 0 | H10: =G10/F10 -> #DIV/0! | J10: =I10/F10 -> #DIV/0! | M10: =G10+I10+K10+L10 -> 0 | N10: =M10/F10 -> #DIV/0! | S10: =M10/R10 -> #DIV/0! | Z10: =SUM(W10:Y10)/3 -> 0 | AB10: 曇 | AD10: 2 | AI10: 24.2 | AJ10: 34 | AK10: 3 | AL10: 3 | AM10: 3 | AN10: =SUM(AK10:AM10)/3 -> 3 | AP10: 曇 | AR10: 2
A11: 木 | B11: 1 | D11: 木 | E11: =B11 -> 1 | F11: 350 | G11: 1126050 | H11: =G11/F11 -> 3217.2857 | I11: 575550 | J11: =I11/F11 -> 1644.4286 | K11: 46530 | M11: =G11+I11+K11+L11 -> 1748130 | N11: =M11/F11 -> 4994.6571 | S11: =M11/R11 -> #DIV/0! | U11: 20.5 | V11: 28.4 | W11: 3 | X11: 1 | Y11: 3 | Z11: =SUM(W11:Y11)/3 -> 2.3333333 | AB11: 雨 | AD11: 1 | AI11: 25.6 | AJ11: 32.2 | AK11: 3 | AL11: 3 | AM11: 5 | AN11: =SUM(AK11:AM11)/3 -> 3.6666667 | AP11: 雨 | AR11: 1
A12: 金 | B12: 2 | D12: 金 | E12: =B12 -> 2 | F12: 634 | G12: 2073900 | H12: =G12/F12 -> 3271.1356 | I12: 1102350 | J12: =I12/F12 -> 1738.7224 | K12: 17050 | L12: 20790 | M12: =G12+I12+K12+L12 -> 3214090 | N12: =M12/F12 -> 5069.5426 | S12: =M12/R12 -> #DIV/0! | U12: 23.2 | V12: 30 | W12: 3 | X12: 3 | Y12: 3 | Z12: =SUM(W12:Y12)/3 -> 3 | AB12: 豪雨・雷雨 | AD12: 0 | AI12: 27.1 | AJ12: 31 | AK12: 3 | AL12: 3 | AM12: 1 | AN12: =SUM(AK12:AM12)/3 -> 2.3333333 | AP12: 豪雨・雷雨 | AR12: 0
A13: 土 | B13: 3 | D13: 土 | E13: =B13 -> 3 | F13: 689 | G13: 2070400 | H13: =G13/F13 -> 3004.9347 | I13: 1133850 | J13: =I13/F13 -> 1645.6459 | K13: 96690 | L13: 5940 | M13: =G13+I13+K13+L13 -> 3306880 | N13: =M13/F13 -> 4799.5356 | S13: =M13/R13 -> #DIV/0! | U13: 24.1 | V13: 29.5 | W13: 3 | X13: 3 | Y13: 1 | Z13: =SUM(W13:Y13)/3 -> 2.3333333 | AB13: ※5.6月は18時は最低気温を採用。7月〜は最高気温を採用。 | AI13: 22.9 | AJ13: 29.4 | AK13: 3 | AL13: 1 | AM13: 3 | AN13: =SUM(AK13:AM13)/3 -> 2.3333333 | AP13: ※5.6月は18時は最低気温を採用。7月〜は最高気温を採用。
A14: SUB TOTAL | C14: =#REF! -> #REF! | D14: SUB TOTAL | F14: =SUM(F7:F13) -> 1673 | G14: =SUM(G7:G13) -> 5270350 | H14: =G14/F14 -> 3150.2391 | I14: =SUM(I7:I13) -> 2811750 | J14: =I14/F14 -> 1680.6635 | K14: =SUM(K7:K13) -> 160270 | L14: =SUM(L7:L13) -> 26730 | M14: =G14+I14+K14+L14 -> 8269100 | N14: =M14/F14 -> 4942.6778 | R14: =SUM(R7:R13) -> 0 | S14: =M14/R14 -> #DIV/0! | T14: 3 | U14: =SUM(U7:U13)/T14 -> 22.6 | V14: =SUM(V7:V13)/T14 -> 29.3 | W14: =SUM(W7:W13)/T14 -> 3 | X14: =SUM(X7:X13)/T14 -> 2.3333333 | Y14: =SUM(Y7:Y13)/T14 -> 2.3333333 | Z14: =SUM(W14:Y14)/3 -> 2.5555556 | AA14: 11 | AB14: =M14/T14 -> 2756366.7 | AH14: 5 | AI14: =SUM(AI7:AI13)/AH14 -> 24.26 | AJ14: =SUM(AJ7:AJ13)/AH14 -> 31.54 | AK14: =SUM(AK7:AK13)/AH14 -> 3.4 | AL14: =SUM(AL7:AL13)/AH14 -> 2.6 | AM14: =SUM(AM7:AM13)/AH14 -> 3.4 | AN14: =SUM(AK14:AM14)/3 -> 3.1333333 | AO14: 11 | AP14: =AC14/AH14 -> 0
A15: 2nd week | D15: 2nd week | U15: =D15 -> 2nd week | AI15: =U15 -> 2nd week
A16: 曜日 | B16: 日にち | C16: S | D16: 曜日 | E16: 日にち | F16: 客数 | G16: 料理売上 | H16: 料理単価 | I16: 飲料売上 | J16: 飲料単価 | K16: その他売上 | L16: 物販 | M16: 売上合計 | N16: 合計単価 | R16: 労働時間数 | S16: 人時売上高 | U16: 最低 | V16: 最高 | W16: 12時 | X16: 15時 | Y16: 18時 | Z16: Ave | AB16: ■天候要因 | AD16: 評価点 | AI16: 最低 | AJ16: 最高 | AK16: 12時 | AL16: 15時 | AM16: 18時 | AN16: Ave | AP16: ■天候要因 | AR16: 評価点
A17: 日 | B17: 4 | D17: 日 | E17: =B17 -> 4 | F17: 445 | G17: 1310550 | H17: =G17/F17 -> 2945.0562 | I17: 665150 | J17: =I17/F17 -> 1494.7191 | K17: 29590 | M17: =G17+I17+K17+L17 -> 2005290 | N17: =M17/F17 -> 4506.2697 | S17: =M17/R17 -> #DIV/0! | U17: 20.4 | V17: 22.9 | W17: 2 | X17: 2 | Y17: 2 | Z17: =SUM(W17:Y17)/3 -> 2 | AB17: 晴れ（33度まで） | AD17: 5 | AI17: 22.2 | AJ17: 25.7 | AK17: 1 | AL17: 3 | AM17: 1 | AN17: =SUM(AK17:AM17)/3 -> 1.6666667 | AP17: 晴れ（33度まで） | AR17: 5
A18: 月 | B18: 5 | D18: 月 | E18: =B18 -> 5 | F18: 389 | G18: 1000400 | H18: =G18/F18 -> 2571.7224 | I18: 495400 | J18: =I18/F18 -> 1273.5219 | K18: 23210 | L18: 2970 | M18: =G18+I18+K18+L18 -> 1521980 | N18: =M18/F18 -> 3912.545 | S18: =M18/R18 -> #DIV/0! | U18: 19.9 | V18: 24.4 | W18: 2 | X18: 2 | Y18: 2 | Z18: =SUM(W18:Y18)/3 -> 2 | AB18: 晴れ（25度以下） | AD18: 4 | AI18: 19.7 | AJ18: 26.1 | AK18: 3 | AL18: 3 | AM18: 3 | AN18: =SUM(AK18:AM18)/3 -> 3 | AP18: 晴れ（25度以下） | AR18: 4
A19: 火 | B19: 6 | D19: 火 | E19: =B19 -> 6 | F19: 565 | G19: 1517600 | H19: =G19/F19 -> 2686.0177 | I19: 803450 | J19: =I19/F19 -> 1422.0354 | K19: 33220 | L19: 0 | M19: =G19+I19+K19+L19 -> 2354270 | N19: =M19/F19 -> 4166.8496 | S19: =M19/R19 -> #DIV/0! | U19: 20.7 | V19: 26.4 | W19: 3 | X19: 3 | Y19: 5 | Z19: =SUM(W19:Y19)/3 -> 3.6666667 | AB19: 晴れ（33度以上）曇25度以上 | AD19: 3 | AI19: 23.3 | AJ19: 27.7 | AK19: 1 | AL19: 1 | AM19: 5 | AN19: =SUM(AK19:AM19)/3 -> 2.3333333 | AP19: 晴れ（33度以上）曇25度以上 | AR19: 3
A20: 水 | B20: 7 | D20: 水 | E20: =B20 -> 7 | F20: 573 | G20: 1792600 | H20: =G20/F20 -> 3128.4468 | I20: 926200 | J20: =I20/F20 -> 1616.4049 | K20: 49390 | L20: 8910 | M20: =G20+I20+K20+L20 -> 2777100 | N20: =M20/F20 -> 4846.5969 | S20: =M20/R20 -> #DIV/0! | U20: 21.8 | V20: 32 | W20: 5 | X20: 3 | Y20: 3 | Z20: =SUM(W20:Y20)/3 -> 3.6666667 | AB20: 曇 | AD20: 2 | AI20: 24.5 | AJ20: 30.8 | AK20: 1 | AL20: 3 | AM20: 5 | AN20: =SUM(AK20:AM20)/3 -> 3 | AP20: 曇 | AR20: 2
A21: 木 | B21: 8 | D21: 木 | E21: =B21 -> 8 | F21: 548 | G21: 1461350 | H21: =G21/F21 -> 2666.6971 | I21: 755400 | J21: =I21/F21 -> 1378.4672 | K21: 26400 | L21: 0 | M21: =G21+I21+K21+L21 -> 2243150 | N21: =M21/F21 -> 4093.3394 | S21: =M21/R21 -> #DIV/0! | U21: 23.7 | V21: 30.1 | W21: 3 | X21: 1 | Y21: 3 | Z21: =SUM(W21:Y21)/3 -> 2.3333333 | AB21: 雨 | AD21: 1 | AI21: 25.7 | AJ21: 31.1 | AK21: 5 | AL21: 5 | AM21: 5 | AN21: =SUM(AK21:AM21)/3 -> 5 | AP21: 雨 | AR21: 1
A22: 金 | B22: 9 | D22: 金 | E22: =B22 -> 9 | F22: 538 | G22: 1659800 | H22: =G22/F22 -> 3085.1301 | I22: 891950 | J22: =I22/F22 -> 1657.8996 | K22: 52140 | L22: 8910 | M22: =G22+I22+K22+L22 -> 2612800 | N22: =M22/F22 -> 4856.5056 | S22: =M22/R22 -> #DIV/0! | U22: 24.8 | V22: 30.2 | W22: 3 | X22: 3 | Y22: 3 | Z22: =SUM(W22:Y22)/3 -> 3 | AB22: 豪雨・雷雨 | AD22: 0 | AI22: 24.7 | AJ22: 32.3 | AK22: 5 | AL22: 5 | AM22: 5 | AN22: =SUM(AK22:AM22)/3 -> 5 | AP22: 豪雨・雷雨 | AR22: 0
A23: 土 | B23: 10 | D23: 土 | E23: =B23 -> 10 | F23: 557 | G23: 1645950 | H23: =G23/F23 -> 2955.0269 | I23: =880010+5500 -> 885510 | J23: =I23/F23 -> 1589.7846 | K23: 62920 | L23: 0 | M23: =G23+I23+K23+L23 -> 2594380 | N23: =M23/F23 -> 4657.7738 | S23: =M23/R23 -> #DIV/0! | U23: 24.5 | V23: 28.6 | W23: 5 | X23: 5 | Y23: 5 | Z23: =SUM(W23:Y23)/3 -> 5 | AB23: ※5.6月は18時は最低気温を採用。7月〜は最高気温を採用。 | AI23: 23.3 | AJ23: 32 | AK23: 5 | AL23: 5 | AM23: 5 | AN23: =SUM(AK23:AM23)/3 -> 5 | AP23: ※5.6月は18時は最低気温を採用。7月〜は最高気温を採用。
A24: SUB TOTAL | C24: =#REF! -> #REF! | D24: SUB TOTAL | F24: =SUM(F17:F23) -> 3615 | G24: =SUM(G17:G23) -> 10388250 | H24: =G24/F24 -> 2873.6515 | I24: =SUM(I17:I23) -> 5423060 | J24: =I24/F24 -> 1500.1549 | K24: =SUM(K17:K23) -> 276870 | L24: =SUM(L17:L23) -> 20790 | M24: =G24+I24+K24+L24 -> 16108970 | N24: =M24/F24 -> 4456.1466 | R24: =SUM(R17:R23) -> 0 | S24: =M24/R24 -> #DIV/0! | T24: 7 | U24: =SUM(U17:U23)/T24 -> 22.257143 | V24: =SUM(V17:V23)/T24 -> 27.8 | W24: =SUM(W17:W23)/T24 -> 3.2857143 | X24: =SUM(X17:X23)/T24 -> 2.7142857 | Y24: =SUM(Y17:Y23)/T24 -> 3.2857143 | Z24: =SUM(W24:Y24)/3 -> 3.0952381 | AA24: 12 | AB24: =M24/T24 -> 2301281.4 | AH24: 7 | AI24: =SUM(AI17:AI23)/AH24 -> 23.342857 | AJ24: =SUM(AJ17:AJ23)/AH24 -> 29.385714 | AK24: =SUM(AK17:AK23)/AH24 -> 3 | AL24: =SUM(AL17:AL23)/AH24 -> 3.5714286 | AM24: =SUM(AM17:AM23)/AH24 -> 4.1428571 | AN24: =SUM(AK24:AM24)/3 -> 3.5714286 | AO24: 12 | AP24: =AC24/AH24 -> 0
A25: 3rd week | D25: 3rd week | U25: =D25 -> 3rd week | AI25: =U25 -> 3rd week
A26: 曜日 | B26: 日にち | C26: S | D26: 曜日 | E26: 日にち | F26: 客数 | G26: 料理売上 | H26: 料理単価 | I26: 飲料売上 | J26: 飲料単価 | K26: その他売上 | L26: 物販 | M26: 売上合計 | N26: 合計単価 | R26: 労働時間数 | S26: 人時売上高 | U26: 最低 | V26: 最高 | W26: 12時 | X26: 15時 | Y26: 18時 | Z26: Ave | AB26: ■天候要因 | AD26: 評価点 | AI26: 最低 | AJ26: 最高 | AK26: 12時 | AL26: 15時 | AM26: 18時 | AN26: Ave | AP26: ■天候要因 | AR26: 評価点
A27: 日 | B27: 11 | D27: 日 | E27: =B27 -> 11 | F27: 612 | G27: 1751350 | H27: =G27/F27 -> 2861.683 | I27: 895610 | J27: =I27/F27 -> 1463.415 | K27: 37950 | L27: 8910 | M27: =G27+I27+K27+L27 -> 2693820 | N27: =M27/F27 -> 4401.6667 | S27: =M27/R27 -> #DIV/0! | U27: 22.1 | V27: 29.4 | W27: 5 | X27: 5 | Y27: 5 | Z27: =SUM(W27:Y27)/3 -> 5 | AB27: 晴れ（33度まで） | AD27: 5 | AI27: 23.5 | AJ27: 30.5 | AK27: 3 | AL27: 5 | AM27: 5 | AN27: =SUM(AK27:AM27)/3 -> 4.3333333 | AP27: 晴れ（33度まで） | AR27: 5
A28: 月 | B28: 12 | D28: 月 | E28: =B28 -> 12 | F28: 576 | G28: 1597650 | H28: =G28/F28 -> 2773.6979 | I28: 833920 | J28: =I28/F28 -> 1447.7778 | K28: 42570 | L28: 0 | M28: =G28+I28+K28+L28 -> 2474140 | N28: =M28/F28 -> 4295.3819 | S28: =M28/R28 -> #DIV/0! | U28: 23.3 | V28: 34.1 | W28: 3 | X28: 3 | Y28: 3 | Z28: =SUM(W28:Y28)/3 -> 3 | AB28: 晴れ（25度以下） | AD28: 4 | AI28: 23.1 | AJ28: 30.7 | AK28: 5 | AL28: 3 | AM28: 3 | AN28: =SUM(AK28:AM28)/3 -> 3.6666667 | AP28: 晴れ（25度以下） | AR28: 4
A29: 火 | B29: 13 | D29: 火 | E29: =B29 -> 13 | F29: 289 | G29: 821850 | H29: =G29/F29 -> 2843.7716 | I29: 436550 | J29: =I29/F29 -> 1510.5536 | K29: 20570 | L29: 0 | M29: =G29+I29+K29+L29 -> 1278970 | N29: =M29/F29 -> 4425.5017 | S29: =M29/R29 -> #DIV/0! | U29: 25.7 | V29: 28.5 | W29: 1 | X29: 1 | Y29: 1 | Z29: =SUM(W29:Y29)/3 -> 1 | AB29: 晴れ（33度以上）曇25度以上 | AD29: 3 | AI29: 22.5 | AJ29: 30 | AK29: 5 | AL29: 3 | AM29: 3 | AN29: =SUM(AK29:AM29)/3 -> 3.6666667 | AP29: 晴れ（33度以上）曇25度以上 | AR29: 3
A30: 水 | B30: 14 | D30: 水 | E30: =B30 -> 14 | F30: 283 | G30: 713750 | H30: =G30/F30 -> 2522.0848 | I30: =416150+600 -> 416750 | J30: =I30/F30 -> 1472.6148 | K30: 26950 | L30: 0 | M30: =G30+I30+K30+L30 -> 1157450 | N30: =M30/F30 -> 4089.9293 | S30: =M30/R30 -> #DIV/0! | U30: 24.7 | V30: 28.5 | W30: 1 | X30: 1 | Y30: 1 | Z30: =SUM(W30:Y30)/3 -> 1 | AB30: 曇 | AD30: 2 | AI30: 23.2 | AJ30: 26.5 | AK30: 1 | AL30: 1 | AM30: 3 | AN30: =SUM(AK30:AM30)/3 -> 1.6666667 | AP30: 曇 | AR30: 2
A31: 木 | B31: 15 | D31: 木 | E31: =B31 -> 15 | F31: 610 | G31: 1585650 | H31: =G31/F31 -> 2599.4262 | I31: 920950 | J31: =I31/F31 -> 1509.7541 | K31: 43340 | L31: 0 | M31: =G31+I31+K31+L31 -> 2549940 | N31: =M31/F31 -> 4180.2295 | S31: =M31/R31 -> #DIV/0! | U31: 22.3 | V31: 27.6 | W31: 5 | X31: 1 | Y31: 5 | Z31: =SUM(W31:Y31)/3 -> 3.6666667 | AB31: 雨 | AD31: 1 | AI31: 25.2 | AJ31: 31.1 | AK31: 5 | AL31: 1 | AM31: 1 | AN31: =SUM(AK31:AM31)/3 -> 2.3333333 | AP31: 雨 | AR31: 1
A32: 金 | B32: 16 | D32: 金 | E32: =B32 -> 16 | F32: 628 | G32: 1747950 | H32: =G32/F32 -> 2783.3599 | I32: 997050 | J32: =I32/F32 -> 1587.6592 | K32: 34430 | L32: 2970 | M32: =G32+I32+K32+L32 -> 2782400 | N32: =M32/F32 -> 4430.5732 | S32: =M32/R32 -> #DIV/0! | U32: 23 | V32: 29.3 | W32: 3 | X32: 3 | Y32: 3 | Z32: =SUM(W32:Y32)/3 -> 3 | AB32: 豪雨・雷雨 | AD32: 0 | AI32: 23.4 | AJ32: 31 | AK32: 3 | AL32: 1 | AM32: 3 | AN32: =SUM(AK32:AM32)/3 -> 2.3333333 | AP32: 豪雨・雷雨 | AR32: 0
A33: 土 | B33: 17 | D33: 土 | E33: =B33 -> 17 | F33: 479 | G33: 1393000 | H33: =G33/F33 -> 2908.142 | I33: 745750 | J33: =I33/F33 -> 1556.8894 | K33: 28050 | L33: 5940 | M33: =G33+I33+K33+L33 -> 2172740 | N33: =M33/F33 -> 4535.9916 | S33: =M33/R33 -> #DIV/0! | U33: 23.2 | V33: 27.6 | W33: 3 | X33: 3 | Y33: 5 | Z33: =SUM(W33:Y33)/3 -> 3.6666667 | AB33: ※5.6月は18時は最低気温を採用。7月〜は最高気温を採用。 | AI33: 22.9 | AJ33: 32.2 | AK33: 3 | AL33: 3 | AM33: 5 | AN33: =SUM(AK33:AM33)/3 -> 3.6666667 | AP33: ※5.6月は18時は最低気温を採用。7月〜は最高気温を採用。
A34: SUB TOTAL | C34: =#REF! -> #REF! | D34: SUB TOTAL | F34: =SUM(F27:F33) -> 3477 | G34: =SUM(G27:G33) -> 9611200 | H34: =G34/F34 -> 2764.222 | I34: =SUM(I27:I33) -> 5246580 | J34: =I34/F34 -> 1508.9387 | K34: =SUM(K27:K33) -> 233860 | L34: =SUM(L27:L33) -> 17820 | M34: =G34+I34+K34+L34 -> 15109460 | N34: =M34/F34 -> 4345.545 | R34: =SUM(R27:R33) -> 0 | S34: =M34/R34 -> #DIV/0! | T34: 7 | U34: =SUM(U27:U33)/T34 -> 23.471429 | V34: =SUM(V27:V33)/T34 -> 29.285714 | W34: =SUM(W27:W33)/T34 -> 3 | X34: =SUM(X27:X33)/T34 -> 2.4285714 | Y34: =SUM(Y27:Y33)/T34 -> 3.2857143 | Z34: =SUM(W34:Y34)/3 -> 2.9047619 | AA34: 13 | AB34: =M34/T34 -> 2158494.3 | AH34: 7 | AI34: =SUM(AI27:AI33)/AH34 -> 23.4 | AJ34: =SUM(AJ27:AJ33)/AH34 -> 30.285714 | AK34: =SUM(AK27:AK33)/AH34 -> 3.5714286 | AL34: =SUM(AL27:AL33)/AH34 -> 2.4285714 | AM34: =SUM(AM27:AM33)/AH34 -> 3.2857143 | AN34: =SUM(AK34:AM34)/3 -> 3.0952381 | AO34: 13 | AP34: =AC34/AH34 -> 0
A35: 4th week | D35: 4th week | U35: =D35 -> 4th week | AI35: =U35 -> 4th week
A36: 曜日 | B36: 日にち | C36: S | D36: 曜日 | E36: 日にち | F36: 客数 | G36: 料理売上 | H36: 料理単価 | I36: 飲料売上 | J36: 飲料単価 | K36: その他売上 | L36: 物販 | M36: 売上合計 | N36: 合計単価 | R36: 労働時間数 | S36: 人時売上高 | U36: 最低 | V36: 最高 | W36: 12時 | X36: 15時 | Y36: 18時 | Z36: Ave | AB36: ■天候要因 | AD36: 評価点 | AI36: 最低 | AJ36: 最高 | AK36: 12時 | AL36: 15時 | AM36: 18時 | AN36: Ave | AP36: ■天候要因 | AR36: 評価点
A37: 日 | B37: 18 | D37: 日 | E37: =B37 -> 18 | F37: 478 | G37: 1149200 | H37: =G37/F37 -> 2404.1841 | I37: 648950 | J37: =I37/F37 -> 1357.636 | K37: 15400 | L37: 5940 | M37: =G37+I37+K37+L37 -> 1819490 | N37: =M37/F37 -> 3806.4644 | S37: =M37/R37 -> #DIV/0! | U37: 22 | V37: 25.8 | W37: 5 | X37: 5 | Y37: 5 | Z37: =SUM(W37:Y37)/3 -> 5 | AB37: 晴れ（33度まで） | AD37: 5 | AI37: 24.4 | AJ37: 29.8 | AK37: 1 | AL37: 5 | AM37: 3 | AN37: =SUM(AK37:AM37)/3 -> 3 | AP37: 晴れ（33度まで） | AR37: 5
A38: 月 | B38: 19 | D38: 月 | E38: =B38 -> 19 | F38: 279 | G38: 618650 | H38: =G38/F38 -> 2217.3835 | I38: 344400 | J38: =I38/F38 -> 1234.4086 | K38: 4400 | M38: =G38+I38+K38+L38 -> 967450 | N38: =M38/F38 -> 3467.5627 | S38: =M38/R38 -> #DIV/0! | U38: 20 | V38: 29.4 | W38: 5 | X38: 3 | Y38: 3 | Z38: =SUM(W38:Y38)/3 -> 3.6666667 | AB38: 晴れ（25度以下） | AD38: 4 | AI38: 23.9 | AJ38: 32.4 | AK38: 5 | AL38: 5 | AM38: 4 | AN38: =SUM(AK38:AM38)/3 -> 4.6666667 | AP38: 晴れ（25度以下） | AR38: 4
A39: 火 | B39: 20 | D39: 火 | E39: =B39 -> 20 | F39: 333 | G39: 984150 | H39: =G39/F39 -> 2955.4054 | I39: 489750 | J39: =I39/F39 -> 1470.7207 | K39: 37400 | M39: =G39+I39+K39+L39 -> 1511300 | N39: =M39/F39 -> 4538.4384 | S39: =M39/R39 -> #DIV/0! | U39: 19.4 | V39: 25.1 | W39: 1 | X39: 3 | Y39: 3 | Z39: =SUM(W39:Y39)/3 -> 2.3333333 | AB39: 晴れ（33度以上）曇25度以上 | AD39: 3 | AI39: 24.7 | AJ39: 33.2 | AK39: 3 | AL39: 3 | AM39: 4 | AN39: =SUM(AK39:AM39)/3 -> 3.3333333 | AP39: 晴れ（33度以上）曇25度以上 | AR39: 3
A40: 水 | B40: 21 | D40: 水 | E40: =B40 -> 21 | F40: 506 | G40: 1302600 | H40: =G40/F40 -> 2574.3083 | I40: 664850 | J40: =I40/F40 -> 1313.9328 | K40: 20350 | M40: =G40+I40+K40+L40 -> 1987800 | N40: =M40/F40 -> 3928.4585 | S40: =M40/R40 -> #DIV/0! | U40: 18.2 | V40: 28.7 | W40: 5 | X40: 5 | Y40: 5 | Z40: =SUM(W40:Y40)/3 -> 5 | AB40: 曇 | AD40: 2 | AI40: 26.2 | AJ40: 36.3 | AK40: 3 | AL40: 3 | AM40: 4 | AN40: =SUM(AK40:AM40)/3 -> 3.3333333 | AP40: 曇 | AR40: 2
A41: 木 | B41: 22 | D41: 木 | E41: =B41 -> 22 | F41: 244 | G41: 721350 | H41: =G41/F41 -> 2956.3525 | I41: 388750 | J41: =I41/F41 -> 1593.2377 | K41: 41250 | M41: =G41+I41+K41+L41 -> 1151350 | N41: =M41/F41 -> 4718.6475 | S41: =M41/R41 -> #DIV/0! | U41: 19.6 | V41: 25.7 | W41: 3 | X41: 1 | Y41: 1 | Z41: =SUM(W41:Y41)/3 -> 1.6666667 | AB41: 雨 | AD41: 1 | AI41: 26.3 | AJ41: 35 | AK41: 3 | AL41: 1 | AM41: 4 | AN41: =SUM(AK41:AM41)/3 -> 2.6666667 | AP41: 雨 | AR41: 1
A42: 金 | B42: 23 | D42: 金 | E42: =B42 -> 23 | F42: 383 | G42: 1116150 | H42: =G42/F42 -> 2914.2298 | I42: 576300 | J42: =I42/F42 -> 1504.6997 | K42: 36960 | M42: =G42+I42+K42+L42 -> 1729410 | N42: =M42/F42 -> 4515.4308 | S42: =M42/R42 -> #DIV/0! | U42: 22.5 | V42: 30.7 | W42: 1 | X42: 1 | Y42: 1 | Z42: =SUM(W42:Y42)/3 -> 1 | AB42: 豪雨・雷雨 | AD42: 0 | AI42: 26 | AJ42: 34.7 | AK42: 3 | AL42: 3 | AM42: 4 | AN42: =SUM(AK42:AM42)/3 -> 3.3333333 | AP42: 豪雨・雷雨 | AR42: 0
A43: 土 | B43: 24 | D43: 土 | E43: =B43 -> 24 | F43: 572 | G43: 1595750 | H43: =G43/F43 -> 2789.7727 | I43: 884020 | J43: =I43/F43 -> 1545.4895 | K43: 63030 | L43: 5940 | M43: =G43+I43+K43+L43 -> 2548740 | N43: =M43/F43 -> 4455.8392 | S43: =M43/R43 -> #DIV/0! | U43: 25.3 | V43: 29 | W43: 5 | X43: 5 | Y43: 5 | Z43: =SUM(W43:Y43)/3 -> 5 | AB43: ※5.6月は18時は最低気温を採用。7月〜は最高気温を採用。 | AI43: 26.7 | AJ43: 35.6 | AK43: 3 | AL43: 3 | AM43: 4 | AN43: =SUM(AK43:AM43)/3 -> 3.3333333 | AP43: ※5.6月は18時は最低気温を採用。7月〜は最高気温を採用。
A44: SUB TOTAL | C44: =#REF! -> #REF! | D44: SUB TOTAL | F44: =SUM(F37:F43) -> 2795 | G44: =SUM(G37:G43) -> 7487850 | H44: =G44/F44 -> 2679.0161 | I44: =SUM(I37:I43) -> 3997020 | J44: =I44/F44 -> 1430.0608 | K44: =SUM(K37:K43) -> 218790 | L44: =SUM(L37:L43) -> 11880 | M44: =G44+I44+K44+L44 -> 11715540 | N44: =M44/F44 -> 4191.6064 | R44: =SUM(R37:R43) -> 0 | S44: =M44/R44 -> #DIV/0! | T44: 7 | U44: =SUM(U37:U43)/T44 -> 21 | V44: =SUM(V37:V43)/T44 -> 27.771429 | W44: =SUM(W37:W43)/T44 -> 3.5714286 | X44: =SUM(X37:X43)/T44 -> 3.2857143 | Y44: =SUM(Y37:Y43)/T44 -> 3.2857143 | Z44: =SUM(W44:Y44)/3 -> 3.3809524 | AA44: 14 | AB44: =M44/T44 -> 1673648.6 | AH44: 7 | AI44: =SUM(AI37:AI43)/AH44 -> 25.457143 | AJ44: =SUM(AJ37:AJ43)/AH44 -> 33.857143 | AK44: =SUM(AK37:AK43)/AH44 -> 3 | AL44: =SUM(AL37:AL43)/AH44 -> 3.2857143 | AM44: =SUM(AM37:AM43)/AH44 -> 3.8571429 | AN44: =SUM(AK44:AM44)/3 -> 3.3809524 | AO44: 14 | AP44: =AC44/AH44 -> 0
A45: 5th week | D45: 5th week | U45: =D45 -> 5th week | AI45: =U45 -> 5th week
A46: 曜日 | B46: 日にち | C46: S | D46: 曜日 | E46: 日にち | F46: 客数 | G46: 料理売上 | H46: 料理単価 | I46: 飲料売上 | J46: 飲料単価 | K46: その他売上 | L46: 物販 | M46: 売上合計 | N46: 合計単価 | R46: 労働時間数 | S46: 人時売上高 | U46: 最低 | V46: 最高 | W46: 12時 | X46: 15時 | Y46: 18時 | Z46: Ave | AB46: ■天候要因 | AD46: 評価点 | AI46: 最低 | AJ46: 最高 | AK46: 12時 | AL46: 15時 | AM46: 18時 | AN46: Ave | AP46: ■天候要因 | AR46: 評価点
A47: 日 | B47: 25 | D47: 日 | E47: =B47 -> 25 | F47: 659 | G47: 1393200 | H47: =G47/F47 -> 2114.1123 | I47: 794950 | J47: =I47/F47 -> 1206.2974 | K47: 44660 | L47: 5940 | M47: =G47+I47+K47+L47 -> 2238750 | N47: =M47/F47 -> 3397.1927 | S47: =M47/R47 -> #DIV/0! | U47: 20.2 | V47: 28.9 | W47: 5 | X47: 3 | Y47: 3 | Z47: =SUM(W47:Y47)/3 -> 3.6666667 | AB47: 晴れ（33度まで） | AD47: 5 | AI47: 26.4 | AJ47: 30.7 | AK47: 1 | AL47: 1 | AM47: 3 | AN47: =SUM(AK47:AM47)/3 -> 1.6666667 | AP47: 晴れ（33度まで） | AR47: 5
A48: 月 | B48: 26 | D48: 月 | E48: =B48 -> 26 | F48: 202 | G48: 560400 | H48: =G48/F48 -> 2774.2574 | I48: 302700 | J48: =I48/F48 -> 1498.5149 | K48: 4950 | M48: =G48+I48+K48+L48 -> 868050 | N48: =M48/F48 -> 4297.2772 | S48: =M48/R48 -> #DIV/0! | U48: 21.5 | V48: 28.3 | W48: 3 | X48: 3 | Y48: 3 | Z48: =SUM(W48:Y48)/3 -> 3 | AB48: 晴れ（25度以下） | AD48: 4 | AI48: 23.3 | AJ48: 27.8 | AK48: 5 | AL48: 5 | AM48: 5 | AN48: =SUM(AK48:AM48)/3 -> 5 | AP48: 晴れ（25度以下） | AR48: 4
A49: 火 | B49: 27 | D49: 火 | E49: =B49 -> 27 | F49: 100 | G49: 297950 | H49: =G49/F49 -> 2979.5 | I49: 164800 | J49: =I49/F49 -> 1648 | K49: 234596 | M49: =G49+I49+K49+L49 -> 697346 | N49: =M49/F49 -> 6973.46 | S49: =M49/R49 -> #DIV/0! | U49: 22.3 | V49: 25.2 | W49: 1 | X49: 1 | Y49: 1 | Z49: =SUM(W49:Y49)/3 -> 1 | AB49: 晴れ（33度以上）曇25度以上 | AD49: 3 | AI49: 21.2 | AJ49: 27.2 | AK49: 3 | AL49: 3 | AM49: 3 | AN49: =SUM(AK49:AM49)/3 -> 3 | AP49: 晴れ（33度以上）曇25度以上 | AR49: 3
A50: 水 | B50: 28 | D50: 水 | E50: =B50 -> 28 | F50: 229 | G50: 602900 | H50: =G50/F50 -> 2632.7511 | I50: 359350 | J50: =I50/F50 -> 1569.214 | K50: 28270 | M50: =G50+I50+K50+L50 -> 990520 | N50: =M50/F50 -> 4325.4148 | S50: =M50/R50 -> #DIV/0! | U50: 19.5 | V50: 28.5 | W50: 5 | X50: 5 | Y50: 3 | Z50: =SUM(W50:Y50)/3 -> 4.3333333 | AB50: 曇 | AD50: 2 | AI50: 22.3 | AJ50: 27.7 | AK50: 5 | AL50: 5 | AM50: 5 | AN50: =SUM(AK50:AM50)/3 -> 5 | AP50: 曇 | AR50: 2
A51: 木 | B51: 29 | D51: 木 | E51: =B51 -> 29 | F51: 249 | G51: 729600 | H51: =G51/F51 -> 2930.1205 | I51: 399500 | J51: =I51/F51 -> 1604.4177 | K51: 18040 | L51: 2970 | M51: =G51+I51+K51+L51 -> 1150110 | N51: =M51/F51 -> 4618.9157 | S51: =M51/R51 -> #DIV/0! | U51: 19.8 | V51: 30.6 | W51: 5 | X51: 3 | Y51: 3 | Z51: =SUM(W51:Y51)/3 -> 3.6666667 | AB51: 雨 | AD51: 1 | AI51: 23.5 | AJ51: 31.1 | AK51: 5 | AL51: 5 | AM51: 3 | AN51: =SUM(AK51:AM51)/3 -> 4.3333333 | AP51: 雨 | AR51: 1
A52: 金 | B52: 30 | D52: 金 | E52: =B52 -> 30 | F52: 371 | G52: 1347850 | H52: =G52/F52 -> 3633.0189 | I52: 653450 | J52: =I52/F52 -> 1761.3208 | K52: 25850 | M52: =G52+I52+K52+L52 -> 2027150 | N52: =M52/F52 -> 5464.0162 | S52: =M52/R52 -> #DIV/0! | U52: 23.5 | V52: 30.3 | W52: 5 | X52: 1 | Y52: 1 | Z52: =SUM(W52:Y52)/3 -> 2.3333333 | AB52: 豪雨・雷雨 | AD52: 0 | AN52: =SUM(AK52:AM52)/3 -> 0 | AP52: 豪雨・雷雨 | AR52: 0
A53: 土 | B53: 31 | D53: 土 | E53: =B53 -> 31 | F53: 521 | G53: 1455450 | H53: =G53/F53 -> 2793.5701 | I53: 765150 | J53: =I53/F53 -> 1468.618 | K53: 66880 | M53: =G53+I53+K53+L53 -> 2287480 | N53: =M53/F53 -> 4390.5566 | S53: =M53/R53 -> #DIV/0! | U53: 21.7 | V53: 28 | W53: 1 | X53: 3 | Y53: 5 | Z53: =SUM(W53:Y53)/3 -> 3 | AB53: ※5.6月は18時は最低気温を採用。7月〜は最高気温を採用。 | AN53: =SUM(AK53:AM53)/3 -> 0 | AP53: ※5.6月は18時は最低気温を採用。7月〜は最高気温を採用。
A54: SUB TOTAL | C54: =#REF! -> #REF! | D54: SUB TOTAL | F54: =SUM(F47:F53) -> 2331 | G54: =SUM(G47:G53) -> 6387350 | H54: =G54/F54 -> 2740.1759 | I54: =SUM(I47:I53) -> 3439900 | J54: =I54/F54 -> 1475.7186 | K54: =SUM(K47:K53) -> 423246 | L54: =SUM(L47:L53) -> 8910 | M54: =G54+I54+K54+L54 -> 10259406 | N54: =M54/F54 -> 4401.2896 | R54: =SUM(R47:R53) -> 0 | S54: =M54/R54 -> #DIV/0! | T54: 7 | U54: =SUM(U47:U53)/T54 -> 21.214286 | V54: =SUM(V47:V53)/T54 -> 28.542857 | W54: =SUM(W47:W53)/T54 -> 3.5714286 | X54: =SUM(X47:X53)/T54 -> 2.7142857 | Y54: =SUM(Y47:Y53)/T54 -> 2.7142857 | Z54: =SUM(W54:Y54)/3 -> 3 | AA54: 15 | AB54: =M54/T54 -> 1465629.4 | AH54: 5 | AI54: =SUM(AI47:AI53)/AH54 -> 23.34 | AJ54: =SUM(AJ47:AJ53)/AH54 -> 28.9 | AK54: =SUM(AK47:AK53)/AH54 -> 3.8 | AL54: =SUM(AL47:AL53)/AH54 -> 3.8 | AM54: =SUM(AM47:AM53)/AH54 -> 3.8 | AN54: =SUM(AK54:AM54)/3 -> 3.8 | AO54: 15 | AP54: =AC54/AH54 -> 0
A55: 6th week | D55: 6th week | U55: =D55 -> 6th week | AI55: =U55 -> 6th week
A56: 曜日 | B56: 日にち | C56: S | D56: 曜日 | E56: 日にち | F56: 客数 | G56: 料理売上 | H56: 料理単価 | I56: 飲料売上 | J56: 飲料単価 | K56: その他売上 | L56: 物販 | M56: 売上合計 | N56: 合計単価 | R56: 労働時間数 | S56: 人時売上高 | U56: 最低 | V56: 最高 | W56: 12時 | X56: 15時 | Y56: 18時 | Z56: Ave | AB56: ■天候要因 | AD56: 評価点 | AI56: 最低 | AJ56: 最高 | AK56: 12時 | AL56: 15時 | AM56: 18時 | AN56: Ave | AP56: ■天候要因 | AR56: 評価点
A57: 日 | D57: 日 | E57: =B57 -> 0 | H57: =G57/F57 -> #DIV/0! | J57: =I57/F57 -> #DIV/0! | K57: 0 | M57: =G57+I57+K57+L57 -> 0 | N57: =M57/F57 -> #DIV/0! | S57: =M57/R57 -> #DIV/0! | Z57: =SUM(W57:Y57)/3 -> 0 | AB57: 晴れ（33度まで） | AD57: 5 | AN57: =SUM(AK57:AM57)/3 -> 0 | AP57: 晴れ（33度まで） | AR57: 5
A58: 月 | D58: 月 | E58: =B58 -> 0 | H58: =G58/F58 -> #DIV/0! | J58: =I58/F58 -> #DIV/0! | K58: 0 | M58: =G58+I58+K58+L58 -> 0 | N58: =M58/F58 -> #DIV/0! | S58: =M58/R58 -> #DIV/0! | Z58: =SUM(W58:Y58)/3 -> 0 | AB58: 晴れ（25度以下） | AD58: 4 | AN58: =SUM(AK58:AM58)/3 -> 0 | AP58: 晴れ（25度以下） | AR58: 4
A59: 火 | D59: 火 | E59: =B59 -> 0 | H59: =G59/F59 -> #DIV/0! | J59: =I59/F59 -> #DIV/0! | K59: 0 | M59: =G59+I59+K59+L59 -> 0 | N59: =M59/F59 -> #DIV/0! | S59: =M59/R59 -> #DIV/0! | Z59: =SUM(W59:Y59)/3 -> 0 | AB59: 晴れ（33度以上）曇25度以上 | AD59: 3 | AN59: =SUM(AK59:AM59)/3 -> 0 | AP59: 晴れ（33度以上）曇25度以上 | AR59: 3
A60: 水 | D60: 水 | E60: =B60 -> 0 | H60: =G60/F60 -> #DIV/0! | J60: =I60/F60 -> #DIV/0! | K60: 0 | M60: =G60+I60+K60+L60 -> 0 | N60: =M60/F60 -> #DIV/0! | S60: =M60/R60 -> #DIV/0! | Z60: =SUM(W60:Y60)/3 -> 0 | AB60: 曇 | AD60: 2 | AN60: =SUM(AK60:AM60)/3 -> 0 | AP60: 曇 | AR60: 2
A61: 木 | D61: 木 | E61: =B61 -> 0 | H61: =G61/F61 -> #DIV/0! | J61: =I61/F61 -> #DIV/0! | M61: =G61+I61+K61+L61 -> 0 | N61: =M61/F61 -> #DIV/0! | S61: =M61/R61 -> #DIV/0! | Z61: =SUM(W61:Y61)/3 -> 0 | AB61: 雨 | AD61: 1 | AN61: =SUM(AK61:AM61)/3 -> 0 | AP61: 雨 | AR61: 1
A62: 金 | D62: 金 | E62: =B62 -> 0 | H62: =G62/F62 -> #DIV/0! | I62: 0 | J62: =I62/F62 -> #DIV/0! | M62: =G62+I62+K62+L62 -> 0 | N62: =M62/F62 -> #DIV/0! | S62: =M62/R62 -> #DIV/0! | Z62: =SUM(W62:Y62)/3 -> 0 | AB62: 豪雨・雷雨 | AD62: 0 | AN62: =SUM(AK62:AM62)/3 -> 0 | AP62: 豪雨・雷雨 | AR62: 0
A63: 土 | D63: 土 | E63: =B63 -> 0 | H63: =G63/F63 -> #DIV/0! | I63: 0 | J63: =I63/F63 -> #DIV/0! | M63: =G63+I63+K63+L63 -> 0 | N63: =M63/F63 -> #DIV/0! | S63: =M63/R63 -> #DIV/0! | Z63: =SUM(W63:Y63)/3 -> 0 | AB63: ※5.6月は18時は最低気温を採用。7月〜は最高気温を採用。 | AN63: =SUM(AK63:AM63)/3 -> 0 | AP63: ※5.6月は18時は最低気温を採用。7月〜は最高気温を採用。
A64: SUB TOTAL | C64: =#REF! -> #REF! | D64: SUB TOTAL | F64: =SUM(F57:F63) -> 0 | G64: =SUM(G57:G63) -> 0 | H64: =G64/F64 -> #DIV/0! | I64: =SUM(I57:I63) -> 0 | J64: =I64/F64 -> #DIV/0! | K64: =SUM(K57:K63) -> 0 | L64: =SUM(L57:L63) -> 0 | M64: =G64+I64+K64+L64 -> 0 | N64: =M64/F64 -> #DIV/0! | R64: =SUM(R57:R63) -> 0 | S64: =M64/R64 -> #DIV/0! | U64: =SUM(U57:U63)/T64 -> #DIV/0! | V64: =SUM(V57:V63)/T64 -> #DIV/0! | W64: =SUM(W57:W63)/T64 -> #DIV/0! | X64: =SUM(X57:X63)/T64 -> #DIV/0! | Y64: =SUM(Y57:Y63)/T64 -> #DIV/0! | Z64: =SUM(W64:Y64)/3 -> #DIV/0! | AB64: =M64/T64 -> #DIV/0! | AI64: =SUM(AI57:AI63)/AH64 -> #DIV/0! | AJ64: =SUM(AJ57:AJ63)/AH64 -> #DIV/0! | AK64: =SUM(AK57:AK63)/AH64 -> #DIV/0! | AL64: =SUM(AL57:AL63)/AH64 -> #DIV/0! | AM64: =SUM(AM57:AM63)/AH64 -> #DIV/0! | AN64: =SUM(AK64:AM64)/3 -> #DIV/0! | AP64: =AC64/AH64 -> #DIV/0!
A65: TOTAL | D65: TOTAL | U65: =D65 -> TOTAL | AI65: =U65 -> TOTAL
A66: 曜日 | B66: 日数 | D66: 曜日 | E66: 日数 | F66: 客数 | G66: 料理売上 | H66: 料理単価 | I66: 飲料売上 | J66: 飲料単価 | M66: 合計売上実績 | N66: 合計単価 | R66: 労働時間数 | S66: 人時売上高 | U66: 最低 | V66: 最高 | W66: 12時 | X66: 15時 | Y66: 18時 | Z66: Ave | AB66: 2024年 8月 天候実績 | AI66: 最低 | AJ66: 最高 | AK66: 12時 | AL66: 15時 | AM66: 18時 | AN66: Ave | AP66: 2023年 8月 天候実績対比
A67: 日 | D67: 日 | F67: =F7+F17+F27+F37+F47+F57 -> 2194 | G67: =G7+G17+G27+G37+G47+G57 -> 5604300 | H67: =G67/F67 -> 2554.3756 | I67: =I7+I17+I27+I37+I47+I57 -> 3004660 | J67: =I67/F67 -> 1369.4895 | K67: =K7+K17+K27+K37+K47+K57 -> 127600 | L67: =L7+L17+L27+L37+L47+L57 -> 20790 | M67: =M7+M17+M27+M37+M47+M57 -> 8757350 | N67: =N7+N17+N27+N37+N47+N57 -> #DIV/0! | R67: =R7+R17+R27+R37+R47+R57 -> 0 | S67: =M67/R67 -> #DIV/0! | U67: =U7+U17+U27+U37+U47+U57 -> 84.7 | V67: =V7+V17+V27+V37+V47+V57 -> 107 | W67: =W7+W17+W37+W47+W27+W57 -> 17 | X67: =X7+X17+X37+X47+X27+X57 -> 15 | Y67: =Y7+Y17+Y37+Y47+Y27+Y57 -> 15 | Z67: =SUM(W67:Y67)/3 -> 15.666667 | AB67: 天候状況 | AD67: ポイント | AE67: 2024日数 | AF67: 2024合計 | AG67: 比率 | AI67: =AI7+AI17+AI27+AI37+AI47+AI57 -> 96.5 | AJ67: =AJ7+AJ17+AJ27+AJ37+AJ47+AJ57 -> 116.7 | AK67: =AK7+AK17+AK37+AK47+AK27+AK57 -> 6 | AL67: =AL7+AL17+AL37+AL47+AL27+AL57 -> 14 | AM67: =AM7+AM17+AM37+AM47+AM27+AM57 -> 12 | AN67: =SUM(AK67:AM67)/3 -> 10.666667 | AP67: 天候状況 | AR67: ポイント | AS67: 2023日数 | AT67: 2023合計 | AU67: 比率
A68: 月 | D68: 月 | F68: =F8+F18+F28+F38+F48+F58 -> 1446 | G68: =G8+G18+G28+G38+G48+G58 -> 3777100 | H68: =G68/F68 -> 2612.1024 | I68: =I8+I18+I28+I38+I48+I58 -> 1976420 | J68: =I68/F68 -> 1366.8188 | K68: =K8+K18+K28+K38+K48+K58 -> 75130 | L68: =L8+L18+L28+L38+L48+L58 -> 2970 | M68: =M8+M18+M28+M38+M48+M58 -> 5831620 | N68: =N8+N18+N28+N38+N48+N58 -> #DIV/0! | R68: =R8+R18+R28+R38+R48+R58 -> 0 | S68: =M68/R68 -> #DIV/0! | U68: =U8+U18+U28+U38+U48+U58 -> 84.7 | V68: =V8+V18+V28+V38+V48+V58 -> 116.2 | W68: =W8+W18+W38+W48+W28+W58 -> 13 | X68: =X8+X18+X38+X48+X28+X58 -> 11 | Y68: =Y8+Y18+Y38+Y48+Y28+Y58 -> 11 | Z68: =SUM(W68:Y68)/3 -> 11.666667 | AB68: 晴れ（33度まで） | AD68: 5 | AE68: 27 | AF68: =AD68*AE68 -> 135 | AG68: =(AE68+AE69+AE70)/AE74 -> 0.69892473 | AI68: =AI8+AI18+AI28+AI38+AI48+AI58 -> 90 | AJ68: =AJ8+AJ18+AJ28+AJ38+AJ48+AJ58 -> 117 | AK68: =AK8+AK18+AK38+AK48+AK28+AK58 -> 18 | AL68: =AL8+AL18+AL38+AL48+AL28+AL58 -> 16 | AM68: =AM8+AM18+AM38+AM48+AM28+AM58 -> 15 | AN68: =SUM(AK68:AM68)/3 -> 16.333333 | AP68: 晴れ（33度まで） | AR68: 5 | AS68: 31 | AT68: =AR68*AS68 -> 155 | AU68: =(AS68+AS69+AS70)/AS74 -> 0.82795699
A69: 火 | D69: 火 | F69: =F9+F19+F29+F39+F49+F59 -> 1287 | G69: =G9+G19+G29+G39+G49+G59 -> 3621550 | H69: =G69/F69 -> 2813.9472 | I69: =I9+I19+I29+I39+I49+I59 -> 1894550 | J69: =I69/F69 -> 1472.0668 | K69: =K9+K19+K29+K39+K49+K59 -> 325786 | L69: =L9+L19+L29+L39+L49+L59 -> 0 | M69: =M9+M19+M29+M39+M49+M59 -> 5841886 | N69: =N9+N19+N29+N39+N49+N59 -> #DIV/0! | R69: =R9+R19+R29+R39+R49+R59 -> 0 | S69: =M69/R69 -> #DIV/0! | U69: =U9+U19+U29+U39+U49+U59 -> 88.1 | V69: =V9+V19+V29+V39+V49+V59 -> 105.2 | W69: =W9+W19+W39+W49+W29+W59 -> 6 | X69: =X9+X19+X39+X49+X29+X59 -> 8 | Y69: =Y9+Y19+Y39+Y49+Y29+Y59 -> 10 | Z69: =SUM(W69:Y69)/3 -> 8 | AB69: 晴れ（25度以下） | AD69: 4 | AF69: =AD69*AE69 -> 0 | AI69: =AI9+AI19+AI29+AI39+AI49+AI59 -> 113.2 | AJ69: =AJ9+AJ19+AJ29+AJ39+AJ49+AJ59 -> 149.2 | AK69: =AK9+AK19+AK39+AK49+AK29+AK59 -> 17 | AL69: =AL9+AL19+AL39+AL49+AL29+AL59 -> 13 | AM69: =AM9+AM19+AM39+AM49+AM29+AM59 -> 20 | AN69: =SUM(AK69:AM69)/3 -> 16.666667 | AP69: 晴れ（25度以下） | AR69: 4 | AS69: 6 | AT69: =AR69*AS69 -> 24
A70: 水 | D70: 水 | F70: =F10+F20+F30+F40+F50+F60 -> 1591 | G70: =G10+G20+G30+G40+G50+G60 -> 4411850 | H70: =G70/F70 -> 2773.0044 | I70: =I10+I20+I30+I40+I50+I60 -> 2367150 | J70: =I70/F70 -> 1487.8378 | K70: =K10+K20+K30+K40+K50+K60 -> 124960 | L70: =L10+L20+L30+L40+L50+L60 -> 8910 | M70: =M10+M20+M30+M40+M50+M60 -> 6912870 | N70: =N10+N20+N30+N40+N50+N60 -> #DIV/0! | R70: =R10+R20+R30+R40+R50+R60 -> 0 | S70: =M70/R70 -> #DIV/0! | U70: =U10+U20+U30+U40+U50+U60 -> 84.2 | V70: =V10+V20+V30+V40+V50+V60 -> 117.7 | W70: =W10+W20+W40+W50+W30+W60 -> 16 | X70: =X10+X20+X40+X50+X30+X60 -> 14 | Y70: =Y10+Y20+Y40+Y50+Y30+Y60 -> 12 | Z70: =SUM(W70:Y70)/3 -> 14 | AB70: 晴れ（33度以上15以下） 曇25度以上 | AD70: 3 | AE70: 38 | AF70: =AD70*AE70 -> 114 | AI70: =AI10+AI20+AI30+AI40+AI50+AI60 -> 120.4 | AJ70: =AJ10+AJ20+AJ30+AJ40+AJ50+AJ60 -> 155.3 | AK70: =AK10+AK20+AK40+AK50+AK30+AK60 -> 13 | AL70: =AL10+AL20+AL40+AL50+AL30+AL60 -> 15 | AM70: =AM10+AM20+AM40+AM50+AM30+AM60 -> 20 | AN70: =SUM(AK70:AM70)/3 -> 16 | AP70: 晴れ（33度以上15以下） 曇25度以上 | AR70: 3 | AS70: 40 | AT70: =AR70*AS70 -> 120
A71: 木 | D71: 木 | F71: =F21+F11+F31+F41+F51+F61 -> 2001 | G71: =G21+G11+G31+G41+G51+G61 -> 5624000 | H71: =G71/F71 -> 2810.5947 | I71: =I21+I11+I31+I41+I51+I61 -> 3040150 | J71: =I71/F71 -> 1519.3153 | K71: =K21+K11+K31+K41+K51+K61 -> 175560 | L71: =L21+L11+L31+L41+L51+L61 -> 2970 | M71: =M21+M11+M31+M41+M51+M61 -> 8842680 | N71: =N21+N11+N31+N41+N51+N61 -> #DIV/0! | R71: =R21+R11+R31+R41+R51+R61 -> 0 | S71: =M71/R71 -> #DIV/0! | U71: =U11+U21+U31+U41+U51+U61 -> 105.9 | V71: =V11+V21+V31+V41+V51+V61 -> 142.4 | W71: =W11+W21+W41+W51+W31+W61 -> 19 | X71: =X11+X21+X41+X51+X31+X61 -> 7 | Y71: =Y11+Y21+Y41+Y51+Y31+Y61 -> 15 | Z71: =SUM(W71:Y71)/3 -> 13.666667 | AB71: 曇 | AD71: 2 | AE71: 6 | AF71: =AD71*AE71 -> 12 | AG71: =(AE71+AE72+AE73)/AE74 -> 0.30107527 | AI71: =AI11+AI21+AI31+AI41+AI51+AI61 -> 126.3 | AJ71: =AJ11+AJ21+AJ31+AJ41+AJ51+AJ61 -> 160.5 | AK71: =AK11+AK21+AK41+AK51+AK31+AK61 -> 21 | AL71: =AL11+AL21+AL41+AL51+AL31+AL61 -> 15 | AM71: =AM11+AM21+AM41+AM51+AM31+AM61 -> 18 | AN71: =SUM(AK71:AM71)/3 -> 18 | AP71: 曇 | AR71: 2 | AS71: 0 | AT71: =AR71*AS71 -> 0 | AU71: =(AS71+AS72+AS73)/AS74 -> 0.17204301
A72: 金 | D72: 金 | F72: =F12+F22+F32+F42+F52+F62 -> 2554 | G72: =G12+G22+G32+G42+G52+G62 -> 7945650 | H72: =G72/F72 -> 3111.0611 | I72: =I12+I22+I32+I42+I52+I62 -> 4221100 | J72: =I72/F72 -> 1652.7408 | K72: =K12+K22+K32+K42+K52+K62 -> 166430 | L72: =L12+L22+L32+L42+L52+L62 -> 32670 | M72: =M12+M22+M32+M42+M52+M62 -> 12365850 | N72: =N12+N22+N32+N42+N52+N62 -> #DIV/0! | R72: =R12+R22+R32+R42+R52+R62 -> 0 | S72: =M72/R72 -> #DIV/0! | U72: =U12+U22+U32+U42+U52+U62 -> 117 | V72: =V12+V22+V32+V42+V52+V62 -> 150.5 | W72: =W12+W22+W42+W52+W32+W62 -> 15 | X72: =X12+X22+X42+X52+X32+X62 -> 11 | Y72: =Y12+Y22+Y42+Y52+Y32+Y62 -> 11 | Z72: =SUM(W72:Y72)/3 -> 12.333333 | AB72: 雨 | AD72: 1 | AE72: 22 | AF72: =AD72*AE72 -> 22 | AI72: =AI12+AI22+AI32+AI42+AI52+AI62 -> 101.2 | AJ72: =AJ12+AJ22+AJ32+AJ42+AJ52+AJ62 -> 129 | AK72: =AK12+AK22+AK42+AK52+AK32+AK62 -> 14 | AL72: =AL12+AL22+AL42+AL52+AL32+AL62 -> 12 | AM72: =AM12+AM22+AM42+AM52+AM32+AM62 -> 13 | AN72: =SUM(AK72:AM72)/3 -> 13 | AP72: 雨 | AR72: 1 | AS72: 16 | AT72: =AR72*AS72 -> 16
A73: 土 | D73: 土 | F73: =F13+F23+F33+F43+F53+F63 -> 2818 | G73: =G13+G23+G33+G43+G53+G63 -> 8160550 | H73: =G73/F73 -> 2895.8659 | I73: =I13+I23+I33+I43+I53+I63 -> 4414280 | J73: =I73/F73 -> 1566.4585 | K73: =K13+K23+K33+K43+K53+K63 -> 317570 | L73: =L13+L23+L33+L43+L53+L63 -> 17820 | M73: =M13+M23+M33+M43+M53+M63 -> 12910220 | N73: =N13+N23+N33+N43+N53+N63 -> #DIV/0! | R73: =R13+R23+R33+R43+R53+R63 -> 0 | S73: =M73/R73 -> #DIV/0! | T73: =T14+T24+T34+T44+T54+T64 -> 31 | U73: =U13+U23+U33+U43+U53+U63 -> 118.8 | V73: =V13+V23+V33+V43+V53+V63 -> 142.7 | W73: =W13+W23+W43+W53+W33+W63 -> 17 | X73: =X13+X23+X43+X53+X33+X63 -> 19 | Y73: =Y13+Y23+Y43+Y53+Y33+Y63 -> 21 | Z73: =SUM(W73:Y73)/3 -> 19 | AB73: 豪雨・雷雨 | AD73: 0 | AF73: =AD73*AE73 -> 0 | AH73: =AH14+AH24+AH34+AH44+AH54+AH64 -> 31 | AI73: =AI13+AI23+AI33+AI43+AI53+AI63 -> 95.8 | AJ73: =AJ13+AJ23+AJ33+AJ43+AJ53+AJ63 -> 129.2 | AK73: =AK13+AK23+AK43+AK53+AK33+AK63 -> 14 | AL73: =AL13+AL23+AL43+AL53+AL33+AL63 -> 12 | AM73: =AM13+AM23+AM43+AM53+AM33+AM63 -> 17 | AN73: =SUM(AK73:AM73)/3 -> 14.333333 | AP73: 豪雨・雷雨 | AR73: 0 | AT73: =AR73*AS73 -> 0
A74: TOTAL | B74: =SUM(B67:B73) -> 0 | C74: =#REF! -> #REF! | D74: TOTAL | E74: =SUM(E67:E73) -> 0 | F74: =SUM(F67:F73) -> 13891 | G74: =SUM(G67:G73) -> 39145000 | H74: =G74/F74 -> 2818.0117 | I74: =SUM(I67:I73) -> 20918310 | J74: =I74/F74 -> 1505.8894 | K74: =SUM(K67:K73) -> 1313036 | L74: =SUM(L67:L73) -> 86130 | M74: =SUM(M67:M73) -> 61462476 | N74: =M74/F74 -> 4424.6257 | R74: =SUM(R67:R73) -> 0 | S74: =M74/R74 -> #DIV/0! | U74: =SUM(U67:U73)/T73 -> 22.045161 | V74: =SUM(V67:V73)/T73 -> 28.441935 | W74: =SUM(W67:W73)/T73 -> 3.3225806 | X74: =SUM(X67:X73)/T73 -> 2.7419355 | Y74: =SUM(Y67:Y73)/T73 -> 3.0645161 | Z74: =SUM(W74:Y74)/3 -> 3.0430108 | AB74: TOTAL | AE74: =SUM(AE68:AE73) -> 93 | AF74: =SUM(AF68:AF73) -> 283 | AG74: =AG68+AG71 -> 1 | AI74: =SUM(AI67:AI73)/AH73 -> 23.980645 | AJ74: =SUM(AJ67:AJ73)/AH73 -> 30.867742 | AK74: =SUM(AK67:AK73)/AH73 -> 3.3225806 | AL74: =SUM(AL67:AL73)/AH73 -> 3.1290323 | AM74: =SUM(AM67:AM73)/AH73 -> 3.7096774 | AN74: =SUM(AK74:AM74)/3 -> 3.3870968 | AP74: TOTAL | AS74: =SUM(AS68:AS73) -> 93 | AT74: =SUM(AT68:AT73) -> 315 | AU74: =AU68+AU71 -> 1
A75: ■対比 | D75: ■対比
A77: ランチ | D77: ランチ | F77: 予算
F78: ランチ
F79: 客数 | I79: F売上 | M79: B売上
I80: =#REF!*F80 -> #REF! | M80: =#REF!*F80 -> #REF!
F82: ■予算差異
F83: 客数 | I83: F売上 | M83: B売上
F84: =F74-F80 -> 13891 | I84: =I74-I80 -> #REF! | M84: =M74-M80 -> #REF!
F85: =F74/F80 -> #DIV/0! | I85: =I74/I80 -> #REF! | M85: =M74/M80 -> #REF!
F86: ■前年値（数値残っていない休業）
F87: 客数 | I87: F売上 | M87: B売上
F89: ■前年差異
F90: 客数 | I90: F売上 | M90: B売上
F91: =F74-F88 -> 13891 | I91: =I74-I88 -> 20918310 | M91: =M74-M88 -> 61462476
F92: =F74/F88 -> #DIV/0! | I92: =I74/I88 -> #DIV/0! | M92: =M74/M88 -> #DIV/0!
A93: 構成比率 | F93: =F74/30 -> 463.03333 | K93: 税抜売上 | M93: =M74/1.1 -> 55874978 | N93: 対予測達成率 | R93: =M93/#REF! -> #REF! | S93: =M93-#REF! -> #REF! | AC93: =AE93/AS93 -> 0.8984127 | AE93: =AF74/AE74 -> 3.0430108 | AQ93: =AC93/BE93 -> #DIV/0! | AS93: =AT74/AS74 -> 3.3870968
G94: =G74/1.1 -> 35586364 | I94: =I74/1.1 -> 19016645 | N94: 合計予算進捗 | R94: ウチその他対比 | AE94: =AE93/AS93 -> 0.8984127
I95: 売上合計予算対比 | N95: =M93/#REF! -> #REF! | R95: =K94/#REF! -> #REF! | S95: =M93-#REF! -> #REF!
L97: 前年比 | M97: 31
A98: ■モデルシフト | I98: 7615389 | M98: 31 | N98: =M97-M98 -> 0
A99: モデルシフト カテゴリー | I99: =I98/I94 -> 0.40045911 | M99: =M93/M98 -> 1802418.7
A100: TOP1 | F100: =I74+#REF!+'2024.6月実績'!L93+'2024.5月実績'!L93 -> #REF! | L100: 予算まで | M100: =#REF!-M93 -> #REF! | S100: =M93 -> 55874978
A101: TOP2 | F101: 18147154 | L101: 1日あたり | M101: =M100/N98 -> #REF! | S101: =#REF! -> #REF! | T101: 前年同日
A102: ON1 | F102: =F101/F100 -> #REF! | L102: 目標 | M102: 54000000 | N102: =M102*1.1 -> 59400000 | S102: =S100-S101 -> #REF! | T102: 差異
A103: ON2 | L103: 目標まで | M103: =M102-M93 -> -1874978.2 | S103: =S100/S101 -> #REF!
A104: ショルダー | L104: 1日あたり | M104: =M103/N98 -> #DIV/0!
...

Sheet 2024.7月実績
A1: ■R6年度 ビアガーデン売上実績
A2: 7月 | L2: =L14+L24+L34+L44+L54+L64 -> 52374680 | R2: 31
A3: FOOD予測 | C3: ビアガーデン7月 TOTAL実績 | N3: 客数 | R3: 売上
A4: 予算 | C4: 実績 | E4: 客数 | G4: 客単価 | I4: 売上予算 | M4: 1日平均 | R4: =L4/R2 -> 0 | T4: 天候要因（売上との関連性を数値化する） | AH4: 天候要因（売上との関連性を数値化する）
A5: 1st week | C5: 1st week | T5: =C5 -> 1st week | AH5: =U5 -> 0
A6: 曜日 | B6: 日にち | C6: 曜日 | D6: 日にち | E6: 客数 | F6: 料理売上 | G6: 料理単価 | H6: 飲料売上 | I6: 飲料単価 | J6: その他売上 | K6: 物販 | L6: 売上合計 | M6: 合計単価 | Q6: 労働時間数 | R6: 人時売上高 | T6: 最低 | U6: 最高 | V6: 12時 | W6: 15時 | X6: 18時 | Y6: Ave | AA6: ■天候要因 | AC6: 評価点 | AH6: 最低 | AI6: 最高 | AJ6: 12時 | AK6: 15時 | AL6: 18時 | AM6: Ave | AO6: ■天候要因 | AQ6: 評価点
A7: 日 | C7: 日 | D7: =B7 -> 0 | G7: =F7/E7 -> #DIV/0! | I7: =H7/E7 -> #DIV/0! | L7: =F7+H7+J7 -> 0 | M7: =L7/E7 -> #DIV/0! | R7: =L7/Q7 -> #DIV/0! | Y7: =SUM(V7:X7)/3 -> 0 | AA7: 晴れ（33度まで） | AC7: 5 | AM7: =SUM(AJ7:AL7)/3 -> 0 | AO7: 晴れ（33度まで） | AQ7: 5
A8: 月 | B8: 1 | C8: 月 | D8: =B8 -> 1 | E8: 52 | F8: 165300 | G8: =F8/E8 -> 3178.8462 | H8: 88400 | I8: =H8/E8 -> 1700 | L8: =F8+H8+J8 -> 253700 | M8: =L8/E8 -> 4878.8462 | R8: =L8/Q8 -> #DIV/0! | T8: 18.6 | U8: 23.8 | V8: 1 | W8: 1 | X8: 1 | Y8: =SUM(V8:X8)/3 -> 1 | AA8: 晴れ（25度以下） | AC8: 4 | AM8: =SUM(AJ8:AL8)/3 -> 0 | AO8: 晴れ（25度以下） | AQ8: 4
A9: 火 | B9: 2 | C9: 火 | D9: =B9 -> 2 | E9: 198 | F9: 482100 | G9: =F9/E9 -> 2434.8485 | H9: 297350 | I9: =H9/E9 -> 1501.7677 | J9: 8250 | L9: =F9+H9+J9 -> 787700 | M9: =L9/E9 -> 3978.2828 | R9: =L9/Q9 -> #DIV/0! | T9: 13.9 | U9: 24.2 | V9: 2 | W9: 4 | X9: 4 | Y9: =SUM(V9:X9)/3 -> 3.3333333 | AA9: 晴れ（33度以上）曇25度以上 | AC9: 3 | AM9: =SUM(AJ9:AL9)/3 -> 0 | AO9: 晴れ（33度以上）曇25度以上 | AQ9: 3
A10: 水 | B10: 3 | C10: 水 | D10: =B10 -> 3 | E10: 275 | F10: 670500 | G10: =F10/E10 -> 2438.1818 | H10: 390650 | I10: =H10/E10 -> 1420.5455 | J10: 4950 | L10: =F10+H10+J10 -> 1066100 | M10: =L10/E10 -> 3876.7273 | R10: =L10/Q10 -> #DIV/0! | T10: 15.2 | U10: 29.6 | V10: 5 | W10: 3 | X10: 3 | Y10: =SUM(V10:X10)/3 -> 3.6666667 | AA10: 曇 | AC10: 2 | AM10: =SUM(AJ10:AL10)/3 -> 0 | AO10: 曇 | AQ10: 2
A11: 木 | B11: 4 | C11: 木 | D11: =B11 -> 4 | E11: 193 | F11: 435200 | G11: =F11/E11 -> 2254.9223 | H11: 266750 | I11: =H11/E11 -> 1382.1244 | J11: 5500 | L11: =F11+H11+J11 -> 707450 | M11: =L11/E11 -> 3665.544 | R11: =L11/Q11 -> #DIV/0! | T11: 18.2 | U11: 28.9 | V11: 3 | W11: 3 | X11: 3 | Y11: =SUM(V11:X11)/3 -> 3 | AA11: 雨 | AC11: 1 | AM11: =SUM(AJ11:AL11)/3 -> 0 | AO11: 雨 | AQ11: 1
A12: 金 | B12: 5 | C12: 金 | D12: =B12 -> 5 | E12: 264 | F12: 768450 | G12: =F12/E12 -> 2910.7955 | H12: 439150 | I12: =H12/E12 -> 1663.447 | J12: 22550 | L12: =F12+H12+J12 -> 1230150 | M12: =L12/E12 -> 4659.6591 | R12: =L12/Q12 -> #DIV/0! | T12: 19.5 | U12: 30.5 | V12: 3 | W12: 3 | X12: 3 | Y12: =SUM(V12:X12)/3 -> 3 | AA12: 豪雨・雷雨 | AC12: 0 | AM12: =SUM(AJ12:AL12)/3 -> 0 | AO12: 豪雨・雷雨 | AQ12: 0
A13: 土 | B13: 6 | C13: 土 | D13: =B13 -> 6 | E13: 353 | F13: 1020450 | G13: =F13/E13 -> 2890.7932 | H13: 521050 | I13: =H13/E13 -> 1476.0623 | J13: 55000 | L13: =F13+H13+J13 -> 1596500 | M13: =L13/E13 -> 4522.6629 | R13: =L13/Q13 -> #DIV/0! | T13: 21 | U13: 24.9 | V13: 1 | W13: 1 | X13: 2 | Y13: =SUM(V13:X13)/3 -> 1.3333333 | AA13: ※5.6月は18時は最低気温を採用。7月〜は最高気温を採用。 | AH13: 19.6 | AI13: 21.2 | AJ13: 2 | AK13: 4 | AL13: 4 | AM13: =SUM(AJ13:AL13)/3 -> 3.3333333 | AO13: ※5.6月は18時は最低気温を採用。7月〜は最高気温を採用。
A14: SUB TOTAL | C14: SUB TOTAL | E14: =SUM(E7:E13) -> 1335 | F14: =SUM(F7:F13) -> 3542000 | G14: =F14/E14 -> 2653.1835 | H14: =SUM(H7:H13) -> 2003350 | I14: =H14/E14 -> 1500.6367 | J14: =SUM(J7:J13) -> 96250 | K14: =SUM(K7:K13) -> 0 | L14: =F14+H14+J14 -> 5641600 | M14: =L14/E14 -> 4225.9176 | Q14: =SUM(Q7:Q13) -> 0 | R14: =L14/Q14 -> #DIV/0! | S14: 6 | T14: =SUM(T7:T13)/S14 -> 17.733333 | U14: =SUM(U7:U13)/S14 -> 26.983333 | V14: =SUM(V7:V13)/S14 -> 2.5 | W14: =SUM(W7:W13)/S14 -> 2.5 | X14: =SUM(X7:X13)/S14 -> 2.6666667 | Y14: =SUM(V14:X14)/3 -> 2.5555556 | Z14: ⑥ | AA14: =L14/S14 -> 940266.67 | AF14: ※1日平均売上 | AG14: 1 | AH14: =SUM(AH7:AH13)/AG14 -> 19.6 | AI14: =SUM(AI7:AI13)/AG14 -> 21.2 | AJ14: =SUM(AJ7:AJ13)/AG14 -> 2 | AK14: =SUM(AK7:AK13)/AG14 -> 4 | AL14: =SUM(AL7:AL13)/AG14 -> 4 | AM14: =SUM(AJ14:AL14)/3 -> 3.3333333 | AN14: ⑥ | AO14: 987150 | AT14: ※1日平均売上
A15: 2nd week | C15: 2nd week | T15: =C15 -> 2nd week | AF15: ※1日平均売上 | AH15: =U15 -> 0 | AT15: ※1日平均売上
A16: 曜日 | B16: 日にち | C16: 曜日 | D16: 日にち | E16: 客数 | F16: 料理売上 | G16: 料理単価 | H16: 飲料売上 | I16: 飲料単価 | J16: その他売上 | K16: 物販 | L16: 売上合計 | M16: 合計単価 | Q16: 労働時間数 | R16: 人時売上高 | T16: 最低 | U16: 最高 | V16: 12時 | W16: 15時 | X16: 18時 | Y16: Ave | AA16: ■天候要因 | AC16: 評価点 | AH16: 最低 | AI16: 最高 | AJ16: 12時 | AK16: 15時 | AL16: 18時 | AM16: Ave | AO16: ■天候要因 | AQ16: 評価点
A17: 日 | B17: 7 | C17: 日 | D17: =B17 -> 7 | E17: 246 | F17: 749750 | G17: =F17/E17 -> 3047.7642 | H17: 382450 | I17: =H17/E17 -> 1554.6748 | J17: 13750 | L17: =F17+H17+J17 -> 1145950 | M17: =L17/E17 -> 4658.3333 | R17: =L17/Q17 -> #DIV/0! | T17: 21.7 | U17: 25 | V17: 2 | W17: 2 | X17: 2 | Y17: =SUM(V17:X17)/3 -> 2 | AA17: 晴れ（33度まで） | AC17: 5 | AH17: 17 | AI17: 22.9 | AJ17: 4 | AK17: 3 | AL17: 2 | AM17: =SUM(AJ17:AL17)/3 -> 3 | AO17: 晴れ（33度まで） | AQ17: 5
A18: 月 | B18: 8 | C18: 月 | D18: =B18 -> 8 | E18: 161 | F18: 484800 | G18: =F18/E18 -> 3011.1801 | H18: 249550 | I18: =H18/E18 -> 1550 | J18: 13200 | L18: =F18+H18+J18 -> 747550 | M18: =L18/E18 -> 4643.1677 | R18: =L18/Q18 -> #DIV/0! | T18: 19.8 | U18: 22.7 | V18: 2 | W18: 2 | X18: 2 | Y18: =SUM(V18:X18)/3 -> 2 | AA18: 晴れ（25度以下） | AC18: 4 | AH18: 17.7 | AI18: 23.9 | AJ18: 4 | AK18: 4 | AL18: 4 | AM18: =SUM(AJ18:AL18)/3 -> 4 | AO18: 晴れ（25度以下） | AQ18: 4
A19: 火 | B19: 9 | C19: 火 | D19: =B19 -> 9 | E19: 233 | F19: 694450 | G19: =F19/E19 -> 2980.4721 | H19: 379450 | I19: =H19/E19 -> 1628.5408 | J19: 28050 | L19: =F19+H19+J19 -> 1101950 | M19: =L19/E19 -> 4729.3991 | R19: =L19/Q19 -> #DIV/0! | T19: 18.6 | U19: 25.3 | V19: 2 | W19: 1 | X19: 1 | Y19: =SUM(V19:X19)/3 -> 1.3333333 | AA19: 晴れ（33度以上）曇25度以上 | AC19: 3 | AH19: 18.2 | AI19: 24.8 | AJ19: 4 | AK19: 4 | AL19: 4 | AM19: =SUM(AJ19:AL19)/3 -> 4 | AO19: 晴れ（33度以上）曇25度以上 | AQ19: 3
A20: 水 | B20: 10 | C20: 水 | D20: =B20 -> 10 | E20: 292 | F20: 817300 | G20: =F20/E20 -> 2798.9726 | H20: 472500 | I20: =H20/E20 -> 1618.1507 | J20: 5500 | L20: =F20+H20+J20 -> 1295300 | M20: =L20/E20 -> 4435.9589 | R20: =L20/Q20 -> #DIV/0! | T20: 19 | U20: 27.2 | V20: 5 | W20: 5 | X20: 3 | Y20: =SUM(V20:X20)/3 -> 4.3333333 | AA20: 曇 | AC20: 2 | AH20: 18 | AI20: 27.4 | AJ20: 5 | AK20: 5 | AL20: 4 | AM20: =SUM(AJ20:AL20)/3 -> 4.6666667 | AO20: 曇 | AQ20: 2
A21: 木 | B21: 11 | C21: 木 | D21: =B21 -> 11 | E21: 303 | F21: 893900 | G21: =F21/E21 -> 2950.165 | H21: 509800 | I21: =H21/E21 -> 1682.5083 | J21: 15400 | L21: =F21+H21+J21 -> 1419100 | M21: =L21/E21 -> 4683.4983 | R21: =L21/Q21 -> #DIV/0! | T21: 18.1 | U21: 25.9 | V21: 5 | W21: 3 | X21: 3 | Y21: =SUM(V21:X21)/3 -> 3.6666667 | AA21: 雨 | AC21: 1 | AH21: 18.4 | AI21: 25.2 | AJ21: 3 | AK21: 1 | AL21: 1 | AM21: =SUM(AJ21:AL21)/3 -> 1.6666667 | AO21: 雨 | AQ21: 1
A22: 金 | B22: 12 | C22: 金 | D22: =B22 -> 12 | E22: 402 | F22: 1206750 | G22: =F22/E22 -> 3001.8657 | H22: 648800 | I22: =H22/E22 -> 1613.9303 | J22: 33000 | L22: =F22+H22+J22 -> 1888550 | M22: =L22/E22 -> 4697.8856 | R22: =L22/Q22 -> #DIV/0! | T22: 19.5 | U22: 27.6 | V22: 5 | W22: 3 | X22: 3 | Y22: =SUM(V22:X22)/3 -> 3.6666667 | AA22: 豪雨・雷雨 | AC22: 0 | AH22: 19.2 | AI22: 26.1 | AJ22: 3 | AK22: 5 | AL22: 5 | AM22: =SUM(AJ22:AL22)/3 -> 4.3333333 | AO22: 豪雨・雷雨 | AQ22: 0
A23: 土 | B23: 13 | C23: 土 | D23: =B23 -> 13 | E23: 506 | F23: 1704150 | G23: =F23/E23 -> 3367.8854 | H23: 946300 | I23: =H23/E23 -> 1870.1581 | J23: 15400 | K23: 11880 | L23: =F23+H23+J23+K23 -> 2677730 | M23: =L23/E23 -> 5291.9565 | R23: =L23/Q23 -> #DIV/0! | T23: 19.3 | U23: 24.5 | V23: 4 | W23: 4 | X23: 4 | Y23: =SUM(V23:X23)/3 -> 4 | AA23: ※5.6月は18時は最低気温を採用。7月〜は最高気温を採用。 | AH23: 19.6 | AI23: 31.4 | AJ23: 5 | AK23: 5 | AL23: 5 | AM23: =SUM(AJ23:AL23)/3 -> 5 | AO23: ※5.6月は18時は最低気温を採用。7月〜は最高気温を採用。
A24: SUB TOTAL | C24: SUB TOTAL | E24: =SUM(E17:E23) -> 2143 | F24: =SUM(F17:F23) -> 6551100 | G24: =F24/E24 -> 3056.9762 | H24: =SUM(H17:H23) -> 3588850 | I24: =H24/E24 -> 1674.685 | J24: =SUM(J17:J23) -> 124300 | K24: =SUM(K17:K23) -> 11880 | L24: =F24+H24+J24+K24 -> 10276130 | M24: =L24/E24 -> 4795.2077 | Q24: =SUM(Q17:Q23) -> 0 | R24: =L24/Q24 -> #DIV/0! | S24: 7 | T24: =SUM(T17:T23)/S24 -> 19.428571 | U24: =SUM(U17:U23)/S24 -> 25.457143 | V24: =SUM(V17:V23)/S24 -> 3.5714286 | W24: =SUM(W17:W23)/S24 -> 2.8571429 | X24: =SUM(X17:X23)/S24 -> 2.5714286 | Y24: =SUM(V24:X24)/3 -> 3 | Z24: ⑦ | AA24: =L24/S24 -> 1468018.6 | AF24: ※1日平均売上 | AG24: 7 | AH24: =SUM(AH17:AH23)/AG24 -> 18.3 | AI24: =SUM(AI17:AI23)/AG24 -> 25.957143 | AJ24: =SUM(AJ17:AJ23)/AG24 -> 4 | AK24: =SUM(AK17:AK23)/AG24 -> 3.8571429 | AL24: =SUM(AL17:AL23)/AG24 -> 3.5714286 | AM24: =SUM(AJ24:AL24)/3 -> 3.8095238 | AN24: ⑦ | AO24: 1368342.9 | AT24: ※1日平均売上
A25: 3rd week | C25: 3rd week | T25: =C25 -> 3rd week | AH25: =U25 -> 0
A26: 曜日 | B26: 日にち | C26: 曜日 | D26: 日にち | E26: 客数 | F26: 料理売上 | G26: 料理単価 | H26: 飲料売上 | I26: 飲料単価 | J26: その他売上 | K26: 物販 | L26: 売上合計 | M26: 合計単価 | Q26: 労働時間数 | R26: 人時売上高 | T26: 最低 | U26: 最高 | V26: 12時 | W26: 15時 | X26: 18時 | Y26: Ave | AA26: ■天候要因 | AC26: 評価点 | AH26: 最低 | AI26: 最高 | AJ26: 12時 | AK26: 15時 | AL26: 18時 | AM26: Ave | AO26: ■天候要因 | AQ26: 評価点
A27: 日 | B27: 14 | C27: 日 | D27: =B27 -> 14 | E27: 639 | F27: 2019300 | G27: =F27/E27 -> 3160.0939 | H27: 1031800 | I27: =H27/E27 -> 1614.7105 | J27: 25300 | K27: 5940 | L27: =F27+H27+J27+K27 -> 3082340 | M27: =L27/E27 -> 4823.6933 | R27: =L27/Q27 -> #DIV/0! | T27: 18.5 | U27: 29.5 | V27: 5 | W27: 5 | X27: 5 | Y27: =SUM(V27:X27)/3 -> 5 | AA27: 晴れ（33度まで） | AC27: 5 | AH27: 21.3 | AI27: 31.4 | AJ27: 1 | AK27: 3 | AL27: 5 | AM27: =SUM(AJ27:AL27)/3 -> 3 | AO27: 晴れ（33度まで） | AQ27: 5
A28: 月 | B28: 15 | C28: 月 | D28: =B28 -> 15 | E28: 473 | F28: 1423750 | G28: =F28/E28 -> 3010.0423 | H28: 754950 | I28: =H28/E28 -> 1596.0888 | J28: 23650 | K28: 5940 | L28: =F28+H28+J28+K28 -> 2208290 | M28: =L28/E28 -> 4668.6892 | R28: =L28/Q28 -> #DIV/0! | T28: 20.3 | U28: 29.3 | V28: 5 | W28: 5 | X28: 5 | Y28: =SUM(V28:X28)/3 -> 5 | AA28: 晴れ（25度以下） | AC28: 4 | AH28: 20.9 | AI28: 28.4 | AJ28: 3 | AK28: 3 | AL28: 3 | AM28: =SUM(AJ28:AL28)/3 -> 3 | AO28: 晴れ（25度以下） | AQ28: 4
A29: 火 | B29: 16 | C29: 火 | D29: =B29 -> 16 | E29: 272 | F29: 731800 | G29: =F29/E29 -> 2690.4412 | H29: 407700 | I29: =H29/E29 -> 1498.8971 | J29: 3850 | K29: 2970 | L29: =F29+H29+J29+K29 -> 1146320 | M29: =L29/E29 -> 4214.4118 | R29: =L29/Q29 -> #DIV/0! | T29: 21 | U29: 30.1 | V29: 5 | W29: 5 | X29: 5 | Y29: =SUM(V29:X29)/3 -> 5 | AA29: 晴れ（33度以上）曇25度以上 | AC29: 3 | AH29: 22.3 | AI29: 30.2 | AJ29: 5 | AK29: 3 | AL29: 3 | AM29: =SUM(AJ29:AL29)/3 -> 3.6666667 | AO29: 晴れ（33度以上）曇25度以上 | AQ29: 3
A30: 水 | B30: 17 | C30: 水 | D30: =B30 -> 17 | E30: 548 | F30: 1607800 | G30: =F30/E30 -> 2933.9416 | H30: 896100 | I30: =H30/E30 -> 1635.219 | J30: 6600 | K30: 5940 | L30: =F30+H30+J30+K30 -> 2516440 | M30: =L30/E30 -> 4592.0438 | R30: =L30/Q30 -> #DIV/0! | T30: 21.4 | U30: 31.4 | V30: 5 | W30: 5 | X30: 5 | Y30: =SUM(V30:X30)/3 -> 5 | AA30: 曇 | AC30: 2 | AH30: 21.4 | AI30: 26.1 | AJ30: 1 | AK30: 1 | AL30: 1 | AM30: =SUM(AJ30:AL30)/3 -> 1 | AO30: 曇 | AQ30: 2
A31: 木 | B31: 18 | C31: 木 | D31: =B31 -> 18 | E31: 555 | F31: 1469550 | G31: =F31/E31 -> 2647.8378 | H31: 806100 | I31: =H31/E31 -> 1452.4324 | J31: 1100 | K31: 0 | L31: =F31+H31+J31+K31 -> 2276750 | M31: =L31/E31 -> 4102.2523 | R31: =L31/Q31 -> #DIV/0! | T31: 21.2 | U31: 33.4 | V31: 3 | W31: 3 | X31: 3 | Y31: =SUM(V31:X31)/3 -> 3 | AA31: 雨 | AC31: 1 | AH31: 21 | AI31: 26.7 | AJ31: 3 | AK31: 3 | AL31: 3 | AM31: =SUM(AJ31:AL31)/3 -> 3 | AO31: 雨 | AQ31: 1
A32: 金 | B32: 19 | C32: 金 | D32: =B32 -> 19 | E32: 438 | F32: 1426400 | G32: =F32/E32 -> 3256.621 | H32: 758750 | I32: =H32/E32 -> 1732.3059 | J32: 54450 | K32: 2970 | L32: =F32+H32+J32+K32 -> 2242570 | M32: =L32/E32 -> 5120.0228 | R32: =L32/Q32 -> #DIV/0! | T32: 22.9 | U32: 25.3 | V32: 1 | W32: 1 | X32: 3 | Y32: =SUM(V32:X32)/3 -> 1.6666667 | AA32: 豪雨・雷雨 | AC32: 0 | AH32: 20 | AI32: 25.4 | AJ32: 3 | AK32: 5 | AL32: 1 | AM32: =SUM(AJ32:AL32)/3 -> 3 | AO32: 豪雨・雷雨 | AQ32: 0
A33: 土 | B33: 20 | C33: 土 | D33: =B33 -> 20 | E33: 595 | F33: 1901650 | G33: =F33/E33 -> 3196.0504 | H33: 1005300 | I33: =H33/E33 -> 1689.5798 | J33: 48950 | K33: 0 | L33: =F33+H33+J33+K33 -> 2955900 | M33: =L33/E33 -> 4967.8992 | R33: =L33/Q33 -> #DIV/0! | T33: 23.3 | U33: 33 | V33: 3 | W33: 5 | X33: 5 | Y33: =SUM(V33:X33)/3 -> 4.3333333 | AA33: ※5.6月は18時は最低気温を採用。7月〜は最高気温を採用。 | AH33: 19.4 | AI33: 21.4 | AJ33: 1 | AK33: 1 | AL33: 1 | AM33: =SUM(AJ33:AL33)/3 -> 1 | AO33: ※5.6月は18時は最低気温を採用。7月〜は最高気温を採用。
A34: SUB TOTAL | C34: SUB TOTAL | E34: =SUM(E27:E33) -> 3520 | F34: =SUM(F27:F33) -> 10580250 | G34: =F34/E34 -> 3005.7528 | H34: =SUM(H27:H33) -> 5660700 | I34: =H34/E34 -> 1608.1534 | J34: =SUM(J27:J33) -> 163900 | K34: =SUM(K27:K33) -> 23760 | L34: =F34+H34+J34+K34 -> 16428610 | M34: =L34/E34 -> 4667.2188 | Q34: =SUM(Q27:Q33) -> 0 | R34: =L34/Q34 -> #DIV/0! | S34: 7 | T34: =SUM(T27:T33)/S34 -> 21.228571 | U34: =SUM(U27:U33)/S34 -> 30.285714 | V34: =SUM(V27:V33)/S34 -> 3.8571429 | W34: =SUM(W27:W33)/S34 -> 4.1428571 | X34: =SUM(X27:X33)/S34 -> 4.4285714 | Y34: =SUM(V34:X34)/3 -> 4.1428571 | Z34: ⑧ | AA34: =L34/S34 -> 2346944.3 | AF34: ※1日平均売上 | AG34: 7 | AH34: =SUM(AH27:AH33)/AG34 -> 20.9 | AI34: =SUM(AI27:AI33)/AG34 -> 27.085714 | AJ34: =SUM(AJ27:AJ33)/AG34 -> 2.4285714 | AK34: =SUM(AK27:AK33)/AG34 -> 2.7142857 | AL34: =SUM(AL27:AL33)/AG34 -> 2.4285714 | AM34: =SUM(AJ34:AL34)/3 -> 2.5238095 | AN34: ⑧ | AO34: 1274542.9 | AT34: ※1日平均売上
A35: 4th week | C35: 4th week | T35: =C35 -> 4th week | AH35: =U35 -> 0
A36: 曜日 | B36: 日にち | C36: 曜日 | D36: 日にち | E36: 客数 | F36: 料理売上 | G36: 料理単価 | H36: 飲料売上 | I36: 飲料単価 | J36: その他売上 | K36: 物販 | L36: 売上合計 | M36: 合計単価 | Q36: 労働時間数 | R36: 人時売上高 | T36: 最低 | U36: 最高 | V36: 12時 | W36: 15時 | X36: 18時 | Y36: Ave | AA36: ■天候要因 | AC36: 評価点 | AH36: 最低 | AI36: 最高 | AJ36: 12時 | AK36: 15時 | AL36: 18時 | AM36: Ave | AO36: ■天候要因 | AQ36: 評価点
A37: 日 | B37: 21 | C37: 日 | D37: =B37 -> 21 | E37: 468 | F37: 1234050 | G37: =F37/E37 -> 2636.859 | H37: 693850 | I37: =H37/E37 -> 1482.5855 | J37: 37400 | K37: 2970 | L37: =F37+H37+J37+K37 -> 1968270 | M37: =L37/E37 -> 4205.7051 | R37: =L37/Q37 -> #DIV/0! | T37: 22.3 | U37: 34.7 | V37: 3 | W37: 3 | X37: 3 | Y37: =SUM(V37:X37)/3 -> 3 | AA37: 晴れ（33度まで） | AC37: 5 | AH37: 20.1 | AI37: 28 | AJ37: 5 | AK37: 3 | AL37: 3 | AM37: =SUM(AJ37:AL37)/3 -> 3.6666667 | AO37: 晴れ（33度まで） | AQ37: 5
A38: 月 | B38: 22 | C38: 月 | D38: =B38 -> 22 | E38: 396 | F38: 1279800 | G38: =F38/E38 -> 3231.8182 | H38: 634000 | I38: =H38/E38 -> 1601.0101 | J38: 27500 | K38: 0 | L38: =F38+H38+J38+K38 -> 1941300 | M38: =L38/E38 -> 4902.2727 | R38: =L38/Q38 -> #DIV/0! | T38: 23.9 | U38: 34.7 | V38: 3 | W38: 3 | X38: 3 | Y38: =SUM(V38:X38)/3 -> 3 | AA38: 晴れ（25度以下） | AC38: 4 | AH38: 21.7 | AI38: 26 | AJ38: 3 | AK38: 3 | AL38: 3 | AM38: =SUM(AJ38:AL38)/3 -> 3 | AO38: 晴れ（25度以下） | AQ38: 4
A39: 火 | B39: 23 | C39: 火 | D39: =B39 -> 23 | E39: 322 | F39: 862150 | G39: =F39/E39 -> 2677.4845 | H39: 452400 | I39: =H39/E39 -> 1404.9689 | J39: 56100 | K39: 0 | L39: =F39+H39+J39+K39-Q39 -> 1370650 | M39: =L39/E39 -> 4256.677 | T39: 26.1 | U39: 31.4 | V39: 3 | W39: 1 | X39: 3 | Y39: =SUM(V39:X39)/3 -> 2.3333333 | AA39: 晴れ（33度以上）曇25度以上 | AC39: 3 | AH39: 19.2 | AI39: 24.7 | AJ39: 2 | AK39: 2 | AL39: 3 | AM39: =SUM(AJ39:AL39)/3 -> 2.3333333 | AO39: 晴れ（33度以上）曇25度以上 | AQ39: 3
A40: 水 | B40: 24 | C40: 水 | D40: =B40 -> 24 | E40: 272 | F40: =721000+1600 -> 722600 | G40: =F40/E40 -> 2656.6176 | H40: 385000 | I40: =H40/E40 -> 1415.4412 | J40: 13200 | K40: 2970 | L40: =F40+H40+J40+K40-Q40 -> 1123770 | M40: =L40/E40 -> 4131.5074 | R40: =L40/Q40 -> #DIV/0! | T40: 24.2 | U40: 27.8 | V40: 1 | W40: 3 | X40: 3 | Y40: =SUM(V40:X40)/3 -> 2.3333333 | AA40: 曇 | AC40: 2 | AH40: 19.4 | AI40: 25 | AJ40: 3 | AK40: 5 | AL40: 5 | AM40: =SUM(AJ40:AL40)/3 -> 4.3333333 | AO40: 曇 | AQ40: 2
A41: 木 | B41: 25 | C41: 木 | D41: =B41 -> 25 | E41: 467 | F41: 1222450 | G41: =F41/E41 -> 2617.666 | H41: 653150 | I41: =H41/E41 -> 1398.6081 | J41: 26950 | K41: 2970 | L41: =F41+H41+J41+K41-Q41 -> 1905520 | M41: =L41/E41 -> 4080.3426 | T41: 20.6 | U41: 26.8 | V41: 3 | W41: 5 | X41: 3 | Y41: =SUM(V41:X41)/3 -> 3.6666667 | AA41: 雨 | AC41: 1 | AH41: 20.1 | AI41: 27.9 | AJ41: 5 | AK41: 5 | AL41: 5 | AM41: =SUM(AJ41:AL41)/3 -> 5 | AO41: 雨 | AQ41: 1
A42: 金 | B42: 26 | C42: 金 | D42: =B42 -> 26 | E42: 460 | F42: 1526050 | G42: =F42/E42 -> 3317.5 | H42: 877300 | I42: =H42/E42 -> 1907.1739 | J42: 41250 | K42: 2970 | L42: =F42+H42+J42+K42 -> 2447570 | M42: =L42/E42 -> 5320.8043 | R42: =L42/Q42 -> #DIV/0! | T42: 20.6 | U42: 28.9 | V42: 3 | W42: 3 | X42: 3 | Y42: =SUM(V42:X42)/3 -> 3 | AA42: 豪雨・雷雨 | AC42: 0 | AH42: 19.3 | AI42: 28.6 | AJ42: 5 | AK42: 5 | AL42: 3 | AM42: =SUM(AJ42:AL42)/3 -> 4.3333333 | AO42: 豪雨・雷雨 | AQ42: 0
A43: 土 | B43: 27 | C43: 土 | D43: =B43 -> 27 | E43: 643 | F43: 2078300 | G43: =F43/E43 -> 3232.1928 | H43: 1068150 | I43: =H43/E43 -> 1661.1975 | J43: 67320 | K43: 0 | L43: =F43+H43+J43+K43 -> 3213770 | M43: =L43/E43 -> 4998.0871 | R43: =L43/Q43 -> #DIV/0! | T43: 20.7 | U43: 25.7 | V43: 3 | W43: 3 | X43: 1 | Y43: =SUM(V43:X43)/3 -> 2.3333333 | AA43: ※5.6月は18時は最低気温を採用。7月〜は最高気温を採用。 | AH43: 18.2 | AI43: 29.4 | AJ43: 5 | AK43: 5 | AL43: 5 | AM43: =SUM(AJ43:AL43)/3 -> 5 | AO43: ※5.6月は18時は最低気温を採用。7月〜は最高気温を採用。
A44: SUB TOTAL | C44: SUB TOTAL | E44: =SUM(E37:E43) -> 3028 | F44: =SUM(F37:F43) -> 8925400 | G44: =F44/E44 -> 2947.6222 | H44: =SUM(H37:H43) -> 4763850 | I44: =H44/E44 -> 1573.2662 | J44: =SUM(J37:J43) -> 269720 | K44: =SUM(K37:K43) -> 11880 | L44: =F44+H44+J44+K44 -> 13970850 | M44: =L44/E44 -> 4613.8871 | Q44: =SUM(Q37:Q43) -> 0 | R44: =L44/Q44 -> #DIV/0! | S44: 7 | T44: =SUM(T37:T43)/S44 -> 22.628571 | U44: =SUM(U37:U43)/S44 -> 30 | V44: =SUM(V37:V43)/S44 -> 2.7142857 | W44: =SUM(W37:W43)/S44 -> 3 | X44: =SUM(X37:X43)/S44 -> 2.7142857 | Y44: =SUM(V44:X44)/3 -> 2.8095238 | Z44: ⑨ | AA44: =L44/S44 -> 1995835.7 | AF44: ※1日平均売上 | AG44: 7 | AH44: =SUM(AH37:AH43)/AG44 -> 19.714286 | AI44: =SUM(AI37:AI43)/AG44 -> 27.085714 | AJ44: =SUM(AJ37:AJ43)/AG44 -> 4 | AK44: =SUM(AK37:AK43)/AG44 -> 4 | AL44: =SUM(AL37:AL43)/AG44 -> 3.8571429 | AM44: =SUM(AJ44:AL44)/3 -> 3.952381 | AN44: ⑨ | AO44: 2059514.3 | AT44: ※1日平均売上
A45: 5th week | C45: 5th week | T45: =C45 -> 5th week | AH45: =U45 -> 0
A46: 曜日 | B46: 日にち | C46: 曜日 | D46: 日にち | E46: 客数 | F46: 料理売上 | G46: 料理単価 | H46: 飲料売上 | I46: 飲料単価 | J46: その他売上 | K46: 物販 | L46: 売上合計 | M46: 合計単価 | Q46: 労働時間数 | R46: 人時売上高 | T46: 最低 | U46: 最高 | V46: 12時 | W46: 15時 | X46: 18時 | Y46: Ave | AA46: ■天候要因 | AC46: 評価点 | AH46: 最低 | AI46: 最高 | AJ46: 12時 | AK46: 15時 | AL46: 18時 | AM46: Ave | AO46: ■天候要因 | AQ46: 評価点
A47: 日 | B47: 28 | C47: 日 | D47: =B47 -> 28 | E47: 394 | F47: 1136250 | G47: =F47/E47 -> 2883.8832 | H47: 582820 | I47: =H47/E47 -> 1479.2386 | J47: 26400 | K47: 0 | L47: =F47+H47+J47+K47 -> 1745470 | M47: =L47/E47 -> 4430.1269 | R47: =L47/Q47 -> #DIV/0! | T47: 20.7 | U47: 27.4 | V47: 3 | W47: 5 | X47: 3 | Y47: =SUM(V47:X47)/3 -> 3.6666667 | AA47: 晴れ（33度まで） | AC47: 5 | AH47: 21.2 | AI47: 28.3 | AJ47: 5 | AK47: 5 | AL47: 5 | AM47: =SUM(AJ47:AL47)/3 -> 5 | AO47: 晴れ（33度まで） | AQ47: 5
A48: 月 | B48: 29 | C48: 月 | D48: =B48 -> 29 | E48: 228 | F48: 565750 | G48: =F48/E48 -> 2481.3596 | H48: 359800 | I48: =H48/E48 -> 1578.0702 | J48: 9900 | K48: 0 | L48: =F48+H48+J48+K48 -> 935450 | M48: =L48/E48 -> 4102.8509 | R48: =L48/Q48 -> #DIV/0! | T48: 21.9 | U48: 24.1 | V48: 1 | W48: 1 | X48: 1 | Y48: =SUM(V48:X48)/3 -> 1 | AA48: 晴れ（25度以下） | AC48: 4 | AH48: 22.7 | AI48: 29.2 | AJ48: 3 | AK48: 3 | AL48: 3 | AM48: =SUM(AJ48:AL48)/3 -> 3 | AO48: 晴れ（25度以下） | AQ48: 4
A49: 火 | B49: 30 | C49: 火 | D49: =B49 -> 30 | E49: 423 | F49: 1120100 | G49: =F49/E49 -> 2647.9905 | H49: 620580 | I49: =H49/E49 -> 1467.0922 | J49: 22660 | K49: 5940 | L49: =F49+H49+J49+K49 -> 1769280 | M49: =L49/E49 -> 4182.695 | R49: =L49/Q49 -> #DIV/0! | T49: 22.3 | U49: 28.2 | V49: 3 | W49: 5 | X49: 5 | Y49: =SUM(V49:X49)/3 -> 4.3333333 | AA49: 晴れ（33度以上）曇25度以上 | AC49: 3 | AH49: 24.8 | AI49: 29.8 | AJ49: 1 | AK49: 3 | AL49: 1 | AM49: =SUM(AJ49:AL49)/3 -> 1.6666667 | AO49: 晴れ（33度以上）曇25度以上 | AQ49: 3
A50: 水 | B50: 31 | C50: 水 | D50: =B50 -> 31 | E50: 367 | F50: 1037950 | G50: =F50/E50 -> 2828.2016 | H50: 550530 | I50: =H50/E50 -> 1500.0817 | J50: 12870 | K50: 5940 | L50: =F50+H50+J50+K50 -> 1607290 | M50: =L50/E50 -> 4379.5368 | R50: =L50/Q50 -> #DIV/0! | T50: 21.1 | U50: 25.7 | V50: 5 | W50: 5 | X50: 5 | Y50: =SUM(V50:X50)/3 -> 5 | AA50: 曇 | AC50: 2 | AH50: 24 | AI50: 32.7 | AJ50: 5 | AK50: 5 | AL50: 5 | AM50: =SUM(AJ50:AL50)/3 -> 5 | AO50: 曇 | AQ50: 2
A51: 木 | C51: 木 | D51: =B51 -> 0 | G51: =F51/E51 -> #DIV/0! | I51: =H51/E51 -> #DIV/0! | L51: =F51+H51+J51+K51 -> 0 | M51: =L51/E51 -> #DIV/0! | R51: =L51/Q51 -> #DIV/0! | Y51: =SUM(V51:X51)/3 -> 0 | AA51: 雨 | AC51: 1 | AH51: 23.9 | AI51: 32.9 | AJ51: 3 | AK51: 5 | AL51: 5 | AM51: =SUM(AJ51:AL51)/3 -> 4.3333333 | AO51: 雨 | AQ51: 1
A52: 金 | C52: 金 | D52: =B52 -> 0 | G52: =F52/E52 -> #DIV/0! | I52: =H52/E52 -> #DIV/0! | L52: =F52+H52+J52+K52 -> 0 | M52: =L52/E52 -> #DIV/0! | R52: =L52/Q52 -> #DIV/0! | Y52: =SUM(V52:X52)/3 -> 0 | AA52: 豪雨・雷雨 | AC52: 0 | AH52: 24.4 | AI52: 33.7 | AJ52: 3 | AK52: 5 | AL52: 5 | AM52: =SUM(AJ52:AL52)/3 -> 4.3333333 | AO52: 豪雨・雷雨 | AQ52: 0
A53: 土 | C53: 土 | D53: =B53 -> 0 | G53: =F53/E53 -> #DIV/0! | I53: =H53/E53 -> #DIV/0! | L53: =F53+H53+J53+K53 -> 0 | M53: =L53/E53 -> #DIV/0! | R53: =L53/Q53 -> #DIV/0! | Y53: =SUM(V53:X53)/3 -> 0 | AA53: ※5.6月は18時は最低気温を採用。7月〜は最高気温を採用。 | AH53: 24.9 | AI53: 34.4 | AJ53: 3 | AK53: 3 | AL53: 3 | AM53: =SUM(AJ53:AL53)/3 -> 3 | AO53: ※5.6月は18時は最低気温を採用。7月〜は最高気温を採用。
A54: SUB TOTAL | C54: SUB TOTAL | E54: =SUM(E47:E53) -> 1412 | F54: =SUM(F47:F53) -> 3860050 | G54: =F54/E54 -> 2733.7465 | H54: =SUM(H47:H53) -> 2113730 | I54: =H54/E54 -> 1496.9759 | J54: =SUM(J47:J53) -> 71830 | K54: =SUM(K47:K53) -> 11880 | L54: =F54+H54+J54+K54 -> 6057490 | M54: =L54/E54 -> 4290.0071 | Q54: =SUM(Q47:Q53) -> 0 | R54: =L54/Q54 -> #DIV/0! | S54: 4 | T54: =SUM(T47:T53)/S54 -> 21.5 | U54: =SUM(U47:U53)/S54 -> 26.35 | V54: =SUM(V47:V53)/S54 -> 3 | W54: =SUM(W47:W53)/S54 -> 4 | X54: =SUM(X47:X53)/S54 -> 3.5 | Y54: =SUM(V54:X54)/3 -> 3.5 | Z54: ➓ | AA54: =L54/S54 -> 1514372.5 | AF54: ※1日平均売上 | AG54: 7 | AH54: =SUM(AH47:AH53)/AG54 -> 23.7 | AI54: =SUM(AI47:AI53)/AG54 -> 31.571429 | AJ54: =SUM(AJ47:AJ53)/AG54 -> 3.2857143 | AK54: =SUM(AK47:AK53)/AG54 -> 4.1428571 | AL54: =SUM(AL47:AL53)/AG54 -> 3.8571429 | AM54: =SUM(AJ54:AL54)/3 -> 3.7619048 | AN54: ➓ | AO54: 1765485.7 | AT54: ※1日平均売上
A55: 6th week | C55: 6th week | T55: =C55 -> 6th week | AH55: =U55 -> 0
A56: 曜日 | B56: 日にち | C56: 曜日 | D56: 日にち | E56: 客数 | F56: 料理売上 | G56: 料理単価 | H56: 飲料売上 | I56: 飲料単価 | J56: その他売上 | K56: 物販 | L56: 売上合計 | M56: 合計単価 | Q56: 労働時間数 | R56: 人時売上高 | T56: 最低 | U56: 最高 | V56: 12時 | W56: 15時 | X56: 18時 | Y56: Ave | AA56: ■天候要因 | AC56: 評価点 | AH56: 最低 | AI56: 最高 | AJ56: 12時 | AK56: 15時 | AL56: 18時 | AM56: Ave | AO56: ■天候要因 | AQ56: 評価点
A57: 日 | C57: 日 | D57: =B57 -> 0 | G57: =F57/E57 -> #DIV/0! | I57: =H57/E57 -> #DIV/0! | L57: =F57+H57+J57+K57 -> 0 | M57: =L57/E57 -> #DIV/0! | R57: =L57/Q57 -> #DIV/0! | Y57: =SUM(V57:X57)/3 -> 0 | AA57: 晴れ（33度まで） | AC57: 5 | AH57: 26 | AI57: 29.9 | AJ57: 5 | AK57: 5 | AL57: 5 | AM57: =SUM(AJ57:AL57)/3 -> 5 | AO57: 晴れ（33度まで） | AQ57: 5
A58: 月 | C58: 月 | D58: =B58 -> 0 | G58: =F58/E58 -> #DIV/0! | I58: =H58/E58 -> #DIV/0! | L58: =F58+H58+J58+K58 -> 0 | M58: =L58/E58 -> #DIV/0! | R58: =L58/Q58 -> #DIV/0! | Y58: =SUM(V58:X58)/3 -> 0 | AA58: 晴れ（25度以下） | AC58: 4 | AH58: 25.8 | AI58: 28.2 | AJ58: 1 | AK58: 1 | AL58: 1 | AM58: =SUM(AJ58:AL58)/3 -> 1 | AO58: 晴れ（25度以下） | AQ58: 4
A59: 火 | C59: 火 | D59: =B59 -> 0 | G59: =F59/E59 -> #DIV/0! | I59: =H59/E59 -> #DIV/0! | L59: =F59+H59+J59+K59 -> 0 | M59: =L59/E59 -> #DIV/0! | R59: =L59/Q59 -> #DIV/0! | Y59: =SUM(V59:X59)/3 -> 0 | AA59: 晴れ（33度以上）曇25度以上 | AC59: 3 | AM59: =SUM(AJ59:AL59)/3 -> 0 | AO59: 晴れ（33度以上）曇25度以上 | AQ59: 3
A60: 水 | C60: 水 | D60: =B60 -> 0 | G60: =F60/E60 -> #DIV/0! | I60: =H60/E60 -> #DIV/0! | L60: =F60+H60+J60+K60 -> 0 | M60: =L60/E60 -> #DIV/0! | R60: =L60/Q60 -> #DIV/0! | Y60: =SUM(V60:X60)/3 -> 0 | AA60: 曇 | AC60: 2 | AM60: =SUM(AJ60:AL60)/3 -> 0 | AO60: 曇 | AQ60: 2
A61: 木 | C61: 木 | D61: =B61 -> 0 | G61: =F61/E61 -> #DIV/0! | I61: =H61/E61 -> #DIV/0! | L61: =F61+H61+J61+K61 -> 0 | M61: =L61/E61 -> #DIV/0! | R61: =L61/Q61 -> #DIV/0! | Y61: =SUM(V61:X61)/3 -> 0 | AA61: 雨 | AC61: 1 | AM61: =SUM(AJ61:AL61)/3 -> 0 | AO61: 雨 | AQ61: 1
A62: 金 | C62: 金 | D62: =B62 -> 0 | G62: =F62/E62 -> #DIV/0! | H62: 0 | I62: =H62/E62 -> #DIV/0! | L62: =F62+H62+J62+K62 -> 0 | M62: =L62/E62 -> #DIV/0! | R62: =L62/Q62 -> #DIV/0! | Y62: =SUM(V62:X62)/3 -> 0 | AA62: 豪雨・雷雨 | AC62: 0 | AM62: =SUM(AJ62:AL62)/3 -> 0 | AO62: 豪雨・雷雨 | AQ62: 0
A63: 土 | C63: 土 | D63: =B63 -> 0 | G63: =F63/E63 -> #DIV/0! | H63: 0 | I63: =H63/E63 -> #DIV/0! | J63: 0 | L63: =F63+H63+J63+K63 -> 0 | M63: =L63/E63 -> #DIV/0! | R63: =L63/Q63 -> #DIV/0! | Y63: =SUM(V63:X63)/3 -> 0 | AA63: ※5.6月は18時は最低気温を採用。7月〜は最高気温を採用。 | AM63: =SUM(AJ63:AL63)/3 -> 0 | AO63: ※5.6月は18時は最低気温を採用。7月〜は最高気温を採用。
A64: SUB TOTAL | C64: SUB TOTAL | E64: =SUM(E57:E63) -> 0 | F64: =SUM(F57:F63) -> 0 | G64: =F64/E64 -> #DIV/0! | H64: =SUM(H57:H63) -> 0 | I64: =H64/E64 -> #DIV/0! | J64: =SUM(J57:J63) -> 0 | K64: =SUM(K57:K63) -> 0 | L64: =F64+H64+J64+K64 -> 0 | M64: =L64/E64 -> #DIV/0! | Q64: =SUM(Q57:Q63) -> 0 | R64: =L64/Q64 -> #DIV/0! | S64: 0 | T64: =SUM(T57:T63)/S64 -> #DIV/0! | U64: =SUM(U57:U63)/S64 -> #DIV/0! | V64: =SUM(V57:V63)/S64 -> #DIV/0! | W64: =SUM(W57:W63)/S64 -> #DIV/0! | X64: =SUM(X57:X63)/S64 -> #DIV/0! | Y64: =SUM(V64:X64)/3 -> #DIV/0! | Z64: 11 | AA64: =L64/S64 -> #DIV/0! | AF64: ※1日平均売上 | AG64: 2 | AH64: =SUM(AH57:AH63)/AG64 -> 25.9 | AI64: =SUM(AI57:AI63)/AG64 -> 29.05 | AJ64: =SUM(AJ57:AJ63)/AG64 -> 3 | AK64: =SUM(AK57:AK63)/AG64 -> 3 | AL64: =SUM(AL57:AL63)/AG64 -> 3 | AM64: =SUM(AJ64:AL64)/3 -> 3 | AN64: 11 | AO64: 1311325 | AT64: ※1日平均売上
A65: TOTAL | C65: TOTAL | T65: =C65 -> TOTAL | AH65: =U65 -> 0
A66: 曜日 | B66: 日数 | C66: 曜日 | D66: 日数 | E66: 客数 | F66: 料理売上 | G66: 料理単価 | H66: 飲料売上 | I66: 飲料単価 | L66: 合計売上実績 | M66: 合計単価 | Q66: 労働時間数 | R66: 人時売上高 | T66: 最低 | U66: 最高 | V66: 12時 | W66: 15時 | X66: 18時 | Y66: Ave | AA66: 2024年 7月 天候実績 | AH66: 最低 | AI66: 最高 | AJ66: 12時 | AK66: 15時 | AL66: 18時 | AM66: Ave | AO66: 2023年 7月 天候実績対比
A67: 日 | C67: 日 | D67: 4 | E67: =E7+E17+E27+E37+E47+E57 -> 1747 | F67: =F7+F17+F27+F37+F47+F57 -> 5139350 | G67: =F67/E67 -> 2941.8145 | H67: =H7+H17+H27+H37+H47+H57 -> 2690920 | I67: =H67/E67 -> 1540.3091 | J67: =J7+J17+J27+J37+J47+J57 -> 102850 | K67: =K7+K17+K27+K37+K47+K57 -> 8910 | L67: =L7+L17+L27+L37+L47+L57 -> 7942030 | M67: =M7+M17+M27+M37+M47+M57 -> #DIV/0! | Q67: =Q7+Q17+Q27+Q37+Q47+Q57 -> 0 | R67: =L67/Q67 -> #DIV/0! | T67: =T7+T17+T27+T37+T47+T57 -> 83.2 | U67: =U7+U17+U27+U37+U47+U57 -> 116.6 | V67: =V7+V17+V37+V47+V27+V57 -> 13 | W67: =W7+W17+W37+W47+W27+W57 -> 15 | X67: =X7+X17+X37+X47+X27+X57 -> 13 | Y67: =SUM(V67:X67)/3 -> 13.666667 | AA67: 天候状況 | AC67: ポイント | AD67: 2024 | AE67: 2024合計 | AF67: 比率 | AH67: =AH7+AH17+AH27+AH37+AH47+AH57 -> 105.6 | AI67: =AI7+AI17+AI27+AI37+AI47+AI57 -> 140.5 | AJ67: =AJ7+AJ17+AJ37+AJ47+AJ27+AJ57 -> 20 | AK67: =AK7+AK17+AK37+AK47+AK27+AK57 -> 19 | AL67: =AL7+AL17+AL37+AL47+AL27+AL57 -> 20 | AM67: =SUM(AJ67:AL67)/3 -> 19.666667 | AO67: 天候状況 | AQ67: ポイント | AR67: 2023 | AS67: 2023合計 | AT67: 比率
A68: 月 | C68: 月 | D68: 5 | E68: =E8+E18+E28+E38+E48+E58 -> 1310 | F68: =F8+F18+F28+F38+F48+F58 -> 3919400 | G68: =F68/E68 -> 2991.9084 | H68: =H8+H18+H28+H38+H48+H58 -> 2086700 | I68: =H68/E68 -> 1592.9008 | J68: =J8+J18+J28+J38+J48+J58 -> 74250 | K68: =K8+K18+K28+K38+K48+K58 -> 5940 | L68: =L8+L18+L28+L38+L48+L58 -> 6086290 | M68: =M8+M18+M28+M38+M48+M58 -> #DIV/0! | Q68: =Q8+Q18+Q28+Q38+Q48+Q58 -> 0 | R68: =L68/Q68 -> #DIV/0! | T68: =T8+T18+T28+T38+T48+T58 -> 104.5 | U68: =U8+U18+U28+U38+U48+U58 -> 134.6 | V68: =V8+V18+V38+V48+V28+V58 -> 12 | W68: =W8+W18+W38+W48+W28+W58 -> 12 | X68: =X8+X18+X38+X48+X28+X58 -> 12 | Y68: =SUM(V68:X68)/3 -> 12 | AA68: 晴れ（33度まで） | AC68: 5 | AD68: 26 | AE68: =AC68*AD68 -> 130 | AF68: =(AD68+AD69+AD70)/AD74 -> 0.74193548 | AH68: =AH8+AH18+AH28+AH38+AH48+AH58 -> 108.8 | AI68: =AI8+AI18+AI28+AI38+AI48+AI58 -> 135.7 | AJ68: =AJ8+AJ18+AJ38+AJ48+AJ28+AJ58 -> 14 | AK68: =AK8+AK18+AK38+AK48+AK28+AK58 -> 14 | AL68: =AL8+AL18+AL38+AL48+AL28+AL58 -> 14 | AM68: =SUM(AJ68:AL68)/3 -> 14 | AO68: 晴れ（33度まで） | AQ68: 5 | AR68: 35 | AS68: =AQ68*AR68 -> 175 | AT68: =(AR68+AR69+AR70)/AR74 -> 0.79569892
A69: 火 | C69: 火 | D69: 5 | E69: =E9+E19+E29+E39+E49+E59 -> 1448 | F69: =F9+F19+F29+F39+F49+F59 -> 3890600 | G69: =F69/E69 -> 2686.8785 | H69: =H9+H19+H29+H39+H49+H59 -> 2157480 | I69: =H69/E69 -> 1489.9724 | J69: =J9+J19+J29+J39+J49+J59 -> 118910 | K69: =K9+K19+K29+K39+K49+K59 -> 8910 | L69: =L9+L19+L29+L39+L49+L59 -> 6175900 | M69: =M9+M19+M29+M39+M49+M59 -> #DIV/0! | Q69: =Q9+Q19+Q29+Q39+Q49+Q59 -> 0 | R69: =L69/Q69 -> #DIV/0! | T69: =T9+T19+T29+T39+T49+T59 -> 101.9 | U69: =U9+U19+U29+U39+U49+U59 -> 139.2 | V69: =V9+V19+V39+V49+V29+V59 -> 15 | W69: =W9+W19+W39+W49+W29+W59 -> 16 | X69: =X9+X19+X39+X49+X29+X59 -> 18 | Y69: =SUM(V69:X69)/3 -> 16.333333 | AA69: 晴れ（25度以下） | AC69: 4 | AD69: 5 | AE69: =AC69*AD69 -> 20 | AH69: =AH9+AH19+AH29+AH39+AH49+AH59 -> 84.5 | AI69: =AI9+AI19+AI29+AI39+AI49+AI59 -> 109.5 | AJ69: =AJ9+AJ19+AJ39+AJ49+AJ29+AJ59 -> 12 | AK69: =AK9+AK19+AK39+AK49+AK29+AK59 -> 12 | AL69: =AL9+AL19+AL39+AL49+AL29+AL59 -> 11 | AM69: =SUM(AJ69:AL69)/3 -> 11.666667 | AO69: 晴れ（25度以下） | AQ69: 4 | AR69: 10 | AS69: =AQ69*AR69 -> 40
A70: 水 | C70: 水 | D70: 5 | E70: =E10+E20+E30+E40+E50+E60 -> 1754 | F70: =F10+F20+F30+F40+F50+F60 -> 4856150 | G70: =F70/E70 -> 2768.6146 | H70: =H10+H20+H30+H40+H50+H60 -> 2694780 | I70: =H70/E70 -> 1536.3626 | J70: =J10+J20+J30+J40+J50+J60 -> 43120 | K70: =K10+K20+K30+K40+K50+K60 -> 14850 | L70: =L10+L20+L30+L40+L50+L60 -> 7608900 | M70: =M10+M20+M30+M40+M50+M60 -> #DIV/0! | Q70: =Q10+Q20+Q30+Q40+Q50+Q60 -> 0 | R70: =L70/Q70 -> #DIV/0! | T70: =T10+T20+T30+T40+T50+T60 -> 100.9 | U70: =U10+U20+U30+U40+U50+U60 -> 141.7 | V70: =V10+V20+V40+V50+V30+V60 -> 21 | W70: =W10+W20+W40+W50+W30+W60 -> 21 | X70: =X10+X20+X40+X50+X30+X60 -> 19 | Y70: =SUM(V70:X70)/3 -> 20.333333 | AA70: 晴れ（33度以上15以下） 曇25度以上 | AC70: 3 | AD70: 38 | AE70: =AC70*AD70 -> 114 | AH70: =AH10+AH20+AH30+AH40+AH50+AH60 -> 82.8 | AI70: =AI10+AI20+AI30+AI40+AI50+AI60 -> 111.2 | AJ70: =AJ10+AJ20+AJ40+AJ50+AJ30+AJ60 -> 14 | AK70: =AK10+AK20+AK40+AK50+AK30+AK60 -> 16 | AL70: =AL10+AL20+AL40+AL50+AL30+AL60 -> 15 | AM70: =SUM(AJ70:AL70)/3 -> 15 | AO70: 晴れ（33度以上15以下） 曇25度以上 | AQ70: 3 | AR70: 29 | AS70: =AQ70*AR70 -> 87
A71: 木 | C71: 木 | D71: 4 | E71: =E21+E11+E31+E41+E51+E61 -> 1518 | F71: =F21+F11+F31+F41+F51+F61 -> 4021100 | G71: =F71/E71 -> 2648.946 | H71: =H21+H11+H31+H41+H51+H61 -> 2235800 | I71: =H71/E71 -> 1472.859 | J71: =J21+J11+J31+J41+J51+J61 -> 48950 | K71: =K21+K11+K31+K41+K51+K61 -> 2970 | L71: =L21+L11+L31+L41+L51+L61 -> 6308820 | M71: =M21+M11+M31+M41+M51+M61 -> #DIV/0! | Q71: =Q21+Q11+Q31+Q41+Q51+Q61 -> 0 | R71: =L71/Q71 -> #DIV/0! | T71: =T11+T21+T31+T41+T51+T61 -> 78.1 | U71: =U11+U21+U31+U41+U51+U61 -> 115 | V71: =V11+V21+V41+V51+V31+V61 -> 14 | W71: =W11+W21+W41+W51+W31+W61 -> 14 | X71: =X11+X21+X41+X51+X31+X61 -> 12 | Y71: =SUM(V71:X71)/3 -> 13.333333 | AA71: 曇 | AC71: 2 | AD71: 9 | AE71: =AC71*AD71 -> 18 | AF71: =(AD71+AD72+AD73)/AD74 -> 0.25806452 | AH71: =AH11+AH21+AH31+AH41+AH51+AH61 -> 83.4 | AI71: =AI11+AI21+AI31+AI41+AI51+AI61 -> 112.7 | AJ71: =AJ11+AJ21+AJ41+AJ51+AJ31+AJ61 -> 14 | AK71: =AK11+AK21+AK41+AK51+AK31+AK61 -> 14 | AL71: =AL11+AL21+AL41+AL51+AL31+AL61 -> 14 | AM71: =SUM(AJ71:AL71)/3 -> 14 | AO71: 曇 | AQ71: 2 | AR71: 4 | AS71: =AQ71*AR71 -> 8 | AT71: =(AR71+AR72+AR73)/AR74 -> 0.20430108
A72: 金 | C72: 金 | D72: 4 | E72: =E12+E22+E32+E42+E52+E62 -> 1564 | F72: =F12+F22+F32+F42+F52+F62 -> 4927650 | G72: =F72/E72 -> 3150.6714 | H72: =H12+H22+H32+H42+H52+H62 -> 2724000 | I72: =H72/E72 -> 1741.688 | J72: =J12+J22+J32+J42+J52+J62 -> 151250 | K72: =K12+K22+K32+K42+K52+K62 -> 5940 | L72: =L12+L22+L32+L42+L52+L62 -> 7808840 | M72: =M12+M22+M32+M42+M52+M62 -> #DIV/0! | Q72: =Q12+Q22+Q32+Q42+Q52+Q62 -> 0 | R72: =L72/Q72 -> #DIV/0! | T72: =T12+T22+T32+T42+T52+T62 -> 82.5 | U72: =U12+U22+U32+U42+U52+U62 -> 112.3 | V72: =V12+V22+V42+V52+V32+V62 -> 12 | W72: =W12+W22+W42+W52+W32+W62 -> 10 | X72: =X12+X22+X42+X52+X32+X62 -> 12 | Y72: =SUM(V72:X72)/3 -> 11.333333 | AA72: 雨 | AC72: 1 | AD72: 15 | AE72: =AC72*AD72 -> 15 | AH72: =AH12+AH22+AH32+AH42+AH52+AH62 -> 82.9 | AI72: =AI12+AI22+AI32+AI42+AI52+AI62 -> 113.8 | AJ72: =AJ12+AJ22+AJ42+AJ52+AJ32+AJ62 -> 14 | AK72: =AK12+AK22+AK42+AK52+AK32+AK62 -> 20 | AL72: =AL12+AL22+AL42+AL52+AL32+AL62 -> 14 | AM72: =SUM(AJ72:AL72)/3 -> 16 | AO72: 雨 | AQ72: 1 | AR72: 15 | AS72: =AQ72*AR72 -> 15
A73: 土 | C73: 土 | D73: 4 | E73: =E13+E23+E33+E43+E53+E63 -> 2097 | F73: =F13+F23+F33+F43+F53+F63 -> 6704550 | G73: =F73/E73 -> 3197.2103 | H73: =H13+H23+H33+H43+H53+H63 -> 3540800 | I73: =H73/E73 -> 1688.5074 | J73: =J13+J23+J33+J43+J53+J63 -> 186670 | K73: =K13+K23+K33+K43+K53+K63 -> 11880 | L73: =L13+L23+L33+L43+L53+L63 -> 10443900 | M73: =M13+M23+M33+M43+M53+M63 -> #DIV/0! | Q73: =Q13+Q23+Q33+Q43+Q53+Q63 -> 0 | R73: =L73/Q73 -> #DIV/0! | S73: =S14+S24+S34+S44+S54+S64 -> 31 | T73: =T13+T23+T33+T43+T53+T63 -> 84.3 | U73: =U13+U23+U33+U43+U53+U63 -> 108.1 | V73: =V13+V23+V43+V53+V33+V63 -> 11 | W73: =W13+W23+W43+W53+W33+W63 -> 13 | X73: =X13+X23+X43+X53+X33+X63 -> 12 | Y73: =SUM(V73:X73)/3 -> 12 | AA73: 豪雨・雷雨 | AC73: 0 | AE73: =AC73*AD73 -> 0 | AG73: =AG14+AG24+AG34+AG44+AG54+AG64 -> 31 | AH73: =AH13+AH23+AH33+AH43+AH53+AH63 -> 101.7 | AI73: =AI13+AI23+AI33+AI43+AI53+AI63 -> 137.8 | AJ73: =AJ13+AJ23+AJ43+AJ53+AJ33+AJ63 -> 16 | AK73: =AK13+AK23+AK43+AK53+AK33+AK63 -> 18 | AL73: =AL13+AL23+AL43+AL53+AL33+AL63 -> 18 | AM73: =SUM(AJ73:AL73)/3 -> 17.333333 | AO73: 豪雨・雷雨 | AQ73: 0 | AS73: =AQ73*AR73 -> 0
A74: TOTAL | B74: =SUM(B67:B73) -> 0 | C74: TOTAL | D74: =SUM(D67:D73) -> 31 | E74: =SUM(E67:E73) -> 11438 | F74: =SUM(F67:F73) -> 33458800 | G74: =F74/E74 -> 2925.2317 | H74: =SUM(H67:H73) -> 18130480 | I74: =H74/E74 -> 1585.1093 | J74: =SUM(J67:J73) -> 726000 | K74: =SUM(K67:K73) -> 59400 | L74: =SUM(L67:L73) -> 52374680 | M74: =L74/E74 -> 4579.0068 | Q74: =SUM(Q67:Q73) -> 0 | R74: =L74/Q74 -> #DIV/0! | T74: =SUM(T67:T73)/S73 -> 20.496774 | U74: =SUM(U67:U73)/S73 -> 27.983871 | V74: =SUM(V67:V73)/S73 -> 3.1612903 | W74: =SUM(W67:W73)/S73 -> 3.2580645 | X74: =SUM(X67:X73)/S73 -> 3.1612903 | Y74: =SUM(V74:X74)/3 -> 3.1935484 | AA74: TOTAL | AD74: =SUM(AD68:AD73) -> 93 | AE74: =SUM(AE68:AE73) -> 297 | AF74: =AF68+AF71 -> 1 | AH74: =SUM(AH67:AH73)/AG73 -> 20.958065 | AI74: =SUM(AI67:AI73)/AG73 -> 27.780645 | AJ74: =SUM(AJ67:AJ73)/AG73 -> 3.3548387 | AK74: =SUM(AK67:AK73)/AG73 -> 3.6451613 | AL74: =SUM(AL67:AL73)/AG73 -> 3.4193548 | AM74: =SUM(AJ74:AL74)/3 -> 3.4731183 | AO74: TOTAL | AR74: =SUM(AR68:AR73) -> 93 | AS74: =SUM(AS68:AS73) -> 325 | AT74: =AT68+AT71 -> 1
A75: ■対比 | C75: ■対比
A77: ランチ | C77: ランチ | E77: 予算
E78: ランチ
E79: 客数 | H79: F売上 | L79: B売上
H80: =#REF!*E80 -> #REF! | L80: =#REF!*E80 -> #REF!
E82: ■予算差異
E83: 客数 | H83: F売上 | L83: B売上
E84: =E74-E80 -> 11438 | H84: =H74-H80 -> #REF! | L84: =L74-L80 -> #REF!
E85: =E74/E80 -> #DIV/0! | H85: =H74/H80 -> #REF! | L85: =L74/L80 -> #REF!
E86: ■前年値（数値残っていない休業）
E87: 客数 | H87: F売上 | L87: B売上
E89: ■前年差異
E90: 客数 | H90: F売上 | L90: B売上
E91: =E74-E88 -> 11438 | H91: =H74-H88 -> 18130480 | L91: =L74-L88 -> 52374680
E92: =E74/E88 -> #DIV/0! | H92: =H74/H88 -> #DIV/0! | L92: =L74/L88 -> #DIV/0!
A93: 構成比率 | E93: =E74/30 -> 381.26667 | G93: =G74/1.1 -> 2659.3015 | I93: =I74/1.1 -> 1441.0084 | J93: 税抜売上 | L93: =L74/1.1 -> 47613345 | M93: 対予測達成率 | Q93: =L93/#REF! -> #REF! | R93: =L93-#REF! -> #REF! | Y93: =Y74/AM74 -> 0.91950464 | AB93: =L93/AP93 -> #DIV/0! | AD93: =AE74/AD74 -> 3.1935484 | AR93: =AS74/AR74 -> 3.4946237
H94: =G93+I93 -> 4100.31 | J94: =(J74+K74)/1.1 -> 714000 | M94: 合計予算進捗 | Q94: ウチその他対比
C95: 残り日数 | D95: 0 | H95: 売上合計予算対比 | M95: =L93/#REF! -> #REF! | Q95: =J94/#REF! -> #REF! | R95: =L93-#REF! -> #REF!
K97: 前年比 | L97: =L93-#REF! -> #REF! | M97: =L93/#REF! -> #REF!
A98: ■モデルシフト
A99: モデルシフト カテゴリー | L99: =L74-17800 -> 52356880
A100: TOP1 | L100: =L99/1.1 -> 47597164 | R100: =#REF!-L93 -> #REF!
A101: TOP2 | R101: =R100/D95 -> #REF!
A102: ON1
A103: ON2
A104: ショルダー
...

Sheet 2024.6月実績
A1: ■R6年度 ビアガーデン売上実績
A2: 6月 | O2: =O14+O24+O34+O44+O54+O64 -> 21113880 | U2: 30
A3: FOOD予測 | G3: ビアガーデン6月 TOTAL実績 | Q3: 客数 | U3: 売上 | AK3: 前年週別売上＆天候実績
A4: 予算 | G4: 実績 | I4: 客数 | K4: 客単価 | M4: 売上予算 | P4: 1日平均 | U4: =O4/U2 -> 0 | W4: 天候要因（売上との関連性を数値化する） | AK4: 天候要因（売上との関連性を数値化する）
A5: 1st week | G5: 1st week | W5: =G5 -> 1st week | AK5: =X5 -> 0
A6: 曜日 | B6: 日にち | C6: A | D6: B | E6: C | F6: S | G6: 曜日 | H6: 日にち | I6: 客数 | J6: 料理売上 | K6: 料理単価 | L6: 飲料売上 | M6: 飲料単価 | N6: その他売上 | O6: 売上合計 | P6: 合計単価 | T6: 労働時間数 | U6: 人時売上高 | W6: 最低 | X6: 最高 | Y6: 12時 | Z6: 15時 | AA6: 18時 | AB6: Ave | AD6: ■天候要因 | AF6: 評価点 | AK6: 最低 | AL6: 最高 | AM6: 12時 | AN6: 15時 | AO6: 18時 | AP6: Ave | AR6: ■天候要因 | AT6: 評価点
A7: 日 | G7: 日 | H7: =B7 -> 0 | K7: =J7/I7 -> #DIV/0! | M7: =L7/I7 -> #DIV/0! | O7: =J7+L7+N7 -> 0 | P7: =O7/I7 -> #DIV/0! | U7: =O7/T7 -> #DIV/0! | AB7: =SUM(Y7:AA7)/3 -> 0 | AD7: 晴れ（33度まで） | AF7: 5 | AP7: =SUM(AM7:AO7)/3 -> 0 | AR7: 晴れ（33度まで） | AT7: 5
A8: 月 | G8: 月 | H8: =B8 -> 0 | K8: =J8/I8 -> #DIV/0! | M8: =L8/I8 -> #DIV/0! | O8: =J8+L8+N8 -> 0 | P8: =O8/I8 -> #DIV/0! | U8: =O8/T8 -> #DIV/0! | AB8: =SUM(Y8:AA8)/3 -> 0 | AD8: 晴れ（25度以下） | AF8: 4 | AP8: =SUM(AM8:AO8)/3 -> 0 | AR8: 晴れ（25度以下） | AT8: 4
A9: 火 | G9: 火 | H9: =B9 -> 0 | K9: =J9/I9 -> #DIV/0! | M9: =L9/I9 -> #DIV/0! | O9: =J9+L9+N9 -> 0 | P9: =O9/I9 -> #DIV/0! | U9: =O9/T9 -> #DIV/0! | AB9: =SUM(Y9:AA9)/3 -> 0 | AD9: 晴れ（33度以上15以下）曇25度以上 | AF9: 3 | AP9: =SUM(AM9:AO9)/3 -> 0 | AR9: 晴れ（33度以上）曇25度以上 | AT9: 3
A10: 水 | G10: 水 | H10: =B10 -> 0 | K10: =J10/I10 -> #DIV/0! | M10: =L10/I10 -> #DIV/0! | O10: =J10+L10+N10 -> 0 | P10: =O10/I10 -> #DIV/0! | U10: =O10/T10 -> #DIV/0! | AB10: =SUM(Y10:AA10)/3 -> 0 | AD10: 曇 | AF10: 2 | AP10: =SUM(AM10:AO10)/3 -> 0 | AR10: 曇 | AT10: 2
A11: 木 | G11: 木 | H11: =B11 -> 0 | K11: =J11/I11 -> #DIV/0! | M11: =L11/I11 -> #DIV/0! | O11: =J11+L11+N11 -> 0 | P11: =O11/I11 -> #DIV/0! | U11: =O11/T11 -> #DIV/0! | AB11: =SUM(Y11:AA11)/3 -> 0 | AD11: 雨 | AF11: 1 | AK11: 9.6 | AL11: 24.7 | AM11: 4 | AN11: 4 | AO11: 4 | AP11: =SUM(AM11:AO11)/3 -> 4 | AR11: 雨 | AT11: 1
A12: 金 | G12: 金 | H12: =B12 -> 0 | K12: =J12/I12 -> #DIV/0! | M12: =L12/I12 -> #DIV/0! | O12: =J12+L12+N12 -> 0 | P12: =O12/I12 -> #DIV/0! | U12: =O12/T12 -> #DIV/0! | AB12: =SUM(Y12:AA12)/3 -> 0 | AD12: 豪雨・雷雨 | AF12: 0 | AK12: 15.4 | AL12: 21.9 | AM12: 4 | AN12: 4 | AO12: 1 | AP12: =SUM(AM12:AO12)/3 -> 3 | AR12: 豪雨・雷雨 | AT12: 0
A13: 土 | B13: 1 | G13: 土 | H13: =B13 -> 1 | I13: 214 | J13: 429850 | K13: =J13/I13 -> 2008.6449 | L13: 258400 | M13: =L13/I13 -> 1207.4766 | N13: 2750 | O13: =J13+L13+N13 -> 691000 | P13: =O13/I13 -> 3228.972 | U13: =O13/T13 -> #DIV/0! | W13: 11.5 | X13: 21.5 | Y13: 3 | Z13: 3 | AA13: 3 | AB13: =SUM(Y13:AA13)/3 -> 3 | AD13: ※5.6月は18時は最低気温を採用。7月〜は最高気温を採用。 | AK13: 13.6 | AL13: 16.4 | AM13: 1 | AN13: 1 | AO13: 4 | AP13: =SUM(AM13:AO13)/3 -> 2 | AR13: ※5.6月は18時は最低気温を採用。7月〜は最高気温を採用。
A14: SUB TOTAL | C14: P/D | D14: =#REF!/F14 -> #REF! | E14: 日にち | F14: =#REF! -> #REF! | G14: SUB TOTAL | I14: =SUM(I7:I13) -> 214 | J14: =SUM(J7:J13) -> 429850 | K14: =J14/I14 -> 2008.6449 | L14: =SUM(L7:L13) -> 258400 | M14: =L14/I14 -> 1207.4766 | N14: =SUM(N7:N13) -> 2750 | O14: =J14+L14+N14 -> 691000 | P14: =O14/I14 -> 3228.972 | T14: =SUM(T7:T13) -> 0 | U14: =O14/T14 -> #DIV/0! | V14: 1 | W14: =SUM(W7:W13)/V14 -> 11.5 | X14: =SUM(X7:X13)/V14 -> 21.5 | Y14: =SUM(Y7:Y13)/V14 -> 3 | Z14: =SUM(Z7:Z13)/V14 -> 3 | AA14: =SUM(AA7:AA13)/V14 -> 3 | AB14: =SUM(Y14:AA14)/3 -> 3 | AC14: ② | AD14: =O14/V14 -> 691000 | AI14: ※1日平均売上 | AJ14: 3 | AK14: =SUM(AK7:AK13)/AJ14 -> 12.866667 | AL14: =SUM(AL7:AL13)/AJ14 -> 21 | AM14: =SUM(AM7:AM13)/AJ14 -> 3 | AN14: =SUM(AN7:AN13)/AJ14 -> 3 | AO14: =SUM(AO7:AO13)/AJ14 -> 3 | AP14: =SUM(AM14:AO14)/3 -> 3 | AQ14: ② | AR14: 387183.33 | AW14: ※1日平均売上
A15: 2nd week | G15: 2nd week | W15: =G15 -> 2nd week | AK15: =X15 -> 0
A16: 曜日 | B16: 日にち | C16: A | D16: B | E16: C | F16: S | G16: 曜日 | H16: 日にち | I16: 客数 | J16: 料理売上 | K16: 料理単価 | L16: 飲料売上 | M16: 飲料単価 | N16: その他売上 | O16: 売上合計 | P16: 合計単価 | T16: 労働時間数 | U16: 人時売上高 | W16: 最低 | X16: 最高 | Y16: 12時 | Z16: 15時 | AA16: 18時 | AB16: Ave | AD16: ■天候要因 | AF16: 評価点 | AK16: 最低 | AL16: 最高 | AM16: 12時 | AN16: 15時 | AO16: 18時 | AP16: Ave | AR16: ■天候要因 | AT16: 評価点
A17: 日 | B17: 2 | G17: 日 | H17: =B17 -> 2 | I17: 176 | J17: 399250 | K17: =J17/I17 -> 2268.4659 | L17: 226050 | M17: =L17/I17 -> 1284.375 | O17: =J17+L17+N17 -> 625300 | P17: =O17/I17 -> 3552.8409 | U17: =O17/T17 -> #DIV/0! | W17: 10.5 | X17: 20.4 | Y17: 3 | Z17: 3 | AA17: 3 | AB17: =SUM(Y17:AA17)/3 -> 3 | AD17: 晴れ（33度まで） | AF17: 5 | AK17: 8.2 | AL17: 17.4 | AM17: 1 | AN17: 1 | AO17: 4 | AP17: =SUM(AM17:AO17)/3 -> 2 | AR17: 晴れ（33度まで） | AT17: 5
A18: 月 | B18: 3 | G18: 月 | H18: =B18 -> 3 | I18: 46 | J18: 112350 | K18: =J18/I18 -> 2442.3913 | L18: 64800 | M18: =L18/I18 -> 1408.6957 | O18: =J18+L18+N18 -> 177150 | P18: =O18/I18 -> 3851.087 | U18: =O18/#REF! -> #REF! | W18: 12.2 | X18: 19.9 | Y18: 2 | Z18: 2 | AA18: 2 | AB18: =SUM(Y18:AA18)/3 -> 2 | AD18: 晴れ（25度以下） | AF18: 4 | AK18: 8.9 | AL18: 17.7 | AM18: 2 | AN18: 1 | AO18: 4 | AP18: =SUM(AM18:AO18)/3 -> 2.3333333 | AR18: 晴れ（25度以下） | AT18: 4
A19: 火 | B19: 4 | G19: 火 | H19: =B19 -> 4 | I19: 31 | J19: 53050 | K19: =J19/I19 -> 1711.2903 | L19: 37250 | M19: =L19/I19 -> 1201.6129 | O19: =J19+L19+N19 -> 90300 | P19: =O19/I19 -> 2912.9032 | U19: =O19/T18 -> #DIV/0! | W19: 11.9 | X19: 22.3 | Y19: 3 | Z19: 1 | AA19: 1 | AB19: =SUM(Y19:AA19)/3 -> 1.6666667 | AD19: 晴れ（33度以上15以下）曇25度以上 | AF19: 3 | AK19: 10.9 | AL19: 22.5 | AM19: 1 | AN19: 1 | AO19: 4 | AP19: =SUM(AM19:AO19)/3 -> 2 | AR19: 晴れ（33度以上）曇25度以上 | AT19: 3
A20: 水 | B20: 5 | G20: 水 | H20: =B20 -> 5 | I20: 51 | J20: 139450 | K20: =J20/I20 -> 2734.3137 | L20: 69900 | M20: =L20/I20 -> 1370.5882 | N20: 2200 | O20: =J20+L20+N20 -> 211550 | P20: =O20/I20 -> 4148.0392 | U20: =O20/T20 -> #DIV/0! | W20: 11.8 | X20: 13.5 | Y20: 1 | Z20: 1 | AA20: 1 | AB20: =SUM(Y20:AA20)/3 -> 1 | AD20: 曇 | AF20: 2 | AK20: 15.5 | AL20: 20.6 | AM20: 1 | AN20: 1 | AO20: 2 | AP20: =SUM(AM20:AO20)/3 -> 1.3333333 | AR20: 曇 | AT20: 2
A21: 木 | B21: 6 | G21: 木 | H21: =B21 -> 6 | I21: 41 | J21: 51350 | K21: =J21/I21 -> 1252.439 | L21: 85950 | M21: =L21/I21 -> 2096.3415 | O21: =J21+L21+N21 -> 137300 | P21: =O21/I21 -> 3348.7805 | U21: =O21/T21 -> #DIV/0! | W21: 10.7 | X21: 15.1 | Y21: 2 | Z21: 2 | AA21: 2 | AB21: =SUM(Y21:AA21)/3 -> 2 | AD21: 雨 | AF21: 1 | AK21: 14.3 | AL21: 26.2 | AM21: 5 | AN21: 5 | AO21: 4 | AP21: =SUM(AM21:AO21)/3 -> 4.6666667 | AR21: 雨 | AT21: 1
A22: 金 | B22: 7 | G22: 金 | H22: =B22 -> 7 | I22: 121 | J22: 277200 | K22: =J22/I22 -> 2290.9091 | L22: 162050 | M22: =L22/I22 -> 1339.2562 | N22: 2200 | O22: =J22+L22+N22 -> 441450 | P22: =O22/I22 -> 3648.3471 | U22: =O22/T22 -> #DIV/0! | W22: 12 | X22: 24.3 | Y22: 3 | Z22: 3 | AA22: 3 | AB22: =SUM(Y22:AA22)/3 -> 3 | AD22: 豪雨・雷雨 | AF22: 0 | AK22: 16.4 | AL22: 19.2 | AM22: 1 | AN22: 1 | AO22: 1 | AP22: =SUM(AM22:AO22)/3 -> 1 | AR22: 豪雨・雷雨 | AT22: 0
A23: 土 | B23: 8 | G23: 土 | H23: =B23 -> 8 | I23: 345 | J23: 950050 | K23: =J23/I23 -> 2753.7681 | L23: 523480 | M23: =L23/I23 -> 1517.3333 | N23: 8250 | O23: =J23+L23+N23 -> 1481780 | P23: =O23/I23 -> 4295.0145 | U23: =O23/T23 -> #DIV/0! | W23: 14.8 | X23: 27 | Y23: 3 | Z23: 4 | AA23: 3 | AB23: =SUM(Y23:AA23)/3 -> 3.3333333 | AD23: ※5.6月は18時は最低気温を採用。7月〜は最高気温を採用。 | AK23: 15.3 | AL23: 19.2 | AM23: 4 | AN23: 4 | AO23: 4 | AP23: =SUM(AM23:AO23)/3 -> 4 | AR23: ※5.6月は18時は最低気温を採用。7月〜は最高気温を採用。
A24: SUB TOTAL | C24: P/D | D24: =#REF!/F24 -> #REF! | E24: 日にち | F24: =#REF! -> #REF! | G24: SUB TOTAL | I24: =SUM(I17:I23) -> 811 | J24: =SUM(J17:J23) -> 1982700 | K24: =J24/I24 -> 2444.7596 | L24: =SUM(L17:L23) -> 1169480 | M24: =L24/I24 -> 1442.0222 | N24: =SUM(N17:N23) -> 12650 | O24: =J24+L24+N24 -> 3164830 | P24: =O24/I24 -> 3902.3798 | T24: =SUM(T17:T23) -> 0 | U24: =O24/T24 -> #DIV/0! | V24: 7 | W24: =SUM(W17:W23)/V24 -> 11.985714 | X24: =SUM(X17:X23)/V24 -> 20.357143 | Y24: =SUM(Y17:Y23)/V24 -> 2.4285714 | Z24: =SUM(Z17:Z23)/V24 -> 2.2857143 | AA24: =SUM(AA17:AA23)/V24 -> 2.1428571 | AB24: =SUM(Y24:AA24)/3 -> 2.2857143 | AC24: ③ | AD24: =O24/V24 -> 452118.57 | AI24: ※1日平均売上 | AJ24: 7 | AK24: =SUM(AK17:AK23)/AJ24 -> 12.785714 | AL24: =SUM(AL17:AL23)/AJ24 -> 20.4 | AM24: =SUM(AM17:AM23)/AJ24 -> 2.1428571 | AN24: =SUM(AN17:AN23)/AJ24 -> 2 | AO24: =SUM(AO17:AO23)/AJ24 -> 3.2857143 | AP24: =SUM(AM24:AO24)/3 -> 2.4761905 | AQ24: ③ | AR24: 317435.71 | AW24: ※1日平均売上
A25: 3rd week | G25: 3rd week | W25: =G25 -> 3rd week | AK25: =X25 -> 0
A26: 曜日 | B26: 日にち | C26: A | D26: B | E26: C | F26: S | G26: 曜日 | H26: 日にち | I26: 客数 | J26: 料理売上 | K26: 料理単価 | L26: 飲料売上 | M26: 飲料単価 | N26: その他売上 | O26: 売上合計 | P26: 合計単価 | T26: 労働時間数 | U26: 人時売上高 | W26: 最低 | X26: 最高 | Y26: 12時 | Z26: 15時 | AA26: 18時 | AB26: Ave | AD26: ■天候要因 | AF26: 評価点 | AK26: 最低 | AL26: 最高 | AM26: 12時 | AN26: 15時 | AO26: 18時 | AP26: Ave | AR26: ■天候要因 | AT26: 評価点
A27: 日 | B27: 9 | G27: 日 | H27: =B27 -> 9 | I27: 54 | J27: 160350 | K27: =J27/I27 -> 2969.4444 | L27: 78200 | M27: =L27/I27 -> 1448.1481 | O27: =J27+L27+N27 -> 238550 | P27: =O27/I27 -> 4417.5926 | U27: =O27/T27 -> #DIV/0! | W27: 17.1 | X27: 20.2 | Y27: 2 | Z27: 1 | AA27: 1 | AB27: =SUM(Y27:AA27)/3 -> 1.3333333 | AD27: 晴れ（33度まで） | AF27: 5 | AK27: 13.4 | AL27: 24.2 | AM27: 4 | AN27: 4 | AO27: 4 | AP27: =SUM(AM27:AO27)/3 -> 4 | AR27: 晴れ（33度まで） | AT27: 5
A28: 月 | B28: 10 | G28: 月 | H28: =B28 -> 10 | I28: 122 | J28: 303200 | K28: =J28/I28 -> 2485.2459 | L28: 182950 | M28: =L28/I28 -> 1499.5902 | O28: =J28+L28+N28 -> 486150 | P28: =O28/I28 -> 3984.8361 | U28: =O28/T28 -> #DIV/0! | W28: 16.3 | X28: 26.1 | Y28: 5 | Z28: 5 | AA28: 4 | AB28: =SUM(Y28:AA28)/3 -> 4.6666667 | AD28: 晴れ（25度以下） | AF28: 4 | AK28: 15.7 | AL28: 25.6 | AM28: 5 | AN28: 5 | AO28: 4 | AP28: =SUM(AM28:AO28)/3 -> 4.6666667 | AR28: 晴れ（25度以下） | AT28: 4
A29: 火 | B29: 11 | G29: 火 | H29: =B29 -> 11 | I29: 163 | J29: 340950 | K29: =J29/I29 -> 2091.7178 | L29: 241750 | M29: =L29/I29 -> 1483.1288 | O29: =J29+L29+N29 -> 582700 | P29: =O29/I29 -> 3574.8466 | U29: =O29/T29 -> #DIV/0! | W29: 16 | X29: 25 | Y29: 1 | Z29: 2 | AA29: 4 | AB29: =SUM(Y29:AA29)/3 -> 2.3333333 | AD29: 晴れ（33度以上15以下）曇25度以上 | AF29: 3 | AK29: 16.9 | AL29: 21.9 | AM29: 2 | AN29: 2 | AO29: 2 | AP29: =SUM(AM29:AO29)/3 -> 2 | AR29: 晴れ（33度以上）曇25度以上 | AT29: 3
A30: 水 | B30: 12 | G30: 水 | H30: =B30 -> 12 | I30: 205 | J30: 482550 | K30: =J30/I30 -> 2353.9024 | L30: 315800 | M30: =L30/I30 -> 1540.4878 | N30: 9900 | O30: =J30+L30+N30 -> 808250 | P30: =O30/I30 -> 3942.6829 | U30: =O30/T30 -> #DIV/0! | W30: 15.8 | X30: 28.4 | Y30: 5 | Z30: 5 | AA30: 4 | AB30: =SUM(Y30:AA30)/3 -> 4.6666667 | AD30: 曇 | AF30: 2 | AK30: 16.5 | AL30: 23.2 | AM30: 1 | AN30: 4 | AO30: 4 | AP30: =SUM(AM30:AO30)/3 -> 3 | AR30: 曇 | AT30: 2
A31: 木 | B31: 13 | G31: 木 | H31: =B31 -> 13 | I31: 279 | J31: 869900 | K31: =J31/I31 -> 3117.9211 | L31: 476050 | M31: =L31/I31 -> 1706.2724 | N31: 6050 | O31: =J31+L31+N31 -> 1352000 | P31: =O31/I31 -> 4845.8781 | U31: =O31/T31 -> #DIV/0! | W31: 18.2 | X31: 23.4 | Y31: 2 | Z31: 2 | AA31: 2 | AB31: =SUM(Y31:AA31)/3 -> 2 | AD31: 雨 | AF31: 1 | AK31: 16 | AL31: 26.5 | AM31: 5 | AN31: 5 | AO31: 4 | AP31: =SUM(AM31:AO31)/3 -> 4.6666667 | AR31: 雨 | AT31: 1
A32: 金 | B32: 14 | G32: 金 | H32: =B32 -> 14 | I32: 154 | J32: 465400 | K32: =J32/I32 -> 3022.0779 | L32: 250500 | M32: =L32/I32 -> 1626.6234 | N32: 2750 | O32: =J32+L32+N32 -> 718650 | P32: =O32/I32 -> 4666.5584 | U32: =O32/T32 -> #DIV/0! | W32: 15.5 | X32: 22.8 | Y32: 2 | Z32: 2 | AA32: 3 | AB32: =SUM(Y32:AA32)/3 -> 2.3333333 | AD32: 豪雨・雷雨 | AF32: 0 | AK32: 17.3 | AL32: 27.3 | AM32: 5 | AN32: 5 | AO32: 3 | AP32: =SUM(AM32:AO32)/3 -> 4.3333333 | AR32: 豪雨・雷雨 | AT32: 0
A33: 土 | B33: 15 | G33: 土 | H33: =B33 -> 15 | I33: 300 | J33: 765900 | K33: =J33/I33 -> 2553 | L33: 420650 | M33: =L33/I33 -> 1402.1667 | N33: 2200 | O33: =J33+L33+N33 -> 1188750 | P33: =O33/I33 -> 3962.5 | U33: =O33/T33 -> #DIV/0! | W33: 15.5 | X33: 25.5 | Y33: 4 | Z33: 5 | AA33: 4 | AB33: =SUM(Y33:AA33)/3 -> 4.3333333 | AD33: ※5.6月は18時は最低気温を採用。7月〜は最高気温を採用。 | AK33: 16.9 | AL33: 28.7 | AM33: 5 | AN33: 5 | AO33: 4 | AP33: =SUM(AM33:AO33)/3 -> 4.6666667 | AR33: ※5.6月は18時は最低気温を採用。7月〜は最高気温を採用。
A34: SUB TOTAL | C34: P/D | D34: =#REF!/F34 -> #REF! | E34: 日にち | F34: =#REF! -> #REF! | G34: SUB TOTAL | I34: =SUM(I27:I33) -> 1277 | J34: =SUM(J27:J33) -> 3388250 | K34: =J34/I34 -> 2653.289 | L34: =SUM(L27:L33) -> 1965900 | M34: =L34/I34 -> 1539.4675 | N34: =SUM(N27:N33) -> 20900 | O34: =J34+L34+N34 -> 5375050 | P34: =O34/I34 -> 4209.1229 | T34: =SUM(T27:T33) -> 0 | U34: =O34/T34 -> #DIV/0! | V34: 7 | W34: =SUM(W27:W33)/V34 -> 16.342857 | X34: =SUM(X27:X33)/V34 -> 24.485714 | Y34: =SUM(Y27:Y33)/V34 -> 3 | Z34: =SUM(Z27:Z33)/V34 -> 3.1428571 | AA34: =SUM(AA27:AA33)/V34 -> 3.1428571 | AB34: =SUM(Y34:AA34)/3 -> 3.0952381 | AC34: ④ | AD34: =O34/V34 -> 767864.29 | AI34: ※1日平均売上 | AJ34: 7 | AK34: =SUM(AK27:AK33)/AJ34 -> 16.1 | AL34: =SUM(AL27:AL33)/AJ34 -> 25.342857 | AM34: =SUM(AM27:AM33)/AJ34 -> 3.8571429 | AN34: =SUM(AN27:AN33)/AJ34 -> 4.2857143 | AO34: =SUM(AO27:AO33)/AJ34 -> 3.5714286 | AP34: =SUM(AM34:AO34)/3 -> 3.9047619 | AQ34: ④ | AR34: 945742.86 | AW34: ※1日平均売上
A35: 4th week | G35: 4th week | W35: =G35 -> 4th week | AK35: =X35 -> 0
A36: 曜日 | B36: 日にち | C36: A | D36: B | E36: C | F36: S | G36: 曜日 | H36: 日にち | I36: 客数 | J36: 料理売上 | K36: 料理単価 | L36: 飲料売上 | M36: 飲料単価 | N36: その他売上 | O36: 売上合計 | P36: 合計単価 | T36: 労働時間数 | U36: 人時売上高 | W36: 最低 | X36: 最高 | Y36: 12時 | Z36: 15時 | AA36: 18時 | AB36: Ave | AD36: ■天候要因 | AF36: 評価点 | AK36: 最低 | AL36: 最高 | AM36: 12時 | AN36: 15時 | AO36: 18時 | AP36: Ave | AR36: ■天候要因 | AT36: 評価点
A37: 日 | B37: 16 | G37: 日 | H37: =B37 -> 16 | I37: 101 | J37: 274850 | K37: =J37/I37 -> 2721.2871 | L37: 143400 | M37: =L37/I37 -> 1419.802 | N37: 12100 | O37: =J37+L37+N37 -> 430350 | P37: =O37/I37 -> 4260.8911 | U37: =O37/T37 -> #DIV/0! | W37: 19.3 | X37: 22.4 | Y37: 1 | Z37: 0 | AA37: 1 | AB37: =SUM(Y37:AA37)/3 -> 0.66666667 | AD37: 晴れ（33度まで） | AF37: 5 | AK37: 17.4 | AL37: 21.5 | AM37: 1 | AN37: 2 | AO37: 4 | AP37: =SUM(AM37:AO37)/3 -> 2.3333333 | AR37: 晴れ（33度まで） | AT37: 5
A38: 月 | B38: 17 | G38: 月 | H38: =B38 -> 17 | I38: 136 | J38: 319450 | K38: =J38/I38 -> 2348.8971 | L38: 215000 | M38: =L38/I38 -> 1580.8824 | O38: =J38+L38+N38 -> 534450 | P38: =O38/I38 -> 3929.7794 | U38: =O38/T38 -> #DIV/0! | W38: 17 | X38: 27.5 | Y38: 2 | Z38: 5 | AA38: 4 | AB38: =SUM(Y38:AA38)/3 -> 3.6666667 | AD38: 晴れ（25度以下） | AF38: 4 | AK38: 14.7 | AL38: 20 | AM38: 4 | AN38: 4 | AO38: 4 | AP38: =SUM(AM38:AO38)/3 -> 4 | AR38: 晴れ（25度以下） | AT38: 4
A39: 火 | B39: 18 | G39: 火 | H39: =B39 -> 18 | I39: 81 | J39: 216100 | K39: =J39/I39 -> 2667.9012 | L39: 112300 | M39: =L39/I39 -> 1386.4198 | N39: 6600 | O39: =J39+L39+N39 -> 335000 | P39: =O39/I39 -> 4135.8025 | U39: =O39/T39 -> #DIV/0! | W39: 20.2 | X39: 25 | Y39: 2 | Z39: 1 | AA39: 1 | AB39: =SUM(Y39:AA39)/3 -> 1.3333333 | AD39: 晴れ（33度以上15以下）曇25度以上 | AF39: 3 | AK39: 13.8 | AL39: 23.6 | AM39: 4 | AN39: 4 | AO39: 4 | AP39: =SUM(AM39:AO39)/3 -> 4 | AR39: 晴れ（33度以上）曇25度以上 | AT39: 3
A40: 水 | B40: 19 | G40: 水 | H40: =B40 -> 19 | I40: 175 | J40: 453600 | K40: =J40/I40 -> 2592 | L40: 248150 | M40: =L40/I40 -> 1418 | N40: 1100 | O40: =J40+L40+N40 -> 702850 | P40: =O40/I40 -> 4016.2857 | U40: =O40/T40 -> #DIV/0! | W40: 15 | X40: 23.8 | Y40: 4 | Z40: 4 | AA40: 4 | AB40: =SUM(Y40:AA40)/3 -> 4 | AD40: 曇 | AF40: 2 | AK40: 14.5 | AL40: 28.2 | AM40: 5 | AN40: 5 | AO40: 4 | AP40: =SUM(AM40:AO40)/3 -> 4.6666667 | AR40: 曇 | AT40: 2
